package game;

final class C_100339_jb implements Runnable
{
	static String field_107392_i;
	volatile boolean field_107388_m;
	static C_100037_wb[] field_107382_e;
	static String field_107381_d;
	static int[] field_107390_k;
	C_100201_qj field_107386_n;
	volatile C_100177_cj[] field_107379_f;
	static String field_107380_g;
	static String field_107383_b;
	volatile boolean field_107385_a;
	static String field_107389_j;
	static String field_107391_h;
	static C_100202_qi field_107387_l;
	static String[][] field_107384_c;
	private static final String[] field_107393_z;
	
	static final int func_107378_a(int arg0, byte arg1, int arg2)
	{
		// @00: iload_2
		// @01: ldc 295033407 (0x1195da3f)
		// @03: iushr
		// @04: istore_3
		// @05: iload_1
		// @06: bipush -71 (0xB9)
		// @08: if_icmple @0E
		// @0B: bipush 12 (0x0C)
		// @0D: ireturn
		// @0E: iload_3
		// @0F: ineg
		// @10: iload_3
		// @11: iload_2
		// @12: iadd
		// @13: iload_0
		// @14: idiv
		// @15: iadd
		// @16: ireturn
		// @17: astore_3
		// @18: aload_3
		// @19: new java.lang.StringBuilder
		// @1C: dup
		// @1D: invokespecial java.lang.StringBuilder.<init>()void
		// @20: getstatic java.lang.String[] game.C_100339_jb.field_107393_z
		// @23: bipush 9 (0x09)
		// @25: aaload
		// @26: invokevirtual java.lang.StringBuilder.append(java.lang.String)java.lang.StringBuilder
		// @29: iload_0
		// @2A: invokevirtual java.lang.StringBuilder.append(int)java.lang.StringBuilder
		// @2D: bipush 44 (0x2C)
		// @2F: invokevirtual java.lang.StringBuilder.append(char)java.lang.StringBuilder
		// @32: iload_1
		// @33: invokevirtual java.lang.StringBuilder.append(int)java.lang.StringBuilder
		// @36: bipush 44 (0x2C)
		// @38: invokevirtual java.lang.StringBuilder.append(char)java.lang.StringBuilder
		// @3B: iload_2
		// @3C: invokevirtual java.lang.StringBuilder.append(int)java.lang.StringBuilder
		// @3F: bipush 41 (0x29)
		// @41: invokevirtual java.lang.StringBuilder.append(char)java.lang.StringBuilder
		// @44: invokevirtual java.lang.StringBuilder.toString()java.lang.String
		// @47: invokestatic game.C_100181_cf.func_105695_a(java.lang.Throwable, java.lang.String)game.C_100170_cm
		// @4A: athrow
	}
	
	public static void func_107377_a(boolean arg0)
	{
		// @00: aconst_null
		// @01: putstatic game.C_100202_qi game.C_100339_jb.field_107387_l
		// @04: aconst_null
		// @05: putstatic java.lang.String game.C_100339_jb.field_107381_d
		// @08: aconst_null
		// @09: putstatic java.lang.String game.C_100339_jb.field_107391_h
		// @0C: aconst_null
		// @0D: checkcast java.lang.String[][]
		// @10: putstatic java.lang.String[][] game.C_100339_jb.field_107384_c
		// @13: aconst_null
		// @14: putstatic java.lang.String game.C_100339_jb.field_107389_j
		// @17: aconst_null
		// @18: putstatic java.lang.String game.C_100339_jb.field_107392_i
		// @1B: aconst_null
		// @1C: putstatic java.lang.String game.C_100339_jb.field_107383_b
		// @1F: iload_0
		// @20: iconst_1
		// @21: if_icmpeq @2C
		// @24: iconst_0
		// @25: invokestatic game.C_100339_jb.func_107377_a(boolean)void
		// @28: goto @2C
		// @2B: athrow
		// @2C: aconst_null
		// @2D: putstatic java.lang.String game.C_100339_jb.field_107380_g
		// @30: aconst_null
		// @31: putstatic int[] game.C_100339_jb.field_107390_k
		// @34: aconst_null
		// @35: putstatic game.C_100037_wb[] game.C_100339_jb.field_107382_e
		// @38: goto @5D
		// @3B: astore_1
		// @3C: aload_1
		// @3D: new java.lang.StringBuilder
		// @40: dup
		// @41: invokespecial java.lang.StringBuilder.<init>()void
		// @44: getstatic java.lang.String[] game.C_100339_jb.field_107393_z
		// @47: bipush 10 (0x0A)
		// @49: aaload
		// @4A: invokevirtual java.lang.StringBuilder.append(java.lang.String)java.lang.StringBuilder
		// @4D: iload_0
		// @4E: invokevirtual java.lang.StringBuilder.append(boolean)java.lang.StringBuilder
		// @51: bipush 41 (0x29)
		// @53: invokevirtual java.lang.StringBuilder.append(char)java.lang.StringBuilder
		// @56: invokevirtual java.lang.StringBuilder.toString()java.lang.String
		// @59: invokestatic game.C_100181_cf.func_105695_a(java.lang.Throwable, java.lang.String)game.C_100170_cm
		// @5C: athrow
		// @5D: return
	}
	
	public final void run()
	{
		// @00: getstatic int game.SteelSentinels.field_105275_O
		// @03: istore #4
		// @05: aload_0
		// @06: iconst_1
		// @07: putfield boolean game.C_100339_jb.field_107385_a
		// @0A: aload_0
		// @0B: getfield boolean game.C_100339_jb.field_107388_m
		// @0E: ifne @58
		// @11: iload #4
		// @13: ifne @5D
		// @16: iconst_0
		// @17: istore_1
		// @18: iconst_2
		// @19: iload_1
		// @1A: if_icmple @41
		// @1D: aload_0
		// @1E: getfield game.C_100177_cj[] game.C_100339_jb.field_107379_f
		// @21: iload_1
		// @22: aaload
		// @23: astore_2
		// @24: iload #4
		// @26: ifne @53
		// @29: aload_2
		// @2A: ifnonnull @35
		// @2D: goto @31
		// @30: athrow
		// @31: goto @39
		// @34: athrow
		// @35: aload_2
		// @36: invokevirtual game.C_100177_cj.func_105641_c()void
		// @39: iinc #1 +1
		// @3C: iload #4
		// @3E: ifeq @18
		// @41: ldc2_w 10
		// @44: bipush -122 (0x86)
		// @46: invokestatic game.C_100138_bo.func_100396_a(long, int)void
		// @49: bipush -108 (0x94)
		// @4B: aload_0
		// @4C: getfield game.C_100201_qj game.C_100339_jb.field_107386_n
		// @4F: aconst_null
		// @50: invokestatic game.C_100333_ij.func_107323_a(byte, game.C_100201_qj, java.lang.Object)void
		// @53: iload #4
		// @55: ifeq @0A
		// @58: aload_0
		// @59: iconst_0
		// @5A: putfield boolean game.C_100339_jb.field_107385_a
		// @5D: goto @77
		// @60: astore_1
		// @61: iconst_1
		// @62: aconst_null
		// @63: aload_1
		// @64: invokestatic game.C_100036_gg.func_103142_a(int, java.lang.String, java.lang.Throwable)void
		// @67: aload_0
		// @68: iconst_0
		// @69: putfield boolean game.C_100339_jb.field_107385_a
		// @6C: goto @77
		// @6F: astore_3
		// @70: aload_0
		// @71: iconst_0
		// @72: putfield boolean game.C_100339_jb.field_107385_a
		// @75: aload_3
		// @76: athrow
		// @77: goto @85
		// @7A: astore_1
		// @7B: aload_1
		// @7C: getstatic java.lang.String[] game.C_100339_jb.field_107393_z
		// @7F: iconst_0
		// @80: aaload
		// @81: invokestatic game.C_100181_cf.func_105695_a(java.lang.Throwable, java.lang.String)game.C_100170_cm
		// @84: athrow
		// @85: return
	}
	
	static final boolean func_107374_a(String arg0, int arg1)
	{
		// @00: getstatic int game.SteelSentinels.field_105275_O
		// @03: istore #4
		// @05: getstatic java.lang.String game.C_100201_qj.field_105872_d
		// @08: getstatic java.lang.String[] game.C_100339_jb.field_107393_z
		// @0B: iconst_2
		// @0C: aaload
		// @0D: invokevirtual java.lang.String.startsWith(java.lang.String)boolean
		// @10: ifne @15
		// @13: iconst_0
		// @14: ireturn
		// @15: aload_0
		// @16: getstatic java.lang.String[] game.C_100339_jb.field_107393_z
		// @19: iconst_4
		// @1A: aaload
		// @1B: invokevirtual java.lang.String.startsWith(java.lang.String)boolean
		// @1E: ifne @37
		// @21: aload_0
		// @22: getstatic java.lang.String[] game.C_100339_jb.field_107393_z
		// @25: iconst_1
		// @26: aaload
		// @27: invokevirtual java.lang.String.startsWith(java.lang.String)boolean
		// @2A: ifeq @35
		// @2D: goto @31
		// @30: athrow
		// @31: goto @37
		// @34: athrow
		// @35: iconst_0
		// @36: ireturn
		// @37: getstatic java.lang.String[] game.C_100339_jb.field_107393_z
		// @3A: iconst_3
		// @3B: aaload
		// @3C: astore_2
		// @3D: iconst_0
		// @3E: istore_3
		// @3F: aload_0
		// @40: invokevirtual java.lang.String.length()int
		// @43: iload_3
		// @44: if_icmple @67
		// @47: iconst_m1
		// @48: aload_2
		// @49: aload_0
		// @4A: iload_3
		// @4B: invokevirtual java.lang.String.charAt(int)char
		// @4E: invokevirtual java.lang.String.indexOf(int)int
		// @51: iload #4
		// @53: ifne @8E
		// @56: if_icmpne @5F
		// @59: goto @5D
		// @5C: athrow
		// @5D: iconst_0
		// @5E: ireturn
		// @5F: iinc #3 +1
		// @62: iload #4
		// @64: ifeq @3F
		// @67: invokestatic java.lang.Runtime.getRuntime()java.lang.Runtime
		// @6A: new java.lang.StringBuilder
		// @6D: dup
		// @6E: invokespecial java.lang.StringBuilder.<init>()void
		// @71: getstatic java.lang.String[] game.C_100339_jb.field_107393_z
		// @74: bipush 7 (0x07)
		// @76: aaload
		// @77: invokevirtual java.lang.StringBuilder.append(java.lang.String)java.lang.StringBuilder
		// @7A: aload_0
		// @7B: invokevirtual java.lang.StringBuilder.append(java.lang.String)java.lang.StringBuilder
		// @7E: ldc "\""
		// @80: invokevirtual java.lang.StringBuilder.append(java.lang.String)java.lang.StringBuilder
		// @83: invokevirtual java.lang.StringBuilder.toString()java.lang.String
		// @86: invokevirtual java.lang.Runtime.exec(java.lang.String)java.lang.Process
		// @89: pop
		// @8A: iload_1
		// @8B: sipush 20947 (0x51D3)
		// @8E: if_icmpeq @93
		// @91: iconst_0
		// @92: ireturn
		// @93: iconst_1
		// @94: ireturn
		// @95: astore_2
		// @96: iconst_0
		// @97: ireturn
		// @98: astore_2
		// @99: aload_2
		// @9A: new java.lang.StringBuilder
		// @9D: dup
		// @9E: invokespecial java.lang.StringBuilder.<init>()void
		// @A1: getstatic java.lang.String[] game.C_100339_jb.field_107393_z
		// @A4: bipush 6 (0x06)
		// @A6: aaload
		// @A7: invokevirtual java.lang.StringBuilder.append(java.lang.String)java.lang.StringBuilder
		// @AA: aload_0
		// @AB: ifnull @B7
		// @AE: getstatic java.lang.String[] game.C_100339_jb.field_107393_z
		// @B1: iconst_5
		// @B2: aaload
		// @B3: goto @BD
		// @B6: athrow
		// @B7: getstatic java.lang.String[] game.C_100339_jb.field_107393_z
		// @BA: bipush 8 (0x08)
		// @BC: aaload
		// @BD: invokevirtual java.lang.StringBuilder.append(java.lang.String)java.lang.StringBuilder
		// @C0: bipush 44 (0x2C)
		// @C2: invokevirtual java.lang.StringBuilder.append(char)java.lang.StringBuilder
		// @C5: iload_1
		// @C6: invokevirtual java.lang.StringBuilder.append(int)java.lang.StringBuilder
		// @C9: bipush 41 (0x29)
		// @CB: invokevirtual java.lang.StringBuilder.append(char)java.lang.StringBuilder
		// @CE: invokevirtual java.lang.StringBuilder.toString()java.lang.String
		// @D1: invokestatic game.C_100181_cf.func_105695_a(java.lang.Throwable, java.lang.String)game.C_100170_cm
		// @D4: athrow
	}
	
	C_100339_jb()
	{
		// @00: aload_0
		// @01: invokespecial java.lang.Object.<init>()void
		// @04: aload_0
		// @05: iconst_2
		// @06: anewarray game.C_100177_cj
		// @09: putfield game.C_100177_cj[] game.C_100339_jb.field_107379_f
		// @0C: aload_0
		// @0D: iconst_0
		// @0E: putfield boolean game.C_100339_jb.field_107388_m
		// @11: aload_0
		// @12: iconst_0
		// @13: putfield boolean game.C_100339_jb.field_107385_a
		// @16: return
	}
	
	static
	{
		// @00: bipush 11 (0x0B)
		// @02: anewarray java.lang.String
		// @05: dup
		// @06: iconst_0
		// @07: ldc "0\u0015V\u0004~4_Q"
		// @09: invokestatic game.C_100339_jb.func_107376_z(java.lang.String)char[]
		// @0C: invokestatic game.C_100339_jb.func_107375_z(char[])java.lang.String
		// @0F: aastore
		// @10: dup
		// @11: iconst_1
		// @12: ldc "2\u0003\u000c\u0006x`XW"
		// @14: invokestatic game.C_100339_jb.func_107376_z(java.lang.String)char[]
		// @17: invokestatic game.C_100339_jb.func_107375_z(char[])java.lang.String
		// @1A: aastore
		// @1B: dup
		// @1C: iconst_2
		// @1D: ldc "-\u001e\u0016"
		// @1F: invokestatic game.C_100339_jb.func_107376_z(java.lang.String)char[]
		// @22: invokestatic game.C_100339_jb.func_107375_z(char[])java.lang.String
		// @25: aastore
		// @26: dup
		// @27: iconst_3
		// @28: ldc ";\u0015\u001b\u0012n<\u0010\u0010\u001fa1\u001b\u0015\u0018d*\u0006\n\u0005\u007f/\u0001\u000f\u000er 6:5O\u001f1?>B\u0010<4;E\u0015')$X\u000e\".!S\u0003-HG9iCM@<bNGP6vY]]&\u0005TBY!"
		// @2A: invokestatic game.C_100339_jb.func_107376_z(java.lang.String)char[]
		// @2D: invokestatic game.C_100339_jb.func_107375_z(char[])java.lang.String
		// @30: aastore
		// @31: dup
		// @32: iconst_4
		// @33: ldc "2\u0003\u000c\u00061uX"
		// @35: invokestatic game.C_100339_jb.func_107376_z(java.lang.String)char[]
		// @38: invokestatic game.C_100339_jb.func_107375_z(char[])java.lang.String
		// @3B: aastore
		// @3C: dup
		// @3D: iconst_5
		// @3E: ldc "!YVXv"
		// @40: invokestatic game.C_100339_jb.func_107376_z(java.lang.String)char[]
		// @43: invokestatic game.C_100339_jb.func_107375_z(char[])java.lang.String
		// @46: aastore
		// @47: dup
		// @48: bipush 6 (0x06)
		// @4A: ldc "0\u0015V7#"
		// @4C: invokestatic game.C_100339_jb.func_107376_z(java.lang.String)char[]
		// @4F: invokestatic game.C_100339_jb.func_107375_z(char[])java.lang.String
		// @52: aastore
		// @53: dup
		// @54: bipush 7 (0x07)
		// @56: ldc "9\u001a\u001cV$9W\u000b\u0002j(\u0003XTaxWZ"
		// @58: invokestatic game.C_100339_jb.func_107376_z(java.lang.String)char[]
		// @5B: invokestatic game.C_100339_jb.func_107375_z(char[])java.lang.String
		// @5E: aastore
		// @5F: dup
		// @60: bipush 8 (0x08)
		// @62: ldc "4\u0002\u0014\u001a"
		// @64: invokestatic game.C_100339_jb.func_107376_z(java.lang.String)char[]
		// @67: invokestatic game.C_100339_jb.func_107375_z(char[])java.lang.String
		// @6A: aastore
		// @6B: dup
		// @6C: bipush 9 (0x09)
		// @6E: ldc "0\u0015V5#"
		// @70: invokestatic game.C_100339_jb.func_107376_z(java.lang.String)char[]
		// @73: invokestatic game.C_100339_jb.func_107375_z(char[])java.lang.String
		// @76: aastore
		// @77: dup
		// @78: bipush 10 (0x0A)
		// @7A: ldc "0\u0015V4#"
		// @7C: invokestatic game.C_100339_jb.func_107376_z(java.lang.String)char[]
		// @7F: invokestatic game.C_100339_jb.func_107375_z(char[])java.lang.String
		// @82: aastore
		// @83: putstatic java.lang.String[] game.C_100339_jb.field_107393_z
		// @86: sipush 8192 (0x2000)
		// @89: newarray int[]
		// @8B: putstatic int[] game.C_100339_jb.field_107390_k
		// @8E: ldc "\u000e\u0012\u0019\u001b+\u0018\u0016\u000c\u0002g?"
		// @90: invokestatic game.C_100339_jb.func_107376_z(java.lang.String)char[]
		// @93: invokestatic game.C_100339_jb.func_107375_z(char[])java.lang.String
		// @96: putstatic java.lang.String game.C_100339_jb.field_107380_g
		// @99: ldc "\u001e\u0018\u0016Q\u007fz\u001a\u0011\u0018o"
		// @9B: invokestatic game.C_100339_jb.func_107376_z(java.lang.String)char[]
		// @9E: invokestatic game.C_100339_jb.func_107375_z(char[])java.lang.String
		// @A1: putstatic java.lang.String game.C_100339_jb.field_107381_d
		// @A4: ldc "\u0019\u0018\u0016\u0010b(\u001aX&j)\u0004\u000f\u0019y>MX"
		// @A6: invokestatic game.C_100339_jb.func_107376_z(java.lang.String)char[]
		// @A9: invokestatic game.C_100339_jb.func_107375_z(char[])java.lang.String
		// @AC: putstatic java.lang.String game.C_100339_jb.field_107383_b
		// @AF: ldc "\r29&D\u0014$"
		// @B1: invokestatic game.C_100339_jb.func_107376_z(java.lang.String)char[]
		// @B4: invokestatic game.C_100339_jb.func_107375_z(char[])java.lang.String
		// @B7: putstatic java.lang.String game.C_100339_jb.field_107392_i
		// @BA: ldc "\u0015!=$+fRHH"
		// @BC: invokestatic game.C_100339_jb.func_107376_z(java.lang.String)char[]
		// @BF: invokestatic game.C_100339_jb.func_107375_z(char[])java.lang.String
		// @C2: putstatic java.lang.String game.C_100339_jb.field_107389_j
		// @C5: return
	}
	
	private static char[] func_107376_z(String arg0)
	{
		// @00: aload_0
		// @01: invokevirtual java.lang.String.toCharArray()char[]
		// @04: dup
		// @05: arraylength
		// @06: iconst_2
		// @07: if_icmpge @13
		// @0A: dup
		// @0B: iconst_0
		// @0C: dup2
		// @0D: caload
		// @0E: bipush 11 (0x0B)
		// @10: ixor
		// @11: i2c
		// @12: castore
		// @13: areturn
	}
	
	private static String func_107375_z(char[] arg0)
	{
		// @00: aload_0
		// @01: dup
		// @02: arraylength
		// @03: swap
		// @04: iconst_0
		// @05: istore_1
		// @06: goto @4C
		// @09: dup
		// @0A: iload_1
		// @0B: dup2
		// @0C: caload
		// @0D: iload_1
		// @0E: iconst_5
		// @0F: irem
		// @10: tableswitch def: @44, for 0: @30, for 1: @35, for 2: @3A, for 3: @3F
		// @30: bipush 90 (0x5A)
		// @32: goto @46
		// @35: bipush 119 (0x77)
		// @37: goto @46
		// @3A: bipush 120 (0x78)
		// @3C: goto @46
		// @3F: bipush 118 (0x76)
		// @41: goto @46
		// @44: bipush 11 (0x0B)
		// @46: ixor
		// @47: i2c
		// @48: castore
		// @49: iinc #1 +1
		// @4C: swap
		// @4D: dup_x1
		// @4E: iload_1
		// @4F: if_icmpgt @09
		// @52: new java.lang.String
		// @55: dup_x1
		// @56: swap
		// @57: invokespecial java.lang.String.<init>(char[])void
		// @5A: invokevirtual java.lang.String.intern()java.lang.String
		// @5D: areturn
	}
}
