package game;

final class C_100095_fe extends C_100030_gm
{
	static String field_103384_P;
	static C_100302_ka field_103385_S;
	static int field_103386_R;
	static boolean field_103387_O;
	static C_100037_wb[] field_103383_Q;
	private static final String[] field_103382_T;
	
	private C_100095_fe(int arg0, int arg1, int arg2, int arg3, C_100326_ic arg4, C_100337_in arg5, C_100336_im arg6)
	{
		// @00: aload_0
		// @01: iload_1
		// @02: iload_2
		// @03: iload_3
		// @04: iload #4
		// @06: aload #5
		// @08: aload #6
		// @0A: invokespecial game.C_100030_gm.<init>(int, int, int, int, game.C_100326_ic, game.C_100337_in)void
		// @0D: aload_0
		// @0E: aload #7
		// @10: putfield game.C_100336_im game.C_100095_fe.field_103351_J
		// @13: goto @A6
		// @16: astore #8
		// @18: aload #8
		// @1A: new java.lang.StringBuilder
		// @1D: dup
		// @1E: invokespecial java.lang.StringBuilder.<init>()void
		// @21: getstatic java.lang.String[] game.C_100095_fe.field_103382_T
		// @24: iconst_3
		// @25: aaload
		// @26: invokevirtual java.lang.StringBuilder.append(java.lang.String)java.lang.StringBuilder
		// @29: iload_1
		// @2A: invokevirtual java.lang.StringBuilder.append(int)java.lang.StringBuilder
		// @2D: bipush 44 (0x2C)
		// @2F: invokevirtual java.lang.StringBuilder.append(char)java.lang.StringBuilder
		// @32: iload_2
		// @33: invokevirtual java.lang.StringBuilder.append(int)java.lang.StringBuilder
		// @36: bipush 44 (0x2C)
		// @38: invokevirtual java.lang.StringBuilder.append(char)java.lang.StringBuilder
		// @3B: iload_3
		// @3C: invokevirtual java.lang.StringBuilder.append(int)java.lang.StringBuilder
		// @3F: bipush 44 (0x2C)
		// @41: invokevirtual java.lang.StringBuilder.append(char)java.lang.StringBuilder
		// @44: iload #4
		// @46: invokevirtual java.lang.StringBuilder.append(int)java.lang.StringBuilder
		// @49: bipush 44 (0x2C)
		// @4B: invokevirtual java.lang.StringBuilder.append(char)java.lang.StringBuilder
		// @4E: aload #5
		// @50: ifnull @5C
		// @53: getstatic java.lang.String[] game.C_100095_fe.field_103382_T
		// @56: iconst_2
		// @57: aaload
		// @58: goto @61
		// @5B: athrow
		// @5C: getstatic java.lang.String[] game.C_100095_fe.field_103382_T
		// @5F: iconst_0
		// @60: aaload
		// @61: invokevirtual java.lang.StringBuilder.append(java.lang.String)java.lang.StringBuilder
		// @64: bipush 44 (0x2C)
		// @66: invokevirtual java.lang.StringBuilder.append(char)java.lang.StringBuilder
		// @69: aload #6
		// @6B: ifnull @77
		// @6E: getstatic java.lang.String[] game.C_100095_fe.field_103382_T
		// @71: iconst_2
		// @72: aaload
		// @73: goto @7C
		// @76: athrow
		// @77: getstatic java.lang.String[] game.C_100095_fe.field_103382_T
		// @7A: iconst_0
		// @7B: aaload
		// @7C: invokevirtual java.lang.StringBuilder.append(java.lang.String)java.lang.StringBuilder
		// @7F: bipush 44 (0x2C)
		// @81: invokevirtual java.lang.StringBuilder.append(char)java.lang.StringBuilder
		// @84: aload #7
		// @86: ifnull @92
		// @89: getstatic java.lang.String[] game.C_100095_fe.field_103382_T
		// @8C: iconst_2
		// @8D: aaload
		// @8E: goto @97
		// @91: athrow
		// @92: getstatic java.lang.String[] game.C_100095_fe.field_103382_T
		// @95: iconst_0
		// @96: aaload
		// @97: invokevirtual java.lang.StringBuilder.append(java.lang.String)java.lang.StringBuilder
		// @9A: bipush 41 (0x29)
		// @9C: invokevirtual java.lang.StringBuilder.append(char)java.lang.StringBuilder
		// @9F: invokevirtual java.lang.StringBuilder.toString()java.lang.String
		// @A2: invokestatic game.C_100181_cf.func_105695_a(java.lang.Throwable, java.lang.String)game.C_100170_cm
		// @A5: athrow
		// @A6: return
	}
	
	static final int func_103372_b(int arg0, int arg1)
	{
		// @000: getstatic int game.SteelSentinels.field_105275_O
		// @003: istore_3
		// @004: iload_0
		// @005: bipush -20 (0xEC)
		// @007: if_icmpeq @015
		// @00A: aconst_null
		// @00B: checkcast game.C_100037_wb[]
		// @00E: putstatic game.C_100037_wb[] game.C_100095_fe.field_103383_Q
		// @011: goto @015
		// @014: athrow
		// @015: iload_1
		// @016: istore_2
		// @017: iload_2
		// @018: ifne @023
		// @01B: iload_3
		// @01C: ifeq @0C1
		// @01F: goto @023
		// @022: athrow
		// @023: iconst_1
		// @024: iload_2
		// @025: if_icmpeq @0C1
		// @028: goto @02C
		// @02B: athrow
		// @02C: bipush -3 (0xFD)
		// @02E: iload_2
		// @02F: iconst_m1
		// @030: ixor
		// @031: if_icmpne @040
		// @034: goto @038
		// @037: athrow
		// @038: iload_3
		// @039: ifeq @0C4
		// @03C: goto @040
		// @03F: athrow
		// @040: bipush -4 (0xFC)
		// @042: iload_2
		// @043: iconst_m1
		// @044: ixor
		// @045: if_icmpeq @0C4
		// @048: goto @04C
		// @04B: athrow
		// @04C: iload_2
		// @04D: iconst_m1
		// @04E: ixor
		// @04F: bipush -5 (0xFB)
		// @051: if_icmpeq @0C4
		// @054: goto @058
		// @057: athrow
		// @058: iload_2
		// @059: iconst_5
		// @05A: if_icmpne @069
		// @05D: goto @061
		// @060: athrow
		// @061: iload_3
		// @062: ifeq @0C4
		// @065: goto @069
		// @068: athrow
		// @069: iload_2
		// @06A: bipush 6 (0x06)
		// @06C: if_icmpeq @0C7
		// @06F: goto @073
		// @072: athrow
		// @073: bipush -8 (0xF8)
		// @075: iload_2
		// @076: iconst_m1
		// @077: ixor
		// @078: if_icmpne @087
		// @07B: goto @07F
		// @07E: athrow
		// @07F: iload_3
		// @080: ifeq @0CA
		// @083: goto @087
		// @086: athrow
		// @087: bipush -9 (0xF7)
		// @089: iload_2
		// @08A: iconst_m1
		// @08B: ixor
		// @08C: if_icmpeq @0CA
		// @08F: goto @093
		// @092: athrow
		// @093: iload_2
		// @094: bipush 10 (0x0A)
		// @096: if_icmpeq @0CA
		// @099: goto @09D
		// @09C: athrow
		// @09D: bipush -10 (0xF6)
		// @09F: iload_2
		// @0A0: iconst_m1
		// @0A1: ixor
		// @0A2: if_icmpne @0B1
		// @0A5: goto @0A9
		// @0A8: athrow
		// @0A9: iload_3
		// @0AA: ifeq @0CD
		// @0AD: goto @0B1
		// @0B0: athrow
		// @0B1: bipush -20 (0xEC)
		// @0B3: iload_2
		// @0B4: iconst_m1
		// @0B5: ixor
		// @0B6: if_icmpeq @0D0
		// @0B9: goto @0BD
		// @0BC: athrow
		// @0BD: goto @0D3
		// @0C0: athrow
		// @0C1: bipush 12 (0x0C)
		// @0C3: ireturn
		// @0C4: bipush 13 (0x0D)
		// @0C6: ireturn
		// @0C7: bipush 14 (0x0E)
		// @0C9: ireturn
		// @0CA: bipush 15 (0x0F)
		// @0CC: ireturn
		// @0CD: bipush 16 (0x10)
		// @0CF: ireturn
		// @0D0: bipush 18 (0x12)
		// @0D2: ireturn
		// @0D3: bipush 17 (0x11)
		// @0D5: ireturn
		// @0D6: astore_2
		// @0D7: aload_2
		// @0D8: new java.lang.StringBuilder
		// @0DB: dup
		// @0DC: invokespecial java.lang.StringBuilder.<init>()void
		// @0DF: getstatic java.lang.String[] game.C_100095_fe.field_103382_T
		// @0E2: bipush 9 (0x09)
		// @0E4: aaload
		// @0E5: invokevirtual java.lang.StringBuilder.append(java.lang.String)java.lang.StringBuilder
		// @0E8: iload_0
		// @0E9: invokevirtual java.lang.StringBuilder.append(int)java.lang.StringBuilder
		// @0EC: bipush 44 (0x2C)
		// @0EE: invokevirtual java.lang.StringBuilder.append(char)java.lang.StringBuilder
		// @0F1: iload_1
		// @0F2: invokevirtual java.lang.StringBuilder.append(int)java.lang.StringBuilder
		// @0F5: bipush 41 (0x29)
		// @0F7: invokevirtual java.lang.StringBuilder.append(char)java.lang.StringBuilder
		// @0FA: invokevirtual java.lang.StringBuilder.toString()java.lang.String
		// @0FD: invokestatic game.C_100181_cf.func_105695_a(java.lang.Throwable, java.lang.String)game.C_100170_cm
		// @100: athrow
	}
	
	static final void func_103371_l(int arg0)
	{
		// @00: iload_0
		// @01: sipush 13313 (0x3401)
		// @04: if_icmpeq @10
		// @07: bipush 95 (0x5F)
		// @09: invokestatic game.C_100095_fe.func_103378_m(int)void
		// @0C: goto @10
		// @0F: athrow
		// @10: aconst_null
		// @11: getstatic game.C_100286_nl game.C_100318_hj.field_107194_f
		// @14: if_acmpne @1B
		// @17: goto @2A
		// @1A: athrow
		// @1B: getstatic game.C_100286_nl game.C_100318_hj.field_107194_f
		// @1E: iload_0
		// @1F: sipush -24130 (0xA1BE)
		// @22: ixor
		// @23: invokevirtual game.C_100286_nl.func_106799_d(int)void
		// @26: aconst_null
		// @27: putstatic game.C_100286_nl game.C_100318_hj.field_107194_f
		// @2A: goto @4E
		// @2D: astore_1
		// @2E: aload_1
		// @2F: new java.lang.StringBuilder
		// @32: dup
		// @33: invokespecial java.lang.StringBuilder.<init>()void
		// @36: getstatic java.lang.String[] game.C_100095_fe.field_103382_T
		// @39: iconst_5
		// @3A: aaload
		// @3B: invokevirtual java.lang.StringBuilder.append(java.lang.String)java.lang.StringBuilder
		// @3E: iload_0
		// @3F: invokevirtual java.lang.StringBuilder.append(int)java.lang.StringBuilder
		// @42: bipush 41 (0x29)
		// @44: invokevirtual java.lang.StringBuilder.append(char)java.lang.StringBuilder
		// @47: invokevirtual java.lang.StringBuilder.toString()java.lang.String
		// @4A: invokestatic game.C_100181_cf.func_105695_a(java.lang.Throwable, java.lang.String)game.C_100170_cm
		// @4D: athrow
		// @4E: return
	}
	
	static final void func_103378_m(int arg0)
	{
		// @00: iload_0
		// @01: sipush 17237 (0x4355)
		// @04: if_icmpeq @13
		// @07: ldc 65495 (0xffd7)
		// @09: bipush -39 (0xD9)
		// @0B: invokestatic game.C_100095_fe.func_103379_a(char, byte)boolean
		// @0E: pop
		// @0F: goto @13
		// @12: athrow
		// @13: iconst_0
		// @14: putstatic int game.C_100084_ug.field_104484_a
		// @17: goto @3C
		// @1A: astore_1
		// @1B: aload_1
		// @1C: new java.lang.StringBuilder
		// @1F: dup
		// @20: invokespecial java.lang.StringBuilder.<init>()void
		// @23: getstatic java.lang.String[] game.C_100095_fe.field_103382_T
		// @26: bipush 7 (0x07)
		// @28: aaload
		// @29: invokevirtual java.lang.StringBuilder.append(java.lang.String)java.lang.StringBuilder
		// @2C: iload_0
		// @2D: invokevirtual java.lang.StringBuilder.append(int)java.lang.StringBuilder
		// @30: bipush 41 (0x29)
		// @32: invokevirtual java.lang.StringBuilder.append(char)java.lang.StringBuilder
		// @35: invokevirtual java.lang.StringBuilder.toString()java.lang.String
		// @38: invokestatic game.C_100181_cf.func_105695_a(java.lang.Throwable, java.lang.String)game.C_100170_cm
		// @3B: athrow
		// @3C: return
	}
	
	static final int func_103381_a(char arg0, CharSequence arg1, int arg2)
	{
		// @00: getstatic int game.SteelSentinels.field_105275_O
		// @03: istore #6
		// @05: iconst_0
		// @06: istore_3
		// @07: aload_1
		// @08: invokeinterface java.lang.CharSequence.length()int
		// @0D: istore #4
		// @0F: iload_2
		// @10: istore #5
		// @12: iload #4
		// @14: iconst_m1
		// @15: ixor
		// @16: iload #5
		// @18: iconst_m1
		// @19: ixor
		// @1A: if_icmpge @45
		// @1D: iload_0
		// @1E: iconst_m1
		// @1F: ixor
		// @20: iload #6
		// @22: ifne @46
		// @25: aload_1
		// @26: iload #5
		// @28: invokeinterface java.lang.CharSequence.charAt(int)char
		// @2D: iconst_m1
		// @2E: ixor
		// @2F: if_icmpne @3D
		// @32: goto @36
		// @35: athrow
		// @36: iinc #3 +1
		// @39: goto @3D
		// @3C: athrow
		// @3D: iinc #5 +1
		// @40: iload #6
		// @42: ifeq @12
		// @45: iload_3
		// @46: ireturn
		// @47: astore_3
		// @48: aload_3
		// @49: new java.lang.StringBuilder
		// @4C: dup
		// @4D: invokespecial java.lang.StringBuilder.<init>()void
		// @50: getstatic java.lang.String[] game.C_100095_fe.field_103382_T
		// @53: iconst_1
		// @54: aaload
		// @55: invokevirtual java.lang.StringBuilder.append(java.lang.String)java.lang.StringBuilder
		// @58: iload_0
		// @59: invokevirtual java.lang.StringBuilder.append(char)java.lang.StringBuilder
		// @5C: bipush 44 (0x2C)
		// @5E: invokevirtual java.lang.StringBuilder.append(char)java.lang.StringBuilder
		// @61: aload_1
		// @62: ifnull @6E
		// @65: getstatic java.lang.String[] game.C_100095_fe.field_103382_T
		// @68: iconst_2
		// @69: aaload
		// @6A: goto @73
		// @6D: athrow
		// @6E: getstatic java.lang.String[] game.C_100095_fe.field_103382_T
		// @71: iconst_0
		// @72: aaload
		// @73: invokevirtual java.lang.StringBuilder.append(java.lang.String)java.lang.StringBuilder
		// @76: bipush 44 (0x2C)
		// @78: invokevirtual java.lang.StringBuilder.append(char)java.lang.StringBuilder
		// @7B: iload_2
		// @7C: invokevirtual java.lang.StringBuilder.append(int)java.lang.StringBuilder
		// @7F: bipush 41 (0x29)
		// @81: invokevirtual java.lang.StringBuilder.append(char)java.lang.StringBuilder
		// @84: invokevirtual java.lang.StringBuilder.toString()java.lang.String
		// @87: invokestatic game.C_100181_cf.func_105695_a(java.lang.Throwable, java.lang.String)game.C_100170_cm
		// @8A: athrow
	}
	
	static final boolean func_103379_a(char arg0, byte arg1)
	{
		// @00: getstatic int game.SteelSentinels.field_105275_O
		// @03: istore #6
		// @05: iconst_m1
		// @06: iload_0
		// @07: iconst_m1
		// @08: ixor
		// @09: if_icmple @19
		// @0C: iload_0
		// @0D: iconst_m1
		// @0E: ixor
		// @0F: sipush -129 (0xFF7F)
		// @12: if_icmpgt @35
		// @15: goto @19
		// @18: athrow
		// @19: iload_0
		// @1A: iconst_m1
		// @1B: ixor
		// @1C: sipush -161 (0xFF5F)
		// @1F: if_icmpgt @37
		// @22: goto @26
		// @25: athrow
		// @26: iload_0
		// @27: sipush 255 (0x00FF)
		// @2A: if_icmple @35
		// @2D: goto @31
		// @30: athrow
		// @31: goto @37
		// @34: athrow
		// @35: iconst_1
		// @36: ireturn
		// @37: bipush -91 (0xA5)
		// @39: bipush -74 (0xB6)
		// @3B: iload_1
		// @3C: isub
		// @3D: bipush 47 (0x2F)
		// @3F: idiv
		// @40: idiv
		// @41: istore_2
		// @42: iload_0
		// @43: ifne @4A
		// @46: goto @7B
		// @49: athrow
		// @4A: getstatic char[] game.C_100133_tk.field_104997_d
		// @4D: astore_3
		// @4E: iconst_0
		// @4F: istore #4
		// @51: iload #4
		// @53: iconst_m1
		// @54: ixor
		// @55: aload_3
		// @56: arraylength
		// @57: iconst_m1
		// @58: ixor
		// @59: if_icmple @7B
		// @5C: aload_3
		// @5D: iload #4
		// @5F: caload
		// @60: istore #5
		// @62: iload_0
		// @63: iload #6
		// @65: ifne @7C
		// @68: iload #5
		// @6A: if_icmpne @73
		// @6D: goto @71
		// @70: athrow
		// @71: iconst_1
		// @72: ireturn
		// @73: iinc #4 +1
		// @76: iload #6
		// @78: ifeq @51
		// @7B: iconst_0
		// @7C: ireturn
		// @7D: astore_2
		// @7E: aload_2
		// @7F: new java.lang.StringBuilder
		// @82: dup
		// @83: invokespecial java.lang.StringBuilder.<init>()void
		// @86: getstatic java.lang.String[] game.C_100095_fe.field_103382_T
		// @89: iconst_4
		// @8A: aaload
		// @8B: invokevirtual java.lang.StringBuilder.append(java.lang.String)java.lang.StringBuilder
		// @8E: iload_0
		// @8F: invokevirtual java.lang.StringBuilder.append(char)java.lang.StringBuilder
		// @92: bipush 44 (0x2C)
		// @94: invokevirtual java.lang.StringBuilder.append(char)java.lang.StringBuilder
		// @97: iload_1
		// @98: invokevirtual java.lang.StringBuilder.append(int)java.lang.StringBuilder
		// @9B: bipush 41 (0x29)
		// @9D: invokevirtual java.lang.StringBuilder.append(char)java.lang.StringBuilder
		// @A0: invokevirtual java.lang.StringBuilder.toString()java.lang.String
		// @A3: invokestatic game.C_100181_cf.func_105695_a(java.lang.Throwable, java.lang.String)game.C_100170_cm
		// @A6: athrow
	}
	
	static final void func_103380_n(int arg0)
	{
		// @00: getstatic game.C_100323_hl game.C_100264_mg.field_106528_i
		// @03: ifnull @1A
		// @06: getstatic game.C_100323_hl game.C_100264_mg.field_106528_i
		// @09: dup
		// @0A: astore_1
		// @0B: monitorenter
		// @0C: aconst_null
		// @0D: putstatic game.C_100323_hl game.C_100264_mg.field_106528_i
		// @10: aload_1
		// @11: monitorexit
		// @12: goto @1A
		// @15: astore_2
		// @16: aload_1
		// @17: monitorexit
		// @18: aload_2
		// @19: athrow
		// @1A: bipush -5 (0xFB)
		// @1C: iload_0
		// @1D: bipush -49 (0xCF)
		// @1F: isub
		// @20: bipush 63 (0x3F)
		// @22: idiv
		// @23: idiv
		// @24: istore_1
		// @25: goto @4A
		// @28: astore_1
		// @29: aload_1
		// @2A: new java.lang.StringBuilder
		// @2D: dup
		// @2E: invokespecial java.lang.StringBuilder.<init>()void
		// @31: getstatic java.lang.String[] game.C_100095_fe.field_103382_T
		// @34: bipush 10 (0x0A)
		// @36: aaload
		// @37: invokevirtual java.lang.StringBuilder.append(java.lang.String)java.lang.StringBuilder
		// @3A: iload_0
		// @3B: invokevirtual java.lang.StringBuilder.append(int)java.lang.StringBuilder
		// @3E: bipush 41 (0x29)
		// @40: invokevirtual java.lang.StringBuilder.append(char)java.lang.StringBuilder
		// @43: invokevirtual java.lang.StringBuilder.toString()java.lang.String
		// @46: invokestatic game.C_100181_cf.func_105695_a(java.lang.Throwable, java.lang.String)game.C_100170_cm
		// @49: athrow
		// @4A: return
	}
	
	static final int func_103375_f(byte arg0)
	{
		// @00: iload_0
		// @01: bipush -78 (0xB2)
		// @03: if_icmplt @09
		// @06: bipush 74 (0x4A)
		// @08: ireturn
		// @09: getstatic int game.C_100162_sc.field_102860_Q
		// @0C: getstatic int game.C_100053_vn.field_102830_fb
		// @0F: ldc -1348117148 (0xafa55d64)
		// @11: ishl
		// @12: getstatic int game.C_100220_ac.field_106065_i
		// @15: ldc -137426750 (0xf7cf08c2)
		// @17: ishl
		// @18: iadd
		// @19: iadd
		// @1A: ireturn
		// @1B: astore_1
		// @1C: aload_1
		// @1D: new java.lang.StringBuilder
		// @20: dup
		// @21: invokespecial java.lang.StringBuilder.<init>()void
		// @24: getstatic java.lang.String[] game.C_100095_fe.field_103382_T
		// @27: bipush 12 (0x0C)
		// @29: aaload
		// @2A: invokevirtual java.lang.StringBuilder.append(java.lang.String)java.lang.StringBuilder
		// @2D: iload_0
		// @2E: invokevirtual java.lang.StringBuilder.append(int)java.lang.StringBuilder
		// @31: bipush 41 (0x29)
		// @33: invokevirtual java.lang.StringBuilder.append(char)java.lang.StringBuilder
		// @36: invokevirtual java.lang.StringBuilder.toString()java.lang.String
		// @39: invokestatic game.C_100181_cf.func_105695_a(java.lang.Throwable, java.lang.String)game.C_100170_cm
		// @3C: athrow
	}
	
	final void func_102519_a(byte arg0, int arg1, int arg2, int arg3, C_100336_im arg4, int arg5)
	{
		// @00: aload_0
		// @01: iload_1
		// @02: iload_2
		// @03: iload_3
		// @04: iload #4
		// @06: aload #5
		// @08: iload #6
		// @0A: invokespecial game.C_100030_gm.func_102519_a(byte, int, int, int, game.C_100336_im, int)void
		// @0D: getstatic game.C_100101_fc game.C_100125_tm.field_100747_o
		// @10: astore #7
		// @12: aload #7
		// @14: ifnull @82
		// @17: aload_0
		// @18: bipush -128 (0x80)
		// @1A: iload_3
		// @1B: iload_2
		// @1C: iload #6
		// @1E: iload #4
		// @20: invokevirtual game.C_100095_fe.func_102508_a(int, int, int, int, int)boolean
		// @23: ifeq @82
		// @26: goto @2A
		// @29: athrow
		// @2A: aload_0
		// @2B: getfield game.C_100337_in game.C_100095_fe.field_102543_u
		// @2E: instanceof game.C_100204_qk
		// @31: ifne @68
		// @34: goto @38
		// @37: athrow
		// @38: aload #7
		// @3A: getfield game.C_100337_in game.C_100101_fc.field_102543_u
		// @3D: instanceof game.C_100204_qk
		// @40: ifeq @82
		// @43: goto @47
		// @46: athrow
		// @47: aload #7
		// @49: getfield game.C_100337_in game.C_100101_fc.field_102543_u
		// @4C: checkcast game.C_100204_qk
		// @4F: sipush 17388 (0x43EC)
		// @52: aload_0
		// @53: aload #7
		// @55: invokeinterface game.C_100204_qk.func_102578_a(int, game.C_100095_fe, game.C_100101_fc)void
		// @5A: aconst_null
		// @5B: putstatic game.C_100101_fc game.C_100125_tm.field_100747_o
		// @5E: getstatic int game.SteelSentinels.field_105275_O
		// @61: ifeq @82
		// @64: goto @68
		// @67: athrow
		// @68: aload_0
		// @69: getfield game.C_100337_in game.C_100095_fe.field_102543_u
		// @6C: checkcast game.C_100204_qk
		// @6F: sipush 17388 (0x43EC)
		// @72: aload_0
		// @73: aload #7
		// @75: invokeinterface game.C_100204_qk.func_102578_a(int, game.C_100095_fe, game.C_100101_fc)void
		// @7A: aconst_null
		// @7B: putstatic game.C_100101_fc game.C_100125_tm.field_100747_o
		// @7E: goto @82
		// @81: athrow
		// @82: goto @EA
		// @85: astore #7
		// @87: aload #7
		// @89: new java.lang.StringBuilder
		// @8C: dup
		// @8D: invokespecial java.lang.StringBuilder.<init>()void
		// @90: getstatic java.lang.String[] game.C_100095_fe.field_103382_T
		// @93: bipush 6 (0x06)
		// @95: aaload
		// @96: invokevirtual java.lang.StringBuilder.append(java.lang.String)java.lang.StringBuilder
		// @99: iload_1
		// @9A: invokevirtual java.lang.StringBuilder.append(int)java.lang.StringBuilder
		// @9D: bipush 44 (0x2C)
		// @9F: invokevirtual java.lang.StringBuilder.append(char)java.lang.StringBuilder
		// @A2: iload_2
		// @A3: invokevirtual java.lang.StringBuilder.append(int)java.lang.StringBuilder
		// @A6: bipush 44 (0x2C)
		// @A8: invokevirtual java.lang.StringBuilder.append(char)java.lang.StringBuilder
		// @AB: iload_3
		// @AC: invokevirtual java.lang.StringBuilder.append(int)java.lang.StringBuilder
		// @AF: bipush 44 (0x2C)
		// @B1: invokevirtual java.lang.StringBuilder.append(char)java.lang.StringBuilder
		// @B4: iload #4
		// @B6: invokevirtual java.lang.StringBuilder.append(int)java.lang.StringBuilder
		// @B9: bipush 44 (0x2C)
		// @BB: invokevirtual java.lang.StringBuilder.append(char)java.lang.StringBuilder
		// @BE: aload #5
		// @C0: ifnull @CC
		// @C3: getstatic java.lang.String[] game.C_100095_fe.field_103382_T
		// @C6: iconst_2
		// @C7: aaload
		// @C8: goto @D1
		// @CB: athrow
		// @CC: getstatic java.lang.String[] game.C_100095_fe.field_103382_T
		// @CF: iconst_0
		// @D0: aaload
		// @D1: invokevirtual java.lang.StringBuilder.append(java.lang.String)java.lang.StringBuilder
		// @D4: bipush 44 (0x2C)
		// @D6: invokevirtual java.lang.StringBuilder.append(char)java.lang.StringBuilder
		// @D9: iload #6
		// @DB: invokevirtual java.lang.StringBuilder.append(int)java.lang.StringBuilder
		// @DE: bipush 41 (0x29)
		// @E0: invokevirtual java.lang.StringBuilder.append(char)java.lang.StringBuilder
		// @E3: invokevirtual java.lang.StringBuilder.toString()java.lang.String
		// @E6: invokestatic game.C_100181_cf.func_105695_a(java.lang.Throwable, java.lang.String)game.C_100170_cm
		// @E9: athrow
		// @EA: return
	}
	
	public static void func_103377_k(int arg0)
	{
		// @00: aconst_null
		// @01: putstatic game.C_100037_wb[] game.C_100095_fe.field_103383_Q
		// @04: aconst_null
		// @05: putstatic game.C_100302_ka game.C_100095_fe.field_103385_S
		// @08: aconst_null
		// @09: putstatic java.lang.String game.C_100095_fe.field_103384_P
		// @0C: iload_0
		// @0D: bipush -22 (0xEA)
		// @0F: if_icmple @19
		// @12: aconst_null
		// @13: checkcast game.C_100302_ka
		// @16: putstatic game.C_100302_ka game.C_100095_fe.field_103385_S
		// @19: goto @3E
		// @1C: astore_1
		// @1D: aload_1
		// @1E: new java.lang.StringBuilder
		// @21: dup
		// @22: invokespecial java.lang.StringBuilder.<init>()void
		// @25: getstatic java.lang.String[] game.C_100095_fe.field_103382_T
		// @28: bipush 11 (0x0B)
		// @2A: aaload
		// @2B: invokevirtual java.lang.StringBuilder.append(java.lang.String)java.lang.StringBuilder
		// @2E: iload_0
		// @2F: invokevirtual java.lang.StringBuilder.append(int)java.lang.StringBuilder
		// @32: bipush 41 (0x29)
		// @34: invokevirtual java.lang.StringBuilder.append(char)java.lang.StringBuilder
		// @37: invokevirtual java.lang.StringBuilder.toString()java.lang.String
		// @3A: invokestatic game.C_100181_cf.func_105695_a(java.lang.Throwable, java.lang.String)game.C_100170_cm
		// @3D: athrow
		// @3E: return
	}
	
	static final C_100009_fg func_103374_a(int arg0, int arg1, int arg2, byte arg3, C_100201_qj arg4, int arg5)
	{
		// @00: bipush 120 (0x78)
		// @02: iload_0
		// @03: aload #4
		// @05: iload_1
		// @06: iload_2
		// @07: iload #5
		// @09: invokestatic game.C_100269_ml.func_101115_a(byte, int, game.C_100201_qj, int, int, int)java.awt.Frame
		// @0C: astore #6
		// @0E: aconst_null
		// @0F: aload #6
		// @11: if_acmpne @16
		// @14: aconst_null
		// @15: areturn
		// @16: iload_3
		// @17: bipush -28 (0xE4)
		// @19: if_icmpeq @27
		// @1C: aconst_null
		// @1D: checkcast java.lang.String
		// @20: putstatic java.lang.String game.C_100095_fe.field_103384_P
		// @23: goto @27
		// @26: athrow
		// @27: new game.C_100009_fg
		// @2A: dup
		// @2B: invokespecial game.C_100009_fg.<init>()void
		// @2E: astore #7
		// @30: aload #7
		// @32: aload #6
		// @34: putfield java.awt.Frame game.C_100009_fg.field_103655_d
		// @37: aload #7
		// @39: getfield java.awt.Frame game.C_100009_fg.field_103655_d
		// @3C: aload #7
		// @3E: invokevirtual java.awt.Frame.add(java.awt.Component)java.awt.Component
		// @41: pop
		// @42: aload #7
		// @44: iconst_0
		// @45: iconst_0
		// @46: iload_0
		// @47: iload_2
		// @48: invokevirtual game.C_100009_fg.setBounds(int, int, int, int)void
		// @4B: aload #7
		// @4D: aload #7
		// @4F: invokevirtual game.C_100009_fg.addFocusListener(java.awt.event.FocusListener)void
		// @52: aload #7
		// @54: invokevirtual game.C_100009_fg.requestFocus()void
		// @57: aload #7
		// @59: areturn
		// @5A: astore #6
		// @5C: aload #6
		// @5E: new java.lang.StringBuilder
		// @61: dup
		// @62: invokespecial java.lang.StringBuilder.<init>()void
		// @65: getstatic java.lang.String[] game.C_100095_fe.field_103382_T
		// @68: bipush 8 (0x08)
		// @6A: aaload
		// @6B: invokevirtual java.lang.StringBuilder.append(java.lang.String)java.lang.StringBuilder
		// @6E: iload_0
		// @6F: invokevirtual java.lang.StringBuilder.append(int)java.lang.StringBuilder
		// @72: bipush 44 (0x2C)
		// @74: invokevirtual java.lang.StringBuilder.append(char)java.lang.StringBuilder
		// @77: iload_1
		// @78: invokevirtual java.lang.StringBuilder.append(int)java.lang.StringBuilder
		// @7B: bipush 44 (0x2C)
		// @7D: invokevirtual java.lang.StringBuilder.append(char)java.lang.StringBuilder
		// @80: iload_2
		// @81: invokevirtual java.lang.StringBuilder.append(int)java.lang.StringBuilder
		// @84: bipush 44 (0x2C)
		// @86: invokevirtual java.lang.StringBuilder.append(char)java.lang.StringBuilder
		// @89: iload_3
		// @8A: invokevirtual java.lang.StringBuilder.append(int)java.lang.StringBuilder
		// @8D: bipush 44 (0x2C)
		// @8F: invokevirtual java.lang.StringBuilder.append(char)java.lang.StringBuilder
		// @92: aload #4
		// @94: ifnull @A0
		// @97: getstatic java.lang.String[] game.C_100095_fe.field_103382_T
		// @9A: iconst_2
		// @9B: aaload
		// @9C: goto @A5
		// @9F: athrow
		// @A0: getstatic java.lang.String[] game.C_100095_fe.field_103382_T
		// @A3: iconst_0
		// @A4: aaload
		// @A5: invokevirtual java.lang.StringBuilder.append(java.lang.String)java.lang.StringBuilder
		// @A8: bipush 44 (0x2C)
		// @AA: invokevirtual java.lang.StringBuilder.append(char)java.lang.StringBuilder
		// @AD: iload #5
		// @AF: invokevirtual java.lang.StringBuilder.append(int)java.lang.StringBuilder
		// @B2: bipush 41 (0x29)
		// @B4: invokevirtual java.lang.StringBuilder.append(char)java.lang.StringBuilder
		// @B7: invokevirtual java.lang.StringBuilder.toString()java.lang.String
		// @BA: invokestatic game.C_100181_cf.func_105695_a(java.lang.Throwable, java.lang.String)game.C_100170_cm
		// @BD: athrow
	}
	
	static
	{
		// @00: bipush 13 (0x0D)
		// @02: anewarray java.lang.String
		// @05: dup
		// @06: iconst_0
		// @07: ldc "L\n\u0019m"
		// @09: invokestatic game.C_100095_fe.func_103376_z(java.lang.String)char[]
		// @0C: invokestatic game.C_100095_fe.func_103373_z(char[])java.lang.String
		// @0F: aastore
		// @10: dup
		// @11: iconst_1
		// @12: ldc "D\u001a[FQ"
		// @14: invokestatic game.C_100095_fe.func_103376_z(java.lang.String)char[]
		// @17: invokestatic game.C_100095_fe.func_103373_z(char[])java.lang.String
		// @1A: aastore
		// @1B: dup
		// @1C: iconst_2
		// @1D: ldc "YQ[/\u0004"
		// @1F: invokestatic game.C_100095_fe.func_103376_z(java.lang.String)char[]
		// @22: invokestatic game.C_100095_fe.func_103373_z(char[])java.lang.String
		// @25: aastore
		// @26: dup
		// @27: iconst_3
		// @28: ldc "D\u001a[=\u0010L\u0016\u0001?Q"
		// @2A: invokestatic game.C_100095_fe.func_103376_z(java.lang.String)char[]
		// @2D: invokestatic game.C_100095_fe.func_103373_z(char[])java.lang.String
		// @30: aastore
		// @31: dup
		// @32: iconst_4
		// @33: ldc "D\u001a[Q8\n"
		// @35: invokestatic game.C_100095_fe.func_103376_z(java.lang.String)char[]
		// @38: invokestatic game.C_100095_fe.func_103373_z(char[])java.lang.String
		// @3B: aastore
		// @3C: dup
		// @3D: iconst_5
		// @3E: ldc "D\u001a[EQ"
		// @40: invokestatic game.C_100095_fe.func_103376_z(java.lang.String)char[]
		// @43: invokestatic game.C_100095_fe.func_103373_z(char[])java.lang.String
		// @46: aastore
		// @47: dup
		// @48: bipush 6 (0x06)
		// @4A: ldc "D\u001a[UQ"
		// @4C: invokestatic game.C_100095_fe.func_103376_z(java.lang.String)char[]
		// @4F: invokestatic game.C_100095_fe.func_103373_z(char[])java.lang.String
		// @52: aastore
		// @53: dup
		// @54: bipush 7 (0x07)
		// @56: ldc "D\u001a[N8\n"
		// @58: invokestatic game.C_100095_fe.func_103376_z(java.lang.String)char[]
		// @5B: invokestatic game.C_100095_fe.func_103373_z(char[])java.lang.String
		// @5E: aastore
		// @5F: dup
		// @60: bipush 8 (0x08)
		// @62: ldc "D\u001a[HQ"
		// @64: invokestatic game.C_100095_fe.func_103376_z(java.lang.String)char[]
		// @67: invokestatic game.C_100095_fe.func_103373_z(char[])java.lang.String
		// @6A: aastore
		// @6B: dup
		// @6C: bipush 9 (0x09)
		// @6E: ldc "D\u001a[IQ"
		// @70: invokestatic game.C_100095_fe.func_103376_z(java.lang.String)char[]
		// @73: invokestatic game.C_100095_fe.func_103373_z(char[])java.lang.String
		// @76: aastore
		// @77: dup
		// @78: bipush 10 (0x0A)
		// @7A: ldc "D\u001a[DQ"
		// @7C: invokestatic game.C_100095_fe.func_103376_z(java.lang.String)char[]
		// @7F: invokestatic game.C_100095_fe.func_103373_z(char[])java.lang.String
		// @82: aastore
		// @83: dup
		// @84: bipush 11 (0x0B)
		// @86: ldc "D\u001a[@Q"
		// @88: invokestatic game.C_100095_fe.func_103376_z(java.lang.String)char[]
		// @8B: invokestatic game.C_100095_fe.func_103373_z(char[])java.lang.String
		// @8E: aastore
		// @8F: dup
		// @90: bipush 12 (0x0C)
		// @92: ldc "D\u001a[CQ"
		// @94: invokestatic game.C_100095_fe.func_103376_z(java.lang.String)char[]
		// @97: invokestatic game.C_100095_fe.func_103373_z(char[])java.lang.String
		// @9A: aastore
		// @9B: putstatic java.lang.String[] game.C_100095_fe.field_103382_T
		// @9E: return
	}
	
	private static char[] func_103376_z(String arg0)
	{
		// @00: aload_0
		// @01: invokevirtual java.lang.String.toCharArray()char[]
		// @04: dup
		// @05: arraylength
		// @06: iconst_2
		// @07: if_icmpge @13
		// @0A: dup
		// @0B: iconst_0
		// @0C: dup2
		// @0D: caload
		// @0E: bipush 121 (0x79)
		// @10: ixor
		// @11: i2c
		// @12: castore
		// @13: areturn
	}
	
	private static String func_103373_z(char[] arg0)
	{
		// @00: aload_0
		// @01: dup
		// @02: arraylength
		// @03: swap
		// @04: iconst_0
		// @05: istore_1
		// @06: goto @4B
		// @09: dup
		// @0A: iload_1
		// @0B: dup2
		// @0C: caload
		// @0D: iload_1
		// @0E: iconst_5
		// @0F: irem
		// @10: tableswitch def: @43, for 0: @30, for 1: @35, for 2: @3A, for 3: @3F
		// @30: bipush 34 (0x22)
		// @32: goto @45
		// @35: bipush 127 (0x7F)
		// @37: goto @45
		// @3A: bipush 117 (0x75)
		// @3C: goto @45
		// @3F: iconst_1
		// @40: goto @45
		// @43: bipush 121 (0x79)
		// @45: ixor
		// @46: i2c
		// @47: castore
		// @48: iinc #1 +1
		// @4B: swap
		// @4C: dup_x1
		// @4D: iload_1
		// @4E: if_icmpgt @09
		// @51: new java.lang.String
		// @54: dup_x1
		// @55: swap
		// @56: invokespecial java.lang.String.<init>(char[])void
		// @59: invokevirtual java.lang.String.intern()java.lang.String
		// @5C: areturn
	}
}
