package game;

import java.applet.Applet;

final class C_100175_cl
{
	static final Object func_105614_a(int arg0, String arg1, Applet arg2) throws Throwable
	{
		// @00: iload_0
		// @01: sipush 17228 (0x434C)
		// @04: if_icmpeq @0C
		// @07: aconst_null
		// @08: checkcast java.lang.Object
		// @0B: areturn
		// @0C: aload_2
		// @0D: invokestatic netscape.javascript.JSObject.getWindow(java.applet.Applet)netscape.javascript.JSObject
		// @10: aload_1
		// @11: aconst_null
		// @12: invokevirtual netscape.javascript.JSObject.call(java.lang.String, java.lang.Object[])java.lang.Object
		// @15: areturn
		// @16: astore_3
		// @17: aload_3
		// @18: athrow
	}
	
	static final void func_105615_a(String arg0, int arg1, Applet arg2) throws Throwable
	{
		// @00: iload_1
		// @01: sipush -1492 (0xFA2C)
		// @04: if_icmpeq @08
		// @07: return
		// @08: aload_2
		// @09: invokestatic netscape.javascript.JSObject.getWindow(java.applet.Applet)netscape.javascript.JSObject
		// @0C: aload_0
		// @0D: invokevirtual netscape.javascript.JSObject.eval(java.lang.String)java.lang.Object
		// @10: pop
		// @11: goto @17
		// @14: astore_3
		// @15: aload_3
		// @16: athrow
		// @17: return
	}
	
	static final Object func_105613_a(String arg0, Applet arg1, byte arg2, Object[] arg3) throws Throwable
	{
		// @00: iload_2
		// @01: bipush -88 (0xA8)
		// @03: if_icmple @0B
		// @06: aconst_null
		// @07: checkcast java.lang.Object
		// @0A: areturn
		// @0B: aload_1
		// @0C: invokestatic netscape.javascript.JSObject.getWindow(java.applet.Applet)netscape.javascript.JSObject
		// @0F: aload_0
		// @10: aload_3
		// @11: invokevirtual netscape.javascript.JSObject.call(java.lang.String, java.lang.Object[])java.lang.Object
		// @14: areturn
		// @15: astore #4
		// @17: aload #4
		// @19: athrow
	}
}
