package game;

import java.awt.Canvas;

final class C_100346_ja extends C_100158_da
{
	static String field_103489_w;
	static String field_103490_v;
	int field_103494_r;
	static String field_103496_p;
	String[][] field_103480_A;
	static String field_103491_u;
	static String field_103481_B;
	int field_103493_s;
	static int field_103498_y;
	int field_103483_n;
	static C_100115_ej field_103486_m;
	int field_103492_t;
	int field_103484_o;
	int field_103485_l;
	static int[] field_103488_k;
	static int[][] field_103487_j;
	boolean field_103499_x;
	int[][] field_103495_q;
	static C_100037_wb[] field_103497_z;
	private static final String[] field_103482_C;
	
	static final boolean func_103474_a(boolean arg0)
	{
		// @00: iload_0
		// @01: iconst_1
		// @02: if_icmpeq @07
		// @05: iconst_0
		// @06: ireturn
		// @07: getstatic game.C_100029_gn game.C_100013_fn.field_103738_g
		// @0A: ifnull @22
		// @0D: aconst_null
		// @0E: getstatic game.C_100029_gn game.C_100013_fn.field_103738_g
		// @11: bipush 126 (0x7E)
		// @13: invokevirtual game.C_100029_gn.func_103353_g(byte)game.C_100136_th
		// @16: if_acmpeq @22
		// @19: goto @1D
		// @1C: athrow
		// @1D: iconst_1
		// @1E: goto @23
		// @21: athrow
		// @22: iconst_0
		// @23: ireturn
		// @24: astore_1
		// @25: aload_1
		// @26: new java.lang.StringBuilder
		// @29: dup
		// @2A: invokespecial java.lang.StringBuilder.<init>()void
		// @2D: getstatic java.lang.String[] game.C_100346_ja.field_103482_C
		// @30: iconst_5
		// @31: aaload
		// @32: invokevirtual java.lang.StringBuilder.append(java.lang.String)java.lang.StringBuilder
		// @35: iload_0
		// @36: invokevirtual java.lang.StringBuilder.append(boolean)java.lang.StringBuilder
		// @39: bipush 41 (0x29)
		// @3B: invokevirtual java.lang.StringBuilder.append(char)java.lang.StringBuilder
		// @3E: invokevirtual java.lang.StringBuilder.toString()java.lang.String
		// @41: invokestatic game.C_100181_cf.func_105695_a(java.lang.Throwable, java.lang.String)game.C_100170_cm
		// @44: athrow
	}
	
	static final void func_103477_a(int arg0, Canvas arg1)
	{
		// @00: iload_0
		// @01: sipush 22173 (0x569D)
		// @04: iadd
		// @05: aload_1
		// @06: invokestatic game.C_100293_kj.func_106880_a(int, java.awt.Component)void
		// @09: aload_1
		// @0A: bipush 45 (0x2D)
		// @0C: invokestatic game.C_100107_u.func_104761_a(java.awt.Component, byte)void
		// @0F: aconst_null
		// @10: getstatic game.C_100089_fa game.C_100143_bl.field_105104_c
		// @13: if_acmpne @1A
		// @16: goto @23
		// @19: athrow
		// @1A: getstatic game.C_100089_fa game.C_100143_bl.field_105104_c
		// @1D: bipush 120 (0x78)
		// @1F: aload_1
		// @20: invokevirtual game.C_100089_fa.func_103720_a(byte, java.awt.Component)void
		// @23: iload_0
		// @24: bipush 89 (0x59)
		// @26: if_icmpeq @34
		// @29: aconst_null
		// @2A: checkcast java.lang.String
		// @2D: putstatic java.lang.String game.C_100346_ja.field_103491_u
		// @30: goto @34
		// @33: athrow
		// @34: goto @72
		// @37: astore_2
		// @38: aload_2
		// @39: new java.lang.StringBuilder
		// @3C: dup
		// @3D: invokespecial java.lang.StringBuilder.<init>()void
		// @40: getstatic java.lang.String[] game.C_100346_ja.field_103482_C
		// @43: iconst_2
		// @44: aaload
		// @45: invokevirtual java.lang.StringBuilder.append(java.lang.String)java.lang.StringBuilder
		// @48: iload_0
		// @49: invokevirtual java.lang.StringBuilder.append(int)java.lang.StringBuilder
		// @4C: bipush 44 (0x2C)
		// @4E: invokevirtual java.lang.StringBuilder.append(char)java.lang.StringBuilder
		// @51: aload_1
		// @52: ifnull @5E
		// @55: getstatic java.lang.String[] game.C_100346_ja.field_103482_C
		// @58: iconst_1
		// @59: aaload
		// @5A: goto @63
		// @5D: athrow
		// @5E: getstatic java.lang.String[] game.C_100346_ja.field_103482_C
		// @61: iconst_0
		// @62: aaload
		// @63: invokevirtual java.lang.StringBuilder.append(java.lang.String)java.lang.StringBuilder
		// @66: bipush 41 (0x29)
		// @68: invokevirtual java.lang.StringBuilder.append(char)java.lang.StringBuilder
		// @6B: invokevirtual java.lang.StringBuilder.toString()java.lang.String
		// @6E: invokestatic game.C_100181_cf.func_105695_a(java.lang.Throwable, java.lang.String)game.C_100170_cm
		// @71: athrow
		// @72: return
	}
	
	static final void func_103479_a(int arg0, byte arg1, int arg2, C_100127_tl arg3, C_100127_tl arg4, int arg5)
	{
		// @00: iload #5
		// @02: putstatic int game.C_100180_ce.field_104811_r
		// @05: aload #4
		// @07: putstatic game.C_100127_tl game.C_100311_le.field_104715_v
		// @0A: iload_2
		// @0B: putstatic int game.C_100283_ni.field_106755_f
		// @0E: iload_0
		// @0F: putstatic int game.C_100099_fb.field_103048_s
		// @12: iload_1
		// @13: bipush -13 (0xF3)
		// @15: if_icmple @23
		// @18: aconst_null
		// @19: checkcast java.lang.String
		// @1C: putstatic java.lang.String game.C_100346_ja.field_103491_u
		// @1F: goto @23
		// @22: athrow
		// @23: aload_3
		// @24: putstatic game.C_100127_tl game.C_100059_df.field_101614_t
		// @27: goto @9E
		// @2A: astore #6
		// @2C: aload #6
		// @2E: new java.lang.StringBuilder
		// @31: dup
		// @32: invokespecial java.lang.StringBuilder.<init>()void
		// @35: getstatic java.lang.String[] game.C_100346_ja.field_103482_C
		// @38: iconst_3
		// @39: aaload
		// @3A: invokevirtual java.lang.StringBuilder.append(java.lang.String)java.lang.StringBuilder
		// @3D: iload_0
		// @3E: invokevirtual java.lang.StringBuilder.append(int)java.lang.StringBuilder
		// @41: bipush 44 (0x2C)
		// @43: invokevirtual java.lang.StringBuilder.append(char)java.lang.StringBuilder
		// @46: iload_1
		// @47: invokevirtual java.lang.StringBuilder.append(int)java.lang.StringBuilder
		// @4A: bipush 44 (0x2C)
		// @4C: invokevirtual java.lang.StringBuilder.append(char)java.lang.StringBuilder
		// @4F: iload_2
		// @50: invokevirtual java.lang.StringBuilder.append(int)java.lang.StringBuilder
		// @53: bipush 44 (0x2C)
		// @55: invokevirtual java.lang.StringBuilder.append(char)java.lang.StringBuilder
		// @58: aload_3
		// @59: ifnull @65
		// @5C: getstatic java.lang.String[] game.C_100346_ja.field_103482_C
		// @5F: iconst_1
		// @60: aaload
		// @61: goto @6A
		// @64: athrow
		// @65: getstatic java.lang.String[] game.C_100346_ja.field_103482_C
		// @68: iconst_0
		// @69: aaload
		// @6A: invokevirtual java.lang.StringBuilder.append(java.lang.String)java.lang.StringBuilder
		// @6D: bipush 44 (0x2C)
		// @6F: invokevirtual java.lang.StringBuilder.append(char)java.lang.StringBuilder
		// @72: aload #4
		// @74: ifnull @80
		// @77: getstatic java.lang.String[] game.C_100346_ja.field_103482_C
		// @7A: iconst_1
		// @7B: aaload
		// @7C: goto @85
		// @7F: athrow
		// @80: getstatic java.lang.String[] game.C_100346_ja.field_103482_C
		// @83: iconst_0
		// @84: aaload
		// @85: invokevirtual java.lang.StringBuilder.append(java.lang.String)java.lang.StringBuilder
		// @88: bipush 44 (0x2C)
		// @8A: invokevirtual java.lang.StringBuilder.append(char)java.lang.StringBuilder
		// @8D: iload #5
		// @8F: invokevirtual java.lang.StringBuilder.append(int)java.lang.StringBuilder
		// @92: bipush 41 (0x29)
		// @94: invokevirtual java.lang.StringBuilder.append(char)java.lang.StringBuilder
		// @97: invokevirtual java.lang.StringBuilder.toString()java.lang.String
		// @9A: invokestatic game.C_100181_cf.func_105695_a(java.lang.Throwable, java.lang.String)game.C_100170_cm
		// @9D: athrow
		// @9E: return
	}
	
	public static void func_103476_a(byte arg0)
	{
		// @00: iload_0
		// @01: bipush 15 (0x0F)
		// @03: if_icmpeq @0F
		// @06: bipush -10 (0xF6)
		// @08: putstatic int game.C_100346_ja.field_103498_y
		// @0B: goto @0F
		// @0E: athrow
		// @0F: aconst_null
		// @10: checkcast int[][]
		// @13: putstatic int[][] game.C_100346_ja.field_103487_j
		// @16: aconst_null
		// @17: putstatic game.C_100115_ej game.C_100346_ja.field_103486_m
		// @1A: aconst_null
		// @1B: putstatic java.lang.String game.C_100346_ja.field_103489_w
		// @1E: aconst_null
		// @1F: putstatic java.lang.String game.C_100346_ja.field_103481_B
		// @22: aconst_null
		// @23: putstatic java.lang.String game.C_100346_ja.field_103490_v
		// @26: aconst_null
		// @27: putstatic java.lang.String game.C_100346_ja.field_103491_u
		// @2A: aconst_null
		// @2B: putstatic game.C_100037_wb[] game.C_100346_ja.field_103497_z
		// @2E: aconst_null
		// @2F: putstatic int[] game.C_100346_ja.field_103488_k
		// @32: aconst_null
		// @33: putstatic java.lang.String game.C_100346_ja.field_103496_p
		// @36: goto @5A
		// @39: astore_1
		// @3A: aload_1
		// @3B: new java.lang.StringBuilder
		// @3E: dup
		// @3F: invokespecial java.lang.StringBuilder.<init>()void
		// @42: getstatic java.lang.String[] game.C_100346_ja.field_103482_C
		// @45: iconst_4
		// @46: aaload
		// @47: invokevirtual java.lang.StringBuilder.append(java.lang.String)java.lang.StringBuilder
		// @4A: iload_0
		// @4B: invokevirtual java.lang.StringBuilder.append(int)java.lang.StringBuilder
		// @4E: bipush 41 (0x29)
		// @50: invokevirtual java.lang.StringBuilder.append(char)java.lang.StringBuilder
		// @53: invokevirtual java.lang.StringBuilder.toString()java.lang.String
		// @56: invokestatic game.C_100181_cf.func_105695_a(java.lang.Throwable, java.lang.String)game.C_100170_cm
		// @59: athrow
		// @5A: return
	}
	
	static
	{
		// @000: bipush 6 (0x06)
		// @002: anewarray java.lang.String
		// @005: dup
		// @006: iconst_0
		// @007: ldc "D\u0010R]"
		// @009: invokestatic game.C_100346_ja.func_103478_z(java.lang.String)char[]
		// @00C: invokestatic game.C_100346_ja.func_103475_z(char[])java.lang.String
		// @00F: aastore
		// @010: dup
		// @011: iconst_1
		// @012: ldc "QK\u0010\u001fz"
		// @014: invokestatic game.C_100346_ja.func_103478_z(java.lang.String)char[]
		// @017: invokestatic game.C_100346_ja.func_103475_z(char[])java.lang.String
		// @01A: aastore
		// @01B: dup
		// @01C: iconst_2
		// @01D: ldc "@\u0004\u0010r/"
		// @01F: invokestatic game.C_100346_ja.func_103478_z(java.lang.String)char[]
		// @022: invokestatic game.C_100346_ja.func_103475_z(char[])java.lang.String
		// @025: aastore
		// @026: dup
		// @027: iconst_3
		// @028: ldc "@\u0004\u0010p/"
		// @02A: invokestatic game.C_100346_ja.func_103478_z(java.lang.String)char[]
		// @02D: invokestatic game.C_100346_ja.func_103475_z(char[])java.lang.String
		// @030: aastore
		// @031: dup
		// @032: iconst_4
		// @033: ldc "@\u0004\u0010u/"
		// @035: invokestatic game.C_100346_ja.func_103478_z(java.lang.String)char[]
		// @038: invokestatic game.C_100346_ja.func_103475_z(char[])java.lang.String
		// @03B: aastore
		// @03C: dup
		// @03D: iconst_5
		// @03E: ldc "@\u0004\u0010s/"
		// @040: invokestatic game.C_100346_ja.func_103478_z(java.lang.String)char[]
		// @043: invokestatic game.C_100346_ja.func_103475_z(char[])java.lang.String
		// @046: aastore
		// @047: putstatic java.lang.String[] game.C_100346_ja.field_103482_C
		// @04A: ldc "y\tQEt\u0010Y\\C9\u0016@\u000e\u000f'\u0016\u0011W\\bY[\u001e\r\"\u001b["
		// @04C: invokestatic game.C_100346_ja.func_103478_z(java.lang.String)char[]
		// @04F: invokestatic game.C_100346_ja.func_103475_z(char[])java.lang.String
		// @052: putstatic java.lang.String game.C_100346_ja.field_103489_w
		// @055: ldc "f\n_UnD\u0002\u001eT\u007f^\u0017_\u0011cK\u0011_"
		// @057: invokestatic game.C_100346_ja.func_103478_z(java.lang.String)char[]
		// @05A: invokestatic game.C_100346_ja.func_103475_z(char[])java.lang.String
		// @05D: putstatic java.lang.String game.C_100346_ja.field_103496_p
		// @060: ldc "\u0016@\u000f\u000f']\u0004M\u0011hH\tWEbX\u0004JTc\n\u000cP\u0011;\u000fU\u0000\u0016t\n\u000bKRkO\u0004L\u0011aC\u0017[SfF\t"
		// @062: invokestatic game.C_100346_ja.func_103478_z(java.lang.String)char[]
		// @065: invokestatic game.C_100346_ja.func_103475_z(char[])java.lang.String
		// @068: putstatic java.lang.String game.C_100346_ja.field_103491_u
		// @06B: ldc "}\u0004WEnD\u0002\u001eWhXEX^i^\u0016"
		// @06D: invokestatic game.C_100346_ja.func_103478_z(java.lang.String)char[]
		// @070: invokestatic game.C_100346_ja.func_103475_z(char[])java.lang.String
		// @073: putstatic java.lang.String game.C_100346_ja.field_103481_B
		// @076: ldc "\u007f\u000b_SkOEJ^'K\u0001Z\u0011aX\u000c[_c\nH\u001eB~Y\u0011[\\'H\u0010MH"
		// @078: invokestatic game.C_100346_ja.func_103478_z(java.lang.String)char[]
		// @07B: invokestatic game.C_100346_ja.func_103475_z(char[])java.lang.String
		// @07E: putstatic java.lang.String game.C_100346_ja.field_103490_v
		// @081: bipush 20 (0x14)
		// @083: newarray int[]
		// @085: dup
		// @086: iconst_0
		// @087: bipush 88 (0x58)
		// @089: iastore
		// @08A: dup
		// @08B: iconst_1
		// @08C: bipush 105 (0x69)
		// @08E: iastore
		// @08F: dup
		// @090: iconst_2
		// @091: bipush 35 (0x23)
		// @093: iastore
		// @094: dup
		// @095: iconst_3
		// @096: bipush 91 (0x5B)
		// @098: iastore
		// @099: dup
		// @09A: iconst_4
		// @09B: bipush 90 (0x5A)
		// @09D: iastore
		// @09E: dup
		// @09F: iconst_5
		// @0A0: bipush 46 (0x2E)
		// @0A2: iastore
		// @0A3: dup
		// @0A4: bipush 6 (0x06)
		// @0A6: bipush 89 (0x59)
		// @0A8: iastore
		// @0A9: dup
		// @0AA: bipush 7 (0x07)
		// @0AC: bipush 50 (0x32)
		// @0AE: iastore
		// @0AF: dup
		// @0B0: bipush 8 (0x08)
		// @0B2: bipush 50 (0x32)
		// @0B4: iastore
		// @0B5: dup
		// @0B6: bipush 9 (0x09)
		// @0B8: bipush 24 (0x18)
		// @0BA: iastore
		// @0BB: dup
		// @0BC: bipush 10 (0x0A)
		// @0BE: bipush 24 (0x18)
		// @0C0: iastore
		// @0C1: dup
		// @0C2: bipush 11 (0x0B)
		// @0C4: bipush 24 (0x18)
		// @0C6: iastore
		// @0C7: dup
		// @0C8: bipush 12 (0x0C)
		// @0CA: iconst_3
		// @0CB: iastore
		// @0CC: dup
		// @0CD: bipush 13 (0x0D)
		// @0CF: bipush 8 (0x08)
		// @0D1: iastore
		// @0D2: dup
		// @0D3: bipush 14 (0x0E)
		// @0D5: bipush 8 (0x08)
		// @0D7: iastore
		// @0D8: dup
		// @0D9: bipush 15 (0x0F)
		// @0DB: bipush 23 (0x17)
		// @0DD: iastore
		// @0DE: dup
		// @0DF: bipush 16 (0x10)
		// @0E1: bipush 13 (0x0D)
		// @0E3: iastore
		// @0E4: dup
		// @0E5: bipush 17 (0x11)
		// @0E7: bipush 15 (0x0F)
		// @0E9: iastore
		// @0EA: dup
		// @0EB: bipush 18 (0x12)
		// @0ED: iconst_m1
		// @0EE: iastore
		// @0EF: dup
		// @0F0: bipush 19 (0x13)
		// @0F2: iconst_m1
		// @0F3: iastore
		// @0F4: putstatic int[] game.C_100346_ja.field_103488_k
		// @0F7: iconst_3
		// @0F8: anewarray int[]
		// @0FB: dup
		// @0FC: iconst_0
		// @0FD: aconst_null
		// @0FE: aastore
		// @0FF: dup
		// @100: iconst_1
		// @101: aconst_null
		// @102: aastore
		// @103: dup
		// @104: iconst_2
		// @105: bipush 6 (0x06)
		// @107: newarray int[]
		// @109: dup
		// @10A: iconst_0
		// @10B: iconst_0
		// @10C: iastore
		// @10D: dup
		// @10E: iconst_1
		// @10F: iconst_0
		// @110: iastore
		// @111: dup
		// @112: iconst_2
		// @113: iconst_0
		// @114: iastore
		// @115: dup
		// @116: iconst_3
		// @117: iconst_0
		// @118: iastore
		// @119: dup
		// @11A: iconst_4
		// @11B: bipush 10 (0x0A)
		// @11D: iastore
		// @11E: dup
		// @11F: iconst_5
		// @120: iconst_0
		// @121: iastore
		// @122: aastore
		// @123: putstatic int[][] game.C_100346_ja.field_103487_j
		// @126: sipush 256 (0x0100)
		// @129: putstatic int game.C_100346_ja.field_103498_y
		// @12C: return
	}
	
	private static char[] func_103478_z(String arg0)
	{
		// @00: aload_0
		// @01: invokevirtual java.lang.String.toCharArray()char[]
		// @04: dup
		// @05: arraylength
		// @06: iconst_2
		// @07: if_icmpge @13
		// @0A: dup
		// @0B: iconst_0
		// @0C: dup2
		// @0D: caload
		// @0E: bipush 7 (0x07)
		// @10: ixor
		// @11: i2c
		// @12: castore
		// @13: areturn
	}
	
	private static String func_103475_z(char[] arg0)
	{
		// @00: aload_0
		// @01: dup
		// @02: arraylength
		// @03: swap
		// @04: iconst_0
		// @05: istore_1
		// @06: goto @4C
		// @09: dup
		// @0A: iload_1
		// @0B: dup2
		// @0C: caload
		// @0D: iload_1
		// @0E: iconst_5
		// @0F: irem
		// @10: tableswitch def: @44, for 0: @30, for 1: @35, for 2: @3A, for 3: @3F
		// @30: bipush 42 (0x2A)
		// @32: goto @46
		// @35: bipush 101 (0x65)
		// @37: goto @46
		// @3A: bipush 62 (0x3E)
		// @3C: goto @46
		// @3F: bipush 49 (0x31)
		// @41: goto @46
		// @44: bipush 7 (0x07)
		// @46: ixor
		// @47: i2c
		// @48: castore
		// @49: iinc #1 +1
		// @4C: swap
		// @4D: dup_x1
		// @4E: iload_1
		// @4F: if_icmpgt @09
		// @52: new java.lang.String
		// @55: dup_x1
		// @56: swap
		// @57: invokespecial java.lang.String.<init>(char[])void
		// @5A: invokevirtual java.lang.String.intern()java.lang.String
		// @5D: areturn
	}
}
