package game;

import java.awt.event.MouseMotionListener;
import java.awt.event.MouseListener;
import java.awt.event.MouseEvent;
import java.awt.event.FocusListener;
import java.awt.event.FocusEvent;

final class C_100047_vh implements MouseListener, MouseMotionListener, FocusListener
{
	static String[][] field_104153_c;
	static String field_104154_a;
	static C_100320_hh field_104150_d;
	static String field_104152_b;
	static String field_104149_f;
	static String field_104151_e;
	private static final String[] field_104155_z;
	
	static final int func_104148_b(int arg0)
	{
		// @00: iload_0
		// @01: iconst_m1
		// @02: if_icmpeq @10
		// @05: aconst_null
		// @06: checkcast java.lang.String
		// @09: putstatic java.lang.String game.C_100047_vh.field_104149_f
		// @0C: goto @10
		// @0F: athrow
		// @10: iconst_1
		// @11: ireturn
		// @12: astore_1
		// @13: aload_1
		// @14: new java.lang.StringBuilder
		// @17: dup
		// @18: invokespecial java.lang.StringBuilder.<init>()void
		// @1B: getstatic java.lang.String[] game.C_100047_vh.field_104155_z
		// @1E: bipush 6 (0x06)
		// @20: aaload
		// @21: invokevirtual java.lang.StringBuilder.append(java.lang.String)java.lang.StringBuilder
		// @24: iload_0
		// @25: invokevirtual java.lang.StringBuilder.append(int)java.lang.StringBuilder
		// @28: bipush 41 (0x29)
		// @2A: invokevirtual java.lang.StringBuilder.append(char)java.lang.StringBuilder
		// @2D: invokevirtual java.lang.StringBuilder.toString()java.lang.String
		// @30: invokestatic game.C_100181_cf.func_105695_a(java.lang.Throwable, java.lang.String)game.C_100170_cm
		// @33: athrow
	}
	
	public final synchronized void mouseExited(MouseEvent arg0)
	{
		// @00: getstatic game.C_100047_vh game.C_100111_el.field_104859_g
		// @03: ifnull @16
		// @06: iconst_0
		// @07: putstatic int game.C_100012_fh.field_100514_J
		// @0A: iconst_m1
		// @0B: putstatic int game.C_100231_oc.field_102198_ec
		// @0E: iconst_m1
		// @0F: putstatic int game.C_100113_ek.field_104884_h
		// @12: iconst_1
		// @13: putstatic boolean game.C_100246_pg.field_106404_b
		// @16: goto @4C
		// @19: astore_2
		// @1A: aload_2
		// @1B: new java.lang.StringBuilder
		// @1E: dup
		// @1F: invokespecial java.lang.StringBuilder.<init>()void
		// @22: getstatic java.lang.String[] game.C_100047_vh.field_104155_z
		// @25: bipush 10 (0x0A)
		// @27: aaload
		// @28: invokevirtual java.lang.StringBuilder.append(java.lang.String)java.lang.StringBuilder
		// @2B: aload_1
		// @2C: ifnull @38
		// @2F: getstatic java.lang.String[] game.C_100047_vh.field_104155_z
		// @32: iconst_1
		// @33: aaload
		// @34: goto @3D
		// @37: athrow
		// @38: getstatic java.lang.String[] game.C_100047_vh.field_104155_z
		// @3B: iconst_3
		// @3C: aaload
		// @3D: invokevirtual java.lang.StringBuilder.append(java.lang.String)java.lang.StringBuilder
		// @40: bipush 41 (0x29)
		// @42: invokevirtual java.lang.StringBuilder.append(char)java.lang.StringBuilder
		// @45: invokevirtual java.lang.StringBuilder.toString()java.lang.String
		// @48: invokestatic game.C_100181_cf.func_105695_a(java.lang.Throwable, java.lang.String)game.C_100170_cm
		// @4B: athrow
		// @4C: return
	}
	
	public static void func_104145_a(byte arg0)
	{
		// @00: aconst_null
		// @01: putstatic java.lang.String game.C_100047_vh.field_104154_a
		// @04: iload_0
		// @05: bipush 79 (0x4F)
		// @07: if_icmpeq @13
		// @0A: bipush -24 (0xE8)
		// @0C: invokestatic game.C_100047_vh.func_104145_a(byte)void
		// @0F: goto @13
		// @12: athrow
		// @13: aconst_null
		// @14: putstatic game.C_100320_hh game.C_100047_vh.field_104150_d
		// @17: aconst_null
		// @18: putstatic java.lang.String game.C_100047_vh.field_104151_e
		// @1B: aconst_null
		// @1C: putstatic java.lang.String game.C_100047_vh.field_104149_f
		// @1F: aconst_null
		// @20: checkcast java.lang.String[][]
		// @23: putstatic java.lang.String[][] game.C_100047_vh.field_104153_c
		// @26: aconst_null
		// @27: putstatic java.lang.String game.C_100047_vh.field_104152_b
		// @2A: goto @4E
		// @2D: astore_1
		// @2E: aload_1
		// @2F: new java.lang.StringBuilder
		// @32: dup
		// @33: invokespecial java.lang.StringBuilder.<init>()void
		// @36: getstatic java.lang.String[] game.C_100047_vh.field_104155_z
		// @39: iconst_4
		// @3A: aaload
		// @3B: invokevirtual java.lang.StringBuilder.append(java.lang.String)java.lang.StringBuilder
		// @3E: iload_0
		// @3F: invokevirtual java.lang.StringBuilder.append(int)java.lang.StringBuilder
		// @42: bipush 41 (0x29)
		// @44: invokevirtual java.lang.StringBuilder.append(char)java.lang.StringBuilder
		// @47: invokevirtual java.lang.StringBuilder.toString()java.lang.String
		// @4A: invokestatic game.C_100181_cf.func_105695_a(java.lang.Throwable, java.lang.String)game.C_100170_cm
		// @4D: athrow
		// @4E: return
	}
	
	public final void mouseClicked(MouseEvent arg0)
	{
		// @00: aload_1
		// @01: invokevirtual java.awt.event.MouseEvent.isPopupTrigger()boolean
		// @04: ifne @0B
		// @07: goto @0F
		// @0A: athrow
		// @0B: aload_1
		// @0C: invokevirtual java.awt.event.MouseEvent.consume()void
		// @0F: goto @45
		// @12: astore_2
		// @13: aload_2
		// @14: new java.lang.StringBuilder
		// @17: dup
		// @18: invokespecial java.lang.StringBuilder.<init>()void
		// @1B: getstatic java.lang.String[] game.C_100047_vh.field_104155_z
		// @1E: bipush 13 (0x0D)
		// @20: aaload
		// @21: invokevirtual java.lang.StringBuilder.append(java.lang.String)java.lang.StringBuilder
		// @24: aload_1
		// @25: ifnull @31
		// @28: getstatic java.lang.String[] game.C_100047_vh.field_104155_z
		// @2B: iconst_1
		// @2C: aaload
		// @2D: goto @36
		// @30: athrow
		// @31: getstatic java.lang.String[] game.C_100047_vh.field_104155_z
		// @34: iconst_3
		// @35: aaload
		// @36: invokevirtual java.lang.StringBuilder.append(java.lang.String)java.lang.StringBuilder
		// @39: bipush 41 (0x29)
		// @3B: invokevirtual java.lang.StringBuilder.append(char)java.lang.StringBuilder
		// @3E: invokevirtual java.lang.StringBuilder.toString()java.lang.String
		// @41: invokestatic game.C_100181_cf.func_105695_a(java.lang.Throwable, java.lang.String)game.C_100170_cm
		// @44: athrow
		// @45: return
	}
	
	public final void focusGained(FocusEvent arg0)
	{
		// @0: return
	}
	
	static final void func_104147_a(String[][] arg0, String[] arg1, int[] arg2, C_100098_h arg3, C_100037_wb[][] arg4, C_100153_be[] arg5, boolean arg6, int arg7, byte[] arg8, int arg9, C_100098_h arg10, byte arg11, C_100098_h arg12, byte[] arg13, int[] arg14, C_100037_wb[][] arg15, String[][] arg16)
	{
		// @000: aload #8
		// @002: aload_3
		// @003: bipush 69 (0x45)
		// @005: iload #7
		// @007: aload_2
		// @008: iconst_1
		// @009: aconst_null
		// @00A: aload #14
		// @00C: aload #13
		// @00E: aload #12
		// @010: aload #10
		// @012: aload #4
		// @014: aload #16
		// @016: aload #15
		// @018: iload #6
		// @01A: iload #9
		// @01C: aload #5
		// @01E: aload_0
		// @01F: aload_1
		// @020: invokestatic game.C_100057_dd.func_104247_a(byte[], game.C_100098_h, byte, int, int[], int, java.lang.String[], int[], byte[], game.C_100098_h, game.C_100098_h, game.C_100037_wb[][], java.lang.String[][], game.C_100037_wb[][], boolean, int, game.C_100153_be[], java.lang.String[][], java.lang.String[])void
		// @023: iload #11
		// @025: bipush -18 (0xEE)
		// @027: if_icmpeq @034
		// @02A: aconst_null
		// @02B: checkcast java.lang.String[][]
		// @02E: checkcast java.lang.String[][]
		// @031: putstatic java.lang.String[][] game.C_100047_vh.field_104153_c
		// @034: goto @1D5
		// @037: astore #17
		// @039: aload #17
		// @03B: new java.lang.StringBuilder
		// @03E: dup
		// @03F: invokespecial java.lang.StringBuilder.<init>()void
		// @042: getstatic java.lang.String[] game.C_100047_vh.field_104155_z
		// @045: bipush 12 (0x0C)
		// @047: aaload
		// @048: invokevirtual java.lang.StringBuilder.append(java.lang.String)java.lang.StringBuilder
		// @04B: aload_0
		// @04C: ifnull @058
		// @04F: getstatic java.lang.String[] game.C_100047_vh.field_104155_z
		// @052: iconst_1
		// @053: aaload
		// @054: goto @05D
		// @057: athrow
		// @058: getstatic java.lang.String[] game.C_100047_vh.field_104155_z
		// @05B: iconst_3
		// @05C: aaload
		// @05D: invokevirtual java.lang.StringBuilder.append(java.lang.String)java.lang.StringBuilder
		// @060: bipush 44 (0x2C)
		// @062: invokevirtual java.lang.StringBuilder.append(char)java.lang.StringBuilder
		// @065: aload_1
		// @066: ifnull @072
		// @069: getstatic java.lang.String[] game.C_100047_vh.field_104155_z
		// @06C: iconst_1
		// @06D: aaload
		// @06E: goto @077
		// @071: athrow
		// @072: getstatic java.lang.String[] game.C_100047_vh.field_104155_z
		// @075: iconst_3
		// @076: aaload
		// @077: invokevirtual java.lang.StringBuilder.append(java.lang.String)java.lang.StringBuilder
		// @07A: bipush 44 (0x2C)
		// @07C: invokevirtual java.lang.StringBuilder.append(char)java.lang.StringBuilder
		// @07F: aload_2
		// @080: ifnull @08C
		// @083: getstatic java.lang.String[] game.C_100047_vh.field_104155_z
		// @086: iconst_1
		// @087: aaload
		// @088: goto @091
		// @08B: athrow
		// @08C: getstatic java.lang.String[] game.C_100047_vh.field_104155_z
		// @08F: iconst_3
		// @090: aaload
		// @091: invokevirtual java.lang.StringBuilder.append(java.lang.String)java.lang.StringBuilder
		// @094: bipush 44 (0x2C)
		// @096: invokevirtual java.lang.StringBuilder.append(char)java.lang.StringBuilder
		// @099: aload_3
		// @09A: ifnull @0A6
		// @09D: getstatic java.lang.String[] game.C_100047_vh.field_104155_z
		// @0A0: iconst_1
		// @0A1: aaload
		// @0A2: goto @0AB
		// @0A5: athrow
		// @0A6: getstatic java.lang.String[] game.C_100047_vh.field_104155_z
		// @0A9: iconst_3
		// @0AA: aaload
		// @0AB: invokevirtual java.lang.StringBuilder.append(java.lang.String)java.lang.StringBuilder
		// @0AE: bipush 44 (0x2C)
		// @0B0: invokevirtual java.lang.StringBuilder.append(char)java.lang.StringBuilder
		// @0B3: aload #4
		// @0B5: ifnull @0C1
		// @0B8: getstatic java.lang.String[] game.C_100047_vh.field_104155_z
		// @0BB: iconst_1
		// @0BC: aaload
		// @0BD: goto @0C6
		// @0C0: athrow
		// @0C1: getstatic java.lang.String[] game.C_100047_vh.field_104155_z
		// @0C4: iconst_3
		// @0C5: aaload
		// @0C6: invokevirtual java.lang.StringBuilder.append(java.lang.String)java.lang.StringBuilder
		// @0C9: bipush 44 (0x2C)
		// @0CB: invokevirtual java.lang.StringBuilder.append(char)java.lang.StringBuilder
		// @0CE: aload #5
		// @0D0: ifnull @0DC
		// @0D3: getstatic java.lang.String[] game.C_100047_vh.field_104155_z
		// @0D6: iconst_1
		// @0D7: aaload
		// @0D8: goto @0E1
		// @0DB: athrow
		// @0DC: getstatic java.lang.String[] game.C_100047_vh.field_104155_z
		// @0DF: iconst_3
		// @0E0: aaload
		// @0E1: invokevirtual java.lang.StringBuilder.append(java.lang.String)java.lang.StringBuilder
		// @0E4: bipush 44 (0x2C)
		// @0E6: invokevirtual java.lang.StringBuilder.append(char)java.lang.StringBuilder
		// @0E9: iload #6
		// @0EB: invokevirtual java.lang.StringBuilder.append(boolean)java.lang.StringBuilder
		// @0EE: bipush 44 (0x2C)
		// @0F0: invokevirtual java.lang.StringBuilder.append(char)java.lang.StringBuilder
		// @0F3: iload #7
		// @0F5: invokevirtual java.lang.StringBuilder.append(int)java.lang.StringBuilder
		// @0F8: bipush 44 (0x2C)
		// @0FA: invokevirtual java.lang.StringBuilder.append(char)java.lang.StringBuilder
		// @0FD: aload #8
		// @0FF: ifnull @10B
		// @102: getstatic java.lang.String[] game.C_100047_vh.field_104155_z
		// @105: iconst_1
		// @106: aaload
		// @107: goto @110
		// @10A: athrow
		// @10B: getstatic java.lang.String[] game.C_100047_vh.field_104155_z
		// @10E: iconst_3
		// @10F: aaload
		// @110: invokevirtual java.lang.StringBuilder.append(java.lang.String)java.lang.StringBuilder
		// @113: bipush 44 (0x2C)
		// @115: invokevirtual java.lang.StringBuilder.append(char)java.lang.StringBuilder
		// @118: iload #9
		// @11A: invokevirtual java.lang.StringBuilder.append(int)java.lang.StringBuilder
		// @11D: bipush 44 (0x2C)
		// @11F: invokevirtual java.lang.StringBuilder.append(char)java.lang.StringBuilder
		// @122: aload #10
		// @124: ifnull @130
		// @127: getstatic java.lang.String[] game.C_100047_vh.field_104155_z
		// @12A: iconst_1
		// @12B: aaload
		// @12C: goto @135
		// @12F: athrow
		// @130: getstatic java.lang.String[] game.C_100047_vh.field_104155_z
		// @133: iconst_3
		// @134: aaload
		// @135: invokevirtual java.lang.StringBuilder.append(java.lang.String)java.lang.StringBuilder
		// @138: bipush 44 (0x2C)
		// @13A: invokevirtual java.lang.StringBuilder.append(char)java.lang.StringBuilder
		// @13D: iload #11
		// @13F: invokevirtual java.lang.StringBuilder.append(int)java.lang.StringBuilder
		// @142: bipush 44 (0x2C)
		// @144: invokevirtual java.lang.StringBuilder.append(char)java.lang.StringBuilder
		// @147: aload #12
		// @149: ifnull @155
		// @14C: getstatic java.lang.String[] game.C_100047_vh.field_104155_z
		// @14F: iconst_1
		// @150: aaload
		// @151: goto @15A
		// @154: athrow
		// @155: getstatic java.lang.String[] game.C_100047_vh.field_104155_z
		// @158: iconst_3
		// @159: aaload
		// @15A: invokevirtual java.lang.StringBuilder.append(java.lang.String)java.lang.StringBuilder
		// @15D: bipush 44 (0x2C)
		// @15F: invokevirtual java.lang.StringBuilder.append(char)java.lang.StringBuilder
		// @162: aload #13
		// @164: ifnull @170
		// @167: getstatic java.lang.String[] game.C_100047_vh.field_104155_z
		// @16A: iconst_1
		// @16B: aaload
		// @16C: goto @175
		// @16F: athrow
		// @170: getstatic java.lang.String[] game.C_100047_vh.field_104155_z
		// @173: iconst_3
		// @174: aaload
		// @175: invokevirtual java.lang.StringBuilder.append(java.lang.String)java.lang.StringBuilder
		// @178: bipush 44 (0x2C)
		// @17A: invokevirtual java.lang.StringBuilder.append(char)java.lang.StringBuilder
		// @17D: aload #14
		// @17F: ifnull @18B
		// @182: getstatic java.lang.String[] game.C_100047_vh.field_104155_z
		// @185: iconst_1
		// @186: aaload
		// @187: goto @190
		// @18A: athrow
		// @18B: getstatic java.lang.String[] game.C_100047_vh.field_104155_z
		// @18E: iconst_3
		// @18F: aaload
		// @190: invokevirtual java.lang.StringBuilder.append(java.lang.String)java.lang.StringBuilder
		// @193: bipush 44 (0x2C)
		// @195: invokevirtual java.lang.StringBuilder.append(char)java.lang.StringBuilder
		// @198: aload #15
		// @19A: ifnull @1A6
		// @19D: getstatic java.lang.String[] game.C_100047_vh.field_104155_z
		// @1A0: iconst_1
		// @1A1: aaload
		// @1A2: goto @1AB
		// @1A5: athrow
		// @1A6: getstatic java.lang.String[] game.C_100047_vh.field_104155_z
		// @1A9: iconst_3
		// @1AA: aaload
		// @1AB: invokevirtual java.lang.StringBuilder.append(java.lang.String)java.lang.StringBuilder
		// @1AE: bipush 44 (0x2C)
		// @1B0: invokevirtual java.lang.StringBuilder.append(char)java.lang.StringBuilder
		// @1B3: aload #16
		// @1B5: ifnull @1C1
		// @1B8: getstatic java.lang.String[] game.C_100047_vh.field_104155_z
		// @1BB: iconst_1
		// @1BC: aaload
		// @1BD: goto @1C6
		// @1C0: athrow
		// @1C1: getstatic java.lang.String[] game.C_100047_vh.field_104155_z
		// @1C4: iconst_3
		// @1C5: aaload
		// @1C6: invokevirtual java.lang.StringBuilder.append(java.lang.String)java.lang.StringBuilder
		// @1C9: bipush 41 (0x29)
		// @1CB: invokevirtual java.lang.StringBuilder.append(char)java.lang.StringBuilder
		// @1CE: invokevirtual java.lang.StringBuilder.toString()java.lang.String
		// @1D1: invokestatic game.C_100181_cf.func_105695_a(java.lang.Throwable, java.lang.String)game.C_100170_cm
		// @1D4: athrow
		// @1D5: return
	}
	
	public final synchronized void mouseEntered(MouseEvent arg0)
	{
		// @00: aconst_null
		// @01: getstatic game.C_100047_vh game.C_100111_el.field_104859_g
		// @04: if_acmpne @0B
		// @07: goto @21
		// @0A: athrow
		// @0B: iconst_0
		// @0C: putstatic int game.C_100012_fh.field_100514_J
		// @0F: aload_1
		// @10: invokevirtual java.awt.event.MouseEvent.getX()int
		// @13: putstatic int game.C_100231_oc.field_102198_ec
		// @16: aload_1
		// @17: invokevirtual java.awt.event.MouseEvent.getY()int
		// @1A: putstatic int game.C_100113_ek.field_104884_h
		// @1D: iconst_1
		// @1E: putstatic boolean game.C_100246_pg.field_106404_b
		// @21: goto @57
		// @24: astore_2
		// @25: aload_2
		// @26: new java.lang.StringBuilder
		// @29: dup
		// @2A: invokespecial java.lang.StringBuilder.<init>()void
		// @2D: getstatic java.lang.String[] game.C_100047_vh.field_104155_z
		// @30: bipush 7 (0x07)
		// @32: aaload
		// @33: invokevirtual java.lang.StringBuilder.append(java.lang.String)java.lang.StringBuilder
		// @36: aload_1
		// @37: ifnull @43
		// @3A: getstatic java.lang.String[] game.C_100047_vh.field_104155_z
		// @3D: iconst_1
		// @3E: aaload
		// @3F: goto @48
		// @42: athrow
		// @43: getstatic java.lang.String[] game.C_100047_vh.field_104155_z
		// @46: iconst_3
		// @47: aaload
		// @48: invokevirtual java.lang.StringBuilder.append(java.lang.String)java.lang.StringBuilder
		// @4B: bipush 41 (0x29)
		// @4D: invokevirtual java.lang.StringBuilder.append(char)java.lang.StringBuilder
		// @50: invokevirtual java.lang.StringBuilder.toString()java.lang.String
		// @53: invokestatic game.C_100181_cf.func_105695_a(java.lang.Throwable, java.lang.String)game.C_100170_cm
		// @56: athrow
		// @57: return
	}
	
	public final synchronized void mousePressed(MouseEvent arg0)
	{
		// @00: getstatic game.C_100047_vh game.C_100111_el.field_104859_g
		// @03: ifnonnull @0A
		// @06: goto @8F
		// @09: athrow
		// @0A: iconst_0
		// @0B: putstatic int game.C_100012_fh.field_100514_J
		// @0E: aload_1
		// @0F: invokevirtual java.awt.event.MouseEvent.getX()int
		// @12: putstatic int game.C_100012_fh.field_100520_R
		// @15: aload_1
		// @16: invokevirtual java.awt.event.MouseEvent.getY()int
		// @19: putstatic int game.C_100001_ge.field_100563_e
		// @1C: bipush 51 (0x33)
		// @1E: invokestatic game.C_100198_qn.func_105828_a(byte)long
		// @21: pop2
		// @22: aload_1
		// @23: invokevirtual java.awt.event.MouseEvent.isMetaDown()boolean
		// @26: ifne @3B
		// @29: iconst_1
		// @2A: putstatic int game.C_100130_tf.field_104958_f
		// @2D: iconst_1
		// @2E: putstatic int game.C_100083_c.field_103172_O
		// @31: getstatic int game.SteelSentinels.field_105275_O
		// @34: ifeq @47
		// @37: goto @3B
		// @3A: athrow
		// @3B: iconst_2
		// @3C: putstatic int game.C_100130_tf.field_104958_f
		// @3F: iconst_2
		// @40: putstatic int game.C_100083_c.field_103172_O
		// @43: goto @47
		// @46: athrow
		// @47: aload_1
		// @48: invokevirtual java.awt.event.MouseEvent.getModifiers()int
		// @4B: istore_2
		// @4C: iconst_0
		// @4D: iload_2
		// @4E: bipush 16 (0x10)
		// @50: iand
		// @51: if_icmpne @58
		// @54: goto @60
		// @57: athrow
		// @58: getstatic int game.C_100062_dk.field_104279_f
		// @5B: iconst_1
		// @5C: ior
		// @5D: putstatic int game.C_100062_dk.field_104279_f
		// @60: iconst_m1
		// @61: iload_2
		// @62: bipush 8 (0x08)
		// @64: iand
		// @65: iconst_m1
		// @66: ixor
		// @67: if_icmpne @6E
		// @6A: goto @76
		// @6D: athrow
		// @6E: getstatic int game.C_100062_dk.field_104279_f
		// @71: iconst_2
		// @72: ior
		// @73: putstatic int game.C_100062_dk.field_104279_f
		// @76: iconst_m1
		// @77: iload_2
		// @78: iconst_4
		// @79: iand
		// @7A: iconst_m1
		// @7B: ixor
		// @7C: if_icmpeq @8B
		// @7F: getstatic int game.C_100062_dk.field_104279_f
		// @82: iconst_4
		// @83: ior
		// @84: putstatic int game.C_100062_dk.field_104279_f
		// @87: goto @8B
		// @8A: athrow
		// @8B: iconst_1
		// @8C: putstatic boolean game.C_100246_pg.field_106404_b
		// @8F: aload_1
		// @90: invokevirtual java.awt.event.MouseEvent.isPopupTrigger()boolean
		// @93: ifne @9A
		// @96: goto @9E
		// @99: athrow
		// @9A: aload_1
		// @9B: invokevirtual java.awt.event.MouseEvent.consume()void
		// @9E: goto @D4
		// @A1: astore_2
		// @A2: aload_2
		// @A3: new java.lang.StringBuilder
		// @A6: dup
		// @A7: invokespecial java.lang.StringBuilder.<init>()void
		// @AA: getstatic java.lang.String[] game.C_100047_vh.field_104155_z
		// @AD: bipush 8 (0x08)
		// @AF: aaload
		// @B0: invokevirtual java.lang.StringBuilder.append(java.lang.String)java.lang.StringBuilder
		// @B3: aload_1
		// @B4: ifnull @C0
		// @B7: getstatic java.lang.String[] game.C_100047_vh.field_104155_z
		// @BA: iconst_1
		// @BB: aaload
		// @BC: goto @C5
		// @BF: athrow
		// @C0: getstatic java.lang.String[] game.C_100047_vh.field_104155_z
		// @C3: iconst_3
		// @C4: aaload
		// @C5: invokevirtual java.lang.StringBuilder.append(java.lang.String)java.lang.StringBuilder
		// @C8: bipush 41 (0x29)
		// @CA: invokevirtual java.lang.StringBuilder.append(char)java.lang.StringBuilder
		// @CD: invokevirtual java.lang.StringBuilder.toString()java.lang.String
		// @D0: invokestatic game.C_100181_cf.func_105695_a(java.lang.Throwable, java.lang.String)game.C_100170_cm
		// @D3: athrow
		// @D4: return
	}
	
	public final synchronized void mouseMoved(MouseEvent arg0)
	{
		// @00: getstatic game.C_100047_vh game.C_100111_el.field_104859_g
		// @03: ifnonnull @0A
		// @06: goto @20
		// @09: athrow
		// @0A: iconst_0
		// @0B: putstatic int game.C_100012_fh.field_100514_J
		// @0E: aload_1
		// @0F: invokevirtual java.awt.event.MouseEvent.getX()int
		// @12: putstatic int game.C_100231_oc.field_102198_ec
		// @15: aload_1
		// @16: invokevirtual java.awt.event.MouseEvent.getY()int
		// @19: putstatic int game.C_100113_ek.field_104884_h
		// @1C: iconst_1
		// @1D: putstatic boolean game.C_100246_pg.field_106404_b
		// @20: goto @56
		// @23: astore_2
		// @24: aload_2
		// @25: new java.lang.StringBuilder
		// @28: dup
		// @29: invokespecial java.lang.StringBuilder.<init>()void
		// @2C: getstatic java.lang.String[] game.C_100047_vh.field_104155_z
		// @2F: bipush 11 (0x0B)
		// @31: aaload
		// @32: invokevirtual java.lang.StringBuilder.append(java.lang.String)java.lang.StringBuilder
		// @35: aload_1
		// @36: ifnull @42
		// @39: getstatic java.lang.String[] game.C_100047_vh.field_104155_z
		// @3C: iconst_1
		// @3D: aaload
		// @3E: goto @47
		// @41: athrow
		// @42: getstatic java.lang.String[] game.C_100047_vh.field_104155_z
		// @45: iconst_3
		// @46: aaload
		// @47: invokevirtual java.lang.StringBuilder.append(java.lang.String)java.lang.StringBuilder
		// @4A: bipush 41 (0x29)
		// @4C: invokevirtual java.lang.StringBuilder.append(char)java.lang.StringBuilder
		// @4F: invokevirtual java.lang.StringBuilder.toString()java.lang.String
		// @52: invokestatic game.C_100181_cf.func_105695_a(java.lang.Throwable, java.lang.String)game.C_100170_cm
		// @55: athrow
		// @56: return
	}
	
	public final synchronized void mouseReleased(MouseEvent arg0)
	{
		// @00: getstatic game.C_100047_vh game.C_100111_el.field_104859_g
		// @03: ifnull @58
		// @06: iconst_0
		// @07: putstatic int game.C_100012_fh.field_100514_J
		// @0A: iconst_0
		// @0B: putstatic int game.C_100083_c.field_103172_O
		// @0E: iconst_1
		// @0F: putstatic boolean game.C_100246_pg.field_106404_b
		// @12: aload_1
		// @13: invokevirtual java.awt.event.MouseEvent.getModifiers()int
		// @16: istore_2
		// @17: iconst_m1
		// @18: iload_2
		// @19: bipush 16 (0x10)
		// @1B: iand
		// @1C: iconst_m1
		// @1D: ixor
		// @1E: if_icmpne @25
		// @21: goto @2E
		// @24: athrow
		// @25: getstatic int game.C_100062_dk.field_104279_f
		// @28: bipush -2 (0xFE)
		// @2A: iand
		// @2B: putstatic int game.C_100062_dk.field_104279_f
		// @2E: bipush 8 (0x08)
		// @30: iload_2
		// @31: iand
		// @32: ifeq @42
		// @35: getstatic int game.C_100062_dk.field_104279_f
		// @38: bipush -3 (0xFD)
		// @3A: iand
		// @3B: putstatic int game.C_100062_dk.field_104279_f
		// @3E: goto @42
		// @41: athrow
		// @42: iconst_m1
		// @43: iload_2
		// @44: iconst_4
		// @45: iand
		// @46: iconst_m1
		// @47: ixor
		// @48: if_icmpeq @58
		// @4B: getstatic int game.C_100062_dk.field_104279_f
		// @4E: bipush -5 (0xFB)
		// @50: iand
		// @51: putstatic int game.C_100062_dk.field_104279_f
		// @54: goto @58
		// @57: athrow
		// @58: aload_1
		// @59: invokevirtual java.awt.event.MouseEvent.isPopupTrigger()boolean
		// @5C: ifeq @67
		// @5F: aload_1
		// @60: invokevirtual java.awt.event.MouseEvent.consume()void
		// @63: goto @67
		// @66: athrow
		// @67: goto @9C
		// @6A: astore_2
		// @6B: aload_2
		// @6C: new java.lang.StringBuilder
		// @6F: dup
		// @70: invokespecial java.lang.StringBuilder.<init>()void
		// @73: getstatic java.lang.String[] game.C_100047_vh.field_104155_z
		// @76: iconst_2
		// @77: aaload
		// @78: invokevirtual java.lang.StringBuilder.append(java.lang.String)java.lang.StringBuilder
		// @7B: aload_1
		// @7C: ifnull @88
		// @7F: getstatic java.lang.String[] game.C_100047_vh.field_104155_z
		// @82: iconst_1
		// @83: aaload
		// @84: goto @8D
		// @87: athrow
		// @88: getstatic java.lang.String[] game.C_100047_vh.field_104155_z
		// @8B: iconst_3
		// @8C: aaload
		// @8D: invokevirtual java.lang.StringBuilder.append(java.lang.String)java.lang.StringBuilder
		// @90: bipush 41 (0x29)
		// @92: invokevirtual java.lang.StringBuilder.append(char)java.lang.StringBuilder
		// @95: invokevirtual java.lang.StringBuilder.toString()java.lang.String
		// @98: invokestatic game.C_100181_cf.func_105695_a(java.lang.Throwable, java.lang.String)game.C_100170_cm
		// @9B: athrow
		// @9C: return
	}
	
	static final void func_104143_a(int arg0)
	{
		// @00: iload_0
		// @01: iconst_4
		// @02: if_icmpeq @06
		// @05: return
		// @06: iconst_0
		// @07: invokestatic game.C_100129_tg.func_102734_a(boolean)void
		// @0A: iconst_m1
		// @0B: invokestatic game.C_100106_ef.func_104746_a(int)void
		// @0E: goto @32
		// @11: astore_1
		// @12: aload_1
		// @13: new java.lang.StringBuilder
		// @16: dup
		// @17: invokespecial java.lang.StringBuilder.<init>()void
		// @1A: getstatic java.lang.String[] game.C_100047_vh.field_104155_z
		// @1D: iconst_0
		// @1E: aaload
		// @1F: invokevirtual java.lang.StringBuilder.append(java.lang.String)java.lang.StringBuilder
		// @22: iload_0
		// @23: invokevirtual java.lang.StringBuilder.append(int)java.lang.StringBuilder
		// @26: bipush 41 (0x29)
		// @28: invokevirtual java.lang.StringBuilder.append(char)java.lang.StringBuilder
		// @2B: invokevirtual java.lang.StringBuilder.toString()java.lang.String
		// @2E: invokestatic game.C_100181_cf.func_105695_a(java.lang.Throwable, java.lang.String)game.C_100170_cm
		// @31: athrow
		// @32: return
	}
	
	public final synchronized void focusLost(FocusEvent arg0)
	{
		// @00: aconst_null
		// @01: getstatic game.C_100047_vh game.C_100111_el.field_104859_g
		// @04: if_acmpne @0B
		// @07: goto @0F
		// @0A: athrow
		// @0B: iconst_0
		// @0C: putstatic int game.C_100083_c.field_103172_O
		// @0F: goto @45
		// @12: astore_2
		// @13: aload_2
		// @14: new java.lang.StringBuilder
		// @17: dup
		// @18: invokespecial java.lang.StringBuilder.<init>()void
		// @1B: getstatic java.lang.String[] game.C_100047_vh.field_104155_z
		// @1E: bipush 9 (0x09)
		// @20: aaload
		// @21: invokevirtual java.lang.StringBuilder.append(java.lang.String)java.lang.StringBuilder
		// @24: aload_1
		// @25: ifnull @31
		// @28: getstatic java.lang.String[] game.C_100047_vh.field_104155_z
		// @2B: iconst_1
		// @2C: aaload
		// @2D: goto @36
		// @30: athrow
		// @31: getstatic java.lang.String[] game.C_100047_vh.field_104155_z
		// @34: iconst_3
		// @35: aaload
		// @36: invokevirtual java.lang.StringBuilder.append(java.lang.String)java.lang.StringBuilder
		// @39: bipush 41 (0x29)
		// @3B: invokevirtual java.lang.StringBuilder.append(char)java.lang.StringBuilder
		// @3E: invokevirtual java.lang.StringBuilder.toString()java.lang.String
		// @41: invokestatic game.C_100181_cf.func_105695_a(java.lang.Throwable, java.lang.String)game.C_100170_cm
		// @44: athrow
		// @45: return
	}
	
	public final synchronized void mouseDragged(MouseEvent arg0)
	{
		// @00: aconst_null
		// @01: getstatic game.C_100047_vh game.C_100111_el.field_104859_g
		// @04: if_acmpne @0B
		// @07: goto @21
		// @0A: athrow
		// @0B: iconst_0
		// @0C: putstatic int game.C_100012_fh.field_100514_J
		// @0F: aload_1
		// @10: invokevirtual java.awt.event.MouseEvent.getX()int
		// @13: putstatic int game.C_100231_oc.field_102198_ec
		// @16: aload_1
		// @17: invokevirtual java.awt.event.MouseEvent.getY()int
		// @1A: putstatic int game.C_100113_ek.field_104884_h
		// @1D: iconst_1
		// @1E: putstatic boolean game.C_100246_pg.field_106404_b
		// @21: goto @56
		// @24: astore_2
		// @25: aload_2
		// @26: new java.lang.StringBuilder
		// @29: dup
		// @2A: invokespecial java.lang.StringBuilder.<init>()void
		// @2D: getstatic java.lang.String[] game.C_100047_vh.field_104155_z
		// @30: iconst_5
		// @31: aaload
		// @32: invokevirtual java.lang.StringBuilder.append(java.lang.String)java.lang.StringBuilder
		// @35: aload_1
		// @36: ifnull @42
		// @39: getstatic java.lang.String[] game.C_100047_vh.field_104155_z
		// @3C: iconst_1
		// @3D: aaload
		// @3E: goto @47
		// @41: athrow
		// @42: getstatic java.lang.String[] game.C_100047_vh.field_104155_z
		// @45: iconst_3
		// @46: aaload
		// @47: invokevirtual java.lang.StringBuilder.append(java.lang.String)java.lang.StringBuilder
		// @4A: bipush 41 (0x29)
		// @4C: invokevirtual java.lang.StringBuilder.append(char)java.lang.StringBuilder
		// @4F: invokevirtual java.lang.StringBuilder.toString()java.lang.String
		// @52: invokestatic game.C_100181_cf.func_105695_a(java.lang.Throwable, java.lang.String)game.C_100170_cm
		// @55: athrow
		// @56: return
	}
	
	static
	{
		// @00: bipush 14 (0x0E)
		// @02: anewarray java.lang.String
		// @05: dup
		// @06: iconst_0
		// @07: ldc "s+M6W"
		// @09: invokestatic game.C_100047_vh.func_104146_z(java.lang.String)char[]
		// @0C: invokestatic game.C_100047_vh.func_104144_z(char[])java.lang.String
		// @0F: aastore
		// @10: dup
		// @11: iconst_1
		// @12: ldc "~mMZ\u0002"
		// @14: invokestatic game.C_100047_vh.func_104146_z(java.lang.String)char[]
		// @17: invokestatic game.C_100047_vh.func_104144_z(char[])java.lang.String
		// @1A: aastore
		// @1B: dup
		// @1C: iconst_2
		// @1D: ldc "s+M\u0019\u0010p0\u0006&\u001ai&\u0002\u0007\u001aak"
		// @1F: invokestatic game.C_100047_vh.func_104146_z(java.lang.String)char[]
		// @22: invokestatic game.C_100047_vh.func_104144_z(char[])java.lang.String
		// @25: aastore
		// @26: dup
		// @27: iconst_3
		// @28: ldc "k6\u000f\u0018"
		// @2A: invokestatic game.C_100047_vh.func_104146_z(java.lang.String)char[]
		// @2D: invokestatic game.C_100047_vh.func_104144_z(char[])java.lang.String
		// @30: aastore
		// @31: dup
		// @32: iconst_4
		// @33: ldc "s+M7W"
		// @35: invokestatic game.C_100047_vh.func_104146_z(java.lang.String)char[]
		// @38: invokestatic game.C_100047_vh.func_104144_z(char[])java.lang.String
		// @3B: aastore
		// @3C: dup
		// @3D: iconst_5
		// @3E: ldc "s+M\u0019\u0010p0\u00060\rd$\u0004\u0011\u001b-"
		// @40: invokestatic game.C_100047_vh.func_104146_z(java.lang.String)char[]
		// @43: invokestatic game.C_100047_vh.func_104144_z(char[])java.lang.String
		// @46: aastore
		// @47: dup
		// @48: bipush 6 (0x06)
		// @4A: ldc "s+M0W"
		// @4C: invokestatic game.C_100047_vh.func_104146_z(java.lang.String)char[]
		// @4F: invokestatic game.C_100047_vh.func_104144_z(char[])java.lang.String
		// @52: aastore
		// @53: dup
		// @54: bipush 7 (0x07)
		// @56: ldc "s+M\u0019\u0010p0\u00061\u0011q&\u0011\u0011\u001b-"
		// @58: invokestatic game.C_100047_vh.func_104146_z(java.lang.String)char[]
		// @5B: invokestatic game.C_100047_vh.func_104144_z(char[])java.lang.String
		// @5E: aastore
		// @5F: dup
		// @60: bipush 8 (0x08)
		// @62: ldc "s+M\u0019\u0010p0\u0006$\r`0\u0010\u0011\u001b-"
		// @64: invokestatic game.C_100047_vh.func_104146_z(java.lang.String)char[]
		// @67: invokestatic game.C_100047_vh.func_104144_z(char[])java.lang.String
		// @6A: aastore
		// @6B: dup
		// @6C: bipush 9 (0x09)
		// @6E: ldc "s+M\u0012\u0010f6\u00108\u0010v7K"
		// @70: invokestatic game.C_100047_vh.func_104146_z(java.lang.String)char[]
		// @73: invokestatic game.C_100047_vh.func_104144_z(char[])java.lang.String
		// @76: aastore
		// @77: dup
		// @78: bipush 10 (0x0A)
		// @7A: ldc "s+M\u0019\u0010p0\u00061\u0007l7\u0006\u0010W"
		// @7C: invokestatic game.C_100047_vh.func_104146_z(java.lang.String)char[]
		// @7F: invokestatic game.C_100047_vh.func_104144_z(char[])java.lang.String
		// @82: aastore
		// @83: dup
		// @84: bipush 11 (0x0B)
		// @86: ldc "s+M\u0019\u0010p0\u00069\u0010s&\u0007\\"
		// @88: invokestatic game.C_100047_vh.func_104146_z(java.lang.String)char[]
		// @8B: invokestatic game.C_100047_vh.func_104144_z(char[])java.lang.String
		// @8E: aastore
		// @8F: dup
		// @90: bipush 12 (0x0C)
		// @92: ldc "s+M5W"
		// @94: invokestatic game.C_100047_vh.func_104146_z(java.lang.String)char[]
		// @97: invokestatic game.C_100047_vh.func_104144_z(char[])java.lang.String
		// @9A: aastore
		// @9B: dup
		// @9C: bipush 13 (0x0D)
		// @9E: ldc "s+M\u0019\u0010p0\u00067\u0013l \u0008\u0011\u001b-"
		// @A0: invokestatic game.C_100047_vh.func_104146_z(java.lang.String)char[]
		// @A3: invokestatic game.C_100047_vh.func_104144_z(char[])java.lang.String
		// @A6: aastore
		// @A7: putstatic java.lang.String[] game.C_100047_vh.field_104155_z
		// @AA: ldc "F1\u0006\u0015\u000bl-\u0004T\u001e%\t\u0002\u0013\u001a}c\u0002\u0017\u001cj6\r\u0000_l0C\u0007\u0016h3\u000f\u0011_d-\u0007T\u0019w&\u0006Z_\\,\u0016\u0006_d \u0000\u001b\nk7C\u0003\u0016i/C\u0006\u001ah&\u000e\u0016\u001awc\u001a\u001b\nwc\u0013\u0006\u0010b1\u0006\u0007\u000c)c\u000b\u001d\u0018m0\u0000\u001b\r`0C\u0015\u0011ac\u0002\u0017\u0017l&\u0015\u0011\u0012`-\u0017\u0007_l-C\u0011\t`1\u001aT\u0018d.\u0006Z_\\,\u0016T\u001cd-C\u0015\u0013v,C\u0001\u000c`c\n\u0000_q,C\u0004\u0013d:C\u0007\u0010h&C\u001b\u0019%,\u0016\u0006_h6\u000f\u0000\u0016u/\u0002\r\u001awc\u0004\u0015\u0012`0CY_d-\u0007T5d$\u0006\u000cXvc\u000c\u0000\u0017`1C\u0013\u001eh&\u0010UCg1]H\u001dw}_\u0017\u0010i~QEI1\u0002QJ/i&\u0002\u0007\u001a%-\u000c\u0000\u001a%nC\u001d\u0019%:\u000c\u0001_m\"\u0015\u0011_dc1\u0001\u0011`\u0010\u0000\u0015\u000f`c\u0002\u0017\u001cj6\r\u0000S%:\u000c\u0001_f\"\rT\u001ci*\u0000\u001f_\"\u0004\u000cT=d \u0008S_d-\u0007T\nv&C\r\u0010p1C\u0011\u0007l0\u0017\u001d\u0011bc\u0002\u0017\u001cj6\r\u0000_q,C\u0018\u0010bc\n\u001a^9l\u0000\u001b\u0013;"
		// @AC: invokestatic game.C_100047_vh.func_104146_z(java.lang.String)char[]
		// @AF: invokestatic game.C_100047_vh.func_104144_z(char[])java.lang.String
		// @B2: putstatic java.lang.String game.C_100047_vh.field_104154_a
		// @B5: ldc "V&\r\u0000\u0016k&\u000fT\u001cj-\u0005\u001d\u0018p1\u0002\u0000\u0016j-C\u001d\u000c%-\u000c\u0003_p-\u000f\u001b\u001cn&\u0007ZCg1]8\u0010bc\n\u001a_j1C\u0017\r`\"\u0017\u0011_dc\u0005\u0006\u001a`c\u0002\u0017\u001cj6\r\u0000_q,C\u0007\u001es&C\r\u0010p1C\u0004\rj$\u0011\u0011\u000cvm"
		// @B7: invokestatic game.C_100047_vh.func_104146_z(java.lang.String)char[]
		// @BA: invokestatic game.C_100047_vh.func_104144_z(char[])java.lang.String
		// @BD: putstatic java.lang.String game.C_100047_vh.field_104152_b
		// @C0: ldc "R\"\n\u0000\u0016k$C\u0012\u0010wc\u000e\u0001\u000cl "
		// @C2: invokestatic game.C_100047_vh.func_104146_z(java.lang.String)char[]
		// @C5: invokestatic game.C_100047_vh.func_104144_z(char[])java.lang.String
		// @C8: putstatic java.lang.String game.C_100047_vh.field_104151_e
		// @CB: ldc "9fRJ_r\"\u0010T\rj\"\u0007\u001f\u0016i/"
		// @CD: invokestatic game.C_100047_vh.func_104146_z(java.lang.String)char[]
		// @D0: invokestatic game.C_100047_vh.func_104144_z(char[])java.lang.String
		// @D3: putstatic java.lang.String game.C_100047_vh.field_104149_f
		// @D6: return
	}
	
	private static char[] func_104146_z(String arg0)
	{
		// @00: aload_0
		// @01: invokevirtual java.lang.String.toCharArray()char[]
		// @04: dup
		// @05: arraylength
		// @06: iconst_2
		// @07: if_icmpge @13
		// @0A: dup
		// @0B: iconst_0
		// @0C: dup2
		// @0D: caload
		// @0E: bipush 127 (0x7F)
		// @10: ixor
		// @11: i2c
		// @12: castore
		// @13: areturn
	}
	
	private static String func_104144_z(char[] arg0)
	{
		// @00: aload_0
		// @01: dup
		// @02: arraylength
		// @03: swap
		// @04: iconst_0
		// @05: istore_1
		// @06: goto @4B
		// @09: dup
		// @0A: iload_1
		// @0B: dup2
		// @0C: caload
		// @0D: iload_1
		// @0E: iconst_5
		// @0F: irem
		// @10: tableswitch def: @43, for 0: @30, for 1: @34, for 2: @39, for 3: @3E
		// @30: iconst_5
		// @31: goto @45
		// @34: bipush 67 (0x43)
		// @36: goto @45
		// @39: bipush 99 (0x63)
		// @3B: goto @45
		// @3E: bipush 116 (0x74)
		// @40: goto @45
		// @43: bipush 127 (0x7F)
		// @45: ixor
		// @46: i2c
		// @47: castore
		// @48: iinc #1 +1
		// @4B: swap
		// @4C: dup_x1
		// @4D: iload_1
		// @4E: if_icmpgt @09
		// @51: new java.lang.String
		// @54: dup_x1
		// @55: swap
		// @56: invokespecial java.lang.String.<init>(char[])void
		// @59: invokevirtual java.lang.String.intern()java.lang.String
		// @5C: areturn
	}
}
