package game;

final class C_100128_ca extends C_100085_a implements C_100276_nb, C_100334_ik
{
	C_100162_sc field_102803_T;
	private C_100078_ul field_102805_V;
	private C_100218_am field_102802_U;
	static String field_102809_R;
	static String field_102807_P;
	static int field_102808_S;
	private C_100218_am field_102806_Q;
	private static final String[] field_102804_W;
	
	static final void func_102801_a(int arg0, int arg1)
	{
		// @00: getstatic int game.SteelSentinels.field_105275_O
		// @03: istore_3
		// @04: getstatic game.C_100202_qi game.C_100205_qf.field_103676_f
		// @07: iload_0
		// @08: sipush 436 (0x01B4)
		// @0B: ixor
		// @0C: invokevirtual game.C_100202_qi.func_105899_c(int)game.C_100158_da
		// @0F: checkcast game.C_100346_ja
		// @12: astore_2
		// @13: aload_2
		// @14: ifnull @36
		// @17: aload_2
		// @18: bipush -9 (0xF7)
		// @1A: iload_1
		// @1B: invokestatic game.C_100213_ak.func_105985_a(game.C_100346_ja, byte, int)void
		// @1E: getstatic game.C_100202_qi game.C_100205_qf.field_103676_f
		// @21: bipush 85 (0x55)
		// @23: invokevirtual game.C_100202_qi.func_105907_c(byte)game.C_100158_da
		// @26: checkcast game.C_100346_ja
		// @29: astore_2
		// @2A: iload_3
		// @2B: ifne @46
		// @2E: iload_3
		// @2F: ifeq @13
		// @32: goto @36
		// @35: athrow
		// @36: iload_0
		// @37: sipush 496 (0x01F0)
		// @3A: if_icmpeq @46
		// @3D: bipush -38 (0xDA)
		// @3F: putstatic int game.C_100128_ca.field_102808_S
		// @42: goto @46
		// @45: athrow
		// @46: goto @74
		// @49: astore_2
		// @4A: aload_2
		// @4B: new java.lang.StringBuilder
		// @4E: dup
		// @4F: invokespecial java.lang.StringBuilder.<init>()void
		// @52: getstatic java.lang.String[] game.C_100128_ca.field_102804_W
		// @55: bipush 9 (0x09)
		// @57: aaload
		// @58: invokevirtual java.lang.StringBuilder.append(java.lang.String)java.lang.StringBuilder
		// @5B: iload_0
		// @5C: invokevirtual java.lang.StringBuilder.append(int)java.lang.StringBuilder
		// @5F: bipush 44 (0x2C)
		// @61: invokevirtual java.lang.StringBuilder.append(char)java.lang.StringBuilder
		// @64: iload_1
		// @65: invokevirtual java.lang.StringBuilder.append(int)java.lang.StringBuilder
		// @68: bipush 41 (0x29)
		// @6A: invokevirtual java.lang.StringBuilder.append(char)java.lang.StringBuilder
		// @6D: invokevirtual java.lang.StringBuilder.toString()java.lang.String
		// @70: invokestatic game.C_100181_cf.func_105695_a(java.lang.Throwable, java.lang.String)game.C_100170_cm
		// @73: athrow
		// @74: return
	}
	
	private final void func_102796_m(int arg0)
	{
		// @00: iload_1
		// @01: sipush -3463 (0xF279)
		// @04: if_icmpeq @12
		// @07: bipush 15 (0x0F)
		// @09: bipush 75 (0x4B)
		// @0B: invokestatic game.C_100128_ca.func_102801_a(int, int)void
		// @0E: goto @12
		// @11: athrow
		// @12: aload_0
		// @13: bipush 119 (0x77)
		// @15: invokespecial game.C_100128_ca.func_102792_g(byte)boolean
		// @18: ifeq @1F
		// @1B: goto @20
		// @1E: athrow
		// @1F: return
		// @20: bipush 24 (0x18)
		// @22: aload_0
		// @23: getfield game.C_100078_ul game.C_100128_ca.field_102805_V
		// @26: getfield java.lang.String game.C_100078_ul.field_102534_C
		// @29: invokestatic game.C_100211_qd.func_102131_a(int, java.lang.String)void
		// @2C: goto @50
		// @2F: astore_2
		// @30: aload_2
		// @31: new java.lang.StringBuilder
		// @34: dup
		// @35: invokespecial java.lang.StringBuilder.<init>()void
		// @38: getstatic java.lang.String[] game.C_100128_ca.field_102804_W
		// @3B: iconst_4
		// @3C: aaload
		// @3D: invokevirtual java.lang.StringBuilder.append(java.lang.String)java.lang.StringBuilder
		// @40: iload_1
		// @41: invokevirtual java.lang.StringBuilder.append(int)java.lang.StringBuilder
		// @44: bipush 41 (0x29)
		// @46: invokevirtual java.lang.StringBuilder.append(char)java.lang.StringBuilder
		// @49: invokevirtual java.lang.StringBuilder.toString()java.lang.String
		// @4C: invokestatic game.C_100181_cf.func_105695_a(java.lang.Throwable, java.lang.String)game.C_100170_cm
		// @4F: athrow
		// @50: return
	}
	
	public final void func_102581_a(int arg0, int arg1, byte arg2, C_100218_am arg3, int arg4)
	{
		// @00: bipush -72 (0xB8)
		// @02: bipush -2 (0xFE)
		// @04: iload_3
		// @05: isub
		// @06: bipush 52 (0x34)
		// @08: idiv
		// @09: idiv
		// @0A: istore #6
		// @0C: aload_0
		// @0D: getfield game.C_100218_am game.C_100128_ca.field_102802_U
		// @10: aload #4
		// @12: if_acmpeq @33
		// @15: aload_0
		// @16: getfield game.C_100218_am game.C_100128_ca.field_102806_Q
		// @19: aload #4
		// @1B: if_acmpeq @26
		// @1E: goto @22
		// @21: athrow
		// @22: goto @3D
		// @25: athrow
		// @26: aload_0
		// @27: sipush -3463 (0xF279)
		// @2A: invokespecial game.C_100128_ca.func_102796_m(int)void
		// @2D: getstatic int game.SteelSentinels.field_105275_O
		// @30: ifeq @3D
		// @33: sipush -3476 (0xF26C)
		// @36: invokestatic game.C_100207_qh.func_102871_k(int)void
		// @39: goto @3D
		// @3C: athrow
		// @3D: goto @9B
		// @40: astore #6
		// @42: aload #6
		// @44: new java.lang.StringBuilder
		// @47: dup
		// @48: invokespecial java.lang.StringBuilder.<init>()void
		// @4B: getstatic java.lang.String[] game.C_100128_ca.field_102804_W
		// @4E: bipush 12 (0x0C)
		// @50: aaload
		// @51: invokevirtual java.lang.StringBuilder.append(java.lang.String)java.lang.StringBuilder
		// @54: iload_1
		// @55: invokevirtual java.lang.StringBuilder.append(int)java.lang.StringBuilder
		// @58: bipush 44 (0x2C)
		// @5A: invokevirtual java.lang.StringBuilder.append(char)java.lang.StringBuilder
		// @5D: iload_2
		// @5E: invokevirtual java.lang.StringBuilder.append(int)java.lang.StringBuilder
		// @61: bipush 44 (0x2C)
		// @63: invokevirtual java.lang.StringBuilder.append(char)java.lang.StringBuilder
		// @66: iload_3
		// @67: invokevirtual java.lang.StringBuilder.append(int)java.lang.StringBuilder
		// @6A: bipush 44 (0x2C)
		// @6C: invokevirtual java.lang.StringBuilder.append(char)java.lang.StringBuilder
		// @6F: aload #4
		// @71: ifnull @7D
		// @74: getstatic java.lang.String[] game.C_100128_ca.field_102804_W
		// @77: iconst_1
		// @78: aaload
		// @79: goto @82
		// @7C: athrow
		// @7D: getstatic java.lang.String[] game.C_100128_ca.field_102804_W
		// @80: iconst_2
		// @81: aaload
		// @82: invokevirtual java.lang.StringBuilder.append(java.lang.String)java.lang.StringBuilder
		// @85: bipush 44 (0x2C)
		// @87: invokevirtual java.lang.StringBuilder.append(char)java.lang.StringBuilder
		// @8A: iload #5
		// @8C: invokevirtual java.lang.StringBuilder.append(int)java.lang.StringBuilder
		// @8F: bipush 41 (0x29)
		// @91: invokevirtual java.lang.StringBuilder.append(char)java.lang.StringBuilder
		// @94: invokevirtual java.lang.StringBuilder.toString()java.lang.String
		// @97: invokestatic game.C_100181_cf.func_105695_a(java.lang.Throwable, java.lang.String)game.C_100170_cm
		// @9A: athrow
		// @9B: return
	}
	
	public C_100128_ca()
	{
		// @000: aload_0
		// @001: iconst_0
		// @002: iconst_0
		// @003: sipush 496 (0x01F0)
		// @006: iconst_0
		// @007: aconst_null
		// @008: invokespecial game.C_100085_a.<init>(int, int, int, int, game.C_100326_ic)void
		// @00B: aload_0
		// @00C: new game.C_100078_ul
		// @00F: dup
		// @010: ldc ""
		// @012: aconst_null
		// @013: bipush 12 (0x0C)
		// @015: invokespecial game.C_100078_ul.<init>(java.lang.String, game.C_100337_in, int)void
		// @018: putfield game.C_100078_ul game.C_100128_ca.field_102805_V
		// @01B: new game.C_100256_pk
		// @01E: dup
		// @01F: getstatic game.C_100112_r game.C_100318_hj.field_107198_b
		// @022: iconst_0
		// @023: iconst_0
		// @024: iconst_0
		// @025: iconst_0
		// @026: ldc 16777215 (0xffffff)
		// @028: iconst_m1
		// @029: iconst_3
		// @02A: iconst_0
		// @02B: getstatic game.C_100112_r game.C_100230_of.field_106205_g
		// @02E: getfield int game.C_100112_r.field_101772_Q
		// @031: iconst_m1
		// @032: ldc 2147483647 (0x7fffffff)
		// @034: iconst_1
		// @035: invokespecial game.C_100256_pk.<init>(game.C_100112_r, int, int, int, int, int, int, int, int, int, int, int, boolean)void
		// @038: astore_1
		// @039: new game.C_100336_im
		// @03C: dup
		// @03D: getstatic java.lang.String game.C_100099_fb.field_103038_D
		// @040: aload_1
		// @041: aconst_null
		// @042: invokespecial game.C_100336_im.<init>(java.lang.String, game.C_100326_ic, game.C_100337_in)void
		// @045: astore_2
		// @046: aload_0
		// @047: new game.C_100218_am
		// @04A: dup
		// @04B: getstatic java.lang.String game.C_100187_rk.field_100836_p
		// @04E: aconst_null
		// @04F: invokespecial game.C_100218_am.<init>(java.lang.String, game.C_100337_in)void
		// @052: putfield game.C_100218_am game.C_100128_ca.field_102806_Q
		// @055: aload_0
		// @056: new game.C_100218_am
		// @059: dup
		// @05A: getstatic java.lang.String game.C_100246_pg.field_106400_f
		// @05D: aconst_null
		// @05E: invokespecial game.C_100218_am.<init>(java.lang.String, game.C_100337_in)void
		// @061: putfield game.C_100218_am game.C_100128_ca.field_102802_U
		// @064: aload_0
		// @065: getfield game.C_100078_ul game.C_100128_ca.field_102805_V
		// @068: getstatic java.lang.String game.C_100106_ef.field_104758_h
		// @06B: putfield java.lang.String game.C_100078_ul.field_102536_o
		// @06E: aload_0
		// @06F: getfield game.C_100078_ul game.C_100128_ca.field_102805_V
		// @072: bipush -66 (0xBE)
		// @074: new game.C_100064_ve
		// @077: dup
		// @078: aload_0
		// @079: getfield game.C_100078_ul game.C_100128_ca.field_102805_V
		// @07C: invokespecial game.C_100064_ve.<init>(game.C_100309_lk)void
		// @07F: invokevirtual game.C_100078_ul.func_103279_a(byte, game.C_100308_lh)void
		// @082: aload_0
		// @083: getfield game.C_100218_am game.C_100128_ca.field_102806_Q
		// @086: iconst_0
		// @087: putfield boolean game.C_100218_am.field_103113_L
		// @08A: aload_0
		// @08B: getfield game.C_100218_am game.C_100128_ca.field_102806_Q
		// @08E: new game.C_100310_lj
		// @091: dup
		// @092: invokespecial game.C_100310_lj.<init>()void
		// @095: putfield game.C_100326_ic game.C_100218_am.field_102533_B
		// @098: aload_0
		// @099: getfield game.C_100218_am game.C_100128_ca.field_102802_U
		// @09C: new game.C_100082_uf
		// @09F: dup
		// @0A0: invokespecial game.C_100082_uf.<init>()void
		// @0A3: putfield game.C_100326_ic game.C_100218_am.field_102533_B
		// @0A6: aload_0
		// @0A7: getfield game.C_100078_ul game.C_100128_ca.field_102805_V
		// @0AA: new game.C_100114_q
		// @0AD: dup
		// @0AE: ldc 10000536 (0x989898)
		// @0B0: invokespecial game.C_100114_q.<init>(int)void
		// @0B3: putfield game.C_100326_ic game.C_100078_ul.field_102533_B
		// @0B6: bipush 20 (0x14)
		// @0B8: istore_3
		// @0B9: iconst_4
		// @0BA: istore #4
		// @0BC: aload_2
		// @0BD: bipush 50 (0x32)
		// @0BF: iload_3
		// @0C0: bipush 20 (0x14)
		// @0C2: sipush 270 (0x010E)
		// @0C5: bipush -94 (0xA2)
		// @0C7: invokevirtual game.C_100336_im.func_102524_a(int, int, int, int, byte)void
		// @0CA: sipush 200 (0x00C8)
		// @0CD: istore #5
		// @0CF: iinc #3 +50
		// @0D2: aload_0
		// @0D3: aload_2
		// @0D4: iconst_1
		// @0D5: invokevirtual game.C_100128_ca.func_102561_b(game.C_100336_im, int)void
		// @0D8: iload_3
		// @0D9: iconst_5
		// @0DA: aload_0
		// @0DB: iload_3
		// @0DC: sipush 170 (0x00AA)
		// @0DF: getstatic java.lang.String game.C_100218_am.field_103118_I
		// @0E2: getstatic java.lang.String game.C_100315_la.field_107180_a
		// @0E5: bipush 35 (0x23)
		// @0E7: aload_0
		// @0E8: getfield game.C_100078_ul game.C_100128_ca.field_102805_V
		// @0EB: invokespecial game.C_100128_ca.func_102797_a(int, int, java.lang.String, java.lang.String, int, game.C_100336_im)int
		// @0EE: iadd
		// @0EF: iadd
		// @0F0: istore_3
		// @0F1: aload_0
		// @0F2: getfield game.C_100218_am game.C_100128_ca.field_102806_Q
		// @0F5: bipush 40 (0x28)
		// @0F7: iload_3
		// @0F8: sipush 496 (0x01F0)
		// @0FB: iload #5
		// @0FD: isub
		// @0FE: ldc -296864799 (0xee4e33e1)
		// @100: ishr
		// @101: iload #5
		// @103: bipush 98 (0x62)
		// @105: invokevirtual game.C_100218_am.func_102524_a(int, int, int, int, byte)void
		// @108: aload_0
		// @109: getfield game.C_100218_am game.C_100128_ca.field_102802_U
		// @10C: bipush 40 (0x28)
		// @10E: iload_3
		// @10F: bipush -15 (0xF1)
		// @111: isub
		// @112: iconst_3
		// @113: iload #4
		// @115: iadd
		// @116: bipush 60 (0x3C)
		// @118: bipush 94 (0x5E)
		// @11A: invokevirtual game.C_100218_am.func_102524_a(int, int, int, int, byte)void
		// @11D: aload_0
		// @11E: getfield game.C_100218_am game.C_100128_ca.field_102802_U
		// @121: aload_0
		// @122: putfield game.C_100337_in game.C_100218_am.field_102543_u
		// @125: aload_0
		// @126: getfield game.C_100218_am game.C_100128_ca.field_102806_Q
		// @129: aload_0
		// @12A: putfield game.C_100337_in game.C_100218_am.field_102543_u
		// @12D: aload_0
		// @12E: aload_0
		// @12F: getfield game.C_100218_am game.C_100128_ca.field_102806_Q
		// @132: iconst_1
		// @133: invokevirtual game.C_100128_ca.func_102561_b(game.C_100336_im, int)void
		// @136: aload_0
		// @137: aload_0
		// @138: getfield game.C_100218_am game.C_100128_ca.field_102802_U
		// @13B: iconst_1
		// @13C: invokevirtual game.C_100128_ca.func_102561_b(game.C_100336_im, int)void
		// @13F: aload_0
		// @140: new game.C_100162_sc
		// @143: dup
		// @144: aload_0
		// @145: invokespecial game.C_100162_sc.<init>(game.C_100276_nb)void
		// @148: putfield game.C_100162_sc game.C_100128_ca.field_102803_T
		// @14B: aload_0
		// @14C: getfield game.C_100162_sc game.C_100128_ca.field_102803_T
		// @14F: sipush 150 (0x0096)
		// @152: bipush 20 (0x14)
		// @154: bipush 60 (0x3C)
		// @156: aload_0
		// @157: getfield game.C_100078_ul game.C_100128_ca.field_102805_V
		// @15A: getfield int game.C_100078_ul.field_102537_l
		// @15D: iadd
		// @15E: aload_0
		// @15F: getfield game.C_100078_ul game.C_100128_ca.field_102805_V
		// @162: getfield int game.C_100078_ul.field_102538_m
		// @165: iadd
		// @166: aload_0
		// @167: getfield game.C_100078_ul game.C_100128_ca.field_102805_V
		// @16A: getfield int game.C_100078_ul.field_102537_l
		// @16D: ineg
		// @16E: aload_0
		// @16F: getfield int game.C_100128_ca.field_102537_l
		// @172: iadd
		// @173: aload_0
		// @174: getfield game.C_100078_ul game.C_100128_ca.field_102805_V
		// @177: getfield int game.C_100078_ul.field_102538_m
		// @17A: bipush -60 (0xC4)
		// @17C: isub
		// @17D: isub
		// @17E: bipush -89 (0xA7)
		// @180: invokevirtual game.C_100162_sc.func_102524_a(int, int, int, int, byte)void
		// @183: aload_0
		// @184: aload_0
		// @185: getfield game.C_100162_sc game.C_100128_ca.field_102803_T
		// @188: iconst_1
		// @189: invokevirtual game.C_100128_ca.func_102561_b(game.C_100336_im, int)void
		// @18C: aload_0
		// @18D: bipush 55 (0x37)
		// @18F: iload_3
		// @190: iload #4
		// @192: ineg
		// @193: isub
		// @194: iadd
		// @195: iconst_0
		// @196: iconst_0
		// @197: sipush 496 (0x01F0)
		// @19A: bipush -127 (0x81)
		// @19C: invokevirtual game.C_100128_ca.func_102524_a(int, int, int, int, byte)void
		// @19F: goto @1AD
		// @1A2: astore_1
		// @1A3: aload_1
		// @1A4: getstatic java.lang.String[] game.C_100128_ca.field_102804_W
		// @1A7: iconst_5
		// @1A8: aaload
		// @1A9: invokestatic game.C_100181_cf.func_105695_a(java.lang.Throwable, java.lang.String)game.C_100170_cm
		// @1AC: athrow
		// @1AD: return
	}
	
	private final boolean func_102794_a(C_100267_mf arg0, boolean arg1)
	{
		// @00: aload_1
		// @01: iconst_1
		// @02: invokeinterface game.C_100267_mf.func_103100_a(boolean)game.C_100308_lh
		// @07: astore_3
		// @08: aconst_null
		// @09: aload_3
		// @0A: if_acmpne @0F
		// @0D: iconst_1
		// @0E: ireturn
		// @0F: aload_3
		// @10: bipush 77 (0x4D)
		// @12: invokeinterface game.C_100308_lh.func_102950_a(byte)game.C_100133_tk
		// @17: astore #4
		// @19: iload_2
		// @1A: ifeq @31
		// @1D: aload_0
		// @1E: bipush 109 (0x6D)
		// @20: bipush 57 (0x39)
		// @22: bipush -37 (0xDB)
		// @24: aconst_null
		// @25: checkcast game.C_100218_am
		// @28: bipush -119 (0x89)
		// @2A: invokevirtual game.C_100128_ca.func_102581_a(int, int, byte, game.C_100218_am, int)void
		// @2D: goto @31
		// @30: athrow
		// @31: getstatic game.C_100133_tk game.C_100079_e.field_102670_tb
		// @34: aload #4
		// @36: if_acmpne @3E
		// @39: iconst_1
		// @3A: goto @3F
		// @3D: athrow
		// @3E: iconst_0
		// @3F: ireturn
		// @40: astore_3
		// @41: aload_3
		// @42: new java.lang.StringBuilder
		// @45: dup
		// @46: invokespecial java.lang.StringBuilder.<init>()void
		// @49: getstatic java.lang.String[] game.C_100128_ca.field_102804_W
		// @4C: bipush 11 (0x0B)
		// @4E: aaload
		// @4F: invokevirtual java.lang.StringBuilder.append(java.lang.String)java.lang.StringBuilder
		// @52: aload_1
		// @53: ifnull @5F
		// @56: getstatic java.lang.String[] game.C_100128_ca.field_102804_W
		// @59: iconst_1
		// @5A: aaload
		// @5B: goto @64
		// @5E: athrow
		// @5F: getstatic java.lang.String[] game.C_100128_ca.field_102804_W
		// @62: iconst_2
		// @63: aaload
		// @64: invokevirtual java.lang.StringBuilder.append(java.lang.String)java.lang.StringBuilder
		// @67: bipush 44 (0x2C)
		// @69: invokevirtual java.lang.StringBuilder.append(char)java.lang.StringBuilder
		// @6C: iload_2
		// @6D: invokevirtual java.lang.StringBuilder.append(boolean)java.lang.StringBuilder
		// @70: bipush 41 (0x29)
		// @72: invokevirtual java.lang.StringBuilder.append(char)java.lang.StringBuilder
		// @75: invokevirtual java.lang.StringBuilder.toString()java.lang.String
		// @78: invokestatic game.C_100181_cf.func_105695_a(java.lang.Throwable, java.lang.String)game.C_100170_cm
		// @7B: athrow
	}
	
	private final boolean func_102792_g(byte arg0)
	{
		// @00: aload_0
		// @01: aload_0
		// @02: getfield game.C_100078_ul game.C_100128_ca.field_102805_V
		// @05: iconst_0
		// @06: invokespecial game.C_100128_ca.func_102794_a(game.C_100267_mf, boolean)boolean
		// @09: ifeq @10
		// @0C: goto @12
		// @0F: athrow
		// @10: iconst_0
		// @11: ireturn
		// @12: iload_1
		// @13: bipush 19 (0x13)
		// @15: if_icmpge @25
		// @18: aload_0
		// @19: aconst_null
		// @1A: checkcast java.lang.String
		// @1D: iconst_0
		// @1E: invokevirtual game.C_100128_ca.func_102789_a(java.lang.String, boolean)void
		// @21: goto @25
		// @24: athrow
		// @25: iconst_1
		// @26: ireturn
		// @27: astore_2
		// @28: aload_2
		// @29: new java.lang.StringBuilder
		// @2C: dup
		// @2D: invokespecial java.lang.StringBuilder.<init>()void
		// @30: getstatic java.lang.String[] game.C_100128_ca.field_102804_W
		// @33: bipush 10 (0x0A)
		// @35: aaload
		// @36: invokevirtual java.lang.StringBuilder.append(java.lang.String)java.lang.StringBuilder
		// @39: iload_1
		// @3A: invokevirtual java.lang.StringBuilder.append(int)java.lang.StringBuilder
		// @3D: bipush 41 (0x29)
		// @3F: invokevirtual java.lang.StringBuilder.append(char)java.lang.StringBuilder
		// @42: invokevirtual java.lang.StringBuilder.toString()java.lang.String
		// @45: invokestatic game.C_100181_cf.func_105695_a(java.lang.Throwable, java.lang.String)game.C_100170_cm
		// @48: athrow
	}
	
	private final int func_102797_a(int arg0, int arg1, String arg2, String arg3, int arg4, C_100336_im arg5)
	{
		// @00: iload #5
		// @02: bipush 35 (0x23)
		// @04: if_icmpeq @13
		// @07: aload_0
		// @08: aconst_null
		// @09: checkcast game.C_100078_ul
		// @0C: putfield game.C_100078_ul game.C_100128_ca.field_102805_V
		// @0F: goto @13
		// @12: athrow
		// @13: aload_0
		// @14: aload_3
		// @15: aload #4
		// @17: aload #6
		// @19: iload_2
		// @1A: iload_1
		// @1B: bipush 35 (0x23)
		// @1D: bipush -8 (0xF8)
		// @1F: invokespecial game.C_100128_ca.func_102798_a(java.lang.String, java.lang.String, game.C_100336_im, int, int, int, byte)int
		// @22: ireturn
		// @23: astore #7
		// @25: aload #7
		// @27: new java.lang.StringBuilder
		// @2A: dup
		// @2B: invokespecial java.lang.StringBuilder.<init>()void
		// @2E: getstatic java.lang.String[] game.C_100128_ca.field_102804_W
		// @31: iconst_3
		// @32: aaload
		// @33: invokevirtual java.lang.StringBuilder.append(java.lang.String)java.lang.StringBuilder
		// @36: iload_1
		// @37: invokevirtual java.lang.StringBuilder.append(int)java.lang.StringBuilder
		// @3A: bipush 44 (0x2C)
		// @3C: invokevirtual java.lang.StringBuilder.append(char)java.lang.StringBuilder
		// @3F: iload_2
		// @40: invokevirtual java.lang.StringBuilder.append(int)java.lang.StringBuilder
		// @43: bipush 44 (0x2C)
		// @45: invokevirtual java.lang.StringBuilder.append(char)java.lang.StringBuilder
		// @48: aload_3
		// @49: ifnull @55
		// @4C: getstatic java.lang.String[] game.C_100128_ca.field_102804_W
		// @4F: iconst_1
		// @50: aaload
		// @51: goto @5A
		// @54: athrow
		// @55: getstatic java.lang.String[] game.C_100128_ca.field_102804_W
		// @58: iconst_2
		// @59: aaload
		// @5A: invokevirtual java.lang.StringBuilder.append(java.lang.String)java.lang.StringBuilder
		// @5D: bipush 44 (0x2C)
		// @5F: invokevirtual java.lang.StringBuilder.append(char)java.lang.StringBuilder
		// @62: aload #4
		// @64: ifnull @70
		// @67: getstatic java.lang.String[] game.C_100128_ca.field_102804_W
		// @6A: iconst_1
		// @6B: aaload
		// @6C: goto @75
		// @6F: athrow
		// @70: getstatic java.lang.String[] game.C_100128_ca.field_102804_W
		// @73: iconst_2
		// @74: aaload
		// @75: invokevirtual java.lang.StringBuilder.append(java.lang.String)java.lang.StringBuilder
		// @78: bipush 44 (0x2C)
		// @7A: invokevirtual java.lang.StringBuilder.append(char)java.lang.StringBuilder
		// @7D: iload #5
		// @7F: invokevirtual java.lang.StringBuilder.append(int)java.lang.StringBuilder
		// @82: bipush 44 (0x2C)
		// @84: invokevirtual java.lang.StringBuilder.append(char)java.lang.StringBuilder
		// @87: aload #6
		// @89: ifnull @95
		// @8C: getstatic java.lang.String[] game.C_100128_ca.field_102804_W
		// @8F: iconst_1
		// @90: aaload
		// @91: goto @9A
		// @94: athrow
		// @95: getstatic java.lang.String[] game.C_100128_ca.field_102804_W
		// @98: iconst_2
		// @99: aaload
		// @9A: invokevirtual java.lang.StringBuilder.append(java.lang.String)java.lang.StringBuilder
		// @9D: bipush 41 (0x29)
		// @9F: invokevirtual java.lang.StringBuilder.append(char)java.lang.StringBuilder
		// @A2: invokevirtual java.lang.StringBuilder.toString()java.lang.String
		// @A5: invokestatic game.C_100181_cf.func_105695_a(java.lang.Throwable, java.lang.String)game.C_100170_cm
		// @A8: athrow
	}
	
	public final void func_102790_a(byte arg0)
	{
		// @00: iload_1
		// @01: bipush 70 (0x46)
		// @03: if_icmpge @1A
		// @06: aload_0
		// @07: bipush 76 (0x4C)
		// @09: bipush -84 (0xAC)
		// @0B: bipush 77 (0x4D)
		// @0D: aconst_null
		// @0E: checkcast game.C_100218_am
		// @11: bipush -116 (0x8C)
		// @13: invokevirtual game.C_100128_ca.func_102581_a(int, int, byte, game.C_100218_am, int)void
		// @16: goto @1A
		// @19: athrow
		// @1A: aload_0
		// @1B: getfield game.C_100078_ul game.C_100128_ca.field_102805_V
		// @1E: iconst_1
		// @1F: invokevirtual game.C_100078_ul.func_103100_a(boolean)game.C_100308_lh
		// @22: checkcast game.C_100064_ve
		// @25: iconst_0
		// @26: invokevirtual game.C_100064_ve.func_103006_c(boolean)void
		// @29: goto @4E
		// @2C: astore_2
		// @2D: aload_2
		// @2E: new java.lang.StringBuilder
		// @31: dup
		// @32: invokespecial java.lang.StringBuilder.<init>()void
		// @35: getstatic java.lang.String[] game.C_100128_ca.field_102804_W
		// @38: bipush 6 (0x06)
		// @3A: aaload
		// @3B: invokevirtual java.lang.StringBuilder.append(java.lang.String)java.lang.StringBuilder
		// @3E: iload_1
		// @3F: invokevirtual java.lang.StringBuilder.append(int)java.lang.StringBuilder
		// @42: bipush 41 (0x29)
		// @44: invokevirtual java.lang.StringBuilder.append(char)java.lang.StringBuilder
		// @47: invokevirtual java.lang.StringBuilder.toString()java.lang.String
		// @4A: invokestatic game.C_100181_cf.func_105695_a(java.lang.Throwable, java.lang.String)game.C_100170_cm
		// @4D: athrow
		// @4E: return
	}
	
	private final int func_102798_a(String arg0, String arg1, C_100336_im arg2, int arg3, int arg4, int arg5, byte arg6)
	{
		// @000: iload #7
		// @002: bipush -8 (0xF8)
		// @004: if_icmpeq @015
		// @007: aload_0
		// @008: aconst_null
		// @009: checkcast game.C_100267_mf
		// @00C: iconst_0
		// @00D: invokespecial game.C_100128_ca.func_102794_a(game.C_100267_mf, boolean)boolean
		// @010: pop
		// @011: goto @015
		// @014: athrow
		// @015: new game.C_100271_mj
		// @018: dup
		// @019: bipush 20 (0x14)
		// @01B: iload #5
		// @01D: iload #4
		// @01F: bipush 120 (0x78)
		// @021: iadd
		// @022: bipush 25 (0x19)
		// @024: aload_3
		// @025: iconst_0
		// @026: bipush 120 (0x78)
		// @028: iconst_3
		// @029: getstatic game.C_100112_r game.C_100230_of.field_106205_g
		// @02C: ldc 16777215 (0xffffff)
		// @02E: aload_2
		// @02F: invokespecial game.C_100271_mj.<init>(int, int, int, int, game.C_100336_im, boolean, int, int, game.C_100112_r, int, java.lang.String)void
		// @032: astore #8
		// @034: aload_0
		// @035: aload #8
		// @037: iconst_1
		// @038: invokevirtual game.C_100128_ca.func_102561_b(game.C_100336_im, int)void
		// @03B: new game.C_100056_de
		// @03E: dup
		// @03F: aload_3
		// @040: checkcast game.C_100267_mf
		// @043: iconst_1
		// @044: invokeinterface game.C_100267_mf.func_103100_a(boolean)game.C_100308_lh
		// @049: aload_1
		// @04A: bipush 126 (0x7E)
		// @04C: aload #8
		// @04E: getfield int game.C_100271_mj.field_102544_t
		// @051: iload #5
		// @053: iadd
		// @054: iload #4
		// @056: bipush 25 (0x19)
		// @058: iadd
		// @059: iload #6
		// @05B: invokespecial game.C_100056_de.<init>(game.C_100308_lh, java.lang.String, int, int, int, int)void
		// @05E: astore #9
		// @060: aload #9
		// @062: aload_0
		// @063: putfield game.C_100337_in game.C_100056_de.field_102543_u
		// @066: aload_0
		// @067: aload #9
		// @069: iconst_1
		// @06A: invokevirtual game.C_100128_ca.func_102561_b(game.C_100336_im, int)void
		// @06D: aload #8
		// @06F: getfield int game.C_100271_mj.field_102544_t
		// @072: aload #9
		// @074: getfield int game.C_100056_de.field_102544_t
		// @077: ineg
		// @078: isub
		// @079: ireturn
		// @07A: astore #8
		// @07C: aload #8
		// @07E: new java.lang.StringBuilder
		// @081: dup
		// @082: invokespecial java.lang.StringBuilder.<init>()void
		// @085: getstatic java.lang.String[] game.C_100128_ca.field_102804_W
		// @088: bipush 8 (0x08)
		// @08A: aaload
		// @08B: invokevirtual java.lang.StringBuilder.append(java.lang.String)java.lang.StringBuilder
		// @08E: aload_1
		// @08F: ifnull @09B
		// @092: getstatic java.lang.String[] game.C_100128_ca.field_102804_W
		// @095: iconst_1
		// @096: aaload
		// @097: goto @0A0
		// @09A: athrow
		// @09B: getstatic java.lang.String[] game.C_100128_ca.field_102804_W
		// @09E: iconst_2
		// @09F: aaload
		// @0A0: invokevirtual java.lang.StringBuilder.append(java.lang.String)java.lang.StringBuilder
		// @0A3: bipush 44 (0x2C)
		// @0A5: invokevirtual java.lang.StringBuilder.append(char)java.lang.StringBuilder
		// @0A8: aload_2
		// @0A9: ifnull @0B5
		// @0AC: getstatic java.lang.String[] game.C_100128_ca.field_102804_W
		// @0AF: iconst_1
		// @0B0: aaload
		// @0B1: goto @0BA
		// @0B4: athrow
		// @0B5: getstatic java.lang.String[] game.C_100128_ca.field_102804_W
		// @0B8: iconst_2
		// @0B9: aaload
		// @0BA: invokevirtual java.lang.StringBuilder.append(java.lang.String)java.lang.StringBuilder
		// @0BD: bipush 44 (0x2C)
		// @0BF: invokevirtual java.lang.StringBuilder.append(char)java.lang.StringBuilder
		// @0C2: aload_3
		// @0C3: ifnull @0CF
		// @0C6: getstatic java.lang.String[] game.C_100128_ca.field_102804_W
		// @0C9: iconst_1
		// @0CA: aaload
		// @0CB: goto @0D4
		// @0CE: athrow
		// @0CF: getstatic java.lang.String[] game.C_100128_ca.field_102804_W
		// @0D2: iconst_2
		// @0D3: aaload
		// @0D4: invokevirtual java.lang.StringBuilder.append(java.lang.String)java.lang.StringBuilder
		// @0D7: bipush 44 (0x2C)
		// @0D9: invokevirtual java.lang.StringBuilder.append(char)java.lang.StringBuilder
		// @0DC: iload #4
		// @0DE: invokevirtual java.lang.StringBuilder.append(int)java.lang.StringBuilder
		// @0E1: bipush 44 (0x2C)
		// @0E3: invokevirtual java.lang.StringBuilder.append(char)java.lang.StringBuilder
		// @0E6: iload #5
		// @0E8: invokevirtual java.lang.StringBuilder.append(int)java.lang.StringBuilder
		// @0EB: bipush 44 (0x2C)
		// @0ED: invokevirtual java.lang.StringBuilder.append(char)java.lang.StringBuilder
		// @0F0: iload #6
		// @0F2: invokevirtual java.lang.StringBuilder.append(int)java.lang.StringBuilder
		// @0F5: bipush 44 (0x2C)
		// @0F7: invokevirtual java.lang.StringBuilder.append(char)java.lang.StringBuilder
		// @0FA: iload #7
		// @0FC: invokevirtual java.lang.StringBuilder.append(int)java.lang.StringBuilder
		// @0FF: bipush 41 (0x29)
		// @101: invokevirtual java.lang.StringBuilder.append(char)java.lang.StringBuilder
		// @104: invokevirtual java.lang.StringBuilder.toString()java.lang.String
		// @107: invokestatic game.C_100181_cf.func_105695_a(java.lang.Throwable, java.lang.String)game.C_100170_cm
		// @10A: athrow
	}
	
	public static void func_102799_k(int arg0)
	{
		// @00: aconst_null
		// @01: putstatic java.lang.String game.C_100128_ca.field_102809_R
		// @04: iload_0
		// @05: sipush 19563 (0x4C6B)
		// @08: if_icmpeq @0C
		// @0B: return
		// @0C: aconst_null
		// @0D: putstatic java.lang.String game.C_100128_ca.field_102807_P
		// @10: goto @35
		// @13: astore_1
		// @14: aload_1
		// @15: new java.lang.StringBuilder
		// @18: dup
		// @19: invokespecial java.lang.StringBuilder.<init>()void
		// @1C: getstatic java.lang.String[] game.C_100128_ca.field_102804_W
		// @1F: bipush 14 (0x0E)
		// @21: aaload
		// @22: invokevirtual java.lang.StringBuilder.append(java.lang.String)java.lang.StringBuilder
		// @25: iload_0
		// @26: invokevirtual java.lang.StringBuilder.append(int)java.lang.StringBuilder
		// @29: bipush 41 (0x29)
		// @2B: invokevirtual java.lang.StringBuilder.append(char)java.lang.StringBuilder
		// @2E: invokevirtual java.lang.StringBuilder.toString()java.lang.String
		// @31: invokestatic game.C_100181_cf.func_105695_a(java.lang.Throwable, java.lang.String)game.C_100170_cm
		// @34: athrow
		// @35: return
	}
	
	static final void func_102800_f(byte arg0)
	{
		// @00: iconst_0
		// @01: putstatic boolean game.C_100021_wn.field_103871_b
		// @04: aconst_null
		// @05: getstatic game.C_100033_gj game.C_100159_sn.field_105401_e
		// @08: if_acmpeq @18
		// @0B: getstatic game.C_100033_gj game.C_100159_sn.field_105401_e
		// @0E: sipush -21723 (0xAB25)
		// @11: invokevirtual game.C_100033_gj.func_101904_o(int)void
		// @14: goto @18
		// @17: athrow
		// @18: getstatic int game.C_100113_ek.field_104880_b
		// @1B: ifne @22
		// @1E: goto @29
		// @21: athrow
		// @22: iload_0
		// @23: bipush 80 (0x50)
		// @25: iadd
		// @26: invokestatic game.C_100233_oa.func_106223_b(int)void
		// @29: iconst_0
		// @2A: putstatic int game.C_100231_oc.field_102200_Wb
		// @2D: iload_0
		// @2E: bipush 39 (0x27)
		// @30: if_icmpeq @3E
		// @33: aconst_null
		// @34: checkcast java.lang.String
		// @37: putstatic java.lang.String game.C_100128_ca.field_102807_P
		// @3A: goto @3E
		// @3D: athrow
		// @3E: goto @62
		// @41: astore_1
		// @42: aload_1
		// @43: new java.lang.StringBuilder
		// @46: dup
		// @47: invokespecial java.lang.StringBuilder.<init>()void
		// @4A: getstatic java.lang.String[] game.C_100128_ca.field_102804_W
		// @4D: iconst_0
		// @4E: aaload
		// @4F: invokevirtual java.lang.StringBuilder.append(java.lang.String)java.lang.StringBuilder
		// @52: iload_0
		// @53: invokevirtual java.lang.StringBuilder.append(int)java.lang.StringBuilder
		// @56: bipush 41 (0x29)
		// @58: invokevirtual java.lang.StringBuilder.append(char)java.lang.StringBuilder
		// @5B: invokevirtual java.lang.StringBuilder.toString()java.lang.String
		// @5E: invokestatic game.C_100181_cf.func_105695_a(java.lang.Throwable, java.lang.String)game.C_100170_cm
		// @61: athrow
		// @62: return
	}
	
	static final void func_102791_l(int arg0)
	{
		// @000: getstatic int game.SteelSentinels.field_105275_O
		// @003: istore #5
		// @005: sipush -20928 (0xAE40)
		// @008: invokestatic game.C_100275_na.func_103081_f(int)void
		// @00B: bipush 77 (0x4D)
		// @00D: putstatic int game.C_100171_cn.field_105573_l
		// @010: iconst_0
		// @011: getstatic game.C_100037_wb game.C_100178_cg.field_105686_f
		// @014: bipush 56 (0x38)
		// @016: iconst_1
		// @017: bipush 9 (0x09)
		// @019: ldc 16711680 (0xff0000)
		// @01B: bipush 49 (0x31)
		// @01D: invokestatic game.C_100242_oh.func_106340_a(int, game.C_100037_wb, int, boolean, int, int, int)void
		// @020: bipush 56 (0x38)
		// @022: getstatic game.C_100037_wb game.C_100178_cg.field_105686_f
		// @025: bipush 63 (0x3F)
		// @027: iconst_1
		// @028: iconst_1
		// @029: ldc 16711680 (0xff0000)
		// @02B: bipush 83 (0x53)
		// @02D: invokestatic game.C_100242_oh.func_106340_a(int, game.C_100037_wb, int, boolean, int, int, int)void
		// @030: getstatic game.C_100037_wb game.C_100255_pj.field_105243_F
		// @033: putstatic game.C_100037_wb game.C_100094_j.field_104545_f
		// @036: iconst_2
		// @037: getstatic game.C_100193_re game.C_100151_bc.field_102942_S
		// @03A: iconst_0
		// @03B: bipush 8 (0x08)
		// @03D: ldc 1146810 (0x117fba)
		// @03F: getstatic game.C_100037_wb[] game.C_100073_f.field_101717_A
		// @042: sipush 240 (0x00F0)
		// @045: iload_0
		// @046: sipush -10565 (0xD6BB)
		// @049: iadd
		// @04A: getstatic game.C_100037_wb[] game.C_100303_kk.field_104789_l
		// @04D: getstatic game.C_100037_wb[] game.C_100106_ef.field_104759_i
		// @050: sipush 320 (0x0140)
		// @053: bipush 8 (0x08)
		// @055: bipush 8 (0x08)
		// @057: ldc 16777215 (0xffffff)
		// @059: bipush 8 (0x08)
		// @05B: invokestatic game.C_100140_bj.func_102953_a(int, game.C_100112_r, int, int, int, game.C_100037_wb[], int, int, game.C_100037_wb[], game.C_100037_wb[], int, int, int, int, int)void
		// @05E: ldc 16777215 (0xffffff)
		// @060: iconst_2
		// @061: bipush -111 (0x91)
		// @063: bipush 8 (0x08)
		// @065: getstatic game.C_100193_re game.C_100151_bc.field_102942_S
		// @068: bipush 8 (0x08)
		// @06A: sipush 240 (0x00F0)
		// @06D: iconst_0
		// @06E: bipush 8 (0x08)
		// @070: getstatic game.C_100037_wb[] game.C_100303_kk.field_104789_l
		// @073: bipush 8 (0x08)
		// @075: sipush 320 (0x0140)
		// @078: getstatic game.C_100037_wb[] game.C_100106_ef.field_104759_i
		// @07B: getstatic game.C_100037_wb[] game.C_100073_f.field_101717_A
		// @07E: ldc 1146810 (0x117fba)
		// @080: invokestatic game.C_100295_kh.func_105282_a(int, int, byte, int, game.C_100112_r, int, int, int, int, game.C_100037_wb[], int, int, game.C_100037_wb[], game.C_100037_wb[], int)void
		// @083: iload_0
		// @084: sipush 24354 (0x5F22)
		// @087: if_icmpeq @093
		// @08A: bipush 12 (0x0C)
		// @08C: invokestatic game.C_100128_ca.func_102791_l(int)void
		// @08F: goto @093
		// @092: athrow
		// @093: bipush 9 (0x09)
		// @095: anewarray game.C_100037_wb
		// @098: putstatic game.C_100037_wb[] game.C_100102_w.field_104655_y
		// @09B: iconst_0
		// @09C: istore_1
		// @09D: bipush -10 (0xF6)
		// @09F: iload_1
		// @0A0: iconst_m1
		// @0A1: ixor
		// @0A2: if_icmpge @121
		// @0A5: getstatic game.C_100037_wb[] game.C_100102_w.field_104655_y
		// @0A8: iload_1
		// @0A9: getstatic game.C_100037_wb[] game.C_100285_nk.field_106786_j
		// @0AC: iload_1
		// @0AD: aaload
		// @0AE: invokevirtual game.C_100037_wb.func_102381_e()game.C_100037_wb
		// @0B1: aastore
		// @0B2: iload_1
		// @0B3: iconst_m1
		// @0B4: ixor
		// @0B5: iload #5
		// @0B7: ifne @129
		// @0BA: bipush -4 (0xFC)
		// @0BC: if_icmple @0DC
		// @0BF: goto @0C3
		// @0C2: athrow
		// @0C3: iconst_0
		// @0C4: bipush 43 (0x2B)
		// @0C6: bipush 10 (0x0A)
		// @0C8: iconst_0
		// @0C9: bipush 50 (0x32)
		// @0CB: getstatic game.C_100037_wb[] game.C_100102_w.field_104655_y
		// @0CE: iload_1
		// @0CF: aaload
		// @0D0: invokestatic game.C_100041_wf.func_104097_a(int, int, int, int, int, game.C_100037_wb)void
		// @0D3: iload #5
		// @0D5: ifeq @119
		// @0D8: goto @0DC
		// @0DB: athrow
		// @0DC: bipush -7 (0xF9)
		// @0DE: iload_1
		// @0DF: iconst_m1
		// @0E0: ixor
		// @0E1: if_icmpge @105
		// @0E4: goto @0E8
		// @0E7: athrow
		// @0E8: iconst_0
		// @0E9: bipush 35 (0x23)
		// @0EB: bipush 10 (0x0A)
		// @0ED: iload_0
		// @0EE: sipush 24354 (0x5F22)
		// @0F1: ixor
		// @0F2: bipush 42 (0x2A)
		// @0F4: getstatic game.C_100037_wb[] game.C_100102_w.field_104655_y
		// @0F7: iload_1
		// @0F8: aaload
		// @0F9: invokestatic game.C_100041_wf.func_104097_a(int, int, int, int, int, game.C_100037_wb)void
		// @0FC: iload #5
		// @0FE: ifeq @119
		// @101: goto @105
		// @104: athrow
		// @105: iconst_0
		// @106: bipush 27 (0x1B)
		// @108: bipush 10 (0x0A)
		// @10A: iconst_0
		// @10B: bipush 34 (0x22)
		// @10D: getstatic game.C_100037_wb[] game.C_100102_w.field_104655_y
		// @110: iload_1
		// @111: aaload
		// @112: invokestatic game.C_100041_wf.func_104097_a(int, int, int, int, int, game.C_100037_wb)void
		// @115: goto @119
		// @118: athrow
		// @119: iinc #1 +1
		// @11C: iload #5
		// @11E: ifeq @09D
		// @121: getstatic game.C_100037_wb[] game.C_100111_el.field_104867_h
		// @124: iconst_0
		// @125: aaload
		// @126: getfield int game.C_100037_wb.field_102340_z
		// @129: istore_1
		// @12A: getstatic game.C_100037_wb[] game.C_100111_el.field_104867_h
		// @12D: iconst_1
		// @12E: new game.C_100037_wb
		// @131: dup
		// @132: iload_1
		// @133: iload_1
		// @134: invokespecial game.C_100037_wb.<init>(int, int)void
		// @137: aastore
		// @138: getstatic game.C_100037_wb[] game.C_100111_el.field_104867_h
		// @13B: iconst_2
		// @13C: new game.C_100037_wb
		// @13F: dup
		// @140: iload_1
		// @141: iload_1
		// @142: invokespecial game.C_100037_wb.<init>(int, int)void
		// @145: aastore
		// @146: getstatic game.C_100037_wb[] game.C_100111_el.field_104867_h
		// @149: iconst_0
		// @14A: aaload
		// @14B: getfield int[] game.C_100037_wb.field_102388_J
		// @14E: astore_2
		// @14F: iconst_0
		// @150: istore_3
		// @151: iload_3
		// @152: aload_2
		// @153: arraylength
		// @154: if_icmpge @191
		// @157: iload #5
		// @159: ifne @1C9
		// @15C: aload_2
		// @15D: iload_3
		// @15E: iaload
		// @15F: ldc 16711680 (0xff0000)
		// @161: if_icmpne @189
		// @164: goto @168
		// @167: athrow
		// @168: getstatic game.C_100037_wb[] game.C_100111_el.field_104867_h
		// @16B: iconst_1
		// @16C: aaload
		// @16D: getfield int[] game.C_100037_wb.field_102388_J
		// @170: iload_3
		// @171: ldc 45056 (0xb000)
		// @173: iastore
		// @174: getstatic game.C_100037_wb[] game.C_100111_el.field_104867_h
		// @177: iconst_2
		// @178: aaload
		// @179: getfield int[] game.C_100037_wb.field_102388_J
		// @17C: iload_3
		// @17D: ldc 8388608 (0x800000)
		// @17F: iastore
		// @180: aload_2
		// @181: iload_3
		// @182: ldc 33023 (0x80ff)
		// @184: iastore
		// @185: goto @189
		// @188: athrow
		// @189: iinc #3 +1
		// @18C: iload #5
		// @18E: ifeq @151
		// @191: getstatic game.C_100037_wb[] game.C_100013_fn.field_103739_d
		// @194: bipush 21 (0x15)
		// @196: getstatic game.C_100037_wb[] game.C_100111_el.field_104867_h
		// @199: iconst_0
		// @19A: aaload
		// @19B: invokevirtual game.C_100037_wb.func_102381_e()game.C_100037_wb
		// @19E: aastore
		// @19F: getstatic game.C_100037_wb[] game.C_100013_fn.field_103739_d
		// @1A2: bipush 22 (0x16)
		// @1A4: getstatic game.C_100037_wb[] game.C_100111_el.field_104867_h
		// @1A7: iconst_1
		// @1A8: aaload
		// @1A9: invokevirtual game.C_100037_wb.func_102381_e()game.C_100037_wb
		// @1AC: aastore
		// @1AD: getstatic game.C_100037_wb[] game.C_100013_fn.field_103739_d
		// @1B0: bipush 23 (0x17)
		// @1B2: getstatic game.C_100037_wb[] game.C_100111_el.field_104867_h
		// @1B5: iconst_2
		// @1B6: aaload
		// @1B7: invokevirtual game.C_100037_wb.func_102381_e()game.C_100037_wb
		// @1BA: aastore
		// @1BB: getstatic game.C_100037_wb[] game.C_100013_fn.field_103739_d
		// @1BE: bipush 24 (0x18)
		// @1C0: getstatic game.C_100037_wb[] game.C_100111_el.field_104867_h
		// @1C3: iconst_2
		// @1C4: aaload
		// @1C5: invokevirtual game.C_100037_wb.func_102381_e()game.C_100037_wb
		// @1C8: aastore
		// @1C9: getstatic game.C_100037_wb[] game.C_100058_dg.field_101562_E
		// @1CC: iconst_0
		// @1CD: aaload
		// @1CE: astore_3
		// @1CF: getstatic game.C_100037_wb[] game.C_100058_dg.field_101562_E
		// @1D2: iconst_0
		// @1D3: getstatic game.C_100037_wb[] game.C_100111_el.field_104867_h
		// @1D6: iconst_0
		// @1D7: aaload
		// @1D8: invokevirtual game.C_100037_wb.func_102381_e()game.C_100037_wb
		// @1DB: aastore
		// @1DC: getstatic game.C_100037_wb[] game.C_100058_dg.field_101562_E
		// @1DF: iconst_0
		// @1E0: aaload
		// @1E1: invokevirtual game.C_100037_wb.func_102379_d()void
		// @1E4: aload_3
		// @1E5: iconst_0
		// @1E6: iconst_0
		// @1E7: invokevirtual game.C_100037_wb.func_102353_h(int, int)void
		// @1EA: iconst_0
		// @1EB: istore #4
		// @1ED: iload #4
		// @1EF: aload_3
		// @1F0: getfield int[] game.C_100037_wb.field_102388_J
		// @1F3: arraylength
		// @1F4: if_icmpge @246
		// @1F7: aload_3
		// @1F8: getfield int[] game.C_100037_wb.field_102388_J
		// @1FB: iload #4
		// @1FD: iaload
		// @1FE: ldc 65280 (0xff00)
		// @200: iand
		// @201: iload #5
		// @203: ifne @262
		// @206: ifne @231
		// @209: goto @20D
		// @20C: athrow
		// @20D: aload_3
		// @20E: getfield int[] game.C_100037_wb.field_102388_J
		// @211: iload #4
		// @213: iaload
		// @214: sipush 255 (0x00FF)
		// @217: iand
		// @218: ifne @223
		// @21B: goto @21F
		// @21E: athrow
		// @21F: goto @23E
		// @222: athrow
		// @223: aload_3
		// @224: getfield int[] game.C_100037_wb.field_102388_J
		// @227: iload #4
		// @229: ldc 32768 (0x8000)
		// @22B: iastore
		// @22C: iload #5
		// @22E: ifeq @23E
		// @231: aload_3
		// @232: getfield int[] game.C_100037_wb.field_102388_J
		// @235: iload #4
		// @237: ldc 8454016 (0x80ff80)
		// @239: iastore
		// @23A: goto @23E
		// @23D: athrow
		// @23E: iinc #4 +1
		// @241: iload #5
		// @243: ifeq @1ED
		// @246: getstatic game.C_100037_wb[] game.C_100058_dg.field_101562_E
		// @249: iconst_1
		// @24A: getstatic game.C_100037_wb[] game.C_100111_el.field_104867_h
		// @24D: iconst_1
		// @24E: aaload
		// @24F: invokevirtual game.C_100037_wb.func_102381_e()game.C_100037_wb
		// @252: aastore
		// @253: getstatic game.C_100037_wb[] game.C_100058_dg.field_101562_E
		// @256: iconst_1
		// @257: aaload
		// @258: invokevirtual game.C_100037_wb.func_102379_d()void
		// @25B: aload_3
		// @25C: iconst_0
		// @25D: iconst_0
		// @25E: invokevirtual game.C_100037_wb.func_102353_h(int, int)void
		// @261: iconst_0
		// @262: istore #4
		// @264: iload #4
		// @266: aload_3
		// @267: getfield int[] game.C_100037_wb.field_102388_J
		// @26A: arraylength
		// @26B: if_icmpge @2BC
		// @26E: ldc -8454017 (0xff7f007f)
		// @270: aload_3
		// @271: getfield int[] game.C_100037_wb.field_102388_J
		// @274: iload #4
		// @276: iaload
		// @277: iconst_m1
		// @278: ixor
		// @279: iload #5
		// @27B: ifne @2E0
		// @27E: if_icmpeq @2A7
		// @281: goto @285
		// @284: athrow
		// @285: aload_3
		// @286: getfield int[] game.C_100037_wb.field_102388_J
		// @289: iload #4
		// @28B: iaload
		// @28C: ldc 32768 (0x8000)
		// @28E: if_icmpne @2B4
		// @291: goto @295
		// @294: athrow
		// @295: aload_3
		// @296: getfield int[] game.C_100037_wb.field_102388_J
		// @299: iload #4
		// @29B: ldc 8388608 (0x800000)
		// @29D: iastore
		// @29E: iload #5
		// @2A0: ifeq @2B4
		// @2A3: goto @2A7
		// @2A6: athrow
		// @2A7: aload_3
		// @2A8: getfield int[] game.C_100037_wb.field_102388_J
		// @2AB: iload #4
		// @2AD: ldc 16711680 (0xff0000)
		// @2AF: iastore
		// @2B0: goto @2B4
		// @2B3: athrow
		// @2B4: iinc #4 +1
		// @2B7: iload #5
		// @2B9: ifeq @264
		// @2BC: getstatic game.C_100037_wb[] game.C_100058_dg.field_101562_E
		// @2BF: iconst_2
		// @2C0: getstatic game.C_100037_wb[] game.C_100111_el.field_104867_h
		// @2C3: iconst_2
		// @2C4: aaload
		// @2C5: invokevirtual game.C_100037_wb.func_102381_e()game.C_100037_wb
		// @2C8: aastore
		// @2C9: getstatic game.C_100037_wb[] game.C_100058_dg.field_101562_E
		// @2CC: iconst_2
		// @2CD: aaload
		// @2CE: invokevirtual game.C_100037_wb.func_102379_d()void
		// @2D1: aload_3
		// @2D2: iconst_0
		// @2D3: iconst_0
		// @2D4: invokevirtual game.C_100037_wb.func_102353_h(int, int)void
		// @2D7: iconst_0
		// @2D8: istore #4
		// @2DA: bipush -4 (0xFC)
		// @2DC: iload #4
		// @2DE: iconst_m1
		// @2DF: ixor
		// @2E0: if_icmpge @30F
		// @2E3: getstatic game.C_100037_wb[] game.C_100013_fn.field_103739_d
		// @2E6: iload #4
		// @2E8: bipush 21 (0x15)
		// @2EA: iadd
		// @2EB: aaload
		// @2EC: invokevirtual game.C_100037_wb.func_102379_d()void
		// @2EF: getstatic game.C_100037_wb[] game.C_100058_dg.field_101562_E
		// @2F2: iload #4
		// @2F4: aaload
		// @2F5: iconst_0
		// @2F6: iconst_0
		// @2F7: invokevirtual game.C_100037_wb.func_102353_h(int, int)void
		// @2FA: iinc #4 +1
		// @2FD: iload #5
		// @2FF: ifne @338
		// @302: goto @306
		// @305: athrow
		// @306: iload #5
		// @308: ifeq @2DA
		// @30B: goto @30F
		// @30E: athrow
		// @30F: getstatic game.C_100037_wb[] game.C_100013_fn.field_103739_d
		// @312: bipush 24 (0x18)
		// @314: aaload
		// @315: invokevirtual game.C_100037_wb.func_102379_d()void
		// @318: getstatic game.C_100037_wb[] game.C_100124_tn.field_104936_c
		// @31B: iconst_1
		// @31C: aaload
		// @31D: iconst_0
		// @31E: iconst_0
		// @31F: iload_1
		// @320: iconst_4
		// @321: imul
		// @322: iload_1
		// @323: iconst_4
		// @324: imul
		// @325: invokevirtual game.C_100037_wb.func_102364_d(int, int, int, int)void
		// @328: getstatic game.C_100185_rm game.C_100049_vf.field_104206_l
		// @32B: bipush 125 (0x7D)
		// @32D: invokevirtual game.C_100185_rm.func_105476_a(byte)void
		// @330: bipush 20 (0x14)
		// @332: anewarray game.C_100037_wb
		// @335: putstatic game.C_100037_wb[] game.C_100049_vf.field_104212_w
		// @338: iconst_0
		// @339: istore #4
		// @33B: iload #4
		// @33D: iconst_m1
		// @33E: ixor
		// @33F: bipush -21 (0xEB)
		// @341: if_icmple @37A
		// @344: getstatic game.C_100037_wb[] game.C_100049_vf.field_104212_w
		// @347: iload #4
		// @349: new game.C_100037_wb
		// @34C: dup
		// @34D: bipush 20 (0x14)
		// @34F: bipush 20 (0x14)
		// @351: invokespecial game.C_100037_wb.<init>(int, int)void
		// @354: aastore
		// @355: getstatic game.C_100037_wb[] game.C_100049_vf.field_104212_w
		// @358: iload #4
		// @35A: aaload
		// @35B: invokevirtual game.C_100037_wb.func_102379_d()void
		// @35E: getstatic game.C_100037_wb[] game.C_100066_dl.field_101640_v
		// @361: iload #4
		// @363: aaload
		// @364: iconst_0
		// @365: iconst_0
		// @366: invokevirtual game.C_100037_wb.func_102360_g(int, int)void
		// @369: iinc #4 +1
		// @36C: iload #5
		// @36E: ifne @38A
		// @371: iload #5
		// @373: ifeq @33B
		// @376: goto @37A
		// @379: athrow
		// @37A: getstatic game.C_100185_rm game.C_100049_vf.field_104206_l
		// @37D: bipush 125 (0x7D)
		// @37F: invokevirtual game.C_100185_rm.func_105476_a(byte)void
		// @382: iload_0
		// @383: sipush -24231 (0xA159)
		// @386: iadd
		// @387: invokestatic game.C_100218_am.func_103103_i(int)void
		// @38A: goto @3AF
		// @38D: astore_1
		// @38E: aload_1
		// @38F: new java.lang.StringBuilder
		// @392: dup
		// @393: invokespecial java.lang.StringBuilder.<init>()void
		// @396: getstatic java.lang.String[] game.C_100128_ca.field_102804_W
		// @399: bipush 15 (0x0F)
		// @39B: aaload
		// @39C: invokevirtual java.lang.StringBuilder.append(java.lang.String)java.lang.StringBuilder
		// @39F: iload_0
		// @3A0: invokevirtual java.lang.StringBuilder.append(int)java.lang.StringBuilder
		// @3A3: bipush 41 (0x29)
		// @3A5: invokevirtual java.lang.StringBuilder.append(char)java.lang.StringBuilder
		// @3A8: invokevirtual java.lang.StringBuilder.toString()java.lang.String
		// @3AB: invokestatic game.C_100181_cf.func_105695_a(java.lang.Throwable, java.lang.String)game.C_100170_cm
		// @3AE: athrow
		// @3AF: return
	}
	
	public final void func_102789_a(String arg0, boolean arg1)
	{
		// @00: aload_0
		// @01: getfield game.C_100078_ul game.C_100128_ca.field_102805_V
		// @04: astore_3
		// @05: aload_1
		// @06: astore #4
		// @08: aload_3
		// @09: iload_2
		// @0A: iconst_1
		// @0B: aload #4
		// @0D: invokevirtual game.C_100309_lk.func_103251_a(boolean, boolean, java.lang.String)void
		// @10: goto @4F
		// @13: astore_3
		// @14: aload_3
		// @15: new java.lang.StringBuilder
		// @18: dup
		// @19: invokespecial java.lang.StringBuilder.<init>()void
		// @1C: getstatic java.lang.String[] game.C_100128_ca.field_102804_W
		// @1F: bipush 16 (0x10)
		// @21: aaload
		// @22: invokevirtual java.lang.StringBuilder.append(java.lang.String)java.lang.StringBuilder
		// @25: aload_1
		// @26: ifnull @32
		// @29: getstatic java.lang.String[] game.C_100128_ca.field_102804_W
		// @2C: iconst_1
		// @2D: aaload
		// @2E: goto @37
		// @31: athrow
		// @32: getstatic java.lang.String[] game.C_100128_ca.field_102804_W
		// @35: iconst_2
		// @36: aaload
		// @37: invokevirtual java.lang.StringBuilder.append(java.lang.String)java.lang.StringBuilder
		// @3A: bipush 44 (0x2C)
		// @3C: invokevirtual java.lang.StringBuilder.append(char)java.lang.StringBuilder
		// @3F: iload_2
		// @40: invokevirtual java.lang.StringBuilder.append(boolean)java.lang.StringBuilder
		// @43: bipush 41 (0x29)
		// @45: invokevirtual java.lang.StringBuilder.append(char)java.lang.StringBuilder
		// @48: invokevirtual java.lang.StringBuilder.toString()java.lang.String
		// @4B: invokestatic game.C_100181_cf.func_105695_a(java.lang.Throwable, java.lang.String)game.C_100170_cm
		// @4E: athrow
		// @4F: return
	}
	
	final boolean func_102506_a(char arg0, int arg1, int arg2, C_100336_im arg3)
	{
		// @00: aload_0
		// @01: iload_1
		// @02: iload_2
		// @03: iload_3
		// @04: aload #4
		// @06: invokespecial game.C_100085_a.func_102506_a(char, int, int, game.C_100336_im)boolean
		// @09: ifeq @0E
		// @0C: iconst_1
		// @0D: ireturn
		// @0E: bipush -99 (0x9D)
		// @10: iload_2
		// @11: iconst_m1
		// @12: ixor
		// @13: if_icmpne @1F
		// @16: aload_0
		// @17: aload #4
		// @19: bipush 118 (0x76)
		// @1B: invokevirtual game.C_100128_ca.func_102555_a(game.C_100336_im, int)boolean
		// @1E: ireturn
		// @1F: iload_2
		// @20: bipush 99 (0x63)
		// @22: if_icmpne @2F
		// @25: aload_0
		// @26: sipush -17543 (0xBB79)
		// @29: aload #4
		// @2B: invokevirtual game.C_100128_ca.func_102558_b(int, game.C_100336_im)boolean
		// @2E: ireturn
		// @2F: iconst_0
		// @30: ireturn
		// @31: astore #5
		// @33: aload #5
		// @35: new java.lang.StringBuilder
		// @38: dup
		// @39: invokespecial java.lang.StringBuilder.<init>()void
		// @3C: getstatic java.lang.String[] game.C_100128_ca.field_102804_W
		// @3F: bipush 7 (0x07)
		// @41: aaload
		// @42: invokevirtual java.lang.StringBuilder.append(java.lang.String)java.lang.StringBuilder
		// @45: iload_1
		// @46: invokevirtual java.lang.StringBuilder.append(char)java.lang.StringBuilder
		// @49: bipush 44 (0x2C)
		// @4B: invokevirtual java.lang.StringBuilder.append(char)java.lang.StringBuilder
		// @4E: iload_2
		// @4F: invokevirtual java.lang.StringBuilder.append(int)java.lang.StringBuilder
		// @52: bipush 44 (0x2C)
		// @54: invokevirtual java.lang.StringBuilder.append(char)java.lang.StringBuilder
		// @57: iload_3
		// @58: invokevirtual java.lang.StringBuilder.append(int)java.lang.StringBuilder
		// @5B: bipush 44 (0x2C)
		// @5D: invokevirtual java.lang.StringBuilder.append(char)java.lang.StringBuilder
		// @60: aload #4
		// @62: ifnull @6E
		// @65: getstatic java.lang.String[] game.C_100128_ca.field_102804_W
		// @68: iconst_1
		// @69: aaload
		// @6A: goto @73
		// @6D: athrow
		// @6E: getstatic java.lang.String[] game.C_100128_ca.field_102804_W
		// @71: iconst_2
		// @72: aaload
		// @73: invokevirtual java.lang.StringBuilder.append(java.lang.String)java.lang.StringBuilder
		// @76: bipush 41 (0x29)
		// @78: invokevirtual java.lang.StringBuilder.append(char)java.lang.StringBuilder
		// @7B: invokevirtual java.lang.StringBuilder.toString()java.lang.String
		// @7E: invokestatic game.C_100181_cf.func_105695_a(java.lang.Throwable, java.lang.String)game.C_100170_cm
		// @81: athrow
	}
	
	final void func_102513_a(C_100336_im arg0, int arg1, int arg2, int arg3)
	{
		// @00: aload_0
		// @01: aload_1
		// @02: iload_2
		// @03: iload_3
		// @04: iload #4
		// @06: invokespecial game.C_100085_a.func_102513_a(game.C_100336_im, int, int, int)void
		// @09: aload_0
		// @0A: getfield game.C_100218_am game.C_100128_ca.field_102806_Q
		// @0D: aload_0
		// @0E: bipush 20 (0x14)
		// @10: invokespecial game.C_100128_ca.func_102792_g(byte)boolean
		// @13: putfield boolean game.C_100218_am.field_103113_L
		// @16: goto @6A
		// @19: astore #5
		// @1B: aload #5
		// @1D: new java.lang.StringBuilder
		// @20: dup
		// @21: invokespecial java.lang.StringBuilder.<init>()void
		// @24: getstatic java.lang.String[] game.C_100128_ca.field_102804_W
		// @27: bipush 13 (0x0D)
		// @29: aaload
		// @2A: invokevirtual java.lang.StringBuilder.append(java.lang.String)java.lang.StringBuilder
		// @2D: aload_1
		// @2E: ifnull @3A
		// @31: getstatic java.lang.String[] game.C_100128_ca.field_102804_W
		// @34: iconst_1
		// @35: aaload
		// @36: goto @3F
		// @39: athrow
		// @3A: getstatic java.lang.String[] game.C_100128_ca.field_102804_W
		// @3D: iconst_2
		// @3E: aaload
		// @3F: invokevirtual java.lang.StringBuilder.append(java.lang.String)java.lang.StringBuilder
		// @42: bipush 44 (0x2C)
		// @44: invokevirtual java.lang.StringBuilder.append(char)java.lang.StringBuilder
		// @47: iload_2
		// @48: invokevirtual java.lang.StringBuilder.append(int)java.lang.StringBuilder
		// @4B: bipush 44 (0x2C)
		// @4D: invokevirtual java.lang.StringBuilder.append(char)java.lang.StringBuilder
		// @50: iload_3
		// @51: invokevirtual java.lang.StringBuilder.append(int)java.lang.StringBuilder
		// @54: bipush 44 (0x2C)
		// @56: invokevirtual java.lang.StringBuilder.append(char)java.lang.StringBuilder
		// @59: iload #4
		// @5B: invokevirtual java.lang.StringBuilder.append(int)java.lang.StringBuilder
		// @5E: bipush 41 (0x29)
		// @60: invokevirtual java.lang.StringBuilder.append(char)java.lang.StringBuilder
		// @63: invokevirtual java.lang.StringBuilder.toString()java.lang.String
		// @66: invokestatic game.C_100181_cf.func_105695_a(java.lang.Throwable, java.lang.String)game.C_100170_cm
		// @69: athrow
		// @6A: return
	}
	
	static
	{
		// @00: bipush 17 (0x11)
		// @02: anewarray java.lang.String
		// @05: dup
		// @06: iconst_0
		// @07: ldc "\u001fwF~hT"
		// @09: invokestatic game.C_100128_ca.func_102795_z(java.lang.String)char[]
		// @0C: invokestatic game.C_100128_ca.func_102793_z(char[])java.lang.String
		// @0F: aastore
		// @10: dup
		// @11: iconst_1
		// @12: ldc "\u00078F\u001fT"
		// @14: invokestatic game.C_100128_ca.func_102795_z(java.lang.String)char[]
		// @17: invokestatic game.C_100128_ca.func_102793_z(char[])java.lang.String
		// @1A: aastore
		// @1B: dup
		// @1C: iconst_2
		// @1D: ldc "\u0012c\u0004]"
		// @1F: invokestatic game.C_100128_ca.func_102795_z(java.lang.String)char[]
		// @22: invokestatic game.C_100128_ca.func_102793_z(char[])java.lang.String
		// @25: aastore
		// @26: dup
		// @27: iconst_3
		// @28: ldc "\u001fwFzhT"
		// @2A: invokestatic game.C_100128_ca.func_102795_z(java.lang.String)char[]
		// @2D: invokestatic game.C_100128_ca.func_102793_z(char[])java.lang.String
		// @30: aastore
		// @31: dup
		// @32: iconst_4
		// @33: ldc "\u001fwFahT"
		// @35: invokestatic game.C_100128_ca.func_102795_z(java.lang.String)char[]
		// @38: invokestatic game.C_100128_ca.func_102793_z(char[])java.lang.String
		// @3B: aastore
		// @3C: dup
		// @3D: iconst_5
		// @3E: ldc "\u001fwF\r@\u0012\u007f\u001c\u000f\u0001U"
		// @40: invokestatic game.C_100128_ca.func_102795_z(java.lang.String)char[]
		// @43: invokestatic game.C_100128_ca.func_102793_z(char[])java.lang.String
		// @46: aastore
		// @47: dup
		// @48: bipush 6 (0x06)
		// @4A: ldc "\u001fwFyhT"
		// @4C: invokestatic game.C_100128_ca.func_102795_z(java.lang.String)char[]
		// @4F: invokestatic game.C_100128_ca.func_102793_z(char[])java.lang.String
		// @52: aastore
		// @53: dup
		// @54: bipush 7 (0x07)
		// @56: ldc "\u001fwFwhT"
		// @58: invokestatic game.C_100128_ca.func_102795_z(java.lang.String)char[]
		// @5B: invokestatic game.C_100128_ca.func_102793_z(char[])java.lang.String
		// @5E: aastore
		// @5F: dup
		// @60: bipush 8 (0x08)
		// @62: ldc "\u001fwF`hT"
		// @64: invokestatic game.C_100128_ca.func_102795_z(java.lang.String)char[]
		// @67: invokestatic game.C_100128_ca.func_102793_z(char[])java.lang.String
		// @6A: aastore
		// @6B: dup
		// @6C: bipush 9 (0x09)
		// @6E: ldc "\u001fwF\u007fhT"
		// @70: invokestatic game.C_100128_ca.func_102795_z(java.lang.String)char[]
		// @73: invokestatic game.C_100128_ca.func_102793_z(char[])java.lang.String
		// @76: aastore
		// @77: dup
		// @78: bipush 10 (0x0A)
		// @7A: ldc "\u001fwFchT"
		// @7C: invokestatic game.C_100128_ca.func_102795_z(java.lang.String)char[]
		// @7F: invokestatic game.C_100128_ca.func_102793_z(char[])java.lang.String
		// @82: aastore
		// @83: dup
		// @84: bipush 11 (0x0B)
		// @86: ldc "\u001fwFbhT"
		// @88: invokestatic game.C_100128_ca.func_102795_z(java.lang.String)char[]
		// @8B: invokestatic game.C_100128_ca.func_102793_z(char[])java.lang.String
		// @8E: aastore
		// @8F: dup
		// @90: bipush 12 (0x0C)
		// @92: ldc "\u001fwF{hT"
		// @94: invokestatic game.C_100128_ca.func_102795_z(java.lang.String)char[]
		// @97: invokestatic game.C_100128_ca.func_102793_z(char[])java.lang.String
		// @9A: aastore
		// @9B: dup
		// @9C: bipush 13 (0x0D)
		// @9E: ldc "\u001fwF`\u0001"
		// @A0: invokestatic game.C_100128_ca.func_102795_z(java.lang.String)char[]
		// @A3: invokestatic game.C_100128_ca.func_102793_z(char[])java.lang.String
		// @A6: aastore
		// @A7: dup
		// @A8: bipush 14 (0x0E)
		// @AA: ldc "\u001fwFxhT"
		// @AC: invokestatic game.C_100128_ca.func_102795_z(java.lang.String)char[]
		// @AF: invokestatic game.C_100128_ca.func_102793_z(char[])java.lang.String
		// @B2: aastore
		// @B3: dup
		// @B4: bipush 15 (0x0F)
		// @B6: ldc "\u001fwF|hT"
		// @B8: invokestatic game.C_100128_ca.func_102795_z(java.lang.String)char[]
		// @BB: invokestatic game.C_100128_ca.func_102793_z(char[])java.lang.String
		// @BE: aastore
		// @BF: dup
		// @C0: bipush 16 (0x10)
		// @C2: ldc "\u001fwFvhT"
		// @C4: invokestatic game.C_100128_ca.func_102795_z(java.lang.String)char[]
		// @C7: invokestatic game.C_100128_ca.func_102793_z(char[])java.lang.String
		// @CA: aastore
		// @CB: putstatic java.lang.String[] game.C_100128_ca.field_102804_W
		// @CE: ldc "2w\u0005TZ\\u\t_G\u0013bHRF\u0012b\tXG\\u\u0007_Z\u0019u\u001dE@\nsHBY\u001du\rB"
		// @D0: invokestatic game.C_100128_ca.func_102795_z(java.lang.String)char[]
		// @D3: invokestatic game.C_100128_ca.func_102793_z(char[])java.lang.String
		// @D6: putstatic java.lang.String game.C_100128_ca.field_102809_R
		// @D9: ldc "+~\u0007\u0011J\u001dxH[F\u0015x"
		// @DB: invokestatic game.C_100128_ca.func_102795_z(java.lang.String)char[]
		// @DE: invokestatic game.C_100128_ca.func_102793_z(char[])java.lang.String
		// @E1: putstatic java.lang.String game.C_100128_ca.field_102807_P
		// @E4: iconst_m1
		// @E5: putstatic int game.C_100128_ca.field_102808_S
		// @E8: return
	}
	
	private static char[] func_102795_z(String arg0)
	{
		// @00: aload_0
		// @01: invokevirtual java.lang.String.toCharArray()char[]
		// @04: dup
		// @05: arraylength
		// @06: iconst_2
		// @07: if_icmpge @13
		// @0A: dup
		// @0B: iconst_0
		// @0C: dup2
		// @0D: caload
		// @0E: bipush 41 (0x29)
		// @10: ixor
		// @11: i2c
		// @12: castore
		// @13: areturn
	}
	
	private static String func_102793_z(char[] arg0)
	{
		// @00: aload_0
		// @01: dup
		// @02: arraylength
		// @03: swap
		// @04: iconst_0
		// @05: istore_1
		// @06: goto @4C
		// @09: dup
		// @0A: iload_1
		// @0B: dup2
		// @0C: caload
		// @0D: iload_1
		// @0E: iconst_5
		// @0F: irem
		// @10: tableswitch def: @44, for 0: @30, for 1: @35, for 2: @3A, for 3: @3F
		// @30: bipush 124 (0x7C)
		// @32: goto @46
		// @35: bipush 22 (0x16)
		// @37: goto @46
		// @3A: bipush 104 (0x68)
		// @3C: goto @46
		// @3F: bipush 49 (0x31)
		// @41: goto @46
		// @44: bipush 41 (0x29)
		// @46: ixor
		// @47: i2c
		// @48: castore
		// @49: iinc #1 +1
		// @4C: swap
		// @4D: dup_x1
		// @4E: iload_1
		// @4F: if_icmpgt @09
		// @52: new java.lang.String
		// @55: dup_x1
		// @56: swap
		// @57: invokespecial java.lang.String.<init>(char[])void
		// @5A: invokevirtual java.lang.String.intern()java.lang.String
		// @5D: areturn
	}
}
