package game;

final class C_100123_uc
{
	static String field_104924_c;
	static int field_104920_g;
	static String field_104921_d;
	static C_100302_ka field_104923_b;
	static C_100302_ka[] field_104925_a;
	static String field_104919_f;
	static String field_104922_e;
	private static final String[] field_104926_z;
	
	static final void func_104914_b(int arg0)
	{
		// @00: getstatic game.C_100009_fg game.C_100146_bf.field_105128_n
		// @03: ifnonnull @07
		// @06: return
		// @07: bipush 90 (0x5A)
		// @09: getstatic game.C_100009_fg game.C_100146_bf.field_105128_n
		// @0C: invokestatic game.C_100178_cg.func_105676_a(byte, java.awt.Canvas)void
		// @0F: getstatic game.C_100009_fg game.C_100146_bf.field_105128_n
		// @12: getstatic game.C_100201_qj game.C_100178_cg.field_105692_a
		// @15: bipush 68 (0x44)
		// @17: invokevirtual game.C_100009_fg.func_103652_a(game.C_100201_qj, int)void
		// @1A: aconst_null
		// @1B: putstatic game.C_100009_fg game.C_100146_bf.field_105128_n
		// @1E: getstatic game.C_100003_ga game.C_100100_i.field_102024_cc
		// @21: ifnull @30
		// @24: getstatic game.C_100003_ga game.C_100100_i.field_102024_cc
		// @27: bipush 89 (0x59)
		// @29: invokevirtual game.C_100003_ga.func_103511_c(byte)void
		// @2C: goto @30
		// @2F: athrow
		// @30: getstatic java.awt.Canvas game.C_100034_gi.field_104033_a
		// @33: invokevirtual java.awt.Canvas.requestFocus()void
		// @36: iload_0
		// @37: bipush 12 (0x0C)
		// @39: if_icmpeq @45
		// @3C: bipush -28 (0xE4)
		// @3E: invokestatic game.C_100123_uc.func_104916_a(int)void
		// @41: goto @45
		// @44: athrow
		// @45: goto @69
		// @48: astore_1
		// @49: aload_1
		// @4A: new java.lang.StringBuilder
		// @4D: dup
		// @4E: invokespecial java.lang.StringBuilder.<init>()void
		// @51: getstatic java.lang.String[] game.C_100123_uc.field_104926_z
		// @54: iconst_0
		// @55: aaload
		// @56: invokevirtual java.lang.StringBuilder.append(java.lang.String)java.lang.StringBuilder
		// @59: iload_0
		// @5A: invokevirtual java.lang.StringBuilder.append(int)java.lang.StringBuilder
		// @5D: bipush 41 (0x29)
		// @5F: invokevirtual java.lang.StringBuilder.append(char)java.lang.StringBuilder
		// @62: invokevirtual java.lang.StringBuilder.toString()java.lang.String
		// @65: invokestatic game.C_100181_cf.func_105695_a(java.lang.Throwable, java.lang.String)game.C_100170_cm
		// @68: athrow
		// @69: return
	}
	
	public static void func_104916_a(int arg0)
	{
		// @00: iload_0
		// @01: bipush -25 (0xE7)
		// @03: if_icmple @10
		// @06: iconst_0
		// @07: bipush 54 (0x36)
		// @09: invokestatic game.C_100123_uc.func_104915_a(boolean, byte)void
		// @0C: goto @10
		// @0F: athrow
		// @10: aconst_null
		// @11: putstatic java.lang.String game.C_100123_uc.field_104921_d
		// @14: aconst_null
		// @15: putstatic java.lang.String game.C_100123_uc.field_104922_e
		// @18: aconst_null
		// @19: putstatic java.lang.String game.C_100123_uc.field_104924_c
		// @1C: aconst_null
		// @1D: putstatic game.C_100302_ka[] game.C_100123_uc.field_104925_a
		// @20: aconst_null
		// @21: putstatic java.lang.String game.C_100123_uc.field_104919_f
		// @24: aconst_null
		// @25: putstatic game.C_100302_ka game.C_100123_uc.field_104923_b
		// @28: goto @4C
		// @2B: astore_1
		// @2C: aload_1
		// @2D: new java.lang.StringBuilder
		// @30: dup
		// @31: invokespecial java.lang.StringBuilder.<init>()void
		// @34: getstatic java.lang.String[] game.C_100123_uc.field_104926_z
		// @37: iconst_2
		// @38: aaload
		// @39: invokevirtual java.lang.StringBuilder.append(java.lang.String)java.lang.StringBuilder
		// @3C: iload_0
		// @3D: invokevirtual java.lang.StringBuilder.append(int)java.lang.StringBuilder
		// @40: bipush 41 (0x29)
		// @42: invokevirtual java.lang.StringBuilder.append(char)java.lang.StringBuilder
		// @45: invokevirtual java.lang.StringBuilder.toString()java.lang.String
		// @48: invokestatic game.C_100181_cf.func_105695_a(java.lang.Throwable, java.lang.String)game.C_100170_cm
		// @4B: athrow
		// @4C: return
	}
	
	static final void func_104915_a(boolean arg0, byte arg1)
	{
		// @00: iload_0
		// @01: iconst_0
		// @02: invokestatic game.C_100149_bi.func_105151_a(boolean, int)void
		// @05: iload_1
		// @06: bipush -94 (0xA2)
		// @08: if_icmple @15
		// @0B: iconst_1
		// @0C: bipush 111 (0x6F)
		// @0E: invokestatic game.C_100123_uc.func_104915_a(boolean, byte)void
		// @11: goto @15
		// @14: athrow
		// @15: aconst_null
		// @16: getstatic java.lang.String game.C_100321_hi.field_107220_c
		// @19: if_acmpeq @29
		// @1C: sipush 500 (0x01F4)
		// @1F: getstatic java.lang.String game.C_100321_hi.field_107220_c
		// @22: invokestatic game.C_100213_ak.func_105990_a(int, java.lang.String)void
		// @25: goto @29
		// @28: athrow
		// @29: goto @56
		// @2C: astore_2
		// @2D: aload_2
		// @2E: new java.lang.StringBuilder
		// @31: dup
		// @32: invokespecial java.lang.StringBuilder.<init>()void
		// @35: getstatic java.lang.String[] game.C_100123_uc.field_104926_z
		// @38: iconst_1
		// @39: aaload
		// @3A: invokevirtual java.lang.StringBuilder.append(java.lang.String)java.lang.StringBuilder
		// @3D: iload_0
		// @3E: invokevirtual java.lang.StringBuilder.append(boolean)java.lang.StringBuilder
		// @41: bipush 44 (0x2C)
		// @43: invokevirtual java.lang.StringBuilder.append(char)java.lang.StringBuilder
		// @46: iload_1
		// @47: invokevirtual java.lang.StringBuilder.append(int)java.lang.StringBuilder
		// @4A: bipush 41 (0x29)
		// @4C: invokevirtual java.lang.StringBuilder.append(char)java.lang.StringBuilder
		// @4F: invokevirtual java.lang.StringBuilder.toString()java.lang.String
		// @52: invokestatic game.C_100181_cf.func_105695_a(java.lang.Throwable, java.lang.String)game.C_100170_cm
		// @55: athrow
		// @56: return
	}
	
	static
	{
		// @00: iconst_3
		// @01: anewarray java.lang.String
		// @04: dup
		// @05: iconst_0
		// @06: ldc "ZiUw>"
		// @08: invokestatic game.C_100123_uc.func_104918_z(java.lang.String)char[]
		// @0B: invokestatic game.C_100123_uc.func_104917_z(char[])java.lang.String
		// @0E: aastore
		// @0F: dup
		// @10: iconst_1
		// @11: ldc "ZiUu>"
		// @13: invokestatic game.C_100123_uc.func_104918_z(java.lang.String)char[]
		// @16: invokestatic game.C_100123_uc.func_104917_z(char[])java.lang.String
		// @19: aastore
		// @1A: dup
		// @1B: iconst_2
		// @1C: ldc "ZiUv>"
		// @1E: invokestatic game.C_100123_uc.func_104918_z(java.lang.String)char[]
		// @21: invokestatic game.C_100123_uc.func_104917_z(char[])java.lang.String
		// @24: aastore
		// @25: putstatic java.lang.String[] game.C_100123_uc.field_104926_z
		// @28: ldc "}o\u000b[d[*\u001aVc\\o"
		// @2A: invokestatic game.C_100123_uc.func_104918_z(java.lang.String)char[]
		// @2D: invokestatic game.C_100123_uc.func_104917_z(char[])java.lang.String
		// @30: putstatic java.lang.String game.C_100123_uc.field_104921_d
		// @33: bipush 12 (0x0C)
		// @35: anewarray game.C_100302_ka
		// @38: putstatic game.C_100302_ka[] game.C_100123_uc.field_104925_a
		// @3B: ldc "{e[Fs_e\t@6N*\u000bXwVo\t\u00186Lf\u0012W}\u000fe\u0015\u0014bGo[Yy\\~[GcF~\u001aVzJ*\u0014DbFe\u0015\u0014p]e\u0016\u0014bGo[fcCo\u0008\u0014yI*8[xK\u007f\u0018@8\u000fZ\u0017Qw\\o[Py\u000fd\u0014@6Nh\u000eGs\u000f~\u0013]e\u000fl\u0014F{\u0001"
		// @3D: invokestatic game.C_100123_uc.func_104918_z(java.lang.String)char[]
		// @40: invokestatic game.C_100123_uc.func_104917_z(char[])java.lang.String
		// @43: putstatic java.lang.String game.C_100123_uc.field_104924_c
		// @46: aconst_null
		// @47: putstatic java.lang.String game.C_100123_uc.field_104922_e
		// @4A: return
	}
	
	private static char[] func_104918_z(String arg0)
	{
		// @00: aload_0
		// @01: invokevirtual java.lang.String.toCharArray()char[]
		// @04: dup
		// @05: arraylength
		// @06: iconst_2
		// @07: if_icmpge @13
		// @0A: dup
		// @0B: iconst_0
		// @0C: dup2
		// @0D: caload
		// @0E: bipush 22 (0x16)
		// @10: ixor
		// @11: i2c
		// @12: castore
		// @13: areturn
	}
	
	private static String func_104917_z(char[] arg0)
	{
		// @00: aload_0
		// @01: dup
		// @02: arraylength
		// @03: swap
		// @04: iconst_0
		// @05: istore_1
		// @06: goto @4C
		// @09: dup
		// @0A: iload_1
		// @0B: dup2
		// @0C: caload
		// @0D: iload_1
		// @0E: iconst_5
		// @0F: irem
		// @10: tableswitch def: @44, for 0: @30, for 1: @35, for 2: @3A, for 3: @3F
		// @30: bipush 47 (0x2F)
		// @32: goto @46
		// @35: bipush 10 (0x0A)
		// @37: goto @46
		// @3A: bipush 123 (0x7B)
		// @3C: goto @46
		// @3F: bipush 52 (0x34)
		// @41: goto @46
		// @44: bipush 22 (0x16)
		// @46: ixor
		// @47: i2c
		// @48: castore
		// @49: iinc #1 +1
		// @4C: swap
		// @4D: dup_x1
		// @4E: iload_1
		// @4F: if_icmpgt @09
		// @52: new java.lang.String
		// @55: dup_x1
		// @56: swap
		// @57: invokespecial java.lang.String.<init>(char[])void
		// @5A: invokevirtual java.lang.String.intern()java.lang.String
		// @5D: areturn
	}
}
