package game;

import java.util.Hashtable;

abstract class C_100289_jl extends C_100336_im implements C_100259_ll
{
	static boolean field_102899_F;
	static boolean field_102901_L;
	C_100336_im[] field_102903_I;
	static String field_102898_E;
	static int[] field_102900_G;
	static String[] field_102904_J;
	static int field_102902_H;
	static C_100302_ka field_102897_D;
	private static final String[] field_102905_K;
	
	abstract void func_102892_i(int arg0);
	
	void func_102528_a(int arg0, int arg1, int arg2, byte arg3)
	{
		// @00: getstatic int game.SteelSentinels.field_105275_O
		// @03: istore #7
		// @05: iconst_m1
		// @06: iload_1
		// @07: iconst_m1
		// @08: ixor
		// @09: if_icmpne @2B
		// @0C: aload_0
		// @0D: getfield game.C_100326_ic game.C_100289_jl.field_102533_B
		// @10: ifnull @2B
		// @13: goto @17
		// @16: athrow
		// @17: aload_0
		// @18: getfield game.C_100326_ic game.C_100289_jl.field_102533_B
		// @1B: iconst_1
		// @1C: sipush -26568 (0x9838)
		// @1F: iload_3
		// @20: iload_2
		// @21: aload_0
		// @22: invokeinterface game.C_100326_ic.func_100362_a(boolean, int, int, int, game.C_100336_im)void
		// @27: goto @2B
		// @2A: athrow
		// @2B: iload #4
		// @2D: bipush -126 (0x82)
		// @2F: if_icmple @33
		// @32: return
		// @33: aconst_null
		// @34: aload_0
		// @35: getfield game.C_100336_im[] game.C_100289_jl.field_102903_I
		// @38: if_acmpne @3F
		// @3B: goto @86
		// @3E: athrow
		// @3F: aload_0
		// @40: getfield game.C_100336_im[] game.C_100289_jl.field_102903_I
		// @43: arraylength
		// @44: iconst_m1
		// @45: iadd
		// @46: istore #5
		// @48: iload #5
		// @4A: iflt @86
		// @4D: aload_0
		// @4E: getfield game.C_100336_im[] game.C_100289_jl.field_102903_I
		// @51: iload #5
		// @53: aaload
		// @54: astore #6
		// @56: iload #7
		// @58: ifne @C9
		// @5B: aconst_null
		// @5C: aload #6
		// @5E: if_acmpne @69
		// @61: goto @65
		// @64: athrow
		// @65: goto @7E
		// @68: athrow
		// @69: aload #6
		// @6B: iload_1
		// @6C: iload_2
		// @6D: aload_0
		// @6E: getfield int game.C_100289_jl.field_102541_w
		// @71: iadd
		// @72: iload_3
		// @73: aload_0
		// @74: getfield int game.C_100289_jl.field_102538_m
		// @77: ineg
		// @78: isub
		// @79: bipush -127 (0x81)
		// @7B: invokevirtual game.C_100336_im.func_102528_a(int, int, int, byte)void
		// @7E: iinc #5 +255
		// @81: iload #7
		// @83: ifeq @48
		// @86: goto @C9
		// @89: astore #5
		// @8B: aload #5
		// @8D: new java.lang.StringBuilder
		// @90: dup
		// @91: invokespecial java.lang.StringBuilder.<init>()void
		// @94: getstatic java.lang.String[] game.C_100289_jl.field_102905_K
		// @97: bipush 6 (0x06)
		// @99: aaload
		// @9A: invokevirtual java.lang.StringBuilder.append(java.lang.String)java.lang.StringBuilder
		// @9D: iload_1
		// @9E: invokevirtual java.lang.StringBuilder.append(int)java.lang.StringBuilder
		// @A1: bipush 44 (0x2C)
		// @A3: invokevirtual java.lang.StringBuilder.append(char)java.lang.StringBuilder
		// @A6: iload_2
		// @A7: invokevirtual java.lang.StringBuilder.append(int)java.lang.StringBuilder
		// @AA: bipush 44 (0x2C)
		// @AC: invokevirtual java.lang.StringBuilder.append(char)java.lang.StringBuilder
		// @AF: iload_3
		// @B0: invokevirtual java.lang.StringBuilder.append(int)java.lang.StringBuilder
		// @B3: bipush 44 (0x2C)
		// @B5: invokevirtual java.lang.StringBuilder.append(char)java.lang.StringBuilder
		// @B8: iload #4
		// @BA: invokevirtual java.lang.StringBuilder.append(int)java.lang.StringBuilder
		// @BD: bipush 41 (0x29)
		// @BF: invokevirtual java.lang.StringBuilder.append(char)java.lang.StringBuilder
		// @C2: invokevirtual java.lang.StringBuilder.toString()java.lang.String
		// @C5: invokestatic game.C_100181_cf.func_105695_a(java.lang.Throwable, java.lang.String)game.C_100170_cm
		// @C8: athrow
		// @C9: return
	}
	
	final int func_102527_g(int arg0)
	{
		// @00: getstatic int game.SteelSentinels.field_105275_O
		// @03: istore #7
		// @05: iconst_0
		// @06: istore_2
		// @07: aload_0
		// @08: getfield game.C_100336_im[] game.C_100289_jl.field_102903_I
		// @0B: astore_3
		// @0C: iconst_0
		// @0D: istore #4
		// @0F: iload #4
		// @11: iconst_m1
		// @12: ixor
		// @13: aload_3
		// @14: arraylength
		// @15: iconst_m1
		// @16: ixor
		// @17: if_icmple @52
		// @1A: aload_3
		// @1B: iload #4
		// @1D: aaload
		// @1E: astore #5
		// @20: iload #7
		// @22: ifne @63
		// @25: aconst_null
		// @26: aload #5
		// @28: if_acmpeq @4A
		// @2B: goto @2F
		// @2E: athrow
		// @2F: aload #5
		// @31: sipush -21742 (0xAB12)
		// @34: invokevirtual game.C_100336_im.func_102527_g(int)int
		// @37: istore #6
		// @39: iload #6
		// @3B: iconst_m1
		// @3C: ixor
		// @3D: iload_2
		// @3E: iconst_m1
		// @3F: ixor
		// @40: if_icmplt @47
		// @43: goto @4A
		// @46: athrow
		// @47: iload #6
		// @49: istore_2
		// @4A: iinc #4 +1
		// @4D: iload #7
		// @4F: ifeq @0F
		// @52: iload_1
		// @53: sipush -21742 (0xAB12)
		// @56: if_icmpeq @63
		// @59: aload_0
		// @5A: bipush 111 (0x6F)
		// @5C: invokevirtual game.C_100289_jl.func_102892_i(int)void
		// @5F: goto @63
		// @62: athrow
		// @63: iload_2
		// @64: ireturn
		// @65: astore_2
		// @66: aload_2
		// @67: new java.lang.StringBuilder
		// @6A: dup
		// @6B: invokespecial java.lang.StringBuilder.<init>()void
		// @6E: getstatic java.lang.String[] game.C_100289_jl.field_102905_K
		// @71: bipush 12 (0x0C)
		// @73: aaload
		// @74: invokevirtual java.lang.StringBuilder.append(java.lang.String)java.lang.StringBuilder
		// @77: iload_1
		// @78: invokevirtual java.lang.StringBuilder.append(int)java.lang.StringBuilder
		// @7B: bipush 41 (0x29)
		// @7D: invokevirtual java.lang.StringBuilder.append(char)java.lang.StringBuilder
		// @80: invokevirtual java.lang.StringBuilder.toString()java.lang.String
		// @83: invokestatic game.C_100181_cf.func_105695_a(java.lang.Throwable, java.lang.String)game.C_100170_cm
		// @86: athrow
	}
	
	final boolean func_102515_d(byte arg0)
	{
		// @00: iload_1
		// @01: bipush 10 (0x0A)
		// @03: if_icmpge @08
		// @06: iconst_0
		// @07: ireturn
		// @08: aconst_null
		// @09: aload_0
		// @0A: iconst_m1
		// @0B: invokespecial game.C_100289_jl.func_102886_k(int)game.C_100336_im
		// @0E: if_acmpeq @16
		// @11: iconst_1
		// @12: goto @17
		// @15: athrow
		// @16: iconst_0
		// @17: ireturn
		// @18: astore_2
		// @19: aload_2
		// @1A: new java.lang.StringBuilder
		// @1D: dup
		// @1E: invokespecial java.lang.StringBuilder.<init>()void
		// @21: getstatic java.lang.String[] game.C_100289_jl.field_102905_K
		// @24: bipush 19 (0x13)
		// @26: aaload
		// @27: invokevirtual java.lang.StringBuilder.append(java.lang.String)java.lang.StringBuilder
		// @2A: iload_1
		// @2B: invokevirtual java.lang.StringBuilder.append(int)java.lang.StringBuilder
		// @2E: bipush 41 (0x29)
		// @30: invokevirtual java.lang.StringBuilder.append(char)java.lang.StringBuilder
		// @33: invokevirtual java.lang.StringBuilder.toString()java.lang.String
		// @36: invokestatic game.C_100181_cf.func_105695_a(java.lang.Throwable, java.lang.String)game.C_100170_cm
		// @39: athrow
	}
	
	private final boolean func_102895_a(byte arg0, C_100336_im arg1)
	{
		// @00: iload_1
		// @01: bipush 104 (0x68)
		// @03: if_icmpeq @10
		// @06: bipush -7 (0xF9)
		// @08: invokestatic game.C_100289_jl.func_102890_j(int)java.lang.String
		// @0B: pop
		// @0C: goto @10
		// @0F: athrow
		// @10: aload_0
		// @11: iconst_0
		// @12: aload_2
		// @13: iconst_1
		// @14: invokespecial game.C_100289_jl.func_102896_a(int, game.C_100336_im, int)boolean
		// @17: ireturn
		// @18: astore_3
		// @19: aload_3
		// @1A: new java.lang.StringBuilder
		// @1D: dup
		// @1E: invokespecial java.lang.StringBuilder.<init>()void
		// @21: getstatic java.lang.String[] game.C_100289_jl.field_102905_K
		// @24: iconst_3
		// @25: aaload
		// @26: invokevirtual java.lang.StringBuilder.append(java.lang.String)java.lang.StringBuilder
		// @29: iload_1
		// @2A: invokevirtual java.lang.StringBuilder.append(int)java.lang.StringBuilder
		// @2D: bipush 44 (0x2C)
		// @2F: invokevirtual java.lang.StringBuilder.append(char)java.lang.StringBuilder
		// @32: aload_2
		// @33: ifnull @3F
		// @36: getstatic java.lang.String[] game.C_100289_jl.field_102905_K
		// @39: iconst_2
		// @3A: aaload
		// @3B: goto @44
		// @3E: athrow
		// @3F: getstatic java.lang.String[] game.C_100289_jl.field_102905_K
		// @42: iconst_4
		// @43: aaload
		// @44: invokevirtual java.lang.StringBuilder.append(java.lang.String)java.lang.StringBuilder
		// @47: bipush 41 (0x29)
		// @49: invokevirtual java.lang.StringBuilder.append(char)java.lang.StringBuilder
		// @4C: invokevirtual java.lang.StringBuilder.toString()java.lang.String
		// @4F: invokestatic game.C_100181_cf.func_105695_a(java.lang.Throwable, java.lang.String)game.C_100170_cm
		// @52: athrow
	}
	
	public static void func_102894_h(int arg0)
	{
		// @00: aconst_null
		// @01: putstatic java.lang.String[] game.C_100289_jl.field_102904_J
		// @04: aconst_null
		// @05: putstatic game.C_100302_ka game.C_100289_jl.field_102897_D
		// @08: aconst_null
		// @09: putstatic int[] game.C_100289_jl.field_102900_G
		// @0C: aconst_null
		// @0D: putstatic java.lang.String game.C_100289_jl.field_102898_E
		// @10: iload_0
		// @11: iconst_m1
		// @12: if_icmpeq @21
		// @15: aconst_null
		// @16: checkcast byte[]
		// @19: bipush 50 (0x32)
		// @1B: bipush -58 (0xC6)
		// @1D: invokestatic game.C_100289_jl.func_102885_a(byte[], int, int)int
		// @20: pop
		// @21: goto @46
		// @24: astore_1
		// @25: aload_1
		// @26: new java.lang.StringBuilder
		// @29: dup
		// @2A: invokespecial java.lang.StringBuilder.<init>()void
		// @2D: getstatic java.lang.String[] game.C_100289_jl.field_102905_K
		// @30: bipush 22 (0x16)
		// @32: aaload
		// @33: invokevirtual java.lang.StringBuilder.append(java.lang.String)java.lang.StringBuilder
		// @36: iload_0
		// @37: invokevirtual java.lang.StringBuilder.append(int)java.lang.StringBuilder
		// @3A: bipush 41 (0x29)
		// @3C: invokevirtual java.lang.StringBuilder.append(char)java.lang.StringBuilder
		// @3F: invokevirtual java.lang.StringBuilder.toString()java.lang.String
		// @42: invokestatic game.C_100181_cf.func_105695_a(java.lang.Throwable, java.lang.String)game.C_100170_cm
		// @45: athrow
		// @46: return
	}
	
	final StringBuilder func_102510_a(int arg0, byte arg1, StringBuilder arg2, Hashtable arg3)
	{
		// @00: aload_0
		// @01: aload #4
		// @03: iload_1
		// @04: aload_3
		// @05: bipush -76 (0xB4)
		// @07: invokevirtual game.C_100289_jl.func_102516_a(java.util.Hashtable, int, java.lang.StringBuilder, byte)boolean
		// @0A: ifeq @25
		// @0D: aload_0
		// @0E: bipush -119 (0x89)
		// @10: aload_3
		// @11: iload_1
		// @12: aload #4
		// @14: invokevirtual game.C_100289_jl.func_102518_a(byte, java.lang.StringBuilder, int, java.util.Hashtable)void
		// @17: aload_0
		// @18: aload #4
		// @1A: aload_3
		// @1B: bipush -127 (0x81)
		// @1D: iload_1
		// @1E: invokespecial game.C_100289_jl.func_102891_a(java.util.Hashtable, java.lang.StringBuilder, int, int)void
		// @21: goto @25
		// @24: athrow
		// @25: bipush 14 (0x0E)
		// @27: bipush -42 (0xD6)
		// @29: iload_2
		// @2A: isub
		// @2B: bipush 63 (0x3F)
		// @2D: idiv
		// @2E: irem
		// @2F: istore #5
		// @31: aload_3
		// @32: areturn
		// @33: astore #5
		// @35: aload #5
		// @37: new java.lang.StringBuilder
		// @3A: dup
		// @3B: invokespecial java.lang.StringBuilder.<init>()void
		// @3E: getstatic java.lang.String[] game.C_100289_jl.field_102905_K
		// @41: bipush 23 (0x17)
		// @43: aaload
		// @44: invokevirtual java.lang.StringBuilder.append(java.lang.String)java.lang.StringBuilder
		// @47: iload_1
		// @48: invokevirtual java.lang.StringBuilder.append(int)java.lang.StringBuilder
		// @4B: bipush 44 (0x2C)
		// @4D: invokevirtual java.lang.StringBuilder.append(char)java.lang.StringBuilder
		// @50: iload_2
		// @51: invokevirtual java.lang.StringBuilder.append(int)java.lang.StringBuilder
		// @54: bipush 44 (0x2C)
		// @56: invokevirtual java.lang.StringBuilder.append(char)java.lang.StringBuilder
		// @59: aload_3
		// @5A: ifnull @66
		// @5D: getstatic java.lang.String[] game.C_100289_jl.field_102905_K
		// @60: iconst_2
		// @61: aaload
		// @62: goto @6B
		// @65: athrow
		// @66: getstatic java.lang.String[] game.C_100289_jl.field_102905_K
		// @69: iconst_4
		// @6A: aaload
		// @6B: invokevirtual java.lang.StringBuilder.append(java.lang.String)java.lang.StringBuilder
		// @6E: bipush 44 (0x2C)
		// @70: invokevirtual java.lang.StringBuilder.append(char)java.lang.StringBuilder
		// @73: aload #4
		// @75: ifnull @81
		// @78: getstatic java.lang.String[] game.C_100289_jl.field_102905_K
		// @7B: iconst_2
		// @7C: aaload
		// @7D: goto @86
		// @80: athrow
		// @81: getstatic java.lang.String[] game.C_100289_jl.field_102905_K
		// @84: iconst_4
		// @85: aaload
		// @86: invokevirtual java.lang.StringBuilder.append(java.lang.String)java.lang.StringBuilder
		// @89: bipush 41 (0x29)
		// @8B: invokevirtual java.lang.StringBuilder.append(char)java.lang.StringBuilder
		// @8E: invokevirtual java.lang.StringBuilder.toString()java.lang.String
		// @91: invokestatic game.C_100181_cf.func_105695_a(java.lang.Throwable, java.lang.String)game.C_100170_cm
		// @94: athrow
	}
	
	final boolean func_102522_a(int arg0, C_100336_im arg1)
	{
		// @00: getstatic int game.SteelSentinels.field_105275_O
		// @03: istore #6
		// @05: aload_0
		// @06: getfield game.C_100336_im[] game.C_100289_jl.field_102903_I
		// @09: astore_3
		// @0A: iconst_0
		// @0B: istore #4
		// @0D: aload_3
		// @0E: arraylength
		// @0F: iconst_m1
		// @10: ixor
		// @11: iload #4
		// @13: iconst_m1
		// @14: ixor
		// @15: if_icmpge @44
		// @18: aload_3
		// @19: iload #4
		// @1B: aaload
		// @1C: astore #5
		// @1E: iload #6
		// @20: ifne @55
		// @23: aload #5
		// @25: ifnull @3C
		// @28: goto @2C
		// @2B: athrow
		// @2C: aload #5
		// @2E: iconst_1
		// @2F: aload_2
		// @30: invokevirtual game.C_100336_im.func_102522_a(int, game.C_100336_im)boolean
		// @33: ifeq @3C
		// @36: goto @3A
		// @39: athrow
		// @3A: iconst_1
		// @3B: ireturn
		// @3C: iinc #4 +1
		// @3F: iload #6
		// @41: ifeq @0D
		// @44: iload_1
		// @45: iconst_1
		// @46: if_icmpeq @55
		// @49: aload_0
		// @4A: aconst_null
		// @4B: checkcast game.C_100336_im[]
		// @4E: putfield game.C_100336_im[] game.C_100289_jl.field_102903_I
		// @51: goto @55
		// @54: athrow
		// @55: iconst_0
		// @56: ireturn
		// @57: astore_3
		// @58: aload_3
		// @59: new java.lang.StringBuilder
		// @5C: dup
		// @5D: invokespecial java.lang.StringBuilder.<init>()void
		// @60: getstatic java.lang.String[] game.C_100289_jl.field_102905_K
		// @63: bipush 8 (0x08)
		// @65: aaload
		// @66: invokevirtual java.lang.StringBuilder.append(java.lang.String)java.lang.StringBuilder
		// @69: iload_1
		// @6A: invokevirtual java.lang.StringBuilder.append(int)java.lang.StringBuilder
		// @6D: bipush 44 (0x2C)
		// @6F: invokevirtual java.lang.StringBuilder.append(char)java.lang.StringBuilder
		// @72: aload_2
		// @73: ifnull @7F
		// @76: getstatic java.lang.String[] game.C_100289_jl.field_102905_K
		// @79: iconst_2
		// @7A: aaload
		// @7B: goto @84
		// @7E: athrow
		// @7F: getstatic java.lang.String[] game.C_100289_jl.field_102905_K
		// @82: iconst_4
		// @83: aaload
		// @84: invokevirtual java.lang.StringBuilder.append(java.lang.String)java.lang.StringBuilder
		// @87: bipush 41 (0x29)
		// @89: invokevirtual java.lang.StringBuilder.append(char)java.lang.StringBuilder
		// @8C: invokevirtual java.lang.StringBuilder.toString()java.lang.String
		// @8F: invokestatic game.C_100181_cf.func_105695_a(java.lang.Throwable, java.lang.String)game.C_100170_cm
		// @92: athrow
	}
	
	final boolean func_102512_b(int arg0, C_100336_im arg1, int arg2, int arg3, int arg4, int arg5, int arg6)
	{
		// @00: getstatic int game.SteelSentinels.field_105275_O
		// @03: istore #11
		// @05: iload #4
		// @07: bipush -20 (0xEC)
		// @09: if_icmple @17
		// @0C: aconst_null
		// @0D: checkcast game.C_100302_ka
		// @10: putstatic game.C_100302_ka game.C_100289_jl.field_102897_D
		// @13: goto @17
		// @16: athrow
		// @17: aconst_null
		// @18: aload_0
		// @19: getfield game.C_100336_im[] game.C_100289_jl.field_102903_I
		// @1C: if_acmpne @21
		// @1F: iconst_0
		// @20: ireturn
		// @21: aload_0
		// @22: getfield game.C_100336_im[] game.C_100289_jl.field_102903_I
		// @25: astore #8
		// @27: iconst_0
		// @28: istore #9
		// @2A: aload #8
		// @2C: arraylength
		// @2D: iload #9
		// @2F: if_icmple @71
		// @32: aload #8
		// @34: iload #9
		// @36: aaload
		// @37: astore #10
		// @39: aload #10
		// @3B: ifnull @69
		// @3E: aload #10
		// @40: bipush 58 (0x3A)
		// @42: invokevirtual game.C_100336_im.func_102515_d(byte)boolean
		// @45: ifeq @69
		// @48: goto @4C
		// @4B: athrow
		// @4C: aload #10
		// @4E: iload_1
		// @4F: aload_2
		// @50: iload_3
		// @51: bipush -65 (0xBF)
		// @53: iload #5
		// @55: iload #6
		// @57: iload #7
		// @59: invokevirtual game.C_100336_im.func_102512_b(int, game.C_100336_im, int, int, int, int, int)boolean
		// @5C: ifne @67
		// @5F: goto @63
		// @62: athrow
		// @63: goto @69
		// @66: athrow
		// @67: iconst_1
		// @68: ireturn
		// @69: iinc #9 +1
		// @6C: iload #11
		// @6E: ifeq @2A
		// @71: iconst_0
		// @72: ireturn
		// @73: astore #8
		// @75: aload #8
		// @77: new java.lang.StringBuilder
		// @7A: dup
		// @7B: invokespecial java.lang.StringBuilder.<init>()void
		// @7E: getstatic java.lang.String[] game.C_100289_jl.field_102905_K
		// @81: bipush 21 (0x15)
		// @83: aaload
		// @84: invokevirtual java.lang.StringBuilder.append(java.lang.String)java.lang.StringBuilder
		// @87: iload_1
		// @88: invokevirtual java.lang.StringBuilder.append(int)java.lang.StringBuilder
		// @8B: bipush 44 (0x2C)
		// @8D: invokevirtual java.lang.StringBuilder.append(char)java.lang.StringBuilder
		// @90: aload_2
		// @91: ifnull @9D
		// @94: getstatic java.lang.String[] game.C_100289_jl.field_102905_K
		// @97: iconst_2
		// @98: aaload
		// @99: goto @A2
		// @9C: athrow
		// @9D: getstatic java.lang.String[] game.C_100289_jl.field_102905_K
		// @A0: iconst_4
		// @A1: aaload
		// @A2: invokevirtual java.lang.StringBuilder.append(java.lang.String)java.lang.StringBuilder
		// @A5: bipush 44 (0x2C)
		// @A7: invokevirtual java.lang.StringBuilder.append(char)java.lang.StringBuilder
		// @AA: iload_3
		// @AB: invokevirtual java.lang.StringBuilder.append(int)java.lang.StringBuilder
		// @AE: bipush 44 (0x2C)
		// @B0: invokevirtual java.lang.StringBuilder.append(char)java.lang.StringBuilder
		// @B3: iload #4
		// @B5: invokevirtual java.lang.StringBuilder.append(int)java.lang.StringBuilder
		// @B8: bipush 44 (0x2C)
		// @BA: invokevirtual java.lang.StringBuilder.append(char)java.lang.StringBuilder
		// @BD: iload #5
		// @BF: invokevirtual java.lang.StringBuilder.append(int)java.lang.StringBuilder
		// @C2: bipush 44 (0x2C)
		// @C4: invokevirtual java.lang.StringBuilder.append(char)java.lang.StringBuilder
		// @C7: iload #6
		// @C9: invokevirtual java.lang.StringBuilder.append(int)java.lang.StringBuilder
		// @CC: bipush 44 (0x2C)
		// @CE: invokevirtual java.lang.StringBuilder.append(char)java.lang.StringBuilder
		// @D1: iload #7
		// @D3: invokevirtual java.lang.StringBuilder.append(int)java.lang.StringBuilder
		// @D6: bipush 41 (0x29)
		// @D8: invokevirtual java.lang.StringBuilder.append(char)java.lang.StringBuilder
		// @DB: invokevirtual java.lang.StringBuilder.toString()java.lang.String
		// @DE: invokestatic game.C_100181_cf.func_105695_a(java.lang.Throwable, java.lang.String)game.C_100170_cm
		// @E1: athrow
	}
	
	private final boolean func_102893_b(int arg0, C_100336_im arg1)
	{
		// @00: iload_1
		// @01: iconst_1
		// @02: if_icmpeq @07
		// @05: iconst_0
		// @06: ireturn
		// @07: aload_0
		// @08: iconst_m1
		// @09: aload_2
		// @0A: iconst_1
		// @0B: invokespecial game.C_100289_jl.func_102889_b(int, game.C_100336_im, int)boolean
		// @0E: ireturn
		// @0F: astore_3
		// @10: aload_3
		// @11: new java.lang.StringBuilder
		// @14: dup
		// @15: invokespecial java.lang.StringBuilder.<init>()void
		// @18: getstatic java.lang.String[] game.C_100289_jl.field_102905_K
		// @1B: bipush 18 (0x12)
		// @1D: aaload
		// @1E: invokevirtual java.lang.StringBuilder.append(java.lang.String)java.lang.StringBuilder
		// @21: iload_1
		// @22: invokevirtual java.lang.StringBuilder.append(int)java.lang.StringBuilder
		// @25: bipush 44 (0x2C)
		// @27: invokevirtual java.lang.StringBuilder.append(char)java.lang.StringBuilder
		// @2A: aload_2
		// @2B: ifnull @37
		// @2E: getstatic java.lang.String[] game.C_100289_jl.field_102905_K
		// @31: iconst_2
		// @32: aaload
		// @33: goto @3C
		// @36: athrow
		// @37: getstatic java.lang.String[] game.C_100289_jl.field_102905_K
		// @3A: iconst_4
		// @3B: aaload
		// @3C: invokevirtual java.lang.StringBuilder.append(java.lang.String)java.lang.StringBuilder
		// @3F: bipush 41 (0x29)
		// @41: invokevirtual java.lang.StringBuilder.append(char)java.lang.StringBuilder
		// @44: invokevirtual java.lang.StringBuilder.toString()java.lang.String
		// @47: invokestatic game.C_100181_cf.func_105695_a(java.lang.Throwable, java.lang.String)game.C_100170_cm
		// @4A: athrow
	}
	
	final void func_102526_b(boolean arg0)
	{
		// @00: getstatic int game.SteelSentinels.field_105275_O
		// @03: istore #5
		// @05: aload_0
		// @06: getfield game.C_100336_im[] game.C_100289_jl.field_102903_I
		// @09: astore_2
		// @0A: iconst_0
		// @0B: istore_3
		// @0C: iload_3
		// @0D: iconst_m1
		// @0E: ixor
		// @0F: aload_2
		// @10: arraylength
		// @11: iconst_m1
		// @12: ixor
		// @13: if_icmple @3C
		// @16: aload_2
		// @17: iload_3
		// @18: aaload
		// @19: astore #4
		// @1B: iload #5
		// @1D: ifne @4B
		// @20: aconst_null
		// @21: aload #4
		// @23: if_acmpeq @34
		// @26: goto @2A
		// @29: athrow
		// @2A: aload #4
		// @2C: iconst_0
		// @2D: invokevirtual game.C_100336_im.func_102526_b(boolean)void
		// @30: goto @34
		// @33: athrow
		// @34: iinc #3 +1
		// @37: iload #5
		// @39: ifeq @0C
		// @3C: iload_1
		// @3D: ifeq @4B
		// @40: aload_0
		// @41: bipush 58 (0x3A)
		// @43: invokevirtual game.C_100289_jl.func_102515_d(byte)boolean
		// @46: pop
		// @47: goto @4B
		// @4A: athrow
		// @4B: goto @6F
		// @4E: astore_2
		// @4F: aload_2
		// @50: new java.lang.StringBuilder
		// @53: dup
		// @54: invokespecial java.lang.StringBuilder.<init>()void
		// @57: getstatic java.lang.String[] game.C_100289_jl.field_102905_K
		// @5A: iconst_0
		// @5B: aaload
		// @5C: invokevirtual java.lang.StringBuilder.append(java.lang.String)java.lang.StringBuilder
		// @5F: iload_1
		// @60: invokevirtual java.lang.StringBuilder.append(boolean)java.lang.StringBuilder
		// @63: bipush 41 (0x29)
		// @65: invokevirtual java.lang.StringBuilder.append(char)java.lang.StringBuilder
		// @68: invokevirtual java.lang.StringBuilder.toString()java.lang.String
		// @6B: invokestatic game.C_100181_cf.func_105695_a(java.lang.Throwable, java.lang.String)game.C_100170_cm
		// @6E: athrow
		// @6F: return
	}
	
	final void func_102519_a(byte arg0, int arg1, int arg2, int arg3, C_100336_im arg4, int arg5)
	{
		// @00: getstatic int game.SteelSentinels.field_105275_O
		// @03: istore #10
		// @05: aconst_null
		// @06: aload_0
		// @07: getfield game.C_100336_im[] game.C_100289_jl.field_102903_I
		// @0A: if_acmpeq @10
		// @0D: goto @11
		// @10: return
		// @11: iload_1
		// @12: bipush 122 (0x7A)
		// @14: if_icmpeq @20
		// @17: bipush -98 (0x9E)
		// @19: putstatic int game.C_100289_jl.field_102902_H
		// @1C: goto @20
		// @1F: athrow
		// @20: aload_0
		// @21: getfield game.C_100336_im[] game.C_100289_jl.field_102903_I
		// @24: astore #7
		// @26: iconst_0
		// @27: istore #8
		// @29: aload #7
		// @2B: arraylength
		// @2C: iconst_m1
		// @2D: ixor
		// @2E: iload #8
		// @30: iconst_m1
		// @31: ixor
		// @32: if_icmpge @70
		// @35: aload #7
		// @37: iload #8
		// @39: aaload
		// @3A: astore #9
		// @3C: iload #10
		// @3E: ifne @D8
		// @41: aload #9
		// @43: ifnonnull @4E
		// @46: goto @4A
		// @49: athrow
		// @4A: goto @68
		// @4D: athrow
		// @4E: aload #9
		// @50: bipush 122 (0x7A)
		// @52: iload_2
		// @53: aload_0
		// @54: getfield int game.C_100289_jl.field_102538_m
		// @57: iadd
		// @58: iload_3
		// @59: iload #4
		// @5B: aload #5
		// @5D: iload #6
		// @5F: aload_0
		// @60: getfield int game.C_100289_jl.field_102541_w
		// @63: ineg
		// @64: isub
		// @65: invokevirtual game.C_100336_im.func_102519_a(byte, int, int, int, game.C_100336_im, int)void
		// @68: iinc #8 +1
		// @6B: iload #10
		// @6D: ifeq @29
		// @70: goto @D8
		// @73: astore #7
		// @75: aload #7
		// @77: new java.lang.StringBuilder
		// @7A: dup
		// @7B: invokespecial java.lang.StringBuilder.<init>()void
		// @7E: getstatic java.lang.String[] game.C_100289_jl.field_102905_K
		// @81: bipush 14 (0x0E)
		// @83: aaload
		// @84: invokevirtual java.lang.StringBuilder.append(java.lang.String)java.lang.StringBuilder
		// @87: iload_1
		// @88: invokevirtual java.lang.StringBuilder.append(int)java.lang.StringBuilder
		// @8B: bipush 44 (0x2C)
		// @8D: invokevirtual java.lang.StringBuilder.append(char)java.lang.StringBuilder
		// @90: iload_2
		// @91: invokevirtual java.lang.StringBuilder.append(int)java.lang.StringBuilder
		// @94: bipush 44 (0x2C)
		// @96: invokevirtual java.lang.StringBuilder.append(char)java.lang.StringBuilder
		// @99: iload_3
		// @9A: invokevirtual java.lang.StringBuilder.append(int)java.lang.StringBuilder
		// @9D: bipush 44 (0x2C)
		// @9F: invokevirtual java.lang.StringBuilder.append(char)java.lang.StringBuilder
		// @A2: iload #4
		// @A4: invokevirtual java.lang.StringBuilder.append(int)java.lang.StringBuilder
		// @A7: bipush 44 (0x2C)
		// @A9: invokevirtual java.lang.StringBuilder.append(char)java.lang.StringBuilder
		// @AC: aload #5
		// @AE: ifnull @BA
		// @B1: getstatic java.lang.String[] game.C_100289_jl.field_102905_K
		// @B4: iconst_2
		// @B5: aaload
		// @B6: goto @BF
		// @B9: athrow
		// @BA: getstatic java.lang.String[] game.C_100289_jl.field_102905_K
		// @BD: iconst_4
		// @BE: aaload
		// @BF: invokevirtual java.lang.StringBuilder.append(java.lang.String)java.lang.StringBuilder
		// @C2: bipush 44 (0x2C)
		// @C4: invokevirtual java.lang.StringBuilder.append(char)java.lang.StringBuilder
		// @C7: iload #6
		// @C9: invokevirtual java.lang.StringBuilder.append(int)java.lang.StringBuilder
		// @CC: bipush 41 (0x29)
		// @CE: invokevirtual java.lang.StringBuilder.append(char)java.lang.StringBuilder
		// @D1: invokevirtual java.lang.StringBuilder.toString()java.lang.String
		// @D4: invokestatic game.C_100181_cf.func_105695_a(java.lang.Throwable, java.lang.String)game.C_100170_cm
		// @D7: athrow
		// @D8: return
	}
	
	static final int func_102885_a(byte[] arg0, int arg1, int arg2)
	{
		// @00: iload_1
		// @01: ifeq @0D
		// @04: bipush 35 (0x23)
		// @06: invokestatic game.C_100289_jl.func_102894_h(int)void
		// @09: goto @0D
		// @0C: athrow
		// @0D: aload_0
		// @0E: bipush 16 (0x10)
		// @10: iconst_0
		// @11: iload_2
		// @12: invokestatic game.C_100056_de.func_103179_a(byte[], byte, int, int)int
		// @15: ireturn
		// @16: astore_3
		// @17: aload_3
		// @18: new java.lang.StringBuilder
		// @1B: dup
		// @1C: invokespecial java.lang.StringBuilder.<init>()void
		// @1F: getstatic java.lang.String[] game.C_100289_jl.field_102905_K
		// @22: bipush 9 (0x09)
		// @24: aaload
		// @25: invokevirtual java.lang.StringBuilder.append(java.lang.String)java.lang.StringBuilder
		// @28: aload_0
		// @29: ifnull @35
		// @2C: getstatic java.lang.String[] game.C_100289_jl.field_102905_K
		// @2F: iconst_2
		// @30: aaload
		// @31: goto @3A
		// @34: athrow
		// @35: getstatic java.lang.String[] game.C_100289_jl.field_102905_K
		// @38: iconst_4
		// @39: aaload
		// @3A: invokevirtual java.lang.StringBuilder.append(java.lang.String)java.lang.StringBuilder
		// @3D: bipush 44 (0x2C)
		// @3F: invokevirtual java.lang.StringBuilder.append(char)java.lang.StringBuilder
		// @42: iload_1
		// @43: invokevirtual java.lang.StringBuilder.append(int)java.lang.StringBuilder
		// @46: bipush 44 (0x2C)
		// @48: invokevirtual java.lang.StringBuilder.append(char)java.lang.StringBuilder
		// @4B: iload_2
		// @4C: invokevirtual java.lang.StringBuilder.append(int)java.lang.StringBuilder
		// @4F: bipush 41 (0x29)
		// @51: invokevirtual java.lang.StringBuilder.append(char)java.lang.StringBuilder
		// @54: invokevirtual java.lang.StringBuilder.toString()java.lang.String
		// @57: invokestatic game.C_100181_cf.func_105695_a(java.lang.Throwable, java.lang.String)game.C_100170_cm
		// @5A: athrow
	}
	
	static final String func_102890_j(int arg0)
	{
		// @00: bipush 55 (0x37)
		// @02: bipush 7 (0x07)
		// @04: iload_0
		// @05: isub
		// @06: bipush 41 (0x29)
		// @08: idiv
		// @09: idiv
		// @0A: istore_1
		// @0B: getstatic game.C_100278_nd game.C_100288_jn.field_106839_f
		// @0E: sipush 9692 (0x25DC)
		// @11: invokevirtual game.C_100278_nd.func_101164_f(int)java.lang.String
		// @14: areturn
		// @15: astore_1
		// @16: aload_1
		// @17: new java.lang.StringBuilder
		// @1A: dup
		// @1B: invokespecial java.lang.StringBuilder.<init>()void
		// @1E: getstatic java.lang.String[] game.C_100289_jl.field_102905_K
		// @21: bipush 13 (0x0D)
		// @23: aaload
		// @24: invokevirtual java.lang.StringBuilder.append(java.lang.String)java.lang.StringBuilder
		// @27: iload_0
		// @28: invokevirtual java.lang.StringBuilder.append(int)java.lang.StringBuilder
		// @2B: bipush 41 (0x29)
		// @2D: invokevirtual java.lang.StringBuilder.append(char)java.lang.StringBuilder
		// @30: invokevirtual java.lang.StringBuilder.toString()java.lang.String
		// @33: invokestatic game.C_100181_cf.func_105695_a(java.lang.Throwable, java.lang.String)game.C_100170_cm
		// @36: athrow
	}
	
	final boolean func_102506_a(char arg0, int arg1, int arg2, C_100336_im arg3)
	{
		// @00: getstatic int game.SteelSentinels.field_105275_O
		// @03: istore #8
		// @05: aconst_null
		// @06: aload_0
		// @07: getfield game.C_100336_im[] game.C_100289_jl.field_102903_I
		// @0A: if_acmpne @0F
		// @0D: iconst_0
		// @0E: ireturn
		// @0F: aload_0
		// @10: getfield game.C_100336_im[] game.C_100289_jl.field_102903_I
		// @13: astore #5
		// @15: iconst_0
		// @16: istore #6
		// @18: aload #5
		// @1A: arraylength
		// @1B: iconst_m1
		// @1C: ixor
		// @1D: iload #6
		// @1F: iconst_m1
		// @20: ixor
		// @21: if_icmpge @65
		// @24: aload #5
		// @26: iload #6
		// @28: aaload
		// @29: astore #7
		// @2B: iload #8
		// @2D: ifne @77
		// @30: aconst_null
		// @31: aload #7
		// @33: if_acmpeq @5D
		// @36: goto @3A
		// @39: athrow
		// @3A: aload #7
		// @3C: bipush 50 (0x32)
		// @3E: invokevirtual game.C_100336_im.func_102515_d(byte)boolean
		// @41: ifeq @5D
		// @44: goto @48
		// @47: athrow
		// @48: aload #7
		// @4A: iload_1
		// @4B: iload_2
		// @4C: sipush 22545 (0x5811)
		// @4F: aload #4
		// @51: invokevirtual game.C_100336_im.func_102506_a(char, int, int, game.C_100336_im)boolean
		// @54: ifeq @5D
		// @57: goto @5B
		// @5A: athrow
		// @5B: iconst_1
		// @5C: ireturn
		// @5D: iinc #6 +1
		// @60: iload #8
		// @62: ifeq @18
		// @65: iload_3
		// @66: sipush 22545 (0x5811)
		// @69: if_icmpeq @77
		// @6C: aload_0
		// @6D: bipush 14 (0x0E)
		// @6F: invokevirtual game.C_100289_jl.func_102515_d(byte)boolean
		// @72: pop
		// @73: goto @77
		// @76: athrow
		// @77: iload_2
		// @78: istore #5
		// @7A: bipush 80 (0x50)
		// @7C: iload #5
		// @7E: if_icmpne @A6
		// @81: goto @85
		// @84: athrow
		// @85: getstatic boolean[] game.C_100309_lk.field_103258_hb
		// @88: bipush 81 (0x51)
		// @8A: baload
		// @8B: ifne @9A
		// @8E: aload_0
		// @8F: bipush 104 (0x68)
		// @91: aload #4
		// @93: invokespecial game.C_100289_jl.func_102895_a(byte, game.C_100336_im)boolean
		// @96: goto @A5
		// @99: athrow
		// @9A: aload_0
		// @9B: iload_3
		// @9C: sipush 22544 (0x5810)
		// @9F: ixor
		// @A0: aload #4
		// @A2: invokespecial game.C_100289_jl.func_102893_b(int, game.C_100336_im)boolean
		// @A5: ireturn
		// @A6: iconst_0
		// @A7: ireturn
		// @A8: astore #5
		// @AA: aload #5
		// @AC: new java.lang.StringBuilder
		// @AF: dup
		// @B0: invokespecial java.lang.StringBuilder.<init>()void
		// @B3: getstatic java.lang.String[] game.C_100289_jl.field_102905_K
		// @B6: bipush 15 (0x0F)
		// @B8: aaload
		// @B9: invokevirtual java.lang.StringBuilder.append(java.lang.String)java.lang.StringBuilder
		// @BC: iload_1
		// @BD: invokevirtual java.lang.StringBuilder.append(char)java.lang.StringBuilder
		// @C0: bipush 44 (0x2C)
		// @C2: invokevirtual java.lang.StringBuilder.append(char)java.lang.StringBuilder
		// @C5: iload_2
		// @C6: invokevirtual java.lang.StringBuilder.append(int)java.lang.StringBuilder
		// @C9: bipush 44 (0x2C)
		// @CB: invokevirtual java.lang.StringBuilder.append(char)java.lang.StringBuilder
		// @CE: iload_3
		// @CF: invokevirtual java.lang.StringBuilder.append(int)java.lang.StringBuilder
		// @D2: bipush 44 (0x2C)
		// @D4: invokevirtual java.lang.StringBuilder.append(char)java.lang.StringBuilder
		// @D7: aload #4
		// @D9: ifnull @E5
		// @DC: getstatic java.lang.String[] game.C_100289_jl.field_102905_K
		// @DF: iconst_2
		// @E0: aaload
		// @E1: goto @EA
		// @E4: athrow
		// @E5: getstatic java.lang.String[] game.C_100289_jl.field_102905_K
		// @E8: iconst_4
		// @E9: aaload
		// @EA: invokevirtual java.lang.StringBuilder.append(java.lang.String)java.lang.StringBuilder
		// @ED: bipush 41 (0x29)
		// @EF: invokevirtual java.lang.StringBuilder.append(char)java.lang.StringBuilder
		// @F2: invokevirtual java.lang.StringBuilder.toString()java.lang.String
		// @F5: invokestatic game.C_100181_cf.func_105695_a(java.lang.Throwable, java.lang.String)game.C_100170_cm
		// @F8: athrow
	}
	
	final boolean func_102520_a(int arg0, C_100336_im arg1, int arg2, int arg3, int arg4, int arg5, int arg6)
	{
		// @00: getstatic int game.SteelSentinels.field_105275_O
		// @03: istore #12
		// @05: bipush 105 (0x69)
		// @07: bipush 32 (0x20)
		// @09: iload_3
		// @0A: isub
		// @0B: bipush 52 (0x34)
		// @0D: idiv
		// @0E: irem
		// @0F: istore #8
		// @11: aload_0
		// @12: getfield game.C_100336_im[] game.C_100289_jl.field_102903_I
		// @15: ifnonnull @1A
		// @18: iconst_0
		// @19: ireturn
		// @1A: aload_0
		// @1B: getfield game.C_100336_im[] game.C_100289_jl.field_102903_I
		// @1E: astore #9
		// @20: iconst_0
		// @21: istore #10
		// @23: iload #10
		// @25: aload #9
		// @27: arraylength
		// @28: if_icmpge @64
		// @2B: aload #9
		// @2D: iload #10
		// @2F: aaload
		// @30: astore #11
		// @32: aconst_null
		// @33: aload #11
		// @35: if_acmpeq @5C
		// @38: aload #11
		// @3A: iload_1
		// @3B: aload_2
		// @3C: bipush -92 (0xA4)
		// @3E: iload #4
		// @40: aload_0
		// @41: getfield int game.C_100289_jl.field_102541_w
		// @44: iload #5
		// @46: iadd
		// @47: aload_0
		// @48: getfield int game.C_100289_jl.field_102538_m
		// @4B: iload #6
		// @4D: iadd
		// @4E: iload #7
		// @50: invokevirtual game.C_100336_im.func_102520_a(int, game.C_100336_im, int, int, int, int, int)boolean
		// @53: ifeq @5C
		// @56: goto @5A
		// @59: athrow
		// @5A: iconst_1
		// @5B: ireturn
		// @5C: iinc #10 +1
		// @5F: iload #12
		// @61: ifeq @23
		// @64: iconst_0
		// @65: ireturn
		// @66: astore #8
		// @68: aload #8
		// @6A: new java.lang.StringBuilder
		// @6D: dup
		// @6E: invokespecial java.lang.StringBuilder.<init>()void
		// @71: getstatic java.lang.String[] game.C_100289_jl.field_102905_K
		// @74: bipush 11 (0x0B)
		// @76: aaload
		// @77: invokevirtual java.lang.StringBuilder.append(java.lang.String)java.lang.StringBuilder
		// @7A: iload_1
		// @7B: invokevirtual java.lang.StringBuilder.append(int)java.lang.StringBuilder
		// @7E: bipush 44 (0x2C)
		// @80: invokevirtual java.lang.StringBuilder.append(char)java.lang.StringBuilder
		// @83: aload_2
		// @84: ifnull @90
		// @87: getstatic java.lang.String[] game.C_100289_jl.field_102905_K
		// @8A: iconst_2
		// @8B: aaload
		// @8C: goto @95
		// @8F: athrow
		// @90: getstatic java.lang.String[] game.C_100289_jl.field_102905_K
		// @93: iconst_4
		// @94: aaload
		// @95: invokevirtual java.lang.StringBuilder.append(java.lang.String)java.lang.StringBuilder
		// @98: bipush 44 (0x2C)
		// @9A: invokevirtual java.lang.StringBuilder.append(char)java.lang.StringBuilder
		// @9D: iload_3
		// @9E: invokevirtual java.lang.StringBuilder.append(int)java.lang.StringBuilder
		// @A1: bipush 44 (0x2C)
		// @A3: invokevirtual java.lang.StringBuilder.append(char)java.lang.StringBuilder
		// @A6: iload #4
		// @A8: invokevirtual java.lang.StringBuilder.append(int)java.lang.StringBuilder
		// @AB: bipush 44 (0x2C)
		// @AD: invokevirtual java.lang.StringBuilder.append(char)java.lang.StringBuilder
		// @B0: iload #5
		// @B2: invokevirtual java.lang.StringBuilder.append(int)java.lang.StringBuilder
		// @B5: bipush 44 (0x2C)
		// @B7: invokevirtual java.lang.StringBuilder.append(char)java.lang.StringBuilder
		// @BA: iload #6
		// @BC: invokevirtual java.lang.StringBuilder.append(int)java.lang.StringBuilder
		// @BF: bipush 44 (0x2C)
		// @C1: invokevirtual java.lang.StringBuilder.append(char)java.lang.StringBuilder
		// @C4: iload #7
		// @C6: invokevirtual java.lang.StringBuilder.append(int)java.lang.StringBuilder
		// @C9: bipush 41 (0x29)
		// @CB: invokevirtual java.lang.StringBuilder.append(char)java.lang.StringBuilder
		// @CE: invokevirtual java.lang.StringBuilder.toString()java.lang.String
		// @D1: invokestatic game.C_100181_cf.func_105695_a(java.lang.Throwable, java.lang.String)game.C_100170_cm
		// @D4: athrow
	}
	
	C_100289_jl(int arg0, int arg1, int arg2, int arg3, C_100326_ic arg4)
	{
		// @0: aload_0
		// @1: iload_1
		// @2: iload_2
		// @3: iload_3
		// @4: iload #4
		// @6: aload #5
		// @8: aconst_null
		// @9: invokespecial game.C_100336_im.<init>(int, int, int, int, game.C_100326_ic, game.C_100337_in)void
		// @C: return
	}
	
	void func_102513_a(C_100336_im arg0, int arg1, int arg2, int arg3)
	{
		// @00: getstatic int game.SteelSentinels.field_105275_O
		// @03: istore #8
		// @05: aload_0
		// @06: aload_1
		// @07: iload_2
		// @08: iload_3
		// @09: iload #4
		// @0B: invokespecial game.C_100336_im.func_102513_a(game.C_100336_im, int, int, int)void
		// @0E: aload_0
		// @0F: getfield game.C_100336_im[] game.C_100289_jl.field_102903_I
		// @12: ifnull @18
		// @15: goto @19
		// @18: return
		// @19: aload_0
		// @1A: getfield game.C_100336_im[] game.C_100289_jl.field_102903_I
		// @1D: astore #5
		// @1F: iconst_0
		// @20: istore #6
		// @22: aload #5
		// @24: arraylength
		// @25: iconst_m1
		// @26: ixor
		// @27: iload #6
		// @29: iconst_m1
		// @2A: ixor
		// @2B: if_icmpge @65
		// @2E: aload #5
		// @30: iload #6
		// @32: aaload
		// @33: astore #7
		// @35: iload #8
		// @37: ifne @B8
		// @3A: aload #7
		// @3C: ifnonnull @47
		// @3F: goto @43
		// @42: athrow
		// @43: goto @5D
		// @46: athrow
		// @47: aload #7
		// @49: aload_1
		// @4A: iload_2
		// @4B: aload_0
		// @4C: getfield int game.C_100289_jl.field_102541_w
		// @4F: ineg
		// @50: isub
		// @51: iconst_2
		// @52: iload #4
		// @54: aload_0
		// @55: getfield int game.C_100289_jl.field_102538_m
		// @58: ineg
		// @59: isub
		// @5A: invokevirtual game.C_100336_im.func_102513_a(game.C_100336_im, int, int, int)void
		// @5D: iinc #6 +1
		// @60: iload #8
		// @62: ifeq @22
		// @65: goto @B8
		// @68: astore #5
		// @6A: aload #5
		// @6C: new java.lang.StringBuilder
		// @6F: dup
		// @70: invokespecial java.lang.StringBuilder.<init>()void
		// @73: getstatic java.lang.String[] game.C_100289_jl.field_102905_K
		// @76: iconst_5
		// @77: aaload
		// @78: invokevirtual java.lang.StringBuilder.append(java.lang.String)java.lang.StringBuilder
		// @7B: aload_1
		// @7C: ifnull @88
		// @7F: getstatic java.lang.String[] game.C_100289_jl.field_102905_K
		// @82: iconst_2
		// @83: aaload
		// @84: goto @8D
		// @87: athrow
		// @88: getstatic java.lang.String[] game.C_100289_jl.field_102905_K
		// @8B: iconst_4
		// @8C: aaload
		// @8D: invokevirtual java.lang.StringBuilder.append(java.lang.String)java.lang.StringBuilder
		// @90: bipush 44 (0x2C)
		// @92: invokevirtual java.lang.StringBuilder.append(char)java.lang.StringBuilder
		// @95: iload_2
		// @96: invokevirtual java.lang.StringBuilder.append(int)java.lang.StringBuilder
		// @99: bipush 44 (0x2C)
		// @9B: invokevirtual java.lang.StringBuilder.append(char)java.lang.StringBuilder
		// @9E: iload_3
		// @9F: invokevirtual java.lang.StringBuilder.append(int)java.lang.StringBuilder
		// @A2: bipush 44 (0x2C)
		// @A4: invokevirtual java.lang.StringBuilder.append(char)java.lang.StringBuilder
		// @A7: iload #4
		// @A9: invokevirtual java.lang.StringBuilder.append(int)java.lang.StringBuilder
		// @AC: bipush 41 (0x29)
		// @AE: invokevirtual java.lang.StringBuilder.append(char)java.lang.StringBuilder
		// @B1: invokevirtual java.lang.StringBuilder.toString()java.lang.String
		// @B4: invokestatic game.C_100181_cf.func_105695_a(java.lang.Throwable, java.lang.String)game.C_100170_cm
		// @B7: athrow
		// @B8: return
	}
	
	private final void func_102891_a(Hashtable arg0, StringBuilder arg1, int arg2, int arg3)
	{
		// @00: getstatic int game.SteelSentinels.field_105275_O
		// @03: istore #9
		// @05: aload_0
		// @06: getfield game.C_100336_im[] game.C_100289_jl.field_102903_I
		// @09: ifnull @0F
		// @0C: goto @10
		// @0F: return
		// @10: iload_3
		// @11: bipush -121 (0x87)
		// @13: if_icmplt @1E
		// @16: iconst_1
		// @17: putstatic boolean game.C_100289_jl.field_102899_F
		// @1A: goto @1E
		// @1D: athrow
		// @1E: aload_0
		// @1F: getfield game.C_100336_im[] game.C_100289_jl.field_102903_I
		// @22: astore #5
		// @24: iconst_0
		// @25: istore #6
		// @27: iload #6
		// @29: aload #5
		// @2B: arraylength
		// @2C: if_icmpge @92
		// @2F: aload #5
		// @31: iload #6
		// @33: aaload
		// @34: astore #7
		// @36: aload_2
		// @37: bipush 10 (0x0A)
		// @39: invokevirtual java.lang.StringBuilder.append(char)java.lang.StringBuilder
		// @3C: pop
		// @3D: iload #9
		// @3F: ifne @F7
		// @42: iconst_0
		// @43: istore #8
		// @45: iload #8
		// @47: iload #4
		// @49: if_icmpgt @64
		// @4C: aload_2
		// @4D: bipush 32 (0x20)
		// @4F: invokevirtual java.lang.StringBuilder.append(char)java.lang.StringBuilder
		// @52: pop
		// @53: iinc #8 +1
		// @56: iload #9
		// @58: ifne @7C
		// @5B: iload #9
		// @5D: ifeq @45
		// @60: goto @64
		// @63: athrow
		// @64: aload #7
		// @66: ifnonnull @7C
		// @69: aload_2
		// @6A: getstatic java.lang.String[] game.C_100289_jl.field_102905_K
		// @6D: iconst_4
		// @6E: aaload
		// @6F: invokevirtual java.lang.StringBuilder.append(java.lang.String)java.lang.StringBuilder
		// @72: pop
		// @73: iload #9
		// @75: ifeq @8A
		// @78: goto @7C
		// @7B: athrow
		// @7C: aload #7
		// @7E: iconst_1
		// @7F: iload #4
		// @81: iadd
		// @82: bipush -114 (0x8E)
		// @84: aload_2
		// @85: aload_1
		// @86: invokevirtual game.C_100336_im.func_102510_a(int, byte, java.lang.StringBuilder, java.util.Hashtable)java.lang.StringBuilder
		// @89: pop
		// @8A: iinc #6 +1
		// @8D: iload #9
		// @8F: ifeq @27
		// @92: goto @F7
		// @95: astore #5
		// @97: aload #5
		// @99: new java.lang.StringBuilder
		// @9C: dup
		// @9D: invokespecial java.lang.StringBuilder.<init>()void
		// @A0: getstatic java.lang.String[] game.C_100289_jl.field_102905_K
		// @A3: bipush 20 (0x14)
		// @A5: aaload
		// @A6: invokevirtual java.lang.StringBuilder.append(java.lang.String)java.lang.StringBuilder
		// @A9: aload_1
		// @AA: ifnull @B6
		// @AD: getstatic java.lang.String[] game.C_100289_jl.field_102905_K
		// @B0: iconst_2
		// @B1: aaload
		// @B2: goto @BB
		// @B5: athrow
		// @B6: getstatic java.lang.String[] game.C_100289_jl.field_102905_K
		// @B9: iconst_4
		// @BA: aaload
		// @BB: invokevirtual java.lang.StringBuilder.append(java.lang.String)java.lang.StringBuilder
		// @BE: bipush 44 (0x2C)
		// @C0: invokevirtual java.lang.StringBuilder.append(char)java.lang.StringBuilder
		// @C3: aload_2
		// @C4: ifnull @D0
		// @C7: getstatic java.lang.String[] game.C_100289_jl.field_102905_K
		// @CA: iconst_2
		// @CB: aaload
		// @CC: goto @D5
		// @CF: athrow
		// @D0: getstatic java.lang.String[] game.C_100289_jl.field_102905_K
		// @D3: iconst_4
		// @D4: aaload
		// @D5: invokevirtual java.lang.StringBuilder.append(java.lang.String)java.lang.StringBuilder
		// @D8: bipush 44 (0x2C)
		// @DA: invokevirtual java.lang.StringBuilder.append(char)java.lang.StringBuilder
		// @DD: iload_3
		// @DE: invokevirtual java.lang.StringBuilder.append(int)java.lang.StringBuilder
		// @E1: bipush 44 (0x2C)
		// @E3: invokevirtual java.lang.StringBuilder.append(char)java.lang.StringBuilder
		// @E6: iload #4
		// @E8: invokevirtual java.lang.StringBuilder.append(int)java.lang.StringBuilder
		// @EB: bipush 41 (0x29)
		// @ED: invokevirtual java.lang.StringBuilder.append(char)java.lang.StringBuilder
		// @F0: invokevirtual java.lang.StringBuilder.toString()java.lang.String
		// @F3: invokestatic game.C_100181_cf.func_105695_a(java.lang.Throwable, java.lang.String)game.C_100170_cm
		// @F6: athrow
		// @F7: return
	}
	
	final String func_102525_c(byte arg0)
	{
		// @00: getstatic int game.SteelSentinels.field_105275_O
		// @03: istore #6
		// @05: aload_0
		// @06: getfield game.C_100336_im[] game.C_100289_jl.field_102903_I
		// @09: ifnonnull @0E
		// @0C: aconst_null
		// @0D: areturn
		// @0E: aload_0
		// @0F: getfield game.C_100336_im[] game.C_100289_jl.field_102903_I
		// @12: astore_2
		// @13: iconst_0
		// @14: istore_3
		// @15: aload_2
		// @16: arraylength
		// @17: iload_3
		// @18: if_icmple @47
		// @1B: aload_2
		// @1C: iload_3
		// @1D: aaload
		// @1E: astore #4
		// @20: iload #6
		// @22: ifne @60
		// @25: aload #4
		// @27: ifnull @3F
		// @2A: goto @2E
		// @2D: athrow
		// @2E: aload #4
		// @30: bipush 72 (0x48)
		// @32: invokevirtual game.C_100336_im.func_102525_c(byte)java.lang.String
		// @35: astore #5
		// @37: aload #5
		// @39: ifnull @3F
		// @3C: aload #5
		// @3E: areturn
		// @3F: iinc #3 +1
		// @42: iload #6
		// @44: ifeq @15
		// @47: iload_1
		// @48: bipush 34 (0x22)
		// @4A: if_icmpge @60
		// @4D: aload_0
		// @4E: bipush 78 (0x4E)
		// @50: bipush -41 (0xD7)
		// @52: bipush -17 (0xEF)
		// @54: aconst_null
		// @55: checkcast game.C_100336_im
		// @58: invokevirtual game.C_100289_jl.func_102506_a(char, int, int, game.C_100336_im)boolean
		// @5B: pop
		// @5C: goto @60
		// @5F: athrow
		// @60: aconst_null
		// @61: areturn
		// @62: astore_2
		// @63: aload_2
		// @64: new java.lang.StringBuilder
		// @67: dup
		// @68: invokespecial java.lang.StringBuilder.<init>()void
		// @6B: getstatic java.lang.String[] game.C_100289_jl.field_102905_K
		// @6E: iconst_1
		// @6F: aaload
		// @70: invokevirtual java.lang.StringBuilder.append(java.lang.String)java.lang.StringBuilder
		// @73: iload_1
		// @74: invokevirtual java.lang.StringBuilder.append(int)java.lang.StringBuilder
		// @77: bipush 41 (0x29)
		// @79: invokevirtual java.lang.StringBuilder.append(char)java.lang.StringBuilder
		// @7C: invokevirtual java.lang.StringBuilder.toString()java.lang.String
		// @7F: invokestatic game.C_100181_cf.func_105695_a(java.lang.Throwable, java.lang.String)game.C_100170_cm
		// @82: athrow
	}
	
	private final boolean func_102889_b(int arg0, C_100336_im arg1, int arg2)
	{
		// @00: getstatic int game.SteelSentinels.field_105275_O
		// @03: istore #7
		// @05: aconst_null
		// @06: aload_0
		// @07: getfield game.C_100336_im[] game.C_100289_jl.field_102903_I
		// @0A: if_acmpne @0F
		// @0D: iconst_0
		// @0E: ireturn
		// @0F: iload_1
		// @10: iconst_m1
		// @11: if_icmpeq @23
		// @14: aload_0
		// @15: bipush -70 (0xBA)
		// @17: aconst_null
		// @18: checkcast game.C_100336_im
		// @1B: invokespecial game.C_100289_jl.func_102893_b(int, game.C_100336_im)boolean
		// @1E: pop
		// @1F: goto @23
		// @22: athrow
		// @23: aload_0
		// @24: getfield game.C_100336_im[] game.C_100289_jl.field_102903_I
		// @27: arraylength
		// @28: iconst_1
		// @29: isub
		// @2A: istore #4
		// @2C: iconst_m1
		// @2D: iload #4
		// @2F: iconst_m1
		// @30: ixor
		// @31: if_icmplt @9D
		// @34: aload_0
		// @35: getfield game.C_100336_im[] game.C_100289_jl.field_102903_I
		// @38: iload #4
		// @3A: aaload
		// @3B: astore #5
		// @3D: aload #5
		// @3F: ifnull @95
		// @42: aload #5
		// @44: bipush 76 (0x4C)
		// @46: invokevirtual game.C_100336_im.func_102515_d(byte)boolean
		// @49: ifeq @95
		// @4C: iload #4
		// @4E: iload_3
		// @4F: isub
		// @50: istore #4
		// @52: iload #4
		// @54: iconst_m1
		// @55: ixor
		// @56: iconst_m1
		// @57: if_icmpgt @95
		// @5A: aload_0
		// @5B: getfield game.C_100336_im[] game.C_100289_jl.field_102903_I
		// @5E: iload #4
		// @60: aaload
		// @61: astore #6
		// @63: aload #6
		// @65: iload #7
		// @67: ifne @3F
		// @6A: ifnonnull @76
		// @6D: iload #7
		// @6F: ifeq @8A
		// @72: goto @76
		// @75: athrow
		// @76: aload #6
		// @78: iconst_1
		// @79: aload_2
		// @7A: invokevirtual game.C_100336_im.func_102522_a(int, game.C_100336_im)boolean
		// @7D: ifne @88
		// @80: goto @84
		// @83: athrow
		// @84: goto @8A
		// @87: athrow
		// @88: iconst_1
		// @89: ireturn
		// @8A: iload #4
		// @8C: iload_3
		// @8D: isub
		// @8E: istore #4
		// @90: iload #7
		// @92: ifeq @52
		// @95: iinc #4 +255
		// @98: iload #7
		// @9A: ifeq @2C
		// @9D: iconst_0
		// @9E: ireturn
		// @9F: astore #4
		// @A1: aload #4
		// @A3: new java.lang.StringBuilder
		// @A6: dup
		// @A7: invokespecial java.lang.StringBuilder.<init>()void
		// @AA: getstatic java.lang.String[] game.C_100289_jl.field_102905_K
		// @AD: bipush 10 (0x0A)
		// @AF: aaload
		// @B0: invokevirtual java.lang.StringBuilder.append(java.lang.String)java.lang.StringBuilder
		// @B3: iload_1
		// @B4: invokevirtual java.lang.StringBuilder.append(int)java.lang.StringBuilder
		// @B7: bipush 44 (0x2C)
		// @B9: invokevirtual java.lang.StringBuilder.append(char)java.lang.StringBuilder
		// @BC: aload_2
		// @BD: ifnull @C9
		// @C0: getstatic java.lang.String[] game.C_100289_jl.field_102905_K
		// @C3: iconst_2
		// @C4: aaload
		// @C5: goto @CE
		// @C8: athrow
		// @C9: getstatic java.lang.String[] game.C_100289_jl.field_102905_K
		// @CC: iconst_4
		// @CD: aaload
		// @CE: invokevirtual java.lang.StringBuilder.append(java.lang.String)java.lang.StringBuilder
		// @D1: bipush 44 (0x2C)
		// @D3: invokevirtual java.lang.StringBuilder.append(char)java.lang.StringBuilder
		// @D6: iload_3
		// @D7: invokevirtual java.lang.StringBuilder.append(int)java.lang.StringBuilder
		// @DA: bipush 41 (0x29)
		// @DC: invokevirtual java.lang.StringBuilder.append(char)java.lang.StringBuilder
		// @DF: invokevirtual java.lang.StringBuilder.toString()java.lang.String
		// @E2: invokestatic game.C_100181_cf.func_105695_a(java.lang.Throwable, java.lang.String)game.C_100170_cm
		// @E5: athrow
	}
	
	private final boolean func_102896_a(int arg0, C_100336_im arg1, int arg2)
	{
		// @00: getstatic int game.SteelSentinels.field_105275_O
		// @03: istore #7
		// @05: aconst_null
		// @06: aload_0
		// @07: getfield game.C_100336_im[] game.C_100289_jl.field_102903_I
		// @0A: if_acmpeq @11
		// @0D: goto @13
		// @10: athrow
		// @11: iconst_0
		// @12: ireturn
		// @13: iload_1
		// @14: istore #4
		// @16: aload_0
		// @17: getfield game.C_100336_im[] game.C_100289_jl.field_102903_I
		// @1A: arraylength
		// @1B: iload #4
		// @1D: if_icmple @8F
		// @20: aload_0
		// @21: getfield game.C_100336_im[] game.C_100289_jl.field_102903_I
		// @24: iload #4
		// @26: aaload
		// @27: astore #5
		// @29: aload #5
		// @2B: ifnull @87
		// @2E: aload #5
		// @30: bipush 126 (0x7E)
		// @32: invokevirtual game.C_100336_im.func_102515_d(byte)boolean
		// @35: ifeq @87
		// @38: iload #4
		// @3A: iload_3
		// @3B: iadd
		// @3C: istore #4
		// @3E: aload_0
		// @3F: getfield game.C_100336_im[] game.C_100289_jl.field_102903_I
		// @42: arraylength
		// @43: iconst_m1
		// @44: ixor
		// @45: iload #4
		// @47: iconst_m1
		// @48: ixor
		// @49: if_icmpge @87
		// @4C: aload_0
		// @4D: getfield game.C_100336_im[] game.C_100289_jl.field_102903_I
		// @50: iload #4
		// @52: aaload
		// @53: astore #6
		// @55: aload #6
		// @57: iload #7
		// @59: ifne @2B
		// @5C: ifnonnull @68
		// @5F: iload #7
		// @61: ifeq @7C
		// @64: goto @68
		// @67: athrow
		// @68: aload #6
		// @6A: iconst_1
		// @6B: aload_2
		// @6C: invokevirtual game.C_100336_im.func_102522_a(int, game.C_100336_im)boolean
		// @6F: ifne @7A
		// @72: goto @76
		// @75: athrow
		// @76: goto @7C
		// @79: athrow
		// @7A: iconst_1
		// @7B: ireturn
		// @7C: iload #4
		// @7E: iload_3
		// @7F: iadd
		// @80: istore #4
		// @82: iload #7
		// @84: ifeq @3E
		// @87: iinc #4 +1
		// @8A: iload #7
		// @8C: ifeq @16
		// @8F: iconst_0
		// @90: ireturn
		// @91: astore #4
		// @93: aload #4
		// @95: new java.lang.StringBuilder
		// @98: dup
		// @99: invokespecial java.lang.StringBuilder.<init>()void
		// @9C: getstatic java.lang.String[] game.C_100289_jl.field_102905_K
		// @9F: bipush 17 (0x11)
		// @A1: aaload
		// @A2: invokevirtual java.lang.StringBuilder.append(java.lang.String)java.lang.StringBuilder
		// @A5: iload_1
		// @A6: invokevirtual java.lang.StringBuilder.append(int)java.lang.StringBuilder
		// @A9: bipush 44 (0x2C)
		// @AB: invokevirtual java.lang.StringBuilder.append(char)java.lang.StringBuilder
		// @AE: aload_2
		// @AF: ifnull @BB
		// @B2: getstatic java.lang.String[] game.C_100289_jl.field_102905_K
		// @B5: iconst_2
		// @B6: aaload
		// @B7: goto @C0
		// @BA: athrow
		// @BB: getstatic java.lang.String[] game.C_100289_jl.field_102905_K
		// @BE: iconst_4
		// @BF: aaload
		// @C0: invokevirtual java.lang.StringBuilder.append(java.lang.String)java.lang.StringBuilder
		// @C3: bipush 44 (0x2C)
		// @C5: invokevirtual java.lang.StringBuilder.append(char)java.lang.StringBuilder
		// @C8: iload_3
		// @C9: invokevirtual java.lang.StringBuilder.append(int)java.lang.StringBuilder
		// @CC: bipush 41 (0x29)
		// @CE: invokevirtual java.lang.StringBuilder.append(char)java.lang.StringBuilder
		// @D1: invokevirtual java.lang.StringBuilder.toString()java.lang.String
		// @D4: invokestatic game.C_100181_cf.func_105695_a(java.lang.Throwable, java.lang.String)game.C_100170_cm
		// @D7: athrow
	}
	
	final void func_102524_a(int arg0, int arg1, int arg2, int arg3, byte arg4)
	{
		// @00: aload_0
		// @01: iload_1
		// @02: iload_2
		// @03: iload_3
		// @04: iload #4
		// @06: bipush -110 (0x92)
		// @08: invokespecial game.C_100336_im.func_102524_a(int, int, int, int, byte)void
		// @0B: bipush -17 (0xEF)
		// @0D: iload #5
		// @0F: bipush -11 (0xF5)
		// @11: isub
		// @12: bipush 48 (0x30)
		// @14: idiv
		// @15: irem
		// @16: istore #6
		// @18: aload_0
		// @19: bipush -123 (0x85)
		// @1B: invokevirtual game.C_100289_jl.func_102892_i(int)void
		// @1E: goto @6B
		// @21: astore #6
		// @23: aload #6
		// @25: new java.lang.StringBuilder
		// @28: dup
		// @29: invokespecial java.lang.StringBuilder.<init>()void
		// @2C: getstatic java.lang.String[] game.C_100289_jl.field_102905_K
		// @2F: bipush 7 (0x07)
		// @31: aaload
		// @32: invokevirtual java.lang.StringBuilder.append(java.lang.String)java.lang.StringBuilder
		// @35: iload_1
		// @36: invokevirtual java.lang.StringBuilder.append(int)java.lang.StringBuilder
		// @39: bipush 44 (0x2C)
		// @3B: invokevirtual java.lang.StringBuilder.append(char)java.lang.StringBuilder
		// @3E: iload_2
		// @3F: invokevirtual java.lang.StringBuilder.append(int)java.lang.StringBuilder
		// @42: bipush 44 (0x2C)
		// @44: invokevirtual java.lang.StringBuilder.append(char)java.lang.StringBuilder
		// @47: iload_3
		// @48: invokevirtual java.lang.StringBuilder.append(int)java.lang.StringBuilder
		// @4B: bipush 44 (0x2C)
		// @4D: invokevirtual java.lang.StringBuilder.append(char)java.lang.StringBuilder
		// @50: iload #4
		// @52: invokevirtual java.lang.StringBuilder.append(int)java.lang.StringBuilder
		// @55: bipush 44 (0x2C)
		// @57: invokevirtual java.lang.StringBuilder.append(char)java.lang.StringBuilder
		// @5A: iload #5
		// @5C: invokevirtual java.lang.StringBuilder.append(int)java.lang.StringBuilder
		// @5F: bipush 41 (0x29)
		// @61: invokevirtual java.lang.StringBuilder.append(char)java.lang.StringBuilder
		// @64: invokevirtual java.lang.StringBuilder.toString()java.lang.String
		// @67: invokestatic game.C_100181_cf.func_105695_a(java.lang.Throwable, java.lang.String)game.C_100170_cm
		// @6A: athrow
		// @6B: return
	}
	
	private final C_100336_im func_102886_k(int arg0)
	{
		// @00: getstatic int game.SteelSentinels.field_105275_O
		// @03: istore #5
		// @05: iload_1
		// @06: iconst_m1
		// @07: if_icmpeq @1E
		// @0A: aload_0
		// @0B: aconst_null
		// @0C: checkcast java.util.Hashtable
		// @0F: aconst_null
		// @10: checkcast java.lang.StringBuilder
		// @13: bipush 48 (0x30)
		// @15: bipush 35 (0x23)
		// @17: invokespecial game.C_100289_jl.func_102891_a(java.util.Hashtable, java.lang.StringBuilder, int, int)void
		// @1A: goto @1E
		// @1D: athrow
		// @1E: aload_0
		// @1F: getfield game.C_100336_im[] game.C_100289_jl.field_102903_I
		// @22: ifnonnull @27
		// @25: aconst_null
		// @26: areturn
		// @27: aload_0
		// @28: getfield game.C_100336_im[] game.C_100289_jl.field_102903_I
		// @2B: astore_2
		// @2C: iconst_0
		// @2D: istore_3
		// @2E: aload_2
		// @2F: arraylength
		// @30: iload_3
		// @31: if_icmple @5B
		// @34: aload_2
		// @35: iload_3
		// @36: aaload
		// @37: astore #4
		// @39: aload #4
		// @3B: ifnull @53
		// @3E: aload #4
		// @40: bipush 100 (0x64)
		// @42: invokevirtual game.C_100336_im.func_102515_d(byte)boolean
		// @45: ifne @50
		// @48: goto @4C
		// @4B: athrow
		// @4C: goto @53
		// @4F: athrow
		// @50: aload #4
		// @52: areturn
		// @53: iinc #3 +1
		// @56: iload #5
		// @58: ifeq @2E
		// @5B: aconst_null
		// @5C: areturn
		// @5D: astore_2
		// @5E: aload_2
		// @5F: new java.lang.StringBuilder
		// @62: dup
		// @63: invokespecial java.lang.StringBuilder.<init>()void
		// @66: getstatic java.lang.String[] game.C_100289_jl.field_102905_K
		// @69: bipush 16 (0x10)
		// @6B: aaload
		// @6C: invokevirtual java.lang.StringBuilder.append(java.lang.String)java.lang.StringBuilder
		// @6F: iload_1
		// @70: invokevirtual java.lang.StringBuilder.append(int)java.lang.StringBuilder
		// @73: bipush 41 (0x29)
		// @75: invokevirtual java.lang.StringBuilder.append(char)java.lang.StringBuilder
		// @78: invokevirtual java.lang.StringBuilder.toString()java.lang.String
		// @7B: invokestatic game.C_100181_cf.func_105695_a(java.lang.Throwable, java.lang.String)game.C_100170_cm
		// @7E: athrow
	}
	
	static
	{
		// @000: bipush 24 (0x18)
		// @002: anewarray java.lang.String
		// @005: dup
		// @006: iconst_0
		// @007: ldc "QB\nBF"
		// @009: invokestatic game.C_100289_jl.func_102888_z(java.lang.String)char[]
		// @00C: invokestatic game.C_100289_jl.func_102887_z(char[])java.lang.String
		// @00F: aastore
		// @010: dup
		// @011: iconst_1
		// @012: ldc "QB\nSF"
		// @014: invokestatic game.C_100289_jl.func_102888_z(java.lang.String)char[]
		// @017: invokestatic game.C_100289_jl.func_102887_z(char[])java.lang.String
		// @01A: aastore
		// @01B: dup
		// @01C: iconst_2
		// @01D: ldc "@\u0000\n;\u0013"
		// @01F: invokestatic game.C_100289_jl.func_102888_z(java.lang.String)char[]
		// @022: invokestatic game.C_100289_jl.func_102887_z(char[])java.lang.String
		// @025: aastore
		// @026: dup
		// @027: iconst_3
		// @028: ldc "QB\n]F"
		// @02A: invokestatic game.C_100289_jl.func_102888_z(java.lang.String)char[]
		// @02D: invokestatic game.C_100289_jl.func_102887_z(char[])java.lang.String
		// @030: aastore
		// @031: dup
		// @032: iconst_4
		// @033: ldc "U[Hy"
		// @035: invokestatic game.C_100289_jl.func_102888_z(java.lang.String)char[]
		// @038: invokestatic game.C_100289_jl.func_102887_z(char[])java.lang.String
		// @03B: aastore
		// @03C: dup
		// @03D: iconst_5
		// @03E: ldc "QB\nDF"
		// @040: invokestatic game.C_100289_jl.func_102888_z(java.lang.String)char[]
		// @043: invokestatic game.C_100289_jl.func_102887_z(char[])java.lang.String
		// @046: aastore
		// @047: dup
		// @048: bipush 6 (0x06)
		// @04A: ldc "QB\nVF"
		// @04C: invokestatic game.C_100289_jl.func_102888_z(java.lang.String)char[]
		// @04F: invokestatic game.C_100289_jl.func_102887_z(char[])java.lang.String
		// @052: aastore
		// @053: dup
		// @054: bipush 7 (0x07)
		// @056: ldc "QB\nY/\u0013"
		// @058: invokestatic game.C_100289_jl.func_102888_z(java.lang.String)char[]
		// @05B: invokestatic game.C_100289_jl.func_102887_z(char[])java.lang.String
		// @05E: aastore
		// @05F: dup
		// @060: bipush 8 (0x08)
		// @062: ldc "QB\nFF"
		// @064: invokestatic game.C_100289_jl.func_102888_z(java.lang.String)char[]
		// @067: invokestatic game.C_100289_jl.func_102887_z(char[])java.lang.String
		// @06A: aastore
		// @06B: dup
		// @06C: bipush 9 (0x09)
		// @06E: ldc "QB\nGF"
		// @070: invokestatic game.C_100289_jl.func_102888_z(java.lang.String)char[]
		// @073: invokestatic game.C_100289_jl.func_102887_z(char[])java.lang.String
		// @076: aastore
		// @077: dup
		// @078: bipush 10 (0x0A)
		// @07A: ldc "QB\nPF"
		// @07C: invokestatic game.C_100289_jl.func_102888_z(java.lang.String)char[]
		// @07F: invokestatic game.C_100289_jl.func_102887_z(char[])java.lang.String
		// @082: aastore
		// @083: dup
		// @084: bipush 11 (0x0B)
		// @086: ldc "QB\n@F"
		// @088: invokestatic game.C_100289_jl.func_102888_z(java.lang.String)char[]
		// @08B: invokestatic game.C_100289_jl.func_102887_z(char[])java.lang.String
		// @08E: aastore
		// @08F: dup
		// @090: bipush 12 (0x0C)
		// @092: ldc "QB\nQ/\u0013"
		// @094: invokestatic game.C_100289_jl.func_102888_z(java.lang.String)char[]
		// @097: invokestatic game.C_100289_jl.func_102887_z(char[])java.lang.String
		// @09A: aastore
		// @09B: dup
		// @09C: bipush 13 (0x0D)
		// @09E: ldc "QB\nQF"
		// @0A0: invokestatic game.C_100289_jl.func_102888_z(java.lang.String)char[]
		// @0A3: invokestatic game.C_100289_jl.func_102887_z(char[])java.lang.String
		// @0A6: aastore
		// @0A7: dup
		// @0A8: bipush 14 (0x0E)
		// @0AA: ldc "QB\nAF"
		// @0AC: invokestatic game.C_100289_jl.func_102888_z(java.lang.String)char[]
		// @0AF: invokestatic game.C_100289_jl.func_102887_z(char[])java.lang.String
		// @0B2: aastore
		// @0B3: dup
		// @0B4: bipush 15 (0x0F)
		// @0B6: ldc "QB\nS/\u0013"
		// @0B8: invokestatic game.C_100289_jl.func_102888_z(java.lang.String)char[]
		// @0BB: invokestatic game.C_100289_jl.func_102887_z(char[])java.lang.String
		// @0BE: aastore
		// @0BF: dup
		// @0C0: bipush 16 (0x10)
		// @0C2: ldc "QB\nRF"
		// @0C4: invokestatic game.C_100289_jl.func_102888_z(java.lang.String)char[]
		// @0C7: invokestatic game.C_100289_jl.func_102887_z(char[])java.lang.String
		// @0CA: aastore
		// @0CB: dup
		// @0CC: bipush 17 (0x11)
		// @0CE: ldc "QB\n\\F"
		// @0D0: invokestatic game.C_100289_jl.func_102888_z(java.lang.String)char[]
		// @0D3: invokestatic game.C_100289_jl.func_102887_z(char[])java.lang.String
		// @0D6: aastore
		// @0D7: dup
		// @0D8: bipush 18 (0x12)
		// @0DA: ldc "QB\nTF"
		// @0DC: invokestatic game.C_100289_jl.func_102888_z(java.lang.String)char[]
		// @0DF: invokestatic game.C_100289_jl.func_102887_z(char[])java.lang.String
		// @0E2: aastore
		// @0E3: dup
		// @0E4: bipush 19 (0x13)
		// @0E6: ldc "QB\nP/\u0013"
		// @0E8: invokestatic game.C_100289_jl.func_102888_z(java.lang.String)char[]
		// @0EB: invokestatic game.C_100289_jl.func_102887_z(char[])java.lang.String
		// @0EE: aastore
		// @0EF: dup
		// @0F0: bipush 20 (0x14)
		// @0F2: ldc "QB\nCF"
		// @0F4: invokestatic game.C_100289_jl.func_102888_z(java.lang.String)char[]
		// @0F7: invokestatic game.C_100289_jl.func_102887_z(char[])java.lang.String
		// @0FA: aastore
		// @0FB: dup
		// @0FC: bipush 21 (0x15)
		// @0FE: ldc "QB\nV/\u0013"
		// @100: invokestatic game.C_100289_jl.func_102888_z(java.lang.String)char[]
		// @103: invokestatic game.C_100289_jl.func_102887_z(char[])java.lang.String
		// @106: aastore
		// @107: dup
		// @108: bipush 22 (0x16)
		// @10A: ldc "QB\nWF"
		// @10C: invokestatic game.C_100289_jl.func_102888_z(java.lang.String)char[]
		// @10F: invokestatic game.C_100289_jl.func_102887_z(char[])java.lang.String
		// @112: aastore
		// @113: dup
		// @114: bipush 23 (0x17)
		// @116: ldc "QB\nT/\u0013"
		// @118: invokestatic game.C_100289_jl.func_102888_z(java.lang.String)char[]
		// @11B: invokestatic game.C_100289_jl.func_102887_z(char[])java.lang.String
		// @11E: aastore
		// @11F: putstatic java.lang.String[] game.C_100289_jl.field_102905_K
		// @122: iconst_1
		// @123: putstatic boolean game.C_100289_jl.field_102901_L
		// @126: iconst_3
		// @127: newarray int[]
		// @129: dup
		// @12A: iconst_0
		// @12B: ldc 6559605 (0x641775)
		// @12D: iastore
		// @12E: dup
		// @12F: iconst_1
		// @130: ldc 16752640 (0xffa000)
		// @132: iastore
		// @133: dup
		// @134: iconst_2
		// @135: ldc 65280 (0xff00)
		// @137: iastore
		// @138: putstatic int[] game.C_100289_jl.field_102900_G
		// @13B: ldc "lOV{\u0007UI\u001e5"
		// @13D: invokestatic game.C_100289_jl.func_102888_z(java.lang.String)char[]
		// @140: invokestatic game.C_100289_jl.func_102887_z(char[])java.lang.String
		// @143: putstatic java.lang.String game.C_100289_jl.field_102898_E
		// @146: bipush 7 (0x07)
		// @148: anewarray java.lang.String
		// @14B: dup
		// @14C: iconst_0
		// @14D: ldc "\u0001\u000e\u0018v\u0001W\u0013Bs^\u000b\u001e\u0014+\"tmoP*\u0007\u0001Gz\u0002\u0005"
		// @14F: invokestatic game.C_100289_jl.func_102888_z(java.lang.String)char[]
		// @152: invokestatic game.C_100289_jl.func_102887_z(char[])java.lang.String
		// @155: aastore
		// @156: dup
		// @157: iconst_1
		// @158: ldc "\u0001\u000egZ#kbaA+"
		// @15A: invokestatic game.C_100289_jl.func_102888_z(java.lang.String)char[]
		// @15D: invokestatic game.C_100289_jl.func_102887_z(char[])java.lang.String
		// @160: aastore
		// @161: dup
		// @162: iconst_2
		// @163: ldc "\u0016\u000e\u0018v\u0001W\u0013Bs\u0008]HB+:rca/N\u0007\u000b\u0014+R\u0014MKyP"
		// @165: invokestatic game.C_100289_jl.func_102888_z(java.lang.String)char[]
		// @168: invokestatic game.C_100289_jl.func_102887_z(char[])java.lang.String
		// @16B: aastore
		// @16C: dup
		// @16D: iconst_3
		// @16E: ldc "\u0001\u000e\u0018v\u0001W\u0013\u001cs\n]HB+/momY/yba)AXAH+"
		// @170: invokestatic game.C_100289_jl.func_102888_z(java.lang.String)char[]
		// @173: invokestatic game.C_100289_jl.func_102887_z(char[])java.lang.String
		// @176: aastore
		// @177: dup
		// @178: iconst_4
		// @179: ldc "wAG~\u000b_"
		// @17B: invokestatic game.C_100289_jl.func_102888_z(java.lang.String)char[]
		// @17E: invokestatic game.C_100289_jl.func_102887_z(char[])java.lang.String
		// @181: aastore
		// @182: dup
		// @183: iconst_5
		// @184: ldc "xAIe\u0002^ZA"
		// @186: invokestatic game.C_100289_jl.func_102888_z(java.lang.String)char[]
		// @189: invokestatic game.C_100289_jl.func_102887_z(char[])java.lang.String
		// @18C: aastore
		// @18D: dup
		// @18E: bipush 6 (0x06)
		// @190: ldc "zXE|\u0002ZLHp"
		// @192: invokestatic game.C_100289_jl.func_102888_z(java.lang.String)char[]
		// @195: invokestatic game.C_100289_jl.func_102887_z(char[])java.lang.String
		// @198: aastore
		// @199: putstatic java.lang.String[] game.C_100289_jl.field_102904_J
		// @19C: return
	}
	
	private static char[] func_102888_z(String arg0)
	{
		// @00: aload_0
		// @01: invokevirtual java.lang.String.toCharArray()char[]
		// @04: dup
		// @05: arraylength
		// @06: iconst_2
		// @07: if_icmpge @13
		// @0A: dup
		// @0B: iconst_0
		// @0C: dup2
		// @0D: caload
		// @0E: bipush 110 (0x6E)
		// @10: ixor
		// @11: i2c
		// @12: castore
		// @13: areturn
	}
	
	private static String func_102887_z(char[] arg0)
	{
		// @00: aload_0
		// @01: dup
		// @02: arraylength
		// @03: swap
		// @04: iconst_0
		// @05: istore_1
		// @06: goto @4C
		// @09: dup
		// @0A: iload_1
		// @0B: dup2
		// @0C: caload
		// @0D: iload_1
		// @0E: iconst_5
		// @0F: irem
		// @10: tableswitch def: @44, for 0: @30, for 1: @35, for 2: @3A, for 3: @3F
		// @30: bipush 59 (0x3B)
		// @32: goto @46
		// @35: bipush 46 (0x2E)
		// @37: goto @46
		// @3A: bipush 36 (0x24)
		// @3C: goto @46
		// @3F: bipush 21 (0x15)
		// @41: goto @46
		// @44: bipush 110 (0x6E)
		// @46: ixor
		// @47: i2c
		// @48: castore
		// @49: iinc #1 +1
		// @4C: swap
		// @4D: dup_x1
		// @4E: iload_1
		// @4F: if_icmpgt @09
		// @52: new java.lang.String
		// @55: dup_x1
		// @56: swap
		// @57: invokespecial java.lang.String.<init>(char[])void
		// @5A: invokevirtual java.lang.String.intern()java.lang.String
		// @5D: areturn
	}
}
