package game;

import java.awt.image.ImageProducer;
import java.awt.image.ImageObserver;
import java.awt.image.ImageConsumer;
import java.awt.image.ColorModel;
import java.awt.Graphics;
import java.awt.Component;
import java.awt.Image;
import java.applet.Applet;

final class C_100252_pn extends C_100185_rm implements ImageProducer, ImageObserver
{
	static long field_105508_w;
	static byte[] field_105509_v;
	static String field_105514_q;
	static int field_105503_o;
	static String[] field_105505_m;
	private ColorModel field_105502_n;
	static String[] field_105506_j;
	static C_100037_wb[] field_105511_t;
	static int field_105512_s;
	static String field_105507_k;
	private ImageConsumer field_105510_u;
	static C_100302_ka field_105515_p;
	static C_100201_qj field_105504_l;
	static C_100037_wb field_105513_r;
	private static final String[] field_105516_z;
	
	static final void func_105501_a(int arg0, int arg1)
	{
		// @00: getstatic game.C_100278_nd game.C_100115_ej.field_102043_Yb
		// @03: astore_2
		// @04: aload_2
		// @05: iload_1
		// @06: iload_0
		// @07: sipush 26850 (0x68E2)
		// @0A: ixor
		// @0B: invokevirtual game.C_100278_nd.func_101189_h(int, int)void
		// @0E: iload_0
		// @0F: sipush 26780 (0x689C)
		// @12: if_icmpeq @1E
		// @15: bipush -40 (0xD8)
		// @17: putstatic int game.C_100252_pn.field_105503_o
		// @1A: goto @1E
		// @1D: athrow
		// @1E: aload_2
		// @1F: iload_0
		// @20: sipush -18942 (0xB602)
		// @23: iadd
		// @24: iconst_1
		// @25: invokevirtual game.C_100278_nd.func_101169_f(int, int)void
		// @28: aload_2
		// @29: sipush 7838 (0x1E9E)
		// @2C: iconst_0
		// @2D: invokevirtual game.C_100278_nd.func_101169_f(int, int)void
		// @30: goto @5D
		// @33: astore_2
		// @34: aload_2
		// @35: new java.lang.StringBuilder
		// @38: dup
		// @39: invokespecial java.lang.StringBuilder.<init>()void
		// @3C: getstatic java.lang.String[] game.C_100252_pn.field_105516_z
		// @3F: iconst_0
		// @40: aaload
		// @41: invokevirtual java.lang.StringBuilder.append(java.lang.String)java.lang.StringBuilder
		// @44: iload_0
		// @45: invokevirtual java.lang.StringBuilder.append(int)java.lang.StringBuilder
		// @48: bipush 44 (0x2C)
		// @4A: invokevirtual java.lang.StringBuilder.append(char)java.lang.StringBuilder
		// @4D: iload_1
		// @4E: invokevirtual java.lang.StringBuilder.append(int)java.lang.StringBuilder
		// @51: bipush 41 (0x29)
		// @53: invokevirtual java.lang.StringBuilder.append(char)java.lang.StringBuilder
		// @56: invokevirtual java.lang.StringBuilder.toString()java.lang.String
		// @59: invokestatic game.C_100181_cf.func_105695_a(java.lang.Throwable, java.lang.String)game.C_100170_cm
		// @5C: athrow
		// @5D: return
	}
	
	final void func_105478_a(int arg0, int arg1, Component arg2, byte arg3)
	{
		// @00: aload_0
		// @01: iload_2
		// @02: putfield int game.C_100252_pn.field_105483_g
		// @05: aload_0
		// @06: iload_1
		// @07: iload_2
		// @08: imul
		// @09: iconst_1
		// @0A: iadd
		// @0B: newarray int[]
		// @0D: putfield int[] game.C_100252_pn.field_105486_b
		// @10: aload_0
		// @11: iload_1
		// @12: putfield int game.C_100252_pn.field_105491_i
		// @15: aload_0
		// @16: new java.awt.image.DirectColorModel
		// @19: dup
		// @1A: bipush 32 (0x20)
		// @1C: ldc 16711680 (0xff0000)
		// @1E: ldc 65280 (0xff00)
		// @20: sipush 255 (0x00FF)
		// @23: invokespecial java.awt.image.DirectColorModel.<init>(int, int, int, int)void
		// @26: putfield java.awt.image.ColorModel game.C_100252_pn.field_105502_n
		// @29: aload_0
		// @2A: aload_3
		// @2B: aload_0
		// @2C: invokevirtual java.awt.Component.createImage(java.awt.image.ImageProducer)java.awt.Image
		// @2F: putfield java.awt.Image game.C_100252_pn.field_105482_f
		// @32: aload_0
		// @33: bipush -71 (0xB9)
		// @35: invokespecial game.C_100252_pn.func_105497_b(byte)void
		// @38: aload_3
		// @39: aload_0
		// @3A: getfield java.awt.Image game.C_100252_pn.field_105482_f
		// @3D: aload_0
		// @3E: invokevirtual java.awt.Component.prepareImage(java.awt.Image, java.awt.image.ImageObserver)boolean
		// @41: pop
		// @42: iload #4
		// @44: bipush 15 (0x0F)
		// @46: if_icmpeq @4A
		// @49: return
		// @4A: aload_0
		// @4B: bipush -71 (0xB9)
		// @4D: invokespecial game.C_100252_pn.func_105497_b(byte)void
		// @50: aload_3
		// @51: aload_0
		// @52: getfield java.awt.Image game.C_100252_pn.field_105482_f
		// @55: aload_0
		// @56: invokevirtual java.awt.Component.prepareImage(java.awt.Image, java.awt.image.ImageObserver)boolean
		// @59: pop
		// @5A: aload_0
		// @5B: bipush -71 (0xB9)
		// @5D: invokespecial game.C_100252_pn.func_105497_b(byte)void
		// @60: aload_3
		// @61: aload_0
		// @62: getfield java.awt.Image game.C_100252_pn.field_105482_f
		// @65: aload_0
		// @66: invokevirtual java.awt.Component.prepareImage(java.awt.Image, java.awt.image.ImageObserver)boolean
		// @69: pop
		// @6A: aload_0
		// @6B: bipush 126 (0x7E)
		// @6D: invokevirtual game.C_100252_pn.func_105476_a(byte)void
		// @70: goto @C4
		// @73: astore #5
		// @75: aload #5
		// @77: new java.lang.StringBuilder
		// @7A: dup
		// @7B: invokespecial java.lang.StringBuilder.<init>()void
		// @7E: getstatic java.lang.String[] game.C_100252_pn.field_105516_z
		// @81: bipush 6 (0x06)
		// @83: aaload
		// @84: invokevirtual java.lang.StringBuilder.append(java.lang.String)java.lang.StringBuilder
		// @87: iload_1
		// @88: invokevirtual java.lang.StringBuilder.append(int)java.lang.StringBuilder
		// @8B: bipush 44 (0x2C)
		// @8D: invokevirtual java.lang.StringBuilder.append(char)java.lang.StringBuilder
		// @90: iload_2
		// @91: invokevirtual java.lang.StringBuilder.append(int)java.lang.StringBuilder
		// @94: bipush 44 (0x2C)
		// @96: invokevirtual java.lang.StringBuilder.append(char)java.lang.StringBuilder
		// @99: aload_3
		// @9A: ifnull @A6
		// @9D: getstatic java.lang.String[] game.C_100252_pn.field_105516_z
		// @A0: iconst_3
		// @A1: aaload
		// @A2: goto @AB
		// @A5: athrow
		// @A6: getstatic java.lang.String[] game.C_100252_pn.field_105516_z
		// @A9: iconst_1
		// @AA: aaload
		// @AB: invokevirtual java.lang.StringBuilder.append(java.lang.String)java.lang.StringBuilder
		// @AE: bipush 44 (0x2C)
		// @B0: invokevirtual java.lang.StringBuilder.append(char)java.lang.StringBuilder
		// @B3: iload #4
		// @B5: invokevirtual java.lang.StringBuilder.append(int)java.lang.StringBuilder
		// @B8: bipush 41 (0x29)
		// @BA: invokevirtual java.lang.StringBuilder.append(char)java.lang.StringBuilder
		// @BD: invokevirtual java.lang.StringBuilder.toString()java.lang.String
		// @C0: invokestatic game.C_100181_cf.func_105695_a(java.lang.Throwable, java.lang.String)game.C_100170_cm
		// @C3: athrow
		// @C4: return
	}
	
	public final synchronized boolean isConsumer(ImageConsumer arg0)
	{
		// @00: aload_1
		// @01: aload_0
		// @02: getfield java.awt.image.ImageConsumer game.C_100252_pn.field_105510_u
		// @05: if_acmpne @0D
		// @08: iconst_1
		// @09: goto @0E
		// @0C: athrow
		// @0D: iconst_0
		// @0E: ireturn
		// @0F: astore_2
		// @10: aload_2
		// @11: new java.lang.StringBuilder
		// @14: dup
		// @15: invokespecial java.lang.StringBuilder.<init>()void
		// @18: getstatic java.lang.String[] game.C_100252_pn.field_105516_z
		// @1B: bipush 21 (0x15)
		// @1D: aaload
		// @1E: invokevirtual java.lang.StringBuilder.append(java.lang.String)java.lang.StringBuilder
		// @21: aload_1
		// @22: ifnull @2E
		// @25: getstatic java.lang.String[] game.C_100252_pn.field_105516_z
		// @28: iconst_3
		// @29: aaload
		// @2A: goto @33
		// @2D: athrow
		// @2E: getstatic java.lang.String[] game.C_100252_pn.field_105516_z
		// @31: iconst_1
		// @32: aaload
		// @33: invokevirtual java.lang.StringBuilder.append(java.lang.String)java.lang.StringBuilder
		// @36: bipush 41 (0x29)
		// @38: invokevirtual java.lang.StringBuilder.append(char)java.lang.StringBuilder
		// @3B: invokevirtual java.lang.StringBuilder.toString()java.lang.String
		// @3E: invokestatic game.C_100181_cf.func_105695_a(java.lang.Throwable, java.lang.String)game.C_100170_cm
		// @41: athrow
	}
	
	static final String func_105498_a(int arg0, String arg1, String arg2, C_100098_h arg3)
	{
		// @00: aload_3
		// @01: iconst_0
		// @02: invokevirtual game.C_100098_h.func_104597_a(boolean)boolean
		// @05: ifeq @0C
		// @08: goto @0E
		// @0B: athrow
		// @0C: aload_1
		// @0D: areturn
		// @0E: iload_0
		// @0F: iconst_1
		// @10: if_icmpeq @1E
		// @13: aconst_null
		// @14: checkcast game.C_100037_wb
		// @17: putstatic game.C_100037_wb game.C_100252_pn.field_105513_r
		// @1A: goto @1E
		// @1D: athrow
		// @1E: new java.lang.StringBuilder
		// @21: dup
		// @22: invokespecial java.lang.StringBuilder.<init>()void
		// @25: aload_2
		// @26: invokevirtual java.lang.StringBuilder.append(java.lang.String)java.lang.StringBuilder
		// @29: getstatic java.lang.String[] game.C_100252_pn.field_105516_z
		// @2C: bipush 7 (0x07)
		// @2E: aaload
		// @2F: invokevirtual java.lang.StringBuilder.append(java.lang.String)java.lang.StringBuilder
		// @32: aload_3
		// @33: iconst_0
		// @34: invokevirtual game.C_100098_h.func_104590_b(boolean)int
		// @37: invokevirtual java.lang.StringBuilder.append(int)java.lang.StringBuilder
		// @3A: ldc "%"
		// @3C: invokevirtual java.lang.StringBuilder.append(java.lang.String)java.lang.StringBuilder
		// @3F: invokevirtual java.lang.StringBuilder.toString()java.lang.String
		// @42: areturn
		// @43: astore #4
		// @45: aload #4
		// @47: new java.lang.StringBuilder
		// @4A: dup
		// @4B: invokespecial java.lang.StringBuilder.<init>()void
		// @4E: getstatic java.lang.String[] game.C_100252_pn.field_105516_z
		// @51: bipush 8 (0x08)
		// @53: aaload
		// @54: invokevirtual java.lang.StringBuilder.append(java.lang.String)java.lang.StringBuilder
		// @57: iload_0
		// @58: invokevirtual java.lang.StringBuilder.append(int)java.lang.StringBuilder
		// @5B: bipush 44 (0x2C)
		// @5D: invokevirtual java.lang.StringBuilder.append(char)java.lang.StringBuilder
		// @60: aload_1
		// @61: ifnull @6D
		// @64: getstatic java.lang.String[] game.C_100252_pn.field_105516_z
		// @67: iconst_3
		// @68: aaload
		// @69: goto @72
		// @6C: athrow
		// @6D: getstatic java.lang.String[] game.C_100252_pn.field_105516_z
		// @70: iconst_1
		// @71: aaload
		// @72: invokevirtual java.lang.StringBuilder.append(java.lang.String)java.lang.StringBuilder
		// @75: bipush 44 (0x2C)
		// @77: invokevirtual java.lang.StringBuilder.append(char)java.lang.StringBuilder
		// @7A: aload_2
		// @7B: ifnull @87
		// @7E: getstatic java.lang.String[] game.C_100252_pn.field_105516_z
		// @81: iconst_3
		// @82: aaload
		// @83: goto @8C
		// @86: athrow
		// @87: getstatic java.lang.String[] game.C_100252_pn.field_105516_z
		// @8A: iconst_1
		// @8B: aaload
		// @8C: invokevirtual java.lang.StringBuilder.append(java.lang.String)java.lang.StringBuilder
		// @8F: bipush 44 (0x2C)
		// @91: invokevirtual java.lang.StringBuilder.append(char)java.lang.StringBuilder
		// @94: aload_3
		// @95: ifnull @A1
		// @98: getstatic java.lang.String[] game.C_100252_pn.field_105516_z
		// @9B: iconst_3
		// @9C: aaload
		// @9D: goto @A6
		// @A0: athrow
		// @A1: getstatic java.lang.String[] game.C_100252_pn.field_105516_z
		// @A4: iconst_1
		// @A5: aaload
		// @A6: invokevirtual java.lang.StringBuilder.append(java.lang.String)java.lang.StringBuilder
		// @A9: bipush 41 (0x29)
		// @AB: invokevirtual java.lang.StringBuilder.append(char)java.lang.StringBuilder
		// @AE: invokevirtual java.lang.StringBuilder.toString()java.lang.String
		// @B1: invokestatic game.C_100181_cf.func_105695_a(java.lang.Throwable, java.lang.String)game.C_100170_cm
		// @B4: athrow
	}
	
	final void func_105474_a(int arg0, int arg1, Graphics arg2, int arg3)
	{
		// @00: aload_0
		// @01: bipush -71 (0xB9)
		// @03: invokespecial game.C_100252_pn.func_105497_b(byte)void
		// @06: bipush -120 (0x88)
		// @08: bipush -42 (0xD6)
		// @0A: iload_1
		// @0B: isub
		// @0C: bipush 49 (0x31)
		// @0E: idiv
		// @0F: idiv
		// @10: istore #5
		// @12: aload_3
		// @13: aload_0
		// @14: getfield java.awt.Image game.C_100252_pn.field_105482_f
		// @17: iload_2
		// @18: iload #4
		// @1A: aload_0
		// @1B: invokevirtual java.awt.Graphics.drawImage(java.awt.Image, int, int, java.awt.image.ImageObserver)boolean
		// @1E: pop
		// @1F: goto @73
		// @22: astore #5
		// @24: aload #5
		// @26: new java.lang.StringBuilder
		// @29: dup
		// @2A: invokespecial java.lang.StringBuilder.<init>()void
		// @2D: getstatic java.lang.String[] game.C_100252_pn.field_105516_z
		// @30: bipush 23 (0x17)
		// @32: aaload
		// @33: invokevirtual java.lang.StringBuilder.append(java.lang.String)java.lang.StringBuilder
		// @36: iload_1
		// @37: invokevirtual java.lang.StringBuilder.append(int)java.lang.StringBuilder
		// @3A: bipush 44 (0x2C)
		// @3C: invokevirtual java.lang.StringBuilder.append(char)java.lang.StringBuilder
		// @3F: iload_2
		// @40: invokevirtual java.lang.StringBuilder.append(int)java.lang.StringBuilder
		// @43: bipush 44 (0x2C)
		// @45: invokevirtual java.lang.StringBuilder.append(char)java.lang.StringBuilder
		// @48: aload_3
		// @49: ifnull @55
		// @4C: getstatic java.lang.String[] game.C_100252_pn.field_105516_z
		// @4F: iconst_3
		// @50: aaload
		// @51: goto @5A
		// @54: athrow
		// @55: getstatic java.lang.String[] game.C_100252_pn.field_105516_z
		// @58: iconst_1
		// @59: aaload
		// @5A: invokevirtual java.lang.StringBuilder.append(java.lang.String)java.lang.StringBuilder
		// @5D: bipush 44 (0x2C)
		// @5F: invokevirtual java.lang.StringBuilder.append(char)java.lang.StringBuilder
		// @62: iload #4
		// @64: invokevirtual java.lang.StringBuilder.append(int)java.lang.StringBuilder
		// @67: bipush 41 (0x29)
		// @69: invokevirtual java.lang.StringBuilder.append(char)java.lang.StringBuilder
		// @6C: invokevirtual java.lang.StringBuilder.toString()java.lang.String
		// @6F: invokestatic game.C_100181_cf.func_105695_a(java.lang.Throwable, java.lang.String)game.C_100170_cm
		// @72: athrow
		// @73: return
	}
	
	public final synchronized void addConsumer(ImageConsumer arg0)
	{
		// @00: aload_0
		// @01: aload_1
		// @02: putfield java.awt.image.ImageConsumer game.C_100252_pn.field_105510_u
		// @05: aload_1
		// @06: aload_0
		// @07: getfield int game.C_100252_pn.field_105483_g
		// @0A: aload_0
		// @0B: getfield int game.C_100252_pn.field_105491_i
		// @0E: invokeinterface java.awt.image.ImageConsumer.setDimensions(int, int)void
		// @13: aload_1
		// @14: aconst_null
		// @15: invokeinterface java.awt.image.ImageConsumer.setProperties(java.util.Hashtable)void
		// @1A: aload_1
		// @1B: aload_0
		// @1C: getfield java.awt.image.ColorModel game.C_100252_pn.field_105502_n
		// @1F: invokeinterface java.awt.image.ImageConsumer.setColorModel(java.awt.image.ColorModel)void
		// @24: aload_1
		// @25: bipush 14 (0x0E)
		// @27: invokeinterface java.awt.image.ImageConsumer.setHints(int)void
		// @2C: goto @61
		// @2F: astore_2
		// @30: aload_2
		// @31: new java.lang.StringBuilder
		// @34: dup
		// @35: invokespecial java.lang.StringBuilder.<init>()void
		// @38: getstatic java.lang.String[] game.C_100252_pn.field_105516_z
		// @3B: iconst_2
		// @3C: aaload
		// @3D: invokevirtual java.lang.StringBuilder.append(java.lang.String)java.lang.StringBuilder
		// @40: aload_1
		// @41: ifnull @4D
		// @44: getstatic java.lang.String[] game.C_100252_pn.field_105516_z
		// @47: iconst_3
		// @48: aaload
		// @49: goto @52
		// @4C: athrow
		// @4D: getstatic java.lang.String[] game.C_100252_pn.field_105516_z
		// @50: iconst_1
		// @51: aaload
		// @52: invokevirtual java.lang.StringBuilder.append(java.lang.String)java.lang.StringBuilder
		// @55: bipush 41 (0x29)
		// @57: invokevirtual java.lang.StringBuilder.append(char)java.lang.StringBuilder
		// @5A: invokevirtual java.lang.StringBuilder.toString()java.lang.String
		// @5D: invokestatic game.C_100181_cf.func_105695_a(java.lang.Throwable, java.lang.String)game.C_100170_cm
		// @60: athrow
		// @61: return
	}
	
	static final void func_105492_a(boolean arg0, Applet arg1, String arg2, String arg3, long arg4)
	{
		// @000: iload_0
		// @001: ifeq @005
		// @004: return
		// @005: aload_1
		// @006: getstatic java.lang.String[] game.C_100252_pn.field_105516_z
		// @009: bipush 15 (0x0F)
		// @00B: aaload
		// @00C: invokevirtual java.applet.Applet.getParameter(java.lang.String)java.lang.String
		// @00F: astore #6
		// @011: new java.lang.StringBuilder
		// @014: dup
		// @015: invokespecial java.lang.StringBuilder.<init>()void
		// @018: aload_2
		// @019: invokevirtual java.lang.StringBuilder.append(java.lang.String)java.lang.StringBuilder
		// @01C: ldc "="
		// @01E: invokevirtual java.lang.StringBuilder.append(java.lang.String)java.lang.StringBuilder
		// @021: aload_3
		// @022: invokevirtual java.lang.StringBuilder.append(java.lang.String)java.lang.StringBuilder
		// @025: getstatic java.lang.String[] game.C_100252_pn.field_105516_z
		// @028: bipush 17 (0x11)
		// @02A: aaload
		// @02B: invokevirtual java.lang.StringBuilder.append(java.lang.String)java.lang.StringBuilder
		// @02E: aload #6
		// @030: invokevirtual java.lang.StringBuilder.append(java.lang.String)java.lang.StringBuilder
		// @033: invokevirtual java.lang.StringBuilder.toString()java.lang.String
		// @036: astore #7
		// @038: ldc2_w -1
		// @03B: lload #4
		// @03D: ldc2_w -1
		// @040: lxor
		// @041: lcmp
		// @042: iflt @087
		// @045: new java.lang.StringBuilder
		// @048: dup
		// @049: invokespecial java.lang.StringBuilder.<init>()void
		// @04C: aload #7
		// @04E: invokevirtual java.lang.StringBuilder.append(java.lang.String)java.lang.StringBuilder
		// @051: getstatic java.lang.String[] game.C_100252_pn.field_105516_z
		// @054: bipush 14 (0x0E)
		// @056: aaload
		// @057: invokevirtual java.lang.StringBuilder.append(java.lang.String)java.lang.StringBuilder
		// @05A: bipush -46 (0xD2)
		// @05C: ldc2_w 1000
		// @05F: lload #4
		// @061: lmul
		// @062: bipush -94 (0xA2)
		// @064: invokestatic game.C_100198_qn.func_105828_a(byte)long
		// @067: ladd
		// @068: invokestatic game.C_100159_sn.func_105399_a(byte, long)java.lang.String
		// @06B: invokevirtual java.lang.StringBuilder.append(java.lang.String)java.lang.StringBuilder
		// @06E: getstatic java.lang.String[] game.C_100252_pn.field_105516_z
		// @071: bipush 19 (0x13)
		// @073: aaload
		// @074: invokevirtual java.lang.StringBuilder.append(java.lang.String)java.lang.StringBuilder
		// @077: lload #4
		// @079: invokevirtual java.lang.StringBuilder.append(long)java.lang.StringBuilder
		// @07C: invokevirtual java.lang.StringBuilder.toString()java.lang.String
		// @07F: astore #7
		// @081: getstatic int game.SteelSentinels.field_105275_O
		// @084: ifeq @0A1
		// @087: new java.lang.StringBuilder
		// @08A: dup
		// @08B: invokespecial java.lang.StringBuilder.<init>()void
		// @08E: aload #7
		// @090: invokevirtual java.lang.StringBuilder.append(java.lang.String)java.lang.StringBuilder
		// @093: getstatic java.lang.String[] game.C_100252_pn.field_105516_z
		// @096: bipush 16 (0x10)
		// @098: aaload
		// @099: invokevirtual java.lang.StringBuilder.append(java.lang.String)java.lang.StringBuilder
		// @09C: invokevirtual java.lang.StringBuilder.toString()java.lang.String
		// @09F: astore #7
		// @0A1: new java.lang.StringBuilder
		// @0A4: dup
		// @0A5: invokespecial java.lang.StringBuilder.<init>()void
		// @0A8: getstatic java.lang.String[] game.C_100252_pn.field_105516_z
		// @0AB: bipush 18 (0x12)
		// @0AD: aaload
		// @0AE: invokevirtual java.lang.StringBuilder.append(java.lang.String)java.lang.StringBuilder
		// @0B1: aload #7
		// @0B3: invokevirtual java.lang.StringBuilder.append(java.lang.String)java.lang.StringBuilder
		// @0B6: ldc "\""
		// @0B8: invokevirtual java.lang.StringBuilder.append(java.lang.String)java.lang.StringBuilder
		// @0BB: invokevirtual java.lang.StringBuilder.toString()java.lang.String
		// @0BE: sipush -1492 (0xFA2C)
		// @0C1: aload_1
		// @0C2: invokestatic game.C_100175_cl.func_105615_a(java.lang.String, int, java.applet.Applet)void
		// @0C5: goto @0CA
		// @0C8: astore #6
		// @0CA: goto @149
		// @0CD: astore #6
		// @0CF: aload #6
		// @0D1: new java.lang.StringBuilder
		// @0D4: dup
		// @0D5: invokespecial java.lang.StringBuilder.<init>()void
		// @0D8: getstatic java.lang.String[] game.C_100252_pn.field_105516_z
		// @0DB: bipush 20 (0x14)
		// @0DD: aaload
		// @0DE: invokevirtual java.lang.StringBuilder.append(java.lang.String)java.lang.StringBuilder
		// @0E1: iload_0
		// @0E2: invokevirtual java.lang.StringBuilder.append(boolean)java.lang.StringBuilder
		// @0E5: bipush 44 (0x2C)
		// @0E7: invokevirtual java.lang.StringBuilder.append(char)java.lang.StringBuilder
		// @0EA: aload_1
		// @0EB: ifnull @0F7
		// @0EE: getstatic java.lang.String[] game.C_100252_pn.field_105516_z
		// @0F1: iconst_3
		// @0F2: aaload
		// @0F3: goto @0FC
		// @0F6: athrow
		// @0F7: getstatic java.lang.String[] game.C_100252_pn.field_105516_z
		// @0FA: iconst_1
		// @0FB: aaload
		// @0FC: invokevirtual java.lang.StringBuilder.append(java.lang.String)java.lang.StringBuilder
		// @0FF: bipush 44 (0x2C)
		// @101: invokevirtual java.lang.StringBuilder.append(char)java.lang.StringBuilder
		// @104: aload_2
		// @105: ifnull @111
		// @108: getstatic java.lang.String[] game.C_100252_pn.field_105516_z
		// @10B: iconst_3
		// @10C: aaload
		// @10D: goto @116
		// @110: athrow
		// @111: getstatic java.lang.String[] game.C_100252_pn.field_105516_z
		// @114: iconst_1
		// @115: aaload
		// @116: invokevirtual java.lang.StringBuilder.append(java.lang.String)java.lang.StringBuilder
		// @119: bipush 44 (0x2C)
		// @11B: invokevirtual java.lang.StringBuilder.append(char)java.lang.StringBuilder
		// @11E: aload_3
		// @11F: ifnull @12B
		// @122: getstatic java.lang.String[] game.C_100252_pn.field_105516_z
		// @125: iconst_3
		// @126: aaload
		// @127: goto @130
		// @12A: athrow
		// @12B: getstatic java.lang.String[] game.C_100252_pn.field_105516_z
		// @12E: iconst_1
		// @12F: aaload
		// @130: invokevirtual java.lang.StringBuilder.append(java.lang.String)java.lang.StringBuilder
		// @133: bipush 44 (0x2C)
		// @135: invokevirtual java.lang.StringBuilder.append(char)java.lang.StringBuilder
		// @138: lload #4
		// @13A: invokevirtual java.lang.StringBuilder.append(long)java.lang.StringBuilder
		// @13D: bipush 41 (0x29)
		// @13F: invokevirtual java.lang.StringBuilder.append(char)java.lang.StringBuilder
		// @142: invokevirtual java.lang.StringBuilder.toString()java.lang.String
		// @145: invokestatic game.C_100181_cf.func_105695_a(java.lang.Throwable, java.lang.String)game.C_100170_cm
		// @148: athrow
		// @149: return
	}
	
	public final boolean imageUpdate(Image arg0, int arg1, int arg2, int arg3, int arg4, int arg5)
	{
		// @00: iconst_1
		// @01: ireturn
		// @02: astore #7
		// @04: aload #7
		// @06: new java.lang.StringBuilder
		// @09: dup
		// @0A: invokespecial java.lang.StringBuilder.<init>()void
		// @0D: getstatic java.lang.String[] game.C_100252_pn.field_105516_z
		// @10: bipush 12 (0x0C)
		// @12: aaload
		// @13: invokevirtual java.lang.StringBuilder.append(java.lang.String)java.lang.StringBuilder
		// @16: aload_1
		// @17: ifnull @23
		// @1A: getstatic java.lang.String[] game.C_100252_pn.field_105516_z
		// @1D: iconst_3
		// @1E: aaload
		// @1F: goto @28
		// @22: athrow
		// @23: getstatic java.lang.String[] game.C_100252_pn.field_105516_z
		// @26: iconst_1
		// @27: aaload
		// @28: invokevirtual java.lang.StringBuilder.append(java.lang.String)java.lang.StringBuilder
		// @2B: bipush 44 (0x2C)
		// @2D: invokevirtual java.lang.StringBuilder.append(char)java.lang.StringBuilder
		// @30: iload_2
		// @31: invokevirtual java.lang.StringBuilder.append(int)java.lang.StringBuilder
		// @34: bipush 44 (0x2C)
		// @36: invokevirtual java.lang.StringBuilder.append(char)java.lang.StringBuilder
		// @39: iload_3
		// @3A: invokevirtual java.lang.StringBuilder.append(int)java.lang.StringBuilder
		// @3D: bipush 44 (0x2C)
		// @3F: invokevirtual java.lang.StringBuilder.append(char)java.lang.StringBuilder
		// @42: iload #4
		// @44: invokevirtual java.lang.StringBuilder.append(int)java.lang.StringBuilder
		// @47: bipush 44 (0x2C)
		// @49: invokevirtual java.lang.StringBuilder.append(char)java.lang.StringBuilder
		// @4C: iload #5
		// @4E: invokevirtual java.lang.StringBuilder.append(int)java.lang.StringBuilder
		// @51: bipush 44 (0x2C)
		// @53: invokevirtual java.lang.StringBuilder.append(char)java.lang.StringBuilder
		// @56: iload #6
		// @58: invokevirtual java.lang.StringBuilder.append(int)java.lang.StringBuilder
		// @5B: bipush 41 (0x29)
		// @5D: invokevirtual java.lang.StringBuilder.append(char)java.lang.StringBuilder
		// @60: invokevirtual java.lang.StringBuilder.toString()java.lang.String
		// @63: invokestatic game.C_100181_cf.func_105695_a(java.lang.Throwable, java.lang.String)game.C_100170_cm
		// @66: athrow
	}
	
	public static void func_105496_e(int arg0)
	{
		// @00: aconst_null
		// @01: putstatic java.lang.String game.C_100252_pn.field_105514_q
		// @04: aconst_null
		// @05: putstatic java.lang.String[] game.C_100252_pn.field_105505_m
		// @08: aconst_null
		// @09: putstatic byte[] game.C_100252_pn.field_105509_v
		// @0C: aconst_null
		// @0D: putstatic java.lang.String[] game.C_100252_pn.field_105506_j
		// @10: aconst_null
		// @11: putstatic game.C_100201_qj game.C_100252_pn.field_105504_l
		// @14: aconst_null
		// @15: putstatic game.C_100037_wb[] game.C_100252_pn.field_105511_t
		// @18: aconst_null
		// @19: putstatic java.lang.String game.C_100252_pn.field_105507_k
		// @1C: aconst_null
		// @1D: putstatic game.C_100302_ka game.C_100252_pn.field_105515_p
		// @20: aconst_null
		// @21: putstatic game.C_100037_wb game.C_100252_pn.field_105513_r
		// @24: iload_0
		// @25: iconst_m1
		// @26: if_icmpeq @2E
		// @29: bipush -51 (0xCD)
		// @2B: putstatic int game.C_100252_pn.field_105503_o
		// @2E: goto @53
		// @31: astore_1
		// @32: aload_1
		// @33: new java.lang.StringBuilder
		// @36: dup
		// @37: invokespecial java.lang.StringBuilder.<init>()void
		// @3A: getstatic java.lang.String[] game.C_100252_pn.field_105516_z
		// @3D: bipush 13 (0x0D)
		// @3F: aaload
		// @40: invokevirtual java.lang.StringBuilder.append(java.lang.String)java.lang.StringBuilder
		// @43: iload_0
		// @44: invokevirtual java.lang.StringBuilder.append(int)java.lang.StringBuilder
		// @47: bipush 41 (0x29)
		// @49: invokevirtual java.lang.StringBuilder.append(char)java.lang.StringBuilder
		// @4C: invokevirtual java.lang.StringBuilder.toString()java.lang.String
		// @4F: invokestatic game.C_100181_cf.func_105695_a(java.lang.Throwable, java.lang.String)game.C_100170_cm
		// @52: athrow
		// @53: return
	}
	
	public final void requestTopDownLeftRightResend(ImageConsumer arg0)
	{
		// @0: return
	}
	
	static final boolean func_105499_a(boolean arg0)
	{
		// @00: iload_0
		// @01: ifeq @06
		// @04: iconst_1
		// @05: ireturn
		// @06: getstatic game.C_100302_ka game.C_100266_me.field_106650_d
		// @09: ifnull @11
		// @0C: iconst_1
		// @0D: goto @12
		// @10: athrow
		// @11: iconst_0
		// @12: ireturn
		// @13: astore_1
		// @14: aload_1
		// @15: new java.lang.StringBuilder
		// @18: dup
		// @19: invokespecial java.lang.StringBuilder.<init>()void
		// @1C: getstatic java.lang.String[] game.C_100252_pn.field_105516_z
		// @1F: bipush 11 (0x0B)
		// @21: aaload
		// @22: invokevirtual java.lang.StringBuilder.append(java.lang.String)java.lang.StringBuilder
		// @25: iload_0
		// @26: invokevirtual java.lang.StringBuilder.append(boolean)java.lang.StringBuilder
		// @29: bipush 41 (0x29)
		// @2B: invokevirtual java.lang.StringBuilder.append(char)java.lang.StringBuilder
		// @2E: invokevirtual java.lang.StringBuilder.toString()java.lang.String
		// @31: invokestatic game.C_100181_cf.func_105695_a(java.lang.Throwable, java.lang.String)game.C_100170_cm
		// @34: athrow
	}
	
	public final synchronized void removeConsumer(ImageConsumer arg0)
	{
		// @00: aload_0
		// @01: getfield java.awt.image.ImageConsumer game.C_100252_pn.field_105510_u
		// @04: aload_1
		// @05: if_acmpne @0D
		// @08: aload_0
		// @09: aconst_null
		// @0A: putfield java.awt.image.ImageConsumer game.C_100252_pn.field_105510_u
		// @0D: goto @42
		// @10: astore_2
		// @11: aload_2
		// @12: new java.lang.StringBuilder
		// @15: dup
		// @16: invokespecial java.lang.StringBuilder.<init>()void
		// @19: getstatic java.lang.String[] game.C_100252_pn.field_105516_z
		// @1C: iconst_5
		// @1D: aaload
		// @1E: invokevirtual java.lang.StringBuilder.append(java.lang.String)java.lang.StringBuilder
		// @21: aload_1
		// @22: ifnull @2E
		// @25: getstatic java.lang.String[] game.C_100252_pn.field_105516_z
		// @28: iconst_3
		// @29: aaload
		// @2A: goto @33
		// @2D: athrow
		// @2E: getstatic java.lang.String[] game.C_100252_pn.field_105516_z
		// @31: iconst_1
		// @32: aaload
		// @33: invokevirtual java.lang.StringBuilder.append(java.lang.String)java.lang.StringBuilder
		// @36: bipush 41 (0x29)
		// @38: invokevirtual java.lang.StringBuilder.append(char)java.lang.StringBuilder
		// @3B: invokevirtual java.lang.StringBuilder.toString()java.lang.String
		// @3E: invokestatic game.C_100181_cf.func_105695_a(java.lang.Throwable, java.lang.String)game.C_100170_cm
		// @41: athrow
		// @42: return
	}
	
	private final synchronized void func_105497_b(byte arg0)
	{
		// @00: aload_0
		// @01: getfield java.awt.image.ImageConsumer game.C_100252_pn.field_105510_u
		// @04: ifnonnull @08
		// @07: return
		// @08: aload_0
		// @09: getfield java.awt.image.ImageConsumer game.C_100252_pn.field_105510_u
		// @0C: iconst_0
		// @0D: iconst_0
		// @0E: aload_0
		// @0F: getfield int game.C_100252_pn.field_105483_g
		// @12: aload_0
		// @13: getfield int game.C_100252_pn.field_105491_i
		// @16: aload_0
		// @17: getfield java.awt.image.ColorModel game.C_100252_pn.field_105502_n
		// @1A: aload_0
		// @1B: getfield int[] game.C_100252_pn.field_105486_b
		// @1E: iconst_0
		// @1F: aload_0
		// @20: getfield int game.C_100252_pn.field_105483_g
		// @23: invokeinterface java.awt.image.ImageConsumer.setPixels(int, int, int, int, java.awt.image.ColorModel, int[], int, int)void
		// @28: iload_1
		// @29: bipush -71 (0xB9)
		// @2B: if_icmpeq @38
		// @2E: aload_0
		// @2F: bipush -12 (0xF4)
		// @31: invokespecial game.C_100252_pn.func_105497_b(byte)void
		// @34: goto @38
		// @37: athrow
		// @38: aload_0
		// @39: getfield java.awt.image.ImageConsumer game.C_100252_pn.field_105510_u
		// @3C: iconst_2
		// @3D: invokeinterface java.awt.image.ImageConsumer.imageComplete(int)void
		// @42: goto @67
		// @45: astore_2
		// @46: aload_2
		// @47: new java.lang.StringBuilder
		// @4A: dup
		// @4B: invokespecial java.lang.StringBuilder.<init>()void
		// @4E: getstatic java.lang.String[] game.C_100252_pn.field_105516_z
		// @51: bipush 9 (0x09)
		// @53: aaload
		// @54: invokevirtual java.lang.StringBuilder.append(java.lang.String)java.lang.StringBuilder
		// @57: iload_1
		// @58: invokevirtual java.lang.StringBuilder.append(int)java.lang.StringBuilder
		// @5B: bipush 41 (0x29)
		// @5D: invokevirtual java.lang.StringBuilder.append(char)java.lang.StringBuilder
		// @60: invokevirtual java.lang.StringBuilder.toString()java.lang.String
		// @63: invokestatic game.C_100181_cf.func_105695_a(java.lang.Throwable, java.lang.String)game.C_100170_cm
		// @66: athrow
		// @67: return
	}
	
	static final void func_105500_a(int arg0, int arg1, int arg2, byte arg3, int arg4, boolean arg5, boolean arg6, boolean arg7, boolean arg8, boolean arg9)
	{
		// @000: getstatic int game.SteelSentinels.field_105275_O
		// @003: istore #11
		// @005: iload #9
		// @007: ifne @089
		// @00A: getstatic int game.C_100196_rb.field_105819_e
		// @00D: iconst_m1
		// @00E: ixor
		// @00F: getstatic int game.C_100260_mc.field_102234_jc
		// @012: iconst_m1
		// @013: ixor
		// @014: if_icmpne @02C
		// @017: goto @01B
		// @01A: athrow
		// @01B: getstatic int game.C_100196_rb.field_105821_c
		// @01E: iconst_m1
		// @01F: ixor
		// @020: getstatic int game.C_100103_eh.field_104666_b
		// @023: iconst_m1
		// @024: ixor
		// @025: if_icmpeq @089
		// @028: goto @02C
		// @02B: athrow
		// @02C: getstatic int game.C_100196_rb.field_105821_c
		// @02F: iconst_m1
		// @030: ixor
		// @031: getstatic game.C_100185_rm game.C_100049_vf.field_104206_l
		// @034: getfield int game.C_100185_rm.field_105491_i
		// @037: iconst_m1
		// @038: ixor
		// @039: if_icmpne @089
		// @03C: goto @040
		// @03F: athrow
		// @040: getstatic int game.C_100196_rb.field_105819_e
		// @043: getstatic game.C_100185_rm game.C_100049_vf.field_104206_l
		// @046: getfield int game.C_100185_rm.field_105483_g
		// @049: if_icmpne @089
		// @04C: goto @050
		// @04F: athrow
		// @050: aconst_null
		// @051: getstatic game.C_100211_qd game.C_100068_vc.field_104342_d
		// @054: if_acmpne @080
		// @057: goto @05B
		// @05A: athrow
		// @05B: getstatic game.C_100211_qd game.SteelSentinels.field_105274_N
		// @05E: ifnonnull @072
		// @061: goto @065
		// @064: athrow
		// @065: iconst_5
		// @066: invokestatic game.C_100303_kk.func_104785_b(byte)void
		// @069: iload #11
		// @06B: ifeq @089
		// @06E: goto @072
		// @071: athrow
		// @072: iconst_0
		// @073: iconst_1
		// @074: invokestatic game.C_100239_oi.func_102291_a(int, boolean)void
		// @077: iload #11
		// @079: ifeq @089
		// @07C: goto @080
		// @07F: athrow
		// @080: iconst_0
		// @081: iconst_0
		// @082: invokestatic game.C_100239_oi.func_102291_a(int, boolean)void
		// @085: goto @089
		// @088: athrow
		// @089: iload #9
		// @08B: ifne @0A3
		// @08E: sipush -640 (0xFD80)
		// @091: getstatic int game.C_100260_mc.field_102234_jc
		// @094: iadd
		// @095: iconst_2
		// @096: idiv
		// @097: putstatic int game.C_100268_mk.field_106671_a
		// @09A: iload #11
		// @09C: ifeq @0AD
		// @09F: goto @0A3
		// @0A2: athrow
		// @0A3: getstatic int game.C_100146_bf.field_105132_j
		// @0A6: putstatic int game.C_100268_mk.field_106671_a
		// @0A9: goto @0AD
		// @0AC: athrow
		// @0AD: bipush 76 (0x4C)
		// @0AF: iload #9
		// @0B1: invokestatic game.C_100240_oj.func_106301_a(byte, boolean)void
		// @0B4: iconst_0
		// @0B5: getstatic int game.C_100015_wh.field_103782_d
		// @0B8: if_icmplt @0BF
		// @0BB: goto @0C9
		// @0BE: athrow
		// @0BF: iconst_0
		// @0C0: iload #5
		// @0C2: iload #4
		// @0C4: iload #9
		// @0C6: invokestatic game.C_100006_fj.func_103614_a(int, boolean, int, boolean)void
		// @0C9: getstatic game.C_100302_ka game.C_100084_ug.field_104481_e
		// @0CC: iconst_1
		// @0CD: putfield int game.C_100302_ka.field_101850_Fb
		// @0D0: getstatic game.C_100302_ka game.C_100084_ug.field_104481_e
		// @0D3: getstatic game.C_100302_ka game.C_100316_lc.field_102409_C
		// @0D6: getfield int game.C_100302_ka.field_101829_Db
		// @0D9: putfield int game.C_100302_ka.field_101829_Db
		// @0DC: getstatic int game.C_100102_w.field_104635_b
		// @0DF: iconst_m1
		// @0E0: ixor
		// @0E1: iconst_m1
		// @0E2: if_icmplt @0E9
		// @0E5: goto @0F5
		// @0E8: athrow
		// @0E9: sipush -20168 (0xB138)
		// @0EC: iload #4
		// @0EE: iload #9
		// @0F0: iload #5
		// @0F2: invokestatic game.C_100189_ri.func_105749_a(int, int, boolean, boolean)void
		// @0F5: getstatic int game.C_100100_i.field_102014_hc
		// @0F8: ifgt @0FF
		// @0FB: goto @10C
		// @0FE: athrow
		// @0FF: iload #5
		// @101: bipush 56 (0x38)
		// @103: iload #4
		// @105: iload #8
		// @107: iload #9
		// @109: invokestatic game.C_100115_ej.func_102026_a(boolean, byte, int, boolean, boolean)void
		// @10C: getstatic boolean game.C_100003_ga.field_103535_w
		// @10F: ifeq @129
		// @112: getstatic game.C_100211_qd game.C_100068_vc.field_104342_d
		// @115: getfield int game.C_100211_qd.field_102160_Zb
		// @118: iconst_m1
		// @119: ixor
		// @11A: getstatic game.C_100211_qd game.C_100068_vc.field_104342_d
		// @11D: getfield int game.C_100211_qd.field_102138_ec
		// @120: iconst_m1
		// @121: ixor
		// @122: if_icmpge @150
		// @125: goto @129
		// @128: athrow
		// @129: getstatic game.C_100302_ka game.C_100099_fb.field_103050_z
		// @12C: iconst_1
		// @12D: putfield boolean game.C_100302_ka.field_101864_W
		// @130: getstatic game.C_100115_ej game.C_100179_ch.field_100811_n
		// @133: getfield game.C_100302_ka game.C_100115_ej.field_102040_Zb
		// @136: aconst_null
		// @137: putfield java.lang.String game.C_100302_ka.field_101890_ab
		// @13A: iload #7
		// @13C: bipush 123 (0x7B)
		// @13E: getstatic game.C_100115_ej game.C_100179_ch.field_100811_n
		// @141: iload #4
		// @143: iload_0
		// @144: invokestatic game.C_100031_gl.func_103961_a(boolean, int, game.C_100115_ej, int, int)void
		// @147: iload #11
		// @149: ifeq @171
		// @14C: goto @150
		// @14F: athrow
		// @150: getstatic game.C_100302_ka game.C_100099_fb.field_103050_z
		// @153: iconst_0
		// @154: putfield boolean game.C_100302_ka.field_101864_W
		// @157: getstatic game.C_100115_ej game.C_100179_ch.field_100811_n
		// @15A: getfield game.C_100302_ka game.C_100115_ej.field_102040_Zb
		// @15D: getstatic java.lang.String game.C_100320_hh.field_102911_U
		// @160: putfield java.lang.String game.C_100302_ka.field_101890_ab
		// @163: iconst_1
		// @164: getstatic game.C_100115_ej game.C_100179_ch.field_100811_n
		// @167: getfield game.C_100302_ka game.C_100115_ej.field_102036_Wb
		// @16A: invokestatic game.C_100107_u.func_104760_a(boolean, game.C_100302_ka)void
		// @16D: goto @171
		// @170: athrow
		// @171: iload #7
		// @173: iload #4
		// @175: iload_2
		// @176: iconst_0
		// @177: iload #6
		// @179: iload_0
		// @17A: iload_1
		// @17B: invokestatic game.C_100305_km.func_103227_a(boolean, int, int, int, boolean, int, int)void
		// @17E: iload #7
		// @180: bipush 68 (0x44)
		// @182: getstatic game.C_100115_ej game.C_100009_fg.field_103654_g
		// @185: iload #4
		// @187: iload_0
		// @188: invokestatic game.C_100031_gl.func_103961_a(boolean, int, game.C_100115_ej, int, int)void
		// @18B: getstatic int game.C_100132_td.field_104984_i
		// @18E: iconst_1
		// @18F: iadd
		// @190: putstatic int game.C_100132_td.field_104984_i
		// @193: iload_3
		// @194: bipush -2 (0xFE)
		// @196: if_icmplt @1A4
		// @199: aconst_null
		// @19A: checkcast game.C_100037_wb[]
		// @19D: putstatic game.C_100037_wb[] game.C_100252_pn.field_105511_t
		// @1A0: goto @1A4
		// @1A3: athrow
		// @1A4: goto @222
		// @1A7: astore #10
		// @1A9: aload #10
		// @1AB: new java.lang.StringBuilder
		// @1AE: dup
		// @1AF: invokespecial java.lang.StringBuilder.<init>()void
		// @1B2: getstatic java.lang.String[] game.C_100252_pn.field_105516_z
		// @1B5: bipush 10 (0x0A)
		// @1B7: aaload
		// @1B8: invokevirtual java.lang.StringBuilder.append(java.lang.String)java.lang.StringBuilder
		// @1BB: iload_0
		// @1BC: invokevirtual java.lang.StringBuilder.append(int)java.lang.StringBuilder
		// @1BF: bipush 44 (0x2C)
		// @1C1: invokevirtual java.lang.StringBuilder.append(char)java.lang.StringBuilder
		// @1C4: iload_1
		// @1C5: invokevirtual java.lang.StringBuilder.append(int)java.lang.StringBuilder
		// @1C8: bipush 44 (0x2C)
		// @1CA: invokevirtual java.lang.StringBuilder.append(char)java.lang.StringBuilder
		// @1CD: iload_2
		// @1CE: invokevirtual java.lang.StringBuilder.append(int)java.lang.StringBuilder
		// @1D1: bipush 44 (0x2C)
		// @1D3: invokevirtual java.lang.StringBuilder.append(char)java.lang.StringBuilder
		// @1D6: iload_3
		// @1D7: invokevirtual java.lang.StringBuilder.append(int)java.lang.StringBuilder
		// @1DA: bipush 44 (0x2C)
		// @1DC: invokevirtual java.lang.StringBuilder.append(char)java.lang.StringBuilder
		// @1DF: iload #4
		// @1E1: invokevirtual java.lang.StringBuilder.append(int)java.lang.StringBuilder
		// @1E4: bipush 44 (0x2C)
		// @1E6: invokevirtual java.lang.StringBuilder.append(char)java.lang.StringBuilder
		// @1E9: iload #5
		// @1EB: invokevirtual java.lang.StringBuilder.append(boolean)java.lang.StringBuilder
		// @1EE: bipush 44 (0x2C)
		// @1F0: invokevirtual java.lang.StringBuilder.append(char)java.lang.StringBuilder
		// @1F3: iload #6
		// @1F5: invokevirtual java.lang.StringBuilder.append(boolean)java.lang.StringBuilder
		// @1F8: bipush 44 (0x2C)
		// @1FA: invokevirtual java.lang.StringBuilder.append(char)java.lang.StringBuilder
		// @1FD: iload #7
		// @1FF: invokevirtual java.lang.StringBuilder.append(boolean)java.lang.StringBuilder
		// @202: bipush 44 (0x2C)
		// @204: invokevirtual java.lang.StringBuilder.append(char)java.lang.StringBuilder
		// @207: iload #8
		// @209: invokevirtual java.lang.StringBuilder.append(boolean)java.lang.StringBuilder
		// @20C: bipush 44 (0x2C)
		// @20E: invokevirtual java.lang.StringBuilder.append(char)java.lang.StringBuilder
		// @211: iload #9
		// @213: invokevirtual java.lang.StringBuilder.append(boolean)java.lang.StringBuilder
		// @216: bipush 41 (0x29)
		// @218: invokevirtual java.lang.StringBuilder.append(char)java.lang.StringBuilder
		// @21B: invokevirtual java.lang.StringBuilder.toString()java.lang.String
		// @21E: invokestatic game.C_100181_cf.func_105695_a(java.lang.Throwable, java.lang.String)game.C_100170_cm
		// @221: athrow
		// @222: return
	}
	
	static final int func_105493_a(int arg0, int[] arg1)
	{
		// @00: getstatic int game.SteelSentinels.field_105275_O
		// @03: istore #4
		// @05: iconst_0
		// @06: istore_2
		// @07: iload_0
		// @08: bipush 47 (0x2F)
		// @0A: if_icmpgt @1B
		// @0D: bipush 47 (0x2F)
		// @0F: aconst_null
		// @10: checkcast int[]
		// @13: invokestatic game.C_100252_pn.func_105493_a(int, int[])int
		// @16: pop
		// @17: goto @1B
		// @1A: athrow
		// @1B: iconst_0
		// @1C: istore_3
		// @1D: aload_1
		// @1E: arraylength
		// @1F: iload_3
		// @20: if_icmple @3B
		// @23: iload_2
		// @24: aload_1
		// @25: iload_3
		// @26: iaload
		// @27: bipush -106 (0x96)
		// @29: invokestatic game.C_100303_kk.func_104778_a(int, byte)int
		// @2C: iadd
		// @2D: iload #4
		// @2F: ifne @3C
		// @32: istore_2
		// @33: iinc #3 +1
		// @36: iload #4
		// @38: ifeq @1D
		// @3B: iload_2
		// @3C: ireturn
		// @3D: astore_2
		// @3E: aload_2
		// @3F: new java.lang.StringBuilder
		// @42: dup
		// @43: invokespecial java.lang.StringBuilder.<init>()void
		// @46: getstatic java.lang.String[] game.C_100252_pn.field_105516_z
		// @49: iconst_4
		// @4A: aaload
		// @4B: invokevirtual java.lang.StringBuilder.append(java.lang.String)java.lang.StringBuilder
		// @4E: iload_0
		// @4F: invokevirtual java.lang.StringBuilder.append(int)java.lang.StringBuilder
		// @52: bipush 44 (0x2C)
		// @54: invokevirtual java.lang.StringBuilder.append(char)java.lang.StringBuilder
		// @57: aload_1
		// @58: ifnull @64
		// @5B: getstatic java.lang.String[] game.C_100252_pn.field_105516_z
		// @5E: iconst_3
		// @5F: aaload
		// @60: goto @69
		// @63: athrow
		// @64: getstatic java.lang.String[] game.C_100252_pn.field_105516_z
		// @67: iconst_1
		// @68: aaload
		// @69: invokevirtual java.lang.StringBuilder.append(java.lang.String)java.lang.StringBuilder
		// @6C: bipush 41 (0x29)
		// @6E: invokevirtual java.lang.StringBuilder.append(char)java.lang.StringBuilder
		// @71: invokevirtual java.lang.StringBuilder.toString()java.lang.String
		// @74: invokestatic game.C_100181_cf.func_105695_a(java.lang.Throwable, java.lang.String)game.C_100170_cm
		// @77: athrow
	}
	
	public final void startProduction(ImageConsumer arg0)
	{
		// @00: aload_0
		// @01: aload_1
		// @02: invokevirtual game.C_100252_pn.addConsumer(java.awt.image.ImageConsumer)void
		// @05: goto @3B
		// @08: astore_2
		// @09: aload_2
		// @0A: new java.lang.StringBuilder
		// @0D: dup
		// @0E: invokespecial java.lang.StringBuilder.<init>()void
		// @11: getstatic java.lang.String[] game.C_100252_pn.field_105516_z
		// @14: bipush 22 (0x16)
		// @16: aaload
		// @17: invokevirtual java.lang.StringBuilder.append(java.lang.String)java.lang.StringBuilder
		// @1A: aload_1
		// @1B: ifnull @27
		// @1E: getstatic java.lang.String[] game.C_100252_pn.field_105516_z
		// @21: iconst_3
		// @22: aaload
		// @23: goto @2C
		// @26: athrow
		// @27: getstatic java.lang.String[] game.C_100252_pn.field_105516_z
		// @2A: iconst_1
		// @2B: aaload
		// @2C: invokevirtual java.lang.StringBuilder.append(java.lang.String)java.lang.StringBuilder
		// @2F: bipush 41 (0x29)
		// @31: invokevirtual java.lang.StringBuilder.append(char)java.lang.StringBuilder
		// @34: invokevirtual java.lang.StringBuilder.toString()java.lang.String
		// @37: invokestatic game.C_100181_cf.func_105695_a(java.lang.Throwable, java.lang.String)game.C_100170_cm
		// @3A: athrow
		// @3B: return
	}
	
	static
	{
		// @000: bipush 24 (0x18)
		// @002: anewarray java.lang.String
		// @005: dup
		// @006: iconst_0
		// @007: ldc "\u00199&9z"
		// @009: invokestatic game.C_100252_pn.func_105495_z(java.lang.String)char[]
		// @00C: invokestatic game.C_100252_pn.func_105494_z(char[])java.lang.String
		// @00F: aastore
		// @010: dup
		// @011: iconst_1
		// @012: ldc "\u0007\"d\u001c"
		// @014: invokestatic game.C_100252_pn.func_105495_z(java.lang.String)char[]
		// @017: invokestatic game.C_100252_pn.func_105494_z(char[])java.lang.String
		// @01A: aastore
		// @01B: dup
		// @01C: iconst_2
		// @01D: ldc "\u00199&\u00116\r\u0014g\u001e!\u001c:m\u0002z"
		// @01F: invokestatic game.C_100252_pn.func_105495_z(java.lang.String)char[]
		// @022: invokestatic game.C_100252_pn.func_105494_z(char[])java.lang.String
		// @025: aastore
		// @026: dup
		// @027: iconst_3
		// @028: ldc "\u0012y&^/"
		// @02A: invokestatic game.C_100252_pn.func_105495_z(java.lang.String)char[]
		// @02D: invokestatic game.C_100252_pn.func_105494_z(char[])java.lang.String
		// @030: aastore
		// @031: dup
		// @032: iconst_4
		// @033: ldc "\u00199&3z"
		// @035: invokestatic game.C_100252_pn.func_105495_z(java.lang.String)char[]
		// @038: invokestatic game.C_100252_pn.func_105494_z(char[])java.lang.String
		// @03B: aastore
		// @03C: dup
		// @03D: iconst_5
		// @03E: ldc "\u00199&\u00027\u00048~\u0015\u0011\u00069{\u0005?\u000c% "
		// @040: invokestatic game.C_100252_pn.func_105495_z(java.lang.String)char[]
		// @043: invokestatic game.C_100252_pn.func_105494_z(char[])java.lang.String
		// @046: aastore
		// @047: dup
		// @048: bipush 6 (0x06)
		// @04A: ldc "\u00199&2z"
		// @04C: invokestatic game.C_100252_pn.func_105495_z(java.lang.String)char[]
		// @04F: invokestatic game.C_100252_pn.func_105494_z(char[])java.lang.String
		// @052: aastore
		// @053: dup
		// @054: bipush 7 (0x07)
		// @056: ldc "Iz("
		// @058: invokestatic game.C_100252_pn.func_105495_z(java.lang.String)char[]
		// @05B: invokestatic game.C_100252_pn.func_105494_z(char[])java.lang.String
		// @05E: aastore
		// @05F: dup
		// @060: bipush 8 (0x08)
		// @062: ldc "\u00199&:z"
		// @064: invokestatic game.C_100252_pn.func_105495_z(java.lang.String)char[]
		// @067: invokestatic game.C_100252_pn.func_105494_z(char[])java.lang.String
		// @06A: aastore
		// @06B: dup
		// @06C: bipush 9 (0x09)
		// @06E: ldc "\u00199&7z"
		// @070: invokestatic game.C_100252_pn.func_105495_z(java.lang.String)char[]
		// @073: invokestatic game.C_100252_pn.func_105494_z(char[])java.lang.String
		// @076: aastore
		// @077: dup
		// @078: bipush 10 (0x0A)
		// @07A: ldc "\u00199&1z"
		// @07C: invokestatic game.C_100252_pn.func_105495_z(java.lang.String)char[]
		// @07F: invokestatic game.C_100252_pn.func_105494_z(char[])java.lang.String
		// @082: aastore
		// @083: dup
		// @084: bipush 11 (0x0B)
		// @086: ldc "\u00199&8z"
		// @088: invokestatic game.C_100252_pn.func_105495_z(java.lang.String)char[]
		// @08B: invokestatic game.C_100252_pn.func_105494_z(char[])java.lang.String
		// @08E: aastore
		// @08F: dup
		// @090: bipush 12 (0x0C)
		// @092: ldc "\u00199&\u0019?\u00080m%\"\r6|\u0015z"
		// @094: invokestatic game.C_100252_pn.func_105495_z(java.lang.String)char[]
		// @097: invokestatic game.C_100252_pn.func_105494_z(char[])java.lang.String
		// @09A: aastore
		// @09B: dup
		// @09C: bipush 13 (0x0D)
		// @09E: ldc "\u00199&5z"
		// @0A0: invokestatic game.C_100252_pn.func_105495_z(java.lang.String)char[]
		// @0A3: invokestatic game.C_100252_pn.func_105494_z(char[])java.lang.String
		// @0A6: aastore
		// @0A7: dup
		// @0A8: bipush 14 (0x0E)
		// @0AA: ldc "RwM\u0008\"\u0000%m\u0003o"
		// @0AC: invokestatic game.C_100252_pn.func_105495_z(java.lang.String)char[]
		// @0AF: invokestatic game.C_100252_pn.func_105494_z(char[])java.lang.String
		// @0B2: aastore
		// @0B3: dup
		// @0B4: bipush 15 (0x0F)
		// @0B6: ldc "\n8g\u001b;\u000c?g\u0003&"
		// @0B8: invokestatic game.C_100252_pn.func_105495_z(java.lang.String)char[]
		// @0BB: invokestatic game.C_100252_pn.func_105494_z(char[])java.lang.String
		// @0BE: aastore
		// @0BF: dup
		// @0C0: bipush 16 (0x10)
		// @0C2: ldc "RwL\u0019!\n6z\u0014i"
		// @0C4: invokestatic game.C_100252_pn.func_105495_z(java.lang.String)char[]
		// @0C7: invokestatic game.C_100252_pn.func_105494_z(char[])java.lang.String
		// @0CA: aastore
		// @0CB: dup
		// @0CC: bipush 17 (0x11)
		// @0CE: ldc "Rw~\u0015 \u001a>g\u001eoXl(\u00003\u001d?5_iI3g\u001d3\u000095"
		// @0D0: invokestatic game.C_100252_pn.func_105495_z(java.lang.String)char[]
		// @0D3: invokestatic game.C_100252_pn.func_105494_z(char[])java.lang.String
		// @0D6: aastore
		// @0D7: dup
		// @0D8: bipush 18 (0x12)
		// @0DA: ldc "\r8k\u0005?\u000c9|^1\u00068c\u00197Tu"
		// @0DC: invokestatic game.C_100252_pn.func_105495_z(java.lang.String)char[]
		// @0DF: invokestatic game.C_100252_pn.func_105494_z(char[])java.lang.String
		// @0E2: aastore
		// @0E3: dup
		// @0E4: bipush 19 (0x13)
		// @0E6: ldc "RwE\u0011*D\u0016o\u0015o"
		// @0E8: invokestatic game.C_100252_pn.func_105495_z(java.lang.String)char[]
		// @0EB: invokestatic game.C_100252_pn.func_105494_z(char[])java.lang.String
		// @0EE: aastore
		// @0EF: dup
		// @0F0: bipush 20 (0x14)
		// @0F2: ldc "\u00199&6z"
		// @0F4: invokestatic game.C_100252_pn.func_105495_z(java.lang.String)char[]
		// @0F7: invokestatic game.C_100252_pn.func_105494_z(char[])java.lang.String
		// @0FA: aastore
		// @0FB: dup
		// @0FC: bipush 21 (0x15)
		// @0FE: ldc "\u00199&\u0019!*8f\u0003'\u00042zX"
		// @100: invokestatic game.C_100252_pn.func_105495_z(java.lang.String)char[]
		// @103: invokestatic game.C_100252_pn.func_105494_z(char[])java.lang.String
		// @106: aastore
		// @107: dup
		// @108: bipush 22 (0x16)
		// @10A: ldc "\u00199&\u0003&\u0008%|  \u00063}\u0013&\u00008fX"
		// @10C: invokestatic game.C_100252_pn.func_105495_z(java.lang.String)char[]
		// @10F: invokestatic game.C_100252_pn.func_105494_z(char[])java.lang.String
		// @112: aastore
		// @113: dup
		// @114: bipush 23 (0x17)
		// @116: ldc "\u00199&4z"
		// @118: invokestatic game.C_100252_pn.func_105495_z(java.lang.String)char[]
		// @11B: invokestatic game.C_100252_pn.func_105494_z(char[])java.lang.String
		// @11E: aastore
		// @11F: putstatic java.lang.String[] game.C_100252_pn.field_105516_z
		// @122: ldc "=%qP3\u000e6a\u001e"
		// @124: invokestatic game.C_100252_pn.func_105495_z(java.lang.String)char[]
		// @127: invokestatic game.C_100252_pn.func_105494_z(char[])java.lang.String
		// @12A: putstatic java.lang.String game.C_100252_pn.field_105514_q
		// @12D: iconst_4
		// @12E: anewarray java.lang.String
		// @131: dup
		// @132: iconst_0
		// @133: ldc "'\u0016E5"
		// @135: invokestatic game.C_100252_pn.func_105495_z(java.lang.String)char[]
		// @138: invokestatic game.C_100252_pn.func_105494_z(char[])java.lang.String
		// @13B: aastore
		// @13C: dup
		// @13D: iconst_1
		// @13E: ldc "*\u001fI#\u0001 \u0004"
		// @140: invokestatic game.C_100252_pn.func_105495_z(java.lang.String)char[]
		// @143: invokestatic game.C_100252_pn.func_105494_z(char[])java.lang.String
		// @146: aastore
		// @147: dup
		// @148: iconst_2
		// @149: ldc ">\u0016^5"
		// @14B: invokestatic game.C_100252_pn.func_105495_z(java.lang.String)char[]
		// @14E: invokestatic game.C_100252_pn.func_105494_z(char[])java.lang.String
		// @151: aastore
		// @152: dup
		// @153: iconst_3
		// @154: ldc ":\u0014G\"\u0017"
		// @156: invokestatic game.C_100252_pn.func_105495_z(java.lang.String)char[]
		// @159: invokestatic game.C_100252_pn.func_105494_z(char[])java.lang.String
		// @15C: aastore
		// @15D: putstatic java.lang.String[] game.C_100252_pn.field_105505_m
		// @160: bipush 12 (0x0C)
		// @162: anewarray java.lang.String
		// @165: dup
		// @166: iconst_0
		// @167: ldc "#6f\u00053\u001b."
		// @169: invokestatic game.C_100252_pn.func_105495_z(java.lang.String)char[]
		// @16C: invokestatic game.C_100252_pn.func_105494_z(char[])java.lang.String
		// @16F: aastore
		// @170: dup
		// @171: iconst_1
		// @172: ldc "/2j\u0002'\u0008%q"
		// @174: invokestatic game.C_100252_pn.func_105495_z(java.lang.String)char[]
		// @177: invokestatic game.C_100252_pn.func_105494_z(char[])java.lang.String
		// @17A: aastore
		// @17B: dup
		// @17C: iconst_2
		// @17D: ldc "$6z\u0013:"
		// @17F: invokestatic game.C_100252_pn.func_105495_z(java.lang.String)char[]
		// @182: invokestatic game.C_100252_pn.func_105494_z(char[])java.lang.String
		// @185: aastore
		// @186: dup
		// @187: iconst_3
		// @188: ldc "('z\u0019>"
		// @18A: invokestatic game.C_100252_pn.func_105495_z(java.lang.String)char[]
		// @18D: invokestatic game.C_100252_pn.func_105494_z(char[])java.lang.String
		// @190: aastore
		// @191: dup
		// @192: iconst_4
		// @193: ldc "$6q"
		// @195: invokestatic game.C_100252_pn.func_105495_z(java.lang.String)char[]
		// @198: invokestatic game.C_100252_pn.func_105494_z(char[])java.lang.String
		// @19B: aastore
		// @19C: dup
		// @19D: iconst_5
		// @19E: ldc "#\"f\u0015"
		// @1A0: invokestatic game.C_100252_pn.func_105495_z(java.lang.String)char[]
		// @1A3: invokestatic game.C_100252_pn.func_105494_z(char[])java.lang.String
		// @1A6: aastore
		// @1A7: dup
		// @1A8: bipush 6 (0x06)
		// @1AA: ldc "#\"d\t"
		// @1AC: invokestatic game.C_100252_pn.func_105495_z(java.lang.String)char[]
		// @1AF: invokestatic game.C_100252_pn.func_105494_z(char[])java.lang.String
		// @1B2: aastore
		// @1B3: dup
		// @1B4: bipush 7 (0x07)
		// @1B6: ldc "(\"o\u0005!\u001d"
		// @1B8: invokestatic game.C_100252_pn.func_105495_z(java.lang.String)char[]
		// @1BB: invokestatic game.C_100252_pn.func_105494_z(char[])java.lang.String
		// @1BE: aastore
		// @1BF: dup
		// @1C0: bipush 8 (0x08)
		// @1C2: ldc ":2x\u00047\u00045m\u0002"
		// @1C4: invokestatic game.C_100252_pn.func_105495_z(java.lang.String)char[]
		// @1C7: invokestatic game.C_100252_pn.func_105494_z(char[])java.lang.String
		// @1CA: aastore
		// @1CB: dup
		// @1CC: bipush 9 (0x09)
		// @1CE: ldc "&4|\u001f0\u000c%"
		// @1D0: invokestatic game.C_100252_pn.func_105495_z(java.lang.String)char[]
		// @1D3: invokestatic game.C_100252_pn.func_105494_z(char[])java.lang.String
		// @1D6: aastore
		// @1D7: dup
		// @1D8: bipush 10 (0x0A)
		// @1DA: ldc "'8~\u0015?\u000b2z"
		// @1DC: invokestatic game.C_100252_pn.func_105495_z(java.lang.String)char[]
		// @1DF: invokestatic game.C_100252_pn.func_105494_z(char[])java.lang.String
		// @1E2: aastore
		// @1E3: dup
		// @1E4: bipush 11 (0x0B)
		// @1E6: ldc "-2k\u0015?\u000b2z"
		// @1E8: invokestatic game.C_100252_pn.func_105495_z(java.lang.String)char[]
		// @1EB: invokestatic game.C_100252_pn.func_105494_z(char[])java.lang.String
		// @1EE: aastore
		// @1EF: putstatic java.lang.String[] game.C_100252_pn.field_105506_j
		// @1F2: lconst_0
		// @1F3: putstatic long game.C_100252_pn.field_105508_w
		// @1F6: ldc "=?a\u0003r\u00196{\u0003%\u0006%lP1\u00069|\u0011;\u0007$(\u00027\u00192i\u00047\rwk\u00183\u001b6k\u00047\u001b$$P3\u00073(\u0007=\u001c;lP0\u000cwm\u0011!\u0010w|\u001fr\u000e\"m\u0003!"
		// @1F8: invokestatic game.C_100252_pn.func_105495_z(java.lang.String)char[]
		// @1FB: invokestatic game.C_100252_pn.func_105494_z(char[])java.lang.String
		// @1FE: putstatic java.lang.String game.C_100252_pn.field_105507_k
		// @201: return
	}
	
	private static char[] func_105495_z(String arg0)
	{
		// @00: aload_0
		// @01: invokevirtual java.lang.String.toCharArray()char[]
		// @04: dup
		// @05: arraylength
		// @06: iconst_2
		// @07: if_icmpge @13
		// @0A: dup
		// @0B: iconst_0
		// @0C: dup2
		// @0D: caload
		// @0E: bipush 82 (0x52)
		// @10: ixor
		// @11: i2c
		// @12: castore
		// @13: areturn
	}
	
	private static String func_105494_z(char[] arg0)
	{
		// @00: aload_0
		// @01: dup
		// @02: arraylength
		// @03: swap
		// @04: iconst_0
		// @05: istore_1
		// @06: goto @4C
		// @09: dup
		// @0A: iload_1
		// @0B: dup2
		// @0C: caload
		// @0D: iload_1
		// @0E: iconst_5
		// @0F: irem
		// @10: tableswitch def: @44, for 0: @30, for 1: @35, for 2: @3A, for 3: @3F
		// @30: bipush 105 (0x69)
		// @32: goto @46
		// @35: bipush 87 (0x57)
		// @37: goto @46
		// @3A: bipush 8 (0x08)
		// @3C: goto @46
		// @3F: bipush 112 (0x70)
		// @41: goto @46
		// @44: bipush 82 (0x52)
		// @46: ixor
		// @47: i2c
		// @48: castore
		// @49: iinc #1 +1
		// @4C: swap
		// @4D: dup_x1
		// @4E: iload_1
		// @4F: if_icmpgt @09
		// @52: new java.lang.String
		// @55: dup_x1
		// @56: swap
		// @57: invokespecial java.lang.String.<init>(char[])void
		// @5A: invokevirtual java.lang.String.intern()java.lang.String
		// @5D: areturn
	}
}
