package game;

import java.awt.event.FocusListener;
import java.awt.event.WindowListener;
import java.awt.event.FocusEvent;
import java.awt.event.WindowEvent;
import java.awt.Graphics;
import java.net.URL;
import java.awt.Canvas;
import java.applet.Applet;

public abstract class C_100152_bd extends Applet implements Runnable, FocusListener, WindowListener
{
	static C_100243_pd[] field_105199_d;
	static String field_105205_o;
	static String field_105208_j;
	static C_100302_ka field_105207_m;
	static C_100186_rl field_105206_l;
	boolean field_105212_p;
	static String field_105204_n;
	static C_100302_ka[] field_105211_i;
	static C_100317_lb field_105209_k;
	public static boolean field_105198_g;
	public static int field_105200_e;
	public static int field_105197_f;
	public static int field_105203_a;
	public static int field_105210_h;
	public static boolean field_105201_b;
	public static boolean field_105202_c;
	private static final String[] field_105213_z;
	
	public final void focusLost(FocusEvent arg0)
	{
		// @00: iconst_0
		// @01: putstatic boolean game.C_100080_b.field_104436_a
		// @04: goto @3B
		// @07: astore_2
		// @08: aload_2
		// @09: new java.lang.StringBuilder
		// @0C: dup
		// @0D: invokespecial java.lang.StringBuilder.<init>()void
		// @10: getstatic java.lang.String[] game.C_100152_bd.field_105213_z
		// @13: bipush 23 (0x17)
		// @15: aaload
		// @16: invokevirtual java.lang.StringBuilder.append(java.lang.String)java.lang.StringBuilder
		// @19: aload_1
		// @1A: ifnull @27
		// @1D: getstatic java.lang.String[] game.C_100152_bd.field_105213_z
		// @20: bipush 6 (0x06)
		// @22: aaload
		// @23: goto @2C
		// @26: athrow
		// @27: getstatic java.lang.String[] game.C_100152_bd.field_105213_z
		// @2A: iconst_0
		// @2B: aaload
		// @2C: invokevirtual java.lang.StringBuilder.append(java.lang.String)java.lang.StringBuilder
		// @2F: bipush 41 (0x29)
		// @31: invokevirtual java.lang.StringBuilder.append(char)java.lang.StringBuilder
		// @34: invokevirtual java.lang.StringBuilder.toString()java.lang.String
		// @37: invokestatic game.C_100181_cf.func_105695_a(java.lang.Throwable, java.lang.String)game.C_100170_cm
		// @3A: athrow
		// @3B: return
	}
	
	final boolean func_105192_e(int arg0)
	{
		// @00: getstatic int game.SteelSentinels.field_105275_O
		// @03: istore_3
		// @04: aload_0
		// @05: invokevirtual game.C_100152_bd.getDocumentBase()java.net.URL
		// @08: invokevirtual java.net.URL.getHost()java.lang.String
		// @0B: invokevirtual java.lang.String.toLowerCase()java.lang.String
		// @0E: astore_2
		// @0F: aload_2
		// @10: getstatic java.lang.String[] game.C_100152_bd.field_105213_z
		// @13: bipush 49 (0x31)
		// @15: aaload
		// @16: invokevirtual java.lang.String.equals(java.lang.Object)boolean
		// @19: ifne @2D
		// @1C: aload_2
		// @1D: getstatic java.lang.String[] game.C_100152_bd.field_105213_z
		// @20: bipush 47 (0x2F)
		// @22: aaload
		// @23: invokevirtual java.lang.String.endsWith(java.lang.String)boolean
		// @26: ifeq @2F
		// @29: goto @2D
		// @2C: athrow
		// @2D: iconst_1
		// @2E: ireturn
		// @2F: aload_2
		// @30: getstatic java.lang.String[] game.C_100152_bd.field_105213_z
		// @33: bipush 52 (0x34)
		// @35: aaload
		// @36: invokevirtual java.lang.String.equals(java.lang.Object)boolean
		// @39: ifne @51
		// @3C: aload_2
		// @3D: getstatic java.lang.String[] game.C_100152_bd.field_105213_z
		// @40: bipush 54 (0x36)
		// @42: aaload
		// @43: invokevirtual java.lang.String.endsWith(java.lang.String)boolean
		// @46: ifne @51
		// @49: goto @4D
		// @4C: athrow
		// @4D: goto @53
		// @50: athrow
		// @51: iconst_1
		// @52: ireturn
		// @53: aload_2
		// @54: getstatic java.lang.String[] game.C_100152_bd.field_105213_z
		// @57: bipush 50 (0x32)
		// @59: aaload
		// @5A: invokevirtual java.lang.String.endsWith(java.lang.String)boolean
		// @5D: ifeq @62
		// @60: iconst_1
		// @61: ireturn
		// @62: aload_2
		// @63: invokevirtual java.lang.String.length()int
		// @66: iconst_m1
		// @67: ixor
		// @68: iconst_m1
		// @69: if_icmpge @A6
		// @6C: aload_2
		// @6D: iconst_m1
		// @6E: aload_2
		// @6F: invokevirtual java.lang.String.length()int
		// @72: iadd
		// @73: invokevirtual java.lang.String.charAt(int)char
		// @76: bipush 48 (0x30)
		// @78: iload_3
		// @79: ifne @B8
		// @7C: if_icmplt @A6
		// @7F: goto @83
		// @82: athrow
		// @83: bipush 57 (0x39)
		// @85: aload_2
		// @86: aload_2
		// @87: invokevirtual java.lang.String.length()int
		// @8A: iconst_1
		// @8B: isub
		// @8C: invokevirtual java.lang.String.charAt(int)char
		// @8F: if_icmplt @A6
		// @92: goto @96
		// @95: athrow
		// @96: aload_2
		// @97: iconst_0
		// @98: aload_2
		// @99: invokevirtual java.lang.String.length()int
		// @9C: iconst_1
		// @9D: isub
		// @9E: invokevirtual java.lang.String.substring(int, int)java.lang.String
		// @A1: astore_2
		// @A2: iload_3
		// @A3: ifeq @62
		// @A6: aload_2
		// @A7: getstatic java.lang.String[] game.C_100152_bd.field_105213_z
		// @AA: bipush 48 (0x30)
		// @AC: aaload
		// @AD: invokevirtual java.lang.String.endsWith(java.lang.String)boolean
		// @B0: ifeq @B5
		// @B3: iconst_1
		// @B4: ireturn
		// @B5: iload_1
		// @B6: bipush 92 (0x5C)
		// @B8: if_icmpge @C6
		// @BB: aconst_null
		// @BC: checkcast java.lang.String
		// @BF: putstatic java.lang.String game.C_100152_bd.field_105205_o
		// @C2: goto @C6
		// @C5: athrow
		// @C6: aload_0
		// @C7: getstatic java.lang.String[] game.C_100152_bd.field_105213_z
		// @CA: bipush 53 (0x35)
		// @CC: aaload
		// @CD: bipush -27 (0xE5)
		// @CF: invokevirtual game.C_100152_bd.func_105182_a(java.lang.String, int)void
		// @D2: iconst_0
		// @D3: ireturn
		// @D4: astore_2
		// @D5: aload_2
		// @D6: new java.lang.StringBuilder
		// @D9: dup
		// @DA: invokespecial java.lang.StringBuilder.<init>()void
		// @DD: getstatic java.lang.String[] game.C_100152_bd.field_105213_z
		// @E0: bipush 51 (0x33)
		// @E2: aaload
		// @E3: invokevirtual java.lang.StringBuilder.append(java.lang.String)java.lang.StringBuilder
		// @E6: iload_1
		// @E7: invokevirtual java.lang.StringBuilder.append(int)java.lang.StringBuilder
		// @EA: bipush 41 (0x29)
		// @EC: invokevirtual java.lang.StringBuilder.append(char)java.lang.StringBuilder
		// @EF: invokevirtual java.lang.StringBuilder.toString()java.lang.String
		// @F2: invokestatic game.C_100181_cf.func_105695_a(java.lang.Throwable, java.lang.String)game.C_100170_cm
		// @F5: athrow
	}
	
	public final void windowActivated(WindowEvent arg0)
	{
		// @0: return
	}
	
	static final void func_105190_a(int arg0, int arg1, C_100201_qj arg2, int arg3, int arg4, String arg5, int arg6, int arg7, int arg8)
	{
		// @00: iload_0
		// @01: putstatic int game.C_100030_gm.field_103344_G
		// @04: aload #5
		// @06: putstatic java.lang.String game.C_100260_mc.field_102244_ac
		// @09: aload_2
		// @0A: putstatic game.C_100201_qj game.C_100252_pn.field_105504_l
		// @0D: iload_1
		// @0E: putstatic int game.C_100209_qb.field_102691_Hb
		// @11: iload #7
		// @13: putstatic int game.C_100325_id.field_101487_j
		// @16: iload_3
		// @17: putstatic int game.C_100187_rk.field_100834_r
		// @1A: iload #8
		// @1C: putstatic int game.C_100031_gl.field_103965_e
		// @1F: iload #6
		// @21: putstatic int game.C_100146_bf.field_105131_m
		// @24: iload #4
		// @26: iconst_m1
		// @27: if_icmpeq @35
		// @2A: aconst_null
		// @2B: checkcast java.lang.String
		// @2E: putstatic java.lang.String game.C_100152_bd.field_105208_j
		// @31: goto @35
		// @34: athrow
		// @35: new game.C_100311_le
		// @38: dup
		// @39: invokespecial game.C_100311_le.<init>()void
		// @3C: putstatic game.C_100104_v game.C_100311_le.field_104714_w
		// @3F: new game.C_100178_cg
		// @42: dup
		// @43: aload_2
		// @44: invokespecial game.C_100178_cg.<init>(game.C_100201_qj)void
		// @47: putstatic game.C_100178_cg game.C_100163_sf.field_105439_c
		// @4A: new game.C_100208_qg
		// @4D: dup
		// @4E: getstatic game.C_100104_v game.C_100311_le.field_104714_w
		// @51: getstatic game.C_100178_cg game.C_100163_sf.field_105439_c
		// @54: invokespecial game.C_100208_qg.<init>(game.C_100104_v, game.C_100178_cg)void
		// @57: putstatic game.C_100208_qg game.C_100271_mj.field_103440_O
		// @5A: goto @F2
		// @5D: astore #9
		// @5F: aload #9
		// @61: new java.lang.StringBuilder
		// @64: dup
		// @65: invokespecial java.lang.StringBuilder.<init>()void
		// @68: getstatic java.lang.String[] game.C_100152_bd.field_105213_z
		// @6B: bipush 21 (0x15)
		// @6D: aaload
		// @6E: invokevirtual java.lang.StringBuilder.append(java.lang.String)java.lang.StringBuilder
		// @71: iload_0
		// @72: invokevirtual java.lang.StringBuilder.append(int)java.lang.StringBuilder
		// @75: bipush 44 (0x2C)
		// @77: invokevirtual java.lang.StringBuilder.append(char)java.lang.StringBuilder
		// @7A: iload_1
		// @7B: invokevirtual java.lang.StringBuilder.append(int)java.lang.StringBuilder
		// @7E: bipush 44 (0x2C)
		// @80: invokevirtual java.lang.StringBuilder.append(char)java.lang.StringBuilder
		// @83: aload_2
		// @84: ifnull @91
		// @87: getstatic java.lang.String[] game.C_100152_bd.field_105213_z
		// @8A: bipush 6 (0x06)
		// @8C: aaload
		// @8D: goto @96
		// @90: athrow
		// @91: getstatic java.lang.String[] game.C_100152_bd.field_105213_z
		// @94: iconst_0
		// @95: aaload
		// @96: invokevirtual java.lang.StringBuilder.append(java.lang.String)java.lang.StringBuilder
		// @99: bipush 44 (0x2C)
		// @9B: invokevirtual java.lang.StringBuilder.append(char)java.lang.StringBuilder
		// @9E: iload_3
		// @9F: invokevirtual java.lang.StringBuilder.append(int)java.lang.StringBuilder
		// @A2: bipush 44 (0x2C)
		// @A4: invokevirtual java.lang.StringBuilder.append(char)java.lang.StringBuilder
		// @A7: iload #4
		// @A9: invokevirtual java.lang.StringBuilder.append(int)java.lang.StringBuilder
		// @AC: bipush 44 (0x2C)
		// @AE: invokevirtual java.lang.StringBuilder.append(char)java.lang.StringBuilder
		// @B1: aload #5
		// @B3: ifnull @C0
		// @B6: getstatic java.lang.String[] game.C_100152_bd.field_105213_z
		// @B9: bipush 6 (0x06)
		// @BB: aaload
		// @BC: goto @C5
		// @BF: athrow
		// @C0: getstatic java.lang.String[] game.C_100152_bd.field_105213_z
		// @C3: iconst_0
		// @C4: aaload
		// @C5: invokevirtual java.lang.StringBuilder.append(java.lang.String)java.lang.StringBuilder
		// @C8: bipush 44 (0x2C)
		// @CA: invokevirtual java.lang.StringBuilder.append(char)java.lang.StringBuilder
		// @CD: iload #6
		// @CF: invokevirtual java.lang.StringBuilder.append(int)java.lang.StringBuilder
		// @D2: bipush 44 (0x2C)
		// @D4: invokevirtual java.lang.StringBuilder.append(char)java.lang.StringBuilder
		// @D7: iload #7
		// @D9: invokevirtual java.lang.StringBuilder.append(int)java.lang.StringBuilder
		// @DC: bipush 44 (0x2C)
		// @DE: invokevirtual java.lang.StringBuilder.append(char)java.lang.StringBuilder
		// @E1: iload #8
		// @E3: invokevirtual java.lang.StringBuilder.append(int)java.lang.StringBuilder
		// @E6: bipush 41 (0x29)
		// @E8: invokevirtual java.lang.StringBuilder.append(char)java.lang.StringBuilder
		// @EB: invokevirtual java.lang.StringBuilder.toString()java.lang.String
		// @EE: invokestatic game.C_100181_cf.func_105695_a(java.lang.Throwable, java.lang.String)game.C_100170_cm
		// @F1: athrow
		// @F2: return
	}
	
	public final void windowIconified(WindowEvent arg0)
	{
		// @0: return
	}
	
	final synchronized void func_105196_h(int arg0)
	{
		// @000: getstatic int game.SteelSentinels.field_105275_O
		// @003: istore #4
		// @005: getstatic java.awt.Canvas game.C_100034_gi.field_104033_a
		// @008: ifnonnull @00F
		// @00B: goto @02E
		// @00E: athrow
		// @00F: getstatic java.awt.Canvas game.C_100034_gi.field_104033_a
		// @012: aload_0
		// @013: invokevirtual java.awt.Canvas.removeFocusListener(java.awt.event.FocusListener)void
		// @016: getstatic java.awt.Canvas game.C_100034_gi.field_104033_a
		// @019: invokevirtual java.awt.Canvas.getParent()java.awt.Container
		// @01C: getstatic java.awt.Color java.awt.Color.black
		// @01F: invokevirtual java.awt.Container.setBackground(java.awt.Color)void
		// @022: getstatic java.awt.Canvas game.C_100034_gi.field_104033_a
		// @025: invokevirtual java.awt.Canvas.getParent()java.awt.Container
		// @028: getstatic java.awt.Canvas game.C_100034_gi.field_104033_a
		// @02B: invokevirtual java.awt.Container.remove(java.awt.Component)void
		// @02E: aconst_null
		// @02F: getstatic java.awt.Frame game.C_100137_bn.field_105039_m
		// @032: if_acmpne @065
		// @035: getstatic java.awt.Frame game.C_100227_af.field_106168_b
		// @038: ifnull @048
		// @03B: goto @03F
		// @03E: athrow
		// @03F: getstatic java.awt.Frame game.C_100227_af.field_106168_b
		// @042: astore_2
		// @043: iload #4
		// @045: ifeq @069
		// @048: aconst_null
		// @049: getstatic java.applet.Applet game.C_100107_u.field_104771_d
		// @04C: if_acmpne @05C
		// @04F: goto @053
		// @052: athrow
		// @053: getstatic game.C_100152_bd game.C_100272_mn.field_102428_L
		// @056: astore_2
		// @057: iload #4
		// @059: ifeq @069
		// @05C: getstatic java.applet.Applet game.C_100107_u.field_104771_d
		// @05F: astore_2
		// @060: iload #4
		// @062: ifeq @069
		// @065: getstatic java.awt.Frame game.C_100137_bn.field_105039_m
		// @068: astore_2
		// @069: aload_2
		// @06A: aconst_null
		// @06B: invokevirtual java.awt.Container.setLayout(java.awt.LayoutManager)void
		// @06E: new game.C_100212_qc
		// @071: dup
		// @072: aload_0
		// @073: invokespecial game.C_100212_qc.<init>(java.awt.Component)void
		// @076: putstatic java.awt.Canvas game.C_100034_gi.field_104033_a
		// @079: aload_2
		// @07A: getstatic java.awt.Canvas game.C_100034_gi.field_104033_a
		// @07D: invokevirtual java.awt.Container.add(java.awt.Component)java.awt.Component
		// @080: pop
		// @081: getstatic java.awt.Canvas game.C_100034_gi.field_104033_a
		// @084: getstatic int game.C_100270_mi.field_102282_cc
		// @087: getstatic int game.C_100165_sh.field_100769_s
		// @08A: invokevirtual java.awt.Canvas.setSize(int, int)void
		// @08D: getstatic java.awt.Canvas game.C_100034_gi.field_104033_a
		// @090: iconst_1
		// @091: invokevirtual java.awt.Canvas.setVisible(boolean)void
		// @094: aload_2
		// @095: getstatic java.awt.Frame game.C_100227_af.field_106168_b
		// @098: if_acmpeq @0B0
		// @09B: getstatic java.awt.Canvas game.C_100034_gi.field_104033_a
		// @09E: getstatic int game.C_100227_af.field_106166_d
		// @0A1: getstatic int game.C_100058_dg.field_101580_s
		// @0A4: invokevirtual java.awt.Canvas.setLocation(int, int)void
		// @0A7: iload #4
		// @0A9: ifeq @0CD
		// @0AC: goto @0B0
		// @0AF: athrow
		// @0B0: getstatic java.awt.Frame game.C_100227_af.field_106168_b
		// @0B3: invokevirtual java.awt.Frame.getInsets()java.awt.Insets
		// @0B6: astore_3
		// @0B7: getstatic java.awt.Canvas game.C_100034_gi.field_104033_a
		// @0BA: getstatic int game.C_100227_af.field_106166_d
		// @0BD: aload_3
		// @0BE: getfield int java.awt.Insets.left
		// @0C1: iadd
		// @0C2: getstatic int game.C_100058_dg.field_101580_s
		// @0C5: aload_3
		// @0C6: getfield int java.awt.Insets.top
		// @0C9: iadd
		// @0CA: invokevirtual java.awt.Canvas.setLocation(int, int)void
		// @0CD: iload_1
		// @0CE: ifeq @0DB
		// @0D1: iconst_1
		// @0D2: bipush 18 (0x12)
		// @0D4: invokestatic game.C_100152_bd.func_105184_a(boolean, int)void
		// @0D7: goto @0DB
		// @0DA: athrow
		// @0DB: getstatic java.awt.Canvas game.C_100034_gi.field_104033_a
		// @0DE: aload_0
		// @0DF: invokevirtual java.awt.Canvas.addFocusListener(java.awt.event.FocusListener)void
		// @0E2: getstatic java.awt.Canvas game.C_100034_gi.field_104033_a
		// @0E5: invokevirtual java.awt.Canvas.requestFocus()void
		// @0E8: iconst_1
		// @0E9: putstatic boolean game.C_100080_b.field_104436_a
		// @0EC: iconst_1
		// @0ED: putstatic boolean game.C_100299_kd.field_107018_F
		// @0F0: iconst_1
		// @0F1: putstatic boolean game.C_100226_ae.field_106154_h
		// @0F4: iconst_0
		// @0F5: putstatic boolean game.C_100188_rj.field_105736_d
		// @0F8: bipush -21 (0xEB)
		// @0FA: invokestatic game.C_100198_qn.func_105828_a(byte)long
		// @0FD: putstatic long game.C_100001_ge.field_100571_j
		// @100: goto @125
		// @103: astore_2
		// @104: aload_2
		// @105: new java.lang.StringBuilder
		// @108: dup
		// @109: invokespecial java.lang.StringBuilder.<init>()void
		// @10C: getstatic java.lang.String[] game.C_100152_bd.field_105213_z
		// @10F: bipush 55 (0x37)
		// @111: aaload
		// @112: invokevirtual java.lang.StringBuilder.append(java.lang.String)java.lang.StringBuilder
		// @115: iload_1
		// @116: invokevirtual java.lang.StringBuilder.append(int)java.lang.StringBuilder
		// @119: bipush 41 (0x29)
		// @11B: invokevirtual java.lang.StringBuilder.append(char)java.lang.StringBuilder
		// @11E: invokevirtual java.lang.StringBuilder.toString()java.lang.String
		// @121: invokestatic game.C_100181_cf.func_105695_a(java.lang.Throwable, java.lang.String)game.C_100170_cm
		// @124: athrow
		// @125: return
	}
	
	final void func_105183_a(int arg0, int arg1, int arg2, String arg3, int arg4, int arg5, int arg6)
	{
		// @000: getstatic int game.SteelSentinels.field_105275_O
		// @003: istore #9
		// @005: aconst_null
		// @006: getstatic game.C_100152_bd game.C_100272_mn.field_102428_L
		// @009: if_acmpeq @044
		// @00C: getstatic int game.C_100161_sd.field_105427_c
		// @00F: iconst_1
		// @010: iadd
		// @011: putstatic int game.C_100161_sd.field_105427_c
		// @014: getstatic int game.C_100161_sd.field_105427_c
		// @017: iconst_3
		// @018: if_icmpge @023
		// @01B: goto @01F
		// @01E: athrow
		// @01F: goto @030
		// @022: athrow
		// @023: aload_0
		// @024: getstatic java.lang.String[] game.C_100152_bd.field_105213_z
		// @027: bipush 27 (0x1B)
		// @029: aaload
		// @02A: bipush -72 (0xB8)
		// @02C: invokevirtual game.C_100152_bd.func_105182_a(java.lang.String, int)void
		// @02F: return
		// @030: aload_0
		// @031: invokevirtual game.C_100152_bd.getAppletContext()java.applet.AppletContext
		// @034: aload_0
		// @035: invokevirtual game.C_100152_bd.getDocumentBase()java.net.URL
		// @038: getstatic java.lang.String[] game.C_100152_bd.field_105213_z
		// @03B: bipush 28 (0x1C)
		// @03D: aaload
		// @03E: invokeinterface java.applet.AppletContext.showDocument(java.net.URL, java.lang.String)void
		// @043: return
		// @044: iconst_0
		// @045: putstatic int game.C_100227_af.field_106166_d
		// @048: iload #5
		// @04A: bipush 22 (0x16)
		// @04C: if_icmpgt @06C
		// @04F: bipush 24 (0x18)
		// @051: bipush 32 (0x20)
		// @053: aconst_null
		// @054: checkcast game.C_100201_qj
		// @057: bipush 97 (0x61)
		// @059: bipush 118 (0x76)
		// @05B: aconst_null
		// @05C: checkcast java.lang.String
		// @05F: bipush -46 (0xD2)
		// @061: bipush 125 (0x7D)
		// @063: bipush 44 (0x2C)
		// @065: invokestatic game.C_100152_bd.func_105190_a(int, int, game.C_100201_qj, int, int, java.lang.String, int, int, int)void
		// @068: goto @06C
		// @06B: athrow
		// @06C: iload_2
		// @06D: dup
		// @06E: putstatic int game.C_100270_mi.field_102282_cc
		// @071: putstatic int game.C_100340_je.field_102980_l
		// @074: iload_3
		// @075: putstatic int game.C_100095_fe.field_103386_R
		// @078: iconst_0
		// @079: putstatic int game.C_100058_dg.field_101580_s
		// @07C: aload_0
		// @07D: putstatic game.C_100152_bd game.C_100272_mn.field_102428_L
		// @080: iload #7
		// @082: dup
		// @083: putstatic int game.C_100165_sh.field_100769_s
		// @086: putstatic int game.C_100149_bi.field_105155_e
		// @089: iconst_0
		// @08A: invokestatic game.C_100206_qe.func_105938_b(boolean)java.applet.Applet
		// @08D: putstatic java.applet.Applet game.C_100254_pi.field_106447_g
		// @090: new game.C_100201_qj
		// @093: dup
		// @094: iload_1
		// @095: aload #4
		// @097: iload #6
		// @099: iconst_1
		// @09A: invokespecial game.C_100201_qj.<init>(int, java.lang.String, int, boolean)void
		// @09D: dup
		// @09E: putstatic game.C_100201_qj game.C_100178_cg.field_105692_a
		// @0A1: putstatic game.C_100201_qj game.C_100158_da.field_100593_e
		// @0A4: getstatic game.C_100201_qj game.C_100178_cg.field_105692_a
		// @0A7: iconst_1
		// @0A8: bipush 91 (0x5B)
		// @0AA: aload_0
		// @0AB: invokevirtual game.C_100201_qj.func_105856_a(int, int, java.lang.Runnable)game.C_100331_ie
		// @0AE: astore #8
		// @0B0: aload #8
		// @0B2: getfield int game.C_100331_ie.field_107293_f
		// @0B5: iconst_m1
		// @0B6: ixor
		// @0B7: iconst_m1
		// @0B8: if_icmpne @0D1
		// @0BB: ldc2_w 10
		// @0BE: bipush -125 (0x83)
		// @0C0: invokestatic game.C_100138_bo.func_100396_a(long, int)void
		// @0C3: iload #9
		// @0C5: ifne @0E9
		// @0C8: iload #9
		// @0CA: ifeq @0B0
		// @0CD: goto @0D1
		// @0D0: athrow
		// @0D1: goto @0E9
		// @0D4: astore #8
		// @0D6: iconst_1
		// @0D7: aconst_null
		// @0D8: aload #8
		// @0DA: invokestatic game.C_100036_gg.func_103142_a(int, java.lang.String, java.lang.Throwable)void
		// @0DD: aload_0
		// @0DE: getstatic java.lang.String[] game.C_100152_bd.field_105213_z
		// @0E1: bipush 26 (0x1A)
		// @0E3: aaload
		// @0E4: bipush -63 (0xC1)
		// @0E6: invokevirtual game.C_100152_bd.func_105182_a(java.lang.String, int)void
		// @0E9: goto @15C
		// @0EC: astore #8
		// @0EE: aload #8
		// @0F0: new java.lang.StringBuilder
		// @0F3: dup
		// @0F4: invokespecial java.lang.StringBuilder.<init>()void
		// @0F7: getstatic java.lang.String[] game.C_100152_bd.field_105213_z
		// @0FA: bipush 25 (0x19)
		// @0FC: aaload
		// @0FD: invokevirtual java.lang.StringBuilder.append(java.lang.String)java.lang.StringBuilder
		// @100: iload_1
		// @101: invokevirtual java.lang.StringBuilder.append(int)java.lang.StringBuilder
		// @104: bipush 44 (0x2C)
		// @106: invokevirtual java.lang.StringBuilder.append(char)java.lang.StringBuilder
		// @109: iload_2
		// @10A: invokevirtual java.lang.StringBuilder.append(int)java.lang.StringBuilder
		// @10D: bipush 44 (0x2C)
		// @10F: invokevirtual java.lang.StringBuilder.append(char)java.lang.StringBuilder
		// @112: iload_3
		// @113: invokevirtual java.lang.StringBuilder.append(int)java.lang.StringBuilder
		// @116: bipush 44 (0x2C)
		// @118: invokevirtual java.lang.StringBuilder.append(char)java.lang.StringBuilder
		// @11B: aload #4
		// @11D: ifnull @12A
		// @120: getstatic java.lang.String[] game.C_100152_bd.field_105213_z
		// @123: bipush 6 (0x06)
		// @125: aaload
		// @126: goto @12F
		// @129: athrow
		// @12A: getstatic java.lang.String[] game.C_100152_bd.field_105213_z
		// @12D: iconst_0
		// @12E: aaload
		// @12F: invokevirtual java.lang.StringBuilder.append(java.lang.String)java.lang.StringBuilder
		// @132: bipush 44 (0x2C)
		// @134: invokevirtual java.lang.StringBuilder.append(char)java.lang.StringBuilder
		// @137: iload #5
		// @139: invokevirtual java.lang.StringBuilder.append(int)java.lang.StringBuilder
		// @13C: bipush 44 (0x2C)
		// @13E: invokevirtual java.lang.StringBuilder.append(char)java.lang.StringBuilder
		// @141: iload #6
		// @143: invokevirtual java.lang.StringBuilder.append(int)java.lang.StringBuilder
		// @146: bipush 44 (0x2C)
		// @148: invokevirtual java.lang.StringBuilder.append(char)java.lang.StringBuilder
		// @14B: iload #7
		// @14D: invokevirtual java.lang.StringBuilder.append(int)java.lang.StringBuilder
		// @150: bipush 41 (0x29)
		// @152: invokevirtual java.lang.StringBuilder.append(char)java.lang.StringBuilder
		// @155: invokevirtual java.lang.StringBuilder.toString()java.lang.String
		// @158: invokestatic game.C_100181_cf.func_105695_a(java.lang.Throwable, java.lang.String)game.C_100170_cm
		// @15B: athrow
		// @15C: return
	}
	
	public final void windowDeiconified(WindowEvent arg0)
	{
		// @0: return
	}
	
	private final void func_105176_a(int arg0)
	{
		// @00: bipush -71 (0xB9)
		// @02: invokestatic game.C_100198_qn.func_105828_a(byte)long
		// @05: lstore_2
		// @06: getstatic long[] game.C_100270_mi.field_102262_dc
		// @09: getstatic int game.C_100017_wj.field_103814_f
		// @0C: laload
		// @0D: lstore #4
		// @0F: getstatic long[] game.C_100270_mi.field_102262_dc
		// @12: getstatic int game.C_100017_wj.field_103814_f
		// @15: lload_2
		// @16: lastore
		// @17: lload #4
		// @19: ldc2_w -1
		// @1C: lxor
		// @1D: ldc2_w -1
		// @20: lcmp
		// @21: ifeq @37
		// @24: lload #4
		// @26: ldc2_w -1
		// @29: lxor
		// @2A: lload_2
		// @2B: ldc2_w -1
		// @2E: lxor
		// @2F: lcmp
		// @30: ifle @37
		// @33: goto @37
		// @36: athrow
		// @37: bipush 31 (0x1F)
		// @39: getstatic int game.C_100017_wj.field_103814_f
		// @3C: iload_1
		// @3D: isub
		// @3E: iand
		// @3F: putstatic int game.C_100017_wj.field_103814_f
		// @42: aload_0
		// @43: dup
		// @44: astore #6
		// @46: monitorenter
		// @47: getstatic boolean game.C_100080_b.field_104436_a
		// @4A: putstatic boolean game.C_100299_kd.field_107018_F
		// @4D: aload #6
		// @4F: monitorexit
		// @50: goto @5B
		// @53: astore #7
		// @55: aload #6
		// @57: monitorexit
		// @58: aload #7
		// @5A: athrow
		// @5B: aload_0
		// @5C: bipush 110 (0x6E)
		// @5E: invokevirtual game.C_100152_bd.func_105175_b(int)void
		// @61: goto @86
		// @64: astore_2
		// @65: aload_2
		// @66: new java.lang.StringBuilder
		// @69: dup
		// @6A: invokespecial java.lang.StringBuilder.<init>()void
		// @6D: getstatic java.lang.String[] game.C_100152_bd.field_105213_z
		// @70: bipush 60 (0x3C)
		// @72: aaload
		// @73: invokevirtual java.lang.StringBuilder.append(java.lang.String)java.lang.StringBuilder
		// @76: iload_1
		// @77: invokevirtual java.lang.StringBuilder.append(int)java.lang.StringBuilder
		// @7A: bipush 41 (0x29)
		// @7C: invokevirtual java.lang.StringBuilder.append(char)java.lang.StringBuilder
		// @7F: invokevirtual java.lang.StringBuilder.toString()java.lang.String
		// @82: invokestatic game.C_100181_cf.func_105695_a(java.lang.Throwable, java.lang.String)game.C_100170_cm
		// @85: athrow
		// @86: return
	}
	
	public final void update(Graphics arg0)
	{
		// @00: aload_0
		// @01: aload_1
		// @02: invokevirtual game.C_100152_bd.paint(java.awt.Graphics)void
		// @05: goto @3C
		// @08: astore_2
		// @09: aload_2
		// @0A: new java.lang.StringBuilder
		// @0D: dup
		// @0E: invokespecial java.lang.StringBuilder.<init>()void
		// @11: getstatic java.lang.String[] game.C_100152_bd.field_105213_z
		// @14: bipush 19 (0x13)
		// @16: aaload
		// @17: invokevirtual java.lang.StringBuilder.append(java.lang.String)java.lang.StringBuilder
		// @1A: aload_1
		// @1B: ifnull @28
		// @1E: getstatic java.lang.String[] game.C_100152_bd.field_105213_z
		// @21: bipush 6 (0x06)
		// @23: aaload
		// @24: goto @2D
		// @27: athrow
		// @28: getstatic java.lang.String[] game.C_100152_bd.field_105213_z
		// @2B: iconst_0
		// @2C: aaload
		// @2D: invokevirtual java.lang.StringBuilder.append(java.lang.String)java.lang.StringBuilder
		// @30: bipush 41 (0x29)
		// @32: invokevirtual java.lang.StringBuilder.append(char)java.lang.StringBuilder
		// @35: invokevirtual java.lang.StringBuilder.toString()java.lang.String
		// @38: invokestatic game.C_100181_cf.func_105695_a(java.lang.Throwable, java.lang.String)game.C_100170_cm
		// @3B: athrow
		// @3C: return
	}
	
	static final boolean func_105185_d(byte arg0)
	{
		// @00: iload_0
		// @01: bipush 108 (0x6C)
		// @03: if_icmpgt @08
		// @06: iconst_1
		// @07: ireturn
		// @08: getstatic game.C_100208_qg game.C_100271_mj.field_103440_O
		// @0B: iconst_1
		// @0C: invokevirtual game.C_100208_qg.func_105946_a(boolean)boolean
		// @0F: ireturn
		// @10: astore_1
		// @11: aload_1
		// @12: new java.lang.StringBuilder
		// @15: dup
		// @16: invokespecial java.lang.StringBuilder.<init>()void
		// @19: getstatic java.lang.String[] game.C_100152_bd.field_105213_z
		// @1C: bipush 16 (0x10)
		// @1E: aaload
		// @1F: invokevirtual java.lang.StringBuilder.append(java.lang.String)java.lang.StringBuilder
		// @22: iload_0
		// @23: invokevirtual java.lang.StringBuilder.append(int)java.lang.StringBuilder
		// @26: bipush 41 (0x29)
		// @28: invokevirtual java.lang.StringBuilder.append(char)java.lang.StringBuilder
		// @2B: invokevirtual java.lang.StringBuilder.toString()java.lang.String
		// @2E: invokestatic game.C_100181_cf.func_105695_a(java.lang.Throwable, java.lang.String)game.C_100170_cm
		// @31: athrow
	}
	
	static final void func_105184_a(boolean arg0, int arg1)
	{
		// @00: iload_1
		// @01: putstatic int game.C_100148_bh.field_101798_C
		// @04: iload_0
		// @05: iconst_1
		// @06: if_icmpeq @10
		// @09: aconst_null
		// @0A: checkcast game.C_100243_pd[]
		// @0D: putstatic game.C_100243_pd[] game.C_100152_bd.field_105199_d
		// @10: goto @3E
		// @13: astore_2
		// @14: aload_2
		// @15: new java.lang.StringBuilder
		// @18: dup
		// @19: invokespecial java.lang.StringBuilder.<init>()void
		// @1C: getstatic java.lang.String[] game.C_100152_bd.field_105213_z
		// @1F: bipush 10 (0x0A)
		// @21: aaload
		// @22: invokevirtual java.lang.StringBuilder.append(java.lang.String)java.lang.StringBuilder
		// @25: iload_0
		// @26: invokevirtual java.lang.StringBuilder.append(boolean)java.lang.StringBuilder
		// @29: bipush 44 (0x2C)
		// @2B: invokevirtual java.lang.StringBuilder.append(char)java.lang.StringBuilder
		// @2E: iload_1
		// @2F: invokevirtual java.lang.StringBuilder.append(int)java.lang.StringBuilder
		// @32: bipush 41 (0x29)
		// @34: invokevirtual java.lang.StringBuilder.append(char)java.lang.StringBuilder
		// @37: invokevirtual java.lang.StringBuilder.toString()java.lang.String
		// @3A: invokestatic game.C_100181_cf.func_105695_a(java.lang.Throwable, java.lang.String)game.C_100170_cm
		// @3D: athrow
		// @3E: return
	}
	
	abstract void func_105180_d(int arg0);
	
	public final URL getCodeBase()
	{
		// @00: aconst_null
		// @01: getstatic java.awt.Frame game.C_100227_af.field_106168_b
		// @04: if_acmpne @0B
		// @07: goto @0D
		// @0A: athrow
		// @0B: aconst_null
		// @0C: areturn
		// @0D: aconst_null
		// @0E: getstatic java.applet.Applet game.C_100107_u.field_104771_d
		// @11: if_acmpeq @2A
		// @14: aload_0
		// @15: getstatic java.applet.Applet game.C_100107_u.field_104771_d
		// @18: if_acmpne @23
		// @1B: goto @1F
		// @1E: athrow
		// @1F: goto @2A
		// @22: athrow
		// @23: getstatic java.applet.Applet game.C_100107_u.field_104771_d
		// @26: invokevirtual java.applet.Applet.getCodeBase()java.net.URL
		// @29: areturn
		// @2A: aload_0
		// @2B: invokespecial java.applet.Applet.getCodeBase()java.net.URL
		// @2E: areturn
		// @2F: astore_1
		// @30: aload_1
		// @31: athrow
	}
	
	public final void start()
	{
		// @00: aload_0
		// @01: getstatic game.C_100152_bd game.C_100272_mn.field_102428_L
		// @04: if_acmpne @0D
		// @07: getstatic boolean game.C_100101_fc.field_103407_Z
		// @0A: ifeq @0E
		// @0D: return
		// @0E: lconst_0
		// @0F: putstatic long game.C_100252_pn.field_105508_w
		// @12: goto @21
		// @15: astore_1
		// @16: aload_1
		// @17: getstatic java.lang.String[] game.C_100152_bd.field_105213_z
		// @1A: bipush 22 (0x16)
		// @1C: aaload
		// @1D: invokestatic game.C_100181_cf.func_105695_a(java.lang.Throwable, java.lang.String)game.C_100170_cm
		// @20: athrow
		// @21: return
	}
	
	final void func_105182_a(String arg0, int arg1)
	{
		// @00: aload_0
		// @01: getfield boolean game.C_100152_bd.field_105212_p
		// @04: ifne @0A
		// @07: goto @0B
		// @0A: return
		// @0B: aload_0
		// @0C: iconst_1
		// @0D: putfield boolean game.C_100152_bd.field_105212_p
		// @10: getstatic java.io.PrintStream java.lang.System.out
		// @13: new java.lang.StringBuilder
		// @16: dup
		// @17: invokespecial java.lang.StringBuilder.<init>()void
		// @1A: getstatic java.lang.String[] game.C_100152_bd.field_105213_z
		// @1D: iconst_4
		// @1E: aaload
		// @1F: invokevirtual java.lang.StringBuilder.append(java.lang.String)java.lang.StringBuilder
		// @22: aload_1
		// @23: invokevirtual java.lang.StringBuilder.append(java.lang.String)java.lang.StringBuilder
		// @26: invokevirtual java.lang.StringBuilder.toString()java.lang.String
		// @29: invokevirtual java.io.PrintStream.println(java.lang.String)void
		// @2C: sipush 17228 (0x434C)
		// @2F: getstatic java.lang.String[] game.C_100152_bd.field_105213_z
		// @32: iconst_5
		// @33: aaload
		// @34: iconst_0
		// @35: invokestatic game.C_100206_qe.func_105938_b(boolean)java.applet.Applet
		// @38: invokestatic game.C_100175_cl.func_105614_a(int, java.lang.String, java.applet.Applet)java.lang.Object
		// @3B: pop
		// @3C: goto @40
		// @3F: astore_3
		// @40: iload_2
		// @41: bipush -18 (0xEE)
		// @43: if_icmplt @52
		// @46: aload_0
		// @47: aconst_null
		// @48: checkcast java.awt.event.WindowEvent
		// @4B: invokevirtual game.C_100152_bd.windowIconified(java.awt.event.WindowEvent)void
		// @4E: goto @52
		// @51: athrow
		// @52: aload_0
		// @53: invokevirtual game.C_100152_bd.getAppletContext()java.applet.AppletContext
		// @56: new java.net.URL
		// @59: dup
		// @5A: aload_0
		// @5B: invokevirtual game.C_100152_bd.getCodeBase()java.net.URL
		// @5E: new java.lang.StringBuilder
		// @61: dup
		// @62: invokespecial java.lang.StringBuilder.<init>()void
		// @65: getstatic java.lang.String[] game.C_100152_bd.field_105213_z
		// @68: iconst_4
		// @69: aaload
		// @6A: invokevirtual java.lang.StringBuilder.append(java.lang.String)java.lang.StringBuilder
		// @6D: aload_1
		// @6E: invokevirtual java.lang.StringBuilder.append(java.lang.String)java.lang.StringBuilder
		// @71: getstatic java.lang.String[] game.C_100152_bd.field_105213_z
		// @74: iconst_1
		// @75: aaload
		// @76: invokevirtual java.lang.StringBuilder.append(java.lang.String)java.lang.StringBuilder
		// @79: invokevirtual java.lang.StringBuilder.toString()java.lang.String
		// @7C: invokespecial java.net.URL.<init>(java.net.URL, java.lang.String)void
		// @7F: getstatic java.lang.String[] game.C_100152_bd.field_105213_z
		// @82: iconst_3
		// @83: aaload
		// @84: invokeinterface java.applet.AppletContext.showDocument(java.net.URL, java.lang.String)void
		// @89: goto @8D
		// @8C: astore_3
		// @8D: goto @CC
		// @90: astore_3
		// @91: aload_3
		// @92: new java.lang.StringBuilder
		// @95: dup
		// @96: invokespecial java.lang.StringBuilder.<init>()void
		// @99: getstatic java.lang.String[] game.C_100152_bd.field_105213_z
		// @9C: iconst_2
		// @9D: aaload
		// @9E: invokevirtual java.lang.StringBuilder.append(java.lang.String)java.lang.StringBuilder
		// @A1: aload_1
		// @A2: ifnull @AF
		// @A5: getstatic java.lang.String[] game.C_100152_bd.field_105213_z
		// @A8: bipush 6 (0x06)
		// @AA: aaload
		// @AB: goto @B4
		// @AE: athrow
		// @AF: getstatic java.lang.String[] game.C_100152_bd.field_105213_z
		// @B2: iconst_0
		// @B3: aaload
		// @B4: invokevirtual java.lang.StringBuilder.append(java.lang.String)java.lang.StringBuilder
		// @B7: bipush 44 (0x2C)
		// @B9: invokevirtual java.lang.StringBuilder.append(char)java.lang.StringBuilder
		// @BC: iload_2
		// @BD: invokevirtual java.lang.StringBuilder.append(int)java.lang.StringBuilder
		// @C0: bipush 41 (0x29)
		// @C2: invokevirtual java.lang.StringBuilder.append(char)java.lang.StringBuilder
		// @C5: invokevirtual java.lang.StringBuilder.toString()java.lang.String
		// @C8: invokestatic game.C_100181_cf.func_105695_a(java.lang.Throwable, java.lang.String)game.C_100170_cm
		// @CB: athrow
		// @CC: return
	}
	
	public final AppletContext getAppletContext()
	{
		// @00: getstatic java.awt.Frame game.C_100227_af.field_106168_b
		// @03: ifnull @08
		// @06: aconst_null
		// @07: areturn
		// @08: getstatic java.applet.Applet game.C_100107_u.field_104771_d
		// @0B: ifnull @24
		// @0E: aload_0
		// @0F: getstatic java.applet.Applet game.C_100107_u.field_104771_d
		// @12: if_acmpne @1D
		// @15: goto @19
		// @18: athrow
		// @19: goto @24
		// @1C: athrow
		// @1D: getstatic java.applet.Applet game.C_100107_u.field_104771_d
		// @20: invokevirtual java.applet.Applet.getAppletContext()java.applet.AppletContext
		// @23: areturn
		// @24: aload_0
		// @25: invokespecial java.applet.Applet.getAppletContext()java.applet.AppletContext
		// @28: areturn
		// @29: astore_1
		// @2A: aload_1
		// @2B: getstatic java.lang.String[] game.C_100152_bd.field_105213_z
		// @2E: bipush 17 (0x11)
		// @30: aaload
		// @31: invokestatic game.C_100181_cf.func_105695_a(java.lang.Throwable, java.lang.String)game.C_100170_cm
		// @34: athrow
	}
	
	public final void stop()
	{
		// @00: getstatic game.C_100152_bd game.C_100272_mn.field_102428_L
		// @03: aload_0
		// @04: if_acmpne @15
		// @07: getstatic boolean game.C_100101_fc.field_103407_Z
		// @0A: ifne @15
		// @0D: goto @11
		// @10: athrow
		// @11: goto @16
		// @14: athrow
		// @15: return
		// @16: bipush -25 (0xE7)
		// @18: invokestatic game.C_100198_qn.func_105828_a(byte)long
		// @1B: ldc2_w 4000
		// @1E: ladd
		// @1F: putstatic long game.C_100252_pn.field_105508_w
		// @22: goto @31
		// @25: astore_1
		// @26: aload_1
		// @27: getstatic java.lang.String[] game.C_100152_bd.field_105213_z
		// @2A: bipush 12 (0x0C)
		// @2C: aaload
		// @2D: invokestatic game.C_100181_cf.func_105695_a(java.lang.Throwable, java.lang.String)game.C_100170_cm
		// @30: athrow
		// @31: return
	}
	
	abstract void func_105194_f(int arg0);
	
	abstract void func_105193_c(int arg0);
	
	public final void focusGained(FocusEvent arg0)
	{
		// @00: iconst_1
		// @01: putstatic boolean game.C_100080_b.field_104436_a
		// @04: iconst_1
		// @05: putstatic boolean game.C_100226_ae.field_106154_h
		// @08: goto @3F
		// @0B: astore_2
		// @0C: aload_2
		// @0D: new java.lang.StringBuilder
		// @10: dup
		// @11: invokespecial java.lang.StringBuilder.<init>()void
		// @14: getstatic java.lang.String[] game.C_100152_bd.field_105213_z
		// @17: bipush 56 (0x38)
		// @19: aaload
		// @1A: invokevirtual java.lang.StringBuilder.append(java.lang.String)java.lang.StringBuilder
		// @1D: aload_1
		// @1E: ifnull @2B
		// @21: getstatic java.lang.String[] game.C_100152_bd.field_105213_z
		// @24: bipush 6 (0x06)
		// @26: aaload
		// @27: goto @30
		// @2A: athrow
		// @2B: getstatic java.lang.String[] game.C_100152_bd.field_105213_z
		// @2E: iconst_0
		// @2F: aaload
		// @30: invokevirtual java.lang.StringBuilder.append(java.lang.String)java.lang.StringBuilder
		// @33: bipush 41 (0x29)
		// @35: invokevirtual java.lang.StringBuilder.append(char)java.lang.StringBuilder
		// @38: invokevirtual java.lang.StringBuilder.toString()java.lang.String
		// @3B: invokestatic game.C_100181_cf.func_105695_a(java.lang.Throwable, java.lang.String)game.C_100170_cm
		// @3E: athrow
		// @3F: return
	}
	
	public final void destroy()
	{
		// @00: aload_0
		// @01: getstatic game.C_100152_bd game.C_100272_mn.field_102428_L
		// @04: if_acmpne @15
		// @07: getstatic boolean game.C_100101_fc.field_103407_Z
		// @0A: ifne @15
		// @0D: goto @11
		// @10: athrow
		// @11: goto @16
		// @14: athrow
		// @15: return
		// @16: bipush -37 (0xDB)
		// @18: invokestatic game.C_100198_qn.func_105828_a(byte)long
		// @1B: putstatic long game.C_100252_pn.field_105508_w
		// @1E: ldc2_w 5000
		// @21: bipush -122 (0x86)
		// @23: invokestatic game.C_100138_bo.func_100396_a(long, int)void
		// @26: aconst_null
		// @27: putstatic game.C_100201_qj game.C_100158_da.field_100593_e
		// @2A: aload_0
		// @2B: iconst_0
		// @2C: bipush -120 (0x88)
		// @2E: invokespecial game.C_100152_bd.func_105181_a(boolean, byte)void
		// @31: goto @40
		// @34: astore_1
		// @35: aload_1
		// @36: getstatic java.lang.String[] game.C_100152_bd.field_105213_z
		// @39: bipush 18 (0x12)
		// @3B: aaload
		// @3C: invokestatic game.C_100181_cf.func_105695_a(java.lang.Throwable, java.lang.String)game.C_100170_cm
		// @3F: athrow
		// @40: return
	}
	
	public final String getParameter(String arg0)
	{
		// @00: getstatic java.awt.Frame game.C_100227_af.field_106168_b
		// @03: ifnull @08
		// @06: aconst_null
		// @07: areturn
		// @08: aconst_null
		// @09: getstatic java.applet.Applet game.C_100107_u.field_104771_d
		// @0C: if_acmpeq @22
		// @0F: getstatic java.applet.Applet game.C_100107_u.field_104771_d
		// @12: aload_0
		// @13: if_acmpeq @22
		// @16: goto @1A
		// @19: athrow
		// @1A: getstatic java.applet.Applet game.C_100107_u.field_104771_d
		// @1D: aload_1
		// @1E: invokevirtual java.applet.Applet.getParameter(java.lang.String)java.lang.String
		// @21: areturn
		// @22: aload_0
		// @23: aload_1
		// @24: invokespecial java.applet.Applet.getParameter(java.lang.String)java.lang.String
		// @27: areturn
		// @28: astore_2
		// @29: aload_2
		// @2A: new java.lang.StringBuilder
		// @2D: dup
		// @2E: invokespecial java.lang.StringBuilder.<init>()void
		// @31: getstatic java.lang.String[] game.C_100152_bd.field_105213_z
		// @34: bipush 20 (0x14)
		// @36: aaload
		// @37: invokevirtual java.lang.StringBuilder.append(java.lang.String)java.lang.StringBuilder
		// @3A: aload_1
		// @3B: ifnull @48
		// @3E: getstatic java.lang.String[] game.C_100152_bd.field_105213_z
		// @41: bipush 6 (0x06)
		// @43: aaload
		// @44: goto @4D
		// @47: athrow
		// @48: getstatic java.lang.String[] game.C_100152_bd.field_105213_z
		// @4B: iconst_0
		// @4C: aaload
		// @4D: invokevirtual java.lang.StringBuilder.append(java.lang.String)java.lang.StringBuilder
		// @50: bipush 41 (0x29)
		// @52: invokevirtual java.lang.StringBuilder.append(char)java.lang.StringBuilder
		// @55: invokevirtual java.lang.StringBuilder.toString()java.lang.String
		// @58: invokestatic game.C_100181_cf.func_105695_a(java.lang.Throwable, java.lang.String)game.C_100170_cm
		// @5B: athrow
	}
	
	public final URL getDocumentBase()
	{
		// @00: getstatic java.awt.Frame game.C_100227_af.field_106168_b
		// @03: ifnonnull @0A
		// @06: goto @0C
		// @09: athrow
		// @0A: aconst_null
		// @0B: areturn
		// @0C: aconst_null
		// @0D: getstatic java.applet.Applet game.C_100107_u.field_104771_d
		// @10: if_acmpeq @29
		// @13: aload_0
		// @14: getstatic java.applet.Applet game.C_100107_u.field_104771_d
		// @17: if_acmpne @22
		// @1A: goto @1E
		// @1D: athrow
		// @1E: goto @29
		// @21: athrow
		// @22: getstatic java.applet.Applet game.C_100107_u.field_104771_d
		// @25: invokevirtual java.applet.Applet.getDocumentBase()java.net.URL
		// @28: areturn
		// @29: aload_0
		// @2A: invokespecial java.applet.Applet.getDocumentBase()java.net.URL
		// @2D: areturn
		// @2E: astore_1
		// @2F: aload_1
		// @30: getstatic java.lang.String[] game.C_100152_bd.field_105213_z
		// @33: bipush 11 (0x0B)
		// @35: aaload
		// @36: invokestatic game.C_100181_cf.func_105695_a(java.lang.Throwable, java.lang.String)game.C_100170_cm
		// @39: athrow
	}
	
	static final int func_105179_a(int arg0, int arg1)
	{
		// @00: getstatic int game.SteelSentinels.field_105275_O
		// @03: istore_3
		// @04: iload_1
		// @05: iconst_m1
		// @06: if_icmpeq @14
		// @09: aconst_null
		// @0A: checkcast game.C_100317_lb
		// @0D: putstatic game.C_100317_lb game.C_100152_bd.field_105209_k
		// @10: goto @14
		// @13: athrow
		// @14: iconst_0
		// @15: istore_2
		// @16: getstatic int[] game.C_100017_wj.field_103821_j
		// @19: arraylength
		// @1A: iload_2
		// @1B: if_icmple @40
		// @1E: iload_0
		// @1F: iconst_m1
		// @20: ixor
		// @21: iload_3
		// @22: ifne @41
		// @25: getstatic int[] game.C_100017_wj.field_103821_j
		// @28: iload_2
		// @29: iaload
		// @2A: iconst_m1
		// @2B: ixor
		// @2C: if_icmpeq @37
		// @2F: goto @33
		// @32: athrow
		// @33: goto @39
		// @36: athrow
		// @37: iload_2
		// @38: ireturn
		// @39: iinc #2 +1
		// @3C: iload_3
		// @3D: ifeq @16
		// @40: iconst_m1
		// @41: ireturn
		// @42: astore_2
		// @43: aload_2
		// @44: new java.lang.StringBuilder
		// @47: dup
		// @48: invokespecial java.lang.StringBuilder.<init>()void
		// @4B: getstatic java.lang.String[] game.C_100152_bd.field_105213_z
		// @4E: bipush 57 (0x39)
		// @50: aaload
		// @51: invokevirtual java.lang.StringBuilder.append(java.lang.String)java.lang.StringBuilder
		// @54: iload_0
		// @55: invokevirtual java.lang.StringBuilder.append(int)java.lang.StringBuilder
		// @58: bipush 44 (0x2C)
		// @5A: invokevirtual java.lang.StringBuilder.append(char)java.lang.StringBuilder
		// @5D: iload_1
		// @5E: invokevirtual java.lang.StringBuilder.append(int)java.lang.StringBuilder
		// @61: bipush 41 (0x29)
		// @63: invokevirtual java.lang.StringBuilder.append(char)java.lang.StringBuilder
		// @66: invokevirtual java.lang.StringBuilder.toString()java.lang.String
		// @69: invokestatic game.C_100181_cf.func_105695_a(java.lang.Throwable, java.lang.String)game.C_100170_cm
		// @6C: athrow
	}
	
	public static void func_105191_g(int arg0)
	{
		// @00: aconst_null
		// @01: putstatic game.C_100186_rl game.C_100152_bd.field_105206_l
		// @04: aconst_null
		// @05: putstatic java.lang.String game.C_100152_bd.field_105204_n
		// @08: aconst_null
		// @09: putstatic java.lang.String game.C_100152_bd.field_105208_j
		// @0C: iload_0
		// @0D: ifeq @1B
		// @10: aconst_null
		// @11: checkcast game.C_100317_lb
		// @14: putstatic game.C_100317_lb game.C_100152_bd.field_105209_k
		// @17: goto @1B
		// @1A: athrow
		// @1B: aconst_null
		// @1C: putstatic game.C_100302_ka[] game.C_100152_bd.field_105211_i
		// @1F: aconst_null
		// @20: putstatic game.C_100302_ka game.C_100152_bd.field_105207_m
		// @23: aconst_null
		// @24: putstatic game.C_100243_pd[] game.C_100152_bd.field_105199_d
		// @27: aconst_null
		// @28: putstatic java.lang.String game.C_100152_bd.field_105205_o
		// @2B: aconst_null
		// @2C: putstatic game.C_100317_lb game.C_100152_bd.field_105209_k
		// @2F: goto @54
		// @32: astore_1
		// @33: aload_1
		// @34: new java.lang.StringBuilder
		// @37: dup
		// @38: invokespecial java.lang.StringBuilder.<init>()void
		// @3B: getstatic java.lang.String[] game.C_100152_bd.field_105213_z
		// @3E: bipush 58 (0x3A)
		// @40: aaload
		// @41: invokevirtual java.lang.StringBuilder.append(java.lang.String)java.lang.StringBuilder
		// @44: iload_0
		// @45: invokevirtual java.lang.StringBuilder.append(int)java.lang.StringBuilder
		// @48: bipush 41 (0x29)
		// @4A: invokevirtual java.lang.StringBuilder.append(char)java.lang.StringBuilder
		// @4D: invokevirtual java.lang.StringBuilder.toString()java.lang.String
		// @50: invokestatic game.C_100181_cf.func_105695_a(java.lang.Throwable, java.lang.String)game.C_100170_cm
		// @53: athrow
		// @54: return
	}
	
	public final synchronized void paint(Graphics arg0)
	{
		// @00: aload_0
		// @01: getstatic game.C_100152_bd game.C_100272_mn.field_102428_L
		// @04: if_acmpne @15
		// @07: getstatic boolean game.C_100101_fc.field_103407_Z
		// @0A: ifne @15
		// @0D: goto @11
		// @10: athrow
		// @11: goto @16
		// @14: athrow
		// @15: return
		// @16: iconst_1
		// @17: putstatic boolean game.C_100226_ae.field_106154_h
		// @1A: getstatic boolean game.C_100131_te.field_100758_p
		// @1D: ifeq @6F
		// @20: ldc2_w -1001
		// @23: bipush 104 (0x68)
		// @25: invokestatic game.C_100198_qn.func_105828_a(byte)long
		// @28: getstatic long game.C_100001_ge.field_100571_j
		// @2B: lneg
		// @2C: ladd
		// @2D: ldc2_w -1
		// @30: lxor
		// @31: lcmp
		// @32: ifle @6F
		// @35: goto @39
		// @38: athrow
		// @39: aload_1
		// @3A: invokevirtual java.awt.Graphics.getClipBounds()java.awt.Rectangle
		// @3D: astore_2
		// @3E: aconst_null
		// @3F: aload_2
		// @40: if_acmpeq @6B
		// @43: aload_2
		// @44: getfield int java.awt.Rectangle.width
		// @47: iconst_m1
		// @48: ixor
		// @49: getstatic int game.C_100340_je.field_102980_l
		// @4C: iconst_m1
		// @4D: ixor
		// @4E: if_icmpgt @6F
		// @51: goto @55
		// @54: athrow
		// @55: getstatic int game.C_100149_bi.field_105155_e
		// @58: iconst_m1
		// @59: ixor
		// @5A: aload_2
		// @5B: getfield int java.awt.Rectangle.height
		// @5E: iconst_m1
		// @5F: ixor
		// @60: if_icmpge @6B
		// @63: goto @67
		// @66: athrow
		// @67: goto @6F
		// @6A: athrow
		// @6B: iconst_1
		// @6C: putstatic boolean game.C_100188_rj.field_105736_d
		// @6F: goto @A6
		// @72: astore_2
		// @73: aload_2
		// @74: new java.lang.StringBuilder
		// @77: dup
		// @78: invokespecial java.lang.StringBuilder.<init>()void
		// @7B: getstatic java.lang.String[] game.C_100152_bd.field_105213_z
		// @7E: bipush 59 (0x3B)
		// @80: aaload
		// @81: invokevirtual java.lang.StringBuilder.append(java.lang.String)java.lang.StringBuilder
		// @84: aload_1
		// @85: ifnull @92
		// @88: getstatic java.lang.String[] game.C_100152_bd.field_105213_z
		// @8B: bipush 6 (0x06)
		// @8D: aaload
		// @8E: goto @97
		// @91: athrow
		// @92: getstatic java.lang.String[] game.C_100152_bd.field_105213_z
		// @95: iconst_0
		// @96: aaload
		// @97: invokevirtual java.lang.StringBuilder.append(java.lang.String)java.lang.StringBuilder
		// @9A: bipush 41 (0x29)
		// @9C: invokevirtual java.lang.StringBuilder.append(char)java.lang.StringBuilder
		// @9F: invokevirtual java.lang.StringBuilder.toString()java.lang.String
		// @A2: invokestatic game.C_100181_cf.func_105695_a(java.lang.Throwable, java.lang.String)game.C_100170_cm
		// @A5: athrow
		// @A6: return
	}
	
	abstract void func_105175_b(int arg0);
	
	static final void func_105178_a(boolean arg0, Canvas arg1, int arg2)
	{
		// @00: getstatic int game.SteelSentinels.field_105275_O
		// @03: istore #4
		// @05: iload_2
		// @06: ifeq @17
		// @09: iconst_1
		// @0A: aconst_null
		// @0B: checkcast java.awt.Canvas
		// @0E: bipush 58 (0x3A)
		// @10: invokestatic game.C_100152_bd.func_105178_a(boolean, java.awt.Canvas, int)void
		// @13: goto @17
		// @16: athrow
		// @17: getstatic int game.C_100283_ni.field_106760_c
		// @1A: iconst_m1
		// @1B: ixor
		// @1C: bipush -11 (0xF5)
		// @1E: if_icmple @4C
		// @21: iconst_0
		// @22: istore_3
		// @23: getstatic boolean game.C_100226_ae.field_106154_h
		// @26: ifne @2D
		// @29: goto @33
		// @2C: athrow
		// @2D: iconst_0
		// @2E: putstatic boolean game.C_100226_ae.field_106154_h
		// @31: iconst_1
		// @32: istore_3
		// @33: bipush -54 (0xCA)
		// @35: invokestatic game.C_100333_ij.func_107326_e(int)java.lang.String
		// @38: iload_3
		// @39: iload_2
		// @3A: bipush 80 (0x50)
		// @3C: ixor
		// @3D: invokestatic game.C_100162_sc.func_102854_k(int)int
		// @40: iconst_3
		// @41: getstatic java.awt.Color game.C_100227_af.field_106165_g
		// @44: invokestatic game.C_100160_sm.func_105411_a(java.lang.String, boolean, int, int, java.awt.Color)void
		// @47: iload #4
		// @49: ifeq @A8
		// @4C: iload_2
		// @4D: sipush 29613 (0x73AD)
		// @50: iadd
		// @51: invokestatic game.C_100172_ck.func_102103_l(int)boolean
		// @54: ifne @7B
		// @57: goto @5B
		// @5A: athrow
		// @5B: invokestatic game.C_100196_rb.func_105792_b()void
		// @5E: bipush 125 (0x7D)
		// @60: sipush 320 (0x0140)
		// @63: sipush 240 (0x00F0)
		// @66: invokestatic game.C_100333_ij.func_107325_a(byte, int, int)void
		// @69: iconst_0
		// @6A: sipush -25993 (0x9A77)
		// @6D: iconst_0
		// @6E: aload_1
		// @6F: invokestatic game.C_100238_ol.func_101689_a(int, int, int, java.awt.Canvas)void
		// @72: iload #4
		// @74: ifeq @A8
		// @77: goto @7B
		// @7A: athrow
		// @7B: iconst_0
		// @7C: getstatic int game.C_100087_n.field_100697_v
		// @7F: if_icmpeq @94
		// @82: goto @86
		// @85: athrow
		// @86: aload_1
		// @87: iconst_0
		// @88: invokestatic game.C_100000_gd.func_100347_a(java.awt.Canvas, int)void
		// @8B: iload #4
		// @8D: ifeq @A8
		// @90: goto @94
		// @93: athrow
		// @94: iload_0
		// @95: iconst_0
		// @96: bipush -109 (0x93)
		// @98: invokestatic game.C_100144_bm.func_102089_a(boolean, boolean, int)void
		// @9B: iconst_0
		// @9C: sipush -25993 (0x9A77)
		// @9F: iconst_0
		// @A0: aload_1
		// @A1: invokestatic game.C_100238_ol.func_101689_a(int, int, int, java.awt.Canvas)void
		// @A4: goto @A8
		// @A7: athrow
		// @A8: goto @F1
		// @AB: astore_3
		// @AC: aload_3
		// @AD: new java.lang.StringBuilder
		// @B0: dup
		// @B1: invokespecial java.lang.StringBuilder.<init>()void
		// @B4: getstatic java.lang.String[] game.C_100152_bd.field_105213_z
		// @B7: bipush 24 (0x18)
		// @B9: aaload
		// @BA: invokevirtual java.lang.StringBuilder.append(java.lang.String)java.lang.StringBuilder
		// @BD: iload_0
		// @BE: invokevirtual java.lang.StringBuilder.append(boolean)java.lang.StringBuilder
		// @C1: bipush 44 (0x2C)
		// @C3: invokevirtual java.lang.StringBuilder.append(char)java.lang.StringBuilder
		// @C6: aload_1
		// @C7: ifnull @D4
		// @CA: getstatic java.lang.String[] game.C_100152_bd.field_105213_z
		// @CD: bipush 6 (0x06)
		// @CF: aaload
		// @D0: goto @D9
		// @D3: athrow
		// @D4: getstatic java.lang.String[] game.C_100152_bd.field_105213_z
		// @D7: iconst_0
		// @D8: aaload
		// @D9: invokevirtual java.lang.StringBuilder.append(java.lang.String)java.lang.StringBuilder
		// @DC: bipush 44 (0x2C)
		// @DE: invokevirtual java.lang.StringBuilder.append(char)java.lang.StringBuilder
		// @E1: iload_2
		// @E2: invokevirtual java.lang.StringBuilder.append(int)java.lang.StringBuilder
		// @E5: bipush 41 (0x29)
		// @E7: invokevirtual java.lang.StringBuilder.append(char)java.lang.StringBuilder
		// @EA: invokevirtual java.lang.StringBuilder.toString()java.lang.String
		// @ED: invokestatic game.C_100181_cf.func_105695_a(java.lang.Throwable, java.lang.String)game.C_100170_cm
		// @F0: athrow
		// @F1: return
	}
	
	private final void func_105181_a(boolean arg0, byte arg1)
	{
		// @00: aload_0
		// @01: dup
		// @02: astore_3
		// @03: monitorenter
		// @04: getstatic boolean game.C_100101_fc.field_103407_Z
		// @07: ifeq @0D
		// @0A: aload_3
		// @0B: monitorexit
		// @0C: return
		// @0D: iload_2
		// @0E: bipush -120 (0x88)
		// @10: if_icmpeq @16
		// @13: aload_3
		// @14: monitorexit
		// @15: return
		// @16: iconst_1
		// @17: putstatic boolean game.C_100101_fc.field_103407_Z
		// @1A: aload_3
		// @1B: monitorexit
		// @1C: goto @26
		// @1F: astore #4
		// @21: aload_3
		// @22: monitorexit
		// @23: aload #4
		// @25: athrow
		// @26: aconst_null
		// @27: getstatic java.applet.Applet game.C_100107_u.field_104771_d
		// @2A: if_acmpeq @37
		// @2D: getstatic java.applet.Applet game.C_100107_u.field_104771_d
		// @30: invokevirtual java.applet.Applet.destroy()void
		// @33: goto @37
		// @36: athrow
		// @37: aload_0
		// @38: iconst_3
		// @39: invokevirtual game.C_100152_bd.func_105194_f(int)void
		// @3C: goto @40
		// @3F: astore_3
		// @40: getstatic java.awt.Canvas game.C_100034_gi.field_104033_a
		// @43: ifnonnull @4A
		// @46: goto @61
		// @49: athrow
		// @4A: getstatic java.awt.Canvas game.C_100034_gi.field_104033_a
		// @4D: aload_0
		// @4E: invokevirtual java.awt.Canvas.removeFocusListener(java.awt.event.FocusListener)void
		// @51: getstatic java.awt.Canvas game.C_100034_gi.field_104033_a
		// @54: invokevirtual java.awt.Canvas.getParent()java.awt.Container
		// @57: getstatic java.awt.Canvas game.C_100034_gi.field_104033_a
		// @5A: invokevirtual java.awt.Container.remove(java.awt.Component)void
		// @5D: goto @61
		// @60: astore_3
		// @61: getstatic game.C_100201_qj game.C_100178_cg.field_105692_a
		// @64: ifnull @73
		// @67: getstatic game.C_100201_qj game.C_100178_cg.field_105692_a
		// @6A: bipush -99 (0x9D)
		// @6C: invokevirtual game.C_100201_qj.func_105858_b(int)void
		// @6F: goto @73
		// @72: astore_3
		// @73: aload_0
		// @74: iload_2
		// @75: bipush -120 (0x88)
		// @77: ixor
		// @78: invokevirtual game.C_100152_bd.func_105193_c(int)void
		// @7B: getstatic java.awt.Frame game.C_100227_af.field_106168_b
		// @7E: ifnonnull @85
		// @81: goto @8D
		// @84: athrow
		// @85: iconst_0
		// @86: invokestatic java.lang.System.exit(int)void
		// @89: goto @8D
		// @8C: astore_3
		// @8D: getstatic java.io.PrintStream java.lang.System.out
		// @90: new java.lang.StringBuilder
		// @93: dup
		// @94: invokespecial java.lang.StringBuilder.<init>()void
		// @97: getstatic java.lang.String[] game.C_100152_bd.field_105213_z
		// @9A: bipush 14 (0x0E)
		// @9C: aaload
		// @9D: invokevirtual java.lang.StringBuilder.append(java.lang.String)java.lang.StringBuilder
		// @A0: iload_1
		// @A1: invokevirtual java.lang.StringBuilder.append(boolean)java.lang.StringBuilder
		// @A4: invokevirtual java.lang.StringBuilder.toString()java.lang.String
		// @A7: invokevirtual java.io.PrintStream.println(java.lang.String)void
		// @AA: goto @D8
		// @AD: astore_3
		// @AE: aload_3
		// @AF: new java.lang.StringBuilder
		// @B2: dup
		// @B3: invokespecial java.lang.StringBuilder.<init>()void
		// @B6: getstatic java.lang.String[] game.C_100152_bd.field_105213_z
		// @B9: bipush 15 (0x0F)
		// @BB: aaload
		// @BC: invokevirtual java.lang.StringBuilder.append(java.lang.String)java.lang.StringBuilder
		// @BF: iload_1
		// @C0: invokevirtual java.lang.StringBuilder.append(boolean)java.lang.StringBuilder
		// @C3: bipush 44 (0x2C)
		// @C5: invokevirtual java.lang.StringBuilder.append(char)java.lang.StringBuilder
		// @C8: iload_2
		// @C9: invokevirtual java.lang.StringBuilder.append(int)java.lang.StringBuilder
		// @CC: bipush 41 (0x29)
		// @CE: invokevirtual java.lang.StringBuilder.append(char)java.lang.StringBuilder
		// @D1: invokevirtual java.lang.StringBuilder.toString()java.lang.String
		// @D4: invokestatic game.C_100181_cf.func_105695_a(java.lang.Throwable, java.lang.String)game.C_100170_cm
		// @D7: athrow
		// @D8: return
	}
	
	public static final void func_105195_provideLoaderApplet(Applet arg0)
	{
		// @00: aload_0
		// @01: putstatic java.applet.Applet game.C_100107_u.field_104771_d
		// @04: goto @3B
		// @07: astore_1
		// @08: aload_1
		// @09: new java.lang.StringBuilder
		// @0C: dup
		// @0D: invokespecial java.lang.StringBuilder.<init>()void
		// @10: getstatic java.lang.String[] game.C_100152_bd.field_105213_z
		// @13: bipush 46 (0x2E)
		// @15: aaload
		// @16: invokevirtual java.lang.StringBuilder.append(java.lang.String)java.lang.StringBuilder
		// @19: aload_0
		// @1A: ifnull @27
		// @1D: getstatic java.lang.String[] game.C_100152_bd.field_105213_z
		// @20: bipush 6 (0x06)
		// @22: aaload
		// @23: goto @2C
		// @26: athrow
		// @27: getstatic java.lang.String[] game.C_100152_bd.field_105213_z
		// @2A: iconst_0
		// @2B: aaload
		// @2C: invokevirtual java.lang.StringBuilder.append(java.lang.String)java.lang.StringBuilder
		// @2F: bipush 41 (0x29)
		// @31: invokevirtual java.lang.StringBuilder.append(char)java.lang.StringBuilder
		// @34: invokevirtual java.lang.StringBuilder.toString()java.lang.String
		// @37: invokestatic game.C_100181_cf.func_105695_a(java.lang.Throwable, java.lang.String)game.C_100170_cm
		// @3A: athrow
		// @3B: return
	}
	
	public final void windowDeactivated(WindowEvent arg0)
	{
		// @0: return
	}
	
	abstract void func_105189_b(byte arg0);
	
	private final void func_105186_a(byte arg0)
	{
		// @00: bipush -95 (0xA1)
		// @02: invokestatic game.C_100198_qn.func_105828_a(byte)long
		// @05: lstore_2
		// @06: getstatic long[] game.C_100103_eh.field_104673_i
		// @09: getstatic int game.C_100268_mk.field_106666_g
		// @0C: laload
		// @0D: lstore #4
		// @0F: getstatic long[] game.C_100103_eh.field_104673_i
		// @12: getstatic int game.C_100268_mk.field_106666_g
		// @15: lload_2
		// @16: lastore
		// @17: iconst_1
		// @18: getstatic int game.C_100268_mk.field_106666_g
		// @1B: iadd
		// @1C: bipush 31 (0x1F)
		// @1E: iand
		// @1F: putstatic int game.C_100268_mk.field_106666_g
		// @22: lload #4
		// @24: ldc2_w -1
		// @27: lxor
		// @28: ldc2_w -1
		// @2B: lcmp
		// @2C: ifeq @42
		// @2F: lload_2
		// @30: ldc2_w -1
		// @33: lxor
		// @34: lload #4
		// @36: ldc2_w -1
		// @39: lxor
		// @3A: lcmp
		// @3B: iflt @42
		// @3E: goto @42
		// @41: athrow
		// @42: iload_1
		// @43: bipush 16 (0x10)
		// @45: if_icmpeq @51
		// @48: aload_0
		// @49: iconst_0
		// @4A: putfield boolean game.C_100152_bd.field_105212_p
		// @4D: goto @51
		// @50: athrow
		// @51: getstatic int game.C_100142_bk.field_105089_c
		// @54: dup
		// @55: iconst_1
		// @56: iadd
		// @57: putstatic int game.C_100142_bk.field_105089_c
		// @5A: bipush 50 (0x32)
		// @5C: if_icmple @CC
		// @5F: getstatic int game.C_100142_bk.field_105089_c
		// @62: bipush 50 (0x32)
		// @64: isub
		// @65: putstatic int game.C_100142_bk.field_105089_c
		// @68: iconst_1
		// @69: putstatic boolean game.C_100226_ae.field_106154_h
		// @6C: getstatic java.awt.Canvas game.C_100034_gi.field_104033_a
		// @6F: getstatic int game.C_100270_mi.field_102282_cc
		// @72: getstatic int game.C_100165_sh.field_100769_s
		// @75: invokevirtual java.awt.Canvas.setSize(int, int)void
		// @78: getstatic java.awt.Canvas game.C_100034_gi.field_104033_a
		// @7B: iconst_1
		// @7C: invokevirtual java.awt.Canvas.setVisible(boolean)void
		// @7F: aconst_null
		// @80: getstatic java.awt.Frame game.C_100227_af.field_106168_b
		// @83: if_acmpeq @BC
		// @86: goto @8A
		// @89: athrow
		// @8A: aconst_null
		// @8B: getstatic java.awt.Frame game.C_100137_bn.field_105039_m
		// @8E: if_acmpne @BC
		// @91: goto @95
		// @94: athrow
		// @95: getstatic java.awt.Frame game.C_100227_af.field_106168_b
		// @98: invokevirtual java.awt.Frame.getInsets()java.awt.Insets
		// @9B: astore #6
		// @9D: getstatic java.awt.Canvas game.C_100034_gi.field_104033_a
		// @A0: aload #6
		// @A2: getfield int java.awt.Insets.left
		// @A5: getstatic int game.C_100227_af.field_106166_d
		// @A8: ineg
		// @A9: isub
		// @AA: getstatic int game.C_100058_dg.field_101580_s
		// @AD: aload #6
		// @AF: getfield int java.awt.Insets.top
		// @B2: iadd
		// @B3: invokevirtual java.awt.Canvas.setLocation(int, int)void
		// @B6: getstatic int game.SteelSentinels.field_105275_O
		// @B9: ifeq @CC
		// @BC: getstatic java.awt.Canvas game.C_100034_gi.field_104033_a
		// @BF: getstatic int game.C_100227_af.field_106166_d
		// @C2: getstatic int game.C_100058_dg.field_101580_s
		// @C5: invokevirtual java.awt.Canvas.setLocation(int, int)void
		// @C8: goto @CC
		// @CB: athrow
		// @CC: aload_0
		// @CD: bipush -108 (0x94)
		// @CF: invokevirtual game.C_100152_bd.func_105189_b(byte)void
		// @D2: goto @F7
		// @D5: astore_2
		// @D6: aload_2
		// @D7: new java.lang.StringBuilder
		// @DA: dup
		// @DB: invokespecial java.lang.StringBuilder.<init>()void
		// @DE: getstatic java.lang.String[] game.C_100152_bd.field_105213_z
		// @E1: bipush 13 (0x0D)
		// @E3: aaload
		// @E4: invokevirtual java.lang.StringBuilder.append(java.lang.String)java.lang.StringBuilder
		// @E7: iload_1
		// @E8: invokevirtual java.lang.StringBuilder.append(int)java.lang.StringBuilder
		// @EB: bipush 41 (0x29)
		// @ED: invokevirtual java.lang.StringBuilder.append(char)java.lang.StringBuilder
		// @F0: invokevirtual java.lang.StringBuilder.toString()java.lang.String
		// @F3: invokestatic game.C_100181_cf.func_105695_a(java.lang.Throwable, java.lang.String)game.C_100170_cm
		// @F6: athrow
		// @F7: return
	}
	
	public final void run()
	{
		// @000: getstatic int game.SteelSentinels.field_105275_O
		// @003: istore #5
		// @005: getstatic java.lang.String game.C_100201_qj.field_105887_u
		// @008: ifnull @180
		// @00B: getstatic java.lang.String game.C_100201_qj.field_105887_u
		// @00E: invokevirtual java.lang.String.toLowerCase()java.lang.String
		// @011: astore_1
		// @012: aload_1
		// @013: getstatic java.lang.String[] game.C_100152_bd.field_105213_z
		// @016: bipush 34 (0x22)
		// @018: aaload
		// @019: invokevirtual java.lang.String.indexOf(java.lang.String)int
		// @01C: iconst_m1
		// @01D: ixor
		// @01E: ifne @033
		// @021: iconst_m1
		// @022: aload_1
		// @023: getstatic java.lang.String[] game.C_100152_bd.field_105213_z
		// @026: bipush 40 (0x28)
		// @028: aaload
		// @029: invokevirtual java.lang.String.indexOf(java.lang.String)int
		// @02C: if_icmpeq @180
		// @02F: goto @033
		// @032: athrow
		// @033: getstatic java.lang.String game.C_100201_qj.field_105886_v
		// @036: astore_2
		// @037: aload_2
		// @038: getstatic java.lang.String[] game.C_100152_bd.field_105213_z
		// @03B: bipush 45 (0x2D)
		// @03D: aaload
		// @03E: invokevirtual java.lang.String.equals(java.lang.Object)boolean
		// @041: ifne @0EE
		// @044: aload_2
		// @045: getstatic java.lang.String[] game.C_100152_bd.field_105213_z
		// @048: bipush 31 (0x1F)
		// @04A: aaload
		// @04B: invokevirtual java.lang.String.startsWith(java.lang.String)boolean
		// @04E: ifne @0EE
		// @051: goto @055
		// @054: athrow
		// @055: aload_2
		// @056: getstatic java.lang.String[] game.C_100152_bd.field_105213_z
		// @059: bipush 32 (0x20)
		// @05B: aaload
		// @05C: invokevirtual java.lang.String.equals(java.lang.Object)boolean
		// @05F: ifne @0EE
		// @062: goto @066
		// @065: athrow
		// @066: aload_2
		// @067: getstatic java.lang.String[] game.C_100152_bd.field_105213_z
		// @06A: bipush 30 (0x1E)
		// @06C: aaload
		// @06D: invokevirtual java.lang.String.startsWith(java.lang.String)boolean
		// @070: ifne @0EE
		// @073: goto @077
		// @076: athrow
		// @077: aload_2
		// @078: getstatic java.lang.String[] game.C_100152_bd.field_105213_z
		// @07B: bipush 37 (0x25)
		// @07D: aaload
		// @07E: invokevirtual java.lang.String.equals(java.lang.Object)boolean
		// @081: ifne @0EE
		// @084: goto @088
		// @087: athrow
		// @088: aload_2
		// @089: getstatic java.lang.String[] game.C_100152_bd.field_105213_z
		// @08C: bipush 33 (0x21)
		// @08E: aaload
		// @08F: invokevirtual java.lang.String.startsWith(java.lang.String)boolean
		// @092: ifne @0EE
		// @095: goto @099
		// @098: athrow
		// @099: aload_2
		// @09A: getstatic java.lang.String[] game.C_100152_bd.field_105213_z
		// @09D: bipush 43 (0x2B)
		// @09F: aaload
		// @0A0: invokevirtual java.lang.String.equals(java.lang.Object)boolean
		// @0A3: ifne @0EE
		// @0A6: goto @0AA
		// @0A9: athrow
		// @0AA: aload_2
		// @0AB: getstatic java.lang.String[] game.C_100152_bd.field_105213_z
		// @0AE: bipush 39 (0x27)
		// @0B0: aaload
		// @0B1: invokevirtual java.lang.String.startsWith(java.lang.String)boolean
		// @0B4: ifne @0EE
		// @0B7: goto @0BB
		// @0BA: athrow
		// @0BB: aload_2
		// @0BC: getstatic java.lang.String[] game.C_100152_bd.field_105213_z
		// @0BF: bipush 36 (0x24)
		// @0C1: aaload
		// @0C2: invokevirtual java.lang.String.equals(java.lang.Object)boolean
		// @0C5: ifne @0EE
		// @0C8: goto @0CC
		// @0CB: athrow
		// @0CC: aload_2
		// @0CD: getstatic java.lang.String[] game.C_100152_bd.field_105213_z
		// @0D0: bipush 35 (0x23)
		// @0D2: aaload
		// @0D3: invokevirtual java.lang.String.startsWith(java.lang.String)boolean
		// @0D6: ifne @0EE
		// @0D9: goto @0DD
		// @0DC: athrow
		// @0DD: aload_2
		// @0DE: getstatic java.lang.String[] game.C_100152_bd.field_105213_z
		// @0E1: bipush 29 (0x1D)
		// @0E3: aaload
		// @0E4: invokevirtual java.lang.String.equals(java.lang.Object)boolean
		// @0E7: ifeq @103
		// @0EA: goto @0EE
		// @0ED: athrow
		// @0EE: aload_0
		// @0EF: getstatic java.lang.String[] game.C_100152_bd.field_105213_z
		// @0F2: bipush 41 (0x29)
		// @0F4: aaload
		// @0F5: bipush -52 (0xCC)
		// @0F7: invokevirtual game.C_100152_bd.func_105182_a(java.lang.String, int)void
		// @0FA: iload #5
		// @0FC: ifeq @2BD
		// @0FF: goto @103
		// @102: athrow
		// @103: aload_2
		// @104: getstatic java.lang.String[] game.C_100152_bd.field_105213_z
		// @107: bipush 42 (0x2A)
		// @109: aaload
		// @10A: invokevirtual java.lang.String.startsWith(java.lang.String)boolean
		// @10D: ifne @118
		// @110: goto @114
		// @113: athrow
		// @114: goto @180
		// @117: athrow
		// @118: bipush 6 (0x06)
		// @11A: istore_3
		// @11B: iload_3
		// @11C: iconst_m1
		// @11D: ixor
		// @11E: aload_2
		// @11F: invokevirtual java.lang.String.length()int
		// @122: iconst_m1
		// @123: ixor
		// @124: if_icmple @149
		// @127: aload_2
		// @128: iload_3
		// @129: invokevirtual java.lang.String.charAt(int)char
		// @12C: bipush -100 (0x9C)
		// @12E: invokestatic game.C_100064_ve.func_103007_a(char, byte)boolean
		// @131: iload #5
		// @133: ifne @19B
		// @136: ifeq @149
		// @139: goto @13D
		// @13C: athrow
		// @13D: iinc #3 +1
		// @140: iload #5
		// @142: ifeq @11B
		// @145: goto @149
		// @148: athrow
		// @149: aload_2
		// @14A: bipush 6 (0x06)
		// @14C: iload_3
		// @14D: invokevirtual java.lang.String.substring(int, int)java.lang.String
		// @150: astore #4
		// @152: iconst_1
		// @153: aload #4
		// @155: invokestatic game.C_100298_ke.func_103205_a(boolean, java.lang.CharSequence)boolean
		// @158: ifeq @180
		// @15B: aload #4
		// @15D: bipush -116 (0x8C)
		// @15F: invokestatic game.C_100001_ge.func_100552_a(java.lang.CharSequence, int)int
		// @162: bipush 10 (0x0A)
		// @164: if_icmplt @16F
		// @167: goto @16B
		// @16A: athrow
		// @16B: goto @180
		// @16E: athrow
		// @16F: aload_0
		// @170: getstatic java.lang.String[] game.C_100152_bd.field_105213_z
		// @173: bipush 41 (0x29)
		// @175: aaload
		// @176: bipush -42 (0xD6)
		// @178: invokevirtual game.C_100152_bd.func_105182_a(java.lang.String, int)void
		// @17B: iload #5
		// @17D: ifeq @2BD
		// @180: aconst_null
		// @181: getstatic java.lang.String game.C_100201_qj.field_105886_v
		// @184: if_acmpeq @1FC
		// @187: goto @18B
		// @18A: athrow
		// @18B: getstatic java.lang.String game.C_100201_qj.field_105886_v
		// @18E: getstatic java.lang.String[] game.C_100152_bd.field_105213_z
		// @191: bipush 44 (0x2C)
		// @193: aaload
		// @194: invokevirtual java.lang.String.startsWith(java.lang.String)boolean
		// @197: goto @19B
		// @19A: athrow
		// @19B: ifeq @1FC
		// @19E: iconst_2
		// @19F: istore_1
		// @1A0: iconst_0
		// @1A1: istore_2
		// @1A2: iload_1
		// @1A3: iconst_m1
		// @1A4: ixor
		// @1A5: getstatic java.lang.String game.C_100201_qj.field_105886_v
		// @1A8: invokevirtual java.lang.String.length()int
		// @1AB: iconst_m1
		// @1AC: ixor
		// @1AD: if_icmple @1F0
		// @1B0: getstatic java.lang.String game.C_100201_qj.field_105886_v
		// @1B3: iload_1
		// @1B4: invokevirtual java.lang.String.charAt(int)char
		// @1B7: istore_3
		// @1B8: iload_3
		// @1B9: iconst_m1
		// @1BA: ixor
		// @1BB: bipush -49 (0xCF)
		// @1BD: iload #5
		// @1BF: ifne @1F2
		// @1C2: if_icmpgt @1F0
		// @1C5: goto @1C9
		// @1C8: athrow
		// @1C9: iload_3
		// @1CA: iconst_m1
		// @1CB: ixor
		// @1CC: bipush -58 (0xC6)
		// @1CE: if_icmpge @1DE
		// @1D1: goto @1D5
		// @1D4: athrow
		// @1D5: iload #5
		// @1D7: ifeq @1F0
		// @1DA: goto @1DE
		// @1DD: athrow
		// @1DE: iload_3
		// @1DF: bipush 48 (0x30)
		// @1E1: isub
		// @1E2: iload_2
		// @1E3: bipush 10 (0x0A)
		// @1E5: imul
		// @1E6: iadd
		// @1E7: istore_2
		// @1E8: iinc #1 +1
		// @1EB: iload #5
		// @1ED: ifeq @1A2
		// @1F0: iload_2
		// @1F1: iconst_5
		// @1F2: if_icmpge @1F8
		// @1F5: goto @1FC
		// @1F8: iconst_1
		// @1F9: putstatic boolean game.C_100131_te.field_100758_p
		// @1FC: getstatic game.C_100152_bd game.C_100272_mn.field_102428_L
		// @1FF: astore_1
		// @200: getstatic java.applet.Applet game.C_100107_u.field_104771_d
		// @203: ifnonnull @20A
		// @206: goto @20E
		// @209: athrow
		// @20A: getstatic java.applet.Applet game.C_100107_u.field_104771_d
		// @20D: astore_1
		// @20E: getstatic java.lang.reflect.Method game.C_100201_qj.field_105880_m
		// @211: astore_2
		// @212: aload_2
		// @213: ifnonnull @21A
		// @216: goto @22E
		// @219: athrow
		// @21A: aload_2
		// @21B: aload_1
		// @21C: iconst_1
		// @21D: anewarray java.lang.Object
		// @220: dup
		// @221: iconst_0
		// @222: getstatic java.lang.Boolean java.lang.Boolean.TRUE
		// @225: aastore
		// @226: invokevirtual java.lang.reflect.Method.invoke(java.lang.Object, java.lang.Object[])java.lang.Object
		// @229: pop
		// @22A: goto @22E
		// @22D: astore_3
		// @22E: iconst_0
		// @22F: invokestatic game.C_100286_nl.func_106802_a(boolean)void
		// @232: aload_0
		// @233: iconst_0
		// @234: invokevirtual game.C_100152_bd.func_105196_h(int)void
		// @237: getstatic java.awt.Canvas game.C_100034_gi.field_104033_a
		// @23A: iconst_2
		// @23B: getstatic int game.C_100165_sh.field_100769_s
		// @23E: getstatic int game.C_100270_mi.field_102282_cc
		// @241: invokestatic game.C_100264_mg.func_106516_a(java.awt.Component, int, int, int)game.C_100185_rm
		// @244: putstatic game.C_100185_rm game.C_100049_vf.field_104206_l
		// @247: aload_0
		// @248: sipush -1697 (0xF95F)
		// @24B: invokevirtual game.C_100152_bd.func_105180_d(int)void
		// @24E: iconst_2
		// @24F: invokestatic game.C_100048_vi.func_104169_a(byte)game.C_100338_jc
		// @252: putstatic game.C_100338_jc game.C_100301_kb.field_107094_a
		// @255: getstatic long game.C_100252_pn.field_105508_w
		// @258: lconst_0
		// @259: lcmp
		// @25A: ifeq @272
		// @25D: bipush 107 (0x6B)
		// @25F: invokestatic game.C_100198_qn.func_105828_a(byte)long
		// @262: getstatic long game.C_100252_pn.field_105508_w
		// @265: lcmp
		// @266: iload #5
		// @268: ifne @285
		// @26B: ifge @2BD
		// @26E: goto @272
		// @271: athrow
		// @272: getstatic game.C_100338_jc game.C_100301_kb.field_107094_a
		// @275: getstatic long game.C_100042_we.field_104142_i
		// @278: bipush 79 (0x4F)
		// @27A: invokevirtual game.C_100338_jc.func_105362_a(long, byte)int
		// @27D: putstatic int game.C_100012_fh.field_100518_P
		// @280: iconst_0
		// @281: goto @285
		// @284: athrow
		// @285: istore_3
		// @286: getstatic int game.C_100012_fh.field_100518_P
		// @289: iconst_m1
		// @28A: ixor
		// @28B: iload_3
		// @28C: iconst_m1
		// @28D: ixor
		// @28E: if_icmpge @2A7
		// @291: aload_0
		// @292: iconst_m1
		// @293: invokespecial game.C_100152_bd.func_105176_a(int)void
		// @296: iinc #3 +1
		// @299: iload #5
		// @29B: ifne @2B8
		// @29E: iload #5
		// @2A0: ifeq @286
		// @2A3: goto @2A7
		// @2A6: athrow
		// @2A7: aload_0
		// @2A8: bipush 16 (0x10)
		// @2AA: invokespecial game.C_100152_bd.func_105186_a(byte)void
		// @2AD: bipush -108 (0x94)
		// @2AF: getstatic game.C_100201_qj game.C_100178_cg.field_105692_a
		// @2B2: getstatic java.awt.Canvas game.C_100034_gi.field_104033_a
		// @2B5: invokestatic game.C_100333_ij.func_107323_a(byte, game.C_100201_qj, java.lang.Object)void
		// @2B8: iload #5
		// @2BA: ifeq @255
		// @2BD: goto @2D3
		// @2C0: astore_1
		// @2C1: iconst_1
		// @2C2: aconst_null
		// @2C3: aload_1
		// @2C4: invokestatic game.C_100036_gg.func_103142_a(int, java.lang.String, java.lang.Throwable)void
		// @2C7: aload_0
		// @2C8: getstatic java.lang.String[] game.C_100152_bd.field_105213_z
		// @2CB: bipush 26 (0x1A)
		// @2CD: aaload
		// @2CE: bipush -52 (0xCC)
		// @2D0: invokevirtual game.C_100152_bd.func_105182_a(java.lang.String, int)void
		// @2D3: aload_0
		// @2D4: iconst_1
		// @2D5: bipush -120 (0x88)
		// @2D7: invokespecial game.C_100152_bd.func_105181_a(boolean, byte)void
		// @2DA: goto @2E9
		// @2DD: astore_1
		// @2DE: aload_1
		// @2DF: getstatic java.lang.String[] game.C_100152_bd.field_105213_z
		// @2E2: bipush 38 (0x26)
		// @2E4: aaload
		// @2E5: invokestatic game.C_100181_cf.func_105695_a(java.lang.Throwable, java.lang.String)game.C_100170_cm
		// @2E8: athrow
		// @2E9: return
	}
	
	public final void windowClosed(WindowEvent arg0)
	{
		// @0: return
	}
	
	public final void windowOpened(WindowEvent arg0)
	{
		// @0: return
	}
	
	static final void func_105188_c(byte arg0)
	{
		// @00: getstatic int game.SteelSentinels.field_105275_O
		// @03: istore_2
		// @04: aconst_null
		// @05: putstatic java.lang.String game.C_100069_vb.field_104358_b
		// @08: iconst_0
		// @09: putstatic boolean game.C_100198_qn.field_105834_b
		// @0C: iload_0
		// @0D: bipush -86 (0xAA)
		// @0F: if_icmpeq @13
		// @12: return
		// @13: getstatic boolean game.C_100186_rl.field_105720_f
		// @16: ifeq @29
		// @19: getstatic game.C_100282_nh game.C_100027_hc.field_102598_S
		// @1C: bipush -98 (0x9E)
		// @1E: invokevirtual game.C_100282_nh.func_102702_h(byte)void
		// @21: iload_2
		// @22: ifeq @9A
		// @25: goto @29
		// @28: athrow
		// @29: getstatic int game.C_100300_kc.field_107071_c
		// @2C: istore_1
		// @2D: iconst_0
		// @2E: iload_1
		// @2F: if_icmpge @88
		// @32: iload_1
		// @33: iconst_m1
		// @34: ixor
		// @35: bipush -2 (0xFE)
		// @37: if_icmpne @4C
		// @3A: goto @3E
		// @3D: athrow
		// @3E: getstatic java.lang.String game.C_100125_tm.field_100746_n
		// @41: putstatic java.lang.String game.C_100069_vb.field_104358_b
		// @44: iload_2
		// @45: ifeq @67
		// @48: goto @4C
		// @4B: athrow
		// @4C: sipush -30945 (0x871F)
		// @4F: iconst_1
		// @50: anewarray java.lang.String
		// @53: dup
		// @54: iconst_0
		// @55: iload_1
		// @56: invokestatic java.lang.Integer.toString(int)java.lang.String
		// @59: aastore
		// @5A: getstatic java.lang.String game.C_100157_db.field_103560_c
		// @5D: invokestatic game.C_100132_td.func_104965_a(int, java.lang.String[], java.lang.String)java.lang.String
		// @60: putstatic java.lang.String game.C_100069_vb.field_104358_b
		// @63: goto @67
		// @66: athrow
		// @67: bipush 109 (0x6D)
		// @69: iconst_3
		// @6A: anewarray java.lang.CharSequence
		// @6D: dup
		// @6E: iconst_0
		// @6F: getstatic java.lang.String game.C_100069_vb.field_104358_b
		// @72: aastore
		// @73: dup
		// @74: iconst_1
		// @75: getstatic java.lang.String[] game.C_100152_bd.field_105213_z
		// @78: bipush 8 (0x08)
		// @7A: aaload
		// @7B: aastore
		// @7C: dup
		// @7D: iconst_2
		// @7E: getstatic java.lang.String game.C_100045_vj.field_100611_k
		// @81: aastore
		// @82: invokestatic game.C_100270_mi.func_102260_a(byte, java.lang.CharSequence[])java.lang.String
		// @85: putstatic java.lang.String game.C_100069_vb.field_104358_b
		// @88: getstatic game.C_100282_nh game.C_100027_hc.field_102598_S
		// @8B: iload_0
		// @8C: bipush 121 (0x79)
		// @8E: iadd
		// @8F: invokevirtual game.C_100282_nh.func_102701_r(int)void
		// @92: iload_0
		// @93: sipush -18887 (0xB639)
		// @96: iadd
		// @97: invokestatic game.C_100091_m.func_104503_a(int)void
		// @9A: goto @BF
		// @9D: astore_1
		// @9E: aload_1
		// @9F: new java.lang.StringBuilder
		// @A2: dup
		// @A3: invokespecial java.lang.StringBuilder.<init>()void
		// @A6: getstatic java.lang.String[] game.C_100152_bd.field_105213_z
		// @A9: bipush 9 (0x09)
		// @AB: aaload
		// @AC: invokevirtual java.lang.StringBuilder.append(java.lang.String)java.lang.StringBuilder
		// @AF: iload_0
		// @B0: invokevirtual java.lang.StringBuilder.append(int)java.lang.StringBuilder
		// @B3: bipush 41 (0x29)
		// @B5: invokevirtual java.lang.StringBuilder.append(char)java.lang.StringBuilder
		// @B8: invokevirtual java.lang.StringBuilder.toString()java.lang.String
		// @BB: invokestatic game.C_100181_cf.func_105695_a(java.lang.Throwable, java.lang.String)game.C_100170_cm
		// @BE: athrow
		// @BF: return
	}
	
	public abstract void init();
	
	public final void windowClosing(WindowEvent arg0)
	{
		// @00: aload_0
		// @01: invokevirtual game.C_100152_bd.destroy()void
		// @04: goto @3B
		// @07: astore_2
		// @08: aload_2
		// @09: new java.lang.StringBuilder
		// @0C: dup
		// @0D: invokespecial java.lang.StringBuilder.<init>()void
		// @10: getstatic java.lang.String[] game.C_100152_bd.field_105213_z
		// @13: bipush 7 (0x07)
		// @15: aaload
		// @16: invokevirtual java.lang.StringBuilder.append(java.lang.String)java.lang.StringBuilder
		// @19: aload_1
		// @1A: ifnull @27
		// @1D: getstatic java.lang.String[] game.C_100152_bd.field_105213_z
		// @20: bipush 6 (0x06)
		// @22: aaload
		// @23: goto @2C
		// @26: athrow
		// @27: getstatic java.lang.String[] game.C_100152_bd.field_105213_z
		// @2A: iconst_0
		// @2B: aaload
		// @2C: invokevirtual java.lang.StringBuilder.append(java.lang.String)java.lang.StringBuilder
		// @2F: bipush 41 (0x29)
		// @31: invokevirtual java.lang.StringBuilder.append(char)java.lang.StringBuilder
		// @34: invokevirtual java.lang.StringBuilder.toString()java.lang.String
		// @37: invokestatic game.C_100181_cf.func_105695_a(java.lang.Throwable, java.lang.String)game.C_100170_cm
		// @3A: athrow
		// @3B: return
	}
	
	protected C_100152_bd()
	{
		// @0: aload_0
		// @1: invokespecial java.applet.Applet.<init>()void
		// @4: aload_0
		// @5: iconst_0
		// @6: putfield boolean game.C_100152_bd.field_105212_p
		// @9: return
	}
	
	static
	{
		// @000: bipush 61 (0x3D)
		// @002: anewarray java.lang.String
		// @005: dup
		// @006: iconst_0
		// @007: ldc "F\u0006\u001br"
		// @009: invokestatic game.C_100152_bd.func_105187_z(java.lang.String)char[]
		// @00C: invokestatic game.C_100152_bd.func_105177_z(char[])java.lang.String
		// @00F: aastore
		// @010: dup
		// @011: iconst_1
		// @012: ldc "\u0006\u0004\u0004"
		// @014: invokestatic game.C_100152_bd.func_105187_z(java.lang.String)char[]
		// @017: invokestatic game.C_100152_bd.func_105177_z(char[])java.lang.String
		// @01A: aastore
		// @01B: dup
		// @01C: iconst_2
		// @01D: ldc "J\u0017Y]'\u0000"
		// @01F: invokestatic game.C_100152_bd.func_105187_z(java.lang.String)char[]
		// @022: invokestatic game.C_100152_bd.func_105177_z(char[])java.lang.String
		// @025: aastore
		// @026: dup
		// @027: iconst_3
		// @028: ldc "w\u0007\u0018n"
		// @02A: invokestatic game.C_100152_bd.func_105187_z(java.lang.String)char[]
		// @02D: invokestatic game.C_100152_bd.func_105177_z(char[])java.lang.String
		// @030: aastore
		// @031: dup
		// @032: iconst_4
		// @033: ldc "M\u0001\u0005q\u0017w\u0014\u0016s\u0000w"
		// @035: invokestatic game.C_100152_bd.func_105187_z(java.lang.String)char[]
		// @038: invokestatic game.C_100152_bd.func_105177_z(char[])java.lang.String
		// @03B: aastore
		// @03C: dup
		// @03D: iconst_5
		// @03E: ldc "D\u001c\u0010y\u0000L\u001c\u0002j"
		// @040: invokestatic game.C_100152_bd.func_105187_z(java.lang.String)char[]
		// @043: invokestatic game.C_100152_bd.func_105177_z(char[])java.lang.String
		// @046: aastore
		// @047: dup
		// @048: bipush 6 (0x06)
		// @04A: ldc "S]Y0\u0018"
		// @04C: invokestatic game.C_100152_bd.func_105187_z(java.lang.String)char[]
		// @04F: invokestatic game.C_100152_bd.func_105177_z(char[])java.lang.String
		// @052: aastore
		// @053: dup
		// @054: bipush 7 (0x07)
		// @056: ldc_w "J\u0017Yi\u000cF\u0017\u0018i&D\u001c\u0004w\u000bO["
		// @059: invokestatic game.C_100152_bd.func_105187_z(java.lang.String)char[]
		// @05C: invokestatic game.C_100152_bd.func_105177_z(char[])java.lang.String
		// @05F: aastore
		// @060: dup
		// @061: bipush 8 (0x08)
		// @063: ldc "\u0014\u0011\u0005 "
		// @065: invokestatic game.C_100152_bd.func_105187_z(java.lang.String)char[]
		// @068: invokestatic game.C_100152_bd.func_105177_z(char[])java.lang.String
		// @06B: aastore
		// @06C: dup
		// @06D: bipush 9 (0x09)
		// @06F: ldc_w "J\u0017YO$\u0000"
		// @072: invokestatic game.C_100152_bd.func_105187_z(java.lang.String)char[]
		// @075: invokestatic game.C_100152_bd.func_105177_z(char[])java.lang.String
		// @078: aastore
		// @079: dup
		// @07A: bipush 10 (0x0A)
		// @07C: ldc "J\u0017YJ$\u0000"
		// @07E: invokestatic game.C_100152_bd.func_105187_z(java.lang.String)char[]
		// @081: invokestatic game.C_100152_bd.func_105177_z(char[])java.lang.String
		// @084: aastore
		// @085: dup
		// @086: bipush 11 (0x0B)
		// @088: ldc "J\u0017Yy\u0000\\7\u0018}\u0010E\u0016\u0019j'I\u0000\u00126L"
		// @08A: invokestatic game.C_100152_bd.func_105187_z(java.lang.String)char[]
		// @08D: invokestatic game.C_100152_bd.func_105177_z(char[])java.lang.String
		// @090: aastore
		// @091: dup
		// @092: bipush 12 (0x0C)
		// @094: ldc "J\u0017Ym\u0011G\u0003_7"
		// @096: invokestatic game.C_100152_bd.func_105187_z(java.lang.String)char[]
		// @099: invokestatic game.C_100152_bd.func_105177_z(char[])java.lang.String
		// @09C: aastore
		// @09D: dup
		// @09E: bipush 13 (0x0D)
		// @0A0: ldc "J\u0017YI$\u0000"
		// @0A2: invokestatic game.C_100152_bd.func_105187_z(java.lang.String)char[]
		// @0A5: invokestatic game.C_100152_bd.func_105177_z(char[])java.lang.String
		// @0A8: aastore
		// @0A9: dup
		// @0AA: bipush 14 (0x0E)
		// @0AC: ldc "{\u001b\u0002j\u0001G\u0004\u0019>\u0006G\u001e\u0007r\u0000\\\u0016W3EK\u001f\u0012\u007f\u000b\u0012"
		// @0AE: invokestatic game.C_100152_bd.func_105187_z(java.lang.String)char[]
		// @0B1: invokestatic game.C_100152_bd.func_105177_z(char[])java.lang.String
		// @0B4: aastore
		// @0B5: dup
		// @0B6: bipush 15 (0x0F)
		// @0B8: ldc "J\u0017YY'\u0000"
		// @0BA: invokestatic game.C_100152_bd.func_105187_z(java.lang.String)char[]
		// @0BD: invokestatic game.C_100152_bd.func_105177_z(char[])java.lang.String
		// @0C0: aastore
		// @0C1: dup
		// @0C2: bipush 16 (0x10)
		// @0C4: ldc "J\u0017YZ'\u0000"
		// @0C6: invokestatic game.C_100152_bd.func_105187_z(java.lang.String)char[]
		// @0C9: invokestatic game.C_100152_bd.func_105177_z(char[])java.lang.String
		// @0CC: aastore
		// @0CD: dup
		// @0CE: bipush 17 (0x11)
		// @0D0: ldc "J\u0017Yy\u0000\\2\u0007n\tM\u00074q\u000b\\\u0016\u000fjM\u0001"
		// @0D2: invokestatic game.C_100152_bd.func_105187_z(java.lang.String)char[]
		// @0D5: invokestatic game.C_100152_bd.func_105177_z(char[])java.lang.String
		// @0D8: aastore
		// @0D9: dup
		// @0DA: bipush 18 (0x12)
		// @0DC: ldc "J\u0017Yz\u0000[\u0007\u0005q\u001c\u0000Z"
		// @0DE: invokestatic game.C_100152_bd.func_105187_z(java.lang.String)char[]
		// @0E1: invokestatic game.C_100152_bd.func_105177_z(char[])java.lang.String
		// @0E4: aastore
		// @0E5: dup
		// @0E6: bipush 19 (0x13)
		// @0E8: ldc "J\u0017Yk\u0015L\u0012\u0003{M"
		// @0EA: invokestatic game.C_100152_bd.func_105187_z(java.lang.String)char[]
		// @0ED: invokestatic game.C_100152_bd.func_105177_z(char[])java.lang.String
		// @0F0: aastore
		// @0F1: dup
		// @0F2: bipush 20 (0x14)
		// @0F4: ldc "J\u0017Yy\u0000\\#\u0016l\u0004E\u0016\u0003{\u0017\u0000"
		// @0F6: invokestatic game.C_100152_bd.func_105187_z(java.lang.String)char[]
		// @0F9: invokestatic game.C_100152_bd.func_105177_z(char[])java.lang.String
		// @0FC: aastore
		// @0FD: dup
		// @0FE: bipush 21 (0x15)
		// @100: ldc "J\u0017YL$\u0000"
		// @102: invokestatic game.C_100152_bd.func_105187_z(java.lang.String)char[]
		// @105: invokestatic game.C_100152_bd.func_105177_z(char[])java.lang.String
		// @108: aastore
		// @109: dup
		// @10A: bipush 22 (0x16)
		// @10C: ldc "J\u0017Ym\u0011I\u0001\u00036L"
		// @10E: invokestatic game.C_100152_bd.func_105187_z(java.lang.String)char[]
		// @111: invokestatic game.C_100152_bd.func_105177_z(char[])java.lang.String
		// @114: aastore
		// @115: dup
		// @116: bipush 23 (0x17)
		// @118: ldc "J\u0017Yx\nK\u0006\u0004R\n[\u0007_"
		// @11A: invokestatic game.C_100152_bd.func_105187_z(java.lang.String)char[]
		// @11D: invokestatic game.C_100152_bd.func_105177_z(char[])java.lang.String
		// @120: aastore
		// @121: dup
		// @122: bipush 24 (0x18)
		// @124: ldc "J\u0017YX'\u0000"
		// @126: invokestatic game.C_100152_bd.func_105187_z(java.lang.String)char[]
		// @129: invokestatic game.C_100152_bd.func_105177_z(char[])java.lang.String
		// @12C: aastore
		// @12D: dup
		// @12E: bipush 25 (0x19)
		// @130: ldc "J\u0017Y\\'\u0000"
		// @132: invokestatic game.C_100152_bd.func_105187_z(java.lang.String)char[]
		// @135: invokestatic game.C_100152_bd.func_105177_z(char[])java.lang.String
		// @138: aastore
		// @139: dup
		// @13A: bipush 26 (0x1A)
		// @13C: ldc "K\u0001\u0016m\r"
		// @13E: invokestatic game.C_100152_bd.func_105187_z(java.lang.String)char[]
		// @141: invokestatic game.C_100152_bd.func_105177_z(char[])java.lang.String
		// @144: aastore
		// @145: dup
		// @146: bipush 27 (0x1B)
		// @148: ldc "I\u001f\u0005{\u0004L\n\u001bq\u0004L\u0016\u0013"
		// @14A: invokestatic game.C_100152_bd.func_105187_z(java.lang.String)char[]
		// @14D: invokestatic game.C_100152_bd.func_105177_z(char[])java.lang.String
		// @150: aastore
		// @151: dup
		// @152: bipush 28 (0x1C)
		// @154: ldc "w\u0000\u0012r\u0003"
		// @156: invokestatic game.C_100152_bd.func_105187_z(java.lang.String)char[]
		// @159: invokestatic game.C_100152_bd.func_105177_z(char[])java.lang.String
		// @15C: aastore
		// @15D: dup
		// @15E: bipush 29 (0x1D)
		// @160: ldc "\u0019]A0U"
		// @162: invokestatic game.C_100152_bd.func_105187_z(java.lang.String)char[]
		// @165: invokestatic game.C_100152_bd.func_105177_z(char[])java.lang.String
		// @168: aastore
		// @169: dup
		// @16A: bipush 30 (0x1E)
		// @16C: ldc "\u0019]E0"
		// @16E: invokestatic game.C_100152_bd.func_105187_z(java.lang.String)char[]
		// @171: invokestatic game.C_100152_bd.func_105177_z(char[])java.lang.String
		// @174: aastore
		// @175: dup
		// @176: bipush 31 (0x1F)
		// @178: ldc "\u0019]F0"
		// @17A: invokestatic game.C_100152_bd.func_105187_z(java.lang.String)char[]
		// @17D: invokestatic game.C_100152_bd.func_105177_z(char[])java.lang.String
		// @180: aastore
		// @181: dup
		// @182: bipush 32 (0x20)
		// @184: ldc "\u0019]E"
		// @186: invokestatic game.C_100152_bd.func_105187_z(java.lang.String)char[]
		// @189: invokestatic game.C_100152_bd.func_105177_z(char[])java.lang.String
		// @18C: aastore
		// @18D: dup
		// @18E: bipush 33 (0x21)
		// @190: ldc "\u0019]D0"
		// @192: invokestatic game.C_100152_bd.func_105187_z(java.lang.String)char[]
		// @195: invokestatic game.C_100152_bd.func_105177_z(char[])java.lang.String
		// @198: aastore
		// @199: dup
		// @19A: bipush 34 (0x22)
		// @19C: ldc "[\u0006\u0019"
		// @19E: invokestatic game.C_100152_bd.func_105187_z(java.lang.String)char[]
		// @1A1: invokestatic game.C_100152_bd.func_105177_z(char[])java.lang.String
		// @1A4: aastore
		// @1A5: dup
		// @1A6: bipush 35 (0x23)
		// @1A8: ldc "\u0019]B0"
		// @1AA: invokestatic game.C_100152_bd.func_105187_z(java.lang.String)char[]
		// @1AD: invokestatic game.C_100152_bd.func_105177_z(char[])java.lang.String
		// @1B0: aastore
		// @1B1: dup
		// @1B2: bipush 36 (0x24)
		// @1B4: ldc "\u0019]B"
		// @1B6: invokestatic game.C_100152_bd.func_105187_z(java.lang.String)char[]
		// @1B9: invokestatic game.C_100152_bd.func_105177_z(char[])java.lang.String
		// @1BC: aastore
		// @1BD: dup
		// @1BE: bipush 37 (0x25)
		// @1C0: ldc "\u0019]D"
		// @1C2: invokestatic game.C_100152_bd.func_105187_z(java.lang.String)char[]
		// @1C5: invokestatic game.C_100152_bd.func_105177_z(char[])java.lang.String
		// @1C8: aastore
		// @1C9: dup
		// @1CA: bipush 38 (0x26)
		// @1CC: ldc "J\u0017Yl\u0010F[^"
		// @1CE: invokestatic game.C_100152_bd.func_105187_z(java.lang.String)char[]
		// @1D1: invokestatic game.C_100152_bd.func_105177_z(char[])java.lang.String
		// @1D4: aastore
		// @1D5: dup
		// @1D6: bipush 39 (0x27)
		// @1D8: ldc "\u0019]C0"
		// @1DA: invokestatic game.C_100152_bd.func_105187_z(java.lang.String)char[]
		// @1DD: invokestatic game.C_100152_bd.func_105177_z(char[])java.lang.String
		// @1E0: aastore
		// @1E1: dup
		// @1E2: bipush 40 (0x28)
		// @1E4: ldc "I\u0003\u0007r\u0000"
		// @1E6: invokestatic game.C_100152_bd.func_105187_z(java.lang.String)char[]
		// @1E9: invokestatic game.C_100152_bd.func_105177_z(char[])java.lang.String
		// @1EC: aastore
		// @1ED: dup
		// @1EE: bipush 41 (0x29)
		// @1F0: ldc "_\u0001\u0018p\u0002B\u0012\u0001\u007f"
		// @1F2: invokestatic game.C_100152_bd.func_105187_z(java.lang.String)char[]
		// @1F5: invokestatic game.C_100152_bd.func_105177_z(char[])java.lang.String
		// @1F8: aastore
		// @1F9: dup
		// @1FA: bipush 42 (0x2A)
		// @1FC: ldc "\u0019]A0Uw"
		// @1FE: invokestatic game.C_100152_bd.func_105187_z(java.lang.String)char[]
		// @201: invokestatic game.C_100152_bd.func_105177_z(char[])java.lang.String
		// @204: aastore
		// @205: dup
		// @206: bipush 43 (0x2B)
		// @208: ldc "\u0019]C"
		// @20A: invokestatic game.C_100152_bd.func_105187_z(java.lang.String)char[]
		// @20D: invokestatic game.C_100152_bd.func_105177_z(char[])java.lang.String
		// @210: aastore
		// @211: dup
		// @212: bipush 44 (0x2C)
		// @214: ldc "\u0019]"
		// @216: invokestatic game.C_100152_bd.func_105187_z(java.lang.String)char[]
		// @219: invokestatic game.C_100152_bd.func_105177_z(char[])java.lang.String
		// @21C: aastore
		// @21D: dup
		// @21E: bipush 45 (0x2D)
		// @220: ldc "\u0019]F"
		// @222: invokestatic game.C_100152_bd.func_105187_z(java.lang.String)char[]
		// @225: invokestatic game.C_100152_bd.func_105177_z(char[])java.lang.String
		// @228: aastore
		// @229: dup
		// @22A: bipush 46 (0x2E)
		// @22C: ldc "J\u0017Yn\u0017G\u0005\u001ez\u0000d\u001c\u0016z\u0000Z2\u0007n\tM\u0007_"
		// @22E: invokestatic game.C_100152_bd.func_105187_z(java.lang.String)char[]
		// @231: invokestatic game.C_100152_bd.func_105177_z(char[])java.lang.String
		// @234: aastore
		// @235: dup
		// @236: bipush 47 (0x2F)
		// @238: ldc "\u0006\u0019\u0016y\u0000P]\u0014q\u0008"
		// @23A: invokestatic game.C_100152_bd.func_105187_z(java.lang.String)char[]
		// @23D: invokestatic game.C_100152_bd.func_105177_z(char[])java.lang.String
		// @240: aastore
		// @241: dup
		// @242: bipush 48 (0x30)
		// @244: ldc "\u0019JE0T\u001eKY/K"
		// @246: invokestatic game.C_100152_bd.func_105187_z(java.lang.String)char[]
		// @249: invokestatic game.C_100152_bd.func_105177_z(char[])java.lang.String
		// @24C: aastore
		// @24D: dup
		// @24E: bipush 49 (0x31)
		// @250: ldc "B\u0012\u0010{\u001d\u0006\u0010\u0018s"
		// @252: invokestatic game.C_100152_bd.func_105187_z(java.lang.String)char[]
		// @255: invokestatic game.C_100152_bd.func_105177_z(char[])java.lang.String
		// @258: aastore
		// @259: dup
		// @25A: bipush 50 (0x32)
		// @25C: ldc "\u0019A@0U\u0006CY/"
		// @25E: invokestatic game.C_100152_bd.func_105187_z(java.lang.String)char[]
		// @261: invokestatic game.C_100152_bd.func_105177_z(char[])java.lang.String
		// @264: aastore
		// @265: dup
		// @266: bipush 51 (0x33)
		// @268: ldc "J\u0017Y['\u0000"
		// @26A: invokestatic game.C_100152_bd.func_105187_z(java.lang.String)char[]
		// @26D: invokestatic game.C_100152_bd.func_105177_z(char[])java.lang.String
		// @270: aastore
		// @271: dup
		// @272: bipush 52 (0x34)
		// @274: ldc "N\u0006\u0019q\u0017J]\u0014q\u0008"
		// @276: invokestatic game.C_100152_bd.func_105187_z(java.lang.String)char[]
		// @279: invokestatic game.C_100152_bd.func_105177_z(char[])java.lang.String
		// @27C: aastore
		// @27D: dup
		// @27E: bipush 53 (0x35)
		// @280: ldc "A\u001d\u0001\u007f\tA\u0017\u001fq\u0016\\"
		// @282: invokestatic game.C_100152_bd.func_105187_z(java.lang.String)char[]
		// @285: invokestatic game.C_100152_bd.func_105177_z(char[])java.lang.String
		// @288: aastore
		// @289: dup
		// @28A: bipush 54 (0x36)
		// @28C: ldc "\u0006\u0015\u0002p\nZ\u0011Y}\nE"
		// @28E: invokestatic game.C_100152_bd.func_105187_z(java.lang.String)char[]
		// @291: invokestatic game.C_100152_bd.func_105177_z(char[])java.lang.String
		// @294: aastore
		// @295: dup
		// @296: bipush 55 (0x37)
		// @298: ldc "J\u0017YM$\u0000"
		// @29A: invokestatic game.C_100152_bd.func_105187_z(java.lang.String)char[]
		// @29D: invokestatic game.C_100152_bd.func_105177_z(char[])java.lang.String
		// @2A0: aastore
		// @2A1: dup
		// @2A2: bipush 56 (0x38)
		// @2A4: ldc "J\u0017Yx\nK\u0006\u0004Y\u0004A\u001d\u0012zM"
		// @2A6: invokestatic game.C_100152_bd.func_105187_z(java.lang.String)char[]
		// @2A9: invokestatic game.C_100152_bd.func_105177_z(char[])java.lang.String
		// @2AC: aastore
		// @2AD: dup
		// @2AE: bipush 57 (0x39)
		// @2B0: ldc "J\u0017YK$\u0000"
		// @2B2: invokestatic game.C_100152_bd.func_105187_z(java.lang.String)char[]
		// @2B5: invokestatic game.C_100152_bd.func_105177_z(char[])java.lang.String
		// @2B8: aastore
		// @2B9: dup
		// @2BA: bipush 58 (0x3A)
		// @2BC: ldc "J\u0017Y_'\u0000"
		// @2BE: invokestatic game.C_100152_bd.func_105187_z(java.lang.String)char[]
		// @2C1: invokestatic game.C_100152_bd.func_105177_z(char[])java.lang.String
		// @2C4: aastore
		// @2C5: dup
		// @2C6: bipush 59 (0x3B)
		// @2C8: ldc "J\u0017Yn\u0004A\u001d\u00036"
		// @2CA: invokestatic game.C_100152_bd.func_105187_z(java.lang.String)char[]
		// @2CD: invokestatic game.C_100152_bd.func_105177_z(char[])java.lang.String
		// @2D0: aastore
		// @2D1: dup
		// @2D2: bipush 60 (0x3C)
		// @2D4: ldc "J\u0017YH$\u0000"
		// @2D6: invokestatic game.C_100152_bd.func_105187_z(java.lang.String)char[]
		// @2D9: invokestatic game.C_100152_bd.func_105177_z(char[])java.lang.String
		// @2DC: aastore
		// @2DD: putstatic java.lang.String[] game.C_100152_bd.field_105213_z
		// @2E0: ldc_w "{\u0007\u0016x\u0003\u0008\u001a\u001an\u0000Z\u0000\u0018p\u0004\\\u001a\u0018p"
		// @2E3: invokestatic game.C_100152_bd.func_105187_z(java.lang.String)char[]
		// @2E6: invokestatic game.C_100152_bd.func_105177_z(char[])java.lang.String
		// @2E9: putstatic java.lang.String game.C_100152_bd.field_105204_n
		// @2EC: ldc_w "|\u001cWm\u0000Z\u0005\u0012lED\u001a\u0004j"
		// @2EF: invokestatic game.C_100152_bd.func_105187_z(java.lang.String)char[]
		// @2F2: invokestatic game.C_100152_bd.func_105177_z(char[])java.lang.String
		// @2F5: putstatic java.lang.String game.C_100152_bd.field_105205_o
		// @2F8: ldc_w "a\u001d\u0001\u007f\tA\u0017WR\nO\u001a\u0019>\nZS'\u007f\u0016[\u0004\u0018l\u0001\u0014\u0011\u0005 YJ\u0001IX\nZS\u0016}\u0006G\u0006\u0019j\u0016\u0008\u0010\u0005{\u0004\\\u0016\u0013>\u0004N\u0007\u0012lE\\\u001b\u0012>W\u001c\u0007\u001f>\nNS9q\u0013M\u001e\u0015{\u0017\u0008AG/U\u0004S\u0007r\u0000I\u0000\u0012>\u0010[\u0016Wg\n]\u0001W{\u0008I\u001a\u001b>\u0004L\u0017\u0005{\u0016[S\u0003qED\u001c\u0010>\u000cF]K|\u0017\u0016O\u0015l[g\u0007\u001f{\u0017_\u001a\u0004{EX\u001f\u0012\u007f\u0016MS\u001bq\u0002\u0008\u001a\u0019>\u0012A\u0007\u001f>\u001cG\u0006\u0005>\u0010[\u0016\u0005p\u0004E\u0016Y"
		// @2FB: invokestatic game.C_100152_bd.func_105187_z(java.lang.String)char[]
		// @2FE: invokestatic game.C_100152_bd.func_105177_z(char[])java.lang.String
		// @301: putstatic java.lang.String game.C_100152_bd.field_105208_j
		// @304: new game.C_100186_rl
		// @307: dup
		// @308: invokespecial game.C_100186_rl.<init>()void
		// @30B: putstatic game.C_100186_rl game.C_100152_bd.field_105206_l
		// @30E: return
	}
	
	private static char[] func_105187_z(String arg0)
	{
		// @00: aload_0
		// @01: invokevirtual java.lang.String.toCharArray()char[]
		// @04: dup
		// @05: arraylength
		// @06: iconst_2
		// @07: if_icmpge @13
		// @0A: dup
		// @0B: iconst_0
		// @0C: dup2
		// @0D: caload
		// @0E: bipush 101 (0x65)
		// @10: ixor
		// @11: i2c
		// @12: castore
		// @13: areturn
	}
	
	private static String func_105177_z(char[] arg0)
	{
		// @00: aload_0
		// @01: dup
		// @02: arraylength
		// @03: swap
		// @04: iconst_0
		// @05: istore_1
		// @06: goto @4C
		// @09: dup
		// @0A: iload_1
		// @0B: dup2
		// @0C: caload
		// @0D: iload_1
		// @0E: iconst_5
		// @0F: irem
		// @10: tableswitch def: @44, for 0: @30, for 1: @35, for 2: @3A, for 3: @3F
		// @30: bipush 40 (0x28)
		// @32: goto @46
		// @35: bipush 115 (0x73)
		// @37: goto @46
		// @3A: bipush 119 (0x77)
		// @3C: goto @46
		// @3F: bipush 30 (0x1E)
		// @41: goto @46
		// @44: bipush 101 (0x65)
		// @46: ixor
		// @47: i2c
		// @48: castore
		// @49: iinc #1 +1
		// @4C: swap
		// @4D: dup_x1
		// @4E: iload_1
		// @4F: if_icmpgt @09
		// @52: new java.lang.String
		// @55: dup_x1
		// @56: swap
		// @57: invokespecial java.lang.String.<init>(char[])void
		// @5A: invokevirtual java.lang.String.intern()java.lang.String
		// @5D: areturn
	}
}
