package game;

final class C_100211_qd extends C_100302_ka
{
	C_100302_ka field_102143_oc;
	int field_102160_Zb;
	C_100302_ka field_102144_mc;
	static int[] field_102164_fc;
	int field_102142_Ub;
	static String field_102169_Bc;
	int field_102138_ec;
	C_100302_ka field_102145_tc;
	String field_102155_dc;
	static int field_102149_xc;
	boolean field_102175_Kc;
	C_100302_ka[] field_102162_hc;
	boolean field_102153_Lc;
	boolean field_102135_Dc;
	C_100302_ka field_102141_ic;
	int field_102170_ac;
	C_100302_ka field_102161_Xb;
	static int field_102139_rc;
	C_100302_ka field_102172_uc;
	C_100302_ka field_102177_cc;
	boolean field_102173_Ic;
	String[] field_102171_lc;
	boolean field_102134_zc;
	C_100302_ka field_102147_kc;
	C_100302_ka field_102152_bc;
	long field_102140_Wb;
	int field_102151_vc;
	C_100302_ka field_102174_wc;
	int field_102159_sc;
	static int field_102163_qc;
	byte[] field_102165_jc;
	long field_102156_Gc;
	C_100302_ka field_102137_Yb;
	boolean field_102167_nc;
	static String field_102154_Jc;
	boolean field_102150_Cc;
	C_100302_ka field_102146_Ac;
	C_100302_ka field_102166_Vb;
	C_100302_ka field_102136_gc;
	static boolean field_102158_yc;
	int field_102133_Fc;
	C_100302_ka field_102148_Hc;
	C_100302_ka field_102168_pc;
	int field_102157_Ec;
	private static final String[] field_102176_Mc;
	
	final int func_102127_b(boolean arg0)
	{
		// @00: iload_1
		// @01: iconst_1
		// @02: if_icmpeq @08
		// @05: bipush 107 (0x6B)
		// @07: ireturn
		// @08: aload_0
		// @09: bipush 116 (0x74)
		// @0B: invokevirtual game.C_100211_qd.func_101470_f(int)long
		// @0E: l2i
		// @0F: ireturn
		// @10: astore_2
		// @11: aload_2
		// @12: new java.lang.StringBuilder
		// @15: dup
		// @16: invokespecial java.lang.StringBuilder.<init>()void
		// @19: getstatic java.lang.String[] game.C_100211_qd.field_102176_Mc
		// @1C: iconst_3
		// @1D: aaload
		// @1E: invokevirtual java.lang.StringBuilder.append(java.lang.String)java.lang.StringBuilder
		// @21: iload_1
		// @22: invokevirtual java.lang.StringBuilder.append(boolean)java.lang.StringBuilder
		// @25: bipush 41 (0x29)
		// @27: invokevirtual java.lang.StringBuilder.append(char)java.lang.StringBuilder
		// @2A: invokevirtual java.lang.StringBuilder.toString()java.lang.String
		// @2D: invokestatic game.C_100181_cf.func_105695_a(java.lang.Throwable, java.lang.String)game.C_100170_cm
		// @30: athrow
	}
	
	C_100211_qd(int arg0)
	{
		// @00: aload_0
		// @01: lconst_0
		// @02: aconst_null
		// @03: invokespecial game.C_100302_ka.<init>(long, game.C_100302_ka)void
		// @06: aload_0
		// @07: iload_1
		// @08: newarray byte[]
		// @0A: putfield byte[] game.C_100211_qd.field_102165_jc
		// @0D: goto @32
		// @10: astore_2
		// @11: aload_2
		// @12: new java.lang.StringBuilder
		// @15: dup
		// @16: invokespecial java.lang.StringBuilder.<init>()void
		// @19: getstatic java.lang.String[] game.C_100211_qd.field_102176_Mc
		// @1C: bipush 8 (0x08)
		// @1E: aaload
		// @1F: invokevirtual java.lang.StringBuilder.append(java.lang.String)java.lang.StringBuilder
		// @22: iload_1
		// @23: invokevirtual java.lang.StringBuilder.append(int)java.lang.StringBuilder
		// @26: bipush 41 (0x29)
		// @28: invokevirtual java.lang.StringBuilder.append(char)java.lang.StringBuilder
		// @2B: invokevirtual java.lang.StringBuilder.toString()java.lang.String
		// @2E: invokestatic game.C_100181_cf.func_105695_a(java.lang.Throwable, java.lang.String)game.C_100170_cm
		// @31: athrow
		// @32: return
	}
	
	final boolean func_102125_g(byte arg0)
	{
		// @00: iload_1
		// @01: bipush -108 (0x94)
		// @03: if_icmpeq @08
		// @06: iconst_0
		// @07: ireturn
		// @08: aload_0
		// @09: bipush -57 (0xC7)
		// @0B: invokevirtual game.C_100211_qd.func_101469_a(byte)boolean
		// @0E: ifne @16
		// @11: iconst_1
		// @12: goto @17
		// @15: athrow
		// @16: iconst_0
		// @17: ireturn
		// @18: astore_2
		// @19: aload_2
		// @1A: new java.lang.StringBuilder
		// @1D: dup
		// @1E: invokespecial java.lang.StringBuilder.<init>()void
		// @21: getstatic java.lang.String[] game.C_100211_qd.field_102176_Mc
		// @24: bipush 7 (0x07)
		// @26: aaload
		// @27: invokevirtual java.lang.StringBuilder.append(java.lang.String)java.lang.StringBuilder
		// @2A: iload_1
		// @2B: invokevirtual java.lang.StringBuilder.append(int)java.lang.StringBuilder
		// @2E: bipush 41 (0x29)
		// @30: invokevirtual java.lang.StringBuilder.append(char)java.lang.StringBuilder
		// @33: invokevirtual java.lang.StringBuilder.toString()java.lang.String
		// @36: invokestatic game.C_100181_cf.func_105695_a(java.lang.Throwable, java.lang.String)game.C_100170_cm
		// @39: athrow
	}
	
	final boolean func_102132_a(byte arg0, C_100211_qd arg1)
	{
		// @000: iload_1
		// @001: bipush 32 (0x20)
		// @003: if_icmpge @008
		// @006: iconst_0
		// @007: ireturn
		// @008: aload_0
		// @009: getfield boolean game.C_100211_qd.field_102153_Lc
		// @00C: ifne @01C
		// @00F: bipush 6 (0x06)
		// @011: aload_0
		// @012: getfield int game.C_100211_qd.field_102170_ac
		// @015: if_icmpne @021
		// @018: goto @01C
		// @01B: athrow
		// @01C: iconst_1
		// @01D: goto @022
		// @020: athrow
		// @021: iconst_0
		// @022: istore_3
		// @023: aload_2
		// @024: getfield boolean game.C_100211_qd.field_102153_Lc
		// @027: ifne @037
		// @02A: aload_2
		// @02B: getfield int game.C_100211_qd.field_102170_ac
		// @02E: bipush 6 (0x06)
		// @030: if_icmpne @03C
		// @033: goto @037
		// @036: athrow
		// @037: iconst_1
		// @038: goto @03D
		// @03B: athrow
		// @03C: iconst_0
		// @03D: istore #4
		// @03F: iload_3
		// @040: iload #4
		// @042: ifne @04A
		// @045: iconst_1
		// @046: goto @04B
		// @049: athrow
		// @04A: iconst_0
		// @04B: if_icmpne @050
		// @04E: iload_3
		// @04F: ireturn
		// @050: iload_3
		// @051: ifne @098
		// @054: aload_0
		// @055: getfield boolean game.C_100211_qd.field_102167_nc
		// @058: aload_2
		// @059: getfield boolean game.C_100211_qd.field_102167_nc
		// @05C: if_icmpeq @068
		// @05F: goto @063
		// @062: athrow
		// @063: aload_0
		// @064: getfield boolean game.C_100211_qd.field_102167_nc
		// @067: ireturn
		// @068: aload_0
		// @069: getfield boolean game.C_100211_qd.field_102167_nc
		// @06C: ifeq @098
		// @06F: aload_2
		// @070: getfield int game.C_100211_qd.field_102159_sc
		// @073: iconst_m1
		// @074: ixor
		// @075: aload_0
		// @076: getfield int game.C_100211_qd.field_102159_sc
		// @079: iconst_m1
		// @07A: ixor
		// @07B: if_icmpeq @098
		// @07E: goto @082
		// @081: athrow
		// @082: aload_2
		// @083: getfield int game.C_100211_qd.field_102159_sc
		// @086: aload_0
		// @087: getfield int game.C_100211_qd.field_102159_sc
		// @08A: if_icmple @096
		// @08D: goto @091
		// @090: athrow
		// @091: iconst_1
		// @092: goto @097
		// @095: athrow
		// @096: iconst_0
		// @097: ireturn
		// @098: aload_2
		// @099: getfield boolean game.C_100211_qd.field_102173_Ic
		// @09C: ifne @0A4
		// @09F: iconst_1
		// @0A0: goto @0A5
		// @0A3: athrow
		// @0A4: iconst_0
		// @0A5: aload_0
		// @0A6: getfield boolean game.C_100211_qd.field_102173_Ic
		// @0A9: ifne @0B1
		// @0AC: iconst_1
		// @0AD: goto @0B2
		// @0B0: athrow
		// @0B1: iconst_0
		// @0B2: if_icmpeq @0C7
		// @0B5: aload_0
		// @0B6: getfield boolean game.C_100211_qd.field_102173_Ic
		// @0B9: ifne @0C5
		// @0BC: goto @0C0
		// @0BF: athrow
		// @0C0: iconst_1
		// @0C1: goto @0C6
		// @0C4: athrow
		// @0C5: iconst_0
		// @0C6: ireturn
		// @0C7: aload_0
		// @0C8: getfield boolean game.C_100211_qd.field_102173_Ic
		// @0CB: ifne @0ED
		// @0CE: aload_0
		// @0CF: getfield long game.C_100211_qd.field_102140_Wb
		// @0D2: ldc2_w -1
		// @0D5: lxor
		// @0D6: aload_2
		// @0D7: getfield long game.C_100211_qd.field_102140_Wb
		// @0DA: ldc2_w -1
		// @0DD: lxor
		// @0DE: lcmp
		// @0DF: ifle @0EB
		// @0E2: goto @0E6
		// @0E5: athrow
		// @0E6: iconst_1
		// @0E7: goto @0EC
		// @0EA: athrow
		// @0EB: iconst_0
		// @0EC: ireturn
		// @0ED: aload_0
		// @0EE: getfield boolean game.C_100211_qd.field_102135_Dc
		// @0F1: ifne @103
		// @0F4: aload_0
		// @0F5: getfield int game.C_100211_qd.field_102133_Fc
		// @0F8: iconst_m1
		// @0F9: ixor
		// @0FA: bipush -3 (0xFD)
		// @0FC: if_icmpne @108
		// @0FF: goto @103
		// @102: athrow
		// @103: iconst_1
		// @104: goto @109
		// @107: athrow
		// @108: iconst_0
		// @109: istore #5
		// @10B: aload_2
		// @10C: getfield boolean game.C_100211_qd.field_102135_Dc
		// @10F: ifne @121
		// @112: bipush -3 (0xFD)
		// @114: aload_2
		// @115: getfield int game.C_100211_qd.field_102133_Fc
		// @118: iconst_m1
		// @119: ixor
		// @11A: if_icmpne @126
		// @11D: goto @121
		// @120: athrow
		// @121: iconst_1
		// @122: goto @127
		// @125: athrow
		// @126: iconst_0
		// @127: istore #6
		// @129: iload #5
		// @12B: ifne @133
		// @12E: iconst_1
		// @12F: goto @134
		// @132: athrow
		// @133: iconst_0
		// @134: iload #6
		// @136: ifne @13E
		// @139: iconst_1
		// @13A: goto @13F
		// @13D: athrow
		// @13E: iconst_0
		// @13F: if_icmpeq @145
		// @142: iload #5
		// @144: ireturn
		// @145: aload_0
		// @146: getfield long game.C_100211_qd.field_102140_Wb
		// @149: aload_2
		// @14A: getfield long game.C_100211_qd.field_102140_Wb
		// @14D: lcmp
		// @14E: ifle @156
		// @151: iconst_1
		// @152: goto @157
		// @155: athrow
		// @156: iconst_0
		// @157: ireturn
		// @158: astore_3
		// @159: aload_3
		// @15A: new java.lang.StringBuilder
		// @15D: dup
		// @15E: invokespecial java.lang.StringBuilder.<init>()void
		// @161: getstatic java.lang.String[] game.C_100211_qd.field_102176_Mc
		// @164: iconst_1
		// @165: aaload
		// @166: invokevirtual java.lang.StringBuilder.append(java.lang.String)java.lang.StringBuilder
		// @169: iload_1
		// @16A: invokevirtual java.lang.StringBuilder.append(int)java.lang.StringBuilder
		// @16D: bipush 44 (0x2C)
		// @16F: invokevirtual java.lang.StringBuilder.append(char)java.lang.StringBuilder
		// @172: aload_2
		// @173: ifnull @17F
		// @176: getstatic java.lang.String[] game.C_100211_qd.field_102176_Mc
		// @179: iconst_2
		// @17A: aaload
		// @17B: goto @184
		// @17E: athrow
		// @17F: getstatic java.lang.String[] game.C_100211_qd.field_102176_Mc
		// @182: iconst_0
		// @183: aaload
		// @184: invokevirtual java.lang.StringBuilder.append(java.lang.String)java.lang.StringBuilder
		// @187: bipush 41 (0x29)
		// @189: invokevirtual java.lang.StringBuilder.append(char)java.lang.StringBuilder
		// @18C: invokevirtual java.lang.StringBuilder.toString()java.lang.String
		// @18F: invokestatic game.C_100181_cf.func_105695_a(java.lang.Throwable, java.lang.String)game.C_100170_cm
		// @192: athrow
	}
	
	static final void func_102124_l(int arg0)
	{
		// @00: new game.C_100053_vn
		// @03: dup
		// @04: invokespecial game.C_100053_vn.<init>()void
		// @07: putstatic game.C_100053_vn game.C_100282_nh.field_102713_Jb
		// @0A: getstatic game.C_100209_qb game.C_100318_hj.field_107201_j
		// @0D: getstatic game.C_100053_vn game.C_100282_nh.field_102713_Jb
		// @10: bipush 75 (0x4B)
		// @12: invokevirtual game.C_100209_qb.func_102660_a(game.C_100336_im, byte)void
		// @15: iload_0
		// @16: bipush -70 (0xBA)
		// @18: if_icmple @20
		// @1B: bipush -9 (0xF7)
		// @1D: invokestatic game.C_100211_qd.func_102124_l(int)void
		// @20: goto @45
		// @23: astore_1
		// @24: aload_1
		// @25: new java.lang.StringBuilder
		// @28: dup
		// @29: invokespecial java.lang.StringBuilder.<init>()void
		// @2C: getstatic java.lang.String[] game.C_100211_qd.field_102176_Mc
		// @2F: bipush 9 (0x09)
		// @31: aaload
		// @32: invokevirtual java.lang.StringBuilder.append(java.lang.String)java.lang.StringBuilder
		// @35: iload_0
		// @36: invokevirtual java.lang.StringBuilder.append(int)java.lang.StringBuilder
		// @39: bipush 41 (0x29)
		// @3B: invokevirtual java.lang.StringBuilder.append(char)java.lang.StringBuilder
		// @3E: invokevirtual java.lang.StringBuilder.toString()java.lang.String
		// @41: invokestatic game.C_100181_cf.func_105695_a(java.lang.Throwable, java.lang.String)game.C_100170_cm
		// @44: athrow
		// @45: return
	}
	
	static final void func_102129_c(boolean arg0)
	{
		// @00: iload_0
		// @01: iconst_1
		// @02: if_icmpeq @15
		// @05: bipush -88 (0xA8)
		// @07: bipush 55 (0x37)
		// @09: bipush -45 (0xD3)
		// @0B: bipush -56 (0xC8)
		// @0D: invokestatic game.C_100211_qd.func_102123_a(int, int, int, int)int
		// @10: pop
		// @11: goto @15
		// @14: athrow
		// @15: new game.C_100202_qi
		// @18: dup
		// @19: invokespecial game.C_100202_qi.<init>()void
		// @1C: putstatic game.C_100202_qi game.C_100132_td.field_104979_l
		// @1F: goto @44
		// @22: astore_1
		// @23: aload_1
		// @24: new java.lang.StringBuilder
		// @27: dup
		// @28: invokespecial java.lang.StringBuilder.<init>()void
		// @2B: getstatic java.lang.String[] game.C_100211_qd.field_102176_Mc
		// @2E: bipush 10 (0x0A)
		// @30: aaload
		// @31: invokevirtual java.lang.StringBuilder.append(java.lang.String)java.lang.StringBuilder
		// @34: iload_0
		// @35: invokevirtual java.lang.StringBuilder.append(boolean)java.lang.StringBuilder
		// @38: bipush 41 (0x29)
		// @3A: invokevirtual java.lang.StringBuilder.append(char)java.lang.StringBuilder
		// @3D: invokevirtual java.lang.StringBuilder.toString()java.lang.String
		// @40: invokestatic game.C_100181_cf.func_105695_a(java.lang.Throwable, java.lang.String)game.C_100170_cm
		// @43: athrow
		// @44: return
	}
	
	static final void func_102131_a(int arg0, String arg1)
	{
		// @00: iload_0
		// @01: bipush 12 (0x0C)
		// @03: if_icmpge @13
		// @06: bipush 63 (0x3F)
		// @08: aconst_null
		// @09: checkcast java.lang.String
		// @0C: invokestatic game.C_100211_qd.func_102131_a(int, java.lang.String)void
		// @0F: goto @13
		// @12: athrow
		// @13: bipush -85 (0xAB)
		// @15: aload_1
		// @16: invokestatic game.C_100132_td.func_104969_a(byte, java.lang.String)void
		// @19: bipush 45 (0x2D)
		// @1B: getstatic java.lang.String game.C_100341_jd.field_102644_rb
		// @1E: iconst_0
		// @1F: invokestatic game.C_100158_da.func_100589_a(int, java.lang.String, boolean)void
		// @22: goto @61
		// @25: astore_2
		// @26: aload_2
		// @27: new java.lang.StringBuilder
		// @2A: dup
		// @2B: invokespecial java.lang.StringBuilder.<init>()void
		// @2E: getstatic java.lang.String[] game.C_100211_qd.field_102176_Mc
		// @31: bipush 6 (0x06)
		// @33: aaload
		// @34: invokevirtual java.lang.StringBuilder.append(java.lang.String)java.lang.StringBuilder
		// @37: iload_0
		// @38: invokevirtual java.lang.StringBuilder.append(int)java.lang.StringBuilder
		// @3B: bipush 44 (0x2C)
		// @3D: invokevirtual java.lang.StringBuilder.append(char)java.lang.StringBuilder
		// @40: aload_1
		// @41: ifnull @4D
		// @44: getstatic java.lang.String[] game.C_100211_qd.field_102176_Mc
		// @47: iconst_2
		// @48: aaload
		// @49: goto @52
		// @4C: athrow
		// @4D: getstatic java.lang.String[] game.C_100211_qd.field_102176_Mc
		// @50: iconst_0
		// @51: aaload
		// @52: invokevirtual java.lang.StringBuilder.append(java.lang.String)java.lang.StringBuilder
		// @55: bipush 41 (0x29)
		// @57: invokevirtual java.lang.StringBuilder.append(char)java.lang.StringBuilder
		// @5A: invokevirtual java.lang.StringBuilder.toString()java.lang.String
		// @5D: invokestatic game.C_100181_cf.func_105695_a(java.lang.Throwable, java.lang.String)game.C_100170_cm
		// @60: athrow
		// @61: return
	}
	
	public static void func_102130_f(byte arg0)
	{
		// @00: aconst_null
		// @01: putstatic int[] game.C_100211_qd.field_102164_fc
		// @04: iload_0
		// @05: bipush 54 (0x36)
		// @07: if_icmpgt @1A
		// @0A: bipush -86 (0xAA)
		// @0C: bipush 100 (0x64)
		// @0E: bipush -95 (0xA1)
		// @10: bipush -52 (0xCC)
		// @12: invokestatic game.C_100211_qd.func_102123_a(int, int, int, int)int
		// @15: pop
		// @16: goto @1A
		// @19: athrow
		// @1A: aconst_null
		// @1B: putstatic java.lang.String game.C_100211_qd.field_102169_Bc
		// @1E: aconst_null
		// @1F: putstatic java.lang.String game.C_100211_qd.field_102154_Jc
		// @22: goto @46
		// @25: astore_1
		// @26: aload_1
		// @27: new java.lang.StringBuilder
		// @2A: dup
		// @2B: invokespecial java.lang.StringBuilder.<init>()void
		// @2E: getstatic java.lang.String[] game.C_100211_qd.field_102176_Mc
		// @31: iconst_5
		// @32: aaload
		// @33: invokevirtual java.lang.StringBuilder.append(java.lang.String)java.lang.StringBuilder
		// @36: iload_0
		// @37: invokevirtual java.lang.StringBuilder.append(int)java.lang.StringBuilder
		// @3A: bipush 41 (0x29)
		// @3C: invokevirtual java.lang.StringBuilder.append(char)java.lang.StringBuilder
		// @3F: invokevirtual java.lang.StringBuilder.toString()java.lang.String
		// @42: invokestatic game.C_100181_cf.func_105695_a(java.lang.Throwable, java.lang.String)game.C_100170_cm
		// @45: athrow
		// @46: return
	}
	
	static final int func_102123_a(int arg0, int arg1, int arg2, int arg3)
	{
		// @00: iload_2
		// @01: iload_1
		// @02: iadd
		// @03: getstatic int game.C_100196_rb.field_105819_e
		// @06: if_icmpgt @0B
		// @09: iload_1
		// @0A: ireturn
		// @0B: iload_2
		// @0C: ineg
		// @0D: iload_0
		// @0E: iadd
		// @0F: iload_1
		// @10: iadd
		// @11: iconst_m1
		// @12: ixor
		// @13: iload_3
		// @14: if_icmpgt @1E
		// @17: iload_2
		// @18: ineg
		// @19: iload_0
		// @1A: iload_1
		// @1B: iadd
		// @1C: iadd
		// @1D: ireturn
		// @1E: getstatic int game.C_100196_rb.field_105819_e
		// @21: iload_2
		// @22: isub
		// @23: ireturn
		// @24: astore #4
		// @26: aload #4
		// @28: new java.lang.StringBuilder
		// @2B: dup
		// @2C: invokespecial java.lang.StringBuilder.<init>()void
		// @2F: getstatic java.lang.String[] game.C_100211_qd.field_102176_Mc
		// @32: iconst_4
		// @33: aaload
		// @34: invokevirtual java.lang.StringBuilder.append(java.lang.String)java.lang.StringBuilder
		// @37: iload_0
		// @38: invokevirtual java.lang.StringBuilder.append(int)java.lang.StringBuilder
		// @3B: bipush 44 (0x2C)
		// @3D: invokevirtual java.lang.StringBuilder.append(char)java.lang.StringBuilder
		// @40: iload_1
		// @41: invokevirtual java.lang.StringBuilder.append(int)java.lang.StringBuilder
		// @44: bipush 44 (0x2C)
		// @46: invokevirtual java.lang.StringBuilder.append(char)java.lang.StringBuilder
		// @49: iload_2
		// @4A: invokevirtual java.lang.StringBuilder.append(int)java.lang.StringBuilder
		// @4D: bipush 44 (0x2C)
		// @4F: invokevirtual java.lang.StringBuilder.append(char)java.lang.StringBuilder
		// @52: iload_3
		// @53: invokevirtual java.lang.StringBuilder.append(int)java.lang.StringBuilder
		// @56: bipush 41 (0x29)
		// @58: invokevirtual java.lang.StringBuilder.append(char)java.lang.StringBuilder
		// @5B: invokevirtual java.lang.StringBuilder.toString()java.lang.String
		// @5E: invokestatic game.C_100181_cf.func_105695_a(java.lang.Throwable, java.lang.String)game.C_100170_cm
		// @61: athrow
	}
	
	static
	{
		// @00: bipush 11 (0x0B)
		// @02: anewarray java.lang.String
		// @05: dup
		// @06: iconst_0
		// @07: ldc "(,$\u001b"
		// @09: invokestatic game.C_100211_qd.func_102128_z(java.lang.String)char[]
		// @0C: invokestatic game.C_100211_qd.func_102126_z(char[])java.lang.String
		// @0F: aastore
		// @10: dup
		// @11: iconst_1
		// @12: ldc "7=f4h"
		// @14: invokestatic game.C_100211_qd.func_102128_z(java.lang.String)char[]
		// @17: invokestatic game.C_100211_qd.func_102126_z(char[])java.lang.String
		// @1A: aastore
		// @1B: dup
		// @1C: iconst_2
		// @1D: ldc "=wfY="
		// @1F: invokestatic game.C_100211_qd.func_102128_z(java.lang.String)char[]
		// @22: invokestatic game.C_100211_qd.func_102126_z(char[])java.lang.String
		// @25: aastore
		// @26: dup
		// @27: iconst_3
		// @28: ldc "7=f?h"
		// @2A: invokestatic game.C_100211_qd.func_102128_z(java.lang.String)char[]
		// @2D: invokestatic game.C_100211_qd.func_102126_z(char[])java.lang.String
		// @30: aastore
		// @31: dup
		// @32: iconst_4
		// @33: ldc "7=f6h"
		// @35: invokestatic game.C_100211_qd.func_102128_z(java.lang.String)char[]
		// @38: invokestatic game.C_100211_qd.func_102126_z(char[])java.lang.String
		// @3B: aastore
		// @3C: dup
		// @3D: iconst_5
		// @3E: ldc "7=f1h"
		// @40: invokestatic game.C_100211_qd.func_102128_z(java.lang.String)char[]
		// @43: invokestatic game.C_100211_qd.func_102126_z(char[])java.lang.String
		// @46: aastore
		// @47: dup
		// @48: bipush 6 (0x06)
		// @4A: ldc "7=f2h"
		// @4C: invokestatic game.C_100211_qd.func_102128_z(java.lang.String)char[]
		// @4F: invokestatic game.C_100211_qd.func_102126_z(char[])java.lang.String
		// @52: aastore
		// @53: dup
		// @54: bipush 7 (0x07)
		// @56: ldc "7=f3h"
		// @58: invokestatic game.C_100211_qd.func_102128_z(java.lang.String)char[]
		// @5B: invokestatic game.C_100211_qd.func_102126_z(char[])java.lang.String
		// @5E: aastore
		// @5F: dup
		// @60: bipush 8 (0x08)
		// @62: ldc "7=fK)(0<Ih"
		// @64: invokestatic game.C_100211_qd.func_102128_z(java.lang.String)char[]
		// @67: invokestatic game.C_100211_qd.func_102126_z(char[])java.lang.String
		// @6A: aastore
		// @6B: dup
		// @6C: bipush 9 (0x09)
		// @6E: ldc "7=f0h"
		// @70: invokestatic game.C_100211_qd.func_102128_z(java.lang.String)char[]
		// @73: invokestatic game.C_100211_qd.func_102126_z(char[])java.lang.String
		// @76: aastore
		// @77: dup
		// @78: bipush 10 (0x0A)
		// @7A: ldc "7=f5h"
		// @7C: invokestatic game.C_100211_qd.func_102128_z(java.lang.String)char[]
		// @7F: invokestatic game.C_100211_qd.func_102126_z(char[])java.lang.String
		// @82: aastore
		// @83: putstatic java.lang.String[] game.C_100211_qd.field_102176_Mc
		// @86: ldc "\u0008\u0016\u00062"
		// @88: invokestatic game.C_100211_qd.func_102128_z(java.lang.String)char[]
		// @8B: invokestatic game.C_100211_qd.func_102126_z(char[])java.lang.String
		// @8E: putstatic java.lang.String game.C_100211_qd.field_102169_Bc
		// @91: bipush 9 (0x09)
		// @93: newarray int[]
		// @95: dup
		// @96: iconst_0
		// @97: iconst_2
		// @98: iastore
		// @99: dup
		// @9A: iconst_1
		// @9B: bipush 20 (0x14)
		// @9D: iastore
		// @9E: dup
		// @9F: iconst_2
		// @A0: bipush 21 (0x15)
		// @A2: iastore
		// @A3: dup
		// @A4: iconst_3
		// @A5: bipush 6 (0x06)
		// @A7: iastore
		// @A8: dup
		// @A9: iconst_4
		// @AA: bipush 37 (0x25)
		// @AC: iastore
		// @AD: dup
		// @AE: iconst_5
		// @AF: bipush 45 (0x2D)
		// @B1: iastore
		// @B2: dup
		// @B3: bipush 6 (0x06)
		// @B5: iconst_5
		// @B6: iastore
		// @B7: dup
		// @B8: bipush 7 (0x07)
		// @BA: bipush 12 (0x0C)
		// @BC: iastore
		// @BD: dup
		// @BE: bipush 8 (0x08)
		// @C0: bipush 13 (0x0D)
		// @C2: iastore
		// @C3: putstatic int[] game.C_100211_qd.field_102164_fc
		// @C6: ldc "\n6)\u0013)(>h\u001a550+"
		// @C8: invokestatic game.C_100211_qd.func_102128_z(java.lang.String)char[]
		// @CB: invokestatic game.C_100211_qd.func_102126_z(char[])java.lang.String
		// @CE: putstatic java.lang.String game.C_100211_qd.field_102154_Jc
		// @D1: iconst_0
		// @D2: putstatic boolean game.C_100211_qd.field_102158_yc
		// @D5: return
	}
	
	private static char[] func_102128_z(String arg0)
	{
		// @00: aload_0
		// @01: invokevirtual java.lang.String.toCharArray()char[]
		// @04: dup
		// @05: arraylength
		// @06: iconst_2
		// @07: if_icmpge @13
		// @0A: dup
		// @0B: iconst_0
		// @0C: dup2
		// @0D: caload
		// @0E: bipush 64 (0x40)
		// @10: ixor
		// @11: i2c
		// @12: castore
		// @13: areturn
	}
	
	private static String func_102126_z(char[] arg0)
	{
		// @00: aload_0
		// @01: dup
		// @02: arraylength
		// @03: swap
		// @04: iconst_0
		// @05: istore_1
		// @06: goto @4C
		// @09: dup
		// @0A: iload_1
		// @0B: dup2
		// @0C: caload
		// @0D: iload_1
		// @0E: iconst_5
		// @0F: irem
		// @10: tableswitch def: @44, for 0: @30, for 1: @35, for 2: @3A, for 3: @3F
		// @30: bipush 70 (0x46)
		// @32: goto @46
		// @35: bipush 89 (0x59)
		// @37: goto @46
		// @3A: bipush 72 (0x48)
		// @3C: goto @46
		// @3F: bipush 119 (0x77)
		// @41: goto @46
		// @44: bipush 64 (0x40)
		// @46: ixor
		// @47: i2c
		// @48: castore
		// @49: iinc #1 +1
		// @4C: swap
		// @4D: dup_x1
		// @4E: iload_1
		// @4F: if_icmpgt @09
		// @52: new java.lang.String
		// @55: dup_x1
		// @56: swap
		// @57: invokespecial java.lang.String.<init>(char[])void
		// @5A: invokevirtual java.lang.String.intern()java.lang.String
		// @5D: areturn
	}
}
