package game;

import java.awt.Component;
import java.awt.Graphics;
import java.awt.Canvas;

final class C_100212_qc extends Canvas
{
	static String field_105977_c;
	private Component field_105981_k;
	static int field_105982_h;
	static String[] field_105979_l;
	static String field_105973_g;
	static int[] field_105980_j;
	static String[] field_105975_e;
	static int field_105976_b;
	static String field_105978_a;
	static int[] field_105972_f;
	static String field_105983_i;
	static String field_105974_d;
	private static final String[] field_105984_z;
	
	public final void update(Graphics arg0)
	{
		// @00: aload_0
		// @01: getfield java.awt.Component game.C_100212_qc.field_105981_k
		// @04: aload_1
		// @05: invokevirtual java.awt.Component.update(java.awt.Graphics)void
		// @08: goto @3E
		// @0B: astore_2
		// @0C: aload_2
		// @0D: new java.lang.StringBuilder
		// @10: dup
		// @11: invokespecial java.lang.StringBuilder.<init>()void
		// @14: getstatic java.lang.String[] game.C_100212_qc.field_105984_z
		// @17: bipush 6 (0x06)
		// @19: aaload
		// @1A: invokevirtual java.lang.StringBuilder.append(java.lang.String)java.lang.StringBuilder
		// @1D: aload_1
		// @1E: ifnull @2A
		// @21: getstatic java.lang.String[] game.C_100212_qc.field_105984_z
		// @24: iconst_2
		// @25: aaload
		// @26: goto @2F
		// @29: athrow
		// @2A: getstatic java.lang.String[] game.C_100212_qc.field_105984_z
		// @2D: iconst_1
		// @2E: aaload
		// @2F: invokevirtual java.lang.StringBuilder.append(java.lang.String)java.lang.StringBuilder
		// @32: bipush 41 (0x29)
		// @34: invokevirtual java.lang.StringBuilder.append(char)java.lang.StringBuilder
		// @37: invokevirtual java.lang.StringBuilder.toString()java.lang.String
		// @3A: invokestatic game.C_100181_cf.func_105695_a(java.lang.Throwable, java.lang.String)game.C_100170_cm
		// @3D: athrow
		// @3E: return
	}
	
	public final void paint(Graphics arg0)
	{
		// @00: aload_0
		// @01: getfield java.awt.Component game.C_100212_qc.field_105981_k
		// @04: aload_1
		// @05: invokevirtual java.awt.Component.paint(java.awt.Graphics)void
		// @08: goto @3D
		// @0B: astore_2
		// @0C: aload_2
		// @0D: new java.lang.StringBuilder
		// @10: dup
		// @11: invokespecial java.lang.StringBuilder.<init>()void
		// @14: getstatic java.lang.String[] game.C_100212_qc.field_105984_z
		// @17: iconst_4
		// @18: aaload
		// @19: invokevirtual java.lang.StringBuilder.append(java.lang.String)java.lang.StringBuilder
		// @1C: aload_1
		// @1D: ifnull @29
		// @20: getstatic java.lang.String[] game.C_100212_qc.field_105984_z
		// @23: iconst_2
		// @24: aaload
		// @25: goto @2E
		// @28: athrow
		// @29: getstatic java.lang.String[] game.C_100212_qc.field_105984_z
		// @2C: iconst_1
		// @2D: aaload
		// @2E: invokevirtual java.lang.StringBuilder.append(java.lang.String)java.lang.StringBuilder
		// @31: bipush 41 (0x29)
		// @33: invokevirtual java.lang.StringBuilder.append(char)java.lang.StringBuilder
		// @36: invokevirtual java.lang.StringBuilder.toString()java.lang.String
		// @39: invokestatic game.C_100181_cf.func_105695_a(java.lang.Throwable, java.lang.String)game.C_100170_cm
		// @3C: athrow
		// @3D: return
	}
	
	public static void func_105968_a(int arg0)
	{
		// @00: aconst_null
		// @01: putstatic java.lang.String game.C_100212_qc.field_105973_g
		// @04: aconst_null
		// @05: putstatic java.lang.String[] game.C_100212_qc.field_105975_e
		// @08: aconst_null
		// @09: putstatic java.lang.String[] game.C_100212_qc.field_105979_l
		// @0C: aconst_null
		// @0D: putstatic int[] game.C_100212_qc.field_105972_f
		// @10: iload_0
		// @11: bipush 7 (0x07)
		// @13: if_icmpeq @21
		// @16: aconst_null
		// @17: checkcast java.lang.String[]
		// @1A: putstatic java.lang.String[] game.C_100212_qc.field_105975_e
		// @1D: goto @21
		// @20: athrow
		// @21: aconst_null
		// @22: putstatic java.lang.String game.C_100212_qc.field_105974_d
		// @25: aconst_null
		// @26: putstatic java.lang.String game.C_100212_qc.field_105983_i
		// @29: aconst_null
		// @2A: putstatic java.lang.String game.C_100212_qc.field_105977_c
		// @2D: aconst_null
		// @2E: putstatic java.lang.String game.C_100212_qc.field_105978_a
		// @31: aconst_null
		// @32: putstatic int[] game.C_100212_qc.field_105980_j
		// @35: goto @5A
		// @38: astore_1
		// @39: aload_1
		// @3A: new java.lang.StringBuilder
		// @3D: dup
		// @3E: invokespecial java.lang.StringBuilder.<init>()void
		// @41: getstatic java.lang.String[] game.C_100212_qc.field_105984_z
		// @44: bipush 7 (0x07)
		// @46: aaload
		// @47: invokevirtual java.lang.StringBuilder.append(java.lang.String)java.lang.StringBuilder
		// @4A: iload_0
		// @4B: invokevirtual java.lang.StringBuilder.append(int)java.lang.StringBuilder
		// @4E: bipush 41 (0x29)
		// @50: invokevirtual java.lang.StringBuilder.append(char)java.lang.StringBuilder
		// @53: invokevirtual java.lang.StringBuilder.toString()java.lang.String
		// @56: invokestatic game.C_100181_cf.func_105695_a(java.lang.Throwable, java.lang.String)game.C_100170_cm
		// @59: athrow
		// @5A: return
	}
	
	C_100212_qc(Component arg0)
	{
		// @00: aload_0
		// @01: invokespecial java.awt.Canvas.<init>()void
		// @04: aload_0
		// @05: aload_1
		// @06: putfield java.awt.Component game.C_100212_qc.field_105981_k
		// @09: goto @3E
		// @0C: astore_2
		// @0D: aload_2
		// @0E: new java.lang.StringBuilder
		// @11: dup
		// @12: invokespecial java.lang.StringBuilder.<init>()void
		// @15: getstatic java.lang.String[] game.C_100212_qc.field_105984_z
		// @18: iconst_3
		// @19: aaload
		// @1A: invokevirtual java.lang.StringBuilder.append(java.lang.String)java.lang.StringBuilder
		// @1D: aload_1
		// @1E: ifnull @2A
		// @21: getstatic java.lang.String[] game.C_100212_qc.field_105984_z
		// @24: iconst_2
		// @25: aaload
		// @26: goto @2F
		// @29: athrow
		// @2A: getstatic java.lang.String[] game.C_100212_qc.field_105984_z
		// @2D: iconst_1
		// @2E: aaload
		// @2F: invokevirtual java.lang.StringBuilder.append(java.lang.String)java.lang.StringBuilder
		// @32: bipush 41 (0x29)
		// @34: invokevirtual java.lang.StringBuilder.append(char)java.lang.StringBuilder
		// @37: invokevirtual java.lang.StringBuilder.toString()java.lang.String
		// @3A: invokestatic game.C_100181_cf.func_105695_a(java.lang.Throwable, java.lang.String)game.C_100170_cm
		// @3D: athrow
		// @3E: return
	}
	
	static final void func_105971_a(int arg0, int arg1)
	{
		// @00: bipush -110 (0x92)
		// @02: iload_1
		// @03: invokestatic game.C_100091_m.func_104509_a(int, int)void
		// @06: iload_0
		// @07: iconst_1
		// @08: if_icmpeq @15
		// @0B: bipush 110 (0x6E)
		// @0D: ldc2_w -98
		// @10: bipush -56 (0xC8)
		// @12: invokestatic game.C_100212_qc.func_105967_a(int, long, int)void
		// @15: goto @42
		// @18: astore_2
		// @19: aload_2
		// @1A: new java.lang.StringBuilder
		// @1D: dup
		// @1E: invokespecial java.lang.StringBuilder.<init>()void
		// @21: getstatic java.lang.String[] game.C_100212_qc.field_105984_z
		// @24: iconst_5
		// @25: aaload
		// @26: invokevirtual java.lang.StringBuilder.append(java.lang.String)java.lang.StringBuilder
		// @29: iload_0
		// @2A: invokevirtual java.lang.StringBuilder.append(int)java.lang.StringBuilder
		// @2D: bipush 44 (0x2C)
		// @2F: invokevirtual java.lang.StringBuilder.append(char)java.lang.StringBuilder
		// @32: iload_1
		// @33: invokevirtual java.lang.StringBuilder.append(int)java.lang.StringBuilder
		// @36: bipush 41 (0x29)
		// @38: invokevirtual java.lang.StringBuilder.append(char)java.lang.StringBuilder
		// @3B: invokevirtual java.lang.StringBuilder.toString()java.lang.String
		// @3E: invokestatic game.C_100181_cf.func_105695_a(java.lang.Throwable, java.lang.String)game.C_100170_cm
		// @41: athrow
		// @42: return
	}
	
	static final void func_105967_a(int arg0, long arg1, int arg2)
	{
		// @00: getstatic game.C_100278_nd game.C_100115_ej.field_102043_Yb
		// @03: astore #4
		// @05: aload #4
		// @07: iload_3
		// @08: bipush 114 (0x72)
		// @0A: invokevirtual game.C_100278_nd.func_101189_h(int, int)void
		// @0D: aload #4
		// @0F: dup
		// @10: getfield int game.C_100278_nd.field_101177_n
		// @13: iconst_1
		// @14: iadd
		// @15: putfield int game.C_100278_nd.field_101177_n
		// @18: aload #4
		// @1A: getfield int game.C_100278_nd.field_101177_n
		// @1D: istore #5
		// @1F: aload #4
		// @21: sipush 7838 (0x1E9E)
		// @24: bipush 6 (0x06)
		// @26: invokevirtual game.C_100278_nd.func_101169_f(int, int)void
		// @29: aload #4
		// @2B: iconst_0
		// @2C: lload_1
		// @2D: invokevirtual game.C_100278_nd.func_101131_a(int, long)void
		// @30: aload #4
		// @32: iload #5
		// @34: ineg
		// @35: aload #4
		// @37: getfield int game.C_100278_nd.field_101177_n
		// @3A: iadd
		// @3B: bipush -91 (0xA5)
		// @3D: invokevirtual game.C_100278_nd.func_101139_c(int, byte)void
		// @40: iload_0
		// @41: sipush -1181 (0xFB63)
		// @44: if_icmpeq @54
		// @47: bipush -107 (0x95)
		// @49: ldc2_w -48
		// @4C: iconst_0
		// @4D: invokestatic game.C_100212_qc.func_105967_a(int, long, int)void
		// @50: goto @54
		// @53: athrow
		// @54: goto @8C
		// @57: astore #4
		// @59: aload #4
		// @5B: new java.lang.StringBuilder
		// @5E: dup
		// @5F: invokespecial java.lang.StringBuilder.<init>()void
		// @62: getstatic java.lang.String[] game.C_100212_qc.field_105984_z
		// @65: iconst_0
		// @66: aaload
		// @67: invokevirtual java.lang.StringBuilder.append(java.lang.String)java.lang.StringBuilder
		// @6A: iload_0
		// @6B: invokevirtual java.lang.StringBuilder.append(int)java.lang.StringBuilder
		// @6E: bipush 44 (0x2C)
		// @70: invokevirtual java.lang.StringBuilder.append(char)java.lang.StringBuilder
		// @73: lload_1
		// @74: invokevirtual java.lang.StringBuilder.append(long)java.lang.StringBuilder
		// @77: bipush 44 (0x2C)
		// @79: invokevirtual java.lang.StringBuilder.append(char)java.lang.StringBuilder
		// @7C: iload_3
		// @7D: invokevirtual java.lang.StringBuilder.append(int)java.lang.StringBuilder
		// @80: bipush 41 (0x29)
		// @82: invokevirtual java.lang.StringBuilder.append(char)java.lang.StringBuilder
		// @85: invokevirtual java.lang.StringBuilder.toString()java.lang.String
		// @88: invokestatic game.C_100181_cf.func_105695_a(java.lang.Throwable, java.lang.String)game.C_100170_cm
		// @8B: athrow
		// @8C: return
	}
	
	static
	{
		// @000: bipush 8 (0x08)
		// @002: anewarray java.lang.String
		// @005: dup
		// @006: iconst_0
		// @007: ldc "4:U\r0"
		// @009: invokestatic game.C_100212_qc.func_105970_z(java.lang.String)char[]
		// @00C: invokestatic game.C_100212_qc.func_105969_z(char[])java.lang.String
		// @00F: aastore
		// @010: dup
		// @011: iconst_1
		// @012: ldc "+,\u0017#"
		// @014: invokestatic game.C_100212_qc.func_105970_z(java.lang.String)char[]
		// @017: invokestatic game.C_100212_qc.func_105969_z(char[])java.lang.String
		// @01A: aastore
		// @01B: dup
		// @01C: iconst_2
		// @01D: ldc ">wUae"
		// @01F: invokestatic game.C_100212_qc.func_105970_z(java.lang.String)char[]
		// @022: invokestatic game.C_100212_qc.func_105969_z(char[])java.lang.String
		// @025: aastore
		// @026: dup
		// @027: iconst_3
		// @028: ldc "4:Usq+0\u000fq0"
		// @02A: invokestatic game.C_100212_qc.func_105970_z(java.lang.String)char[]
		// @02D: invokestatic game.C_100212_qc.func_105969_z(char[])java.lang.String
		// @030: aastore
		// @031: dup
		// @032: iconst_4
		// @033: ldc "4:U?y,7\u000fg"
		// @035: invokestatic game.C_100212_qc.func_105970_z(java.lang.String)char[]
		// @038: invokestatic game.C_100212_qc.func_105969_z(char[])java.lang.String
		// @03B: aastore
		// @03C: dup
		// @03D: iconst_5
		// @03E: ldc "4:U\u000c0"
		// @040: invokestatic game.C_100212_qc.func_105970_z(java.lang.String)char[]
		// @043: invokestatic game.C_100212_qc.func_105969_z(char[])java.lang.String
		// @046: aastore
		// @047: dup
		// @048: bipush 6 (0x06)
		// @04A: ldc "4:U:h!8\u000f*0"
		// @04C: invokestatic game.C_100212_qc.func_105970_z(java.lang.String)char[]
		// @04F: invokestatic game.C_100212_qc.func_105969_z(char[])java.lang.String
		// @052: aastore
		// @053: dup
		// @054: bipush 7 (0x07)
		// @056: ldc "4:U\u000e0"
		// @058: invokestatic game.C_100212_qc.func_105970_z(java.lang.String)char[]
		// @05B: invokestatic game.C_100212_qc.func_105969_z(char[])java.lang.String
		// @05E: aastore
		// @05F: putstatic java.lang.String[] game.C_100212_qc.field_105984_z
		// @062: iconst_4
		// @063: anewarray java.lang.String
		// @066: dup
		// @067: iconst_0
		// @068: ldc "\u00061\u001a<k,*"
		// @06A: invokestatic game.C_100212_qc.func_105970_z(java.lang.String)char[]
		// @06D: invokestatic game.C_100212_qc.func_105969_z(char[])java.lang.String
		// @070: aastore
		// @071: dup
		// @072: iconst_1
		// @073: ldc "\u00066\u0016?w+<\u0015;k"
		// @075: invokestatic game.C_100212_qc.func_105970_z(java.lang.String)char[]
		// @078: invokestatic game.C_100212_qc.func_105969_z(char[])java.lang.String
		// @07B: aastore
		// @07C: dup
		// @07D: iconst_2
		// @07E: ldc "\u0012<\u001a?w+*"
		// @080: invokestatic game.C_100212_qc.func_105970_z(java.lang.String)char[]
		// @083: invokestatic game.C_100212_qc.func_105969_z(char[])java.lang.String
		// @086: aastore
		// @087: dup
		// @088: iconst_3
		// @089: ldc "\u00086\u001f:t *"
		// @08B: invokestatic game.C_100212_qc.func_105970_z(java.lang.String)char[]
		// @08E: invokestatic game.C_100212_qc.func_105969_z(char[])java.lang.String
		// @091: aastore
		// @092: putstatic java.lang.String[] game.C_100212_qc.field_105979_l
		// @095: ldc "y|Kq$'+Es=tg[sl,4\u001e<&ee^}&"
		// @097: invokestatic game.C_100212_qc.func_105970_z(java.lang.String)char[]
		// @09A: invokestatic game.C_100212_qc.func_105969_z(char[])java.lang.String
		// @09D: putstatic java.lang.String game.C_100212_qc.field_105973_g
		// @0A0: ldc "\u00155\u001e.k y\u000c.q1y\u000c'q)<[8}e*\u001e.j&1Usz7g<.u *[:k08\u0017#ae*\u000f.j1y\u000c&l-0\u0015oye4\u0012!m1<Woh76\r&| =[;p y\u0008*j3<\toq6y\u0019:k<y\u001e!w0>\u0013a$'+Esz7g/'}e5\u0014!\u007f +[6w0y\u001a=}e?\u0014={ =[;we.\u001a&liy\u000f'}e<\u001a=t,<\toq+y\u000f'}e5\u0012<le6\u001doh)8\u0002*j6y\u0002 me8\t*8)0\u0010*t<y\u000f 8$)\u000b*y7wG-j{e\u0019=&\u000c?[;p y\u001c.u y\u001f }67\\;86-\u001a=liy\u0018#q&2[h[$7\u0018*tby\u001a!|e-\u0013*ve-\t68&1\u0014 k,7\u001co?\u00016\u0015hle4\u0012!|by\u001d je4\u0014=}e6\u000b;q*7\u0008ow7y\u00088q1:\u0013&v\"y\u000f 8$y\u0019:k,<\tot*;\u001966"
		// @0A2: invokestatic game.C_100212_qc.func_105970_z(java.lang.String)char[]
		// @0A5: invokestatic game.C_100212_qc.func_105969_z(char[])java.lang.String
		// @0A8: putstatic java.lang.String game.C_100212_qc.field_105978_a
		// @0AB: iconst_4
		// @0AC: anewarray java.lang.String
		// @0AF: dup
		// @0B0: iconst_0
		// @0B1: ldc "y|Jq828\u0008ok-6\u0018$}!y\u000f 86<\u001eo$`iEhke;\u0017.| "
		// @0B3: invokestatic game.C_100212_qc.func_105970_z(java.lang.String)char[]
		// @0B6: invokestatic game.C_100212_qc.func_105969_z(char[])java.lang.String
		// @0B9: aastore
		// @0BA: dup
		// @0BB: iconst_1
		// @0BC: ldc "y|Jq828\u0008o{$,\u001c'le0\u0015o$`iEhke4\u0012(p1 [<p*:\u00108y3<"
		// @0BE: invokestatic game.C_100212_qc.func_105970_z(java.lang.String)char[]
		// @0C1: invokestatic game.C_100212_qc.func_105969_z(char[])java.lang.String
		// @0C4: aastore
		// @0C5: dup
		// @0C6: iconst_2
		// @0C7: ldc "y|Jq828\u0008o| *\u000f=w<<\u001foq+yGj({~\u0008ou,>\u0013;ae*\u0013 {..\u001a9}"
		// @0C9: invokestatic game.C_100212_qc.func_105970_z(java.lang.String)char[]
		// @0CC: invokestatic game.C_100212_qc.func_105969_z(char[])java.lang.String
		// @0CF: aastore
		// @0D0: dup
		// @0D1: iconst_3
		// @0D2: ldc "y|Jq828\u0008o}30\u0008,}78\u000f*|e;\u0002o$`iEhke?\u000e<q*7[#y+:\u001e"
		// @0D4: invokestatic game.C_100212_qc.func_105970_z(java.lang.String)char[]
		// @0D7: invokestatic game.C_100212_qc.func_105969_z(char[])java.lang.String
		// @0DA: aastore
		// @0DB: putstatic java.lang.String[] game.C_100212_qc.field_105975_e
		// @0DE: bipush 35 (0x23)
		// @0E0: newarray int[]
		// @0E2: dup
		// @0E3: iconst_0
		// @0E4: iconst_0
		// @0E5: iastore
		// @0E6: dup
		// @0E7: iconst_1
		// @0E8: iconst_0
		// @0E9: iastore
		// @0EA: dup
		// @0EB: iconst_2
		// @0EC: iconst_0
		// @0ED: iastore
		// @0EE: dup
		// @0EF: iconst_3
		// @0F0: iconst_0
		// @0F1: iastore
		// @0F2: dup
		// @0F3: iconst_4
		// @0F4: iconst_0
		// @0F5: iastore
		// @0F6: dup
		// @0F7: iconst_5
		// @0F8: iconst_1
		// @0F9: iastore
		// @0FA: dup
		// @0FB: bipush 6 (0x06)
		// @0FD: iconst_1
		// @0FE: iastore
		// @0FF: dup
		// @100: bipush 7 (0x07)
		// @102: iconst_1
		// @103: iastore
		// @104: dup
		// @105: bipush 8 (0x08)
		// @107: iconst_1
		// @108: iastore
		// @109: dup
		// @10A: bipush 9 (0x09)
		// @10C: iconst_1
		// @10D: iastore
		// @10E: dup
		// @10F: bipush 10 (0x0A)
		// @111: iconst_2
		// @112: iastore
		// @113: dup
		// @114: bipush 11 (0x0B)
		// @116: iconst_2
		// @117: iastore
		// @118: dup
		// @119: bipush 12 (0x0C)
		// @11B: iconst_2
		// @11C: iastore
		// @11D: dup
		// @11E: bipush 13 (0x0D)
		// @120: iconst_2
		// @121: iastore
		// @122: dup
		// @123: bipush 14 (0x0E)
		// @125: iconst_2
		// @126: iastore
		// @127: dup
		// @128: bipush 15 (0x0F)
		// @12A: bipush 7 (0x07)
		// @12C: iastore
		// @12D: dup
		// @12E: bipush 16 (0x10)
		// @130: iconst_4
		// @131: iastore
		// @132: dup
		// @133: bipush 17 (0x11)
		// @135: iconst_4
		// @136: iastore
		// @137: dup
		// @138: bipush 18 (0x12)
		// @13A: iconst_4
		// @13B: iastore
		// @13C: dup
		// @13D: bipush 19 (0x13)
		// @13F: bipush 7 (0x07)
		// @141: iastore
		// @142: dup
		// @143: bipush 20 (0x14)
		// @145: iconst_0
		// @146: iastore
		// @147: dup
		// @148: bipush 21 (0x15)
		// @14A: iconst_4
		// @14B: iastore
		// @14C: dup
		// @14D: bipush 22 (0x16)
		// @14F: iconst_5
		// @150: iastore
		// @151: dup
		// @152: bipush 23 (0x17)
		// @154: iconst_5
		// @155: iastore
		// @156: dup
		// @157: bipush 24 (0x18)
		// @159: bipush 6 (0x06)
		// @15B: iastore
		// @15C: dup
		// @15D: bipush 25 (0x19)
		// @15F: iconst_5
		// @160: iastore
		// @161: dup
		// @162: bipush 26 (0x1A)
		// @164: iconst_3
		// @165: iastore
		// @166: dup
		// @167: bipush 27 (0x1B)
		// @169: iconst_3
		// @16A: iastore
		// @16B: dup
		// @16C: bipush 28 (0x1C)
		// @16E: bipush 6 (0x06)
		// @170: iastore
		// @171: dup
		// @172: bipush 29 (0x1D)
		// @174: bipush 6 (0x06)
		// @176: iastore
		// @177: dup
		// @178: bipush 30 (0x1E)
		// @17A: iconst_4
		// @17B: iastore
		// @17C: dup
		// @17D: bipush 31 (0x1F)
		// @17F: iconst_5
		// @180: iastore
		// @181: dup
		// @182: bipush 32 (0x20)
		// @184: iconst_3
		// @185: iastore
		// @186: dup
		// @187: bipush 33 (0x21)
		// @189: iconst_3
		// @18A: iastore
		// @18B: dup
		// @18C: bipush 34 (0x22)
		// @18E: bipush 7 (0x07)
		// @190: iastore
		// @191: putstatic int[] game.C_100212_qc.field_105980_j
		// @194: sipush 8192 (0x2000)
		// @197: newarray int[]
		// @199: putstatic int[] game.C_100212_qc.field_105972_f
		// @19C: ldc "\u00111\u001eo\u007f$4\u001eow5-\u0012 v6y\u001a=}e7\u0014;8$5\u0017ok -U"
		// @19E: invokestatic game.C_100212_qc.func_105970_z(java.lang.String)char[]
		// @1A1: invokestatic game.C_100212_qc.func_105969_z(char[])java.lang.String
		// @1A4: putstatic java.lang.String game.C_100212_qc.field_105983_i
		// @1A7: ldc "\u00155\u001e.k y\u0008*v!y\u0016*8+<\u000c<8$7\u001fom5=\u001a;}6yS\u00068&8\u0015om+*\u000e-k&+\u0012-}e8\u000foy+ [;q(<R"
		// @1A9: invokestatic game.C_100212_qc.func_105970_z(java.lang.String)char[]
		// @1AC: invokestatic game.C_100212_qc.func_105969_z(char[])java.lang.String
		// @1AF: putstatic java.lang.String game.C_100212_qc.field_105977_c
		// @1B2: ldc "\u00166\t=aiy\u0002 me.\u001e=}e+\u001e\"w3<\u001fo~76\u0016ol-<[(y(<[6w0y\u000c*j y\u0012!6e\r\u0013&ke:\u001a!8-8\u000b?}+y\u0012)8<6\u000eoy7<[+q6:\u0014!v :\u000f*|e?\u0014=816\u0014ot*7\u001cow7y\u0012)811\u001eok +\r*je0\u0008om5=\u001a;}!w"
		// @1B4: invokestatic game.C_100212_qc.func_105970_z(java.lang.String)char[]
		// @1B7: invokestatic game.C_100212_qc.func_105969_z(char[])java.lang.String
		// @1BA: putstatic java.lang.String game.C_100212_qc.field_105974_d
		// @1BD: return
	}
	
	private static char[] func_105970_z(String arg0)
	{
		// @00: aload_0
		// @01: invokevirtual java.lang.String.toCharArray()char[]
		// @04: dup
		// @05: arraylength
		// @06: iconst_2
		// @07: if_icmpge @13
		// @0A: dup
		// @0B: iconst_0
		// @0C: dup2
		// @0D: caload
		// @0E: bipush 24 (0x18)
		// @10: ixor
		// @11: i2c
		// @12: castore
		// @13: areturn
	}
	
	private static String func_105969_z(char[] arg0)
	{
		// @00: aload_0
		// @01: dup
		// @02: arraylength
		// @03: swap
		// @04: iconst_0
		// @05: istore_1
		// @06: goto @4C
		// @09: dup
		// @0A: iload_1
		// @0B: dup2
		// @0C: caload
		// @0D: iload_1
		// @0E: iconst_5
		// @0F: irem
		// @10: tableswitch def: @44, for 0: @30, for 1: @35, for 2: @3A, for 3: @3F
		// @30: bipush 69 (0x45)
		// @32: goto @46
		// @35: bipush 89 (0x59)
		// @37: goto @46
		// @3A: bipush 123 (0x7B)
		// @3C: goto @46
		// @3F: bipush 79 (0x4F)
		// @41: goto @46
		// @44: bipush 24 (0x18)
		// @46: ixor
		// @47: i2c
		// @48: castore
		// @49: iinc #1 +1
		// @4C: swap
		// @4D: dup_x1
		// @4E: iload_1
		// @4F: if_icmpgt @09
		// @52: new java.lang.String
		// @55: dup_x1
		// @56: swap
		// @57: invokespecial java.lang.String.<init>(char[])void
		// @5A: invokevirtual java.lang.String.intern()java.lang.String
		// @5D: areturn
	}
}
