package game;

import java.net.Socket;
import java.io.OutputStream;
import java.io.InputStream;
import java.io.IOException;

final class C_100286_nl implements Runnable
{
	private Socket field_106805_d;
	private boolean field_106816_h;
	private InputStream field_106811_o;
	private byte[] field_106815_k;
	static C_100302_ka field_106813_m;
	private boolean field_106804_g;
	private C_100201_qj field_106810_n;
	private int field_106812_l;
	private int field_106806_e;
	private OutputStream field_106814_j;
	static String field_106808_c;
	static String field_106807_b;
	private int field_106803_f;
	private C_100331_ie field_106817_i;
	static int[] field_106809_a;
	private static final String[] field_106818_z;
	
	final void func_106799_d(int arg0)
	{
		// @00: getstatic int game.SteelSentinels.field_105275_O
		// @03: istore #4
		// @05: aload_0
		// @06: getfield boolean game.C_100286_nl.field_106804_g
		// @09: ifne @0F
		// @0C: goto @10
		// @0F: return
		// @10: iload_1
		// @11: sipush -27201 (0x95BF)
		// @14: if_icmpeq @18
		// @17: return
		// @18: aload_0
		// @19: dup
		// @1A: astore_2
		// @1B: monitorenter
		// @1C: aload_0
		// @1D: iconst_1
		// @1E: putfield boolean game.C_100286_nl.field_106804_g
		// @21: aload_0
		// @22: invokevirtual java.lang.Object.notifyAll()void
		// @25: aload_2
		// @26: monitorexit
		// @27: goto @2F
		// @2A: astore_3
		// @2B: aload_2
		// @2C: monitorexit
		// @2D: aload_3
		// @2E: athrow
		// @2F: aconst_null
		// @30: aload_0
		// @31: getfield game.C_100331_ie game.C_100286_nl.field_106817_i
		// @34: if_acmpne @3B
		// @37: goto @7F
		// @3A: athrow
		// @3B: iconst_m1
		// @3C: aload_0
		// @3D: getfield game.C_100331_ie game.C_100286_nl.field_106817_i
		// @40: getfield int game.C_100331_ie.field_107293_f
		// @43: iconst_m1
		// @44: ixor
		// @45: if_icmpne @5C
		// @48: lconst_1
		// @49: bipush -126 (0x82)
		// @4B: invokestatic game.C_100138_bo.func_100396_a(long, int)void
		// @4E: iload #4
		// @50: ifne @7B
		// @53: iload #4
		// @55: ifeq @3B
		// @58: goto @5C
		// @5B: athrow
		// @5C: aload_0
		// @5D: getfield game.C_100331_ie game.C_100286_nl.field_106817_i
		// @60: getfield int game.C_100331_ie.field_107293_f
		// @63: iconst_m1
		// @64: ixor
		// @65: bipush -2 (0xFE)
		// @67: if_icmpeq @6E
		// @6A: goto @7F
		// @6D: athrow
		// @6E: aload_0
		// @6F: getfield game.C_100331_ie game.C_100286_nl.field_106817_i
		// @72: getfield java.lang.Object game.C_100331_ie.field_107294_g
		// @75: checkcast java.lang.Thread
		// @78: invokevirtual java.lang.Thread.join()void
		// @7B: goto @7F
		// @7E: astore_2
		// @7F: aload_0
		// @80: aconst_null
		// @81: putfield game.C_100331_ie game.C_100286_nl.field_106817_i
		// @84: goto @A9
		// @87: astore_2
		// @88: aload_2
		// @89: new java.lang.StringBuilder
		// @8C: dup
		// @8D: invokespecial java.lang.StringBuilder.<init>()void
		// @90: getstatic java.lang.String[] game.C_100286_nl.field_106818_z
		// @93: bipush 15 (0x0F)
		// @95: aaload
		// @96: invokevirtual java.lang.StringBuilder.append(java.lang.String)java.lang.StringBuilder
		// @99: iload_1
		// @9A: invokevirtual java.lang.StringBuilder.append(int)java.lang.StringBuilder
		// @9D: bipush 41 (0x29)
		// @9F: invokevirtual java.lang.StringBuilder.append(char)java.lang.StringBuilder
		// @A2: invokevirtual java.lang.StringBuilder.toString()java.lang.String
		// @A5: invokestatic game.C_100181_cf.func_105695_a(java.lang.Throwable, java.lang.String)game.C_100170_cm
		// @A8: athrow
		// @A9: return
	}
	
	final int func_106800_b(int arg0) throws IOException
	{
		// @00: iload_1
		// @01: ifeq @0E
		// @04: bipush 10 (0x0A)
		// @06: invokestatic game.C_100286_nl.func_106795_b(byte)boolean
		// @09: pop
		// @0A: goto @0E
		// @0D: athrow
		// @0E: aload_0
		// @0F: getfield boolean game.C_100286_nl.field_106804_g
		// @12: ifne @19
		// @15: goto @1B
		// @18: athrow
		// @19: iconst_0
		// @1A: ireturn
		// @1B: aload_0
		// @1C: getfield java.io.InputStream game.C_100286_nl.field_106811_o
		// @1F: invokevirtual java.io.InputStream.read()int
		// @22: ireturn
		// @23: astore_2
		// @24: aload_2
		// @25: new java.lang.StringBuilder
		// @28: dup
		// @29: invokespecial java.lang.StringBuilder.<init>()void
		// @2C: getstatic java.lang.String[] game.C_100286_nl.field_106818_z
		// @2F: bipush 14 (0x0E)
		// @31: aaload
		// @32: invokevirtual java.lang.StringBuilder.append(java.lang.String)java.lang.StringBuilder
		// @35: iload_1
		// @36: invokevirtual java.lang.StringBuilder.append(int)java.lang.StringBuilder
		// @39: bipush 41 (0x29)
		// @3B: invokevirtual java.lang.StringBuilder.append(char)java.lang.StringBuilder
		// @3E: invokevirtual java.lang.StringBuilder.toString()java.lang.String
		// @41: invokestatic game.C_100181_cf.func_105695_a(java.lang.Throwable, java.lang.String)game.C_100170_cm
		// @44: athrow
	}
	
	static final void func_106801_c(int arg0)
	{
		// @00: aconst_null
		// @01: putstatic java.awt.Image game.C_100080_b.field_104434_b
		// @04: aconst_null
		// @05: putstatic java.awt.Font game.C_100081_ue.field_100673_o
		// @08: iload_0
		// @09: ifeq @13
		// @0C: aconst_null
		// @0D: checkcast java.lang.String
		// @10: putstatic java.lang.String game.C_100286_nl.field_106807_b
		// @13: goto @38
		// @16: astore_1
		// @17: aload_1
		// @18: new java.lang.StringBuilder
		// @1B: dup
		// @1C: invokespecial java.lang.StringBuilder.<init>()void
		// @1F: getstatic java.lang.String[] game.C_100286_nl.field_106818_z
		// @22: bipush 9 (0x09)
		// @24: aaload
		// @25: invokevirtual java.lang.StringBuilder.append(java.lang.String)java.lang.StringBuilder
		// @28: iload_0
		// @29: invokevirtual java.lang.StringBuilder.append(int)java.lang.StringBuilder
		// @2C: bipush 41 (0x29)
		// @2E: invokevirtual java.lang.StringBuilder.append(char)java.lang.StringBuilder
		// @31: invokevirtual java.lang.StringBuilder.toString()java.lang.String
		// @34: invokestatic game.C_100181_cf.func_105695_a(java.lang.Throwable, java.lang.String)game.C_100170_cm
		// @37: athrow
		// @38: return
	}
	
	public static void func_106797_e(int arg0)
	{
		// @00: bipush -122 (0x86)
		// @02: bipush -73 (0xB7)
		// @04: iload_0
		// @05: isub
		// @06: bipush 32 (0x20)
		// @08: idiv
		// @09: irem
		// @0A: istore_1
		// @0B: aconst_null
		// @0C: putstatic int[] game.C_100286_nl.field_106809_a
		// @0F: aconst_null
		// @10: putstatic java.lang.String game.C_100286_nl.field_106807_b
		// @13: aconst_null
		// @14: putstatic game.C_100302_ka game.C_100286_nl.field_106813_m
		// @17: aconst_null
		// @18: putstatic java.lang.String game.C_100286_nl.field_106808_c
		// @1B: goto @40
		// @1E: astore_1
		// @1F: aload_1
		// @20: new java.lang.StringBuilder
		// @23: dup
		// @24: invokespecial java.lang.StringBuilder.<init>()void
		// @27: getstatic java.lang.String[] game.C_100286_nl.field_106818_z
		// @2A: bipush 7 (0x07)
		// @2C: aaload
		// @2D: invokevirtual java.lang.StringBuilder.append(java.lang.String)java.lang.StringBuilder
		// @30: iload_0
		// @31: invokevirtual java.lang.StringBuilder.append(int)java.lang.StringBuilder
		// @34: bipush 41 (0x29)
		// @36: invokevirtual java.lang.StringBuilder.append(char)java.lang.StringBuilder
		// @39: invokevirtual java.lang.StringBuilder.toString()java.lang.String
		// @3C: invokestatic game.C_100181_cf.func_105695_a(java.lang.Throwable, java.lang.String)game.C_100170_cm
		// @3F: athrow
		// @40: return
	}
	
	C_100286_nl(Socket arg0, C_100201_qj arg1) throws IOException
	{
		// @0: aload_0
		// @1: aload_1
		// @2: aload_2
		// @3: sipush 5000 (0x1388)
		// @6: invokespecial game.C_100286_nl.<init>(java.net.Socket, game.C_100201_qj, int)void
		// @9: return
	}
	
	public final void run()
	{
		// @000: getstatic int game.SteelSentinels.field_105275_O
		// @003: istore #6
		// @005: aload_0
		// @006: dup
		// @007: astore_3
		// @008: monitorenter
		// @009: aload_0
		// @00A: getfield int game.C_100286_nl.field_106812_l
		// @00D: aload_0
		// @00E: getfield int game.C_100286_nl.field_106806_e
		// @011: if_icmpne @034
		// @014: aload_0
		// @015: getfield boolean game.C_100286_nl.field_106804_g
		// @018: iload #6
		// @01A: ifne @038
		// @01D: ifeq @02B
		// @020: goto @024
		// @023: athrow
		// @024: aload_3
		// @025: monitorexit
		// @026: iload #6
		// @028: ifeq @0BB
		// @02B: aload_0
		// @02C: invokevirtual java.lang.Object.wait()void
		// @02F: goto @034
		// @032: astore #4
		// @034: aload_0
		// @035: getfield int game.C_100286_nl.field_106806_e
		// @038: aload_0
		// @039: getfield int game.C_100286_nl.field_106812_l
		// @03C: if_icmpgt @04F
		// @03F: aload_0
		// @040: getfield int game.C_100286_nl.field_106812_l
		// @043: aload_0
		// @044: getfield int game.C_100286_nl.field_106806_e
		// @047: ineg
		// @048: iadd
		// @049: istore_1
		// @04A: iload #6
		// @04C: ifeq @05A
		// @04F: aload_0
		// @050: getfield int game.C_100286_nl.field_106803_f
		// @053: aload_0
		// @054: getfield int game.C_100286_nl.field_106806_e
		// @057: ineg
		// @058: iadd
		// @059: istore_1
		// @05A: aload_0
		// @05B: getfield int game.C_100286_nl.field_106806_e
		// @05E: istore_2
		// @05F: aload_3
		// @060: monitorexit
		// @061: goto @06B
		// @064: astore #5
		// @066: aload_3
		// @067: monitorexit
		// @068: aload #5
		// @06A: athrow
		// @06B: iconst_0
		// @06C: iload_1
		// @06D: if_icmplt @074
		// @070: goto @0B8
		// @073: athrow
		// @074: aload_0
		// @075: getfield java.io.OutputStream game.C_100286_nl.field_106814_j
		// @078: aload_0
		// @079: getfield byte[] game.C_100286_nl.field_106815_k
		// @07C: iload_2
		// @07D: iload_1
		// @07E: invokevirtual java.io.OutputStream.write(byte[], int, int)void
		// @081: goto @08A
		// @084: astore_3
		// @085: aload_0
		// @086: iconst_1
		// @087: putfield boolean game.C_100286_nl.field_106816_h
		// @08A: aload_0
		// @08B: iload_1
		// @08C: aload_0
		// @08D: getfield int game.C_100286_nl.field_106806_e
		// @090: iadd
		// @091: aload_0
		// @092: getfield int game.C_100286_nl.field_106803_f
		// @095: irem
		// @096: putfield int game.C_100286_nl.field_106806_e
		// @099: aload_0
		// @09A: getfield int game.C_100286_nl.field_106806_e
		// @09D: aload_0
		// @09E: getfield int game.C_100286_nl.field_106812_l
		// @0A1: if_icmpne @0AF
		// @0A4: aload_0
		// @0A5: getfield java.io.OutputStream game.C_100286_nl.field_106814_j
		// @0A8: invokevirtual java.io.OutputStream.flush()void
		// @0AB: goto @0AF
		// @0AE: athrow
		// @0AF: goto @0B8
		// @0B2: astore_3
		// @0B3: aload_0
		// @0B4: iconst_1
		// @0B5: putfield boolean game.C_100286_nl.field_106816_h
		// @0B8: goto @005
		// @0BB: aload_0
		// @0BC: getfield java.io.InputStream game.C_100286_nl.field_106811_o
		// @0BF: ifnull @0CD
		// @0C2: aload_0
		// @0C3: getfield java.io.InputStream game.C_100286_nl.field_106811_o
		// @0C6: invokevirtual java.io.InputStream.close()void
		// @0C9: goto @0CD
		// @0CC: athrow
		// @0CD: aconst_null
		// @0CE: aload_0
		// @0CF: getfield java.io.OutputStream game.C_100286_nl.field_106814_j
		// @0D2: if_acmpne @0D9
		// @0D5: goto @0E0
		// @0D8: athrow
		// @0D9: aload_0
		// @0DA: getfield java.io.OutputStream game.C_100286_nl.field_106814_j
		// @0DD: invokevirtual java.io.OutputStream.close()void
		// @0E0: aconst_null
		// @0E1: aload_0
		// @0E2: getfield java.net.Socket game.C_100286_nl.field_106805_d
		// @0E5: if_acmpeq @0F3
		// @0E8: aload_0
		// @0E9: getfield java.net.Socket game.C_100286_nl.field_106805_d
		// @0EC: invokevirtual java.net.Socket.close()void
		// @0EF: goto @0F3
		// @0F2: athrow
		// @0F3: goto @0F7
		// @0F6: astore_1
		// @0F7: aload_0
		// @0F8: aconst_null
		// @0F9: putfield byte[] game.C_100286_nl.field_106815_k
		// @0FC: goto @106
		// @0FF: astore_1
		// @100: iconst_1
		// @101: aconst_null
		// @102: aload_1
		// @103: invokestatic game.C_100036_gg.func_103142_a(int, java.lang.String, java.lang.Throwable)void
		// @106: goto @115
		// @109: astore_1
		// @10A: aload_1
		// @10B: getstatic java.lang.String[] game.C_100286_nl.field_106818_z
		// @10E: bipush 13 (0x0D)
		// @110: aaload
		// @111: invokestatic game.C_100181_cf.func_105695_a(java.lang.Throwable, java.lang.String)game.C_100170_cm
		// @114: athrow
		// @115: return
	}
	
	protected final void finalize()
	{
		// @00: aload_0
		// @01: sipush -27201 (0x95BF)
		// @04: invokevirtual game.C_100286_nl.func_106799_d(int)void
		// @07: goto @16
		// @0A: astore_1
		// @0B: aload_1
		// @0C: getstatic java.lang.String[] game.C_100286_nl.field_106818_z
		// @0F: bipush 8 (0x08)
		// @11: aaload
		// @12: invokestatic game.C_100181_cf.func_105695_a(java.lang.Throwable, java.lang.String)game.C_100170_cm
		// @15: athrow
		// @16: return
	}
	
	final void func_106792_a(byte arg0) throws IOException
	{
		// @00: aload_0
		// @01: getfield boolean game.C_100286_nl.field_106804_g
		// @04: ifeq @09
		// @07: return
		// @08: athrow
		// @09: iload_1
		// @0A: bipush -121 (0x87)
		// @0C: if_icmplt @1B
		// @0F: aload_0
		// @10: aconst_null
		// @11: checkcast java.net.Socket
		// @14: putfield java.net.Socket game.C_100286_nl.field_106805_d
		// @17: goto @1B
		// @1A: athrow
		// @1B: aload_0
		// @1C: getfield boolean game.C_100286_nl.field_106816_h
		// @1F: ifne @26
		// @22: goto @33
		// @25: athrow
		// @26: aload_0
		// @27: iconst_0
		// @28: putfield boolean game.C_100286_nl.field_106816_h
		// @2B: new java.io.IOException
		// @2E: dup
		// @2F: invokespecial java.io.IOException.<init>()void
		// @32: athrow
		// @33: goto @57
		// @36: astore_2
		// @37: aload_2
		// @38: new java.lang.StringBuilder
		// @3B: dup
		// @3C: invokespecial java.lang.StringBuilder.<init>()void
		// @3F: getstatic java.lang.String[] game.C_100286_nl.field_106818_z
		// @42: iconst_3
		// @43: aaload
		// @44: invokevirtual java.lang.StringBuilder.append(java.lang.String)java.lang.StringBuilder
		// @47: iload_1
		// @48: invokevirtual java.lang.StringBuilder.append(int)java.lang.StringBuilder
		// @4B: bipush 41 (0x29)
		// @4D: invokevirtual java.lang.StringBuilder.append(char)java.lang.StringBuilder
		// @50: invokevirtual java.lang.StringBuilder.toString()java.lang.String
		// @53: invokestatic game.C_100181_cf.func_105695_a(java.lang.Throwable, java.lang.String)game.C_100170_cm
		// @56: athrow
		// @57: return
	}
	
	static final void func_106802_a(boolean arg0)
	{
		// @00: iload_0
		// @01: ifeq @05
		// @04: return
		// @05: ldc Class<java.lang.Runtime>
		// @07: getstatic java.lang.String[] game.C_100286_nl.field_106818_z
		// @0A: bipush 11 (0x0B)
		// @0C: aaload
		// @0D: iconst_0
		// @0E: anewarray java.lang.Class
		// @11: invokevirtual java.lang.Class.getMethod(java.lang.String, java.lang.Class[])java.lang.reflect.Method
		// @14: astore_1
		// @15: aconst_null
		// @16: aload_1
		// @17: if_acmpne @1E
		// @1A: goto @41
		// @1D: athrow
		// @1E: invokestatic java.lang.Runtime.getRuntime()java.lang.Runtime
		// @21: astore_2
		// @22: aload_1
		// @23: aload_2
		// @24: aconst_null
		// @25: checkcast java.lang.Object[]
		// @28: invokevirtual java.lang.reflect.Method.invoke(java.lang.Object, java.lang.Object[])java.lang.Object
		// @2B: checkcast java.lang.Long
		// @2E: astore_3
		// @2F: aload_3
		// @30: invokevirtual java.lang.Long.longValue()long
		// @33: ldc2_w 1048576
		// @36: ldiv
		// @37: l2i
		// @38: iconst_1
		// @39: iadd
		// @3A: putstatic int game.C_100272_mn.field_102431_O
		// @3D: goto @41
		// @40: astore_2
		// @41: goto @45
		// @44: astore_1
		// @45: goto @6A
		// @48: astore_1
		// @49: aload_1
		// @4A: new java.lang.StringBuilder
		// @4D: dup
		// @4E: invokespecial java.lang.StringBuilder.<init>()void
		// @51: getstatic java.lang.String[] game.C_100286_nl.field_106818_z
		// @54: bipush 10 (0x0A)
		// @56: aaload
		// @57: invokevirtual java.lang.StringBuilder.append(java.lang.String)java.lang.StringBuilder
		// @5A: iload_0
		// @5B: invokevirtual java.lang.StringBuilder.append(boolean)java.lang.StringBuilder
		// @5E: bipush 41 (0x29)
		// @60: invokevirtual java.lang.StringBuilder.append(char)java.lang.StringBuilder
		// @63: invokevirtual java.lang.StringBuilder.toString()java.lang.String
		// @66: invokestatic game.C_100181_cf.func_105695_a(java.lang.Throwable, java.lang.String)game.C_100170_cm
		// @69: athrow
		// @6A: return
	}
	
	static final void func_106790_a(int arg0)
	{
		// @00: getstatic int game.SteelSentinels.field_105275_O
		// @03: istore_2
		// @04: iconst_0
		// @05: istore_1
		// @06: getstatic int game.C_100188_rj.field_105737_e
		// @09: iload_1
		// @0A: if_icmple @22
		// @0D: getstatic game.C_100240_oj[] game.C_100006_fj.field_103617_g
		// @10: iload_1
		// @11: aconst_null
		// @12: aastore
		// @13: iinc #1 +1
		// @16: iload_2
		// @17: ifne @26
		// @1A: iload_2
		// @1B: ifeq @06
		// @1E: goto @22
		// @21: athrow
		// @22: iload_0
		// @23: putstatic int game.C_100188_rj.field_105737_e
		// @26: goto @4A
		// @29: astore_1
		// @2A: aload_1
		// @2B: new java.lang.StringBuilder
		// @2E: dup
		// @2F: invokespecial java.lang.StringBuilder.<init>()void
		// @32: getstatic java.lang.String[] game.C_100286_nl.field_106818_z
		// @35: iconst_5
		// @36: aaload
		// @37: invokevirtual java.lang.StringBuilder.append(java.lang.String)java.lang.StringBuilder
		// @3A: iload_0
		// @3B: invokevirtual java.lang.StringBuilder.append(int)java.lang.StringBuilder
		// @3E: bipush 41 (0x29)
		// @40: invokevirtual java.lang.StringBuilder.append(char)java.lang.StringBuilder
		// @43: invokevirtual java.lang.StringBuilder.toString()java.lang.String
		// @46: invokestatic game.C_100181_cf.func_105695_a(java.lang.Throwable, java.lang.String)game.C_100170_cm
		// @49: athrow
		// @4A: return
	}
	
	static final boolean func_106795_b(byte arg0)
	{
		// @00: iload_0
		// @01: bipush -42 (0xD6)
		// @03: if_icmpeq @08
		// @06: iconst_0
		// @07: ireturn
		// @08: getstatic long game.C_100290_jm.field_106867_i
		// @0B: getstatic java.lang.String game.C_100243_pd.field_106355_f
		// @0E: bipush -39 (0xD9)
		// @10: invokestatic game.C_100256_pk.func_100444_a(long, java.lang.String, byte)boolean
		// @13: ireturn
		// @14: astore_1
		// @15: aload_1
		// @16: new java.lang.StringBuilder
		// @19: dup
		// @1A: invokespecial java.lang.StringBuilder.<init>()void
		// @1D: getstatic java.lang.String[] game.C_100286_nl.field_106818_z
		// @20: bipush 12 (0x0C)
		// @22: aaload
		// @23: invokevirtual java.lang.StringBuilder.append(java.lang.String)java.lang.StringBuilder
		// @26: iload_0
		// @27: invokevirtual java.lang.StringBuilder.append(int)java.lang.StringBuilder
		// @2A: bipush 41 (0x29)
		// @2C: invokevirtual java.lang.StringBuilder.append(char)java.lang.StringBuilder
		// @2F: invokevirtual java.lang.StringBuilder.toString()java.lang.String
		// @32: invokestatic game.C_100181_cf.func_105695_a(java.lang.Throwable, java.lang.String)game.C_100170_cm
		// @35: athrow
	}
	
	final int func_106796_f(int arg0) throws IOException
	{
		// @00: aload_0
		// @01: getfield boolean game.C_100286_nl.field_106804_g
		// @04: ifne @0B
		// @07: goto @0D
		// @0A: athrow
		// @0B: iconst_0
		// @0C: ireturn
		// @0D: iload_1
		// @0E: iconst_1
		// @0F: if_icmpeq @1C
		// @12: aload_0
		// @13: bipush 88 (0x58)
		// @15: putfield int game.C_100286_nl.field_106812_l
		// @18: goto @1C
		// @1B: athrow
		// @1C: aload_0
		// @1D: getfield java.io.InputStream game.C_100286_nl.field_106811_o
		// @20: invokevirtual java.io.InputStream.available()int
		// @23: ireturn
		// @24: astore_2
		// @25: aload_2
		// @26: new java.lang.StringBuilder
		// @29: dup
		// @2A: invokespecial java.lang.StringBuilder.<init>()void
		// @2D: getstatic java.lang.String[] game.C_100286_nl.field_106818_z
		// @30: bipush 6 (0x06)
		// @32: aaload
		// @33: invokevirtual java.lang.StringBuilder.append(java.lang.String)java.lang.StringBuilder
		// @36: iload_1
		// @37: invokevirtual java.lang.StringBuilder.append(int)java.lang.StringBuilder
		// @3A: bipush 41 (0x29)
		// @3C: invokevirtual java.lang.StringBuilder.append(char)java.lang.StringBuilder
		// @3F: invokevirtual java.lang.StringBuilder.toString()java.lang.String
		// @42: invokestatic game.C_100181_cf.func_105695_a(java.lang.Throwable, java.lang.String)game.C_100170_cm
		// @45: athrow
	}
	
	final void func_106798_a(int arg0, byte[] arg1, int arg2, int arg3) throws IOException
	{
		// @000: getstatic int game.SteelSentinels.field_105275_O
		// @003: istore #8
		// @005: aload_0
		// @006: getfield boolean game.C_100286_nl.field_106804_g
		// @009: ifeq @00E
		// @00C: return
		// @00D: athrow
		// @00E: aload_0
		// @00F: getfield boolean game.C_100286_nl.field_106816_h
		// @012: ifeq @023
		// @015: aload_0
		// @016: iconst_0
		// @017: putfield boolean game.C_100286_nl.field_106816_h
		// @01A: new java.io.IOException
		// @01D: dup
		// @01E: invokespecial java.io.IOException.<init>()void
		// @021: athrow
		// @022: athrow
		// @023: aconst_null
		// @024: aload_0
		// @025: getfield byte[] game.C_100286_nl.field_106815_k
		// @028: if_acmpeq @02F
		// @02B: goto @039
		// @02E: athrow
		// @02F: aload_0
		// @030: aload_0
		// @031: getfield int game.C_100286_nl.field_106803_f
		// @034: newarray byte[]
		// @036: putfield byte[] game.C_100286_nl.field_106815_k
		// @039: aload_0
		// @03A: dup
		// @03B: astore #5
		// @03D: monitorenter
		// @03E: iconst_0
		// @03F: istore #6
		// @041: iload #4
		// @043: iload #6
		// @045: if_icmple @09C
		// @048: aload_0
		// @049: getfield byte[] game.C_100286_nl.field_106815_k
		// @04C: aload_0
		// @04D: getfield int game.C_100286_nl.field_106812_l
		// @050: aload_2
		// @051: iload #6
		// @053: iload_3
		// @054: iadd
		// @055: baload
		// @056: bastore
		// @057: aload_0
		// @058: iconst_1
		// @059: aload_0
		// @05A: getfield int game.C_100286_nl.field_106812_l
		// @05D: iadd
		// @05E: aload_0
		// @05F: getfield int game.C_100286_nl.field_106803_f
		// @062: irem
		// @063: putfield int game.C_100286_nl.field_106812_l
		// @066: aload_0
		// @067: getfield int game.C_100286_nl.field_106812_l
		// @06A: iconst_m1
		// @06B: ixor
		// @06C: aload_0
		// @06D: getfield int game.C_100286_nl.field_106803_f
		// @070: aload_0
		// @071: getfield int game.C_100286_nl.field_106806_e
		// @074: iadd
		// @075: bipush -100 (0x9C)
		// @077: iadd
		// @078: aload_0
		// @079: getfield int game.C_100286_nl.field_106803_f
		// @07C: irem
		// @07D: iconst_m1
		// @07E: ixor
		// @07F: iload #8
		// @081: ifne @0B9
		// @084: if_icmpne @094
		// @087: goto @08B
		// @08A: athrow
		// @08B: new java.io.IOException
		// @08E: dup
		// @08F: invokespecial java.io.IOException.<init>()void
		// @092: athrow
		// @093: athrow
		// @094: iinc #6 +1
		// @097: iload #8
		// @099: ifeq @041
		// @09C: aload_0
		// @09D: getfield game.C_100331_ie game.C_100286_nl.field_106817_i
		// @0A0: ifnonnull @0B6
		// @0A3: aload_0
		// @0A4: aload_0
		// @0A5: getfield game.C_100201_qj game.C_100286_nl.field_106810_n
		// @0A8: iconst_3
		// @0A9: bipush 108 (0x6C)
		// @0AB: aload_0
		// @0AC: invokevirtual game.C_100201_qj.func_105856_a(int, int, java.lang.Runnable)game.C_100331_ie
		// @0AF: putfield game.C_100331_ie game.C_100286_nl.field_106817_i
		// @0B2: goto @0B6
		// @0B5: athrow
		// @0B6: iload_1
		// @0B7: bipush 99 (0x63)
		// @0B9: if_icmpge @0C0
		// @0BC: aload #5
		// @0BE: monitorexit
		// @0BF: return
		// @0C0: aload_0
		// @0C1: invokevirtual java.lang.Object.notifyAll()void
		// @0C4: aload #5
		// @0C6: monitorexit
		// @0C7: goto @0D2
		// @0CA: astore #7
		// @0CC: aload #5
		// @0CE: monitorexit
		// @0CF: aload #7
		// @0D1: athrow
		// @0D2: goto @125
		// @0D5: astore #5
		// @0D7: aload #5
		// @0D9: new java.lang.StringBuilder
		// @0DC: dup
		// @0DD: invokespecial java.lang.StringBuilder.<init>()void
		// @0E0: getstatic java.lang.String[] game.C_100286_nl.field_106818_z
		// @0E3: iconst_4
		// @0E4: aaload
		// @0E5: invokevirtual java.lang.StringBuilder.append(java.lang.String)java.lang.StringBuilder
		// @0E8: iload_1
		// @0E9: invokevirtual java.lang.StringBuilder.append(int)java.lang.StringBuilder
		// @0EC: bipush 44 (0x2C)
		// @0EE: invokevirtual java.lang.StringBuilder.append(char)java.lang.StringBuilder
		// @0F1: aload_2
		// @0F2: ifnull @0FE
		// @0F5: getstatic java.lang.String[] game.C_100286_nl.field_106818_z
		// @0F8: iconst_2
		// @0F9: aaload
		// @0FA: goto @103
		// @0FD: athrow
		// @0FE: getstatic java.lang.String[] game.C_100286_nl.field_106818_z
		// @101: iconst_1
		// @102: aaload
		// @103: invokevirtual java.lang.StringBuilder.append(java.lang.String)java.lang.StringBuilder
		// @106: bipush 44 (0x2C)
		// @108: invokevirtual java.lang.StringBuilder.append(char)java.lang.StringBuilder
		// @10B: iload_3
		// @10C: invokevirtual java.lang.StringBuilder.append(int)java.lang.StringBuilder
		// @10F: bipush 44 (0x2C)
		// @111: invokevirtual java.lang.StringBuilder.append(char)java.lang.StringBuilder
		// @114: iload #4
		// @116: invokevirtual java.lang.StringBuilder.append(int)java.lang.StringBuilder
		// @119: bipush 41 (0x29)
		// @11B: invokevirtual java.lang.StringBuilder.append(char)java.lang.StringBuilder
		// @11E: invokevirtual java.lang.StringBuilder.toString()java.lang.String
		// @121: invokestatic game.C_100181_cf.func_105695_a(java.lang.Throwable, java.lang.String)game.C_100170_cm
		// @124: athrow
		// @125: return
	}
	
	final void func_106794_a(int arg0, int arg1, byte[] arg2, int arg3) throws IOException
	{
		// @00: getstatic int game.SteelSentinels.field_105275_O
		// @03: istore #6
		// @05: aload_0
		// @06: getfield boolean game.C_100286_nl.field_106804_g
		// @09: ifne @10
		// @0C: goto @11
		// @0F: athrow
		// @10: return
		// @11: iload #4
		// @13: ifle @50
		// @16: aload_0
		// @17: getfield java.io.InputStream game.C_100286_nl.field_106811_o
		// @1A: aload_3
		// @1B: iload_2
		// @1C: iload #4
		// @1E: invokevirtual java.io.InputStream.read(byte[], int, int)int
		// @21: istore #5
		// @23: iconst_m1
		// @24: iload #5
		// @26: iconst_m1
		// @27: ixor
		// @28: iload #6
		// @2A: ifne @53
		// @2D: if_icmple @37
		// @30: goto @34
		// @33: athrow
		// @34: goto @3F
		// @37: new java.io.EOFException
		// @3A: dup
		// @3B: invokespecial java.io.EOFException.<init>()void
		// @3E: athrow
		// @3F: iload #4
		// @41: iload #5
		// @43: isub
		// @44: istore #4
		// @46: iload_2
		// @47: iload #5
		// @49: iadd
		// @4A: istore_2
		// @4B: iload #6
		// @4D: ifeq @11
		// @50: iload_1
		// @51: bipush -84 (0xAC)
		// @53: if_icmplt @5F
		// @56: bipush -64 (0xC0)
		// @58: invokestatic game.C_100286_nl.func_106797_e(int)void
		// @5B: goto @5F
		// @5E: athrow
		// @5F: goto @B3
		// @62: astore #5
		// @64: aload #5
		// @66: new java.lang.StringBuilder
		// @69: dup
		// @6A: invokespecial java.lang.StringBuilder.<init>()void
		// @6D: getstatic java.lang.String[] game.C_100286_nl.field_106818_z
		// @70: bipush 16 (0x10)
		// @72: aaload
		// @73: invokevirtual java.lang.StringBuilder.append(java.lang.String)java.lang.StringBuilder
		// @76: iload_1
		// @77: invokevirtual java.lang.StringBuilder.append(int)java.lang.StringBuilder
		// @7A: bipush 44 (0x2C)
		// @7C: invokevirtual java.lang.StringBuilder.append(char)java.lang.StringBuilder
		// @7F: iload_2
		// @80: invokevirtual java.lang.StringBuilder.append(int)java.lang.StringBuilder
		// @83: bipush 44 (0x2C)
		// @85: invokevirtual java.lang.StringBuilder.append(char)java.lang.StringBuilder
		// @88: aload_3
		// @89: ifnull @95
		// @8C: getstatic java.lang.String[] game.C_100286_nl.field_106818_z
		// @8F: iconst_2
		// @90: aaload
		// @91: goto @9A
		// @94: athrow
		// @95: getstatic java.lang.String[] game.C_100286_nl.field_106818_z
		// @98: iconst_1
		// @99: aaload
		// @9A: invokevirtual java.lang.StringBuilder.append(java.lang.String)java.lang.StringBuilder
		// @9D: bipush 44 (0x2C)
		// @9F: invokevirtual java.lang.StringBuilder.append(char)java.lang.StringBuilder
		// @A2: iload #4
		// @A4: invokevirtual java.lang.StringBuilder.append(int)java.lang.StringBuilder
		// @A7: bipush 41 (0x29)
		// @A9: invokevirtual java.lang.StringBuilder.append(char)java.lang.StringBuilder
		// @AC: invokevirtual java.lang.StringBuilder.toString()java.lang.String
		// @AF: invokestatic game.C_100181_cf.func_105695_a(java.lang.Throwable, java.lang.String)game.C_100170_cm
		// @B2: athrow
		// @B3: return
	}
	
	private C_100286_nl(Socket arg0, C_100201_qj arg1, int arg2) throws IOException
	{
		// @00: aload_0
		// @01: invokespecial java.lang.Object.<init>()void
		// @04: aload_0
		// @05: iconst_0
		// @06: putfield boolean game.C_100286_nl.field_106816_h
		// @09: aload_0
		// @0A: iconst_0
		// @0B: putfield boolean game.C_100286_nl.field_106804_g
		// @0E: aload_0
		// @0F: iconst_0
		// @10: putfield int game.C_100286_nl.field_106812_l
		// @13: aload_0
		// @14: iconst_0
		// @15: putfield int game.C_100286_nl.field_106806_e
		// @18: aload_0
		// @19: aload_2
		// @1A: putfield game.C_100201_qj game.C_100286_nl.field_106810_n
		// @1D: aload_0
		// @1E: aload_1
		// @1F: putfield java.net.Socket game.C_100286_nl.field_106805_d
		// @22: aload_0
		// @23: getfield java.net.Socket game.C_100286_nl.field_106805_d
		// @26: sipush 30000 (0x7530)
		// @29: invokevirtual java.net.Socket.setSoTimeout(int)void
		// @2C: aload_0
		// @2D: getfield java.net.Socket game.C_100286_nl.field_106805_d
		// @30: iconst_1
		// @31: invokevirtual java.net.Socket.setTcpNoDelay(boolean)void
		// @34: aload_0
		// @35: aload_0
		// @36: getfield java.net.Socket game.C_100286_nl.field_106805_d
		// @39: invokevirtual java.net.Socket.getInputStream()java.io.InputStream
		// @3C: putfield java.io.InputStream game.C_100286_nl.field_106811_o
		// @3F: aload_0
		// @40: aload_0
		// @41: getfield java.net.Socket game.C_100286_nl.field_106805_d
		// @44: invokevirtual java.net.Socket.getOutputStream()java.io.OutputStream
		// @47: putfield java.io.OutputStream game.C_100286_nl.field_106814_j
		// @4A: aload_0
		// @4B: iload_3
		// @4C: putfield int game.C_100286_nl.field_106803_f
		// @4F: goto @A9
		// @52: astore #4
		// @54: aload #4
		// @56: new java.lang.StringBuilder
		// @59: dup
		// @5A: invokespecial java.lang.StringBuilder.<init>()void
		// @5D: getstatic java.lang.String[] game.C_100286_nl.field_106818_z
		// @60: iconst_0
		// @61: aaload
		// @62: invokevirtual java.lang.StringBuilder.append(java.lang.String)java.lang.StringBuilder
		// @65: aload_1
		// @66: ifnull @72
		// @69: getstatic java.lang.String[] game.C_100286_nl.field_106818_z
		// @6C: iconst_2
		// @6D: aaload
		// @6E: goto @77
		// @71: athrow
		// @72: getstatic java.lang.String[] game.C_100286_nl.field_106818_z
		// @75: iconst_1
		// @76: aaload
		// @77: invokevirtual java.lang.StringBuilder.append(java.lang.String)java.lang.StringBuilder
		// @7A: bipush 44 (0x2C)
		// @7C: invokevirtual java.lang.StringBuilder.append(char)java.lang.StringBuilder
		// @7F: aload_2
		// @80: ifnull @8C
		// @83: getstatic java.lang.String[] game.C_100286_nl.field_106818_z
		// @86: iconst_2
		// @87: aaload
		// @88: goto @91
		// @8B: athrow
		// @8C: getstatic java.lang.String[] game.C_100286_nl.field_106818_z
		// @8F: iconst_1
		// @90: aaload
		// @91: invokevirtual java.lang.StringBuilder.append(java.lang.String)java.lang.StringBuilder
		// @94: bipush 44 (0x2C)
		// @96: invokevirtual java.lang.StringBuilder.append(char)java.lang.StringBuilder
		// @99: iload_3
		// @9A: invokevirtual java.lang.StringBuilder.append(int)java.lang.StringBuilder
		// @9D: bipush 41 (0x29)
		// @9F: invokevirtual java.lang.StringBuilder.append(char)java.lang.StringBuilder
		// @A2: invokevirtual java.lang.StringBuilder.toString()java.lang.String
		// @A5: invokestatic game.C_100181_cf.func_105695_a(java.lang.Throwable, java.lang.String)game.C_100170_cm
		// @A8: athrow
		// @A9: return
	}
	
	static
	{
		// @00: bipush 17 (0x11)
		// @02: anewarray java.lang.String
		// @05: dup
		// @06: iconst_0
		// @07: ldc "!\u000eu6%!\u000b/4d"
		// @09: invokestatic game.C_100286_nl.func_106793_z(java.lang.String)char[]
		// @0C: invokestatic game.C_100286_nl.func_106791_z(char[])java.lang.String
		// @0F: aastore
		// @10: dup
		// @11: iconst_1
		// @12: ldc "!\u00177f"
		// @14: invokestatic game.C_100286_nl.func_106793_z(java.lang.String)char[]
		// @17: invokestatic game.C_100286_nl.func_106791_z(char[])java.lang.String
		// @1A: aastore
		// @1B: dup
		// @1C: iconst_2
		// @1D: ldc "4Lu$1"
		// @1F: invokestatic game.C_100286_nl.func_106793_z(java.lang.String)char[]
		// @22: invokestatic game.C_100286_nl.func_106791_z(char[])java.lang.String
		// @25: aastore
		// @26: dup
		// @27: iconst_3
		// @28: ldc "!\u000euNd"
		// @2A: invokestatic game.C_100286_nl.func_106793_z(java.lang.String)char[]
		// @2D: invokestatic game.C_100286_nl.func_106791_z(char[])java.lang.String
		// @30: aastore
		// @31: dup
		// @32: iconst_4
		// @33: ldc "!\u000euId"
		// @35: invokestatic game.C_100286_nl.func_106793_z(java.lang.String)char[]
		// @38: invokestatic game.C_100286_nl.func_106791_z(char[])java.lang.String
		// @3B: aastore
		// @3C: dup
		// @3D: iconst_5
		// @3E: ldc "!\u000euAd"
		// @40: invokestatic game.C_100286_nl.func_106793_z(java.lang.String)char[]
		// @43: invokestatic game.C_100286_nl.func_106791_z(char[])java.lang.String
		// @46: aastore
		// @47: dup
		// @48: bipush 6 (0x06)
		// @4A: ldc "!\u000euCd"
		// @4C: invokestatic game.C_100286_nl.func_106793_z(java.lang.String)char[]
		// @4F: invokestatic game.C_100286_nl.func_106791_z(char[])java.lang.String
		// @52: aastore
		// @53: dup
		// @54: bipush 7 (0x07)
		// @56: ldc "!\u000euMd"
		// @58: invokestatic game.C_100286_nl.func_106793_z(java.lang.String)char[]
		// @5B: invokestatic game.C_100286_nl.func_106791_z(char[])java.lang.String
		// @5E: aastore
		// @5F: dup
		// @60: bipush 8 (0x08)
		// @62: ldc "!\u000eul%!\u00037c6*Jr"
		// @64: invokestatic game.C_100286_nl.func_106793_z(java.lang.String)char[]
		// @67: invokestatic game.C_100286_nl.func_106791_z(char[])java.lang.String
		// @6A: aastore
		// @6B: dup
		// @6C: bipush 9 (0x09)
		// @6E: ldc "!\u000euBd"
		// @70: invokestatic game.C_100286_nl.func_106793_z(java.lang.String)char[]
		// @73: invokestatic game.C_100286_nl.func_106791_z(char[])java.lang.String
		// @76: aastore
		// @77: dup
		// @78: bipush 10 (0x0A)
		// @7A: ldc "!\u000euLd"
		// @7C: invokestatic game.C_100286_nl.func_106793_z(java.lang.String)char[]
		// @7F: invokestatic game.C_100286_nl.func_106791_z(char[])java.lang.String
		// @82: aastore
		// @83: dup
		// @84: bipush 11 (0x0B)
		// @86: ldc "\"\u0003#G)\"\r)s"
		// @88: invokestatic game.C_100286_nl.func_106793_z(java.lang.String)char[]
		// @8B: invokestatic game.C_100286_nl.func_106791_z(char[])java.lang.String
		// @8E: aastore
		// @8F: dup
		// @90: bipush 12 (0x0C)
		// @92: ldc "!\u000euHd"
		// @94: invokestatic game.C_100286_nl.func_106793_z(java.lang.String)char[]
		// @97: invokestatic game.C_100286_nl.func_106791_z(char[])java.lang.String
		// @9A: aastore
		// @9B: dup
		// @9C: bipush 13 (0x0D)
		// @9E: ldc "!\u000eux9!Jr"
		// @A0: invokestatic game.C_100286_nl.func_106793_z(java.lang.String)char[]
		// @A3: invokestatic game.C_100286_nl.func_106791_z(char[])java.lang.String
		// @A6: aastore
		// @A7: dup
		// @A8: bipush 14 (0x0E)
		// @AA: ldc "!\u000euOd"
		// @AC: invokestatic game.C_100286_nl.func_106793_z(java.lang.String)char[]
		// @AF: invokestatic game.C_100286_nl.func_106791_z(char[])java.lang.String
		// @B2: aastore
		// @B3: dup
		// @B4: bipush 15 (0x0F)
		// @B6: ldc "!\u000eu@d"
		// @B8: invokestatic game.C_100286_nl.func_106793_z(java.lang.String)char[]
		// @BB: invokestatic game.C_100286_nl.func_106791_z(char[])java.lang.String
		// @BE: aastore
		// @BF: dup
		// @C0: bipush 16 (0x10)
		// @C2: ldc "!\u000euKd"
		// @C4: invokestatic game.C_100286_nl.func_106793_z(java.lang.String)char[]
		// @C7: invokestatic game.C_100286_nl.func_106791_z(char[])java.lang.String
		// @CA: aastore
		// @CB: putstatic java.lang.String[] game.C_100286_nl.field_106818_z
		// @CE: ldc "\u001b\u0003<yl)\u00104gl\u001a\u000c)k8*\u0006{m-\"\u0007(*-=\u0007{d#;B)o/ \u0010?o(a"
		// @D0: invokestatic game.C_100286_nl.func_106793_z(java.lang.String)char[]
		// @D3: invokestatic game.C_100286_nl.func_106791_z(char[])java.lang.String
		// @D6: putstatic java.lang.String game.C_100286_nl.field_106808_c
		// @D9: sipush 8192 (0x2000)
		// @DC: newarray int[]
		// @DE: putstatic int[] game.C_100286_nl.field_106809_a
		// @E1: ldc "\u001b\n2yl?\u0003(y; \u0010?*/ \u000c/k%!\u0011{s#:\u0010{Z .\u001b>xl\u0001\u00036o`o\u00035nl8\r.f(o\u0000>*).\u0011\"*8 B<\u007f)<\u0011"
		// @E3: invokestatic game.C_100286_nl.func_106793_z(java.lang.String)char[]
		// @E6: invokestatic game.C_100286_nl.func_106791_z(char[])java.lang.String
		// @E9: putstatic java.lang.String game.C_100286_nl.field_106807_b
		// @EC: return
	}
	
	private static char[] func_106793_z(String arg0)
	{
		// @00: aload_0
		// @01: invokevirtual java.lang.String.toCharArray()char[]
		// @04: dup
		// @05: arraylength
		// @06: iconst_2
		// @07: if_icmpge @13
		// @0A: dup
		// @0B: iconst_0
		// @0C: dup2
		// @0D: caload
		// @0E: bipush 76 (0x4C)
		// @10: ixor
		// @11: i2c
		// @12: castore
		// @13: areturn
	}
	
	private static String func_106791_z(char[] arg0)
	{
		// @00: aload_0
		// @01: dup
		// @02: arraylength
		// @03: swap
		// @04: iconst_0
		// @05: istore_1
		// @06: goto @4C
		// @09: dup
		// @0A: iload_1
		// @0B: dup2
		// @0C: caload
		// @0D: iload_1
		// @0E: iconst_5
		// @0F: irem
		// @10: tableswitch def: @44, for 0: @30, for 1: @35, for 2: @3A, for 3: @3F
		// @30: bipush 79 (0x4F)
		// @32: goto @46
		// @35: bipush 98 (0x62)
		// @37: goto @46
		// @3A: bipush 91 (0x5B)
		// @3C: goto @46
		// @3F: bipush 10 (0x0A)
		// @41: goto @46
		// @44: bipush 76 (0x4C)
		// @46: ixor
		// @47: i2c
		// @48: castore
		// @49: iinc #1 +1
		// @4C: swap
		// @4D: dup_x1
		// @4E: iload_1
		// @4F: if_icmpgt @09
		// @52: new java.lang.String
		// @55: dup_x1
		// @56: swap
		// @57: invokespecial java.lang.String.<init>(char[])void
		// @5A: invokevirtual java.lang.String.intern()java.lang.String
		// @5D: areturn
	}
}
