package game;

import java.net.Socket;
import java.io.IOException;

abstract class C_100157_db
{
	static String field_103556_f;
	String field_103561_a;
	static String field_103559_b;
	int field_103557_d;
	static String field_103560_c;
	static C_100037_wb[] field_103558_e;
	private static final String[] field_103562_z;
	
	final Socket func_103551_a(int arg0) throws IOException
	{
		// @00: iload_1
		// @01: sipush 9640 (0x25A8)
		// @04: if_icmpeq @0D
		// @07: aconst_null
		// @08: checkcast java.net.Socket
		// @0B: areturn
		// @0C: athrow
		// @0D: new java.net.Socket
		// @10: dup
		// @11: aload_0
		// @12: getfield java.lang.String game.C_100157_db.field_103561_a
		// @15: aload_0
		// @16: getfield int game.C_100157_db.field_103557_d
		// @19: invokespecial java.net.Socket.<init>(java.lang.String, int)void
		// @1C: areturn
		// @1D: astore_2
		// @1E: aload_2
		// @1F: new java.lang.StringBuilder
		// @22: dup
		// @23: invokespecial java.lang.StringBuilder.<init>()void
		// @26: getstatic java.lang.String[] game.C_100157_db.field_103562_z
		// @29: iconst_5
		// @2A: aaload
		// @2B: invokevirtual java.lang.StringBuilder.append(java.lang.String)java.lang.StringBuilder
		// @2E: iload_1
		// @2F: invokevirtual java.lang.StringBuilder.append(int)java.lang.StringBuilder
		// @32: bipush 41 (0x29)
		// @34: invokevirtual java.lang.StringBuilder.append(char)java.lang.StringBuilder
		// @37: invokevirtual java.lang.StringBuilder.toString()java.lang.String
		// @3A: invokestatic game.C_100181_cf.func_105695_a(java.lang.Throwable, java.lang.String)game.C_100170_cm
		// @3D: athrow
	}
	
	public static void func_103550_a(byte arg0)
	{
		// @00: iload_0
		// @01: bipush -39 (0xD9)
		// @03: if_icmpeq @07
		// @06: return
		// @07: aconst_null
		// @08: putstatic java.lang.String game.C_100157_db.field_103556_f
		// @0B: aconst_null
		// @0C: putstatic game.C_100037_wb[] game.C_100157_db.field_103558_e
		// @0F: aconst_null
		// @10: putstatic java.lang.String game.C_100157_db.field_103560_c
		// @13: aconst_null
		// @14: putstatic java.lang.String game.C_100157_db.field_103559_b
		// @17: goto @3C
		// @1A: astore_1
		// @1B: aload_1
		// @1C: new java.lang.StringBuilder
		// @1F: dup
		// @20: invokespecial java.lang.StringBuilder.<init>()void
		// @23: getstatic java.lang.String[] game.C_100157_db.field_103562_z
		// @26: bipush 7 (0x07)
		// @28: aaload
		// @29: invokevirtual java.lang.StringBuilder.append(java.lang.String)java.lang.StringBuilder
		// @2C: iload_0
		// @2D: invokevirtual java.lang.StringBuilder.append(int)java.lang.StringBuilder
		// @30: bipush 41 (0x29)
		// @32: invokevirtual java.lang.StringBuilder.append(char)java.lang.StringBuilder
		// @35: invokevirtual java.lang.StringBuilder.toString()java.lang.String
		// @38: invokestatic game.C_100181_cf.func_105695_a(java.lang.Throwable, java.lang.String)game.C_100170_cm
		// @3B: athrow
		// @3C: return
	}
	
	static final byte[] func_103547_a(int arg0, byte[] arg1)
	{
		// @00: aload_1
		// @01: arraylength
		// @02: istore_2
		// @03: iload_2
		// @04: newarray byte[]
		// @06: astore_3
		// @07: aload_1
		// @08: iconst_0
		// @09: aload_3
		// @0A: iload_0
		// @0B: iload_2
		// @0C: invokestatic game.C_100120_en.func_104911_a(byte[], int, byte[], int, int)void
		// @0F: aload_3
		// @10: areturn
		// @11: astore_2
		// @12: aload_2
		// @13: new java.lang.StringBuilder
		// @16: dup
		// @17: invokespecial java.lang.StringBuilder.<init>()void
		// @1A: getstatic java.lang.String[] game.C_100157_db.field_103562_z
		// @1D: bipush 6 (0x06)
		// @1F: aaload
		// @20: invokevirtual java.lang.StringBuilder.append(java.lang.String)java.lang.StringBuilder
		// @23: iload_0
		// @24: invokevirtual java.lang.StringBuilder.append(int)java.lang.StringBuilder
		// @27: bipush 44 (0x2C)
		// @29: invokevirtual java.lang.StringBuilder.append(char)java.lang.StringBuilder
		// @2C: aload_1
		// @2D: ifnull @39
		// @30: getstatic java.lang.String[] game.C_100157_db.field_103562_z
		// @33: iconst_2
		// @34: aaload
		// @35: goto @3E
		// @38: athrow
		// @39: getstatic java.lang.String[] game.C_100157_db.field_103562_z
		// @3C: iconst_0
		// @3D: aaload
		// @3E: invokevirtual java.lang.StringBuilder.append(java.lang.String)java.lang.StringBuilder
		// @41: bipush 41 (0x29)
		// @43: invokevirtual java.lang.StringBuilder.append(char)java.lang.StringBuilder
		// @46: invokevirtual java.lang.StringBuilder.toString()java.lang.String
		// @49: invokestatic game.C_100181_cf.func_105695_a(java.lang.Throwable, java.lang.String)game.C_100170_cm
		// @4C: athrow
	}
	
	static final void func_103554_a(int arg0, int arg1, int arg2, int arg3, C_100037_wb[] arg4, int arg5)
	{
		// @000: getstatic int game.SteelSentinels.field_105275_O
		// @003: istore #22
		// @005: iconst_4
		// @006: newarray int[]
		// @008: astore #6
		// @00A: aload #4
		// @00C: ifnonnull @010
		// @00F: return
		// @010: iconst_m1
		// @011: iload_3
		// @012: iconst_m1
		// @013: ixor
		// @014: if_icmple @027
		// @017: iconst_m1
		// @018: iload #5
		// @01A: iconst_m1
		// @01B: ixor
		// @01C: if_icmple @027
		// @01F: goto @023
		// @022: athrow
		// @023: goto @028
		// @026: athrow
		// @027: return
		// @028: aconst_null
		// @029: aload #4
		// @02B: iconst_3
		// @02C: aaload
		// @02D: if_acmpne @035
		// @030: iconst_0
		// @031: goto @03C
		// @034: athrow
		// @035: aload #4
		// @037: iconst_3
		// @038: aaload
		// @039: getfield int game.C_100037_wb.field_102341_y
		// @03C: istore #7
		// @03E: aload #4
		// @040: iconst_5
		// @041: aaload
		// @042: ifnonnull @04A
		// @045: iconst_0
		// @046: goto @051
		// @049: athrow
		// @04A: aload #4
		// @04C: iconst_5
		// @04D: aaload
		// @04E: getfield int game.C_100037_wb.field_102341_y
		// @051: istore #8
		// @053: aconst_null
		// @054: aload #4
		// @056: iconst_1
		// @057: aaload
		// @058: if_acmpne @060
		// @05B: iconst_0
		// @05C: goto @067
		// @05F: athrow
		// @060: aload #4
		// @062: iconst_1
		// @063: aaload
		// @064: getfield int game.C_100037_wb.field_102340_z
		// @067: istore #9
		// @069: aload #4
		// @06B: bipush 7 (0x07)
		// @06D: aaload
		// @06E: ifnonnull @076
		// @071: iconst_0
		// @072: goto @07E
		// @075: athrow
		// @076: aload #4
		// @078: bipush 7 (0x07)
		// @07A: aaload
		// @07B: getfield int game.C_100037_wb.field_102340_z
		// @07E: istore #10
		// @080: iload_3
		// @081: iload_0
		// @082: iadd
		// @083: istore #11
		// @085: iload_1
		// @086: iload #5
		// @088: iadd
		// @089: istore #12
		// @08B: iload_0
		// @08C: iload #7
		// @08E: iadd
		// @08F: istore #13
		// @091: iload #8
		// @093: ineg
		// @094: iload #11
		// @096: iadd
		// @097: istore #14
		// @099: iload #9
		// @09B: iload_1
		// @09C: iadd
		// @09D: istore #15
		// @09F: iload #12
		// @0A1: iload #10
		// @0A3: ineg
		// @0A4: iadd
		// @0A5: istore #16
		// @0A7: iload #13
		// @0A9: istore #17
		// @0AB: iload #14
		// @0AD: istore #18
		// @0AF: iload #17
		// @0B1: iconst_m1
		// @0B2: ixor
		// @0B3: iload #18
		// @0B5: iconst_m1
		// @0B6: ixor
		// @0B7: if_icmpge @0CC
		// @0BA: iload_0
		// @0BB: iload #7
		// @0BD: iload_3
		// @0BE: imul
		// @0BF: iload #8
		// @0C1: iload #7
		// @0C3: iadd
		// @0C4: idiv
		// @0C5: ineg
		// @0C6: isub
		// @0C7: dup
		// @0C8: istore #18
		// @0CA: istore #17
		// @0CC: iload #15
		// @0CE: istore #19
		// @0D0: iload #16
		// @0D2: istore #20
		// @0D4: aload #6
		// @0D6: invokestatic game.C_100196_rb.func_105801_a(int[])void
		// @0D9: iload #20
		// @0DB: iload #19
		// @0DD: if_icmplt @0E4
		// @0E0: goto @0F7
		// @0E3: athrow
		// @0E4: iload_1
		// @0E5: iload #5
		// @0E7: iload #9
		// @0E9: imul
		// @0EA: iload #10
		// @0EC: iload #9
		// @0EE: iadd
		// @0EF: idiv
		// @0F0: ineg
		// @0F1: isub
		// @0F2: dup
		// @0F3: istore #20
		// @0F5: istore #19
		// @0F7: aconst_null
		// @0F8: aload #4
		// @0FA: iconst_0
		// @0FB: aaload
		// @0FC: if_acmpne @103
		// @0FF: goto @11A
		// @102: athrow
		// @103: iload_0
		// @104: iload_1
		// @105: iload #17
		// @107: iload #19
		// @109: invokestatic game.C_100196_rb.func_105779_e(int, int, int, int)void
		// @10C: aload #4
		// @10E: iconst_0
		// @10F: aaload
		// @110: iload_0
		// @111: iload_1
		// @112: invokevirtual game.C_100037_wb.func_102353_h(int, int)void
		// @115: aload #6
		// @117: invokestatic game.C_100196_rb.func_105777_b(int[])void
		// @11A: aload #4
		// @11C: iconst_2
		// @11D: aaload
		// @11E: ifnonnull @125
		// @121: goto @13E
		// @124: athrow
		// @125: iload #18
		// @127: iload_1
		// @128: iload #11
		// @12A: iload #19
		// @12C: invokestatic game.C_100196_rb.func_105779_e(int, int, int, int)void
		// @12F: aload #4
		// @131: iconst_2
		// @132: aaload
		// @133: iload #14
		// @135: iload_1
		// @136: invokevirtual game.C_100037_wb.func_102353_h(int, int)void
		// @139: aload #6
		// @13B: invokestatic game.C_100196_rb.func_105777_b(int[])void
		// @13E: aload #4
		// @140: bipush 6 (0x06)
		// @142: aaload
		// @143: ifnull @164
		// @146: iload_0
		// @147: iload #20
		// @149: iload #17
		// @14B: iload #12
		// @14D: invokestatic game.C_100196_rb.func_105779_e(int, int, int, int)void
		// @150: aload #4
		// @152: bipush 6 (0x06)
		// @154: aaload
		// @155: iload_0
		// @156: iload #16
		// @158: invokevirtual game.C_100037_wb.func_102353_h(int, int)void
		// @15B: aload #6
		// @15D: invokestatic game.C_100196_rb.func_105777_b(int[])void
		// @160: goto @164
		// @163: athrow
		// @164: aconst_null
		// @165: aload #4
		// @167: bipush 8 (0x08)
		// @169: aaload
		// @16A: if_acmpne @171
		// @16D: goto @18D
		// @170: athrow
		// @171: iload #18
		// @173: iload #20
		// @175: iload #11
		// @177: iload #12
		// @179: invokestatic game.C_100196_rb.func_105779_e(int, int, int, int)void
		// @17C: aload #4
		// @17E: bipush 8 (0x08)
		// @180: aaload
		// @181: iload #14
		// @183: iload #16
		// @185: invokevirtual game.C_100037_wb.func_102353_h(int, int)void
		// @188: aload #6
		// @18A: invokestatic game.C_100196_rb.func_105777_b(int[])void
		// @18D: aconst_null
		// @18E: aload #4
		// @190: iconst_1
		// @191: aaload
		// @192: if_acmpeq @1E8
		// @195: aload #4
		// @197: iconst_1
		// @198: aaload
		// @199: getfield int game.C_100037_wb.field_102341_y
		// @19C: iconst_m1
		// @19D: ixor
		// @19E: iconst_m1
		// @19F: if_icmpne @1AA
		// @1A2: goto @1A6
		// @1A5: athrow
		// @1A6: goto @1E8
		// @1A9: athrow
		// @1AA: iload #17
		// @1AC: iload_1
		// @1AD: iload #18
		// @1AF: iload #19
		// @1B1: invokestatic game.C_100196_rb.func_105779_e(int, int, int, int)void
		// @1B4: iload #13
		// @1B6: istore #21
		// @1B8: iload #14
		// @1BA: iload #21
		// @1BC: if_icmple @1E3
		// @1BF: aload #4
		// @1C1: iconst_1
		// @1C2: aaload
		// @1C3: iload #21
		// @1C5: iload_1
		// @1C6: invokevirtual game.C_100037_wb.func_102353_h(int, int)void
		// @1C9: iload #21
		// @1CB: aload #4
		// @1CD: iconst_1
		// @1CE: aaload
		// @1CF: getfield int game.C_100037_wb.field_102341_y
		// @1D2: iadd
		// @1D3: istore #21
		// @1D5: iload #22
		// @1D7: ifne @1E8
		// @1DA: iload #22
		// @1DC: ifeq @1B8
		// @1DF: goto @1E3
		// @1E2: athrow
		// @1E3: aload #6
		// @1E5: invokestatic game.C_100196_rb.func_105777_b(int[])void
		// @1E8: aconst_null
		// @1E9: aload #4
		// @1EB: bipush 7 (0x07)
		// @1ED: aaload
		// @1EE: if_acmpeq @243
		// @1F1: iconst_0
		// @1F2: aload #4
		// @1F4: bipush 7 (0x07)
		// @1F6: aaload
		// @1F7: getfield int game.C_100037_wb.field_102341_y
		// @1FA: if_icmpeq @243
		// @1FD: goto @201
		// @200: athrow
		// @201: iload #17
		// @203: iload #20
		// @205: iload #18
		// @207: iload #12
		// @209: invokestatic game.C_100196_rb.func_105779_e(int, int, int, int)void
		// @20C: iload #13
		// @20E: istore #21
		// @210: iload #14
		// @212: iload #21
		// @214: if_icmple @23E
		// @217: aload #4
		// @219: bipush 7 (0x07)
		// @21B: aaload
		// @21C: iload #21
		// @21E: iload #16
		// @220: invokevirtual game.C_100037_wb.func_102353_h(int, int)void
		// @223: iload #21
		// @225: aload #4
		// @227: bipush 7 (0x07)
		// @229: aaload
		// @22A: getfield int game.C_100037_wb.field_102341_y
		// @22D: iadd
		// @22E: istore #21
		// @230: iload #22
		// @232: ifne @243
		// @235: iload #22
		// @237: ifeq @210
		// @23A: goto @23E
		// @23D: athrow
		// @23E: aload #6
		// @240: invokestatic game.C_100196_rb.func_105777_b(int[])void
		// @243: aload #4
		// @245: iconst_3
		// @246: aaload
		// @247: ifnull @27E
		// @24A: iconst_0
		// @24B: aload #4
		// @24D: iconst_3
		// @24E: aaload
		// @24F: getfield int game.C_100037_wb.field_102340_z
		// @252: if_icmpne @25D
		// @255: goto @259
		// @258: athrow
		// @259: goto @27E
		// @25C: athrow
		// @25D: iload_0
		// @25E: iload #19
		// @260: iload #17
		// @262: iload #20
		// @264: invokestatic game.C_100196_rb.func_105779_e(int, int, int, int)void
		// @267: aload #4
		// @269: iconst_3
		// @26A: aaload
		// @26B: iload_0
		// @26C: iload #15
		// @26E: iload #7
		// @270: iload #16
		// @272: iload #15
		// @274: ineg
		// @275: iadd
		// @276: invokevirtual game.C_100037_wb.func_102364_d(int, int, int, int)void
		// @279: aload #6
		// @27B: invokestatic game.C_100196_rb.func_105777_b(int[])void
		// @27E: aconst_null
		// @27F: aload #4
		// @281: iconst_5
		// @282: aaload
		// @283: if_acmpeq @2BD
		// @286: iconst_m1
		// @287: aload #4
		// @289: iconst_5
		// @28A: aaload
		// @28B: getfield int game.C_100037_wb.field_102340_z
		// @28E: iconst_m1
		// @28F: ixor
		// @290: if_icmpeq @2BD
		// @293: goto @297
		// @296: athrow
		// @297: iload #18
		// @299: iload #19
		// @29B: iload #11
		// @29D: iload #20
		// @29F: invokestatic game.C_100196_rb.func_105779_e(int, int, int, int)void
		// @2A2: aload #4
		// @2A4: iconst_5
		// @2A5: aaload
		// @2A6: iload #14
		// @2A8: iload #15
		// @2AA: iload #8
		// @2AC: iload #16
		// @2AE: iload #15
		// @2B0: isub
		// @2B1: invokevirtual game.C_100037_wb.func_102364_d(int, int, int, int)void
		// @2B4: aload #6
		// @2B6: invokestatic game.C_100196_rb.func_105777_b(int[])void
		// @2B9: goto @2BD
		// @2BC: athrow
		// @2BD: aload #4
		// @2BF: iconst_4
		// @2C0: aaload
		// @2C1: ifnull @30E
		// @2C4: aload #4
		// @2C6: iconst_4
		// @2C7: aaload
		// @2C8: getfield int game.C_100037_wb.field_102341_y
		// @2CB: ifeq @30E
		// @2CE: goto @2D2
		// @2D1: athrow
		// @2D2: iconst_m1
		// @2D3: aload #4
		// @2D5: iconst_4
		// @2D6: aaload
		// @2D7: getfield int game.C_100037_wb.field_102340_z
		// @2DA: iconst_m1
		// @2DB: ixor
		// @2DC: if_icmpeq @30E
		// @2DF: goto @2E3
		// @2E2: athrow
		// @2E3: iload #17
		// @2E5: iload #19
		// @2E7: iload #18
		// @2E9: iload #20
		// @2EB: invokestatic game.C_100196_rb.func_105779_e(int, int, int, int)void
		// @2EE: aload #4
		// @2F0: iconst_4
		// @2F1: aaload
		// @2F2: iload #13
		// @2F4: iload #15
		// @2F6: iload #13
		// @2F8: ineg
		// @2F9: iload #14
		// @2FB: iadd
		// @2FC: iload #15
		// @2FE: ineg
		// @2FF: iload #16
		// @301: iadd
		// @302: invokevirtual game.C_100037_wb.func_102364_d(int, int, int, int)void
		// @305: aload #6
		// @307: invokestatic game.C_100196_rb.func_105777_b(int[])void
		// @30A: goto @30E
		// @30D: athrow
		// @30E: bipush -39 (0xD9)
		// @310: iload_2
		// @311: bipush 63 (0x3F)
		// @313: isub
		// @314: bipush 60 (0x3C)
		// @316: idiv
		// @317: irem
		// @318: istore #21
		// @31A: goto @380
		// @31D: astore #6
		// @31F: aload #6
		// @321: new java.lang.StringBuilder
		// @324: dup
		// @325: invokespecial java.lang.StringBuilder.<init>()void
		// @328: getstatic java.lang.String[] game.C_100157_db.field_103562_z
		// @32B: iconst_1
		// @32C: aaload
		// @32D: invokevirtual java.lang.StringBuilder.append(java.lang.String)java.lang.StringBuilder
		// @330: iload_0
		// @331: invokevirtual java.lang.StringBuilder.append(int)java.lang.StringBuilder
		// @334: bipush 44 (0x2C)
		// @336: invokevirtual java.lang.StringBuilder.append(char)java.lang.StringBuilder
		// @339: iload_1
		// @33A: invokevirtual java.lang.StringBuilder.append(int)java.lang.StringBuilder
		// @33D: bipush 44 (0x2C)
		// @33F: invokevirtual java.lang.StringBuilder.append(char)java.lang.StringBuilder
		// @342: iload_2
		// @343: invokevirtual java.lang.StringBuilder.append(int)java.lang.StringBuilder
		// @346: bipush 44 (0x2C)
		// @348: invokevirtual java.lang.StringBuilder.append(char)java.lang.StringBuilder
		// @34B: iload_3
		// @34C: invokevirtual java.lang.StringBuilder.append(int)java.lang.StringBuilder
		// @34F: bipush 44 (0x2C)
		// @351: invokevirtual java.lang.StringBuilder.append(char)java.lang.StringBuilder
		// @354: aload #4
		// @356: ifnull @362
		// @359: getstatic java.lang.String[] game.C_100157_db.field_103562_z
		// @35C: iconst_2
		// @35D: aaload
		// @35E: goto @367
		// @361: athrow
		// @362: getstatic java.lang.String[] game.C_100157_db.field_103562_z
		// @365: iconst_0
		// @366: aaload
		// @367: invokevirtual java.lang.StringBuilder.append(java.lang.String)java.lang.StringBuilder
		// @36A: bipush 44 (0x2C)
		// @36C: invokevirtual java.lang.StringBuilder.append(char)java.lang.StringBuilder
		// @36F: iload #5
		// @371: invokevirtual java.lang.StringBuilder.append(int)java.lang.StringBuilder
		// @374: bipush 41 (0x29)
		// @376: invokevirtual java.lang.StringBuilder.append(char)java.lang.StringBuilder
		// @379: invokevirtual java.lang.StringBuilder.toString()java.lang.String
		// @37C: invokestatic game.C_100181_cf.func_105695_a(java.lang.Throwable, java.lang.String)game.C_100170_cm
		// @37F: athrow
		// @380: return
	}
	
	static final C_100059_df func_103553_a(int arg0, int arg1, boolean arg2, int arg3, int arg4, C_100294_ki arg5, byte arg6, int arg7, int arg8, int arg9)
	{
		// @00: iconst_0
		// @01: invokestatic game.C_100297_kf.func_101226_b(boolean)game.C_100059_df
		// @04: astore #10
		// @06: aload #10
		// @08: aload #5
		// @0A: putfield game.C_100294_ki game.C_100059_df.field_101596_A
		// @0D: aload #10
		// @0F: iload_2
		// @10: putfield boolean game.C_100059_df.field_101617_y
		// @13: aload #10
		// @15: iload #7
		// @17: putfield int game.C_100059_df.field_101602_O
		// @1A: iload #6
		// @1C: bipush -124 (0x84)
		// @1E: if_icmpeq @26
		// @21: aconst_null
		// @22: checkcast game.C_100059_df
		// @25: areturn
		// @26: aload #10
		// @28: iload_1
		// @29: putfield int game.C_100059_df.field_101595_G
		// @2C: aload #10
		// @2E: iload #9
		// @30: putfield int game.C_100059_df.field_101618_x
		// @33: aload #10
		// @35: iload #8
		// @37: putfield int game.C_100059_df.field_101608_P
		// @3A: aload #10
		// @3C: iload #4
		// @3E: putfield int game.C_100059_df.field_101607_Q
		// @41: aload #10
		// @43: iload_0
		// @44: putfield int game.C_100059_df.field_101610_R
		// @47: aload #10
		// @49: iload_3
		// @4A: putfield int game.C_100059_df.field_101605_J
		// @4D: aload #10
		// @4F: iconst_0
		// @50: putfield int game.C_100059_df.field_101598_C
		// @53: aload #10
		// @55: areturn
		// @56: astore #10
		// @58: aload #10
		// @5A: new java.lang.StringBuilder
		// @5D: dup
		// @5E: invokespecial java.lang.StringBuilder.<init>()void
		// @61: getstatic java.lang.String[] game.C_100157_db.field_103562_z
		// @64: iconst_4
		// @65: aaload
		// @66: invokevirtual java.lang.StringBuilder.append(java.lang.String)java.lang.StringBuilder
		// @69: iload_0
		// @6A: invokevirtual java.lang.StringBuilder.append(int)java.lang.StringBuilder
		// @6D: bipush 44 (0x2C)
		// @6F: invokevirtual java.lang.StringBuilder.append(char)java.lang.StringBuilder
		// @72: iload_1
		// @73: invokevirtual java.lang.StringBuilder.append(int)java.lang.StringBuilder
		// @76: bipush 44 (0x2C)
		// @78: invokevirtual java.lang.StringBuilder.append(char)java.lang.StringBuilder
		// @7B: iload_2
		// @7C: invokevirtual java.lang.StringBuilder.append(boolean)java.lang.StringBuilder
		// @7F: bipush 44 (0x2C)
		// @81: invokevirtual java.lang.StringBuilder.append(char)java.lang.StringBuilder
		// @84: iload_3
		// @85: invokevirtual java.lang.StringBuilder.append(int)java.lang.StringBuilder
		// @88: bipush 44 (0x2C)
		// @8A: invokevirtual java.lang.StringBuilder.append(char)java.lang.StringBuilder
		// @8D: iload #4
		// @8F: invokevirtual java.lang.StringBuilder.append(int)java.lang.StringBuilder
		// @92: bipush 44 (0x2C)
		// @94: invokevirtual java.lang.StringBuilder.append(char)java.lang.StringBuilder
		// @97: aload #5
		// @99: ifnull @A5
		// @9C: getstatic java.lang.String[] game.C_100157_db.field_103562_z
		// @9F: iconst_2
		// @A0: aaload
		// @A1: goto @AA
		// @A4: athrow
		// @A5: getstatic java.lang.String[] game.C_100157_db.field_103562_z
		// @A8: iconst_0
		// @A9: aaload
		// @AA: invokevirtual java.lang.StringBuilder.append(java.lang.String)java.lang.StringBuilder
		// @AD: bipush 44 (0x2C)
		// @AF: invokevirtual java.lang.StringBuilder.append(char)java.lang.StringBuilder
		// @B2: iload #6
		// @B4: invokevirtual java.lang.StringBuilder.append(int)java.lang.StringBuilder
		// @B7: bipush 44 (0x2C)
		// @B9: invokevirtual java.lang.StringBuilder.append(char)java.lang.StringBuilder
		// @BC: iload #7
		// @BE: invokevirtual java.lang.StringBuilder.append(int)java.lang.StringBuilder
		// @C1: bipush 44 (0x2C)
		// @C3: invokevirtual java.lang.StringBuilder.append(char)java.lang.StringBuilder
		// @C6: iload #8
		// @C8: invokevirtual java.lang.StringBuilder.append(int)java.lang.StringBuilder
		// @CB: bipush 44 (0x2C)
		// @CD: invokevirtual java.lang.StringBuilder.append(char)java.lang.StringBuilder
		// @D0: iload #9
		// @D2: invokevirtual java.lang.StringBuilder.append(int)java.lang.StringBuilder
		// @D5: bipush 41 (0x29)
		// @D7: invokevirtual java.lang.StringBuilder.append(char)java.lang.StringBuilder
		// @DA: invokevirtual java.lang.StringBuilder.toString()java.lang.String
		// @DD: invokestatic game.C_100181_cf.func_105695_a(java.lang.Throwable, java.lang.String)game.C_100170_cm
		// @E0: athrow
	}
	
	static final C_100327_ib func_103546_a(int[] arg0, byte arg1, int[] arg2)
	{
		// @00: bipush -93 (0xA3)
		// @02: bipush 19 (0x13)
		// @04: iload_1
		// @05: isub
		// @06: bipush 50 (0x32)
		// @08: idiv
		// @09: irem
		// @0A: istore_3
		// @0B: iconst_1
		// @0C: aload_2
		// @0D: aload_0
		// @0E: bipush -46 (0xD2)
		// @10: invokestatic game.C_100195_rc.func_105771_a(boolean, int[], int[], byte)game.C_100327_ib
		// @13: areturn
		// @14: astore_3
		// @15: aload_3
		// @16: new java.lang.StringBuilder
		// @19: dup
		// @1A: invokespecial java.lang.StringBuilder.<init>()void
		// @1D: getstatic java.lang.String[] game.C_100157_db.field_103562_z
		// @20: bipush 8 (0x08)
		// @22: aaload
		// @23: invokevirtual java.lang.StringBuilder.append(java.lang.String)java.lang.StringBuilder
		// @26: aload_0
		// @27: ifnull @33
		// @2A: getstatic java.lang.String[] game.C_100157_db.field_103562_z
		// @2D: iconst_2
		// @2E: aaload
		// @2F: goto @38
		// @32: athrow
		// @33: getstatic java.lang.String[] game.C_100157_db.field_103562_z
		// @36: iconst_0
		// @37: aaload
		// @38: invokevirtual java.lang.StringBuilder.append(java.lang.String)java.lang.StringBuilder
		// @3B: bipush 44 (0x2C)
		// @3D: invokevirtual java.lang.StringBuilder.append(char)java.lang.StringBuilder
		// @40: iload_1
		// @41: invokevirtual java.lang.StringBuilder.append(int)java.lang.StringBuilder
		// @44: bipush 44 (0x2C)
		// @46: invokevirtual java.lang.StringBuilder.append(char)java.lang.StringBuilder
		// @49: aload_2
		// @4A: ifnull @56
		// @4D: getstatic java.lang.String[] game.C_100157_db.field_103562_z
		// @50: iconst_2
		// @51: aaload
		// @52: goto @5B
		// @55: athrow
		// @56: getstatic java.lang.String[] game.C_100157_db.field_103562_z
		// @59: iconst_0
		// @5A: aaload
		// @5B: invokevirtual java.lang.StringBuilder.append(java.lang.String)java.lang.StringBuilder
		// @5E: bipush 41 (0x29)
		// @60: invokevirtual java.lang.StringBuilder.append(char)java.lang.StringBuilder
		// @63: invokevirtual java.lang.StringBuilder.toString()java.lang.String
		// @66: invokestatic game.C_100181_cf.func_105695_a(java.lang.Throwable, java.lang.String)game.C_100170_cm
		// @69: athrow
	}
	
	static final void func_103549_a(int arg0, int arg1, boolean arg2, int arg3)
	{
		// @00: iload_2
		// @01: bipush 94 (0x5E)
		// @03: iload_3
		// @04: iload_0
		// @05: invokestatic game.C_100093_fd.func_102770_a(boolean, byte, int, int)void
		// @08: bipush -110 (0x92)
		// @0A: bipush -7 (0xF9)
		// @0C: iload_1
		// @0D: isub
		// @0E: bipush 58 (0x3A)
		// @10: idiv
		// @11: irem
		// @12: istore #4
		// @14: goto @55
		// @17: astore #4
		// @19: aload #4
		// @1B: new java.lang.StringBuilder
		// @1E: dup
		// @1F: invokespecial java.lang.StringBuilder.<init>()void
		// @22: getstatic java.lang.String[] game.C_100157_db.field_103562_z
		// @25: iconst_3
		// @26: aaload
		// @27: invokevirtual java.lang.StringBuilder.append(java.lang.String)java.lang.StringBuilder
		// @2A: iload_0
		// @2B: invokevirtual java.lang.StringBuilder.append(int)java.lang.StringBuilder
		// @2E: bipush 44 (0x2C)
		// @30: invokevirtual java.lang.StringBuilder.append(char)java.lang.StringBuilder
		// @33: iload_1
		// @34: invokevirtual java.lang.StringBuilder.append(int)java.lang.StringBuilder
		// @37: bipush 44 (0x2C)
		// @39: invokevirtual java.lang.StringBuilder.append(char)java.lang.StringBuilder
		// @3C: iload_2
		// @3D: invokevirtual java.lang.StringBuilder.append(boolean)java.lang.StringBuilder
		// @40: bipush 44 (0x2C)
		// @42: invokevirtual java.lang.StringBuilder.append(char)java.lang.StringBuilder
		// @45: iload_3
		// @46: invokevirtual java.lang.StringBuilder.append(int)java.lang.StringBuilder
		// @49: bipush 41 (0x29)
		// @4B: invokevirtual java.lang.StringBuilder.append(char)java.lang.StringBuilder
		// @4E: invokevirtual java.lang.StringBuilder.toString()java.lang.String
		// @51: invokestatic game.C_100181_cf.func_105695_a(java.lang.Throwable, java.lang.String)game.C_100170_cm
		// @54: athrow
		// @55: return
	}
	
	abstract Socket func_103555_b(int arg0) throws IOException;
	
	static
	{
		// @00: bipush 9 (0x09)
		// @02: anewarray java.lang.String
		// @05: dup
		// @06: iconst_0
		// @07: ldc "\u0003\u0010>\u001b"
		// @09: invokestatic game.C_100157_db.func_103552_z(java.lang.String)char[]
		// @0C: invokestatic game.C_100157_db.func_103548_z(char[])java.lang.String
		// @0F: aastore
		// @10: dup
		// @11: iconst_1
		// @12: ldc "\t\u0007|82"
		// @14: invokestatic game.C_100157_db.func_103552_z(java.lang.String)char[]
		// @17: invokestatic game.C_100157_db.func_103548_z(char[])java.lang.String
		// @1A: aastore
		// @1B: dup
		// @1C: iconst_2
		// @1D: ldc "\u0016K|Yg"
		// @1F: invokestatic game.C_100157_db.func_103552_z(java.lang.String)char[]
		// @22: invokestatic game.C_100157_db.func_103548_z(char[])java.lang.String
		// @25: aastore
		// @26: dup
		// @27: iconst_3
		// @28: ldc "\t\u0007|<2"
		// @2A: invokestatic game.C_100157_db.func_103552_z(java.lang.String)char[]
		// @2D: invokestatic game.C_100157_db.func_103548_z(char[])java.lang.String
		// @30: aastore
		// @31: dup
		// @32: iconst_4
		// @33: ldc "\t\u0007|;2"
		// @35: invokestatic game.C_100157_db.func_103552_z(java.lang.String)char[]
		// @38: invokestatic game.C_100157_db.func_103548_z(char[])java.lang.String
		// @3B: aastore
		// @3C: dup
		// @3D: iconst_5
		// @3E: ldc "\t\u0007|:2"
		// @40: invokestatic game.C_100157_db.func_103552_z(java.lang.String)char[]
		// @43: invokestatic game.C_100157_db.func_103548_z(char[])java.lang.String
		// @46: aastore
		// @47: dup
		// @48: bipush 6 (0x06)
		// @4A: ldc "\t\u0007|92"
		// @4C: invokestatic game.C_100157_db.func_103552_z(java.lang.String)char[]
		// @4F: invokestatic game.C_100157_db.func_103548_z(char[])java.lang.String
		// @52: aastore
		// @53: dup
		// @54: bipush 7 (0x07)
		// @56: ldc "\t\u0007|>2"
		// @58: invokestatic game.C_100157_db.func_103552_z(java.lang.String)char[]
		// @5B: invokestatic game.C_100157_db.func_103548_z(char[])java.lang.String
		// @5E: aastore
		// @5F: dup
		// @60: bipush 8 (0x08)
		// @62: ldc "\t\u0007|=2"
		// @64: invokestatic game.C_100157_db.func_103552_z(java.lang.String)char[]
		// @67: invokestatic game.C_100157_db.func_103548_z(char[])java.lang.String
		// @6A: aastore
		// @6B: putstatic java.lang.String[] game.C_100157_db.field_103562_z
		// @6E: ldc "Q@bI:\u000e\u0004<\u0019u\u0019E8\u0018s\u0003^r\u0003r\u0008E5\u0016w\u0008E:\u0016iM\u0016&\u0016h\u0019\u00006Y"
		// @70: invokestatic game.C_100157_db.func_103552_z(java.lang.String)char[]
		// @73: invokestatic game.C_100157_db.func_103548_z(char[])java.lang.String
		// @76: putstatic java.lang.String game.C_100157_db.field_103556_f
		// @79: ldc "Q@bI:\u0000\u000c5\u001fnM\u0006:\u0016t\n\u0000r\u0003r\u0008E=\u0007n\u0004\n<\u0004:@E%\u0016s\u0019E3\u0019~M\u00167\u00124"
		// @7B: invokestatic game.C_100157_db.func_103552_z(java.lang.String)char[]
		// @7E: invokestatic game.C_100157_db.func_103548_z(char[])java.lang.String
		// @81: putstatic java.lang.String game.C_100157_db.field_103559_b
		// @84: ldc "4\n'Wr\u000c\u00137W&HUlWo\u0003\u00177\u0016~M\u00087\u0004i\u000c\u00027\u0004;"
		// @86: invokestatic game.C_100157_db.func_103552_z(java.lang.String)char[]
		// @89: invokestatic game.C_100157_db.func_103548_z(char[])java.lang.String
		// @8C: putstatic java.lang.String game.C_100157_db.field_103560_c
		// @8F: return
	}
	
	private static char[] func_103552_z(String arg0)
	{
		// @00: aload_0
		// @01: invokevirtual java.lang.String.toCharArray()char[]
		// @04: dup
		// @05: arraylength
		// @06: iconst_2
		// @07: if_icmpge @13
		// @0A: dup
		// @0B: iconst_0
		// @0C: dup2
		// @0D: caload
		// @0E: bipush 26 (0x1A)
		// @10: ixor
		// @11: i2c
		// @12: castore
		// @13: areturn
	}
	
	private static String func_103548_z(char[] arg0)
	{
		// @00: aload_0
		// @01: dup
		// @02: arraylength
		// @03: swap
		// @04: iconst_0
		// @05: istore_1
		// @06: goto @4C
		// @09: dup
		// @0A: iload_1
		// @0B: dup2
		// @0C: caload
		// @0D: iload_1
		// @0E: iconst_5
		// @0F: irem
		// @10: tableswitch def: @44, for 0: @30, for 1: @35, for 2: @3A, for 3: @3F
		// @30: bipush 109 (0x6D)
		// @32: goto @46
		// @35: bipush 101 (0x65)
		// @37: goto @46
		// @3A: bipush 82 (0x52)
		// @3C: goto @46
		// @3F: bipush 119 (0x77)
		// @41: goto @46
		// @44: bipush 26 (0x1A)
		// @46: ixor
		// @47: i2c
		// @48: castore
		// @49: iinc #1 +1
		// @4C: swap
		// @4D: dup_x1
		// @4E: iload_1
		// @4F: if_icmpgt @09
		// @52: new java.lang.String
		// @55: dup_x1
		// @56: swap
		// @57: invokespecial java.lang.String.<init>(char[])void
		// @5A: invokevirtual java.lang.String.intern()java.lang.String
		// @5D: areturn
	}
}
