package game;

final class C_100225_ah
{
	static boolean field_106131_k;
	C_100037_wb field_106128_l;
	C_100037_wb[] field_106124_c;
	private int field_106127_o;
	static int field_106122_e;
	private boolean field_106130_j;
	private int field_106119_f;
	private int field_106120_g;
	static String field_106126_n;
	static String field_106123_b;
	static String field_106134_r;
	static String field_106121_d;
	static String field_106125_a;
	static C_100037_wb field_106129_m;
	static C_100301_kb[] field_106136_p;
	private int field_106135_q;
	static boolean field_106133_i;
	private int field_106132_h;
	private static final String[] field_106137_z;
	
	final C_100225_ah func_106117_c(int arg0, int arg1)
	{
		// @00: aload_0
		// @01: iload_1
		// @02: putfield int game.C_100225_ah.field_106127_o
		// @05: iload_2
		// @06: ifeq @1F
		// @09: aload_0
		// @0A: bipush -59 (0xC5)
		// @0C: bipush -126 (0x82)
		// @0E: aconst_null
		// @0F: checkcast game.C_100336_im
		// @12: aconst_null
		// @13: checkcast game.C_100139_tb
		// @16: bipush 34 (0x22)
		// @18: invokevirtual game.C_100225_ah.func_106109_a(int, int, game.C_100336_im, game.C_100139_tb, int)void
		// @1B: goto @1F
		// @1E: athrow
		// @1F: aload_0
		// @20: areturn
		// @21: astore_3
		// @22: aload_3
		// @23: new java.lang.StringBuilder
		// @26: dup
		// @27: invokespecial java.lang.StringBuilder.<init>()void
		// @2A: getstatic java.lang.String[] game.C_100225_ah.field_106137_z
		// @2D: bipush 11 (0x0B)
		// @2F: aaload
		// @30: invokevirtual java.lang.StringBuilder.append(java.lang.String)java.lang.StringBuilder
		// @33: iload_1
		// @34: invokevirtual java.lang.StringBuilder.append(int)java.lang.StringBuilder
		// @37: bipush 44 (0x2C)
		// @39: invokevirtual java.lang.StringBuilder.append(char)java.lang.StringBuilder
		// @3C: iload_2
		// @3D: invokevirtual java.lang.StringBuilder.append(int)java.lang.StringBuilder
		// @40: bipush 41 (0x29)
		// @42: invokevirtual java.lang.StringBuilder.append(char)java.lang.StringBuilder
		// @45: invokevirtual java.lang.StringBuilder.toString()java.lang.String
		// @48: invokestatic game.C_100181_cf.func_105695_a(java.lang.Throwable, java.lang.String)game.C_100170_cm
		// @4B: athrow
	}
	
	final C_100225_ah func_106112_a(boolean arg0, int arg1)
	{
		// @00: aload_0
		// @01: iload_1
		// @02: putfield boolean game.C_100225_ah.field_106130_j
		// @05: iload_2
		// @06: bipush 15 (0x0F)
		// @08: if_icmpge @17
		// @0B: aload_0
		// @0C: iconst_0
		// @0D: bipush -76 (0xB4)
		// @0F: invokevirtual game.C_100225_ah.func_106112_a(boolean, int)game.C_100225_ah
		// @12: pop
		// @13: goto @17
		// @16: athrow
		// @17: aload_0
		// @18: areturn
		// @19: astore_3
		// @1A: aload_3
		// @1B: new java.lang.StringBuilder
		// @1E: dup
		// @1F: invokespecial java.lang.StringBuilder.<init>()void
		// @22: getstatic java.lang.String[] game.C_100225_ah.field_106137_z
		// @25: bipush 7 (0x07)
		// @27: aaload
		// @28: invokevirtual java.lang.StringBuilder.append(java.lang.String)java.lang.StringBuilder
		// @2B: iload_1
		// @2C: invokevirtual java.lang.StringBuilder.append(boolean)java.lang.StringBuilder
		// @2F: bipush 44 (0x2C)
		// @31: invokevirtual java.lang.StringBuilder.append(char)java.lang.StringBuilder
		// @34: iload_2
		// @35: invokevirtual java.lang.StringBuilder.append(int)java.lang.StringBuilder
		// @38: bipush 41 (0x29)
		// @3A: invokevirtual java.lang.StringBuilder.append(char)java.lang.StringBuilder
		// @3D: invokevirtual java.lang.StringBuilder.toString()java.lang.String
		// @40: invokestatic game.C_100181_cf.func_105695_a(java.lang.Throwable, java.lang.String)game.C_100170_cm
		// @43: athrow
	}
	
	public static void func_106105_b(int arg0)
	{
		// @00: aconst_null
		// @01: putstatic java.lang.String game.C_100225_ah.field_106134_r
		// @04: iload_0
		// @05: ldc -2147483648 (0x80000000)
		// @07: if_icmpeq @0B
		// @0A: return
		// @0B: aconst_null
		// @0C: putstatic java.lang.String game.C_100225_ah.field_106121_d
		// @0F: aconst_null
		// @10: putstatic game.C_100301_kb[] game.C_100225_ah.field_106136_p
		// @13: aconst_null
		// @14: putstatic java.lang.String game.C_100225_ah.field_106125_a
		// @17: aconst_null
		// @18: putstatic java.lang.String game.C_100225_ah.field_106123_b
		// @1B: aconst_null
		// @1C: putstatic java.lang.String game.C_100225_ah.field_106126_n
		// @1F: aconst_null
		// @20: putstatic game.C_100037_wb game.C_100225_ah.field_106129_m
		// @23: goto @47
		// @26: astore_1
		// @27: aload_1
		// @28: new java.lang.StringBuilder
		// @2B: dup
		// @2C: invokespecial java.lang.StringBuilder.<init>()void
		// @2F: getstatic java.lang.String[] game.C_100225_ah.field_106137_z
		// @32: iconst_2
		// @33: aaload
		// @34: invokevirtual java.lang.StringBuilder.append(java.lang.String)java.lang.StringBuilder
		// @37: iload_0
		// @38: invokevirtual java.lang.StringBuilder.append(int)java.lang.StringBuilder
		// @3B: bipush 41 (0x29)
		// @3D: invokevirtual java.lang.StringBuilder.append(char)java.lang.StringBuilder
		// @40: invokevirtual java.lang.StringBuilder.toString()java.lang.String
		// @43: invokestatic game.C_100181_cf.func_105695_a(java.lang.Throwable, java.lang.String)game.C_100170_cm
		// @46: athrow
		// @47: return
	}
	
	final void func_106118_a(C_100336_im arg0, C_100139_tb arg1, C_100225_ah arg2, int arg3, int arg4, byte arg5)
	{
		// @000: aload_0
		// @001: getfield boolean game.C_100225_ah.field_106130_j
		// @004: ifne @00B
		// @007: goto @01E
		// @00A: athrow
		// @00B: aload_3
		// @00C: bipush -68 (0xBC)
		// @00E: iload #4
		// @010: aload_1
		// @011: aload_2
		// @012: iload #5
		// @014: invokevirtual game.C_100225_ah.func_106109_a(int, int, game.C_100336_im, game.C_100139_tb, int)void
		// @017: aload_3
		// @018: sipush 26632 (0x6808)
		// @01B: invokevirtual game.C_100225_ah.func_106115_c(int)void
		// @01E: ldc 2147483647 (0x7fffffff)
		// @020: aload_0
		// @021: getfield int game.C_100225_ah.field_106135_q
		// @024: iconst_m1
		// @025: ixor
		// @026: if_icmpeq @035
		// @029: aload_3
		// @02A: aload_0
		// @02B: getfield int game.C_100225_ah.field_106135_q
		// @02E: putfield int game.C_100225_ah.field_106135_q
		// @031: goto @035
		// @034: athrow
		// @035: aload_0
		// @036: getfield int game.C_100225_ah.field_106127_o
		// @039: ldc -2147483648 (0x80000000)
		// @03B: if_icmpne @042
		// @03E: goto @04A
		// @041: athrow
		// @042: aload_3
		// @043: aload_0
		// @044: getfield int game.C_100225_ah.field_106127_o
		// @047: putfield int game.C_100225_ah.field_106127_o
		// @04A: bipush 115 (0x73)
		// @04C: iload #6
		// @04E: bipush -40 (0xD8)
		// @050: isub
		// @051: bipush 62 (0x3E)
		// @053: idiv
		// @054: idiv
		// @055: istore #7
		// @057: aload_0
		// @058: getfield int game.C_100225_ah.field_106119_f
		// @05B: iconst_m1
		// @05C: ixor
		// @05D: ifgt @06C
		// @060: aload_3
		// @061: aload_0
		// @062: getfield int game.C_100225_ah.field_106119_f
		// @065: putfield int game.C_100225_ah.field_106119_f
		// @068: goto @06C
		// @06B: athrow
		// @06C: aconst_null
		// @06D: aload_0
		// @06E: getfield game.C_100037_wb game.C_100225_ah.field_106128_l
		// @071: if_acmpeq @080
		// @074: aload_3
		// @075: aload_0
		// @076: getfield game.C_100037_wb game.C_100225_ah.field_106128_l
		// @079: putfield game.C_100037_wb game.C_100225_ah.field_106128_l
		// @07C: goto @080
		// @07F: athrow
		// @080: aconst_null
		// @081: aload_0
		// @082: getfield game.C_100037_wb[] game.C_100225_ah.field_106124_c
		// @085: if_acmpne @08C
		// @088: goto @094
		// @08B: athrow
		// @08C: aload_3
		// @08D: aload_0
		// @08E: getfield game.C_100037_wb[] game.C_100225_ah.field_106124_c
		// @091: putfield game.C_100037_wb[] game.C_100225_ah.field_106124_c
		// @094: ldc -2147483648 (0x80000000)
		// @096: aload_0
		// @097: getfield int game.C_100225_ah.field_106120_g
		// @09A: if_icmpne @0A1
		// @09D: goto @0A9
		// @0A0: athrow
		// @0A1: aload_3
		// @0A2: aload_0
		// @0A3: getfield int game.C_100225_ah.field_106120_g
		// @0A6: putfield int game.C_100225_ah.field_106120_g
		// @0A9: aload_0
		// @0AA: getfield int game.C_100225_ah.field_106132_h
		// @0AD: iconst_m1
		// @0AE: ixor
		// @0AF: ifgt @0BE
		// @0B2: aload_3
		// @0B3: aload_0
		// @0B4: getfield int game.C_100225_ah.field_106132_h
		// @0B7: putfield int game.C_100225_ah.field_106132_h
		// @0BA: goto @0BE
		// @0BD: athrow
		// @0BE: goto @148
		// @0C1: astore #7
		// @0C3: aload #7
		// @0C5: new java.lang.StringBuilder
		// @0C8: dup
		// @0C9: invokespecial java.lang.StringBuilder.<init>()void
		// @0CC: getstatic java.lang.String[] game.C_100225_ah.field_106137_z
		// @0CF: bipush 8 (0x08)
		// @0D1: aaload
		// @0D2: invokevirtual java.lang.StringBuilder.append(java.lang.String)java.lang.StringBuilder
		// @0D5: aload_1
		// @0D6: ifnull @0E2
		// @0D9: getstatic java.lang.String[] game.C_100225_ah.field_106137_z
		// @0DC: iconst_3
		// @0DD: aaload
		// @0DE: goto @0E7
		// @0E1: athrow
		// @0E2: getstatic java.lang.String[] game.C_100225_ah.field_106137_z
		// @0E5: iconst_4
		// @0E6: aaload
		// @0E7: invokevirtual java.lang.StringBuilder.append(java.lang.String)java.lang.StringBuilder
		// @0EA: bipush 44 (0x2C)
		// @0EC: invokevirtual java.lang.StringBuilder.append(char)java.lang.StringBuilder
		// @0EF: aload_2
		// @0F0: ifnull @0FC
		// @0F3: getstatic java.lang.String[] game.C_100225_ah.field_106137_z
		// @0F6: iconst_3
		// @0F7: aaload
		// @0F8: goto @101
		// @0FB: athrow
		// @0FC: getstatic java.lang.String[] game.C_100225_ah.field_106137_z
		// @0FF: iconst_4
		// @100: aaload
		// @101: invokevirtual java.lang.StringBuilder.append(java.lang.String)java.lang.StringBuilder
		// @104: bipush 44 (0x2C)
		// @106: invokevirtual java.lang.StringBuilder.append(char)java.lang.StringBuilder
		// @109: aload_3
		// @10A: ifnull @116
		// @10D: getstatic java.lang.String[] game.C_100225_ah.field_106137_z
		// @110: iconst_3
		// @111: aaload
		// @112: goto @11B
		// @115: athrow
		// @116: getstatic java.lang.String[] game.C_100225_ah.field_106137_z
		// @119: iconst_4
		// @11A: aaload
		// @11B: invokevirtual java.lang.StringBuilder.append(java.lang.String)java.lang.StringBuilder
		// @11E: bipush 44 (0x2C)
		// @120: invokevirtual java.lang.StringBuilder.append(char)java.lang.StringBuilder
		// @123: iload #4
		// @125: invokevirtual java.lang.StringBuilder.append(int)java.lang.StringBuilder
		// @128: bipush 44 (0x2C)
		// @12A: invokevirtual java.lang.StringBuilder.append(char)java.lang.StringBuilder
		// @12D: iload #5
		// @12F: invokevirtual java.lang.StringBuilder.append(int)java.lang.StringBuilder
		// @132: bipush 44 (0x2C)
		// @134: invokevirtual java.lang.StringBuilder.append(char)java.lang.StringBuilder
		// @137: iload #6
		// @139: invokevirtual java.lang.StringBuilder.append(int)java.lang.StringBuilder
		// @13C: bipush 41 (0x29)
		// @13E: invokevirtual java.lang.StringBuilder.append(char)java.lang.StringBuilder
		// @141: invokevirtual java.lang.StringBuilder.toString()java.lang.String
		// @144: invokestatic game.C_100181_cf.func_105695_a(java.lang.Throwable, java.lang.String)game.C_100170_cm
		// @147: athrow
		// @148: return
	}
	
	final void func_106110_a(byte arg0, C_100225_ah arg1)
	{
		// @00: aload_2
		// @01: aload_0
		// @02: getfield game.C_100037_wb game.C_100225_ah.field_106128_l
		// @05: putfield game.C_100037_wb game.C_100225_ah.field_106128_l
		// @08: aload_2
		// @09: aload_0
		// @0A: getfield int game.C_100225_ah.field_106135_q
		// @0D: putfield int game.C_100225_ah.field_106135_q
		// @10: aload_2
		// @11: aload_0
		// @12: getfield int game.C_100225_ah.field_106127_o
		// @15: putfield int game.C_100225_ah.field_106127_o
		// @18: aload_2
		// @19: aload_0
		// @1A: getfield int game.C_100225_ah.field_106120_g
		// @1D: putfield int game.C_100225_ah.field_106120_g
		// @20: aload_2
		// @21: aload_0
		// @22: getfield boolean game.C_100225_ah.field_106130_j
		// @25: putfield boolean game.C_100225_ah.field_106130_j
		// @28: aload_2
		// @29: aload_0
		// @2A: getfield int game.C_100225_ah.field_106119_f
		// @2D: putfield int game.C_100225_ah.field_106119_f
		// @30: aload_2
		// @31: aload_0
		// @32: getfield int game.C_100225_ah.field_106132_h
		// @35: putfield int game.C_100225_ah.field_106132_h
		// @38: aload_2
		// @39: aload_0
		// @3A: getfield game.C_100037_wb[] game.C_100225_ah.field_106124_c
		// @3D: putfield game.C_100037_wb[] game.C_100225_ah.field_106124_c
		// @40: iload_1
		// @41: bipush -93 (0xA3)
		// @43: if_icmpeq @50
		// @46: aconst_null
		// @47: checkcast game.C_100327_ib
		// @4A: bipush -84 (0xAC)
		// @4C: invokestatic game.C_100225_ah.func_106114_a(game.C_100327_ib, int)java.lang.String
		// @4F: pop
		// @50: goto @8F
		// @53: astore_3
		// @54: aload_3
		// @55: new java.lang.StringBuilder
		// @58: dup
		// @59: invokespecial java.lang.StringBuilder.<init>()void
		// @5C: getstatic java.lang.String[] game.C_100225_ah.field_106137_z
		// @5F: bipush 12 (0x0C)
		// @61: aaload
		// @62: invokevirtual java.lang.StringBuilder.append(java.lang.String)java.lang.StringBuilder
		// @65: iload_1
		// @66: invokevirtual java.lang.StringBuilder.append(int)java.lang.StringBuilder
		// @69: bipush 44 (0x2C)
		// @6B: invokevirtual java.lang.StringBuilder.append(char)java.lang.StringBuilder
		// @6E: aload_2
		// @6F: ifnull @7B
		// @72: getstatic java.lang.String[] game.C_100225_ah.field_106137_z
		// @75: iconst_3
		// @76: aaload
		// @77: goto @80
		// @7A: athrow
		// @7B: getstatic java.lang.String[] game.C_100225_ah.field_106137_z
		// @7E: iconst_4
		// @7F: aaload
		// @80: invokevirtual java.lang.StringBuilder.append(java.lang.String)java.lang.StringBuilder
		// @83: bipush 41 (0x29)
		// @85: invokevirtual java.lang.StringBuilder.append(char)java.lang.StringBuilder
		// @88: invokevirtual java.lang.StringBuilder.toString()java.lang.String
		// @8B: invokestatic game.C_100181_cf.func_105695_a(java.lang.Throwable, java.lang.String)game.C_100170_cm
		// @8E: athrow
		// @8F: return
	}
	
	final C_100225_ah func_106104_a(C_100037_wb[] arg0, int arg1)
	{
		// @00: aload_0
		// @01: aload_1
		// @02: putfield game.C_100037_wb[] game.C_100225_ah.field_106124_c
		// @05: iload_2
		// @06: bipush -64 (0xC0)
		// @08: if_icmple @14
		// @0B: bipush 70 (0x46)
		// @0D: invokestatic game.C_100225_ah.func_106105_b(int)void
		// @10: goto @14
		// @13: athrow
		// @14: aload_0
		// @15: areturn
		// @16: astore_3
		// @17: aload_3
		// @18: new java.lang.StringBuilder
		// @1B: dup
		// @1C: invokespecial java.lang.StringBuilder.<init>()void
		// @1F: getstatic java.lang.String[] game.C_100225_ah.field_106137_z
		// @22: bipush 9 (0x09)
		// @24: aaload
		// @25: invokevirtual java.lang.StringBuilder.append(java.lang.String)java.lang.StringBuilder
		// @28: aload_1
		// @29: ifnull @35
		// @2C: getstatic java.lang.String[] game.C_100225_ah.field_106137_z
		// @2F: iconst_3
		// @30: aaload
		// @31: goto @3A
		// @34: athrow
		// @35: getstatic java.lang.String[] game.C_100225_ah.field_106137_z
		// @38: iconst_4
		// @39: aaload
		// @3A: invokevirtual java.lang.StringBuilder.append(java.lang.String)java.lang.StringBuilder
		// @3D: bipush 44 (0x2C)
		// @3F: invokevirtual java.lang.StringBuilder.append(char)java.lang.StringBuilder
		// @42: iload_2
		// @43: invokevirtual java.lang.StringBuilder.append(int)java.lang.StringBuilder
		// @46: bipush 41 (0x29)
		// @48: invokevirtual java.lang.StringBuilder.append(char)java.lang.StringBuilder
		// @4B: invokevirtual java.lang.StringBuilder.toString()java.lang.String
		// @4E: invokestatic game.C_100181_cf.func_105695_a(java.lang.Throwable, java.lang.String)game.C_100170_cm
		// @51: athrow
	}
	
	static final void func_106106_a(int arg0)
	{
		// @00: iload_0
		// @01: bipush -2 (0xFE)
		// @03: if_icmpeq @0A
		// @06: iconst_3
		// @07: invokestatic game.C_100225_ah.func_106106_a(int)void
		// @0A: goto @2E
		// @0D: astore_1
		// @0E: aload_1
		// @0F: new java.lang.StringBuilder
		// @12: dup
		// @13: invokespecial java.lang.StringBuilder.<init>()void
		// @16: getstatic java.lang.String[] game.C_100225_ah.field_106137_z
		// @19: iconst_1
		// @1A: aaload
		// @1B: invokevirtual java.lang.StringBuilder.append(java.lang.String)java.lang.StringBuilder
		// @1E: iload_0
		// @1F: invokevirtual java.lang.StringBuilder.append(int)java.lang.StringBuilder
		// @22: bipush 41 (0x29)
		// @24: invokevirtual java.lang.StringBuilder.append(char)java.lang.StringBuilder
		// @27: invokevirtual java.lang.StringBuilder.toString()java.lang.String
		// @2A: invokestatic game.C_100181_cf.func_105695_a(java.lang.Throwable, java.lang.String)game.C_100170_cm
		// @2D: athrow
		// @2E: return
	}
	
	final void func_106115_c(int arg0)
	{
		// @00: aload_0
		// @01: iconst_m1
		// @02: putfield int game.C_100225_ah.field_106119_f
		// @05: aload_0
		// @06: aconst_null
		// @07: putfield game.C_100037_wb game.C_100225_ah.field_106128_l
		// @0A: aload_0
		// @0B: iconst_0
		// @0C: putfield int game.C_100225_ah.field_106132_h
		// @0F: aload_0
		// @10: aconst_null
		// @11: putfield game.C_100037_wb[] game.C_100225_ah.field_106124_c
		// @14: aload_0
		// @15: sipush 256 (0x0100)
		// @18: putfield int game.C_100225_ah.field_106135_q
		// @1B: iload_1
		// @1C: sipush 26632 (0x6808)
		// @1F: if_icmpeq @2C
		// @22: aload_0
		// @23: bipush -68 (0xBC)
		// @25: invokevirtual game.C_100225_ah.func_106115_c(int)void
		// @28: goto @2C
		// @2B: athrow
		// @2C: aload_0
		// @2D: iconst_0
		// @2E: putfield int game.C_100225_ah.field_106120_g
		// @31: aload_0
		// @32: iconst_0
		// @33: putfield int game.C_100225_ah.field_106127_o
		// @36: goto @5B
		// @39: astore_2
		// @3A: aload_2
		// @3B: new java.lang.StringBuilder
		// @3E: dup
		// @3F: invokespecial java.lang.StringBuilder.<init>()void
		// @42: getstatic java.lang.String[] game.C_100225_ah.field_106137_z
		// @45: bipush 10 (0x0A)
		// @47: aaload
		// @48: invokevirtual java.lang.StringBuilder.append(java.lang.String)java.lang.StringBuilder
		// @4B: iload_1
		// @4C: invokevirtual java.lang.StringBuilder.append(int)java.lang.StringBuilder
		// @4F: bipush 41 (0x29)
		// @51: invokevirtual java.lang.StringBuilder.append(char)java.lang.StringBuilder
		// @54: invokevirtual java.lang.StringBuilder.toString()java.lang.String
		// @57: invokestatic game.C_100181_cf.func_105695_a(java.lang.Throwable, java.lang.String)game.C_100170_cm
		// @5A: athrow
		// @5B: return
	}
	
	final C_100225_ah func_106113_a(int arg0, int arg1)
	{
		// @00: iload_1
		// @01: bipush -102 (0x9A)
		// @03: if_icmplt @10
		// @06: aload_0
		// @07: bipush -126 (0x82)
		// @09: putfield int game.C_100225_ah.field_106135_q
		// @0C: goto @10
		// @0F: athrow
		// @10: aload_0
		// @11: iload_2
		// @12: putfield int game.C_100225_ah.field_106132_h
		// @15: aload_0
		// @16: areturn
		// @17: astore_3
		// @18: aload_3
		// @19: new java.lang.StringBuilder
		// @1C: dup
		// @1D: invokespecial java.lang.StringBuilder.<init>()void
		// @20: getstatic java.lang.String[] game.C_100225_ah.field_106137_z
		// @23: iconst_0
		// @24: aaload
		// @25: invokevirtual java.lang.StringBuilder.append(java.lang.String)java.lang.StringBuilder
		// @28: iload_1
		// @29: invokevirtual java.lang.StringBuilder.append(int)java.lang.StringBuilder
		// @2C: bipush 44 (0x2C)
		// @2E: invokevirtual java.lang.StringBuilder.append(char)java.lang.StringBuilder
		// @31: iload_2
		// @32: invokevirtual java.lang.StringBuilder.append(int)java.lang.StringBuilder
		// @35: bipush 41 (0x29)
		// @37: invokevirtual java.lang.StringBuilder.append(char)java.lang.StringBuilder
		// @3A: invokevirtual java.lang.StringBuilder.toString()java.lang.String
		// @3D: invokestatic game.C_100181_cf.func_105695_a(java.lang.Throwable, java.lang.String)game.C_100170_cm
		// @40: athrow
	}
	
	final C_100225_ah func_106111_b(int arg0, int arg1)
	{
		// @00: aload_0
		// @01: iload_2
		// @02: putfield int game.C_100225_ah.field_106119_f
		// @05: iload_1
		// @06: bipush -2 (0xFE)
		// @08: if_icmpeq @18
		// @0B: aload_0
		// @0C: bipush 83 (0x53)
		// @0E: bipush -74 (0xB6)
		// @10: invokevirtual game.C_100225_ah.func_106116_d(int, int)game.C_100225_ah
		// @13: pop
		// @14: goto @18
		// @17: athrow
		// @18: aload_0
		// @19: areturn
		// @1A: astore_3
		// @1B: aload_3
		// @1C: new java.lang.StringBuilder
		// @1F: dup
		// @20: invokespecial java.lang.StringBuilder.<init>()void
		// @23: getstatic java.lang.String[] game.C_100225_ah.field_106137_z
		// @26: bipush 14 (0x0E)
		// @28: aaload
		// @29: invokevirtual java.lang.StringBuilder.append(java.lang.String)java.lang.StringBuilder
		// @2C: iload_1
		// @2D: invokevirtual java.lang.StringBuilder.append(int)java.lang.StringBuilder
		// @30: bipush 44 (0x2C)
		// @32: invokevirtual java.lang.StringBuilder.append(char)java.lang.StringBuilder
		// @35: iload_2
		// @36: invokevirtual java.lang.StringBuilder.append(int)java.lang.StringBuilder
		// @39: bipush 41 (0x29)
		// @3B: invokevirtual java.lang.StringBuilder.append(char)java.lang.StringBuilder
		// @3E: invokevirtual java.lang.StringBuilder.toString()java.lang.String
		// @41: invokestatic game.C_100181_cf.func_105695_a(java.lang.Throwable, java.lang.String)game.C_100170_cm
		// @44: athrow
	}
	
	final C_100225_ah func_106116_d(int arg0, int arg1)
	{
		// @00: iload_2
		// @01: sipush -19529 (0xB3B7)
		// @04: if_icmpeq @11
		// @07: aload_0
		// @08: bipush 48 (0x30)
		// @0A: invokevirtual game.C_100225_ah.func_106115_c(int)void
		// @0D: goto @11
		// @10: athrow
		// @11: aload_0
		// @12: iload_1
		// @13: putfield int game.C_100225_ah.field_106120_g
		// @16: aload_0
		// @17: areturn
		// @18: astore_3
		// @19: aload_3
		// @1A: new java.lang.StringBuilder
		// @1D: dup
		// @1E: invokespecial java.lang.StringBuilder.<init>()void
		// @21: getstatic java.lang.String[] game.C_100225_ah.field_106137_z
		// @24: bipush 13 (0x0D)
		// @26: aaload
		// @27: invokevirtual java.lang.StringBuilder.append(java.lang.String)java.lang.StringBuilder
		// @2A: iload_1
		// @2B: invokevirtual java.lang.StringBuilder.append(int)java.lang.StringBuilder
		// @2E: bipush 44 (0x2C)
		// @30: invokevirtual java.lang.StringBuilder.append(char)java.lang.StringBuilder
		// @33: iload_2
		// @34: invokevirtual java.lang.StringBuilder.append(int)java.lang.StringBuilder
		// @37: bipush 41 (0x29)
		// @39: invokevirtual java.lang.StringBuilder.append(char)java.lang.StringBuilder
		// @3C: invokevirtual java.lang.StringBuilder.toString()java.lang.String
		// @3F: invokestatic game.C_100181_cf.func_105695_a(java.lang.Throwable, java.lang.String)game.C_100170_cm
		// @42: athrow
	}
	
	final void func_106109_a(int arg0, int arg1, C_100336_im arg2, C_100139_tb arg3, int arg4)
	{
		// @000: iconst_m1
		// @001: aload_3
		// @002: getfield int game.C_100336_im.field_102537_l
		// @005: aload_0
		// @006: getfield game.C_100037_wb[] game.C_100225_ah.field_106124_c
		// @009: aload_3
		// @00A: getfield int game.C_100336_im.field_102538_m
		// @00D: iload_2
		// @00E: iadd
		// @00F: aload_3
		// @010: getfield int game.C_100336_im.field_102544_t
		// @013: aload_3
		// @014: getfield int game.C_100336_im.field_102541_w
		// @017: iload #5
		// @019: iadd
		// @01A: invokestatic game.C_100100_i.func_102009_a(int, int, game.C_100037_wb[], int, int, int)void
		// @01D: aconst_null
		// @01E: aload_0
		// @01F: getfield game.C_100037_wb game.C_100225_ah.field_106128_l
		// @022: if_acmpeq @0C7
		// @025: aload_0
		// @026: getfield int game.C_100225_ah.field_106120_g
		// @029: aload_3
		// @02A: getfield int game.C_100336_im.field_102538_m
		// @02D: iload_2
		// @02E: iadd
		// @02F: iadd
		// @030: istore #6
		// @032: aload_3
		// @033: getfield int game.C_100336_im.field_102541_w
		// @036: iload #5
		// @038: iadd
		// @039: aload_0
		// @03A: getfield int game.C_100225_ah.field_106127_o
		// @03D: iadd
		// @03E: istore #7
		// @040: aload #4
		// @042: getfield int game.C_100139_tb.field_100468_o
		// @045: iconst_m1
		// @046: ixor
		// @047: bipush -2 (0xFE)
		// @049: if_icmpne @05F
		// @04C: iload #6
		// @04E: aload_3
		// @04F: getfield int game.C_100336_im.field_102537_l
		// @052: aload_0
		// @053: getfield game.C_100037_wb game.C_100225_ah.field_106128_l
		// @056: getfield int game.C_100037_wb.field_102341_y
		// @059: isub
		// @05A: iconst_2
		// @05B: idiv
		// @05C: iadd
		// @05D: istore #6
		// @05F: aload #4
		// @061: getfield int game.C_100139_tb.field_100480_p
		// @064: iconst_m1
		// @065: ixor
		// @066: bipush -2 (0xFE)
		// @068: if_icmpeq @06F
		// @06B: goto @083
		// @06E: athrow
		// @06F: iload #7
		// @071: aload_3
		// @072: getfield int game.C_100336_im.field_102544_t
		// @075: aload_0
		// @076: getfield game.C_100037_wb game.C_100225_ah.field_106128_l
		// @079: getfield int game.C_100037_wb.field_102340_z
		// @07C: ineg
		// @07D: iadd
		// @07E: iconst_2
		// @07F: idiv
		// @080: iadd
		// @081: istore #7
		// @083: aload #4
		// @085: getfield int game.C_100139_tb.field_100468_o
		// @088: iconst_2
		// @089: if_icmpne @09E
		// @08C: iload #6
		// @08E: aload_3
		// @08F: getfield int game.C_100336_im.field_102537_l
		// @092: aload_0
		// @093: getfield game.C_100037_wb game.C_100225_ah.field_106128_l
		// @096: getfield int game.C_100037_wb.field_102341_y
		// @099: ineg
		// @09A: iadd
		// @09B: iadd
		// @09C: istore #6
		// @09E: aload #4
		// @0A0: getfield int game.C_100139_tb.field_100480_p
		// @0A3: iconst_2
		// @0A4: if_icmpeq @0AB
		// @0A7: goto @0BC
		// @0AA: athrow
		// @0AB: iload #7
		// @0AD: aload_3
		// @0AE: getfield int game.C_100336_im.field_102544_t
		// @0B1: aload_0
		// @0B2: getfield game.C_100037_wb game.C_100225_ah.field_106128_l
		// @0B5: getfield int game.C_100037_wb.field_102340_z
		// @0B8: isub
		// @0B9: iadd
		// @0BA: istore #7
		// @0BC: aload_0
		// @0BD: getfield game.C_100037_wb game.C_100225_ah.field_106128_l
		// @0C0: iload #6
		// @0C2: iload #7
		// @0C4: invokevirtual game.C_100037_wb.func_102353_h(int, int)void
		// @0C7: aload #4
		// @0C9: aload_3
		// @0CA: iconst_0
		// @0CB: invokevirtual game.C_100139_tb.func_100450_a(game.C_100336_im, boolean)java.lang.String
		// @0CE: astore #6
		// @0D0: aload #6
		// @0D2: ifnull @18E
		// @0D5: aload #4
		// @0D7: getfield game.C_100112_r game.C_100139_tb.field_100460_f
		// @0DA: ifnull @18E
		// @0DD: goto @0E1
		// @0E0: athrow
		// @0E1: iconst_m1
		// @0E2: aload_0
		// @0E3: getfield int game.C_100225_ah.field_106132_h
		// @0E6: iconst_m1
		// @0E7: ixor
		// @0E8: if_icmpge @0F3
		// @0EB: goto @0EF
		// @0EE: athrow
		// @0EF: goto @18E
		// @0F2: athrow
		// @0F3: aload #4
		// @0F5: getfield game.C_100112_r game.C_100139_tb.field_100460_f
		// @0F8: aload #6
		// @0FA: ldc -2147483648 (0x80000000)
		// @0FC: aload_0
		// @0FD: getfield int game.C_100225_ah.field_106120_g
		// @100: if_icmpne @108
		// @103: iconst_0
		// @104: goto @10C
		// @107: athrow
		// @108: aload_0
		// @109: getfield int game.C_100225_ah.field_106120_g
		// @10C: aload #4
		// @10E: getfield int game.C_100139_tb.field_100465_c
		// @111: aload_3
		// @112: getfield int game.C_100336_im.field_102538_m
		// @115: iadd
		// @116: iadd
		// @117: iload_2
		// @118: iadd
		// @119: aload #4
		// @11B: getfield int game.C_100139_tb.field_100464_b
		// @11E: aload_3
		// @11F: getfield int game.C_100336_im.field_102541_w
		// @122: iload #5
		// @124: aload_0
		// @125: getfield int game.C_100225_ah.field_106127_o
		// @128: ldc -2147483648 (0x80000000)
		// @12A: if_icmpeq @135
		// @12D: aload_0
		// @12E: getfield int game.C_100225_ah.field_106127_o
		// @131: goto @136
		// @134: athrow
		// @135: iconst_0
		// @136: iadd
		// @137: iadd
		// @138: iadd
		// @139: aload #4
		// @13B: getfield int game.C_100139_tb.field_100472_k
		// @13E: ineg
		// @13F: aload #4
		// @141: getfield int game.C_100139_tb.field_100465_c
		// @144: ineg
		// @145: iadd
		// @146: aload_3
		// @147: getfield int game.C_100336_im.field_102537_l
		// @14A: iadd
		// @14B: aload #4
		// @14D: getfield int game.C_100139_tb.field_100474_i
		// @150: ineg
		// @151: aload #4
		// @153: getfield int game.C_100139_tb.field_100464_b
		// @156: ineg
		// @157: aload_3
		// @158: getfield int game.C_100336_im.field_102544_t
		// @15B: iadd
		// @15C: iadd
		// @15D: aload_0
		// @15E: getfield int game.C_100225_ah.field_106132_h
		// @161: aload_0
		// @162: getfield int game.C_100225_ah.field_106119_f
		// @165: ldc 2147483647 (0x7fffffff)
		// @167: aload_0
		// @168: getfield int game.C_100225_ah.field_106135_q
		// @16B: iconst_m1
		// @16C: ixor
		// @16D: if_icmpne @177
		// @170: sipush 256 (0x0100)
		// @173: goto @17B
		// @176: athrow
		// @177: aload_0
		// @178: getfield int game.C_100225_ah.field_106135_q
		// @17B: aload #4
		// @17D: getfield int game.C_100139_tb.field_100468_o
		// @180: aload #4
		// @182: getfield int game.C_100139_tb.field_100480_p
		// @185: aload #4
		// @187: getfield int game.C_100139_tb.field_100463_e
		// @18A: invokevirtual game.C_100112_r.func_101745_a(java.lang.String, int, int, int, int, int, int, int, int, int, int)int
		// @18D: pop
		// @18E: bipush 79 (0x4F)
		// @190: bipush 48 (0x30)
		// @192: iload_1
		// @193: isub
		// @194: bipush 53 (0x35)
		// @196: idiv
		// @197: irem
		// @198: istore #7
		// @19A: goto @208
		// @19D: astore #6
		// @19F: aload #6
		// @1A1: new java.lang.StringBuilder
		// @1A4: dup
		// @1A5: invokespecial java.lang.StringBuilder.<init>()void
		// @1A8: getstatic java.lang.String[] game.C_100225_ah.field_106137_z
		// @1AB: iconst_5
		// @1AC: aaload
		// @1AD: invokevirtual java.lang.StringBuilder.append(java.lang.String)java.lang.StringBuilder
		// @1B0: iload_1
		// @1B1: invokevirtual java.lang.StringBuilder.append(int)java.lang.StringBuilder
		// @1B4: bipush 44 (0x2C)
		// @1B6: invokevirtual java.lang.StringBuilder.append(char)java.lang.StringBuilder
		// @1B9: iload_2
		// @1BA: invokevirtual java.lang.StringBuilder.append(int)java.lang.StringBuilder
		// @1BD: bipush 44 (0x2C)
		// @1BF: invokevirtual java.lang.StringBuilder.append(char)java.lang.StringBuilder
		// @1C2: aload_3
		// @1C3: ifnull @1CF
		// @1C6: getstatic java.lang.String[] game.C_100225_ah.field_106137_z
		// @1C9: iconst_3
		// @1CA: aaload
		// @1CB: goto @1D4
		// @1CE: athrow
		// @1CF: getstatic java.lang.String[] game.C_100225_ah.field_106137_z
		// @1D2: iconst_4
		// @1D3: aaload
		// @1D4: invokevirtual java.lang.StringBuilder.append(java.lang.String)java.lang.StringBuilder
		// @1D7: bipush 44 (0x2C)
		// @1D9: invokevirtual java.lang.StringBuilder.append(char)java.lang.StringBuilder
		// @1DC: aload #4
		// @1DE: ifnull @1EA
		// @1E1: getstatic java.lang.String[] game.C_100225_ah.field_106137_z
		// @1E4: iconst_3
		// @1E5: aaload
		// @1E6: goto @1EF
		// @1E9: athrow
		// @1EA: getstatic java.lang.String[] game.C_100225_ah.field_106137_z
		// @1ED: iconst_4
		// @1EE: aaload
		// @1EF: invokevirtual java.lang.StringBuilder.append(java.lang.String)java.lang.StringBuilder
		// @1F2: bipush 44 (0x2C)
		// @1F4: invokevirtual java.lang.StringBuilder.append(char)java.lang.StringBuilder
		// @1F7: iload #5
		// @1F9: invokevirtual java.lang.StringBuilder.append(int)java.lang.StringBuilder
		// @1FC: bipush 41 (0x29)
		// @1FE: invokevirtual java.lang.StringBuilder.append(char)java.lang.StringBuilder
		// @201: invokevirtual java.lang.StringBuilder.toString()java.lang.String
		// @204: invokestatic game.C_100181_cf.func_105695_a(java.lang.Throwable, java.lang.String)game.C_100170_cm
		// @207: athrow
		// @208: return
	}
	
	static final String func_106114_a(C_100327_ib arg0, int arg1)
	{
		// @000: getstatic int game.SteelSentinels.field_105275_O
		// @003: istore #10
		// @005: bipush 16 (0x10)
		// @007: newarray int[]
		// @009: astore_2
		// @00A: bipush 44 (0x2C)
		// @00C: aload_2
		// @00D: aload_0
		// @00E: iconst_0
		// @00F: invokestatic game.C_100256_pk.func_100448_a(byte, int[], game.C_100327_ib, int)int
		// @012: istore_3
		// @013: bipush -51 (0xCD)
		// @015: aload_0
		// @016: getfield int game.C_100327_ib.field_102494_P
		// @019: invokestatic game.C_100073_f.func_101710_a(byte, int)int
		// @01C: istore #4
		// @01E: iconst_0
		// @01F: iload #4
		// @021: if_icmple @029
		// @024: aconst_null
		// @025: goto @030
		// @028: athrow
		// @029: iload #4
		// @02B: bipush 85 (0x55)
		// @02D: invokestatic game.C_100209_qb.func_102686_b(int, byte)game.C_100327_ib
		// @030: astore #5
		// @032: aload #5
		// @034: ifnull @041
		// @037: bipush 126 (0x7E)
		// @039: aload_2
		// @03A: aload #5
		// @03C: iload_3
		// @03D: invokestatic game.C_100256_pk.func_100448_a(byte, int[], game.C_100327_ib, int)int
		// @040: istore_3
		// @041: iconst_0
		// @042: istore #6
		// @044: iload_3
		// @045: iconst_1
		// @046: isub
		// @047: iconst_m1
		// @048: ixor
		// @049: iload #6
		// @04B: iconst_m1
		// @04C: ixor
		// @04D: if_icmpge @0AF
		// @050: iload #6
		// @052: istore #7
		// @054: iload #6
		// @056: iconst_m1
		// @057: isub
		// @058: istore #8
		// @05A: iload_3
		// @05B: iconst_m1
		// @05C: ixor
		// @05D: iload #8
		// @05F: iconst_m1
		// @060: ixor
		// @061: if_icmpge @088
		// @064: aload_2
		// @065: iload #8
		// @067: iaload
		// @068: iconst_m1
		// @069: ixor
		// @06A: aload_2
		// @06B: iload #7
		// @06D: iaload
		// @06E: iconst_m1
		// @06F: ixor
		// @070: iload #10
		// @072: ifne @090
		// @075: if_icmple @080
		// @078: goto @07C
		// @07B: athrow
		// @07C: iload #8
		// @07E: istore #7
		// @080: iinc #8 +1
		// @083: iload #10
		// @085: ifeq @05A
		// @088: iload #7
		// @08A: iconst_m1
		// @08B: ixor
		// @08C: iload #6
		// @08E: iconst_m1
		// @08F: ixor
		// @090: if_icmpeq @0A7
		// @093: aload_2
		// @094: iload #6
		// @096: iaload
		// @097: istore #8
		// @099: aload_2
		// @09A: iload #6
		// @09C: aload_2
		// @09D: iload #7
		// @09F: iaload
		// @0A0: iastore
		// @0A1: aload_2
		// @0A2: iload #7
		// @0A4: iload #8
		// @0A6: iastore
		// @0A7: iinc #6 +1
		// @0AA: iload #10
		// @0AC: ifeq @044
		// @0AF: aconst_null
		// @0B0: astore #6
		// @0B2: iconst_0
		// @0B3: istore #7
		// @0B5: iload #7
		// @0B7: iconst_m1
		// @0B8: ixor
		// @0B9: iload_3
		// @0BA: iconst_m1
		// @0BB: ixor
		// @0BC: if_icmple @161
		// @0BF: iconst_1
		// @0C0: iload #10
		// @0C2: ifne @162
		// @0C5: istore #8
		// @0C7: iload_3
		// @0C8: iconst_m1
		// @0C9: ixor
		// @0CA: iload #7
		// @0CC: iload #8
		// @0CE: ineg
		// @0CF: isub
		// @0D0: iconst_m1
		// @0D1: ixor
		// @0D2: if_icmpge @0F9
		// @0D5: aload_2
		// @0D6: iload #7
		// @0D8: iload #8
		// @0DA: ineg
		// @0DB: isub
		// @0DC: iaload
		// @0DD: aload_2
		// @0DE: iload #7
		// @0E0: iaload
		// @0E1: iload #10
		// @0E3: ifne @0FE
		// @0E6: if_icmpne @0F9
		// @0E9: goto @0ED
		// @0EC: athrow
		// @0ED: iinc #8 +1
		// @0F0: iload #10
		// @0F2: ifeq @0C7
		// @0F5: goto @0F9
		// @0F8: athrow
		// @0F9: aload_2
		// @0FA: iload #7
		// @0FC: iaload
		// @0FD: iconst_0
		// @0FE: invokestatic game.C_100055_ed.func_104238_a(int, int)java.lang.String
		// @101: astore #9
		// @103: aconst_null
		// @104: aload #9
		// @106: if_acmpne @10D
		// @109: goto @155
		// @10C: athrow
		// @10D: aconst_null
		// @10E: aload #6
		// @110: if_acmpeq @139
		// @113: sipush -30945 (0x871F)
		// @116: iconst_3
		// @117: anewarray java.lang.String
		// @11A: dup
		// @11B: iconst_0
		// @11C: aload #6
		// @11E: aastore
		// @11F: dup
		// @120: iconst_1
		// @121: iload #8
		// @123: invokestatic java.lang.Integer.toString(int)java.lang.String
		// @126: aastore
		// @127: dup
		// @128: iconst_2
		// @129: aload #9
		// @12B: aastore
		// @12C: getstatic java.lang.String game.C_100212_qc.field_105973_g
		// @12F: invokestatic game.C_100132_td.func_104965_a(int, java.lang.String[], java.lang.String)java.lang.String
		// @132: astore #6
		// @134: iload #10
		// @136: ifeq @155
		// @139: sipush -30945 (0x871F)
		// @13C: iconst_2
		// @13D: anewarray java.lang.String
		// @140: dup
		// @141: iconst_0
		// @142: iload #8
		// @144: invokestatic java.lang.Integer.toString(int)java.lang.String
		// @147: aastore
		// @148: dup
		// @149: iconst_1
		// @14A: aload #9
		// @14C: aastore
		// @14D: getstatic java.lang.String game.C_100346_ja.field_103489_w
		// @150: invokestatic game.C_100132_td.func_104965_a(int, java.lang.String[], java.lang.String)java.lang.String
		// @153: astore #6
		// @155: iload #7
		// @157: iload #8
		// @159: iadd
		// @15A: istore #7
		// @15C: iload #10
		// @15E: ifeq @0B5
		// @161: iload_1
		// @162: bipush 38 (0x26)
		// @164: if_icmpgt @16C
		// @167: aconst_null
		// @168: checkcast java.lang.String
		// @16B: areturn
		// @16C: aload #6
		// @16E: areturn
		// @16F: astore_2
		// @170: aload_2
		// @171: new java.lang.StringBuilder
		// @174: dup
		// @175: invokespecial java.lang.StringBuilder.<init>()void
		// @178: getstatic java.lang.String[] game.C_100225_ah.field_106137_z
		// @17B: bipush 6 (0x06)
		// @17D: aaload
		// @17E: invokevirtual java.lang.StringBuilder.append(java.lang.String)java.lang.StringBuilder
		// @181: aload_0
		// @182: ifnull @18E
		// @185: getstatic java.lang.String[] game.C_100225_ah.field_106137_z
		// @188: iconst_3
		// @189: aaload
		// @18A: goto @193
		// @18D: athrow
		// @18E: getstatic java.lang.String[] game.C_100225_ah.field_106137_z
		// @191: iconst_4
		// @192: aaload
		// @193: invokevirtual java.lang.StringBuilder.append(java.lang.String)java.lang.StringBuilder
		// @196: bipush 44 (0x2C)
		// @198: invokevirtual java.lang.StringBuilder.append(char)java.lang.StringBuilder
		// @19B: iload_1
		// @19C: invokevirtual java.lang.StringBuilder.append(int)java.lang.StringBuilder
		// @19F: bipush 41 (0x29)
		// @1A1: invokevirtual java.lang.StringBuilder.append(char)java.lang.StringBuilder
		// @1A4: invokevirtual java.lang.StringBuilder.toString()java.lang.String
		// @1A7: invokestatic game.C_100181_cf.func_105695_a(java.lang.Throwable, java.lang.String)game.C_100170_cm
		// @1AA: athrow
	}
	
	C_100225_ah()
	{
		// @00: aload_0
		// @01: invokespecial java.lang.Object.<init>()void
		// @04: aload_0
		// @05: aconst_null
		// @06: putfield game.C_100037_wb game.C_100225_ah.field_106128_l
		// @09: aload_0
		// @0A: bipush -2 (0xFE)
		// @0C: putfield int game.C_100225_ah.field_106119_f
		// @0F: aload_0
		// @10: aconst_null
		// @11: putfield game.C_100037_wb[] game.C_100225_ah.field_106124_c
		// @14: aload_0
		// @15: iconst_0
		// @16: putfield boolean game.C_100225_ah.field_106130_j
		// @19: aload_0
		// @1A: ldc -2147483648 (0x80000000)
		// @1C: putfield int game.C_100225_ah.field_106127_o
		// @1F: aload_0
		// @20: ldc -2147483648 (0x80000000)
		// @22: putfield int game.C_100225_ah.field_106120_g
		// @25: aload_0
		// @26: ldc -2147483648 (0x80000000)
		// @28: putfield int game.C_100225_ah.field_106135_q
		// @2B: aload_0
		// @2C: bipush -2 (0xFE)
		// @2E: putfield int game.C_100225_ah.field_106132_h
		// @31: return
	}
	
	static
	{
		// @00: bipush 15 (0x0F)
		// @02: anewarray java.lang.String
		// @05: dup
		// @06: iconst_0
		// @07: ldc "\u0010\u0005l=y"
		// @09: invokestatic game.C_100225_ah.func_106108_z(java.lang.String)char[]
		// @0C: invokestatic game.C_100225_ah.func_106107_z(char[])java.lang.String
		// @0F: aastore
		// @10: dup
		// @11: iconst_1
		// @12: ldc "\u0010\u0005l8y"
		// @14: invokestatic game.C_100225_ah.func_106108_z(java.lang.String)char[]
		// @17: invokestatic game.C_100225_ah.func_106107_z(char[])java.lang.String
		// @1A: aastore
		// @1B: dup
		// @1C: iconst_2
		// @1D: ldc "\u0010\u0005l2y"
		// @1F: invokestatic game.C_100225_ah.func_106108_z(java.lang.String)char[]
		// @22: invokestatic game.C_100225_ah.func_106107_z(char[])java.lang.String
		// @25: aastore
		// @26: dup
		// @27: iconst_3
		// @28: ldc "\nClT,"
		// @2A: invokestatic game.C_100225_ah.func_106108_z(java.lang.String)char[]
		// @2D: invokestatic game.C_100225_ah.func_106107_z(char[])java.lang.String
		// @30: aastore
		// @31: dup
		// @32: iconst_4
		// @33: ldc "\u001f\u0018.\u0016"
		// @35: invokestatic game.C_100225_ah.func_106108_z(java.lang.String)char[]
		// @38: invokestatic game.C_100225_ah.func_106107_z(char[])java.lang.String
		// @3B: aastore
		// @3C: dup
		// @3D: iconst_5
		// @3E: ldc "\u0010\u0005l3y"
		// @40: invokestatic game.C_100225_ah.func_106108_z(java.lang.String)char[]
		// @43: invokestatic game.C_100225_ah.func_106107_z(char[])java.lang.String
		// @46: aastore
		// @47: dup
		// @48: bipush 6 (0x06)
		// @4A: ldc "\u0010\u0005l9y"
		// @4C: invokestatic game.C_100225_ah.func_106108_z(java.lang.String)char[]
		// @4F: invokestatic game.C_100225_ah.func_106107_z(char[])java.lang.String
		// @52: aastore
		// @53: dup
		// @54: bipush 7 (0x07)
		// @56: ldc "\u0010\u0005l1y"
		// @58: invokestatic game.C_100225_ah.func_106108_z(java.lang.String)char[]
		// @5B: invokestatic game.C_100225_ah.func_106107_z(char[])java.lang.String
		// @5E: aastore
		// @5F: dup
		// @60: bipush 8 (0x08)
		// @62: ldc "\u0010\u0005l6y"
		// @64: invokestatic game.C_100225_ah.func_106108_z(java.lang.String)char[]
		// @67: invokestatic game.C_100225_ah.func_106107_z(char[])java.lang.String
		// @6A: aastore
		// @6B: dup
		// @6C: bipush 9 (0x09)
		// @6E: ldc "\u0010\u0005l;y"
		// @70: invokestatic game.C_100225_ah.func_106108_z(java.lang.String)char[]
		// @73: invokestatic game.C_100225_ah.func_106107_z(char[])java.lang.String
		// @76: aastore
		// @77: dup
		// @78: bipush 10 (0x0A)
		// @7A: ldc "\u0010\u0005l7y"
		// @7C: invokestatic game.C_100225_ah.func_106108_z(java.lang.String)char[]
		// @7F: invokestatic game.C_100225_ah.func_106107_z(char[])java.lang.String
		// @82: aastore
		// @83: dup
		// @84: bipush 11 (0x0B)
		// @86: ldc "\u0010\u0005l?y"
		// @88: invokestatic game.C_100225_ah.func_106108_z(java.lang.String)char[]
		// @8B: invokestatic game.C_100225_ah.func_106107_z(char[])java.lang.String
		// @8E: aastore
		// @8F: dup
		// @90: bipush 12 (0x0C)
		// @92: ldc "\u0010\u0005l<y"
		// @94: invokestatic game.C_100225_ah.func_106108_z(java.lang.String)char[]
		// @97: invokestatic game.C_100225_ah.func_106107_z(char[])java.lang.String
		// @9A: aastore
		// @9B: dup
		// @9C: bipush 13 (0x0D)
		// @9E: ldc "\u0010\u0005l0y"
		// @A0: invokestatic game.C_100225_ah.func_106108_z(java.lang.String)char[]
		// @A3: invokestatic game.C_100225_ah.func_106107_z(char[])java.lang.String
		// @A6: aastore
		// @A7: dup
		// @A8: bipush 14 (0x0E)
		// @AA: ldc "\u0010\u0005l>y"
		// @AC: invokestatic game.C_100225_ah.func_106108_z(java.lang.String)char[]
		// @AF: invokestatic game.C_100225_ah.func_106107_z(char[])java.lang.String
		// @B2: aastore
		// @B3: putstatic java.lang.String[] game.C_100225_ah.field_106137_z
		// @B6: ldc "(\u00027Z9\u0010\u001b'\u0014v\u0005M'\u0014>\u0004\n*Z\"\u001e\u0001#\u00088\u0005\u0008b\u0019$\u0013\u00081Z%\u001eM'\u00146\u0018\u0003'\u001f#Q\u0019*\u001fqMHrDq\u0010\u0019b\u000e9\u0018\u001eb\u000e8\u001c\u0008lF3\u0003S~\u0018#O(#\u0008?Q\u0000-\u00084Q\u001e-\u00160\u0003\u00046\u001fq\u0012\u0018 \u001f\"Q\u000f;Z!\u001d\u000c;\u0013?\u0016M\u0010\u001b%\u0014\tb\u001d0\u001c\u00081T"
		// @B8: invokestatic game.C_100225_ah.func_106108_z(java.lang.String)char[]
		// @BB: invokestatic game.C_100225_ah.func_106107_z(char[])java.lang.String
		// @BE: putstatic java.lang.String game.C_100225_ah.field_106126_n
		// @C1: ldc "%(\u00012q',\u000e/\u0014KM~_aOMjFt@Sk"
		// @C3: invokestatic game.C_100225_ah.func_106108_z(java.lang.String)char[]
		// @C6: invokestatic game.C_100225_ah.func_106107_z(char[])java.lang.String
		// @C9: putstatic java.lang.String game.C_100225_ah.field_106125_a
		// @CC: ldc "<\"\u0006/\u001d4>"
		// @CE: invokestatic game.C_100225_ah.func_106108_z(java.lang.String)char[]
		// @D1: invokestatic game.C_100225_ah.func_106107_z(char[])java.lang.String
		// @D4: putstatic java.lang.String game.C_100225_ah.field_106123_b
		// @D7: iconst_0
		// @D8: putstatic boolean game.C_100225_ah.field_106133_i
		// @DB: iconst_m1
		// @DC: putstatic int game.C_100225_ah.field_106122_e
		// @DF: ldc "\"\u0005-\rq\u0012\u0005#\u000e"
		// @E1: invokestatic game.C_100225_ah.func_106108_z(java.lang.String)char[]
		// @E4: invokestatic game.C_100225_ah.func_106107_z(char[])java.lang.String
		// @E7: putstatic java.lang.String game.C_100225_ah.field_106121_d
		// @EA: return
	}
	
	private static char[] func_106108_z(String arg0)
	{
		// @00: aload_0
		// @01: invokevirtual java.lang.String.toCharArray()char[]
		// @04: dup
		// @05: arraylength
		// @06: iconst_2
		// @07: if_icmpge @13
		// @0A: dup
		// @0B: iconst_0
		// @0C: dup2
		// @0D: caload
		// @0E: bipush 81 (0x51)
		// @10: ixor
		// @11: i2c
		// @12: castore
		// @13: areturn
	}
	
	private static String func_106107_z(char[] arg0)
	{
		// @00: aload_0
		// @01: dup
		// @02: arraylength
		// @03: swap
		// @04: iconst_0
		// @05: istore_1
		// @06: goto @4C
		// @09: dup
		// @0A: iload_1
		// @0B: dup2
		// @0C: caload
		// @0D: iload_1
		// @0E: iconst_5
		// @0F: irem
		// @10: tableswitch def: @44, for 0: @30, for 1: @35, for 2: @3A, for 3: @3F
		// @30: bipush 113 (0x71)
		// @32: goto @46
		// @35: bipush 109 (0x6D)
		// @37: goto @46
		// @3A: bipush 66 (0x42)
		// @3C: goto @46
		// @3F: bipush 122 (0x7A)
		// @41: goto @46
		// @44: bipush 81 (0x51)
		// @46: ixor
		// @47: i2c
		// @48: castore
		// @49: iinc #1 +1
		// @4C: swap
		// @4D: dup_x1
		// @4E: iload_1
		// @4F: if_icmpgt @09
		// @52: new java.lang.String
		// @55: dup_x1
		// @56: swap
		// @57: invokespecial java.lang.String.<init>(char[])void
		// @5A: invokevirtual java.lang.String.intern()java.lang.String
		// @5D: areturn
	}
}
