package game;

import java.util.Hashtable;

class C_100218_am extends C_100336_im
{
	private boolean field_103119_J;
	static C_100037_wb field_103112_G;
	static String field_103118_I;
	private boolean field_103114_M;
	static int field_103115_N;
	static C_100112_r field_103109_D;
	static C_100037_wb[] field_103110_E;
	static String field_103117_H;
	boolean field_103120_K;
	boolean field_103113_L;
	static String field_103111_F;
	private static final String[] field_103116_O;
	
	final void func_102526_b(boolean arg0)
	{
		// @00: aload_0
		// @01: getfield boolean game.C_100218_am.field_103114_M
		// @04: ifne @0B
		// @07: goto @3E
		// @0A: athrow
		// @0B: aload_0
		// @0C: iconst_0
		// @0D: putfield boolean game.C_100218_am.field_103114_M
		// @10: aconst_null
		// @11: aload_0
		// @12: getfield game.C_100337_in game.C_100218_am.field_102543_u
		// @15: if_acmpeq @3E
		// @18: aload_0
		// @19: getfield game.C_100337_in game.C_100218_am.field_102543_u
		// @1C: instanceof game.C_100088_o
		// @1F: ifne @2A
		// @22: goto @26
		// @25: athrow
		// @26: goto @3E
		// @29: athrow
		// @2A: aload_0
		// @2B: getfield game.C_100337_in game.C_100218_am.field_102543_u
		// @2E: checkcast game.C_100088_o
		// @31: aload_0
		// @32: sipush -22170 (0xA966)
		// @35: aload_0
		// @36: getfield boolean game.C_100218_am.field_103114_M
		// @39: invokeinterface game.C_100088_o.func_102577_a(game.C_100336_im, int, boolean)void
		// @3E: iload_1
		// @3F: ifeq @52
		// @42: aload_0
		// @43: bipush 30 (0x1E)
		// @45: bipush -2 (0xFE)
		// @47: bipush 84 (0x54)
		// @49: bipush 95 (0x5F)
		// @4B: invokevirtual game.C_100218_am.func_103101_a(int, int, int, int)void
		// @4E: goto @52
		// @51: athrow
		// @52: goto @77
		// @55: astore_2
		// @56: aload_2
		// @57: new java.lang.StringBuilder
		// @5A: dup
		// @5B: invokespecial java.lang.StringBuilder.<init>()void
		// @5E: getstatic java.lang.String[] game.C_100218_am.field_103116_O
		// @61: bipush 14 (0x0E)
		// @63: aaload
		// @64: invokevirtual java.lang.StringBuilder.append(java.lang.String)java.lang.StringBuilder
		// @67: iload_1
		// @68: invokevirtual java.lang.StringBuilder.append(boolean)java.lang.StringBuilder
		// @6B: bipush 41 (0x29)
		// @6D: invokevirtual java.lang.StringBuilder.append(char)java.lang.StringBuilder
		// @70: invokevirtual java.lang.StringBuilder.toString()java.lang.String
		// @73: invokestatic game.C_100181_cf.func_105695_a(java.lang.Throwable, java.lang.String)game.C_100170_cm
		// @76: athrow
		// @77: return
	}
	
	static final void func_103106_a(String arg0, int arg1)
	{
		// @000: getstatic int game.C_100010_ff.field_103699_j
		// @003: iconst_1
		// @004: iadd
		// @005: putstatic int game.C_100010_ff.field_103699_j
		// @008: iconst_m1
		// @009: getstatic int game.C_100225_ah.field_106122_e
		// @00C: if_icmpne @02A
		// @00F: iconst_m1
		// @010: getstatic int game.C_100208_qg.field_105964_h
		// @013: if_icmpne @02A
		// @016: goto @01A
		// @019: athrow
		// @01A: getstatic int game.C_100015_wh.field_103781_g
		// @01D: putstatic int game.C_100225_ah.field_106122_e
		// @020: getstatic int game.C_100338_jc.field_105370_l
		// @023: putstatic int game.C_100208_qg.field_105964_h
		// @026: goto @02A
		// @029: athrow
		// @02A: aconst_null
		// @02B: aload_0
		// @02C: if_acmpne @03D
		// @02F: getstatic java.lang.String game.C_100123_uc.field_104922_e
		// @032: ifnonnull @0CA
		// @035: goto @039
		// @038: athrow
		// @039: goto @04B
		// @03C: athrow
		// @03D: aload_0
		// @03E: getstatic java.lang.String game.C_100123_uc.field_104922_e
		// @041: invokevirtual java.lang.String.equals(java.lang.Object)boolean
		// @044: ifeq @04B
		// @047: goto @0CA
		// @04A: athrow
		// @04B: getstatic boolean game.C_100009_fg.field_103662_i
		// @04E: ifne @07C
		// @051: getstatic int game.C_100041_wf.field_104104_d
		// @054: iconst_m1
		// @055: ixor
		// @056: getstatic int game.C_100010_ff.field_103699_j
		// @059: iconst_m1
		// @05A: ixor
		// @05B: if_icmplt @07C
		// @05E: goto @062
		// @061: athrow
		// @062: getstatic int game.C_100041_wf.field_104104_d
		// @065: getstatic int game.C_100012_fh.field_100506_F
		// @068: iadd
		// @069: iconst_m1
		// @06A: ixor
		// @06B: getstatic int game.C_100010_ff.field_103699_j
		// @06E: iconst_m1
		// @06F: ixor
		// @070: if_icmpge @07C
		// @073: goto @077
		// @076: athrow
		// @077: iconst_1
		// @078: goto @07D
		// @07B: athrow
		// @07C: iconst_0
		// @07D: istore_2
		// @07E: aconst_null
		// @07F: aload_0
		// @080: if_acmpeq @09F
		// @083: getstatic boolean game.C_100009_fg.field_103662_i
		// @086: ifne @095
		// @089: goto @08D
		// @08C: athrow
		// @08D: iload_2
		// @08E: ifeq @09F
		// @091: goto @095
		// @094: athrow
		// @095: getstatic int game.C_100041_wf.field_104104_d
		// @098: putstatic int game.C_100010_ff.field_103699_j
		// @09B: goto @0A3
		// @09E: athrow
		// @09F: iconst_0
		// @0A0: putstatic int game.C_100010_ff.field_103699_j
		// @0A3: aload_0
		// @0A4: ifnonnull @0BA
		// @0A7: iload_2
		// @0A8: ifne @0B3
		// @0AB: goto @0AF
		// @0AE: athrow
		// @0AF: goto @0BE
		// @0B2: athrow
		// @0B3: iconst_1
		// @0B4: putstatic boolean game.C_100009_fg.field_103662_i
		// @0B7: goto @0BE
		// @0BA: iconst_0
		// @0BB: putstatic boolean game.C_100009_fg.field_103662_i
		// @0BE: getstatic int game.C_100225_ah.field_106122_e
		// @0C1: putstatic int game.C_100055_ed.field_104244_c
		// @0C4: getstatic int game.C_100208_qg.field_105964_h
		// @0C7: putstatic int game.C_100260_mc.field_102228_Yb
		// @0CA: aload_0
		// @0CB: putstatic java.lang.String game.C_100123_uc.field_104922_e
		// @0CE: getstatic boolean game.C_100009_fg.field_103662_i
		// @0D1: ifne @0FF
		// @0D4: getstatic int game.C_100041_wf.field_104104_d
		// @0D7: getstatic int game.C_100010_ff.field_103699_j
		// @0DA: if_icmple @0FF
		// @0DD: goto @0E1
		// @0E0: athrow
		// @0E1: getstatic boolean game.C_100240_oj.field_106322_j
		// @0E4: ifeq @0FF
		// @0E7: goto @0EB
		// @0EA: athrow
		// @0EB: getstatic int game.C_100225_ah.field_106122_e
		// @0EE: putstatic int game.C_100055_ed.field_104244_c
		// @0F1: getstatic int game.C_100208_qg.field_105964_h
		// @0F4: putstatic int game.C_100260_mc.field_102228_Yb
		// @0F7: iconst_0
		// @0F8: putstatic int game.C_100010_ff.field_103699_j
		// @0FB: goto @0FF
		// @0FE: athrow
		// @0FF: iload_1
		// @100: putstatic int game.C_100225_ah.field_106122_e
		// @103: getstatic boolean game.C_100009_fg.field_103662_i
		// @106: ifeq @126
		// @109: getstatic int game.C_100239_oi.field_102293_E
		// @10C: iconst_m1
		// @10D: ixor
		// @10E: getstatic int game.C_100010_ff.field_103699_j
		// @111: iconst_m1
		// @112: ixor
		// @113: if_icmpeq @11E
		// @116: goto @11A
		// @119: athrow
		// @11A: goto @126
		// @11D: athrow
		// @11E: iconst_0
		// @11F: putstatic int game.C_100010_ff.field_103699_j
		// @122: iconst_0
		// @123: putstatic boolean game.C_100009_fg.field_103662_i
		// @126: iconst_m1
		// @127: putstatic int game.C_100208_qg.field_105964_h
		// @12A: goto @169
		// @12D: astore_2
		// @12E: aload_2
		// @12F: new java.lang.StringBuilder
		// @132: dup
		// @133: invokespecial java.lang.StringBuilder.<init>()void
		// @136: getstatic java.lang.String[] game.C_100218_am.field_103116_O
		// @139: bipush 12 (0x0C)
		// @13B: aaload
		// @13C: invokevirtual java.lang.StringBuilder.append(java.lang.String)java.lang.StringBuilder
		// @13F: aload_0
		// @140: ifnull @14C
		// @143: getstatic java.lang.String[] game.C_100218_am.field_103116_O
		// @146: iconst_2
		// @147: aaload
		// @148: goto @151
		// @14B: athrow
		// @14C: getstatic java.lang.String[] game.C_100218_am.field_103116_O
		// @14F: iconst_1
		// @150: aaload
		// @151: invokevirtual java.lang.StringBuilder.append(java.lang.String)java.lang.StringBuilder
		// @154: bipush 44 (0x2C)
		// @156: invokevirtual java.lang.StringBuilder.append(char)java.lang.StringBuilder
		// @159: iload_1
		// @15A: invokevirtual java.lang.StringBuilder.append(int)java.lang.StringBuilder
		// @15D: bipush 41 (0x29)
		// @15F: invokevirtual java.lang.StringBuilder.append(char)java.lang.StringBuilder
		// @162: invokevirtual java.lang.StringBuilder.toString()java.lang.String
		// @165: invokestatic game.C_100181_cf.func_105695_a(java.lang.Throwable, java.lang.String)game.C_100170_cm
		// @168: athrow
		// @169: return
	}
	
	boolean func_102522_a(int arg0, C_100336_im arg1)
	{
		// @00: aload_0
		// @01: getfield boolean game.C_100218_am.field_103113_L
		// @04: ifeq @16
		// @07: aload_0
		// @08: getfield boolean game.C_100218_am.field_103119_J
		// @0B: ifeq @16
		// @0E: goto @12
		// @11: athrow
		// @12: goto @18
		// @15: athrow
		// @16: iconst_0
		// @17: ireturn
		// @18: aload_2
		// @19: iconst_0
		// @1A: invokevirtual game.C_100336_im.func_102526_b(boolean)void
		// @1D: aload_0
		// @1E: iconst_1
		// @1F: putfield boolean game.C_100218_am.field_103114_M
		// @22: aload_0
		// @23: getfield game.C_100337_in game.C_100218_am.field_102543_u
		// @26: ifnull @4F
		// @29: aload_0
		// @2A: getfield game.C_100337_in game.C_100218_am.field_102543_u
		// @2D: instanceof game.C_100088_o
		// @30: ifne @3B
		// @33: goto @37
		// @36: athrow
		// @37: goto @4F
		// @3A: athrow
		// @3B: aload_0
		// @3C: getfield game.C_100337_in game.C_100218_am.field_102543_u
		// @3F: checkcast game.C_100088_o
		// @42: aload_0
		// @43: sipush -22170 (0xA966)
		// @46: aload_0
		// @47: getfield boolean game.C_100218_am.field_103114_M
		// @4A: invokeinterface game.C_100088_o.func_102577_a(game.C_100336_im, int, boolean)void
		// @4F: iload_1
		// @50: iconst_1
		// @51: if_icmpeq @5F
		// @54: aconst_null
		// @55: checkcast game.C_100112_r
		// @58: putstatic game.C_100112_r game.C_100218_am.field_103109_D
		// @5B: goto @5F
		// @5E: athrow
		// @5F: iconst_1
		// @60: ireturn
		// @61: astore_3
		// @62: aload_3
		// @63: new java.lang.StringBuilder
		// @66: dup
		// @67: invokespecial java.lang.StringBuilder.<init>()void
		// @6A: getstatic java.lang.String[] game.C_100218_am.field_103116_O
		// @6D: iconst_0
		// @6E: aaload
		// @6F: invokevirtual java.lang.StringBuilder.append(java.lang.String)java.lang.StringBuilder
		// @72: iload_1
		// @73: invokevirtual java.lang.StringBuilder.append(int)java.lang.StringBuilder
		// @76: bipush 44 (0x2C)
		// @78: invokevirtual java.lang.StringBuilder.append(char)java.lang.StringBuilder
		// @7B: aload_2
		// @7C: ifnull @88
		// @7F: getstatic java.lang.String[] game.C_100218_am.field_103116_O
		// @82: iconst_2
		// @83: aaload
		// @84: goto @8D
		// @87: athrow
		// @88: getstatic java.lang.String[] game.C_100218_am.field_103116_O
		// @8B: iconst_1
		// @8C: aaload
		// @8D: invokevirtual java.lang.StringBuilder.append(java.lang.String)java.lang.StringBuilder
		// @90: bipush 41 (0x29)
		// @92: invokevirtual java.lang.StringBuilder.append(char)java.lang.StringBuilder
		// @95: invokevirtual java.lang.StringBuilder.toString()java.lang.String
		// @98: invokestatic game.C_100181_cf.func_105695_a(java.lang.Throwable, java.lang.String)game.C_100170_cm
		// @9B: athrow
	}
	
	final boolean func_102515_d(byte arg0)
	{
		// @00: iload_1
		// @01: bipush 10 (0x0A)
		// @03: if_icmpgt @15
		// @06: aload_0
		// @07: bipush -51 (0xCD)
		// @09: aconst_null
		// @0A: checkcast game.C_100336_im
		// @0D: invokevirtual game.C_100218_am.func_102522_a(int, game.C_100336_im)boolean
		// @10: pop
		// @11: goto @15
		// @14: athrow
		// @15: aload_0
		// @16: getfield boolean game.C_100218_am.field_103114_M
		// @19: ireturn
		// @1A: astore_2
		// @1B: aload_2
		// @1C: new java.lang.StringBuilder
		// @1F: dup
		// @20: invokespecial java.lang.StringBuilder.<init>()void
		// @23: getstatic java.lang.String[] game.C_100218_am.field_103116_O
		// @26: bipush 8 (0x08)
		// @28: aaload
		// @29: invokevirtual java.lang.StringBuilder.append(java.lang.String)java.lang.StringBuilder
		// @2C: iload_1
		// @2D: invokevirtual java.lang.StringBuilder.append(int)java.lang.StringBuilder
		// @30: bipush 41 (0x29)
		// @32: invokevirtual java.lang.StringBuilder.append(char)java.lang.StringBuilder
		// @35: invokevirtual java.lang.StringBuilder.toString()java.lang.String
		// @38: invokestatic game.C_100181_cf.func_105695_a(java.lang.Throwable, java.lang.String)game.C_100170_cm
		// @3B: athrow
	}
	
	static final void func_103103_i(int arg0)
	{
		// @000: bipush 17 (0x11)
		// @002: anewarray game.C_100067_vd
		// @005: putstatic game.C_100067_vd[] game.C_100066_dl.field_101641_u
		// @008: getstatic game.C_100067_vd[] game.C_100066_dl.field_101641_u
		// @00B: iconst_0
		// @00C: new game.C_100067_vd
		// @00F: dup
		// @010: iconst_0
		// @011: sipush 170 (0x00AA)
		// @014: sipush 170 (0x00AA)
		// @017: sipush 300 (0x012C)
		// @01A: iconst_0
		// @01B: aconst_null
		// @01C: iconst_1
		// @01D: invokespecial game.C_100067_vd.<init>(int, int, int, int, int, game.C_100037_wb, boolean)void
		// @020: aastore
		// @021: getstatic game.C_100067_vd[] game.C_100066_dl.field_101641_u
		// @024: iconst_1
		// @025: new game.C_100067_vd
		// @028: dup
		// @029: iconst_1
		// @02A: sipush 224 (0x00E0)
		// @02D: bipush 110 (0x6E)
		// @02F: sipush 200 (0x00C8)
		// @032: iconst_0
		// @033: aconst_null
		// @034: iconst_0
		// @035: invokespecial game.C_100067_vd.<init>(int, int, int, int, int, game.C_100037_wb, boolean)void
		// @038: aastore
		// @039: getstatic game.C_100067_vd[] game.C_100066_dl.field_101641_u
		// @03C: iconst_2
		// @03D: new game.C_100067_vd
		// @040: dup
		// @041: iconst_2
		// @042: sipush 224 (0x00E0)
		// @045: bipush 86 (0x56)
		// @047: sipush 400 (0x0190)
		// @04A: iconst_0
		// @04B: aconst_null
		// @04C: iconst_1
		// @04D: invokespecial game.C_100067_vd.<init>(int, int, int, int, int, game.C_100037_wb, boolean)void
		// @050: aastore
		// @051: getstatic game.C_100067_vd[] game.C_100066_dl.field_101641_u
		// @054: iconst_3
		// @055: new game.C_100067_vd
		// @058: dup
		// @059: iconst_3
		// @05A: sipush 224 (0x00E0)
		// @05D: bipush 60 (0x3C)
		// @05F: sipush 200 (0x00C8)
		// @062: iconst_0
		// @063: aconst_null
		// @064: iconst_0
		// @065: invokespecial game.C_100067_vd.<init>(int, int, int, int, int, game.C_100037_wb, boolean)void
		// @068: aastore
		// @069: getstatic game.C_100067_vd[] game.C_100066_dl.field_101641_u
		// @06C: iconst_4
		// @06D: new game.C_100067_vd
		// @070: dup
		// @071: iconst_4
		// @072: sipush 224 (0x00E0)
		// @075: bipush 60 (0x3C)
		// @077: sipush 285 (0x011D)
		// @07A: iconst_0
		// @07B: aconst_null
		// @07C: iconst_0
		// @07D: invokespecial game.C_100067_vd.<init>(int, int, int, int, int, game.C_100037_wb, boolean)void
		// @080: aastore
		// @081: getstatic game.C_100067_vd[] game.C_100066_dl.field_101641_u
		// @084: iconst_5
		// @085: new game.C_100067_vd
		// @088: dup
		// @089: iconst_5
		// @08A: sipush 224 (0x00E0)
		// @08D: bipush 60 (0x3C)
		// @08F: sipush 200 (0x00C8)
		// @092: iconst_0
		// @093: aconst_null
		// @094: iconst_0
		// @095: invokespecial game.C_100067_vd.<init>(int, int, int, int, int, game.C_100037_wb, boolean)void
		// @098: aastore
		// @099: getstatic game.C_100067_vd[] game.C_100066_dl.field_101641_u
		// @09C: bipush 6 (0x06)
		// @09E: new game.C_100067_vd
		// @0A1: dup
		// @0A2: bipush 6 (0x06)
		// @0A4: sipush 224 (0x00E0)
		// @0A7: bipush 60 (0x3C)
		// @0A9: sipush 285 (0x011D)
		// @0AC: iconst_0
		// @0AD: aconst_null
		// @0AE: iconst_0
		// @0AF: invokespecial game.C_100067_vd.<init>(int, int, int, int, int, game.C_100037_wb, boolean)void
		// @0B2: aastore
		// @0B3: getstatic game.C_100067_vd[] game.C_100066_dl.field_101641_u
		// @0B6: bipush 7 (0x07)
		// @0B8: new game.C_100067_vd
		// @0BB: dup
		// @0BC: bipush 7 (0x07)
		// @0BE: sipush 224 (0x00E0)
		// @0C1: bipush 120 (0x78)
		// @0C3: sipush 200 (0x00C8)
		// @0C6: iconst_0
		// @0C7: aconst_null
		// @0C8: iconst_0
		// @0C9: invokespecial game.C_100067_vd.<init>(int, int, int, int, int, game.C_100037_wb, boolean)void
		// @0CC: aastore
		// @0CD: getstatic game.C_100067_vd[] game.C_100066_dl.field_101641_u
		// @0D0: bipush 8 (0x08)
		// @0D2: new game.C_100067_vd
		// @0D5: dup
		// @0D6: bipush 8 (0x08)
		// @0D8: sipush 224 (0x00E0)
		// @0DB: bipush 86 (0x56)
		// @0DD: sipush 285 (0x011D)
		// @0E0: iconst_0
		// @0E1: aconst_null
		// @0E2: iconst_0
		// @0E3: invokespecial game.C_100067_vd.<init>(int, int, int, int, int, game.C_100037_wb, boolean)void
		// @0E6: aastore
		// @0E7: getstatic game.C_100067_vd[] game.C_100066_dl.field_101641_u
		// @0EA: bipush 9 (0x09)
		// @0EC: new game.C_100067_vd
		// @0EF: dup
		// @0F0: bipush 9 (0x09)
		// @0F2: sipush 170 (0x00AA)
		// @0F5: bipush 86 (0x56)
		// @0F7: sipush 300 (0x012C)
		// @0FA: iconst_0
		// @0FB: aconst_null
		// @0FC: iconst_1
		// @0FD: invokespecial game.C_100067_vd.<init>(int, int, int, int, int, game.C_100037_wb, boolean)void
		// @100: aastore
		// @101: getstatic game.C_100067_vd[] game.C_100066_dl.field_101641_u
		// @104: bipush 10 (0x0A)
		// @106: new game.C_100067_vd
		// @109: dup
		// @10A: bipush 10 (0x0A)
		// @10C: sipush 224 (0x00E0)
		// @10F: bipush 60 (0x3C)
		// @111: sipush 200 (0x00C8)
		// @114: iconst_0
		// @115: aconst_null
		// @116: iconst_0
		// @117: invokespecial game.C_100067_vd.<init>(int, int, int, int, int, game.C_100037_wb, boolean)void
		// @11A: aastore
		// @11B: getstatic game.C_100067_vd[] game.C_100066_dl.field_101641_u
		// @11E: bipush 11 (0x0B)
		// @120: new game.C_100067_vd
		// @123: dup
		// @124: bipush 11 (0x0B)
		// @126: sipush 224 (0x00E0)
		// @129: bipush 60 (0x3C)
		// @12B: sipush 285 (0x011D)
		// @12E: iconst_0
		// @12F: aconst_null
		// @130: iconst_0
		// @131: invokespecial game.C_100067_vd.<init>(int, int, int, int, int, game.C_100037_wb, boolean)void
		// @134: aastore
		// @135: iload_0
		// @136: bipush 114 (0x72)
		// @138: if_icmpge @146
		// @13B: ldc 65525 (0xfff5)
		// @13D: iconst_1
		// @13E: invokestatic game.C_100218_am.func_103102_a(char, boolean)boolean
		// @141: pop
		// @142: goto @146
		// @145: athrow
		// @146: getstatic game.C_100067_vd[] game.C_100066_dl.field_101641_u
		// @149: bipush 12 (0x0C)
		// @14B: new game.C_100067_vd
		// @14E: dup
		// @14F: bipush 12 (0x0C)
		// @151: sipush 224 (0x00E0)
		// @154: bipush 100 (0x64)
		// @156: sipush 285 (0x011D)
		// @159: iconst_0
		// @15A: getstatic game.C_100037_wb[] game.C_100058_dg.field_101562_E
		// @15D: iconst_2
		// @15E: aaload
		// @15F: iconst_0
		// @160: invokespecial game.C_100067_vd.<init>(int, int, int, int, int, game.C_100037_wb, boolean)void
		// @163: aastore
		// @164: getstatic game.C_100067_vd[] game.C_100066_dl.field_101641_u
		// @167: bipush 13 (0x0D)
		// @169: new game.C_100067_vd
		// @16C: dup
		// @16D: bipush 13 (0x0D)
		// @16F: sipush 170 (0x00AA)
		// @172: sipush 174 (0x00AE)
		// @175: sipush 300 (0x012C)
		// @178: iconst_0
		// @179: aconst_null
		// @17A: iconst_1
		// @17B: invokespecial game.C_100067_vd.<init>(int, int, int, int, int, game.C_100037_wb, boolean)void
		// @17E: aastore
		// @17F: getstatic game.C_100067_vd[] game.C_100066_dl.field_101641_u
		// @182: bipush 14 (0x0E)
		// @184: new game.C_100067_vd
		// @187: dup
		// @188: bipush 14 (0x0E)
		// @18A: sipush 224 (0x00E0)
		// @18D: bipush 60 (0x3C)
		// @18F: sipush 200 (0x00C8)
		// @192: iconst_0
		// @193: aconst_null
		// @194: iconst_0
		// @195: invokespecial game.C_100067_vd.<init>(int, int, int, int, int, game.C_100037_wb, boolean)void
		// @198: aastore
		// @199: getstatic game.C_100067_vd[] game.C_100066_dl.field_101641_u
		// @19C: bipush 15 (0x0F)
		// @19E: new game.C_100067_vd
		// @1A1: dup
		// @1A2: bipush 15 (0x0F)
		// @1A4: sipush 224 (0x00E0)
		// @1A7: bipush 60 (0x3C)
		// @1A9: sipush 400 (0x0190)
		// @1AC: iconst_0
		// @1AD: getstatic game.C_100037_wb[] game.C_100058_dg.field_101562_E
		// @1B0: iconst_2
		// @1B1: aaload
		// @1B2: iconst_0
		// @1B3: invokespecial game.C_100067_vd.<init>(int, int, int, int, int, game.C_100037_wb, boolean)void
		// @1B6: aastore
		// @1B7: getstatic game.C_100067_vd[] game.C_100066_dl.field_101641_u
		// @1BA: bipush 16 (0x10)
		// @1BC: new game.C_100067_vd
		// @1BF: dup
		// @1C0: bipush 16 (0x10)
		// @1C2: sipush 170 (0x00AA)
		// @1C5: sipush 170 (0x00AA)
		// @1C8: sipush 300 (0x012C)
		// @1CB: iconst_0
		// @1CC: aconst_null
		// @1CD: iconst_1
		// @1CE: invokespecial game.C_100067_vd.<init>(int, int, int, int, int, game.C_100037_wb, boolean)void
		// @1D1: aastore
		// @1D2: goto @1F7
		// @1D5: astore_1
		// @1D6: aload_1
		// @1D7: new java.lang.StringBuilder
		// @1DA: dup
		// @1DB: invokespecial java.lang.StringBuilder.<init>()void
		// @1DE: getstatic java.lang.String[] game.C_100218_am.field_103116_O
		// @1E1: bipush 18 (0x12)
		// @1E3: aaload
		// @1E4: invokevirtual java.lang.StringBuilder.append(java.lang.String)java.lang.StringBuilder
		// @1E7: iload_0
		// @1E8: invokevirtual java.lang.StringBuilder.append(int)java.lang.StringBuilder
		// @1EB: bipush 41 (0x29)
		// @1ED: invokevirtual java.lang.StringBuilder.append(char)java.lang.StringBuilder
		// @1F0: invokevirtual java.lang.StringBuilder.toString()java.lang.String
		// @1F3: invokestatic game.C_100181_cf.func_105695_a(java.lang.Throwable, java.lang.String)game.C_100170_cm
		// @1F6: athrow
		// @1F7: return
	}
	
	void func_103101_a(int arg0, int arg1, int arg2, int arg3)
	{
		// @00: aconst_null
		// @01: aload_0
		// @02: getfield game.C_100337_in game.C_100218_am.field_102543_u
		// @05: if_acmpeq @2D
		// @08: aload_0
		// @09: getfield game.C_100337_in game.C_100218_am.field_102543_u
		// @0C: instanceof game.C_100334_ik
		// @0F: ifne @1A
		// @12: goto @16
		// @15: athrow
		// @16: goto @2D
		// @19: athrow
		// @1A: aload_0
		// @1B: getfield game.C_100337_in game.C_100218_am.field_102543_u
		// @1E: checkcast game.C_100334_ik
		// @21: iload_2
		// @22: iload_3
		// @23: bipush -88 (0xA8)
		// @25: aload_0
		// @26: iload #4
		// @28: invokeinterface game.C_100334_ik.func_102581_a(int, int, byte, game.C_100218_am, int)void
		// @2D: iload_1
		// @2E: sipush 30483 (0x7713)
		// @31: if_icmpeq @44
		// @34: aload_0
		// @35: bipush -121 (0x87)
		// @37: bipush -42 (0xD6)
		// @39: bipush 44 (0x2C)
		// @3B: bipush 79 (0x4F)
		// @3D: invokevirtual game.C_100218_am.func_103101_a(int, int, int, int)void
		// @40: goto @44
		// @43: athrow
		// @44: goto @87
		// @47: astore #5
		// @49: aload #5
		// @4B: new java.lang.StringBuilder
		// @4E: dup
		// @4F: invokespecial java.lang.StringBuilder.<init>()void
		// @52: getstatic java.lang.String[] game.C_100218_am.field_103116_O
		// @55: bipush 10 (0x0A)
		// @57: aaload
		// @58: invokevirtual java.lang.StringBuilder.append(java.lang.String)java.lang.StringBuilder
		// @5B: iload_1
		// @5C: invokevirtual java.lang.StringBuilder.append(int)java.lang.StringBuilder
		// @5F: bipush 44 (0x2C)
		// @61: invokevirtual java.lang.StringBuilder.append(char)java.lang.StringBuilder
		// @64: iload_2
		// @65: invokevirtual java.lang.StringBuilder.append(int)java.lang.StringBuilder
		// @68: bipush 44 (0x2C)
		// @6A: invokevirtual java.lang.StringBuilder.append(char)java.lang.StringBuilder
		// @6D: iload_3
		// @6E: invokevirtual java.lang.StringBuilder.append(int)java.lang.StringBuilder
		// @71: bipush 44 (0x2C)
		// @73: invokevirtual java.lang.StringBuilder.append(char)java.lang.StringBuilder
		// @76: iload #4
		// @78: invokevirtual java.lang.StringBuilder.append(int)java.lang.StringBuilder
		// @7B: bipush 41 (0x29)
		// @7D: invokevirtual java.lang.StringBuilder.append(char)java.lang.StringBuilder
		// @80: invokevirtual java.lang.StringBuilder.toString()java.lang.String
		// @83: invokestatic game.C_100181_cf.func_105695_a(java.lang.Throwable, java.lang.String)game.C_100170_cm
		// @86: athrow
		// @87: return
	}
	
	static final int func_103108_a(int arg0, int arg1)
	{
		// @00: iload_0
		// @01: sipush 5308 (0x14BC)
		// @04: if_icmpeq @12
		// @07: aconst_null
		// @08: checkcast java.lang.String
		// @0B: putstatic java.lang.String game.C_100218_am.field_103117_H
		// @0E: goto @12
		// @11: athrow
		// @12: iconst_0
		// @13: istore_2
		// @14: iload_1
		// @15: iconst_m1
		// @16: ixor
		// @17: iconst_m1
		// @18: if_icmpeq @1F
		// @1B: goto @23
		// @1E: athrow
		// @1F: getstatic int game.C_100053_vn.field_102830_fb
		// @22: istore_2
		// @23: iload_1
		// @24: iconst_m1
		// @25: ixor
		// @26: bipush -2 (0xFE)
		// @28: if_icmpeq @2F
		// @2B: goto @33
		// @2E: athrow
		// @2F: getstatic int game.C_100220_ac.field_106065_i
		// @32: istore_2
		// @33: iload_1
		// @34: iconst_2
		// @35: if_icmpeq @3C
		// @38: goto @40
		// @3B: athrow
		// @3C: getstatic int game.C_100162_sc.field_102860_Q
		// @3F: istore_2
		// @40: iload_2
		// @41: ireturn
		// @42: astore_2
		// @43: aload_2
		// @44: new java.lang.StringBuilder
		// @47: dup
		// @48: invokespecial java.lang.StringBuilder.<init>()void
		// @4B: getstatic java.lang.String[] game.C_100218_am.field_103116_O
		// @4E: bipush 17 (0x11)
		// @50: aaload
		// @51: invokevirtual java.lang.StringBuilder.append(java.lang.String)java.lang.StringBuilder
		// @54: iload_0
		// @55: invokevirtual java.lang.StringBuilder.append(int)java.lang.StringBuilder
		// @58: bipush 44 (0x2C)
		// @5A: invokevirtual java.lang.StringBuilder.append(char)java.lang.StringBuilder
		// @5D: iload_1
		// @5E: invokevirtual java.lang.StringBuilder.append(int)java.lang.StringBuilder
		// @61: bipush 41 (0x29)
		// @63: invokevirtual java.lang.StringBuilder.append(char)java.lang.StringBuilder
		// @66: invokevirtual java.lang.StringBuilder.toString()java.lang.String
		// @69: invokestatic game.C_100181_cf.func_105695_a(java.lang.Throwable, java.lang.String)game.C_100170_cm
		// @6C: athrow
	}
	
	C_100218_am(String arg0, C_100326_ic arg1, C_100337_in arg2)
	{
		// @00: aload_0
		// @01: aload_1
		// @02: aload_2
		// @03: aload_3
		// @04: invokespecial game.C_100336_im.<init>(java.lang.String, game.C_100326_ic, game.C_100337_in)void
		// @07: aload_0
		// @08: iconst_1
		// @09: putfield boolean game.C_100218_am.field_103119_J
		// @0C: aload_0
		// @0D: iconst_0
		// @0E: putfield boolean game.C_100218_am.field_103114_M
		// @11: aload_0
		// @12: iconst_1
		// @13: putfield boolean game.C_100218_am.field_103113_L
		// @16: return
	}
	
	static final boolean func_103102_a(char arg0, boolean arg1)
	{
		// @00: iload_0
		// @01: invokestatic java.lang.Character.isISOControl(char)boolean
		// @04: ifeq @09
		// @07: iconst_0
		// @08: ireturn
		// @09: iload_0
		// @0A: sipush 28481 (0x6F41)
		// @0D: invokestatic game.C_100007_fm.func_103626_a(char, int)boolean
		// @10: ifne @17
		// @13: goto @19
		// @16: athrow
		// @17: iconst_1
		// @18: ireturn
		// @19: bipush -46 (0xD2)
		// @1B: iload_0
		// @1C: iconst_m1
		// @1D: ixor
		// @1E: if_icmpeq @48
		// @21: sipush 160 (0x00A0)
		// @24: iload_0
		// @25: if_icmpeq @48
		// @28: goto @2C
		// @2B: athrow
		// @2C: bipush -33 (0xDF)
		// @2E: iload_0
		// @2F: iconst_m1
		// @30: ixor
		// @31: if_icmpeq @48
		// @34: goto @38
		// @37: athrow
		// @38: iload_0
		// @39: iconst_m1
		// @3A: ixor
		// @3B: bipush -96 (0xA0)
		// @3D: if_icmpeq @48
		// @40: goto @44
		// @43: athrow
		// @44: goto @4A
		// @47: athrow
		// @48: iconst_1
		// @49: ireturn
		// @4A: iload_1
		// @4B: iconst_1
		// @4C: if_icmpeq @5A
		// @4F: aconst_null
		// @50: checkcast game.C_100037_wb[]
		// @53: putstatic game.C_100037_wb[] game.C_100218_am.field_103110_E
		// @56: goto @5A
		// @59: athrow
		// @5A: iconst_0
		// @5B: ireturn
		// @5C: astore_2
		// @5D: aload_2
		// @5E: new java.lang.StringBuilder
		// @61: dup
		// @62: invokespecial java.lang.StringBuilder.<init>()void
		// @65: getstatic java.lang.String[] game.C_100218_am.field_103116_O
		// @68: bipush 6 (0x06)
		// @6A: aaload
		// @6B: invokevirtual java.lang.StringBuilder.append(java.lang.String)java.lang.StringBuilder
		// @6E: iload_0
		// @6F: invokevirtual java.lang.StringBuilder.append(char)java.lang.StringBuilder
		// @72: bipush 44 (0x2C)
		// @74: invokevirtual java.lang.StringBuilder.append(char)java.lang.StringBuilder
		// @77: iload_1
		// @78: invokevirtual java.lang.StringBuilder.append(boolean)java.lang.StringBuilder
		// @7B: bipush 41 (0x29)
		// @7D: invokevirtual java.lang.StringBuilder.append(char)java.lang.StringBuilder
		// @80: invokevirtual java.lang.StringBuilder.toString()java.lang.String
		// @83: invokestatic game.C_100181_cf.func_105695_a(java.lang.Throwable, java.lang.String)game.C_100170_cm
		// @86: athrow
	}
	
	final void func_102519_a(byte arg0, int arg1, int arg2, int arg3, C_100336_im arg4, int arg5)
	{
		// @00: aload_0
		// @01: getfield game.C_100337_in game.C_100218_am.field_102543_u
		// @04: ifnull @2E
		// @07: aload_0
		// @08: getfield game.C_100337_in game.C_100218_am.field_102543_u
		// @0B: instanceof game.C_100065_dm
		// @0E: ifne @19
		// @11: goto @15
		// @14: athrow
		// @15: goto @2E
		// @18: athrow
		// @19: aload_0
		// @1A: getfield game.C_100337_in game.C_100218_am.field_102543_u
		// @1D: checkcast game.C_100065_dm
		// @20: iload_2
		// @21: iload_3
		// @22: aload_0
		// @23: iload #6
		// @25: iload #4
		// @27: bipush -110 (0x92)
		// @29: invokeinterface game.C_100065_dm.func_102846_a(int, int, game.C_100218_am, int, int, byte)void
		// @2E: aload_0
		// @2F: iconst_0
		// @30: putfield int game.C_100218_am.field_102532_A
		// @33: iload_1
		// @34: bipush 122 (0x7A)
		// @36: if_icmpeq @44
		// @39: aconst_null
		// @3A: checkcast game.C_100037_wb[]
		// @3D: putstatic game.C_100037_wb[] game.C_100218_am.field_103110_E
		// @40: goto @44
		// @43: athrow
		// @44: goto @AC
		// @47: astore #7
		// @49: aload #7
		// @4B: new java.lang.StringBuilder
		// @4E: dup
		// @4F: invokespecial java.lang.StringBuilder.<init>()void
		// @52: getstatic java.lang.String[] game.C_100218_am.field_103116_O
		// @55: bipush 16 (0x10)
		// @57: aaload
		// @58: invokevirtual java.lang.StringBuilder.append(java.lang.String)java.lang.StringBuilder
		// @5B: iload_1
		// @5C: invokevirtual java.lang.StringBuilder.append(int)java.lang.StringBuilder
		// @5F: bipush 44 (0x2C)
		// @61: invokevirtual java.lang.StringBuilder.append(char)java.lang.StringBuilder
		// @64: iload_2
		// @65: invokevirtual java.lang.StringBuilder.append(int)java.lang.StringBuilder
		// @68: bipush 44 (0x2C)
		// @6A: invokevirtual java.lang.StringBuilder.append(char)java.lang.StringBuilder
		// @6D: iload_3
		// @6E: invokevirtual java.lang.StringBuilder.append(int)java.lang.StringBuilder
		// @71: bipush 44 (0x2C)
		// @73: invokevirtual java.lang.StringBuilder.append(char)java.lang.StringBuilder
		// @76: iload #4
		// @78: invokevirtual java.lang.StringBuilder.append(int)java.lang.StringBuilder
		// @7B: bipush 44 (0x2C)
		// @7D: invokevirtual java.lang.StringBuilder.append(char)java.lang.StringBuilder
		// @80: aload #5
		// @82: ifnull @8E
		// @85: getstatic java.lang.String[] game.C_100218_am.field_103116_O
		// @88: iconst_2
		// @89: aaload
		// @8A: goto @93
		// @8D: athrow
		// @8E: getstatic java.lang.String[] game.C_100218_am.field_103116_O
		// @91: iconst_1
		// @92: aaload
		// @93: invokevirtual java.lang.StringBuilder.append(java.lang.String)java.lang.StringBuilder
		// @96: bipush 44 (0x2C)
		// @98: invokevirtual java.lang.StringBuilder.append(char)java.lang.StringBuilder
		// @9B: iload #6
		// @9D: invokevirtual java.lang.StringBuilder.append(int)java.lang.StringBuilder
		// @A0: bipush 41 (0x29)
		// @A2: invokevirtual java.lang.StringBuilder.append(char)java.lang.StringBuilder
		// @A5: invokevirtual java.lang.StringBuilder.toString()java.lang.String
		// @A8: invokestatic game.C_100181_cf.func_105695_a(java.lang.Throwable, java.lang.String)game.C_100170_cm
		// @AB: athrow
		// @AC: return
	}
	
	boolean func_102520_a(int arg0, C_100336_im arg1, int arg2, int arg3, int arg4, int arg5, int arg6)
	{
		// @00: bipush -101 (0x9B)
		// @02: bipush 32 (0x20)
		// @04: iload_3
		// @05: isub
		// @06: bipush 52 (0x34)
		// @08: idiv
		// @09: irem
		// @0A: istore #8
		// @0C: aload_0
		// @0D: getfield boolean game.C_100218_am.field_103113_L
		// @10: ifeq @6C
		// @13: aload_0
		// @14: bipush -128 (0x80)
		// @16: iload_1
		// @17: iload #6
		// @19: iload #5
		// @1B: iload #4
		// @1D: invokevirtual game.C_100218_am.func_102508_a(int, int, int, int, int)boolean
		// @20: ifeq @6C
		// @23: goto @27
		// @26: athrow
		// @27: aload_0
		// @28: iconst_1
		// @29: aload_2
		// @2A: invokevirtual game.C_100218_am.func_102522_a(int, game.C_100336_im)boolean
		// @2D: pop
		// @2E: aload_0
		// @2F: iload #7
		// @31: putfield int game.C_100218_am.field_102532_A
		// @34: aconst_null
		// @35: aload_0
		// @36: getfield game.C_100337_in game.C_100218_am.field_102543_u
		// @39: if_acmpeq @6A
		// @3C: goto @40
		// @3F: athrow
		// @40: aload_0
		// @41: getfield game.C_100337_in game.C_100218_am.field_102543_u
		// @44: instanceof game.C_100065_dm
		// @47: ifne @52
		// @4A: goto @4E
		// @4D: athrow
		// @4E: goto @6A
		// @51: athrow
		// @52: aload_0
		// @53: getfield game.C_100337_in game.C_100218_am.field_102543_u
		// @56: checkcast game.C_100065_dm
		// @59: aload_0
		// @5A: iload #7
		// @5C: iload #6
		// @5E: bipush 110 (0x6E)
		// @60: iload_1
		// @61: iload #5
		// @63: iload #4
		// @65: invokeinterface game.C_100065_dm.func_102847_a(game.C_100218_am, int, int, byte, int, int, int)void
		// @6A: iconst_1
		// @6B: ireturn
		// @6C: iconst_0
		// @6D: ireturn
		// @6E: astore #8
		// @70: aload #8
		// @72: new java.lang.StringBuilder
		// @75: dup
		// @76: invokespecial java.lang.StringBuilder.<init>()void
		// @79: getstatic java.lang.String[] game.C_100218_am.field_103116_O
		// @7C: bipush 7 (0x07)
		// @7E: aaload
		// @7F: invokevirtual java.lang.StringBuilder.append(java.lang.String)java.lang.StringBuilder
		// @82: iload_1
		// @83: invokevirtual java.lang.StringBuilder.append(int)java.lang.StringBuilder
		// @86: bipush 44 (0x2C)
		// @88: invokevirtual java.lang.StringBuilder.append(char)java.lang.StringBuilder
		// @8B: aload_2
		// @8C: ifnull @98
		// @8F: getstatic java.lang.String[] game.C_100218_am.field_103116_O
		// @92: iconst_2
		// @93: aaload
		// @94: goto @9D
		// @97: athrow
		// @98: getstatic java.lang.String[] game.C_100218_am.field_103116_O
		// @9B: iconst_1
		// @9C: aaload
		// @9D: invokevirtual java.lang.StringBuilder.append(java.lang.String)java.lang.StringBuilder
		// @A0: bipush 44 (0x2C)
		// @A2: invokevirtual java.lang.StringBuilder.append(char)java.lang.StringBuilder
		// @A5: iload_3
		// @A6: invokevirtual java.lang.StringBuilder.append(int)java.lang.StringBuilder
		// @A9: bipush 44 (0x2C)
		// @AB: invokevirtual java.lang.StringBuilder.append(char)java.lang.StringBuilder
		// @AE: iload #4
		// @B0: invokevirtual java.lang.StringBuilder.append(int)java.lang.StringBuilder
		// @B3: bipush 44 (0x2C)
		// @B5: invokevirtual java.lang.StringBuilder.append(char)java.lang.StringBuilder
		// @B8: iload #5
		// @BA: invokevirtual java.lang.StringBuilder.append(int)java.lang.StringBuilder
		// @BD: bipush 44 (0x2C)
		// @BF: invokevirtual java.lang.StringBuilder.append(char)java.lang.StringBuilder
		// @C2: iload #6
		// @C4: invokevirtual java.lang.StringBuilder.append(int)java.lang.StringBuilder
		// @C7: bipush 44 (0x2C)
		// @C9: invokevirtual java.lang.StringBuilder.append(char)java.lang.StringBuilder
		// @CC: iload #7
		// @CE: invokevirtual java.lang.StringBuilder.append(int)java.lang.StringBuilder
		// @D1: bipush 41 (0x29)
		// @D3: invokevirtual java.lang.StringBuilder.append(char)java.lang.StringBuilder
		// @D6: invokevirtual java.lang.StringBuilder.toString()java.lang.String
		// @D9: invokestatic game.C_100181_cf.func_105695_a(java.lang.Throwable, java.lang.String)game.C_100170_cm
		// @DC: athrow
	}
	
	void func_102513_a(C_100336_im arg0, int arg1, int arg2, int arg3)
	{
		// @00: aload_0
		// @01: aload_1
		// @02: iload_2
		// @03: iload_3
		// @04: iconst_0
		// @05: ixor
		// @06: iload #4
		// @08: invokespecial game.C_100336_im.func_102513_a(game.C_100336_im, int, int, int)void
		// @0B: aload_0
		// @0C: getfield int game.C_100218_am.field_102532_A
		// @0F: iconst_m1
		// @10: ixor
		// @11: iconst_m1
		// @12: if_icmpeq @78
		// @15: aload_0
		// @16: getfield int game.C_100218_am.field_102532_A
		// @19: iconst_m1
		// @1A: ixor
		// @1B: getstatic int game.C_100083_c.field_103171_R
		// @1E: iconst_m1
		// @1F: ixor
		// @20: if_icmpeq @78
		// @23: goto @27
		// @26: athrow
		// @27: aload_0
		// @28: iload_3
		// @29: bipush -126 (0x82)
		// @2B: ixor
		// @2C: getstatic int game.C_100015_wh.field_103781_g
		// @2F: iload #4
		// @31: iload_2
		// @32: getstatic int game.C_100338_jc.field_105370_l
		// @35: invokevirtual game.C_100218_am.func_102508_a(int, int, int, int, int)boolean
		// @38: ifeq @68
		// @3B: goto @3F
		// @3E: athrow
		// @3F: iconst_0
		// @40: getstatic int game.C_100083_c.field_103171_R
		// @43: if_icmpeq @4E
		// @46: goto @4A
		// @49: athrow
		// @4A: goto @68
		// @4D: athrow
		// @4E: aload_0
		// @4F: iload_3
		// @50: sipush 30481 (0x7711)
		// @53: ixor
		// @54: getstatic int game.C_100015_wh.field_103781_g
		// @57: iload #4
		// @59: ineg
		// @5A: iadd
		// @5B: aload_0
		// @5C: getfield int game.C_100218_am.field_102532_A
		// @5F: iload_2
		// @60: ineg
		// @61: getstatic int game.C_100338_jc.field_105370_l
		// @64: iadd
		// @65: invokevirtual game.C_100218_am.func_103101_a(int, int, int, int)void
		// @68: aload_0
		// @69: bipush 122 (0x7A)
		// @6B: iload #4
		// @6D: getstatic int game.C_100015_wh.field_103781_g
		// @70: getstatic int game.C_100338_jc.field_105370_l
		// @73: aload_1
		// @74: iload_2
		// @75: invokevirtual game.C_100218_am.func_102519_a(byte, int, int, int, game.C_100336_im, int)void
		// @78: iload_3
		// @79: iconst_2
		// @7A: if_icmpeq @86
		// @7D: aload_0
		// @7E: iconst_1
		// @7F: putfield boolean game.C_100218_am.field_103120_K
		// @82: goto @86
		// @85: athrow
		// @86: goto @DA
		// @89: astore #5
		// @8B: aload #5
		// @8D: new java.lang.StringBuilder
		// @90: dup
		// @91: invokespecial java.lang.StringBuilder.<init>()void
		// @94: getstatic java.lang.String[] game.C_100218_am.field_103116_O
		// @97: bipush 13 (0x0D)
		// @99: aaload
		// @9A: invokevirtual java.lang.StringBuilder.append(java.lang.String)java.lang.StringBuilder
		// @9D: aload_1
		// @9E: ifnull @AA
		// @A1: getstatic java.lang.String[] game.C_100218_am.field_103116_O
		// @A4: iconst_2
		// @A5: aaload
		// @A6: goto @AF
		// @A9: athrow
		// @AA: getstatic java.lang.String[] game.C_100218_am.field_103116_O
		// @AD: iconst_1
		// @AE: aaload
		// @AF: invokevirtual java.lang.StringBuilder.append(java.lang.String)java.lang.StringBuilder
		// @B2: bipush 44 (0x2C)
		// @B4: invokevirtual java.lang.StringBuilder.append(char)java.lang.StringBuilder
		// @B7: iload_2
		// @B8: invokevirtual java.lang.StringBuilder.append(int)java.lang.StringBuilder
		// @BB: bipush 44 (0x2C)
		// @BD: invokevirtual java.lang.StringBuilder.append(char)java.lang.StringBuilder
		// @C0: iload_3
		// @C1: invokevirtual java.lang.StringBuilder.append(int)java.lang.StringBuilder
		// @C4: bipush 44 (0x2C)
		// @C6: invokevirtual java.lang.StringBuilder.append(char)java.lang.StringBuilder
		// @C9: iload #4
		// @CB: invokevirtual java.lang.StringBuilder.append(int)java.lang.StringBuilder
		// @CE: bipush 41 (0x29)
		// @D0: invokevirtual java.lang.StringBuilder.append(char)java.lang.StringBuilder
		// @D3: invokevirtual java.lang.StringBuilder.toString()java.lang.String
		// @D6: invokestatic game.C_100181_cf.func_105695_a(java.lang.Throwable, java.lang.String)game.C_100170_cm
		// @D9: athrow
		// @DA: return
	}
	
	final StringBuilder func_102510_a(int arg0, byte arg1, StringBuilder arg2, Hashtable arg3)
	{
		// @00: bipush 73 (0x49)
		// @02: iload_2
		// @03: bipush -42 (0xD6)
		// @05: isub
		// @06: bipush 63 (0x3F)
		// @08: idiv
		// @09: idiv
		// @0A: istore #5
		// @0C: aload_0
		// @0D: aload #4
		// @0F: iload_1
		// @10: aload_3
		// @11: bipush -76 (0xB4)
		// @13: invokevirtual game.C_100218_am.func_102516_a(java.util.Hashtable, int, java.lang.StringBuilder, byte)boolean
		// @16: ifne @1D
		// @19: goto @51
		// @1C: athrow
		// @1D: aload_0
		// @1E: bipush -124 (0x84)
		// @20: aload_3
		// @21: iload_1
		// @22: aload #4
		// @24: invokevirtual game.C_100218_am.func_102518_a(byte, java.lang.StringBuilder, int, java.util.Hashtable)void
		// @27: aload_0
		// @28: getfield boolean game.C_100218_am.field_103120_K
		// @2B: ifeq @3C
		// @2E: aload_3
		// @2F: getstatic java.lang.String[] game.C_100218_am.field_103116_O
		// @32: iconst_5
		// @33: aaload
		// @34: invokevirtual java.lang.StringBuilder.append(java.lang.String)java.lang.StringBuilder
		// @37: pop
		// @38: goto @3C
		// @3B: athrow
		// @3C: aload_0
		// @3D: getfield boolean game.C_100218_am.field_103113_L
		// @40: ifne @51
		// @43: aload_3
		// @44: getstatic java.lang.String[] game.C_100218_am.field_103116_O
		// @47: iconst_3
		// @48: aaload
		// @49: invokevirtual java.lang.StringBuilder.append(java.lang.String)java.lang.StringBuilder
		// @4C: pop
		// @4D: goto @51
		// @50: athrow
		// @51: aload_3
		// @52: areturn
		// @53: astore #5
		// @55: aload #5
		// @57: new java.lang.StringBuilder
		// @5A: dup
		// @5B: invokespecial java.lang.StringBuilder.<init>()void
		// @5E: getstatic java.lang.String[] game.C_100218_am.field_103116_O
		// @61: iconst_4
		// @62: aaload
		// @63: invokevirtual java.lang.StringBuilder.append(java.lang.String)java.lang.StringBuilder
		// @66: iload_1
		// @67: invokevirtual java.lang.StringBuilder.append(int)java.lang.StringBuilder
		// @6A: bipush 44 (0x2C)
		// @6C: invokevirtual java.lang.StringBuilder.append(char)java.lang.StringBuilder
		// @6F: iload_2
		// @70: invokevirtual java.lang.StringBuilder.append(int)java.lang.StringBuilder
		// @73: bipush 44 (0x2C)
		// @75: invokevirtual java.lang.StringBuilder.append(char)java.lang.StringBuilder
		// @78: aload_3
		// @79: ifnull @85
		// @7C: getstatic java.lang.String[] game.C_100218_am.field_103116_O
		// @7F: iconst_2
		// @80: aaload
		// @81: goto @8A
		// @84: athrow
		// @85: getstatic java.lang.String[] game.C_100218_am.field_103116_O
		// @88: iconst_1
		// @89: aaload
		// @8A: invokevirtual java.lang.StringBuilder.append(java.lang.String)java.lang.StringBuilder
		// @8D: bipush 44 (0x2C)
		// @8F: invokevirtual java.lang.StringBuilder.append(char)java.lang.StringBuilder
		// @92: aload #4
		// @94: ifnull @A0
		// @97: getstatic java.lang.String[] game.C_100218_am.field_103116_O
		// @9A: iconst_2
		// @9B: aaload
		// @9C: goto @A5
		// @9F: athrow
		// @A0: getstatic java.lang.String[] game.C_100218_am.field_103116_O
		// @A3: iconst_1
		// @A4: aaload
		// @A5: invokevirtual java.lang.StringBuilder.append(java.lang.String)java.lang.StringBuilder
		// @A8: bipush 41 (0x29)
		// @AA: invokevirtual java.lang.StringBuilder.append(char)java.lang.StringBuilder
		// @AD: invokevirtual java.lang.StringBuilder.toString()java.lang.String
		// @B0: invokestatic game.C_100181_cf.func_105695_a(java.lang.Throwable, java.lang.String)game.C_100170_cm
		// @B3: athrow
	}
	
	C_100218_am(String arg0, C_100337_in arg1)
	{
		// @0: aload_0
		// @1: aload_1
		// @2: getstatic game.C_100233_oa game.C_100043_vl.field_101945_cc
		// @5: getfield game.C_100326_ic game.C_100233_oa.field_106237_d
		// @8: aload_2
		// @9: invokespecial game.C_100218_am.<init>(java.lang.String, game.C_100326_ic, game.C_100337_in)void
		// @C: return
	}
	
	boolean func_102506_a(char arg0, int arg1, int arg2, C_100336_im arg3)
	{
		// @00: aload_0
		// @01: bipush 88 (0x58)
		// @03: invokevirtual game.C_100218_am.func_102515_d(byte)boolean
		// @06: ifeq @31
		// @09: bipush -85 (0xAB)
		// @0B: iload_2
		// @0C: iconst_m1
		// @0D: ixor
		// @0E: if_icmpeq @25
		// @11: goto @15
		// @14: athrow
		// @15: bipush -84 (0xAC)
		// @17: iload_2
		// @18: iconst_m1
		// @19: ixor
		// @1A: if_icmpeq @25
		// @1D: goto @21
		// @20: athrow
		// @21: goto @31
		// @24: athrow
		// @25: aload_0
		// @26: sipush 30483 (0x7713)
		// @29: iconst_m1
		// @2A: iconst_1
		// @2B: iconst_m1
		// @2C: invokevirtual game.C_100218_am.func_103101_a(int, int, int, int)void
		// @2F: iconst_1
		// @30: ireturn
		// @31: iload_3
		// @32: sipush 22545 (0x5811)
		// @35: if_icmpeq @41
		// @38: aload_0
		// @39: iconst_0
		// @3A: putfield boolean game.C_100218_am.field_103114_M
		// @3D: goto @41
		// @40: athrow
		// @41: iconst_0
		// @42: ireturn
		// @43: astore #5
		// @45: aload #5
		// @47: new java.lang.StringBuilder
		// @4A: dup
		// @4B: invokespecial java.lang.StringBuilder.<init>()void
		// @4E: getstatic java.lang.String[] game.C_100218_am.field_103116_O
		// @51: bipush 9 (0x09)
		// @53: aaload
		// @54: invokevirtual java.lang.StringBuilder.append(java.lang.String)java.lang.StringBuilder
		// @57: iload_1
		// @58: invokevirtual java.lang.StringBuilder.append(char)java.lang.StringBuilder
		// @5B: bipush 44 (0x2C)
		// @5D: invokevirtual java.lang.StringBuilder.append(char)java.lang.StringBuilder
		// @60: iload_2
		// @61: invokevirtual java.lang.StringBuilder.append(int)java.lang.StringBuilder
		// @64: bipush 44 (0x2C)
		// @66: invokevirtual java.lang.StringBuilder.append(char)java.lang.StringBuilder
		// @69: iload_3
		// @6A: invokevirtual java.lang.StringBuilder.append(int)java.lang.StringBuilder
		// @6D: bipush 44 (0x2C)
		// @6F: invokevirtual java.lang.StringBuilder.append(char)java.lang.StringBuilder
		// @72: aload #4
		// @74: ifnull @80
		// @77: getstatic java.lang.String[] game.C_100218_am.field_103116_O
		// @7A: iconst_2
		// @7B: aaload
		// @7C: goto @85
		// @7F: athrow
		// @80: getstatic java.lang.String[] game.C_100218_am.field_103116_O
		// @83: iconst_1
		// @84: aaload
		// @85: invokevirtual java.lang.StringBuilder.append(java.lang.String)java.lang.StringBuilder
		// @88: bipush 41 (0x29)
		// @8A: invokevirtual java.lang.StringBuilder.append(char)java.lang.StringBuilder
		// @8D: invokevirtual java.lang.StringBuilder.toString()java.lang.String
		// @90: invokestatic game.C_100181_cf.func_105695_a(java.lang.Throwable, java.lang.String)game.C_100170_cm
		// @93: athrow
	}
	
	public static void func_103107_h(int arg0)
	{
		// @00: aconst_null
		// @01: putstatic java.lang.String game.C_100218_am.field_103111_F
		// @04: iload_0
		// @05: iconst_2
		// @06: if_icmpeq @12
		// @09: bipush 25 (0x19)
		// @0B: putstatic int game.C_100218_am.field_103115_N
		// @0E: goto @12
		// @11: athrow
		// @12: aconst_null
		// @13: putstatic game.C_100112_r game.C_100218_am.field_103109_D
		// @16: aconst_null
		// @17: putstatic game.C_100037_wb[] game.C_100218_am.field_103110_E
		// @1A: aconst_null
		// @1B: putstatic game.C_100037_wb game.C_100218_am.field_103112_G
		// @1E: aconst_null
		// @1F: putstatic java.lang.String game.C_100218_am.field_103117_H
		// @22: aconst_null
		// @23: putstatic java.lang.String game.C_100218_am.field_103118_I
		// @26: goto @4B
		// @29: astore_1
		// @2A: aload_1
		// @2B: new java.lang.StringBuilder
		// @2E: dup
		// @2F: invokespecial java.lang.StringBuilder.<init>()void
		// @32: getstatic java.lang.String[] game.C_100218_am.field_103116_O
		// @35: bipush 11 (0x0B)
		// @37: aaload
		// @38: invokevirtual java.lang.StringBuilder.append(java.lang.String)java.lang.StringBuilder
		// @3B: iload_0
		// @3C: invokevirtual java.lang.StringBuilder.append(int)java.lang.StringBuilder
		// @3F: bipush 41 (0x29)
		// @41: invokevirtual java.lang.StringBuilder.append(char)java.lang.StringBuilder
		// @44: invokevirtual java.lang.StringBuilder.toString()java.lang.String
		// @47: invokestatic game.C_100181_cf.func_105695_a(java.lang.Throwable, java.lang.String)game.C_100170_cm
		// @4A: athrow
		// @4B: return
	}
	
	protected C_100218_am()
	{
		// @00: aload_0
		// @01: invokespecial game.C_100336_im.<init>()void
		// @04: aload_0
		// @05: iconst_1
		// @06: putfield boolean game.C_100218_am.field_103119_J
		// @09: aload_0
		// @0A: iconst_0
		// @0B: putfield boolean game.C_100218_am.field_103114_M
		// @0E: aload_0
		// @0F: iconst_1
		// @10: putfield boolean game.C_100218_am.field_103113_L
		// @13: aload_0
		// @14: getstatic game.C_100233_oa game.C_100043_vl.field_101945_cc
		// @17: getfield game.C_100326_ic game.C_100233_oa.field_106245_o
		// @1A: putfield game.C_100326_ic game.C_100218_am.field_102533_B
		// @1D: goto @2C
		// @20: astore_1
		// @21: aload_1
		// @22: getstatic java.lang.String[] game.C_100218_am.field_103116_O
		// @25: bipush 15 (0x0F)
		// @27: aaload
		// @28: invokestatic game.C_100181_cf.func_105695_a(java.lang.Throwable, java.lang.String)game.C_100170_cm
		// @2B: athrow
		// @2C: return
	}
	
	static
	{
		// @000: bipush 19 (0x13)
		// @002: anewarray java.lang.String
		// @005: dup
		// @006: iconst_0
		// @007: ldc "}y\\q\u0001"
		// @009: invokestatic game.C_100218_am.func_103105_z(java.lang.String)char[]
		// @00C: invokestatic game.C_100218_am.func_103104_z(char[])java.lang.String
		// @00F: aastore
		// @010: dup
		// @011: iconst_1
		// @012: ldc "ra\u001eN"
		// @014: invokestatic game.C_100218_am.func_103105_z(java.lang.String)char[]
		// @017: invokestatic game.C_100218_am.func_103104_z(char[])java.lang.String
		// @01A: aastore
		// @01B: dup
		// @01C: iconst_2
		// @01D: ldc "g:\\\u000cT"
		// @01F: invokestatic game.C_100218_am.func_103105_z(java.lang.String)char[]
		// @022: invokestatic game.C_100218_am.func_103104_z(char[])java.lang.String
		// @025: aastore
		// @026: dup
		// @027: iconst_3
		// @028: ldc "<p\u001bQH~x\u0017F"
		// @02A: invokestatic game.C_100218_am.func_103105_z(java.lang.String)char[]
		// @02D: invokestatic game.C_100218_am.func_103104_z(char[])java.lang.String
		// @030: aastore
		// @031: dup
		// @032: iconst_4
		// @033: ldc "}y\\ch4"
		// @035: invokestatic game.C_100218_am.func_103105_z(java.lang.String)char[]
		// @038: invokestatic game.C_100218_am.func_103104_z(char[])java.lang.String
		// @03B: aastore
		// @03C: dup
		// @03D: iconst_5
		// @03E: ldc "<u\u0011V@jq"
		// @040: invokestatic game.C_100218_am.func_103105_z(java.lang.String)char[]
		// @043: invokestatic game.C_100218_am.func_103104_z(char[])java.lang.String
		// @046: aastore
		// @047: dup
		// @048: bipush 6 (0x06)
		// @04A: ldc "}y\\ck4"
		// @04C: invokestatic game.C_100218_am.func_103105_z(java.lang.String)char[]
		// @04F: invokestatic game.C_100218_am.func_103104_z(char[])java.lang.String
		// @052: aastore
		// @053: dup
		// @054: bipush 7 (0x07)
		// @056: ldc "}y\\w\u0001"
		// @058: invokestatic game.C_100218_am.func_103105_z(java.lang.String)char[]
		// @05B: invokestatic game.C_100218_am.func_103104_z(char[])java.lang.String
		// @05E: aastore
		// @05F: dup
		// @060: bipush 8 (0x08)
		// @062: ldc "}y\\gh4"
		// @064: invokestatic game.C_100218_am.func_103105_z(java.lang.String)char[]
		// @067: invokestatic game.C_100218_am.func_103104_z(char[])java.lang.String
		// @06A: aastore
		// @06B: dup
		// @06C: bipush 9 (0x09)
		// @06E: ldc "}y\\dh4"
		// @070: invokestatic game.C_100218_am.func_103105_z(java.lang.String)char[]
		// @073: invokestatic game.C_100218_am.func_103104_z(char[])java.lang.String
		// @076: aastore
		// @077: dup
		// @078: bipush 10 (0x0A)
		// @07A: ldc "}y\\e\u0001"
		// @07C: invokestatic game.C_100218_am.func_103105_z(java.lang.String)char[]
		// @07F: invokestatic game.C_100218_am.func_103104_z(char[])java.lang.String
		// @082: aastore
		// @083: dup
		// @084: bipush 11 (0x0B)
		// @086: ldc "}y\\ak4"
		// @088: invokestatic game.C_100218_am.func_103105_z(java.lang.String)char[]
		// @08B: invokestatic game.C_100218_am.func_103104_z(char[])java.lang.String
		// @08E: aastore
		// @08F: dup
		// @090: bipush 12 (0x0C)
		// @092: ldc "}y\\uh4"
		// @094: invokestatic game.C_100218_am.func_103105_z(java.lang.String)char[]
		// @097: invokestatic game.C_100218_am.func_103104_z(char[])java.lang.String
		// @09A: aastore
		// @09B: dup
		// @09C: bipush 13 (0x0D)
		// @09E: ldc "}y\\s\u0001"
		// @0A0: invokestatic game.C_100218_am.func_103105_z(java.lang.String)char[]
		// @0A3: invokestatic game.C_100218_am.func_103104_z(char[])java.lang.String
		// @0A6: aastore
		// @0A7: dup
		// @0A8: bipush 14 (0x0E)
		// @0AA: ldc "}y\\u\u0001"
		// @0AC: invokestatic game.C_100218_am.func_103105_z(java.lang.String)char[]
		// @0AF: invokestatic game.C_100218_am.func_103104_z(char[])java.lang.String
		// @0B2: aastore
		// @0B3: dup
		// @0B4: bipush 15 (0x0F)
		// @0B6: ldc "}y\\\u001e@r}\u0006\u001c\u00015"
		// @0B8: invokestatic game.C_100218_am.func_103105_z(java.lang.String)char[]
		// @0BB: invokestatic game.C_100218_am.func_103104_z(char[])java.lang.String
		// @0BE: aastore
		// @0BF: dup
		// @0C0: bipush 16 (0x10)
		// @0C2: ldc "}y\\v\u0001"
		// @0C4: invokestatic game.C_100218_am.func_103105_z(java.lang.String)char[]
		// @0C7: invokestatic game.C_100218_am.func_103104_z(char[])java.lang.String
		// @0CA: aastore
		// @0CB: dup
		// @0CC: bipush 17 (0x11)
		// @0CE: ldc "}y\\th4"
		// @0D0: invokestatic game.C_100218_am.func_103105_z(java.lang.String)char[]
		// @0D3: invokestatic game.C_100218_am.func_103104_z(char[])java.lang.String
		// @0D6: aastore
		// @0D7: dup
		// @0D8: bipush 18 (0x12)
		// @0DA: ldc "}y\\`k4"
		// @0DC: invokestatic game.C_100218_am.func_103105_z(java.lang.String)char[]
		// @0DF: invokestatic game.C_100218_am.func_103104_z(char[])java.lang.String
		// @0E2: aastore
		// @0E3: putstatic java.lang.String[] game.C_100218_am.field_103116_O
		// @0E6: iconst_m1
		// @0E7: putstatic int game.C_100218_am.field_103115_N
		// @0EA: ldc "Lx\u0013[Ln4\u001cCDygRAHr4\u0010G\tidRVF<%@\u0002Ey`\u0006G[o8RL\\qv\u0017PZ<u\u001cF\tiz\u0016G[ow\u001dPLo"
		// @0EC: invokestatic game.C_100218_am.func_103105_z(java.lang.String)char[]
		// @0EF: invokestatic game.C_100218_am.func_103104_z(char[])java.lang.String
		// @0F2: putstatic java.lang.String game.C_100218_am.field_103118_I
		// @0F5: ldc "V"
		// @0F7: putstatic java.lang.String game.C_100218_am.field_103117_H
		// @0FA: ldc "Yy\u0002VP<g\u001eM]"
		// @0FC: invokestatic game.C_100218_am.func_103105_z(java.lang.String)char[]
		// @0FF: invokestatic game.C_100218_am.func_103104_z(char[])java.lang.String
		// @102: putstatic java.lang.String game.C_100218_am.field_103111_F
		// @105: return
	}
	
	private static char[] func_103105_z(String arg0)
	{
		// @00: aload_0
		// @01: invokevirtual java.lang.String.toCharArray()char[]
		// @04: dup
		// @05: arraylength
		// @06: iconst_2
		// @07: if_icmpge @13
		// @0A: dup
		// @0B: iconst_0
		// @0C: dup2
		// @0D: caload
		// @0E: bipush 41 (0x29)
		// @10: ixor
		// @11: i2c
		// @12: castore
		// @13: areturn
	}
	
	private static String func_103104_z(char[] arg0)
	{
		// @00: aload_0
		// @01: dup
		// @02: arraylength
		// @03: swap
		// @04: iconst_0
		// @05: istore_1
		// @06: goto @4C
		// @09: dup
		// @0A: iload_1
		// @0B: dup2
		// @0C: caload
		// @0D: iload_1
		// @0E: iconst_5
		// @0F: irem
		// @10: tableswitch def: @44, for 0: @30, for 1: @35, for 2: @3A, for 3: @3F
		// @30: bipush 28 (0x1C)
		// @32: goto @46
		// @35: bipush 20 (0x14)
		// @37: goto @46
		// @3A: bipush 114 (0x72)
		// @3C: goto @46
		// @3F: bipush 34 (0x22)
		// @41: goto @46
		// @44: bipush 41 (0x29)
		// @46: ixor
		// @47: i2c
		// @48: castore
		// @49: iinc #1 +1
		// @4C: swap
		// @4D: dup_x1
		// @4E: iload_1
		// @4F: if_icmpgt @09
		// @52: new java.lang.String
		// @55: dup_x1
		// @56: swap
		// @57: invokespecial java.lang.String.<init>(char[])void
		// @5A: invokevirtual java.lang.String.intern()java.lang.String
		// @5D: areturn
	}
}
