package game;

import java.awt.Canvas;

final class C_100178_cg implements Runnable
{
	static C_100098_h field_105688_d;
	static C_100037_wb field_105686_f;
	static C_100202_qi field_105689_e;
	private C_100300_kc field_105687_g;
	static C_100201_qj field_105692_a;
	private boolean field_105691_c;
	int field_105690_b;
	private Thread field_105694_h;
	private static final String[] field_105693_z;
	
	public final void run()
	{
		// @00: getstatic int game.SteelSentinels.field_105275_O
		// @03: istore #5
		// @05: aload_0
		// @06: getfield boolean game.C_100178_cg.field_105691_c
		// @09: ifne @BF
		// @0C: aload_0
		// @0D: getfield game.C_100300_kc game.C_100178_cg.field_105687_g
		// @10: dup
		// @11: astore_2
		// @12: monitorenter
		// @13: aload_0
		// @14: getfield game.C_100300_kc game.C_100178_cg.field_105687_g
		// @17: bipush -30 (0xE2)
		// @19: invokevirtual game.C_100300_kc.func_107059_f(int)game.C_100325_id
		// @1C: checkcast game.C_100238_ol
		// @1F: astore_1
		// @20: iload #5
		// @22: ifne @CE
		// @25: aload_1
		// @26: ifnull @40
		// @29: goto @2D
		// @2C: athrow
		// @2D: aload_0
		// @2E: dup
		// @2F: getfield int game.C_100178_cg.field_105690_b
		// @32: iconst_1
		// @33: isub
		// @34: putfield int game.C_100178_cg.field_105690_b
		// @37: iload #5
		// @39: ifeq @53
		// @3C: goto @40
		// @3F: athrow
		// @40: aload_0
		// @41: getfield game.C_100300_kc game.C_100178_cg.field_105687_g
		// @44: invokevirtual java.lang.Object.wait()void
		// @47: goto @4C
		// @4A: athrow
		// @4B: astore_3
		// @4C: aload_2
		// @4D: monitorexit
		// @4E: iload #5
		// @50: ifeq @05
		// @53: aload_2
		// @54: monitorexit
		// @55: goto @5F
		// @58: astore #4
		// @5A: aload_2
		// @5B: monitorexit
		// @5C: aload #4
		// @5E: athrow
		// @5F: aload_1
		// @60: getfield int game.C_100238_ol.field_101695_P
		// @63: iconst_2
		// @64: if_icmpne @89
		// @67: aload_1
		// @68: getfield game.C_100091_m game.C_100238_ol.field_101699_N
		// @6B: aload_1
		// @6C: getfield long game.C_100238_ol.field_101484_o
		// @6F: l2i
		// @70: aload_1
		// @71: getfield byte[] game.C_100238_ol.field_101703_K
		// @74: aload_1
		// @75: getfield byte[] game.C_100238_ol.field_101703_K
		// @78: arraylength
		// @79: sipush -3598 (0xF1F2)
		// @7C: invokevirtual game.C_100091_m.func_104501_a(int, byte[], int, int)boolean
		// @7F: pop
		// @80: iload #5
		// @82: ifeq @AB
		// @85: goto @89
		// @88: athrow
		// @89: aload_1
		// @8A: getfield int game.C_100238_ol.field_101695_P
		// @8D: iconst_3
		// @8E: if_icmpne @AB
		// @91: goto @95
		// @94: athrow
		// @95: aload_1
		// @96: aload_1
		// @97: getfield game.C_100091_m game.C_100238_ol.field_101699_N
		// @9A: bipush 40 (0x28)
		// @9C: aload_1
		// @9D: getfield long game.C_100238_ol.field_101484_o
		// @A0: l2i
		// @A1: invokevirtual game.C_100091_m.func_104505_a(byte, int)byte[]
		// @A4: putfield byte[] game.C_100238_ol.field_101703_K
		// @A7: goto @AB
		// @AA: athrow
		// @AB: goto @B5
		// @AE: astore_2
		// @AF: iconst_1
		// @B0: aconst_null
		// @B1: aload_2
		// @B2: invokestatic game.C_100036_gg.func_103142_a(int, java.lang.String, java.lang.Throwable)void
		// @B5: aload_1
		// @B6: iconst_0
		// @B7: putfield boolean game.C_100238_ol.field_101661_C
		// @BA: iload #5
		// @BC: ifeq @05
		// @BF: goto @CE
		// @C2: astore_1
		// @C3: aload_1
		// @C4: getstatic java.lang.String[] game.C_100178_cg.field_105693_z
		// @C7: bipush 6 (0x06)
		// @C9: aaload
		// @CA: invokestatic game.C_100181_cf.func_105695_a(java.lang.Throwable, java.lang.String)game.C_100170_cm
		// @CD: athrow
		// @CE: return
	}
	
	static final C_100243_pd[] func_105681_a(C_100278_nd arg0, int arg1)
	{
		// @000: getstatic int game.SteelSentinels.field_105275_O
		// @003: istore #7
		// @005: aload_0
		// @006: bipush 8 (0x08)
		// @008: sipush 15738 (0x3D7A)
		// @00B: invokevirtual game.C_100278_nd.func_101195_i(int, int)int
		// @00E: istore_2
		// @00F: iload_2
		// @010: ifle @015
		// @013: aconst_null
		// @014: areturn
		// @015: aload_0
		// @016: bipush 12 (0x0C)
		// @018: iload_1
		// @019: sipush -4502 (0xEE6A)
		// @01C: ixor
		// @01D: invokevirtual game.C_100278_nd.func_101195_i(int, int)int
		// @020: istore_3
		// @021: iload_1
		// @022: sipush -11504 (0xD310)
		// @025: if_icmpeq @033
		// @028: aconst_null
		// @029: checkcast game.C_100098_h
		// @02C: putstatic game.C_100098_h game.C_100178_cg.field_105688_d
		// @02F: goto @033
		// @032: athrow
		// @033: iload_3
		// @034: anewarray game.C_100243_pd
		// @037: astore #4
		// @039: iconst_0
		// @03A: istore #5
		// @03C: iload #5
		// @03E: iconst_m1
		// @03F: ixor
		// @040: iload_3
		// @041: iconst_m1
		// @042: ixor
		// @043: if_icmple @0D8
		// @046: aload_0
		// @047: bipush 115 (0x73)
		// @049: invokestatic game.C_100210_qa.func_101041_a(game.C_100278_nd, int)boolean
		// @04C: ifeq @0B2
		// @04F: new game.C_100243_pd
		// @052: dup
		// @053: invokespecial game.C_100243_pd.<init>()void
		// @056: astore #6
		// @058: aload_0
		// @059: bipush 24 (0x18)
		// @05B: sipush 15738 (0x3D7A)
		// @05E: invokevirtual game.C_100278_nd.func_101195_i(int, int)int
		// @061: pop
		// @062: aload_0
		// @063: bipush 24 (0x18)
		// @065: sipush 15738 (0x3D7A)
		// @068: invokevirtual game.C_100278_nd.func_101195_i(int, int)int
		// @06B: pop
		// @06C: aload #6
		// @06E: aload_0
		// @06F: bipush 24 (0x18)
		// @071: sipush 15738 (0x3D7A)
		// @074: invokevirtual game.C_100278_nd.func_101195_i(int, int)int
		// @077: putfield int game.C_100243_pd.field_106361_a
		// @07A: aload_0
		// @07B: bipush 9 (0x09)
		// @07D: iload_1
		// @07E: sipush 27242 (0x6A6A)
		// @081: iadd
		// @082: invokevirtual game.C_100278_nd.func_101195_i(int, int)int
		// @085: pop
		// @086: aload_0
		// @087: bipush 12 (0x0C)
		// @089: sipush 15738 (0x3D7A)
		// @08C: invokevirtual game.C_100278_nd.func_101195_i(int, int)int
		// @08F: pop
		// @090: aload_0
		// @091: bipush 12 (0x0C)
		// @093: iload_1
		// @094: sipush 27242 (0x6A6A)
		// @097: iadd
		// @098: invokevirtual game.C_100278_nd.func_101195_i(int, int)int
		// @09B: pop
		// @09C: aload_0
		// @09D: bipush 12 (0x0C)
		// @09F: sipush 15738 (0x3D7A)
		// @0A2: invokevirtual game.C_100278_nd.func_101195_i(int, int)int
		// @0A5: pop
		// @0A6: aload #4
		// @0A8: iload #5
		// @0AA: aload #6
		// @0AC: aastore
		// @0AD: iload #7
		// @0AF: ifeq @0D0
		// @0B2: aload_0
		// @0B3: bipush 127 (0x7F)
		// @0B5: iload #5
		// @0B7: iconst_m1
		// @0B8: iadd
		// @0B9: invokestatic game.C_100305_km.func_103222_b(int, int)int
		// @0BC: iload_1
		// @0BD: sipush -4502 (0xEE6A)
		// @0C0: ixor
		// @0C1: invokevirtual game.C_100278_nd.func_101195_i(int, int)int
		// @0C4: istore #6
		// @0C6: aload #4
		// @0C8: iload #5
		// @0CA: aload #4
		// @0CC: iload #6
		// @0CE: aaload
		// @0CF: aastore
		// @0D0: iinc #5 +1
		// @0D3: iload #7
		// @0D5: ifeq @03C
		// @0D8: aload #4
		// @0DA: areturn
		// @0DB: astore_2
		// @0DC: aload_2
		// @0DD: new java.lang.StringBuilder
		// @0E0: dup
		// @0E1: invokespecial java.lang.StringBuilder.<init>()void
		// @0E4: getstatic java.lang.String[] game.C_100178_cg.field_105693_z
		// @0E7: iconst_0
		// @0E8: aaload
		// @0E9: invokevirtual java.lang.StringBuilder.append(java.lang.String)java.lang.StringBuilder
		// @0EC: aload_0
		// @0ED: ifnull @0F9
		// @0F0: getstatic java.lang.String[] game.C_100178_cg.field_105693_z
		// @0F3: iconst_2
		// @0F4: aaload
		// @0F5: goto @0FE
		// @0F8: athrow
		// @0F9: getstatic java.lang.String[] game.C_100178_cg.field_105693_z
		// @0FC: iconst_1
		// @0FD: aaload
		// @0FE: invokevirtual java.lang.StringBuilder.append(java.lang.String)java.lang.StringBuilder
		// @101: bipush 44 (0x2C)
		// @103: invokevirtual java.lang.StringBuilder.append(char)java.lang.StringBuilder
		// @106: iload_1
		// @107: invokevirtual java.lang.StringBuilder.append(int)java.lang.StringBuilder
		// @10A: bipush 41 (0x29)
		// @10C: invokevirtual java.lang.StringBuilder.append(char)java.lang.StringBuilder
		// @10F: invokevirtual java.lang.StringBuilder.toString()java.lang.String
		// @112: invokestatic game.C_100181_cf.func_105695_a(java.lang.Throwable, java.lang.String)game.C_100170_cm
		// @115: athrow
	}
	
	public static void func_105674_b(int arg0)
	{
		// @00: aconst_null
		// @01: putstatic game.C_100201_qj game.C_100178_cg.field_105692_a
		// @04: bipush -123 (0x85)
		// @06: iload_0
		// @07: bipush -19 (0xED)
		// @09: isub
		// @0A: bipush 56 (0x38)
		// @0C: idiv
		// @0D: irem
		// @0E: istore_1
		// @0F: aconst_null
		// @10: putstatic game.C_100098_h game.C_100178_cg.field_105688_d
		// @13: aconst_null
		// @14: putstatic game.C_100202_qi game.C_100178_cg.field_105689_e
		// @17: aconst_null
		// @18: putstatic game.C_100037_wb game.C_100178_cg.field_105686_f
		// @1B: goto @40
		// @1E: astore_1
		// @1F: aload_1
		// @20: new java.lang.StringBuilder
		// @23: dup
		// @24: invokespecial java.lang.StringBuilder.<init>()void
		// @27: getstatic java.lang.String[] game.C_100178_cg.field_105693_z
		// @2A: bipush 7 (0x07)
		// @2C: aaload
		// @2D: invokevirtual java.lang.StringBuilder.append(java.lang.String)java.lang.StringBuilder
		// @30: iload_0
		// @31: invokevirtual java.lang.StringBuilder.append(int)java.lang.StringBuilder
		// @34: bipush 41 (0x29)
		// @36: invokevirtual java.lang.StringBuilder.append(char)java.lang.StringBuilder
		// @39: invokevirtual java.lang.StringBuilder.toString()java.lang.String
		// @3C: invokestatic game.C_100181_cf.func_105695_a(java.lang.Throwable, java.lang.String)game.C_100170_cm
		// @3F: athrow
		// @40: return
	}
	
	final C_100238_ol func_105684_a(C_100091_m arg0, byte arg1, int arg2)
	{
		// @000: getstatic int game.SteelSentinels.field_105275_O
		// @003: istore #8
		// @005: new game.C_100238_ol
		// @008: dup
		// @009: invokespecial game.C_100238_ol.<init>()void
		// @00C: astore #4
		// @00E: aload #4
		// @010: iconst_1
		// @011: putfield int game.C_100238_ol.field_101695_P
		// @014: aload_0
		// @015: getfield game.C_100300_kc game.C_100178_cg.field_105687_g
		// @018: dup
		// @019: astore #5
		// @01B: monitorenter
		// @01C: aload_0
		// @01D: getfield game.C_100300_kc game.C_100178_cg.field_105687_g
		// @020: sipush -9190 (0xDC1A)
		// @023: invokevirtual game.C_100300_kc.func_107065_a(int)game.C_100325_id
		// @026: checkcast game.C_100238_ol
		// @029: astore #6
		// @02B: aconst_null
		// @02C: aload #6
		// @02E: if_acmpeq @093
		// @031: iload_3
		// @032: i2l
		// @033: ldc2_w -1
		// @036: lxor
		// @037: aload #6
		// @039: getfield long game.C_100238_ol.field_101484_o
		// @03C: ldc2_w -1
		// @03F: lxor
		// @040: lcmp
		// @041: iload #8
		// @043: ifne @0AB
		// @046: ifne @081
		// @049: goto @04D
		// @04C: athrow
		// @04D: aload #6
		// @04F: getfield game.C_100091_m game.C_100238_ol.field_101699_N
		// @052: aload_1
		// @053: if_acmpne @081
		// @056: goto @05A
		// @059: athrow
		// @05A: aload #6
		// @05C: getfield int game.C_100238_ol.field_101695_P
		// @05F: iconst_2
		// @060: if_icmpeq @06B
		// @063: goto @067
		// @066: athrow
		// @067: goto @081
		// @06A: athrow
		// @06B: aload #4
		// @06D: aload #6
		// @06F: getfield byte[] game.C_100238_ol.field_101703_K
		// @072: putfield byte[] game.C_100238_ol.field_101703_K
		// @075: aload #4
		// @077: iconst_0
		// @078: putfield boolean game.C_100238_ol.field_101661_C
		// @07B: aload #4
		// @07D: aload #5
		// @07F: monitorexit
		// @080: areturn
		// @081: aload_0
		// @082: getfield game.C_100300_kc game.C_100178_cg.field_105687_g
		// @085: iconst_0
		// @086: invokevirtual game.C_100300_kc.func_107063_c(int)game.C_100325_id
		// @089: checkcast game.C_100238_ol
		// @08C: astore #6
		// @08E: iload #8
		// @090: ifeq @02B
		// @093: aload #5
		// @095: monitorexit
		// @096: goto @0A1
		// @099: astore #7
		// @09B: aload #5
		// @09D: monitorexit
		// @09E: aload #7
		// @0A0: athrow
		// @0A1: bipush -101 (0x9B)
		// @0A3: bipush 56 (0x38)
		// @0A5: iload_2
		// @0A6: isub
		// @0A7: bipush 48 (0x30)
		// @0A9: idiv
		// @0AA: idiv
		// @0AB: istore #5
		// @0AD: aload #4
		// @0AF: aload_1
		// @0B0: bipush 40 (0x28)
		// @0B2: iload_3
		// @0B3: invokevirtual game.C_100091_m.func_104505_a(byte, int)byte[]
		// @0B6: putfield byte[] game.C_100238_ol.field_101703_K
		// @0B9: aload #4
		// @0BB: iconst_0
		// @0BC: putfield boolean game.C_100238_ol.field_101661_C
		// @0BF: aload #4
		// @0C1: iconst_1
		// @0C2: putfield boolean game.C_100238_ol.field_101657_D
		// @0C5: aload #4
		// @0C7: areturn
		// @0C8: astore #4
		// @0CA: aload #4
		// @0CC: new java.lang.StringBuilder
		// @0CF: dup
		// @0D0: invokespecial java.lang.StringBuilder.<init>()void
		// @0D3: getstatic java.lang.String[] game.C_100178_cg.field_105693_z
		// @0D6: bipush 10 (0x0A)
		// @0D8: aaload
		// @0D9: invokevirtual java.lang.StringBuilder.append(java.lang.String)java.lang.StringBuilder
		// @0DC: aload_1
		// @0DD: ifnull @0E9
		// @0E0: getstatic java.lang.String[] game.C_100178_cg.field_105693_z
		// @0E3: iconst_2
		// @0E4: aaload
		// @0E5: goto @0EE
		// @0E8: athrow
		// @0E9: getstatic java.lang.String[] game.C_100178_cg.field_105693_z
		// @0EC: iconst_1
		// @0ED: aaload
		// @0EE: invokevirtual java.lang.StringBuilder.append(java.lang.String)java.lang.StringBuilder
		// @0F1: bipush 44 (0x2C)
		// @0F3: invokevirtual java.lang.StringBuilder.append(char)java.lang.StringBuilder
		// @0F6: iload_2
		// @0F7: invokevirtual java.lang.StringBuilder.append(int)java.lang.StringBuilder
		// @0FA: bipush 44 (0x2C)
		// @0FC: invokevirtual java.lang.StringBuilder.append(char)java.lang.StringBuilder
		// @0FF: iload_3
		// @100: invokevirtual java.lang.StringBuilder.append(int)java.lang.StringBuilder
		// @103: bipush 41 (0x29)
		// @105: invokevirtual java.lang.StringBuilder.append(char)java.lang.StringBuilder
		// @108: invokevirtual java.lang.StringBuilder.toString()java.lang.String
		// @10B: invokestatic game.C_100181_cf.func_105695_a(java.lang.Throwable, java.lang.String)game.C_100170_cm
		// @10E: athrow
	}
	
	static final int func_105682_a(byte arg0)
	{
		// @000: getstatic int game.SteelSentinels.field_105275_O
		// @003: istore #7
		// @005: iload_0
		// @006: bipush 102 (0x66)
		// @008: if_icmpeq @019
		// @00B: aconst_null
		// @00C: checkcast game.C_100278_nd
		// @00F: bipush -15 (0xF1)
		// @011: invokestatic game.C_100178_cg.func_105681_a(game.C_100278_nd, int)game.C_100243_pd[]
		// @014: pop
		// @015: goto @019
		// @018: athrow
		// @019: iconst_0
		// @01A: istore_1
		// @01B: iconst_0
		// @01C: istore_2
		// @01D: bipush 64 (0x40)
		// @01F: invokestatic game.C_100189_ri.func_105748_a(int)boolean
		// @022: ifeq @057
		// @025: getstatic game.C_100333_ij game.C_100102_w.field_104631_f
		// @028: bipush -61 (0xC3)
		// @02A: invokevirtual game.C_100333_ij.func_107328_a(int)void
		// @02D: getstatic game.C_100333_ij game.C_100102_w.field_104631_f
		// @030: iconst_1
		// @031: invokevirtual game.C_100333_ij.func_107339_b(boolean)boolean
		// @034: iload #7
		// @036: ifne @07E
		// @039: ifeq @042
		// @03C: goto @040
		// @03F: athrow
		// @040: iconst_1
		// @041: istore_1
		// @042: getstatic int game.C_100293_kj.field_106890_c
		// @045: iconst_m1
		// @046: ixor
		// @047: bipush -14 (0xF2)
		// @049: if_icmpeq @050
		// @04C: goto @01D
		// @04F: athrow
		// @050: iconst_1
		// @051: istore_2
		// @052: iload #7
		// @054: ifeq @01D
		// @057: getstatic game.C_100333_ij game.C_100102_w.field_104631_f
		// @05A: bipush 80 (0x50)
		// @05C: sipush 3939 (0x0F63)
		// @05F: getstatic int game.C_100125_tm.field_100745_p
		// @062: getstatic int game.C_100340_je.field_102981_m
		// @065: invokestatic game.C_100077_d.func_103315_b(int, int, int)int
		// @068: sipush 3939 (0x0F63)
		// @06B: getstatic int game.C_100338_jc.field_105370_l
		// @06E: getstatic int game.C_100015_wh.field_103781_g
		// @071: invokestatic game.C_100077_d.func_103315_b(int, int, int)int
		// @074: invokevirtual game.C_100333_ij.func_107335_a(int, int, int)void
		// @077: getstatic game.C_100333_ij game.C_100102_w.field_104631_f
		// @07A: iconst_1
		// @07B: invokevirtual game.C_100333_ij.func_107339_b(boolean)boolean
		// @07E: ifne @084
		// @081: goto @086
		// @084: iconst_1
		// @085: istore_1
		// @086: iconst_0
		// @087: istore_3
		// @088: iload_1
		// @089: ifeq @099
		// @08C: getstatic game.C_100333_ij game.C_100102_w.field_104631_f
		// @08F: getfield int game.C_100333_ij.field_107347_b
		// @092: ifge @0BF
		// @095: goto @099
		// @098: athrow
		// @099: iload_2
		// @09A: ifeq @0E4
		// @09D: goto @0A1
		// @0A0: athrow
		// @0A1: bipush -3 (0xFD)
		// @0A3: getstatic int game.C_100078_ul.field_103285_pb
		// @0A6: iconst_m1
		// @0A7: ixor
		// @0A8: if_icmpeq @0E4
		// @0AB: goto @0AF
		// @0AE: athrow
		// @0AF: iload_0
		// @0B0: bipush -26 (0xE6)
		// @0B2: ixor
		// @0B3: invokestatic game.C_100130_tf.func_104953_a(int)void
		// @0B6: iload #7
		// @0B8: ifeq @0E4
		// @0BB: goto @0BF
		// @0BE: athrow
		// @0BF: getstatic int[] game.C_100064_ve.field_103014_w
		// @0C2: getstatic game.C_100333_ij game.C_100102_w.field_104631_f
		// @0C5: getfield int game.C_100333_ij.field_107347_b
		// @0C8: iaload
		// @0C9: istore_3
		// @0CA: iload_3
		// @0CB: iconst_m1
		// @0CC: ixor
		// @0CD: bipush -3 (0xFD)
		// @0CF: if_icmpeq @0DF
		// @0D2: iload_3
		// @0D3: iconst_5
		// @0D4: if_icmpeq @0DF
		// @0D7: goto @0DB
		// @0DA: athrow
		// @0DB: goto @0E4
		// @0DE: athrow
		// @0DF: bipush -128 (0x80)
		// @0E1: invokestatic game.C_100130_tf.func_104953_a(int)void
		// @0E4: iload_3
		// @0E5: ifne @128
		// @0E8: getstatic int game.C_100078_ul.field_103285_pb
		// @0EB: iconst_m1
		// @0EC: ixor
		// @0ED: bipush -3 (0xFD)
		// @0EF: if_icmpeq @0FA
		// @0F2: goto @0F6
		// @0F5: athrow
		// @0F6: goto @128
		// @0F9: athrow
		// @0FA: getstatic long game.C_100015_wh.field_103780_f
		// @0FD: lneg
		// @0FE: bipush 94 (0x5E)
		// @100: invokestatic game.C_100198_qn.func_105828_a(byte)long
		// @103: ladd
		// @104: lstore #4
		// @106: lload #4
		// @108: lneg
		// @109: ldc2_w 10999
		// @10C: ladd
		// @10D: ldc2_w 1000
		// @110: ldiv
		// @111: l2i
		// @112: istore #6
		// @114: iconst_m1
		// @115: iload #6
		// @117: iconst_m1
		// @118: ixor
		// @119: if_icmple @120
		// @11C: goto @128
		// @11F: athrow
		// @120: iconst_2
		// @121: istore_3
		// @122: iconst_5
		// @123: iconst_1
		// @124: iconst_1
		// @125: invokestatic game.C_100053_vn.func_102818_a(int, int, boolean)void
		// @128: iload_3
		// @129: ireturn
		// @12A: astore_1
		// @12B: aload_1
		// @12C: new java.lang.StringBuilder
		// @12F: dup
		// @130: invokespecial java.lang.StringBuilder.<init>()void
		// @133: getstatic java.lang.String[] game.C_100178_cg.field_105693_z
		// @136: iconst_3
		// @137: aaload
		// @138: invokevirtual java.lang.StringBuilder.append(java.lang.String)java.lang.StringBuilder
		// @13B: iload_0
		// @13C: invokevirtual java.lang.StringBuilder.append(int)java.lang.StringBuilder
		// @13F: bipush 41 (0x29)
		// @141: invokevirtual java.lang.StringBuilder.append(char)java.lang.StringBuilder
		// @144: invokevirtual java.lang.StringBuilder.toString()java.lang.String
		// @147: invokestatic game.C_100181_cf.func_105695_a(java.lang.Throwable, java.lang.String)game.C_100170_cm
		// @14A: athrow
	}
	
	static final boolean func_105685_a(int arg0)
	{
		// @00: iload_0
		// @01: bipush -3 (0xFD)
		// @03: if_icmpeq @08
		// @06: iconst_0
		// @07: ireturn
		// @08: aconst_null
		// @09: getstatic game.C_100286_nl game.C_100318_hj.field_107194_f
		// @0C: if_acmpeq @23
		// @0F: getstatic game.C_100268_mk game.C_100066_dl.field_101642_t
		// @12: bipush 118 (0x76)
		// @14: invokevirtual game.C_100268_mk.func_106663_a(int)boolean
		// @17: ifeq @23
		// @1A: goto @1E
		// @1D: athrow
		// @1E: iconst_1
		// @1F: goto @24
		// @22: athrow
		// @23: iconst_0
		// @24: ireturn
		// @25: astore_1
		// @26: aload_1
		// @27: new java.lang.StringBuilder
		// @2A: dup
		// @2B: invokespecial java.lang.StringBuilder.<init>()void
		// @2E: getstatic java.lang.String[] game.C_100178_cg.field_105693_z
		// @31: bipush 9 (0x09)
		// @33: aaload
		// @34: invokevirtual java.lang.StringBuilder.append(java.lang.String)java.lang.StringBuilder
		// @37: iload_0
		// @38: invokevirtual java.lang.StringBuilder.append(int)java.lang.StringBuilder
		// @3B: bipush 41 (0x29)
		// @3D: invokevirtual java.lang.StringBuilder.append(char)java.lang.StringBuilder
		// @40: invokevirtual java.lang.StringBuilder.toString()java.lang.String
		// @43: invokestatic game.C_100181_cf.func_105695_a(java.lang.Throwable, java.lang.String)game.C_100170_cm
		// @46: athrow
	}
	
	private final void func_105680_a(C_100238_ol arg0, int arg1)
	{
		// @00: aload_0
		// @01: getfield game.C_100300_kc game.C_100178_cg.field_105687_g
		// @04: dup
		// @05: astore_3
		// @06: monitorenter
		// @07: iload_2
		// @08: iconst_3
		// @09: if_icmpeq @0F
		// @0C: aload_3
		// @0D: monitorexit
		// @0E: return
		// @0F: aload_0
		// @10: getfield game.C_100300_kc game.C_100178_cg.field_105687_g
		// @13: bipush 127 (0x7F)
		// @15: aload_1
		// @16: invokevirtual game.C_100300_kc.func_107058_a(int, game.C_100325_id)void
		// @19: aload_0
		// @1A: dup
		// @1B: getfield int game.C_100178_cg.field_105690_b
		// @1E: iconst_1
		// @1F: iadd
		// @20: putfield int game.C_100178_cg.field_105690_b
		// @23: aload_0
		// @24: getfield game.C_100300_kc game.C_100178_cg.field_105687_g
		// @27: invokevirtual java.lang.Object.notifyAll()void
		// @2A: aload_3
		// @2B: monitorexit
		// @2C: goto @36
		// @2F: astore #4
		// @31: aload_3
		// @32: monitorexit
		// @33: aload #4
		// @35: athrow
		// @36: goto @75
		// @39: astore_3
		// @3A: aload_3
		// @3B: new java.lang.StringBuilder
		// @3E: dup
		// @3F: invokespecial java.lang.StringBuilder.<init>()void
		// @42: getstatic java.lang.String[] game.C_100178_cg.field_105693_z
		// @45: bipush 12 (0x0C)
		// @47: aaload
		// @48: invokevirtual java.lang.StringBuilder.append(java.lang.String)java.lang.StringBuilder
		// @4B: aload_1
		// @4C: ifnull @58
		// @4F: getstatic java.lang.String[] game.C_100178_cg.field_105693_z
		// @52: iconst_2
		// @53: aaload
		// @54: goto @5D
		// @57: athrow
		// @58: getstatic java.lang.String[] game.C_100178_cg.field_105693_z
		// @5B: iconst_1
		// @5C: aaload
		// @5D: invokevirtual java.lang.StringBuilder.append(java.lang.String)java.lang.StringBuilder
		// @60: bipush 44 (0x2C)
		// @62: invokevirtual java.lang.StringBuilder.append(char)java.lang.StringBuilder
		// @65: iload_2
		// @66: invokevirtual java.lang.StringBuilder.append(int)java.lang.StringBuilder
		// @69: bipush 41 (0x29)
		// @6B: invokevirtual java.lang.StringBuilder.append(char)java.lang.StringBuilder
		// @6E: invokevirtual java.lang.StringBuilder.toString()java.lang.String
		// @71: invokestatic game.C_100181_cf.func_105695_a(java.lang.Throwable, java.lang.String)game.C_100170_cm
		// @74: athrow
		// @75: return
	}
	
	final C_100238_ol func_105683_a(byte[] arg0, C_100091_m arg1, int arg2, int arg3)
	{
		// @00: new game.C_100238_ol
		// @03: dup
		// @04: invokespecial game.C_100238_ol.<init>()void
		// @07: astore #5
		// @09: aload #5
		// @0B: aload_1
		// @0C: putfield byte[] game.C_100238_ol.field_101703_K
		// @0F: aload #5
		// @11: iload_3
		// @12: i2l
		// @13: putfield long game.C_100238_ol.field_101484_o
		// @16: aload #5
		// @18: iconst_0
		// @19: putfield boolean game.C_100238_ol.field_101657_D
		// @1C: aload #5
		// @1E: aload_2
		// @1F: putfield game.C_100091_m game.C_100238_ol.field_101699_N
		// @22: aload #5
		// @24: iload #4
		// @26: putfield int game.C_100238_ol.field_101695_P
		// @29: aload_0
		// @2A: aload #5
		// @2C: iload #4
		// @2E: iconst_1
		// @2F: iadd
		// @30: invokespecial game.C_100178_cg.func_105680_a(game.C_100238_ol, int)void
		// @33: aload #5
		// @35: areturn
		// @36: astore #5
		// @38: aload #5
		// @3A: new java.lang.StringBuilder
		// @3D: dup
		// @3E: invokespecial java.lang.StringBuilder.<init>()void
		// @41: getstatic java.lang.String[] game.C_100178_cg.field_105693_z
		// @44: bipush 8 (0x08)
		// @46: aaload
		// @47: invokevirtual java.lang.StringBuilder.append(java.lang.String)java.lang.StringBuilder
		// @4A: aload_1
		// @4B: ifnull @57
		// @4E: getstatic java.lang.String[] game.C_100178_cg.field_105693_z
		// @51: iconst_2
		// @52: aaload
		// @53: goto @5C
		// @56: athrow
		// @57: getstatic java.lang.String[] game.C_100178_cg.field_105693_z
		// @5A: iconst_1
		// @5B: aaload
		// @5C: invokevirtual java.lang.StringBuilder.append(java.lang.String)java.lang.StringBuilder
		// @5F: bipush 44 (0x2C)
		// @61: invokevirtual java.lang.StringBuilder.append(char)java.lang.StringBuilder
		// @64: aload_2
		// @65: ifnull @71
		// @68: getstatic java.lang.String[] game.C_100178_cg.field_105693_z
		// @6B: iconst_2
		// @6C: aaload
		// @6D: goto @76
		// @70: athrow
		// @71: getstatic java.lang.String[] game.C_100178_cg.field_105693_z
		// @74: iconst_1
		// @75: aaload
		// @76: invokevirtual java.lang.StringBuilder.append(java.lang.String)java.lang.StringBuilder
		// @79: bipush 44 (0x2C)
		// @7B: invokevirtual java.lang.StringBuilder.append(char)java.lang.StringBuilder
		// @7E: iload_3
		// @7F: invokevirtual java.lang.StringBuilder.append(int)java.lang.StringBuilder
		// @82: bipush 44 (0x2C)
		// @84: invokevirtual java.lang.StringBuilder.append(char)java.lang.StringBuilder
		// @87: iload #4
		// @89: invokevirtual java.lang.StringBuilder.append(int)java.lang.StringBuilder
		// @8C: bipush 41 (0x29)
		// @8E: invokevirtual java.lang.StringBuilder.append(char)java.lang.StringBuilder
		// @91: invokevirtual java.lang.StringBuilder.toString()java.lang.String
		// @94: invokestatic game.C_100181_cf.func_105695_a(java.lang.Throwable, java.lang.String)game.C_100170_cm
		// @97: athrow
	}
	
	static final void func_105676_a(byte arg0, Canvas arg1)
	{
		// @00: iconst_m1
		// @01: aload_1
		// @02: invokestatic game.C_100172_ck.func_102100_a(int, java.awt.Component)void
		// @05: bipush -37 (0xDB)
		// @07: aload_1
		// @08: invokestatic game.C_100126_cb.func_103056_a(byte, java.awt.Component)void
		// @0B: bipush 109 (0x6D)
		// @0D: iload_0
		// @0E: bipush -17 (0xEF)
		// @10: isub
		// @11: bipush 39 (0x27)
		// @13: idiv
		// @14: irem
		// @15: istore_2
		// @16: aconst_null
		// @17: getstatic game.C_100089_fa game.C_100143_bl.field_105104_c
		// @1A: if_acmpne @21
		// @1D: goto @2B
		// @20: athrow
		// @21: getstatic game.C_100089_fa game.C_100143_bl.field_105104_c
		// @24: sipush 23265 (0x5AE1)
		// @27: aload_1
		// @28: invokevirtual game.C_100089_fa.func_103712_a(int, java.awt.Component)void
		// @2B: goto @69
		// @2E: astore_2
		// @2F: aload_2
		// @30: new java.lang.StringBuilder
		// @33: dup
		// @34: invokespecial java.lang.StringBuilder.<init>()void
		// @37: getstatic java.lang.String[] game.C_100178_cg.field_105693_z
		// @3A: iconst_5
		// @3B: aaload
		// @3C: invokevirtual java.lang.StringBuilder.append(java.lang.String)java.lang.StringBuilder
		// @3F: iload_0
		// @40: invokevirtual java.lang.StringBuilder.append(int)java.lang.StringBuilder
		// @43: bipush 44 (0x2C)
		// @45: invokevirtual java.lang.StringBuilder.append(char)java.lang.StringBuilder
		// @48: aload_1
		// @49: ifnull @55
		// @4C: getstatic java.lang.String[] game.C_100178_cg.field_105693_z
		// @4F: iconst_2
		// @50: aaload
		// @51: goto @5A
		// @54: athrow
		// @55: getstatic java.lang.String[] game.C_100178_cg.field_105693_z
		// @58: iconst_1
		// @59: aaload
		// @5A: invokevirtual java.lang.StringBuilder.append(java.lang.String)java.lang.StringBuilder
		// @5D: bipush 41 (0x29)
		// @5F: invokevirtual java.lang.StringBuilder.append(char)java.lang.StringBuilder
		// @62: invokevirtual java.lang.StringBuilder.toString()java.lang.String
		// @65: invokestatic game.C_100181_cf.func_105695_a(java.lang.Throwable, java.lang.String)game.C_100170_cm
		// @68: athrow
		// @69: return
	}
	
	final C_100238_ol func_105678_a(C_100091_m arg0, int arg1, byte arg2)
	{
		// @00: new game.C_100238_ol
		// @03: dup
		// @04: invokespecial game.C_100238_ol.<init>()void
		// @07: astore #4
		// @09: aload #4
		// @0B: iload_2
		// @0C: i2l
		// @0D: putfield long game.C_100238_ol.field_101484_o
		// @10: aload #4
		// @12: iconst_3
		// @13: putfield int game.C_100238_ol.field_101695_P
		// @16: aload #4
		// @18: iconst_0
		// @19: putfield boolean game.C_100238_ol.field_101657_D
		// @1C: aload #4
		// @1E: aload_1
		// @1F: putfield game.C_100091_m game.C_100238_ol.field_101699_N
		// @22: aload_0
		// @23: aload #4
		// @25: iconst_3
		// @26: invokespecial game.C_100178_cg.func_105680_a(game.C_100238_ol, int)void
		// @29: bipush -58 (0xC6)
		// @2B: iload_3
		// @2C: bipush 74 (0x4A)
		// @2E: isub
		// @2F: bipush 42 (0x2A)
		// @31: idiv
		// @32: irem
		// @33: istore #5
		// @35: aload #4
		// @37: areturn
		// @38: astore #4
		// @3A: aload #4
		// @3C: new java.lang.StringBuilder
		// @3F: dup
		// @40: invokespecial java.lang.StringBuilder.<init>()void
		// @43: getstatic java.lang.String[] game.C_100178_cg.field_105693_z
		// @46: bipush 13 (0x0D)
		// @48: aaload
		// @49: invokevirtual java.lang.StringBuilder.append(java.lang.String)java.lang.StringBuilder
		// @4C: aload_1
		// @4D: ifnull @59
		// @50: getstatic java.lang.String[] game.C_100178_cg.field_105693_z
		// @53: iconst_2
		// @54: aaload
		// @55: goto @5E
		// @58: athrow
		// @59: getstatic java.lang.String[] game.C_100178_cg.field_105693_z
		// @5C: iconst_1
		// @5D: aaload
		// @5E: invokevirtual java.lang.StringBuilder.append(java.lang.String)java.lang.StringBuilder
		// @61: bipush 44 (0x2C)
		// @63: invokevirtual java.lang.StringBuilder.append(char)java.lang.StringBuilder
		// @66: iload_2
		// @67: invokevirtual java.lang.StringBuilder.append(int)java.lang.StringBuilder
		// @6A: bipush 44 (0x2C)
		// @6C: invokevirtual java.lang.StringBuilder.append(char)java.lang.StringBuilder
		// @6F: iload_3
		// @70: invokevirtual java.lang.StringBuilder.append(int)java.lang.StringBuilder
		// @73: bipush 41 (0x29)
		// @75: invokevirtual java.lang.StringBuilder.append(char)java.lang.StringBuilder
		// @78: invokevirtual java.lang.StringBuilder.toString()java.lang.String
		// @7B: invokestatic game.C_100181_cf.func_105695_a(java.lang.Throwable, java.lang.String)game.C_100170_cm
		// @7E: athrow
	}
	
	final void func_105679_b(byte arg0)
	{
		// @00: aload_0
		// @01: iconst_1
		// @02: putfield boolean game.C_100178_cg.field_105691_c
		// @05: aload_0
		// @06: getfield game.C_100300_kc game.C_100178_cg.field_105687_g
		// @09: dup
		// @0A: astore_2
		// @0B: monitorenter
		// @0C: aload_0
		// @0D: getfield game.C_100300_kc game.C_100178_cg.field_105687_g
		// @10: invokevirtual java.lang.Object.notifyAll()void
		// @13: iload_1
		// @14: bipush -73 (0xB7)
		// @16: if_icmple @23
		// @19: aconst_null
		// @1A: checkcast game.C_100278_nd
		// @1D: bipush -84 (0xAC)
		// @1F: invokestatic game.C_100178_cg.func_105681_a(game.C_100278_nd, int)game.C_100243_pd[]
		// @22: pop
		// @23: aload_2
		// @24: monitorexit
		// @25: goto @2D
		// @28: astore_3
		// @29: aload_2
		// @2A: monitorexit
		// @2B: aload_3
		// @2C: athrow
		// @2D: aload_0
		// @2E: getfield java.lang.Thread game.C_100178_cg.field_105694_h
		// @31: invokevirtual java.lang.Thread.join()void
		// @34: goto @38
		// @37: astore_2
		// @38: aload_0
		// @39: aconst_null
		// @3A: putfield java.lang.Thread game.C_100178_cg.field_105694_h
		// @3D: goto @61
		// @40: astore_2
		// @41: aload_2
		// @42: new java.lang.StringBuilder
		// @45: dup
		// @46: invokespecial java.lang.StringBuilder.<init>()void
		// @49: getstatic java.lang.String[] game.C_100178_cg.field_105693_z
		// @4C: iconst_4
		// @4D: aaload
		// @4E: invokevirtual java.lang.StringBuilder.append(java.lang.String)java.lang.StringBuilder
		// @51: iload_1
		// @52: invokevirtual java.lang.StringBuilder.append(int)java.lang.StringBuilder
		// @55: bipush 41 (0x29)
		// @57: invokevirtual java.lang.StringBuilder.append(char)java.lang.StringBuilder
		// @5A: invokevirtual java.lang.StringBuilder.toString()java.lang.String
		// @5D: invokestatic game.C_100181_cf.func_105695_a(java.lang.Throwable, java.lang.String)game.C_100170_cm
		// @60: athrow
		// @61: return
	}
	
	C_100178_cg(C_100201_qj arg0)
	{
		// @00: getstatic int game.SteelSentinels.field_105275_O
		// @03: istore_3
		// @04: aload_0
		// @05: invokespecial java.lang.Object.<init>()void
		// @08: aload_0
		// @09: new game.C_100300_kc
		// @0C: dup
		// @0D: invokespecial game.C_100300_kc.<init>()void
		// @10: putfield game.C_100300_kc game.C_100178_cg.field_105687_g
		// @13: aload_0
		// @14: iconst_0
		// @15: putfield boolean game.C_100178_cg.field_105691_c
		// @18: aload_0
		// @19: iconst_0
		// @1A: putfield int game.C_100178_cg.field_105690_b
		// @1D: aload_1
		// @1E: iconst_5
		// @1F: bipush 28 (0x1C)
		// @21: aload_0
		// @22: invokevirtual game.C_100201_qj.func_105856_a(int, int, java.lang.Runnable)game.C_100331_ie
		// @25: astore_2
		// @26: iconst_0
		// @27: aload_2
		// @28: getfield int game.C_100331_ie.field_107293_f
		// @2B: if_icmpne @42
		// @2E: ldc2_w 10
		// @31: bipush -126 (0x82)
		// @33: invokestatic game.C_100138_bo.func_100396_a(long, int)void
		// @36: iload_3
		// @37: ifne @5E
		// @3A: iload_3
		// @3B: ifeq @26
		// @3E: goto @42
		// @41: athrow
		// @42: aload_2
		// @43: getfield int game.C_100331_ie.field_107293_f
		// @46: iconst_2
		// @47: if_icmpne @53
		// @4A: new java.lang.RuntimeException
		// @4D: dup
		// @4E: invokespecial java.lang.RuntimeException.<init>()void
		// @51: athrow
		// @52: athrow
		// @53: aload_0
		// @54: aload_2
		// @55: getfield java.lang.Object game.C_100331_ie.field_107294_g
		// @58: checkcast java.lang.Thread
		// @5B: putfield java.lang.Thread game.C_100178_cg.field_105694_h
		// @5E: goto @94
		// @61: astore_2
		// @62: aload_2
		// @63: new java.lang.StringBuilder
		// @66: dup
		// @67: invokespecial java.lang.StringBuilder.<init>()void
		// @6A: getstatic java.lang.String[] game.C_100178_cg.field_105693_z
		// @6D: bipush 11 (0x0B)
		// @6F: aaload
		// @70: invokevirtual java.lang.StringBuilder.append(java.lang.String)java.lang.StringBuilder
		// @73: aload_1
		// @74: ifnull @80
		// @77: getstatic java.lang.String[] game.C_100178_cg.field_105693_z
		// @7A: iconst_2
		// @7B: aaload
		// @7C: goto @85
		// @7F: athrow
		// @80: getstatic java.lang.String[] game.C_100178_cg.field_105693_z
		// @83: iconst_1
		// @84: aaload
		// @85: invokevirtual java.lang.StringBuilder.append(java.lang.String)java.lang.StringBuilder
		// @88: bipush 41 (0x29)
		// @8A: invokevirtual java.lang.StringBuilder.append(char)java.lang.StringBuilder
		// @8D: invokevirtual java.lang.StringBuilder.toString()java.lang.String
		// @90: invokestatic game.C_100181_cf.func_105695_a(java.lang.Throwable, java.lang.String)game.C_100170_cm
		// @93: athrow
		// @94: return
	}
	
	static
	{
		// @00: bipush 14 (0x0E)
		// @02: anewarray java.lang.String
		// @05: dup
		// @06: iconst_0
		// @07: ldc "\nd\u0006b`"
		// @09: invokestatic game.C_100178_cg.func_105677_z(java.lang.String)char[]
		// @0C: invokestatic game.C_100178_cg.func_105675_z(char[])java.lang.String
		// @0F: aastore
		// @10: dup
		// @11: iconst_1
		// @12: ldc "\u0007vDJ"
		// @14: invokestatic game.C_100178_cg.func_105677_z(java.lang.String)char[]
		// @17: invokestatic game.C_100178_cg.func_105675_z(char[])java.lang.String
		// @1A: aastore
		// @1B: dup
		// @1C: iconst_2
		// @1D: ldc "\u0012-\u0006\u00085"
		// @1F: invokestatic game.C_100178_cg.func_105677_z(java.lang.String)char[]
		// @22: invokestatic game.C_100178_cg.func_105675_z(char[])java.lang.String
		// @25: aastore
		// @26: dup
		// @27: iconst_3
		// @28: ldc "\nd\u0006a`"
		// @2A: invokestatic game.C_100178_cg.func_105677_z(java.lang.String)char[]
		// @2D: invokestatic game.C_100178_cg.func_105675_z(char[])java.lang.String
		// @30: aastore
		// @31: dup
		// @32: iconst_4
		// @33: ldc "\nd\u0006l`"
		// @35: invokestatic game.C_100178_cg.func_105677_z(java.lang.String)char[]
		// @38: invokestatic game.C_100178_cg.func_105675_z(char[])java.lang.String
		// @3B: aastore
		// @3C: dup
		// @3D: iconst_5
		// @3E: ldc "\nd\u0006n`"
		// @40: invokestatic game.C_100178_cg.func_105677_z(java.lang.String)char[]
		// @43: invokestatic game.C_100178_cg.func_105675_z(char[])java.lang.String
		// @46: aastore
		// @47: dup
		// @48: bipush 6 (0x06)
		// @4A: ldc "\nd\u0006T=\u0007+\u0001"
		// @4C: invokestatic game.C_100178_cg.func_105677_z(java.lang.String)char[]
		// @4F: invokestatic game.C_100178_cg.func_105675_z(char[])java.lang.String
		// @52: aastore
		// @53: dup
		// @54: bipush 7 (0x07)
		// @56: ldc "\nd\u0006g`"
		// @58: invokestatic game.C_100178_cg.func_105677_z(java.lang.String)char[]
		// @5B: invokestatic game.C_100178_cg.func_105675_z(char[])java.lang.String
		// @5E: aastore
		// @5F: dup
		// @60: bipush 8 (0x08)
		// @62: ldc "\nd\u0006e`"
		// @64: invokestatic game.C_100178_cg.func_105677_z(java.lang.String)char[]
		// @67: invokestatic game.C_100178_cg.func_105675_z(char[])java.lang.String
		// @6A: aastore
		// @6B: dup
		// @6C: bipush 9 (0x09)
		// @6E: ldc "\nd\u0006d`"
		// @70: invokestatic game.C_100178_cg.func_105677_z(java.lang.String)char[]
		// @73: invokestatic game.C_100178_cg.func_105675_z(char[])java.lang.String
		// @76: aastore
		// @77: dup
		// @78: bipush 10 (0x0A)
		// @7A: ldc "\nd\u0006c`"
		// @7C: invokestatic game.C_100178_cg.func_105677_z(java.lang.String)char[]
		// @7F: invokestatic game.C_100178_cg.func_105675_z(char[])java.lang.String
		// @82: aastore
		// @83: dup
		// @84: bipush 11 (0x0B)
		// @86: ldc "\nd\u0006\u001a!\u0007j\\\u0018`"
		// @88: invokestatic game.C_100178_cg.func_105677_z(java.lang.String)char[]
		// @8B: invokestatic game.C_100178_cg.func_105675_z(char[])java.lang.String
		// @8E: aastore
		// @8F: dup
		// @90: bipush 12 (0x0C)
		// @92: ldc "\nd\u0006``"
		// @94: invokestatic game.C_100178_cg.func_105677_z(java.lang.String)char[]
		// @97: invokestatic game.C_100178_cg.func_105675_z(char[])java.lang.String
		// @9A: aastore
		// @9B: dup
		// @9C: bipush 13 (0x0D)
		// @9E: ldc "\nd\u0006o`"
		// @A0: invokestatic game.C_100178_cg.func_105677_z(java.lang.String)char[]
		// @A3: invokestatic game.C_100178_cg.func_105675_z(char[])java.lang.String
		// @A6: aastore
		// @A7: putstatic java.lang.String[] game.C_100178_cg.field_105693_z
		// @AA: new game.C_100202_qi
		// @AD: dup
		// @AE: invokespecial game.C_100202_qi.<init>()void
		// @B1: putstatic game.C_100202_qi game.C_100178_cg.field_105689_e
		// @B4: return
	}
	
	private static char[] func_105677_z(String arg0)
	{
		// @00: aload_0
		// @01: invokevirtual java.lang.String.toCharArray()char[]
		// @04: dup
		// @05: arraylength
		// @06: iconst_2
		// @07: if_icmpge @13
		// @0A: dup
		// @0B: iconst_0
		// @0C: dup2
		// @0D: caload
		// @0E: bipush 72 (0x48)
		// @10: ixor
		// @11: i2c
		// @12: castore
		// @13: areturn
	}
	
	private static String func_105675_z(char[] arg0)
	{
		// @00: aload_0
		// @01: dup
		// @02: arraylength
		// @03: swap
		// @04: iconst_0
		// @05: istore_1
		// @06: goto @4B
		// @09: dup
		// @0A: iload_1
		// @0B: dup2
		// @0C: caload
		// @0D: iload_1
		// @0E: iconst_5
		// @0F: irem
		// @10: tableswitch def: @43, for 0: @30, for 1: @35, for 2: @39, for 3: @3E
		// @30: bipush 105 (0x69)
		// @32: goto @45
		// @35: iconst_3
		// @36: goto @45
		// @39: bipush 40 (0x28)
		// @3B: goto @45
		// @3E: bipush 38 (0x26)
		// @40: goto @45
		// @43: bipush 72 (0x48)
		// @45: ixor
		// @46: i2c
		// @47: castore
		// @48: iinc #1 +1
		// @4B: swap
		// @4C: dup_x1
		// @4D: iload_1
		// @4E: if_icmpgt @09
		// @51: new java.lang.String
		// @54: dup_x1
		// @55: swap
		// @56: invokespecial java.lang.String.<init>(char[])void
		// @59: invokevirtual java.lang.String.intern()java.lang.String
		// @5C: areturn
	}
}
