package game;

abstract class C_100205_qf
{
	C_100306_kn[] field_103677_g;
	static C_100268_mk field_103679_e;
	static C_100202_qi field_103676_f;
	static boolean field_103681_c;
	static int field_103678_d;
	static C_100202_qi field_103680_b;
	static String field_103682_a;
	private static final String[] field_103683_z;
	
	final int func_103666_a(int arg0, byte arg1, String arg2, int arg3)
	{
		// @00: getstatic int game.SteelSentinels.field_105275_O
		// @03: istore #10
		// @05: iload_2
		// @06: bipush 113 (0x71)
		// @08: if_icmpge @0E
		// @0B: bipush 49 (0x31)
		// @0D: ireturn
		// @0E: iconst_0
		// @0F: istore #5
		// @11: iconst_0
		// @12: istore #6
		// @14: aload_3
		// @15: invokevirtual java.lang.String.length()int
		// @18: istore #7
		// @1A: iconst_0
		// @1B: istore #8
		// @1D: iload #8
		// @1F: iload #7
		// @21: if_icmpge @7C
		// @24: aload_3
		// @25: iload #8
		// @27: invokevirtual java.lang.String.charAt(int)char
		// @2A: istore #9
		// @2C: iload #9
		// @2E: bipush 60 (0x3C)
		// @30: iload #10
		// @32: ifne @81
		// @35: if_icmpeq @71
		// @38: goto @3C
		// @3B: athrow
		// @3C: bipush 62 (0x3E)
		// @3E: iload #9
		// @40: if_icmpeq @69
		// @43: goto @47
		// @46: athrow
		// @47: iload #6
		// @49: ifne @74
		// @4C: goto @50
		// @4F: athrow
		// @50: iload #9
		// @52: iconst_m1
		// @53: ixor
		// @54: bipush -33 (0xDF)
		// @56: if_icmpne @74
		// @59: goto @5D
		// @5C: athrow
		// @5D: iinc #5 +1
		// @60: iload #10
		// @62: ifeq @74
		// @65: goto @69
		// @68: athrow
		// @69: iconst_0
		// @6A: istore #6
		// @6C: iload #10
		// @6E: ifeq @74
		// @71: iconst_1
		// @72: istore #6
		// @74: iinc #8 +1
		// @77: iload #10
		// @79: ifeq @1D
		// @7C: iconst_m1
		// @7D: iload #5
		// @7F: iconst_m1
		// @80: ixor
		// @81: if_icmpgt @87
		// @84: goto @93
		// @87: iload_1
		// @88: ineg
		// @89: iload #4
		// @8B: iadd
		// @8C: ldc 870949224 (0x33e9a168)
		// @8E: ishl
		// @8F: iload #5
		// @91: idiv
		// @92: ireturn
		// @93: iconst_0
		// @94: ireturn
		// @95: astore #5
		// @97: aload #5
		// @99: new java.lang.StringBuilder
		// @9C: dup
		// @9D: invokespecial java.lang.StringBuilder.<init>()void
		// @A0: getstatic java.lang.String[] game.C_100205_qf.field_103683_z
		// @A3: iconst_5
		// @A4: aaload
		// @A5: invokevirtual java.lang.StringBuilder.append(java.lang.String)java.lang.StringBuilder
		// @A8: iload_1
		// @A9: invokevirtual java.lang.StringBuilder.append(int)java.lang.StringBuilder
		// @AC: bipush 44 (0x2C)
		// @AE: invokevirtual java.lang.StringBuilder.append(char)java.lang.StringBuilder
		// @B1: iload_2
		// @B2: invokevirtual java.lang.StringBuilder.append(int)java.lang.StringBuilder
		// @B5: bipush 44 (0x2C)
		// @B7: invokevirtual java.lang.StringBuilder.append(char)java.lang.StringBuilder
		// @BA: aload_3
		// @BB: ifnull @C7
		// @BE: getstatic java.lang.String[] game.C_100205_qf.field_103683_z
		// @C1: iconst_3
		// @C2: aaload
		// @C3: goto @CC
		// @C6: athrow
		// @C7: getstatic java.lang.String[] game.C_100205_qf.field_103683_z
		// @CA: iconst_4
		// @CB: aaload
		// @CC: invokevirtual java.lang.StringBuilder.append(java.lang.String)java.lang.StringBuilder
		// @CF: bipush 44 (0x2C)
		// @D1: invokevirtual java.lang.StringBuilder.append(char)java.lang.StringBuilder
		// @D4: iload #4
		// @D6: invokevirtual java.lang.StringBuilder.append(int)java.lang.StringBuilder
		// @D9: bipush 41 (0x29)
		// @DB: invokevirtual java.lang.StringBuilder.append(char)java.lang.StringBuilder
		// @DE: invokevirtual java.lang.StringBuilder.toString()java.lang.String
		// @E1: invokestatic game.C_100181_cf.func_105695_a(java.lang.Throwable, java.lang.String)game.C_100170_cm
		// @E4: athrow
	}
	
	static final void func_103672_d(int arg0)
	{
		// @00: getstatic int game.SteelSentinels.field_105275_O
		// @03: istore_2
		// @04: aconst_null
		// @05: putstatic java.lang.String game.C_100119_ua.field_104909_i
		// @08: iconst_0
		// @09: putstatic int game.C_100291_jj.field_106878_a
		// @0C: iconst_0
		// @0D: putstatic int game.C_100316_lc.field_102407_A
		// @10: iload_0
		// @11: sipush -31849 (0x8397)
		// @14: if_icmpeq @22
		// @17: aconst_null
		// @18: checkcast game.C_100202_qi
		// @1B: putstatic game.C_100202_qi game.C_100205_qf.field_103680_b
		// @1E: goto @22
		// @21: athrow
		// @22: getstatic game.C_100202_qi game.C_100085_a.field_102569_L
		// @25: bipush -102 (0x9A)
		// @27: invokevirtual game.C_100202_qi.func_105905_b(byte)void
		// @2A: getstatic game.C_100202_qi game.C_100312_ld.field_107155_b
		// @2D: bipush -112 (0x90)
		// @2F: invokevirtual game.C_100202_qi.func_105905_b(byte)void
		// @32: getstatic game.C_100105_eg game.C_100170_cm.field_105536_f
		// @35: iconst_0
		// @36: invokevirtual game.C_100105_eg.func_104730_b(int)game.C_100325_id
		// @39: astore_1
		// @3A: aload_1
		// @3B: ifnull @59
		// @3E: aload_1
		// @3F: bipush 8 (0x08)
		// @41: invokevirtual game.C_100325_id.func_101479_c(byte)void
		// @44: getstatic game.C_100105_eg game.C_100170_cm.field_105536_f
		// @47: bipush 8 (0x08)
		// @49: invokevirtual game.C_100105_eg.func_104729_a(byte)game.C_100325_id
		// @4C: astore_1
		// @4D: iload_2
		// @4E: ifne @61
		// @51: iload_2
		// @52: ifeq @3A
		// @55: goto @59
		// @58: athrow
		// @59: getstatic game.C_100105_eg game.C_100003_ga.field_103533_h
		// @5C: iconst_0
		// @5D: invokevirtual game.C_100105_eg.func_104730_b(int)game.C_100325_id
		// @60: astore_1
		// @61: aload_1
		// @62: ifnull @80
		// @65: aload_1
		// @66: bipush 8 (0x08)
		// @68: invokevirtual game.C_100325_id.func_101479_c(byte)void
		// @6B: getstatic game.C_100105_eg game.C_100003_ga.field_103533_h
		// @6E: bipush 8 (0x08)
		// @70: invokevirtual game.C_100105_eg.func_104729_a(byte)game.C_100325_id
		// @73: astore_1
		// @74: iload_2
		// @75: ifne @84
		// @78: iload_2
		// @79: ifeq @61
		// @7C: goto @80
		// @7F: athrow
		// @80: iconst_0
		// @81: putstatic int game.C_100062_dk.field_104281_d
		// @84: goto @A9
		// @87: astore_1
		// @88: aload_1
		// @89: new java.lang.StringBuilder
		// @8C: dup
		// @8D: invokespecial java.lang.StringBuilder.<init>()void
		// @90: getstatic java.lang.String[] game.C_100205_qf.field_103683_z
		// @93: bipush 77 (0x4D)
		// @95: aaload
		// @96: invokevirtual java.lang.StringBuilder.append(java.lang.String)java.lang.StringBuilder
		// @99: iload_0
		// @9A: invokevirtual java.lang.StringBuilder.append(int)java.lang.StringBuilder
		// @9D: bipush 41 (0x29)
		// @9F: invokevirtual java.lang.StringBuilder.append(char)java.lang.StringBuilder
		// @A2: invokevirtual java.lang.StringBuilder.toString()java.lang.String
		// @A5: invokestatic game.C_100181_cf.func_105695_a(java.lang.Throwable, java.lang.String)game.C_100170_cm
		// @A8: athrow
		// @A9: return
	}
	
	final int func_103674_b(int arg0)
	{
		// @00: iload_1
		// @01: ifeq @0D
		// @04: bipush 6 (0x06)
		// @06: invokestatic game.C_100205_qf.func_103672_d(int)void
		// @09: goto @0D
		// @0C: athrow
		// @0D: aload_0
		// @0E: getfield game.C_100306_kn[] game.C_100205_qf.field_103677_g
		// @11: ifnull @21
		// @14: iconst_0
		// @15: aload_0
		// @16: getfield game.C_100306_kn[] game.C_100205_qf.field_103677_g
		// @19: arraylength
		// @1A: if_icmplt @26
		// @1D: goto @21
		// @20: athrow
		// @21: iconst_0
		// @22: goto @40
		// @25: athrow
		// @26: aload_0
		// @27: getfield game.C_100306_kn[] game.C_100205_qf.field_103677_g
		// @2A: aload_0
		// @2B: getfield game.C_100306_kn[] game.C_100205_qf.field_103677_g
		// @2E: arraylength
		// @2F: iconst_1
		// @30: isub
		// @31: aaload
		// @32: getfield int game.C_100306_kn.field_107135_a
		// @35: aload_0
		// @36: getfield game.C_100306_kn[] game.C_100205_qf.field_103677_g
		// @39: iconst_0
		// @3A: aaload
		// @3B: getfield int game.C_100306_kn.field_107129_f
		// @3E: ineg
		// @3F: iadd
		// @40: ireturn
		// @41: astore_2
		// @42: aload_2
		// @43: new java.lang.StringBuilder
		// @46: dup
		// @47: invokespecial java.lang.StringBuilder.<init>()void
		// @4A: getstatic java.lang.String[] game.C_100205_qf.field_103683_z
		// @4D: iconst_0
		// @4E: aaload
		// @4F: invokevirtual java.lang.StringBuilder.append(java.lang.String)java.lang.StringBuilder
		// @52: iload_1
		// @53: invokevirtual java.lang.StringBuilder.append(int)java.lang.StringBuilder
		// @56: bipush 41 (0x29)
		// @58: invokevirtual java.lang.StringBuilder.append(char)java.lang.StringBuilder
		// @5B: invokevirtual java.lang.StringBuilder.toString()java.lang.String
		// @5E: invokestatic game.C_100181_cf.func_105695_a(java.lang.Throwable, java.lang.String)game.C_100170_cm
		// @61: athrow
	}
	
	static final C_100154_sl func_103670_a(int arg0)
	{
		// @00: iload_0
		// @01: ifeq @09
		// @04: aconst_null
		// @05: checkcast game.C_100154_sl
		// @08: areturn
		// @09: new game.C_100154_sl
		// @0C: dup
		// @0D: bipush 97 (0x61)
		// @0F: invokestatic game.C_100301_kb.func_107076_b(byte)java.lang.String
		// @12: iconst_1
		// @13: invokestatic game.C_100295_kh.func_105281_a(boolean)boolean
		// @16: invokespecial game.C_100154_sl.<init>(java.lang.String, boolean)void
		// @19: areturn
		// @1A: astore_1
		// @1B: aload_1
		// @1C: new java.lang.StringBuilder
		// @1F: dup
		// @20: invokespecial java.lang.StringBuilder.<init>()void
		// @23: getstatic java.lang.String[] game.C_100205_qf.field_103683_z
		// @26: iconst_2
		// @27: aaload
		// @28: invokevirtual java.lang.StringBuilder.append(java.lang.String)java.lang.StringBuilder
		// @2B: iload_0
		// @2C: invokevirtual java.lang.StringBuilder.append(int)java.lang.StringBuilder
		// @2F: bipush 41 (0x29)
		// @31: invokevirtual java.lang.StringBuilder.append(char)java.lang.StringBuilder
		// @34: invokevirtual java.lang.StringBuilder.toString()java.lang.String
		// @37: invokestatic game.C_100181_cf.func_105695_a(java.lang.Throwable, java.lang.String)game.C_100170_cm
		// @3A: athrow
	}
	
	static final void func_103668_a(byte arg0)
	{
		// @00: bipush 12 (0x0C)
		// @02: invokestatic game.C_100123_uc.func_104914_b(int)void
		// @05: getstatic java.awt.Canvas game.C_100034_gi.field_104033_a
		// @08: ifnonnull @0F
		// @0B: goto @17
		// @0E: athrow
		// @0F: bipush 39 (0x27)
		// @11: getstatic java.awt.Canvas game.C_100034_gi.field_104033_a
		// @14: invokestatic game.C_100178_cg.func_105676_a(byte, java.awt.Canvas)void
		// @17: bipush 14 (0x0E)
		// @19: invokestatic game.C_100095_fe.func_103380_n(int)void
		// @1C: bipush -100 (0x9C)
		// @1E: invokestatic game.C_100255_pj.func_105235_f(byte)void
		// @21: iconst_0
		// @22: invokestatic game.C_100053_vn.func_102810_l(int)void
		// @25: bipush -3 (0xFD)
		// @27: invokestatic game.C_100178_cg.func_105685_a(int)boolean
		// @2A: ifne @31
		// @2D: goto @40
		// @30: athrow
		// @31: getstatic game.C_100278_nd game.C_100115_ej.field_102043_Yb
		// @34: iconst_1
		// @35: bipush 123 (0x7B)
		// @37: invokevirtual game.C_100278_nd.func_101189_h(int, int)void
		// @3A: iconst_0
		// @3B: bipush -75 (0xB5)
		// @3D: invokestatic game.C_100306_kn.func_107128_a(int, byte)void
		// @40: sipush 13313 (0x3401)
		// @43: invokestatic game.C_100095_fe.func_103371_l(int)void
		// @46: iload_0
		// @47: bipush -58 (0xC6)
		// @49: if_icmple @57
		// @4C: aconst_null
		// @4D: checkcast java.lang.String
		// @50: putstatic java.lang.String game.C_100205_qf.field_103682_a
		// @53: goto @57
		// @56: athrow
		// @57: goto @7C
		// @5A: astore_1
		// @5B: aload_1
		// @5C: new java.lang.StringBuilder
		// @5F: dup
		// @60: invokespecial java.lang.StringBuilder.<init>()void
		// @63: getstatic java.lang.String[] game.C_100205_qf.field_103683_z
		// @66: bipush 7 (0x07)
		// @68: aaload
		// @69: invokevirtual java.lang.StringBuilder.append(java.lang.String)java.lang.StringBuilder
		// @6C: iload_0
		// @6D: invokevirtual java.lang.StringBuilder.append(int)java.lang.StringBuilder
		// @70: bipush 41 (0x29)
		// @72: invokevirtual java.lang.StringBuilder.append(char)java.lang.StringBuilder
		// @75: invokevirtual java.lang.StringBuilder.toString()java.lang.String
		// @78: invokestatic game.C_100181_cf.func_105695_a(java.lang.Throwable, java.lang.String)game.C_100170_cm
		// @7B: athrow
		// @7C: return
	}
	
	final int func_103665_b(int arg0, int arg1)
	{
		// @00: getstatic int game.SteelSentinels.field_105275_O
		// @03: istore #6
		// @05: iload_2
		// @06: ldc 6316128 (0x606060)
		// @08: if_icmpeq @16
		// @0B: aconst_null
		// @0C: checkcast game.C_100202_qi
		// @0F: putstatic game.C_100202_qi game.C_100205_qf.field_103676_f
		// @12: goto @16
		// @15: athrow
		// @16: aload_0
		// @17: getfield game.C_100306_kn[] game.C_100205_qf.field_103677_g
		// @1A: astore_3
		// @1B: iconst_0
		// @1C: istore #4
		// @1E: iload #4
		// @20: aload_3
		// @21: arraylength
		// @22: if_icmpge @59
		// @25: aload_3
		// @26: iload #4
		// @28: aaload
		// @29: astore #5
		// @2B: iload_1
		// @2C: iload #6
		// @2E: ifne @5A
		// @31: aload #5
		// @33: getfield int[] game.C_100306_kn.field_107130_g
		// @36: arraylength
		// @37: if_icmpge @46
		// @3A: goto @3E
		// @3D: athrow
		// @3E: aload #5
		// @40: getfield int[] game.C_100306_kn.field_107130_g
		// @43: iload_1
		// @44: iaload
		// @45: ireturn
		// @46: iload_1
		// @47: iconst_m1
		// @48: aload #5
		// @4A: getfield int[] game.C_100306_kn.field_107130_g
		// @4D: arraylength
		// @4E: iadd
		// @4F: isub
		// @50: istore_1
		// @51: iinc #4 +1
		// @54: iload #6
		// @56: ifeq @1E
		// @59: iconst_0
		// @5A: ireturn
		// @5B: astore_3
		// @5C: aload_3
		// @5D: new java.lang.StringBuilder
		// @60: dup
		// @61: invokespecial java.lang.StringBuilder.<init>()void
		// @64: getstatic java.lang.String[] game.C_100205_qf.field_103683_z
		// @67: iconst_1
		// @68: aaload
		// @69: invokevirtual java.lang.StringBuilder.append(java.lang.String)java.lang.StringBuilder
		// @6C: iload_1
		// @6D: invokevirtual java.lang.StringBuilder.append(int)java.lang.StringBuilder
		// @70: bipush 44 (0x2C)
		// @72: invokevirtual java.lang.StringBuilder.append(char)java.lang.StringBuilder
		// @75: iload_2
		// @76: invokevirtual java.lang.StringBuilder.append(int)java.lang.StringBuilder
		// @79: bipush 41 (0x29)
		// @7B: invokevirtual java.lang.StringBuilder.append(char)java.lang.StringBuilder
		// @7E: invokevirtual java.lang.StringBuilder.toString()java.lang.String
		// @81: invokestatic game.C_100181_cf.func_105695_a(java.lang.Throwable, java.lang.String)game.C_100170_cm
		// @84: athrow
	}
	
	final int func_103673_a(int arg0, int arg1)
	{
		// @00: getstatic int game.SteelSentinels.field_105275_O
		// @03: istore #5
		// @05: iload_1
		// @06: iconst_1
		// @07: if_icmpeq @13
		// @0A: bipush -27 (0xE5)
		// @0C: invokestatic game.C_100205_qf.func_103672_d(int)void
		// @0F: goto @13
		// @12: athrow
		// @13: iconst_0
		// @14: istore_3
		// @15: aload_0
		// @16: getfield game.C_100306_kn[] game.C_100205_qf.field_103677_g
		// @19: arraylength
		// @1A: iconst_m1
		// @1B: ixor
		// @1C: iload_3
		// @1D: iconst_m1
		// @1E: ixor
		// @1F: if_icmpge @56
		// @22: aload_0
		// @23: getfield game.C_100306_kn[] game.C_100205_qf.field_103677_g
		// @26: iload_3
		// @27: aaload
		// @28: astore #4
		// @2A: iload_2
		// @2B: iconst_m1
		// @2C: ixor
		// @2D: iload #5
		// @2F: ifne @5B
		// @32: aload #4
		// @34: getfield int[] game.C_100306_kn.field_107130_g
		// @37: arraylength
		// @38: iconst_m1
		// @39: ixor
		// @3A: if_icmple @43
		// @3D: goto @41
		// @40: athrow
		// @41: iload_3
		// @42: ireturn
		// @43: iload_2
		// @44: aload #4
		// @46: getfield int[] game.C_100306_kn.field_107130_g
		// @49: arraylength
		// @4A: iconst_1
		// @4B: isub
		// @4C: isub
		// @4D: istore_2
		// @4E: iinc #3 +1
		// @51: iload #5
		// @53: ifeq @15
		// @56: aload_0
		// @57: getfield game.C_100306_kn[] game.C_100205_qf.field_103677_g
		// @5A: arraylength
		// @5B: ireturn
		// @5C: astore_3
		// @5D: aload_3
		// @5E: new java.lang.StringBuilder
		// @61: dup
		// @62: invokespecial java.lang.StringBuilder.<init>()void
		// @65: getstatic java.lang.String[] game.C_100205_qf.field_103683_z
		// @68: bipush 76 (0x4C)
		// @6A: aaload
		// @6B: invokevirtual java.lang.StringBuilder.append(java.lang.String)java.lang.StringBuilder
		// @6E: iload_1
		// @6F: invokevirtual java.lang.StringBuilder.append(int)java.lang.StringBuilder
		// @72: bipush 44 (0x2C)
		// @74: invokevirtual java.lang.StringBuilder.append(char)java.lang.StringBuilder
		// @77: iload_2
		// @78: invokevirtual java.lang.StringBuilder.append(int)java.lang.StringBuilder
		// @7B: bipush 41 (0x29)
		// @7D: invokevirtual java.lang.StringBuilder.append(char)java.lang.StringBuilder
		// @80: invokevirtual java.lang.StringBuilder.toString()java.lang.String
		// @83: invokestatic game.C_100181_cf.func_105695_a(java.lang.Throwable, java.lang.String)game.C_100170_cm
		// @86: athrow
	}
	
	final int func_103663_c(int arg0)
	{
		// @00: getstatic int game.SteelSentinels.field_105275_O
		// @03: istore #8
		// @05: bipush -128 (0x80)
		// @07: iload_1
		// @08: bipush -12 (0xF4)
		// @0A: isub
		// @0B: bipush 55 (0x37)
		// @0D: idiv
		// @0E: irem
		// @0F: istore_2
		// @10: iconst_m1
		// @11: istore_3
		// @12: aconst_null
		// @13: aload_0
		// @14: getfield game.C_100306_kn[] game.C_100205_qf.field_103677_g
		// @17: if_acmpne @1E
		// @1A: goto @59
		// @1D: athrow
		// @1E: aload_0
		// @1F: getfield game.C_100306_kn[] game.C_100205_qf.field_103677_g
		// @22: astore #4
		// @24: iconst_0
		// @25: istore #5
		// @27: iload #5
		// @29: aload #4
		// @2B: arraylength
		// @2C: if_icmpge @59
		// @2F: aload #4
		// @31: iload #5
		// @33: aaload
		// @34: astore #6
		// @36: aload #6
		// @38: ifnull @51
		// @3B: aload #6
		// @3D: bipush -34 (0xDE)
		// @3F: invokevirtual game.C_100306_kn.func_107126_a(int)int
		// @42: istore #7
		// @44: iload #7
		// @46: iload_3
		// @47: if_icmpgt @4E
		// @4A: goto @51
		// @4D: athrow
		// @4E: iload #7
		// @50: istore_3
		// @51: iinc #5 +1
		// @54: iload #8
		// @56: ifeq @27
		// @59: iload_3
		// @5A: ireturn
		// @5B: astore_2
		// @5C: aload_2
		// @5D: new java.lang.StringBuilder
		// @60: dup
		// @61: invokespecial java.lang.StringBuilder.<init>()void
		// @64: getstatic java.lang.String[] game.C_100205_qf.field_103683_z
		// @67: bipush 6 (0x06)
		// @69: aaload
		// @6A: invokevirtual java.lang.StringBuilder.append(java.lang.String)java.lang.StringBuilder
		// @6D: iload_1
		// @6E: invokevirtual java.lang.StringBuilder.append(int)java.lang.StringBuilder
		// @71: bipush 41 (0x29)
		// @73: invokevirtual java.lang.StringBuilder.append(char)java.lang.StringBuilder
		// @76: invokevirtual java.lang.StringBuilder.toString()java.lang.String
		// @79: invokestatic game.C_100181_cf.func_105695_a(java.lang.Throwable, java.lang.String)game.C_100170_cm
		// @7C: athrow
	}
	
	public static void func_103671_b(byte arg0)
	{
		// @00: aconst_null
		// @01: putstatic java.lang.String game.C_100205_qf.field_103682_a
		// @04: aconst_null
		// @05: putstatic game.C_100202_qi game.C_100205_qf.field_103676_f
		// @08: aconst_null
		// @09: putstatic game.C_100202_qi game.C_100205_qf.field_103680_b
		// @0C: bipush 125 (0x7D)
		// @0E: bipush 58 (0x3A)
		// @10: iload_0
		// @11: isub
		// @12: bipush 33 (0x21)
		// @14: idiv
		// @15: idiv
		// @16: istore_1
		// @17: aconst_null
		// @18: putstatic game.C_100268_mk game.C_100205_qf.field_103679_e
		// @1B: goto @40
		// @1E: astore_1
		// @1F: aload_1
		// @20: new java.lang.StringBuilder
		// @23: dup
		// @24: invokespecial java.lang.StringBuilder.<init>()void
		// @27: getstatic java.lang.String[] game.C_100205_qf.field_103683_z
		// @2A: bipush 75 (0x4B)
		// @2C: aaload
		// @2D: invokevirtual java.lang.StringBuilder.append(java.lang.String)java.lang.StringBuilder
		// @30: iload_0
		// @31: invokevirtual java.lang.StringBuilder.append(int)java.lang.StringBuilder
		// @34: bipush 41 (0x29)
		// @36: invokevirtual java.lang.StringBuilder.append(char)java.lang.StringBuilder
		// @39: invokevirtual java.lang.StringBuilder.toString()java.lang.String
		// @3C: invokestatic game.C_100181_cf.func_105695_a(java.lang.Throwable, java.lang.String)game.C_100170_cm
		// @3F: athrow
		// @40: return
	}
	
	static final void func_103675_a(byte arg0, C_100153_be[] arg1, C_100098_h arg2, int[] arg3, C_100098_h arg4)
	{
		// @000: getstatic int game.SteelSentinels.field_105275_O
		// @003: istore #19
		// @005: getstatic java.lang.String[] game.C_100205_qf.field_103683_z
		// @008: bipush 29 (0x1D)
		// @00A: aaload
		// @00B: aload #4
		// @00D: getstatic java.lang.String[] game.C_100205_qf.field_103683_z
		// @010: bipush 38 (0x26)
		// @012: aaload
		// @013: bipush 110 (0x6E)
		// @015: invokestatic game.C_100341_jd.func_102631_a(java.lang.String, game.C_100098_h, java.lang.String, int)game.C_100153_be[]
		// @018: astore #5
		// @01A: aload #5
		// @01C: arraylength
		// @01D: putstatic int game.C_100136_th.field_102620_Q
		// @020: aconst_null
		// @021: aload_1
		// @022: if_acmpeq @08A
		// @025: aload_1
		// @026: arraylength
		// @027: getstatic int game.C_100136_th.field_102620_Q
		// @02A: iadd
		// @02B: anewarray game.C_100153_be
		// @02E: astore #6
		// @030: iconst_0
		// @031: istore #7
		// @033: iload #7
		// @035: iconst_m1
		// @036: ixor
		// @037: getstatic int game.C_100136_th.field_102620_Q
		// @03A: iconst_m1
		// @03B: ixor
		// @03C: if_icmple @05A
		// @03F: aload #6
		// @041: iload #7
		// @043: aload #5
		// @045: iload #7
		// @047: aaload
		// @048: aastore
		// @049: iinc #7 +1
		// @04C: iload #19
		// @04E: ifne @05E
		// @051: iload #19
		// @053: ifeq @033
		// @056: goto @05A
		// @059: athrow
		// @05A: aload #6
		// @05C: astore #5
		// @05E: iconst_0
		// @05F: istore #7
		// @061: iload #7
		// @063: iconst_m1
		// @064: ixor
		// @065: aload_1
		// @066: arraylength
		// @067: iconst_m1
		// @068: ixor
		// @069: if_icmple @08A
		// @06C: aload #6
		// @06E: iload #19
		// @070: ifne @08C
		// @073: iload #7
		// @075: getstatic int game.C_100136_th.field_102620_Q
		// @078: iadd
		// @079: aload_1
		// @07A: iload #7
		// @07C: aaload
		// @07D: aastore
		// @07E: iinc #7 +1
		// @081: iload #19
		// @083: ifeq @061
		// @086: goto @08A
		// @089: athrow
		// @08A: aload #5
		// @08C: arraylength
		// @08D: newarray int[]
		// @08F: astore #6
		// @091: iconst_0
		// @092: istore #7
		// @094: getstatic int game.C_100136_th.field_102620_Q
		// @097: iload #7
		// @099: if_icmple @0B4
		// @09C: aload #6
		// @09E: iload #7
		// @0A0: bipush 10 (0x0A)
		// @0A2: iastore
		// @0A3: iinc #7 +1
		// @0A6: iload #19
		// @0A8: ifne @0BD
		// @0AB: iload #19
		// @0AD: ifeq @094
		// @0B0: goto @0B4
		// @0B3: athrow
		// @0B4: aconst_null
		// @0B5: aload_1
		// @0B6: if_acmpne @0BD
		// @0B9: goto @119
		// @0BC: athrow
		// @0BD: aload_3
		// @0BE: ifnonnull @0F1
		// @0C1: iconst_0
		// @0C2: istore #7
		// @0C4: aload_1
		// @0C5: arraylength
		// @0C6: iload #7
		// @0C8: if_icmple @0EC
		// @0CB: aload #6
		// @0CD: iload #7
		// @0CF: getstatic int game.C_100136_th.field_102620_Q
		// @0D2: iadd
		// @0D3: aload_1
		// @0D4: iload #7
		// @0D6: aaload
		// @0D7: getfield int game.C_100153_be.field_105303_s
		// @0DA: iastore
		// @0DB: iinc #7 +1
		// @0DE: iload #19
		// @0E0: ifne @12F
		// @0E3: iload #19
		// @0E5: ifeq @0C4
		// @0E8: goto @0EC
		// @0EB: athrow
		// @0EC: iload #19
		// @0EE: ifeq @119
		// @0F1: iconst_0
		// @0F2: istore #7
		// @0F4: aload_1
		// @0F5: arraylength
		// @0F6: iload #7
		// @0F8: if_icmple @119
		// @0FB: aload #6
		// @0FD: iload #7
		// @0FF: getstatic int game.C_100136_th.field_102620_Q
		// @102: iadd
		// @103: aload_3
		// @104: iload #7
		// @106: iaload
		// @107: iastore
		// @108: iinc #7 +1
		// @10B: iload #19
		// @10D: ifne @12F
		// @110: iload #19
		// @112: ifeq @0F4
		// @115: goto @119
		// @118: athrow
		// @119: iconst_2
		// @11A: putstatic int game.C_100245_pf.field_106389_c
		// @11D: bipush 15 (0x0F)
		// @11F: putstatic int game.C_100033_gj.field_101917_jc
		// @122: bipush 11 (0x0B)
		// @124: putstatic int game.C_100140_bj.field_102963_f
		// @127: iconst_4
		// @128: putstatic int game.C_100244_pe.field_106375_d
		// @12B: iconst_2
		// @12C: putstatic int game.C_100284_nj.field_106771_c
		// @12F: bipush 104 (0x68)
		// @131: aload_2
		// @132: aload #4
		// @134: getstatic java.lang.String[] game.C_100205_qf.field_103683_z
		// @137: bipush 38 (0x26)
		// @139: aaload
		// @13A: getstatic java.lang.String[] game.C_100205_qf.field_103683_z
		// @13D: bipush 62 (0x3E)
		// @13F: aaload
		// @140: invokestatic game.C_100004_gb.func_103564_a(int, game.C_100098_h, game.C_100098_h, java.lang.String, java.lang.String)game.C_100317_lb
		// @143: astore #7
		// @145: bipush 123 (0x7B)
		// @147: aload_2
		// @148: aload #4
		// @14A: getstatic java.lang.String[] game.C_100205_qf.field_103683_z
		// @14D: bipush 38 (0x26)
		// @14F: aaload
		// @150: getstatic java.lang.String[] game.C_100205_qf.field_103683_z
		// @153: bipush 73 (0x49)
		// @155: aaload
		// @156: invokestatic game.C_100004_gb.func_103564_a(int, game.C_100098_h, game.C_100098_h, java.lang.String, java.lang.String)game.C_100317_lb
		// @159: putstatic game.C_100317_lb game.C_100152_bd.field_105209_k
		// @15C: bipush 91 (0x5B)
		// @15E: aload_2
		// @15F: aload #4
		// @161: getstatic java.lang.String[] game.C_100205_qf.field_103683_z
		// @164: bipush 38 (0x26)
		// @166: aaload
		// @167: getstatic java.lang.String[] game.C_100205_qf.field_103683_z
		// @16A: bipush 11 (0x0B)
		// @16C: aaload
		// @16D: invokestatic game.C_100004_gb.func_103564_a(int, game.C_100098_h, game.C_100098_h, java.lang.String, java.lang.String)game.C_100317_lb
		// @170: putstatic game.C_100317_lb game.C_100342_jg.field_102724_Vb
		// @173: aload #7
		// @175: aload #5
		// @177: aload #6
		// @179: invokevirtual game.C_100317_lb.func_101728_a(game.C_100295_kh[], int[])void
		// @17C: getstatic game.C_100317_lb game.C_100152_bd.field_105209_k
		// @17F: aload #5
		// @181: aload #6
		// @183: invokevirtual game.C_100317_lb.func_101728_a(game.C_100295_kh[], int[])void
		// @186: getstatic game.C_100317_lb game.C_100342_jg.field_102724_Vb
		// @189: aload #5
		// @18B: aload #6
		// @18D: invokevirtual game.C_100317_lb.func_101728_a(game.C_100295_kh[], int[])void
		// @190: new game.C_100302_ka
		// @193: dup
		// @194: lconst_0
		// @195: aconst_null
		// @196: invokespecial game.C_100302_ka.<init>(long, game.C_100302_ka)void
		// @199: astore #8
		// @19B: aload #8
		// @19D: ldc 16777215 (0xffffff)
		// @19F: putfield int game.C_100302_ka.field_101830_gb
		// @1A2: aload #8
		// @1A4: getstatic int game.C_100033_gj.field_101917_jc
		// @1A7: putfield int game.C_100302_ka.field_101833_ob
		// @1AA: aload #8
		// @1AC: aload #7
		// @1AE: putfield game.C_100112_r game.C_100302_ka.field_101845_sb
		// @1B1: aload #8
		// @1B3: astore #9
		// @1B5: aload #8
		// @1B7: iconst_1
		// @1B8: putfield int game.C_100302_ka.field_101858_J
		// @1BB: aload #9
		// @1BD: iconst_1
		// @1BE: putfield int game.C_100302_ka.field_101850_Fb
		// @1C1: new game.C_100302_ka
		// @1C4: dup
		// @1C5: lconst_0
		// @1C6: aconst_null
		// @1C7: invokespecial game.C_100302_ka.<init>(long, game.C_100302_ka)void
		// @1CA: astore #10
		// @1CC: aload #10
		// @1CE: ldc 16777215 (0xffffff)
		// @1D0: putfield int game.C_100302_ka.field_101830_gb
		// @1D3: aload #10
		// @1D5: getstatic game.C_100317_lb game.C_100152_bd.field_105209_k
		// @1D8: putfield game.C_100112_r game.C_100302_ka.field_101845_sb
		// @1DB: aload #10
		// @1DD: getstatic int game.C_100033_gj.field_101917_jc
		// @1E0: putfield int game.C_100302_ka.field_101833_ob
		// @1E3: aload #10
		// @1E5: astore #11
		// @1E7: aload #10
		// @1E9: iconst_1
		// @1EA: putfield int game.C_100302_ka.field_101858_J
		// @1ED: aload #11
		// @1EF: iconst_1
		// @1F0: putfield int game.C_100302_ka.field_101850_Fb
		// @1F3: new game.C_100302_ka
		// @1F6: dup
		// @1F7: lconst_0
		// @1F8: aload #8
		// @1FA: invokespecial game.C_100302_ka.<init>(long, game.C_100302_ka)void
		// @1FD: putstatic game.C_100302_ka game.C_100170_cm.field_105545_l
		// @200: getstatic game.C_100302_ka game.C_100170_cm.field_105545_l
		// @203: aload #4
		// @205: getstatic java.lang.String[] game.C_100205_qf.field_103683_z
		// @208: bipush 23 (0x17)
		// @20A: aaload
		// @20B: getstatic java.lang.String[] game.C_100205_qf.field_103683_z
		// @20E: bipush 38 (0x26)
		// @210: aaload
		// @211: bipush -107 (0x95)
		// @213: invokestatic game.C_100163_sf.func_105433_a(game.C_100098_h, java.lang.String, java.lang.String, byte)game.C_100037_wb[]
		// @216: bipush 123 (0x7B)
		// @218: invokestatic game.C_100215_ai.func_106004_a(game.C_100037_wb[], byte)game.C_100037_wb[]
		// @21B: putfield game.C_100037_wb[] game.C_100302_ka.field_101862_T
		// @21E: new game.C_100302_ka
		// @221: dup
		// @222: lconst_0
		// @223: aconst_null
		// @224: invokespecial game.C_100302_ka.<init>(long, game.C_100302_ka)void
		// @227: putstatic game.C_100302_ka game.C_100062_dk.field_104284_c
		// @22A: getstatic game.C_100302_ka game.C_100062_dk.field_104284_c
		// @22D: ldc 4210752 (0x404040)
		// @22F: ldc 8421504 (0x808080)
		// @231: sipush 7293 (0x1C7D)
		// @234: bipush 120 (0x78)
		// @236: iconst_0
		// @237: iconst_0
		// @238: invokestatic game.C_100029_gn.func_103354_a(int, int, int, int, boolean, boolean)game.C_100037_wb[]
		// @23B: putfield game.C_100037_wb[] game.C_100302_ka.field_101862_T
		// @23E: new game.C_100302_ka
		// @241: dup
		// @242: lconst_0
		// @243: aconst_null
		// @244: invokespecial game.C_100302_ka.<init>(long, game.C_100302_ka)void
		// @247: putstatic game.C_100302_ka game.C_100081_ue.field_100678_k
		// @24A: getstatic game.C_100302_ka game.C_100081_ue.field_100678_k
		// @24D: ldc 6316128 (0x606060)
		// @24F: iconst_1
		// @250: ldc 6316128 (0x606060)
		// @252: iconst_3
		// @253: iconst_1
		// @254: bipush 114 (0x72)
		// @256: invokestatic game.C_100265_mh.func_106563_a(int, boolean, int, int, int, int)game.C_100037_wb[]
		// @259: putfield game.C_100037_wb[] game.C_100302_ka.field_101862_T
		// @25C: new game.C_100302_ka
		// @25F: dup
		// @260: lconst_0
		// @261: aconst_null
		// @262: invokespecial game.C_100302_ka.<init>(long, game.C_100302_ka)void
		// @265: putstatic game.C_100302_ka game.C_100138_bo.field_100405_b
		// @268: getstatic game.C_100302_ka game.C_100138_bo.field_100405_b
		// @26B: aload #4
		// @26D: getstatic java.lang.String[] game.C_100205_qf.field_103683_z
		// @270: bipush 53 (0x35)
		// @272: aaload
		// @273: getstatic java.lang.String[] game.C_100205_qf.field_103683_z
		// @276: bipush 38 (0x26)
		// @278: aaload
		// @279: bipush -106 (0x96)
		// @27B: invokestatic game.C_100163_sf.func_105433_a(game.C_100098_h, java.lang.String, java.lang.String, byte)game.C_100037_wb[]
		// @27E: bipush 118 (0x76)
		// @280: invokestatic game.C_100215_ai.func_106004_a(game.C_100037_wb[], byte)game.C_100037_wb[]
		// @283: putfield game.C_100037_wb[] game.C_100302_ka.field_101862_T
		// @286: aload #4
		// @288: getstatic java.lang.String[] game.C_100205_qf.field_103683_z
		// @28B: bipush 31 (0x1F)
		// @28D: aaload
		// @28E: getstatic java.lang.String[] game.C_100205_qf.field_103683_z
		// @291: bipush 38 (0x26)
		// @293: aaload
		// @294: bipush -126 (0x82)
		// @296: invokestatic game.C_100163_sf.func_105433_a(game.C_100098_h, java.lang.String, java.lang.String, byte)game.C_100037_wb[]
		// @299: bipush 122 (0x7A)
		// @29B: invokestatic game.C_100215_ai.func_106004_a(game.C_100037_wb[], byte)game.C_100037_wb[]
		// @29E: astore #12
		// @2A0: bipush -88 (0xA8)
		// @2A2: bipush 67 (0x43)
		// @2A4: iload_0
		// @2A5: isub
		// @2A6: bipush 37 (0x25)
		// @2A8: idiv
		// @2A9: idiv
		// @2AA: istore #13
		// @2AC: aload #4
		// @2AE: getstatic java.lang.String[] game.C_100205_qf.field_103683_z
		// @2B1: bipush 27 (0x1B)
		// @2B3: aaload
		// @2B4: getstatic java.lang.String[] game.C_100205_qf.field_103683_z
		// @2B7: bipush 38 (0x26)
		// @2B9: aaload
		// @2BA: bipush -90 (0xA6)
		// @2BC: invokestatic game.C_100163_sf.func_105433_a(game.C_100098_h, java.lang.String, java.lang.String, byte)game.C_100037_wb[]
		// @2BF: astore #14
		// @2C1: aload #4
		// @2C3: getstatic java.lang.String[] game.C_100205_qf.field_103683_z
		// @2C6: bipush 54 (0x36)
		// @2C8: aaload
		// @2C9: getstatic java.lang.String[] game.C_100205_qf.field_103683_z
		// @2CC: bipush 38 (0x26)
		// @2CE: aaload
		// @2CF: bipush -126 (0x82)
		// @2D1: invokestatic game.C_100163_sf.func_105433_a(game.C_100098_h, java.lang.String, java.lang.String, byte)game.C_100037_wb[]
		// @2D4: bipush 124 (0x7C)
		// @2D6: invokestatic game.C_100215_ai.func_106004_a(game.C_100037_wb[], byte)game.C_100037_wb[]
		// @2D9: astore #15
		// @2DB: new game.C_100302_ka
		// @2DE: dup
		// @2DF: lconst_0
		// @2E0: aload #8
		// @2E2: invokespecial game.C_100302_ka.<init>(long, game.C_100302_ka)void
		// @2E5: putstatic game.C_100302_ka game.C_100151_bc.field_102932_cb
		// @2E8: getstatic game.C_100302_ka game.C_100151_bc.field_102932_cb
		// @2EB: aload #15
		// @2ED: putfield game.C_100037_wb[] game.C_100302_ka.field_101862_T
		// @2F0: new game.C_100302_ka
		// @2F3: dup
		// @2F4: lconst_0
		// @2F5: aconst_null
		// @2F6: invokespecial game.C_100302_ka.<init>(long, game.C_100302_ka)void
		// @2F9: putstatic game.C_100302_ka game.C_100164_se.field_105456_h
		// @2FC: getstatic game.C_100302_ka game.C_100164_se.field_105456_h
		// @2FF: bipush 114 (0x72)
		// @301: getstatic java.lang.String[] game.C_100205_qf.field_103683_z
		// @304: bipush 38 (0x26)
		// @306: aaload
		// @307: aload #4
		// @309: getstatic java.lang.String[] game.C_100205_qf.field_103683_z
		// @30C: bipush 50 (0x32)
		// @30E: aaload
		// @30F: invokestatic game.C_100021_wn.func_103861_a(byte, java.lang.String, game.C_100098_h, java.lang.String)game.C_100037_wb
		// @312: putfield game.C_100037_wb game.C_100302_ka.field_101887_nb
		// @315: getstatic game.C_100302_ka game.C_100164_se.field_105456_h
		// @318: bipush 114 (0x72)
		// @31A: getstatic java.lang.String[] game.C_100205_qf.field_103683_z
		// @31D: bipush 38 (0x26)
		// @31F: aaload
		// @320: aload #4
		// @322: getstatic java.lang.String[] game.C_100205_qf.field_103683_z
		// @325: bipush 61 (0x3D)
		// @327: aaload
		// @328: invokestatic game.C_100021_wn.func_103861_a(byte, java.lang.String, game.C_100098_h, java.lang.String)game.C_100037_wb
		// @32B: putfield game.C_100037_wb game.C_100302_ka.field_101844_pb
		// @32E: new game.C_100302_ka
		// @331: dup
		// @332: lconst_0
		// @333: aload #8
		// @335: invokespecial game.C_100302_ka.<init>(long, game.C_100302_ka)void
		// @338: putstatic game.C_100302_ka game.C_100077_d.field_103323_Y
		// @33B: getstatic game.C_100302_ka game.C_100077_d.field_103323_Y
		// @33E: ldc 2039583 (0x1f1f1f)
		// @340: ldc 3815994 (0x3a3a3a)
		// @342: sipush 7293 (0x1C7D)
		// @345: bipush 40 (0x28)
		// @347: iconst_1
		// @348: iconst_1
		// @349: invokestatic game.C_100029_gn.func_103354_a(int, int, int, int, boolean, boolean)game.C_100037_wb[]
		// @34C: putfield game.C_100037_wb[] game.C_100302_ka.field_101862_T
		// @34F: new game.C_100302_ka
		// @352: dup
		// @353: lconst_0
		// @354: aload #10
		// @356: invokespecial game.C_100302_ka.<init>(long, game.C_100302_ka)void
		// @359: putstatic game.C_100302_ka game.C_100252_pn.field_105515_p
		// @35C: getstatic game.C_100302_ka game.C_100252_pn.field_105515_p
		// @35F: iconst_2
		// @360: putfield int game.C_100302_ka.field_101829_Db
		// @363: getstatic game.C_100302_ka game.C_100252_pn.field_105515_p
		// @366: ldc 2039583 (0x1f1f1f)
		// @368: ldc 3815994 (0x3a3a3a)
		// @36A: sipush 7293 (0x1C7D)
		// @36D: bipush 30 (0x1E)
		// @36F: iconst_0
		// @370: iconst_1
		// @371: invokestatic game.C_100029_gn.func_103354_a(int, int, int, int, boolean, boolean)game.C_100037_wb[]
		// @374: putfield game.C_100037_wb[] game.C_100302_ka.field_101862_T
		// @377: new game.C_100302_ka
		// @37A: dup
		// @37B: lconst_0
		// @37C: aload #10
		// @37E: invokespecial game.C_100302_ka.<init>(long, game.C_100302_ka)void
		// @381: putstatic game.C_100302_ka game.C_100250_pl.field_106438_a
		// @384: getstatic game.C_100302_ka game.C_100250_pl.field_106438_a
		// @387: iconst_2
		// @388: putfield int game.C_100302_ka.field_101829_Db
		// @38B: getstatic game.C_100302_ka game.C_100250_pl.field_106438_a
		// @38E: ldc 2039583 (0x1f1f1f)
		// @390: ldc 3815994 (0x3a3a3a)
		// @392: sipush 7293 (0x1C7D)
		// @395: bipush 30 (0x1E)
		// @397: iconst_0
		// @398: iconst_0
		// @399: invokestatic game.C_100029_gn.func_103354_a(int, int, int, int, boolean, boolean)game.C_100037_wb[]
		// @39C: putfield game.C_100037_wb[] game.C_100302_ka.field_101862_T
		// @39F: new game.C_100302_ka
		// @3A2: dup
		// @3A3: lconst_0
		// @3A4: aload #10
		// @3A6: invokespecial game.C_100302_ka.<init>(long, game.C_100302_ka)void
		// @3A9: putstatic game.C_100302_ka game.C_100038_wa.field_104074_o
		// @3AC: getstatic game.C_100302_ka game.C_100038_wa.field_104074_o
		// @3AF: iconst_2
		// @3B0: putfield int game.C_100302_ka.field_101829_Db
		// @3B3: getstatic game.C_100302_ka game.C_100038_wa.field_104074_o
		// @3B6: ldc 2039583 (0x1f1f1f)
		// @3B8: ldc 3815994 (0x3a3a3a)
		// @3BA: sipush 7293 (0x1C7D)
		// @3BD: bipush 30 (0x1E)
		// @3BF: iconst_1
		// @3C0: iconst_0
		// @3C1: invokestatic game.C_100029_gn.func_103354_a(int, int, int, int, boolean, boolean)game.C_100037_wb[]
		// @3C4: putfield game.C_100037_wb[] game.C_100302_ka.field_101862_T
		// @3C7: new game.C_100302_ka
		// @3CA: dup
		// @3CB: lconst_0
		// @3CC: aconst_null
		// @3CD: invokespecial game.C_100302_ka.<init>(long, game.C_100302_ka)void
		// @3D0: putstatic game.C_100302_ka game.C_100129_tg.field_102750_sb
		// @3D3: getstatic game.C_100302_ka game.C_100129_tg.field_102750_sb
		// @3D6: getstatic game.C_100317_lb game.C_100152_bd.field_105209_k
		// @3D9: putfield game.C_100112_r game.C_100302_ka.field_101845_sb
		// @3DC: getstatic game.C_100302_ka game.C_100129_tg.field_102750_sb
		// @3DF: ldc 13421772 (0xcccccc)
		// @3E1: putfield int game.C_100302_ka.field_101830_gb
		// @3E4: getstatic game.C_100302_ka game.C_100129_tg.field_102750_sb
		// @3E7: iconst_1
		// @3E8: putfield int game.C_100302_ka.field_101858_J
		// @3EB: getstatic game.C_100302_ka game.C_100129_tg.field_102750_sb
		// @3EE: getstatic int game.C_100033_gj.field_101917_jc
		// @3F1: putfield int game.C_100302_ka.field_101833_ob
		// @3F4: new game.C_100302_ka
		// @3F7: dup
		// @3F8: lconst_0
		// @3F9: getstatic game.C_100302_ka game.C_100129_tg.field_102750_sb
		// @3FC: invokespecial game.C_100302_ka.<init>(long, game.C_100302_ka)void
		// @3FF: putstatic game.C_100302_ka game.C_100236_on.field_100906_r
		// @402: getstatic game.C_100302_ka game.C_100236_on.field_100906_r
		// @405: ldc 8421504 (0x808080)
		// @407: putfield int game.C_100302_ka.field_101859_rb
		// @40A: getstatic game.C_100302_ka game.C_100236_on.field_100906_r
		// @40D: ldc 16777215 (0xffffff)
		// @40F: putfield int game.C_100302_ka.field_101860_K
		// @412: getstatic game.C_100302_ka game.C_100236_on.field_100906_r
		// @415: ldc 16777215 (0xffffff)
		// @417: putfield int game.C_100302_ka.field_101868_Ab
		// @41A: getstatic game.C_100302_ka game.C_100236_on.field_100906_r
		// @41D: ldc 16777215 (0xffffff)
		// @41F: putfield int game.C_100302_ka.field_101872_Nb
		// @422: getstatic game.C_100302_ka game.C_100236_on.field_100906_r
		// @425: ldc 16764006 (0xffcc66)
		// @427: putfield int game.C_100302_ka.field_101830_gb
		// @42A: new game.C_100302_ka
		// @42D: dup
		// @42E: lconst_0
		// @42F: getstatic game.C_100302_ka game.C_100236_on.field_100906_r
		// @432: invokespecial game.C_100302_ka.<init>(long, game.C_100302_ka)void
		// @435: astore #16
		// @437: aload #16
		// @439: ldc 16777215 (0xffffff)
		// @43B: putfield int game.C_100302_ka.field_101830_gb
		// @43E: aload #16
		// @440: aload #7
		// @442: putfield game.C_100112_r game.C_100302_ka.field_101845_sb
		// @445: aload #16
		// @447: getstatic int game.C_100033_gj.field_101917_jc
		// @44A: putfield int game.C_100302_ka.field_101833_ob
		// @44D: new game.C_100302_ka
		// @450: dup
		// @451: lconst_0
		// @452: getstatic game.C_100302_ka game.C_100129_tg.field_102750_sb
		// @455: invokespecial game.C_100302_ka.<init>(long, game.C_100302_ka)void
		// @458: putstatic game.C_100302_ka game.C_100316_lc.field_102409_C
		// @45B: getstatic game.C_100302_ka game.C_100316_lc.field_102409_C
		// @45E: ldc 2236962 (0x222222)
		// @460: ldc 2236962 (0x222222)
		// @462: sipush 7293 (0x1C7D)
		// @465: bipush 16 (0x10)
		// @467: iconst_0
		// @468: iconst_0
		// @469: invokestatic game.C_100029_gn.func_103354_a(int, int, int, int, boolean, boolean)game.C_100037_wb[]
		// @46C: putfield game.C_100037_wb[] game.C_100302_ka.field_101862_T
		// @46F: getstatic game.C_100302_ka game.C_100316_lc.field_102409_C
		// @472: iconst_2
		// @473: putfield int game.C_100302_ka.field_101829_Db
		// @476: new game.C_100302_ka
		// @479: dup
		// @47A: lconst_0
		// @47B: getstatic game.C_100302_ka game.C_100129_tg.field_102750_sb
		// @47E: invokespecial game.C_100302_ka.<init>(long, game.C_100302_ka)void
		// @481: putstatic game.C_100302_ka game.C_100167_sj.field_100797_q
		// @484: getstatic game.C_100302_ka game.C_100167_sj.field_100797_q
		// @487: ldc 1513239 (0x171717)
		// @489: ldc 1513239 (0x171717)
		// @48B: sipush 7293 (0x1C7D)
		// @48E: bipush 16 (0x10)
		// @490: iconst_0
		// @491: iconst_0
		// @492: invokestatic game.C_100029_gn.func_103354_a(int, int, int, int, boolean, boolean)game.C_100037_wb[]
		// @495: putfield game.C_100037_wb[] game.C_100302_ka.field_101862_T
		// @498: getstatic game.C_100302_ka game.C_100167_sj.field_100797_q
		// @49B: iconst_2
		// @49C: putfield int game.C_100302_ka.field_101829_Db
		// @49F: new game.C_100302_ka
		// @4A2: dup
		// @4A3: lconst_0
		// @4A4: getstatic game.C_100302_ka game.C_100316_lc.field_102409_C
		// @4A7: invokespecial game.C_100302_ka.<init>(long, game.C_100302_ka)void
		// @4AA: putstatic game.C_100302_ka game.C_100299_kd.field_107022_C
		// @4AD: getstatic game.C_100302_ka game.C_100299_kd.field_107022_C
		// @4B0: sipush 32280 (0x7E18)
		// @4B3: getstatic game.C_100302_ka game.C_100236_on.field_100906_r
		// @4B6: invokevirtual game.C_100302_ka.func_101810_a(int, game.C_100302_ka)void
		// @4B9: new game.C_100302_ka
		// @4BC: dup
		// @4BD: lconst_0
		// @4BE: getstatic game.C_100302_ka game.C_100167_sj.field_100797_q
		// @4C1: invokespecial game.C_100302_ka.<init>(long, game.C_100302_ka)void
		// @4C4: putstatic game.C_100302_ka game.C_100160_sm.field_105414_e
		// @4C7: getstatic game.C_100302_ka game.C_100160_sm.field_105414_e
		// @4CA: sipush 32280 (0x7E18)
		// @4CD: getstatic game.C_100302_ka game.C_100236_on.field_100906_r
		// @4D0: invokevirtual game.C_100302_ka.func_101810_a(int, game.C_100302_ka)void
		// @4D3: aload #4
		// @4D5: getstatic java.lang.String[] game.C_100205_qf.field_103683_z
		// @4D8: bipush 52 (0x34)
		// @4DA: aaload
		// @4DB: getstatic java.lang.String[] game.C_100205_qf.field_103683_z
		// @4DE: bipush 38 (0x26)
		// @4E0: aaload
		// @4E1: bipush -89 (0xA7)
		// @4E3: invokestatic game.C_100163_sf.func_105433_a(game.C_100098_h, java.lang.String, java.lang.String, byte)game.C_100037_wb[]
		// @4E6: astore #17
		// @4E8: new game.C_100270_mi
		// @4EB: dup
		// @4EC: getstatic game.C_100302_ka game.C_100138_bo.field_100405_b
		// @4EF: aload #12
		// @4F1: getstatic game.C_100302_ka game.C_100129_tg.field_102750_sb
		// @4F4: getstatic game.C_100302_ka game.C_100236_on.field_100906_r
		// @4F7: iconst_3
		// @4F8: iconst_2
		// @4F9: getstatic int game.C_100284_nj.field_106771_c
		// @4FC: iconst_3
		// @4FD: getstatic int game.C_100033_gj.field_101917_jc
		// @500: invokespecial game.C_100270_mi.<init>(game.C_100302_ka, game.C_100037_wb[], game.C_100302_ka, game.C_100302_ka, int, int, int, int, int)void
		// @503: putstatic game.C_100270_mi game.C_100138_bo.field_100412_k
		// @506: new game.C_100302_ka
		// @509: dup
		// @50A: lconst_0
		// @50B: getstatic game.C_100302_ka game.C_100236_on.field_100906_r
		// @50E: invokespecial game.C_100302_ka.<init>(long, game.C_100302_ka)void
		// @511: putstatic game.C_100302_ka game.C_100256_pk.field_100475_u
		// @514: getstatic game.C_100302_ka game.C_100256_pk.field_100475_u
		// @517: iconst_1
		// @518: putfield int game.C_100302_ka.field_101869_S
		// @51B: getstatic game.C_100302_ka game.C_100256_pk.field_100475_u
		// @51E: iconst_1
		// @51F: putfield int game.C_100302_ka.field_101877_Z
		// @522: getstatic game.C_100302_ka game.C_100256_pk.field_100475_u
		// @525: aload #14
		// @527: putfield game.C_100037_wb[] game.C_100302_ka.field_101862_T
		// @52A: getstatic game.C_100302_ka game.C_100256_pk.field_100475_u
		// @52D: aload #17
		// @52F: putfield game.C_100037_wb[] game.C_100302_ka.field_101883_qb
		// @532: getstatic game.C_100302_ka game.C_100256_pk.field_100475_u
		// @535: iconst_1
		// @536: putfield int game.C_100302_ka.field_101867_P
		// @539: getstatic game.C_100302_ka game.C_100256_pk.field_100475_u
		// @53C: iconst_1
		// @53D: putfield int game.C_100302_ka.field_101866_Q
		// @540: getstatic game.C_100302_ka game.C_100256_pk.field_100475_u
		// @543: aload #4
		// @545: getstatic java.lang.String[] game.C_100205_qf.field_103683_z
		// @548: bipush 66 (0x42)
		// @54A: aaload
		// @54B: getstatic java.lang.String[] game.C_100205_qf.field_103683_z
		// @54E: bipush 38 (0x26)
		// @550: aaload
		// @551: bipush -105 (0x97)
		// @553: invokestatic game.C_100163_sf.func_105433_a(game.C_100098_h, java.lang.String, java.lang.String, byte)game.C_100037_wb[]
		// @556: putfield game.C_100037_wb[] game.C_100302_ka.field_101851_zb
		// @559: getstatic game.C_100302_ka game.C_100256_pk.field_100475_u
		// @55C: aload #4
		// @55E: getstatic java.lang.String[] game.C_100205_qf.field_103683_z
		// @561: bipush 56 (0x38)
		// @563: aaload
		// @564: getstatic java.lang.String[] game.C_100205_qf.field_103683_z
		// @567: bipush 38 (0x26)
		// @569: aaload
		// @56A: bipush -118 (0x8A)
		// @56C: invokestatic game.C_100163_sf.func_105433_a(game.C_100098_h, java.lang.String, java.lang.String, byte)game.C_100037_wb[]
		// @56F: putfield game.C_100037_wb[] game.C_100302_ka.field_101878_Jb
		// @572: getstatic game.C_100302_ka game.C_100256_pk.field_100475_u
		// @575: aload #4
		// @577: getstatic java.lang.String[] game.C_100205_qf.field_103683_z
		// @57A: bipush 63 (0x3F)
		// @57C: aaload
		// @57D: getstatic java.lang.String[] game.C_100205_qf.field_103683_z
		// @580: bipush 38 (0x26)
		// @582: aaload
		// @583: bipush -100 (0x9C)
		// @585: invokestatic game.C_100163_sf.func_105433_a(game.C_100098_h, java.lang.String, java.lang.String, byte)game.C_100037_wb[]
		// @588: putfield game.C_100037_wb[] game.C_100302_ka.field_101853_M
		// @58B: getstatic game.C_100302_ka game.C_100256_pk.field_100475_u
		// @58E: iconst_1
		// @58F: putfield int game.C_100302_ka.field_101850_Fb
		// @592: new game.C_100302_ka
		// @595: dup
		// @596: lconst_0
		// @597: getstatic game.C_100302_ka game.C_100236_on.field_100906_r
		// @59A: invokespecial game.C_100302_ka.<init>(long, game.C_100302_ka)void
		// @59D: putstatic game.C_100302_ka game.C_100056_de.field_103195_bb
		// @5A0: getstatic game.C_100302_ka game.C_100056_de.field_103195_bb
		// @5A3: iconst_1
		// @5A4: putfield int game.C_100302_ka.field_101850_Fb
		// @5A7: getstatic game.C_100302_ka game.C_100056_de.field_103195_bb
		// @5AA: aload #4
		// @5AC: getstatic java.lang.String[] game.C_100205_qf.field_103683_z
		// @5AF: bipush 32 (0x20)
		// @5B1: aaload
		// @5B2: getstatic java.lang.String[] game.C_100205_qf.field_103683_z
		// @5B5: bipush 38 (0x26)
		// @5B7: aaload
		// @5B8: bipush -87 (0xA9)
		// @5BA: invokestatic game.C_100163_sf.func_105433_a(game.C_100098_h, java.lang.String, java.lang.String, byte)game.C_100037_wb[]
		// @5BD: bipush 115 (0x73)
		// @5BF: invokestatic game.C_100215_ai.func_106004_a(game.C_100037_wb[], byte)game.C_100037_wb[]
		// @5C2: putfield game.C_100037_wb[] game.C_100302_ka.field_101862_T
		// @5C5: getstatic game.C_100302_ka game.C_100056_de.field_103195_bb
		// @5C8: aload #4
		// @5CA: getstatic java.lang.String[] game.C_100205_qf.field_103683_z
		// @5CD: bipush 19 (0x13)
		// @5CF: aaload
		// @5D0: getstatic java.lang.String[] game.C_100205_qf.field_103683_z
		// @5D3: bipush 38 (0x26)
		// @5D5: aaload
		// @5D6: bipush -96 (0xA0)
		// @5D8: invokestatic game.C_100163_sf.func_105433_a(game.C_100098_h, java.lang.String, java.lang.String, byte)game.C_100037_wb[]
		// @5DB: bipush 110 (0x6E)
		// @5DD: invokestatic game.C_100215_ai.func_106004_a(game.C_100037_wb[], byte)game.C_100037_wb[]
		// @5E0: putfield game.C_100037_wb[] game.C_100302_ka.field_101883_qb
		// @5E3: getstatic game.C_100302_ka game.C_100056_de.field_103195_bb
		// @5E6: aload #15
		// @5E8: putfield game.C_100037_wb[] game.C_100302_ka.field_101878_Jb
		// @5EB: new game.C_100302_ka
		// @5EE: dup
		// @5EF: lconst_0
		// @5F0: aconst_null
		// @5F1: invokespecial game.C_100302_ka.<init>(long, game.C_100302_ka)void
		// @5F4: putstatic game.C_100302_ka game.C_100028_ha.field_103944_f
		// @5F7: getstatic game.C_100302_ka game.C_100028_ha.field_103944_f
		// @5FA: ldc 1856141 (0x1c528d)
		// @5FC: iconst_1
		// @5FD: ldc 1127256 (0x113358)
		// @5FF: iconst_3
		// @600: iconst_m1
		// @601: sipush 206 (0x00CE)
		// @604: invokestatic game.C_100265_mh.func_106563_a(int, boolean, int, int, int, int)game.C_100037_wb[]
		// @607: putfield game.C_100037_wb[] game.C_100302_ka.field_101862_T
		// @60A: new game.C_100302_ka
		// @60D: dup
		// @60E: lconst_0
		// @60F: aconst_null
		// @610: invokespecial game.C_100302_ka.<init>(long, game.C_100302_ka)void
		// @613: putstatic game.C_100302_ka game.C_100277_nc.field_106699_G
		// @616: getstatic game.C_100302_ka game.C_100277_nc.field_106699_G
		// @619: ldc 11579568 (0xb0b0b0)
		// @61B: iconst_1
		// @61C: ldc 6052956 (0x5c5c5c)
		// @61E: iconst_3
		// @61F: iconst_m1
		// @620: sipush 290 (0x0122)
		// @623: invokestatic game.C_100265_mh.func_106563_a(int, boolean, int, int, int, int)game.C_100037_wb[]
		// @626: putfield game.C_100037_wb[] game.C_100302_ka.field_101862_T
		// @629: new game.C_100302_ka
		// @62C: dup
		// @62D: lconst_0
		// @62E: aload #16
		// @630: invokespecial game.C_100302_ka.<init>(long, game.C_100302_ka)void
		// @633: putstatic game.C_100302_ka game.C_100075_uj.field_100659_q
		// @636: getstatic game.C_100302_ka game.C_100075_uj.field_100659_q
		// @639: iconst_1
		// @63A: putfield int game.C_100302_ka.field_101869_S
		// @63D: getstatic game.C_100302_ka game.C_100075_uj.field_100659_q
		// @640: iconst_1
		// @641: putfield int game.C_100302_ka.field_101850_Fb
		// @644: getstatic game.C_100302_ka game.C_100075_uj.field_100659_q
		// @647: iconst_1
		// @648: putfield int game.C_100302_ka.field_101877_Z
		// @64B: getstatic game.C_100302_ka game.C_100075_uj.field_100659_q
		// @64E: iconst_1
		// @64F: putfield int game.C_100302_ka.field_101866_Q
		// @652: getstatic game.C_100302_ka game.C_100075_uj.field_100659_q
		// @655: iconst_1
		// @656: putfield int game.C_100302_ka.field_101867_P
		// @659: new game.C_100302_ka
		// @65C: dup
		// @65D: lconst_0
		// @65E: getstatic game.C_100302_ka game.C_100075_uj.field_100659_q
		// @661: invokespecial game.C_100302_ka.<init>(long, game.C_100302_ka)void
		// @664: putstatic game.C_100302_ka game.C_100101_fc.field_103395_U
		// @667: new game.C_100302_ka
		// @66A: dup
		// @66B: lconst_0
		// @66C: getstatic game.C_100302_ka game.C_100236_on.field_100906_r
		// @66F: invokespecial game.C_100302_ka.<init>(long, game.C_100302_ka)void
		// @672: putstatic game.C_100302_ka game.C_100017_wj.field_103816_d
		// @675: getstatic game.C_100302_ka game.C_100017_wj.field_103816_d
		// @678: iconst_1
		// @679: putfield int game.C_100302_ka.field_101866_Q
		// @67C: getstatic game.C_100302_ka game.C_100017_wj.field_103816_d
		// @67F: iconst_1
		// @680: putfield int game.C_100302_ka.field_101877_Z
		// @683: getstatic game.C_100302_ka game.C_100017_wj.field_103816_d
		// @686: iconst_1
		// @687: putfield int game.C_100302_ka.field_101869_S
		// @68A: getstatic game.C_100302_ka game.C_100017_wj.field_103816_d
		// @68D: iconst_1
		// @68E: putfield int game.C_100302_ka.field_101867_P
		// @691: getstatic game.C_100302_ka game.C_100017_wj.field_103816_d
		// @694: iconst_1
		// @695: putfield int game.C_100302_ka.field_101850_Fb
		// @698: new game.C_100302_ka
		// @69B: dup
		// @69C: lconst_0
		// @69D: getstatic game.C_100302_ka game.C_100017_wj.field_103816_d
		// @6A0: invokespecial game.C_100302_ka.<init>(long, game.C_100302_ka)void
		// @6A3: putstatic game.C_100302_ka game.C_100338_jc.field_105375_i
		// @6A6: new game.C_100302_ka
		// @6A9: dup
		// @6AA: lconst_0
		// @6AB: getstatic game.C_100302_ka game.C_100017_wj.field_103816_d
		// @6AE: invokespecial game.C_100302_ka.<init>(long, game.C_100302_ka)void
		// @6B1: putstatic game.C_100302_ka game.C_100309_lk.field_103272_bb
		// @6B4: new game.C_100302_ka
		// @6B7: dup
		// @6B8: lconst_0
		// @6B9: getstatic game.C_100302_ka game.C_100075_uj.field_100659_q
		// @6BC: invokespecial game.C_100302_ka.<init>(long, game.C_100302_ka)void
		// @6BF: putstatic game.C_100302_ka game.C_100031_gl.field_103967_c
		// @6C2: new game.C_100302_ka
		// @6C5: dup
		// @6C6: lconst_0
		// @6C7: getstatic game.C_100302_ka game.C_100017_wj.field_103816_d
		// @6CA: invokespecial game.C_100302_ka.<init>(long, game.C_100302_ka)void
		// @6CD: putstatic game.C_100302_ka game.C_100316_lc.field_102404_D
		// @6D0: new game.C_100302_ka
		// @6D3: dup
		// @6D4: lconst_0
		// @6D5: getstatic game.C_100302_ka game.C_100017_wj.field_103816_d
		// @6D8: invokespecial game.C_100302_ka.<init>(long, game.C_100302_ka)void
		// @6DB: putstatic game.C_100302_ka game.C_100341_jd.field_102652_kb
		// @6DE: new game.C_100302_ka
		// @6E1: dup
		// @6E2: lconst_0
		// @6E3: getstatic game.C_100302_ka game.C_100017_wj.field_103816_d
		// @6E6: invokespecial game.C_100302_ka.<init>(long, game.C_100302_ka)void
		// @6E9: putstatic game.C_100302_ka game.C_100061_dh.field_101985_ec
		// @6EC: getstatic game.C_100302_ka game.C_100017_wj.field_103816_d
		// @6EF: aload #4
		// @6F1: getstatic java.lang.String[] game.C_100205_qf.field_103683_z
		// @6F4: bipush 15 (0x0F)
		// @6F6: aaload
		// @6F7: getstatic java.lang.String[] game.C_100205_qf.field_103683_z
		// @6FA: bipush 38 (0x26)
		// @6FC: aaload
		// @6FD: bipush -116 (0x8C)
		// @6FF: invokestatic game.C_100163_sf.func_105433_a(game.C_100098_h, java.lang.String, java.lang.String, byte)game.C_100037_wb[]
		// @702: bipush 114 (0x72)
		// @704: invokestatic game.C_100215_ai.func_106004_a(game.C_100037_wb[], byte)game.C_100037_wb[]
		// @707: putfield game.C_100037_wb[] game.C_100302_ka.field_101862_T
		// @70A: getstatic game.C_100302_ka game.C_100017_wj.field_103816_d
		// @70D: aload #4
		// @70F: getstatic java.lang.String[] game.C_100205_qf.field_103683_z
		// @712: bipush 12 (0x0C)
		// @714: aaload
		// @715: getstatic java.lang.String[] game.C_100205_qf.field_103683_z
		// @718: bipush 38 (0x26)
		// @71A: aaload
		// @71B: bipush -126 (0x82)
		// @71D: invokestatic game.C_100163_sf.func_105433_a(game.C_100098_h, java.lang.String, java.lang.String, byte)game.C_100037_wb[]
		// @720: bipush 114 (0x72)
		// @722: invokestatic game.C_100215_ai.func_106004_a(game.C_100037_wb[], byte)game.C_100037_wb[]
		// @725: putfield game.C_100037_wb[] game.C_100302_ka.field_101883_qb
		// @728: getstatic game.C_100302_ka game.C_100017_wj.field_103816_d
		// @72B: getstatic game.C_100302_ka game.C_100017_wj.field_103816_d
		// @72E: aload #4
		// @730: getstatic java.lang.String[] game.C_100205_qf.field_103683_z
		// @733: bipush 59 (0x3B)
		// @735: aaload
		// @736: getstatic java.lang.String[] game.C_100205_qf.field_103683_z
		// @739: bipush 38 (0x26)
		// @73B: aaload
		// @73C: bipush -128 (0x80)
		// @73E: invokestatic game.C_100163_sf.func_105433_a(game.C_100098_h, java.lang.String, java.lang.String, byte)game.C_100037_wb[]
		// @741: bipush 110 (0x6E)
		// @743: invokestatic game.C_100215_ai.func_106004_a(game.C_100037_wb[], byte)game.C_100037_wb[]
		// @746: dup_x1
		// @747: putfield game.C_100037_wb[] game.C_100302_ka.field_101878_Jb
		// @74A: putfield game.C_100037_wb[] game.C_100302_ka.field_101851_zb
		// @74D: getstatic game.C_100302_ka game.C_100017_wj.field_103816_d
		// @750: aload #4
		// @752: getstatic java.lang.String[] game.C_100205_qf.field_103683_z
		// @755: bipush 22 (0x16)
		// @757: aaload
		// @758: getstatic java.lang.String[] game.C_100205_qf.field_103683_z
		// @75B: bipush 38 (0x26)
		// @75D: aaload
		// @75E: bipush -126 (0x82)
		// @760: invokestatic game.C_100163_sf.func_105433_a(game.C_100098_h, java.lang.String, java.lang.String, byte)game.C_100037_wb[]
		// @763: bipush 126 (0x7E)
		// @765: invokestatic game.C_100215_ai.func_106004_a(game.C_100037_wb[], byte)game.C_100037_wb[]
		// @768: putfield game.C_100037_wb[] game.C_100302_ka.field_101853_M
		// @76B: getstatic game.C_100302_ka game.C_100101_fc.field_103395_U
		// @76E: aload #4
		// @770: getstatic java.lang.String[] game.C_100205_qf.field_103683_z
		// @773: bipush 69 (0x45)
		// @775: aaload
		// @776: getstatic java.lang.String[] game.C_100205_qf.field_103683_z
		// @779: bipush 38 (0x26)
		// @77B: aaload
		// @77C: bipush -103 (0x99)
		// @77E: invokestatic game.C_100163_sf.func_105433_a(game.C_100098_h, java.lang.String, java.lang.String, byte)game.C_100037_wb[]
		// @781: bipush 110 (0x6E)
		// @783: invokestatic game.C_100215_ai.func_106004_a(game.C_100037_wb[], byte)game.C_100037_wb[]
		// @786: putfield game.C_100037_wb[] game.C_100302_ka.field_101862_T
		// @789: getstatic game.C_100302_ka game.C_100101_fc.field_103395_U
		// @78C: aload #4
		// @78E: getstatic java.lang.String[] game.C_100205_qf.field_103683_z
		// @791: bipush 45 (0x2D)
		// @793: aaload
		// @794: getstatic java.lang.String[] game.C_100205_qf.field_103683_z
		// @797: bipush 38 (0x26)
		// @799: aaload
		// @79A: bipush -95 (0xA1)
		// @79C: invokestatic game.C_100163_sf.func_105433_a(game.C_100098_h, java.lang.String, java.lang.String, byte)game.C_100037_wb[]
		// @79F: bipush 110 (0x6E)
		// @7A1: invokestatic game.C_100215_ai.func_106004_a(game.C_100037_wb[], byte)game.C_100037_wb[]
		// @7A4: putfield game.C_100037_wb[] game.C_100302_ka.field_101883_qb
		// @7A7: getstatic game.C_100302_ka game.C_100101_fc.field_103395_U
		// @7AA: aload #4
		// @7AC: getstatic java.lang.String[] game.C_100205_qf.field_103683_z
		// @7AF: bipush 55 (0x37)
		// @7B1: aaload
		// @7B2: getstatic java.lang.String[] game.C_100205_qf.field_103683_z
		// @7B5: bipush 38 (0x26)
		// @7B7: aaload
		// @7B8: bipush -114 (0x8E)
		// @7BA: invokestatic game.C_100163_sf.func_105433_a(game.C_100098_h, java.lang.String, java.lang.String, byte)game.C_100037_wb[]
		// @7BD: bipush 113 (0x71)
		// @7BF: invokestatic game.C_100215_ai.func_106004_a(game.C_100037_wb[], byte)game.C_100037_wb[]
		// @7C2: putfield game.C_100037_wb[] game.C_100302_ka.field_101851_zb
		// @7C5: getstatic game.C_100302_ka game.C_100075_uj.field_100659_q
		// @7C8: aload #4
		// @7CA: getstatic java.lang.String[] game.C_100205_qf.field_103683_z
		// @7CD: bipush 37 (0x25)
		// @7CF: aaload
		// @7D0: getstatic java.lang.String[] game.C_100205_qf.field_103683_z
		// @7D3: bipush 38 (0x26)
		// @7D5: aaload
		// @7D6: bipush -106 (0x96)
		// @7D8: invokestatic game.C_100163_sf.func_105433_a(game.C_100098_h, java.lang.String, java.lang.String, byte)game.C_100037_wb[]
		// @7DB: bipush 127 (0x7F)
		// @7DD: invokestatic game.C_100215_ai.func_106004_a(game.C_100037_wb[], byte)game.C_100037_wb[]
		// @7E0: putfield game.C_100037_wb[] game.C_100302_ka.field_101862_T
		// @7E3: getstatic game.C_100302_ka game.C_100075_uj.field_100659_q
		// @7E6: aload #4
		// @7E8: getstatic java.lang.String[] game.C_100205_qf.field_103683_z
		// @7EB: bipush 13 (0x0D)
		// @7ED: aaload
		// @7EE: getstatic java.lang.String[] game.C_100205_qf.field_103683_z
		// @7F1: bipush 38 (0x26)
		// @7F3: aaload
		// @7F4: bipush -127 (0x81)
		// @7F6: invokestatic game.C_100163_sf.func_105433_a(game.C_100098_h, java.lang.String, java.lang.String, byte)game.C_100037_wb[]
		// @7F9: bipush 117 (0x75)
		// @7FB: invokestatic game.C_100215_ai.func_106004_a(game.C_100037_wb[], byte)game.C_100037_wb[]
		// @7FE: putfield game.C_100037_wb[] game.C_100302_ka.field_101883_qb
		// @801: getstatic game.C_100302_ka game.C_100075_uj.field_100659_q
		// @804: aload #4
		// @806: getstatic java.lang.String[] game.C_100205_qf.field_103683_z
		// @809: bipush 18 (0x12)
		// @80B: aaload
		// @80C: getstatic java.lang.String[] game.C_100205_qf.field_103683_z
		// @80F: bipush 38 (0x26)
		// @811: aaload
		// @812: bipush -120 (0x88)
		// @814: invokestatic game.C_100163_sf.func_105433_a(game.C_100098_h, java.lang.String, java.lang.String, byte)game.C_100037_wb[]
		// @817: bipush 116 (0x74)
		// @819: invokestatic game.C_100215_ai.func_106004_a(game.C_100037_wb[], byte)game.C_100037_wb[]
		// @81C: putfield game.C_100037_wb[] game.C_100302_ka.field_101851_zb
		// @81F: getstatic game.C_100302_ka game.C_100075_uj.field_100659_q
		// @822: aload #4
		// @824: getstatic java.lang.String[] game.C_100205_qf.field_103683_z
		// @827: bipush 43 (0x2B)
		// @829: aaload
		// @82A: getstatic java.lang.String[] game.C_100205_qf.field_103683_z
		// @82D: bipush 38 (0x26)
		// @82F: aaload
		// @830: bipush -108 (0x94)
		// @832: invokestatic game.C_100163_sf.func_105433_a(game.C_100098_h, java.lang.String, java.lang.String, byte)game.C_100037_wb[]
		// @835: bipush 122 (0x7A)
		// @837: invokestatic game.C_100215_ai.func_106004_a(game.C_100037_wb[], byte)game.C_100037_wb[]
		// @83A: putfield game.C_100037_wb[] game.C_100302_ka.field_101853_M
		// @83D: getstatic game.C_100302_ka game.C_100338_jc.field_105375_i
		// @840: aload #4
		// @842: getstatic java.lang.String[] game.C_100205_qf.field_103683_z
		// @845: bipush 35 (0x23)
		// @847: aaload
		// @848: getstatic java.lang.String[] game.C_100205_qf.field_103683_z
		// @84B: bipush 38 (0x26)
		// @84D: aaload
		// @84E: bipush -99 (0x9D)
		// @850: invokestatic game.C_100163_sf.func_105433_a(game.C_100098_h, java.lang.String, java.lang.String, byte)game.C_100037_wb[]
		// @853: bipush 118 (0x76)
		// @855: invokestatic game.C_100215_ai.func_106004_a(game.C_100037_wb[], byte)game.C_100037_wb[]
		// @858: putfield game.C_100037_wb[] game.C_100302_ka.field_101862_T
		// @85B: getstatic game.C_100302_ka game.C_100338_jc.field_105375_i
		// @85E: aload #4
		// @860: getstatic java.lang.String[] game.C_100205_qf.field_103683_z
		// @863: bipush 33 (0x21)
		// @865: aaload
		// @866: getstatic java.lang.String[] game.C_100205_qf.field_103683_z
		// @869: bipush 38 (0x26)
		// @86B: aaload
		// @86C: bipush -120 (0x88)
		// @86E: invokestatic game.C_100163_sf.func_105433_a(game.C_100098_h, java.lang.String, java.lang.String, byte)game.C_100037_wb[]
		// @871: bipush 111 (0x6F)
		// @873: invokestatic game.C_100215_ai.func_106004_a(game.C_100037_wb[], byte)game.C_100037_wb[]
		// @876: putfield game.C_100037_wb[] game.C_100302_ka.field_101883_qb
		// @879: getstatic game.C_100302_ka game.C_100338_jc.field_105375_i
		// @87C: aload #4
		// @87E: getstatic java.lang.String[] game.C_100205_qf.field_103683_z
		// @881: bipush 44 (0x2C)
		// @883: aaload
		// @884: getstatic java.lang.String[] game.C_100205_qf.field_103683_z
		// @887: bipush 38 (0x26)
		// @889: aaload
		// @88A: bipush -88 (0xA8)
		// @88C: invokestatic game.C_100163_sf.func_105433_a(game.C_100098_h, java.lang.String, java.lang.String, byte)game.C_100037_wb[]
		// @88F: bipush 116 (0x74)
		// @891: invokestatic game.C_100215_ai.func_106004_a(game.C_100037_wb[], byte)game.C_100037_wb[]
		// @894: putfield game.C_100037_wb[] game.C_100302_ka.field_101851_zb
		// @897: getstatic game.C_100302_ka game.C_100309_lk.field_103272_bb
		// @89A: aload #4
		// @89C: getstatic java.lang.String[] game.C_100205_qf.field_103683_z
		// @89F: bipush 46 (0x2E)
		// @8A1: aaload
		// @8A2: getstatic java.lang.String[] game.C_100205_qf.field_103683_z
		// @8A5: bipush 38 (0x26)
		// @8A7: aaload
		// @8A8: bipush -99 (0x9D)
		// @8AA: invokestatic game.C_100163_sf.func_105433_a(game.C_100098_h, java.lang.String, java.lang.String, byte)game.C_100037_wb[]
		// @8AD: bipush 115 (0x73)
		// @8AF: invokestatic game.C_100215_ai.func_106004_a(game.C_100037_wb[], byte)game.C_100037_wb[]
		// @8B2: putfield game.C_100037_wb[] game.C_100302_ka.field_101862_T
		// @8B5: getstatic game.C_100302_ka game.C_100309_lk.field_103272_bb
		// @8B8: aload #4
		// @8BA: getstatic java.lang.String[] game.C_100205_qf.field_103683_z
		// @8BD: bipush 67 (0x43)
		// @8BF: aaload
		// @8C0: getstatic java.lang.String[] game.C_100205_qf.field_103683_z
		// @8C3: bipush 38 (0x26)
		// @8C5: aaload
		// @8C6: bipush -106 (0x96)
		// @8C8: invokestatic game.C_100163_sf.func_105433_a(game.C_100098_h, java.lang.String, java.lang.String, byte)game.C_100037_wb[]
		// @8CB: bipush 111 (0x6F)
		// @8CD: invokestatic game.C_100215_ai.func_106004_a(game.C_100037_wb[], byte)game.C_100037_wb[]
		// @8D0: putfield game.C_100037_wb[] game.C_100302_ka.field_101883_qb
		// @8D3: getstatic game.C_100302_ka game.C_100309_lk.field_103272_bb
		// @8D6: aload #4
		// @8D8: getstatic java.lang.String[] game.C_100205_qf.field_103683_z
		// @8DB: bipush 26 (0x1A)
		// @8DD: aaload
		// @8DE: getstatic java.lang.String[] game.C_100205_qf.field_103683_z
		// @8E1: bipush 38 (0x26)
		// @8E3: aaload
		// @8E4: bipush -121 (0x87)
		// @8E6: invokestatic game.C_100163_sf.func_105433_a(game.C_100098_h, java.lang.String, java.lang.String, byte)game.C_100037_wb[]
		// @8E9: bipush 116 (0x74)
		// @8EB: invokestatic game.C_100215_ai.func_106004_a(game.C_100037_wb[], byte)game.C_100037_wb[]
		// @8EE: putfield game.C_100037_wb[] game.C_100302_ka.field_101851_zb
		// @8F1: getstatic game.C_100302_ka game.C_100031_gl.field_103967_c
		// @8F4: aload #4
		// @8F6: getstatic java.lang.String[] game.C_100205_qf.field_103683_z
		// @8F9: bipush 49 (0x31)
		// @8FB: aaload
		// @8FC: getstatic java.lang.String[] game.C_100205_qf.field_103683_z
		// @8FF: bipush 38 (0x26)
		// @901: aaload
		// @902: bipush -101 (0x9B)
		// @904: invokestatic game.C_100163_sf.func_105433_a(game.C_100098_h, java.lang.String, java.lang.String, byte)game.C_100037_wb[]
		// @907: bipush 115 (0x73)
		// @909: invokestatic game.C_100215_ai.func_106004_a(game.C_100037_wb[], byte)game.C_100037_wb[]
		// @90C: putfield game.C_100037_wb[] game.C_100302_ka.field_101862_T
		// @90F: getstatic game.C_100302_ka game.C_100031_gl.field_103967_c
		// @912: aload #4
		// @914: getstatic java.lang.String[] game.C_100205_qf.field_103683_z
		// @917: bipush 39 (0x27)
		// @919: aaload
		// @91A: getstatic java.lang.String[] game.C_100205_qf.field_103683_z
		// @91D: bipush 38 (0x26)
		// @91F: aaload
		// @920: bipush -117 (0x8B)
		// @922: invokestatic game.C_100163_sf.func_105433_a(game.C_100098_h, java.lang.String, java.lang.String, byte)game.C_100037_wb[]
		// @925: bipush 111 (0x6F)
		// @927: invokestatic game.C_100215_ai.func_106004_a(game.C_100037_wb[], byte)game.C_100037_wb[]
		// @92A: putfield game.C_100037_wb[] game.C_100302_ka.field_101883_qb
		// @92D: getstatic game.C_100302_ka game.C_100031_gl.field_103967_c
		// @930: aload #4
		// @932: getstatic java.lang.String[] game.C_100205_qf.field_103683_z
		// @935: bipush 58 (0x3A)
		// @937: aaload
		// @938: getstatic java.lang.String[] game.C_100205_qf.field_103683_z
		// @93B: bipush 38 (0x26)
		// @93D: aaload
		// @93E: bipush -95 (0xA1)
		// @940: invokestatic game.C_100163_sf.func_105433_a(game.C_100098_h, java.lang.String, java.lang.String, byte)game.C_100037_wb[]
		// @943: bipush 127 (0x7F)
		// @945: invokestatic game.C_100215_ai.func_106004_a(game.C_100037_wb[], byte)game.C_100037_wb[]
		// @948: putfield game.C_100037_wb[] game.C_100302_ka.field_101851_zb
		// @94B: getstatic game.C_100302_ka game.C_100031_gl.field_103967_c
		// @94E: aload #4
		// @950: getstatic java.lang.String[] game.C_100205_qf.field_103683_z
		// @953: bipush 41 (0x29)
		// @955: aaload
		// @956: getstatic java.lang.String[] game.C_100205_qf.field_103683_z
		// @959: bipush 38 (0x26)
		// @95B: aaload
		// @95C: bipush -97 (0x9F)
		// @95E: invokestatic game.C_100163_sf.func_105433_a(game.C_100098_h, java.lang.String, java.lang.String, byte)game.C_100037_wb[]
		// @961: bipush 127 (0x7F)
		// @963: invokestatic game.C_100215_ai.func_106004_a(game.C_100037_wb[], byte)game.C_100037_wb[]
		// @966: putfield game.C_100037_wb[] game.C_100302_ka.field_101853_M
		// @969: getstatic game.C_100302_ka game.C_100061_dh.field_101985_ec
		// @96C: aload #4
		// @96E: getstatic java.lang.String[] game.C_100205_qf.field_103683_z
		// @971: bipush 42 (0x2A)
		// @973: aaload
		// @974: getstatic java.lang.String[] game.C_100205_qf.field_103683_z
		// @977: bipush 38 (0x26)
		// @979: aaload
		// @97A: bipush -108 (0x94)
		// @97C: invokestatic game.C_100163_sf.func_105433_a(game.C_100098_h, java.lang.String, java.lang.String, byte)game.C_100037_wb[]
		// @97F: bipush 118 (0x76)
		// @981: invokestatic game.C_100215_ai.func_106004_a(game.C_100037_wb[], byte)game.C_100037_wb[]
		// @984: putfield game.C_100037_wb[] game.C_100302_ka.field_101862_T
		// @987: getstatic game.C_100302_ka game.C_100061_dh.field_101985_ec
		// @98A: aload #4
		// @98C: getstatic java.lang.String[] game.C_100205_qf.field_103683_z
		// @98F: bipush 9 (0x09)
		// @991: aaload
		// @992: getstatic java.lang.String[] game.C_100205_qf.field_103683_z
		// @995: bipush 38 (0x26)
		// @997: aaload
		// @998: bipush -91 (0xA5)
		// @99A: invokestatic game.C_100163_sf.func_105433_a(game.C_100098_h, java.lang.String, java.lang.String, byte)game.C_100037_wb[]
		// @99D: bipush 127 (0x7F)
		// @99F: invokestatic game.C_100215_ai.func_106004_a(game.C_100037_wb[], byte)game.C_100037_wb[]
		// @9A2: putfield game.C_100037_wb[] game.C_100302_ka.field_101883_qb
		// @9A5: getstatic game.C_100302_ka game.C_100061_dh.field_101985_ec
		// @9A8: getstatic game.C_100302_ka game.C_100061_dh.field_101985_ec
		// @9AB: aload #4
		// @9AD: getstatic java.lang.String[] game.C_100205_qf.field_103683_z
		// @9B0: bipush 20 (0x14)
		// @9B2: aaload
		// @9B3: getstatic java.lang.String[] game.C_100205_qf.field_103683_z
		// @9B6: bipush 38 (0x26)
		// @9B8: aaload
		// @9B9: bipush -120 (0x88)
		// @9BB: invokestatic game.C_100163_sf.func_105433_a(game.C_100098_h, java.lang.String, java.lang.String, byte)game.C_100037_wb[]
		// @9BE: bipush 115 (0x73)
		// @9C0: invokestatic game.C_100215_ai.func_106004_a(game.C_100037_wb[], byte)game.C_100037_wb[]
		// @9C3: dup_x1
		// @9C4: putfield game.C_100037_wb[] game.C_100302_ka.field_101878_Jb
		// @9C7: putfield game.C_100037_wb[] game.C_100302_ka.field_101851_zb
		// @9CA: getstatic game.C_100302_ka game.C_100061_dh.field_101985_ec
		// @9CD: aload #4
		// @9CF: getstatic java.lang.String[] game.C_100205_qf.field_103683_z
		// @9D2: bipush 48 (0x30)
		// @9D4: aaload
		// @9D5: getstatic java.lang.String[] game.C_100205_qf.field_103683_z
		// @9D8: bipush 38 (0x26)
		// @9DA: aaload
		// @9DB: bipush -95 (0xA1)
		// @9DD: invokestatic game.C_100163_sf.func_105433_a(game.C_100098_h, java.lang.String, java.lang.String, byte)game.C_100037_wb[]
		// @9E0: bipush 124 (0x7C)
		// @9E2: invokestatic game.C_100215_ai.func_106004_a(game.C_100037_wb[], byte)game.C_100037_wb[]
		// @9E5: putfield game.C_100037_wb[] game.C_100302_ka.field_101853_M
		// @9E8: getstatic game.C_100302_ka game.C_100316_lc.field_102404_D
		// @9EB: aload #4
		// @9ED: getstatic java.lang.String[] game.C_100205_qf.field_103683_z
		// @9F0: bipush 72 (0x48)
		// @9F2: aaload
		// @9F3: getstatic java.lang.String[] game.C_100205_qf.field_103683_z
		// @9F6: bipush 38 (0x26)
		// @9F8: aaload
		// @9F9: bipush -117 (0x8B)
		// @9FB: invokestatic game.C_100163_sf.func_105433_a(game.C_100098_h, java.lang.String, java.lang.String, byte)game.C_100037_wb[]
		// @9FE: bipush 125 (0x7D)
		// @A00: invokestatic game.C_100215_ai.func_106004_a(game.C_100037_wb[], byte)game.C_100037_wb[]
		// @A03: putfield game.C_100037_wb[] game.C_100302_ka.field_101862_T
		// @A06: getstatic game.C_100302_ka game.C_100316_lc.field_102404_D
		// @A09: aload #4
		// @A0B: getstatic java.lang.String[] game.C_100205_qf.field_103683_z
		// @A0E: bipush 40 (0x28)
		// @A10: aaload
		// @A11: getstatic java.lang.String[] game.C_100205_qf.field_103683_z
		// @A14: bipush 38 (0x26)
		// @A16: aaload
		// @A17: bipush -113 (0x8F)
		// @A19: invokestatic game.C_100163_sf.func_105433_a(game.C_100098_h, java.lang.String, java.lang.String, byte)game.C_100037_wb[]
		// @A1C: bipush 115 (0x73)
		// @A1E: invokestatic game.C_100215_ai.func_106004_a(game.C_100037_wb[], byte)game.C_100037_wb[]
		// @A21: putfield game.C_100037_wb[] game.C_100302_ka.field_101883_qb
		// @A24: getstatic game.C_100302_ka game.C_100316_lc.field_102404_D
		// @A27: getstatic game.C_100302_ka game.C_100316_lc.field_102404_D
		// @A2A: aload #4
		// @A2C: getstatic java.lang.String[] game.C_100205_qf.field_103683_z
		// @A2F: bipush 14 (0x0E)
		// @A31: aaload
		// @A32: getstatic java.lang.String[] game.C_100205_qf.field_103683_z
		// @A35: bipush 38 (0x26)
		// @A37: aaload
		// @A38: bipush -119 (0x89)
		// @A3A: invokestatic game.C_100163_sf.func_105433_a(game.C_100098_h, java.lang.String, java.lang.String, byte)game.C_100037_wb[]
		// @A3D: bipush 114 (0x72)
		// @A3F: invokestatic game.C_100215_ai.func_106004_a(game.C_100037_wb[], byte)game.C_100037_wb[]
		// @A42: dup_x1
		// @A43: putfield game.C_100037_wb[] game.C_100302_ka.field_101878_Jb
		// @A46: putfield game.C_100037_wb[] game.C_100302_ka.field_101851_zb
		// @A49: getstatic game.C_100302_ka game.C_100341_jd.field_102652_kb
		// @A4C: aload #4
		// @A4E: getstatic java.lang.String[] game.C_100205_qf.field_103683_z
		// @A51: bipush 17 (0x11)
		// @A53: aaload
		// @A54: getstatic java.lang.String[] game.C_100205_qf.field_103683_z
		// @A57: bipush 38 (0x26)
		// @A59: aaload
		// @A5A: bipush -95 (0xA1)
		// @A5C: invokestatic game.C_100163_sf.func_105433_a(game.C_100098_h, java.lang.String, java.lang.String, byte)game.C_100037_wb[]
		// @A5F: bipush 127 (0x7F)
		// @A61: invokestatic game.C_100215_ai.func_106004_a(game.C_100037_wb[], byte)game.C_100037_wb[]
		// @A64: putfield game.C_100037_wb[] game.C_100302_ka.field_101862_T
		// @A67: getstatic game.C_100302_ka game.C_100341_jd.field_102652_kb
		// @A6A: aload #4
		// @A6C: getstatic java.lang.String[] game.C_100205_qf.field_103683_z
		// @A6F: bipush 25 (0x19)
		// @A71: aaload
		// @A72: getstatic java.lang.String[] game.C_100205_qf.field_103683_z
		// @A75: bipush 38 (0x26)
		// @A77: aaload
		// @A78: bipush -98 (0x9E)
		// @A7A: invokestatic game.C_100163_sf.func_105433_a(game.C_100098_h, java.lang.String, java.lang.String, byte)game.C_100037_wb[]
		// @A7D: bipush 116 (0x74)
		// @A7F: invokestatic game.C_100215_ai.func_106004_a(game.C_100037_wb[], byte)game.C_100037_wb[]
		// @A82: putfield game.C_100037_wb[] game.C_100302_ka.field_101883_qb
		// @A85: getstatic game.C_100302_ka game.C_100341_jd.field_102652_kb
		// @A88: getstatic game.C_100302_ka game.C_100341_jd.field_102652_kb
		// @A8B: aload #4
		// @A8D: getstatic java.lang.String[] game.C_100205_qf.field_103683_z
		// @A90: bipush 57 (0x39)
		// @A92: aaload
		// @A93: getstatic java.lang.String[] game.C_100205_qf.field_103683_z
		// @A96: bipush 38 (0x26)
		// @A98: aaload
		// @A99: bipush -95 (0xA1)
		// @A9B: invokestatic game.C_100163_sf.func_105433_a(game.C_100098_h, java.lang.String, java.lang.String, byte)game.C_100037_wb[]
		// @A9E: bipush 116 (0x74)
		// @AA0: invokestatic game.C_100215_ai.func_106004_a(game.C_100037_wb[], byte)game.C_100037_wb[]
		// @AA3: dup_x1
		// @AA4: putfield game.C_100037_wb[] game.C_100302_ka.field_101878_Jb
		// @AA7: putfield game.C_100037_wb[] game.C_100302_ka.field_101851_zb
		// @AAA: aload #4
		// @AAC: getstatic java.lang.String[] game.C_100205_qf.field_103683_z
		// @AAF: bipush 28 (0x1C)
		// @AB1: aaload
		// @AB2: getstatic java.lang.String[] game.C_100205_qf.field_103683_z
		// @AB5: bipush 38 (0x26)
		// @AB7: aaload
		// @AB8: bipush -105 (0x97)
		// @ABA: invokestatic game.C_100163_sf.func_105433_a(game.C_100098_h, java.lang.String, java.lang.String, byte)game.C_100037_wb[]
		// @ABD: astore #18
		// @ABF: new game.C_100122_em
		// @AC2: dup
		// @AC3: lconst_0
		// @AC4: aload #18
		// @AC6: iconst_1
		// @AC7: aaload
		// @AC8: aload #18
		// @ACA: iconst_0
		// @ACB: aaload
		// @ACC: iconst_1
		// @ACD: getstatic game.C_100302_ka game.C_100236_on.field_100906_r
		// @AD0: aconst_null
		// @AD1: invokespecial game.C_100122_em.<init>(long, game.C_100037_wb, game.C_100037_wb, int, game.C_100302_ka, java.lang.String)void
		// @AD4: putstatic game.C_100122_em game.C_100119_ua.field_104902_b
		// @AD7: new game.C_100302_ka
		// @ADA: dup
		// @ADB: lconst_0
		// @ADC: aconst_null
		// @ADD: invokespecial game.C_100302_ka.<init>(long, game.C_100302_ka)void
		// @AE0: putstatic game.C_100302_ka game.C_100180_ce.field_104814_y
		// @AE3: getstatic game.C_100302_ka game.C_100180_ce.field_104814_y
		// @AE6: bipush 90 (0x5A)
		// @AE8: getstatic java.lang.String[] game.C_100205_qf.field_103683_z
		// @AEB: bipush 38 (0x26)
		// @AED: aaload
		// @AEE: aload #4
		// @AF0: getstatic java.lang.String[] game.C_100205_qf.field_103683_z
		// @AF3: bipush 74 (0x4A)
		// @AF5: aaload
		// @AF6: invokestatic game.C_100021_wn.func_103861_a(byte, java.lang.String, game.C_100098_h, java.lang.String)game.C_100037_wb
		// @AF9: iconst_0
		// @AFA: invokestatic game.C_100207_qh.func_102870_a(game.C_100037_wb, int)game.C_100037_wb[]
		// @AFD: putfield game.C_100037_wb[] game.C_100302_ka.field_101862_T
		// @B00: getstatic game.C_100302_ka game.C_100180_ce.field_104814_y
		// @B03: bipush 81 (0x51)
		// @B05: getstatic java.lang.String[] game.C_100205_qf.field_103683_z
		// @B08: bipush 38 (0x26)
		// @B0A: aaload
		// @B0B: aload #4
		// @B0D: getstatic java.lang.String[] game.C_100205_qf.field_103683_z
		// @B10: bipush 60 (0x3C)
		// @B12: aaload
		// @B13: invokestatic game.C_100021_wn.func_103861_a(byte, java.lang.String, game.C_100098_h, java.lang.String)game.C_100037_wb
		// @B16: iconst_0
		// @B17: invokestatic game.C_100207_qh.func_102870_a(game.C_100037_wb, int)game.C_100037_wb[]
		// @B1A: putfield game.C_100037_wb[] game.C_100302_ka.field_101883_qb
		// @B1D: getstatic game.C_100302_ka game.C_100180_ce.field_104814_y
		// @B20: bipush 101 (0x65)
		// @B22: getstatic java.lang.String[] game.C_100205_qf.field_103683_z
		// @B25: bipush 38 (0x26)
		// @B27: aaload
		// @B28: aload #4
		// @B2A: getstatic java.lang.String[] game.C_100205_qf.field_103683_z
		// @B2D: bipush 34 (0x22)
		// @B2F: aaload
		// @B30: invokestatic game.C_100021_wn.func_103861_a(byte, java.lang.String, game.C_100098_h, java.lang.String)game.C_100037_wb
		// @B33: iconst_0
		// @B34: invokestatic game.C_100207_qh.func_102870_a(game.C_100037_wb, int)game.C_100037_wb[]
		// @B37: putfield game.C_100037_wb[] game.C_100302_ka.field_101851_zb
		// @B3A: getstatic game.C_100302_ka game.C_100180_ce.field_104814_y
		// @B3D: bipush 119 (0x77)
		// @B3F: getstatic java.lang.String[] game.C_100205_qf.field_103683_z
		// @B42: bipush 38 (0x26)
		// @B44: aaload
		// @B45: aload #4
		// @B47: getstatic java.lang.String[] game.C_100205_qf.field_103683_z
		// @B4A: bipush 51 (0x33)
		// @B4C: aaload
		// @B4D: invokestatic game.C_100021_wn.func_103861_a(byte, java.lang.String, game.C_100098_h, java.lang.String)game.C_100037_wb
		// @B50: iconst_0
		// @B51: invokestatic game.C_100207_qh.func_102870_a(game.C_100037_wb, int)game.C_100037_wb[]
		// @B54: putfield game.C_100037_wb[] game.C_100302_ka.field_101853_M
		// @B57: new game.C_100302_ka
		// @B5A: dup
		// @B5B: lconst_0
		// @B5C: aconst_null
		// @B5D: invokespecial game.C_100302_ka.<init>(long, game.C_100302_ka)void
		// @B60: putstatic game.C_100302_ka game.C_100122_em.field_102081_bc
		// @B63: getstatic game.C_100302_ka game.C_100122_em.field_102081_bc
		// @B66: aload #4
		// @B68: getstatic java.lang.String[] game.C_100205_qf.field_103683_z
		// @B6B: bipush 24 (0x18)
		// @B6D: aaload
		// @B6E: getstatic java.lang.String[] game.C_100205_qf.field_103683_z
		// @B71: bipush 38 (0x26)
		// @B73: aaload
		// @B74: bipush -128 (0x80)
		// @B76: invokestatic game.C_100163_sf.func_105433_a(game.C_100098_h, java.lang.String, java.lang.String, byte)game.C_100037_wb[]
		// @B79: bipush 123 (0x7B)
		// @B7B: invokestatic game.C_100215_ai.func_106004_a(game.C_100037_wb[], byte)game.C_100037_wb[]
		// @B7E: putfield game.C_100037_wb[] game.C_100302_ka.field_101862_T
		// @B81: getstatic game.C_100302_ka game.C_100122_em.field_102081_bc
		// @B84: aload #4
		// @B86: getstatic java.lang.String[] game.C_100205_qf.field_103683_z
		// @B89: bipush 10 (0x0A)
		// @B8B: aaload
		// @B8C: getstatic java.lang.String[] game.C_100205_qf.field_103683_z
		// @B8F: bipush 38 (0x26)
		// @B91: aaload
		// @B92: bipush -120 (0x88)
		// @B94: invokestatic game.C_100163_sf.func_105433_a(game.C_100098_h, java.lang.String, java.lang.String, byte)game.C_100037_wb[]
		// @B97: bipush 114 (0x72)
		// @B99: invokestatic game.C_100215_ai.func_106004_a(game.C_100037_wb[], byte)game.C_100037_wb[]
		// @B9C: putfield game.C_100037_wb[] game.C_100302_ka.field_101883_qb
		// @B9F: getstatic game.C_100302_ka game.C_100122_em.field_102081_bc
		// @BA2: aload #4
		// @BA4: getstatic java.lang.String[] game.C_100205_qf.field_103683_z
		// @BA7: bipush 30 (0x1E)
		// @BA9: aaload
		// @BAA: getstatic java.lang.String[] game.C_100205_qf.field_103683_z
		// @BAD: bipush 38 (0x26)
		// @BAF: aaload
		// @BB0: bipush -101 (0x9B)
		// @BB2: invokestatic game.C_100163_sf.func_105433_a(game.C_100098_h, java.lang.String, java.lang.String, byte)game.C_100037_wb[]
		// @BB5: bipush 123 (0x7B)
		// @BB7: invokestatic game.C_100215_ai.func_106004_a(game.C_100037_wb[], byte)game.C_100037_wb[]
		// @BBA: putfield game.C_100037_wb[] game.C_100302_ka.field_101851_zb
		// @BBD: getstatic game.C_100302_ka game.C_100122_em.field_102081_bc
		// @BC0: aload #4
		// @BC2: getstatic java.lang.String[] game.C_100205_qf.field_103683_z
		// @BC5: bipush 16 (0x10)
		// @BC7: aaload
		// @BC8: getstatic java.lang.String[] game.C_100205_qf.field_103683_z
		// @BCB: bipush 38 (0x26)
		// @BCD: aaload
		// @BCE: bipush -88 (0xA8)
		// @BD0: invokestatic game.C_100163_sf.func_105433_a(game.C_100098_h, java.lang.String, java.lang.String, byte)game.C_100037_wb[]
		// @BD3: bipush 127 (0x7F)
		// @BD5: invokestatic game.C_100215_ai.func_106004_a(game.C_100037_wb[], byte)game.C_100037_wb[]
		// @BD8: putfield game.C_100037_wb[] game.C_100302_ka.field_101853_M
		// @BDB: new game.C_100302_ka
		// @BDE: dup
		// @BDF: lconst_0
		// @BE0: aconst_null
		// @BE1: invokespecial game.C_100302_ka.<init>(long, game.C_100302_ka)void
		// @BE4: putstatic game.C_100302_ka game.C_100228_nn.field_106185_g
		// @BE7: getstatic game.C_100302_ka game.C_100228_nn.field_106185_g
		// @BEA: bipush 92 (0x5C)
		// @BEC: getstatic java.lang.String[] game.C_100205_qf.field_103683_z
		// @BEF: bipush 38 (0x26)
		// @BF1: aaload
		// @BF2: aload #4
		// @BF4: getstatic java.lang.String[] game.C_100205_qf.field_103683_z
		// @BF7: bipush 36 (0x24)
		// @BF9: aaload
		// @BFA: invokestatic game.C_100021_wn.func_103861_a(byte, java.lang.String, game.C_100098_h, java.lang.String)game.C_100037_wb
		// @BFD: putfield game.C_100037_wb game.C_100302_ka.field_101887_nb
		// @C00: getstatic game.C_100302_ka game.C_100228_nn.field_106185_g
		// @C03: bipush 123 (0x7B)
		// @C05: getstatic java.lang.String[] game.C_100205_qf.field_103683_z
		// @C08: bipush 38 (0x26)
		// @C0A: aaload
		// @C0B: aload #4
		// @C0D: getstatic java.lang.String[] game.C_100205_qf.field_103683_z
		// @C10: bipush 68 (0x44)
		// @C12: aaload
		// @C13: invokestatic game.C_100021_wn.func_103861_a(byte, java.lang.String, game.C_100098_h, java.lang.String)game.C_100037_wb
		// @C16: putfield game.C_100037_wb game.C_100302_ka.field_101844_pb
		// @C19: getstatic game.C_100302_ka game.C_100228_nn.field_106185_g
		// @C1C: bipush 97 (0x61)
		// @C1E: getstatic java.lang.String[] game.C_100205_qf.field_103683_z
		// @C21: bipush 38 (0x26)
		// @C23: aaload
		// @C24: aload #4
		// @C26: getstatic java.lang.String[] game.C_100205_qf.field_103683_z
		// @C29: bipush 71 (0x47)
		// @C2B: aaload
		// @C2C: invokestatic game.C_100021_wn.func_103861_a(byte, java.lang.String, game.C_100098_h, java.lang.String)game.C_100037_wb
		// @C2F: putfield game.C_100037_wb game.C_100302_ka.field_101884_fb
		// @C32: getstatic game.C_100302_ka game.C_100228_nn.field_106185_g
		// @C35: bipush 112 (0x70)
		// @C37: getstatic java.lang.String[] game.C_100205_qf.field_103683_z
		// @C3A: bipush 38 (0x26)
		// @C3C: aaload
		// @C3D: aload #4
		// @C3F: getstatic java.lang.String[] game.C_100205_qf.field_103683_z
		// @C42: bipush 65 (0x41)
		// @C44: aaload
		// @C45: invokestatic game.C_100021_wn.func_103861_a(byte, java.lang.String, game.C_100098_h, java.lang.String)game.C_100037_wb
		// @C48: putfield game.C_100037_wb game.C_100302_ka.field_101852_L
		// @C4B: new game.C_100302_ka
		// @C4E: dup
		// @C4F: lconst_0
		// @C50: aconst_null
		// @C51: invokespecial game.C_100302_ka.<init>(long, game.C_100302_ka)void
		// @C54: putstatic game.C_100302_ka game.C_100144_bm.field_102098_Yb
		// @C57: getstatic game.C_100302_ka game.C_100144_bm.field_102098_Yb
		// @C5A: bipush 91 (0x5B)
		// @C5C: getstatic java.lang.String[] game.C_100205_qf.field_103683_z
		// @C5F: bipush 38 (0x26)
		// @C61: aaload
		// @C62: aload #4
		// @C64: getstatic java.lang.String[] game.C_100205_qf.field_103683_z
		// @C67: bipush 47 (0x2F)
		// @C69: aaload
		// @C6A: invokestatic game.C_100021_wn.func_103861_a(byte, java.lang.String, game.C_100098_h, java.lang.String)game.C_100037_wb
		// @C6D: putfield game.C_100037_wb game.C_100302_ka.field_101887_nb
		// @C70: getstatic game.C_100302_ka game.C_100144_bm.field_102098_Yb
		// @C73: bipush 122 (0x7A)
		// @C75: getstatic java.lang.String[] game.C_100205_qf.field_103683_z
		// @C78: bipush 38 (0x26)
		// @C7A: aaload
		// @C7B: aload #4
		// @C7D: getstatic java.lang.String[] game.C_100205_qf.field_103683_z
		// @C80: bipush 8 (0x08)
		// @C82: aaload
		// @C83: invokestatic game.C_100021_wn.func_103861_a(byte, java.lang.String, game.C_100098_h, java.lang.String)game.C_100037_wb
		// @C86: putfield game.C_100037_wb game.C_100302_ka.field_101844_pb
		// @C89: getstatic game.C_100302_ka game.C_100144_bm.field_102098_Yb
		// @C8C: bipush 125 (0x7D)
		// @C8E: getstatic java.lang.String[] game.C_100205_qf.field_103683_z
		// @C91: bipush 38 (0x26)
		// @C93: aaload
		// @C94: aload #4
		// @C96: getstatic java.lang.String[] game.C_100205_qf.field_103683_z
		// @C99: bipush 70 (0x46)
		// @C9B: aaload
		// @C9C: invokestatic game.C_100021_wn.func_103861_a(byte, java.lang.String, game.C_100098_h, java.lang.String)game.C_100037_wb
		// @C9F: putfield game.C_100037_wb game.C_100302_ka.field_101884_fb
		// @CA2: getstatic game.C_100302_ka game.C_100144_bm.field_102098_Yb
		// @CA5: bipush 85 (0x55)
		// @CA7: getstatic java.lang.String[] game.C_100205_qf.field_103683_z
		// @CAA: bipush 38 (0x26)
		// @CAC: aaload
		// @CAD: aload #4
		// @CAF: getstatic java.lang.String[] game.C_100205_qf.field_103683_z
		// @CB2: bipush 21 (0x15)
		// @CB4: aaload
		// @CB5: invokestatic game.C_100021_wn.func_103861_a(byte, java.lang.String, game.C_100098_h, java.lang.String)game.C_100037_wb
		// @CB8: putfield game.C_100037_wb game.C_100302_ka.field_101852_L
		// @CBB: new game.C_100231_oc
		// @CBE: dup
		// @CBF: lconst_0
		// @CC0: getstatic game.C_100302_ka game.C_100228_nn.field_106185_g
		// @CC3: getstatic game.C_100302_ka game.C_100144_bm.field_102098_Yb
		// @CC6: getstatic game.C_100302_ka game.C_100180_ce.field_104814_y
		// @CC9: getstatic game.C_100302_ka game.C_100122_em.field_102081_bc
		// @CCC: invokespecial game.C_100231_oc.<init>(long, game.C_100302_ka, game.C_100302_ka, game.C_100302_ka, game.C_100302_ka)void
		// @CCF: putstatic game.C_100231_oc game.C_100013_fn.field_103737_f
		// @CD2: new game.C_100100_i
		// @CD5: dup
		// @CD6: lconst_0
		// @CD7: aconst_null
		// @CD8: getstatic game.C_100302_ka game.C_100085_a.field_102572_O
		// @CDB: getstatic game.C_100231_oc game.C_100013_fn.field_103737_f
		// @CDE: getstatic game.C_100302_ka game.C_100017_wj.field_103816_d
		// @CE1: aconst_null
		// @CE2: aconst_null
		// @CE3: invokespecial game.C_100100_i.<init>(long, game.C_100302_ka, game.C_100302_ka, game.C_100231_oc, game.C_100302_ka, java.lang.String, java.lang.String)void
		// @CE6: putstatic game.C_100100_i game.C_100078_ul.field_103283_nb
		// @CE9: goto @D79
		// @CEC: astore #5
		// @CEE: aload #5
		// @CF0: new java.lang.StringBuilder
		// @CF3: dup
		// @CF4: invokespecial java.lang.StringBuilder.<init>()void
		// @CF7: getstatic java.lang.String[] game.C_100205_qf.field_103683_z
		// @CFA: bipush 64 (0x40)
		// @CFC: aaload
		// @CFD: invokevirtual java.lang.StringBuilder.append(java.lang.String)java.lang.StringBuilder
		// @D00: iload_0
		// @D01: invokevirtual java.lang.StringBuilder.append(int)java.lang.StringBuilder
		// @D04: bipush 44 (0x2C)
		// @D06: invokevirtual java.lang.StringBuilder.append(char)java.lang.StringBuilder
		// @D09: aload_1
		// @D0A: ifnull @D16
		// @D0D: getstatic java.lang.String[] game.C_100205_qf.field_103683_z
		// @D10: iconst_3
		// @D11: aaload
		// @D12: goto @D1B
		// @D15: athrow
		// @D16: getstatic java.lang.String[] game.C_100205_qf.field_103683_z
		// @D19: iconst_4
		// @D1A: aaload
		// @D1B: invokevirtual java.lang.StringBuilder.append(java.lang.String)java.lang.StringBuilder
		// @D1E: bipush 44 (0x2C)
		// @D20: invokevirtual java.lang.StringBuilder.append(char)java.lang.StringBuilder
		// @D23: aload_2
		// @D24: ifnull @D30
		// @D27: getstatic java.lang.String[] game.C_100205_qf.field_103683_z
		// @D2A: iconst_3
		// @D2B: aaload
		// @D2C: goto @D35
		// @D2F: athrow
		// @D30: getstatic java.lang.String[] game.C_100205_qf.field_103683_z
		// @D33: iconst_4
		// @D34: aaload
		// @D35: invokevirtual java.lang.StringBuilder.append(java.lang.String)java.lang.StringBuilder
		// @D38: bipush 44 (0x2C)
		// @D3A: invokevirtual java.lang.StringBuilder.append(char)java.lang.StringBuilder
		// @D3D: aload_3
		// @D3E: ifnull @D4A
		// @D41: getstatic java.lang.String[] game.C_100205_qf.field_103683_z
		// @D44: iconst_3
		// @D45: aaload
		// @D46: goto @D4F
		// @D49: athrow
		// @D4A: getstatic java.lang.String[] game.C_100205_qf.field_103683_z
		// @D4D: iconst_4
		// @D4E: aaload
		// @D4F: invokevirtual java.lang.StringBuilder.append(java.lang.String)java.lang.StringBuilder
		// @D52: bipush 44 (0x2C)
		// @D54: invokevirtual java.lang.StringBuilder.append(char)java.lang.StringBuilder
		// @D57: aload #4
		// @D59: ifnull @D65
		// @D5C: getstatic java.lang.String[] game.C_100205_qf.field_103683_z
		// @D5F: iconst_3
		// @D60: aaload
		// @D61: goto @D6A
		// @D64: athrow
		// @D65: getstatic java.lang.String[] game.C_100205_qf.field_103683_z
		// @D68: iconst_4
		// @D69: aaload
		// @D6A: invokevirtual java.lang.StringBuilder.append(java.lang.String)java.lang.StringBuilder
		// @D6D: bipush 41 (0x29)
		// @D6F: invokevirtual java.lang.StringBuilder.append(char)java.lang.StringBuilder
		// @D72: invokevirtual java.lang.StringBuilder.toString()java.lang.String
		// @D75: invokestatic game.C_100181_cf.func_105695_a(java.lang.Throwable, java.lang.String)game.C_100170_cm
		// @D78: athrow
		// @D79: return
	}
	
	final int func_103664_a(int arg0, int arg1, int arg2)
	{
		// @000: getstatic int game.SteelSentinels.field_105275_O
		// @003: istore #8
		// @005: aload_0
		// @006: getfield game.C_100306_kn[] game.C_100205_qf.field_103677_g
		// @009: ifnull @02C
		// @00C: aload_0
		// @00D: getfield game.C_100306_kn[] game.C_100205_qf.field_103677_g
		// @010: arraylength
		// @011: iconst_m1
		// @012: ixor
		// @013: iconst_m1
		// @014: if_icmpeq @02C
		// @017: goto @01B
		// @01A: athrow
		// @01B: iload_1
		// @01C: aload_0
		// @01D: getfield game.C_100306_kn[] game.C_100205_qf.field_103677_g
		// @020: iconst_0
		// @021: aaload
		// @022: getfield int game.C_100306_kn.field_107129_f
		// @025: if_icmpge @02E
		// @028: goto @02C
		// @02B: athrow
		// @02C: iconst_m1
		// @02D: ireturn
		// @02E: iload_1
		// @02F: aload_0
		// @030: getfield game.C_100306_kn[] game.C_100205_qf.field_103677_g
		// @033: aload_0
		// @034: getfield game.C_100306_kn[] game.C_100205_qf.field_103677_g
		// @037: arraylength
		// @038: iconst_m1
		// @039: iadd
		// @03A: aaload
		// @03B: getfield int game.C_100306_kn.field_107135_a
		// @03E: if_icmple @043
		// @041: iconst_m1
		// @042: ireturn
		// @043: iload_3
		// @044: bipush -33 (0xDF)
		// @046: if_icmpeq @052
		// @049: bipush -53 (0xCB)
		// @04B: putstatic int game.C_100205_qf.field_103678_d
		// @04E: goto @052
		// @051: athrow
		// @052: iconst_1
		// @053: aload_0
		// @054: getfield game.C_100306_kn[] game.C_100205_qf.field_103677_g
		// @057: arraylength
		// @058: if_icmpeq @05F
		// @05B: goto @06B
		// @05E: athrow
		// @05F: aload_0
		// @060: getfield game.C_100306_kn[] game.C_100205_qf.field_103677_g
		// @063: iconst_0
		// @064: aaload
		// @065: iconst_0
		// @066: iload_2
		// @067: invokevirtual game.C_100306_kn.func_107127_a(boolean, int)int
		// @06A: ireturn
		// @06B: iconst_0
		// @06C: istore #4
		// @06E: iconst_0
		// @06F: istore #5
		// @071: aload_0
		// @072: getfield game.C_100306_kn[] game.C_100205_qf.field_103677_g
		// @075: arraylength
		// @076: iload #5
		// @078: if_icmple @0D5
		// @07B: aload_0
		// @07C: getfield game.C_100306_kn[] game.C_100205_qf.field_103677_g
		// @07F: iload #5
		// @081: aaload
		// @082: astore #6
		// @084: aload #6
		// @086: getfield int game.C_100306_kn.field_107129_f
		// @089: iload #8
		// @08B: ifne @0D6
		// @08E: iload_1
		// @08F: if_icmpgt @0C0
		// @092: goto @096
		// @095: athrow
		// @096: iload_1
		// @097: aload #6
		// @099: getfield int game.C_100306_kn.field_107135_a
		// @09C: if_icmpgt @0C0
		// @09F: goto @0A3
		// @0A2: athrow
		// @0A3: aload #6
		// @0A5: iconst_0
		// @0A6: iload_2
		// @0A7: invokevirtual game.C_100306_kn.func_107127_a(boolean, int)int
		// @0AA: istore #7
		// @0AC: iconst_0
		// @0AD: iload #7
		// @0AF: iconst_m1
		// @0B0: ixor
		// @0B1: if_icmpeq @0B8
		// @0B4: goto @0BA
		// @0B7: athrow
		// @0B8: iconst_m1
		// @0B9: ireturn
		// @0BA: iload #7
		// @0BC: iload #4
		// @0BE: iadd
		// @0BF: ireturn
		// @0C0: iload #4
		// @0C2: iconst_m1
		// @0C3: aload #6
		// @0C5: getfield int[] game.C_100306_kn.field_107130_g
		// @0C8: arraylength
		// @0C9: iadd
		// @0CA: iadd
		// @0CB: istore #4
		// @0CD: iinc #5 +1
		// @0D0: iload #8
		// @0D2: ifeq @071
		// @0D5: iconst_m1
		// @0D6: ireturn
		// @0D7: astore #4
		// @0D9: aload #4
		// @0DB: new java.lang.StringBuilder
		// @0DE: dup
		// @0DF: invokespecial java.lang.StringBuilder.<init>()void
		// @0E2: getstatic java.lang.String[] game.C_100205_qf.field_103683_z
		// @0E5: bipush 78 (0x4E)
		// @0E7: aaload
		// @0E8: invokevirtual java.lang.StringBuilder.append(java.lang.String)java.lang.StringBuilder
		// @0EB: iload_1
		// @0EC: invokevirtual java.lang.StringBuilder.append(int)java.lang.StringBuilder
		// @0EF: bipush 44 (0x2C)
		// @0F1: invokevirtual java.lang.StringBuilder.append(char)java.lang.StringBuilder
		// @0F4: iload_2
		// @0F5: invokevirtual java.lang.StringBuilder.append(int)java.lang.StringBuilder
		// @0F8: bipush 44 (0x2C)
		// @0FA: invokevirtual java.lang.StringBuilder.append(char)java.lang.StringBuilder
		// @0FD: iload_3
		// @0FE: invokevirtual java.lang.StringBuilder.append(int)java.lang.StringBuilder
		// @101: bipush 41 (0x29)
		// @103: invokevirtual java.lang.StringBuilder.append(char)java.lang.StringBuilder
		// @106: invokevirtual java.lang.StringBuilder.toString()java.lang.String
		// @109: invokestatic game.C_100181_cf.func_105695_a(java.lang.Throwable, java.lang.String)game.C_100170_cm
		// @10C: athrow
	}
	
	static
	{
		// @000: bipush 79 (0x4F)
		// @002: anewarray java.lang.String
		// @005: dup
		// @006: iconst_0
		// @007: ldc "\u0010jz\tO"
		// @009: invokestatic game.C_100205_qf.func_103669_z(java.lang.String)char[]
		// @00C: invokestatic game.C_100205_qf.func_103667_z(char[])java.lang.String
		// @00F: aastore
		// @010: dup
		// @011: iconst_1
		// @012: ldc "\u0010jz\u0015O"
		// @014: invokestatic game.C_100205_qf.func_103669_z(java.lang.String)char[]
		// @017: invokestatic game.C_100205_qf.func_103667_z(char[])java.lang.String
		// @01A: aastore
		// @01B: dup
		// @01C: iconst_2
		// @01D: ldc "\u0010jz\u0016O"
		// @01F: invokestatic game.C_100205_qf.func_103669_z(java.lang.String)char[]
		// @022: invokestatic game.C_100205_qf.func_103667_z(char[])java.lang.String
		// @025: aastore
		// @026: dup
		// @027: iconst_3
		// @028: ldc "\u001a\"zv\u001a"
		// @02A: invokestatic game.C_100205_qf.func_103669_z(java.lang.String)char[]
		// @02D: invokestatic game.C_100205_qf.func_103667_z(char[])java.lang.String
		// @030: aastore
		// @031: dup
		// @032: iconst_4
		// @033: ldc "\u000fy84"
		// @035: invokestatic game.C_100205_qf.func_103669_z(java.lang.String)char[]
		// @038: invokestatic game.C_100205_qf.func_103667_z(char[])java.lang.String
		// @03B: aastore
		// @03C: dup
		// @03D: iconst_5
		// @03E: ldc "\u0010jz\u0012O"
		// @040: invokestatic game.C_100205_qf.func_103669_z(java.lang.String)char[]
		// @043: invokestatic game.C_100205_qf.func_103667_z(char[])java.lang.String
		// @046: aastore
		// @047: dup
		// @048: bipush 6 (0x06)
		// @04A: ldc "\u0010jz\u0013O"
		// @04C: invokestatic game.C_100205_qf.func_103669_z(java.lang.String)char[]
		// @04F: invokestatic game.C_100205_qf.func_103667_z(char[])java.lang.String
		// @052: aastore
		// @053: dup
		// @054: bipush 7 (0x07)
		// @056: ldc "\u0010jz\u0014O"
		// @058: invokestatic game.C_100205_qf.func_103669_z(java.lang.String)char[]
		// @05B: invokestatic game.C_100205_qf.func_103667_z(char[])java.lang.String
		// @05E: aastore
		// @05F: dup
		// @060: bipush 8 (0x08)
		// @062: ldc "\u0005c#6\u0005\u0014x 7\t>a;-\u0014\u0004c\"=\u0015"
		// @064: invokestatic game.C_100205_qf.func_103669_z(java.lang.String)char[]
		// @067: invokestatic game.C_100205_qf.func_103667_z(char[])java.lang.String
		// @06A: aastore
		// @06B: dup
		// @06C: bipush 9 (0x09)
		// @06E: ldc "\u0006m9=\u0008\u0011x=7\t\u0003y ,\u0008\u000fS97\u0012\u0012i;.\u0002\u0013"
		// @070: invokestatic game.C_100205_qf.func_103669_z(java.lang.String)char[]
		// @073: invokestatic game.C_100205_qf.func_103667_z(char[])java.lang.String
		// @076: aastore
		// @077: dup
		// @078: bipush 10 (0x0A)
		// @07A: ldc "\u0005~5?\u0005\u0000~\u000b5\u0008\u0014\u007f17\u0011\u0004~"
		// @07C: invokestatic game.C_100205_qf.func_103669_z(java.lang.String)char[]
		// @07F: invokestatic game.C_100205_qf.func_103667_z(char[])java.lang.String
		// @082: aastore
		// @083: dup
		// @084: bipush 11 (0x0B)
		// @086: ldc "\u0002d5,\u0001\u000eb "
		// @088: invokestatic game.C_100205_qf.func_103669_z(java.lang.String)char[]
		// @08B: invokestatic game.C_100205_qf.func_103667_z(char[])java.lang.String
		// @08E: aastore
		// @08F: dup
		// @090: bipush 12 (0x0C)
		// @092: ldc "\u0012a54\u000b\u0003y ,\u0008\u000fS97\u0012\u0012i;.\u0002\u0013"
		// @094: invokestatic game.C_100205_qf.func_103669_z(java.lang.String)char[]
		// @097: invokestatic game.C_100205_qf.func_103667_z(char[])java.lang.String
		// @09A: aastore
		// @09B: dup
		// @09C: bipush 13 (0x0D)
		// @09E: ldc "\u0003e3:\u0012\u0015x;68\u000cc!+\u0002\u000ez1*"
		// @0A0: invokestatic game.C_100205_qf.func_103669_z(java.lang.String)char[]
		// @0A3: invokestatic game.C_100205_qf.func_103667_z(char[])java.lang.String
		// @0A6: aastore
		// @0A7: dup
		// @0A8: bipush 14 (0x0E)
		// @0AA: ldc "\u0002d5,\u0005\u0014x 7\t>m7,\u000e\u0017i"
		// @0AC: invokestatic game.C_100205_qf.func_103669_z(java.lang.String)char[]
		// @0AF: invokestatic game.C_100205_qf.func_103667_z(char[])java.lang.String
		// @0B2: aastore
		// @0B3: dup
		// @0B4: bipush 15 (0x0F)
		// @0B6: ldc "\u0012a54\u000b\u0003y ,\u0008\u000f"
		// @0B8: invokestatic game.C_100205_qf.func_103669_z(java.lang.String)char[]
		// @0BB: invokestatic game.C_100205_qf.func_103667_z(char[])java.lang.String
		// @0BE: aastore
		// @0BF: dup
		// @0C0: bipush 16 (0x10)
		// @0C2: ldc "\u0005~5?\u0005\u0000~\u000b<\u000e\u0012m64\u0002\u0005"
		// @0C4: invokestatic game.C_100205_qf.func_103669_z(java.lang.String)char[]
		// @0C7: invokestatic game.C_100205_qf.func_103667_z(char[])java.lang.String
		// @0CA: aastore
		// @0CB: dup
		// @0CC: bipush 17 (0x11)
		// @0CE: ldc "\u0002d5,\u0001\u0008` =\u0015\u0003y ,\u0008\u000f"
		// @0D0: invokestatic game.C_100205_qf.func_103669_z(java.lang.String)char[]
		// @0D3: invokestatic game.C_100205_qf.func_103667_z(char[])java.lang.String
		// @0D6: aastore
		// @0D7: dup
		// @0D8: bipush 18 (0x12)
		// @0DA: ldc "\u0003e3:\u0012\u0015x;68\u000cc!+\u0002\ti8<"
		// @0DC: invokestatic game.C_100205_qf.func_103669_z(java.lang.String)char[]
		// @0DF: invokestatic game.C_100205_qf.func_103667_z(char[])java.lang.String
		// @0E2: aastore
		// @0E3: dup
		// @0E4: bipush 19 (0x13)
		// @0E6: ldc "\u0015m6\u0007\n\u000ey'=\u0008\u0017i&"
		// @0E8: invokestatic game.C_100205_qf.func_103669_z(java.lang.String)char[]
		// @0EB: invokestatic game.C_100205_qf.func_103667_z(char[])java.lang.String
		// @0EE: aastore
		// @0EF: dup
		// @0F0: bipush 20 (0x14)
		// @0F2: ldc "\u0006m9=\u0008\u0011x=7\t\u0003y ,\u0008\u000fS5;\u0013\u0008z1"
		// @0F4: invokestatic game.C_100205_qf.func_103669_z(java.lang.String)char[]
		// @0F7: invokestatic game.C_100205_qf.func_103667_z(char[])java.lang.String
		// @0FA: aastore
		// @0FB: dup
		// @0FC: bipush 21 (0x15)
		// @0FE: ldc "\u0005c#6\u0005\u0014x 7\t>h=+\u0006\u0003`1<"
		// @100: invokestatic game.C_100205_qf.func_103669_z(java.lang.String)char[]
		// @103: invokestatic game.C_100205_qf.func_103667_z(char[])java.lang.String
		// @106: aastore
		// @107: dup
		// @108: bipush 22 (0x16)
		// @10A: ldc "\u0012a54\u000b\u0003y ,\u0008\u000fS01\u0014\u0000n8=\u0003"
		// @10C: invokestatic game.C_100205_qf.func_103669_z(java.lang.String)char[]
		// @10F: invokestatic game.C_100205_qf.func_103667_z(char[])java.lang.String
		// @112: aastore
		// @113: dup
		// @114: bipush 23 (0x17)
		// @116: ldc "\ti5<\u000e\u000fk"
		// @118: invokestatic game.C_100205_qf.func_103669_z(java.lang.String)char[]
		// @11B: invokestatic game.C_100205_qf.func_103667_z(char[])java.lang.String
		// @11E: aastore
		// @11F: dup
		// @120: bipush 24 (0x18)
		// @122: ldc "\u0005~5?\u0005\u0000~"
		// @124: invokestatic game.C_100205_qf.func_103669_z(java.lang.String)char[]
		// @127: invokestatic game.C_100205_qf.func_103667_z(char[])java.lang.String
		// @12A: aastore
		// @12B: dup
		// @12C: bipush 25 (0x19)
		// @12E: ldc "\u0002d5,\u0001\u0008` =\u0015\u0003y ,\u0008\u000fS97\u0012\u0012i;.\u0002\u0013"
		// @130: invokestatic game.C_100205_qf.func_103669_z(java.lang.String)char[]
		// @133: invokestatic game.C_100205_qf.func_103667_z(char[])java.lang.String
		// @136: aastore
		// @137: dup
		// @138: bipush 26 (0x1A)
		// @13A: ldc "\u0013i0:\u0012\u0015x;68\u000cc!+\u0002\ti8<"
		// @13C: invokestatic game.C_100205_qf.func_103669_z(java.lang.String)char[]
		// @13F: invokestatic game.C_100205_qf.func_103667_z(char[])java.lang.String
		// @142: aastore
		// @143: dup
		// @144: bipush 27 (0x1B)
		// @146: ldc "\u0003y ,\u0008\u000f"
		// @148: invokestatic game.C_100205_qf.func_103669_z(java.lang.String)char[]
		// @14B: invokestatic game.C_100205_qf.func_103667_z(char[])java.lang.String
		// @14E: aastore
		// @14F: dup
		// @150: bipush 28 (0x1C)
		// @152: ldc "\u0002d1;\u000c\u0003c,"
		// @154: invokestatic game.C_100205_qf.func_103669_z(java.lang.String)char[]
		// @157: invokestatic game.C_100205_qf.func_103667_z(char[])java.lang.String
		// @15A: aastore
		// @15B: dup
		// @15C: bipush 29 (0x1D)
		// @15E: ldc "\u0002~;/\t\u0012"
		// @160: invokestatic game.C_100205_qf.func_103669_z(java.lang.String)char[]
		// @163: invokestatic game.C_100205_qf.func_103667_z(char[])java.lang.String
		// @166: aastore
		// @167: dup
		// @168: bipush 30 (0x1E)
		// @16A: ldc "\u0005~5?\u0005\u0000~\u000b5\u0008\u0014\u007f10\u0002\rh"
		// @16C: invokestatic game.C_100205_qf.func_103669_z(java.lang.String)char[]
		// @16F: invokestatic game.C_100205_qf.func_103667_z(char[])java.lang.String
		// @172: aastore
		// @173: dup
		// @174: bipush 31 (0x1F)
		// @176: ldc "\u0011c$-\u0017>a;-\u0014\u0004c\"=\u0015"
		// @178: invokestatic game.C_100205_qf.func_103669_z(java.lang.String)char[]
		// @17B: invokestatic game.C_100205_qf.func_103667_z(char[])java.lang.String
		// @17E: aastore
		// @17F: dup
		// @180: bipush 32 (0x20)
		// @182: ldc "\u0015m6\u0007\u000e\u000fm7,\u000e\u0017i"
		// @184: invokestatic game.C_100205_qf.func_103669_z(java.lang.String)char[]
		// @187: invokestatic game.C_100205_qf.func_103667_z(char[])java.lang.String
		// @18A: aastore
		// @18B: dup
		// @18C: bipush 33 (0x21)
		// @18E: ldc "\u0006~1=\t\u0003y ,\u0008\u000fS97\u0012\u0012i;.\u0002\u0013"
		// @190: invokestatic game.C_100205_qf.func_103669_z(java.lang.String)char[]
		// @193: invokestatic game.C_100205_qf.func_103667_z(char[])java.lang.String
		// @196: aastore
		// @197: dup
		// @198: bipush 34 (0x22)
		// @19A: ldc "\u0012`=<\u0002\u0013i31\u0008\u000fS97\u0012\u0012i<=\u000b\u0005"
		// @19C: invokestatic game.C_100205_qf.func_103669_z(java.lang.String)char[]
		// @19F: invokestatic game.C_100205_qf.func_103667_z(char[])java.lang.String
		// @1A2: aastore
		// @1A3: dup
		// @1A4: bipush 35 (0x23)
		// @1A6: ldc "\u0006~1=\t\u0003y ,\u0008\u000f"
		// @1A8: invokestatic game.C_100205_qf.func_103669_z(java.lang.String)char[]
		// @1AB: invokestatic game.C_100205_qf.func_103667_z(char[])java.lang.String
		// @1AE: aastore
		// @1AF: dup
		// @1B0: bipush 36 (0x24)
		// @1B2: ldc "\u0014|6-\u0013\u0015c:"
		// @1B4: invokestatic game.C_100205_qf.func_103669_z(java.lang.String)char[]
		// @1B7: invokestatic game.C_100205_qf.func_103667_z(char[])java.lang.String
		// @1BA: aastore
		// @1BB: dup
		// @1BC: bipush 37 (0x25)
		// @1BE: ldc "\u0003e3:\u0012\u0015x;6"
		// @1C0: invokestatic game.C_100205_qf.func_103669_z(java.lang.String)char[]
		// @1C3: invokestatic game.C_100205_qf.func_103667_z(char[])java.lang.String
		// @1C6: aastore
		// @1C7: dup
		// @1C8: bipush 38 (0x26)
		// @1CA: ldc "\rc6:\u001e"
		// @1CC: invokestatic game.C_100205_qf.func_103669_z(java.lang.String)char[]
		// @1CF: invokestatic game.C_100205_qf.func_103667_z(char[])java.lang.String
		// @1D2: aastore
		// @1D3: dup
		// @1D4: bipush 39 (0x27)
		// @1D6: ldc "\u0003m73\u0005\u0014x 7\t>a;-\u0014\u0004c\"=\u0015"
		// @1D8: invokestatic game.C_100205_qf.func_103669_z(java.lang.String)char[]
		// @1DB: invokestatic game.C_100205_qf.func_103667_z(char[])java.lang.String
		// @1DE: aastore
		// @1DF: dup
		// @1E0: bipush 40 (0x28)
		// @1E2: ldc "\u0002d5,\u0005\u0014x 7\t>a;-\u0014\u0004c\"=\u0015"
		// @1E4: invokestatic game.C_100205_qf.func_103669_z(java.lang.String)char[]
		// @1E7: invokestatic game.C_100205_qf.func_103667_z(char[])java.lang.String
		// @1EA: aastore
		// @1EB: dup
		// @1EC: bipush 41 (0x29)
		// @1EE: ldc "\u0003m73\u0005\u0014x 7\t>h=+\u0006\u0003`1<"
		// @1F0: invokestatic game.C_100205_qf.func_103669_z(java.lang.String)char[]
		// @1F3: invokestatic game.C_100205_qf.func_103667_z(char[])java.lang.String
		// @1F6: aastore
		// @1F7: dup
		// @1F8: bipush 42 (0x2A)
		// @1FA: ldc "\u0006m9=\u0008\u0011x=7\t\u0003y ,\u0008\u000f"
		// @1FC: invokestatic game.C_100205_qf.func_103669_z(java.lang.String)char[]
		// @1FF: invokestatic game.C_100205_qf.func_103667_z(char[])java.lang.String
		// @202: aastore
		// @203: dup
		// @204: bipush 43 (0x2B)
		// @206: ldc "\u0003e3:\u0012\u0015x;68\u0005e'9\u0005\ri0"
		// @208: invokestatic game.C_100205_qf.func_103669_z(java.lang.String)char[]
		// @20B: invokestatic game.C_100205_qf.func_103667_z(char[])java.lang.String
		// @20E: aastore
		// @20F: dup
		// @210: bipush 44 (0x2C)
		// @212: ldc "\u0006~1=\t\u0003y ,\u0008\u000fS97\u0012\u0012i<=\u000b\u0005"
		// @214: invokestatic game.C_100205_qf.func_103669_z(java.lang.String)char[]
		// @217: invokestatic game.C_100205_qf.func_103667_z(char[])java.lang.String
		// @21A: aastore
		// @21B: dup
		// @21C: bipush 45 (0x2D)
		// @21E: ldc "\u000ci01\u0012\u000cn!,\u0013\u000eb\u000b5\u0008\u0014\u007f17\u0011\u0004~"
		// @220: invokestatic game.C_100205_qf.func_103669_z(java.lang.String)char[]
		// @223: invokestatic game.C_100205_qf.func_103667_z(char[])java.lang.String
		// @226: aastore
		// @227: dup
		// @228: bipush 46 (0x2E)
		// @22A: ldc "\u0013i0:\u0012\u0015x;6"
		// @22C: invokestatic game.C_100205_qf.func_103669_z(java.lang.String)char[]
		// @22F: invokestatic game.C_100205_qf.func_103667_z(char[])java.lang.String
		// @232: aastore
		// @233: dup
		// @234: bipush 47 (0x2F)
		// @236: ldc "\u0005c#6\u0005\u0014x 7\t"
		// @238: invokestatic game.C_100205_qf.func_103669_z(java.lang.String)char[]
		// @23B: invokestatic game.C_100205_qf.func_103667_z(char[])java.lang.String
		// @23E: aastore
		// @23F: dup
		// @240: bipush 48 (0x30)
		// @242: ldc "\u0006m9=\u0008\u0011x=7\t\u0003y ,\u0008\u000fS01\u0014\u0000n8=\u0003"
		// @244: invokestatic game.C_100205_qf.func_103669_z(java.lang.String)char[]
		// @247: invokestatic game.C_100205_qf.func_103667_z(char[])java.lang.String
		// @24A: aastore
		// @24B: dup
		// @24C: bipush 49 (0x31)
		// @24E: ldc "\u0003m73\u0005\u0014x 7\t"
		// @250: invokestatic game.C_100205_qf.func_103669_z(java.lang.String)char[]
		// @253: invokestatic game.C_100205_qf.func_103667_z(char[])java.lang.String
		// @256: aastore
		// @257: dup
		// @258: bipush 50 (0x32)
		// @25A: ldc "\u0002`;+\u0002\u0003y ,\u0008\u000f"
		// @25C: invokestatic game.C_100205_qf.func_103669_z(java.lang.String)char[]
		// @25F: invokestatic game.C_100205_qf.func_103667_z(char[])java.lang.String
		// @262: aastore
		// @263: dup
		// @264: bipush 51 (0x33)
		// @266: ldc "\u0012`=<\u0002\u0013i31\u0008\u000fS01\u0014\u0000n8=\u0003"
		// @268: invokestatic game.C_100205_qf.func_103669_z(java.lang.String)char[]
		// @26B: invokestatic game.C_100205_qf.func_103667_z(char[])java.lang.String
		// @26E: aastore
		// @26F: dup
		// @270: bipush 52 (0x34)
		// @272: ldc "\u0003y ,\u0008\u000fS97\u0012\u0012i;.\u0002\u0013"
		// @274: invokestatic game.C_100205_qf.func_103669_z(java.lang.String)char[]
		// @277: invokestatic game.C_100205_qf.func_103667_z(char[])java.lang.String
		// @27A: aastore
		// @27B: dup
		// @27C: bipush 53 (0x35)
		// @27E: ldc "\u0011c$-\u0017"
		// @280: invokestatic game.C_100205_qf.func_103669_z(java.lang.String)char[]
		// @283: invokestatic game.C_100205_qf.func_103667_z(char[])java.lang.String
		// @286: aastore
		// @287: dup
		// @288: bipush 54 (0x36)
		// @28A: ldc "\u0015m6\u0007\u0006\u0002x=.\u0002"
		// @28C: invokestatic game.C_100205_qf.func_103669_z(java.lang.String)char[]
		// @28F: invokestatic game.C_100205_qf.func_103667_z(char[])java.lang.String
		// @292: aastore
		// @293: dup
		// @294: bipush 55 (0x37)
		// @296: ldc "\u000ci01\u0012\u000cn!,\u0013\u000eb\u000b5\u0008\u0014\u007f10\u0002\rh"
		// @298: invokestatic game.C_100205_qf.func_103669_z(java.lang.String)char[]
		// @29B: invokestatic game.C_100205_qf.func_103667_z(char[])java.lang.String
		// @29E: aastore
		// @29F: dup
		// @2A0: bipush 56 (0x38)
		// @2A2: ldc "\u0003y ,\u0008\u000fS5;\u0013\u0008z1"
		// @2A4: invokestatic game.C_100205_qf.func_103669_z(java.lang.String)char[]
		// @2A7: invokestatic game.C_100205_qf.func_103667_z(char[])java.lang.String
		// @2AA: aastore
		// @2AB: dup
		// @2AC: bipush 57 (0x39)
		// @2AE: ldc "\u0002d5,\u0001\u0008` =\u0015\u0003y ,\u0008\u000fS5;\u0013\u0008z1"
		// @2B0: invokestatic game.C_100205_qf.func_103669_z(java.lang.String)char[]
		// @2B3: invokestatic game.C_100205_qf.func_103667_z(char[])java.lang.String
		// @2B6: aastore
		// @2B7: dup
		// @2B8: bipush 58 (0x3A)
		// @2BA: ldc "\u0003m73\u0005\u0014x 7\t>a;-\u0014\u0004d14\u0003"
		// @2BC: invokestatic game.C_100205_qf.func_103669_z(java.lang.String)char[]
		// @2BF: invokestatic game.C_100205_qf.func_103667_z(char[])java.lang.String
		// @2C2: aastore
		// @2C3: dup
		// @2C4: bipush 59 (0x3B)
		// @2C6: ldc "\u0012a54\u000b\u0003y ,\u0008\u000fS5;\u0013\u0008z1"
		// @2C8: invokestatic game.C_100205_qf.func_103669_z(java.lang.String)char[]
		// @2CB: invokestatic game.C_100205_qf.func_103667_z(char[])java.lang.String
		// @2CE: aastore
		// @2CF: dup
		// @2D0: bipush 60 (0x3C)
		// @2D2: ldc "\u0012`=<\u0002\u0013i31\u0008\u000fS97\u0012\u0012i;.\u0002\u0013"
		// @2D4: invokestatic game.C_100205_qf.func_103669_z(java.lang.String)char[]
		// @2D7: invokestatic game.C_100205_qf.func_103667_z(char[])java.lang.String
		// @2DA: aastore
		// @2DB: dup
		// @2DC: bipush 61 (0x3D)
		// @2DE: ldc "\u0002`;+\u0002\u0003y ,\u0008\u000fS97\u0012\u0012i;.\u0002\u0013"
		// @2E0: invokestatic game.C_100205_qf.func_103669_z(java.lang.String)char[]
		// @2E3: invokestatic game.C_100205_qf.func_103667_z(char[])java.lang.String
		// @2E6: aastore
		// @2E7: dup
		// @2E8: bipush 62 (0x3E)
		// @2EA: ldc "\rm&?\u0002\u0007c:,"
		// @2EC: invokestatic game.C_100205_qf.func_103669_z(java.lang.String)char[]
		// @2EF: invokestatic game.C_100205_qf.func_103667_z(char[])java.lang.String
		// @2F2: aastore
		// @2F3: dup
		// @2F4: bipush 63 (0x3F)
		// @2F6: ldc "\u0003y ,\u0008\u000fS01\u0014\u0000n8=\u0003"
		// @2F8: invokestatic game.C_100205_qf.func_103669_z(java.lang.String)char[]
		// @2FB: invokestatic game.C_100205_qf.func_103667_z(char[])java.lang.String
		// @2FE: aastore
		// @2FF: dup
		// @300: bipush 64 (0x40)
		// @302: ldc "\u0010jz\nO"
		// @304: invokestatic game.C_100205_qf.func_103669_z(java.lang.String)char[]
		// @307: invokestatic game.C_100205_qf.func_103667_z(char[])java.lang.String
		// @30A: aastore
		// @30B: dup
		// @30C: bipush 65 (0x41)
		// @30E: ldc "\u0014|6-\u0013\u0015c:\u0007\u0003\u0008\u007f5:\u000b\u0004h"
		// @310: invokestatic game.C_100205_qf.func_103669_z(java.lang.String)char[]
		// @313: invokestatic game.C_100205_qf.func_103667_z(char[])java.lang.String
		// @316: aastore
		// @317: dup
		// @318: bipush 66 (0x42)
		// @31A: ldc "\u0003y ,\u0008\u000fS97\u0012\u0012i<=\u000b\u0005"
		// @31C: invokestatic game.C_100205_qf.func_103669_z(java.lang.String)char[]
		// @31F: invokestatic game.C_100205_qf.func_103667_z(char[])java.lang.String
		// @322: aastore
		// @323: dup
		// @324: bipush 67 (0x43)
		// @326: ldc "\u0013i0:\u0012\u0015x;68\u000cc!+\u0002\u000ez1*"
		// @328: invokestatic game.C_100205_qf.func_103669_z(java.lang.String)char[]
		// @32B: invokestatic game.C_100205_qf.func_103667_z(char[])java.lang.String
		// @32E: aastore
		// @32F: dup
		// @330: bipush 68 (0x44)
		// @332: ldc "\u0014|6-\u0013\u0015c:\u0007\n\u000ey'=\u0008\u0017i&"
		// @334: invokestatic game.C_100205_qf.func_103669_z(java.lang.String)char[]
		// @337: invokestatic game.C_100205_qf.func_103667_z(char[])java.lang.String
		// @33A: aastore
		// @33B: dup
		// @33C: bipush 69 (0x45)
		// @33E: ldc "\u000ci01\u0012\u000cn!,\u0013\u000eb"
		// @340: invokestatic game.C_100205_qf.func_103669_z(java.lang.String)char[]
		// @343: invokestatic game.C_100205_qf.func_103667_z(char[])java.lang.String
		// @346: aastore
		// @347: dup
		// @348: bipush 70 (0x46)
		// @34A: ldc "\u0005c#6\u0005\u0014x 7\t>a;-\u0014\u0004d14\u0003"
		// @34C: invokestatic game.C_100205_qf.func_103669_z(java.lang.String)char[]
		// @34F: invokestatic game.C_100205_qf.func_103667_z(char[])java.lang.String
		// @352: aastore
		// @353: dup
		// @354: bipush 71 (0x47)
		// @356: ldc "\u0014|6-\u0013\u0015c:\u0007\n\u000ey'=\u000f\u0004`0"
		// @358: invokestatic game.C_100205_qf.func_103669_z(java.lang.String)char[]
		// @35B: invokestatic game.C_100205_qf.func_103667_z(char[])java.lang.String
		// @35E: aastore
		// @35F: dup
		// @360: bipush 72 (0x48)
		// @362: ldc "\u0002d5,\u0005\u0014x 7\t"
		// @364: invokestatic game.C_100205_qf.func_103669_z(java.lang.String)char[]
		// @367: invokestatic game.C_100205_qf.func_103667_z(char[])java.lang.String
		// @36A: aastore
		// @36B: dup
		// @36C: bipush 73 (0x49)
		// @36E: ldc "\u0006i:=\u0015\u0000`27\t\u0015"
		// @370: invokestatic game.C_100205_qf.func_103669_z(java.lang.String)char[]
		// @373: invokestatic game.C_100205_qf.func_103667_z(char[])java.lang.String
		// @376: aastore
		// @377: dup
		// @378: bipush 74 (0x4A)
		// @37A: ldc "\u0012`=<\u0002\u0013i31\u0008\u000f"
		// @37C: invokestatic game.C_100205_qf.func_103669_z(java.lang.String)char[]
		// @37F: invokestatic game.C_100205_qf.func_103667_z(char[])java.lang.String
		// @382: aastore
		// @383: dup
		// @384: bipush 75 (0x4B)
		// @386: ldc "\u0010jz\u000bO"
		// @388: invokestatic game.C_100205_qf.func_103669_z(java.lang.String)char[]
		// @38B: invokestatic game.C_100205_qf.func_103667_z(char[])java.lang.String
		// @38E: aastore
		// @38F: dup
		// @390: bipush 76 (0x4C)
		// @392: ldc "\u0010jz\u0008O"
		// @394: invokestatic game.C_100205_qf.func_103669_z(java.lang.String)char[]
		// @397: invokestatic game.C_100205_qf.func_103667_z(char[])java.lang.String
		// @39A: aastore
		// @39B: dup
		// @39C: bipush 77 (0x4D)
		// @39E: ldc "\u0010jz\u000cO"
		// @3A0: invokestatic game.C_100205_qf.func_103669_z(java.lang.String)char[]
		// @3A3: invokestatic game.C_100205_qf.func_103667_z(char[])java.lang.String
		// @3A6: aastore
		// @3A7: dup
		// @3A8: bipush 78 (0x4E)
		// @3AA: ldc "\u0010jz\u0017O"
		// @3AC: invokestatic game.C_100205_qf.func_103669_z(java.lang.String)char[]
		// @3AF: invokestatic game.C_100205_qf.func_103667_z(char[])java.lang.String
		// @3B2: aastore
		// @3B3: putstatic java.lang.String[] game.C_100205_qf.field_103683_z
		// @3B6: new game.C_100268_mk
		// @3B9: dup
		// @3BA: invokespecial game.C_100268_mk.<init>()void
		// @3BD: putstatic game.C_100268_mk game.C_100205_qf.field_103679_e
		// @3C0: iconst_0
		// @3C1: putstatic int game.C_100205_qf.field_103678_d
		// @3C4: new game.C_100202_qi
		// @3C7: dup
		// @3C8: invokespecial game.C_100202_qi.<init>()void
		// @3CB: putstatic game.C_100202_qi game.C_100205_qf.field_103676_f
		// @3CE: aconst_null
		// @3CF: putstatic game.C_100202_qi game.C_100205_qf.field_103680_b
		// @3D2: ldc "\"cy7\u0017Ad=?\u000f\u0012o;*\u0002\u0012"
		// @3D4: invokestatic game.C_100205_qf.func_103669_z(java.lang.String)char[]
		// @3D7: invokestatic game.C_100205_qf.func_103667_z(char[])java.lang.String
		// @3DA: putstatic java.lang.String game.C_100205_qf.field_103682_a
		// @3DD: return
	}
	
	private static char[] func_103669_z(String arg0)
	{
		// @00: aload_0
		// @01: invokevirtual java.lang.String.toCharArray()char[]
		// @04: dup
		// @05: arraylength
		// @06: iconst_2
		// @07: if_icmpge @13
		// @0A: dup
		// @0B: iconst_0
		// @0C: dup2
		// @0D: caload
		// @0E: bipush 103 (0x67)
		// @10: ixor
		// @11: i2c
		// @12: castore
		// @13: areturn
	}
	
	private static String func_103667_z(char[] arg0)
	{
		// @00: aload_0
		// @01: dup
		// @02: arraylength
		// @03: swap
		// @04: iconst_0
		// @05: istore_1
		// @06: goto @4C
		// @09: dup
		// @0A: iload_1
		// @0B: dup2
		// @0C: caload
		// @0D: iload_1
		// @0E: iconst_5
		// @0F: irem
		// @10: tableswitch def: @44, for 0: @30, for 1: @35, for 2: @3A, for 3: @3F
		// @30: bipush 97 (0x61)
		// @32: goto @46
		// @35: bipush 12 (0x0C)
		// @37: goto @46
		// @3A: bipush 84 (0x54)
		// @3C: goto @46
		// @3F: bipush 88 (0x58)
		// @41: goto @46
		// @44: bipush 103 (0x67)
		// @46: ixor
		// @47: i2c
		// @48: castore
		// @49: iinc #1 +1
		// @4C: swap
		// @4D: dup_x1
		// @4E: iload_1
		// @4F: if_icmpgt @09
		// @52: new java.lang.String
		// @55: dup_x1
		// @56: swap
		// @57: invokespecial java.lang.String.<init>(char[])void
		// @5A: invokevirtual java.lang.String.intern()java.lang.String
		// @5D: areturn
	}
}
