package game;

final class C_100111_el
{
	static C_100302_ka field_104868_i;
	static C_100047_vh field_104859_g;
	static String field_104863_c;
	static C_100187_rk field_104864_a;
	static char[] field_104865_j;
	static String field_104858_f;
	static String field_104861_e;
	static C_100302_ka field_104860_d;
	static C_100037_wb[] field_104867_h;
	static int[] field_104862_b;
	private static final String[] field_104866_z;
	
	static final C_100096_un func_104855_a(String arg0, boolean arg1, int arg2)
	{
		// @00: new game.C_100096_un
		// @03: dup
		// @04: iload_1
		// @05: invokespecial game.C_100096_un.<init>(boolean)void
		// @08: astore_3
		// @09: aload_3
		// @0A: aload_0
		// @0B: putfield java.lang.String game.C_100096_un.field_104567_a
		// @0E: aload_3
		// @0F: iload_2
		// @10: putfield int game.C_100096_un.field_104564_e
		// @13: aload_3
		// @14: areturn
		// @15: astore_3
		// @16: aload_3
		// @17: new java.lang.StringBuilder
		// @1A: dup
		// @1B: invokespecial java.lang.StringBuilder.<init>()void
		// @1E: getstatic java.lang.String[] game.C_100111_el.field_104866_z
		// @21: iconst_3
		// @22: aaload
		// @23: invokevirtual java.lang.StringBuilder.append(java.lang.String)java.lang.StringBuilder
		// @26: aload_0
		// @27: ifnull @33
		// @2A: getstatic java.lang.String[] game.C_100111_el.field_104866_z
		// @2D: iconst_2
		// @2E: aaload
		// @2F: goto @38
		// @32: athrow
		// @33: getstatic java.lang.String[] game.C_100111_el.field_104866_z
		// @36: iconst_1
		// @37: aaload
		// @38: invokevirtual java.lang.StringBuilder.append(java.lang.String)java.lang.StringBuilder
		// @3B: bipush 44 (0x2C)
		// @3D: invokevirtual java.lang.StringBuilder.append(char)java.lang.StringBuilder
		// @40: iload_1
		// @41: invokevirtual java.lang.StringBuilder.append(boolean)java.lang.StringBuilder
		// @44: bipush 44 (0x2C)
		// @46: invokevirtual java.lang.StringBuilder.append(char)java.lang.StringBuilder
		// @49: iload_2
		// @4A: invokevirtual java.lang.StringBuilder.append(int)java.lang.StringBuilder
		// @4D: bipush 41 (0x29)
		// @4F: invokevirtual java.lang.StringBuilder.append(char)java.lang.StringBuilder
		// @52: invokevirtual java.lang.StringBuilder.toString()java.lang.String
		// @55: invokestatic game.C_100181_cf.func_105695_a(java.lang.Throwable, java.lang.String)game.C_100170_cm
		// @58: athrow
	}
	
	static final String func_104851_a(boolean arg0)
	{
		// @00: getstatic game.C_100068_vc game.C_100222_aa.field_106086_a
		// @03: getstatic game.C_100068_vc game.C_100148_bh.field_101797_B
		// @06: if_acmpne @0D
		// @09: getstatic java.lang.String game.C_100095_fe.field_103384_P
		// @0C: areturn
		// @0D: getstatic game.C_100068_vc game.C_100191_rg.field_100845_o
		// @10: getstatic game.C_100068_vc game.C_100148_bh.field_101797_B
		// @13: if_acmpne @1A
		// @16: getstatic java.lang.String game.C_100061_dh.field_101989_ic
		// @19: areturn
		// @1A: iload_0
		// @1B: ifeq @29
		// @1E: aconst_null
		// @1F: checkcast game.C_100037_wb[]
		// @22: putstatic game.C_100037_wb[] game.C_100111_el.field_104867_h
		// @25: goto @29
		// @28: athrow
		// @29: getstatic game.C_100321_hi game.C_100106_ef.field_104753_e
		// @2C: bipush -2 (0xFE)
		// @2E: invokevirtual game.C_100321_hi.func_107211_b(int)boolean
		// @31: ifne @38
		// @34: getstatic java.lang.String game.C_100061_dh.field_101989_ic
		// @37: areturn
		// @38: getstatic java.lang.String game.C_100322_hn.field_107239_c
		// @3B: areturn
		// @3C: astore_1
		// @3D: aload_1
		// @3E: new java.lang.StringBuilder
		// @41: dup
		// @42: invokespecial java.lang.StringBuilder.<init>()void
		// @45: getstatic java.lang.String[] game.C_100111_el.field_104866_z
		// @48: bipush 7 (0x07)
		// @4A: aaload
		// @4B: invokevirtual java.lang.StringBuilder.append(java.lang.String)java.lang.StringBuilder
		// @4E: iload_0
		// @4F: invokevirtual java.lang.StringBuilder.append(boolean)java.lang.StringBuilder
		// @52: bipush 41 (0x29)
		// @54: invokevirtual java.lang.StringBuilder.append(char)java.lang.StringBuilder
		// @57: invokevirtual java.lang.StringBuilder.toString()java.lang.String
		// @5A: invokestatic game.C_100181_cf.func_105695_a(java.lang.Throwable, java.lang.String)game.C_100170_cm
		// @5D: athrow
	}
	
	public static void func_104852_a(int arg0)
	{
		// @00: aconst_null
		// @01: putstatic int[] game.C_100111_el.field_104862_b
		// @04: aconst_null
		// @05: putstatic char[] game.C_100111_el.field_104865_j
		// @08: aconst_null
		// @09: putstatic java.lang.String game.C_100111_el.field_104861_e
		// @0C: aconst_null
		// @0D: putstatic game.C_100302_ka game.C_100111_el.field_104860_d
		// @10: aconst_null
		// @11: putstatic java.lang.String game.C_100111_el.field_104858_f
		// @14: aconst_null
		// @15: putstatic game.C_100302_ka game.C_100111_el.field_104868_i
		// @18: iload_0
		// @19: bipush 95 (0x5F)
		// @1B: if_icmpgt @29
		// @1E: aconst_null
		// @1F: checkcast game.C_100037_wb[]
		// @22: putstatic game.C_100037_wb[] game.C_100111_el.field_104867_h
		// @25: goto @29
		// @28: athrow
		// @29: aconst_null
		// @2A: putstatic java.lang.String game.C_100111_el.field_104863_c
		// @2D: aconst_null
		// @2E: putstatic game.C_100187_rk game.C_100111_el.field_104864_a
		// @31: aconst_null
		// @32: putstatic game.C_100047_vh game.C_100111_el.field_104859_g
		// @35: aconst_null
		// @36: putstatic game.C_100037_wb[] game.C_100111_el.field_104867_h
		// @39: goto @5E
		// @3C: astore_1
		// @3D: aload_1
		// @3E: new java.lang.StringBuilder
		// @41: dup
		// @42: invokespecial java.lang.StringBuilder.<init>()void
		// @45: getstatic java.lang.String[] game.C_100111_el.field_104866_z
		// @48: bipush 6 (0x06)
		// @4A: aaload
		// @4B: invokevirtual java.lang.StringBuilder.append(java.lang.String)java.lang.StringBuilder
		// @4E: iload_0
		// @4F: invokevirtual java.lang.StringBuilder.append(int)java.lang.StringBuilder
		// @52: bipush 41 (0x29)
		// @54: invokevirtual java.lang.StringBuilder.append(char)java.lang.StringBuilder
		// @57: invokevirtual java.lang.StringBuilder.toString()java.lang.String
		// @5A: invokestatic game.C_100181_cf.func_105695_a(java.lang.Throwable, java.lang.String)game.C_100170_cm
		// @5D: athrow
		// @5E: return
	}
	
	static final boolean func_104857_a(String arg0, boolean arg1, int arg2, C_100053_vn arg3, String arg4, int arg5, String arg6)
	{
		// @000: getstatic game.C_100068_vc game.C_100222_aa.field_106086_a
		// @003: getstatic game.C_100068_vc game.C_100220_ac.field_106056_e
		// @006: if_acmpne @00D
		// @009: goto @00F
		// @00C: athrow
		// @00D: iconst_0
		// @00E: ireturn
		// @00F: iload_2
		// @010: sipush 250 (0x00FA)
		// @013: if_icmpeq @018
		// @016: iconst_1
		// @017: ireturn
		// @018: new game.C_100342_jg
		// @01B: dup
		// @01C: getstatic game.C_100029_gn game.C_100085_a.field_102576_K
		// @01F: aload_3
		// @020: invokespecial game.C_100342_jg.<init>(game.C_100029_gn, game.C_100053_vn)void
		// @023: astore #7
		// @025: getstatic game.C_100029_gn game.C_100085_a.field_102576_K
		// @028: aload #7
		// @02A: sipush 2839 (0x0B17)
		// @02D: invokevirtual game.C_100029_gn.func_103359_a(game.C_100336_im, int)void
		// @030: bipush -79 (0xB1)
		// @032: invokestatic game.C_100009_fg.func_103647_b(byte)boolean
		// @035: ifne @063
		// @038: aload_0
		// @039: putstatic java.lang.String game.C_100095_fe.field_103384_P
		// @03C: getstatic game.C_100068_vc game.C_100148_bh.field_101797_B
		// @03F: putstatic game.C_100068_vc game.C_100222_aa.field_106086_a
		// @042: aconst_null
		// @043: putstatic game.C_100096_un game.C_100236_on.field_100900_k
		// @046: aload #6
		// @048: putstatic java.lang.String game.C_100062_dk.field_104282_e
		// @04B: aload #4
		// @04D: putstatic java.lang.String game.C_100257_ln.field_106485_a
		// @050: iload_1
		// @051: putstatic boolean game.C_100247_pa.field_106416_c
		// @054: iload #5
		// @056: putstatic int game.C_100089_fa.field_103728_c
		// @059: getstatic int game.SteelSentinels.field_105275_O
		// @05C: ifeq @06E
		// @05F: goto @063
		// @062: athrow
		// @063: aload #7
		// @065: bipush 45 (0x2D)
		// @067: invokevirtual game.C_100342_jg.func_102718_i(byte)void
		// @06A: goto @06E
		// @06D: athrow
		// @06E: iconst_1
		// @06F: ireturn
		// @070: astore #7
		// @072: aload #7
		// @074: new java.lang.StringBuilder
		// @077: dup
		// @078: invokespecial java.lang.StringBuilder.<init>()void
		// @07B: getstatic java.lang.String[] game.C_100111_el.field_104866_z
		// @07E: iconst_4
		// @07F: aaload
		// @080: invokevirtual java.lang.StringBuilder.append(java.lang.String)java.lang.StringBuilder
		// @083: aload_0
		// @084: ifnull @090
		// @087: getstatic java.lang.String[] game.C_100111_el.field_104866_z
		// @08A: iconst_2
		// @08B: aaload
		// @08C: goto @095
		// @08F: athrow
		// @090: getstatic java.lang.String[] game.C_100111_el.field_104866_z
		// @093: iconst_1
		// @094: aaload
		// @095: invokevirtual java.lang.StringBuilder.append(java.lang.String)java.lang.StringBuilder
		// @098: bipush 44 (0x2C)
		// @09A: invokevirtual java.lang.StringBuilder.append(char)java.lang.StringBuilder
		// @09D: iload_1
		// @09E: invokevirtual java.lang.StringBuilder.append(boolean)java.lang.StringBuilder
		// @0A1: bipush 44 (0x2C)
		// @0A3: invokevirtual java.lang.StringBuilder.append(char)java.lang.StringBuilder
		// @0A6: iload_2
		// @0A7: invokevirtual java.lang.StringBuilder.append(int)java.lang.StringBuilder
		// @0AA: bipush 44 (0x2C)
		// @0AC: invokevirtual java.lang.StringBuilder.append(char)java.lang.StringBuilder
		// @0AF: aload_3
		// @0B0: ifnull @0BC
		// @0B3: getstatic java.lang.String[] game.C_100111_el.field_104866_z
		// @0B6: iconst_2
		// @0B7: aaload
		// @0B8: goto @0C1
		// @0BB: athrow
		// @0BC: getstatic java.lang.String[] game.C_100111_el.field_104866_z
		// @0BF: iconst_1
		// @0C0: aaload
		// @0C1: invokevirtual java.lang.StringBuilder.append(java.lang.String)java.lang.StringBuilder
		// @0C4: bipush 44 (0x2C)
		// @0C6: invokevirtual java.lang.StringBuilder.append(char)java.lang.StringBuilder
		// @0C9: aload #4
		// @0CB: ifnull @0D7
		// @0CE: getstatic java.lang.String[] game.C_100111_el.field_104866_z
		// @0D1: iconst_2
		// @0D2: aaload
		// @0D3: goto @0DC
		// @0D6: athrow
		// @0D7: getstatic java.lang.String[] game.C_100111_el.field_104866_z
		// @0DA: iconst_1
		// @0DB: aaload
		// @0DC: invokevirtual java.lang.StringBuilder.append(java.lang.String)java.lang.StringBuilder
		// @0DF: bipush 44 (0x2C)
		// @0E1: invokevirtual java.lang.StringBuilder.append(char)java.lang.StringBuilder
		// @0E4: iload #5
		// @0E6: invokevirtual java.lang.StringBuilder.append(int)java.lang.StringBuilder
		// @0E9: bipush 44 (0x2C)
		// @0EB: invokevirtual java.lang.StringBuilder.append(char)java.lang.StringBuilder
		// @0EE: aload #6
		// @0F0: ifnull @0FC
		// @0F3: getstatic java.lang.String[] game.C_100111_el.field_104866_z
		// @0F6: iconst_2
		// @0F7: aaload
		// @0F8: goto @101
		// @0FB: athrow
		// @0FC: getstatic java.lang.String[] game.C_100111_el.field_104866_z
		// @0FF: iconst_1
		// @100: aaload
		// @101: invokevirtual java.lang.StringBuilder.append(java.lang.String)java.lang.StringBuilder
		// @104: bipush 41 (0x29)
		// @106: invokevirtual java.lang.StringBuilder.append(char)java.lang.StringBuilder
		// @109: invokevirtual java.lang.StringBuilder.toString()java.lang.String
		// @10C: invokestatic game.C_100181_cf.func_105695_a(java.lang.Throwable, java.lang.String)game.C_100170_cm
		// @10F: athrow
	}
	
	static final void func_104856_a(String[] arg0, String arg1, int arg2, boolean arg3)
	{
		// @00: getstatic int game.SteelSentinels.field_105275_O
		// @03: istore #5
		// @05: getstatic game.C_100068_vc game.C_100213_ak.field_105993_g
		// @08: putstatic game.C_100068_vc game.C_100191_rg.field_100845_o
		// @0B: iload_3
		// @0C: ifeq @1A
		// @0F: aconst_null
		// @10: checkcast game.C_100302_ka
		// @13: putstatic game.C_100302_ka game.C_100111_el.field_104860_d
		// @16: goto @1A
		// @19: athrow
		// @1A: sipush 255 (0x00FF)
		// @1D: iload_2
		// @1E: if_icmpne @46
		// @21: bipush -128 (0x80)
		// @23: bipush 13 (0x0D)
		// @25: getstatic int game.C_100089_fa.field_103728_c
		// @28: if_icmple @34
		// @2B: goto @2F
		// @2E: athrow
		// @2F: iconst_1
		// @30: goto @35
		// @33: athrow
		// @34: iconst_0
		// @35: invokestatic game.C_100217_ao.func_106032_a(byte, boolean)game.C_100096_un
		// @38: putstatic game.C_100096_un game.C_100077_d.field_103320_W
		// @3B: bipush -110 (0x92)
		// @3D: aconst_null
		// @3E: invokestatic game.C_100046_vk.func_102757_a(int, java.lang.String[])void
		// @41: iload #5
		// @43: ifeq @81
		// @46: bipush 100 (0x64)
		// @48: iload_2
		// @49: if_icmpgt @74
		// @4C: goto @50
		// @4F: athrow
		// @50: bipush -106 (0x96)
		// @52: iload_2
		// @53: iconst_m1
		// @54: ixor
		// @55: if_icmpgt @74
		// @58: goto @5C
		// @5B: athrow
		// @5C: aload_0
		// @5D: astore #4
		// @5F: bipush -27 (0xE5)
		// @61: aload #4
		// @63: invokestatic game.C_100046_vk.func_102757_a(int, java.lang.String[])void
		// @66: bipush -25 (0xE7)
		// @68: aload_0
		// @69: invokestatic game.C_100320_hh.func_102907_a(int, java.lang.String[])game.C_100096_un
		// @6C: putstatic game.C_100096_un game.C_100077_d.field_103320_W
		// @6F: iload #5
		// @71: ifeq @81
		// @74: aload_1
		// @75: iconst_0
		// @76: iload_2
		// @77: invokestatic game.C_100111_el.func_104855_a(java.lang.String, boolean, int)game.C_100096_un
		// @7A: putstatic game.C_100096_un game.C_100077_d.field_103320_W
		// @7D: goto @81
		// @80: athrow
		// @81: goto @E4
		// @84: astore #4
		// @86: aload #4
		// @88: new java.lang.StringBuilder
		// @8B: dup
		// @8C: invokespecial java.lang.StringBuilder.<init>()void
		// @8F: getstatic java.lang.String[] game.C_100111_el.field_104866_z
		// @92: iconst_5
		// @93: aaload
		// @94: invokevirtual java.lang.StringBuilder.append(java.lang.String)java.lang.StringBuilder
		// @97: aload_0
		// @98: ifnull @A4
		// @9B: getstatic java.lang.String[] game.C_100111_el.field_104866_z
		// @9E: iconst_2
		// @9F: aaload
		// @A0: goto @A9
		// @A3: athrow
		// @A4: getstatic java.lang.String[] game.C_100111_el.field_104866_z
		// @A7: iconst_1
		// @A8: aaload
		// @A9: invokevirtual java.lang.StringBuilder.append(java.lang.String)java.lang.StringBuilder
		// @AC: bipush 44 (0x2C)
		// @AE: invokevirtual java.lang.StringBuilder.append(char)java.lang.StringBuilder
		// @B1: aload_1
		// @B2: ifnull @BE
		// @B5: getstatic java.lang.String[] game.C_100111_el.field_104866_z
		// @B8: iconst_2
		// @B9: aaload
		// @BA: goto @C3
		// @BD: athrow
		// @BE: getstatic java.lang.String[] game.C_100111_el.field_104866_z
		// @C1: iconst_1
		// @C2: aaload
		// @C3: invokevirtual java.lang.StringBuilder.append(java.lang.String)java.lang.StringBuilder
		// @C6: bipush 44 (0x2C)
		// @C8: invokevirtual java.lang.StringBuilder.append(char)java.lang.StringBuilder
		// @CB: iload_2
		// @CC: invokevirtual java.lang.StringBuilder.append(int)java.lang.StringBuilder
		// @CF: bipush 44 (0x2C)
		// @D1: invokevirtual java.lang.StringBuilder.append(char)java.lang.StringBuilder
		// @D4: iload_3
		// @D5: invokevirtual java.lang.StringBuilder.append(boolean)java.lang.StringBuilder
		// @D8: bipush 41 (0x29)
		// @DA: invokevirtual java.lang.StringBuilder.append(char)java.lang.StringBuilder
		// @DD: invokevirtual java.lang.StringBuilder.toString()java.lang.String
		// @E0: invokestatic game.C_100181_cf.func_105695_a(java.lang.Throwable, java.lang.String)game.C_100170_cm
		// @E3: athrow
		// @E4: return
	}
	
	static final boolean func_104850_a(int arg0, int[] arg1, int arg2)
	{
		// @00: iload_0
		// @01: bipush 31 (0x1F)
		// @03: if_icmpeq @11
		// @06: aconst_null
		// @07: checkcast game.C_100187_rk
		// @0A: putstatic game.C_100187_rk game.C_100111_el.field_104864_a
		// @0D: goto @11
		// @10: athrow
		// @11: iconst_0
		// @12: aload_1
		// @13: iload_2
		// @14: ldc -1130530843 (0xbc9d77e5)
		// @16: ishr
		// @17: iaload
		// @18: iconst_1
		// @19: iload_2
		// @1A: bipush 31 (0x1F)
		// @1C: iand
		// @1D: ishl
		// @1E: iand
		// @1F: if_icmpne @27
		// @22: iconst_1
		// @23: goto @28
		// @26: athrow
		// @27: iconst_0
		// @28: ireturn
		// @29: astore_3
		// @2A: aload_3
		// @2B: new java.lang.StringBuilder
		// @2E: dup
		// @2F: invokespecial java.lang.StringBuilder.<init>()void
		// @32: getstatic java.lang.String[] game.C_100111_el.field_104866_z
		// @35: iconst_0
		// @36: aaload
		// @37: invokevirtual java.lang.StringBuilder.append(java.lang.String)java.lang.StringBuilder
		// @3A: iload_0
		// @3B: invokevirtual java.lang.StringBuilder.append(int)java.lang.StringBuilder
		// @3E: bipush 44 (0x2C)
		// @40: invokevirtual java.lang.StringBuilder.append(char)java.lang.StringBuilder
		// @43: aload_1
		// @44: ifnull @50
		// @47: getstatic java.lang.String[] game.C_100111_el.field_104866_z
		// @4A: iconst_2
		// @4B: aaload
		// @4C: goto @55
		// @4F: athrow
		// @50: getstatic java.lang.String[] game.C_100111_el.field_104866_z
		// @53: iconst_1
		// @54: aaload
		// @55: invokevirtual java.lang.StringBuilder.append(java.lang.String)java.lang.StringBuilder
		// @58: bipush 44 (0x2C)
		// @5A: invokevirtual java.lang.StringBuilder.append(char)java.lang.StringBuilder
		// @5D: iload_2
		// @5E: invokevirtual java.lang.StringBuilder.append(int)java.lang.StringBuilder
		// @61: bipush 41 (0x29)
		// @63: invokevirtual java.lang.StringBuilder.append(char)java.lang.StringBuilder
		// @66: invokevirtual java.lang.StringBuilder.toString()java.lang.String
		// @69: invokestatic game.C_100181_cf.func_105695_a(java.lang.Throwable, java.lang.String)game.C_100170_cm
		// @6C: athrow
	}
	
	static
	{
		// @000: bipush 8 (0x08)
		// @002: anewarray java.lang.String
		// @005: dup
		// @006: iconst_0
		// @007: ldc "{i\u00007t"
		// @009: invokestatic game.C_100111_el.func_104854_z(java.lang.String)char[]
		// @00C: invokestatic game.C_100111_el.func_104853_z(char[])java.lang.String
		// @00F: aastore
		// @010: dup
		// @011: iconst_1
		// @012: ldc "ppB\u001f"
		// @014: invokestatic game.C_100111_el.func_104854_z(java.lang.String)char[]
		// @017: invokestatic game.C_100111_el.func_104853_z(char[])java.lang.String
		// @01A: aastore
		// @01B: dup
		// @01C: iconst_2
		// @01D: ldc "e+\u0000]!"
		// @01F: invokestatic game.C_100111_el.func_104854_z(java.lang.String)char[]
		// @022: invokestatic game.C_100111_el.func_104853_z(char[])java.lang.String
		// @025: aastore
		// @026: dup
		// @027: iconst_3
		// @028: ldc "{i\u00002t"
		// @02A: invokestatic game.C_100111_el.func_104854_z(java.lang.String)char[]
		// @02D: invokestatic game.C_100111_el.func_104853_z(char[])java.lang.String
		// @030: aastore
		// @031: dup
		// @032: iconst_4
		// @033: ldc "{i\u00005t"
		// @035: invokestatic game.C_100111_el.func_104854_z(java.lang.String)char[]
		// @038: invokestatic game.C_100111_el.func_104853_z(char[])java.lang.String
		// @03B: aastore
		// @03C: dup
		// @03D: iconst_5
		// @03E: ldc "{i\u00000t"
		// @040: invokestatic game.C_100111_el.func_104854_z(java.lang.String)char[]
		// @043: invokestatic game.C_100111_el.func_104853_z(char[])java.lang.String
		// @046: aastore
		// @047: dup
		// @048: bipush 6 (0x06)
		// @04A: ldc "{i\u00006t"
		// @04C: invokestatic game.C_100111_el.func_104854_z(java.lang.String)char[]
		// @04F: invokestatic game.C_100111_el.func_104853_z(char[])java.lang.String
		// @052: aastore
		// @053: dup
		// @054: bipush 7 (0x07)
		// @056: ldc "{i\u00001t"
		// @058: invokestatic game.C_100111_el.func_104854_z(java.lang.String)char[]
		// @05B: invokestatic game.C_100111_el.func_104853_z(char[])java.lang.String
		// @05E: aastore
		// @05F: putstatic java.lang.String[] game.C_100111_el.field_104866_z
		// @062: aconst_null
		// @063: putstatic game.C_100187_rk game.C_100111_el.field_104864_a
		// @066: ldc "OpG\u00107>FF\u0012(>MK\u001f,"
		// @068: invokestatic game.C_100111_el.func_104854_z(java.lang.String)char[]
		// @06B: invokestatic game.C_100111_el.func_104853_z(char[])java.lang.String
		// @06E: putstatic java.lang.String game.C_100111_el.field_104858_f
		// @071: ldc "[}^\u0016.j%z\u0001=wkG\u001d;"
		// @073: invokestatic game.C_100111_el.func_104854_z(java.lang.String)char[]
		// @076: invokestatic game.C_100111_el.func_104853_z(char[])java.lang.String
		// @079: putstatic java.lang.String game.C_100111_el.field_104861_e
		// @07C: ldc "L`C\u001c*{%\u0012Vl %H\u00013s%H\u00015{kJS0wvZ"
		// @07E: invokestatic game.C_100111_el.func_104854_z(java.lang.String)char[]
		// @081: invokestatic game.C_100111_el.func_104853_z(char[])java.lang.String
		// @084: putstatic java.lang.String game.C_100111_el.field_104863_c
		// @087: bipush 53 (0x35)
		// @089: newarray char[]
		// @08B: dup
		// @08C: iconst_0
		// @08D: bipush 32 (0x20)
		// @08F: castore
		// @090: dup
		// @091: iconst_1
		// @092: sipush 160 (0x00A0)
		// @095: castore
		// @096: dup
		// @097: iconst_2
		// @098: bipush 95 (0x5F)
		// @09A: castore
		// @09B: dup
		// @09C: iconst_3
		// @09D: bipush 45 (0x2D)
		// @09F: castore
		// @0A0: dup
		// @0A1: iconst_4
		// @0A2: sipush 224 (0x00E0)
		// @0A5: castore
		// @0A6: dup
		// @0A7: iconst_5
		// @0A8: sipush 225 (0x00E1)
		// @0AB: castore
		// @0AC: dup
		// @0AD: bipush 6 (0x06)
		// @0AF: sipush 226 (0x00E2)
		// @0B2: castore
		// @0B3: dup
		// @0B4: bipush 7 (0x07)
		// @0B6: sipush 228 (0x00E4)
		// @0B9: castore
		// @0BA: dup
		// @0BB: bipush 8 (0x08)
		// @0BD: sipush 227 (0x00E3)
		// @0C0: castore
		// @0C1: dup
		// @0C2: bipush 9 (0x09)
		// @0C4: sipush 192 (0x00C0)
		// @0C7: castore
		// @0C8: dup
		// @0C9: bipush 10 (0x0A)
		// @0CB: sipush 193 (0x00C1)
		// @0CE: castore
		// @0CF: dup
		// @0D0: bipush 11 (0x0B)
		// @0D2: sipush 194 (0x00C2)
		// @0D5: castore
		// @0D6: dup
		// @0D7: bipush 12 (0x0C)
		// @0D9: sipush 196 (0x00C4)
		// @0DC: castore
		// @0DD: dup
		// @0DE: bipush 13 (0x0D)
		// @0E0: sipush 195 (0x00C3)
		// @0E3: castore
		// @0E4: dup
		// @0E5: bipush 14 (0x0E)
		// @0E7: sipush 232 (0x00E8)
		// @0EA: castore
		// @0EB: dup
		// @0EC: bipush 15 (0x0F)
		// @0EE: sipush 233 (0x00E9)
		// @0F1: castore
		// @0F2: dup
		// @0F3: bipush 16 (0x10)
		// @0F5: sipush 234 (0x00EA)
		// @0F8: castore
		// @0F9: dup
		// @0FA: bipush 17 (0x11)
		// @0FC: sipush 235 (0x00EB)
		// @0FF: castore
		// @100: dup
		// @101: bipush 18 (0x12)
		// @103: sipush 200 (0x00C8)
		// @106: castore
		// @107: dup
		// @108: bipush 19 (0x13)
		// @10A: sipush 201 (0x00C9)
		// @10D: castore
		// @10E: dup
		// @10F: bipush 20 (0x14)
		// @111: sipush 202 (0x00CA)
		// @114: castore
		// @115: dup
		// @116: bipush 21 (0x15)
		// @118: sipush 203 (0x00CB)
		// @11B: castore
		// @11C: dup
		// @11D: bipush 22 (0x16)
		// @11F: sipush 237 (0x00ED)
		// @122: castore
		// @123: dup
		// @124: bipush 23 (0x17)
		// @126: sipush 238 (0x00EE)
		// @129: castore
		// @12A: dup
		// @12B: bipush 24 (0x18)
		// @12D: sipush 239 (0x00EF)
		// @130: castore
		// @131: dup
		// @132: bipush 25 (0x19)
		// @134: sipush 205 (0x00CD)
		// @137: castore
		// @138: dup
		// @139: bipush 26 (0x1A)
		// @13B: sipush 206 (0x00CE)
		// @13E: castore
		// @13F: dup
		// @140: bipush 27 (0x1B)
		// @142: sipush 207 (0x00CF)
		// @145: castore
		// @146: dup
		// @147: bipush 28 (0x1C)
		// @149: sipush 242 (0x00F2)
		// @14C: castore
		// @14D: dup
		// @14E: bipush 29 (0x1D)
		// @150: sipush 243 (0x00F3)
		// @153: castore
		// @154: dup
		// @155: bipush 30 (0x1E)
		// @157: sipush 244 (0x00F4)
		// @15A: castore
		// @15B: dup
		// @15C: bipush 31 (0x1F)
		// @15E: sipush 246 (0x00F6)
		// @161: castore
		// @162: dup
		// @163: bipush 32 (0x20)
		// @165: sipush 245 (0x00F5)
		// @168: castore
		// @169: dup
		// @16A: bipush 33 (0x21)
		// @16C: sipush 210 (0x00D2)
		// @16F: castore
		// @170: dup
		// @171: bipush 34 (0x22)
		// @173: sipush 211 (0x00D3)
		// @176: castore
		// @177: dup
		// @178: bipush 35 (0x23)
		// @17A: sipush 212 (0x00D4)
		// @17D: castore
		// @17E: dup
		// @17F: bipush 36 (0x24)
		// @181: sipush 214 (0x00D6)
		// @184: castore
		// @185: dup
		// @186: bipush 37 (0x25)
		// @188: sipush 213 (0x00D5)
		// @18B: castore
		// @18C: dup
		// @18D: bipush 38 (0x26)
		// @18F: sipush 249 (0x00F9)
		// @192: castore
		// @193: dup
		// @194: bipush 39 (0x27)
		// @196: sipush 250 (0x00FA)
		// @199: castore
		// @19A: dup
		// @19B: bipush 40 (0x28)
		// @19D: sipush 251 (0x00FB)
		// @1A0: castore
		// @1A1: dup
		// @1A2: bipush 41 (0x29)
		// @1A4: sipush 252 (0x00FC)
		// @1A7: castore
		// @1A8: dup
		// @1A9: bipush 42 (0x2A)
		// @1AB: sipush 217 (0x00D9)
		// @1AE: castore
		// @1AF: dup
		// @1B0: bipush 43 (0x2B)
		// @1B2: sipush 218 (0x00DA)
		// @1B5: castore
		// @1B6: dup
		// @1B7: bipush 44 (0x2C)
		// @1B9: sipush 219 (0x00DB)
		// @1BC: castore
		// @1BD: dup
		// @1BE: bipush 45 (0x2D)
		// @1C0: sipush 220 (0x00DC)
		// @1C3: castore
		// @1C4: dup
		// @1C5: bipush 46 (0x2E)
		// @1C7: sipush 231 (0x00E7)
		// @1CA: castore
		// @1CB: dup
		// @1CC: bipush 47 (0x2F)
		// @1CE: sipush 199 (0x00C7)
		// @1D1: castore
		// @1D2: dup
		// @1D3: bipush 48 (0x30)
		// @1D5: sipush 255 (0x00FF)
		// @1D8: castore
		// @1D9: dup
		// @1DA: bipush 49 (0x31)
		// @1DC: sipush 376 (0x0178)
		// @1DF: castore
		// @1E0: dup
		// @1E1: bipush 50 (0x32)
		// @1E3: sipush 241 (0x00F1)
		// @1E6: castore
		// @1E7: dup
		// @1E8: bipush 51 (0x33)
		// @1EA: sipush 209 (0x00D1)
		// @1ED: castore
		// @1EE: dup
		// @1EF: bipush 52 (0x34)
		// @1F1: sipush 223 (0x00DF)
		// @1F4: castore
		// @1F5: putstatic char[] game.C_100111_el.field_104865_j
		// @1F8: new game.C_100047_vh
		// @1FB: dup
		// @1FC: invokespecial game.C_100047_vh.<init>()void
		// @1FF: putstatic game.C_100047_vh game.C_100111_el.field_104859_g
		// @202: iconst_3
		// @203: anewarray game.C_100037_wb
		// @206: putstatic game.C_100037_wb[] game.C_100111_el.field_104867_h
		// @209: iconst_5
		// @20A: newarray int[]
		// @20C: dup
		// @20D: iconst_0
		// @20E: bipush 48 (0x30)
		// @210: iastore
		// @211: dup
		// @212: iconst_1
		// @213: sipush 272 (0x0110)
		// @216: iastore
		// @217: dup
		// @218: iconst_2
		// @219: sipush 380 (0x017C)
		// @21C: iastore
		// @21D: dup
		// @21E: iconst_3
		// @21F: sipush 490 (0x01EA)
		// @222: iastore
		// @223: dup
		// @224: iconst_4
		// @225: sipush 591 (0x024F)
		// @228: iastore
		// @229: putstatic int[] game.C_100111_el.field_104862_b
		// @22C: return
	}
	
	private static char[] func_104854_z(String arg0)
	{
		// @00: aload_0
		// @01: invokevirtual java.lang.String.toCharArray()char[]
		// @04: dup
		// @05: arraylength
		// @06: iconst_2
		// @07: if_icmpge @13
		// @0A: dup
		// @0B: iconst_0
		// @0C: dup2
		// @0D: caload
		// @0E: bipush 92 (0x5C)
		// @10: ixor
		// @11: i2c
		// @12: castore
		// @13: areturn
	}
	
	private static String func_104853_z(char[] arg0)
	{
		// @00: aload_0
		// @01: dup
		// @02: arraylength
		// @03: swap
		// @04: iconst_0
		// @05: istore_1
		// @06: goto @4B
		// @09: dup
		// @0A: iload_1
		// @0B: dup2
		// @0C: caload
		// @0D: iload_1
		// @0E: iconst_5
		// @0F: irem
		// @10: tableswitch def: @43, for 0: @30, for 1: @35, for 2: @39, for 3: @3E
		// @30: bipush 30 (0x1E)
		// @32: goto @45
		// @35: iconst_5
		// @36: goto @45
		// @39: bipush 46 (0x2E)
		// @3B: goto @45
		// @3E: bipush 115 (0x73)
		// @40: goto @45
		// @43: bipush 92 (0x5C)
		// @45: ixor
		// @46: i2c
		// @47: castore
		// @48: iinc #1 +1
		// @4B: swap
		// @4C: dup_x1
		// @4D: iload_1
		// @4E: if_icmpgt @09
		// @51: new java.lang.String
		// @54: dup_x1
		// @55: swap
		// @56: invokespecial java.lang.String.<init>(char[])void
		// @59: invokevirtual java.lang.String.intern()java.lang.String
		// @5C: areturn
	}
}
