package game;

final class C_100060_di
{
	static C_100112_r field_104269_d;
	static String field_104272_c;
	static C_100037_wb[] field_104271_b;
	static String field_104270_e;
	static C_100013_fn field_104273_a;
	private static final String[] field_104274_z;
	
	static final void func_104264_a(C_100098_h arg0, int arg1)
	{
		// @00: aload_0
		// @01: ldc ""
		// @03: getstatic java.lang.String[] game.C_100060_di.field_104274_z
		// @06: bipush 7 (0x07)
		// @08: aaload
		// @09: bipush -125 (0x83)
		// @0B: invokevirtual game.C_100098_h.func_104608_a(java.lang.String, java.lang.String, int)byte[]
		// @0E: invokestatic game.C_100319_hk.func_101421_a(byte[])void
		// @11: iload_1
		// @12: ifeq @20
		// @15: aconst_null
		// @16: checkcast java.lang.String
		// @19: putstatic java.lang.String game.C_100060_di.field_104272_c
		// @1C: goto @20
		// @1F: athrow
		// @20: aload_0
		// @21: getstatic java.lang.String[] game.C_100060_di.field_104274_z
		// @24: bipush 6 (0x06)
		// @26: aaload
		// @27: ldc ""
		// @29: invokestatic game.C_100319_hk.func_101420_a(game.C_100098_h, java.lang.String, java.lang.String)game.C_100319_hk
		// @2C: astore_2
		// @2D: aload_2
		// @2E: invokevirtual game.C_100319_hk.func_101424_c()game.C_100214_al
		// @31: pop
		// @32: goto @70
		// @35: astore_2
		// @36: aload_2
		// @37: new java.lang.StringBuilder
		// @3A: dup
		// @3B: invokespecial java.lang.StringBuilder.<init>()void
		// @3E: getstatic java.lang.String[] game.C_100060_di.field_104274_z
		// @41: iconst_5
		// @42: aaload
		// @43: invokevirtual java.lang.StringBuilder.append(java.lang.String)java.lang.StringBuilder
		// @46: aload_0
		// @47: ifnull @53
		// @4A: getstatic java.lang.String[] game.C_100060_di.field_104274_z
		// @4D: iconst_0
		// @4E: aaload
		// @4F: goto @58
		// @52: athrow
		// @53: getstatic java.lang.String[] game.C_100060_di.field_104274_z
		// @56: iconst_3
		// @57: aaload
		// @58: invokevirtual java.lang.StringBuilder.append(java.lang.String)java.lang.StringBuilder
		// @5B: bipush 44 (0x2C)
		// @5D: invokevirtual java.lang.StringBuilder.append(char)java.lang.StringBuilder
		// @60: iload_1
		// @61: invokevirtual java.lang.StringBuilder.append(int)java.lang.StringBuilder
		// @64: bipush 41 (0x29)
		// @66: invokevirtual java.lang.StringBuilder.append(char)java.lang.StringBuilder
		// @69: invokevirtual java.lang.StringBuilder.toString()java.lang.String
		// @6C: invokestatic game.C_100181_cf.func_105695_a(java.lang.Throwable, java.lang.String)game.C_100170_cm
		// @6F: athrow
		// @70: return
	}
	
	static final C_100292_jk func_104268_a(int arg0, int arg1, int[] arg2, byte arg3, int arg4, int arg5, int arg6, int arg7, int arg8)
	{
		// @00: new game.C_100292_jk
		// @03: dup
		// @04: iload #6
		// @06: iload #4
		// @08: iload_0
		// @09: iload_1
		// @0A: iload #7
		// @0C: iload #5
		// @0E: aload_2
		// @0F: invokespecial game.C_100292_jk.<init>(int, int, int, int, int, int, int[])void
		// @12: astore #9
		// @14: getstatic game.C_100202_qi game.C_100178_cg.field_105689_e
		// @17: bipush 124 (0x7C)
		// @19: aload #9
		// @1B: invokevirtual game.C_100202_qi.func_105901_a(int, game.C_100158_da)void
		// @1E: bipush 47 (0x2F)
		// @20: aload #9
		// @22: iload #8
		// @24: invokestatic game.C_100016_wi.func_103801_a(int, game.C_100292_jk, int)void
		// @27: iload_3
		// @28: bipush 48 (0x30)
		// @2A: if_icmpeq @32
		// @2D: aconst_null
		// @2E: checkcast game.C_100292_jk
		// @31: areturn
		// @32: aload #9
		// @34: areturn
		// @35: astore #9
		// @37: aload #9
		// @39: new java.lang.StringBuilder
		// @3C: dup
		// @3D: invokespecial java.lang.StringBuilder.<init>()void
		// @40: getstatic java.lang.String[] game.C_100060_di.field_104274_z
		// @43: iconst_4
		// @44: aaload
		// @45: invokevirtual java.lang.StringBuilder.append(java.lang.String)java.lang.StringBuilder
		// @48: iload_0
		// @49: invokevirtual java.lang.StringBuilder.append(int)java.lang.StringBuilder
		// @4C: bipush 44 (0x2C)
		// @4E: invokevirtual java.lang.StringBuilder.append(char)java.lang.StringBuilder
		// @51: iload_1
		// @52: invokevirtual java.lang.StringBuilder.append(int)java.lang.StringBuilder
		// @55: bipush 44 (0x2C)
		// @57: invokevirtual java.lang.StringBuilder.append(char)java.lang.StringBuilder
		// @5A: aload_2
		// @5B: ifnull @67
		// @5E: getstatic java.lang.String[] game.C_100060_di.field_104274_z
		// @61: iconst_0
		// @62: aaload
		// @63: goto @6C
		// @66: athrow
		// @67: getstatic java.lang.String[] game.C_100060_di.field_104274_z
		// @6A: iconst_3
		// @6B: aaload
		// @6C: invokevirtual java.lang.StringBuilder.append(java.lang.String)java.lang.StringBuilder
		// @6F: bipush 44 (0x2C)
		// @71: invokevirtual java.lang.StringBuilder.append(char)java.lang.StringBuilder
		// @74: iload_3
		// @75: invokevirtual java.lang.StringBuilder.append(int)java.lang.StringBuilder
		// @78: bipush 44 (0x2C)
		// @7A: invokevirtual java.lang.StringBuilder.append(char)java.lang.StringBuilder
		// @7D: iload #4
		// @7F: invokevirtual java.lang.StringBuilder.append(int)java.lang.StringBuilder
		// @82: bipush 44 (0x2C)
		// @84: invokevirtual java.lang.StringBuilder.append(char)java.lang.StringBuilder
		// @87: iload #5
		// @89: invokevirtual java.lang.StringBuilder.append(int)java.lang.StringBuilder
		// @8C: bipush 44 (0x2C)
		// @8E: invokevirtual java.lang.StringBuilder.append(char)java.lang.StringBuilder
		// @91: iload #6
		// @93: invokevirtual java.lang.StringBuilder.append(int)java.lang.StringBuilder
		// @96: bipush 44 (0x2C)
		// @98: invokevirtual java.lang.StringBuilder.append(char)java.lang.StringBuilder
		// @9B: iload #7
		// @9D: invokevirtual java.lang.StringBuilder.append(int)java.lang.StringBuilder
		// @A0: bipush 44 (0x2C)
		// @A2: invokevirtual java.lang.StringBuilder.append(char)java.lang.StringBuilder
		// @A5: iload #8
		// @A7: invokevirtual java.lang.StringBuilder.append(int)java.lang.StringBuilder
		// @AA: bipush 41 (0x29)
		// @AC: invokevirtual java.lang.StringBuilder.append(char)java.lang.StringBuilder
		// @AF: invokevirtual java.lang.StringBuilder.toString()java.lang.String
		// @B2: invokestatic game.C_100181_cf.func_105695_a(java.lang.Throwable, java.lang.String)game.C_100170_cm
		// @B5: athrow
	}
	
	static final void func_104263_b(C_100098_h arg0, int arg1)
	{
		// @00: new game.C_100037_wb
		// @03: dup
		// @04: aload_0
		// @05: ldc ""
		// @07: getstatic java.lang.String[] game.C_100060_di.field_104274_z
		// @0A: iconst_2
		// @0B: aaload
		// @0C: iload_1
		// @0D: bipush -16 (0xF0)
		// @0F: iadd
		// @10: invokevirtual game.C_100098_h.func_104608_a(java.lang.String, java.lang.String, int)byte[]
		// @13: getstatic java.awt.Canvas game.C_100034_gi.field_104033_a
		// @16: invokespecial game.C_100037_wb.<init>(byte[], java.awt.Component)void
		// @19: astore_2
		// @1A: aload_2
		// @1B: getfield int game.C_100037_wb.field_102339_s
		// @1E: istore_3
		// @1F: aload_2
		// @20: getfield int game.C_100037_wb.field_102337_u
		// @23: istore #4
		// @25: bipush -46 (0xD2)
		// @27: invokestatic game.C_100328_ia.func_107254_b(byte)void
		// @2A: new game.C_100037_wb
		// @2D: dup
		// @2E: iload_3
		// @2F: iload #4
		// @31: iconst_3
		// @32: imul
		// @33: iconst_4
		// @34: idiv
		// @35: invokespecial game.C_100037_wb.<init>(int, int)void
		// @38: putstatic game.C_100037_wb game.C_100149_bi.field_105156_b
		// @3B: getstatic game.C_100037_wb game.C_100149_bi.field_105156_b
		// @3E: invokevirtual game.C_100037_wb.func_102379_d()void
		// @41: aload_2
		// @42: iconst_0
		// @43: iconst_0
		// @44: invokevirtual game.C_100037_wb.func_102386_f(int, int)void
		// @47: new game.C_100037_wb
		// @4A: dup
		// @4B: iload_3
		// @4C: iload #4
		// @4E: getstatic game.C_100037_wb game.C_100149_bi.field_105156_b
		// @51: getfield int game.C_100037_wb.field_102337_u
		// @54: ineg
		// @55: iadd
		// @56: invokespecial game.C_100037_wb.<init>(int, int)void
		// @59: putstatic game.C_100037_wb game.C_100217_ao.field_106036_e
		// @5C: getstatic game.C_100037_wb game.C_100217_ao.field_106036_e
		// @5F: invokevirtual game.C_100037_wb.func_102379_d()void
		// @62: aload_2
		// @63: iload_1
		// @64: getstatic game.C_100037_wb game.C_100149_bi.field_105156_b
		// @67: getfield int game.C_100037_wb.field_102337_u
		// @6A: ineg
		// @6B: invokevirtual game.C_100037_wb.func_102386_f(int, int)void
		// @6E: getstatic game.C_100037_wb game.C_100217_ao.field_106036_e
		// @71: getstatic game.C_100037_wb game.C_100149_bi.field_105156_b
		// @74: getfield int game.C_100037_wb.field_102337_u
		// @77: putfield int game.C_100037_wb.field_102332_H
		// @7A: bipush -77 (0xB3)
		// @7C: invokestatic game.C_100200_ba.func_105842_a(byte)void
		// @7F: goto @BD
		// @82: astore_2
		// @83: aload_2
		// @84: new java.lang.StringBuilder
		// @87: dup
		// @88: invokespecial java.lang.StringBuilder.<init>()void
		// @8B: getstatic java.lang.String[] game.C_100060_di.field_104274_z
		// @8E: iconst_1
		// @8F: aaload
		// @90: invokevirtual java.lang.StringBuilder.append(java.lang.String)java.lang.StringBuilder
		// @93: aload_0
		// @94: ifnull @A0
		// @97: getstatic java.lang.String[] game.C_100060_di.field_104274_z
		// @9A: iconst_0
		// @9B: aaload
		// @9C: goto @A5
		// @9F: athrow
		// @A0: getstatic java.lang.String[] game.C_100060_di.field_104274_z
		// @A3: iconst_3
		// @A4: aaload
		// @A5: invokevirtual java.lang.StringBuilder.append(java.lang.String)java.lang.StringBuilder
		// @A8: bipush 44 (0x2C)
		// @AA: invokevirtual java.lang.StringBuilder.append(char)java.lang.StringBuilder
		// @AD: iload_1
		// @AE: invokevirtual java.lang.StringBuilder.append(int)java.lang.StringBuilder
		// @B1: bipush 41 (0x29)
		// @B3: invokevirtual java.lang.StringBuilder.append(char)java.lang.StringBuilder
		// @B6: invokevirtual java.lang.StringBuilder.toString()java.lang.String
		// @B9: invokestatic game.C_100181_cf.func_105695_a(java.lang.Throwable, java.lang.String)game.C_100170_cm
		// @BC: athrow
		// @BD: return
	}
	
	public static void func_104266_a(byte arg0)
	{
		// @00: aconst_null
		// @01: putstatic game.C_100112_r game.C_100060_di.field_104269_d
		// @04: bipush -116 (0x8C)
		// @06: bipush 58 (0x3A)
		// @08: iload_0
		// @09: isub
		// @0A: bipush 59 (0x3B)
		// @0C: idiv
		// @0D: idiv
		// @0E: istore_1
		// @0F: aconst_null
		// @10: putstatic java.lang.String game.C_100060_di.field_104272_c
		// @13: aconst_null
		// @14: putstatic game.C_100013_fn game.C_100060_di.field_104273_a
		// @17: aconst_null
		// @18: putstatic java.lang.String game.C_100060_di.field_104270_e
		// @1B: aconst_null
		// @1C: putstatic game.C_100037_wb[] game.C_100060_di.field_104271_b
		// @1F: goto @44
		// @22: astore_1
		// @23: aload_1
		// @24: new java.lang.StringBuilder
		// @27: dup
		// @28: invokespecial java.lang.StringBuilder.<init>()void
		// @2B: getstatic java.lang.String[] game.C_100060_di.field_104274_z
		// @2E: bipush 8 (0x08)
		// @30: aaload
		// @31: invokevirtual java.lang.StringBuilder.append(java.lang.String)java.lang.StringBuilder
		// @34: iload_0
		// @35: invokevirtual java.lang.StringBuilder.append(int)java.lang.StringBuilder
		// @38: bipush 41 (0x29)
		// @3A: invokevirtual java.lang.StringBuilder.append(char)java.lang.StringBuilder
		// @3D: invokevirtual java.lang.StringBuilder.toString()java.lang.String
		// @40: invokestatic game.C_100181_cf.func_105695_a(java.lang.Throwable, java.lang.String)game.C_100170_cm
		// @43: athrow
		// @44: return
	}
	
	static
	{
		// @00: bipush 9 (0x09)
		// @02: anewarray java.lang.String
		// @05: dup
		// @06: iconst_0
		// @07: ldc ")/\u001f;\u0015"
		// @09: invokestatic game.C_100060_di.func_104267_z(java.lang.String)char[]
		// @0C: invokestatic game.C_100060_di.func_104265_z(char[])java.lang.String
		// @0F: aastore
		// @10: dup
		// @11: iconst_1
		// @12: ldc "6h\u001fW@"
		// @14: invokestatic game.C_100060_di.func_104267_z(java.lang.String)char[]
		// @17: invokestatic game.C_100060_di.func_104265_z(char[])java.lang.String
		// @1A: aastore
		// @1B: dup
		// @1C: iconst_2
		// @1D: ldc "4h_t\u0004\rgCt\u00057/[e\u000f"
		// @1F: invokestatic game.C_100060_di.func_104267_z(java.lang.String)char[]
		// @22: invokestatic game.C_100060_di.func_104265_z(char[])java.lang.String
		// @25: aastore
		// @26: dup
		// @27: iconst_3
		// @28: ldc "<t]y"
		// @2A: invokestatic game.C_100060_di.func_104267_z(java.lang.String)char[]
		// @2D: invokestatic game.C_100060_di.func_104265_z(char[])java.lang.String
		// @30: aastore
		// @31: dup
		// @32: iconst_4
		// @33: ldc "6h\u001fT@"
		// @35: invokestatic game.C_100060_di.func_104267_z(java.lang.String)char[]
		// @38: invokestatic game.C_100060_di.func_104265_z(char[])java.lang.String
		// @3B: aastore
		// @3C: dup
		// @3D: iconst_5
		// @3E: ldc "6h\u001fQ@"
		// @40: invokestatic game.C_100060_di.func_104267_z(java.lang.String)char[]
		// @43: invokestatic game.C_100060_di.func_104265_z(char[])java.lang.String
		// @46: aastore
		// @47: dup
		// @48: bipush 6 (0x06)
		// @4A: ldc "8`Vp\u0010rm^r\u0007`/At\u000b9w^g\n;r"
		// @4C: invokestatic game.C_100060_di.func_104267_z(java.lang.String)char[]
		// @4F: invokestatic game.C_100060_di.func_104265_z(char[])java.lang.String
		// @52: aastore
		// @53: dup
		// @54: bipush 7 (0x07)
		// @56: ldc ":dPq\r r\u001fe\t1jGz\u001a0hB"
		// @58: invokestatic game.C_100060_di.func_104267_z(java.lang.String)char[]
		// @5B: invokestatic game.C_100060_di.func_104265_z(char[])java.lang.String
		// @5E: aastore
		// @5F: dup
		// @60: bipush 8 (0x08)
		// @62: ldc "6h\u001fV@"
		// @64: invokestatic game.C_100060_di.func_104267_z(java.lang.String)char[]
		// @67: invokestatic game.C_100060_di.func_104265_z(char[])java.lang.String
		// @6A: aastore
		// @6B: putstatic java.lang.String[] game.C_100060_di.field_104274_z
		// @6E: ldc "\u0011sTt\u001c7!P5\u000e dT5\t1b^`\u0006&!EzH!uPg\u001crtB|\u00065!E}\u0001!!Wp\t&tCp"
		// @70: invokestatic game.C_100060_di.func_104267_z(java.lang.String)char[]
		// @73: invokestatic game.C_100060_di.func_104265_z(char[])java.lang.String
		// @76: putstatic java.lang.String game.C_100060_di.field_104270_e
		// @79: ldc "\u0002sTc\u0001=tB"
		// @7B: invokestatic game.C_100060_di.func_104267_z(java.lang.String)char[]
		// @7E: invokestatic game.C_100060_di.func_104265_z(char[])java.lang.String
		// @81: putstatic java.lang.String game.C_100060_di.field_104272_c
		// @84: new game.C_100013_fn
		// @87: dup
		// @88: iconst_3
		// @89: invokespecial game.C_100013_fn.<init>(int)void
		// @8C: putstatic game.C_100013_fn game.C_100060_di.field_104273_a
		// @8F: return
	}
	
	private static char[] func_104267_z(String arg0)
	{
		// @00: aload_0
		// @01: invokevirtual java.lang.String.toCharArray()char[]
		// @04: dup
		// @05: arraylength
		// @06: iconst_2
		// @07: if_icmpge @13
		// @0A: dup
		// @0B: iconst_0
		// @0C: dup2
		// @0D: caload
		// @0E: bipush 104 (0x68)
		// @10: ixor
		// @11: i2c
		// @12: castore
		// @13: areturn
	}
	
	private static String func_104265_z(char[] arg0)
	{
		// @00: aload_0
		// @01: dup
		// @02: arraylength
		// @03: swap
		// @04: iconst_0
		// @05: istore_1
		// @06: goto @4B
		// @09: dup
		// @0A: iload_1
		// @0B: dup2
		// @0C: caload
		// @0D: iload_1
		// @0E: iconst_5
		// @0F: irem
		// @10: tableswitch def: @43, for 0: @30, for 1: @35, for 2: @39, for 3: @3E
		// @30: bipush 82 (0x52)
		// @32: goto @45
		// @35: iconst_1
		// @36: goto @45
		// @39: bipush 49 (0x31)
		// @3B: goto @45
		// @3E: bipush 21 (0x15)
		// @40: goto @45
		// @43: bipush 104 (0x68)
		// @45: ixor
		// @46: i2c
		// @47: castore
		// @48: iinc #1 +1
		// @4B: swap
		// @4C: dup_x1
		// @4D: iload_1
		// @4E: if_icmpgt @09
		// @51: new java.lang.String
		// @54: dup_x1
		// @55: swap
		// @56: invokespecial java.lang.String.<init>(char[])void
		// @59: invokevirtual java.lang.String.intern()java.lang.String
		// @5C: areturn
	}
}
