package game;

import java.awt.Frame;

final class C_100269_ml extends C_100158_da
{
	static int field_101127_j;
	static int field_101124_o;
	static String field_101122_p;
	static C_100037_wb field_101129_k;
	static int[] field_101125_l;
	static C_100217_ao field_101121_q;
	static int[] field_101123_n;
	String field_101120_r;
	C_100037_wb field_101126_m;
	private static final String[] field_101128_z;
	
	public static void func_101118_a(boolean arg0)
	{
		// @00: aconst_null
		// @01: putstatic int[] game.C_100269_ml.field_101123_n
		// @04: iload_0
		// @05: iconst_1
		// @06: if_icmpeq @14
		// @09: aconst_null
		// @0A: checkcast game.C_100037_wb
		// @0D: putstatic game.C_100037_wb game.C_100269_ml.field_101129_k
		// @10: goto @14
		// @13: athrow
		// @14: aconst_null
		// @15: putstatic game.C_100037_wb game.C_100269_ml.field_101129_k
		// @18: aconst_null
		// @19: putstatic java.lang.String game.C_100269_ml.field_101122_p
		// @1C: aconst_null
		// @1D: putstatic int[] game.C_100269_ml.field_101125_l
		// @20: aconst_null
		// @21: putstatic game.C_100217_ao game.C_100269_ml.field_101121_q
		// @24: goto @48
		// @27: astore_1
		// @28: aload_1
		// @29: new java.lang.StringBuilder
		// @2C: dup
		// @2D: invokespecial java.lang.StringBuilder.<init>()void
		// @30: getstatic java.lang.String[] game.C_100269_ml.field_101128_z
		// @33: iconst_0
		// @34: aaload
		// @35: invokevirtual java.lang.StringBuilder.append(java.lang.String)java.lang.StringBuilder
		// @38: iload_0
		// @39: invokevirtual java.lang.StringBuilder.append(boolean)java.lang.StringBuilder
		// @3C: bipush 41 (0x29)
		// @3E: invokevirtual java.lang.StringBuilder.append(char)java.lang.StringBuilder
		// @41: invokevirtual java.lang.StringBuilder.toString()java.lang.String
		// @44: invokestatic game.C_100181_cf.func_105695_a(java.lang.Throwable, java.lang.String)game.C_100170_cm
		// @47: athrow
		// @48: return
	}
	
	static final String func_101119_a(int arg0, String arg1, String arg2, int arg3)
	{
		// @000: aload_1
		// @001: bipush -85 (0xAB)
		// @003: invokestatic game.C_100240_oj.func_106310_a(java.lang.CharSequence, byte)boolean
		// @006: ifeq @00D
		// @009: goto @011
		// @00C: athrow
		// @00D: getstatic java.lang.String game.C_100315_la.field_107175_g
		// @010: areturn
		// @011: bipush -3 (0xFD)
		// @013: getstatic int game.C_100062_dk.field_104281_d
		// @016: iconst_m1
		// @017: ixor
		// @018: if_icmpne @01F
		// @01B: goto @023
		// @01E: athrow
		// @01F: getstatic java.lang.String game.C_100155_dc.field_105347_f
		// @022: areturn
		// @023: aload_2
		// @024: bipush 126 (0x7E)
		// @026: invokestatic game.C_100075_uj.func_100640_a(java.lang.String, int)game.C_100061_dh
		// @029: astore #4
		// @02B: aconst_null
		// @02C: aload #4
		// @02E: if_acmpne @043
		// @031: sipush -30945 (0x871F)
		// @034: iconst_1
		// @035: anewarray java.lang.String
		// @038: dup
		// @039: iconst_0
		// @03A: aload_2
		// @03B: aastore
		// @03C: getstatic java.lang.String game.C_100069_vb.field_104354_f
		// @03F: invokestatic game.C_100132_td.func_104965_a(int, java.lang.String[], java.lang.String)java.lang.String
		// @042: areturn
		// @043: aload #4
		// @045: bipush 45 (0x2D)
		// @047: invokevirtual game.C_100061_dh.func_100583_c(int)void
		// @04A: aload #4
		// @04C: bipush 8 (0x08)
		// @04E: invokevirtual game.C_100061_dh.func_101479_c(byte)void
		// @051: getstatic int game.C_100316_lc.field_102407_A
		// @054: iconst_1
		// @055: isub
		// @056: putstatic int game.C_100316_lc.field_102407_A
		// @059: getstatic game.C_100278_nd game.C_100115_ej.field_102043_Yb
		// @05C: astore #5
		// @05E: iload_3
		// @05F: bipush 78 (0x4E)
		// @061: if_icmpge @06D
		// @064: bipush 114 (0x72)
		// @066: putstatic int game.C_100269_ml.field_101127_j
		// @069: goto @06D
		// @06C: athrow
		// @06D: aload #5
		// @06F: iload_0
		// @070: bipush 113 (0x71)
		// @072: invokevirtual game.C_100278_nd.func_101189_h(int, int)void
		// @075: aload #5
		// @077: dup
		// @078: getfield int game.C_100278_nd.field_101177_n
		// @07B: iconst_1
		// @07C: iadd
		// @07D: putfield int game.C_100278_nd.field_101177_n
		// @080: aload #5
		// @082: getfield int game.C_100278_nd.field_101177_n
		// @085: istore #6
		// @087: aload #5
		// @089: sipush 7838 (0x1E9E)
		// @08C: iconst_3
		// @08D: invokevirtual game.C_100278_nd.func_101169_f(int, int)void
		// @090: aload #5
		// @092: sipush -28365 (0x9133)
		// @095: aload_1
		// @096: invokevirtual game.C_100278_nd.func_101167_a(int, java.lang.String)void
		// @099: aload #5
		// @09B: iload #6
		// @09D: ineg
		// @09E: aload #5
		// @0A0: getfield int game.C_100278_nd.field_101177_n
		// @0A3: iadd
		// @0A4: bipush -94 (0xA2)
		// @0A6: invokevirtual game.C_100278_nd.func_101139_c(int, byte)void
		// @0A9: aconst_null
		// @0AA: areturn
		// @0AB: astore #4
		// @0AD: aload #4
		// @0AF: new java.lang.StringBuilder
		// @0B2: dup
		// @0B3: invokespecial java.lang.StringBuilder.<init>()void
		// @0B6: getstatic java.lang.String[] game.C_100269_ml.field_101128_z
		// @0B9: iconst_3
		// @0BA: aaload
		// @0BB: invokevirtual java.lang.StringBuilder.append(java.lang.String)java.lang.StringBuilder
		// @0BE: iload_0
		// @0BF: invokevirtual java.lang.StringBuilder.append(int)java.lang.StringBuilder
		// @0C2: bipush 44 (0x2C)
		// @0C4: invokevirtual java.lang.StringBuilder.append(char)java.lang.StringBuilder
		// @0C7: aload_1
		// @0C8: ifnull @0D4
		// @0CB: getstatic java.lang.String[] game.C_100269_ml.field_101128_z
		// @0CE: iconst_2
		// @0CF: aaload
		// @0D0: goto @0D9
		// @0D3: athrow
		// @0D4: getstatic java.lang.String[] game.C_100269_ml.field_101128_z
		// @0D7: iconst_1
		// @0D8: aaload
		// @0D9: invokevirtual java.lang.StringBuilder.append(java.lang.String)java.lang.StringBuilder
		// @0DC: bipush 44 (0x2C)
		// @0DE: invokevirtual java.lang.StringBuilder.append(char)java.lang.StringBuilder
		// @0E1: aload_2
		// @0E2: ifnull @0EE
		// @0E5: getstatic java.lang.String[] game.C_100269_ml.field_101128_z
		// @0E8: iconst_2
		// @0E9: aaload
		// @0EA: goto @0F3
		// @0ED: athrow
		// @0EE: getstatic java.lang.String[] game.C_100269_ml.field_101128_z
		// @0F1: iconst_1
		// @0F2: aaload
		// @0F3: invokevirtual java.lang.StringBuilder.append(java.lang.String)java.lang.StringBuilder
		// @0F6: bipush 44 (0x2C)
		// @0F8: invokevirtual java.lang.StringBuilder.append(char)java.lang.StringBuilder
		// @0FB: iload_3
		// @0FC: invokevirtual java.lang.StringBuilder.append(int)java.lang.StringBuilder
		// @0FF: bipush 41 (0x29)
		// @101: invokevirtual java.lang.StringBuilder.append(char)java.lang.StringBuilder
		// @104: invokevirtual java.lang.StringBuilder.toString()java.lang.String
		// @107: invokestatic game.C_100181_cf.func_105695_a(java.lang.Throwable, java.lang.String)game.C_100170_cm
		// @10A: athrow
	}
	
	static final Frame func_101115_a(byte arg0, int arg1, C_100201_qj arg2, int arg3, int arg4, int arg5)
	{
		// @000: getstatic int game.SteelSentinels.field_105275_O
		// @003: istore #9
		// @005: aload_2
		// @006: iconst_1
		// @007: invokevirtual game.C_100201_qj.func_105867_a(boolean)boolean
		// @00A: ifeq @011
		// @00D: goto @013
		// @010: athrow
		// @011: aconst_null
		// @012: areturn
		// @013: iconst_0
		// @014: iload_3
		// @015: if_icmpeq @01C
		// @018: goto @0BB
		// @01B: athrow
		// @01C: iconst_1
		// @01D: aload_2
		// @01E: invokestatic game.C_100301_kb.func_107084_a(boolean, game.C_100201_qj)game.C_100285_nk[]
		// @021: astore #6
		// @023: aconst_null
		// @024: aload #6
		// @026: if_acmpeq @02D
		// @029: goto @02F
		// @02C: athrow
		// @02D: aconst_null
		// @02E: areturn
		// @02F: iconst_0
		// @030: istore #7
		// @032: iconst_0
		// @033: istore #8
		// @035: aload #6
		// @037: arraylength
		// @038: iload #8
		// @03A: if_icmple @0B1
		// @03D: aload #6
		// @03F: iload #8
		// @041: aaload
		// @042: getfield int game.C_100285_nk.field_106780_g
		// @045: iload #9
		// @047: ifne @0B3
		// @04A: iload_1
		// @04B: if_icmpne @0A9
		// @04E: goto @052
		// @051: athrow
		// @052: iload #4
		// @054: iconst_m1
		// @055: ixor
		// @056: aload #6
		// @058: iload #8
		// @05A: aaload
		// @05B: getfield int game.C_100285_nk.field_106789_i
		// @05E: iconst_m1
		// @05F: ixor
		// @060: if_icmpne @0A9
		// @063: goto @067
		// @066: athrow
		// @067: iconst_m1
		// @068: iload #5
		// @06A: iconst_m1
		// @06B: ixor
		// @06C: if_icmpeq @088
		// @06F: goto @073
		// @072: athrow
		// @073: iload #5
		// @075: aload #6
		// @077: iload #8
		// @079: aaload
		// @07A: getfield int game.C_100285_nk.field_106781_d
		// @07D: if_icmpeq @088
		// @080: goto @084
		// @083: athrow
		// @084: goto @0A9
		// @087: athrow
		// @088: iload #7
		// @08A: ifeq @09D
		// @08D: aload #6
		// @08F: iload #8
		// @091: aaload
		// @092: getfield int game.C_100285_nk.field_106785_a
		// @095: iload_3
		// @096: if_icmple @0A9
		// @099: goto @09D
		// @09C: athrow
		// @09D: iconst_1
		// @09E: istore #7
		// @0A0: aload #6
		// @0A2: iload #8
		// @0A4: aaload
		// @0A5: getfield int game.C_100285_nk.field_106785_a
		// @0A8: istore_3
		// @0A9: iinc #8 +1
		// @0AC: iload #9
		// @0AE: ifeq @035
		// @0B1: iload #7
		// @0B3: ifeq @0B9
		// @0B6: goto @0BB
		// @0B9: aconst_null
		// @0BA: areturn
		// @0BB: aload_2
		// @0BC: bipush 6 (0x06)
		// @0BE: iload #4
		// @0C0: iload_3
		// @0C1: iload_1
		// @0C2: iload #5
		// @0C4: invokevirtual game.C_100201_qj.func_105869_a(int, int, int, int, int)game.C_100331_ie
		// @0C7: astore #6
		// @0C9: aload #6
		// @0CB: getfield int game.C_100331_ie.field_107293_f
		// @0CE: iconst_m1
		// @0CF: ixor
		// @0D0: iconst_m1
		// @0D1: if_icmpne @0E1
		// @0D4: ldc2_w 10
		// @0D7: bipush -123 (0x85)
		// @0D9: invokestatic game.C_100138_bo.func_100396_a(long, int)void
		// @0DC: iload #9
		// @0DE: ifeq @0C9
		// @0E1: aload #6
		// @0E3: getfield java.lang.Object game.C_100331_ie.field_107294_g
		// @0E6: checkcast java.awt.Frame
		// @0E9: astore #7
		// @0EB: bipush -80 (0xB0)
		// @0ED: iload_0
		// @0EE: bipush 47 (0x2F)
		// @0F0: isub
		// @0F1: bipush 62 (0x3E)
		// @0F3: idiv
		// @0F4: irem
		// @0F5: istore #8
		// @0F7: aload #7
		// @0F9: ifnull @100
		// @0FC: goto @102
		// @0FF: athrow
		// @100: aconst_null
		// @101: areturn
		// @102: aload #6
		// @104: getfield int game.C_100331_ie.field_107293_f
		// @107: iconst_2
		// @108: if_icmpne @116
		// @10B: aload_2
		// @10C: aload #7
		// @10E: sipush 8192 (0x2000)
		// @111: invokestatic game.C_100110_s.func_104842_a(game.C_100201_qj, java.awt.Frame, int)void
		// @114: aconst_null
		// @115: areturn
		// @116: aload #7
		// @118: areturn
		// @119: astore #6
		// @11B: aload #6
		// @11D: new java.lang.StringBuilder
		// @120: dup
		// @121: invokespecial java.lang.StringBuilder.<init>()void
		// @124: getstatic java.lang.String[] game.C_100269_ml.field_101128_z
		// @127: iconst_4
		// @128: aaload
		// @129: invokevirtual java.lang.StringBuilder.append(java.lang.String)java.lang.StringBuilder
		// @12C: iload_0
		// @12D: invokevirtual java.lang.StringBuilder.append(int)java.lang.StringBuilder
		// @130: bipush 44 (0x2C)
		// @132: invokevirtual java.lang.StringBuilder.append(char)java.lang.StringBuilder
		// @135: iload_1
		// @136: invokevirtual java.lang.StringBuilder.append(int)java.lang.StringBuilder
		// @139: bipush 44 (0x2C)
		// @13B: invokevirtual java.lang.StringBuilder.append(char)java.lang.StringBuilder
		// @13E: aload_2
		// @13F: ifnull @14B
		// @142: getstatic java.lang.String[] game.C_100269_ml.field_101128_z
		// @145: iconst_2
		// @146: aaload
		// @147: goto @150
		// @14A: athrow
		// @14B: getstatic java.lang.String[] game.C_100269_ml.field_101128_z
		// @14E: iconst_1
		// @14F: aaload
		// @150: invokevirtual java.lang.StringBuilder.append(java.lang.String)java.lang.StringBuilder
		// @153: bipush 44 (0x2C)
		// @155: invokevirtual java.lang.StringBuilder.append(char)java.lang.StringBuilder
		// @158: iload_3
		// @159: invokevirtual java.lang.StringBuilder.append(int)java.lang.StringBuilder
		// @15C: bipush 44 (0x2C)
		// @15E: invokevirtual java.lang.StringBuilder.append(char)java.lang.StringBuilder
		// @161: iload #4
		// @163: invokevirtual java.lang.StringBuilder.append(int)java.lang.StringBuilder
		// @166: bipush 44 (0x2C)
		// @168: invokevirtual java.lang.StringBuilder.append(char)java.lang.StringBuilder
		// @16B: iload #5
		// @16D: invokevirtual java.lang.StringBuilder.append(int)java.lang.StringBuilder
		// @170: bipush 41 (0x29)
		// @172: invokevirtual java.lang.StringBuilder.append(char)java.lang.StringBuilder
		// @175: invokevirtual java.lang.StringBuilder.toString()java.lang.String
		// @178: invokestatic game.C_100181_cf.func_105695_a(java.lang.Throwable, java.lang.String)game.C_100170_cm
		// @17B: athrow
	}
	
	C_100269_ml(C_100037_wb arg0, String arg1)
	{
		// @00: aload_0
		// @01: invokespecial game.C_100158_da.<init>()void
		// @04: aload_0
		// @05: aload_1
		// @06: putfield game.C_100037_wb game.C_100269_ml.field_101126_m
		// @09: aload_0
		// @0A: aload_2
		// @0B: putfield java.lang.String game.C_100269_ml.field_101120_r
		// @0E: goto @5D
		// @11: astore_3
		// @12: aload_3
		// @13: new java.lang.StringBuilder
		// @16: dup
		// @17: invokespecial java.lang.StringBuilder.<init>()void
		// @1A: getstatic java.lang.String[] game.C_100269_ml.field_101128_z
		// @1D: iconst_5
		// @1E: aaload
		// @1F: invokevirtual java.lang.StringBuilder.append(java.lang.String)java.lang.StringBuilder
		// @22: aload_1
		// @23: ifnull @2F
		// @26: getstatic java.lang.String[] game.C_100269_ml.field_101128_z
		// @29: iconst_2
		// @2A: aaload
		// @2B: goto @34
		// @2E: athrow
		// @2F: getstatic java.lang.String[] game.C_100269_ml.field_101128_z
		// @32: iconst_1
		// @33: aaload
		// @34: invokevirtual java.lang.StringBuilder.append(java.lang.String)java.lang.StringBuilder
		// @37: bipush 44 (0x2C)
		// @39: invokevirtual java.lang.StringBuilder.append(char)java.lang.StringBuilder
		// @3C: aload_2
		// @3D: ifnull @49
		// @40: getstatic java.lang.String[] game.C_100269_ml.field_101128_z
		// @43: iconst_2
		// @44: aaload
		// @45: goto @4E
		// @48: athrow
		// @49: getstatic java.lang.String[] game.C_100269_ml.field_101128_z
		// @4C: iconst_1
		// @4D: aaload
		// @4E: invokevirtual java.lang.StringBuilder.append(java.lang.String)java.lang.StringBuilder
		// @51: bipush 41 (0x29)
		// @53: invokevirtual java.lang.StringBuilder.append(char)java.lang.StringBuilder
		// @56: invokevirtual java.lang.StringBuilder.toString()java.lang.String
		// @59: invokestatic game.C_100181_cf.func_105695_a(java.lang.Throwable, java.lang.String)game.C_100170_cm
		// @5C: athrow
		// @5D: return
	}
	
	static
	{
		// @00: bipush 6 (0x06)
		// @02: anewarray java.lang.String
		// @05: dup
		// @06: iconst_0
		// @07: ldc "n0e{M"
		// @09: invokestatic game.C_100269_ml.func_101117_z(java.lang.String)char[]
		// @0C: invokestatic game.C_100269_ml.func_101116_z(char[])java.lang.String
		// @0F: aastore
		// @10: dup
		// @11: iconst_1
		// @12: ldc "m)'V"
		// @14: invokestatic game.C_100269_ml.func_101117_z(java.lang.String)char[]
		// @17: invokestatic game.C_100269_ml.func_101116_z(char[])java.lang.String
		// @1A: aastore
		// @1B: dup
		// @1C: iconst_2
		// @1D: ldc "xre\u0014\u0018"
		// @1F: invokestatic game.C_100269_ml.func_101117_z(java.lang.String)char[]
		// @22: invokestatic game.C_100269_ml.func_101116_z(char[])java.lang.String
		// @25: aastore
		// @26: dup
		// @27: iconst_3
		// @28: ldc "n0eyM"
		// @2A: invokestatic game.C_100269_ml.func_101117_z(java.lang.String)char[]
		// @2D: invokestatic game.C_100269_ml.func_101116_z(char[])java.lang.String
		// @30: aastore
		// @31: dup
		// @32: iconst_4
		// @33: ldc "n0exM"
		// @35: invokestatic game.C_100269_ml.func_101117_z(java.lang.String)char[]
		// @38: invokestatic game.C_100269_ml.func_101116_z(char[])java.lang.String
		// @3B: aastore
		// @3C: dup
		// @3D: iconst_5
		// @3E: ldc "n0e\u0006\u000cm5?\u0004M"
		// @40: invokestatic game.C_100269_ml.func_101117_z(java.lang.String)char[]
		// @43: invokestatic game.C_100269_ml.func_101116_z(char[])java.lang.String
		// @46: aastore
		// @47: putstatic java.lang.String[] game.C_100269_ml.field_101128_z
		// @4A: iconst_2
		// @4B: putstatic int game.C_100269_ml.field_101127_j
		// @4E: ldc "T4$\u001a\u0006b2kP\nj2"
		// @50: invokestatic game.C_100269_ml.func_101117_z(java.lang.String)char[]
		// @53: invokestatic game.C_100269_ml.func_101116_z(char[])java.lang.String
		// @56: putstatic java.lang.String game.C_100269_ml.field_101122_p
		// @59: iconst_5
		// @5A: newarray int[]
		// @5C: putstatic int[] game.C_100269_ml.field_101123_n
		// @5F: new game.C_100217_ao
		// @62: dup
		// @63: iconst_0
		// @64: iconst_2
		// @65: iconst_2
		// @66: iconst_1
		// @67: invokespecial game.C_100217_ao.<init>(int, int, int, int)void
		// @6A: putstatic game.C_100217_ao game.C_100269_ml.field_101121_q
		// @6D: return
	}
	
	private static char[] func_101117_z(String arg0)
	{
		// @00: aload_0
		// @01: invokevirtual java.lang.String.toCharArray()char[]
		// @04: dup
		// @05: arraylength
		// @06: iconst_2
		// @07: if_icmpge @13
		// @0A: dup
		// @0B: iconst_0
		// @0C: dup2
		// @0D: caload
		// @0E: bipush 101 (0x65)
		// @10: ixor
		// @11: i2c
		// @12: castore
		// @13: areturn
	}
	
	private static String func_101116_z(char[] arg0)
	{
		// @00: aload_0
		// @01: dup
		// @02: arraylength
		// @03: swap
		// @04: iconst_0
		// @05: istore_1
		// @06: goto @4B
		// @09: dup
		// @0A: iload_1
		// @0B: dup2
		// @0C: caload
		// @0D: iload_1
		// @0E: iconst_5
		// @0F: irem
		// @10: tableswitch def: @43, for 0: @30, for 1: @34, for 2: @39, for 3: @3E
		// @30: iconst_3
		// @31: goto @45
		// @34: bipush 92 (0x5C)
		// @36: goto @45
		// @39: bipush 75 (0x4B)
		// @3B: goto @45
		// @3E: bipush 58 (0x3A)
		// @40: goto @45
		// @43: bipush 101 (0x65)
		// @45: ixor
		// @46: i2c
		// @47: castore
		// @48: iinc #1 +1
		// @4B: swap
		// @4C: dup_x1
		// @4D: iload_1
		// @4E: if_icmpgt @09
		// @51: new java.lang.String
		// @54: dup_x1
		// @55: swap
		// @56: invokespecial java.lang.String.<init>(char[])void
		// @59: invokevirtual java.lang.String.intern()java.lang.String
		// @5C: areturn
	}
}
