package game;

final class C_100066_dl extends C_100325_id
{
	static C_100037_wb[] field_101640_v;
	private String[] field_101633_A;
	private int[] field_101631_F;
	static String field_101634_B;
	static int[] field_101632_G;
	static int[] field_101635_C;
	static C_100268_mk field_101642_t;
	static byte[][] field_101629_D;
	static int field_101646_x;
	private int[][] field_101630_E;
	static boolean field_101637_I;
	int[] field_101643_s;
	static C_100067_vd[] field_101641_u;
	static C_100302_ka field_101639_w;
	static String field_101645_y;
	static String[] field_101644_z;
	static int field_101636_H;
	private static final String[] field_101638_J;
	
	public static void func_101624_i(int arg0)
	{
		// @00: aconst_null
		// @01: putstatic java.lang.String game.C_100066_dl.field_101634_B
		// @04: aconst_null
		// @05: putstatic game.C_100302_ka game.C_100066_dl.field_101639_w
		// @08: aconst_null
		// @09: putstatic game.C_100067_vd[] game.C_100066_dl.field_101641_u
		// @0C: aconst_null
		// @0D: putstatic java.lang.String[] game.C_100066_dl.field_101644_z
		// @10: aconst_null
		// @11: putstatic game.C_100037_wb[] game.C_100066_dl.field_101640_v
		// @14: aconst_null
		// @15: putstatic game.C_100268_mk game.C_100066_dl.field_101642_t
		// @18: bipush 118 (0x76)
		// @1A: bipush 74 (0x4A)
		// @1C: iload_0
		// @1D: isub
		// @1E: bipush 33 (0x21)
		// @20: idiv
		// @21: irem
		// @22: istore_1
		// @23: aconst_null
		// @24: checkcast byte[][]
		// @27: putstatic byte[][] game.C_100066_dl.field_101629_D
		// @2A: aconst_null
		// @2B: putstatic int[] game.C_100066_dl.field_101632_G
		// @2E: aconst_null
		// @2F: putstatic int[] game.C_100066_dl.field_101635_C
		// @32: aconst_null
		// @33: putstatic java.lang.String game.C_100066_dl.field_101645_y
		// @36: goto @5B
		// @39: astore_1
		// @3A: aload_1
		// @3B: new java.lang.StringBuilder
		// @3E: dup
		// @3F: invokespecial java.lang.StringBuilder.<init>()void
		// @42: getstatic java.lang.String[] game.C_100066_dl.field_101638_J
		// @45: bipush 6 (0x06)
		// @47: aaload
		// @48: invokevirtual java.lang.StringBuilder.append(java.lang.String)java.lang.StringBuilder
		// @4B: iload_0
		// @4C: invokevirtual java.lang.StringBuilder.append(int)java.lang.StringBuilder
		// @4F: bipush 41 (0x29)
		// @51: invokevirtual java.lang.StringBuilder.append(char)java.lang.StringBuilder
		// @54: invokevirtual java.lang.StringBuilder.toString()java.lang.String
		// @57: invokestatic game.C_100181_cf.func_105695_a(java.lang.Throwable, java.lang.String)game.C_100170_cm
		// @5A: athrow
		// @5B: return
	}
	
	static final void func_101622_a(int arg0, byte arg1, int arg2)
	{
		// @00: getstatic game.C_100278_nd game.C_100115_ej.field_102043_Yb
		// @03: astore_3
		// @04: aload_3
		// @05: iload_0
		// @06: bipush 125 (0x7D)
		// @08: invokevirtual game.C_100278_nd.func_101189_h(int, int)void
		// @0B: aload_3
		// @0C: sipush 7838 (0x1E9E)
		// @0F: iconst_3
		// @10: invokevirtual game.C_100278_nd.func_101169_f(int, int)void
		// @13: aload_3
		// @14: sipush 7838 (0x1E9E)
		// @17: bipush 9 (0x09)
		// @19: invokevirtual game.C_100278_nd.func_101169_f(int, int)void
		// @1C: aload_3
		// @1D: iload_2
		// @1E: bipush 65 (0x41)
		// @20: invokevirtual game.C_100278_nd.func_101141_d(int, byte)void
		// @23: iload_1
		// @24: bipush -61 (0xC3)
		// @26: if_icmplt @34
		// @29: aconst_null
		// @2A: checkcast game.C_100037_wb[]
		// @2D: putstatic game.C_100037_wb[] game.C_100066_dl.field_101640_v
		// @30: goto @34
		// @33: athrow
		// @34: goto @6B
		// @37: astore_3
		// @38: aload_3
		// @39: new java.lang.StringBuilder
		// @3C: dup
		// @3D: invokespecial java.lang.StringBuilder.<init>()void
		// @40: getstatic java.lang.String[] game.C_100066_dl.field_101638_J
		// @43: bipush 10 (0x0A)
		// @45: aaload
		// @46: invokevirtual java.lang.StringBuilder.append(java.lang.String)java.lang.StringBuilder
		// @49: iload_0
		// @4A: invokevirtual java.lang.StringBuilder.append(int)java.lang.StringBuilder
		// @4D: bipush 44 (0x2C)
		// @4F: invokevirtual java.lang.StringBuilder.append(char)java.lang.StringBuilder
		// @52: iload_1
		// @53: invokevirtual java.lang.StringBuilder.append(int)java.lang.StringBuilder
		// @56: bipush 44 (0x2C)
		// @58: invokevirtual java.lang.StringBuilder.append(char)java.lang.StringBuilder
		// @5B: iload_2
		// @5C: invokevirtual java.lang.StringBuilder.append(int)java.lang.StringBuilder
		// @5F: bipush 41 (0x29)
		// @61: invokevirtual java.lang.StringBuilder.append(char)java.lang.StringBuilder
		// @64: invokevirtual java.lang.StringBuilder.toString()java.lang.String
		// @67: invokestatic game.C_100181_cf.func_105695_a(java.lang.Throwable, java.lang.String)game.C_100170_cm
		// @6A: athrow
		// @6B: return
	}
	
	static final void func_101628_j(int arg0)
	{
		// @00: iconst_0
		// @01: putstatic boolean game.C_100272_mn.field_102435_K
		// @04: getstatic game.C_100278_nd game.C_100288_jn.field_106839_f
		// @07: iconst_0
		// @08: invokevirtual game.C_100278_nd.func_101156_c(boolean)int
		// @0B: iconst_m1
		// @0C: ixor
		// @0D: iload_0
		// @0E: if_icmpne @16
		// @11: iconst_1
		// @12: goto @17
		// @15: athrow
		// @16: iconst_0
		// @17: putstatic boolean game.C_100164_se.field_105449_g
		// @1A: goto @3E
		// @1D: astore_1
		// @1E: aload_1
		// @1F: new java.lang.StringBuilder
		// @22: dup
		// @23: invokespecial java.lang.StringBuilder.<init>()void
		// @26: getstatic java.lang.String[] game.C_100066_dl.field_101638_J
		// @29: iconst_5
		// @2A: aaload
		// @2B: invokevirtual java.lang.StringBuilder.append(java.lang.String)java.lang.StringBuilder
		// @2E: iload_0
		// @2F: invokevirtual java.lang.StringBuilder.append(int)java.lang.StringBuilder
		// @32: bipush 41 (0x29)
		// @34: invokevirtual java.lang.StringBuilder.append(char)java.lang.StringBuilder
		// @37: invokevirtual java.lang.StringBuilder.toString()java.lang.String
		// @3A: invokestatic game.C_100181_cf.func_105695_a(java.lang.Throwable, java.lang.String)game.C_100170_cm
		// @3D: athrow
		// @3E: return
	}
	
	static final void func_101627_a(int arg0, int[] arg1, int arg2, int arg3, int arg4, int arg5, int arg6, int arg7, int arg8, int arg9)
	{
		// @000: getstatic int game.SteelSentinels.field_105275_O
		// @003: istore #16
		// @005: iconst_0
		// @006: iinc #5 +255
		// @009: iload #5
		// @00B: if_icmpgt @07D
		// @00E: aload_1
		// @00F: astore #10
		// @011: iload #4
		// @013: istore #11
		// @015: iload #8
		// @017: istore #12
		// @019: iload #6
		// @01B: istore #13
		// @01D: iload #7
		// @01F: istore #14
		// @021: aload #10
		// @023: iload #11
		// @025: iaload
		// @026: ldc -1266953279 (0xb47bd3c1)
		// @028: ishr
		// @029: ldc 8355711 (0x7f7f7f)
		// @02B: iand
		// @02C: istore #15
		// @02E: aload #10
		// @030: iload #11
		// @032: iload #15
		// @034: iload #14
		// @036: ldc 33488633 (0x1fefef9)
		// @038: invokestatic game.C_100256_pk.func_100449_a(int, int)int
		// @03B: ldc -583068271 (0xdd3f1591)
		// @03D: ishr
		// @03E: ineg
		// @03F: ldc 33423360 (0x1fe0000)
		// @041: iload #12
		// @043: invokestatic game.C_100256_pk.func_100449_a(int, int)int
		// @046: ldc -2082819327 (0x83dab301)
		// @048: ishr
		// @049: ineg
		// @04A: ldc 65280 (0xff00)
		// @04C: iload #13
		// @04E: ldc 447699529 (0x1aaf5a49)
		// @050: ishr
		// @051: invokestatic game.C_100256_pk.func_100449_a(int, int)int
		// @054: ineg
		// @055: iadd
		// @056: iadd
		// @057: isub
		// @058: iastore
		// @059: iload #7
		// @05B: iload_3
		// @05C: iadd
		// @05D: istore #7
		// @05F: iload #6
		// @061: iload_0
		// @062: iadd
		// @063: istore #6
		// @065: iload #8
		// @067: iload #9
		// @069: iadd
		// @06A: istore #8
		// @06C: iinc #4 +1
		// @06F: iload #16
		// @071: ifne @0A0
		// @074: iload #16
		// @076: ifeq @005
		// @079: goto @07D
		// @07C: athrow
		// @07D: iload_2
		// @07E: ldc -1266953279 (0xb47bd3c1)
		// @080: if_icmpeq @0A0
		// @083: bipush -70 (0xBA)
		// @085: aconst_null
		// @086: checkcast int[]
		// @089: bipush 38 (0x26)
		// @08B: bipush 96 (0x60)
		// @08D: bipush 16 (0x10)
		// @08F: bipush -47 (0xD1)
		// @091: bipush 104 (0x68)
		// @093: bipush 70 (0x46)
		// @095: bipush 48 (0x30)
		// @097: bipush 110 (0x6E)
		// @099: invokestatic game.C_100066_dl.func_101627_a(int, int[], int, int, int, int, int, int, int, int)void
		// @09C: goto @0A0
		// @09F: athrow
		// @0A0: goto @12E
		// @0A3: astore #10
		// @0A5: aload #10
		// @0A7: new java.lang.StringBuilder
		// @0AA: dup
		// @0AB: invokespecial java.lang.StringBuilder.<init>()void
		// @0AE: getstatic java.lang.String[] game.C_100066_dl.field_101638_J
		// @0B1: iconst_4
		// @0B2: aaload
		// @0B3: invokevirtual java.lang.StringBuilder.append(java.lang.String)java.lang.StringBuilder
		// @0B6: iload_0
		// @0B7: invokevirtual java.lang.StringBuilder.append(int)java.lang.StringBuilder
		// @0BA: bipush 44 (0x2C)
		// @0BC: invokevirtual java.lang.StringBuilder.append(char)java.lang.StringBuilder
		// @0BF: aload_1
		// @0C0: ifnull @0CC
		// @0C3: getstatic java.lang.String[] game.C_100066_dl.field_101638_J
		// @0C6: iconst_1
		// @0C7: aaload
		// @0C8: goto @0D1
		// @0CB: athrow
		// @0CC: getstatic java.lang.String[] game.C_100066_dl.field_101638_J
		// @0CF: iconst_3
		// @0D0: aaload
		// @0D1: invokevirtual java.lang.StringBuilder.append(java.lang.String)java.lang.StringBuilder
		// @0D4: bipush 44 (0x2C)
		// @0D6: invokevirtual java.lang.StringBuilder.append(char)java.lang.StringBuilder
		// @0D9: iload_2
		// @0DA: invokevirtual java.lang.StringBuilder.append(int)java.lang.StringBuilder
		// @0DD: bipush 44 (0x2C)
		// @0DF: invokevirtual java.lang.StringBuilder.append(char)java.lang.StringBuilder
		// @0E2: iload_3
		// @0E3: invokevirtual java.lang.StringBuilder.append(int)java.lang.StringBuilder
		// @0E6: bipush 44 (0x2C)
		// @0E8: invokevirtual java.lang.StringBuilder.append(char)java.lang.StringBuilder
		// @0EB: iload #4
		// @0ED: invokevirtual java.lang.StringBuilder.append(int)java.lang.StringBuilder
		// @0F0: bipush 44 (0x2C)
		// @0F2: invokevirtual java.lang.StringBuilder.append(char)java.lang.StringBuilder
		// @0F5: iload #5
		// @0F7: invokevirtual java.lang.StringBuilder.append(int)java.lang.StringBuilder
		// @0FA: bipush 44 (0x2C)
		// @0FC: invokevirtual java.lang.StringBuilder.append(char)java.lang.StringBuilder
		// @0FF: iload #6
		// @101: invokevirtual java.lang.StringBuilder.append(int)java.lang.StringBuilder
		// @104: bipush 44 (0x2C)
		// @106: invokevirtual java.lang.StringBuilder.append(char)java.lang.StringBuilder
		// @109: iload #7
		// @10B: invokevirtual java.lang.StringBuilder.append(int)java.lang.StringBuilder
		// @10E: bipush 44 (0x2C)
		// @110: invokevirtual java.lang.StringBuilder.append(char)java.lang.StringBuilder
		// @113: iload #8
		// @115: invokevirtual java.lang.StringBuilder.append(int)java.lang.StringBuilder
		// @118: bipush 44 (0x2C)
		// @11A: invokevirtual java.lang.StringBuilder.append(char)java.lang.StringBuilder
		// @11D: iload #9
		// @11F: invokevirtual java.lang.StringBuilder.append(int)java.lang.StringBuilder
		// @122: bipush 41 (0x29)
		// @124: invokevirtual java.lang.StringBuilder.append(char)java.lang.StringBuilder
		// @127: invokevirtual java.lang.StringBuilder.toString()java.lang.String
		// @12A: invokestatic game.C_100181_cf.func_105695_a(java.lang.Throwable, java.lang.String)game.C_100170_cm
		// @12D: athrow
		// @12E: return
	}
	
	final void func_101621_a(C_100280_nf arg0, boolean arg1)
	{
		// @00: getstatic int game.SteelSentinels.field_105275_O
		// @03: istore #4
		// @05: iload_2
		// @06: ifeq @14
		// @09: aconst_null
		// @0A: checkcast game.C_100268_mk
		// @0D: putstatic game.C_100268_mk game.C_100066_dl.field_101642_t
		// @10: goto @14
		// @13: athrow
		// @14: aload_1
		// @15: iconst_0
		// @16: invokevirtual game.C_100280_nf.func_101156_c(boolean)int
		// @19: istore_3
		// @1A: iload_3
		// @1B: ifeq @34
		// @1E: aload_0
		// @1F: iload_3
		// @20: aload_1
		// @21: bipush 97 (0x61)
		// @23: invokespecial game.C_100066_dl.func_101619_a(int, game.C_100280_nf, byte)void
		// @26: iload #4
		// @28: ifne @73
		// @2B: iload #4
		// @2D: ifeq @14
		// @30: goto @34
		// @33: athrow
		// @34: goto @73
		// @37: astore_3
		// @38: aload_3
		// @39: new java.lang.StringBuilder
		// @3C: dup
		// @3D: invokespecial java.lang.StringBuilder.<init>()void
		// @40: getstatic java.lang.String[] game.C_100066_dl.field_101638_J
		// @43: bipush 9 (0x09)
		// @45: aaload
		// @46: invokevirtual java.lang.StringBuilder.append(java.lang.String)java.lang.StringBuilder
		// @49: aload_1
		// @4A: ifnull @56
		// @4D: getstatic java.lang.String[] game.C_100066_dl.field_101638_J
		// @50: iconst_1
		// @51: aaload
		// @52: goto @5B
		// @55: athrow
		// @56: getstatic java.lang.String[] game.C_100066_dl.field_101638_J
		// @59: iconst_3
		// @5A: aaload
		// @5B: invokevirtual java.lang.StringBuilder.append(java.lang.String)java.lang.StringBuilder
		// @5E: bipush 44 (0x2C)
		// @60: invokevirtual java.lang.StringBuilder.append(char)java.lang.StringBuilder
		// @63: iload_2
		// @64: invokevirtual java.lang.StringBuilder.append(boolean)java.lang.StringBuilder
		// @67: bipush 41 (0x29)
		// @69: invokevirtual java.lang.StringBuilder.append(char)java.lang.StringBuilder
		// @6C: invokevirtual java.lang.StringBuilder.toString()java.lang.String
		// @6F: invokestatic game.C_100181_cf.func_105695_a(java.lang.Throwable, java.lang.String)game.C_100170_cm
		// @72: athrow
		// @73: return
	}
	
	final String func_101620_k(int arg0)
	{
		// @00: getstatic int game.SteelSentinels.field_105275_O
		// @03: istore #4
		// @05: new java.lang.StringBuilder
		// @08: dup
		// @09: bipush 80 (0x50)
		// @0B: invokespecial java.lang.StringBuilder.<init>(int)void
		// @0E: astore_2
		// @0F: iload_1
		// @10: bipush 19 (0x13)
		// @12: if_icmpge @1A
		// @15: aconst_null
		// @16: checkcast java.lang.String
		// @19: areturn
		// @1A: aload_0
		// @1B: getfield java.lang.String[] game.C_100066_dl.field_101633_A
		// @1E: ifnull @25
		// @21: goto @28
		// @24: athrow
		// @25: ldc ""
		// @27: areturn
		// @28: aload_2
		// @29: aload_0
		// @2A: getfield java.lang.String[] game.C_100066_dl.field_101633_A
		// @2D: iconst_0
		// @2E: aaload
		// @2F: invokevirtual java.lang.StringBuilder.append(java.lang.String)java.lang.StringBuilder
		// @32: pop
		// @33: iconst_1
		// @34: istore_3
		// @35: aload_0
		// @36: getfield java.lang.String[] game.C_100066_dl.field_101633_A
		// @39: arraylength
		// @3A: iload_3
		// @3B: if_icmple @65
		// @3E: aload_2
		// @3F: getstatic java.lang.String[] game.C_100066_dl.field_101638_J
		// @42: bipush 8 (0x08)
		// @44: aaload
		// @45: invokevirtual java.lang.StringBuilder.append(java.lang.String)java.lang.StringBuilder
		// @48: pop
		// @49: aload_2
		// @4A: aload_0
		// @4B: getfield java.lang.String[] game.C_100066_dl.field_101633_A
		// @4E: iload_3
		// @4F: aaload
		// @50: invokevirtual java.lang.StringBuilder.append(java.lang.String)java.lang.StringBuilder
		// @53: iload #4
		// @55: ifne @66
		// @58: pop
		// @59: iinc #3 +1
		// @5C: iload #4
		// @5E: ifeq @35
		// @61: goto @65
		// @64: athrow
		// @65: aload_2
		// @66: invokevirtual java.lang.StringBuilder.toString()java.lang.String
		// @69: areturn
		// @6A: astore_2
		// @6B: aload_2
		// @6C: new java.lang.StringBuilder
		// @6F: dup
		// @70: invokespecial java.lang.StringBuilder.<init>()void
		// @73: getstatic java.lang.String[] game.C_100066_dl.field_101638_J
		// @76: bipush 7 (0x07)
		// @78: aaload
		// @79: invokevirtual java.lang.StringBuilder.append(java.lang.String)java.lang.StringBuilder
		// @7C: iload_1
		// @7D: invokevirtual java.lang.StringBuilder.append(int)java.lang.StringBuilder
		// @80: bipush 41 (0x29)
		// @82: invokevirtual java.lang.StringBuilder.append(char)java.lang.StringBuilder
		// @85: invokevirtual java.lang.StringBuilder.toString()java.lang.String
		// @88: invokestatic game.C_100181_cf.func_105695_a(java.lang.Throwable, java.lang.String)game.C_100170_cm
		// @8B: athrow
	}
	
	private final void func_101619_a(int arg0, C_100280_nf arg1, byte arg2)
	{
		// @000: getstatic int game.SteelSentinels.field_105275_O
		// @003: istore #9
		// @005: bipush -2 (0xFE)
		// @007: iload_1
		// @008: iconst_m1
		// @009: ixor
		// @00A: if_icmpeq @106
		// @00D: bipush -3 (0xFD)
		// @00F: iload_1
		// @010: iconst_m1
		// @011: ixor
		// @012: if_icmpne @055
		// @015: goto @019
		// @018: athrow
		// @019: aload_2
		// @01A: iconst_0
		// @01B: invokevirtual game.C_100280_nf.func_101156_c(boolean)int
		// @01E: istore #4
		// @020: aload_0
		// @021: iload #4
		// @023: newarray int[]
		// @025: putfield int[] game.C_100066_dl.field_101643_s
		// @028: iconst_0
		// @029: istore #5
		// @02B: iload #4
		// @02D: iload #5
		// @02F: if_icmple @050
		// @032: aload_0
		// @033: getfield int[] game.C_100066_dl.field_101643_s
		// @036: iload #5
		// @038: aload_2
		// @039: bipush -2 (0xFE)
		// @03B: invokevirtual game.C_100280_nf.func_101143_l(int)int
		// @03E: iastore
		// @03F: iinc #5 +1
		// @042: iload #9
		// @044: ifne @11C
		// @047: iload #9
		// @049: ifeq @02B
		// @04C: goto @050
		// @04F: athrow
		// @050: iload #9
		// @052: ifeq @11C
		// @055: iconst_3
		// @056: iload_1
		// @057: if_icmpeq @06E
		// @05A: goto @05E
		// @05D: athrow
		// @05E: bipush -5 (0xFB)
		// @060: iload_1
		// @061: iconst_m1
		// @062: ixor
		// @063: if_icmpeq @11C
		// @066: goto @06A
		// @069: athrow
		// @06A: goto @11C
		// @06D: athrow
		// @06E: aload_2
		// @06F: iconst_0
		// @070: invokevirtual game.C_100280_nf.func_101156_c(boolean)int
		// @073: istore #4
		// @075: aload_0
		// @076: iload #4
		// @078: anewarray int[]
		// @07B: putfield int[][] game.C_100066_dl.field_101630_E
		// @07E: aload_0
		// @07F: iload #4
		// @081: newarray int[]
		// @083: putfield int[] game.C_100066_dl.field_101631_F
		// @086: iconst_0
		// @087: istore #5
		// @089: iload #5
		// @08B: iload #4
		// @08D: if_icmpge @101
		// @090: aload_2
		// @091: bipush -2 (0xFE)
		// @093: invokevirtual game.C_100280_nf.func_101143_l(int)int
		// @096: istore #6
		// @098: iload #6
		// @09A: bipush 112 (0x70)
		// @09C: invokestatic game.C_100106_ef.func_104743_a(int, byte)game.C_100217_ao
		// @09F: astore #7
		// @0A1: aconst_null
		// @0A2: iload #9
		// @0A4: ifne @126
		// @0A7: aload #7
		// @0A9: if_acmpne @0B4
		// @0AC: goto @0B0
		// @0AF: athrow
		// @0B0: goto @0F9
		// @0B3: athrow
		// @0B4: aload_0
		// @0B5: getfield int[] game.C_100066_dl.field_101631_F
		// @0B8: iload #5
		// @0BA: iload #6
		// @0BC: iastore
		// @0BD: aload_0
		// @0BE: getfield int[][] game.C_100066_dl.field_101630_E
		// @0C1: iload #5
		// @0C3: aload #7
		// @0C5: getfield int game.C_100217_ao.field_106043_k
		// @0C8: newarray int[]
		// @0CA: aastore
		// @0CB: iconst_0
		// @0CC: istore #8
		// @0CE: aload #7
		// @0D0: getfield int game.C_100217_ao.field_106043_k
		// @0D3: iload #8
		// @0D5: if_icmple @0F9
		// @0D8: aload_0
		// @0D9: getfield int[][] game.C_100066_dl.field_101630_E
		// @0DC: iload #5
		// @0DE: aaload
		// @0DF: iload #8
		// @0E1: aload_2
		// @0E2: bipush -2 (0xFE)
		// @0E4: invokevirtual game.C_100280_nf.func_101143_l(int)int
		// @0E7: iastore
		// @0E8: iinc #8 +1
		// @0EB: iload #9
		// @0ED: ifne @0FC
		// @0F0: iload #9
		// @0F2: ifeq @0CE
		// @0F5: goto @0F9
		// @0F8: athrow
		// @0F9: iinc #5 +1
		// @0FC: iload #9
		// @0FE: ifeq @089
		// @101: iload #9
		// @103: ifeq @11C
		// @106: aload_0
		// @107: bipush 119 (0x77)
		// @109: aload_2
		// @10A: sipush 9692 (0x25DC)
		// @10D: invokevirtual game.C_100280_nf.func_101164_f(int)java.lang.String
		// @110: bipush 60 (0x3C)
		// @112: invokestatic game.C_100087_n.func_100679_a(int, java.lang.String, char)java.lang.String[]
		// @115: putfield java.lang.String[] game.C_100066_dl.field_101633_A
		// @118: goto @11C
		// @11B: athrow
		// @11C: iload_3
		// @11D: iconst_3
		// @11E: if_icmpge @12C
		// @121: aconst_null
		// @122: goto @126
		// @125: athrow
		// @126: checkcast game.C_100302_ka
		// @129: putstatic game.C_100302_ka game.C_100066_dl.field_101639_w
		// @12C: goto @175
		// @12F: astore #4
		// @131: aload #4
		// @133: new java.lang.StringBuilder
		// @136: dup
		// @137: invokespecial java.lang.StringBuilder.<init>()void
		// @13A: getstatic java.lang.String[] game.C_100066_dl.field_101638_J
		// @13D: iconst_2
		// @13E: aaload
		// @13F: invokevirtual java.lang.StringBuilder.append(java.lang.String)java.lang.StringBuilder
		// @142: iload_1
		// @143: invokevirtual java.lang.StringBuilder.append(int)java.lang.StringBuilder
		// @146: bipush 44 (0x2C)
		// @148: invokevirtual java.lang.StringBuilder.append(char)java.lang.StringBuilder
		// @14B: aload_2
		// @14C: ifnull @158
		// @14F: getstatic java.lang.String[] game.C_100066_dl.field_101638_J
		// @152: iconst_1
		// @153: aaload
		// @154: goto @15D
		// @157: athrow
		// @158: getstatic java.lang.String[] game.C_100066_dl.field_101638_J
		// @15B: iconst_3
		// @15C: aaload
		// @15D: invokevirtual java.lang.StringBuilder.append(java.lang.String)java.lang.StringBuilder
		// @160: bipush 44 (0x2C)
		// @162: invokevirtual java.lang.StringBuilder.append(char)java.lang.StringBuilder
		// @165: iload_3
		// @166: invokevirtual java.lang.StringBuilder.append(int)java.lang.StringBuilder
		// @169: bipush 41 (0x29)
		// @16B: invokevirtual java.lang.StringBuilder.append(char)java.lang.StringBuilder
		// @16E: invokevirtual java.lang.StringBuilder.toString()java.lang.String
		// @171: invokestatic game.C_100181_cf.func_105695_a(java.lang.Throwable, java.lang.String)game.C_100170_cm
		// @174: athrow
		// @175: return
	}
	
	final void func_101623_d(byte arg0)
	{
		// @00: getstatic int game.SteelSentinels.field_105275_O
		// @03: istore_3
		// @04: aload_0
		// @05: getfield int[] game.C_100066_dl.field_101643_s
		// @08: ifnull @36
		// @0B: iconst_0
		// @0C: istore_2
		// @0D: aload_0
		// @0E: getfield int[] game.C_100066_dl.field_101643_s
		// @11: arraylength
		// @12: iload_2
		// @13: if_icmple @36
		// @16: aload_0
		// @17: getfield int[] game.C_100066_dl.field_101643_s
		// @1A: iload_2
		// @1B: aload_0
		// @1C: getfield int[] game.C_100066_dl.field_101643_s
		// @1F: iload_2
		// @20: iaload
		// @21: ldc 32768 (0x8000)
		// @23: invokestatic game.C_100116_ei.func_104117_a(int, int)int
		// @26: iastore
		// @27: iinc #2 +1
		// @2A: iload_3
		// @2B: ifne @4C
		// @2E: iload_3
		// @2F: ifeq @0D
		// @32: goto @36
		// @35: athrow
		// @36: iload_1
		// @37: bipush 14 (0x0E)
		// @39: if_icmpeq @4C
		// @3C: aload_0
		// @3D: bipush -37 (0xDB)
		// @3F: aconst_null
		// @40: checkcast game.C_100280_nf
		// @43: bipush 124 (0x7C)
		// @45: invokespecial game.C_100066_dl.func_101619_a(int, game.C_100280_nf, byte)void
		// @48: goto @4C
		// @4B: athrow
		// @4C: goto @70
		// @4F: astore_2
		// @50: aload_2
		// @51: new java.lang.StringBuilder
		// @54: dup
		// @55: invokespecial java.lang.StringBuilder.<init>()void
		// @58: getstatic java.lang.String[] game.C_100066_dl.field_101638_J
		// @5B: iconst_0
		// @5C: aaload
		// @5D: invokevirtual java.lang.StringBuilder.append(java.lang.String)java.lang.StringBuilder
		// @60: iload_1
		// @61: invokevirtual java.lang.StringBuilder.append(int)java.lang.StringBuilder
		// @64: bipush 41 (0x29)
		// @66: invokevirtual java.lang.StringBuilder.append(char)java.lang.StringBuilder
		// @69: invokevirtual java.lang.StringBuilder.toString()java.lang.String
		// @6C: invokestatic game.C_100181_cf.func_105695_a(java.lang.Throwable, java.lang.String)game.C_100170_cm
		// @6F: athrow
		// @70: return
	}
	
	static
	{
		// @000: bipush 11 (0x0B)
		// @002: anewarray java.lang.String
		// @005: dup
		// @006: iconst_0
		// @007: ldc "@#-d!"
		// @009: invokestatic game.C_100066_dl.func_101626_z(java.lang.String)char[]
		// @00C: invokestatic game.C_100066_dl.func_101625_z(char[])java.lang.String
		// @00F: aastore
		// @010: dup
		// @011: iconst_1
		// @012: ldc "_a-\u0008t"
		// @014: invokestatic game.C_100066_dl.func_101626_z(java.lang.String)char[]
		// @017: invokestatic game.C_100066_dl.func_101625_z(char[])java.lang.String
		// @01A: aastore
		// @01B: dup
		// @01C: iconst_2
		// @01D: ldc "@#-b!"
		// @01F: invokestatic game.C_100066_dl.func_101626_z(java.lang.String)char[]
		// @022: invokestatic game.C_100066_dl.func_101625_z(char[])java.lang.String
		// @025: aastore
		// @026: dup
		// @027: iconst_3
		// @028: ldc "J:oJ"
		// @02A: invokestatic game.C_100066_dl.func_101626_z(java.lang.String)char[]
		// @02D: invokestatic game.C_100066_dl.func_101625_z(char[])java.lang.String
		// @030: aastore
		// @031: dup
		// @032: iconst_4
		// @033: ldc "@#-c!"
		// @035: invokestatic game.C_100066_dl.func_101626_z(java.lang.String)char[]
		// @038: invokestatic game.C_100066_dl.func_101625_z(char[])java.lang.String
		// @03B: aastore
		// @03C: dup
		// @03D: iconst_5
		// @03E: ldc "@#-a!"
		// @040: invokestatic game.C_100066_dl.func_101626_z(java.lang.String)char[]
		// @043: invokestatic game.C_100066_dl.func_101625_z(char[])java.lang.String
		// @046: aastore
		// @047: dup
		// @048: bipush 6 (0x06)
		// @04A: ldc "@#-g!"
		// @04C: invokestatic game.C_100066_dl.func_101626_z(java.lang.String)char[]
		// @04F: invokestatic game.C_100066_dl.func_101625_z(char[])java.lang.String
		// @052: aastore
		// @053: dup
		// @054: bipush 7 (0x07)
		// @056: ldc "@#-e!"
		// @058: invokestatic game.C_100066_dl.func_101626_z(java.lang.String)char[]
		// @05B: invokestatic game.C_100066_dl.func_101625_z(char[])java.lang.String
		// @05E: aastore
		// @05F: dup
		// @060: bipush 8 (0x08)
		// @062: ldc "\na-"
		// @064: invokestatic game.C_100066_dl.func_101626_z(java.lang.String)char[]
		// @067: invokestatic game.C_100066_dl.func_101625_z(char[])java.lang.String
		// @06A: aastore
		// @06B: dup
		// @06C: bipush 9 (0x09)
		// @06E: ldc "@#-`!"
		// @070: invokestatic game.C_100066_dl.func_101626_z(java.lang.String)char[]
		// @073: invokestatic game.C_100066_dl.func_101625_z(char[])java.lang.String
		// @076: aastore
		// @077: dup
		// @078: bipush 10 (0x0A)
		// @07A: ldc "@#-n!"
		// @07C: invokestatic game.C_100066_dl.func_101626_z(java.lang.String)char[]
		// @07F: invokestatic game.C_100066_dl.func_101625_z(char[])java.lang.String
		// @082: aastore
		// @083: putstatic java.lang.String[] game.C_100066_dl.field_101638_J
		// @086: ldc "e+uGgG*g\u0006]V.jH`J("
		// @088: invokestatic game.C_100066_dl.func_101626_z(java.lang.String)char[]
		// @08B: invokestatic game.C_100066_dl.func_101625_z(char[])java.lang.String
		// @08E: putstatic java.lang.String game.C_100066_dl.field_101634_B
		// @091: iconst_0
		// @092: putstatic boolean game.C_100066_dl.field_101637_I
		// @095: bipush 50 (0x32)
		// @097: anewarray byte[]
		// @09A: putstatic byte[][] game.C_100066_dl.field_101629_D
		// @09D: bipush 10 (0x0A)
		// @09F: newarray int[]
		// @0A1: dup
		// @0A2: iconst_0
		// @0A3: bipush 107 (0x6B)
		// @0A5: iastore
		// @0A6: dup
		// @0A7: iconst_1
		// @0A8: bipush 30 (0x1E)
		// @0AA: iastore
		// @0AB: dup
		// @0AC: iconst_2
		// @0AD: bipush 33 (0x21)
		// @0AF: iastore
		// @0B0: dup
		// @0B1: iconst_3
		// @0B2: bipush 32 (0x20)
		// @0B4: iastore
		// @0B5: dup
		// @0B6: iconst_4
		// @0B7: bipush 26 (0x1A)
		// @0B9: iastore
		// @0BA: dup
		// @0BB: iconst_5
		// @0BC: iconst_m1
		// @0BD: iastore
		// @0BE: dup
		// @0BF: bipush 6 (0x06)
		// @0C1: iconst_m1
		// @0C2: iastore
		// @0C3: dup
		// @0C4: bipush 7 (0x07)
		// @0C6: iconst_m1
		// @0C7: iastore
		// @0C8: dup
		// @0C9: bipush 8 (0x08)
		// @0CB: iconst_m1
		// @0CC: iastore
		// @0CD: dup
		// @0CE: bipush 9 (0x09)
		// @0D0: iconst_m1
		// @0D1: iastore
		// @0D2: putstatic int[] game.C_100066_dl.field_101635_C
		// @0D5: iconst_2
		// @0D6: invokestatic game.C_100015_wh.func_103779_b(int)int[]
		// @0D9: putstatic int[] game.C_100066_dl.field_101632_G
		// @0DC: iconst_2
		// @0DD: anewarray java.lang.String
		// @0E0: dup
		// @0E1: iconst_0
		// @0E2: ldc "}\nP"
		// @0E4: invokestatic game.C_100066_dl.func_101626_z(java.lang.String)char[]
		// @0E7: invokestatic game.C_100066_dl.func_101625_z(char[])java.lang.String
		// @0EA: aastore
		// @0EB: dup
		// @0EC: iconst_1
		// @0ED: ldc "j\u0000"
		// @0EF: invokestatic game.C_100066_dl.func_101626_z(java.lang.String)char[]
		// @0F2: invokestatic game.C_100066_dl.func_101625_z(char[])java.lang.String
		// @0F5: aastore
		// @0F6: putstatic java.lang.String[] game.C_100066_dl.field_101644_z
		// @0F9: ldc "q!bDeAowI)E+g\u0006gE\"f\u0006$\u0004<zU}A\"#D|W6"
		// @0FB: invokestatic game.C_100066_dl.func_101626_z(java.lang.String)char[]
		// @0FE: invokestatic game.C_100066_dl.func_101625_z(char[])java.lang.String
		// @101: putstatic java.lang.String game.C_100066_dl.field_101645_y
		// @104: return
	}
	
	private static char[] func_101626_z(String arg0)
	{
		// @00: aload_0
		// @01: invokevirtual java.lang.String.toCharArray()char[]
		// @04: dup
		// @05: arraylength
		// @06: iconst_2
		// @07: if_icmpge @13
		// @0A: dup
		// @0B: iconst_0
		// @0C: dup2
		// @0D: caload
		// @0E: bipush 9 (0x09)
		// @10: ixor
		// @11: i2c
		// @12: castore
		// @13: areturn
	}
	
	private static String func_101625_z(char[] arg0)
	{
		// @00: aload_0
		// @01: dup
		// @02: arraylength
		// @03: swap
		// @04: iconst_0
		// @05: istore_1
		// @06: goto @4B
		// @09: dup
		// @0A: iload_1
		// @0B: dup2
		// @0C: caload
		// @0D: iload_1
		// @0E: iconst_5
		// @0F: irem
		// @10: tableswitch def: @43, for 0: @30, for 1: @35, for 2: @3A, for 3: @3E
		// @30: bipush 36 (0x24)
		// @32: goto @45
		// @35: bipush 79 (0x4F)
		// @37: goto @45
		// @3A: iconst_3
		// @3B: goto @45
		// @3E: bipush 38 (0x26)
		// @40: goto @45
		// @43: bipush 9 (0x09)
		// @45: ixor
		// @46: i2c
		// @47: castore
		// @48: iinc #1 +1
		// @4B: swap
		// @4C: dup_x1
		// @4D: iload_1
		// @4E: if_icmpgt @09
		// @51: new java.lang.String
		// @54: dup_x1
		// @55: swap
		// @56: invokespecial java.lang.String.<init>(char[])void
		// @59: invokevirtual java.lang.String.intern()java.lang.String
		// @5C: areturn
	}
}
