package game;

final class C_100273_mm
{
	static boolean field_106682_e;
	static C_100217_ao field_106681_d;
	static int field_106684_c;
	static int field_106679_f;
	static String field_106683_b;
	static int[] field_106680_g;
	static C_100302_ka field_106685_a;
	private static final String[] field_106686_z;
	
	static final C_100317_lb func_106675_a(int arg0, int arg1, C_100098_h arg2, C_100098_h arg3, int arg4)
	{
		// @00: iload_0
		// @01: iconst_1
		// @02: aload_3
		// @03: iload #4
		// @05: invokestatic game.C_100333_ij.func_107341_a(int, boolean, game.C_100098_h, int)boolean
		// @08: ifeq @0F
		// @0B: goto @11
		// @0E: athrow
		// @0F: aconst_null
		// @10: areturn
		// @11: iload_1
		// @12: ldc 1073741823 (0x3fffffff)
		// @14: if_icmpeq @1C
		// @17: aconst_null
		// @18: checkcast game.C_100317_lb
		// @1B: areturn
		// @1C: aload_2
		// @1D: iload #4
		// @1F: iconst_0
		// @20: iload_0
		// @21: invokevirtual game.C_100098_h.func_104610_b(int, int, int)byte[]
		// @24: bipush -109 (0x93)
		// @26: invokestatic game.C_100314_lf.func_101246_a(byte[], byte)game.C_100317_lb
		// @29: areturn
		// @2A: astore #5
		// @2C: aload #5
		// @2E: new java.lang.StringBuilder
		// @31: dup
		// @32: invokespecial java.lang.StringBuilder.<init>()void
		// @35: getstatic java.lang.String[] game.C_100273_mm.field_106686_z
		// @38: iconst_4
		// @39: aaload
		// @3A: invokevirtual java.lang.StringBuilder.append(java.lang.String)java.lang.StringBuilder
		// @3D: iload_0
		// @3E: invokevirtual java.lang.StringBuilder.append(int)java.lang.StringBuilder
		// @41: bipush 44 (0x2C)
		// @43: invokevirtual java.lang.StringBuilder.append(char)java.lang.StringBuilder
		// @46: iload_1
		// @47: invokevirtual java.lang.StringBuilder.append(int)java.lang.StringBuilder
		// @4A: bipush 44 (0x2C)
		// @4C: invokevirtual java.lang.StringBuilder.append(char)java.lang.StringBuilder
		// @4F: aload_2
		// @50: ifnull @5C
		// @53: getstatic java.lang.String[] game.C_100273_mm.field_106686_z
		// @56: iconst_2
		// @57: aaload
		// @58: goto @61
		// @5B: athrow
		// @5C: getstatic java.lang.String[] game.C_100273_mm.field_106686_z
		// @5F: iconst_0
		// @60: aaload
		// @61: invokevirtual java.lang.StringBuilder.append(java.lang.String)java.lang.StringBuilder
		// @64: bipush 44 (0x2C)
		// @66: invokevirtual java.lang.StringBuilder.append(char)java.lang.StringBuilder
		// @69: aload_3
		// @6A: ifnull @76
		// @6D: getstatic java.lang.String[] game.C_100273_mm.field_106686_z
		// @70: iconst_2
		// @71: aaload
		// @72: goto @7B
		// @75: athrow
		// @76: getstatic java.lang.String[] game.C_100273_mm.field_106686_z
		// @79: iconst_0
		// @7A: aaload
		// @7B: invokevirtual java.lang.StringBuilder.append(java.lang.String)java.lang.StringBuilder
		// @7E: bipush 44 (0x2C)
		// @80: invokevirtual java.lang.StringBuilder.append(char)java.lang.StringBuilder
		// @83: iload #4
		// @85: invokevirtual java.lang.StringBuilder.append(int)java.lang.StringBuilder
		// @88: bipush 41 (0x29)
		// @8A: invokevirtual java.lang.StringBuilder.append(char)java.lang.StringBuilder
		// @8D: invokevirtual java.lang.StringBuilder.toString()java.lang.String
		// @90: invokestatic game.C_100181_cf.func_105695_a(java.lang.Throwable, java.lang.String)game.C_100170_cm
		// @93: athrow
	}
	
	static final int func_106673_a(int arg0, boolean arg1)
	{
		// @00: iload_0
		// @01: sipush 8191 (0x1FFF)
		// @04: iand
		// @05: istore_0
		// @06: iload_1
		// @07: ifeq @0D
		// @0A: bipush -90 (0xA6)
		// @0C: ireturn
		// @0D: sipush -4097 (0xEFFF)
		// @10: iload_0
		// @11: iconst_m1
		// @12: ixor
		// @13: if_icmplt @3C
		// @16: iload_0
		// @17: iconst_m1
		// @18: ixor
		// @19: sipush -6145 (0xE7FF)
		// @1C: if_icmpgt @30
		// @1F: goto @23
		// @22: athrow
		// @23: getstatic int[] game.C_100266_me.field_106653_c
		// @26: iload_0
		// @27: sipush 6144 (0x1800)
		// @2A: isub
		// @2B: iaload
		// @2C: goto @3B
		// @2F: athrow
		// @30: getstatic int[] game.C_100266_me.field_106653_c
		// @33: iload_0
		// @34: ineg
		// @35: sipush 6144 (0x1800)
		// @38: iadd
		// @39: iaload
		// @3A: ineg
		// @3B: ireturn
		// @3C: sipush 2048 (0x0800)
		// @3F: iload_0
		// @40: if_icmpgt @51
		// @43: getstatic int[] game.C_100266_me.field_106653_c
		// @46: sipush -2048 (0xF800)
		// @49: iload_0
		// @4A: iadd
		// @4B: iaload
		// @4C: ineg
		// @4D: goto @5B
		// @50: athrow
		// @51: getstatic int[] game.C_100266_me.field_106653_c
		// @54: iload_0
		// @55: ineg
		// @56: sipush 2048 (0x0800)
		// @59: iadd
		// @5A: iaload
		// @5B: ireturn
		// @5C: astore_2
		// @5D: aload_2
		// @5E: new java.lang.StringBuilder
		// @61: dup
		// @62: invokespecial java.lang.StringBuilder.<init>()void
		// @65: getstatic java.lang.String[] game.C_100273_mm.field_106686_z
		// @68: iconst_5
		// @69: aaload
		// @6A: invokevirtual java.lang.StringBuilder.append(java.lang.String)java.lang.StringBuilder
		// @6D: iload_0
		// @6E: invokevirtual java.lang.StringBuilder.append(int)java.lang.StringBuilder
		// @71: bipush 44 (0x2C)
		// @73: invokevirtual java.lang.StringBuilder.append(char)java.lang.StringBuilder
		// @76: iload_1
		// @77: invokevirtual java.lang.StringBuilder.append(boolean)java.lang.StringBuilder
		// @7A: bipush 41 (0x29)
		// @7C: invokevirtual java.lang.StringBuilder.append(char)java.lang.StringBuilder
		// @7F: invokevirtual java.lang.StringBuilder.toString()java.lang.String
		// @82: invokestatic game.C_100181_cf.func_105695_a(java.lang.Throwable, java.lang.String)game.C_100170_cm
		// @85: athrow
	}
	
	public static void func_106676_a(int arg0)
	{
		// @00: aconst_null
		// @01: putstatic game.C_100302_ka game.C_100273_mm.field_106685_a
		// @04: aconst_null
		// @05: putstatic java.lang.String game.C_100273_mm.field_106683_b
		// @08: aconst_null
		// @09: putstatic int[] game.C_100273_mm.field_106680_g
		// @0C: iload_0
		// @0D: bipush -98 (0x9E)
		// @0F: if_icmplt @2C
		// @12: aconst_null
		// @13: checkcast game.C_100302_ka
		// @16: aconst_null
		// @17: checkcast game.C_100302_ka
		// @1A: bipush 44 (0x2C)
		// @1C: aconst_null
		// @1D: checkcast game.C_100302_ka
		// @20: aconst_null
		// @21: checkcast int[]
		// @24: invokestatic game.C_100273_mm.func_106674_a(game.C_100302_ka, game.C_100302_ka, int, game.C_100302_ka, int[])game.C_100033_gj
		// @27: pop
		// @28: goto @2C
		// @2B: athrow
		// @2C: aconst_null
		// @2D: putstatic game.C_100217_ao game.C_100273_mm.field_106681_d
		// @30: goto @54
		// @33: astore_1
		// @34: aload_1
		// @35: new java.lang.StringBuilder
		// @38: dup
		// @39: invokespecial java.lang.StringBuilder.<init>()void
		// @3C: getstatic java.lang.String[] game.C_100273_mm.field_106686_z
		// @3F: iconst_3
		// @40: aaload
		// @41: invokevirtual java.lang.StringBuilder.append(java.lang.String)java.lang.StringBuilder
		// @44: iload_0
		// @45: invokevirtual java.lang.StringBuilder.append(int)java.lang.StringBuilder
		// @48: bipush 41 (0x29)
		// @4A: invokevirtual java.lang.StringBuilder.append(char)java.lang.StringBuilder
		// @4D: invokevirtual java.lang.StringBuilder.toString()java.lang.String
		// @50: invokestatic game.C_100181_cf.func_105695_a(java.lang.Throwable, java.lang.String)game.C_100170_cm
		// @53: athrow
		// @54: return
	}
	
	static final C_100033_gj func_106674_a(C_100302_ka arg0, C_100302_ka arg1, int arg2, C_100302_ka arg3, int[] arg4)
	{
		// @000: getstatic int game.SteelSentinels.field_105275_O
		// @003: istore #12
		// @005: aload #4
		// @007: arraylength
		// @008: istore #5
		// @00A: iload #5
		// @00C: anewarray java.lang.String
		// @00F: astore #6
		// @011: iload #5
		// @013: newarray char[]
		// @015: astore #7
		// @017: iload #5
		// @019: anewarray game.C_100033_gj
		// @01C: astore #8
		// @01E: bipush 49 (0x31)
		// @020: istore #9
		// @022: iload_2
		// @023: bipush -71 (0xB9)
		// @025: if_icmplt @030
		// @028: iconst_3
		// @029: invokestatic game.C_100273_mm.func_106676_a(int)void
		// @02C: goto @030
		// @02F: athrow
		// @030: iconst_0
		// @031: istore #10
		// @033: iload #10
		// @035: iconst_m1
		// @036: ixor
		// @037: iload #5
		// @039: iconst_m1
		// @03A: ixor
		// @03B: if_icmple @07E
		// @03E: getstatic game.C_100137_bn game.C_100302_ka.field_101847_wb
		// @041: aload #4
		// @043: iload #10
		// @045: iaload
		// @046: bipush 28 (0x1C)
		// @048: invokevirtual game.C_100137_bn.func_105026_a(int, byte)game.C_100066_dl
		// @04B: astore #11
		// @04D: aload #6
		// @04F: iload #10
		// @051: aload #11
		// @053: bipush 91 (0x5B)
		// @055: invokevirtual game.C_100066_dl.func_101620_k(int)java.lang.String
		// @058: aastore
		// @059: aload #7
		// @05B: iload #10
		// @05D: iload #9
		// @05F: iload #9
		// @061: iconst_1
		// @062: iadd
		// @063: i2c
		// @064: istore #9
		// @066: castore
		// @067: aload #8
		// @069: iload #10
		// @06B: aconst_null
		// @06C: aastore
		// @06D: iinc #10 +1
		// @070: iload #12
		// @072: ifne @085
		// @075: iload #12
		// @077: ifeq @033
		// @07A: goto @07E
		// @07D: athrow
		// @07E: goto @085
		// @081: astore #10
		// @083: aconst_null
		// @084: areturn
		// @085: new game.C_100033_gj
		// @088: dup
		// @089: lconst_0
		// @08A: aload_1
		// @08B: aload_0
		// @08C: aload_3
		// @08D: aload #8
		// @08F: aload #4
		// @091: aload #6
		// @093: aload #7
		// @095: invokespecial game.C_100033_gj.<init>(long, game.C_100302_ka, game.C_100302_ka, game.C_100302_ka, game.C_100033_gj[], int[], java.lang.String[], char[])void
		// @098: areturn
		// @099: astore #5
		// @09B: aload #5
		// @09D: new java.lang.StringBuilder
		// @0A0: dup
		// @0A1: invokespecial java.lang.StringBuilder.<init>()void
		// @0A4: getstatic java.lang.String[] game.C_100273_mm.field_106686_z
		// @0A7: iconst_1
		// @0A8: aaload
		// @0A9: invokevirtual java.lang.StringBuilder.append(java.lang.String)java.lang.StringBuilder
		// @0AC: aload_0
		// @0AD: ifnull @0B9
		// @0B0: getstatic java.lang.String[] game.C_100273_mm.field_106686_z
		// @0B3: iconst_2
		// @0B4: aaload
		// @0B5: goto @0BE
		// @0B8: athrow
		// @0B9: getstatic java.lang.String[] game.C_100273_mm.field_106686_z
		// @0BC: iconst_0
		// @0BD: aaload
		// @0BE: invokevirtual java.lang.StringBuilder.append(java.lang.String)java.lang.StringBuilder
		// @0C1: bipush 44 (0x2C)
		// @0C3: invokevirtual java.lang.StringBuilder.append(char)java.lang.StringBuilder
		// @0C6: aload_1
		// @0C7: ifnull @0D3
		// @0CA: getstatic java.lang.String[] game.C_100273_mm.field_106686_z
		// @0CD: iconst_2
		// @0CE: aaload
		// @0CF: goto @0D8
		// @0D2: athrow
		// @0D3: getstatic java.lang.String[] game.C_100273_mm.field_106686_z
		// @0D6: iconst_0
		// @0D7: aaload
		// @0D8: invokevirtual java.lang.StringBuilder.append(java.lang.String)java.lang.StringBuilder
		// @0DB: bipush 44 (0x2C)
		// @0DD: invokevirtual java.lang.StringBuilder.append(char)java.lang.StringBuilder
		// @0E0: iload_2
		// @0E1: invokevirtual java.lang.StringBuilder.append(int)java.lang.StringBuilder
		// @0E4: bipush 44 (0x2C)
		// @0E6: invokevirtual java.lang.StringBuilder.append(char)java.lang.StringBuilder
		// @0E9: aload_3
		// @0EA: ifnull @0F6
		// @0ED: getstatic java.lang.String[] game.C_100273_mm.field_106686_z
		// @0F0: iconst_2
		// @0F1: aaload
		// @0F2: goto @0FB
		// @0F5: athrow
		// @0F6: getstatic java.lang.String[] game.C_100273_mm.field_106686_z
		// @0F9: iconst_0
		// @0FA: aaload
		// @0FB: invokevirtual java.lang.StringBuilder.append(java.lang.String)java.lang.StringBuilder
		// @0FE: bipush 44 (0x2C)
		// @100: invokevirtual java.lang.StringBuilder.append(char)java.lang.StringBuilder
		// @103: aload #4
		// @105: ifnull @111
		// @108: getstatic java.lang.String[] game.C_100273_mm.field_106686_z
		// @10B: iconst_2
		// @10C: aaload
		// @10D: goto @116
		// @110: athrow
		// @111: getstatic java.lang.String[] game.C_100273_mm.field_106686_z
		// @114: iconst_0
		// @115: aaload
		// @116: invokevirtual java.lang.StringBuilder.append(java.lang.String)java.lang.StringBuilder
		// @119: bipush 41 (0x29)
		// @11B: invokevirtual java.lang.StringBuilder.append(char)java.lang.StringBuilder
		// @11E: invokevirtual java.lang.StringBuilder.toString()java.lang.String
		// @121: invokestatic game.C_100181_cf.func_105695_a(java.lang.Throwable, java.lang.String)game.C_100170_cm
		// @124: athrow
	}
	
	static
	{
		// @000: bipush 6 (0x06)
		// @002: anewarray java.lang.String
		// @005: dup
		// @006: iconst_0
		// @007: ldc "oE\u000b-"
		// @009: invokestatic game.C_100273_mm.func_106678_z(java.lang.String)char[]
		// @00C: invokestatic game.C_100273_mm.func_106677_z(char[])java.lang.String
		// @00F: aastore
		// @010: dup
		// @011: iconst_1
		// @012: ldc "l]I\u0002d"
		// @014: invokestatic game.C_100273_mm.func_106678_z(java.lang.String)char[]
		// @017: invokestatic game.C_100273_mm.func_106677_z(char[])java.lang.String
		// @01A: aastore
		// @01B: dup
		// @01C: iconst_2
		// @01D: ldc "z\u001eIo1"
		// @01F: invokestatic game.C_100273_mm.func_106678_z(java.lang.String)char[]
		// @022: invokestatic game.C_100273_mm.func_106677_z(char[])java.lang.String
		// @025: aastore
		// @026: dup
		// @027: iconst_3
		// @028: ldc "l]I\u0003d"
		// @02A: invokestatic game.C_100273_mm.func_106678_z(java.lang.String)char[]
		// @02D: invokestatic game.C_100273_mm.func_106677_z(char[])java.lang.String
		// @030: aastore
		// @031: dup
		// @032: iconst_4
		// @033: ldc "l]I\u0005d"
		// @035: invokestatic game.C_100273_mm.func_106678_z(java.lang.String)char[]
		// @038: invokestatic game.C_100273_mm.func_106677_z(char[])java.lang.String
		// @03B: aastore
		// @03C: dup
		// @03D: iconst_5
		// @03E: ldc "l]I\u0000d"
		// @040: invokestatic game.C_100273_mm.func_106678_z(java.lang.String)char[]
		// @043: invokestatic game.C_100273_mm.func_106677_z(char[])java.lang.String
		// @046: aastore
		// @047: putstatic java.lang.String[] game.C_100273_mm.field_106686_z
		// @04A: iconst_1
		// @04B: putstatic boolean game.C_100273_mm.field_106682_e
		// @04E: new game.C_100217_ao
		// @051: dup
		// @052: bipush 7 (0x07)
		// @054: iconst_0
		// @055: iconst_1
		// @056: iconst_1
		// @057: invokespecial game.C_100217_ao.<init>(int, int, int, int)void
		// @05A: putstatic game.C_100217_ao game.C_100273_mm.field_106681_d
		// @05D: ldc "UB\u0006(\"h^\u0000a\u000fn]\u0017-)uU"
		// @05F: invokestatic game.C_100273_mm.func_106678_z(java.lang.String)char[]
		// @062: invokestatic game.C_100273_mm.func_106677_z(char[])java.lang.String
		// @065: putstatic java.lang.String game.C_100273_mm.field_106683_b
		// @068: bipush 33 (0x21)
		// @06A: newarray int[]
		// @06C: dup
		// @06D: iconst_0
		// @06E: iconst_0
		// @06F: iastore
		// @070: dup
		// @071: iconst_1
		// @072: iconst_1
		// @073: iastore
		// @074: dup
		// @075: iconst_2
		// @076: iconst_3
		// @077: iastore
		// @078: dup
		// @079: iconst_3
		// @07A: bipush 7 (0x07)
		// @07C: iastore
		// @07D: dup
		// @07E: iconst_4
		// @07F: bipush 15 (0x0F)
		// @081: iastore
		// @082: dup
		// @083: iconst_5
		// @084: bipush 31 (0x1F)
		// @086: iastore
		// @087: dup
		// @088: bipush 6 (0x06)
		// @08A: bipush 63 (0x3F)
		// @08C: iastore
		// @08D: dup
		// @08E: bipush 7 (0x07)
		// @090: bipush 127 (0x7F)
		// @092: iastore
		// @093: dup
		// @094: bipush 8 (0x08)
		// @096: sipush 255 (0x00FF)
		// @099: iastore
		// @09A: dup
		// @09B: bipush 9 (0x09)
		// @09D: sipush 511 (0x01FF)
		// @0A0: iastore
		// @0A1: dup
		// @0A2: bipush 10 (0x0A)
		// @0A4: sipush 1023 (0x03FF)
		// @0A7: iastore
		// @0A8: dup
		// @0A9: bipush 11 (0x0B)
		// @0AB: sipush 2047 (0x07FF)
		// @0AE: iastore
		// @0AF: dup
		// @0B0: bipush 12 (0x0C)
		// @0B2: sipush 4095 (0x0FFF)
		// @0B5: iastore
		// @0B6: dup
		// @0B7: bipush 13 (0x0D)
		// @0B9: sipush 8191 (0x1FFF)
		// @0BC: iastore
		// @0BD: dup
		// @0BE: bipush 14 (0x0E)
		// @0C0: sipush 16383 (0x3FFF)
		// @0C3: iastore
		// @0C4: dup
		// @0C5: bipush 15 (0x0F)
		// @0C7: sipush 32767 (0x7FFF)
		// @0CA: iastore
		// @0CB: dup
		// @0CC: bipush 16 (0x10)
		// @0CE: ldc 65535 (0xffff)
		// @0D0: iastore
		// @0D1: dup
		// @0D2: bipush 17 (0x11)
		// @0D4: ldc 131071 (0x1ffff)
		// @0D6: iastore
		// @0D7: dup
		// @0D8: bipush 18 (0x12)
		// @0DA: ldc 262143 (0x3ffff)
		// @0DC: iastore
		// @0DD: dup
		// @0DE: bipush 19 (0x13)
		// @0E0: ldc 524287 (0x7ffff)
		// @0E2: iastore
		// @0E3: dup
		// @0E4: bipush 20 (0x14)
		// @0E6: ldc 1048575 (0xfffff)
		// @0E8: iastore
		// @0E9: dup
		// @0EA: bipush 21 (0x15)
		// @0EC: ldc 2097151 (0x1fffff)
		// @0EE: iastore
		// @0EF: dup
		// @0F0: bipush 22 (0x16)
		// @0F2: ldc 4194303 (0x3fffff)
		// @0F4: iastore
		// @0F5: dup
		// @0F6: bipush 23 (0x17)
		// @0F8: ldc 8388607 (0x7fffff)
		// @0FA: iastore
		// @0FB: dup
		// @0FC: bipush 24 (0x18)
		// @0FE: ldc 16777215 (0xffffff)
		// @100: iastore
		// @101: dup
		// @102: bipush 25 (0x19)
		// @104: ldc 33554431 (0x1ffffff)
		// @106: iastore
		// @107: dup
		// @108: bipush 26 (0x1A)
		// @10A: ldc 67108863 (0x3ffffff)
		// @10C: iastore
		// @10D: dup
		// @10E: bipush 27 (0x1B)
		// @110: ldc 134217727 (0x7ffffff)
		// @112: iastore
		// @113: dup
		// @114: bipush 28 (0x1C)
		// @116: ldc 268435455 (0xfffffff)
		// @118: iastore
		// @119: dup
		// @11A: bipush 29 (0x1D)
		// @11C: ldc 536870911 (0x1fffffff)
		// @11E: iastore
		// @11F: dup
		// @120: bipush 30 (0x1E)
		// @122: ldc 1073741823 (0x3fffffff)
		// @124: iastore
		// @125: dup
		// @126: bipush 31 (0x1F)
		// @128: ldc 2147483647 (0x7fffffff)
		// @12A: iastore
		// @12B: dup
		// @12C: bipush 32 (0x20)
		// @12E: iconst_m1
		// @12F: iastore
		// @130: putstatic int[] game.C_100273_mm.field_106680_g
		// @133: return
	}
	
	private static char[] func_106678_z(String arg0)
	{
		// @00: aload_0
		// @01: invokevirtual java.lang.String.toCharArray()char[]
		// @04: dup
		// @05: arraylength
		// @06: iconst_2
		// @07: if_icmpge @13
		// @0A: dup
		// @0B: iconst_0
		// @0C: dup2
		// @0D: caload
		// @0E: bipush 76 (0x4C)
		// @10: ixor
		// @11: i2c
		// @12: castore
		// @13: areturn
	}
	
	private static String func_106677_z(char[] arg0)
	{
		// @00: aload_0
		// @01: dup
		// @02: arraylength
		// @03: swap
		// @04: iconst_0
		// @05: istore_1
		// @06: goto @4B
		// @09: dup
		// @0A: iload_1
		// @0B: dup2
		// @0C: caload
		// @0D: iload_1
		// @0E: iconst_5
		// @0F: irem
		// @10: tableswitch def: @43, for 0: @30, for 1: @34, for 2: @39, for 3: @3E
		// @30: iconst_1
		// @31: goto @45
		// @34: bipush 48 (0x30)
		// @36: goto @45
		// @39: bipush 103 (0x67)
		// @3B: goto @45
		// @3E: bipush 65 (0x41)
		// @40: goto @45
		// @43: bipush 76 (0x4C)
		// @45: ixor
		// @46: i2c
		// @47: castore
		// @48: iinc #1 +1
		// @4B: swap
		// @4C: dup_x1
		// @4D: iload_1
		// @4E: if_icmpgt @09
		// @51: new java.lang.String
		// @54: dup_x1
		// @55: swap
		// @56: invokespecial java.lang.String.<init>(char[])void
		// @59: invokevirtual java.lang.String.intern()java.lang.String
		// @5C: areturn
	}
}
