package game;

final class C_100106_ef
{
	static String field_104755_c;
	static C_100037_wb[] field_104759_i;
	static C_100321_hi field_104753_e;
	static String field_104758_h;
	static int[] field_104750_f;
	static C_100037_wb[] field_104752_d;
	static C_100202_qi field_104754_b;
	static String field_104751_g;
	static String field_104756_a;
	private static final String[] field_104757_z;
	
	public static void func_104744_b(int arg0)
	{
		// @00: aconst_null
		// @01: putstatic java.lang.String game.C_100106_ef.field_104756_a
		// @04: aconst_null
		// @05: putstatic java.lang.String game.C_100106_ef.field_104751_g
		// @08: aconst_null
		// @09: putstatic game.C_100037_wb[] game.C_100106_ef.field_104752_d
		// @0C: iload_0
		// @0D: bipush -61 (0xC3)
		// @0F: if_icmple @13
		// @12: return
		// @13: aconst_null
		// @14: putstatic game.C_100037_wb[] game.C_100106_ef.field_104759_i
		// @17: aconst_null
		// @18: putstatic int[] game.C_100106_ef.field_104750_f
		// @1B: aconst_null
		// @1C: putstatic game.C_100202_qi game.C_100106_ef.field_104754_b
		// @1F: aconst_null
		// @20: putstatic java.lang.String game.C_100106_ef.field_104755_c
		// @23: aconst_null
		// @24: putstatic java.lang.String game.C_100106_ef.field_104758_h
		// @27: aconst_null
		// @28: putstatic game.C_100321_hi game.C_100106_ef.field_104753_e
		// @2B: goto @4F
		// @2E: astore_1
		// @2F: aload_1
		// @30: new java.lang.StringBuilder
		// @33: dup
		// @34: invokespecial java.lang.StringBuilder.<init>()void
		// @37: getstatic java.lang.String[] game.C_100106_ef.field_104757_z
		// @3A: iconst_4
		// @3B: aaload
		// @3C: invokevirtual java.lang.StringBuilder.append(java.lang.String)java.lang.StringBuilder
		// @3F: iload_0
		// @40: invokevirtual java.lang.StringBuilder.append(int)java.lang.StringBuilder
		// @43: bipush 41 (0x29)
		// @45: invokevirtual java.lang.StringBuilder.append(char)java.lang.StringBuilder
		// @48: invokevirtual java.lang.StringBuilder.toString()java.lang.String
		// @4B: invokestatic game.C_100181_cf.func_105695_a(java.lang.Throwable, java.lang.String)game.C_100170_cm
		// @4E: athrow
		// @4F: return
	}
	
	static final C_100217_ao func_104743_a(int arg0, byte arg1)
	{
		// @00: getstatic int game.SteelSentinels.field_105275_O
		// @03: istore #4
		// @05: sipush -28085 (0x924B)
		// @08: invokestatic game.C_100179_ch.func_100802_e(int)game.C_100217_ao[]
		// @0B: astore_2
		// @0C: iload_1
		// @0D: bipush 112 (0x70)
		// @0F: if_icmpeq @1D
		// @12: aconst_null
		// @13: checkcast game.C_100037_wb[]
		// @16: putstatic game.C_100037_wb[] game.C_100106_ef.field_104759_i
		// @19: goto @1D
		// @1C: athrow
		// @1D: iconst_0
		// @1E: istore_3
		// @1F: aload_2
		// @20: arraylength
		// @21: iload_3
		// @22: if_icmple @3B
		// @25: aload_2
		// @26: iload_3
		// @27: aaload
		// @28: getfield int game.C_100217_ao.field_106039_a
		// @2B: iload_0
		// @2C: if_icmpne @33
		// @2F: aload_2
		// @30: iload_3
		// @31: aaload
		// @32: areturn
		// @33: iinc #3 +1
		// @36: iload #4
		// @38: ifeq @1F
		// @3B: aconst_null
		// @3C: areturn
		// @3D: astore_2
		// @3E: aload_2
		// @3F: new java.lang.StringBuilder
		// @42: dup
		// @43: invokespecial java.lang.StringBuilder.<init>()void
		// @46: getstatic java.lang.String[] game.C_100106_ef.field_104757_z
		// @49: iconst_0
		// @4A: aaload
		// @4B: invokevirtual java.lang.StringBuilder.append(java.lang.String)java.lang.StringBuilder
		// @4E: iload_0
		// @4F: invokevirtual java.lang.StringBuilder.append(int)java.lang.StringBuilder
		// @52: bipush 44 (0x2C)
		// @54: invokevirtual java.lang.StringBuilder.append(char)java.lang.StringBuilder
		// @57: iload_1
		// @58: invokevirtual java.lang.StringBuilder.append(int)java.lang.StringBuilder
		// @5B: bipush 41 (0x29)
		// @5D: invokevirtual java.lang.StringBuilder.append(char)java.lang.StringBuilder
		// @60: invokevirtual java.lang.StringBuilder.toString()java.lang.String
		// @63: invokestatic game.C_100181_cf.func_105695_a(java.lang.Throwable, java.lang.String)game.C_100170_cm
		// @66: athrow
	}
	
	static final String func_104742_a(byte arg0, CharSequence arg1)
	{
		// @000: getstatic int game.SteelSentinels.field_105275_O
		// @003: istore #9
		// @005: aload_1
		// @006: ifnonnull @00B
		// @009: aconst_null
		// @00A: areturn
		// @00B: iconst_0
		// @00C: istore_2
		// @00D: aload_1
		// @00E: invokeinterface java.lang.CharSequence.length()int
		// @013: istore_3
		// @014: iload_2
		// @015: iconst_m1
		// @016: ixor
		// @017: iload_3
		// @018: iconst_m1
		// @019: ixor
		// @01A: if_icmple @041
		// @01D: bipush -96 (0xA0)
		// @01F: aload_1
		// @020: iload_2
		// @021: invokeinterface java.lang.CharSequence.charAt(int)char
		// @026: invokestatic game.C_100053_vn.func_102812_a(int, char)boolean
		// @029: iload #9
		// @02B: ifne @042
		// @02E: ifeq @041
		// @031: goto @035
		// @034: athrow
		// @035: iinc #2 +1
		// @038: iload #9
		// @03A: ifeq @014
		// @03D: goto @041
		// @040: athrow
		// @041: iload_3
		// @042: iload_2
		// @043: if_icmple @070
		// @046: bipush -96 (0xA0)
		// @048: aload_1
		// @049: iload_3
		// @04A: iconst_1
		// @04B: isub
		// @04C: invokeinterface java.lang.CharSequence.charAt(int)char
		// @051: invokestatic game.C_100053_vn.func_102812_a(int, char)boolean
		// @054: iload #9
		// @056: ifne @074
		// @059: goto @05D
		// @05C: athrow
		// @05D: ifeq @070
		// @060: goto @064
		// @063: athrow
		// @064: iinc #3 +255
		// @067: iload #9
		// @069: ifeq @041
		// @06C: goto @070
		// @06F: athrow
		// @070: iload_3
		// @071: iload_2
		// @072: ineg
		// @073: iadd
		// @074: istore #4
		// @076: iconst_1
		// @077: iload #4
		// @079: if_icmpgt @089
		// @07C: iload #4
		// @07E: iconst_m1
		// @07F: ixor
		// @080: bipush -13 (0xF3)
		// @082: if_icmpge @08B
		// @085: goto @089
		// @088: athrow
		// @089: aconst_null
		// @08A: areturn
		// @08B: new java.lang.StringBuilder
		// @08E: dup
		// @08F: iload #4
		// @091: invokespecial java.lang.StringBuilder.<init>(int)void
		// @094: astore #5
		// @096: iload_2
		// @097: istore #6
		// @099: iload #6
		// @09B: iload_3
		// @09C: if_icmpge @0E0
		// @09F: aload_1
		// @0A0: iload #6
		// @0A2: invokeinterface java.lang.CharSequence.charAt(int)char
		// @0A7: istore #7
		// @0A9: iload #7
		// @0AB: bipush 49 (0x31)
		// @0AD: invokestatic game.C_100129_tg.func_102732_a(char, int)boolean
		// @0B0: iload #9
		// @0B2: ifne @0F1
		// @0B5: ifeq @0D8
		// @0B8: goto @0BC
		// @0BB: athrow
		// @0BC: sipush 194 (0x00C2)
		// @0BF: iload #7
		// @0C1: invokestatic game.C_100183_cd.func_103412_a(int, char)char
		// @0C4: istore #8
		// @0C6: iconst_0
		// @0C7: iload #8
		// @0C9: if_icmpeq @0D8
		// @0CC: aload #5
		// @0CE: iload #8
		// @0D0: invokevirtual java.lang.StringBuilder.append(char)java.lang.StringBuilder
		// @0D3: pop
		// @0D4: goto @0D8
		// @0D7: athrow
		// @0D8: iinc #6 +1
		// @0DB: iload #9
		// @0DD: ifeq @099
		// @0E0: bipush 114 (0x72)
		// @0E2: iload_0
		// @0E3: bipush -16 (0xF0)
		// @0E5: isub
		// @0E6: bipush 46 (0x2E)
		// @0E8: idiv
		// @0E9: irem
		// @0EA: istore #6
		// @0EC: aload #5
		// @0EE: invokevirtual java.lang.StringBuilder.length()int
		// @0F1: ifne @0F6
		// @0F4: aconst_null
		// @0F5: areturn
		// @0F6: aload #5
		// @0F8: invokevirtual java.lang.StringBuilder.toString()java.lang.String
		// @0FB: areturn
		// @0FC: astore_2
		// @0FD: aload_2
		// @0FE: new java.lang.StringBuilder
		// @101: dup
		// @102: invokespecial java.lang.StringBuilder.<init>()void
		// @105: getstatic java.lang.String[] game.C_100106_ef.field_104757_z
		// @108: bipush 6 (0x06)
		// @10A: aaload
		// @10B: invokevirtual java.lang.StringBuilder.append(java.lang.String)java.lang.StringBuilder
		// @10E: iload_0
		// @10F: invokevirtual java.lang.StringBuilder.append(int)java.lang.StringBuilder
		// @112: bipush 44 (0x2C)
		// @114: invokevirtual java.lang.StringBuilder.append(char)java.lang.StringBuilder
		// @117: aload_1
		// @118: ifnull @124
		// @11B: getstatic java.lang.String[] game.C_100106_ef.field_104757_z
		// @11E: iconst_2
		// @11F: aaload
		// @120: goto @129
		// @123: athrow
		// @124: getstatic java.lang.String[] game.C_100106_ef.field_104757_z
		// @127: iconst_3
		// @128: aaload
		// @129: invokevirtual java.lang.StringBuilder.append(java.lang.String)java.lang.StringBuilder
		// @12C: bipush 41 (0x29)
		// @12E: invokevirtual java.lang.StringBuilder.append(char)java.lang.StringBuilder
		// @131: invokevirtual java.lang.StringBuilder.toString()java.lang.String
		// @134: invokestatic game.C_100181_cf.func_105695_a(java.lang.Throwable, java.lang.String)game.C_100170_cm
		// @137: athrow
	}
	
	static final void func_104746_a(int arg0)
	{
		// @00: getstatic int game.SteelSentinels.field_105275_O
		// @03: istore_2
		// @04: getstatic int game.C_100015_wh.field_103782_d
		// @07: ifle @1A
		// @0A: getstatic int game.C_100015_wh.field_103782_d
		// @0D: iconst_1
		// @0E: isub
		// @0F: putstatic int game.C_100015_wh.field_103782_d
		// @12: iload_2
		// @13: ifeq @4E
		// @16: goto @1A
		// @19: athrow
		// @1A: iconst_0
		// @1B: getstatic int game.C_100102_w.field_104635_b
		// @1E: if_icmpge @35
		// @21: goto @25
		// @24: athrow
		// @25: getstatic int game.C_100102_w.field_104635_b
		// @28: iconst_1
		// @29: isub
		// @2A: putstatic int game.C_100102_w.field_104635_b
		// @2D: iload_2
		// @2E: ifeq @4E
		// @31: goto @35
		// @34: athrow
		// @35: iconst_m1
		// @36: getstatic int game.C_100100_i.field_102014_hc
		// @39: iconst_m1
		// @3A: ixor
		// @3B: if_icmpgt @46
		// @3E: goto @42
		// @41: athrow
		// @42: goto @4E
		// @45: athrow
		// @46: getstatic int game.C_100100_i.field_102014_hc
		// @49: iconst_1
		// @4A: isub
		// @4B: putstatic int game.C_100100_i.field_102014_hc
		// @4E: iconst_m1
		// @4F: getstatic int game.C_100015_wh.field_103782_d
		// @52: iconst_m1
		// @53: ixor
		// @54: if_icmpgt @5B
		// @57: goto @60
		// @5A: athrow
		// @5B: bipush 94 (0x5E)
		// @5D: invokestatic game.C_100192_rf.func_101673_d(byte)void
		// @60: iconst_0
		// @61: getstatic int game.C_100102_w.field_104635_b
		// @64: if_icmplt @6B
		// @67: goto @72
		// @6A: athrow
		// @6B: iconst_0
		// @6C: getstatic int game.C_100102_w.field_104635_b
		// @6F: invokestatic game.C_100080_b.func_104428_a(boolean, int)void
		// @72: iload_0
		// @73: getstatic int game.C_100100_i.field_102014_hc
		// @76: iconst_m1
		// @77: ixor
		// @78: if_icmple @86
		// @7B: iconst_0
		// @7C: getstatic int game.C_100100_i.field_102014_hc
		// @7F: invokestatic game.C_100080_b.func_104428_a(boolean, int)void
		// @82: goto @86
		// @85: athrow
		// @86: goto @AB
		// @89: astore_1
		// @8A: aload_1
		// @8B: new java.lang.StringBuilder
		// @8E: dup
		// @8F: invokespecial java.lang.StringBuilder.<init>()void
		// @92: getstatic java.lang.String[] game.C_100106_ef.field_104757_z
		// @95: bipush 7 (0x07)
		// @97: aaload
		// @98: invokevirtual java.lang.StringBuilder.append(java.lang.String)java.lang.StringBuilder
		// @9B: iload_0
		// @9C: invokevirtual java.lang.StringBuilder.append(int)java.lang.StringBuilder
		// @9F: bipush 41 (0x29)
		// @A1: invokevirtual java.lang.StringBuilder.append(char)java.lang.StringBuilder
		// @A4: invokevirtual java.lang.StringBuilder.toString()java.lang.String
		// @A7: invokestatic game.C_100181_cf.func_105695_a(java.lang.Throwable, java.lang.String)game.C_100170_cm
		// @AA: athrow
		// @AB: return
	}
	
	static final boolean func_104749_a(boolean arg0, int arg1, CharSequence arg2)
	{
		// @00: getstatic int game.SteelSentinels.field_105275_O
		// @03: istore #4
		// @05: iload_0
		// @06: iconst_0
		// @07: aload_2
		// @08: invokestatic game.C_100270_mi.func_102256_a(boolean, int, java.lang.CharSequence)boolean
		// @0B: ifeq @12
		// @0E: goto @14
		// @11: athrow
		// @12: iconst_0
		// @13: ireturn
		// @14: iconst_0
		// @15: istore_3
		// @16: iload_3
		// @17: iconst_m1
		// @18: ixor
		// @19: aload_2
		// @1A: invokeinterface java.lang.CharSequence.length()int
		// @1F: iconst_m1
		// @20: ixor
		// @21: if_icmple @48
		// @24: aload_2
		// @25: iload_3
		// @26: invokeinterface java.lang.CharSequence.charAt(int)char
		// @2B: iconst_1
		// @2C: invokestatic game.C_100218_am.func_103102_a(char, boolean)boolean
		// @2F: iload #4
		// @31: ifne @49
		// @34: ifeq @3E
		// @37: goto @3B
		// @3A: athrow
		// @3B: goto @40
		// @3E: iconst_0
		// @3F: ireturn
		// @40: iinc #3 +1
		// @43: iload #4
		// @45: ifeq @16
		// @48: iload_1
		// @49: bipush -119 (0x89)
		// @4B: if_icmplt @59
		// @4E: aconst_null
		// @4F: checkcast game.C_100037_wb[]
		// @52: putstatic game.C_100037_wb[] game.C_100106_ef.field_104752_d
		// @55: goto @59
		// @58: athrow
		// @59: iconst_1
		// @5A: ireturn
		// @5B: astore_3
		// @5C: aload_3
		// @5D: new java.lang.StringBuilder
		// @60: dup
		// @61: invokespecial java.lang.StringBuilder.<init>()void
		// @64: getstatic java.lang.String[] game.C_100106_ef.field_104757_z
		// @67: iconst_1
		// @68: aaload
		// @69: invokevirtual java.lang.StringBuilder.append(java.lang.String)java.lang.StringBuilder
		// @6C: iload_0
		// @6D: invokevirtual java.lang.StringBuilder.append(boolean)java.lang.StringBuilder
		// @70: bipush 44 (0x2C)
		// @72: invokevirtual java.lang.StringBuilder.append(char)java.lang.StringBuilder
		// @75: iload_1
		// @76: invokevirtual java.lang.StringBuilder.append(int)java.lang.StringBuilder
		// @79: bipush 44 (0x2C)
		// @7B: invokevirtual java.lang.StringBuilder.append(char)java.lang.StringBuilder
		// @7E: aload_2
		// @7F: ifnull @8B
		// @82: getstatic java.lang.String[] game.C_100106_ef.field_104757_z
		// @85: iconst_2
		// @86: aaload
		// @87: goto @90
		// @8A: athrow
		// @8B: getstatic java.lang.String[] game.C_100106_ef.field_104757_z
		// @8E: iconst_3
		// @8F: aaload
		// @90: invokevirtual java.lang.StringBuilder.append(java.lang.String)java.lang.StringBuilder
		// @93: bipush 41 (0x29)
		// @95: invokevirtual java.lang.StringBuilder.append(char)java.lang.StringBuilder
		// @98: invokevirtual java.lang.StringBuilder.toString()java.lang.String
		// @9B: invokestatic game.C_100181_cf.func_105695_a(java.lang.Throwable, java.lang.String)game.C_100170_cm
		// @9E: athrow
	}
	
	static final String func_104745_a(int arg0, char arg1, int arg2)
	{
		// @00: getstatic int game.SteelSentinels.field_105275_O
		// @03: istore #5
		// @05: iload_0
		// @06: newarray char[]
		// @08: astore_3
		// @09: iconst_0
		// @0A: istore #4
		// @0C: iload_0
		// @0D: iconst_m1
		// @0E: ixor
		// @0F: iload #4
		// @11: iconst_m1
		// @12: ixor
		// @13: if_icmpge @2C
		// @16: aload_3
		// @17: iload #4
		// @19: iload_1
		// @1A: castore
		// @1B: iinc #4 +1
		// @1E: iload #5
		// @20: ifne @41
		// @23: iload #5
		// @25: ifeq @0C
		// @28: goto @2C
		// @2B: athrow
		// @2C: iload_2
		// @2D: sipush -3521 (0xF23F)
		// @30: if_icmpeq @41
		// @33: bipush 103 (0x67)
		// @35: bipush 42 (0x2A)
		// @37: bipush -97 (0x9F)
		// @39: invokestatic game.C_100106_ef.func_104745_a(int, char, int)java.lang.String
		// @3C: pop
		// @3D: goto @41
		// @40: athrow
		// @41: new java.lang.String
		// @44: dup
		// @45: aload_3
		// @46: invokespecial java.lang.String.<init>(char[])void
		// @49: areturn
		// @4A: astore_3
		// @4B: aload_3
		// @4C: new java.lang.StringBuilder
		// @4F: dup
		// @50: invokespecial java.lang.StringBuilder.<init>()void
		// @53: getstatic java.lang.String[] game.C_100106_ef.field_104757_z
		// @56: iconst_5
		// @57: aaload
		// @58: invokevirtual java.lang.StringBuilder.append(java.lang.String)java.lang.StringBuilder
		// @5B: iload_0
		// @5C: invokevirtual java.lang.StringBuilder.append(int)java.lang.StringBuilder
		// @5F: bipush 44 (0x2C)
		// @61: invokevirtual java.lang.StringBuilder.append(char)java.lang.StringBuilder
		// @64: iload_1
		// @65: invokevirtual java.lang.StringBuilder.append(char)java.lang.StringBuilder
		// @68: bipush 44 (0x2C)
		// @6A: invokevirtual java.lang.StringBuilder.append(char)java.lang.StringBuilder
		// @6D: iload_2
		// @6E: invokevirtual java.lang.StringBuilder.append(int)java.lang.StringBuilder
		// @71: bipush 41 (0x29)
		// @73: invokevirtual java.lang.StringBuilder.append(char)java.lang.StringBuilder
		// @76: invokevirtual java.lang.StringBuilder.toString()java.lang.String
		// @79: invokestatic game.C_100181_cf.func_105695_a(java.lang.Throwable, java.lang.String)game.C_100170_cm
		// @7C: athrow
	}
	
	static
	{
		// @00: bipush 8 (0x08)
		// @02: anewarray java.lang.String
		// @05: dup
		// @06: iconst_0
		// @07: ldc "G\u007fu\u001bb"
		// @09: invokestatic game.C_100106_ef.func_104748_z(java.lang.String)char[]
		// @0C: invokestatic game.C_100106_ef.func_104747_z(char[])java.lang.String
		// @0F: aastore
		// @10: dup
		// @11: iconst_1
		// @12: ldc "G\u007fu\u0018b"
		// @14: invokestatic game.C_100106_ef.func_104748_z(java.lang.String)char[]
		// @17: invokestatic game.C_100106_ef.func_104747_z(char[])java.lang.String
		// @1A: aastore
		// @1B: dup
		// @1C: iconst_2
		// @1D: ldc "Y7uw7"
		// @1F: invokestatic game.C_100106_ef.func_104748_z(java.lang.String)char[]
		// @22: invokestatic game.C_100106_ef.func_104747_z(char[])java.lang.String
		// @25: aastore
		// @26: dup
		// @27: iconst_3
		// @28: ldc "Ll75"
		// @2A: invokestatic game.C_100106_ef.func_104748_z(java.lang.String)char[]
		// @2D: invokestatic game.C_100106_ef.func_104747_z(char[])java.lang.String
		// @30: aastore
		// @31: dup
		// @32: iconst_4
		// @33: ldc "G\u007fu\u001cb"
		// @35: invokestatic game.C_100106_ef.func_104748_z(java.lang.String)char[]
		// @38: invokestatic game.C_100106_ef.func_104747_z(char[])java.lang.String
		// @3B: aastore
		// @3C: dup
		// @3D: iconst_5
		// @3E: ldc "G\u007fu\u001ab"
		// @40: invokestatic game.C_100106_ef.func_104748_z(java.lang.String)char[]
		// @43: invokestatic game.C_100106_ef.func_104747_z(char[])java.lang.String
		// @46: aastore
		// @47: dup
		// @48: bipush 6 (0x06)
		// @4A: ldc "G\u007fu\u001fb"
		// @4C: invokestatic game.C_100106_ef.func_104748_z(java.lang.String)char[]
		// @4F: invokestatic game.C_100106_ef.func_104747_z(char[])java.lang.String
		// @52: aastore
		// @53: dup
		// @54: bipush 7 (0x07)
		// @56: ldc "G\u007fu\u001db"
		// @58: invokestatic game.C_100106_ef.func_104748_z(java.lang.String)char[]
		// @5B: invokestatic game.C_100106_ef.func_104747_z(char[])java.lang.String
		// @5E: aastore
		// @5F: putstatic java.lang.String[] game.C_100106_ef.field_104757_z
		// @62: iconst_4
		// @63: newarray int[]
		// @65: dup
		// @66: iconst_0
		// @67: iconst_4
		// @68: iastore
		// @69: dup
		// @6A: iconst_1
		// @6B: iconst_m1
		// @6C: iastore
		// @6D: dup
		// @6E: iconst_2
		// @6F: iconst_m1
		// @70: iastore
		// @71: dup
		// @72: iconst_3
		// @73: bipush 8 (0x08)
		// @75: iastore
		// @76: putstatic int[] game.C_100106_ef.field_104750_f
		// @79: ldc "gw/<8\u0002m3<jLx6<j[v.~.\u0002i)<,Gkuy\u001eJp(y#Q9/1/\u0002w:4/\u0002}2*:Nx\"<.\u0002m4y%Vq>+jRu: /Pju"
		// @7B: invokestatic game.C_100106_ef.func_104748_z(java.lang.String)char[]
		// @7E: invokestatic game.C_100106_ef.func_104747_z(char[])java.lang.String
		// @81: putstatic java.lang.String game.C_100106_ef.field_104758_h
		// @84: ldc "kw-0>G947&["
		// @86: invokestatic game.C_100106_ef.func_104748_z(java.lang.String)char[]
		// @89: invokestatic game.C_100106_ef.func_104747_z(char[])java.lang.String
		// @8C: putstatic java.lang.String game.C_100106_ef.field_104755_c
		// @8F: ldc "rk4>8Gj(yvAv7d,D\u007f=?,\u001c%~it\u0007%t:%N'"
		// @91: invokestatic game.C_100106_ef.func_104748_z(java.lang.String)char[]
		// @94: invokestatic game.C_100106_ef.func_104747_z(char[])java.lang.String
		// @97: putstatic java.lang.String game.C_100106_ef.field_104751_g
		// @9A: ldc "gw>+-[9769Q"
		// @9C: invokestatic game.C_100106_ef.func_104748_z(java.lang.String)char[]
		// @9F: invokestatic game.C_100106_ef.func_104747_z(char[])java.lang.String
		// @A2: putstatic java.lang.String game.C_100106_ef.field_104756_a
		// @A5: new game.C_100202_qi
		// @A8: dup
		// @A9: invokespecial game.C_100202_qi.<init>()void
		// @AC: putstatic game.C_100202_qi game.C_100106_ef.field_104754_b
		// @AF: return
	}
	
	private static char[] func_104748_z(String arg0)
	{
		// @00: aload_0
		// @01: invokevirtual java.lang.String.toCharArray()char[]
		// @04: dup
		// @05: arraylength
		// @06: iconst_2
		// @07: if_icmpge @13
		// @0A: dup
		// @0B: iconst_0
		// @0C: dup2
		// @0D: caload
		// @0E: bipush 74 (0x4A)
		// @10: ixor
		// @11: i2c
		// @12: castore
		// @13: areturn
	}
	
	private static String func_104747_z(char[] arg0)
	{
		// @00: aload_0
		// @01: dup
		// @02: arraylength
		// @03: swap
		// @04: iconst_0
		// @05: istore_1
		// @06: goto @4C
		// @09: dup
		// @0A: iload_1
		// @0B: dup2
		// @0C: caload
		// @0D: iload_1
		// @0E: iconst_5
		// @0F: irem
		// @10: tableswitch def: @44, for 0: @30, for 1: @35, for 2: @3A, for 3: @3F
		// @30: bipush 34 (0x22)
		// @32: goto @46
		// @35: bipush 25 (0x19)
		// @37: goto @46
		// @3A: bipush 91 (0x5B)
		// @3C: goto @46
		// @3F: bipush 89 (0x59)
		// @41: goto @46
		// @44: bipush 74 (0x4A)
		// @46: ixor
		// @47: i2c
		// @48: castore
		// @49: iinc #1 +1
		// @4C: swap
		// @4D: dup_x1
		// @4E: iload_1
		// @4F: if_icmpgt @09
		// @52: new java.lang.String
		// @55: dup_x1
		// @56: swap
		// @57: invokespecial java.lang.String.<init>(char[])void
		// @5A: invokevirtual java.lang.String.intern()java.lang.String
		// @5D: areturn
	}
}
