package game;

final class C_100144_bm extends C_100302_ka
{
	C_100302_ka field_102093_Vb;
	static String field_102091_Wb;
	private C_100302_ka field_102092_Ub;
	static C_100113_ek field_102096_Xb;
	static C_100098_h field_102095_Zb;
	static C_100302_ka field_102098_Yb;
	static C_100037_wb field_102094_ac;
	private static final String[] field_102097_bc;
	
	static final void func_102087_a(int arg0, int arg1, byte arg2)
	{
		// @00: iload_1
		// @01: putstatic int game.C_100022_hf.field_103894_g
		// @04: iload_2
		// @05: bipush 98 (0x62)
		// @07: if_icmpgt @17
		// @0A: bipush -59 (0xC5)
		// @0C: bipush 103 (0x67)
		// @0E: bipush 34 (0x22)
		// @10: invokestatic game.C_100144_bm.func_102087_a(int, int, byte)void
		// @13: goto @17
		// @16: athrow
		// @17: iload_0
		// @18: putstatic int game.C_100316_lc.field_102412_u
		// @1B: goto @52
		// @1E: astore_3
		// @1F: aload_3
		// @20: new java.lang.StringBuilder
		// @23: dup
		// @24: invokespecial java.lang.StringBuilder.<init>()void
		// @27: getstatic java.lang.String[] game.C_100144_bm.field_102097_bc
		// @2A: bipush 7 (0x07)
		// @2C: aaload
		// @2D: invokevirtual java.lang.StringBuilder.append(java.lang.String)java.lang.StringBuilder
		// @30: iload_0
		// @31: invokevirtual java.lang.StringBuilder.append(int)java.lang.StringBuilder
		// @34: bipush 44 (0x2C)
		// @36: invokevirtual java.lang.StringBuilder.append(char)java.lang.StringBuilder
		// @39: iload_1
		// @3A: invokevirtual java.lang.StringBuilder.append(int)java.lang.StringBuilder
		// @3D: bipush 44 (0x2C)
		// @3F: invokevirtual java.lang.StringBuilder.append(char)java.lang.StringBuilder
		// @42: iload_2
		// @43: invokevirtual java.lang.StringBuilder.append(int)java.lang.StringBuilder
		// @46: bipush 41 (0x29)
		// @48: invokevirtual java.lang.StringBuilder.append(char)java.lang.StringBuilder
		// @4B: invokevirtual java.lang.StringBuilder.toString()java.lang.String
		// @4E: invokestatic game.C_100181_cf.func_105695_a(java.lang.Throwable, java.lang.String)game.C_100170_cm
		// @51: athrow
		// @52: return
	}
	
	final int func_102084_a(int arg0, int arg1, int arg2)
	{
		// @00: iload_2
		// @01: sipush 23958 (0x5D96)
		// @04: if_icmpeq @13
		// @07: aload_0
		// @08: aconst_null
		// @09: checkcast game.C_100302_ka
		// @0C: putfield game.C_100302_ka game.C_100144_bm.field_102093_Vb
		// @0F: goto @13
		// @12: athrow
		// @13: iload_3
		// @14: ineg
		// @15: istore #4
		// @17: iload_3
		// @18: ineg
		// @19: istore #5
		// @1B: aconst_null
		// @1C: aload_0
		// @1D: getfield game.C_100302_ka game.C_100144_bm.field_102092_Ub
		// @20: if_acmpne @27
		// @23: goto @32
		// @26: athrow
		// @27: aload_0
		// @28: getfield game.C_100302_ka game.C_100144_bm.field_102092_Ub
		// @2B: ldc 218000 (0x35390)
		// @2D: invokevirtual game.C_100302_ka.func_101818_j(int)int
		// @30: istore #4
		// @32: aload_0
		// @33: getfield game.C_100302_ka game.C_100144_bm.field_102093_Vb
		// @36: ifnull @44
		// @39: aload_0
		// @3A: getfield game.C_100302_ka game.C_100144_bm.field_102093_Vb
		// @3D: ldc 218000 (0x35390)
		// @3F: invokevirtual game.C_100302_ka.func_101818_j(int)int
		// @42: istore #5
		// @44: iload_3
		// @45: iload #4
		// @47: iload_1
		// @48: iadd
		// @49: iload #5
		// @4B: iadd
		// @4C: iload_1
		// @4D: iadd
		// @4E: iadd
		// @4F: ireturn
		// @50: astore #4
		// @52: aload #4
		// @54: new java.lang.StringBuilder
		// @57: dup
		// @58: invokespecial java.lang.StringBuilder.<init>()void
		// @5B: getstatic java.lang.String[] game.C_100144_bm.field_102097_bc
		// @5E: iconst_5
		// @5F: aaload
		// @60: invokevirtual java.lang.StringBuilder.append(java.lang.String)java.lang.StringBuilder
		// @63: iload_1
		// @64: invokevirtual java.lang.StringBuilder.append(int)java.lang.StringBuilder
		// @67: bipush 44 (0x2C)
		// @69: invokevirtual java.lang.StringBuilder.append(char)java.lang.StringBuilder
		// @6C: iload_2
		// @6D: invokevirtual java.lang.StringBuilder.append(int)java.lang.StringBuilder
		// @70: bipush 44 (0x2C)
		// @72: invokevirtual java.lang.StringBuilder.append(char)java.lang.StringBuilder
		// @75: iload_3
		// @76: invokevirtual java.lang.StringBuilder.append(int)java.lang.StringBuilder
		// @79: bipush 41 (0x29)
		// @7B: invokevirtual java.lang.StringBuilder.append(char)java.lang.StringBuilder
		// @7E: invokevirtual java.lang.StringBuilder.toString()java.lang.String
		// @81: invokestatic game.C_100181_cf.func_105695_a(java.lang.Throwable, java.lang.String)game.C_100170_cm
		// @84: athrow
	}
	
	private final void func_102083_a(byte arg0, int arg1, int arg2)
	{
		// @000: iload_2
		// @001: ineg
		// @002: istore #4
		// @004: aload_0
		// @005: getfield game.C_100302_ka game.C_100144_bm.field_102092_Ub
		// @008: ifnonnull @00F
		// @00B: goto @01A
		// @00E: athrow
		// @00F: aload_0
		// @010: getfield game.C_100302_ka game.C_100144_bm.field_102092_Ub
		// @013: ldc 218000 (0x35390)
		// @015: invokevirtual game.C_100302_ka.func_101818_j(int)int
		// @018: istore #4
		// @01A: iload_2
		// @01B: ineg
		// @01C: istore #5
		// @01E: bipush 72 (0x48)
		// @020: iload_1
		// @021: bipush -42 (0xD6)
		// @023: isub
		// @024: bipush 41 (0x29)
		// @026: idiv
		// @027: irem
		// @028: istore #6
		// @02A: aload_0
		// @02B: getfield game.C_100302_ka game.C_100144_bm.field_102093_Vb
		// @02E: ifnull @04C
		// @031: aload_0
		// @032: getfield game.C_100302_ka game.C_100144_bm.field_102093_Vb
		// @035: bipush 46 (0x2E)
		// @037: iload_3
		// @038: ineg
		// @039: iload_3
		// @03A: ineg
		// @03B: iadd
		// @03C: aload_0
		// @03D: getfield int game.C_100144_bm.field_101886_Kb
		// @040: iload #4
		// @042: ineg
		// @043: iadd
		// @044: iload_2
		// @045: isub
		// @046: iadd
		// @047: invokevirtual game.C_100302_ka.func_101826_a(byte, int)int
		// @04A: istore #5
		// @04C: iload_3
		// @04D: iload #5
		// @04F: iadd
		// @050: iload_2
		// @051: iload #4
		// @053: iload_3
		// @054: iadd
		// @055: iadd
		// @056: iadd
		// @057: istore #7
		// @059: aload_0
		// @05A: getfield int game.C_100144_bm.field_101886_Kb
		// @05D: iload #7
		// @05F: if_icmplt @066
		// @062: goto @079
		// @065: athrow
		// @066: iload #5
		// @068: iload #7
		// @06A: ineg
		// @06B: aload_0
		// @06C: getfield int game.C_100144_bm.field_101886_Kb
		// @06F: iadd
		// @070: iadd
		// @071: istore #5
		// @073: aload_0
		// @074: getfield int game.C_100144_bm.field_101886_Kb
		// @077: istore #7
		// @079: aload_0
		// @07A: getfield int game.C_100144_bm.field_101850_Fb
		// @07D: iconst_m1
		// @07E: ixor
		// @07F: bipush -2 (0xFE)
		// @081: if_icmpne @091
		// @084: iload_3
		// @085: iload #7
		// @087: ineg
		// @088: aload_0
		// @089: getfield int game.C_100144_bm.field_101886_Kb
		// @08C: iadd
		// @08D: iconst_2
		// @08E: idiv
		// @08F: iadd
		// @090: istore_3
		// @091: aload_0
		// @092: getfield int game.C_100144_bm.field_101850_Fb
		// @095: iconst_m1
		// @096: ixor
		// @097: bipush -3 (0xFD)
		// @099: if_icmpeq @0A0
		// @09C: goto @0AB
		// @09F: athrow
		// @0A0: iload_3
		// @0A1: aload_0
		// @0A2: getfield int game.C_100144_bm.field_101886_Kb
		// @0A5: iload #7
		// @0A7: ineg
		// @0A8: iadd
		// @0A9: iadd
		// @0AA: istore_3
		// @0AB: aload_0
		// @0AC: getfield game.C_100302_ka game.C_100144_bm.field_102092_Ub
		// @0AF: ifnull @0D1
		// @0B2: aload_0
		// @0B3: getfield game.C_100302_ka game.C_100144_bm.field_102092_Ub
		// @0B6: iload_3
		// @0B7: aload_0
		// @0B8: getfield int game.C_100144_bm.field_101848_lb
		// @0BB: iconst_m1
		// @0BC: iconst_0
		// @0BD: iload #4
		// @0BF: invokevirtual game.C_100302_ka.func_101825_a(int, int, int, int, int)void
		// @0C2: aload_0
		// @0C3: getfield game.C_100302_ka game.C_100144_bm.field_102092_Ub
		// @0C6: aload_0
		// @0C7: getfield int game.C_100144_bm.field_101858_J
		// @0CA: putfield int game.C_100302_ka.field_101858_J
		// @0CD: goto @0D1
		// @0D0: athrow
		// @0D1: aconst_null
		// @0D2: aload_0
		// @0D3: getfield game.C_100302_ka game.C_100144_bm.field_102093_Vb
		// @0D6: if_acmpne @0DD
		// @0D9: goto @125
		// @0DC: athrow
		// @0DD: aload_0
		// @0DE: getfield game.C_100302_ka game.C_100144_bm.field_102093_Vb
		// @0E1: iload_2
		// @0E2: iload #4
		// @0E4: iload_3
		// @0E5: iadd
		// @0E6: iadd
		// @0E7: aload_0
		// @0E8: getfield int game.C_100144_bm.field_101848_lb
		// @0EB: iconst_m1
		// @0EC: iconst_0
		// @0ED: iload #5
		// @0EF: invokevirtual game.C_100302_ka.func_101825_a(int, int, int, int, int)void
		// @0F2: aload_0
		// @0F3: getfield game.C_100302_ka game.C_100144_bm.field_102092_Ub
		// @0F6: ifnonnull @10E
		// @0F9: aload_0
		// @0FA: getfield game.C_100302_ka game.C_100144_bm.field_102093_Vb
		// @0FD: aload_0
		// @0FE: getfield int game.C_100144_bm.field_101850_Fb
		// @101: putfield int game.C_100302_ka.field_101850_Fb
		// @104: getstatic int game.SteelSentinels.field_105275_O
		// @107: ifeq @11A
		// @10A: goto @10E
		// @10D: athrow
		// @10E: aload_0
		// @10F: getfield game.C_100302_ka game.C_100144_bm.field_102093_Vb
		// @112: iconst_0
		// @113: putfield int game.C_100302_ka.field_101850_Fb
		// @116: goto @11A
		// @119: athrow
		// @11A: aload_0
		// @11B: getfield game.C_100302_ka game.C_100144_bm.field_102093_Vb
		// @11E: aload_0
		// @11F: getfield int game.C_100144_bm.field_101858_J
		// @122: putfield int game.C_100302_ka.field_101858_J
		// @125: goto @15E
		// @128: astore #4
		// @12A: aload #4
		// @12C: new java.lang.StringBuilder
		// @12F: dup
		// @130: invokespecial java.lang.StringBuilder.<init>()void
		// @133: getstatic java.lang.String[] game.C_100144_bm.field_102097_bc
		// @136: bipush 8 (0x08)
		// @138: aaload
		// @139: invokevirtual java.lang.StringBuilder.append(java.lang.String)java.lang.StringBuilder
		// @13C: iload_1
		// @13D: invokevirtual java.lang.StringBuilder.append(int)java.lang.StringBuilder
		// @140: bipush 44 (0x2C)
		// @142: invokevirtual java.lang.StringBuilder.append(char)java.lang.StringBuilder
		// @145: iload_2
		// @146: invokevirtual java.lang.StringBuilder.append(int)java.lang.StringBuilder
		// @149: bipush 44 (0x2C)
		// @14B: invokevirtual java.lang.StringBuilder.append(char)java.lang.StringBuilder
		// @14E: iload_3
		// @14F: invokevirtual java.lang.StringBuilder.append(int)java.lang.StringBuilder
		// @152: bipush 41 (0x29)
		// @154: invokevirtual java.lang.StringBuilder.append(char)java.lang.StringBuilder
		// @157: invokevirtual java.lang.StringBuilder.toString()java.lang.String
		// @15A: invokestatic game.C_100181_cf.func_105695_a(java.lang.Throwable, java.lang.String)game.C_100170_cm
		// @15D: athrow
		// @15E: return
	}
	
	C_100144_bm(long arg0, C_100302_ka arg1, C_100302_ka arg2, C_100302_ka arg3, C_100037_wb arg4, String arg5)
	{
		// @000: aload_0
		// @001: lload_1
		// @002: aload_3
		// @003: invokespecial game.C_100302_ka.<init>(long, game.C_100302_ka)void
		// @006: aconst_null
		// @007: aload #6
		// @009: if_acmpne @00F
		// @00C: goto @030
		// @00F: aload_0
		// @010: new game.C_100302_ka
		// @013: dup
		// @014: lconst_0
		// @015: aload #4
		// @017: invokespecial game.C_100302_ka.<init>(long, game.C_100302_ka)void
		// @01A: putfield game.C_100302_ka game.C_100144_bm.field_102092_Ub
		// @01D: aload_0
		// @01E: getfield game.C_100302_ka game.C_100144_bm.field_102092_Ub
		// @021: aload #6
		// @023: putfield game.C_100037_wb game.C_100302_ka.field_101887_nb
		// @026: aload_0
		// @027: bipush -104 (0x98)
		// @029: aload_0
		// @02A: getfield game.C_100302_ka game.C_100144_bm.field_102092_Ub
		// @02D: invokevirtual game.C_100144_bm.func_101824_b(int, game.C_100302_ka)void
		// @030: aconst_null
		// @031: aload #7
		// @033: if_acmpne @03A
		// @036: goto @054
		// @039: athrow
		// @03A: aload_0
		// @03B: new game.C_100302_ka
		// @03E: dup
		// @03F: lconst_0
		// @040: aload #5
		// @042: aload #7
		// @044: invokespecial game.C_100302_ka.<init>(long, game.C_100302_ka, java.lang.String)void
		// @047: putfield game.C_100302_ka game.C_100144_bm.field_102093_Vb
		// @04A: aload_0
		// @04B: bipush -104 (0x98)
		// @04D: aload_0
		// @04E: getfield game.C_100302_ka game.C_100144_bm.field_102093_Vb
		// @051: invokevirtual game.C_100144_bm.func_101824_b(int, game.C_100302_ka)void
		// @054: aload_0
		// @055: iconst_0
		// @056: invokevirtual game.C_100144_bm.func_101821_k(int)void
		// @059: goto @105
		// @05C: astore #8
		// @05E: aload #8
		// @060: new java.lang.StringBuilder
		// @063: dup
		// @064: invokespecial java.lang.StringBuilder.<init>()void
		// @067: getstatic java.lang.String[] game.C_100144_bm.field_102097_bc
		// @06A: iconst_3
		// @06B: aaload
		// @06C: invokevirtual java.lang.StringBuilder.append(java.lang.String)java.lang.StringBuilder
		// @06F: lload_1
		// @070: invokevirtual java.lang.StringBuilder.append(long)java.lang.StringBuilder
		// @073: bipush 44 (0x2C)
		// @075: invokevirtual java.lang.StringBuilder.append(char)java.lang.StringBuilder
		// @078: aload_3
		// @079: ifnull @085
		// @07C: getstatic java.lang.String[] game.C_100144_bm.field_102097_bc
		// @07F: iconst_2
		// @080: aaload
		// @081: goto @08A
		// @084: athrow
		// @085: getstatic java.lang.String[] game.C_100144_bm.field_102097_bc
		// @088: iconst_4
		// @089: aaload
		// @08A: invokevirtual java.lang.StringBuilder.append(java.lang.String)java.lang.StringBuilder
		// @08D: bipush 44 (0x2C)
		// @08F: invokevirtual java.lang.StringBuilder.append(char)java.lang.StringBuilder
		// @092: aload #4
		// @094: ifnull @0A0
		// @097: getstatic java.lang.String[] game.C_100144_bm.field_102097_bc
		// @09A: iconst_2
		// @09B: aaload
		// @09C: goto @0A5
		// @09F: athrow
		// @0A0: getstatic java.lang.String[] game.C_100144_bm.field_102097_bc
		// @0A3: iconst_4
		// @0A4: aaload
		// @0A5: invokevirtual java.lang.StringBuilder.append(java.lang.String)java.lang.StringBuilder
		// @0A8: bipush 44 (0x2C)
		// @0AA: invokevirtual java.lang.StringBuilder.append(char)java.lang.StringBuilder
		// @0AD: aload #5
		// @0AF: ifnull @0BB
		// @0B2: getstatic java.lang.String[] game.C_100144_bm.field_102097_bc
		// @0B5: iconst_2
		// @0B6: aaload
		// @0B7: goto @0C0
		// @0BA: athrow
		// @0BB: getstatic java.lang.String[] game.C_100144_bm.field_102097_bc
		// @0BE: iconst_4
		// @0BF: aaload
		// @0C0: invokevirtual java.lang.StringBuilder.append(java.lang.String)java.lang.StringBuilder
		// @0C3: bipush 44 (0x2C)
		// @0C5: invokevirtual java.lang.StringBuilder.append(char)java.lang.StringBuilder
		// @0C8: aload #6
		// @0CA: ifnull @0D6
		// @0CD: getstatic java.lang.String[] game.C_100144_bm.field_102097_bc
		// @0D0: iconst_2
		// @0D1: aaload
		// @0D2: goto @0DB
		// @0D5: athrow
		// @0D6: getstatic java.lang.String[] game.C_100144_bm.field_102097_bc
		// @0D9: iconst_4
		// @0DA: aaload
		// @0DB: invokevirtual java.lang.StringBuilder.append(java.lang.String)java.lang.StringBuilder
		// @0DE: bipush 44 (0x2C)
		// @0E0: invokevirtual java.lang.StringBuilder.append(char)java.lang.StringBuilder
		// @0E3: aload #7
		// @0E5: ifnull @0F1
		// @0E8: getstatic java.lang.String[] game.C_100144_bm.field_102097_bc
		// @0EB: iconst_2
		// @0EC: aaload
		// @0ED: goto @0F6
		// @0F0: athrow
		// @0F1: getstatic java.lang.String[] game.C_100144_bm.field_102097_bc
		// @0F4: iconst_4
		// @0F5: aaload
		// @0F6: invokevirtual java.lang.StringBuilder.append(java.lang.String)java.lang.StringBuilder
		// @0F9: bipush 41 (0x29)
		// @0FB: invokevirtual java.lang.StringBuilder.append(char)java.lang.StringBuilder
		// @0FE: invokevirtual java.lang.StringBuilder.toString()java.lang.String
		// @101: invokestatic game.C_100181_cf.func_105695_a(java.lang.Throwable, java.lang.String)game.C_100170_cm
		// @104: athrow
		// @105: return
	}
	
	public static void func_102090_f(byte arg0)
	{
		// @00: aconst_null
		// @01: putstatic game.C_100037_wb game.C_100144_bm.field_102094_ac
		// @04: aconst_null
		// @05: putstatic java.lang.String game.C_100144_bm.field_102091_Wb
		// @08: bipush 60 (0x3C)
		// @0A: bipush 42 (0x2A)
		// @0C: iload_0
		// @0D: isub
		// @0E: bipush 54 (0x36)
		// @10: idiv
		// @11: idiv
		// @12: istore_1
		// @13: aconst_null
		// @14: putstatic game.C_100098_h game.C_100144_bm.field_102095_Zb
		// @17: aconst_null
		// @18: putstatic game.C_100113_ek game.C_100144_bm.field_102096_Xb
		// @1B: aconst_null
		// @1C: putstatic game.C_100302_ka game.C_100144_bm.field_102098_Yb
		// @1F: goto @43
		// @22: astore_1
		// @23: aload_1
		// @24: new java.lang.StringBuilder
		// @27: dup
		// @28: invokespecial java.lang.StringBuilder.<init>()void
		// @2B: getstatic java.lang.String[] game.C_100144_bm.field_102097_bc
		// @2E: iconst_1
		// @2F: aaload
		// @30: invokevirtual java.lang.StringBuilder.append(java.lang.String)java.lang.StringBuilder
		// @33: iload_0
		// @34: invokevirtual java.lang.StringBuilder.append(int)java.lang.StringBuilder
		// @37: bipush 41 (0x29)
		// @39: invokevirtual java.lang.StringBuilder.append(char)java.lang.StringBuilder
		// @3C: invokevirtual java.lang.StringBuilder.toString()java.lang.String
		// @3F: invokestatic game.C_100181_cf.func_105695_a(java.lang.Throwable, java.lang.String)game.C_100170_cm
		// @42: athrow
		// @43: return
	}
	
	final void func_102086_a(int arg0, int arg1, int arg2, int arg3, int arg4, int arg5, int arg6)
	{
		// @00: aload_0
		// @01: iload_1
		// @02: iload_3
		// @03: iload #5
		// @05: sipush -2533 (0xF61B)
		// @08: ixor
		// @09: iload #7
		// @0B: iload #6
		// @0D: invokevirtual game.C_100144_bm.func_101825_a(int, int, int, int, int)void
		// @10: aload_0
		// @11: bipush 74 (0x4A)
		// @13: iload #4
		// @15: iload_2
		// @16: invokespecial game.C_100144_bm.func_102083_a(byte, int, int)void
		// @19: iload #5
		// @1B: sipush 2532 (0x09E4)
		// @1E: if_icmpeq @28
		// @21: aconst_null
		// @22: checkcast java.lang.String
		// @25: putstatic java.lang.String game.C_100144_bm.field_102091_Wb
		// @28: goto @89
		// @2B: astore #8
		// @2D: aload #8
		// @2F: new java.lang.StringBuilder
		// @32: dup
		// @33: invokespecial java.lang.StringBuilder.<init>()void
		// @36: getstatic java.lang.String[] game.C_100144_bm.field_102097_bc
		// @39: bipush 6 (0x06)
		// @3B: aaload
		// @3C: invokevirtual java.lang.StringBuilder.append(java.lang.String)java.lang.StringBuilder
		// @3F: iload_1
		// @40: invokevirtual java.lang.StringBuilder.append(int)java.lang.StringBuilder
		// @43: bipush 44 (0x2C)
		// @45: invokevirtual java.lang.StringBuilder.append(char)java.lang.StringBuilder
		// @48: iload_2
		// @49: invokevirtual java.lang.StringBuilder.append(int)java.lang.StringBuilder
		// @4C: bipush 44 (0x2C)
		// @4E: invokevirtual java.lang.StringBuilder.append(char)java.lang.StringBuilder
		// @51: iload_3
		// @52: invokevirtual java.lang.StringBuilder.append(int)java.lang.StringBuilder
		// @55: bipush 44 (0x2C)
		// @57: invokevirtual java.lang.StringBuilder.append(char)java.lang.StringBuilder
		// @5A: iload #4
		// @5C: invokevirtual java.lang.StringBuilder.append(int)java.lang.StringBuilder
		// @5F: bipush 44 (0x2C)
		// @61: invokevirtual java.lang.StringBuilder.append(char)java.lang.StringBuilder
		// @64: iload #5
		// @66: invokevirtual java.lang.StringBuilder.append(int)java.lang.StringBuilder
		// @69: bipush 44 (0x2C)
		// @6B: invokevirtual java.lang.StringBuilder.append(char)java.lang.StringBuilder
		// @6E: iload #6
		// @70: invokevirtual java.lang.StringBuilder.append(int)java.lang.StringBuilder
		// @73: bipush 44 (0x2C)
		// @75: invokevirtual java.lang.StringBuilder.append(char)java.lang.StringBuilder
		// @78: iload #7
		// @7A: invokevirtual java.lang.StringBuilder.append(int)java.lang.StringBuilder
		// @7D: bipush 41 (0x29)
		// @7F: invokevirtual java.lang.StringBuilder.append(char)java.lang.StringBuilder
		// @82: invokevirtual java.lang.StringBuilder.toString()java.lang.String
		// @85: invokestatic game.C_100181_cf.func_105695_a(java.lang.Throwable, java.lang.String)game.C_100170_cm
		// @88: athrow
		// @89: return
	}
	
	static final void func_102089_a(boolean arg0, boolean arg1, int arg2)
	{
		// @00: iload_1
		// @01: ifne @11
		// @04: invokestatic game.C_100196_rb.func_105792_b()void
		// @07: getstatic int game.SteelSentinels.field_105275_O
		// @0A: ifeq @24
		// @0D: goto @11
		// @10: athrow
		// @11: iconst_0
		// @12: iconst_0
		// @13: getstatic int game.C_100196_rb.field_105819_e
		// @16: getstatic int game.C_100196_rb.field_105821_c
		// @19: iconst_0
		// @1A: sipush 192 (0x00C0)
		// @1D: invokestatic game.C_100196_rb.func_105804_g(int, int, int, int, int, int)void
		// @20: goto @24
		// @23: athrow
		// @24: iconst_0
		// @25: iload_1
		// @26: invokestatic game.C_100226_ae.func_106145_a(int, boolean)void
		// @29: iload_2
		// @2A: bipush -87 (0xA9)
		// @2C: if_icmplt @3A
		// @2F: iconst_0
		// @30: iconst_0
		// @31: bipush 64 (0x40)
		// @33: invokestatic game.C_100144_bm.func_102089_a(boolean, boolean, int)void
		// @36: goto @3A
		// @39: athrow
		// @3A: goto @70
		// @3D: astore_3
		// @3E: aload_3
		// @3F: new java.lang.StringBuilder
		// @42: dup
		// @43: invokespecial java.lang.StringBuilder.<init>()void
		// @46: getstatic java.lang.String[] game.C_100144_bm.field_102097_bc
		// @49: iconst_0
		// @4A: aaload
		// @4B: invokevirtual java.lang.StringBuilder.append(java.lang.String)java.lang.StringBuilder
		// @4E: iload_0
		// @4F: invokevirtual java.lang.StringBuilder.append(boolean)java.lang.StringBuilder
		// @52: bipush 44 (0x2C)
		// @54: invokevirtual java.lang.StringBuilder.append(char)java.lang.StringBuilder
		// @57: iload_1
		// @58: invokevirtual java.lang.StringBuilder.append(boolean)java.lang.StringBuilder
		// @5B: bipush 44 (0x2C)
		// @5D: invokevirtual java.lang.StringBuilder.append(char)java.lang.StringBuilder
		// @60: iload_2
		// @61: invokevirtual java.lang.StringBuilder.append(int)java.lang.StringBuilder
		// @64: bipush 41 (0x29)
		// @66: invokevirtual java.lang.StringBuilder.append(char)java.lang.StringBuilder
		// @69: invokevirtual java.lang.StringBuilder.toString()java.lang.String
		// @6C: invokestatic game.C_100181_cf.func_105695_a(java.lang.Throwable, java.lang.String)game.C_100170_cm
		// @6F: athrow
		// @70: return
	}
	
	static
	{
		// @00: bipush 9 (0x09)
		// @02: anewarray java.lang.String
		// @05: dup
		// @06: iconst_0
		// @07: ldc "CC'\u0012;"
		// @09: invokestatic game.C_100144_bm.func_102088_z(java.lang.String)char[]
		// @0C: invokestatic game.C_100144_bm.func_102085_z(char[])java.lang.String
		// @0F: aastore
		// @10: dup
		// @11: iconst_1
		// @12: ldc "CC'\u0017;"
		// @14: invokestatic game.C_100144_bm.func_102088_z(java.lang.String)char[]
		// @17: invokestatic game.C_100144_bm.func_102085_z(char[])java.lang.String
		// @1A: aastore
		// @1B: dup
		// @1C: iconst_2
		// @1D: ldc "Z\u0000'zn"
		// @1F: invokestatic game.C_100144_bm.func_102088_z(java.lang.String)char[]
		// @22: invokestatic game.C_100144_bm.func_102085_z(char[])java.lang.String
		// @25: aastore
		// @26: dup
		// @27: iconst_3
		// @28: ldc "CC'hzOG}j;"
		// @2A: invokestatic game.C_100144_bm.func_102088_z(java.lang.String)char[]
		// @2D: invokestatic game.C_100144_bm.func_102085_z(char[])java.lang.String
		// @30: aastore
		// @31: dup
		// @32: iconst_4
		// @33: ldc "O[e8"
		// @35: invokestatic game.C_100144_bm.func_102088_z(java.lang.String)char[]
		// @38: invokestatic game.C_100144_bm.func_102085_z(char[])java.lang.String
		// @3B: aastore
		// @3C: dup
		// @3D: iconst_5
		// @3E: ldc "CC'\u0010;"
		// @40: invokestatic game.C_100144_bm.func_102088_z(java.lang.String)char[]
		// @43: invokestatic game.C_100144_bm.func_102085_z(char[])java.lang.String
		// @46: aastore
		// @47: dup
		// @48: bipush 6 (0x06)
		// @4A: ldc "CC'\u0011;"
		// @4C: invokestatic game.C_100144_bm.func_102088_z(java.lang.String)char[]
		// @4F: invokestatic game.C_100144_bm.func_102085_z(char[])java.lang.String
		// @52: aastore
		// @53: dup
		// @54: bipush 7 (0x07)
		// @56: ldc "CC'\u0016;"
		// @58: invokestatic game.C_100144_bm.func_102088_z(java.lang.String)char[]
		// @5B: invokestatic game.C_100144_bm.func_102085_z(char[])java.lang.String
		// @5E: aastore
		// @5F: dup
		// @60: bipush 8 (0x08)
		// @62: ldc "CC'\u0015;"
		// @64: invokestatic game.C_100144_bm.func_102088_z(java.lang.String)char[]
		// @67: invokestatic game.C_100144_bm.func_102085_z(char[])java.lang.String
		// @6A: aastore
		// @6B: putstatic java.lang.String[] game.C_100144_bm.field_102097_bc
		// @6E: ldc "d@mt~H]z=|O"
		// @70: invokestatic game.C_100144_bm.func_102088_z(java.lang.String)char[]
		// @73: invokestatic game.C_100144_bm.func_102085_z(char[])java.lang.String
		// @76: putstatic java.lang.String game.C_100144_bm.field_102091_Wb
		// @79: new game.C_100113_ek
		// @7C: dup
		// @7D: ldc ""
		// @7F: invokespecial game.C_100113_ek.<init>(java.lang.String)void
		// @82: putstatic game.C_100113_ek game.C_100144_bm.field_102096_Xb
		// @85: aconst_null
		// @86: putstatic game.C_100037_wb game.C_100144_bm.field_102094_ac
		// @89: return
	}
	
	private static char[] func_102088_z(String arg0)
	{
		// @00: aload_0
		// @01: invokevirtual java.lang.String.toCharArray()char[]
		// @04: dup
		// @05: arraylength
		// @06: iconst_2
		// @07: if_icmpge @13
		// @0A: dup
		// @0B: iconst_0
		// @0C: dup2
		// @0D: caload
		// @0E: bipush 19 (0x13)
		// @10: ixor
		// @11: i2c
		// @12: castore
		// @13: areturn
	}
	
	private static String func_102085_z(char[] arg0)
	{
		// @00: aload_0
		// @01: dup
		// @02: arraylength
		// @03: swap
		// @04: iconst_0
		// @05: istore_1
		// @06: goto @4C
		// @09: dup
		// @0A: iload_1
		// @0B: dup2
		// @0C: caload
		// @0D: iload_1
		// @0E: iconst_5
		// @0F: irem
		// @10: tableswitch def: @44, for 0: @30, for 1: @35, for 2: @3A, for 3: @3F
		// @30: bipush 33 (0x21)
		// @32: goto @46
		// @35: bipush 46 (0x2E)
		// @37: goto @46
		// @3A: bipush 9 (0x09)
		// @3C: goto @46
		// @3F: bipush 84 (0x54)
		// @41: goto @46
		// @44: bipush 19 (0x13)
		// @46: ixor
		// @47: i2c
		// @48: castore
		// @49: iinc #1 +1
		// @4C: swap
		// @4D: dup_x1
		// @4E: iload_1
		// @4F: if_icmpgt @09
		// @52: new java.lang.String
		// @55: dup_x1
		// @56: swap
		// @57: invokespecial java.lang.String.<init>(char[])void
		// @5A: invokevirtual java.lang.String.intern()java.lang.String
		// @5D: areturn
	}
}
