package game;

final class C_100013_fn
{
	static String field_103747_i;
	static String field_103746_h;
	static C_100029_gn field_103738_g;
	static int field_103743_a;
	int field_103740_e;
	static C_100049_vf field_103742_c;
	static C_100231_oc field_103737_f;
	static boolean[] field_103741_b;
	static C_100037_wb[] field_103739_d;
	static C_100098_h field_103744_j;
	private static final String[] field_103745_z;
	
	static final int func_103732_a(int[] arg0, byte arg1)
	{
		// @00: getstatic int game.SteelSentinels.field_105275_O
		// @03: istore #5
		// @05: iconst_0
		// @06: istore_2
		// @07: aload_0
		// @08: arraylength
		// @09: istore_3
		// @0A: iload_3
		// @0B: iconst_m1
		// @0C: ixor
		// @0D: bipush -9 (0xF7)
		// @0F: if_icmple @14
		// @12: iconst_0
		// @13: ireturn
		// @14: iconst_0
		// @15: istore #4
		// @17: iload #4
		// @19: bipush -8 (0xF8)
		// @1B: iload_3
		// @1C: iadd
		// @1D: if_icmpge @56
		// @20: aload_0
		// @21: iload #4
		// @23: iaload
		// @24: iload #5
		// @26: ifne @5A
		// @29: iflt @4E
		// @2C: goto @30
		// @2F: athrow
		// @30: getstatic int[] game.C_100064_ve.field_103015_v
		// @33: arraylength
		// @34: iconst_m1
		// @35: ixor
		// @36: aload_0
		// @37: iload #4
		// @39: iaload
		// @3A: iconst_m1
		// @3B: ixor
		// @3C: if_icmpge @4E
		// @3F: goto @43
		// @42: athrow
		// @43: iload_2
		// @44: getstatic int[] game.C_100064_ve.field_103015_v
		// @47: aload_0
		// @48: iload #4
		// @4A: iaload
		// @4B: iaload
		// @4C: iadd
		// @4D: istore_2
		// @4E: iinc #4 +1
		// @51: iload #5
		// @53: ifeq @17
		// @56: bipush -8 (0xF8)
		// @58: iload_3
		// @59: iadd
		// @5A: istore #4
		// @5C: iload_3
		// @5D: iconst_m1
		// @5E: ixor
		// @5F: iload #4
		// @61: iconst_m1
		// @62: ixor
		// @63: if_icmpge @AD
		// @66: aload_0
		// @67: iload #4
		// @69: iaload
		// @6A: iload #5
		// @6C: ifne @BA
		// @6F: iflt @98
		// @72: goto @76
		// @75: athrow
		// @76: aload_0
		// @77: iload #4
		// @79: iaload
		// @7A: iconst_m1
		// @7B: ixor
		// @7C: getstatic int[] game.C_100021_wn.field_103870_e
		// @7F: arraylength
		// @80: iconst_m1
		// @81: ixor
		// @82: if_icmpgt @8D
		// @85: goto @89
		// @88: athrow
		// @89: goto @98
		// @8C: athrow
		// @8D: iload_2
		// @8E: getstatic int[] game.C_100021_wn.field_103870_e
		// @91: aload_0
		// @92: iload #4
		// @94: iaload
		// @95: iaload
		// @96: iadd
		// @97: istore_2
		// @98: bipush 34 (0x22)
		// @9A: aload_0
		// @9B: iload #4
		// @9D: iaload
		// @9E: if_icmpne @A5
		// @A1: sipush 6100 (0x17D4)
		// @A4: ireturn
		// @A5: iinc #4 +1
		// @A8: iload #5
		// @AA: ifeq @5C
		// @AD: bipush -8 (0xF8)
		// @AF: bipush 24 (0x18)
		// @B1: iload_1
		// @B2: isub
		// @B3: bipush 55 (0x37)
		// @B5: idiv
		// @B6: idiv
		// @B7: istore #4
		// @B9: iload_2
		// @BA: ireturn
		// @BB: astore_2
		// @BC: aload_2
		// @BD: new java.lang.StringBuilder
		// @C0: dup
		// @C1: invokespecial java.lang.StringBuilder.<init>()void
		// @C4: getstatic java.lang.String[] game.C_100013_fn.field_103745_z
		// @C7: bipush 6 (0x06)
		// @C9: aaload
		// @CA: invokevirtual java.lang.StringBuilder.append(java.lang.String)java.lang.StringBuilder
		// @CD: aload_0
		// @CE: ifnull @DA
		// @D1: getstatic java.lang.String[] game.C_100013_fn.field_103745_z
		// @D4: iconst_4
		// @D5: aaload
		// @D6: goto @DF
		// @D9: athrow
		// @DA: getstatic java.lang.String[] game.C_100013_fn.field_103745_z
		// @DD: iconst_2
		// @DE: aaload
		// @DF: invokevirtual java.lang.StringBuilder.append(java.lang.String)java.lang.StringBuilder
		// @E2: bipush 44 (0x2C)
		// @E4: invokevirtual java.lang.StringBuilder.append(char)java.lang.StringBuilder
		// @E7: iload_1
		// @E8: invokevirtual java.lang.StringBuilder.append(int)java.lang.StringBuilder
		// @EB: bipush 41 (0x29)
		// @ED: invokevirtual java.lang.StringBuilder.append(char)java.lang.StringBuilder
		// @F0: invokevirtual java.lang.StringBuilder.toString()java.lang.String
		// @F3: invokestatic game.C_100181_cf.func_105695_a(java.lang.Throwable, java.lang.String)game.C_100170_cm
		// @F6: athrow
	}
	
	C_100013_fn(int arg0)
	{
		// @00: aload_0
		// @01: invokespecial java.lang.Object.<init>()void
		// @04: aload_0
		// @05: iload_1
		// @06: putfield int game.C_100013_fn.field_103740_e
		// @09: goto @2D
		// @0C: astore_2
		// @0D: aload_2
		// @0E: new java.lang.StringBuilder
		// @11: dup
		// @12: invokespecial java.lang.StringBuilder.<init>()void
		// @15: getstatic java.lang.String[] game.C_100013_fn.field_103745_z
		// @18: iconst_0
		// @19: aaload
		// @1A: invokevirtual java.lang.StringBuilder.append(java.lang.String)java.lang.StringBuilder
		// @1D: iload_1
		// @1E: invokevirtual java.lang.StringBuilder.append(int)java.lang.StringBuilder
		// @21: bipush 41 (0x29)
		// @23: invokevirtual java.lang.StringBuilder.append(char)java.lang.StringBuilder
		// @26: invokevirtual java.lang.StringBuilder.toString()java.lang.String
		// @29: invokestatic game.C_100181_cf.func_105695_a(java.lang.Throwable, java.lang.String)game.C_100170_cm
		// @2C: athrow
		// @2D: return
	}
	
	static final void func_103736_a(int arg0, C_100327_ib arg1, int arg2)
	{
		// @000: getstatic int game.SteelSentinels.field_105275_O
		// @003: istore #7
		// @005: iconst_m1
		// @006: iload_2
		// @007: iconst_m1
		// @008: ixor
		// @009: if_icmplt @020
		// @00C: iload_2
		// @00D: iconst_m1
		// @00E: ixor
		// @00F: getstatic int[][] game.C_100122_em.field_102073_Xb
		// @012: arraylength
		// @013: iconst_m1
		// @014: ixor
		// @015: if_icmple @020
		// @018: goto @01C
		// @01B: athrow
		// @01C: goto @021
		// @01F: athrow
		// @020: return
		// @021: aconst_null
		// @022: aload_1
		// @023: if_acmpne @085
		// @026: iload_2
		// @027: iconst_m1
		// @028: ixor
		// @029: iconst_m1
		// @02A: if_icmpgt @041
		// @02D: goto @031
		// @030: athrow
		// @031: getstatic int[][] game.C_100122_em.field_102073_Xb
		// @034: arraylength
		// @035: iconst_m1
		// @036: ixor
		// @037: iload_2
		// @038: iconst_m1
		// @039: ixor
		// @03A: if_icmplt @042
		// @03D: goto @041
		// @040: athrow
		// @041: return
		// @042: getstatic int[][] game.C_100122_em.field_102073_Xb
		// @045: iload_2
		// @046: aaload
		// @047: astore_3
		// @048: aconst_null
		// @049: aload_3
		// @04A: if_acmpne @054
		// @04D: getstatic game.C_100037_wb[] game.C_100122_em.field_102075_ec
		// @050: iload_2
		// @051: aconst_null
		// @052: aastore
		// @053: return
		// @054: bipush 8 (0x08)
		// @056: newarray int[]
		// @058: astore #4
		// @05A: aload_3
		// @05B: arraylength
		// @05C: bipush -8 (0xF8)
		// @05E: iadd
		// @05F: newarray int[]
		// @061: astore #5
		// @063: aload_3
		// @064: iconst_0
		// @065: aload #5
		// @067: iconst_0
		// @068: aload #5
		// @06A: arraylength
		// @06B: invokestatic game.C_100120_en.func_104913_a(int[], int, int[], int, int)void
		// @06E: aload_3
		// @06F: aload #5
		// @071: arraylength
		// @072: aload #4
		// @074: iconst_0
		// @075: aload #4
		// @077: arraylength
		// @078: invokestatic game.C_100120_en.func_104913_a(int[], int, int[], int, int)void
		// @07B: aload #5
		// @07D: bipush -57 (0xC7)
		// @07F: aload #4
		// @081: invokestatic game.C_100157_db.func_103546_a(int[], byte, int[])game.C_100327_ib
		// @084: astore_1
		// @085: aconst_null
		// @086: getstatic game.C_100037_wb[] game.C_100122_em.field_102075_ec
		// @089: iload_2
		// @08A: aaload
		// @08B: if_acmpeq @0A9
		// @08E: getstatic game.C_100037_wb[] game.C_100122_em.field_102075_ec
		// @091: iload_2
		// @092: aaload
		// @093: invokevirtual game.C_100037_wb.func_102379_d()void
		// @096: iconst_0
		// @097: iconst_0
		// @098: bipush 62 (0x3E)
		// @09A: bipush 74 (0x4A)
		// @09C: iconst_0
		// @09D: invokestatic game.C_100196_rb.func_105782_i(int, int, int, int, int)void
		// @0A0: iload #7
		// @0A2: ifeq @0C5
		// @0A5: goto @0A9
		// @0A8: athrow
		// @0A9: getstatic game.C_100037_wb[] game.C_100122_em.field_102075_ec
		// @0AC: iload_2
		// @0AD: new game.C_100037_wb
		// @0B0: dup
		// @0B1: bipush 62 (0x3E)
		// @0B3: bipush 74 (0x4A)
		// @0B5: invokespecial game.C_100037_wb.<init>(int, int)void
		// @0B8: aastore
		// @0B9: getstatic game.C_100037_wb[] game.C_100122_em.field_102075_ec
		// @0BC: iload_2
		// @0BD: aaload
		// @0BE: invokevirtual game.C_100037_wb.func_102379_d()void
		// @0C1: goto @0C5
		// @0C4: athrow
		// @0C5: getstatic int game.C_100270_mi.field_102270_jc
		// @0C8: istore_3
		// @0C9: iload_0
		// @0CA: sipush 1000 (0x03E8)
		// @0CD: if_icmpeq @0DE
		// @0D0: aconst_null
		// @0D1: checkcast int[]
		// @0D4: bipush 36 (0x24)
		// @0D6: invokestatic game.C_100013_fn.func_103732_a(int[], byte)int
		// @0D9: pop
		// @0DA: goto @0DE
		// @0DD: athrow
		// @0DE: iconst_m1
		// @0DF: aload_1
		// @0E0: getfield int game.C_100327_ib.field_102494_P
		// @0E3: iconst_m1
		// @0E4: ixor
		// @0E5: if_icmpne @0F2
		// @0E8: sipush 1200 (0x04B0)
		// @0EB: putstatic int game.C_100270_mi.field_102270_jc
		// @0EE: goto @0F2
		// @0F1: athrow
		// @0F2: aload_1
		// @0F3: getfield int game.C_100327_ib.field_102494_P
		// @0F6: iconst_m1
		// @0F7: ixor
		// @0F8: bipush -56 (0xC8)
		// @0FA: if_icmpne @107
		// @0FD: sipush 1200 (0x04B0)
		// @100: putstatic int game.C_100270_mi.field_102270_jc
		// @103: goto @107
		// @106: athrow
		// @107: aload_1
		// @108: getfield int game.C_100327_ib.field_102494_P
		// @10B: bipush 57 (0x39)
		// @10D: if_icmpne @11A
		// @110: sipush 1300 (0x0514)
		// @113: putstatic int game.C_100270_mi.field_102270_jc
		// @116: goto @11A
		// @119: athrow
		// @11A: aload_1
		// @11B: getfield int game.C_100327_ib.field_102494_P
		// @11E: bipush 62 (0x3E)
		// @120: if_icmpne @12D
		// @123: sipush 1400 (0x0578)
		// @126: putstatic int game.C_100270_mi.field_102270_jc
		// @129: goto @12D
		// @12C: athrow
		// @12D: aload_1
		// @12E: getfield int game.C_100327_ib.field_102494_P
		// @131: iconst_m1
		// @132: ixor
		// @133: bipush -66 (0xBE)
		// @135: if_icmpeq @13C
		// @138: goto @142
		// @13B: athrow
		// @13C: sipush 1000 (0x03E8)
		// @13F: putstatic int game.C_100270_mi.field_102270_jc
		// @142: aload_1
		// @143: getfield int game.C_100327_ib.field_102494_P
		// @146: iconst_m1
		// @147: ixor
		// @148: bipush -70 (0xBA)
		// @14A: if_icmpeq @151
		// @14D: goto @157
		// @150: athrow
		// @151: sipush 1400 (0x0578)
		// @154: putstatic int game.C_100270_mi.field_102270_jc
		// @157: bipush -73 (0xB7)
		// @159: aload_1
		// @15A: getfield int game.C_100327_ib.field_102494_P
		// @15D: iconst_m1
		// @15E: ixor
		// @15F: if_icmpne @16C
		// @162: sipush 1000 (0x03E8)
		// @165: putstatic int game.C_100270_mi.field_102270_jc
		// @168: goto @16C
		// @16B: athrow
		// @16C: aload_1
		// @16D: getfield int game.C_100327_ib.field_102494_P
		// @170: iconst_m1
		// @171: ixor
		// @172: bipush -76 (0xB4)
		// @174: if_icmpeq @17B
		// @177: goto @181
		// @17A: athrow
		// @17B: sipush 1000 (0x03E8)
		// @17E: putstatic int game.C_100270_mi.field_102270_jc
		// @181: bipush -80 (0xB0)
		// @183: aload_1
		// @184: getfield int game.C_100327_ib.field_102494_P
		// @187: iconst_m1
		// @188: ixor
		// @189: if_icmpne @196
		// @18C: sipush 1000 (0x03E8)
		// @18F: putstatic int game.C_100270_mi.field_102270_jc
		// @192: goto @196
		// @195: athrow
		// @196: bipush -85 (0xAB)
		// @198: aload_1
		// @199: getfield int game.C_100327_ib.field_102494_P
		// @19C: iconst_m1
		// @19D: ixor
		// @19E: if_icmpeq @1A5
		// @1A1: goto @1AB
		// @1A4: athrow
		// @1A5: sipush 1000 (0x03E8)
		// @1A8: putstatic int game.C_100270_mi.field_102270_jc
		// @1AB: aload_1
		// @1AC: getfield int game.C_100327_ib.field_102494_P
		// @1AF: bipush 88 (0x58)
		// @1B1: if_icmpeq @1B8
		// @1B4: goto @1BE
		// @1B7: athrow
		// @1B8: sipush 1000 (0x03E8)
		// @1BB: putstatic int game.C_100270_mi.field_102270_jc
		// @1BE: aload_1
		// @1BF: getfield int game.C_100327_ib.field_102494_P
		// @1C2: iconst_m1
		// @1C3: ixor
		// @1C4: bipush -93 (0xA3)
		// @1C6: if_icmpeq @1CD
		// @1C9: goto @1D3
		// @1CC: athrow
		// @1CD: sipush 700 (0x02BC)
		// @1D0: putstatic int game.C_100270_mi.field_102270_jc
		// @1D3: aload_1
		// @1D4: bipush 31 (0x1F)
		// @1D6: iconst_0
		// @1D7: iconst_0
		// @1D8: iconst_0
		// @1D9: bipush 74 (0x4A)
		// @1DB: ldc 759988816 (0x2d4c8250)
		// @1DD: invokevirtual game.C_100327_ib.func_102437_a(int, int, boolean, int, int, int)void
		// @1E0: iload_3
		// @1E1: putstatic int game.C_100270_mi.field_102270_jc
		// @1E4: iload_0
		// @1E5: sipush -1108 (0xFBAC)
		// @1E8: iadd
		// @1E9: invokestatic game.C_100100_i.func_102004_l(int)boolean
		// @1EC: ifne @28A
		// @1EF: iconst_0
		// @1F0: istore #4
		// @1F2: getstatic int[][] game.C_100122_em.field_102073_Xb
		// @1F5: iload_2
		// @1F6: aaload
		// @1F7: astore #5
		// @1F9: iconst_0
		// @1FA: istore #6
		// @1FC: iload #6
		// @1FE: aload #5
		// @200: arraylength
		// @201: if_icmpge @256
		// @204: aload #5
		// @206: iload #6
		// @208: iaload
		// @209: iconst_m1
		// @20A: ixor
		// @20B: iload #7
		// @20D: ifne @258
		// @210: ifeq @24A
		// @213: goto @217
		// @216: athrow
		// @217: iload #6
		// @219: iconst_m1
		// @21A: ixor
		// @21B: aload #5
		// @21D: arraylength
		// @21E: bipush -8 (0xF8)
		// @220: iadd
		// @221: iconst_m1
		// @222: ixor
		// @223: if_icmpgt @22F
		// @226: goto @22A
		// @229: athrow
		// @22A: iconst_1
		// @22B: goto @230
		// @22E: athrow
		// @22F: iconst_0
		// @230: sipush -11145 (0xD477)
		// @233: aload #5
		// @235: iload #6
		// @237: iaload
		// @238: invokestatic game.C_100080_b.func_104421_a(boolean, int, int)boolean
		// @23B: ifne @242
		// @23E: goto @24A
		// @241: athrow
		// @242: iconst_1
		// @243: istore #4
		// @245: iload #7
		// @247: ifeq @256
		// @24A: iinc #6 +1
		// @24D: iload #7
		// @24F: ifeq @1FC
		// @252: goto @256
		// @255: athrow
		// @256: iload #4
		// @258: ifne @25E
		// @25B: goto @28A
		// @25E: iconst_0
		// @25F: iconst_0
		// @260: bipush 62 (0x3E)
		// @262: bipush 74 (0x4A)
		// @264: iconst_0
		// @265: sipush 128 (0x0080)
		// @268: invokestatic game.C_100196_rb.func_105804_g(int, int, int, int, int, int)void
		// @26B: getstatic game.C_100037_wb game.C_100244_pe.field_106376_e
		// @26E: astore #6
		// @270: aload #6
		// @272: bipush 62 (0x3E)
		// @274: aload #6
		// @276: getfield int game.C_100037_wb.field_102341_y
		// @279: isub
		// @27A: iconst_2
		// @27B: idiv
		// @27C: aload #6
		// @27E: getfield int game.C_100037_wb.field_102340_z
		// @281: ineg
		// @282: bipush 74 (0x4A)
		// @284: iadd
		// @285: iconst_2
		// @286: idiv
		// @287: invokevirtual game.C_100037_wb.func_102353_h(int, int)void
		// @28A: getstatic game.C_100185_rm game.C_100049_vf.field_104206_l
		// @28D: bipush 123 (0x7B)
		// @28F: invokevirtual game.C_100185_rm.func_105476_a(byte)void
		// @292: goto @2D9
		// @295: astore_3
		// @296: aload_3
		// @297: new java.lang.StringBuilder
		// @29A: dup
		// @29B: invokespecial java.lang.StringBuilder.<init>()void
		// @29E: getstatic java.lang.String[] game.C_100013_fn.field_103745_z
		// @2A1: iconst_3
		// @2A2: aaload
		// @2A3: invokevirtual java.lang.StringBuilder.append(java.lang.String)java.lang.StringBuilder
		// @2A6: iload_0
		// @2A7: invokevirtual java.lang.StringBuilder.append(int)java.lang.StringBuilder
		// @2AA: bipush 44 (0x2C)
		// @2AC: invokevirtual java.lang.StringBuilder.append(char)java.lang.StringBuilder
		// @2AF: aload_1
		// @2B0: ifnull @2BC
		// @2B3: getstatic java.lang.String[] game.C_100013_fn.field_103745_z
		// @2B6: iconst_4
		// @2B7: aaload
		// @2B8: goto @2C1
		// @2BB: athrow
		// @2BC: getstatic java.lang.String[] game.C_100013_fn.field_103745_z
		// @2BF: iconst_2
		// @2C0: aaload
		// @2C1: invokevirtual java.lang.StringBuilder.append(java.lang.String)java.lang.StringBuilder
		// @2C4: bipush 44 (0x2C)
		// @2C6: invokevirtual java.lang.StringBuilder.append(char)java.lang.StringBuilder
		// @2C9: iload_2
		// @2CA: invokevirtual java.lang.StringBuilder.append(int)java.lang.StringBuilder
		// @2CD: bipush 41 (0x29)
		// @2CF: invokevirtual java.lang.StringBuilder.append(char)java.lang.StringBuilder
		// @2D2: invokevirtual java.lang.StringBuilder.toString()java.lang.String
		// @2D5: invokestatic game.C_100181_cf.func_105695_a(java.lang.Throwable, java.lang.String)game.C_100170_cm
		// @2D8: athrow
		// @2D9: return
	}
	
	public static void func_103734_a(byte arg0)
	{
		// @00: bipush 7 (0x07)
		// @02: bipush -28 (0xE4)
		// @04: iload_0
		// @05: isub
		// @06: bipush 36 (0x24)
		// @08: idiv
		// @09: irem
		// @0A: istore_1
		// @0B: aconst_null
		// @0C: putstatic java.lang.String game.C_100013_fn.field_103746_h
		// @0F: aconst_null
		// @10: putstatic game.C_100098_h game.C_100013_fn.field_103744_j
		// @13: aconst_null
		// @14: putstatic game.C_100049_vf game.C_100013_fn.field_103742_c
		// @17: aconst_null
		// @18: putstatic boolean[] game.C_100013_fn.field_103741_b
		// @1B: aconst_null
		// @1C: putstatic game.C_100029_gn game.C_100013_fn.field_103738_g
		// @1F: aconst_null
		// @20: putstatic game.C_100037_wb[] game.C_100013_fn.field_103739_d
		// @23: aconst_null
		// @24: putstatic game.C_100231_oc game.C_100013_fn.field_103737_f
		// @27: aconst_null
		// @28: putstatic java.lang.String game.C_100013_fn.field_103747_i
		// @2B: goto @4F
		// @2E: astore_1
		// @2F: aload_1
		// @30: new java.lang.StringBuilder
		// @33: dup
		// @34: invokespecial java.lang.StringBuilder.<init>()void
		// @37: getstatic java.lang.String[] game.C_100013_fn.field_103745_z
		// @3A: iconst_5
		// @3B: aaload
		// @3C: invokevirtual java.lang.StringBuilder.append(java.lang.String)java.lang.StringBuilder
		// @3F: iload_0
		// @40: invokevirtual java.lang.StringBuilder.append(int)java.lang.StringBuilder
		// @43: bipush 41 (0x29)
		// @45: invokevirtual java.lang.StringBuilder.append(char)java.lang.StringBuilder
		// @48: invokevirtual java.lang.StringBuilder.toString()java.lang.String
		// @4B: invokestatic game.C_100181_cf.func_105695_a(java.lang.Throwable, java.lang.String)game.C_100170_cm
		// @4E: athrow
		// @4F: return
	}
	
	public final String toString()
	{
		// @00: new java.lang.IllegalStateException
		// @03: dup
		// @04: invokespecial java.lang.IllegalStateException.<init>()void
		// @07: athrow
		// @08: astore_1
		// @09: aload_1
		// @0A: getstatic java.lang.String[] game.C_100013_fn.field_103745_z
		// @0D: iconst_1
		// @0E: aaload
		// @0F: invokestatic game.C_100181_cf.func_105695_a(java.lang.Throwable, java.lang.String)game.C_100170_cm
		// @12: athrow
	}
	
	static
	{
		// @00: bipush 7 (0x07)
		// @02: anewarray java.lang.String
		// @05: dup
		// @06: iconst_0
		// @07: ldc "G\u0013\u000e_>O\u0014T]\u007f"
		// @09: invokestatic game.C_100013_fn.func_103735_z(java.lang.String)char[]
		// @0C: invokestatic game.C_100013_fn.func_103733_z(char[])java.lang.String
		// @0F: aastore
		// @10: dup
		// @11: iconst_1
		// @12: ldc "G\u0013\u000e\u00178r\tR\n9FU\t"
		// @14: invokestatic game.C_100013_fn.func_103735_z(java.lang.String)char[]
		// @17: invokestatic game.C_100013_fn.func_103733_z(char[])java.lang.String
		// @1A: aastore
		// @1B: dup
		// @1C: iconst_2
		// @1D: ldc "O\u0008L\u000f"
		// @1F: invokestatic game.C_100013_fn.func_103735_z(java.lang.String)char[]
		// @22: invokestatic game.C_100013_fn.func_103733_z(char[])java.lang.String
		// @25: aastore
		// @26: dup
		// @27: iconst_3
		// @28: ldc "G\u0013\u000e \u007f"
		// @2A: invokestatic game.C_100013_fn.func_103735_z(java.lang.String)char[]
		// @2D: invokestatic game.C_100013_fn.func_103733_z(char[])java.lang.String
		// @30: aastore
		// @31: dup
		// @32: iconst_4
		// @33: ldc "ZS\u000eM*"
		// @35: invokestatic game.C_100013_fn.func_103735_z(java.lang.String)char[]
		// @38: invokestatic game.C_100013_fn.func_103733_z(char[])java.lang.String
		// @3B: aastore
		// @3C: dup
		// @3D: iconst_5
		// @3E: ldc "G\u0013\u000e!\u007f"
		// @40: invokestatic game.C_100013_fn.func_103735_z(java.lang.String)char[]
		// @43: invokestatic game.C_100013_fn.func_103733_z(char[])java.lang.String
		// @46: aastore
		// @47: dup
		// @48: bipush 6 (0x06)
		// @4A: ldc "G\u0013\u000e\"\u007f"
		// @4C: invokestatic game.C_100013_fn.func_103735_z(java.lang.String)char[]
		// @4F: invokestatic game.C_100013_fn.func_103733_z(char[])java.lang.String
		// @52: aastore
		// @53: putstatic java.lang.String[] game.C_100013_fn.field_103745_z
		// @56: ldc "\u001dX\u0010]wI\u001cSC2O\tE\u00112E]A\r8U\u0015E\u0011wF\u001cM\u0006y"
		// @58: invokestatic game.C_100013_fn.func_103735_z(java.lang.String)char[]
		// @5B: invokestatic game.C_100013_fn.func_103733_z(char[])java.lang.String
		// @5E: putstatic java.lang.String game.C_100013_fn.field_103747_i
		// @61: ldc "i\u0018R\u0006wX\u0012UC4@\u0013\u0000\u00102U]U\u0013w@]R\u0002#D\u0019\u0000\u00046L\u0018\u000eC\u001eG]Y\u000c\"\u0001\nI\r{\u0001\u0004O\u0016%\u0001\u000fA\u0017>O\u001a\u0000\u0014>M\u0011\u0000\u00048\u0001\u0008PMwh\u001b\u001c\r5R\r\u001e\u001a8T]L\u000c$DQ\u0000\n#\u0001\nI\u000f;\u0001\u001aOC3N\nNBkC\u000f\u001e_5SCp\u000f2@\u000eEC$Q\u0018C\n1X]Y\u000c\"S]P\u00112G\u0018R\u00069B\u0018SC6O\u0019\u0000\u0000;H\u001eKCp\u001dX\u0010]p\u000f]o\u0016%\u0001\u000eY\u0010#D\u0010\u0000\u0014>M\u0011\u0000\u0017?D\u0013\u0000\u0002#U\u0018M\u0013#\u0001\tOC1H\u0013DC6\u0001\u000eU\n#@\u001fL\u0006wN\rP\u000c9D\u0013TC>O]U\r3D\u000f\u0000\u0002wL\u0014N\u0016#DQ\u0000\u00072Q\u0018N\u0007>O\u001a\u0000\u000c9\u0001\u0015O\u0014wC\u0008S\u001awU\u0015EC;N\u001fB\u001akO\u001fS\u0013iH\u000e\u000e_5SC\u001c\u0001%\u001f)H\n$\u0001\u0014SC6O]E\u001b4D\u0011L\u00069U]W\u0002.\u0001\tOC0D\t\u0000\u00178\u0001\u0016N\u000c \u0001\u0013E\u0014wQ\u0018O\u0013;D\\"
		// @63: invokestatic game.C_100013_fn.func_103735_z(java.lang.String)char[]
		// @66: invokestatic game.C_100013_fn.func_103733_z(char[])java.lang.String
		// @69: putstatic java.lang.String game.C_100013_fn.field_103746_h
		// @6C: bipush 26 (0x1A)
		// @6E: anewarray game.C_100037_wb
		// @71: putstatic game.C_100037_wb[] game.C_100013_fn.field_103739_d
		// @74: iconst_m1
		// @75: putstatic int game.C_100013_fn.field_103743_a
		// @78: bipush 64 (0x40)
		// @7A: newarray boolean[]
		// @7C: putstatic boolean[] game.C_100013_fn.field_103741_b
		// @7F: return
	}
	
	private static char[] func_103735_z(String arg0)
	{
		// @00: aload_0
		// @01: invokevirtual java.lang.String.toCharArray()char[]
		// @04: dup
		// @05: arraylength
		// @06: iconst_2
		// @07: if_icmpge @13
		// @0A: dup
		// @0B: iconst_0
		// @0C: dup2
		// @0D: caload
		// @0E: bipush 87 (0x57)
		// @10: ixor
		// @11: i2c
		// @12: castore
		// @13: areturn
	}
	
	private static String func_103733_z(char[] arg0)
	{
		// @00: aload_0
		// @01: dup
		// @02: arraylength
		// @03: swap
		// @04: iconst_0
		// @05: istore_1
		// @06: goto @4C
		// @09: dup
		// @0A: iload_1
		// @0B: dup2
		// @0C: caload
		// @0D: iload_1
		// @0E: iconst_5
		// @0F: irem
		// @10: tableswitch def: @44, for 0: @30, for 1: @35, for 2: @3A, for 3: @3F
		// @30: bipush 33 (0x21)
		// @32: goto @46
		// @35: bipush 125 (0x7D)
		// @37: goto @46
		// @3A: bipush 32 (0x20)
		// @3C: goto @46
		// @3F: bipush 99 (0x63)
		// @41: goto @46
		// @44: bipush 87 (0x57)
		// @46: ixor
		// @47: i2c
		// @48: castore
		// @49: iinc #1 +1
		// @4C: swap
		// @4D: dup_x1
		// @4E: iload_1
		// @4F: if_icmpgt @09
		// @52: new java.lang.String
		// @55: dup_x1
		// @56: swap
		// @57: invokespecial java.lang.String.<init>(char[])void
		// @5A: invokevirtual java.lang.String.intern()java.lang.String
		// @5D: areturn
	}
}
