package game;

import java.applet.Applet;

final class C_100015_wh
{
	static int field_103781_g;
	static C_100302_ka field_103792_k;
	static int[] field_103788_o;
	static String field_103784_b;
	static C_100153_be[] field_103790_m;
	static String field_103794_i;
	static long field_103780_f;
	static int field_103786_a;
	static C_100037_wb[] field_103785_c;
	static String field_103789_l;
	static String[] field_103791_j;
	static String field_103787_n;
	static int field_103782_d;
	static int field_103783_e;
	static int field_103793_h;
	private static final String[] field_103795_z;
	
	public static void func_103774_c(int arg0)
	{
		// @00: aconst_null
		// @01: putstatic java.lang.String game.C_100015_wh.field_103794_i
		// @04: aconst_null
		// @05: putstatic java.lang.String game.C_100015_wh.field_103784_b
		// @08: aconst_null
		// @09: putstatic java.lang.String[] game.C_100015_wh.field_103791_j
		// @0C: aconst_null
		// @0D: putstatic java.lang.String game.C_100015_wh.field_103789_l
		// @10: aconst_null
		// @11: putstatic java.lang.String game.C_100015_wh.field_103787_n
		// @14: iload_0
		// @15: sipush 199 (0x00C7)
		// @18: if_icmpeq @28
		// @1B: aconst_null
		// @1C: checkcast java.applet.Applet
		// @1F: bipush -68 (0xBC)
		// @21: invokestatic game.C_100015_wh.func_103773_a(java.applet.Applet, int)void
		// @24: goto @28
		// @27: athrow
		// @28: aconst_null
		// @29: putstatic game.C_100153_be[] game.C_100015_wh.field_103790_m
		// @2C: aconst_null
		// @2D: putstatic game.C_100302_ka game.C_100015_wh.field_103792_k
		// @30: aconst_null
		// @31: putstatic int[] game.C_100015_wh.field_103788_o
		// @34: aconst_null
		// @35: putstatic game.C_100037_wb[] game.C_100015_wh.field_103785_c
		// @38: goto @5D
		// @3B: astore_1
		// @3C: aload_1
		// @3D: new java.lang.StringBuilder
		// @40: dup
		// @41: invokespecial java.lang.StringBuilder.<init>()void
		// @44: getstatic java.lang.String[] game.C_100015_wh.field_103795_z
		// @47: bipush 11 (0x0B)
		// @49: aaload
		// @4A: invokevirtual java.lang.StringBuilder.append(java.lang.String)java.lang.StringBuilder
		// @4D: iload_0
		// @4E: invokevirtual java.lang.StringBuilder.append(int)java.lang.StringBuilder
		// @51: bipush 41 (0x29)
		// @53: invokevirtual java.lang.StringBuilder.append(char)java.lang.StringBuilder
		// @56: invokevirtual java.lang.StringBuilder.toString()java.lang.String
		// @59: invokestatic game.C_100181_cf.func_105695_a(java.lang.Throwable, java.lang.String)game.C_100170_cm
		// @5C: athrow
		// @5D: return
	}
	
	static final void func_103773_a(Applet arg0, int arg1)
	{
		// @00: iload_1
		// @01: sipush 198 (0x00C6)
		// @04: if_icmpeq @10
		// @07: bipush 60 (0x3C)
		// @09: invokestatic game.C_100015_wh.func_103774_c(int)void
		// @0C: goto @10
		// @0F: athrow
		// @10: iconst_1
		// @11: putstatic boolean game.C_100004_gb.field_103578_i
		// @14: getstatic java.lang.String[] game.C_100015_wh.field_103795_z
		// @17: iconst_1
		// @18: aaload
		// @19: astore_2
		// @1A: getstatic java.lang.String[] game.C_100015_wh.field_103795_z
		// @1D: iconst_4
		// @1E: aaload
		// @1F: astore_3
		// @20: ldc2_w -1
		// @23: lstore #4
		// @25: iconst_0
		// @26: aload_0
		// @27: aload_2
		// @28: aload_3
		// @29: lload #4
		// @2B: invokestatic game.C_100252_pn.func_105492_a(boolean, java.applet.Applet, java.lang.String, java.lang.String, long)void
		// @2E: goto @6C
		// @31: astore_2
		// @32: aload_2
		// @33: new java.lang.StringBuilder
		// @36: dup
		// @37: invokespecial java.lang.StringBuilder.<init>()void
		// @3A: getstatic java.lang.String[] game.C_100015_wh.field_103795_z
		// @3D: iconst_3
		// @3E: aaload
		// @3F: invokevirtual java.lang.StringBuilder.append(java.lang.String)java.lang.StringBuilder
		// @42: aload_0
		// @43: ifnull @4F
		// @46: getstatic java.lang.String[] game.C_100015_wh.field_103795_z
		// @49: iconst_2
		// @4A: aaload
		// @4B: goto @54
		// @4E: athrow
		// @4F: getstatic java.lang.String[] game.C_100015_wh.field_103795_z
		// @52: iconst_0
		// @53: aaload
		// @54: invokevirtual java.lang.StringBuilder.append(java.lang.String)java.lang.StringBuilder
		// @57: bipush 44 (0x2C)
		// @59: invokevirtual java.lang.StringBuilder.append(char)java.lang.StringBuilder
		// @5C: iload_1
		// @5D: invokevirtual java.lang.StringBuilder.append(int)java.lang.StringBuilder
		// @60: bipush 41 (0x29)
		// @62: invokevirtual java.lang.StringBuilder.append(char)java.lang.StringBuilder
		// @65: invokevirtual java.lang.StringBuilder.toString()java.lang.String
		// @68: invokestatic game.C_100181_cf.func_105695_a(java.lang.Throwable, java.lang.String)game.C_100170_cm
		// @6B: athrow
		// @6C: return
	}
	
	static final int[] func_103779_b(int arg0)
	{
		// @00: iload_0
		// @01: iconst_2
		// @02: if_icmpeq @0E
		// @05: bipush -57 (0xC7)
		// @07: invokestatic game.C_100015_wh.func_103775_a(int)void
		// @0A: goto @0E
		// @0D: athrow
		// @0E: bipush 8 (0x08)
		// @10: newarray int[]
		// @12: areturn
		// @13: astore_1
		// @14: aload_1
		// @15: new java.lang.StringBuilder
		// @18: dup
		// @19: invokespecial java.lang.StringBuilder.<init>()void
		// @1C: getstatic java.lang.String[] game.C_100015_wh.field_103795_z
		// @1F: bipush 12 (0x0C)
		// @21: aaload
		// @22: invokevirtual java.lang.StringBuilder.append(java.lang.String)java.lang.StringBuilder
		// @25: iload_0
		// @26: invokevirtual java.lang.StringBuilder.append(int)java.lang.StringBuilder
		// @29: bipush 41 (0x29)
		// @2B: invokevirtual java.lang.StringBuilder.append(char)java.lang.StringBuilder
		// @2E: invokevirtual java.lang.StringBuilder.toString()java.lang.String
		// @31: invokestatic game.C_100181_cf.func_105695_a(java.lang.Throwable, java.lang.String)game.C_100170_cm
		// @34: athrow
	}
	
	static final void func_103778_a(int arg0, boolean arg1, C_100125_tm arg2)
	{
		// @00: getstatic game.C_100278_nd game.C_100115_ej.field_102043_Yb
		// @03: astore_3
		// @04: aload_3
		// @05: iload_0
		// @06: bipush 115 (0x73)
		// @08: invokevirtual game.C_100278_nd.func_101189_h(int, int)void
		// @0B: aload_3
		// @0C: sipush 7838 (0x1E9E)
		// @0F: aload_2
		// @10: getfield int game.C_100125_tm.field_100750_j
		// @13: invokevirtual game.C_100278_nd.func_101169_f(int, int)void
		// @16: aload_3
		// @17: aload_2
		// @18: getfield int game.C_100125_tm.field_100744_q
		// @1B: bipush 56 (0x38)
		// @1D: invokevirtual game.C_100278_nd.func_101141_d(int, byte)void
		// @20: iload_1
		// @21: ifeq @2F
		// @24: aconst_null
		// @25: checkcast java.lang.String
		// @28: putstatic java.lang.String game.C_100015_wh.field_103784_b
		// @2B: goto @2F
		// @2E: athrow
		// @2F: goto @76
		// @32: astore_3
		// @33: aload_3
		// @34: new java.lang.StringBuilder
		// @37: dup
		// @38: invokespecial java.lang.StringBuilder.<init>()void
		// @3B: getstatic java.lang.String[] game.C_100015_wh.field_103795_z
		// @3E: iconst_5
		// @3F: aaload
		// @40: invokevirtual java.lang.StringBuilder.append(java.lang.String)java.lang.StringBuilder
		// @43: iload_0
		// @44: invokevirtual java.lang.StringBuilder.append(int)java.lang.StringBuilder
		// @47: bipush 44 (0x2C)
		// @49: invokevirtual java.lang.StringBuilder.append(char)java.lang.StringBuilder
		// @4C: iload_1
		// @4D: invokevirtual java.lang.StringBuilder.append(boolean)java.lang.StringBuilder
		// @50: bipush 44 (0x2C)
		// @52: invokevirtual java.lang.StringBuilder.append(char)java.lang.StringBuilder
		// @55: aload_2
		// @56: ifnull @62
		// @59: getstatic java.lang.String[] game.C_100015_wh.field_103795_z
		// @5C: iconst_2
		// @5D: aaload
		// @5E: goto @67
		// @61: athrow
		// @62: getstatic java.lang.String[] game.C_100015_wh.field_103795_z
		// @65: iconst_0
		// @66: aaload
		// @67: invokevirtual java.lang.StringBuilder.append(java.lang.String)java.lang.StringBuilder
		// @6A: bipush 41 (0x29)
		// @6C: invokevirtual java.lang.StringBuilder.append(char)java.lang.StringBuilder
		// @6F: invokevirtual java.lang.StringBuilder.toString()java.lang.String
		// @72: invokestatic game.C_100181_cf.func_105695_a(java.lang.Throwable, java.lang.String)game.C_100170_cm
		// @75: athrow
		// @76: return
	}
	
	static final void func_103775_a(int arg0)
	{
		// @000: sipush 243 (0x00F3)
		// @003: sipush 197 (0x00C5)
		// @006: sipush 369 (0x0171)
		// @009: sipush 143 (0x008F)
		// @00C: ldc 16777215 (0xffffff)
		// @00E: invokestatic game.C_100196_rb.func_105784_h(int, int, int, int, int)void
		// @011: sipush 244 (0x00F4)
		// @014: sipush 198 (0x00C6)
		// @017: sipush 367 (0x016F)
		// @01A: sipush 141 (0x008D)
		// @01D: iconst_0
		// @01E: invokestatic game.C_100196_rb.func_105782_i(int, int, int, int, int)void
		// @021: getstatic game.C_100037_wb[] game.C_100097_k.field_104584_a
		// @024: ifnull @02B
		// @027: goto @053
		// @02A: athrow
		// @02B: aconst_null
		// @02C: getstatic game.C_100112_r game.C_100003_ga.field_103541_q
		// @02F: if_acmpeq @052
		// @032: getstatic game.C_100112_r game.C_100003_ga.field_103541_q
		// @035: getstatic java.lang.String game.C_100185_rm.field_105485_e
		// @038: sipush 245 (0x00F5)
		// @03B: sipush 199 (0x00C7)
		// @03E: sipush 365 (0x016D)
		// @041: sipush 139 (0x008B)
		// @044: ldc 16777215 (0xffffff)
		// @046: iconst_m1
		// @047: iconst_1
		// @048: iconst_1
		// @049: iconst_0
		// @04A: invokevirtual game.C_100112_r.func_101729_a(java.lang.String, int, int, int, int, int, int, int, int, int)int
		// @04D: pop
		// @04E: goto @052
		// @051: athrow
		// @052: return
		// @053: getstatic game.C_100037_wb[] game.C_100097_k.field_104584_a
		// @056: getstatic int game.C_100292_jk.field_101215_r
		// @059: aaload
		// @05A: astore_1
		// @05B: aconst_null
		// @05C: aload_1
		// @05D: if_acmpne @08D
		// @060: getstatic game.C_100112_r game.C_100003_ga.field_103541_q
		// @063: ifnonnull @06E
		// @066: goto @06A
		// @069: athrow
		// @06A: goto @097
		// @06D: athrow
		// @06E: getstatic game.C_100112_r game.C_100003_ga.field_103541_q
		// @071: getstatic java.lang.String game.C_100185_rm.field_105485_e
		// @074: sipush 245 (0x00F5)
		// @077: sipush 199 (0x00C7)
		// @07A: sipush 365 (0x016D)
		// @07D: sipush 139 (0x008B)
		// @080: ldc 16777215 (0xffffff)
		// @082: iconst_m1
		// @083: iconst_1
		// @084: iconst_1
		// @085: iconst_0
		// @086: invokevirtual game.C_100112_r.func_101729_a(java.lang.String, int, int, int, int, int, int, int, int, int)int
		// @089: pop
		// @08A: goto @097
		// @08D: aload_1
		// @08E: sipush 245 (0x00F5)
		// @091: sipush 199 (0x00C7)
		// @094: invokevirtual game.C_100037_wb.func_102353_h(int, int)void
		// @097: iload_0
		// @098: sipush 139 (0x008B)
		// @09B: if_icmpeq @0AC
		// @09E: bipush 73 (0x49)
		// @0A0: iconst_0
		// @0A1: aconst_null
		// @0A2: checkcast game.C_100125_tm
		// @0A5: invokestatic game.C_100015_wh.func_103778_a(int, boolean, game.C_100125_tm)void
		// @0A8: goto @0AC
		// @0AB: athrow
		// @0AC: getstatic int game.C_100338_jc.field_105367_b
		// @0AF: iconst_m1
		// @0B0: ixor
		// @0B1: getstatic int game.C_100042_we.field_104137_m
		// @0B4: iconst_m1
		// @0B5: ixor
		// @0B6: if_icmplt @0BD
		// @0B9: goto @12E
		// @0BC: athrow
		// @0BD: getstatic game.C_100037_wb[] game.C_100097_k.field_104584_a
		// @0C0: getstatic int game.C_100107_u.field_104772_e
		// @0C3: aaload
		// @0C4: astore_1
		// @0C5: aload_1
		// @0C6: ifnonnull @0CD
		// @0C9: goto @12E
		// @0CC: athrow
		// @0CD: getstatic int game.C_100042_we.field_104137_m
		// @0D0: bipush 60 (0x3C)
		// @0D2: aload_1
		// @0D3: getfield int game.C_100037_wb.field_102341_y
		// @0D6: iadd
		// @0D7: imul
		// @0D8: getstatic int game.C_100338_jc.field_105367_b
		// @0DB: idiv
		// @0DC: istore_2
		// @0DD: bipush -30 (0xE2)
		// @0DF: iload_2
		// @0E0: iadd
		// @0E1: istore_3
		// @0E2: getstatic boolean game.C_100145_ta.field_100427_l
		// @0E5: ifne @10D
		// @0E8: sipush 256 (0x0100)
		// @0EB: aload_1
		// @0EC: getfield int game.C_100037_wb.field_102341_y
		// @0EF: iload_3
		// @0F0: ineg
		// @0F1: iadd
		// @0F2: imul
		// @0F3: bipush 30 (0x1E)
		// @0F5: idiv
		// @0F6: sipush -256 (0xFF00)
		// @0F9: iload_3
		// @0FA: imul
		// @0FB: bipush 30 (0x1E)
		// @0FD: idiv
		// @0FE: sipush 199 (0x00C7)
		// @101: iconst_1
		// @102: aload_1
		// @103: sipush 245 (0x00F5)
		// @106: invokestatic game.C_100104_v.func_104678_a(int, int, int, boolean, game.C_100037_wb, int)void
		// @109: goto @12E
		// @10C: athrow
		// @10D: sipush -256 (0xFF00)
		// @110: iload_3
		// @111: imul
		// @112: bipush 30 (0x1E)
		// @114: idiv
		// @115: sipush 256 (0x0100)
		// @118: iload_3
		// @119: ineg
		// @11A: aload_1
		// @11B: getfield int game.C_100037_wb.field_102341_y
		// @11E: iadd
		// @11F: imul
		// @120: bipush 30 (0x1E)
		// @122: idiv
		// @123: sipush 199 (0x00C7)
		// @126: iconst_1
		// @127: aload_1
		// @128: sipush 245 (0x00F5)
		// @12B: invokestatic game.C_100104_v.func_104678_a(int, int, int, boolean, game.C_100037_wb, int)void
		// @12E: aconst_null
		// @12F: getstatic game.C_100112_r game.C_100003_ga.field_103541_q
		// @132: if_acmpeq @1F3
		// @135: aconst_null
		// @136: astore_2
		// @137: iconst_0
		// @138: istore_3
		// @139: iload_3
		// @13A: getstatic game.C_100037_wb[] game.C_100097_k.field_104584_a
		// @13D: arraylength
		// @13E: if_icmpge @19C
		// @141: getstatic game.C_100037_wb[] game.C_100097_k.field_104584_a
		// @144: iload_3
		// @145: aaload
		// @146: astore_1
		// @147: aload_1
		// @148: ifnull @196
		// @14B: aload_1
		// @14C: getfield int game.C_100037_wb.field_102341_y
		// @14F: iconst_m1
		// @150: ixor
		// @151: sipush -366 (0xFE92)
		// @154: if_icmpne @169
		// @157: goto @15B
		// @15A: athrow
		// @15B: sipush 139 (0x008B)
		// @15E: aload_1
		// @15F: getfield int game.C_100037_wb.field_102340_z
		// @162: if_icmpeq @196
		// @165: goto @169
		// @168: athrow
		// @169: aconst_null
		// @16A: aload_2
		// @16B: if_acmpeq @191
		// @16E: goto @172
		// @171: athrow
		// @172: new java.lang.StringBuilder
		// @175: dup
		// @176: invokespecial java.lang.StringBuilder.<init>()void
		// @179: aload_2
		// @17A: invokevirtual java.lang.StringBuilder.append(java.lang.String)java.lang.StringBuilder
		// @17D: getstatic java.lang.String[] game.C_100015_wh.field_103795_z
		// @180: bipush 6 (0x06)
		// @182: aaload
		// @183: invokevirtual java.lang.StringBuilder.append(java.lang.String)java.lang.StringBuilder
		// @186: iload_3
		// @187: invokevirtual java.lang.StringBuilder.append(int)java.lang.StringBuilder
		// @18A: invokevirtual java.lang.StringBuilder.toString()java.lang.String
		// @18D: astore_2
		// @18E: goto @196
		// @191: iload_3
		// @192: invokestatic java.lang.Integer.toString(int)java.lang.String
		// @195: astore_2
		// @196: iinc #3 +1
		// @199: goto @139
		// @19C: aconst_null
		// @19D: aload_2
		// @19E: if_acmpne @1A5
		// @1A1: goto @1F3
		// @1A4: athrow
		// @1A5: getstatic game.C_100112_r game.C_100003_ga.field_103541_q
		// @1A8: new java.lang.StringBuilder
		// @1AB: dup
		// @1AC: invokespecial java.lang.StringBuilder.<init>()void
		// @1AF: getstatic java.lang.String[] game.C_100015_wh.field_103795_z
		// @1B2: bipush 9 (0x09)
		// @1B4: aaload
		// @1B5: invokevirtual java.lang.StringBuilder.append(java.lang.String)java.lang.StringBuilder
		// @1B8: aload_2
		// @1B9: invokevirtual java.lang.StringBuilder.append(java.lang.String)java.lang.StringBuilder
		// @1BC: getstatic java.lang.String[] game.C_100015_wh.field_103795_z
		// @1BF: bipush 7 (0x07)
		// @1C1: aaload
		// @1C2: invokevirtual java.lang.StringBuilder.append(java.lang.String)java.lang.StringBuilder
		// @1C5: sipush 365 (0x016D)
		// @1C8: invokevirtual java.lang.StringBuilder.append(int)java.lang.StringBuilder
		// @1CB: getstatic java.lang.String[] game.C_100015_wh.field_103795_z
		// @1CE: bipush 8 (0x08)
		// @1D0: aaload
		// @1D1: invokevirtual java.lang.StringBuilder.append(java.lang.String)java.lang.StringBuilder
		// @1D4: sipush 139 (0x008B)
		// @1D7: invokevirtual java.lang.StringBuilder.append(int)java.lang.StringBuilder
		// @1DA: invokevirtual java.lang.StringBuilder.toString()java.lang.String
		// @1DD: sipush 245 (0x00F5)
		// @1E0: sipush 199 (0x00C7)
		// @1E3: sipush 365 (0x016D)
		// @1E6: sipush 139 (0x008B)
		// @1E9: ldc 16737843 (0xff6633)
		// @1EB: iconst_0
		// @1EC: iconst_1
		// @1ED: iconst_1
		// @1EE: iconst_0
		// @1EF: invokevirtual game.C_100112_r.func_101729_a(java.lang.String, int, int, int, int, int, int, int, int, int)int
		// @1F2: pop
		// @1F3: goto @218
		// @1F6: astore_1
		// @1F7: aload_1
		// @1F8: new java.lang.StringBuilder
		// @1FB: dup
		// @1FC: invokespecial java.lang.StringBuilder.<init>()void
		// @1FF: getstatic java.lang.String[] game.C_100015_wh.field_103795_z
		// @202: bipush 10 (0x0A)
		// @204: aaload
		// @205: invokevirtual java.lang.StringBuilder.append(java.lang.String)java.lang.StringBuilder
		// @208: iload_0
		// @209: invokevirtual java.lang.StringBuilder.append(int)java.lang.StringBuilder
		// @20C: bipush 41 (0x29)
		// @20E: invokevirtual java.lang.StringBuilder.append(char)java.lang.StringBuilder
		// @211: invokevirtual java.lang.StringBuilder.toString()java.lang.String
		// @214: invokestatic game.C_100181_cf.func_105695_a(java.lang.Throwable, java.lang.String)game.C_100170_cm
		// @217: athrow
		// @218: return
	}
	
	static
	{
		// @000: bipush 13 (0x0D)
		// @002: anewarray java.lang.String
		// @005: dup
		// @006: iconst_0
		// @007: ldc "2DrJ"
		// @009: invokestatic game.C_100015_wh.func_103777_z(java.lang.String)char[]
		// @00C: invokestatic game.C_100015_wh.func_103776_z(char[])java.lang.String
		// @00F: aastore
		// @010: dup
		// @011: iconst_1
		// @012: ldc "(DvUD=E|SD"
		// @014: invokestatic game.C_100015_wh.func_103777_z(java.lang.String)char[]
		// @017: invokestatic game.C_100015_wh.func_103776_z(char[])java.lang.String
		// @01A: aastore
		// @01B: dup
		// @01C: iconst_2
		// @01D: ldc "'\u001f0\u0008M"
		// @01F: invokestatic game.C_100015_wh.func_103777_z(java.lang.String)char[]
		// @022: invokestatic game.C_100015_wh.func_103776_z(char[])java.lang.String
		// @025: aastore
		// @026: dup
		// @027: iconst_3
		// @028: ldc "+Y0c\u0018"
		// @02A: invokestatic game.C_100015_wh.func_103777_z(java.lang.String)char[]
		// @02D: invokestatic game.C_100015_wh.func_103776_z(char[])java.lang.String
		// @030: aastore
		// @031: dup
		// @032: iconst_4
		// @033: ldc ".GpGT0\\"
		// @035: invokestatic game.C_100015_wh.func_103777_z(java.lang.String)char[]
		// @038: invokestatic game.C_100015_wh.func_103776_z(char[])java.lang.String
		// @03B: aastore
		// @03C: dup
		// @03D: iconst_5
		// @03E: ldc "+Y0b\u0018"
		// @040: invokestatic game.C_100015_wh.func_103777_z(java.lang.String)char[]
		// @043: invokestatic game.C_100015_wh.func_103776_z(char[])java.lang.String
		// @046: aastore
		// @047: dup
		// @048: bipush 6 (0x06)
		// @04A: ldc "p\u0011"
		// @04C: invokestatic game.C_100015_wh.func_103777_z(java.lang.String)char[]
		// @04F: invokestatic game.C_100015_wh.func_103776_z(char[])java.lang.String
		// @052: aastore
		// @053: dup
		// @054: bipush 7 (0x07)
		// @056: ldc "|Xm\tQ.T>RX9\u0011iT_2V>UY&T?\u0006c4^kJT|S{\u0006"
		// @058: invokestatic game.C_100015_wh.func_103777_z(java.lang.String)char[]
		// @05B: invokestatic game.C_100015_wh.func_103776_z(char[])java.lang.String
		// @05E: aastore
		// @05F: dup
		// @060: bipush 8 (0x08)
		// @062: ldc "`EwKU/\u000f"
		// @064: invokestatic game.C_100015_wh.func_103777_z(java.lang.String)char[]
		// @067: invokestatic game.C_100015_wh.func_103776_z(char[])java.lang.String
		// @06A: aastore
		// @06B: dup
		// @06C: bipush 9 (0x09)
		// @06E: ldc "\u000fRlCU2BvIDtB7\u0006"
		// @070: invokestatic game.C_100015_wh.func_103777_z(java.lang.String)char[]
		// @073: invokestatic game.C_100015_wh.func_103776_z(char[])java.lang.String
		// @076: aastore
		// @077: dup
		// @078: bipush 10 (0x0A)
		// @07A: ldc "+Y0d\u0018"
		// @07C: invokestatic game.C_100015_wh.func_103777_z(java.lang.String)char[]
		// @07F: invokestatic game.C_100015_wh.func_103776_z(char[])java.lang.String
		// @082: aastore
		// @083: dup
		// @084: bipush 11 (0x0B)
		// @086: ldc "+Y0g\u0018"
		// @088: invokestatic game.C_100015_wh.func_103777_z(java.lang.String)char[]
		// @08B: invokestatic game.C_100015_wh.func_103776_z(char[])java.lang.String
		// @08E: aastore
		// @08F: dup
		// @090: bipush 12 (0x0C)
		// @092: ldc "+Y0e\u0018"
		// @094: invokestatic game.C_100015_wh.func_103777_z(java.lang.String)char[]
		// @097: invokestatic game.C_100015_wh.func_103776_z(char[])java.lang.String
		// @09A: aastore
		// @09B: putstatic java.lang.String[] game.C_100015_wh.field_103795_z
		// @09E: iconst_0
		// @09F: putstatic int game.C_100015_wh.field_103781_g
		// @0A2: bipush 9 (0x09)
		// @0A4: newarray int[]
		// @0A6: dup
		// @0A7: iconst_0
		// @0A8: iconst_2
		// @0A9: iastore
		// @0AA: dup
		// @0AB: iconst_1
		// @0AC: bipush 20 (0x14)
		// @0AE: iastore
		// @0AF: dup
		// @0B0: iconst_2
		// @0B1: bipush 21 (0x15)
		// @0B3: iastore
		// @0B4: dup
		// @0B5: iconst_3
		// @0B6: bipush 6 (0x06)
		// @0B8: iastore
		// @0B9: dup
		// @0BA: iconst_4
		// @0BB: bipush 37 (0x25)
		// @0BD: iastore
		// @0BE: dup
		// @0BF: iconst_5
		// @0C0: bipush 45 (0x2D)
		// @0C2: iastore
		// @0C3: dup
		// @0C4: bipush 6 (0x06)
		// @0C6: iconst_5
		// @0C7: iastore
		// @0C8: dup
		// @0C9: bipush 7 (0x07)
		// @0CB: bipush 11 (0x0B)
		// @0CD: iastore
		// @0CE: dup
		// @0CF: bipush 8 (0x08)
		// @0D1: bipush 13 (0x0D)
		// @0D3: iastore
		// @0D4: putstatic int[] game.C_100015_wh.field_103788_o
		// @0D7: ldc "\u000cD|JY?"
		// @0D9: invokestatic game.C_100015_wh.func_103777_z(java.lang.String)char[]
		// @0DC: invokestatic game.C_100015_wh.func_103776_z(char[])java.lang.String
		// @0DF: putstatic java.lang.String game.C_100015_wh.field_103789_l
		// @0E2: ldc "\u000cPmUG3CzU\u00101DmR\u0010>T>DU(F{C^|\u0004>G^8\u0011,\u0016\u00100TjRU.B>G^8\u0011pS]>TlU"
		// @0E4: invokestatic game.C_100015_wh.func_103777_z(java.lang.String)char[]
		// @0E7: invokestatic game.C_100015_wh.func_103776_z(char[])java.lang.String
		// @0EA: putstatic java.lang.String game.C_100015_wh.field_103794_i
		// @0ED: ldc "\u001dR}C@(\u0011lC]=E}N"
		// @0EF: invokestatic game.C_100015_wh.func_103777_z(java.lang.String)char[]
		// @0F2: invokestatic game.C_100015_wh.func_103776_z(char[])java.lang.String
		// @0F5: putstatic java.lang.String game.C_100015_wh.field_103784_b
		// @0F8: iconst_2
		// @0F9: putstatic int game.C_100015_wh.field_103793_h
		// @0FC: bipush 12 (0x0C)
		// @0FE: anewarray java.lang.String
		// @101: dup
		// @102: iconst_0
		// @103: ldc "\u0008Y{\u0006w3]{K\u001d?]\u007fUC|B{HD5_{J\u00109_jCB9U>RX9\u0011iGB|Xp\u0006D4T>CQ.]g\u0006C(PyCC|Eq\u0006B9ArGS9\u0011}I^*TpRY3_\u007fJ\u0010=CsIE.\u001f>cF9_>R_|EvOC|U\u007f_\u00105E>TU1PwHC|P>UD.^pA\u0010+T\u007fV_2B>V\\=ExIB1\u0011xIB|BkV@3CjO^;\u0011jNU|]\u007fTW9C>EX=BmOCr"
		// @105: invokestatic game.C_100015_wh.func_103777_z(java.lang.String)char[]
		// @108: invokestatic game.C_100015_wh.func_103776_z(char[])java.lang.String
		// @10B: aastore
		// @10C: dup
		// @10D: iconst_1
		// @10E: ldc "\u000f]\u007fPUqRrGC/\u0011mC^(XpC\\/\u0011mVU?X\u007fJY/T>O^|RrIC5_y\u0006Y2\u0011\u007fHT|U{UD.^gO^;\u0011jGB;TjU\u0010=E>E\\3B{\u0006B=_yC\u001e|evCI|PlC\u0010:XjRU8\u0011iOD4\u0011nIG9CxS\\|]{ACp\u0011}G@=SrC\u00103W>JU=AwHW|^pR_|SkO\\8XpAC|WqT\u0010=UzCT|E\u007fED5R\u007fJ\u00101^hC]9_j\u0006Y2\u0011\u007f\u0006S3\\|GD|BwRE=EwI^r"
		// @110: invokestatic game.C_100015_wh.func_103777_z(java.lang.String)char[]
		// @113: invokestatic game.C_100015_wh.func_103776_z(char[])java.lang.String
		// @116: aastore
		// @117: dup
		// @118: iconst_2
		// @119: ldc "\u000bY{H\u0010/A{CT|PpB\u0010=R}SB=Rg\u0006Q.T>TU-DwTU8\u001d>RX9\u0011_WE5]\u007f\u000bS0PmU\u0010/RqSD|B{HD5_{J\u00105B>RX9\u0011lIR3E>@_.\u0011jNU|[qD\u001e|evC\u00108TxGE0E>BU/XyH\u00105B>@Y(E{B\u0010+XjN\u0010=\u0011jGB;TjO^;\u0011m_C(Ts\u0006V3C>VU.W{ED|P}EE.P}_\u0010+XjN\u00105Em\u0006\\=B{TCp\u0011\u007fHT|PrU_|PpRYqPwT\u0010/DnV_.E>@B3\\>OD/\u0011sOC/XrC\u0010/HmRU1B0"
		// @11B: invokestatic game.C_100015_wh.func_103777_z(java.lang.String)char[]
		// @11E: invokestatic game.C_100015_wh.func_103776_z(char[])java.lang.String
		// @121: aastore
		// @122: dup
		// @123: iconst_3
		// @124: ldc "\u0010^pA\u001d.PpAU|WwTU|BkV@3Cj\u0006Y/\u0011yTQ2E{B\u0010(YlIE;Y>RX9\u0011JSB(]{\u000bS0PmU\u0010/TpRY2Tr\u0008\u0010\u001aXjRU8\u0011iOD4\u0011sS\\(XnJU|Y{GF%\u0011lIS7TjU\u0010=_z\u0006Q2\u0011qTT2PpEU|F{G@3_>V_5_j\u0006_2\u0011wRC|S\u007fE[p\u0011\u007f\u0006S3_mRQ2E>DQ.C\u007fAU|^x\u0006T9BjTE?EwI^|R\u007fH\u0010>T>EB9PjCT|FvO\\9\u0011gIE|BrIG0H>GT*PpEUr"
		// @126: invokestatic game.C_100015_wh.func_103777_z(java.lang.String)char[]
		// @129: invokestatic game.C_100015_wh.func_103776_z(char[])java.lang.String
		// @12C: aastore
		// @12D: dup
		// @12E: iconst_4
		// @12F: ldc "\u001f^sKQ2Uq\u000bS0PmU\u0010/TpRY2TrU\u0010,CqPY8T>G\u0010,^iCB:Dr\u0006]5I>IV|tSv\u0010.^}MU(B2\u0006Q|]qHW|C\u007fHW9\u0011mHY,Tl\u0006S=_pI^|PpB\u0010?]qUUqC\u007fHW9\u0011mS@,^lR\u0010+XjN\u0010,]\u007fU]=\u0011\u007fHT|EvS^8Tl\u0006R0PzC\u001e"
		// @131: invokestatic game.C_100015_wh.func_103777_z(java.lang.String)char[]
		// @134: invokestatic game.C_100015_wh.func_103776_z(char[])java.lang.String
		// @137: aastore
		// @138: dup
		// @139: iconst_5
		// @13A: ldc "\u0008Y{\u0006x)ClOS=_{\u000bS0PmU\u0010/TpRY2Tr\u0006G=B>BU/XyHU8\u0011\u007fU\u0010=_>GU.X\u007fJ\u00101XmUY0T>V\\=ExIB1\u001f>oD|]{G@/\u0011wHD3\u0011jNU|PwT\u0010(^>JQ)_}N\u00105Em\u0006@=HrIQ8\u0011iNY0T>SD5]wUY2V>OD/\u0011lGY0\u0011yS^/\u0011xIB|]qHW|C\u007fHW9\u0011mHY,XpA\u001e"
		// @13C: invokestatic game.C_100015_wh.func_103777_z(java.lang.String)char[]
		// @13F: invokestatic game.C_100015_wh.func_103776_z(char[])java.lang.String
		// @142: aastore
		// @143: dup
		// @144: bipush 6 (0x06)
		// @146: ldc "\u0008Y{\u0006X5Vv\u000bC,T{B\u0010\u000fRqT@5^p\u000bS0PmU\u0010?Y\u007fUC5B>BU/ElII/\u0011jGB;TjU\u0010=E>E\\3B{\u0006B=_yC\u0010+XjN\u00105Em\u0006D3A3K_)_jCT|DrRB=\u0011yS^p\u0011iNY0T>MU9AwHW|PwT\u00108TxC^?Tm\u0006U2P|JU8\u0011iOD4\u0011jGB;TjCT|]\u007fUU.\u0011|CQ1B0"
		// @148: invokestatic game.C_100015_wh.func_103777_z(java.lang.String)char[]
		// @14B: invokestatic game.C_100015_wh.func_103776_z(char[])java.lang.String
		// @14E: aastore
		// @14F: dup
		// @150: bipush 7 (0x07)
		// @152: ldc "\u001dB>RX9\u0011iGB|AlIW.TmUU8\u001d>CQ.]wCB|B{HD5_{JC|F{TU|C{V\\=R{B\u0010+XjN\u0010(Y{\u0006X9PhOU.\u0011]TE/Y{T\u001d?]\u007fUCr\u0011XCQ(DlO^;\u0011\u007f\u0006R=Ru\u000b]3DpRU8\u0011qTT2PpEU|BrIDp\u0011mR_.\\vG]1Tl\n\u0010(YlSC(TlU\u0010=_z\u0006Q|C\u007fHW9\u0011q@\u0010+T\u007fV_2\u0011nIY2Em\n\u0010(YwU\u0010/TpRY2Tr\u0006@.^hOT9U>QU0]3UE,AqTD9U>V_+Tl\u0006V3C>G^%\u0011mOD)PjO_2\u001f"
		// @154: invokestatic game.C_100015_wh.func_103777_z(java.lang.String)char[]
		// @157: invokestatic game.C_100015_wh.func_103776_z(char[])java.lang.String
		// @15A: aastore
		// @15B: dup
		// @15C: bipush 8 (0x08)
		// @15E: ldc "\u0008Y{\u0006S3]qUC=]>dU.EvG\u001d?]\u007fUC|B{HD5_{J\u0010+Pm\u0006_2T>IV|EvC\u0010:XlUD|RvGC/Xm\u0006T9BwA^/\u0011jI\u0010>T>SC9U>O^|EvC\u0010+Pl\u0008\u0010\u0010^i\u000bD9Rv\n\u0010>Dj\u0006]=BmOF9\u0011wH\u00108TmOW2\u001d>OD|C{JY9B>I^|^kR\\=BjO^;\u0011wRC|^nV_2TpRC|PpB\u00108T\u007fJY2V>KQ/BwPU|U\u007fKQ;T>GD|]qHW|C\u007fHW9\u0011iOD4\u0011wRC|Y{GF%\u0011lIS7Tj\u0006C%BjC]/\u001f"
		// @160: invokestatic game.C_100015_wh.func_103777_z(java.lang.String)char[]
		// @163: invokestatic game.C_100015_wh.func_103776_z(char[])java.lang.String
		// @166: aastore
		// @167: dup
		// @168: bipush 9 (0x09)
		// @16A: ldc "\u0013_r_\u00106DmR\u00109_jCB5_y\u0006_,TlGD5^p\n\u0010(Y{\u0006\u007f.SwRQ0\u001c}JQ/B>UU2EwHU0\u0011iGC|U{UY;_{B\u0010(^>DU|P>U@=R{\u000bR3CpC\u0010+T\u007fV_2B>V\\=ExIB1\u001f>gD|EvC\u00100PmR\u00101^sC^(\u001d>N_+ThCBp\u0011wR\u0010+Pm\u0006S3_hCB(Tz\u0006V3C>GD1^mVX9CwE\u0010)B{\n\u0010+XjN\u0010(Y{\u0006Q8UwRY3_>IV|TfRB=\u0011vCQ*H>AE2B>@_.\u0011sOC/XrC\u00108TxC^?T0"
		// @16C: invokestatic game.C_100015_wh.func_103777_z(java.lang.String)char[]
		// @16F: invokestatic game.C_100015_wh.func_103776_z(char[])java.lang.String
		// @172: aastore
		// @173: dup
		// @174: bipush 10 (0x0A)
		// @176: ldc "\u001dB>RX9\u0011sIC(\u0011\u007fBF=_}CT|B{HD5_{J\u0010+XjNY2\u0011jNU|F\u007fT\u001c|EvC\u0010\nPrNQ0]\u007f\u000bS0PmU\u00108TmOW2\u0011wU\u0010:T\u007fTU8\u0011|_\u0010?^sKQ2U{TC|EvT_)VvIE(\u0011jNU|BgUD9\\m\u0008\u0010\u0015E>E_2E\u007fO^/\u0011mRQ(T3IVqEvC\u001d=Cj\u0006U2TlAI|F{G@3_m\u0006D3\u0011zCQ0\u0011iOD4\u0011\u007fJ\\|\\\u007fH^9C>IV|BwRE=EwI^/\u001d>GC|F{J\\|Pm\u0006D4T>BU*PmRQ(XpA\u0010:DmO_2\u0011|JQ8T>@_.\u0011}J_/T3TQ2V{\u0006T9R\u007fVY(PjO_2\u001f"
		// @178: invokestatic game.C_100015_wh.func_103777_z(java.lang.String)char[]
		// @17B: invokestatic game.C_100015_wh.func_103776_z(char[])java.lang.String
		// @17E: aastore
		// @17F: dup
		// @180: bipush 11 (0x0B)
		// @182: ldc "\u0008Y{\u0006V5CmR\u0010=_z\u0006\\=Bj\u0006r=S{J\u001d?]\u007fUC|B{HD5_{J\u0010/E\u007fTD9U>RX9\u0011iGBr\u0011JNU|s\u007fDU0\u0011rG^8Tz\u0006_2\u0011WJ_0X\u007fH\u0010\u000cCwKUp\u0011\u007fHT|AlIS9TzCT|Eq\u0006T9BjT_%\u0011jNU|FvI\\9\u0011nJQ2TjGB%\u0011zCV9_}C\u0010:^lEU|^hCB|F{C[/\u0011q@\u0010:XyND5_y\u0008\u0010\u001f^sKQ2U{TC|EvT_)VvIE(\u0011jNU|BgUD9\\m\u0006[2Ti\u0006Q(\u0011jNY/\u0011nIY2E>RX=E>RX9\u0011qJT|F\u007fTC|Y\u007fB\u00109_zCTp\u0011\u007fHT|EvC\u0010=V{\u0006_:\u0011jNU|B{HD5_{J\u00104Pz\u0006R9VkH\u001e"
		// @184: invokestatic game.C_100015_wh.func_103777_z(java.lang.String)char[]
		// @187: invokestatic game.C_100015_wh.func_103776_z(char[])java.lang.String
		// @18A: aastore
		// @18B: putstatic java.lang.String[] game.C_100015_wh.field_103791_j
		// @18E: return
	}
	
	private static char[] func_103777_z(String arg0)
	{
		// @00: aload_0
		// @01: invokevirtual java.lang.String.toCharArray()char[]
		// @04: dup
		// @05: arraylength
		// @06: iconst_2
		// @07: if_icmpge @13
		// @0A: dup
		// @0B: iconst_0
		// @0C: dup2
		// @0D: caload
		// @0E: bipush 48 (0x30)
		// @10: ixor
		// @11: i2c
		// @12: castore
		// @13: areturn
	}
	
	private static String func_103776_z(char[] arg0)
	{
		// @00: aload_0
		// @01: dup
		// @02: arraylength
		// @03: swap
		// @04: iconst_0
		// @05: istore_1
		// @06: goto @4C
		// @09: dup
		// @0A: iload_1
		// @0B: dup2
		// @0C: caload
		// @0D: iload_1
		// @0E: iconst_5
		// @0F: irem
		// @10: tableswitch def: @44, for 0: @30, for 1: @35, for 2: @3A, for 3: @3F
		// @30: bipush 92 (0x5C)
		// @32: goto @46
		// @35: bipush 49 (0x31)
		// @37: goto @46
		// @3A: bipush 30 (0x1E)
		// @3C: goto @46
		// @3F: bipush 38 (0x26)
		// @41: goto @46
		// @44: bipush 48 (0x30)
		// @46: ixor
		// @47: i2c
		// @48: castore
		// @49: iinc #1 +1
		// @4C: swap
		// @4D: dup_x1
		// @4E: iload_1
		// @4F: if_icmpgt @09
		// @52: new java.lang.String
		// @55: dup_x1
		// @56: swap
		// @57: invokespecial java.lang.String.<init>(char[])void
		// @5A: invokevirtual java.lang.String.intern()java.lang.String
		// @5D: areturn
	}
}
