package game;

final class C_100020_wm
{
	static String[] field_103857_c;
	static C_100302_ka field_103858_a;
	static boolean[] field_103854_d;
	static String field_103855_e;
	static C_100037_wb[] field_103856_b;
	private static final String[] field_103859_z;
	
	static final void func_103853_a(int arg0, int arg1)
	{
		// @00: iload_1
		// @01: ldc 1312559792 (0x4e3c12b0)
		// @03: ishl
		// @04: sipush 150 (0x0096)
		// @07: idiv
		// @08: putstatic int game.C_100031_gl.field_103966_b
		// @0B: bipush 100 (0x64)
		// @0D: iload_1
		// @0E: imul
		// @0F: sipush 150 (0x0096)
		// @12: idiv
		// @13: putstatic int game.C_100031_gl.field_103962_f
		// @16: iload_0
		// @17: iload_1
		// @18: imul
		// @19: sipush 150 (0x0096)
		// @1C: idiv
		// @1D: putstatic int game.C_100031_gl.field_103969_j
		// @20: goto @4D
		// @23: astore_2
		// @24: aload_2
		// @25: new java.lang.StringBuilder
		// @28: dup
		// @29: invokespecial java.lang.StringBuilder.<init>()void
		// @2C: getstatic java.lang.String[] game.C_100020_wm.field_103859_z
		// @2F: iconst_5
		// @30: aaload
		// @31: invokevirtual java.lang.StringBuilder.append(java.lang.String)java.lang.StringBuilder
		// @34: iload_0
		// @35: invokevirtual java.lang.StringBuilder.append(int)java.lang.StringBuilder
		// @38: bipush 44 (0x2C)
		// @3A: invokevirtual java.lang.StringBuilder.append(char)java.lang.StringBuilder
		// @3D: iload_1
		// @3E: invokevirtual java.lang.StringBuilder.append(int)java.lang.StringBuilder
		// @41: bipush 41 (0x29)
		// @43: invokevirtual java.lang.StringBuilder.append(char)java.lang.StringBuilder
		// @46: invokevirtual java.lang.StringBuilder.toString()java.lang.String
		// @49: invokestatic game.C_100181_cf.func_105695_a(java.lang.Throwable, java.lang.String)game.C_100170_cm
		// @4C: athrow
		// @4D: return
	}
	
	public static void func_103850_a(byte arg0)
	{
		// @00: aconst_null
		// @01: putstatic game.C_100302_ka game.C_100020_wm.field_103858_a
		// @04: aconst_null
		// @05: putstatic java.lang.String game.C_100020_wm.field_103855_e
		// @08: aconst_null
		// @09: putstatic game.C_100037_wb[] game.C_100020_wm.field_103856_b
		// @0C: aconst_null
		// @0D: putstatic boolean[] game.C_100020_wm.field_103854_d
		// @10: iload_0
		// @11: bipush -69 (0xBB)
		// @13: if_icmplt @21
		// @16: aconst_null
		// @17: checkcast java.lang.String
		// @1A: putstatic java.lang.String game.C_100020_wm.field_103855_e
		// @1D: goto @21
		// @20: athrow
		// @21: aconst_null
		// @22: putstatic java.lang.String[] game.C_100020_wm.field_103857_c
		// @25: goto @49
		// @28: astore_1
		// @29: aload_1
		// @2A: new java.lang.StringBuilder
		// @2D: dup
		// @2E: invokespecial java.lang.StringBuilder.<init>()void
		// @31: getstatic java.lang.String[] game.C_100020_wm.field_103859_z
		// @34: iconst_0
		// @35: aaload
		// @36: invokevirtual java.lang.StringBuilder.append(java.lang.String)java.lang.StringBuilder
		// @39: iload_0
		// @3A: invokevirtual java.lang.StringBuilder.append(int)java.lang.StringBuilder
		// @3D: bipush 41 (0x29)
		// @3F: invokevirtual java.lang.StringBuilder.append(char)java.lang.StringBuilder
		// @42: invokevirtual java.lang.StringBuilder.toString()java.lang.String
		// @45: invokestatic game.C_100181_cf.func_105695_a(java.lang.Throwable, java.lang.String)game.C_100170_cm
		// @48: athrow
		// @49: return
	}
	
	static final boolean func_103852_a(int arg0)
	{
		// @00: getstatic int game.SteelSentinels.field_105275_O
		// @03: istore #6
		// @05: bipush 52 (0x34)
		// @07: invokestatic game.C_100198_qn.func_105828_a(byte)long
		// @0A: lstore_1
		// @0B: getstatic long game.C_100340_je.field_102977_p
		// @0E: lneg
		// @0F: lload_1
		// @10: ladd
		// @11: lstore_3
		// @12: iload_0
		// @13: ifeq @21
		// @16: aconst_null
		// @17: checkcast boolean[]
		// @1A: putstatic boolean[] game.C_100020_wm.field_103854_d
		// @1D: goto @21
		// @20: athrow
		// @21: lload_3
		// @22: ldc2_w 30000
		// @25: lcmp
		// @26: ifgt @8A
		// @29: sipush 3000 (0x0BB8)
		// @2C: istore #5
		// @2E: bipush -8 (0xF8)
		// @30: getstatic int game.C_100142_bk.field_105087_e
		// @33: iconst_m1
		// @34: ixor
		// @35: if_icmplt @42
		// @38: sipush 12000 (0x2EE0)
		// @3B: istore #5
		// @3D: iload #6
		// @3F: ifeq @67
		// @42: iconst_5
		// @43: getstatic int game.C_100142_bk.field_105087_e
		// @46: if_icmpgt @57
		// @49: goto @4D
		// @4C: athrow
		// @4D: sipush 9000 (0x2328)
		// @50: istore #5
		// @52: iload #6
		// @54: ifeq @67
		// @57: getstatic int game.C_100142_bk.field_105087_e
		// @5A: iconst_3
		// @5B: if_icmplt @67
		// @5E: goto @62
		// @61: athrow
		// @62: sipush 6000 (0x1770)
		// @65: istore #5
		// @67: lload_3
		// @68: ldc2_w -1
		// @6B: lxor
		// @6C: iload #5
		// @6E: i2l
		// @6F: ldc2_w -1
		// @72: lxor
		// @73: lcmp
		// @74: ifge @85
		// @77: getstatic int game.C_100142_bk.field_105087_e
		// @7A: iconst_1
		// @7B: iadd
		// @7C: putstatic int game.C_100142_bk.field_105087_e
		// @7F: lload_1
		// @80: putstatic long game.C_100340_je.field_102977_p
		// @83: iconst_1
		// @84: ireturn
		// @85: iload #6
		// @87: ifeq @94
		// @8A: lload_1
		// @8B: putstatic long game.C_100340_je.field_102977_p
		// @8E: iconst_0
		// @8F: putstatic int game.C_100142_bk.field_105087_e
		// @92: iconst_1
		// @93: ireturn
		// @94: iconst_0
		// @95: ireturn
		// @96: astore_1
		// @97: aload_1
		// @98: new java.lang.StringBuilder
		// @9B: dup
		// @9C: invokespecial java.lang.StringBuilder.<init>()void
		// @9F: getstatic java.lang.String[] game.C_100020_wm.field_103859_z
		// @A2: iconst_4
		// @A3: aaload
		// @A4: invokevirtual java.lang.StringBuilder.append(java.lang.String)java.lang.StringBuilder
		// @A7: iload_0
		// @A8: invokevirtual java.lang.StringBuilder.append(int)java.lang.StringBuilder
		// @AB: bipush 41 (0x29)
		// @AD: invokevirtual java.lang.StringBuilder.append(char)java.lang.StringBuilder
		// @B0: invokevirtual java.lang.StringBuilder.toString()java.lang.String
		// @B3: invokestatic game.C_100181_cf.func_105695_a(java.lang.Throwable, java.lang.String)game.C_100170_cm
		// @B6: athrow
	}
	
	static final C_100182_cc func_103848_a(byte arg0, byte[] arg1)
	{
		// @00: aconst_null
		// @01: aload_1
		// @02: if_acmpeq @09
		// @05: goto @0B
		// @08: athrow
		// @09: aconst_null
		// @0A: areturn
		// @0B: new game.C_100182_cc
		// @0E: dup
		// @0F: aload_1
		// @10: getstatic int[] game.C_100068_vc.field_104340_f
		// @13: getstatic int[] game.C_100012_fh.field_100509_M
		// @16: getstatic int[] game.C_100213_ak.field_105994_d
		// @19: getstatic int[] game.C_100312_ld.field_107156_c
		// @1C: getstatic int[] game.C_100085_a.field_102573_H
		// @1F: getstatic byte[][] game.C_100107_u.field_104774_c
		// @22: invokespecial game.C_100182_cc.<init>(byte[], int[], int[], int[], int[], int[], byte[][])void
		// @25: astore_2
		// @26: bipush 65 (0x41)
		// @28: invokestatic game.C_100030_gm.func_103336_a(byte)void
		// @2B: iload_0
		// @2C: bipush -60 (0xC4)
		// @2E: if_icmple @3B
		// @31: bipush -89 (0xA7)
		// @33: invokestatic game.C_100020_wm.func_103852_a(int)boolean
		// @36: pop
		// @37: goto @3B
		// @3A: athrow
		// @3B: aload_2
		// @3C: areturn
		// @3D: astore_2
		// @3E: aload_2
		// @3F: new java.lang.StringBuilder
		// @42: dup
		// @43: invokespecial java.lang.StringBuilder.<init>()void
		// @46: getstatic java.lang.String[] game.C_100020_wm.field_103859_z
		// @49: iconst_2
		// @4A: aaload
		// @4B: invokevirtual java.lang.StringBuilder.append(java.lang.String)java.lang.StringBuilder
		// @4E: iload_0
		// @4F: invokevirtual java.lang.StringBuilder.append(int)java.lang.StringBuilder
		// @52: bipush 44 (0x2C)
		// @54: invokevirtual java.lang.StringBuilder.append(char)java.lang.StringBuilder
		// @57: aload_1
		// @58: ifnull @64
		// @5B: getstatic java.lang.String[] game.C_100020_wm.field_103859_z
		// @5E: iconst_3
		// @5F: aaload
		// @60: goto @69
		// @63: athrow
		// @64: getstatic java.lang.String[] game.C_100020_wm.field_103859_z
		// @67: iconst_1
		// @68: aaload
		// @69: invokevirtual java.lang.StringBuilder.append(java.lang.String)java.lang.StringBuilder
		// @6C: bipush 41 (0x29)
		// @6E: invokevirtual java.lang.StringBuilder.append(char)java.lang.StringBuilder
		// @71: invokevirtual java.lang.StringBuilder.toString()java.lang.String
		// @74: invokestatic game.C_100181_cf.func_105695_a(java.lang.Throwable, java.lang.String)game.C_100170_cm
		// @77: athrow
	}
	
	static
	{
		// @00: bipush 6 (0x06)
		// @02: anewarray java.lang.String
		// @05: dup
		// @06: iconst_0
		// @07: ldc "(~C3\u0015"
		// @09: invokestatic game.C_100020_wm.func_103851_z(java.lang.String)char[]
		// @0C: invokestatic game.C_100020_wm.func_103849_z(char[])java.lang.String
		// @0F: aastore
		// @10: dup
		// @11: iconst_1
		// @12: ldc "1f\u0001\u001d"
		// @14: invokestatic game.C_100020_wm.func_103851_z(java.lang.String)char[]
		// @17: invokestatic game.C_100020_wm.func_103849_z(char[])java.lang.String
		// @1A: aastore
		// @1B: dup
		// @1C: iconst_2
		// @1D: ldc "(~C2\u0015"
		// @1F: invokestatic game.C_100020_wm.func_103851_z(java.lang.String)char[]
		// @22: invokestatic game.C_100020_wm.func_103849_z(char[])java.lang.String
		// @25: aastore
		// @26: dup
		// @27: iconst_3
		// @28: ldc "$=C_@"
		// @2A: invokestatic game.C_100020_wm.func_103851_z(java.lang.String)char[]
		// @2D: invokestatic game.C_100020_wm.func_103849_z(char[])java.lang.String
		// @30: aastore
		// @31: dup
		// @32: iconst_4
		// @33: ldc "(~C0\u0015"
		// @35: invokestatic game.C_100020_wm.func_103851_z(java.lang.String)char[]
		// @38: invokestatic game.C_100020_wm.func_103849_z(char[])java.lang.String
		// @3B: aastore
		// @3C: dup
		// @3D: iconst_5
		// @3E: ldc "(~C5\u0015"
		// @40: invokestatic game.C_100020_wm.func_103851_z(java.lang.String)char[]
		// @43: invokestatic game.C_100020_wm.func_103849_z(char[])java.lang.String
		// @46: aastore
		// @47: putstatic java.lang.String[] game.C_100020_wm.field_103859_z
		// @4A: iconst_2
		// @4B: anewarray java.lang.String
		// @4E: dup
		// @4F: iconst_0
		// @50: ldc "\u0017|\u0001\u0015\u001dcz\u0000\u0016\u0000m%SQ\\1wM\u0015O>tM\u0005R\u007f~\u0002\u0007X\u007fg\u0005\u0014\u001d<r\u0000\u0014O>=Q\u0013Oa4,V\u0011x@J]\u001a\u001b4M\u0012R1g\u001f\u001eQ\u007fd\u000c\u001dV6}\n_\u0001=aSVjx3\u0007\u0004P/="
		// @52: invokestatic game.C_100020_wm.func_103851_z(java.lang.String)char[]
		// @55: invokestatic game.C_100020_wm.func_103849_z(char[])java.lang.String
		// @58: aastore
		// @59: dup
		// @5A: iconst_1
		// @5B: ldc "xDJ]\u001a\u001e4AVnx?J5\u001a\u007f~\u0002\u0007X\u007fg\u0005\u0014\u001d<r\u0000\u0014O>=Q\u0013Oa47V\u0011xKJ]\u001a\u001c4M\u0012R1g\u001f\u001eQ\u007fd\u000c\u001dV6}\n_\u0001=aSMT2tPC\u000ba3\u0002\u0003\u001d\u007f4>9t\u0019GJZ\u00016~\nL\u000fj-M\u001bH2cC"
		// @5D: invokestatic game.C_100020_wm.func_103851_z(java.lang.String)char[]
		// @60: invokestatic game.C_100020_wm.func_103849_z(char[])java.lang.String
		// @63: aastore
		// @64: putstatic java.lang.String[] game.C_100020_wm.field_103857_c
		// @67: ldc "\u001c\\ !q\u001aG("
		// @69: invokestatic game.C_100020_wm.func_103851_z(java.lang.String)char[]
		// @6C: invokestatic game.C_100020_wm.func_103849_z(char[])java.lang.String
		// @6F: putstatic java.lang.String game.C_100020_wm.field_103855_e
		// @72: return
	}
	
	private static char[] func_103851_z(String arg0)
	{
		// @00: aload_0
		// @01: invokevirtual java.lang.String.toCharArray()char[]
		// @04: dup
		// @05: arraylength
		// @06: iconst_2
		// @07: if_icmpge @13
		// @0A: dup
		// @0B: iconst_0
		// @0C: dup2
		// @0D: caload
		// @0E: bipush 61 (0x3D)
		// @10: ixor
		// @11: i2c
		// @12: castore
		// @13: areturn
	}
	
	private static String func_103849_z(char[] arg0)
	{
		// @00: aload_0
		// @01: dup
		// @02: arraylength
		// @03: swap
		// @04: iconst_0
		// @05: istore_1
		// @06: goto @4C
		// @09: dup
		// @0A: iload_1
		// @0B: dup2
		// @0C: caload
		// @0D: iload_1
		// @0E: iconst_5
		// @0F: irem
		// @10: tableswitch def: @44, for 0: @30, for 1: @35, for 2: @3A, for 3: @3F
		// @30: bipush 95 (0x5F)
		// @32: goto @46
		// @35: bipush 19 (0x13)
		// @37: goto @46
		// @3A: bipush 109 (0x6D)
		// @3C: goto @46
		// @3F: bipush 113 (0x71)
		// @41: goto @46
		// @44: bipush 61 (0x3D)
		// @46: ixor
		// @47: i2c
		// @48: castore
		// @49: iinc #1 +1
		// @4C: swap
		// @4D: dup_x1
		// @4E: iload_1
		// @4F: if_icmpgt @09
		// @52: new java.lang.String
		// @55: dup_x1
		// @56: swap
		// @57: invokespecial java.lang.String.<init>(char[])void
		// @5A: invokevirtual java.lang.String.intern()java.lang.String
		// @5D: areturn
	}
}
