package game;

abstract class C_100136_th extends C_100085_a
{
	static String[] field_102616_U;
	static int field_102620_Q;
	boolean field_102619_V;
	private C_100029_gn field_102628_Z;
	static C_100037_wb field_102627_X;
	static C_100302_ka[] field_102618_W;
	static C_100037_wb field_102626_Y;
	static String field_102622_S;
	static String field_102621_P;
	private int field_102617_T;
	static C_100022_hf field_102623_R;
	static String field_102624_ab;
	private static final String[] field_102625_bb;
	
	static final void func_102605_a(byte arg0, boolean arg1)
	{
		// @00: getstatic game.C_100302_ka game.C_100265_mh.field_106621_l
		// @03: bipush -126 (0x82)
		// @05: iload_1
		// @06: invokevirtual game.C_100302_ka.func_101809_a(byte, boolean)void
		// @09: bipush -118 (0x8A)
		// @0B: iload_0
		// @0C: bipush 93 (0x5D)
		// @0E: isub
		// @0F: bipush 32 (0x20)
		// @11: idiv
		// @12: idiv
		// @13: istore_3
		// @14: getstatic game.C_100320_hh game.C_100047_vh.field_104150_d
		// @17: astore_2
		// @18: aconst_null
		// @19: aload_2
		// @1A: if_acmpeq @32
		// @1D: aload_2
		// @1E: getstatic game.C_100302_ka game.C_100265_mh.field_106621_l
		// @21: getfield int game.C_100302_ka.field_101835_xb
		// @24: getstatic game.C_100302_ka game.C_100265_mh.field_106621_l
		// @27: getfield int game.C_100302_ka.field_101840_Eb
		// @2A: iconst_0
		// @2B: invokevirtual game.C_100320_hh.func_102523_a(int, int, int)void
		// @2E: goto @32
		// @31: athrow
		// @32: goto @5F
		// @35: astore_2
		// @36: aload_2
		// @37: new java.lang.StringBuilder
		// @3A: dup
		// @3B: invokespecial java.lang.StringBuilder.<init>()void
		// @3E: getstatic java.lang.String[] game.C_100136_th.field_102625_bb
		// @41: iconst_1
		// @42: aaload
		// @43: invokevirtual java.lang.StringBuilder.append(java.lang.String)java.lang.StringBuilder
		// @46: iload_0
		// @47: invokevirtual java.lang.StringBuilder.append(int)java.lang.StringBuilder
		// @4A: bipush 44 (0x2C)
		// @4C: invokevirtual java.lang.StringBuilder.append(char)java.lang.StringBuilder
		// @4F: iload_1
		// @50: invokevirtual java.lang.StringBuilder.append(boolean)java.lang.StringBuilder
		// @53: bipush 41 (0x29)
		// @55: invokevirtual java.lang.StringBuilder.append(char)java.lang.StringBuilder
		// @58: invokevirtual java.lang.StringBuilder.toString()java.lang.String
		// @5B: invokestatic game.C_100181_cf.func_105695_a(java.lang.Throwable, java.lang.String)game.C_100170_cm
		// @5E: athrow
		// @5F: return
	}
	
	final void func_102528_a(int arg0, int arg1, int arg2, byte arg3)
	{
		// @000: aload_0
		// @001: getfield int game.C_100136_th.field_102617_T
		// @004: ifne @008
		// @007: return
		// @008: sipush -257 (0xFEFF)
		// @00B: aload_0
		// @00C: getfield int game.C_100136_th.field_102617_T
		// @00F: iconst_m1
		// @010: ixor
		// @011: if_icmpge @018
		// @014: goto @03E
		// @017: athrow
		// @018: iload_1
		// @019: iconst_m1
		// @01A: ixor
		// @01B: iconst_m1
		// @01C: if_icmpeq @020
		// @01F: return
		// @020: aload_0
		// @021: bipush -27 (0xE5)
		// @023: iload_3
		// @024: aload_0
		// @025: getfield int game.C_100136_th.field_102538_m
		// @028: ineg
		// @029: isub
		// @02A: iload_2
		// @02B: aload_0
		// @02C: getfield int game.C_100136_th.field_102541_w
		// @02F: ineg
		// @030: isub
		// @031: invokevirtual game.C_100136_th.func_102607_a(byte, int, int)void
		// @034: aload_0
		// @035: iload_1
		// @036: iload_2
		// @037: iload_3
		// @038: bipush -128 (0x80)
		// @03A: invokespecial game.C_100085_a.func_102528_a(int, int, int, byte)void
		// @03D: return
		// @03E: getstatic game.C_100037_wb game.C_100272_mn.field_102433_I
		// @041: ifnull @06A
		// @044: getstatic game.C_100037_wb game.C_100272_mn.field_102433_I
		// @047: getfield int game.C_100037_wb.field_102339_s
		// @04A: iconst_m1
		// @04B: ixor
		// @04C: aload_0
		// @04D: getfield int game.C_100136_th.field_102537_l
		// @050: iconst_m1
		// @051: ixor
		// @052: if_icmpgt @06A
		// @055: goto @059
		// @058: athrow
		// @059: aload_0
		// @05A: getfield int game.C_100136_th.field_102544_t
		// @05D: getstatic game.C_100037_wb game.C_100272_mn.field_102433_I
		// @060: getfield int game.C_100037_wb.field_102337_u
		// @063: if_icmple @080
		// @066: goto @06A
		// @069: athrow
		// @06A: new game.C_100037_wb
		// @06D: dup
		// @06E: aload_0
		// @06F: getfield int game.C_100136_th.field_102537_l
		// @072: aload_0
		// @073: getfield int game.C_100136_th.field_102544_t
		// @076: invokespecial game.C_100037_wb.<init>(int, int)void
		// @079: putstatic game.C_100037_wb game.C_100272_mn.field_102433_I
		// @07C: goto @080
		// @07F: athrow
		// @080: getstatic game.C_100037_wb game.C_100272_mn.field_102433_I
		// @083: bipush -4 (0xFC)
		// @085: invokestatic game.C_100138_bo.func_100398_a(game.C_100037_wb, int)void
		// @088: invokestatic game.C_100196_rb.func_105792_b()void
		// @08B: iload #4
		// @08D: bipush -126 (0x82)
		// @08F: if_icmplt @093
		// @092: return
		// @093: aload_0
		// @094: bipush -97 (0x9F)
		// @096: iconst_0
		// @097: iconst_0
		// @098: invokevirtual game.C_100136_th.func_102607_a(byte, int, int)void
		// @09B: aload_0
		// @09C: iload_1
		// @09D: aload_0
		// @09E: getfield int game.C_100136_th.field_102541_w
		// @0A1: ineg
		// @0A2: iload_2
		// @0A3: ineg
		// @0A4: iadd
		// @0A5: iload_3
		// @0A6: ineg
		// @0A7: aload_0
		// @0A8: getfield int game.C_100136_th.field_102538_m
		// @0AB: isub
		// @0AC: bipush -127 (0x81)
		// @0AE: invokespecial game.C_100085_a.func_102528_a(int, int, int, byte)void
		// @0B1: bipush -77 (0xB3)
		// @0B3: invokestatic game.C_100200_ba.func_105842_a(byte)void
		// @0B6: getstatic game.C_100037_wb game.C_100272_mn.field_102433_I
		// @0B9: iload_3
		// @0BA: aload_0
		// @0BB: getfield int game.C_100136_th.field_102538_m
		// @0BE: iadd
		// @0BF: aload_0
		// @0C0: getfield int game.C_100136_th.field_102541_w
		// @0C3: iload_2
		// @0C4: iadd
		// @0C5: aload_0
		// @0C6: getfield int game.C_100136_th.field_102617_T
		// @0C9: invokevirtual game.C_100037_wb.func_102376_d(int, int, int)void
		// @0CC: goto @10E
		// @0CF: astore #5
		// @0D1: aload #5
		// @0D3: new java.lang.StringBuilder
		// @0D6: dup
		// @0D7: invokespecial java.lang.StringBuilder.<init>()void
		// @0DA: getstatic java.lang.String[] game.C_100136_th.field_102625_bb
		// @0DD: iconst_3
		// @0DE: aaload
		// @0DF: invokevirtual java.lang.StringBuilder.append(java.lang.String)java.lang.StringBuilder
		// @0E2: iload_1
		// @0E3: invokevirtual java.lang.StringBuilder.append(int)java.lang.StringBuilder
		// @0E6: bipush 44 (0x2C)
		// @0E8: invokevirtual java.lang.StringBuilder.append(char)java.lang.StringBuilder
		// @0EB: iload_2
		// @0EC: invokevirtual java.lang.StringBuilder.append(int)java.lang.StringBuilder
		// @0EF: bipush 44 (0x2C)
		// @0F1: invokevirtual java.lang.StringBuilder.append(char)java.lang.StringBuilder
		// @0F4: iload_3
		// @0F5: invokevirtual java.lang.StringBuilder.append(int)java.lang.StringBuilder
		// @0F8: bipush 44 (0x2C)
		// @0FA: invokevirtual java.lang.StringBuilder.append(char)java.lang.StringBuilder
		// @0FD: iload #4
		// @0FF: invokevirtual java.lang.StringBuilder.append(int)java.lang.StringBuilder
		// @102: bipush 41 (0x29)
		// @104: invokevirtual java.lang.StringBuilder.append(char)java.lang.StringBuilder
		// @107: invokevirtual java.lang.StringBuilder.toString()java.lang.String
		// @10A: invokestatic game.C_100181_cf.func_105695_a(java.lang.Throwable, java.lang.String)game.C_100170_cm
		// @10D: athrow
		// @10E: return
	}
	
	static final void func_102610_a(int arg0, long arg1, String arg2)
	{
		// @00: iconst_2
		// @01: putstatic int game.C_100113_ek.field_104880_b
		// @04: aload_3
		// @05: putstatic java.lang.String game.C_100050_vg.field_100630_m
		// @08: bipush 83 (0x53)
		// @0A: aload_3
		// @0B: invokestatic game.C_100106_ef.func_104742_a(byte, java.lang.CharSequence)java.lang.String
		// @0E: putstatic java.lang.String game.C_100243_pd.field_106355_f
		// @11: iconst_1
		// @12: putstatic boolean game.C_100230_of.field_106216_k
		// @15: lload_1
		// @16: putstatic long game.C_100290_jm.field_106867_i
		// @19: iload_0
		// @1A: bipush -120 (0x88)
		// @1C: if_icmple @32
		// @1F: bipush -122 (0x86)
		// @21: bipush -113 (0x8F)
		// @23: bipush -96 (0xA0)
		// @25: bipush -123 (0x85)
		// @27: bipush -43 (0xD5)
		// @29: bipush 118 (0x76)
		// @2B: bipush 24 (0x18)
		// @2D: bipush -124 (0x84)
		// @2F: invokestatic game.C_100136_th.func_102611_a(int, int, int, int, int, int, int, int)void
		// @32: goto @7D
		// @35: astore #4
		// @37: aload #4
		// @39: new java.lang.StringBuilder
		// @3C: dup
		// @3D: invokespecial java.lang.StringBuilder.<init>()void
		// @40: getstatic java.lang.String[] game.C_100136_th.field_102625_bb
		// @43: bipush 6 (0x06)
		// @45: aaload
		// @46: invokevirtual java.lang.StringBuilder.append(java.lang.String)java.lang.StringBuilder
		// @49: iload_0
		// @4A: invokevirtual java.lang.StringBuilder.append(int)java.lang.StringBuilder
		// @4D: bipush 44 (0x2C)
		// @4F: invokevirtual java.lang.StringBuilder.append(char)java.lang.StringBuilder
		// @52: lload_1
		// @53: invokevirtual java.lang.StringBuilder.append(long)java.lang.StringBuilder
		// @56: bipush 44 (0x2C)
		// @58: invokevirtual java.lang.StringBuilder.append(char)java.lang.StringBuilder
		// @5B: aload_3
		// @5C: ifnull @68
		// @5F: getstatic java.lang.String[] game.C_100136_th.field_102625_bb
		// @62: iconst_5
		// @63: aaload
		// @64: goto @6E
		// @67: athrow
		// @68: getstatic java.lang.String[] game.C_100136_th.field_102625_bb
		// @6B: bipush 7 (0x07)
		// @6D: aaload
		// @6E: invokevirtual java.lang.StringBuilder.append(java.lang.String)java.lang.StringBuilder
		// @71: bipush 41 (0x29)
		// @73: invokevirtual java.lang.StringBuilder.append(char)java.lang.StringBuilder
		// @76: invokevirtual java.lang.StringBuilder.toString()java.lang.String
		// @79: invokestatic game.C_100181_cf.func_105695_a(java.lang.Throwable, java.lang.String)game.C_100170_cm
		// @7C: athrow
		// @7D: return
	}
	
	boolean func_102613_k(int arg0)
	{
		// @00: iload_1
		// @01: sipush 248 (0x00F8)
		// @04: if_icmpeq @15
		// @07: aload_0
		// @08: bipush -88 (0xA8)
		// @0A: bipush -128 (0x80)
		// @0C: bipush 41 (0x29)
		// @0E: invokevirtual game.C_100136_th.func_102615_b(byte, int, int)void
		// @11: goto @15
		// @14: athrow
		// @15: aload_0
		// @16: bipush 78 (0x4E)
		// @18: invokespecial game.C_100136_th.func_102612_f(byte)int
		// @1B: istore_2
		// @1C: iload_2
		// @1D: aload_0
		// @1E: getfield int game.C_100136_th.field_102617_T
		// @21: ineg
		// @22: iadd
		// @23: istore_3
		// @24: iconst_0
		// @25: iload_3
		// @26: if_icmplt @2D
		// @29: goto @3F
		// @2C: athrow
		// @2D: aload_0
		// @2E: dup
		// @2F: getfield int game.C_100136_th.field_102617_T
		// @32: iconst_m1
		// @33: bipush 8 (0x08)
		// @35: iload_3
		// @36: iadd
		// @37: iadd
		// @38: bipush 8 (0x08)
		// @3A: idiv
		// @3B: iadd
		// @3C: putfield int game.C_100136_th.field_102617_T
		// @3F: iconst_m1
		// @40: iload_3
		// @41: iconst_m1
		// @42: ixor
		// @43: if_icmplt @4A
		// @46: goto @5C
		// @49: athrow
		// @4A: aload_0
		// @4B: dup
		// @4C: getfield int game.C_100136_th.field_102617_T
		// @4F: iload_3
		// @50: bipush -16 (0xF0)
		// @52: iadd
		// @53: iconst_1
		// @54: iadd
		// @55: bipush 16 (0x10)
		// @57: idiv
		// @58: iadd
		// @59: putfield int game.C_100136_th.field_102617_T
		// @5C: aload_0
		// @5D: getfield int game.C_100136_th.field_102617_T
		// @60: iconst_m1
		// @61: ixor
		// @62: iconst_m1
		// @63: if_icmpne @81
		// @66: iconst_m1
		// @67: iload_2
		// @68: iconst_m1
		// @69: ixor
		// @6A: if_icmpne @81
		// @6D: goto @71
		// @70: athrow
		// @71: aload_0
		// @72: getfield boolean game.C_100136_th.field_102619_V
		// @75: ifne @81
		// @78: goto @7C
		// @7B: athrow
		// @7C: iconst_1
		// @7D: goto @82
		// @80: athrow
		// @81: iconst_0
		// @82: ireturn
		// @83: astore_2
		// @84: aload_2
		// @85: new java.lang.StringBuilder
		// @88: dup
		// @89: invokespecial java.lang.StringBuilder.<init>()void
		// @8C: getstatic java.lang.String[] game.C_100136_th.field_102625_bb
		// @8F: bipush 9 (0x09)
		// @91: aaload
		// @92: invokevirtual java.lang.StringBuilder.append(java.lang.String)java.lang.StringBuilder
		// @95: iload_1
		// @96: invokevirtual java.lang.StringBuilder.append(int)java.lang.StringBuilder
		// @99: bipush 41 (0x29)
		// @9B: invokevirtual java.lang.StringBuilder.append(char)java.lang.StringBuilder
		// @9E: invokevirtual java.lang.StringBuilder.toString()java.lang.String
		// @A1: invokestatic game.C_100181_cf.func_105695_a(java.lang.Throwable, java.lang.String)game.C_100170_cm
		// @A4: athrow
	}
	
	C_100136_th(C_100029_gn arg0, int arg1, int arg2)
	{
		// @00: aload_0
		// @01: iload_2
		// @02: ineg
		// @03: getstatic int game.C_100313_lg.field_107165_e
		// @06: iadd
		// @07: ldc 1332652737 (0x4f6eaac1)
		// @09: ishr
		// @0A: iload_3
		// @0B: ineg
		// @0C: getstatic int game.C_100340_je.field_102984_k
		// @0F: iadd
		// @10: ldc 1356613153 (0x50dc4621)
		// @12: ishr
		// @13: iload_2
		// @14: iload_3
		// @15: aconst_null
		// @16: invokespecial game.C_100085_a.<init>(int, int, int, int, game.C_100326_ic)void
		// @19: aload_0
		// @1A: aload_1
		// @1B: putfield game.C_100029_gn game.C_100136_th.field_102628_Z
		// @1E: aload_0
		// @1F: iconst_0
		// @20: putfield boolean game.C_100136_th.field_102619_V
		// @23: aload_0
		// @24: iconst_0
		// @25: putfield int game.C_100136_th.field_102617_T
		// @28: goto @73
		// @2B: astore #4
		// @2D: aload #4
		// @2F: new java.lang.StringBuilder
		// @32: dup
		// @33: invokespecial java.lang.StringBuilder.<init>()void
		// @36: getstatic java.lang.String[] game.C_100136_th.field_102625_bb
		// @39: bipush 11 (0x0B)
		// @3B: aaload
		// @3C: invokevirtual java.lang.StringBuilder.append(java.lang.String)java.lang.StringBuilder
		// @3F: aload_1
		// @40: ifnull @4C
		// @43: getstatic java.lang.String[] game.C_100136_th.field_102625_bb
		// @46: iconst_5
		// @47: aaload
		// @48: goto @52
		// @4B: athrow
		// @4C: getstatic java.lang.String[] game.C_100136_th.field_102625_bb
		// @4F: bipush 7 (0x07)
		// @51: aaload
		// @52: invokevirtual java.lang.StringBuilder.append(java.lang.String)java.lang.StringBuilder
		// @55: bipush 44 (0x2C)
		// @57: invokevirtual java.lang.StringBuilder.append(char)java.lang.StringBuilder
		// @5A: iload_2
		// @5B: invokevirtual java.lang.StringBuilder.append(int)java.lang.StringBuilder
		// @5E: bipush 44 (0x2C)
		// @60: invokevirtual java.lang.StringBuilder.append(char)java.lang.StringBuilder
		// @63: iload_3
		// @64: invokevirtual java.lang.StringBuilder.append(int)java.lang.StringBuilder
		// @67: bipush 41 (0x29)
		// @69: invokevirtual java.lang.StringBuilder.append(char)java.lang.StringBuilder
		// @6C: invokevirtual java.lang.StringBuilder.toString()java.lang.String
		// @6F: invokestatic game.C_100181_cf.func_105695_a(java.lang.Throwable, java.lang.String)game.C_100170_cm
		// @72: athrow
		// @73: return
	}
	
	public static void func_102614_g(byte arg0)
	{
		// @00: iload_0
		// @01: bipush 24 (0x18)
		// @03: if_icmpeq @16
		// @06: bipush -58 (0xC6)
		// @08: ldc2_w 71
		// @0B: aconst_null
		// @0C: checkcast java.lang.String
		// @0F: invokestatic game.C_100136_th.func_102610_a(int, long, java.lang.String)void
		// @12: goto @16
		// @15: athrow
		// @16: aconst_null
		// @17: putstatic java.lang.String game.C_100136_th.field_102622_S
		// @1A: aconst_null
		// @1B: putstatic game.C_100037_wb game.C_100136_th.field_102627_X
		// @1E: aconst_null
		// @1F: putstatic java.lang.String game.C_100136_th.field_102621_P
		// @22: aconst_null
		// @23: putstatic game.C_100302_ka[] game.C_100136_th.field_102618_W
		// @26: aconst_null
		// @27: putstatic game.C_100022_hf game.C_100136_th.field_102623_R
		// @2A: aconst_null
		// @2B: putstatic game.C_100037_wb game.C_100136_th.field_102626_Y
		// @2E: aconst_null
		// @2F: putstatic java.lang.String[] game.C_100136_th.field_102616_U
		// @32: aconst_null
		// @33: putstatic java.lang.String game.C_100136_th.field_102624_ab
		// @36: goto @5B
		// @39: astore_1
		// @3A: aload_1
		// @3B: new java.lang.StringBuilder
		// @3E: dup
		// @3F: invokespecial java.lang.StringBuilder.<init>()void
		// @42: getstatic java.lang.String[] game.C_100136_th.field_102625_bb
		// @45: bipush 10 (0x0A)
		// @47: aaload
		// @48: invokevirtual java.lang.StringBuilder.append(java.lang.String)java.lang.StringBuilder
		// @4B: iload_0
		// @4C: invokevirtual java.lang.StringBuilder.append(int)java.lang.StringBuilder
		// @4F: bipush 41 (0x29)
		// @51: invokevirtual java.lang.StringBuilder.append(char)java.lang.StringBuilder
		// @54: invokevirtual java.lang.StringBuilder.toString()java.lang.String
		// @57: invokestatic game.C_100181_cf.func_105695_a(java.lang.Throwable, java.lang.String)game.C_100170_cm
		// @5A: athrow
		// @5B: return
	}
	
	static final void func_102611_a(int arg0, int arg1, int arg2, int arg3, int arg4, int arg5, int arg6, int arg7)
	{
		// @000: getstatic int game.SteelSentinels.field_105275_O
		// @003: istore #9
		// @005: iload_3
		// @006: bipush -37 (0xDB)
		// @008: if_icmple @022
		// @00B: bipush 64 (0x40)
		// @00D: bipush -118 (0x8A)
		// @00F: bipush -37 (0xDB)
		// @011: bipush 17 (0x11)
		// @013: bipush 80 (0x50)
		// @015: bipush -87 (0xA9)
		// @017: bipush 122 (0x7A)
		// @019: bipush 91 (0x5B)
		// @01B: invokestatic game.C_100136_th.func_102611_a(int, int, int, int, int, int, int, int)void
		// @01E: goto @022
		// @021: athrow
		// @022: iload_2
		// @023: iconst_m1
		// @024: ixor
		// @025: iload #4
		// @027: iconst_m1
		// @028: ixor
		// @029: if_icmplt @09A
		// @02C: iload #4
		// @02E: iconst_m1
		// @02F: ixor
		// @030: iload #7
		// @032: iconst_m1
		// @033: ixor
		// @034: if_icmple @056
		// @037: goto @03B
		// @03A: athrow
		// @03B: iload #7
		// @03D: iload_1
		// @03E: iload #4
		// @040: iload #6
		// @042: getstatic int[] game.C_100196_rb.field_105818_d
		// @045: iload_0
		// @046: iload_2
		// @047: iload #5
		// @049: iconst_1
		// @04A: invokestatic game.C_100304_kl.func_107109_a(int, int, int, int, int[], int, int, int, boolean)void
		// @04D: iload #9
		// @04F: ifeq @0FB
		// @052: goto @056
		// @055: athrow
		// @056: iload_2
		// @057: iconst_m1
		// @058: ixor
		// @059: iload #7
		// @05B: iconst_m1
		// @05C: ixor
		// @05D: if_icmpgt @07F
		// @060: goto @064
		// @063: athrow
		// @064: iload #4
		// @066: iload #5
		// @068: iload_2
		// @069: iload #6
		// @06B: getstatic int[] game.C_100196_rb.field_105818_d
		// @06E: iload_1
		// @06F: iload #7
		// @071: iload_0
		// @072: iconst_1
		// @073: invokestatic game.C_100304_kl.func_107109_a(int, int, int, int, int[], int, int, int, boolean)void
		// @076: iload #9
		// @078: ifeq @0FB
		// @07B: goto @07F
		// @07E: athrow
		// @07F: iload #4
		// @081: iload_0
		// @082: iload #7
		// @084: iload #6
		// @086: getstatic int[] game.C_100196_rb.field_105818_d
		// @089: iload_1
		// @08A: iload_2
		// @08B: iload #5
		// @08D: iconst_1
		// @08E: invokestatic game.C_100304_kl.func_107109_a(int, int, int, int, int[], int, int, int, boolean)void
		// @091: iload #9
		// @093: ifeq @0FB
		// @096: goto @09A
		// @099: athrow
		// @09A: iload #7
		// @09C: iload_2
		// @09D: if_icmpgt @0E5
		// @0A0: goto @0A4
		// @0A3: athrow
		// @0A4: iload #7
		// @0A6: iload #4
		// @0A8: if_icmple @0CA
		// @0AB: goto @0AF
		// @0AE: athrow
		// @0AF: iload_2
		// @0B0: iload_0
		// @0B1: iload #7
		// @0B3: iload #6
		// @0B5: getstatic int[] game.C_100196_rb.field_105818_d
		// @0B8: iload #5
		// @0BA: iload #4
		// @0BC: iload_1
		// @0BD: iconst_1
		// @0BE: invokestatic game.C_100304_kl.func_107109_a(int, int, int, int, int[], int, int, int, boolean)void
		// @0C1: iload #9
		// @0C3: ifeq @0FB
		// @0C6: goto @0CA
		// @0C9: athrow
		// @0CA: iload_2
		// @0CB: iload_1
		// @0CC: iload #4
		// @0CE: iload #6
		// @0D0: getstatic int[] game.C_100196_rb.field_105818_d
		// @0D3: iload #5
		// @0D5: iload #7
		// @0D7: iload_0
		// @0D8: iconst_1
		// @0D9: invokestatic game.C_100304_kl.func_107109_a(int, int, int, int, int[], int, int, int, boolean)void
		// @0DC: iload #9
		// @0DE: ifeq @0FB
		// @0E1: goto @0E5
		// @0E4: athrow
		// @0E5: iload #7
		// @0E7: iload #5
		// @0E9: iload_2
		// @0EA: iload #6
		// @0EC: getstatic int[] game.C_100196_rb.field_105818_d
		// @0EF: iload_0
		// @0F0: iload #4
		// @0F2: iload_1
		// @0F3: iconst_1
		// @0F4: invokestatic game.C_100304_kl.func_107109_a(int, int, int, int, int[], int, int, int, boolean)void
		// @0F7: goto @0FB
		// @0FA: athrow
		// @0FB: goto @165
		// @0FE: astore #8
		// @100: aload #8
		// @102: new java.lang.StringBuilder
		// @105: dup
		// @106: invokespecial java.lang.StringBuilder.<init>()void
		// @109: getstatic java.lang.String[] game.C_100136_th.field_102625_bb
		// @10C: bipush 8 (0x08)
		// @10E: aaload
		// @10F: invokevirtual java.lang.StringBuilder.append(java.lang.String)java.lang.StringBuilder
		// @112: iload_0
		// @113: invokevirtual java.lang.StringBuilder.append(int)java.lang.StringBuilder
		// @116: bipush 44 (0x2C)
		// @118: invokevirtual java.lang.StringBuilder.append(char)java.lang.StringBuilder
		// @11B: iload_1
		// @11C: invokevirtual java.lang.StringBuilder.append(int)java.lang.StringBuilder
		// @11F: bipush 44 (0x2C)
		// @121: invokevirtual java.lang.StringBuilder.append(char)java.lang.StringBuilder
		// @124: iload_2
		// @125: invokevirtual java.lang.StringBuilder.append(int)java.lang.StringBuilder
		// @128: bipush 44 (0x2C)
		// @12A: invokevirtual java.lang.StringBuilder.append(char)java.lang.StringBuilder
		// @12D: iload_3
		// @12E: invokevirtual java.lang.StringBuilder.append(int)java.lang.StringBuilder
		// @131: bipush 44 (0x2C)
		// @133: invokevirtual java.lang.StringBuilder.append(char)java.lang.StringBuilder
		// @136: iload #4
		// @138: invokevirtual java.lang.StringBuilder.append(int)java.lang.StringBuilder
		// @13B: bipush 44 (0x2C)
		// @13D: invokevirtual java.lang.StringBuilder.append(char)java.lang.StringBuilder
		// @140: iload #5
		// @142: invokevirtual java.lang.StringBuilder.append(int)java.lang.StringBuilder
		// @145: bipush 44 (0x2C)
		// @147: invokevirtual java.lang.StringBuilder.append(char)java.lang.StringBuilder
		// @14A: iload #6
		// @14C: invokevirtual java.lang.StringBuilder.append(int)java.lang.StringBuilder
		// @14F: bipush 44 (0x2C)
		// @151: invokevirtual java.lang.StringBuilder.append(char)java.lang.StringBuilder
		// @154: iload #7
		// @156: invokevirtual java.lang.StringBuilder.append(int)java.lang.StringBuilder
		// @159: bipush 41 (0x29)
		// @15B: invokevirtual java.lang.StringBuilder.append(char)java.lang.StringBuilder
		// @15E: invokevirtual java.lang.StringBuilder.toString()java.lang.String
		// @161: invokestatic game.C_100181_cf.func_105695_a(java.lang.Throwable, java.lang.String)game.C_100170_cm
		// @164: athrow
		// @165: return
	}
	
	final void func_102615_b(byte arg0, int arg1, int arg2)
	{
		// @00: aload_0
		// @01: iload_2
		// @02: getstatic int game.C_100340_je.field_102984_k
		// @05: iload_2
		// @06: isub
		// @07: ldc -592655487 (0xdcaccb81)
		// @09: ishr
		// @0A: iload_3
		// @0B: ineg
		// @0C: getstatic int game.C_100313_lg.field_107165_e
		// @0F: iadd
		// @10: ldc -1398765951 (0xaca08681)
		// @12: ishr
		// @13: iload_3
		// @14: bipush -92 (0xA4)
		// @16: invokevirtual game.C_100136_th.func_102524_a(int, int, int, int, byte)void
		// @19: iload_1
		// @1A: bipush -69 (0xBB)
		// @1C: if_icmple @26
		// @1F: aconst_null
		// @20: checkcast game.C_100302_ka[]
		// @23: putstatic game.C_100302_ka[] game.C_100136_th.field_102618_W
		// @26: goto @5E
		// @29: astore #4
		// @2B: aload #4
		// @2D: new java.lang.StringBuilder
		// @30: dup
		// @31: invokespecial java.lang.StringBuilder.<init>()void
		// @34: getstatic java.lang.String[] game.C_100136_th.field_102625_bb
		// @37: iconst_4
		// @38: aaload
		// @39: invokevirtual java.lang.StringBuilder.append(java.lang.String)java.lang.StringBuilder
		// @3C: iload_1
		// @3D: invokevirtual java.lang.StringBuilder.append(int)java.lang.StringBuilder
		// @40: bipush 44 (0x2C)
		// @42: invokevirtual java.lang.StringBuilder.append(char)java.lang.StringBuilder
		// @45: iload_2
		// @46: invokevirtual java.lang.StringBuilder.append(int)java.lang.StringBuilder
		// @49: bipush 44 (0x2C)
		// @4B: invokevirtual java.lang.StringBuilder.append(char)java.lang.StringBuilder
		// @4E: iload_3
		// @4F: invokevirtual java.lang.StringBuilder.append(int)java.lang.StringBuilder
		// @52: bipush 41 (0x29)
		// @54: invokevirtual java.lang.StringBuilder.append(char)java.lang.StringBuilder
		// @57: invokevirtual java.lang.StringBuilder.toString()java.lang.String
		// @5A: invokestatic game.C_100181_cf.func_105695_a(java.lang.Throwable, java.lang.String)game.C_100170_cm
		// @5D: athrow
		// @5E: return
	}
	
	abstract void func_102607_a(byte arg0, int arg1, int arg2);
	
	private final int func_102612_f(byte arg0)
	{
		// @00: bipush -2 (0xFE)
		// @02: bipush -21 (0xEB)
		// @04: iload_1
		// @05: isub
		// @06: bipush 60 (0x3C)
		// @08: idiv
		// @09: idiv
		// @0A: istore_2
		// @0B: aload_0
		// @0C: getfield boolean game.C_100136_th.field_102619_V
		// @0F: ifeq @2E
		// @12: aload_0
		// @13: getfield game.C_100029_gn game.C_100136_th.field_102628_Z
		// @16: bipush 126 (0x7E)
		// @18: invokevirtual game.C_100029_gn.func_103353_g(byte)game.C_100136_th
		// @1B: aload_0
		// @1C: if_acmpeq @28
		// @1F: goto @23
		// @22: athrow
		// @23: iconst_0
		// @24: goto @2F
		// @27: athrow
		// @28: sipush 256 (0x0100)
		// @2B: goto @2F
		// @2E: iconst_0
		// @2F: ireturn
		// @30: astore_2
		// @31: aload_2
		// @32: new java.lang.StringBuilder
		// @35: dup
		// @36: invokespecial java.lang.StringBuilder.<init>()void
		// @39: getstatic java.lang.String[] game.C_100136_th.field_102625_bb
		// @3C: bipush 12 (0x0C)
		// @3E: aaload
		// @3F: invokevirtual java.lang.StringBuilder.append(java.lang.String)java.lang.StringBuilder
		// @42: iload_1
		// @43: invokevirtual java.lang.StringBuilder.append(int)java.lang.StringBuilder
		// @46: bipush 41 (0x29)
		// @48: invokevirtual java.lang.StringBuilder.append(char)java.lang.StringBuilder
		// @4B: invokevirtual java.lang.StringBuilder.toString()java.lang.String
		// @4E: invokestatic game.C_100181_cf.func_105695_a(java.lang.Throwable, java.lang.String)game.C_100170_cm
		// @51: athrow
	}
	
	boolean func_102606_a(byte arg0)
	{
		// @00: aload_0
		// @01: aload_0
		// @02: bipush -100 (0x9C)
		// @04: invokespecial game.C_100136_th.func_102612_f(byte)int
		// @07: putfield int game.C_100136_th.field_102617_T
		// @0A: bipush -15 (0xF1)
		// @0C: iload_1
		// @0D: bipush -51 (0xCD)
		// @0F: isub
		// @10: bipush 43 (0x2B)
		// @12: idiv
		// @13: irem
		// @14: istore_2
		// @15: iconst_m1
		// @16: aload_0
		// @17: getfield int game.C_100136_th.field_102617_T
		// @1A: iconst_m1
		// @1B: ixor
		// @1C: if_icmpne @2F
		// @1F: aload_0
		// @20: getfield boolean game.C_100136_th.field_102619_V
		// @23: ifne @2F
		// @26: goto @2A
		// @29: athrow
		// @2A: iconst_1
		// @2B: goto @30
		// @2E: athrow
		// @2F: iconst_0
		// @30: ireturn
		// @31: astore_2
		// @32: aload_2
		// @33: new java.lang.StringBuilder
		// @36: dup
		// @37: invokespecial java.lang.StringBuilder.<init>()void
		// @3A: getstatic java.lang.String[] game.C_100136_th.field_102625_bb
		// @3D: iconst_0
		// @3E: aaload
		// @3F: invokevirtual java.lang.StringBuilder.append(java.lang.String)java.lang.StringBuilder
		// @42: iload_1
		// @43: invokevirtual java.lang.StringBuilder.append(int)java.lang.StringBuilder
		// @46: bipush 41 (0x29)
		// @48: invokevirtual java.lang.StringBuilder.append(char)java.lang.StringBuilder
		// @4B: invokevirtual java.lang.StringBuilder.toString()java.lang.String
		// @4E: invokestatic game.C_100181_cf.func_105695_a(java.lang.Throwable, java.lang.String)game.C_100170_cm
		// @51: athrow
	}
	
	final C_100336_im func_102559_j(int arg0)
	{
		// @00: iload_1
		// @01: iconst_m1
		// @02: if_icmpeq @0F
		// @05: aload_0
		// @06: bipush 88 (0x58)
		// @08: putfield int game.C_100136_th.field_102617_T
		// @0B: goto @0F
		// @0E: athrow
		// @0F: aload_0
		// @10: iload_1
		// @11: iconst_0
		// @12: ixor
		// @13: invokespecial game.C_100085_a.func_102559_j(int)game.C_100336_im
		// @16: astore_2
		// @17: aload_2
		// @18: ifnonnull @1F
		// @1B: goto @21
		// @1E: athrow
		// @1F: aload_2
		// @20: areturn
		// @21: aload_0
		// @22: areturn
		// @23: astore_2
		// @24: aload_2
		// @25: new java.lang.StringBuilder
		// @28: dup
		// @29: invokespecial java.lang.StringBuilder.<init>()void
		// @2C: getstatic java.lang.String[] game.C_100136_th.field_102625_bb
		// @2F: iconst_2
		// @30: aaload
		// @31: invokevirtual java.lang.StringBuilder.append(java.lang.String)java.lang.StringBuilder
		// @34: iload_1
		// @35: invokevirtual java.lang.StringBuilder.append(int)java.lang.StringBuilder
		// @38: bipush 41 (0x29)
		// @3A: invokevirtual java.lang.StringBuilder.append(char)java.lang.StringBuilder
		// @3D: invokevirtual java.lang.StringBuilder.toString()java.lang.String
		// @40: invokestatic game.C_100181_cf.func_105695_a(java.lang.Throwable, java.lang.String)game.C_100170_cm
		// @43: athrow
	}
	
	static
	{
		// @00: bipush 13 (0x0D)
		// @02: anewarray java.lang.String
		// @05: dup
		// @06: iconst_0
		// @07: ldc "!d\u0005Uo}"
		// @09: invokestatic game.C_100136_th.func_102609_z(java.lang.String)char[]
		// @0C: invokestatic game.C_100136_th.func_102608_z(char[])java.lang.String
		// @0F: aastore
		// @10: dup
		// @11: iconst_1
		// @12: ldc "!d\u0005Fo}"
		// @14: invokestatic game.C_100136_th.func_102609_z(java.lang.String)char[]
		// @17: invokestatic game.C_100136_th.func_102608_z(char[])java.lang.String
		// @1A: aastore
		// @1B: dup
		// @1C: iconst_2
		// @1D: ldc "!d\u0005P\u0005"
		// @1F: invokestatic game.C_100136_th.func_102609_z(java.lang.String)char[]
		// @22: invokestatic game.C_100136_th.func_102608_z(char[])java.lang.String
		// @25: aastore
		// @26: dup
		// @27: iconst_3
		// @28: ldc "!d\u0005W\u0005"
		// @2A: invokestatic game.C_100136_th.func_102609_z(java.lang.String)char[]
		// @2D: invokestatic game.C_100136_th.func_102608_z(char[])java.lang.String
		// @30: aastore
		// @31: dup
		// @32: iconst_4
		// @33: ldc "!d\u0005Co}"
		// @35: invokestatic game.C_100136_th.func_102609_z(java.lang.String)char[]
		// @38: invokestatic game.C_100136_th.func_102608_z(char[])java.lang.String
		// @3B: aastore
		// @3C: dup
		// @3D: iconst_5
		// @3E: ldc ".\"\u0005:P"
		// @40: invokestatic game.C_100136_th.func_102609_z(java.lang.String)char[]
		// @43: invokestatic game.C_100136_th.func_102608_z(char[])java.lang.String
		// @46: aastore
		// @47: dup
		// @48: bipush 6 (0x06)
		// @4A: ldc "!d\u0005Go}"
		// @4C: invokestatic game.C_100136_th.func_102609_z(java.lang.String)char[]
		// @4F: invokestatic game.C_100136_th.func_102608_z(char[])java.lang.String
		// @52: aastore
		// @53: dup
		// @54: bipush 7 (0x07)
		// @56: ldc ";yGx"
		// @58: invokestatic game.C_100136_th.func_102609_z(java.lang.String)char[]
		// @5B: invokestatic game.C_100136_th.func_102608_z(char[])java.lang.String
		// @5E: aastore
		// @5F: dup
		// @60: bipush 8 (0x08)
		// @62: ldc "!d\u0005Ao}"
		// @64: invokestatic game.C_100136_th.func_102609_z(java.lang.String)char[]
		// @67: invokestatic game.C_100136_th.func_102608_z(char[])java.lang.String
		// @6A: aastore
		// @6B: dup
		// @6C: bipush 9 (0x09)
		// @6E: ldc "!d\u0005@l}"
		// @70: invokestatic game.C_100136_th.func_102609_z(java.lang.String)char[]
		// @73: invokestatic game.C_100136_th.func_102608_z(char[])java.lang.String
		// @76: aastore
		// @77: dup
		// @78: bipush 10 (0x0A)
		// @7A: ldc "!d\u0005@o}"
		// @7C: invokestatic game.C_100136_th.func_102609_z(java.lang.String)char[]
		// @7F: invokestatic game.C_100136_th.func_102608_z(char[])java.lang.String
		// @82: aastore
		// @83: dup
		// @84: bipush 11 (0x0B)
		// @86: ldc "!d\u0005(D;e_*\u0005"
		// @88: invokestatic game.C_100136_th.func_102609_z(java.lang.String)char[]
		// @8B: invokestatic game.C_100136_th.func_102608_z(char[])java.lang.String
		// @8E: aastore
		// @8F: dup
		// @90: bipush 12 (0x0C)
		// @92: ldc "!d\u0005Bo}"
		// @94: invokestatic game.C_100136_th.func_102609_z(java.lang.String)char[]
		// @97: invokestatic game.C_100136_th.func_102608_z(char[])java.lang.String
		// @9A: aastore
		// @9B: putstatic java.lang.String[] game.C_100136_th.field_102625_bb
		// @9E: iconst_1
		// @9F: anewarray java.lang.String
		// @A2: dup
		// @A3: iconst_0
		// @A4: ldc "\u001aG"
		// @A6: invokestatic game.C_100136_th.func_102609_z(java.lang.String)char[]
		// @A9: invokestatic game.C_100136_th.func_102608_z(char[])java.lang.String
		// @AC: aastore
		// @AD: putstatic java.lang.String[] game.C_100136_th.field_102616_U
		// @B0: iconst_4
		// @B1: anewarray game.C_100302_ka
		// @B4: putstatic game.C_100302_ka[] game.C_100136_th.field_102618_W
		// @B7: ldc "\u0014y_{\u0000'iXdB;h\u000b`Bu0\u000e$\u0013"
		// @B9: invokestatic game.C_100136_th.func_102609_z(java.lang.String)char[]
		// @BC: invokestatic game.C_100136_th.func_102608_z(char[])java.lang.String
		// @BF: putstatic java.lang.String game.C_100136_th.field_102622_S
		// @C2: ldc "\u000ciJf"
		// @C4: invokestatic game.C_100136_th.func_102609_z(java.lang.String)char[]
		// @C7: invokestatic game.C_100136_th.func_102608_z(char[])java.lang.String
		// @CA: putstatic java.lang.String game.C_100136_th.field_102621_P
		// @CD: ldc "\u0006iJfN=eEs\r3cY4B%|DzH;xX"
		// @CF: invokestatic game.C_100136_th.func_102609_z(java.lang.String)char[]
		// @D2: invokestatic game.C_100136_th.func_102608_z(char[])java.lang.String
		// @D5: putstatic java.lang.String game.C_100136_th.field_102624_ab
		// @D8: return
	}
	
	private static char[] func_102609_z(String arg0)
	{
		// @00: aload_0
		// @01: invokevirtual java.lang.String.toCharArray()char[]
		// @04: dup
		// @05: arraylength
		// @06: iconst_2
		// @07: if_icmpge @13
		// @0A: dup
		// @0B: iconst_0
		// @0C: dup2
		// @0D: caload
		// @0E: bipush 45 (0x2D)
		// @10: ixor
		// @11: i2c
		// @12: castore
		// @13: areturn
	}
	
	private static String func_102608_z(char[] arg0)
	{
		// @00: aload_0
		// @01: dup
		// @02: arraylength
		// @03: swap
		// @04: iconst_0
		// @05: istore_1
		// @06: goto @4C
		// @09: dup
		// @0A: iload_1
		// @0B: dup2
		// @0C: caload
		// @0D: iload_1
		// @0E: iconst_5
		// @0F: irem
		// @10: tableswitch def: @44, for 0: @30, for 1: @35, for 2: @3A, for 3: @3F
		// @30: bipush 85 (0x55)
		// @32: goto @46
		// @35: bipush 12 (0x0C)
		// @37: goto @46
		// @3A: bipush 43 (0x2B)
		// @3C: goto @46
		// @3F: bipush 20 (0x14)
		// @41: goto @46
		// @44: bipush 45 (0x2D)
		// @46: ixor
		// @47: i2c
		// @48: castore
		// @49: iinc #1 +1
		// @4C: swap
		// @4D: dup_x1
		// @4E: iload_1
		// @4F: if_icmpgt @09
		// @52: new java.lang.String
		// @55: dup_x1
		// @56: swap
		// @57: invokespecial java.lang.String.<init>(char[])void
		// @5A: invokevirtual java.lang.String.intern()java.lang.String
		// @5D: areturn
	}
}
