package game;

class C_100158_da
{
	static String field_100594_b;
	C_100158_da field_100590_f;
	static boolean field_100596_a;
	static int field_100598_h;
	C_100158_da field_100599_i;
	long field_100595_c;
	static int field_100592_d;
	static C_100201_qj field_100593_e;
	static int[] field_100591_g;
	private static final String[] field_100597_z;
	
	static final void func_100588_b(byte arg0)
	{
		// @00: getstatic game.C_100209_qb game.C_100318_hj.field_107201_j
		// @03: new game.C_100207_qh
		// @06: dup
		// @07: invokespecial game.C_100207_qh.<init>()void
		// @0A: bipush 75 (0x4B)
		// @0C: invokevirtual game.C_100209_qb.func_102660_a(game.C_100336_im, byte)void
		// @0F: iload_0
		// @10: bipush -101 (0x9B)
		// @12: if_icmpeq @1C
		// @15: aconst_null
		// @16: checkcast int[]
		// @19: putstatic int[] game.C_100158_da.field_100591_g
		// @1C: goto @40
		// @1F: astore_1
		// @20: aload_1
		// @21: new java.lang.StringBuilder
		// @24: dup
		// @25: invokespecial java.lang.StringBuilder.<init>()void
		// @28: getstatic java.lang.String[] game.C_100158_da.field_100597_z
		// @2B: iconst_1
		// @2C: aaload
		// @2D: invokevirtual java.lang.StringBuilder.append(java.lang.String)java.lang.StringBuilder
		// @30: iload_0
		// @31: invokevirtual java.lang.StringBuilder.append(int)java.lang.StringBuilder
		// @34: bipush 41 (0x29)
		// @36: invokevirtual java.lang.StringBuilder.append(char)java.lang.StringBuilder
		// @39: invokevirtual java.lang.StringBuilder.toString()java.lang.String
		// @3C: invokestatic game.C_100181_cf.func_105695_a(java.lang.Throwable, java.lang.String)game.C_100170_cm
		// @3F: athrow
		// @40: return
	}
	
	final void func_100583_c(int arg0)
	{
		// @00: iload_1
		// @01: bipush 45 (0x2D)
		// @03: if_icmpeq @0F
		// @06: bipush -41 (0xD7)
		// @08: invokestatic game.C_100158_da.func_100582_b(int)void
		// @0B: goto @0F
		// @0E: athrow
		// @0F: aload_0
		// @10: getfield game.C_100158_da game.C_100158_da.field_100599_i
		// @13: ifnull @1A
		// @16: goto @1B
		// @19: athrow
		// @1A: return
		// @1B: aload_0
		// @1C: getfield game.C_100158_da game.C_100158_da.field_100599_i
		// @1F: aload_0
		// @20: getfield game.C_100158_da game.C_100158_da.field_100590_f
		// @23: putfield game.C_100158_da game.C_100158_da.field_100590_f
		// @26: aload_0
		// @27: getfield game.C_100158_da game.C_100158_da.field_100590_f
		// @2A: aload_0
		// @2B: getfield game.C_100158_da game.C_100158_da.field_100599_i
		// @2E: putfield game.C_100158_da game.C_100158_da.field_100599_i
		// @31: aload_0
		// @32: aconst_null
		// @33: putfield game.C_100158_da game.C_100158_da.field_100590_f
		// @36: aload_0
		// @37: aconst_null
		// @38: putfield game.C_100158_da game.C_100158_da.field_100599_i
		// @3B: goto @5F
		// @3E: astore_2
		// @3F: aload_2
		// @40: new java.lang.StringBuilder
		// @43: dup
		// @44: invokespecial java.lang.StringBuilder.<init>()void
		// @47: getstatic java.lang.String[] game.C_100158_da.field_100597_z
		// @4A: iconst_0
		// @4B: aaload
		// @4C: invokevirtual java.lang.StringBuilder.append(java.lang.String)java.lang.StringBuilder
		// @4F: iload_1
		// @50: invokevirtual java.lang.StringBuilder.append(int)java.lang.StringBuilder
		// @53: bipush 41 (0x29)
		// @55: invokevirtual java.lang.StringBuilder.append(char)java.lang.StringBuilder
		// @58: invokevirtual java.lang.StringBuilder.toString()java.lang.String
		// @5B: invokestatic game.C_100181_cf.func_105695_a(java.lang.Throwable, java.lang.String)game.C_100170_cm
		// @5E: athrow
		// @5F: return
	}
	
	static final void func_100589_a(int arg0, String arg1, boolean arg2)
	{
		// @00: iload_0
		// @01: bipush 45 (0x2D)
		// @03: if_icmpeq @14
		// @06: bipush 50 (0x32)
		// @08: aconst_null
		// @09: checkcast java.lang.String
		// @0C: iconst_0
		// @0D: invokestatic game.C_100158_da.func_100589_a(int, java.lang.String, boolean)void
		// @10: goto @14
		// @13: athrow
		// @14: iconst_1
		// @15: putstatic boolean game.C_100198_qn.field_105834_b
		// @18: iload_2
		// @19: putstatic boolean game.C_100291_jj.field_106872_f
		// @1C: new game.C_100282_nh
		// @1F: dup
		// @20: getstatic game.C_100029_gn game.C_100085_a.field_102576_K
		// @23: getstatic game.C_100112_r game.C_100185_rm.field_105484_d
		// @26: aload_1
		// @27: getstatic boolean game.C_100186_rl.field_105720_f
		// @2A: getstatic boolean game.C_100291_jj.field_106872_f
		// @2D: invokespecial game.C_100282_nh.<init>(game.C_100029_gn, game.C_100112_r, java.lang.String, boolean, boolean)void
		// @30: putstatic game.C_100282_nh game.C_100027_hc.field_102598_S
		// @33: getstatic game.C_100029_gn game.C_100085_a.field_102576_K
		// @36: getstatic game.C_100282_nh game.C_100027_hc.field_102598_S
		// @39: sipush 2839 (0x0B17)
		// @3C: invokevirtual game.C_100029_gn.func_103359_a(game.C_100336_im, int)void
		// @3F: goto @89
		// @42: astore_3
		// @43: aload_3
		// @44: new java.lang.StringBuilder
		// @47: dup
		// @48: invokespecial java.lang.StringBuilder.<init>()void
		// @4B: getstatic java.lang.String[] game.C_100158_da.field_100597_z
		// @4E: bipush 8 (0x08)
		// @50: aaload
		// @51: invokevirtual java.lang.StringBuilder.append(java.lang.String)java.lang.StringBuilder
		// @54: iload_0
		// @55: invokevirtual java.lang.StringBuilder.append(int)java.lang.StringBuilder
		// @58: bipush 44 (0x2C)
		// @5A: invokevirtual java.lang.StringBuilder.append(char)java.lang.StringBuilder
		// @5D: aload_1
		// @5E: ifnull @6B
		// @61: getstatic java.lang.String[] game.C_100158_da.field_100597_z
		// @64: bipush 6 (0x06)
		// @66: aaload
		// @67: goto @71
		// @6A: athrow
		// @6B: getstatic java.lang.String[] game.C_100158_da.field_100597_z
		// @6E: bipush 7 (0x07)
		// @70: aaload
		// @71: invokevirtual java.lang.StringBuilder.append(java.lang.String)java.lang.StringBuilder
		// @74: bipush 44 (0x2C)
		// @76: invokevirtual java.lang.StringBuilder.append(char)java.lang.StringBuilder
		// @79: iload_2
		// @7A: invokevirtual java.lang.StringBuilder.append(boolean)java.lang.StringBuilder
		// @7D: bipush 41 (0x29)
		// @7F: invokevirtual java.lang.StringBuilder.append(char)java.lang.StringBuilder
		// @82: invokevirtual java.lang.StringBuilder.toString()java.lang.String
		// @85: invokestatic game.C_100181_cf.func_105695_a(java.lang.Throwable, java.lang.String)game.C_100170_cm
		// @88: athrow
		// @89: return
	}
	
	static final boolean func_100581_a(int arg0, byte arg1)
	{
		// @00: bipush -12 (0xF4)
		// @02: iload_1
		// @03: bipush 63 (0x3F)
		// @05: isub
		// @06: bipush 37 (0x25)
		// @08: idiv
		// @09: irem
		// @0A: istore_2
		// @0B: iload_0
		// @0C: bipush 43 (0x2B)
		// @0E: if_icmpeq @5D
		// @11: bipush -45 (0xD3)
		// @13: iload_0
		// @14: iconst_m1
		// @15: ixor
		// @16: if_icmpeq @5D
		// @19: goto @1D
		// @1C: athrow
		// @1D: iload_0
		// @1E: iconst_m1
		// @1F: ixor
		// @20: bipush -49 (0xCF)
		// @22: if_icmpeq @5D
		// @25: goto @29
		// @28: athrow
		// @29: iload_0
		// @2A: bipush 31 (0x1F)
		// @2C: if_icmpeq @5D
		// @2F: goto @33
		// @32: athrow
		// @33: bipush 46 (0x2E)
		// @35: iload_0
		// @36: if_icmpeq @5D
		// @39: goto @3D
		// @3C: athrow
		// @3D: iload_0
		// @3E: bipush 52 (0x34)
		// @40: if_icmpeq @5D
		// @43: goto @47
		// @46: athrow
		// @47: iload_0
		// @48: bipush 45 (0x2D)
		// @4A: if_icmpeq @5D
		// @4D: goto @51
		// @50: athrow
		// @51: bipush -48 (0xD0)
		// @53: iload_0
		// @54: iconst_m1
		// @55: ixor
		// @56: if_icmpne @62
		// @59: goto @5D
		// @5C: athrow
		// @5D: iconst_1
		// @5E: goto @63
		// @61: athrow
		// @62: iconst_0
		// @63: ireturn
		// @64: astore_2
		// @65: aload_2
		// @66: new java.lang.StringBuilder
		// @69: dup
		// @6A: invokespecial java.lang.StringBuilder.<init>()void
		// @6D: getstatic java.lang.String[] game.C_100158_da.field_100597_z
		// @70: iconst_2
		// @71: aaload
		// @72: invokevirtual java.lang.StringBuilder.append(java.lang.String)java.lang.StringBuilder
		// @75: iload_0
		// @76: invokevirtual java.lang.StringBuilder.append(int)java.lang.StringBuilder
		// @79: bipush 44 (0x2C)
		// @7B: invokevirtual java.lang.StringBuilder.append(char)java.lang.StringBuilder
		// @7E: iload_1
		// @7F: invokevirtual java.lang.StringBuilder.append(int)java.lang.StringBuilder
		// @82: bipush 41 (0x29)
		// @84: invokevirtual java.lang.StringBuilder.append(char)java.lang.StringBuilder
		// @87: invokevirtual java.lang.StringBuilder.toString()java.lang.String
		// @8A: invokestatic game.C_100181_cf.func_105695_a(java.lang.Throwable, java.lang.String)game.C_100170_cm
		// @8D: athrow
	}
	
	final boolean func_100587_d(int arg0)
	{
		// @00: iload_1
		// @01: sipush 31025 (0x7931)
		// @04: if_icmpeq @11
		// @07: bipush -92 (0xA4)
		// @09: invokestatic game.C_100158_da.func_100584_a(int)game.C_100037_wb
		// @0C: pop
		// @0D: goto @11
		// @10: athrow
		// @11: aload_0
		// @12: getfield game.C_100158_da game.C_100158_da.field_100599_i
		// @15: ifnonnull @1A
		// @18: iconst_0
		// @19: ireturn
		// @1A: iconst_1
		// @1B: ireturn
		// @1C: astore_2
		// @1D: aload_2
		// @1E: new java.lang.StringBuilder
		// @21: dup
		// @22: invokespecial java.lang.StringBuilder.<init>()void
		// @25: getstatic java.lang.String[] game.C_100158_da.field_100597_z
		// @28: iconst_5
		// @29: aaload
		// @2A: invokevirtual java.lang.StringBuilder.append(java.lang.String)java.lang.StringBuilder
		// @2D: iload_1
		// @2E: invokevirtual java.lang.StringBuilder.append(int)java.lang.StringBuilder
		// @31: bipush 41 (0x29)
		// @33: invokevirtual java.lang.StringBuilder.append(char)java.lang.StringBuilder
		// @36: invokevirtual java.lang.StringBuilder.toString()java.lang.String
		// @39: invokestatic game.C_100181_cf.func_105695_a(java.lang.Throwable, java.lang.String)game.C_100170_cm
		// @3C: athrow
	}
	
	static final C_100037_wb func_100584_a(int arg0)
	{
		// @00: getstatic int game.SteelSentinels.field_105275_O
		// @03: istore #6
		// @05: bipush -25 (0xE7)
		// @07: bipush 16 (0x10)
		// @09: iload_0
		// @0A: isub
		// @0B: bipush 52 (0x34)
		// @0D: idiv
		// @0E: irem
		// @0F: istore_2
		// @10: getstatic int[] game.C_100312_ld.field_107156_c
		// @13: iconst_0
		// @14: iaload
		// @15: getstatic int[] game.C_100213_ak.field_105994_d
		// @18: iconst_0
		// @19: iaload
		// @1A: imul
		// @1B: istore_1
		// @1C: getstatic byte[][] game.C_100107_u.field_104774_c
		// @1F: iconst_0
		// @20: aaload
		// @21: astore_3
		// @22: iload_1
		// @23: newarray int[]
		// @25: astore #4
		// @27: iconst_0
		// @28: istore #5
		// @2A: iload #5
		// @2C: iconst_m1
		// @2D: ixor
		// @2E: iload_1
		// @2F: iconst_m1
		// @30: ixor
		// @31: if_icmple @4F
		// @34: aload #4
		// @36: iload #5
		// @38: getstatic int[] game.C_100085_a.field_102573_H
		// @3B: aload_3
		// @3C: iload #5
		// @3E: baload
		// @3F: sipush 255 (0x00FF)
		// @42: invokestatic game.C_100256_pk.func_100449_a(int, int)int
		// @45: iaload
		// @46: iastore
		// @47: iinc #5 +1
		// @4A: iload #6
		// @4C: ifeq @2A
		// @4F: new game.C_100037_wb
		// @52: dup
		// @53: getstatic int game.C_100338_jc.field_105371_m
		// @56: getstatic int game.C_100277_nc.field_106702_C
		// @59: getstatic int[] game.C_100068_vc.field_104340_f
		// @5C: iconst_0
		// @5D: iaload
		// @5E: getstatic int[] game.C_100012_fh.field_100509_M
		// @61: iconst_0
		// @62: iaload
		// @63: getstatic int[] game.C_100213_ak.field_105994_d
		// @66: iconst_0
		// @67: iaload
		// @68: getstatic int[] game.C_100312_ld.field_107156_c
		// @6B: iconst_0
		// @6C: iaload
		// @6D: aload #4
		// @6F: invokespecial game.C_100037_wb.<init>(int, int, int, int, int, int, int[])void
		// @72: astore #5
		// @74: bipush 47 (0x2F)
		// @76: invokestatic game.C_100030_gm.func_103336_a(byte)void
		// @79: aload #5
		// @7B: areturn
		// @7C: astore_1
		// @7D: aload_1
		// @7E: new java.lang.StringBuilder
		// @81: dup
		// @82: invokespecial java.lang.StringBuilder.<init>()void
		// @85: getstatic java.lang.String[] game.C_100158_da.field_100597_z
		// @88: iconst_3
		// @89: aaload
		// @8A: invokevirtual java.lang.StringBuilder.append(java.lang.String)java.lang.StringBuilder
		// @8D: iload_0
		// @8E: invokevirtual java.lang.StringBuilder.append(int)java.lang.StringBuilder
		// @91: bipush 41 (0x29)
		// @93: invokevirtual java.lang.StringBuilder.append(char)java.lang.StringBuilder
		// @96: invokevirtual java.lang.StringBuilder.toString()java.lang.String
		// @99: invokestatic game.C_100181_cf.func_105695_a(java.lang.Throwable, java.lang.String)game.C_100170_cm
		// @9C: athrow
	}
	
	public static void func_100582_b(int arg0)
	{
		// @00: iload_0
		// @01: sipush -5406 (0xEAE2)
		// @04: if_icmpeq @08
		// @07: return
		// @08: aconst_null
		// @09: putstatic java.lang.String game.C_100158_da.field_100594_b
		// @0C: aconst_null
		// @0D: putstatic game.C_100201_qj game.C_100158_da.field_100593_e
		// @10: aconst_null
		// @11: putstatic int[] game.C_100158_da.field_100591_g
		// @14: goto @38
		// @17: astore_1
		// @18: aload_1
		// @19: new java.lang.StringBuilder
		// @1C: dup
		// @1D: invokespecial java.lang.StringBuilder.<init>()void
		// @20: getstatic java.lang.String[] game.C_100158_da.field_100597_z
		// @23: iconst_4
		// @24: aaload
		// @25: invokevirtual java.lang.StringBuilder.append(java.lang.String)java.lang.StringBuilder
		// @28: iload_0
		// @29: invokevirtual java.lang.StringBuilder.append(int)java.lang.StringBuilder
		// @2C: bipush 41 (0x29)
		// @2E: invokevirtual java.lang.StringBuilder.append(char)java.lang.StringBuilder
		// @31: invokevirtual java.lang.StringBuilder.toString()java.lang.String
		// @34: invokestatic game.C_100181_cf.func_105695_a(java.lang.Throwable, java.lang.String)game.C_100170_cm
		// @37: athrow
		// @38: return
	}
	
	static
	{
		// @00: bipush 9 (0x09)
		// @02: anewarray java.lang.String
		// @05: dup
		// @06: iconst_0
		// @07: ldc "\u000bwB)\u000b"
		// @09: invokestatic game.C_100158_da.func_100586_z(java.lang.String)char[]
		// @0C: invokestatic game.C_100158_da.func_100585_z(char[])java.lang.String
		// @0F: aastore
		// @10: dup
		// @11: iconst_1
		// @12: ldc "\u000bwB+\u000b"
		// @14: invokestatic game.C_100158_da.func_100586_z(java.lang.String)char[]
		// @17: invokestatic game.C_100158_da.func_100585_z(char[])java.lang.String
		// @1A: aastore
		// @1B: dup
		// @1C: iconst_2
		// @1D: ldc "\u000bwB7\u000b"
		// @1F: invokestatic game.C_100158_da.func_100586_z(java.lang.String)char[]
		// @22: invokestatic game.C_100158_da.func_100585_z(char[])java.lang.String
		// @25: aastore
		// @26: dup
		// @27: iconst_3
		// @28: ldc "\u000bwB,\u000b"
		// @2A: invokestatic game.C_100158_da.func_100586_z(java.lang.String)char[]
		// @2D: invokestatic game.C_100158_da.func_100585_z(char[])java.lang.String
		// @30: aastore
		// @31: dup
		// @32: iconst_4
		// @33: ldc "\u000bwB*\u000b"
		// @35: invokestatic game.C_100158_da.func_100586_z(java.lang.String)char[]
		// @38: invokestatic game.C_100158_da.func_100585_z(char[])java.lang.String
		// @3B: aastore
		// @3C: dup
		// @3D: iconst_5
		// @3E: ldc "\u000bwB(\u000b"
		// @40: invokestatic game.C_100158_da.func_100586_z(java.lang.String)char[]
		// @43: invokestatic game.C_100158_da.func_100585_z(char[])java.lang.String
		// @46: aastore
		// @47: dup
		// @48: bipush 6 (0x06)
		// @4A: ldc "\u00148BI^"
		// @4C: invokestatic game.C_100158_da.func_100586_z(java.lang.String)char[]
		// @4F: invokestatic game.C_100158_da.func_100585_z(char[])java.lang.String
		// @52: aastore
		// @53: dup
		// @54: bipush 7 (0x07)
		// @56: ldc "\u0001c\u0000\u000b"
		// @58: invokestatic game.C_100158_da.func_100586_z(java.lang.String)char[]
		// @5B: invokestatic game.C_100158_da.func_100585_z(char[])java.lang.String
		// @5E: aastore
		// @5F: dup
		// @60: bipush 8 (0x08)
		// @62: ldc "\u000bwB-\u000b"
		// @64: invokestatic game.C_100158_da.func_100586_z(java.lang.String)char[]
		// @67: invokestatic game.C_100158_da.func_100585_z(char[])java.lang.String
		// @6A: aastore
		// @6B: putstatic java.lang.String[] game.C_100158_da.field_100597_z
		// @6E: ldc "Su\u0003\u000b\u001eS3^Y\u001d\"\u007f\u001f\u0014J\u0000xL[\u0006_(L]\u0003S9\u000f\u0008OQ*\u000f\u0008OR*IT\u001dQ*IV\u001dS9\u000f\u0008OQ"
		// @70: invokestatic game.C_100158_da.func_100586_z(java.lang.String)char[]
		// @73: invokestatic game.C_100158_da.func_100585_z(char[])java.lang.String
		// @76: putstatic java.lang.String game.C_100158_da.field_100594_b
		// @79: iconst_0
		// @7A: putstatic int game.C_100158_da.field_100598_h
		// @7D: sipush 200 (0x00C8)
		// @80: putstatic int game.C_100158_da.field_100592_d
		// @83: return
	}
	
	private static char[] func_100586_z(String arg0)
	{
		// @00: aload_0
		// @01: invokevirtual java.lang.String.toCharArray()char[]
		// @04: dup
		// @05: arraylength
		// @06: iconst_2
		// @07: if_icmpge @13
		// @0A: dup
		// @0B: iconst_0
		// @0C: dup2
		// @0D: caload
		// @0E: bipush 35 (0x23)
		// @10: ixor
		// @11: i2c
		// @12: castore
		// @13: areturn
	}
	
	private static String func_100585_z(char[] arg0)
	{
		// @00: aload_0
		// @01: dup
		// @02: arraylength
		// @03: swap
		// @04: iconst_0
		// @05: istore_1
		// @06: goto @4C
		// @09: dup
		// @0A: iload_1
		// @0B: dup2
		// @0C: caload
		// @0D: iload_1
		// @0E: iconst_5
		// @0F: irem
		// @10: tableswitch def: @44, for 0: @30, for 1: @35, for 2: @3A, for 3: @3F
		// @30: bipush 111 (0x6F)
		// @32: goto @46
		// @35: bipush 22 (0x16)
		// @37: goto @46
		// @3A: bipush 108 (0x6C)
		// @3C: goto @46
		// @3F: bipush 103 (0x67)
		// @41: goto @46
		// @44: bipush 35 (0x23)
		// @46: ixor
		// @47: i2c
		// @48: castore
		// @49: iinc #1 +1
		// @4C: swap
		// @4D: dup_x1
		// @4E: iload_1
		// @4F: if_icmpgt @09
		// @52: new java.lang.String
		// @55: dup_x1
		// @56: swap
		// @57: invokespecial java.lang.String.<init>(char[])void
		// @5A: invokevirtual java.lang.String.intern()java.lang.String
		// @5D: areturn
	}
}
