package game;

import java.awt.Frame;

final class C_100137_bn
{
	static int field_105037_a;
	static String field_105035_b;
	private C_100098_h field_105041_k;
	static String field_105033_d;
	static int field_105038_l;
	static String field_105034_e;
	static int field_105036_c;
	static int[][] field_105040_j;
	private C_100098_h field_105031_f;
	static String field_105043_i;
	private C_100318_hj field_105042_h;
	static boolean field_105032_g;
	static Frame field_105039_m;
	private static final String[] field_105044_z;
	
	static final boolean func_105027_a(int arg0, char arg1)
	{
		// @00: bipush -127 (0x81)
		// @02: iload_0
		// @03: bipush 41 (0x29)
		// @05: isub
		// @06: bipush 39 (0x27)
		// @08: idiv
		// @09: irem
		// @0A: istore_2
		// @0B: iload_1
		// @0C: bipush 65 (0x41)
		// @0E: if_icmplt @1D
		// @11: bipush -91 (0xA5)
		// @13: iload_1
		// @14: iconst_m1
		// @15: ixor
		// @16: if_icmple @35
		// @19: goto @1D
		// @1C: athrow
		// @1D: bipush -98 (0x9E)
		// @1F: iload_1
		// @20: iconst_m1
		// @21: ixor
		// @22: if_icmplt @3A
		// @25: goto @29
		// @28: athrow
		// @29: iload_1
		// @2A: iconst_m1
		// @2B: ixor
		// @2C: bipush -123 (0x85)
		// @2E: if_icmplt @3A
		// @31: goto @35
		// @34: athrow
		// @35: iconst_1
		// @36: goto @3B
		// @39: athrow
		// @3A: iconst_0
		// @3B: ireturn
		// @3C: astore_2
		// @3D: aload_2
		// @3E: new java.lang.StringBuilder
		// @41: dup
		// @42: invokespecial java.lang.StringBuilder.<init>()void
		// @45: getstatic java.lang.String[] game.C_100137_bn.field_105044_z
		// @48: bipush 8 (0x08)
		// @4A: aaload
		// @4B: invokevirtual java.lang.StringBuilder.append(java.lang.String)java.lang.StringBuilder
		// @4E: iload_0
		// @4F: invokevirtual java.lang.StringBuilder.append(int)java.lang.StringBuilder
		// @52: bipush 44 (0x2C)
		// @54: invokevirtual java.lang.StringBuilder.append(char)java.lang.StringBuilder
		// @57: iload_1
		// @58: invokevirtual java.lang.StringBuilder.append(char)java.lang.StringBuilder
		// @5B: bipush 41 (0x29)
		// @5D: invokevirtual java.lang.StringBuilder.append(char)java.lang.StringBuilder
		// @60: invokevirtual java.lang.StringBuilder.toString()java.lang.String
		// @63: invokestatic game.C_100181_cf.func_105695_a(java.lang.Throwable, java.lang.String)game.C_100170_cm
		// @66: athrow
	}
	
	public static void func_105024_a(int arg0)
	{
		// @00: aconst_null
		// @01: putstatic java.lang.String game.C_100137_bn.field_105043_i
		// @04: aconst_null
		// @05: putstatic java.awt.Frame game.C_100137_bn.field_105039_m
		// @08: aconst_null
		// @09: putstatic java.lang.String game.C_100137_bn.field_105035_b
		// @0C: aconst_null
		// @0D: putstatic java.lang.String game.C_100137_bn.field_105033_d
		// @10: aconst_null
		// @11: putstatic java.lang.String game.C_100137_bn.field_105034_e
		// @14: bipush 103 (0x67)
		// @16: bipush -44 (0xD4)
		// @18: iload_0
		// @19: isub
		// @1A: bipush 51 (0x33)
		// @1C: idiv
		// @1D: idiv
		// @1E: istore_1
		// @1F: aconst_null
		// @20: checkcast int[][]
		// @23: putstatic int[][] game.C_100137_bn.field_105040_j
		// @26: goto @4B
		// @29: astore_1
		// @2A: aload_1
		// @2B: new java.lang.StringBuilder
		// @2E: dup
		// @2F: invokespecial java.lang.StringBuilder.<init>()void
		// @32: getstatic java.lang.String[] game.C_100137_bn.field_105044_z
		// @35: bipush 10 (0x0A)
		// @37: aaload
		// @38: invokevirtual java.lang.StringBuilder.append(java.lang.String)java.lang.StringBuilder
		// @3B: iload_0
		// @3C: invokevirtual java.lang.StringBuilder.append(int)java.lang.StringBuilder
		// @3F: bipush 41 (0x29)
		// @41: invokevirtual java.lang.StringBuilder.append(char)java.lang.StringBuilder
		// @44: invokevirtual java.lang.StringBuilder.toString()java.lang.String
		// @47: invokestatic game.C_100181_cf.func_105695_a(java.lang.Throwable, java.lang.String)game.C_100170_cm
		// @4A: athrow
		// @4B: return
	}
	
	static final C_100302_ka func_105030_b(int arg0)
	{
		// @00: bipush -3 (0xFD)
		// @02: iload_0
		// @03: bipush 62 (0x3E)
		// @05: isub
		// @06: bipush 57 (0x39)
		// @08: idiv
		// @09: irem
		// @0A: istore_1
		// @0B: bipush -103 (0x99)
		// @0D: invokestatic game.C_100293_kj.func_106885_a(byte)game.C_100302_ka
		// @10: areturn
		// @11: astore_1
		// @12: aload_1
		// @13: new java.lang.StringBuilder
		// @16: dup
		// @17: invokespecial java.lang.StringBuilder.<init>()void
		// @1A: getstatic java.lang.String[] game.C_100137_bn.field_105044_z
		// @1D: iconst_5
		// @1E: aaload
		// @1F: invokevirtual java.lang.StringBuilder.append(java.lang.String)java.lang.StringBuilder
		// @22: iload_0
		// @23: invokevirtual java.lang.StringBuilder.append(int)java.lang.StringBuilder
		// @26: bipush 41 (0x29)
		// @28: invokevirtual java.lang.StringBuilder.append(char)java.lang.StringBuilder
		// @2B: invokevirtual java.lang.StringBuilder.toString()java.lang.String
		// @2E: invokestatic game.C_100181_cf.func_105695_a(java.lang.Throwable, java.lang.String)game.C_100170_cm
		// @31: athrow
	}
	
	final C_100066_dl func_105026_a(int arg0, byte arg1)
	{
		// @00: iload_2
		// @01: bipush 28 (0x1C)
		// @03: if_icmpeq @0B
		// @06: aconst_null
		// @07: checkcast game.C_100066_dl
		// @0A: areturn
		// @0B: aload_0
		// @0C: getfield game.C_100318_hj game.C_100137_bn.field_105042_h
		// @0F: iload_1
		// @10: i2l
		// @11: iconst_0
		// @12: invokevirtual game.C_100318_hj.func_107190_a(long, int)java.lang.Object
		// @15: checkcast game.C_100066_dl
		// @18: astore_3
		// @19: aconst_null
		// @1A: aload_3
		// @1B: if_acmpne @22
		// @1E: goto @24
		// @21: athrow
		// @22: aload_3
		// @23: areturn
		// @24: iload_1
		// @25: ldc 32768 (0x8000)
		// @27: if_icmplt @40
		// @2A: aload_0
		// @2B: getfield game.C_100098_h game.C_100137_bn.field_105031_f
		// @2E: iconst_1
		// @2F: iconst_0
		// @30: sipush 32767 (0x7FFF)
		// @33: iload_1
		// @34: iand
		// @35: invokevirtual game.C_100098_h.func_104610_b(int, int, int)byte[]
		// @38: astore #4
		// @3A: getstatic int game.SteelSentinels.field_105275_O
		// @3D: ifeq @4C
		// @40: aload_0
		// @41: getfield game.C_100098_h game.C_100137_bn.field_105041_k
		// @44: iconst_1
		// @45: iconst_0
		// @46: iload_1
		// @47: invokevirtual game.C_100098_h.func_104610_b(int, int, int)byte[]
		// @4A: astore #4
		// @4C: new game.C_100066_dl
		// @4F: dup
		// @50: invokespecial game.C_100066_dl.<init>()void
		// @53: astore_3
		// @54: aload #4
		// @56: ifnull @6B
		// @59: aload_3
		// @5A: new game.C_100280_nf
		// @5D: dup
		// @5E: aload #4
		// @60: invokespecial game.C_100280_nf.<init>(byte[])void
		// @63: iconst_0
		// @64: invokevirtual game.C_100066_dl.func_101621_a(game.C_100280_nf, boolean)void
		// @67: goto @6B
		// @6A: athrow
		// @6B: iload_1
		// @6C: ldc 32768 (0x8000)
		// @6E: if_icmpge @75
		// @71: goto @7B
		// @74: athrow
		// @75: aload_3
		// @76: bipush 14 (0x0E)
		// @78: invokevirtual game.C_100066_dl.func_101623_d(byte)void
		// @7B: aload_0
		// @7C: getfield game.C_100318_hj game.C_100137_bn.field_105042_h
		// @7F: aload_3
		// @80: iload_2
		// @81: bipush 28 (0x1C)
		// @83: ixor
		// @84: iload_1
		// @85: i2l
		// @86: invokevirtual game.C_100318_hj.func_107183_a(java.lang.Object, int, long)void
		// @89: aload_3
		// @8A: areturn
		// @8B: astore_3
		// @8C: aload_3
		// @8D: new java.lang.StringBuilder
		// @90: dup
		// @91: invokespecial java.lang.StringBuilder.<init>()void
		// @94: getstatic java.lang.String[] game.C_100137_bn.field_105044_z
		// @97: bipush 6 (0x06)
		// @99: aaload
		// @9A: invokevirtual java.lang.StringBuilder.append(java.lang.String)java.lang.StringBuilder
		// @9D: iload_1
		// @9E: invokevirtual java.lang.StringBuilder.append(int)java.lang.StringBuilder
		// @A1: bipush 44 (0x2C)
		// @A3: invokevirtual java.lang.StringBuilder.append(char)java.lang.StringBuilder
		// @A6: iload_2
		// @A7: invokevirtual java.lang.StringBuilder.append(int)java.lang.StringBuilder
		// @AA: bipush 41 (0x29)
		// @AC: invokevirtual java.lang.StringBuilder.append(char)java.lang.StringBuilder
		// @AF: invokevirtual java.lang.StringBuilder.toString()java.lang.String
		// @B2: invokestatic game.C_100181_cf.func_105695_a(java.lang.Throwable, java.lang.String)game.C_100170_cm
		// @B5: athrow
	}
	
	static final void func_105023_a(int arg0, int arg1, C_100075_uj arg2)
	{
		// @00: iload_1
		// @01: bipush -114 (0x8E)
		// @03: if_icmplt @11
		// @06: aconst_null
		// @07: checkcast java.lang.String
		// @0A: putstatic java.lang.String game.C_100137_bn.field_105035_b
		// @0D: goto @11
		// @10: athrow
		// @11: getstatic game.C_100202_qi game.C_100133_tk.field_105000_c
		// @14: bipush 126 (0x7E)
		// @16: aload_2
		// @17: invokevirtual game.C_100202_qi.func_105901_a(int, game.C_100158_da)void
		// @1A: iconst_m1
		// @1B: aload_2
		// @1C: iload_0
		// @1D: invokestatic game.C_100082_uf.func_100363_a(int, game.C_100075_uj, int)void
		// @20: goto @68
		// @23: astore_3
		// @24: aload_3
		// @25: new java.lang.StringBuilder
		// @28: dup
		// @29: invokespecial java.lang.StringBuilder.<init>()void
		// @2C: getstatic java.lang.String[] game.C_100137_bn.field_105044_z
		// @2F: bipush 9 (0x09)
		// @31: aaload
		// @32: invokevirtual java.lang.StringBuilder.append(java.lang.String)java.lang.StringBuilder
		// @35: iload_0
		// @36: invokevirtual java.lang.StringBuilder.append(int)java.lang.StringBuilder
		// @39: bipush 44 (0x2C)
		// @3B: invokevirtual java.lang.StringBuilder.append(char)java.lang.StringBuilder
		// @3E: iload_1
		// @3F: invokevirtual java.lang.StringBuilder.append(int)java.lang.StringBuilder
		// @42: bipush 44 (0x2C)
		// @44: invokevirtual java.lang.StringBuilder.append(char)java.lang.StringBuilder
		// @47: aload_2
		// @48: ifnull @54
		// @4B: getstatic java.lang.String[] game.C_100137_bn.field_105044_z
		// @4E: iconst_4
		// @4F: aaload
		// @50: goto @59
		// @53: athrow
		// @54: getstatic java.lang.String[] game.C_100137_bn.field_105044_z
		// @57: iconst_0
		// @58: aaload
		// @59: invokevirtual java.lang.StringBuilder.append(java.lang.String)java.lang.StringBuilder
		// @5C: bipush 41 (0x29)
		// @5E: invokevirtual java.lang.StringBuilder.append(char)java.lang.StringBuilder
		// @61: invokevirtual java.lang.StringBuilder.toString()java.lang.String
		// @64: invokestatic game.C_100181_cf.func_105695_a(java.lang.Throwable, java.lang.String)game.C_100170_cm
		// @67: athrow
		// @68: return
	}
	
	static final void func_105029_a(boolean arg0, C_100098_h arg1, int arg2, C_100098_h arg3)
	{
		// @00: bipush 52 (0x34)
		// @02: getstatic game.C_100302_ka game.C_100236_on.field_100906_r
		// @05: getstatic game.C_100302_ka game.C_100081_ue.field_100678_k
		// @08: iload_0
		// @09: getstatic game.C_100302_ka game.C_100167_sj.field_100797_q
		// @0C: getstatic game.C_100317_lb game.C_100342_jg.field_102724_Vb
		// @0F: getstatic game.C_100302_ka game.C_100129_tg.field_102750_sb
		// @12: getstatic game.C_100302_ka game.C_100316_lc.field_102409_C
		// @15: getstatic game.C_100302_ka game.C_100316_lc.field_102404_D
		// @18: getstatic game.C_100302_ka game.C_100341_jd.field_102652_kb
		// @1B: getstatic game.C_100302_ka game.C_100062_dk.field_104284_c
		// @1E: getstatic game.C_100231_oc game.C_100013_fn.field_103737_f
		// @21: invokestatic game.C_100231_oc.func_102190_a(byte, game.C_100302_ka, game.C_100302_ka, boolean, game.C_100302_ka, game.C_100112_r, game.C_100302_ka, game.C_100302_ka, game.C_100302_ka, game.C_100302_ka, game.C_100302_ka, game.C_100231_oc)void
		// @24: aload_3
		// @25: getstatic java.lang.String[] game.C_100137_bn.field_105044_z
		// @28: iconst_3
		// @29: aaload
		// @2A: getstatic java.lang.String[] game.C_100137_bn.field_105044_z
		// @2D: iconst_2
		// @2E: aaload
		// @2F: bipush -88 (0xA8)
		// @31: invokestatic game.C_100163_sf.func_105433_a(game.C_100098_h, java.lang.String, java.lang.String, byte)game.C_100037_wb[]
		// @34: putstatic game.C_100037_wb[] game.C_100165_sh.field_100771_q
		// @37: getstatic java.lang.String[] game.C_100000_gd.field_100360_a
		// @3A: iconst_0
		// @3B: getstatic java.lang.String game.C_100226_ae.field_106146_f
		// @3E: aastore
		// @3F: getstatic java.lang.String[] game.C_100000_gd.field_100360_a
		// @42: iconst_1
		// @43: getstatic java.lang.String game.C_100191_rg.field_100843_p
		// @46: aastore
		// @47: iload_2
		// @48: sipush 18958 (0x4A0E)
		// @4B: if_icmpeq @5D
		// @4E: bipush 78 (0x4E)
		// @50: bipush 102 (0x66)
		// @52: aconst_null
		// @53: checkcast game.C_100075_uj
		// @56: invokestatic game.C_100137_bn.func_105023_a(int, int, game.C_100075_uj)void
		// @59: goto @5D
		// @5C: athrow
		// @5D: getstatic java.lang.String[] game.C_100000_gd.field_100360_a
		// @60: iconst_2
		// @61: getstatic java.lang.String game.C_100142_bk.field_105086_d
		// @64: aastore
		// @65: iload_2
		// @66: sipush 19025 (0x4A51)
		// @69: ixor
		// @6A: getstatic game.C_100317_lb game.C_100152_bd.field_105209_k
		// @6D: aload_1
		// @6E: invokestatic game.C_100247_pa.func_106413_a(int, game.C_100112_r, game.C_100098_h)void
		// @71: goto @D4
		// @74: astore #4
		// @76: aload #4
		// @78: new java.lang.StringBuilder
		// @7B: dup
		// @7C: invokespecial java.lang.StringBuilder.<init>()void
		// @7F: getstatic java.lang.String[] game.C_100137_bn.field_105044_z
		// @82: iconst_1
		// @83: aaload
		// @84: invokevirtual java.lang.StringBuilder.append(java.lang.String)java.lang.StringBuilder
		// @87: iload_0
		// @88: invokevirtual java.lang.StringBuilder.append(boolean)java.lang.StringBuilder
		// @8B: bipush 44 (0x2C)
		// @8D: invokevirtual java.lang.StringBuilder.append(char)java.lang.StringBuilder
		// @90: aload_1
		// @91: ifnull @9D
		// @94: getstatic java.lang.String[] game.C_100137_bn.field_105044_z
		// @97: iconst_4
		// @98: aaload
		// @99: goto @A2
		// @9C: athrow
		// @9D: getstatic java.lang.String[] game.C_100137_bn.field_105044_z
		// @A0: iconst_0
		// @A1: aaload
		// @A2: invokevirtual java.lang.StringBuilder.append(java.lang.String)java.lang.StringBuilder
		// @A5: bipush 44 (0x2C)
		// @A7: invokevirtual java.lang.StringBuilder.append(char)java.lang.StringBuilder
		// @AA: iload_2
		// @AB: invokevirtual java.lang.StringBuilder.append(int)java.lang.StringBuilder
		// @AE: bipush 44 (0x2C)
		// @B0: invokevirtual java.lang.StringBuilder.append(char)java.lang.StringBuilder
		// @B3: aload_3
		// @B4: ifnull @C0
		// @B7: getstatic java.lang.String[] game.C_100137_bn.field_105044_z
		// @BA: iconst_4
		// @BB: aaload
		// @BC: goto @C5
		// @BF: athrow
		// @C0: getstatic java.lang.String[] game.C_100137_bn.field_105044_z
		// @C3: iconst_0
		// @C4: aaload
		// @C5: invokevirtual java.lang.StringBuilder.append(java.lang.String)java.lang.StringBuilder
		// @C8: bipush 41 (0x29)
		// @CA: invokevirtual java.lang.StringBuilder.append(char)java.lang.StringBuilder
		// @CD: invokevirtual java.lang.StringBuilder.toString()java.lang.String
		// @D0: invokestatic game.C_100181_cf.func_105695_a(java.lang.Throwable, java.lang.String)game.C_100170_cm
		// @D3: athrow
		// @D4: return
	}
	
	C_100137_bn(int arg0, C_100098_h arg1, C_100098_h arg2, C_100199_qm arg3)
	{
		// @00: aload_0
		// @01: invokespecial java.lang.Object.<init>()void
		// @04: aload_0
		// @05: new game.C_100318_hj
		// @08: dup
		// @09: bipush 64 (0x40)
		// @0B: invokespecial game.C_100318_hj.<init>(int)void
		// @0E: putfield game.C_100318_hj game.C_100137_bn.field_105042_h
		// @11: aload_0
		// @12: aload_3
		// @13: putfield game.C_100098_h game.C_100137_bn.field_105031_f
		// @16: aload_0
		// @17: aload_2
		// @18: putfield game.C_100098_h game.C_100137_bn.field_105041_k
		// @1B: aload_0
		// @1C: getfield game.C_100098_h game.C_100137_bn.field_105041_k
		// @1F: ifnonnull @25
		// @22: goto @30
		// @25: aload_0
		// @26: getfield game.C_100098_h game.C_100137_bn.field_105041_k
		// @29: bipush 38 (0x26)
		// @2B: iconst_1
		// @2C: invokevirtual game.C_100098_h.func_104591_c(int, int)int
		// @2F: pop
		// @30: aconst_null
		// @31: aload_0
		// @32: getfield game.C_100098_h game.C_100137_bn.field_105031_f
		// @35: if_acmpne @3C
		// @38: goto @47
		// @3B: athrow
		// @3C: aload_0
		// @3D: getfield game.C_100098_h game.C_100137_bn.field_105031_f
		// @40: bipush 65 (0x41)
		// @42: iconst_1
		// @43: invokevirtual game.C_100098_h.func_104591_c(int, int)int
		// @46: pop
		// @47: goto @BD
		// @4A: astore #5
		// @4C: aload #5
		// @4E: new java.lang.StringBuilder
		// @51: dup
		// @52: invokespecial java.lang.StringBuilder.<init>()void
		// @55: getstatic java.lang.String[] game.C_100137_bn.field_105044_z
		// @58: bipush 7 (0x07)
		// @5A: aaload
		// @5B: invokevirtual java.lang.StringBuilder.append(java.lang.String)java.lang.StringBuilder
		// @5E: iload_1
		// @5F: invokevirtual java.lang.StringBuilder.append(int)java.lang.StringBuilder
		// @62: bipush 44 (0x2C)
		// @64: invokevirtual java.lang.StringBuilder.append(char)java.lang.StringBuilder
		// @67: aload_2
		// @68: ifnull @74
		// @6B: getstatic java.lang.String[] game.C_100137_bn.field_105044_z
		// @6E: iconst_4
		// @6F: aaload
		// @70: goto @79
		// @73: athrow
		// @74: getstatic java.lang.String[] game.C_100137_bn.field_105044_z
		// @77: iconst_0
		// @78: aaload
		// @79: invokevirtual java.lang.StringBuilder.append(java.lang.String)java.lang.StringBuilder
		// @7C: bipush 44 (0x2C)
		// @7E: invokevirtual java.lang.StringBuilder.append(char)java.lang.StringBuilder
		// @81: aload_3
		// @82: ifnull @8E
		// @85: getstatic java.lang.String[] game.C_100137_bn.field_105044_z
		// @88: iconst_4
		// @89: aaload
		// @8A: goto @93
		// @8D: athrow
		// @8E: getstatic java.lang.String[] game.C_100137_bn.field_105044_z
		// @91: iconst_0
		// @92: aaload
		// @93: invokevirtual java.lang.StringBuilder.append(java.lang.String)java.lang.StringBuilder
		// @96: bipush 44 (0x2C)
		// @98: invokevirtual java.lang.StringBuilder.append(char)java.lang.StringBuilder
		// @9B: aload #4
		// @9D: ifnull @A9
		// @A0: getstatic java.lang.String[] game.C_100137_bn.field_105044_z
		// @A3: iconst_4
		// @A4: aaload
		// @A5: goto @AE
		// @A8: athrow
		// @A9: getstatic java.lang.String[] game.C_100137_bn.field_105044_z
		// @AC: iconst_0
		// @AD: aaload
		// @AE: invokevirtual java.lang.StringBuilder.append(java.lang.String)java.lang.StringBuilder
		// @B1: bipush 41 (0x29)
		// @B3: invokevirtual java.lang.StringBuilder.append(char)java.lang.StringBuilder
		// @B6: invokevirtual java.lang.StringBuilder.toString()java.lang.String
		// @B9: invokestatic game.C_100181_cf.func_105695_a(java.lang.Throwable, java.lang.String)game.C_100170_cm
		// @BC: athrow
		// @BD: return
	}
	
	static
	{
		// @000: bipush 11 (0x0B)
		// @002: anewarray java.lang.String
		// @005: dup
		// @006: iconst_0
		// @007: ldc "+\u001aB-"
		// @009: invokestatic game.C_100137_bn.func_105028_z(java.lang.String)char[]
		// @00C: invokestatic game.C_100137_bn.func_105025_z(char[])java.lang.String
		// @00F: aastore
		// @010: dup
		// @011: iconst_1
		// @012: ldc "'\u0001\u0000\u0007X"
		// @014: invokestatic game.C_100137_bn.func_105028_z(java.lang.String)char[]
		// @017: invokestatic game.C_100137_bn.func_105025_z(char[])java.lang.String
		// @01A: aastore
		// @01B: dup
		// @01C: iconst_2
		// @01D: ldc ")\u0000L#\t"
		// @01F: invokestatic game.C_100137_bn.func_105028_z(java.lang.String)char[]
		// @022: invokestatic game.C_100137_bn.func_105025_z(char[])java.lang.String
		// @025: aastore
		// @026: dup
		// @027: iconst_3
		// @028: ldc "&\u0007O5\u0016,\u0003Z$\u0002"
		// @02A: invokestatic game.C_100137_bn.func_105028_z(java.lang.String)char[]
		// @02D: invokestatic game.C_100137_bn.func_105025_z(char[])java.lang.String
		// @030: aastore
		// @031: dup
		// @032: iconst_4
		// @033: ldc ">A\u0000o\r"
		// @035: invokestatic game.C_100137_bn.func_105028_z(java.lang.String)char[]
		// @038: invokestatic game.C_100137_bn.func_105025_z(char[])java.lang.String
		// @03B: aastore
		// @03C: dup
		// @03D: iconst_5
		// @03E: ldc "'\u0001\u0000\u0002X"
		// @040: invokestatic game.C_100137_bn.func_105028_z(java.lang.String)char[]
		// @043: invokestatic game.C_100137_bn.func_105025_z(char[])java.lang.String
		// @046: aastore
		// @047: dup
		// @048: bipush 6 (0x06)
		// @04A: ldc "'\u0001\u0000\u0004X"
		// @04C: invokestatic game.C_100137_bn.func_105028_z(java.lang.String)char[]
		// @04F: invokestatic game.C_100137_bn.func_105025_z(char[])java.lang.String
		// @052: aastore
		// @053: dup
		// @054: bipush 7 (0x07)
		// @056: ldc "'\u0001\u0000}\u0019+\u0006Z\u007fX"
		// @058: invokestatic game.C_100137_bn.func_105028_z(java.lang.String)char[]
		// @05B: invokestatic game.C_100137_bn.func_105025_z(char[])java.lang.String
		// @05E: aastore
		// @05F: dup
		// @060: bipush 8 (0x08)
		// @062: ldc "'\u0001\u0000\u0003X"
		// @064: invokestatic game.C_100137_bn.func_105028_z(java.lang.String)char[]
		// @067: invokestatic game.C_100137_bn.func_105025_z(char[])java.lang.String
		// @06A: aastore
		// @06B: dup
		// @06C: bipush 9 (0x09)
		// @06E: ldc "'\u0001\u0000\u0000X"
		// @070: invokestatic game.C_100137_bn.func_105028_z(java.lang.String)char[]
		// @073: invokestatic game.C_100137_bn.func_105025_z(char[])java.lang.String
		// @076: aastore
		// @077: dup
		// @078: bipush 10 (0x0A)
		// @07A: ldc "'\u0001\u0000\u0005X"
		// @07C: invokestatic game.C_100137_bn.func_105028_z(java.lang.String)char[]
		// @07F: invokestatic game.C_100137_bn.func_105025_z(char[])java.lang.String
		// @082: aastore
		// @083: putstatic java.lang.String[] game.C_100137_bn.field_105044_z
		// @086: ldc "\u0006 `\u00079\u0002:|\u0000$\u000c `"
		// @088: invokestatic game.C_100137_bn.func_105028_z(java.lang.String)char[]
		// @08B: invokestatic game.C_100137_bn.func_105025_z(char[])java.lang.String
		// @08E: putstatic java.lang.String game.C_100137_bn.field_105034_e
		// @091: bipush 36 (0x24)
		// @093: anewarray int[]
		// @096: putstatic int[][] game.C_100137_bn.field_105040_j
		// @099: sipush 200 (0x00C8)
		// @09C: putstatic int game.C_100137_bn.field_105036_c
		// @09F: ldc "\u0015\u0003O8\u00157\u001c\u0014a"
		// @0A1: invokestatic game.C_100137_bn.func_105028_z(java.lang.String)char[]
		// @0A4: invokestatic game.C_100137_bn.func_105025_z(char[])java.lang.String
		// @0A7: putstatic java.lang.String game.C_100137_bn.field_105035_b
		// @0AA: ldc "\u0015\u0003K \u0003 OZ3\te\u000cF \u001e\"\u0006@&P1\u0007Ka\u0016*\u0003B.\u0007,\u0001Ia\u0003 \u001bZ(\u001e\"\u001c\u0014aP"
		// @0AC: invokestatic game.C_100137_bn.func_105028_z(java.lang.String)char[]
		// @0AF: invokestatic game.C_100137_bn.func_105025_z(char[])java.lang.String
		// @0B2: putstatic java.lang.String game.C_100137_bn.field_105043_i
		// @0B5: getstatic int[][] game.C_100137_bn.field_105040_j
		// @0B8: bipush 18 (0x12)
		// @0BA: iconst_2
		// @0BB: newarray int[]
		// @0BD: dup
		// @0BE: iconst_0
		// @0BF: bipush 97 (0x61)
		// @0C1: iastore
		// @0C2: dup
		// @0C3: iconst_1
		// @0C4: bipush 106 (0x6A)
		// @0C6: iastore
		// @0C7: aastore
		// @0C8: getstatic int[][] game.C_100137_bn.field_105040_j
		// @0CB: iconst_0
		// @0CC: iconst_2
		// @0CD: newarray int[]
		// @0CF: dup
		// @0D0: iconst_0
		// @0D1: bipush 32 (0x20)
		// @0D3: iastore
		// @0D4: dup
		// @0D5: iconst_1
		// @0D6: bipush 24 (0x18)
		// @0D8: iastore
		// @0D9: aastore
		// @0DA: getstatic int[][] game.C_100137_bn.field_105040_j
		// @0DD: bipush 29 (0x1D)
		// @0DF: iconst_2
		// @0E0: newarray int[]
		// @0E2: dup
		// @0E3: iconst_0
		// @0E4: bipush 22 (0x16)
		// @0E6: iastore
		// @0E7: dup
		// @0E8: iconst_1
		// @0E9: bipush 95 (0x5F)
		// @0EB: iastore
		// @0EC: aastore
		// @0ED: getstatic int[][] game.C_100137_bn.field_105040_j
		// @0F0: bipush 31 (0x1F)
		// @0F2: iconst_2
		// @0F3: newarray int[]
		// @0F5: dup
		// @0F6: iconst_0
		// @0F7: bipush 97 (0x61)
		// @0F9: iastore
		// @0FA: dup
		// @0FB: iconst_1
		// @0FC: bipush 69 (0x45)
		// @0FE: iastore
		// @0FF: aastore
		// @100: getstatic int[][] game.C_100137_bn.field_105040_j
		// @103: bipush 10 (0x0A)
		// @105: iconst_2
		// @106: newarray int[]
		// @108: dup
		// @109: iconst_0
		// @10A: bipush 32 (0x20)
		// @10C: iastore
		// @10D: dup
		// @10E: iconst_1
		// @10F: bipush 22 (0x16)
		// @111: iastore
		// @112: aastore
		// @113: getstatic int[][] game.C_100137_bn.field_105040_j
		// @116: bipush 14 (0x0E)
		// @118: iconst_2
		// @119: newarray int[]
		// @11B: dup
		// @11C: iconst_0
		// @11D: bipush 64 (0x40)
		// @11F: iastore
		// @120: dup
		// @121: iconst_1
		// @122: bipush 23 (0x17)
		// @124: iastore
		// @125: aastore
		// @126: getstatic int[][] game.C_100137_bn.field_105040_j
		// @129: bipush 28 (0x1C)
		// @12B: iconst_2
		// @12C: newarray int[]
		// @12E: dup
		// @12F: iconst_0
		// @130: sipush 128 (0x0080)
		// @133: iastore
		// @134: dup
		// @135: iconst_1
		// @136: bipush 48 (0x30)
		// @138: iastore
		// @139: aastore
		// @13A: getstatic int[][] game.C_100137_bn.field_105040_j
		// @13D: bipush 11 (0x0B)
		// @13F: iconst_2
		// @140: newarray int[]
		// @142: dup
		// @143: iconst_0
		// @144: bipush 32 (0x20)
		// @146: iastore
		// @147: dup
		// @148: iconst_1
		// @149: bipush 12 (0x0C)
		// @14B: iastore
		// @14C: aastore
		// @14D: getstatic int[][] game.C_100137_bn.field_105040_j
		// @150: iconst_1
		// @151: iconst_2
		// @152: newarray int[]
		// @154: dup
		// @155: iconst_0
		// @156: bipush 32 (0x20)
		// @158: iastore
		// @159: dup
		// @15A: iconst_1
		// @15B: bipush 22 (0x16)
		// @15D: iastore
		// @15E: aastore
		// @15F: getstatic int[][] game.C_100137_bn.field_105040_j
		// @162: bipush 17 (0x11)
		// @164: iconst_2
		// @165: newarray int[]
		// @167: dup
		// @168: iconst_0
		// @169: bipush 45 (0x2D)
		// @16B: iastore
		// @16C: dup
		// @16D: iconst_1
		// @16E: iconst_4
		// @16F: iastore
		// @170: aastore
		// @171: getstatic int[][] game.C_100137_bn.field_105040_j
		// @174: bipush 26 (0x1A)
		// @176: iconst_2
		// @177: newarray int[]
		// @179: dup
		// @17A: iconst_0
		// @17B: bipush 83 (0x53)
		// @17D: iastore
		// @17E: dup
		// @17F: iconst_1
		// @180: bipush 22 (0x16)
		// @182: iastore
		// @183: aastore
		// @184: getstatic int[][] game.C_100137_bn.field_105040_j
		// @187: bipush 27 (0x1B)
		// @189: iconst_2
		// @18A: newarray int[]
		// @18C: dup
		// @18D: iconst_0
		// @18E: bipush 99 (0x63)
		// @190: iastore
		// @191: dup
		// @192: iconst_1
		// @193: bipush 68 (0x44)
		// @195: iastore
		// @196: aastore
		// @197: getstatic int[][] game.C_100137_bn.field_105040_j
		// @19A: bipush 35 (0x23)
		// @19C: iconst_2
		// @19D: newarray int[]
		// @19F: dup
		// @1A0: iconst_0
		// @1A1: sipush 131 (0x0083)
		// @1A4: iastore
		// @1A5: dup
		// @1A6: iconst_1
		// @1A7: bipush 42 (0x2A)
		// @1A9: iastore
		// @1AA: aastore
		// @1AB: getstatic int[][] game.C_100137_bn.field_105040_j
		// @1AE: bipush 15 (0x0F)
		// @1B0: iconst_2
		// @1B1: newarray int[]
		// @1B3: dup
		// @1B4: iconst_0
		// @1B5: bipush 77 (0x4D)
		// @1B7: iastore
		// @1B8: dup
		// @1B9: iconst_1
		// @1BA: bipush 11 (0x0B)
		// @1BC: iastore
		// @1BD: aastore
		// @1BE: getstatic int[][] game.C_100137_bn.field_105040_j
		// @1C1: bipush 21 (0x15)
		// @1C3: iconst_2
		// @1C4: newarray int[]
		// @1C6: dup
		// @1C7: iconst_0
		// @1C8: sipush 132 (0x0084)
		// @1CB: iastore
		// @1CC: dup
		// @1CD: iconst_1
		// @1CE: bipush 96 (0x60)
		// @1D0: iastore
		// @1D1: aastore
		// @1D2: getstatic int[][] game.C_100137_bn.field_105040_j
		// @1D5: bipush 12 (0x0C)
		// @1D7: iconst_2
		// @1D8: newarray int[]
		// @1DA: dup
		// @1DB: iconst_0
		// @1DC: bipush 32 (0x20)
		// @1DE: iastore
		// @1DF: dup
		// @1E0: iconst_1
		// @1E1: bipush 10 (0x0A)
		// @1E3: iastore
		// @1E4: aastore
		// @1E5: getstatic int[][] game.C_100137_bn.field_105040_j
		// @1E8: iconst_5
		// @1E9: iconst_2
		// @1EA: newarray int[]
		// @1EC: dup
		// @1ED: iconst_0
		// @1EE: bipush 32 (0x20)
		// @1F0: iastore
		// @1F1: dup
		// @1F2: iconst_1
		// @1F3: bipush 16 (0x10)
		// @1F5: iastore
		// @1F6: aastore
		// @1F7: getstatic int[][] game.C_100137_bn.field_105040_j
		// @1FA: iconst_4
		// @1FB: iconst_2
		// @1FC: newarray int[]
		// @1FE: dup
		// @1FF: iconst_0
		// @200: bipush 32 (0x20)
		// @202: iastore
		// @203: dup
		// @204: iconst_1
		// @205: bipush 14 (0x0E)
		// @207: iastore
		// @208: aastore
		// @209: getstatic int[][] game.C_100137_bn.field_105040_j
		// @20C: bipush 30 (0x1E)
		// @20E: iconst_2
		// @20F: newarray int[]
		// @211: dup
		// @212: iconst_0
		// @213: bipush 94 (0x5E)
		// @215: iastore
		// @216: dup
		// @217: iconst_1
		// @218: bipush 58 (0x3A)
		// @21A: iastore
		// @21B: aastore
		// @21C: getstatic int[][] game.C_100137_bn.field_105040_j
		// @21F: bipush 13 (0x0D)
		// @221: iconst_2
		// @222: newarray int[]
		// @224: dup
		// @225: iconst_0
		// @226: bipush 32 (0x20)
		// @228: iastore
		// @229: dup
		// @22A: iconst_1
		// @22B: bipush 12 (0x0C)
		// @22D: iastore
		// @22E: aastore
		// @22F: getstatic int[][] game.C_100137_bn.field_105040_j
		// @232: iconst_2
		// @233: iconst_2
		// @234: newarray int[]
		// @236: dup
		// @237: iconst_0
		// @238: bipush 32 (0x20)
		// @23A: iastore
		// @23B: dup
		// @23C: iconst_1
		// @23D: bipush 26 (0x1A)
		// @23F: iastore
		// @240: aastore
		// @241: getstatic int[][] game.C_100137_bn.field_105040_j
		// @244: bipush 16 (0x10)
		// @246: iconst_2
		// @247: newarray int[]
		// @249: dup
		// @24A: iconst_0
		// @24B: bipush 60 (0x3C)
		// @24D: iastore
		// @24E: dup
		// @24F: iconst_1
		// @250: bipush 45 (0x2D)
		// @252: iastore
		// @253: aastore
		// @254: getstatic int[][] game.C_100137_bn.field_105040_j
		// @257: iconst_3
		// @258: iconst_2
		// @259: newarray int[]
		// @25B: dup
		// @25C: iconst_0
		// @25D: bipush 32 (0x20)
		// @25F: iastore
		// @260: dup
		// @261: iconst_1
		// @262: bipush 23 (0x17)
		// @264: iastore
		// @265: aastore
		// @266: iconst_0
		// @267: putstatic boolean game.C_100137_bn.field_105032_g
		// @26A: return
	}
	
	private static char[] func_105028_z(String arg0)
	{
		// @00: aload_0
		// @01: invokevirtual java.lang.String.toCharArray()char[]
		// @04: dup
		// @05: arraylength
		// @06: iconst_2
		// @07: if_icmpge @13
		// @0A: dup
		// @0B: iconst_0
		// @0C: dup2
		// @0D: caload
		// @0E: bipush 112 (0x70)
		// @10: ixor
		// @11: i2c
		// @12: castore
		// @13: areturn
	}
	
	private static String func_105025_z(char[] arg0)
	{
		// @00: aload_0
		// @01: dup
		// @02: arraylength
		// @03: swap
		// @04: iconst_0
		// @05: istore_1
		// @06: goto @4C
		// @09: dup
		// @0A: iload_1
		// @0B: dup2
		// @0C: caload
		// @0D: iload_1
		// @0E: iconst_5
		// @0F: irem
		// @10: tableswitch def: @44, for 0: @30, for 1: @35, for 2: @3A, for 3: @3F
		// @30: bipush 69 (0x45)
		// @32: goto @46
		// @35: bipush 111 (0x6F)
		// @37: goto @46
		// @3A: bipush 46 (0x2E)
		// @3C: goto @46
		// @3F: bipush 65 (0x41)
		// @41: goto @46
		// @44: bipush 112 (0x70)
		// @46: ixor
		// @47: i2c
		// @48: castore
		// @49: iinc #1 +1
		// @4C: swap
		// @4D: dup_x1
		// @4E: iload_1
		// @4F: if_icmpgt @09
		// @52: new java.lang.String
		// @55: dup_x1
		// @56: swap
		// @57: invokespecial java.lang.String.<init>(char[])void
		// @5A: invokevirtual java.lang.String.intern()java.lang.String
		// @5D: areturn
	}
}
