package game;

final class C_100305_km extends C_100218_am
{
	private C_100308_lh field_103230_P;
	static int field_103229_Q;
	private int field_103233_O;
	static String field_103232_R;
	private static final String[] field_103231_S;
	
	static final void func_103225_a(int arg0, int arg1, String arg2, int arg3, int arg4, C_100302_ka arg5, int arg6, int arg7, int arg8)
	{
		// @000: getstatic int game.SteelSentinels.field_105275_O
		// @003: istore #12
		// @005: new game.C_100302_ka
		// @008: dup
		// @009: iload #6
		// @00B: i2l
		// @00C: getstatic game.C_100302_ka game.C_100286_nl.field_106813_m
		// @00F: aload_2
		// @010: invokespecial game.C_100302_ka.<init>(long, game.C_100302_ka, java.lang.String)void
		// @013: astore #9
		// @015: iload_0
		// @016: sipush 2000 (0x07D0)
		// @019: if_icmpeq @01D
		// @01C: return
		// @01D: aload #9
		// @01F: iload_1
		// @020: bipush -7 (0xF9)
		// @022: iadd
		// @023: bipush 20 (0x14)
		// @025: iconst_m1
		// @026: iload #7
		// @028: iload_1
		// @029: ineg
		// @02A: iload #4
		// @02C: iconst_2
		// @02D: iadd
		// @02E: iadd
		// @02F: invokevirtual game.C_100302_ka.func_101825_a(int, int, int, int, int)void
		// @032: aload #5
		// @034: bipush -76 (0xB4)
		// @036: aload #9
		// @038: invokevirtual game.C_100302_ka.func_101824_b(int, game.C_100302_ka)void
		// @03B: new game.C_100302_ka
		// @03E: dup
		// @03F: iload #6
		// @041: i2l
		// @042: aconst_null
		// @043: invokespecial game.C_100302_ka.<init>(long, game.C_100302_ka)void
		// @046: astore #10
		// @048: aload #10
		// @04A: bipush 22 (0x16)
		// @04C: bipush 12 (0x0C)
		// @04E: iconst_m1
		// @04F: iconst_1
		// @050: iload_1
		// @051: ineg
		// @052: iload #4
		// @054: iadd
		// @055: bipush 20 (0x14)
		// @057: isub
		// @058: invokevirtual game.C_100302_ka.func_101825_a(int, int, int, int, int)void
		// @05B: aload #10
		// @05D: new game.C_100037_wb
		// @060: dup
		// @061: aload #10
		// @063: getfield int game.C_100302_ka.field_101886_Kb
		// @066: aload #10
		// @068: getfield int game.C_100302_ka.field_101848_lb
		// @06B: invokespecial game.C_100037_wb.<init>(int, int)void
		// @06E: putfield game.C_100037_wb game.C_100302_ka.field_101887_nb
		// @071: aload #10
		// @073: getfield game.C_100037_wb game.C_100302_ka.field_101887_nb
		// @076: invokevirtual game.C_100037_wb.func_102379_d()void
		// @079: iconst_0
		// @07A: iconst_0
		// @07B: aload #10
		// @07D: getfield int game.C_100302_ka.field_101886_Kb
		// @080: aload #10
		// @082: getfield int game.C_100302_ka.field_101848_lb
		// @085: ldc 1995681 (0x1e73a1)
		// @087: invokestatic game.C_100196_rb.func_105784_h(int, int, int, int, int)void
		// @08A: iconst_m1
		// @08B: iload_3
		// @08C: iconst_m1
		// @08D: ixor
		// @08E: if_icmple @137
		// @091: iload_3
		// @092: iconst_m1
		// @093: ixor
		// @094: iload #8
		// @096: iconst_m1
		// @097: ixor
		// @098: if_icmplt @118
		// @09B: goto @09F
		// @09E: athrow
		// @09F: iconst_2
		// @0A0: iconst_2
		// @0A1: bipush -4 (0xFC)
		// @0A3: aload #10
		// @0A5: getfield int game.C_100302_ka.field_101886_Kb
		// @0A8: iadd
		// @0A9: iload_3
		// @0AA: imul
		// @0AB: iload #8
		// @0AD: idiv
		// @0AE: bipush -4 (0xFC)
		// @0B0: aload #10
		// @0B2: getfield int game.C_100302_ka.field_101848_lb
		// @0B5: iadd
		// @0B6: ldc 1995681 (0x1e73a1)
		// @0B8: invokestatic game.C_100196_rb.func_105782_i(int, int, int, int, int)void
		// @0BB: bipush 100 (0x64)
		// @0BD: iload #8
		// @0BF: if_icmpge @14C
		// @0C2: goto @0C6
		// @0C5: athrow
		// @0C6: sipush 2000 (0x07D0)
		// @0C9: iload #8
		// @0CB: if_icmple @14C
		// @0CE: goto @0D2
		// @0D1: athrow
		// @0D2: bipush 100 (0x64)
		// @0D4: istore #11
		// @0D6: iload #11
		// @0D8: iconst_m1
		// @0D9: ixor
		// @0DA: iload #8
		// @0DC: iconst_m1
		// @0DD: ixor
		// @0DE: if_icmple @113
		// @0E1: iconst_2
		// @0E2: iload #11
		// @0E4: bipush -4 (0xFC)
		// @0E6: aload #10
		// @0E8: getfield int game.C_100302_ka.field_101886_Kb
		// @0EB: iadd
		// @0EC: imul
		// @0ED: iload #8
		// @0EF: idiv
		// @0F0: ineg
		// @0F1: isub
		// @0F2: iconst_2
		// @0F3: aload #10
		// @0F5: getfield int game.C_100302_ka.field_101848_lb
		// @0F8: bipush -4 (0xFC)
		// @0FA: iadd
		// @0FB: ldc 4473924 (0x444444)
		// @0FD: bipush 96 (0x60)
		// @0FF: invokestatic game.C_100196_rb.func_105805_b(int, int, int, int, int)void
		// @102: iinc #11 +100
		// @105: iload #12
		// @107: ifne @160
		// @10A: iload #12
		// @10C: ifeq @0D6
		// @10F: goto @113
		// @112: athrow
		// @113: iload #12
		// @115: ifeq @14C
		// @118: iconst_2
		// @119: iconst_2
		// @11A: aload #10
		// @11C: getfield int game.C_100302_ka.field_101886_Kb
		// @11F: iconst_4
		// @120: isub
		// @121: bipush -4 (0xFC)
		// @123: aload #10
		// @125: getfield int game.C_100302_ka.field_101848_lb
		// @128: iadd
		// @129: ldc 5157841 (0x4eb3d1)
		// @12B: invokestatic game.C_100196_rb.func_105782_i(int, int, int, int, int)void
		// @12E: iload #12
		// @130: ifeq @14C
		// @133: goto @137
		// @136: athrow
		// @137: iconst_0
		// @138: iconst_0
		// @139: aload #10
		// @13B: getfield int game.C_100302_ka.field_101886_Kb
		// @13E: aload #10
		// @140: getfield int game.C_100302_ka.field_101848_lb
		// @143: ldc 10367841 (0x9e3361)
		// @145: invokestatic game.C_100196_rb.func_105784_h(int, int, int, int, int)void
		// @148: goto @14C
		// @14B: athrow
		// @14C: aload #9
		// @14E: iload_0
		// @14F: sipush -1948 (0xF864)
		// @152: ixor
		// @153: aload #10
		// @155: invokevirtual game.C_100302_ka.func_101824_b(int, game.C_100302_ka)void
		// @158: getstatic game.C_100185_rm game.C_100049_vf.field_104206_l
		// @15B: bipush 113 (0x71)
		// @15D: invokevirtual game.C_100185_rm.func_105476_a(byte)void
		// @160: goto @1F8
		// @163: astore #9
		// @165: aload #9
		// @167: new java.lang.StringBuilder
		// @16A: dup
		// @16B: invokespecial java.lang.StringBuilder.<init>()void
		// @16E: getstatic java.lang.String[] game.C_100305_km.field_103231_S
		// @171: bipush 12 (0x0C)
		// @173: aaload
		// @174: invokevirtual java.lang.StringBuilder.append(java.lang.String)java.lang.StringBuilder
		// @177: iload_0
		// @178: invokevirtual java.lang.StringBuilder.append(int)java.lang.StringBuilder
		// @17B: bipush 44 (0x2C)
		// @17D: invokevirtual java.lang.StringBuilder.append(char)java.lang.StringBuilder
		// @180: iload_1
		// @181: invokevirtual java.lang.StringBuilder.append(int)java.lang.StringBuilder
		// @184: bipush 44 (0x2C)
		// @186: invokevirtual java.lang.StringBuilder.append(char)java.lang.StringBuilder
		// @189: aload_2
		// @18A: ifnull @196
		// @18D: getstatic java.lang.String[] game.C_100305_km.field_103231_S
		// @190: iconst_4
		// @191: aaload
		// @192: goto @19C
		// @195: athrow
		// @196: getstatic java.lang.String[] game.C_100305_km.field_103231_S
		// @199: bipush 6 (0x06)
		// @19B: aaload
		// @19C: invokevirtual java.lang.StringBuilder.append(java.lang.String)java.lang.StringBuilder
		// @19F: bipush 44 (0x2C)
		// @1A1: invokevirtual java.lang.StringBuilder.append(char)java.lang.StringBuilder
		// @1A4: iload_3
		// @1A5: invokevirtual java.lang.StringBuilder.append(int)java.lang.StringBuilder
		// @1A8: bipush 44 (0x2C)
		// @1AA: invokevirtual java.lang.StringBuilder.append(char)java.lang.StringBuilder
		// @1AD: iload #4
		// @1AF: invokevirtual java.lang.StringBuilder.append(int)java.lang.StringBuilder
		// @1B2: bipush 44 (0x2C)
		// @1B4: invokevirtual java.lang.StringBuilder.append(char)java.lang.StringBuilder
		// @1B7: aload #5
		// @1B9: ifnull @1C5
		// @1BC: getstatic java.lang.String[] game.C_100305_km.field_103231_S
		// @1BF: iconst_4
		// @1C0: aaload
		// @1C1: goto @1CB
		// @1C4: athrow
		// @1C5: getstatic java.lang.String[] game.C_100305_km.field_103231_S
		// @1C8: bipush 6 (0x06)
		// @1CA: aaload
		// @1CB: invokevirtual java.lang.StringBuilder.append(java.lang.String)java.lang.StringBuilder
		// @1CE: bipush 44 (0x2C)
		// @1D0: invokevirtual java.lang.StringBuilder.append(char)java.lang.StringBuilder
		// @1D3: iload #6
		// @1D5: invokevirtual java.lang.StringBuilder.append(int)java.lang.StringBuilder
		// @1D8: bipush 44 (0x2C)
		// @1DA: invokevirtual java.lang.StringBuilder.append(char)java.lang.StringBuilder
		// @1DD: iload #7
		// @1DF: invokevirtual java.lang.StringBuilder.append(int)java.lang.StringBuilder
		// @1E2: bipush 44 (0x2C)
		// @1E4: invokevirtual java.lang.StringBuilder.append(char)java.lang.StringBuilder
		// @1E7: iload #8
		// @1E9: invokevirtual java.lang.StringBuilder.append(int)java.lang.StringBuilder
		// @1EC: bipush 41 (0x29)
		// @1EE: invokevirtual java.lang.StringBuilder.append(char)java.lang.StringBuilder
		// @1F1: invokevirtual java.lang.StringBuilder.toString()java.lang.String
		// @1F4: invokestatic game.C_100181_cf.func_105695_a(java.lang.Throwable, java.lang.String)game.C_100170_cm
		// @1F7: athrow
		// @1F8: return
	}
	
	final String func_102525_c(byte arg0)
	{
		// @00: aload_0
		// @01: getfield boolean game.C_100305_km.field_102539_j
		// @04: ifeq @13
		// @07: aload_0
		// @08: getfield game.C_100308_lh game.C_100305_km.field_103230_P
		// @0B: bipush -108 (0x94)
		// @0D: invokeinterface game.C_100308_lh.func_102949_c(int)java.lang.String
		// @12: areturn
		// @13: iload_1
		// @14: bipush 34 (0x22)
		// @16: if_icmpgt @1E
		// @19: aconst_null
		// @1A: checkcast java.lang.String
		// @1D: areturn
		// @1E: aconst_null
		// @1F: areturn
		// @20: astore_2
		// @21: aload_2
		// @22: new java.lang.StringBuilder
		// @25: dup
		// @26: invokespecial java.lang.StringBuilder.<init>()void
		// @29: getstatic java.lang.String[] game.C_100305_km.field_103231_S
		// @2C: iconst_3
		// @2D: aaload
		// @2E: invokevirtual java.lang.StringBuilder.append(java.lang.String)java.lang.StringBuilder
		// @31: iload_1
		// @32: invokevirtual java.lang.StringBuilder.append(int)java.lang.StringBuilder
		// @35: bipush 41 (0x29)
		// @37: invokevirtual java.lang.StringBuilder.append(char)java.lang.StringBuilder
		// @3A: invokevirtual java.lang.StringBuilder.toString()java.lang.String
		// @3D: invokestatic game.C_100181_cf.func_105695_a(java.lang.Throwable, java.lang.String)game.C_100170_cm
		// @40: athrow
	}
	
	static final int func_103222_b(int arg0, int arg1)
	{
		// @00: iconst_m1
		// @01: iload_1
		// @02: iconst_m1
		// @03: ixor
		// @04: if_icmpne @09
		// @07: iconst_0
		// @08: ireturn
		// @09: iconst_m1
		// @0A: iload_1
		// @0B: iconst_m1
		// @0C: ixor
		// @0D: if_icmple @64
		// @10: iconst_1
		// @11: istore_2
		// @12: ldc 65535 (0xffff)
		// @14: iload_1
		// @15: if_icmplt @1C
		// @18: goto @24
		// @1B: athrow
		// @1C: iload_1
		// @1D: bipush 16 (0x10)
		// @1F: ishr
		// @20: istore_1
		// @21: iinc #2 +16
		// @24: iload_1
		// @25: sipush 255 (0x00FF)
		// @28: if_icmpgt @2F
		// @2B: goto @37
		// @2E: athrow
		// @2F: iinc #2 +8
		// @32: iload_1
		// @33: bipush 8 (0x08)
		// @35: ishr
		// @36: istore_1
		// @37: bipush 15 (0x0F)
		// @39: iload_1
		// @3A: if_icmpge @44
		// @3D: iinc #2 +4
		// @40: iload_1
		// @41: iconst_4
		// @42: ishr
		// @43: istore_1
		// @44: bipush -4 (0xFC)
		// @46: iload_1
		// @47: iconst_m1
		// @48: ixor
		// @49: if_icmple @53
		// @4C: iload_1
		// @4D: iconst_2
		// @4E: ishr
		// @4F: istore_1
		// @50: iinc #2 +2
		// @53: bipush -2 (0xFE)
		// @55: iload_1
		// @56: iconst_m1
		// @57: ixor
		// @58: if_icmple @62
		// @5B: iinc #2 +1
		// @5E: iload_1
		// @5F: iconst_1
		// @60: ishr
		// @61: istore_1
		// @62: iload_2
		// @63: ireturn
		// @64: iconst_2
		// @65: istore_2
		// @66: iload_0
		// @67: bipush 63 (0x3F)
		// @69: if_icmpge @6F
		// @6C: bipush -91 (0xA5)
		// @6E: ireturn
		// @6F: iload_1
		// @70: ldc -65536 (0xffff0000)
		// @72: if_icmplt @79
		// @75: goto @81
		// @78: athrow
		// @79: iinc #2 +16
		// @7C: iload_1
		// @7D: bipush 16 (0x10)
		// @7F: ishr
		// @80: istore_1
		// @81: iload_1
		// @82: iconst_m1
		// @83: ixor
		// @84: sipush 255 (0x00FF)
		// @87: if_icmple @92
		// @8A: iinc #2 +8
		// @8D: iload_1
		// @8E: bipush 8 (0x08)
		// @90: ishr
		// @91: istore_1
		// @92: bipush -16 (0xF0)
		// @94: iload_1
		// @95: if_icmpgt @9C
		// @98: goto @A3
		// @9B: athrow
		// @9C: iinc #2 +4
		// @9F: iload_1
		// @A0: iconst_4
		// @A1: ishr
		// @A2: istore_1
		// @A3: iload_1
		// @A4: iconst_m1
		// @A5: ixor
		// @A6: iconst_3
		// @A7: if_icmple @B1
		// @AA: iload_1
		// @AB: iconst_2
		// @AC: ishr
		// @AD: istore_1
		// @AE: iinc #2 +2
		// @B1: iload_1
		// @B2: iconst_m1
		// @B3: ixor
		// @B4: iconst_1
		// @B5: if_icmple @BF
		// @B8: iload_1
		// @B9: iconst_1
		// @BA: ishr
		// @BB: istore_1
		// @BC: iinc #2 +1
		// @BF: iload_2
		// @C0: ireturn
		// @C1: astore_2
		// @C2: aload_2
		// @C3: new java.lang.StringBuilder
		// @C6: dup
		// @C7: invokespecial java.lang.StringBuilder.<init>()void
		// @CA: getstatic java.lang.String[] game.C_100305_km.field_103231_S
		// @CD: bipush 8 (0x08)
		// @CF: aaload
		// @D0: invokevirtual java.lang.StringBuilder.append(java.lang.String)java.lang.StringBuilder
		// @D3: iload_0
		// @D4: invokevirtual java.lang.StringBuilder.append(int)java.lang.StringBuilder
		// @D7: bipush 44 (0x2C)
		// @D9: invokevirtual java.lang.StringBuilder.append(char)java.lang.StringBuilder
		// @DC: iload_1
		// @DD: invokevirtual java.lang.StringBuilder.append(int)java.lang.StringBuilder
		// @E0: bipush 41 (0x29)
		// @E2: invokevirtual java.lang.StringBuilder.append(char)java.lang.StringBuilder
		// @E5: invokevirtual java.lang.StringBuilder.toString()java.lang.String
		// @E8: invokestatic game.C_100181_cf.func_105695_a(java.lang.Throwable, java.lang.String)game.C_100170_cm
		// @EB: athrow
	}
	
	static final void func_103228_a(int arg0, int arg1, int arg2, int arg3, int arg4, int arg5, int arg6, int arg7)
	{
		// @000: getstatic int game.SteelSentinels.field_105275_O
		// @003: istore #16
		// @005: iload_0
		// @006: iconst_m1
		// @007: ixor
		// @008: sipush -32768 (0x8000)
		// @00B: if_icmplt @012
		// @00E: goto @016
		// @011: athrow
		// @012: sipush 32767 (0x7FFF)
		// @015: istore_0
		// @016: iload_1
		// @017: iconst_m1
		// @018: isub
		// @019: iconst_m1
		// @01A: ixor
		// @01B: getstatic int[] game.C_100275_na.field_103087_l
		// @01E: iload #4
		// @020: iaload
		// @021: iconst_m1
		// @022: ixor
		// @023: if_icmplt @07B
		// @026: iconst_1
		// @027: iload #4
		// @029: if_icmpeq @05F
		// @02C: goto @030
		// @02F: athrow
		// @030: iload #4
		// @032: iconst_m1
		// @033: ixor
		// @034: bipush -3 (0xFD)
		// @036: if_icmpeq @041
		// @039: goto @03D
		// @03C: athrow
		// @03D: goto @120
		// @040: athrow
		// @041: iload_0
		// @042: getstatic int[] game.C_100164_se.field_105454_a
		// @045: iload_1
		// @046: bipush 10 (0x0A)
		// @048: iadd
		// @049: iaload
		// @04A: if_icmplt @051
		// @04D: goto @120
		// @050: athrow
		// @051: getstatic int[] game.C_100164_se.field_105454_a
		// @054: bipush 10 (0x0A)
		// @056: iload_1
		// @057: iadd
		// @058: iload_0
		// @059: iastore
		// @05A: iload #16
		// @05C: ifeq @120
		// @05F: getstatic int[] game.C_100164_se.field_105454_a
		// @062: iload_1
		// @063: iaload
		// @064: iload_0
		// @065: if_icmple @120
		// @068: goto @06C
		// @06B: athrow
		// @06C: getstatic int[] game.C_100164_se.field_105454_a
		// @06F: iload_1
		// @070: iload_0
		// @071: iastore
		// @072: iload #16
		// @074: ifeq @120
		// @077: goto @07B
		// @07A: athrow
		// @07B: getstatic int[] game.C_100275_na.field_103087_l
		// @07E: iload #4
		// @080: iconst_1
		// @081: iload_1
		// @082: iadd
		// @083: iastore
		// @084: iconst_0
		// @085: iload #4
		// @087: if_icmpne @0CE
		// @08A: goto @08E
		// @08D: athrow
		// @08E: getstatic int[] game.C_100275_na.field_103087_l
		// @091: iload #4
		// @093: iaload
		// @094: iconst_m1
		// @095: ixor
		// @096: getstatic int game.C_100287_nm.field_106827_c
		// @099: iconst_m1
		// @09A: ixor
		// @09B: if_icmpne @0CE
		// @09E: goto @0A2
		// @0A1: athrow
		// @0A2: bipush -25 (0xE7)
		// @0A4: invokestatic game.C_100234_ob.func_106268_c(byte)boolean
		// @0A7: ifeq @0B5
		// @0AA: goto @0AE
		// @0AD: athrow
		// @0AE: getstatic java.lang.String game.C_100047_vh.field_104152_b
		// @0B1: goto @0B8
		// @0B4: athrow
		// @0B5: getstatic java.lang.String game.C_100333_ij.field_107348_c
		// @0B8: putstatic java.lang.String game.C_100129_tg.field_102743_Db
		// @0BB: iconst_m1
		// @0BC: putstatic int game.C_100100_i.field_102012_Zb
		// @0BF: iconst_1
		// @0C0: getstatic int game.C_100269_ml.field_101127_j
		// @0C3: if_icmple @0CE
		// @0C6: iconst_1
		// @0C7: putstatic int game.C_100269_ml.field_101127_j
		// @0CA: goto @0CE
		// @0CD: athrow
		// @0CE: iload #4
		// @0D0: ifne @0FA
		// @0D3: bipush -11 (0xF5)
		// @0D5: getstatic int[] game.C_100275_na.field_103087_l
		// @0D8: iload #4
		// @0DA: iaload
		// @0DB: iconst_m1
		// @0DC: ixor
		// @0DD: if_icmpne @0FA
		// @0E0: goto @0E4
		// @0E3: athrow
		// @0E4: bipush -25 (0xE7)
		// @0E6: invokestatic game.C_100234_ob.func_106268_c(byte)boolean
		// @0E9: ifeq @0FA
		// @0EC: goto @0F0
		// @0EF: athrow
		// @0F0: getstatic java.lang.String game.C_100163_sf.field_105442_h
		// @0F3: putstatic java.lang.String game.C_100129_tg.field_102743_Db
		// @0F6: goto @0FA
		// @0F9: athrow
		// @0FA: iconst_1
		// @0FB: iload #4
		// @0FD: if_icmpeq @104
		// @100: goto @10A
		// @103: athrow
		// @104: getstatic int[] game.C_100164_se.field_105454_a
		// @107: iload_1
		// @108: iload_0
		// @109: iastore
		// @10A: bipush -3 (0xFD)
		// @10C: iload #4
		// @10E: iconst_m1
		// @10F: ixor
		// @110: if_icmpne @120
		// @113: getstatic int[] game.C_100164_se.field_105454_a
		// @116: iload_1
		// @117: bipush -10 (0xF6)
		// @119: isub
		// @11A: iload_0
		// @11B: iastore
		// @11C: goto @120
		// @11F: athrow
		// @120: bipush -25 (0xE7)
		// @122: invokestatic game.C_100234_ob.func_106268_c(byte)boolean
		// @125: ifne @17A
		// @128: getstatic game.C_100278_nd game.C_100115_ej.field_102043_Yb
		// @12B: bipush 71 (0x47)
		// @12D: bipush 116 (0x74)
		// @12F: invokevirtual game.C_100278_nd.func_101189_h(int, int)void
		// @132: getstatic game.C_100278_nd game.C_100115_ej.field_102043_Yb
		// @135: sipush 7838 (0x1E9E)
		// @138: iload #4
		// @13A: bipush 10 (0x0A)
		// @13C: imul
		// @13D: iload_1
		// @13E: iadd
		// @13F: invokevirtual game.C_100278_nd.func_101169_f(int, int)void
		// @142: getstatic game.C_100278_nd game.C_100115_ej.field_102043_Yb
		// @145: iload_0
		// @146: bipush 116 (0x74)
		// @148: invokevirtual game.C_100278_nd.func_101141_d(int, byte)void
		// @14B: getstatic game.C_100278_nd game.C_100115_ej.field_102043_Yb
		// @14E: iload #5
		// @150: bipush 81 (0x51)
		// @152: invokevirtual game.C_100278_nd.func_101154_d(int, int)void
		// @155: getstatic game.C_100278_nd game.C_100115_ej.field_102043_Yb
		// @158: iload #7
		// @15A: bipush 82 (0x52)
		// @15C: invokevirtual game.C_100278_nd.func_101154_d(int, int)void
		// @15F: getstatic game.C_100278_nd game.C_100115_ej.field_102043_Yb
		// @162: iload_2
		// @163: bipush -128 (0x80)
		// @165: invokevirtual game.C_100278_nd.func_101154_d(int, int)void
		// @168: getstatic game.C_100278_nd game.C_100115_ej.field_102043_Yb
		// @16B: iload_3
		// @16C: bipush 101 (0x65)
		// @16E: invokevirtual game.C_100278_nd.func_101154_d(int, int)void
		// @171: iload #16
		// @173: ifeq @18F
		// @176: goto @17A
		// @179: athrow
		// @17A: getstatic int game.C_100205_qf.field_103678_d
		// @17D: iconst_1
		// @17E: iload #4
		// @180: bipush 10 (0x0A)
		// @182: imul
		// @183: iload_1
		// @184: ineg
		// @185: isub
		// @186: ishl
		// @187: ior
		// @188: putstatic int game.C_100205_qf.field_103678_d
		// @18B: goto @18F
		// @18E: athrow
		// @18F: getstatic int[][] game.C_100170_cm.field_105546_m
		// @192: iload_1
		// @193: iload #4
		// @195: bipush 10 (0x0A)
		// @197: imul
		// @198: iadd
		// @199: aaload
		// @19A: astore #8
		// @19C: getstatic int[][] game.C_100179_ch.field_100815_j
		// @19F: iload_1
		// @1A0: iload #4
		// @1A2: bipush 10 (0x0A)
		// @1A4: imul
		// @1A5: iadd
		// @1A6: aaload
		// @1A7: astore #9
		// @1A9: iconst_0
		// @1AA: istore #10
		// @1AC: aload #8
		// @1AE: astore #12
		// @1B0: iconst_0
		// @1B1: istore #13
		// @1B3: iload #13
		// @1B5: aload #12
		// @1B7: arraylength
		// @1B8: if_icmpge @1E6
		// @1BB: aload #12
		// @1BD: iload #13
		// @1BF: iaload
		// @1C0: istore #14
		// @1C2: iload #14
		// @1C4: getstatic int[] game.C_100257_ln.field_106481_d
		// @1C7: bipush -123 (0x85)
		// @1C9: invokestatic game.C_100097_k.func_104572_a(int, int[], int)boolean
		// @1CC: iload #16
		// @1CE: ifne @1E7
		// @1D1: ifeq @1DB
		// @1D4: goto @1D8
		// @1D7: athrow
		// @1D8: goto @1DE
		// @1DB: iinc #10 +1
		// @1DE: iinc #13 +1
		// @1E1: iload #16
		// @1E3: ifeq @1B3
		// @1E6: iconst_0
		// @1E7: istore #11
		// @1E9: aload #9
		// @1EB: astore #12
		// @1ED: iconst_0
		// @1EE: istore #13
		// @1F0: iload #13
		// @1F2: iconst_m1
		// @1F3: ixor
		// @1F4: aload #12
		// @1F6: arraylength
		// @1F7: iconst_m1
		// @1F8: ixor
		// @1F9: if_icmple @224
		// @1FC: aload #12
		// @1FE: iload #13
		// @200: iaload
		// @201: istore #14
		// @203: iload #14
		// @205: getstatic int[] game.C_100075_uj.field_100655_u
		// @208: bipush -110 (0x92)
		// @20A: invokestatic game.C_100097_k.func_104572_a(int, int[], int)boolean
		// @20D: iload #16
		// @20F: ifne @233
		// @212: ifne @21C
		// @215: goto @219
		// @218: athrow
		// @219: iinc #11 +1
		// @21C: iinc #13 +1
		// @21F: iload #16
		// @221: ifeq @1F0
		// @224: iload #11
		// @226: newarray int[]
		// @228: putstatic int[] game.C_100103_eh.field_104662_f
		// @22B: iload #10
		// @22D: newarray int[]
		// @22F: putstatic int[] game.C_100042_we.field_104132_q
		// @232: iconst_0
		// @233: istore #12
		// @235: aload #8
		// @237: astore #13
		// @239: iconst_0
		// @23A: istore #14
		// @23C: aload #13
		// @23E: arraylength
		// @23F: iload #14
		// @241: if_icmple @277
		// @244: aload #13
		// @246: iload #14
		// @248: iaload
		// @249: istore #15
		// @24B: iload #15
		// @24D: getstatic int[] game.C_100257_ln.field_106481_d
		// @250: bipush -94 (0xA2)
		// @252: invokestatic game.C_100097_k.func_104572_a(int, int[], int)boolean
		// @255: iload #16
		// @257: ifne @27F
		// @25A: ifeq @264
		// @25D: goto @261
		// @260: athrow
		// @261: goto @26F
		// @264: getstatic int[] game.C_100042_we.field_104132_q
		// @267: iload #12
		// @269: iinc #12 +1
		// @26C: iload #15
		// @26E: iastore
		// @26F: iinc #14 +1
		// @272: iload #16
		// @274: ifeq @23C
		// @277: iconst_0
		// @278: istore #12
		// @27A: aload #9
		// @27C: astore #13
		// @27E: iconst_0
		// @27F: istore #14
		// @281: aload #13
		// @283: arraylength
		// @284: iconst_m1
		// @285: ixor
		// @286: iload #14
		// @288: iconst_m1
		// @289: ixor
		// @28A: if_icmpge @2C0
		// @28D: aload #13
		// @28F: iload #14
		// @291: iaload
		// @292: istore #15
		// @294: iload #15
		// @296: getstatic int[] game.C_100075_uj.field_100655_u
		// @299: bipush -111 (0x91)
		// @29B: invokestatic game.C_100097_k.func_104572_a(int, int[], int)boolean
		// @29E: iload #16
		// @2A0: ifne @2C1
		// @2A3: ifeq @2AD
		// @2A6: goto @2AA
		// @2A9: athrow
		// @2AA: goto @2B8
		// @2AD: getstatic int[] game.C_100103_eh.field_104662_f
		// @2B0: iload #12
		// @2B2: iinc #12 +1
		// @2B5: iload #15
		// @2B7: iastore
		// @2B8: iinc #14 +1
		// @2BB: iload #16
		// @2BD: ifeq @281
		// @2C0: iconst_m1
		// @2C1: iload #10
		// @2C3: iconst_m1
		// @2C4: ixor
		// @2C5: if_icmpgt @2D2
		// @2C8: iconst_0
		// @2C9: iload #11
		// @2CB: if_icmpge @2F6
		// @2CE: goto @2D2
		// @2D1: athrow
		// @2D2: bipush -117 (0x8B)
		// @2D4: invokestatic game.C_100203_ql.func_105921_a(int)void
		// @2D7: iconst_0
		// @2D8: istore #12
		// @2DA: iload #12
		// @2DC: iconst_m1
		// @2DD: ixor
		// @2DE: getstatic int[] game.C_100074_g.field_104410_e
		// @2E1: arraylength
		// @2E2: iconst_m1
		// @2E3: ixor
		// @2E4: if_icmple @2F6
		// @2E7: getstatic int[] game.C_100074_g.field_104410_e
		// @2EA: iload #12
		// @2EC: iconst_0
		// @2ED: iastore
		// @2EE: iinc #12 +1
		// @2F1: iload #16
		// @2F3: ifeq @2DA
		// @2F6: bipush -30 (0xE2)
		// @2F8: bipush -45 (0xD3)
		// @2FA: iload #6
		// @2FC: isub
		// @2FD: bipush 42 (0x2A)
		// @2FF: idiv
		// @300: idiv
		// @301: istore #13
		// @303: goto @36D
		// @306: astore #8
		// @308: aload #8
		// @30A: new java.lang.StringBuilder
		// @30D: dup
		// @30E: invokespecial java.lang.StringBuilder.<init>()void
		// @311: getstatic java.lang.String[] game.C_100305_km.field_103231_S
		// @314: bipush 16 (0x10)
		// @316: aaload
		// @317: invokevirtual java.lang.StringBuilder.append(java.lang.String)java.lang.StringBuilder
		// @31A: iload_0
		// @31B: invokevirtual java.lang.StringBuilder.append(int)java.lang.StringBuilder
		// @31E: bipush 44 (0x2C)
		// @320: invokevirtual java.lang.StringBuilder.append(char)java.lang.StringBuilder
		// @323: iload_1
		// @324: invokevirtual java.lang.StringBuilder.append(int)java.lang.StringBuilder
		// @327: bipush 44 (0x2C)
		// @329: invokevirtual java.lang.StringBuilder.append(char)java.lang.StringBuilder
		// @32C: iload_2
		// @32D: invokevirtual java.lang.StringBuilder.append(int)java.lang.StringBuilder
		// @330: bipush 44 (0x2C)
		// @332: invokevirtual java.lang.StringBuilder.append(char)java.lang.StringBuilder
		// @335: iload_3
		// @336: invokevirtual java.lang.StringBuilder.append(int)java.lang.StringBuilder
		// @339: bipush 44 (0x2C)
		// @33B: invokevirtual java.lang.StringBuilder.append(char)java.lang.StringBuilder
		// @33E: iload #4
		// @340: invokevirtual java.lang.StringBuilder.append(int)java.lang.StringBuilder
		// @343: bipush 44 (0x2C)
		// @345: invokevirtual java.lang.StringBuilder.append(char)java.lang.StringBuilder
		// @348: iload #5
		// @34A: invokevirtual java.lang.StringBuilder.append(int)java.lang.StringBuilder
		// @34D: bipush 44 (0x2C)
		// @34F: invokevirtual java.lang.StringBuilder.append(char)java.lang.StringBuilder
		// @352: iload #6
		// @354: invokevirtual java.lang.StringBuilder.append(int)java.lang.StringBuilder
		// @357: bipush 44 (0x2C)
		// @359: invokevirtual java.lang.StringBuilder.append(char)java.lang.StringBuilder
		// @35C: iload #7
		// @35E: invokevirtual java.lang.StringBuilder.append(int)java.lang.StringBuilder
		// @361: bipush 41 (0x29)
		// @363: invokevirtual java.lang.StringBuilder.append(char)java.lang.StringBuilder
		// @366: invokevirtual java.lang.StringBuilder.toString()java.lang.String
		// @369: invokestatic game.C_100181_cf.func_105695_a(java.lang.Throwable, java.lang.String)game.C_100170_cm
		// @36C: athrow
		// @36D: return
	}
	
	static final boolean func_103221_a(byte arg0, C_100098_h arg1, C_100098_h arg2, C_100098_h arg3)
	{
		// @00: iload_0
		// @01: bipush -115 (0x8D)
		// @03: if_icmpeq @08
		// @06: iconst_1
		// @07: ireturn
		// @08: aload_1
		// @09: iconst_0
		// @0A: invokevirtual game.C_100098_h.func_104597_a(boolean)boolean
		// @0D: ifeq @22
		// @10: aload_1
		// @11: getstatic java.lang.String[] game.C_100305_km.field_103231_S
		// @14: bipush 13 (0x0D)
		// @16: aaload
		// @17: iconst_0
		// @18: invokevirtual game.C_100098_h.func_104593_a(java.lang.String, boolean)boolean
		// @1B: ifne @24
		// @1E: goto @22
		// @21: athrow
		// @22: iconst_0
		// @23: ireturn
		// @24: aload_3
		// @25: iconst_0
		// @26: invokevirtual game.C_100098_h.func_104597_a(boolean)boolean
		// @29: ifeq @42
		// @2C: aload_3
		// @2D: getstatic java.lang.String[] game.C_100305_km.field_103231_S
		// @30: bipush 13 (0x0D)
		// @32: aaload
		// @33: iconst_0
		// @34: invokevirtual game.C_100098_h.func_104593_a(java.lang.String, boolean)boolean
		// @37: ifeq @42
		// @3A: goto @3E
		// @3D: athrow
		// @3E: goto @44
		// @41: athrow
		// @42: iconst_0
		// @43: ireturn
		// @44: aload_2
		// @45: iconst_0
		// @46: invokevirtual game.C_100098_h.func_104597_a(boolean)boolean
		// @49: ifeq @62
		// @4C: aload_2
		// @4D: getstatic java.lang.String[] game.C_100305_km.field_103231_S
		// @50: bipush 15 (0x0F)
		// @52: aaload
		// @53: iconst_0
		// @54: invokevirtual game.C_100098_h.func_104593_a(java.lang.String, boolean)boolean
		// @57: ifeq @62
		// @5A: goto @5E
		// @5D: athrow
		// @5E: goto @64
		// @61: athrow
		// @62: iconst_0
		// @63: ireturn
		// @64: iconst_1
		// @65: ireturn
		// @66: astore #4
		// @68: aload #4
		// @6A: new java.lang.StringBuilder
		// @6D: dup
		// @6E: invokespecial java.lang.StringBuilder.<init>()void
		// @71: getstatic java.lang.String[] game.C_100305_km.field_103231_S
		// @74: bipush 14 (0x0E)
		// @76: aaload
		// @77: invokevirtual java.lang.StringBuilder.append(java.lang.String)java.lang.StringBuilder
		// @7A: iload_0
		// @7B: invokevirtual java.lang.StringBuilder.append(int)java.lang.StringBuilder
		// @7E: bipush 44 (0x2C)
		// @80: invokevirtual java.lang.StringBuilder.append(char)java.lang.StringBuilder
		// @83: aload_1
		// @84: ifnull @90
		// @87: getstatic java.lang.String[] game.C_100305_km.field_103231_S
		// @8A: iconst_4
		// @8B: aaload
		// @8C: goto @96
		// @8F: athrow
		// @90: getstatic java.lang.String[] game.C_100305_km.field_103231_S
		// @93: bipush 6 (0x06)
		// @95: aaload
		// @96: invokevirtual java.lang.StringBuilder.append(java.lang.String)java.lang.StringBuilder
		// @99: bipush 44 (0x2C)
		// @9B: invokevirtual java.lang.StringBuilder.append(char)java.lang.StringBuilder
		// @9E: aload_2
		// @9F: ifnull @AB
		// @A2: getstatic java.lang.String[] game.C_100305_km.field_103231_S
		// @A5: iconst_4
		// @A6: aaload
		// @A7: goto @B1
		// @AA: athrow
		// @AB: getstatic java.lang.String[] game.C_100305_km.field_103231_S
		// @AE: bipush 6 (0x06)
		// @B0: aaload
		// @B1: invokevirtual java.lang.StringBuilder.append(java.lang.String)java.lang.StringBuilder
		// @B4: bipush 44 (0x2C)
		// @B6: invokevirtual java.lang.StringBuilder.append(char)java.lang.StringBuilder
		// @B9: aload_3
		// @BA: ifnull @C6
		// @BD: getstatic java.lang.String[] game.C_100305_km.field_103231_S
		// @C0: iconst_4
		// @C1: aaload
		// @C2: goto @CC
		// @C5: athrow
		// @C6: getstatic java.lang.String[] game.C_100305_km.field_103231_S
		// @C9: bipush 6 (0x06)
		// @CB: aaload
		// @CC: invokevirtual java.lang.StringBuilder.append(java.lang.String)java.lang.StringBuilder
		// @CF: bipush 41 (0x29)
		// @D1: invokevirtual java.lang.StringBuilder.append(char)java.lang.StringBuilder
		// @D4: invokevirtual java.lang.StringBuilder.toString()java.lang.String
		// @D7: invokestatic game.C_100181_cf.func_105695_a(java.lang.Throwable, java.lang.String)game.C_100170_cm
		// @DA: athrow
	}
	
	final boolean func_102522_a(int arg0, C_100336_im arg1)
	{
		// @00: iload_1
		// @01: iconst_1
		// @02: if_icmpeq @0E
		// @05: bipush 90 (0x5A)
		// @07: putstatic int game.C_100305_km.field_103229_Q
		// @0A: goto @0E
		// @0D: athrow
		// @0E: iconst_0
		// @0F: ireturn
		// @10: astore_3
		// @11: aload_3
		// @12: new java.lang.StringBuilder
		// @15: dup
		// @16: invokespecial java.lang.StringBuilder.<init>()void
		// @19: getstatic java.lang.String[] game.C_100305_km.field_103231_S
		// @1C: bipush 10 (0x0A)
		// @1E: aaload
		// @1F: invokevirtual java.lang.StringBuilder.append(java.lang.String)java.lang.StringBuilder
		// @22: iload_1
		// @23: invokevirtual java.lang.StringBuilder.append(int)java.lang.StringBuilder
		// @26: bipush 44 (0x2C)
		// @28: invokevirtual java.lang.StringBuilder.append(char)java.lang.StringBuilder
		// @2B: aload_2
		// @2C: ifnull @38
		// @2F: getstatic java.lang.String[] game.C_100305_km.field_103231_S
		// @32: iconst_4
		// @33: aaload
		// @34: goto @3E
		// @37: athrow
		// @38: getstatic java.lang.String[] game.C_100305_km.field_103231_S
		// @3B: bipush 6 (0x06)
		// @3D: aaload
		// @3E: invokevirtual java.lang.StringBuilder.append(java.lang.String)java.lang.StringBuilder
		// @41: bipush 41 (0x29)
		// @43: invokevirtual java.lang.StringBuilder.append(char)java.lang.StringBuilder
		// @46: invokevirtual java.lang.StringBuilder.toString()java.lang.String
		// @49: invokestatic game.C_100181_cf.func_105695_a(java.lang.Throwable, java.lang.String)game.C_100170_cm
		// @4C: athrow
	}
	
	final void func_102513_a(C_100336_im arg0, int arg1, int arg2, int arg3)
	{
		// @00: aload_0
		// @01: dup
		// @02: getfield int game.C_100305_km.field_103233_O
		// @05: iconst_1
		// @06: iadd
		// @07: putfield int game.C_100305_km.field_103233_O
		// @0A: aload_0
		// @0B: aload_1
		// @0C: iload_2
		// @0D: iload_3
		// @0E: iload #4
		// @10: invokespecial game.C_100218_am.func_102513_a(game.C_100336_im, int, int, int)void
		// @13: goto @68
		// @16: astore #5
		// @18: aload #5
		// @1A: new java.lang.StringBuilder
		// @1D: dup
		// @1E: invokespecial java.lang.StringBuilder.<init>()void
		// @21: getstatic java.lang.String[] game.C_100305_km.field_103231_S
		// @24: bipush 11 (0x0B)
		// @26: aaload
		// @27: invokevirtual java.lang.StringBuilder.append(java.lang.String)java.lang.StringBuilder
		// @2A: aload_1
		// @2B: ifnull @37
		// @2E: getstatic java.lang.String[] game.C_100305_km.field_103231_S
		// @31: iconst_4
		// @32: aaload
		// @33: goto @3D
		// @36: athrow
		// @37: getstatic java.lang.String[] game.C_100305_km.field_103231_S
		// @3A: bipush 6 (0x06)
		// @3C: aaload
		// @3D: invokevirtual java.lang.StringBuilder.append(java.lang.String)java.lang.StringBuilder
		// @40: bipush 44 (0x2C)
		// @42: invokevirtual java.lang.StringBuilder.append(char)java.lang.StringBuilder
		// @45: iload_2
		// @46: invokevirtual java.lang.StringBuilder.append(int)java.lang.StringBuilder
		// @49: bipush 44 (0x2C)
		// @4B: invokevirtual java.lang.StringBuilder.append(char)java.lang.StringBuilder
		// @4E: iload_3
		// @4F: invokevirtual java.lang.StringBuilder.append(int)java.lang.StringBuilder
		// @52: bipush 44 (0x2C)
		// @54: invokevirtual java.lang.StringBuilder.append(char)java.lang.StringBuilder
		// @57: iload #4
		// @59: invokevirtual java.lang.StringBuilder.append(int)java.lang.StringBuilder
		// @5C: bipush 41 (0x29)
		// @5E: invokevirtual java.lang.StringBuilder.append(char)java.lang.StringBuilder
		// @61: invokevirtual java.lang.StringBuilder.toString()java.lang.String
		// @64: invokestatic game.C_100181_cf.func_105695_a(java.lang.Throwable, java.lang.String)game.C_100170_cm
		// @67: athrow
		// @68: return
	}
	
	final void func_102528_a(int arg0, int arg1, int arg2, byte arg3)
	{
		// @000: getstatic int game.SteelSentinels.field_105275_O
		// @003: istore #11
		// @005: aload_0
		// @006: iload_1
		// @007: iload_2
		// @008: iload_3
		// @009: bipush -127 (0x81)
		// @00B: invokespecial game.C_100218_am.func_102528_a(int, int, int, byte)void
		// @00E: iload_1
		// @00F: ifne @015
		// @012: goto @016
		// @015: return
		// @016: aload_0
		// @017: getfield int game.C_100305_km.field_102537_l
		// @01A: ldc 2023206913 (0x7897b001)
		// @01C: ishr
		// @01D: aload_0
		// @01E: getfield int game.C_100305_km.field_102538_m
		// @021: iload_3
		// @022: iadd
		// @023: iadd
		// @024: istore #5
		// @026: iload #4
		// @028: bipush -126 (0x82)
		// @02A: if_icmplt @039
		// @02D: aload_0
		// @02E: aconst_null
		// @02F: checkcast game.C_100308_lh
		// @032: putfield game.C_100308_lh game.C_100305_km.field_103230_P
		// @035: goto @039
		// @038: athrow
		// @039: aload_0
		// @03A: getfield int game.C_100305_km.field_102541_w
		// @03D: iload_2
		// @03E: iadd
		// @03F: aload_0
		// @040: getfield int game.C_100305_km.field_102544_t
		// @043: ldc 332850561 (0x13d6e581)
		// @045: ishr
		// @046: iadd
		// @047: istore #6
		// @049: aload_0
		// @04A: getfield game.C_100308_lh game.C_100305_km.field_103230_P
		// @04D: bipush 77 (0x4D)
		// @04F: invokeinterface game.C_100308_lh.func_102950_a(byte)game.C_100133_tk
		// @054: astore #8
		// @056: aload #8
		// @058: getstatic game.C_100133_tk game.C_100297_kf.field_101234_s
		// @05B: if_acmpeq @06A
		// @05E: getstatic game.C_100133_tk game.C_100238_ol.field_101696_R
		// @061: aload #8
		// @063: if_acmpne @126
		// @066: goto @06A
		// @069: athrow
		// @06A: getstatic game.C_100037_wb[] game.C_100163_sf.field_105435_g
		// @06D: iconst_0
		// @06E: aaload
		// @06F: astore #7
		// @071: aload #7
		// @073: getfield int game.C_100037_wb.field_102341_y
		// @076: ldc -309118815 (0xed9338a1)
		// @078: ishl
		// @079: istore #9
		// @07B: aload #7
		// @07D: getfield int game.C_100037_wb.field_102340_z
		// @080: ldc 1753335649 (0x6881c761)
		// @082: ishl
		// @083: istore #10
		// @085: aconst_null
		// @086: getstatic game.C_100037_wb game.C_100170_cm.field_105549_h
		// @089: if_acmpeq @0AE
		// @08C: iload #9
		// @08E: iconst_m1
		// @08F: ixor
		// @090: getstatic game.C_100037_wb game.C_100170_cm.field_105549_h
		// @093: getfield int game.C_100037_wb.field_102339_s
		// @096: iconst_m1
		// @097: ixor
		// @098: if_icmplt @0AE
		// @09B: goto @09F
		// @09E: athrow
		// @09F: iload #10
		// @0A1: getstatic game.C_100037_wb game.C_100170_cm.field_105549_h
		// @0A4: getfield int game.C_100037_wb.field_102337_u
		// @0A7: if_icmple @0CD
		// @0AA: goto @0AE
		// @0AD: athrow
		// @0AE: new game.C_100037_wb
		// @0B1: dup
		// @0B2: iload #9
		// @0B4: iload #10
		// @0B6: invokespecial game.C_100037_wb.<init>(int, int)void
		// @0B9: putstatic game.C_100037_wb game.C_100170_cm.field_105549_h
		// @0BC: getstatic game.C_100037_wb game.C_100170_cm.field_105549_h
		// @0BF: bipush -4 (0xFC)
		// @0C1: invokestatic game.C_100138_bo.func_100398_a(game.C_100037_wb, int)void
		// @0C4: iload #11
		// @0C6: ifeq @0DC
		// @0C9: goto @0CD
		// @0CC: athrow
		// @0CD: getstatic game.C_100037_wb game.C_100170_cm.field_105549_h
		// @0D0: bipush -4 (0xFC)
		// @0D2: invokestatic game.C_100138_bo.func_100398_a(game.C_100037_wb, int)void
		// @0D5: invokestatic game.C_100196_rb.func_105792_b()void
		// @0D8: goto @0DC
		// @0DB: athrow
		// @0DC: aload #7
		// @0DE: bipush 112 (0x70)
		// @0E0: sipush 144 (0x0090)
		// @0E3: aload #7
		// @0E5: getfield int game.C_100037_wb.field_102341_y
		// @0E8: ldc -933864220 (0xc8565ce4)
		// @0EA: ishl
		// @0EB: aload #7
		// @0ED: getfield int game.C_100037_wb.field_102340_z
		// @0F0: ldc -1628579708 (0x9eedd884)
		// @0F2: ishl
		// @0F3: aload_0
		// @0F4: getfield int game.C_100305_km.field_103233_O
		// @0F7: ineg
		// @0F8: ldc -68688086 (0xfbe7e72a)
		// @0FA: ishl
		// @0FB: sipush 4096 (0x1000)
		// @0FE: invokevirtual game.C_100037_wb.func_102357_a(int, int, int, int, int, int)void
		// @101: bipush -77 (0xB3)
		// @103: invokestatic game.C_100200_ba.func_105842_a(byte)void
		// @106: getstatic game.C_100037_wb game.C_100170_cm.field_105549_h
		// @109: iload #5
		// @10B: aload #7
		// @10D: getfield int game.C_100037_wb.field_102341_y
		// @110: ineg
		// @111: iadd
		// @112: aload #7
		// @114: getfield int game.C_100037_wb.field_102340_z
		// @117: ineg
		// @118: iload #6
		// @11A: iadd
		// @11B: sipush 256 (0x0100)
		// @11E: invokevirtual game.C_100037_wb.func_102367_c(int, int, int)void
		// @121: iload #11
		// @123: ifeq @190
		// @126: getstatic game.C_100133_tk game.C_100256_pk.field_100466_a
		// @129: aload #8
		// @12B: if_acmpeq @169
		// @12E: goto @132
		// @131: athrow
		// @132: getstatic game.C_100133_tk game.C_100079_e.field_102670_tb
		// @135: aload #8
		// @137: if_acmpne @190
		// @13A: goto @13E
		// @13D: athrow
		// @13E: getstatic game.C_100037_wb[] game.C_100163_sf.field_105435_g
		// @141: iconst_1
		// @142: aaload
		// @143: astore #7
		// @145: aload #7
		// @147: iload #5
		// @149: aload #7
		// @14B: getfield int game.C_100037_wb.field_102339_s
		// @14E: ldc 932689729 (0x3797b741)
		// @150: ishr
		// @151: isub
		// @152: aload #7
		// @154: getfield int game.C_100037_wb.field_102337_u
		// @157: ldc -1044112639 (0xc1c41b01)
		// @159: ishr
		// @15A: ineg
		// @15B: iload #6
		// @15D: iadd
		// @15E: sipush 256 (0x0100)
		// @161: invokevirtual game.C_100037_wb.func_102367_c(int, int, int)void
		// @164: iload #11
		// @166: ifeq @190
		// @169: getstatic game.C_100037_wb[] game.C_100163_sf.field_105435_g
		// @16C: iconst_2
		// @16D: aaload
		// @16E: astore #7
		// @170: aload #7
		// @172: iload #5
		// @174: aload #7
		// @176: getfield int game.C_100037_wb.field_102339_s
		// @179: ldc 322407649 (0x13378ce1)
		// @17B: ishr
		// @17C: ineg
		// @17D: iadd
		// @17E: iload #6
		// @180: aload #7
		// @182: getfield int game.C_100037_wb.field_102337_u
		// @185: ldc 1895700833 (0x70fe1961)
		// @187: ishr
		// @188: ineg
		// @189: iadd
		// @18A: sipush 256 (0x0100)
		// @18D: invokevirtual game.C_100037_wb.func_102367_c(int, int, int)void
		// @190: goto @1D3
		// @193: astore #5
		// @195: aload #5
		// @197: new java.lang.StringBuilder
		// @19A: dup
		// @19B: invokespecial java.lang.StringBuilder.<init>()void
		// @19E: getstatic java.lang.String[] game.C_100305_km.field_103231_S
		// @1A1: bipush 9 (0x09)
		// @1A3: aaload
		// @1A4: invokevirtual java.lang.StringBuilder.append(java.lang.String)java.lang.StringBuilder
		// @1A7: iload_1
		// @1A8: invokevirtual java.lang.StringBuilder.append(int)java.lang.StringBuilder
		// @1AB: bipush 44 (0x2C)
		// @1AD: invokevirtual java.lang.StringBuilder.append(char)java.lang.StringBuilder
		// @1B0: iload_2
		// @1B1: invokevirtual java.lang.StringBuilder.append(int)java.lang.StringBuilder
		// @1B4: bipush 44 (0x2C)
		// @1B6: invokevirtual java.lang.StringBuilder.append(char)java.lang.StringBuilder
		// @1B9: iload_3
		// @1BA: invokevirtual java.lang.StringBuilder.append(int)java.lang.StringBuilder
		// @1BD: bipush 44 (0x2C)
		// @1BF: invokevirtual java.lang.StringBuilder.append(char)java.lang.StringBuilder
		// @1C2: iload #4
		// @1C4: invokevirtual java.lang.StringBuilder.append(int)java.lang.StringBuilder
		// @1C7: bipush 41 (0x29)
		// @1C9: invokevirtual java.lang.StringBuilder.append(char)java.lang.StringBuilder
		// @1CC: invokevirtual java.lang.StringBuilder.toString()java.lang.String
		// @1CF: invokestatic game.C_100181_cf.func_105695_a(java.lang.Throwable, java.lang.String)game.C_100170_cm
		// @1D2: athrow
		// @1D3: return
	}
	
	public static void func_103224_a(byte arg0)
	{
		// @00: aconst_null
		// @01: putstatic java.lang.String game.C_100305_km.field_103232_R
		// @04: iload_0
		// @05: bipush -118 (0x8A)
		// @07: if_icmplt @0F
		// @0A: bipush 84 (0x54)
		// @0C: putstatic int game.C_100305_km.field_103229_Q
		// @0F: goto @34
		// @12: astore_1
		// @13: aload_1
		// @14: new java.lang.StringBuilder
		// @17: dup
		// @18: invokespecial java.lang.StringBuilder.<init>()void
		// @1B: getstatic java.lang.String[] game.C_100305_km.field_103231_S
		// @1E: bipush 7 (0x07)
		// @20: aaload
		// @21: invokevirtual java.lang.StringBuilder.append(java.lang.String)java.lang.StringBuilder
		// @24: iload_0
		// @25: invokevirtual java.lang.StringBuilder.append(int)java.lang.StringBuilder
		// @28: bipush 41 (0x29)
		// @2A: invokevirtual java.lang.StringBuilder.append(char)java.lang.StringBuilder
		// @2D: invokevirtual java.lang.StringBuilder.toString()java.lang.String
		// @30: invokestatic game.C_100181_cf.func_105695_a(java.lang.Throwable, java.lang.String)game.C_100170_cm
		// @33: athrow
		// @34: return
	}
	
	static final void func_103227_a(boolean arg0, int arg1, int arg2, int arg3, boolean arg4, int arg5, int arg6)
	{
		// @0000: getstatic int game.SteelSentinels.field_105275_O
		// @0003: istore #41
		// @0005: getstatic game.C_100115_ej game.C_100156_sk.field_105389_r
		// @0008: iconst_m1
		// @0009: getstatic int game.C_100033_gj.field_101917_jc
		// @000C: iconst_2
		// @000D: iadd
		// @000E: iconst_2
		// @000F: imul
		// @0010: iconst_4
		// @0011: getstatic int game.C_100033_gj.field_101917_jc
		// @0014: bipush -2 (0xFE)
		// @0016: isub
		// @0017: iload #5
		// @0019: imul
		// @001A: imul
		// @001B: getstatic game.C_100115_ej game.C_100346_ja.field_103486_m
		// @001E: getstatic game.C_100115_ej game.C_100156_sk.field_105389_r
		// @0021: if_acmpne @0029
		// @0024: iconst_1
		// @0025: goto @002A
		// @0028: athrow
		// @0029: iconst_0
		// @002A: iconst_2
		// @002B: iload_0
		// @002C: invokevirtual game.C_100115_ej.func_102034_a(int, int, int, boolean, int, boolean)boolean
		// @002F: istore #7
		// @0031: getstatic game.C_100115_ej game.C_100156_sk.field_105389_r
		// @0034: getfield game.C_100302_ka game.C_100115_ej.field_102036_Wb
		// @0037: getfield game.C_100202_qi game.C_100302_ka.field_101891_Ob
		// @003A: astore #8
		// @003C: bipush 64 (0x40)
		// @003E: invokestatic game.C_100198_qn.func_105828_a(byte)long
		// @0041: lstore #9
		// @0043: aconst_null
		// @0044: astore #11
		// @0046: iload_3
		// @0047: ifeq @0060
		// @004A: bipush 86 (0x56)
		// @004C: aconst_null
		// @004D: checkcast game.C_100098_h
		// @0050: aconst_null
		// @0051: checkcast game.C_100098_h
		// @0054: aconst_null
		// @0055: checkcast game.C_100098_h
		// @0058: invokestatic game.C_100305_km.func_103221_a(byte, game.C_100098_h, game.C_100098_h, game.C_100098_h)boolean
		// @005B: pop
		// @005C: goto @0060
		// @005F: athrow
		// @0060: aload #8
		// @0062: bipush 73 (0x49)
		// @0064: invokevirtual game.C_100202_qi.func_105899_c(int)game.C_100158_da
		// @0067: checkcast game.C_100211_qd
		// @006A: astore #12
		// @006C: aload #12
		// @006E: ifnull @0FCD
		// @0071: iconst_0
		// @0072: istore #13
		// @0074: iload #41
		// @0076: ifne @102C
		// @0079: aconst_null
		// @007A: aload #12
		// @007C: getfield game.C_100202_qi game.C_100211_qd.field_101891_Ob
		// @007F: if_acmpne @0384
		// @0082: goto @0086
		// @0085: athrow
		// @0086: aload #12
		// @0088: new game.C_100302_ka
		// @008B: dup
		// @008C: lconst_0
		// @008D: getstatic game.C_100302_ka game.C_100299_kd.field_107022_C
		// @0090: invokespecial game.C_100302_ka.<init>(long, game.C_100302_ka)void
		// @0093: putfield game.C_100302_ka game.C_100211_qd.field_102172_uc
		// @0096: iload_2
		// @0097: iload #6
		// @0099: goto @009D
		// @009C: athrow
		// @009D: ior
		// @009E: istore #14
		// @00A0: aload #12
		// @00A2: bipush -103 (0x99)
		// @00A4: aload #12
		// @00A6: getfield game.C_100302_ka game.C_100211_qd.field_102172_uc
		// @00A9: invokevirtual game.C_100211_qd.func_101824_b(int, game.C_100302_ka)void
		// @00AC: aload #12
		// @00AE: getfield game.C_100302_ka game.C_100211_qd.field_102172_uc
		// @00B1: iconst_1
		// @00B2: putfield int game.C_100302_ka.field_101850_Fb
		// @00B5: aload #12
		// @00B7: new game.C_100302_ka
		// @00BA: dup
		// @00BB: lconst_0
		// @00BC: getstatic game.C_100302_ka game.C_100160_sm.field_105414_e
		// @00BF: invokespecial game.C_100302_ka.<init>(long, game.C_100302_ka)void
		// @00C2: putfield game.C_100302_ka game.C_100211_qd.field_102136_gc
		// @00C5: aload #12
		// @00C7: bipush -86 (0xAA)
		// @00C9: aload #12
		// @00CB: getfield game.C_100302_ka game.C_100211_qd.field_102136_gc
		// @00CE: invokevirtual game.C_100211_qd.func_101824_b(int, game.C_100302_ka)void
		// @00D1: aload #12
		// @00D3: new game.C_100302_ka
		// @00D6: dup
		// @00D7: lconst_0
		// @00D8: getstatic game.C_100302_ka game.C_100299_kd.field_107022_C
		// @00DB: invokespecial game.C_100302_ka.<init>(long, game.C_100302_ka)void
		// @00DE: putfield game.C_100302_ka game.C_100211_qd.field_102146_Ac
		// @00E1: aload #12
		// @00E3: iload_3
		// @00E4: bipush -83 (0xAD)
		// @00E6: ixor
		// @00E7: aload #12
		// @00E9: getfield game.C_100302_ka game.C_100211_qd.field_102146_Ac
		// @00EC: invokevirtual game.C_100211_qd.func_101824_b(int, game.C_100302_ka)void
		// @00EF: aload #12
		// @00F1: getfield game.C_100302_ka game.C_100211_qd.field_102146_Ac
		// @00F4: iconst_0
		// @00F5: putfield int game.C_100302_ka.field_101829_Db
		// @00F8: aload #12
		// @00FA: new game.C_100302_ka
		// @00FD: dup
		// @00FE: lconst_0
		// @00FF: getstatic game.C_100302_ka game.C_100299_kd.field_107022_C
		// @0102: invokespecial game.C_100302_ka.<init>(long, game.C_100302_ka)void
		// @0105: putfield game.C_100302_ka game.C_100211_qd.field_102166_Vb
		// @0108: aload #12
		// @010A: bipush -124 (0x84)
		// @010C: aload #12
		// @010E: getfield game.C_100302_ka game.C_100211_qd.field_102166_Vb
		// @0111: invokevirtual game.C_100211_qd.func_101824_b(int, game.C_100302_ka)void
		// @0114: aload #12
		// @0116: getfield game.C_100302_ka game.C_100211_qd.field_102166_Vb
		// @0119: iconst_0
		// @011A: putfield int game.C_100302_ka.field_101829_Db
		// @011D: aload #12
		// @011F: new game.C_100302_ka
		// @0122: dup
		// @0123: lconst_0
		// @0124: getstatic game.C_100302_ka game.C_100160_sm.field_105414_e
		// @0127: invokespecial game.C_100302_ka.<init>(long, game.C_100302_ka)void
		// @012A: putfield game.C_100302_ka game.C_100211_qd.field_102143_oc
		// @012D: aload #12
		// @012F: bipush -118 (0x8A)
		// @0131: aload #12
		// @0133: getfield game.C_100302_ka game.C_100211_qd.field_102143_oc
		// @0136: invokevirtual game.C_100211_qd.func_101824_b(int, game.C_100302_ka)void
		// @0139: aload #12
		// @013B: getfield game.C_100302_ka game.C_100211_qd.field_102143_oc
		// @013E: iconst_2
		// @013F: putfield int game.C_100302_ka.field_101850_Fb
		// @0142: aload #12
		// @0144: new game.C_100302_ka
		// @0147: dup
		// @0148: lconst_0
		// @0149: getstatic boolean game.C_100273_mm.field_106682_e
		// @014C: ifeq @0155
		// @014F: getstatic game.C_100302_ka game.C_100299_kd.field_107022_C
		// @0152: goto @0158
		// @0155: getstatic game.C_100302_ka game.C_100160_sm.field_105414_e
		// @0158: invokespecial game.C_100302_ka.<init>(long, game.C_100302_ka)void
		// @015B: putfield game.C_100302_ka game.C_100211_qd.field_102177_cc
		// @015E: aload #12
		// @0160: iload_3
		// @0161: bipush -91 (0xA5)
		// @0163: ixor
		// @0164: aload #12
		// @0166: getfield game.C_100302_ka game.C_100211_qd.field_102177_cc
		// @0169: invokevirtual game.C_100211_qd.func_101824_b(int, game.C_100302_ka)void
		// @016C: aload #12
		// @016E: getstatic int game.C_100137_bn.field_105038_l
		// @0171: anewarray game.C_100302_ka
		// @0174: putfield game.C_100302_ka[] game.C_100211_qd.field_102162_hc
		// @0177: aload #12
		// @0179: new game.C_100302_ka
		// @017C: dup
		// @017D: lconst_0
		// @017E: aconst_null
		// @017F: invokespecial game.C_100302_ka.<init>(long, game.C_100302_ka)void
		// @0182: putfield game.C_100302_ka game.C_100211_qd.field_102174_wc
		// @0185: iconst_1
		// @0186: getstatic int game.C_100167_sj.field_100793_u
		// @0189: ishl
		// @018A: iload #14
		// @018C: iand
		// @018D: iconst_m1
		// @018E: ixor
		// @018F: iconst_m1
		// @0190: if_icmpeq @01A2
		// @0193: aload #12
		// @0195: getfield game.C_100302_ka game.C_100211_qd.field_102177_cc
		// @0198: bipush -119 (0x89)
		// @019A: aload #12
		// @019C: getfield game.C_100302_ka game.C_100211_qd.field_102174_wc
		// @019F: invokevirtual game.C_100302_ka.func_101824_b(int, game.C_100302_ka)void
		// @01A2: aload #12
		// @01A4: new game.C_100302_ka
		// @01A7: dup
		// @01A8: lconst_0
		// @01A9: aconst_null
		// @01AA: invokespecial game.C_100302_ka.<init>(long, game.C_100302_ka)void
		// @01AD: putfield game.C_100302_ka game.C_100211_qd.field_102145_tc
		// @01B0: iconst_m1
		// @01B1: iload #14
		// @01B3: iconst_1
		// @01B4: getstatic int game.C_100313_lg.field_107163_f
		// @01B7: ishl
		// @01B8: iand
		// @01B9: iconst_m1
		// @01BA: ixor
		// @01BB: if_icmpne @01C2
		// @01BE: goto @01D1
		// @01C1: athrow
		// @01C2: aload #12
		// @01C4: getfield game.C_100302_ka game.C_100211_qd.field_102177_cc
		// @01C7: bipush -95 (0xA1)
		// @01C9: aload #12
		// @01CB: getfield game.C_100302_ka game.C_100211_qd.field_102145_tc
		// @01CE: invokevirtual game.C_100302_ka.func_101824_b(int, game.C_100302_ka)void
		// @01D1: aload #12
		// @01D3: new game.C_100302_ka
		// @01D6: dup
		// @01D7: lconst_0
		// @01D8: aconst_null
		// @01D9: invokespecial game.C_100302_ka.<init>(long, game.C_100302_ka)void
		// @01DC: putfield game.C_100302_ka game.C_100211_qd.field_102141_ic
		// @01DF: iconst_0
		// @01E0: iconst_1
		// @01E1: getstatic int game.C_100172_ck.field_102116_fc
		// @01E4: ishl
		// @01E5: iload #14
		// @01E7: iand
		// @01E8: if_icmpne @01EF
		// @01EB: goto @01FE
		// @01EE: athrow
		// @01EF: aload #12
		// @01F1: getfield game.C_100302_ka game.C_100211_qd.field_102177_cc
		// @01F4: bipush -113 (0x8F)
		// @01F6: aload #12
		// @01F8: getfield game.C_100302_ka game.C_100211_qd.field_102141_ic
		// @01FB: invokevirtual game.C_100302_ka.func_101824_b(int, game.C_100302_ka)void
		// @01FE: aload #12
		// @0200: new game.C_100302_ka
		// @0203: dup
		// @0204: lconst_0
		// @0205: aconst_null
		// @0206: invokespecial game.C_100302_ka.<init>(long, game.C_100302_ka)void
		// @0209: putfield game.C_100302_ka game.C_100211_qd.field_102168_pc
		// @020C: iload #14
		// @020E: iconst_1
		// @020F: getstatic int game.C_100148_bh.field_101803_u
		// @0212: ishl
		// @0213: iand
		// @0214: ifeq @022A
		// @0217: aload #12
		// @0219: getfield game.C_100302_ka game.C_100211_qd.field_102177_cc
		// @021C: bipush -126 (0x82)
		// @021E: aload #12
		// @0220: getfield game.C_100302_ka game.C_100211_qd.field_102168_pc
		// @0223: invokevirtual game.C_100302_ka.func_101824_b(int, game.C_100302_ka)void
		// @0226: goto @022A
		// @0229: athrow
		// @022A: aload #12
		// @022C: getfield game.C_100302_ka game.C_100211_qd.field_102174_wc
		// @022F: astore #15
		// @0231: aload #12
		// @0233: getfield game.C_100302_ka game.C_100211_qd.field_102168_pc
		// @0236: astore #16
		// @0238: aload #12
		// @023A: getfield game.C_100302_ka game.C_100211_qd.field_102145_tc
		// @023D: astore #17
		// @023F: aload #12
		// @0241: getfield game.C_100302_ka game.C_100211_qd.field_102141_ic
		// @0244: iconst_1
		// @0245: putfield int game.C_100302_ka.field_101858_J
		// @0248: aload #17
		// @024A: iconst_1
		// @024B: putfield int game.C_100302_ka.field_101858_J
		// @024E: aload #16
		// @0250: iconst_1
		// @0251: putfield int game.C_100302_ka.field_101858_J
		// @0254: aload #15
		// @0256: iconst_1
		// @0257: putfield int game.C_100302_ka.field_101858_J
		// @025A: iconst_0
		// @025B: istore #18
		// @025D: iload #18
		// @025F: iconst_m1
		// @0260: ixor
		// @0261: getstatic int game.C_100137_bn.field_105038_l
		// @0264: iconst_m1
		// @0265: ixor
		// @0266: if_icmple @02B9
		// @0269: aload #12
		// @026B: getfield game.C_100302_ka[] game.C_100211_qd.field_102162_hc
		// @026E: iload #18
		// @0270: new game.C_100302_ka
		// @0273: dup
		// @0274: lconst_0
		// @0275: aconst_null
		// @0276: invokespecial game.C_100302_ka.<init>(long, game.C_100302_ka)void
		// @0279: aastore
		// @027A: iconst_1
		// @027B: iload #18
		// @027D: getstatic int game.C_100062_dk.field_104285_a
		// @0280: iadd
		// @0281: ishl
		// @0282: iload #14
		// @0284: iand
		// @0285: iconst_m1
		// @0286: ixor
		// @0287: iconst_m1
		// @0288: iload #41
		// @028A: ifne @009D
		// @028D: if_icmpne @0293
		// @0290: goto @02A5
		// @0293: aload #12
		// @0295: getfield game.C_100302_ka game.C_100211_qd.field_102177_cc
		// @0298: bipush -82 (0xAE)
		// @029A: aload #12
		// @029C: getfield game.C_100302_ka[] game.C_100211_qd.field_102162_hc
		// @029F: iload #18
		// @02A1: aaload
		// @02A2: invokevirtual game.C_100302_ka.func_101824_b(int, game.C_100302_ka)void
		// @02A5: aload #12
		// @02A7: getfield game.C_100302_ka[] game.C_100211_qd.field_102162_hc
		// @02AA: iload #18
		// @02AC: aaload
		// @02AD: iconst_1
		// @02AE: putfield int game.C_100302_ka.field_101858_J
		// @02B1: iinc #18 +1
		// @02B4: iload #41
		// @02B6: ifeq @025D
		// @02B9: aload #12
		// @02BB: new game.C_100302_ka
		// @02BE: dup
		// @02BF: lconst_0
		// @02C0: getstatic boolean game.C_100273_mm.field_106682_e
		// @02C3: ifne @02CD
		// @02C6: getstatic game.C_100302_ka game.C_100299_kd.field_107022_C
		// @02C9: goto @02D0
		// @02CC: athrow
		// @02CD: getstatic game.C_100302_ka game.C_100160_sm.field_105414_e
		// @02D0: invokespecial game.C_100302_ka.<init>(long, game.C_100302_ka)void
		// @02D3: putfield game.C_100302_ka game.C_100211_qd.field_102137_Yb
		// @02D6: aload #12
		// @02D8: bipush -71 (0xB9)
		// @02DA: aload #12
		// @02DC: getfield game.C_100302_ka game.C_100211_qd.field_102137_Yb
		// @02DF: invokevirtual game.C_100211_qd.func_101824_b(int, game.C_100302_ka)void
		// @02E2: aload #12
		// @02E4: getfield game.C_100302_ka game.C_100211_qd.field_102137_Yb
		// @02E7: iconst_2
		// @02E8: putfield int game.C_100302_ka.field_101850_Fb
		// @02EB: aload #12
		// @02ED: new game.C_100302_ka
		// @02F0: dup
		// @02F1: lconst_0
		// @02F2: getstatic game.C_100302_ka game.C_100160_sm.field_105414_e
		// @02F5: invokespecial game.C_100302_ka.<init>(long, game.C_100302_ka)void
		// @02F8: putfield game.C_100302_ka game.C_100211_qd.field_102152_bc
		// @02FB: aload #12
		// @02FD: bipush -123 (0x85)
		// @02FF: aload #12
		// @0301: getfield game.C_100302_ka game.C_100211_qd.field_102152_bc
		// @0304: invokevirtual game.C_100211_qd.func_101824_b(int, game.C_100302_ka)void
		// @0307: aload #12
		// @0309: new game.C_100302_ka
		// @030C: dup
		// @030D: lconst_0
		// @030E: getstatic game.C_100302_ka game.C_100236_on.field_100906_r
		// @0311: invokespecial game.C_100302_ka.<init>(long, game.C_100302_ka)void
		// @0314: putfield game.C_100302_ka game.C_100211_qd.field_102161_Xb
		// @0317: aload #12
		// @0319: iload_3
		// @031A: bipush -128 (0x80)
		// @031C: iadd
		// @031D: aload #12
		// @031F: getfield game.C_100302_ka game.C_100211_qd.field_102161_Xb
		// @0322: invokevirtual game.C_100211_qd.func_101824_b(int, game.C_100302_ka)void
		// @0325: aload #12
		// @0327: new game.C_100302_ka
		// @032A: dup
		// @032B: lconst_0
		// @032C: getstatic game.C_100302_ka game.C_100236_on.field_100906_r
		// @032F: invokespecial game.C_100302_ka.<init>(long, game.C_100302_ka)void
		// @0332: putfield game.C_100302_ka game.C_100211_qd.field_102144_mc
		// @0335: aload #12
		// @0337: iload_3
		// @0338: bipush -124 (0x84)
		// @033A: iadd
		// @033B: aload #12
		// @033D: getfield game.C_100302_ka game.C_100211_qd.field_102144_mc
		// @0340: invokevirtual game.C_100211_qd.func_101824_b(int, game.C_100302_ka)void
		// @0343: aload #12
		// @0345: new game.C_100302_ka
		// @0348: dup
		// @0349: lconst_0
		// @034A: getstatic game.C_100302_ka game.C_100129_tg.field_102750_sb
		// @034D: invokespecial game.C_100302_ka.<init>(long, game.C_100302_ka)void
		// @0350: putfield game.C_100302_ka game.C_100211_qd.field_102147_kc
		// @0353: aload #12
		// @0355: bipush -78 (0xB2)
		// @0357: aload #12
		// @0359: getfield game.C_100302_ka game.C_100211_qd.field_102147_kc
		// @035C: invokevirtual game.C_100211_qd.func_101824_b(int, game.C_100302_ka)void
		// @035F: aload #12
		// @0361: iconst_0
		// @0362: invokevirtual game.C_100211_qd.func_101821_k(int)void
		// @0365: aload #12
		// @0367: new game.C_100302_ka
		// @036A: dup
		// @036B: lconst_0
		// @036C: getstatic game.C_100302_ka game.C_100338_jc.field_105375_i
		// @036F: invokespecial game.C_100302_ka.<init>(long, game.C_100302_ka)void
		// @0372: putfield game.C_100302_ka game.C_100211_qd.field_102148_Hc
		// @0375: aload #12
		// @0377: bipush -90 (0xA6)
		// @0379: aload #12
		// @037B: getfield game.C_100302_ka game.C_100211_qd.field_102148_Hc
		// @037E: invokevirtual game.C_100211_qd.func_101824_b(int, game.C_100302_ka)void
		// @0381: iconst_1
		// @0382: istore #13
		// @0384: aload #12
		// @0386: getfield game.C_100302_ka game.C_100211_qd.field_102172_uc
		// @0389: aconst_null
		// @038A: putfield java.lang.String game.C_100302_ka.field_101890_ab
		// @038D: aload #12
		// @038F: getfield boolean game.C_100211_qd.field_102173_Ic
		// @0392: ifeq @039A
		// @0395: iload_2
		// @0396: goto @039C
		// @0399: athrow
		// @039A: iload #6
		// @039C: istore #14
		// @039E: aload #12
		// @03A0: getfield game.C_100302_ka game.C_100211_qd.field_102172_uc
		// @03A3: iconst_0
		// @03A4: putfield int game.C_100302_ka.field_101848_lb
		// @03A7: aload #12
		// @03A9: getfield game.C_100302_ka game.C_100211_qd.field_102172_uc
		// @03AC: astore #15
		// @03AE: aload #15
		// @03B0: iconst_0
		// @03B1: putfield int game.C_100302_ka.field_101886_Kb
		// @03B4: aload #12
		// @03B6: getfield game.C_100302_ka game.C_100211_qd.field_102148_Hc
		// @03B9: aconst_null
		// @03BA: putfield java.lang.String game.C_100302_ka.field_101890_ab
		// @03BD: aload #12
		// @03BF: getfield game.C_100302_ka game.C_100211_qd.field_102148_Hc
		// @03C2: astore #16
		// @03C4: aload #12
		// @03C6: getfield game.C_100302_ka game.C_100211_qd.field_102148_Hc
		// @03C9: iconst_0
		// @03CA: putfield int game.C_100302_ka.field_101848_lb
		// @03CD: aload #16
		// @03CF: iconst_0
		// @03D0: putfield int game.C_100302_ka.field_101886_Kb
		// @03D3: aload #12
		// @03D5: getfield game.C_100302_ka game.C_100211_qd.field_102136_gc
		// @03D8: aconst_null
		// @03D9: putfield java.lang.String game.C_100302_ka.field_101890_ab
		// @03DC: aload #12
		// @03DE: getfield game.C_100302_ka game.C_100211_qd.field_102136_gc
		// @03E1: astore #17
		// @03E3: aload #12
		// @03E5: getfield game.C_100302_ka game.C_100211_qd.field_102136_gc
		// @03E8: iconst_0
		// @03E9: putfield int game.C_100302_ka.field_101848_lb
		// @03EC: aload #17
		// @03EE: iconst_0
		// @03EF: putfield int game.C_100302_ka.field_101886_Kb
		// @03F2: aload #12
		// @03F4: getfield game.C_100302_ka game.C_100211_qd.field_102146_Ac
		// @03F7: aconst_null
		// @03F8: putfield java.lang.String game.C_100302_ka.field_101890_ab
		// @03FB: aload #12
		// @03FD: getfield game.C_100302_ka game.C_100211_qd.field_102146_Ac
		// @0400: astore #18
		// @0402: aload #12
		// @0404: getfield game.C_100302_ka game.C_100211_qd.field_102146_Ac
		// @0407: iconst_0
		// @0408: putfield int game.C_100302_ka.field_101848_lb
		// @040B: aload #18
		// @040D: iconst_0
		// @040E: putfield int game.C_100302_ka.field_101886_Kb
		// @0411: aload #12
		// @0413: getfield game.C_100302_ka game.C_100211_qd.field_102166_Vb
		// @0416: aconst_null
		// @0417: putfield java.lang.String game.C_100302_ka.field_101890_ab
		// @041A: aload #12
		// @041C: getfield game.C_100302_ka game.C_100211_qd.field_102166_Vb
		// @041F: astore #19
		// @0421: aload #12
		// @0423: getfield game.C_100302_ka game.C_100211_qd.field_102166_Vb
		// @0426: iconst_0
		// @0427: putfield int game.C_100302_ka.field_101848_lb
		// @042A: aload #12
		// @042C: getfield game.C_100302_ka game.C_100211_qd.field_102143_oc
		// @042F: aconst_null
		// @0430: putfield java.lang.String game.C_100302_ka.field_101890_ab
		// @0433: aload #19
		// @0435: iconst_0
		// @0436: putfield int game.C_100302_ka.field_101886_Kb
		// @0439: aload #12
		// @043B: getfield game.C_100302_ka game.C_100211_qd.field_102143_oc
		// @043E: astore #20
		// @0440: aload #12
		// @0442: getfield game.C_100302_ka game.C_100211_qd.field_102143_oc
		// @0445: iconst_0
		// @0446: putfield int game.C_100302_ka.field_101848_lb
		// @0449: aload #20
		// @044B: iconst_0
		// @044C: putfield int game.C_100302_ka.field_101886_Kb
		// @044F: aload #12
		// @0451: getfield game.C_100302_ka game.C_100211_qd.field_102177_cc
		// @0454: aconst_null
		// @0455: putfield java.lang.String game.C_100302_ka.field_101890_ab
		// @0458: aload #12
		// @045A: getfield game.C_100302_ka game.C_100211_qd.field_102177_cc
		// @045D: astore #21
		// @045F: aload #12
		// @0461: getfield game.C_100302_ka game.C_100211_qd.field_102177_cc
		// @0464: iconst_0
		// @0465: putfield int game.C_100302_ka.field_101848_lb
		// @0468: aload #21
		// @046A: iconst_0
		// @046B: putfield int game.C_100302_ka.field_101886_Kb
		// @046E: iconst_0
		// @046F: istore #22
		// @0471: getstatic int game.C_100137_bn.field_105038_l
		// @0474: iconst_m1
		// @0475: ixor
		// @0476: iload #22
		// @0478: iconst_m1
		// @0479: ixor
		// @047A: if_icmpge @04B6
		// @047D: aload #12
		// @047F: getfield game.C_100302_ka[] game.C_100211_qd.field_102162_hc
		// @0482: iload #22
		// @0484: aaload
		// @0485: aconst_null
		// @0486: putfield game.C_100037_wb game.C_100302_ka.field_101887_nb
		// @0489: aload #12
		// @048B: getfield game.C_100302_ka[] game.C_100211_qd.field_102162_hc
		// @048E: iload #22
		// @0490: aaload
		// @0491: astore #23
		// @0493: aload #12
		// @0495: getfield game.C_100302_ka[] game.C_100211_qd.field_102162_hc
		// @0498: iload #22
		// @049A: aaload
		// @049B: iconst_0
		// @049C: putfield int game.C_100302_ka.field_101848_lb
		// @049F: aload #23
		// @04A1: iconst_0
		// @04A2: putfield int game.C_100302_ka.field_101886_Kb
		// @04A5: iinc #22 +1
		// @04A8: iload #41
		// @04AA: ifne @04BF
		// @04AD: iload #41
		// @04AF: ifeq @0471
		// @04B2: goto @04B6
		// @04B5: athrow
		// @04B6: aload #12
		// @04B8: getfield game.C_100302_ka game.C_100211_qd.field_102174_wc
		// @04BB: aconst_null
		// @04BC: putfield game.C_100037_wb game.C_100302_ka.field_101887_nb
		// @04BF: aload #12
		// @04C1: getfield game.C_100302_ka game.C_100211_qd.field_102174_wc
		// @04C4: astore #22
		// @04C6: aload #12
		// @04C8: getfield game.C_100302_ka game.C_100211_qd.field_102174_wc
		// @04CB: iconst_0
		// @04CC: putfield int game.C_100302_ka.field_101848_lb
		// @04CF: aload #12
		// @04D1: getfield game.C_100302_ka game.C_100211_qd.field_102168_pc
		// @04D4: aconst_null
		// @04D5: putfield game.C_100037_wb game.C_100302_ka.field_101887_nb
		// @04D8: aload #22
		// @04DA: iconst_0
		// @04DB: putfield int game.C_100302_ka.field_101886_Kb
		// @04DE: aload #12
		// @04E0: getfield game.C_100302_ka game.C_100211_qd.field_102168_pc
		// @04E3: astore #23
		// @04E5: aload #12
		// @04E7: getfield game.C_100302_ka game.C_100211_qd.field_102168_pc
		// @04EA: iconst_0
		// @04EB: putfield int game.C_100302_ka.field_101848_lb
		// @04EE: aload #12
		// @04F0: getfield game.C_100302_ka game.C_100211_qd.field_102145_tc
		// @04F3: aconst_null
		// @04F4: putfield game.C_100037_wb game.C_100302_ka.field_101887_nb
		// @04F7: aload #23
		// @04F9: iconst_0
		// @04FA: putfield int game.C_100302_ka.field_101886_Kb
		// @04FD: aload #12
		// @04FF: getfield game.C_100302_ka game.C_100211_qd.field_102145_tc
		// @0502: astore #24
		// @0504: aload #12
		// @0506: getfield game.C_100302_ka game.C_100211_qd.field_102145_tc
		// @0509: iconst_0
		// @050A: putfield int game.C_100302_ka.field_101848_lb
		// @050D: aload #24
		// @050F: iconst_0
		// @0510: putfield int game.C_100302_ka.field_101886_Kb
		// @0513: aload #12
		// @0515: getfield game.C_100302_ka game.C_100211_qd.field_102141_ic
		// @0518: aconst_null
		// @0519: putfield game.C_100037_wb game.C_100302_ka.field_101887_nb
		// @051C: aload #12
		// @051E: getfield game.C_100302_ka game.C_100211_qd.field_102141_ic
		// @0521: iconst_0
		// @0522: putfield int game.C_100302_ka.field_101848_lb
		// @0525: aload #12
		// @0527: getfield game.C_100302_ka game.C_100211_qd.field_102141_ic
		// @052A: astore #25
		// @052C: aload #12
		// @052E: getfield game.C_100302_ka game.C_100211_qd.field_102137_Yb
		// @0531: aconst_null
		// @0532: putfield java.lang.String game.C_100302_ka.field_101890_ab
		// @0535: aload #25
		// @0537: iconst_0
		// @0538: putfield int game.C_100302_ka.field_101886_Kb
		// @053B: aload #12
		// @053D: getfield game.C_100302_ka game.C_100211_qd.field_102137_Yb
		// @0540: astore #26
		// @0542: aload #12
		// @0544: getfield game.C_100302_ka game.C_100211_qd.field_102137_Yb
		// @0547: iconst_0
		// @0548: putfield int game.C_100302_ka.field_101848_lb
		// @054B: aload #12
		// @054D: getfield game.C_100302_ka game.C_100211_qd.field_102152_bc
		// @0550: aconst_null
		// @0551: putfield java.lang.String game.C_100302_ka.field_101890_ab
		// @0554: aload #26
		// @0556: iconst_0
		// @0557: putfield int game.C_100302_ka.field_101886_Kb
		// @055A: aload #12
		// @055C: getfield game.C_100302_ka game.C_100211_qd.field_102152_bc
		// @055F: iconst_0
		// @0560: putfield int game.C_100302_ka.field_101848_lb
		// @0563: aload #12
		// @0565: getfield game.C_100302_ka game.C_100211_qd.field_102152_bc
		// @0568: astore #27
		// @056A: aload #27
		// @056C: iconst_0
		// @056D: putfield int game.C_100302_ka.field_101886_Kb
		// @0570: aload #12
		// @0572: getfield game.C_100302_ka game.C_100211_qd.field_102161_Xb
		// @0575: aconst_null
		// @0576: putfield java.lang.String game.C_100302_ka.field_101890_ab
		// @0579: aload #12
		// @057B: getfield game.C_100302_ka game.C_100211_qd.field_102161_Xb
		// @057E: astore #28
		// @0580: aload #12
		// @0582: getfield game.C_100302_ka game.C_100211_qd.field_102161_Xb
		// @0585: iconst_0
		// @0586: putfield int game.C_100302_ka.field_101848_lb
		// @0589: aload #28
		// @058B: iconst_0
		// @058C: putfield int game.C_100302_ka.field_101886_Kb
		// @058F: aload #12
		// @0591: getfield game.C_100302_ka game.C_100211_qd.field_102144_mc
		// @0594: aconst_null
		// @0595: putfield java.lang.String game.C_100302_ka.field_101890_ab
		// @0598: aload #12
		// @059A: getfield game.C_100302_ka game.C_100211_qd.field_102144_mc
		// @059D: iconst_0
		// @059E: putfield int game.C_100302_ka.field_101848_lb
		// @05A1: aload #12
		// @05A3: getfield game.C_100302_ka game.C_100211_qd.field_102144_mc
		// @05A6: astore #29
		// @05A8: aload #12
		// @05AA: getfield game.C_100302_ka game.C_100211_qd.field_102147_kc
		// @05AD: aconst_null
		// @05AE: putfield java.lang.String game.C_100302_ka.field_101890_ab
		// @05B1: aload #29
		// @05B3: iconst_0
		// @05B4: putfield int game.C_100302_ka.field_101886_Kb
		// @05B7: aload #12
		// @05B9: getfield game.C_100302_ka game.C_100211_qd.field_102147_kc
		// @05BC: iconst_0
		// @05BD: putfield int game.C_100302_ka.field_101848_lb
		// @05C0: aload #12
		// @05C2: getfield game.C_100302_ka game.C_100211_qd.field_102147_kc
		// @05C5: astore #30
		// @05C7: aload #30
		// @05C9: iconst_0
		// @05CA: putfield int game.C_100302_ka.field_101886_Kb
		// @05CD: aload #12
		// @05CF: getstatic game.C_100115_ej game.C_100156_sk.field_105389_r
		// @05D2: getfield game.C_100302_ka game.C_100115_ej.field_102036_Wb
		// @05D5: getfield int game.C_100302_ka.field_101886_Kb
		// @05D8: putfield int game.C_100211_qd.field_101886_Kb
		// @05DB: iconst_0
		// @05DC: istore #31
		// @05DE: aload #12
		// @05E0: getfield java.lang.String game.C_100211_qd.field_102155_dc
		// @05E3: astore #32
		// @05E5: aload #12
		// @05E7: bipush -108 (0x94)
		// @05E9: invokevirtual game.C_100211_qd.func_102125_g(byte)boolean
		// @05EC: ifne @0D09
		// @05EF: aload #12
		// @05F1: getfield boolean game.C_100211_qd.field_102173_Ic
		// @05F4: ifeq @068E
		// @05F7: goto @05FB
		// @05FA: athrow
		// @05FB: aload #12
		// @05FD: getfield int game.C_100211_qd.field_102157_Ec
		// @0600: iconst_m1
		// @0601: ixor
		// @0602: iconst_m1
		// @0603: if_icmpgt @061E
		// @0606: goto @060A
		// @0609: athrow
		// @060A: aload #12
		// @060C: getfield game.C_100302_ka game.C_100211_qd.field_102172_uc
		// @060F: getstatic java.lang.String game.C_100166_sg.field_105464_d
		// @0612: putfield java.lang.String game.C_100302_ka.field_101890_ab
		// @0615: iload #41
		// @0617: ifeq @06E9
		// @061A: goto @061E
		// @061D: athrow
		// @061E: aload #12
		// @0620: getfield boolean game.C_100211_qd.field_102135_Dc
		// @0623: ifeq @0642
		// @0626: goto @062A
		// @0629: athrow
		// @062A: aload #12
		// @062C: getfield boolean game.C_100211_qd.field_102167_nc
		// @062F: ifne @067A
		// @0632: goto @0636
		// @0635: athrow
		// @0636: aload #12
		// @0638: getfield boolean game.C_100211_qd.field_102153_Lc
		// @063B: ifne @067A
		// @063E: goto @0642
		// @0641: athrow
		// @0642: bipush -3 (0xFD)
		// @0644: aload #12
		// @0646: getfield int game.C_100211_qd.field_102133_Fc
		// @0649: iconst_m1
		// @064A: ixor
		// @064B: if_icmpne @0666
		// @064E: goto @0652
		// @0651: athrow
		// @0652: aload #12
		// @0654: getfield game.C_100302_ka game.C_100211_qd.field_102148_Hc
		// @0657: getstatic java.lang.String game.C_100298_ke.field_103213_V
		// @065A: putfield java.lang.String game.C_100302_ka.field_101890_ab
		// @065D: iload #41
		// @065F: ifeq @06E9
		// @0662: goto @0666
		// @0665: athrow
		// @0666: aload #12
		// @0668: getfield game.C_100302_ka game.C_100211_qd.field_102172_uc
		// @066B: getstatic java.lang.String game.C_100257_ln.field_106480_g
		// @066E: putfield java.lang.String game.C_100302_ka.field_101890_ab
		// @0671: iload #41
		// @0673: ifeq @06E9
		// @0676: goto @067A
		// @0679: athrow
		// @067A: aload #12
		// @067C: getfield game.C_100302_ka game.C_100211_qd.field_102148_Hc
		// @067F: getstatic java.lang.String game.C_100087_n.field_100701_r
		// @0682: putfield java.lang.String game.C_100302_ka.field_101890_ab
		// @0685: iload #41
		// @0687: ifeq @06E9
		// @068A: goto @068E
		// @068D: athrow
		// @068E: aload #12
		// @0690: getfield boolean game.C_100211_qd.field_102167_nc
		// @0693: ifne @06DA
		// @0696: goto @069A
		// @0699: athrow
		// @069A: aload #12
		// @069C: getfield boolean game.C_100211_qd.field_102153_Lc
		// @069F: ifne @06DA
		// @06A2: goto @06A6
		// @06A5: athrow
		// @06A6: aload #12
		// @06A8: getfield boolean game.C_100211_qd.field_102175_Kc
		// @06AB: ifeq @06C6
		// @06AE: goto @06B2
		// @06B1: athrow
		// @06B2: aload #12
		// @06B4: getfield game.C_100302_ka game.C_100211_qd.field_102172_uc
		// @06B7: getstatic java.lang.String game.C_100059_df.field_101612_v
		// @06BA: putfield java.lang.String game.C_100302_ka.field_101890_ab
		// @06BD: iload #41
		// @06BF: ifeq @06E9
		// @06C2: goto @06C6
		// @06C5: athrow
		// @06C6: aload #12
		// @06C8: getfield game.C_100302_ka game.C_100211_qd.field_102172_uc
		// @06CB: getstatic java.lang.String game.C_100163_sf.field_105438_b
		// @06CE: putfield java.lang.String game.C_100302_ka.field_101890_ab
		// @06D1: iload #41
		// @06D3: ifeq @06E9
		// @06D6: goto @06DA
		// @06D9: athrow
		// @06DA: aload #12
		// @06DC: getfield game.C_100302_ka game.C_100211_qd.field_102148_Hc
		// @06DF: getstatic java.lang.String game.C_100087_n.field_100701_r
		// @06E2: putfield java.lang.String game.C_100302_ka.field_101890_ab
		// @06E5: goto @06E9
		// @06E8: athrow
		// @06E9: aload #12
		// @06EB: getfield game.C_100302_ka game.C_100211_qd.field_102148_Hc
		// @06EE: getfield java.lang.String game.C_100302_ka.field_101890_ab
		// @06F1: ifnull @070E
		// @06F4: aload #12
		// @06F6: getfield game.C_100302_ka game.C_100211_qd.field_102148_Hc
		// @06F9: iconst_0
		// @06FA: getstatic int game.C_100033_gj.field_101917_jc
		// @06FD: iconst_m1
		// @06FE: iload #31
		// @0700: bipush 68 (0x44)
		// @0702: invokevirtual game.C_100302_ka.func_101825_a(int, int, int, int, int)void
		// @0705: iload #41
		// @0707: ifeq @0723
		// @070A: goto @070E
		// @070D: athrow
		// @070E: aload #12
		// @0710: getfield game.C_100302_ka game.C_100211_qd.field_102172_uc
		// @0713: iconst_0
		// @0714: getstatic int game.C_100033_gj.field_101917_jc
		// @0717: iconst_m1
		// @0718: iload #31
		// @071A: bipush 68 (0x44)
		// @071C: invokevirtual game.C_100302_ka.func_101825_a(int, int, int, int, int)void
		// @071F: goto @0723
		// @0722: athrow
		// @0723: aload #12
		// @0725: getfield game.C_100302_ka game.C_100211_qd.field_102136_gc
		// @0728: aload #12
		// @072A: getfield game.C_100302_ka game.C_100211_qd.field_102136_gc
		// @072D: getfield game.C_100112_r game.C_100302_ka.field_101845_sb
		// @0730: aload #32
		// @0732: bipush 78 (0x4E)
		// @0734: invokestatic game.C_100112_r.func_101748_a(game.C_100112_r, java.lang.String, int)java.lang.String
		// @0737: putfield java.lang.String game.C_100302_ka.field_101890_ab
		// @073A: aload #12
		// @073C: getfield game.C_100302_ka game.C_100211_qd.field_102136_gc
		// @073F: bipush 70 (0x46)
		// @0741: getstatic int game.C_100033_gj.field_101917_jc
		// @0744: iconst_m1
		// @0745: iload #31
		// @0747: bipush 78 (0x4E)
		// @0749: invokevirtual game.C_100302_ka.func_101825_a(int, int, int, int, int)void
		// @074C: aload #12
		// @074E: getfield game.C_100302_ka game.C_100211_qd.field_102136_gc
		// @0751: getfield boolean game.C_100302_ka.field_101839_db
		// @0754: ifeq @0774
		// @0757: aload #12
		// @0759: getfield game.C_100302_ka game.C_100211_qd.field_102136_gc
		// @075C: getfield java.lang.String game.C_100302_ka.field_101890_ab
		// @075F: aload #32
		// @0761: invokevirtual java.lang.String.equals(java.lang.Object)boolean
		// @0764: ifeq @076F
		// @0767: goto @076B
		// @076A: athrow
		// @076B: goto @0774
		// @076E: athrow
		// @076F: aload #32
		// @0771: putstatic java.lang.String game.C_100321_hi.field_107220_c
		// @0774: aload #12
		// @0776: getfield game.C_100302_ka game.C_100211_qd.field_102146_Ac
		// @0779: aload #12
		// @077B: getfield int game.C_100211_qd.field_102138_ec
		// @077E: invokestatic java.lang.Integer.toString(int)java.lang.String
		// @0781: putfield java.lang.String game.C_100302_ka.field_101890_ab
		// @0784: aload #12
		// @0786: getfield boolean game.C_100211_qd.field_102135_Dc
		// @0789: ifeq @0800
		// @078C: aload #12
		// @078E: getfield game.C_100302_ka game.C_100211_qd.field_102146_Ac
		// @0791: iconst_2
		// @0792: putfield int game.C_100302_ka.field_101850_Fb
		// @0795: aload #12
		// @0797: getfield game.C_100302_ka game.C_100211_qd.field_102166_Vb
		// @079A: new java.lang.StringBuilder
		// @079D: dup
		// @079E: invokespecial java.lang.StringBuilder.<init>()void
		// @07A1: ldc "/"
		// @07A3: invokevirtual java.lang.StringBuilder.append(java.lang.String)java.lang.StringBuilder
		// @07A6: aload #12
		// @07A8: getfield int game.C_100211_qd.field_102160_Zb
		// @07AB: invokevirtual java.lang.StringBuilder.append(int)java.lang.StringBuilder
		// @07AE: invokevirtual java.lang.StringBuilder.toString()java.lang.String
		// @07B1: putfield java.lang.String game.C_100302_ka.field_101890_ab
		// @07B4: aload #12
		// @07B6: getfield game.C_100302_ka game.C_100211_qd.field_102166_Vb
		// @07B9: getfield game.C_100112_r game.C_100302_ka.field_101845_sb
		// @07BC: ldc "/"
		// @07BE: invokevirtual game.C_100112_r.func_101739_b(java.lang.String)int
		// @07C1: ineg
		// @07C2: sipush 348 (0x015C)
		// @07C5: iadd
		// @07C6: iconst_2
		// @07C7: idiv
		// @07C8: istore #33
		// @07CA: aload #12
		// @07CC: getfield game.C_100302_ka game.C_100211_qd.field_102146_Ac
		// @07CF: sipush 150 (0x0096)
		// @07D2: getstatic int game.C_100033_gj.field_101917_jc
		// @07D5: iload_3
		// @07D6: iconst_m1
		// @07D7: iadd
		// @07D8: iload #31
		// @07DA: sipush -150 (0xFF6A)
		// @07DD: iload #33
		// @07DF: iadd
		// @07E0: invokevirtual game.C_100302_ka.func_101825_a(int, int, int, int, int)void
		// @07E3: aload #12
		// @07E5: getfield game.C_100302_ka game.C_100211_qd.field_102166_Vb
		// @07E8: iload #33
		// @07EA: getstatic int game.C_100033_gj.field_101917_jc
		// @07ED: iload_3
		// @07EE: iconst_m1
		// @07EF: ixor
		// @07F0: iload #31
		// @07F2: sipush 198 (0x00C6)
		// @07F5: iload #33
		// @07F7: isub
		// @07F8: invokevirtual game.C_100302_ka.func_101825_a(int, int, int, int, int)void
		// @07FB: iload #41
		// @07FD: ifeq @0820
		// @0800: aload #12
		// @0802: getfield game.C_100302_ka game.C_100211_qd.field_102146_Ac
		// @0805: iconst_1
		// @0806: putfield int game.C_100302_ka.field_101850_Fb
		// @0809: aload #12
		// @080B: getfield game.C_100302_ka game.C_100211_qd.field_102146_Ac
		// @080E: sipush 150 (0x0096)
		// @0811: getstatic int game.C_100033_gj.field_101917_jc
		// @0814: iconst_m1
		// @0815: iload #31
		// @0817: bipush 48 (0x30)
		// @0819: invokevirtual game.C_100302_ka.func_101825_a(int, int, int, int, int)void
		// @081C: goto @0820
		// @081F: athrow
		// @0820: aload #12
		// @0822: getfield game.C_100302_ka game.C_100211_qd.field_102143_oc
		// @0825: aload #12
		// @0827: getfield int game.C_100211_qd.field_102151_vc
		// @082A: invokestatic java.lang.Integer.toString(int)java.lang.String
		// @082D: putfield java.lang.String game.C_100302_ka.field_101890_ab
		// @0830: aload #12
		// @0832: getfield game.C_100302_ka game.C_100211_qd.field_102143_oc
		// @0835: sipush 200 (0x00C8)
		// @0838: getstatic int game.C_100033_gj.field_101917_jc
		// @083B: iconst_m1
		// @083C: iload #31
		// @083E: bipush 48 (0x30)
		// @0840: invokevirtual game.C_100302_ka.func_101825_a(int, int, int, int, int)void
		// @0843: getstatic boolean game.C_100273_mm.field_106682_e
		// @0846: ifne @0850
		// @0849: sipush 200 (0x00C8)
		// @084C: goto @0853
		// @084F: athrow
		// @0850: sipush 250 (0x00FA)
		// @0853: istore #33
		// @0855: aload #12
		// @0857: getfield game.C_100302_ka game.C_100211_qd.field_102177_cc
		// @085A: iload #33
		// @085C: getstatic int game.C_100033_gj.field_101917_jc
		// @085F: iconst_m1
		// @0860: iload #31
		// @0862: bipush -2 (0xFE)
		// @0864: iload #33
		// @0866: ineg
		// @0867: sipush 365 (0x016D)
		// @086A: iadd
		// @086B: iadd
		// @086C: invokevirtual game.C_100302_ka.func_101825_a(int, int, int, int, int)void
		// @086F: getstatic int game.C_100284_nj.field_106771_c
		// @0872: istore #34
		// @0874: iconst_1
		// @0875: getstatic int game.C_100167_sj.field_100793_u
		// @0878: ishl
		// @0879: iload #14
		// @087B: iand
		// @087C: ifeq @08BB
		// @087F: getstatic game.C_100037_wb[] game.C_100046_vk.field_102762_tb
		// @0882: aload #12
		// @0884: getfield int game.C_100211_qd.field_102159_sc
		// @0887: aaload
		// @0888: astore #35
		// @088A: aload #12
		// @088C: getfield game.C_100302_ka game.C_100211_qd.field_102174_wc
		// @088F: aload #35
		// @0891: putfield game.C_100037_wb game.C_100302_ka.field_101887_nb
		// @0894: aload #12
		// @0896: getfield game.C_100302_ka game.C_100211_qd.field_102174_wc
		// @0899: iload #34
		// @089B: aload #12
		// @089D: getfield game.C_100302_ka game.C_100211_qd.field_102177_cc
		// @08A0: getfield int game.C_100302_ka.field_101848_lb
		// @08A3: iconst_m1
		// @08A4: iconst_0
		// @08A5: aload #35
		// @08A7: getfield int game.C_100037_wb.field_102341_y
		// @08AA: invokevirtual game.C_100302_ka.func_101825_a(int, int, int, int, int)void
		// @08AD: iload #34
		// @08AF: getstatic int game.C_100284_nj.field_106771_c
		// @08B2: aload #35
		// @08B4: getfield int game.C_100037_wb.field_102341_y
		// @08B7: iadd
		// @08B8: iadd
		// @08B9: istore #34
		// @08BB: iconst_1
		// @08BC: getstatic int game.C_100313_lg.field_107163_f
		// @08BF: ishl
		// @08C0: iload #14
		// @08C2: iand
		// @08C3: iconst_m1
		// @08C4: ixor
		// @08C5: iconst_m1
		// @08C6: if_icmpeq @092B
		// @08C9: aload #12
		// @08CB: getfield boolean game.C_100211_qd.field_102167_nc
		// @08CE: ifne @08E1
		// @08D1: goto @08D5
		// @08D4: athrow
		// @08D5: aload #12
		// @08D7: getfield boolean game.C_100211_qd.field_102153_Lc
		// @08DA: ifeq @08E6
		// @08DD: goto @08E1
		// @08E0: athrow
		// @08E1: iconst_1
		// @08E2: goto @08E7
		// @08E5: athrow
		// @08E6: iconst_0
		// @08E7: istore #36
		// @08E9: getstatic game.C_100037_wb[] game.C_100074_g.field_104411_b
		// @08EC: iload #36
		// @08EE: ifeq @08F6
		// @08F1: iconst_1
		// @08F2: goto @08F7
		// @08F5: athrow
		// @08F6: iconst_0
		// @08F7: aaload
		// @08F8: astore #35
		// @08FA: aload #12
		// @08FC: getfield game.C_100302_ka game.C_100211_qd.field_102145_tc
		// @08FF: aload #35
		// @0901: putfield game.C_100037_wb game.C_100302_ka.field_101887_nb
		// @0904: aload #12
		// @0906: getfield game.C_100302_ka game.C_100211_qd.field_102145_tc
		// @0909: iload #34
		// @090B: aload #12
		// @090D: getfield game.C_100302_ka game.C_100211_qd.field_102177_cc
		// @0910: getfield int game.C_100302_ka.field_101848_lb
		// @0913: iconst_m1
		// @0914: iconst_0
		// @0915: aload #35
		// @0917: getfield int game.C_100037_wb.field_102341_y
		// @091A: invokevirtual game.C_100302_ka.func_101825_a(int, int, int, int, int)void
		// @091D: iload #34
		// @091F: getstatic int game.C_100284_nj.field_106771_c
		// @0922: aload #35
		// @0924: getfield int game.C_100037_wb.field_102341_y
		// @0927: iadd
		// @0928: iadd
		// @0929: istore #34
		// @092B: iload #14
		// @092D: iconst_1
		// @092E: getstatic int game.C_100172_ck.field_102116_fc
		// @0931: ishl
		// @0932: iand
		// @0933: ifeq @0974
		// @0936: getstatic game.C_100037_wb[] game.C_100332_ii.field_107311_b
		// @0939: iconst_m1
		// @093A: aload #12
		// @093C: getfield int game.C_100211_qd.field_102133_Fc
		// @093F: iadd
		// @0940: aaload
		// @0941: astore #35
		// @0943: aload #12
		// @0945: getfield game.C_100302_ka game.C_100211_qd.field_102141_ic
		// @0948: aload #35
		// @094A: putfield game.C_100037_wb game.C_100302_ka.field_101887_nb
		// @094D: aload #12
		// @094F: getfield game.C_100302_ka game.C_100211_qd.field_102141_ic
		// @0952: iload #34
		// @0954: aload #12
		// @0956: getfield game.C_100302_ka game.C_100211_qd.field_102177_cc
		// @0959: getfield int game.C_100302_ka.field_101848_lb
		// @095C: iconst_m1
		// @095D: iconst_0
		// @095E: aload #35
		// @0960: getfield int game.C_100037_wb.field_102341_y
		// @0963: invokevirtual game.C_100302_ka.func_101825_a(int, int, int, int, int)void
		// @0966: iload #34
		// @0968: getstatic int game.C_100284_nj.field_106771_c
		// @096B: aload #35
		// @096D: getfield int game.C_100037_wb.field_102341_y
		// @0970: iadd
		// @0971: iadd
		// @0972: istore #34
		// @0974: iconst_0
		// @0975: iload #14
		// @0977: iconst_1
		// @0978: getstatic int game.C_100148_bh.field_101803_u
		// @097B: ishl
		// @097C: iand
		// @097D: if_icmpeq @09C9
		// @0980: getstatic game.C_100037_wb[] game.C_100208_qg.field_105965_i
		// @0983: goto @0987
		// @0986: athrow
		// @0987: aload #12
		// @0989: getfield boolean game.C_100211_qd.field_102134_zc
		// @098C: ifeq @0994
		// @098F: iconst_1
		// @0990: goto @0995
		// @0993: athrow
		// @0994: iconst_0
		// @0995: aaload
		// @0996: astore #35
		// @0998: aload #12
		// @099A: getfield game.C_100302_ka game.C_100211_qd.field_102168_pc
		// @099D: aload #35
		// @099F: putfield game.C_100037_wb game.C_100302_ka.field_101887_nb
		// @09A2: aload #12
		// @09A4: getfield game.C_100302_ka game.C_100211_qd.field_102168_pc
		// @09A7: iload #34
		// @09A9: aload #12
		// @09AB: getfield game.C_100302_ka game.C_100211_qd.field_102177_cc
		// @09AE: getfield int game.C_100302_ka.field_101848_lb
		// @09B1: iconst_m1
		// @09B2: iconst_0
		// @09B3: aload #35
		// @09B5: getfield int game.C_100037_wb.field_102341_y
		// @09B8: invokevirtual game.C_100302_ka.func_101825_a(int, int, int, int, int)void
		// @09BB: iload #34
		// @09BD: aload #35
		// @09BF: getfield int game.C_100037_wb.field_102341_y
		// @09C2: getstatic int game.C_100284_nj.field_106771_c
		// @09C5: iadd
		// @09C6: iadd
		// @09C7: istore #34
		// @09C9: getstatic game.C_100037_wb[][] game.C_100086_uh.field_103029_t
		// @09CC: ifnull @0A56
		// @09CF: iconst_0
		// @09D0: istore #36
		// @09D2: getstatic int game.C_100137_bn.field_105038_l
		// @09D5: iconst_m1
		// @09D6: ixor
		// @09D7: iload #36
		// @09D9: iconst_m1
		// @09DA: ixor
		// @09DB: if_icmpge @0A56
		// @09DE: getstatic game.C_100037_wb[][] game.C_100086_uh.field_103029_t
		// @09E1: iload #36
		// @09E3: aaload
		// @09E4: iload #41
		// @09E6: ifne @0987
		// @09E9: ifnull @0A4E
		// @09EC: iconst_m1
		// @09ED: iload #14
		// @09EF: iconst_1
		// @09F0: iload #36
		// @09F2: getstatic int game.C_100062_dk.field_104285_a
		// @09F5: iadd
		// @09F6: ishl
		// @09F7: iand
		// @09F8: iconst_m1
		// @09F9: ixor
		// @09FA: if_icmpeq @0A4E
		// @09FD: goto @0A01
		// @0A00: athrow
		// @0A01: getstatic game.C_100037_wb[][] game.C_100086_uh.field_103029_t
		// @0A04: iload #36
		// @0A06: aaload
		// @0A07: sipush 255 (0x00FF)
		// @0A0A: aload #12
		// @0A0C: getfield byte[] game.C_100211_qd.field_102165_jc
		// @0A0F: iload #36
		// @0A11: baload
		// @0A12: iand
		// @0A13: aaload
		// @0A14: astore #35
		// @0A16: aload #12
		// @0A18: getfield game.C_100302_ka[] game.C_100211_qd.field_102162_hc
		// @0A1B: iload #36
		// @0A1D: aaload
		// @0A1E: aload #35
		// @0A20: putfield game.C_100037_wb game.C_100302_ka.field_101887_nb
		// @0A23: aload #12
		// @0A25: getfield game.C_100302_ka[] game.C_100211_qd.field_102162_hc
		// @0A28: iload #36
		// @0A2A: aaload
		// @0A2B: iload #34
		// @0A2D: aload #12
		// @0A2F: getfield game.C_100302_ka game.C_100211_qd.field_102177_cc
		// @0A32: getfield int game.C_100302_ka.field_101848_lb
		// @0A35: iconst_m1
		// @0A36: iconst_0
		// @0A37: aload #35
		// @0A39: getfield int game.C_100037_wb.field_102341_y
		// @0A3C: invokevirtual game.C_100302_ka.func_101825_a(int, int, int, int, int)void
		// @0A3F: iload #34
		// @0A41: aload #35
		// @0A43: getfield int game.C_100037_wb.field_102341_y
		// @0A46: getstatic int game.C_100284_nj.field_106771_c
		// @0A49: ineg
		// @0A4A: isub
		// @0A4B: iadd
		// @0A4C: istore #34
		// @0A4E: iinc #36 +1
		// @0A51: iload #41
		// @0A53: ifeq @09D2
		// @0A56: iload #34
		// @0A58: ineg
		// @0A59: aload #12
		// @0A5B: getfield game.C_100302_ka game.C_100211_qd.field_102177_cc
		// @0A5E: getfield int game.C_100302_ka.field_101886_Kb
		// @0A61: iadd
		// @0A62: iconst_2
		// @0A63: idiv
		// @0A64: istore #36
		// @0A66: iload #36
		// @0A68: iconst_m1
		// @0A69: ixor
		// @0A6A: iconst_m1
		// @0A6B: if_icmpge @0AD8
		// @0A6E: aload #12
		// @0A70: getfield game.C_100302_ka game.C_100211_qd.field_102174_wc
		// @0A73: dup
		// @0A74: getfield int game.C_100302_ka.field_101841_Pb
		// @0A77: iload #36
		// @0A79: iadd
		// @0A7A: putfield int game.C_100302_ka.field_101841_Pb
		// @0A7D: aload #12
		// @0A7F: getfield game.C_100302_ka game.C_100211_qd.field_102145_tc
		// @0A82: dup
		// @0A83: getfield int game.C_100302_ka.field_101841_Pb
		// @0A86: iload #36
		// @0A88: iadd
		// @0A89: putfield int game.C_100302_ka.field_101841_Pb
		// @0A8C: aload #12
		// @0A8E: getfield game.C_100302_ka game.C_100211_qd.field_102141_ic
		// @0A91: dup
		// @0A92: getfield int game.C_100302_ka.field_101841_Pb
		// @0A95: iload #36
		// @0A97: iadd
		// @0A98: putfield int game.C_100302_ka.field_101841_Pb
		// @0A9B: aload #12
		// @0A9D: getfield game.C_100302_ka game.C_100211_qd.field_102168_pc
		// @0AA0: dup
		// @0AA1: getfield int game.C_100302_ka.field_101841_Pb
		// @0AA4: iload #36
		// @0AA6: iadd
		// @0AA7: putfield int game.C_100302_ka.field_101841_Pb
		// @0AAA: iconst_0
		// @0AAB: istore #37
		// @0AAD: iload #37
		// @0AAF: getstatic int game.C_100137_bn.field_105038_l
		// @0AB2: if_icmpge @0AD8
		// @0AB5: aload #12
		// @0AB7: getfield game.C_100302_ka[] game.C_100211_qd.field_102162_hc
		// @0ABA: iload #37
		// @0ABC: aaload
		// @0ABD: dup
		// @0ABE: getfield int game.C_100302_ka.field_101841_Pb
		// @0AC1: iload #36
		// @0AC3: iadd
		// @0AC4: putfield int game.C_100302_ka.field_101841_Pb
		// @0AC7: iinc #37 +1
		// @0ACA: iload #41
		// @0ACC: ifne @0BBF
		// @0ACF: iload #41
		// @0AD1: ifeq @0AAD
		// @0AD4: goto @0AD8
		// @0AD7: athrow
		// @0AD8: aload #12
		// @0ADA: getfield boolean game.C_100211_qd.field_102173_Ic
		// @0ADD: ifeq @0B9D
		// @0AE0: aload #12
		// @0AE2: getfield int game.C_100211_qd.field_102157_Ec
		// @0AE5: istore #37
		// @0AE7: iload #37
		// @0AE9: iflt @0AF0
		// @0AEC: goto @0AFC
		// @0AEF: athrow
		// @0AF0: lload #9
		// @0AF2: aload #12
		// @0AF4: getfield long game.C_100211_qd.field_102140_Wb
		// @0AF7: lneg
		// @0AF8: ladd
		// @0AF9: l2i
		// @0AFA: istore #37
		// @0AFC: iload #37
		// @0AFE: sipush 1000 (0x03E8)
		// @0B01: idiv
		// @0B02: istore #38
		// @0B04: iload #38
		// @0B06: bipush 60 (0x3C)
		// @0B08: idiv
		// @0B09: istore #39
		// @0B0B: iload #38
		// @0B0D: bipush 60 (0x3C)
		// @0B0F: irem
		// @0B10: istore #38
		// @0B12: bipush 60 (0x3C)
		// @0B14: iload #39
		// @0B16: if_icmple @0B4E
		// @0B19: aload #12
		// @0B1B: getfield game.C_100302_ka game.C_100211_qd.field_102137_Yb
		// @0B1E: new java.lang.StringBuilder
		// @0B21: dup
		// @0B22: invokespecial java.lang.StringBuilder.<init>()void
		// @0B25: iload #39
		// @0B27: invokevirtual java.lang.StringBuilder.append(int)java.lang.StringBuilder
		// @0B2A: ldc ":"
		// @0B2C: invokevirtual java.lang.StringBuilder.append(java.lang.String)java.lang.StringBuilder
		// @0B2F: iload #38
		// @0B31: bipush 10 (0x0A)
		// @0B33: idiv
		// @0B34: invokevirtual java.lang.StringBuilder.append(int)java.lang.StringBuilder
		// @0B37: iload #38
		// @0B39: bipush 10 (0x0A)
		// @0B3B: irem
		// @0B3C: invokevirtual java.lang.StringBuilder.append(int)java.lang.StringBuilder
		// @0B3F: invokevirtual java.lang.StringBuilder.toString()java.lang.String
		// @0B42: putfield java.lang.String game.C_100302_ka.field_101890_ab
		// @0B45: iload #41
		// @0B47: ifeq @0B9D
		// @0B4A: goto @0B4E
		// @0B4D: athrow
		// @0B4E: iload #39
		// @0B50: bipush 60 (0x3C)
		// @0B52: idiv
		// @0B53: istore #40
		// @0B55: iload #39
		// @0B57: bipush 60 (0x3C)
		// @0B59: irem
		// @0B5A: istore #39
		// @0B5C: aload #12
		// @0B5E: getfield game.C_100302_ka game.C_100211_qd.field_102137_Yb
		// @0B61: new java.lang.StringBuilder
		// @0B64: dup
		// @0B65: invokespecial java.lang.StringBuilder.<init>()void
		// @0B68: iload #40
		// @0B6A: invokevirtual java.lang.StringBuilder.append(int)java.lang.StringBuilder
		// @0B6D: ldc ":"
		// @0B6F: invokevirtual java.lang.StringBuilder.append(java.lang.String)java.lang.StringBuilder
		// @0B72: iload #39
		// @0B74: bipush 10 (0x0A)
		// @0B76: idiv
		// @0B77: invokevirtual java.lang.StringBuilder.append(int)java.lang.StringBuilder
		// @0B7A: iload #39
		// @0B7C: bipush 10 (0x0A)
		// @0B7E: irem
		// @0B7F: invokevirtual java.lang.StringBuilder.append(int)java.lang.StringBuilder
		// @0B82: ldc ":"
		// @0B84: invokevirtual java.lang.StringBuilder.append(java.lang.String)java.lang.StringBuilder
		// @0B87: iload #38
		// @0B89: bipush 10 (0x0A)
		// @0B8B: idiv
		// @0B8C: invokevirtual java.lang.StringBuilder.append(int)java.lang.StringBuilder
		// @0B8F: iload #38
		// @0B91: bipush 10 (0x0A)
		// @0B93: irem
		// @0B94: invokevirtual java.lang.StringBuilder.append(int)java.lang.StringBuilder
		// @0B97: invokevirtual java.lang.StringBuilder.toString()java.lang.String
		// @0B9A: putfield java.lang.String game.C_100302_ka.field_101890_ab
		// @0B9D: aload #12
		// @0B9F: getfield game.C_100302_ka game.C_100211_qd.field_102137_Yb
		// @0BA2: sipush 365 (0x016D)
		// @0BA5: getstatic int game.C_100033_gj.field_101917_jc
		// @0BA8: iconst_m1
		// @0BA9: iload #31
		// @0BAB: aload #12
		// @0BAD: getfield int game.C_100211_qd.field_101886_Kb
		// @0BB0: sipush -365 (0xFE93)
		// @0BB3: iadd
		// @0BB4: invokevirtual game.C_100302_ka.func_101825_a(int, int, int, int, int)void
		// @0BB7: iload #31
		// @0BB9: getstatic int game.C_100033_gj.field_101917_jc
		// @0BBC: iadd
		// @0BBD: istore #31
		// @0BBF: aload #12
		// @0BC1: getfield java.lang.String[] game.C_100211_qd.field_102171_lc
		// @0BC4: ifnonnull @0BCB
		// @0BC7: goto @0C79
		// @0BCA: athrow
		// @0BCB: iinc #31 +2
		// @0BCE: new java.lang.StringBuilder
		// @0BD1: dup
		// @0BD2: bipush 64 (0x40)
		// @0BD4: invokespecial java.lang.StringBuilder.<init>(int)void
		// @0BD7: astore #37
		// @0BD9: aload #37
		// @0BDB: getstatic java.lang.String game.C_100137_bn.field_105035_b
		// @0BDE: invokevirtual java.lang.StringBuilder.append(java.lang.String)java.lang.StringBuilder
		// @0BE1: pop
		// @0BE2: aload #37
		// @0BE4: aload #12
		// @0BE6: getfield java.lang.String[] game.C_100211_qd.field_102171_lc
		// @0BE9: iconst_0
		// @0BEA: aaload
		// @0BEB: invokevirtual java.lang.StringBuilder.append(java.lang.String)java.lang.StringBuilder
		// @0BEE: pop
		// @0BEF: iconst_1
		// @0BF0: istore #38
		// @0BF2: iload #38
		// @0BF4: aload #12
		// @0BF6: getfield int game.C_100211_qd.field_102138_ec
		// @0BF9: if_icmpge @0C26
		// @0BFC: aload #37
		// @0BFE: getstatic java.lang.String[] game.C_100305_km.field_103231_S
		// @0C01: iconst_0
		// @0C02: aaload
		// @0C03: invokevirtual java.lang.StringBuilder.append(java.lang.String)java.lang.StringBuilder
		// @0C06: pop
		// @0C07: aload #37
		// @0C09: aload #12
		// @0C0B: getfield java.lang.String[] game.C_100211_qd.field_102171_lc
		// @0C0E: iload #38
		// @0C10: aaload
		// @0C11: invokevirtual java.lang.StringBuilder.append(java.lang.String)java.lang.StringBuilder
		// @0C14: pop
		// @0C15: iinc #38 +1
		// @0C18: iload #41
		// @0C1A: ifne @0C79
		// @0C1D: iload #41
		// @0C1F: ifeq @0BF2
		// @0C22: goto @0C26
		// @0C25: athrow
		// @0C26: aload #37
		// @0C28: invokevirtual java.lang.StringBuilder.toString()java.lang.String
		// @0C2B: astore #38
		// @0C2D: aload #12
		// @0C2F: getfield game.C_100302_ka game.C_100211_qd.field_102152_bc
		// @0C32: aload #38
		// @0C34: putfield java.lang.String game.C_100302_ka.field_101890_ab
		// @0C37: aload #12
		// @0C39: getfield game.C_100302_ka game.C_100211_qd.field_102152_bc
		// @0C3C: getfield game.C_100112_r game.C_100302_ka.field_101845_sb
		// @0C3F: aload #38
		// @0C41: aload #12
		// @0C43: getfield int game.C_100211_qd.field_101886_Kb
		// @0C46: aload #12
		// @0C48: getfield game.C_100302_ka game.C_100211_qd.field_102152_bc
		// @0C4B: getfield int game.C_100302_ka.field_101829_Db
		// @0C4E: iconst_2
		// @0C4F: imul
		// @0C50: ineg
		// @0C51: iadd
		// @0C52: invokevirtual game.C_100112_r.func_101724_c(java.lang.String, int)int
		// @0C55: istore #39
		// @0C57: aload #12
		// @0C59: getfield game.C_100302_ka game.C_100211_qd.field_102152_bc
		// @0C5C: iconst_0
		// @0C5D: getstatic int game.C_100033_gj.field_101917_jc
		// @0C60: iload #39
		// @0C62: imul
		// @0C63: iconst_m1
		// @0C64: iload #31
		// @0C66: aload #12
		// @0C68: getfield int game.C_100211_qd.field_101886_Kb
		// @0C6B: invokevirtual game.C_100302_ka.func_101825_a(int, int, int, int, int)void
		// @0C6E: iload #31
		// @0C70: iload #39
		// @0C72: getstatic int game.C_100033_gj.field_101917_jc
		// @0C75: imul
		// @0C76: iadd
		// @0C77: istore #31
		// @0C79: aload #12
		// @0C7B: getfield boolean game.C_100211_qd.field_102153_Lc
		// @0C7E: ifeq @0CC2
		// @0C81: aload #12
		// @0C83: getfield game.C_100302_ka game.C_100211_qd.field_102161_Xb
		// @0C86: iload_3
		// @0C87: sipush -30945 (0x871F)
		// @0C8A: ixor
		// @0C8B: iconst_1
		// @0C8C: anewarray java.lang.String
		// @0C8F: dup
		// @0C90: iconst_0
		// @0C91: aload #32
		// @0C93: aastore
		// @0C94: getstatic java.lang.String game.C_100243_pd.field_106359_b
		// @0C97: invokestatic game.C_100132_td.func_104965_a(int, java.lang.String[], java.lang.String)java.lang.String
		// @0C9A: putfield java.lang.String game.C_100302_ka.field_101890_ab
		// @0C9D: aload #12
		// @0C9F: getfield game.C_100302_ka game.C_100211_qd.field_102161_Xb
		// @0CA2: getstatic int game.C_100244_pe.field_106375_d
		// @0CA5: getstatic int game.C_100033_gj.field_101917_jc
		// @0CA8: iconst_m1
		// @0CA9: iload #31
		// @0CAB: aload #12
		// @0CAD: getfield int game.C_100211_qd.field_101886_Kb
		// @0CB0: getstatic int game.C_100244_pe.field_106375_d
		// @0CB3: iconst_2
		// @0CB4: imul
		// @0CB5: ineg
		// @0CB6: iadd
		// @0CB7: invokevirtual game.C_100302_ka.func_101825_a(int, int, int, int, int)void
		// @0CBA: iload #31
		// @0CBC: getstatic int game.C_100033_gj.field_101917_jc
		// @0CBF: iadd
		// @0CC0: istore #31
		// @0CC2: aload #12
		// @0CC4: getfield boolean game.C_100211_qd.field_102150_Cc
		// @0CC7: ifeq @0D09
		// @0CCA: aload #12
		// @0CCC: getfield game.C_100302_ka game.C_100211_qd.field_102144_mc
		// @0CCF: sipush -30945 (0x871F)
		// @0CD2: iconst_1
		// @0CD3: anewarray java.lang.String
		// @0CD6: dup
		// @0CD7: iconst_0
		// @0CD8: aload #32
		// @0CDA: aastore
		// @0CDB: getstatic java.lang.String game.C_100141_tc.field_105070_h
		// @0CDE: invokestatic game.C_100132_td.func_104965_a(int, java.lang.String[], java.lang.String)java.lang.String
		// @0CE1: putfield java.lang.String game.C_100302_ka.field_101890_ab
		// @0CE4: aload #12
		// @0CE6: getfield game.C_100302_ka game.C_100211_qd.field_102144_mc
		// @0CE9: getstatic int game.C_100244_pe.field_106375_d
		// @0CEC: getstatic int game.C_100033_gj.field_101917_jc
		// @0CEF: iconst_m1
		// @0CF0: iload #31
		// @0CF2: iconst_2
		// @0CF3: getstatic int game.C_100244_pe.field_106375_d
		// @0CF6: imul
		// @0CF7: ineg
		// @0CF8: aload #12
		// @0CFA: getfield int game.C_100211_qd.field_101886_Kb
		// @0CFD: iadd
		// @0CFE: invokevirtual game.C_100302_ka.func_101825_a(int, int, int, int, int)void
		// @0D01: iload #31
		// @0D03: getstatic int game.C_100033_gj.field_101917_jc
		// @0D06: iadd
		// @0D07: istore #31
		// @0D09: sipush 27448 (0x6B38)
		// @0D0C: aload #32
		// @0D0E: aload #12
		// @0D10: getfield int game.C_100211_qd.field_102170_ac
		// @0D13: invokestatic game.C_100057_dd.func_104249_a(int, java.lang.String, int)java.lang.String
		// @0D16: astore #33
		// @0D18: aload #33
		// @0D1A: ifnonnull @0D21
		// @0D1D: goto @0D88
		// @0D20: athrow
		// @0D21: aload #12
		// @0D23: getfield game.C_100302_ka game.C_100211_qd.field_102147_kc
		// @0D26: getfield game.C_100112_r game.C_100302_ka.field_101845_sb
		// @0D29: aload #33
		// @0D2B: getstatic int game.C_100244_pe.field_106375_d
		// @0D2E: ineg
		// @0D2F: aload #12
		// @0D31: getfield int game.C_100211_qd.field_101886_Kb
		// @0D34: iadd
		// @0D35: getstatic int game.C_100244_pe.field_106375_d
		// @0D38: isub
		// @0D39: invokevirtual game.C_100112_r.func_101724_c(java.lang.String, int)int
		// @0D3C: istore #34
		// @0D3E: aload #12
		// @0D40: getfield game.C_100302_ka game.C_100211_qd.field_102147_kc
		// @0D43: aload #33
		// @0D45: putfield java.lang.String game.C_100302_ka.field_101890_ab
		// @0D48: aload #12
		// @0D4A: getfield game.C_100302_ka game.C_100211_qd.field_102147_kc
		// @0D4D: sipush 256 (0x0100)
		// @0D50: aload #12
		// @0D52: getfield int game.C_100211_qd.field_102142_Ub
		// @0D55: imul
		// @0D56: getstatic int game.C_100055_ed.field_104241_d
		// @0D59: idiv
		// @0D5A: putfield int game.C_100302_ka.field_101871_mb
		// @0D5D: aload #12
		// @0D5F: getfield game.C_100302_ka game.C_100211_qd.field_102147_kc
		// @0D62: getstatic int game.C_100244_pe.field_106375_d
		// @0D65: getstatic int game.C_100033_gj.field_101917_jc
		// @0D68: iload #34
		// @0D6A: imul
		// @0D6B: iconst_m1
		// @0D6C: iload #31
		// @0D6E: iconst_2
		// @0D6F: getstatic int game.C_100244_pe.field_106375_d
		// @0D72: imul
		// @0D73: ineg
		// @0D74: aload #12
		// @0D76: getfield int game.C_100211_qd.field_101886_Kb
		// @0D79: iadd
		// @0D7A: invokevirtual game.C_100302_ka.func_101825_a(int, int, int, int, int)void
		// @0D7D: iload #31
		// @0D7F: getstatic int game.C_100033_gj.field_101917_jc
		// @0D82: iload #34
		// @0D84: imul
		// @0D85: iadd
		// @0D86: istore #31
		// @0D88: iload #7
		// @0D8A: ifeq @0D91
		// @0D8D: goto @0D9F
		// @0D90: athrow
		// @0D91: aload #12
		// @0D93: aload #12
		// @0D95: getfield int game.C_100211_qd.field_101848_lb
		// @0D98: ineg
		// @0D99: iload #31
		// @0D9B: iadd
		// @0D9C: putfield int game.C_100211_qd.field_101832_tb
		// @0D9F: iload #13
		// @0DA1: ifne @0DA8
		// @0DA4: goto @0DB7
		// @0DA7: athrow
		// @0DA8: getstatic game.C_100115_ej game.C_100156_sk.field_105389_r
		// @0DAB: getfield game.C_100302_ka game.C_100115_ej.field_102036_Wb
		// @0DAE: aload #12
		// @0DB0: iconst_0
		// @0DB1: aload #11
		// @0DB3: iconst_2
		// @0DB4: invokevirtual game.C_100302_ka.func_101823_a(game.C_100302_ka, boolean, game.C_100302_ka, int)void
		// @0DB7: iconst_0
		// @0DB8: istore #34
		// @0DBA: iload #34
		// @0DBC: getstatic int game.C_100137_bn.field_105038_l
		// @0DBF: if_icmpge @0E55
		// @0DC2: aload #12
		// @0DC4: getfield game.C_100302_ka[] game.C_100211_qd.field_102162_hc
		// @0DC7: iload #34
		// @0DC9: aaload
		// @0DCA: getfield boolean game.C_100302_ka.field_101839_db
		// @0DCD: iload #41
		// @0DCF: ifne @0E5D
		// @0DD2: ifne @0DDC
		// @0DD5: goto @0DD9
		// @0DD8: athrow
		// @0DD9: goto @0E4D
		// @0DDC: aconst_null
		// @0DDD: getstatic java.lang.String[][] game.C_100047_vh.field_104153_c
		// @0DE0: if_acmpeq @0E0B
		// @0DE3: getstatic java.lang.String[][] game.C_100047_vh.field_104153_c
		// @0DE6: iload #34
		// @0DE8: aaload
		// @0DE9: ifnonnull @0DF5
		// @0DEC: goto @0DF0
		// @0DEF: athrow
		// @0DF0: aconst_null
		// @0DF1: goto @0E0C
		// @0DF4: athrow
		// @0DF5: getstatic java.lang.String[][] game.C_100047_vh.field_104153_c
		// @0DF8: iload #34
		// @0DFA: aaload
		// @0DFB: sipush 255 (0x00FF)
		// @0DFE: aload #12
		// @0E00: getfield byte[] game.C_100211_qd.field_102165_jc
		// @0E03: iload #34
		// @0E05: baload
		// @0E06: iand
		// @0E07: aaload
		// @0E08: goto @0E0C
		// @0E0B: aconst_null
		// @0E0C: astore #35
		// @0E0E: aconst_null
		// @0E0F: aload #35
		// @0E11: if_acmpeq @0E40
		// @0E14: new java.lang.StringBuilder
		// @0E17: dup
		// @0E18: invokespecial java.lang.StringBuilder.<init>()void
		// @0E1B: getstatic java.lang.String[] game.C_100036_gg.field_103155_R
		// @0E1E: iload #34
		// @0E20: aaload
		// @0E21: invokevirtual java.lang.StringBuilder.append(java.lang.String)java.lang.StringBuilder
		// @0E24: getstatic java.lang.String[] game.C_100305_km.field_103231_S
		// @0E27: iconst_1
		// @0E28: aaload
		// @0E29: invokevirtual java.lang.StringBuilder.append(java.lang.String)java.lang.StringBuilder
		// @0E2C: aload #35
		// @0E2E: invokevirtual java.lang.StringBuilder.append(java.lang.String)java.lang.StringBuilder
		// @0E31: invokevirtual java.lang.StringBuilder.toString()java.lang.String
		// @0E34: putstatic java.lang.String game.C_100321_hi.field_107220_c
		// @0E37: iload #41
		// @0E39: ifeq @0E4D
		// @0E3C: goto @0E40
		// @0E3F: athrow
		// @0E40: getstatic java.lang.String[] game.C_100036_gg.field_103155_R
		// @0E43: iload #34
		// @0E45: aaload
		// @0E46: putstatic java.lang.String game.C_100321_hi.field_107220_c
		// @0E49: goto @0E4D
		// @0E4C: athrow
		// @0E4D: iinc #34 +1
		// @0E50: iload #41
		// @0E52: ifeq @0DBA
		// @0E55: aload #12
		// @0E57: getfield game.C_100302_ka game.C_100211_qd.field_102174_wc
		// @0E5A: getfield boolean game.C_100302_ka.field_101839_db
		// @0E5D: ifeq @0EA0
		// @0E60: iconst_1
		// @0E61: aload #12
		// @0E63: getfield int game.C_100211_qd.field_102159_sc
		// @0E66: if_icmpeq @0E7B
		// @0E69: goto @0E6D
		// @0E6C: athrow
		// @0E6D: getstatic java.lang.String[] game.C_100277_nc.field_106745_x
		// @0E70: aload #12
		// @0E72: getfield int game.C_100211_qd.field_102159_sc
		// @0E75: aaload
		// @0E76: astore #34
		// @0E78: goto @0E80
		// @0E7B: getstatic java.lang.String game.C_100084_ug.field_104483_c
		// @0E7E: astore #34
		// @0E80: new java.lang.StringBuilder
		// @0E83: dup
		// @0E84: invokespecial java.lang.StringBuilder.<init>()void
		// @0E87: getstatic java.lang.String game.C_100269_ml.field_101122_p
		// @0E8A: invokevirtual java.lang.StringBuilder.append(java.lang.String)java.lang.StringBuilder
		// @0E8D: getstatic java.lang.String[] game.C_100305_km.field_103231_S
		// @0E90: iconst_1
		// @0E91: aaload
		// @0E92: invokevirtual java.lang.StringBuilder.append(java.lang.String)java.lang.StringBuilder
		// @0E95: aload #34
		// @0E97: invokevirtual java.lang.StringBuilder.append(java.lang.String)java.lang.StringBuilder
		// @0E9A: invokevirtual java.lang.StringBuilder.toString()java.lang.String
		// @0E9D: putstatic java.lang.String game.C_100321_hi.field_107220_c
		// @0EA0: aload #12
		// @0EA2: getfield game.C_100302_ka game.C_100211_qd.field_102168_pc
		// @0EA5: getfield boolean game.C_100302_ka.field_101839_db
		// @0EA8: ifne @0EAF
		// @0EAB: goto @0EC4
		// @0EAE: athrow
		// @0EAF: aload #12
		// @0EB1: getfield boolean game.C_100211_qd.field_102134_zc
		// @0EB4: ifne @0EBE
		// @0EB7: getstatic java.lang.String game.C_100270_mi.field_102281_bc
		// @0EBA: goto @0EC1
		// @0EBD: athrow
		// @0EBE: getstatic java.lang.String game.C_100061_dh.field_101994_Vb
		// @0EC1: putstatic java.lang.String game.C_100321_hi.field_107220_c
		// @0EC4: aload #12
		// @0EC6: getfield game.C_100302_ka game.C_100211_qd.field_102145_tc
		// @0EC9: getfield boolean game.C_100302_ka.field_101839_db
		// @0ECC: ifeq @0F06
		// @0ECF: aload #12
		// @0ED1: getfield boolean game.C_100211_qd.field_102167_nc
		// @0ED4: ifne @0F00
		// @0ED7: goto @0EDB
		// @0EDA: athrow
		// @0EDB: aload #12
		// @0EDD: getfield boolean game.C_100211_qd.field_102153_Lc
		// @0EE0: ifne @0F00
		// @0EE3: goto @0EE7
		// @0EE6: athrow
		// @0EE7: aload #12
		// @0EE9: getfield boolean game.C_100211_qd.field_102135_Dc
		// @0EEC: ifeq @0EFA
		// @0EEF: goto @0EF3
		// @0EF2: athrow
		// @0EF3: getstatic java.lang.String game.C_100108_ee.field_100389_a
		// @0EF6: goto @0F03
		// @0EF9: athrow
		// @0EFA: getstatic java.lang.String game.C_100181_cf.field_105711_i
		// @0EFD: goto @0F03
		// @0F00: getstatic java.lang.String game.C_100188_rj.field_105739_c
		// @0F03: putstatic java.lang.String game.C_100321_hi.field_107220_c
		// @0F06: aload #12
		// @0F08: getfield game.C_100302_ka game.C_100211_qd.field_102141_ic
		// @0F0B: getfield boolean game.C_100302_ka.field_101839_db
		// @0F0E: ifne @0F15
		// @0F11: goto @0F2B
		// @0F14: athrow
		// @0F15: iconst_2
		// @0F16: aload #12
		// @0F18: getfield int game.C_100211_qd.field_102133_Fc
		// @0F1B: if_icmpne @0F25
		// @0F1E: getstatic java.lang.String game.C_100148_bh.field_101792_D
		// @0F21: goto @0F28
		// @0F24: athrow
		// @0F25: getstatic java.lang.String game.C_100064_ve.field_103020_z
		// @0F28: putstatic java.lang.String game.C_100321_hi.field_107220_c
		// @0F2B: aload #12
		// @0F2D: getfield int game.C_100211_qd.field_101854_N
		// @0F30: iconst_m1
		// @0F31: ixor
		// @0F32: iconst_m1
		// @0F33: if_icmpeq @0FBC
		// @0F36: aload #12
		// @0F38: bipush -108 (0x94)
		// @0F3A: invokevirtual game.C_100211_qd.func_102125_g(byte)boolean
		// @0F3D: ifeq @0F48
		// @0F40: goto @0F44
		// @0F43: athrow
		// @0F44: goto @0FBC
		// @0F47: athrow
		// @0F48: aload #12
		// @0F4A: getfield game.C_100302_ka game.C_100211_qd.field_102148_Hc
		// @0F4D: getfield int game.C_100302_ka.field_101854_N
		// @0F50: ifeq @0FAD
		// @0F53: aload #12
		// @0F55: getfield boolean game.C_100211_qd.field_102173_Ic
		// @0F58: ifeq @0F99
		// @0F5B: goto @0F5F
		// @0F5E: athrow
		// @0F5F: aload #12
		// @0F61: getfield boolean game.C_100211_qd.field_102135_Dc
		// @0F64: ifeq @0F83
		// @0F67: goto @0F6B
		// @0F6A: athrow
		// @0F6B: aload #12
		// @0F6D: getfield boolean game.C_100211_qd.field_102167_nc
		// @0F70: ifne @0F99
		// @0F73: goto @0F77
		// @0F76: athrow
		// @0F77: aload #12
		// @0F79: getfield boolean game.C_100211_qd.field_102153_Lc
		// @0F7C: ifne @0F99
		// @0F7F: goto @0F83
		// @0F82: athrow
		// @0F83: aload #12
		// @0F85: iconst_1
		// @0F86: invokevirtual game.C_100211_qd.func_102127_b(boolean)int
		// @0F89: sipush -1999 (0xF831)
		// @0F8C: iload_1
		// @0F8D: invokestatic game.C_100335_il.func_107364_a(int, int, int)void
		// @0F90: iload #41
		// @0F92: ifeq @0FBC
		// @0F95: goto @0F99
		// @0F98: athrow
		// @0F99: aload #12
		// @0F9B: iconst_1
		// @0F9C: invokevirtual game.C_100211_qd.func_102127_b(boolean)int
		// @0F9F: iconst_3
		// @0FA0: iload_1
		// @0FA1: invokestatic game.C_100277_nc.func_106695_a(int, int, int)void
		// @0FA4: iload #41
		// @0FA6: ifeq @0FBC
		// @0FA9: goto @0FAD
		// @0FAC: athrow
		// @0FAD: bipush 27 (0x1B)
		// @0FAF: aload #32
		// @0FB1: iload #4
		// @0FB3: aload #12
		// @0FB5: invokestatic game.C_100330_ig.func_107275_a(int, java.lang.String, boolean, game.C_100211_qd)void
		// @0FB8: goto @0FBC
		// @0FBB: athrow
		// @0FBC: aload #8
		// @0FBE: bipush 39 (0x27)
		// @0FC0: invokevirtual game.C_100202_qi.func_105907_c(byte)game.C_100158_da
		// @0FC3: checkcast game.C_100211_qd
		// @0FC6: astore #12
		// @0FC8: iload #41
		// @0FCA: ifeq @006C
		// @0FCD: goto @102C
		// @0FD0: astore #7
		// @0FD2: aload #7
		// @0FD4: new java.lang.StringBuilder
		// @0FD7: dup
		// @0FD8: invokespecial java.lang.StringBuilder.<init>()void
		// @0FDB: getstatic java.lang.String[] game.C_100305_km.field_103231_S
		// @0FDE: iconst_2
		// @0FDF: aaload
		// @0FE0: invokevirtual java.lang.StringBuilder.append(java.lang.String)java.lang.StringBuilder
		// @0FE3: iload_0
		// @0FE4: invokevirtual java.lang.StringBuilder.append(boolean)java.lang.StringBuilder
		// @0FE7: bipush 44 (0x2C)
		// @0FE9: invokevirtual java.lang.StringBuilder.append(char)java.lang.StringBuilder
		// @0FEC: iload_1
		// @0FED: invokevirtual java.lang.StringBuilder.append(int)java.lang.StringBuilder
		// @0FF0: bipush 44 (0x2C)
		// @0FF2: invokevirtual java.lang.StringBuilder.append(char)java.lang.StringBuilder
		// @0FF5: iload_2
		// @0FF6: invokevirtual java.lang.StringBuilder.append(int)java.lang.StringBuilder
		// @0FF9: bipush 44 (0x2C)
		// @0FFB: invokevirtual java.lang.StringBuilder.append(char)java.lang.StringBuilder
		// @0FFE: iload_3
		// @0FFF: invokevirtual java.lang.StringBuilder.append(int)java.lang.StringBuilder
		// @1002: bipush 44 (0x2C)
		// @1004: invokevirtual java.lang.StringBuilder.append(char)java.lang.StringBuilder
		// @1007: iload #4
		// @1009: invokevirtual java.lang.StringBuilder.append(boolean)java.lang.StringBuilder
		// @100C: bipush 44 (0x2C)
		// @100E: invokevirtual java.lang.StringBuilder.append(char)java.lang.StringBuilder
		// @1011: iload #5
		// @1013: invokevirtual java.lang.StringBuilder.append(int)java.lang.StringBuilder
		// @1016: bipush 44 (0x2C)
		// @1018: invokevirtual java.lang.StringBuilder.append(char)java.lang.StringBuilder
		// @101B: iload #6
		// @101D: invokevirtual java.lang.StringBuilder.append(int)java.lang.StringBuilder
		// @1020: bipush 41 (0x29)
		// @1022: invokevirtual java.lang.StringBuilder.append(char)java.lang.StringBuilder
		// @1025: invokevirtual java.lang.StringBuilder.toString()java.lang.String
		// @1028: invokestatic game.C_100181_cf.func_105695_a(java.lang.Throwable, java.lang.String)game.C_100170_cm
		// @102B: athrow
		// @102C: return
	}
	
	C_100305_km(C_100308_lh arg0)
	{
		// @00: aload_0
		// @01: invokespecial game.C_100218_am.<init>()void
		// @04: aload_0
		// @05: aload_1
		// @06: putfield game.C_100308_lh game.C_100305_km.field_103230_P
		// @09: goto @3F
		// @0C: astore_2
		// @0D: aload_2
		// @0E: new java.lang.StringBuilder
		// @11: dup
		// @12: invokespecial java.lang.StringBuilder.<init>()void
		// @15: getstatic java.lang.String[] game.C_100305_km.field_103231_S
		// @18: iconst_5
		// @19: aaload
		// @1A: invokevirtual java.lang.StringBuilder.append(java.lang.String)java.lang.StringBuilder
		// @1D: aload_1
		// @1E: ifnull @2A
		// @21: getstatic java.lang.String[] game.C_100305_km.field_103231_S
		// @24: iconst_4
		// @25: aaload
		// @26: goto @30
		// @29: athrow
		// @2A: getstatic java.lang.String[] game.C_100305_km.field_103231_S
		// @2D: bipush 6 (0x06)
		// @2F: aaload
		// @30: invokevirtual java.lang.StringBuilder.append(java.lang.String)java.lang.StringBuilder
		// @33: bipush 41 (0x29)
		// @35: invokevirtual java.lang.StringBuilder.append(char)java.lang.StringBuilder
		// @38: invokevirtual java.lang.StringBuilder.toString()java.lang.String
		// @3B: invokestatic game.C_100181_cf.func_105695_a(java.lang.Throwable, java.lang.String)game.C_100170_cm
		// @3E: athrow
		// @3F: return
	}
	
	static
	{
		// @00: bipush 17 (0x11)
		// @02: anewarray java.lang.String
		// @05: dup
		// @06: iconst_0
		// @07: ldc "4R"
		// @09: invokestatic game.C_100305_km.func_103226_z(java.lang.String)char[]
		// @0C: invokestatic game.C_100305_km.func_103223_z(char[])java.lang.String
		// @0F: aastore
		// @10: dup
		// @11: iconst_1
		// @12: ldc "8_2"
		// @14: invokestatic game.C_100305_km.func_103226_z(java.lang.String)char[]
		// @17: invokestatic game.C_100305_km.func_103223_z(char[])java.lang.String
		// @1A: aastore
		// @1B: dup
		// @1C: iconst_2
		// @1D: ldc "s\u001f<^\u0008"
		// @1F: invokestatic game.C_100305_km.func_103226_z(java.lang.String)char[]
		// @22: invokestatic game.C_100305_km.func_103223_z(char[])java.lang.String
		// @25: aastore
		// @26: dup
		// @27: iconst_3
		// @28: ldc "s\u001f<\\\u0008"
		// @2A: invokestatic game.C_100305_km.func_103226_z(java.lang.String)char[]
		// @2D: invokestatic game.C_100305_km.func_103223_z(char[])java.lang.String
		// @30: aastore
		// @31: dup
		// @32: iconst_4
		// @33: ldc "c\\<4]"
		// @35: invokestatic game.C_100305_km.func_103226_z(java.lang.String)char[]
		// @38: invokestatic game.C_100305_km.func_103223_z(char[])java.lang.String
		// @3B: aastore
		// @3C: dup
		// @3D: iconst_5
		// @3E: ldc "s\u001f<&Iv\u001bf$\u0008"
		// @40: invokestatic game.C_100305_km.func_103226_z(java.lang.String)char[]
		// @43: invokestatic game.C_100305_km.func_103223_z(char[])java.lang.String
		// @46: aastore
		// @47: dup
		// @48: bipush 6 (0x06)
		// @4A: ldc "v\u0007~v"
		// @4C: invokestatic game.C_100305_km.func_103226_z(java.lang.String)char[]
		// @4F: invokestatic game.C_100305_km.func_103223_z(char[])java.lang.String
		// @52: aastore
		// @53: dup
		// @54: bipush 7 (0x07)
		// @56: ldc "s\u001f<S\u0008"
		// @58: invokestatic game.C_100305_km.func_103226_z(java.lang.String)char[]
		// @5B: invokestatic game.C_100305_km.func_103223_z(char[])java.lang.String
		// @5E: aastore
		// @5F: dup
		// @60: bipush 8 (0x08)
		// @62: ldc "s\u001f<X\u0008"
		// @64: invokestatic game.C_100305_km.func_103226_z(java.lang.String)char[]
		// @67: invokestatic game.C_100305_km.func_103223_z(char[])java.lang.String
		// @6A: aastore
		// @6B: dup
		// @6C: bipush 9 (0x09)
		// @6E: ldc "s\u001f<Y\u0008"
		// @70: invokestatic game.C_100305_km.func_103226_z(java.lang.String)char[]
		// @73: invokestatic game.C_100305_km.func_103223_z(char[])java.lang.String
		// @76: aastore
		// @77: dup
		// @78: bipush 10 (0x0A)
		// @7A: ldc "s\u001f<I\u0008"
		// @7C: invokestatic game.C_100305_km.func_103226_z(java.lang.String)char[]
		// @7F: invokestatic game.C_100305_km.func_103223_z(char[])java.lang.String
		// @82: aastore
		// @83: dup
		// @84: bipush 11 (0x0B)
		// @86: ldc "s\u001f<K\u0008"
		// @88: invokestatic game.C_100305_km.func_103226_z(java.lang.String)char[]
		// @8B: invokestatic game.C_100305_km.func_103223_z(char[])java.lang.String
		// @8E: aastore
		// @8F: dup
		// @90: bipush 12 (0x0C)
		// @92: ldc "s\u001f<[\u0008"
		// @94: invokestatic game.C_100305_km.func_103226_z(java.lang.String)char[]
		// @97: invokestatic game.C_100305_km.func_103223_z(char[])java.lang.String
		// @9A: aastore
		// @9B: dup
		// @9C: bipush 13 (0x0D)
		// @9E: ldc "{\u001d\u007fwOv\u0007{"
		// @A0: invokestatic game.C_100305_km.func_103226_z(java.lang.String)char[]
		// @A3: invokestatic game.C_100305_km.func_103223_z(char[])java.lang.String
		// @A6: aastore
		// @A7: dup
		// @A8: bipush 14 (0x0E)
		// @AA: ldc "s\u001f<R\u0008"
		// @AC: invokestatic game.C_100305_km.func_103226_z(java.lang.String)char[]
		// @AF: invokestatic game.C_100305_km.func_103223_z(char[])java.lang.String
		// @B2: aastore
		// @B3: dup
		// @B4: bipush 15 (0x0F)
		// @B6: ldc "z\u0007fnOv\\usF"
		// @B8: invokestatic game.C_100305_km.func_103226_z(java.lang.String)char[]
		// @BB: invokestatic game.C_100305_km.func_103223_z(char[])java.lang.String
		// @BE: aastore
		// @BF: dup
		// @C0: bipush 16 (0x10)
		// @C2: ldc "s\u001f<_\u0008"
		// @C4: invokestatic game.C_100305_km.func_103226_z(java.lang.String)char[]
		// @C7: invokestatic game.C_100305_km.func_103223_z(char[])java.lang.String
		// @CA: aastore
		// @CB: putstatic java.lang.String[] game.C_100305_km.field_103231_S
		// @CE: iconst_0
		// @CF: putstatic int game.C_100305_km.field_103229_Q
		// @D2: ldc "[\u001d|tE{\u0006{uN8\u001e}iT8_2{Tl\u0017\u007fjTq\u001cu:TwR`\u007fCw\u001c|\u007fCl"
		// @D4: invokestatic game.C_100305_km.func_103226_z(java.lang.String)char[]
		// @D7: invokestatic game.C_100305_km.func_103223_z(char[])java.lang.String
		// @DA: putstatic java.lang.String game.C_100305_km.field_103232_R
		// @DD: return
	}
	
	private static char[] func_103226_z(String arg0)
	{
		// @00: aload_0
		// @01: invokevirtual java.lang.String.toCharArray()char[]
		// @04: dup
		// @05: arraylength
		// @06: iconst_2
		// @07: if_icmpge @13
		// @0A: dup
		// @0B: iconst_0
		// @0C: dup2
		// @0D: caload
		// @0E: bipush 32 (0x20)
		// @10: ixor
		// @11: i2c
		// @12: castore
		// @13: areturn
	}
	
	private static String func_103223_z(char[] arg0)
	{
		// @00: aload_0
		// @01: dup
		// @02: arraylength
		// @03: swap
		// @04: iconst_0
		// @05: istore_1
		// @06: goto @4C
		// @09: dup
		// @0A: iload_1
		// @0B: dup2
		// @0C: caload
		// @0D: iload_1
		// @0E: iconst_5
		// @0F: irem
		// @10: tableswitch def: @44, for 0: @30, for 1: @35, for 2: @3A, for 3: @3F
		// @30: bipush 24 (0x18)
		// @32: goto @46
		// @35: bipush 114 (0x72)
		// @37: goto @46
		// @3A: bipush 18 (0x12)
		// @3C: goto @46
		// @3F: bipush 26 (0x1A)
		// @41: goto @46
		// @44: bipush 32 (0x20)
		// @46: ixor
		// @47: i2c
		// @48: castore
		// @49: iinc #1 +1
		// @4C: swap
		// @4D: dup_x1
		// @4E: iload_1
		// @4F: if_icmpgt @09
		// @52: new java.lang.String
		// @55: dup_x1
		// @56: swap
		// @57: invokespecial java.lang.String.<init>(char[])void
		// @5A: invokevirtual java.lang.String.intern()java.lang.String
		// @5D: areturn
	}
}
