package game;

final class C_100231_oc extends C_100302_ka
{
	private C_100302_ka field_102206_ac;
	static C_100202_qi field_102193_gc;
	static int[][] field_102194_Zb;
	static String field_102209_cc;
	static int field_102196_Yb;
	static int field_102200_Wb;
	private C_100302_ka field_102204_Vb;
	private C_100302_ka field_102203_Ub;
	private C_100302_ka field_102199_fc;
	private C_100302_ka field_102197_hc;
	private int field_102202_ic;
	private C_100302_ka field_102201_jc;
	static volatile int field_102198_ec;
	static String field_102195_Xb;
	static String field_102205_kc;
	static C_100302_ka field_102208_bc;
	static int[] field_102192_dc;
	private static final String[] field_102207_lc;
	
	static final void func_102190_a(byte arg0, C_100302_ka arg1, C_100302_ka arg2, boolean arg3, C_100302_ka arg4, C_100112_r arg5, C_100302_ka arg6, C_100302_ka arg7, C_100302_ka arg8, C_100302_ka arg9, C_100302_ka arg10, C_100231_oc arg11)
	{
		// @000: getstatic int game.SteelSentinels.field_105275_O
		// @003: istore #21
		// @005: getstatic int[] game.C_100269_ml.field_101123_n
		// @008: iconst_1
		// @009: ldc 6356832 (0x60ff60)
		// @00B: iastore
		// @00C: getstatic int[] game.C_100269_ml.field_101123_n
		// @00F: iconst_4
		// @010: ldc 16711935 (0xff00ff)
		// @012: iastore
		// @013: getstatic int[] game.C_100269_ml.field_101123_n
		// @016: iconst_0
		// @017: ldc 16764000 (0xffcc60)
		// @019: iastore
		// @01A: aload_1
		// @01B: putstatic game.C_100302_ka game.C_100114_q.field_100494_y
		// @01E: iload_3
		// @01F: putstatic boolean game.C_100024_hd.field_103002_x
		// @022: getstatic int[] game.C_100269_ml.field_101123_n
		// @025: iconst_3
		// @026: ldc 16736511 (0xff60ff)
		// @028: iastore
		// @029: getstatic int[] game.C_100269_ml.field_101123_n
		// @02C: iconst_2
		// @02D: ldc 9474303 (0x9090ff)
		// @02F: iastore
		// @030: aload #5
		// @032: putstatic game.C_100112_r game.C_100053_vn.field_102827_cb
		// @035: getstatic int[] game.C_100140_bj.field_102968_c
		// @038: iconst_1
		// @039: ldc 6356832 (0x60ff60)
		// @03B: iastore
		// @03C: getstatic int[] game.C_100269_ml.field_101123_n
		// @03F: iconst_4
		// @040: ldc 16711935 (0xff00ff)
		// @042: iastore
		// @043: getstatic int[] game.C_100140_bj.field_102968_c
		// @046: iconst_0
		// @047: ldc 16764000 (0xffcc60)
		// @049: iastore
		// @04A: getstatic int[] game.C_100140_bj.field_102968_c
		// @04D: iconst_3
		// @04E: ldc 16736511 (0xff60ff)
		// @050: iastore
		// @051: ldc 8421504 (0x808080)
		// @053: putstatic int game.C_100273_mm.field_106679_f
		// @056: getstatic int[] game.C_100140_bj.field_102968_c
		// @059: iconst_2
		// @05A: ldc 16736352 (0xff6060)
		// @05C: iastore
		// @05D: new game.C_100037_wb
		// @060: dup
		// @061: iconst_4
		// @062: iconst_4
		// @063: invokespecial game.C_100037_wb.<init>(int, int)void
		// @066: astore #12
		// @068: aload #12
		// @06A: getfield int[] game.C_100037_wb.field_102388_J
		// @06D: astore #13
		// @06F: aload #12
		// @071: getfield int[] game.C_100037_wb.field_102388_J
		// @074: astore #14
		// @076: aload #12
		// @078: getfield int[] game.C_100037_wb.field_102388_J
		// @07B: bipush 15 (0x0F)
		// @07D: ldc 7368816 (0x707070)
		// @07F: iastore
		// @080: aload #12
		// @082: getfield int[] game.C_100037_wb.field_102388_J
		// @085: astore #15
		// @087: aload #14
		// @089: iconst_5
		// @08A: ldc 7368816 (0x707070)
		// @08C: iastore
		// @08D: aload #13
		// @08F: iconst_2
		// @090: ldc 7368816 (0x707070)
		// @092: iastore
		// @093: aload #15
		// @095: bipush 8 (0x08)
		// @097: ldc 7368816 (0x707070)
		// @099: iastore
		// @09A: bipush 9 (0x09)
		// @09C: anewarray game.C_100037_wb
		// @09F: astore #16
		// @0A1: aload #16
		// @0A3: iconst_4
		// @0A4: aload #12
		// @0A6: aastore
		// @0A7: new game.C_100302_ka
		// @0AA: dup
		// @0AB: lconst_0
		// @0AC: aload #10
		// @0AE: invokespecial game.C_100302_ka.<init>(long, game.C_100302_ka)void
		// @0B1: putstatic game.C_100302_ka game.C_100265_mh.field_106621_l
		// @0B4: new game.C_100302_ka
		// @0B7: dup
		// @0B8: lconst_0
		// @0B9: aload_2
		// @0BA: invokespecial game.C_100302_ka.<init>(long, game.C_100302_ka)void
		// @0BD: putstatic game.C_100302_ka game.C_100170_cm.field_105544_o
		// @0C0: getstatic game.C_100302_ka game.C_100265_mh.field_106621_l
		// @0C3: bipush -103 (0x99)
		// @0C5: getstatic game.C_100302_ka game.C_100170_cm.field_105544_o
		// @0C8: invokevirtual game.C_100302_ka.func_101824_b(int, game.C_100302_ka)void
		// @0CB: new game.C_100302_ka
		// @0CE: dup
		// @0CF: lconst_0
		// @0D0: aconst_null
		// @0D1: invokespecial game.C_100302_ka.<init>(long, game.C_100302_ka)void
		// @0D4: astore #17
		// @0D6: aload #17
		// @0D8: new game.C_100202_qi
		// @0DB: dup
		// @0DC: invokespecial game.C_100202_qi.<init>()void
		// @0DF: putfield game.C_100202_qi game.C_100302_ka.field_101891_Ob
		// @0E2: new game.C_100115_ej
		// @0E5: dup
		// @0E6: lconst_0
		// @0E7: aload #17
		// @0E9: aload #4
		// @0EB: aload #11
		// @0ED: invokespecial game.C_100115_ej.<init>(long, game.C_100302_ka, game.C_100302_ka, game.C_100231_oc)void
		// @0F0: putstatic game.C_100115_ej game.C_100081_ue.field_100670_q
		// @0F3: getstatic game.C_100302_ka game.C_100170_cm.field_105544_o
		// @0F6: bipush -107 (0x95)
		// @0F8: getstatic game.C_100115_ej game.C_100081_ue.field_100670_q
		// @0FB: invokevirtual game.C_100302_ka.func_101824_b(int, game.C_100302_ka)void
		// @0FE: new game.C_100302_ka
		// @101: dup
		// @102: lconst_0
		// @103: aload #7
		// @105: invokespecial game.C_100302_ka.<init>(long, game.C_100302_ka)void
		// @108: putstatic game.C_100302_ka game.C_100019_wl.field_103844_b
		// @10B: getstatic game.C_100302_ka game.C_100170_cm.field_105544_o
		// @10E: bipush -116 (0x8C)
		// @110: getstatic game.C_100302_ka game.C_100019_wl.field_103844_b
		// @113: invokevirtual game.C_100302_ka.func_101824_b(int, game.C_100302_ka)void
		// @116: new game.C_100302_ka
		// @119: dup
		// @11A: lconst_0
		// @11B: aload #6
		// @11D: invokespecial game.C_100302_ka.<init>(long, game.C_100302_ka)void
		// @120: putstatic game.C_100302_ka game.C_100235_om.field_106296_j
		// @123: getstatic game.C_100302_ka game.C_100235_om.field_106296_j
		// @126: getstatic game.C_100112_r game.C_100053_vn.field_102827_cb
		// @129: putfield game.C_100112_r game.C_100302_ka.field_101845_sb
		// @12C: getstatic game.C_100302_ka game.C_100019_wl.field_103844_b
		// @12F: bipush -80 (0xB0)
		// @131: getstatic game.C_100302_ka game.C_100235_om.field_106296_j
		// @134: invokevirtual game.C_100302_ka.func_101824_b(int, game.C_100302_ka)void
		// @137: getstatic game.C_100302_ka game.C_100019_wl.field_103844_b
		// @13A: iconst_0
		// @13B: invokevirtual game.C_100302_ka.func_101821_k(int)void
		// @13E: new game.C_100302_ka
		// @141: dup
		// @142: lconst_0
		// @143: aconst_null
		// @144: invokespecial game.C_100302_ka.<init>(long, game.C_100302_ka)void
		// @147: putstatic game.C_100302_ka game.C_100127_tl.field_104946_d
		// @14A: getstatic game.C_100302_ka game.C_100127_tl.field_104946_d
		// @14D: aload #16
		// @14F: putfield game.C_100037_wb[] game.C_100302_ka.field_101862_T
		// @152: getstatic game.C_100302_ka game.C_100019_wl.field_103844_b
		// @155: bipush -119 (0x89)
		// @157: getstatic game.C_100302_ka game.C_100127_tl.field_104946_d
		// @15A: invokevirtual game.C_100302_ka.func_101824_b(int, game.C_100302_ka)void
		// @15D: iconst_5
		// @15E: anewarray game.C_100302_ka
		// @161: putstatic game.C_100302_ka[] game.C_100288_jn.field_106845_a
		// @164: bipush 41 (0x29)
		// @166: iload_0
		// @167: bipush -10 (0xF6)
		// @169: isub
		// @16A: bipush 52 (0x34)
		// @16C: idiv
		// @16D: idiv
		// @16E: istore #18
		// @170: iconst_5
		// @171: anewarray game.C_100302_ka
		// @174: putstatic game.C_100302_ka[] game.C_100067_vd.field_104323_h
		// @177: iconst_5
		// @178: anewarray game.C_100302_ka
		// @17B: putstatic game.C_100302_ka[] game.C_100338_jc.field_105374_h
		// @17E: iconst_5
		// @17F: anewarray game.C_100302_ka
		// @182: putstatic game.C_100302_ka[] game.C_100152_bd.field_105211_i
		// @185: iconst_0
		// @186: istore #19
		// @188: iload #19
		// @18A: iconst_5
		// @18B: if_icmpge @29C
		// @18E: iconst_m1
		// @18F: iload #21
		// @191: ifne @2C2
		// @194: iload #19
		// @196: iconst_m1
		// @197: ixor
		// @198: if_icmpeq @1D4
		// @19B: goto @19F
		// @19E: athrow
		// @19F: iload #19
		// @1A1: iconst_m1
		// @1A2: ixor
		// @1A3: bipush -2 (0xFE)
		// @1A5: if_icmpne @1C0
		// @1A8: goto @1AC
		// @1AB: athrow
		// @1AC: getstatic boolean game.C_100024_hd.field_103002_x
		// @1AF: ifeq @1C0
		// @1B2: goto @1B6
		// @1B5: athrow
		// @1B6: getstatic java.lang.String game.C_100164_se.field_105450_d
		// @1B9: astore #20
		// @1BB: iload #21
		// @1BD: ifeq @1EA
		// @1C0: iconst_2
		// @1C1: iload #19
		// @1C3: if_icmpne @294
		// @1C6: goto @1CA
		// @1C9: athrow
		// @1CA: getstatic java.lang.String game.C_100245_pf.field_106393_k
		// @1CD: astore #20
		// @1CF: iload #21
		// @1D1: ifeq @1EA
		// @1D4: getstatic boolean game.C_100024_hd.field_103002_x
		// @1D7: ifne @1E5
		// @1DA: goto @1DE
		// @1DD: athrow
		// @1DE: getstatic java.lang.String game.C_100015_wh.field_103789_l
		// @1E1: goto @1E8
		// @1E4: athrow
		// @1E5: getstatic java.lang.String game.C_100272_mn.field_102432_H
		// @1E8: astore #20
		// @1EA: getstatic game.C_100302_ka[] game.C_100152_bd.field_105211_i
		// @1ED: iload #19
		// @1EF: new game.C_100302_ka
		// @1F2: dup
		// @1F3: lconst_0
		// @1F4: aload #9
		// @1F6: invokespecial game.C_100302_ka.<init>(long, game.C_100302_ka)void
		// @1F9: aastore
		// @1FA: getstatic game.C_100302_ka[] game.C_100338_jc.field_105374_h
		// @1FD: iload #19
		// @1FF: new game.C_100302_ka
		// @202: dup
		// @203: lconst_0
		// @204: getstatic game.C_100302_ka game.C_100114_q.field_100494_y
		// @207: aload #20
		// @209: invokespecial game.C_100302_ka.<init>(long, game.C_100302_ka, java.lang.String)void
		// @20C: aastore
		// @20D: getstatic game.C_100302_ka[] game.C_100067_vd.field_104323_h
		// @210: iload #19
		// @212: new game.C_100302_ka
		// @215: dup
		// @216: lconst_0
		// @217: aconst_null
		// @218: invokespecial game.C_100302_ka.<init>(long, game.C_100302_ka)void
		// @21B: aastore
		// @21C: getstatic game.C_100302_ka[] game.C_100067_vd.field_104323_h
		// @21F: iload #19
		// @221: aaload
		// @222: iconst_1
		// @223: putfield int game.C_100302_ka.field_101858_J
		// @226: getstatic game.C_100302_ka[] game.C_100288_jn.field_106845_a
		// @229: iload #19
		// @22B: new game.C_100302_ka
		// @22E: dup
		// @22F: lconst_0
		// @230: getstatic game.C_100302_ka game.C_100114_q.field_100494_y
		// @233: invokespecial game.C_100302_ka.<init>(long, game.C_100302_ka)void
		// @236: aastore
		// @237: getstatic game.C_100302_ka[] game.C_100288_jn.field_106845_a
		// @23A: iload #19
		// @23C: aaload
		// @23D: iconst_1
		// @23E: putfield int game.C_100302_ka.field_101858_J
		// @241: getstatic game.C_100302_ka[] game.C_100152_bd.field_105211_i
		// @244: iload #19
		// @246: aaload
		// @247: bipush -116 (0x8C)
		// @249: getstatic game.C_100302_ka[] game.C_100338_jc.field_105374_h
		// @24C: iload #19
		// @24E: aaload
		// @24F: invokevirtual game.C_100302_ka.func_101824_b(int, game.C_100302_ka)void
		// @252: getstatic game.C_100302_ka[] game.C_100152_bd.field_105211_i
		// @255: iload #19
		// @257: aaload
		// @258: bipush -126 (0x82)
		// @25A: getstatic game.C_100302_ka[] game.C_100067_vd.field_104323_h
		// @25D: iload #19
		// @25F: aaload
		// @260: invokevirtual game.C_100302_ka.func_101824_b(int, game.C_100302_ka)void
		// @263: getstatic game.C_100302_ka[] game.C_100152_bd.field_105211_i
		// @266: iload #19
		// @268: aaload
		// @269: bipush -96 (0xA0)
		// @26B: getstatic game.C_100302_ka[] game.C_100288_jn.field_106845_a
		// @26E: iload #19
		// @270: aaload
		// @271: invokevirtual game.C_100302_ka.func_101824_b(int, game.C_100302_ka)void
		// @274: getstatic game.C_100302_ka[] game.C_100152_bd.field_105211_i
		// @277: iload #19
		// @279: aaload
		// @27A: iconst_0
		// @27B: invokevirtual game.C_100302_ka.func_101821_k(int)void
		// @27E: getstatic game.C_100302_ka game.C_100265_mh.field_106621_l
		// @281: bipush -94 (0xA2)
		// @283: getstatic game.C_100302_ka[] game.C_100152_bd.field_105211_i
		// @286: iload #19
		// @288: aaload
		// @289: invokevirtual game.C_100302_ka.func_101824_b(int, game.C_100302_ka)void
		// @28C: getstatic int game.C_100211_qd.field_102149_xc
		// @28F: iconst_1
		// @290: iadd
		// @291: putstatic int game.C_100211_qd.field_102149_xc
		// @294: iinc #19 +1
		// @297: iload #21
		// @299: ifeq @188
		// @29C: new game.C_100302_ka
		// @29F: dup
		// @2A0: lconst_0
		// @2A1: aload #8
		// @2A3: invokespecial game.C_100302_ka.<init>(long, game.C_100302_ka)void
		// @2A6: putstatic game.C_100302_ka game.C_100031_gl.field_103963_g
		// @2A9: getstatic game.C_100302_ka game.C_100031_gl.field_103963_g
		// @2AC: getstatic java.lang.String game.C_100123_uc.field_104921_d
		// @2AF: putfield java.lang.String game.C_100302_ka.field_101890_ab
		// @2B2: getstatic game.C_100302_ka game.C_100265_mh.field_106621_l
		// @2B5: bipush -92 (0xA4)
		// @2B7: getstatic game.C_100302_ka game.C_100031_gl.field_103963_g
		// @2BA: invokevirtual game.C_100302_ka.func_101824_b(int, game.C_100302_ka)void
		// @2BD: bipush -71 (0xB9)
		// @2BF: invokestatic game.C_100238_ol.func_101684_e(byte)boolean
		// @2C2: ifeq @2D3
		// @2C5: getstatic boolean game.C_100272_mn.field_102435_K
		// @2C8: ifne @2D3
		// @2CB: goto @2CF
		// @2CE: athrow
		// @2CF: goto @2E1
		// @2D2: athrow
		// @2D3: new game.C_100320_hh
		// @2D6: dup
		// @2D7: iconst_0
		// @2D8: iconst_0
		// @2D9: iconst_0
		// @2DA: iconst_0
		// @2DB: invokespecial game.C_100320_hh.<init>(int, int, int, int)void
		// @2DE: putstatic game.C_100320_hh game.C_100047_vh.field_104150_d
		// @2E1: goto @427
		// @2E4: astore #12
		// @2E6: aload #12
		// @2E8: new java.lang.StringBuilder
		// @2EB: dup
		// @2EC: invokespecial java.lang.StringBuilder.<init>()void
		// @2EF: getstatic java.lang.String[] game.C_100231_oc.field_102207_lc
		// @2F2: bipush 9 (0x09)
		// @2F4: aaload
		// @2F5: invokevirtual java.lang.StringBuilder.append(java.lang.String)java.lang.StringBuilder
		// @2F8: iload_0
		// @2F9: invokevirtual java.lang.StringBuilder.append(int)java.lang.StringBuilder
		// @2FC: bipush 44 (0x2C)
		// @2FE: invokevirtual java.lang.StringBuilder.append(char)java.lang.StringBuilder
		// @301: aload_1
		// @302: ifnull @30E
		// @305: getstatic java.lang.String[] game.C_100231_oc.field_102207_lc
		// @308: iconst_5
		// @309: aaload
		// @30A: goto @314
		// @30D: athrow
		// @30E: getstatic java.lang.String[] game.C_100231_oc.field_102207_lc
		// @311: bipush 6 (0x06)
		// @313: aaload
		// @314: invokevirtual java.lang.StringBuilder.append(java.lang.String)java.lang.StringBuilder
		// @317: bipush 44 (0x2C)
		// @319: invokevirtual java.lang.StringBuilder.append(char)java.lang.StringBuilder
		// @31C: aload_2
		// @31D: ifnull @329
		// @320: getstatic java.lang.String[] game.C_100231_oc.field_102207_lc
		// @323: iconst_5
		// @324: aaload
		// @325: goto @32F
		// @328: athrow
		// @329: getstatic java.lang.String[] game.C_100231_oc.field_102207_lc
		// @32C: bipush 6 (0x06)
		// @32E: aaload
		// @32F: invokevirtual java.lang.StringBuilder.append(java.lang.String)java.lang.StringBuilder
		// @332: bipush 44 (0x2C)
		// @334: invokevirtual java.lang.StringBuilder.append(char)java.lang.StringBuilder
		// @337: iload_3
		// @338: invokevirtual java.lang.StringBuilder.append(boolean)java.lang.StringBuilder
		// @33B: bipush 44 (0x2C)
		// @33D: invokevirtual java.lang.StringBuilder.append(char)java.lang.StringBuilder
		// @340: aload #4
		// @342: ifnull @34E
		// @345: getstatic java.lang.String[] game.C_100231_oc.field_102207_lc
		// @348: iconst_5
		// @349: aaload
		// @34A: goto @354
		// @34D: athrow
		// @34E: getstatic java.lang.String[] game.C_100231_oc.field_102207_lc
		// @351: bipush 6 (0x06)
		// @353: aaload
		// @354: invokevirtual java.lang.StringBuilder.append(java.lang.String)java.lang.StringBuilder
		// @357: bipush 44 (0x2C)
		// @359: invokevirtual java.lang.StringBuilder.append(char)java.lang.StringBuilder
		// @35C: aload #5
		// @35E: ifnull @36A
		// @361: getstatic java.lang.String[] game.C_100231_oc.field_102207_lc
		// @364: iconst_5
		// @365: aaload
		// @366: goto @370
		// @369: athrow
		// @36A: getstatic java.lang.String[] game.C_100231_oc.field_102207_lc
		// @36D: bipush 6 (0x06)
		// @36F: aaload
		// @370: invokevirtual java.lang.StringBuilder.append(java.lang.String)java.lang.StringBuilder
		// @373: bipush 44 (0x2C)
		// @375: invokevirtual java.lang.StringBuilder.append(char)java.lang.StringBuilder
		// @378: aload #6
		// @37A: ifnull @386
		// @37D: getstatic java.lang.String[] game.C_100231_oc.field_102207_lc
		// @380: iconst_5
		// @381: aaload
		// @382: goto @38C
		// @385: athrow
		// @386: getstatic java.lang.String[] game.C_100231_oc.field_102207_lc
		// @389: bipush 6 (0x06)
		// @38B: aaload
		// @38C: invokevirtual java.lang.StringBuilder.append(java.lang.String)java.lang.StringBuilder
		// @38F: bipush 44 (0x2C)
		// @391: invokevirtual java.lang.StringBuilder.append(char)java.lang.StringBuilder
		// @394: aload #7
		// @396: ifnull @3A2
		// @399: getstatic java.lang.String[] game.C_100231_oc.field_102207_lc
		// @39C: iconst_5
		// @39D: aaload
		// @39E: goto @3A8
		// @3A1: athrow
		// @3A2: getstatic java.lang.String[] game.C_100231_oc.field_102207_lc
		// @3A5: bipush 6 (0x06)
		// @3A7: aaload
		// @3A8: invokevirtual java.lang.StringBuilder.append(java.lang.String)java.lang.StringBuilder
		// @3AB: bipush 44 (0x2C)
		// @3AD: invokevirtual java.lang.StringBuilder.append(char)java.lang.StringBuilder
		// @3B0: aload #8
		// @3B2: ifnull @3BE
		// @3B5: getstatic java.lang.String[] game.C_100231_oc.field_102207_lc
		// @3B8: iconst_5
		// @3B9: aaload
		// @3BA: goto @3C4
		// @3BD: athrow
		// @3BE: getstatic java.lang.String[] game.C_100231_oc.field_102207_lc
		// @3C1: bipush 6 (0x06)
		// @3C3: aaload
		// @3C4: invokevirtual java.lang.StringBuilder.append(java.lang.String)java.lang.StringBuilder
		// @3C7: bipush 44 (0x2C)
		// @3C9: invokevirtual java.lang.StringBuilder.append(char)java.lang.StringBuilder
		// @3CC: aload #9
		// @3CE: ifnull @3DA
		// @3D1: getstatic java.lang.String[] game.C_100231_oc.field_102207_lc
		// @3D4: iconst_5
		// @3D5: aaload
		// @3D6: goto @3E0
		// @3D9: athrow
		// @3DA: getstatic java.lang.String[] game.C_100231_oc.field_102207_lc
		// @3DD: bipush 6 (0x06)
		// @3DF: aaload
		// @3E0: invokevirtual java.lang.StringBuilder.append(java.lang.String)java.lang.StringBuilder
		// @3E3: bipush 44 (0x2C)
		// @3E5: invokevirtual java.lang.StringBuilder.append(char)java.lang.StringBuilder
		// @3E8: aload #10
		// @3EA: ifnull @3F6
		// @3ED: getstatic java.lang.String[] game.C_100231_oc.field_102207_lc
		// @3F0: iconst_5
		// @3F1: aaload
		// @3F2: goto @3FC
		// @3F5: athrow
		// @3F6: getstatic java.lang.String[] game.C_100231_oc.field_102207_lc
		// @3F9: bipush 6 (0x06)
		// @3FB: aaload
		// @3FC: invokevirtual java.lang.StringBuilder.append(java.lang.String)java.lang.StringBuilder
		// @3FF: bipush 44 (0x2C)
		// @401: invokevirtual java.lang.StringBuilder.append(char)java.lang.StringBuilder
		// @404: aload #11
		// @406: ifnull @412
		// @409: getstatic java.lang.String[] game.C_100231_oc.field_102207_lc
		// @40C: iconst_5
		// @40D: aaload
		// @40E: goto @418
		// @411: athrow
		// @412: getstatic java.lang.String[] game.C_100231_oc.field_102207_lc
		// @415: bipush 6 (0x06)
		// @417: aaload
		// @418: invokevirtual java.lang.StringBuilder.append(java.lang.String)java.lang.StringBuilder
		// @41B: bipush 41 (0x29)
		// @41D: invokevirtual java.lang.StringBuilder.append(char)java.lang.StringBuilder
		// @420: invokevirtual java.lang.StringBuilder.toString()java.lang.String
		// @423: invokestatic game.C_100181_cf.func_105695_a(java.lang.Throwable, java.lang.String)game.C_100170_cm
		// @426: athrow
		// @427: return
	}
	
	final int func_102185_a(int arg0, int arg1, int arg2, boolean arg3)
	{
		// @00: iconst_0
		// @01: istore #5
		// @03: aload_0
		// @04: getfield game.C_100302_ka game.C_100231_oc.field_102197_hc
		// @07: getfield int game.C_100302_ka.field_101848_lb
		// @0A: ineg
		// @0B: aload_0
		// @0C: getfield game.C_100302_ka game.C_100231_oc.field_102199_fc
		// @0F: getfield int game.C_100302_ka.field_101848_lb
		// @12: iadd
		// @13: istore #6
		// @15: iconst_0
		// @16: iload #6
		// @18: if_icmplt @1F
		// @1B: goto @3D
		// @1E: athrow
		// @1F: aload_0
		// @20: getfield game.C_100302_ka game.C_100231_oc.field_102197_hc
		// @23: getfield int game.C_100302_ka.field_101880_Gb
		// @26: istore #7
		// @28: iload_1
		// @29: iload_2
		// @2A: isub
		// @2B: istore #8
		// @2D: iload #7
		// @2F: iload #8
		// @31: imul
		// @32: iload #6
		// @34: iconst_2
		// @35: idiv
		// @36: ineg
		// @37: isub
		// @38: iload #6
		// @3A: idiv
		// @3B: istore #5
		// @3D: iload_3
		// @3E: bipush -35 (0xDD)
		// @40: if_icmple @4F
		// @43: aload_0
		// @44: aconst_null
		// @45: checkcast game.C_100302_ka
		// @48: putfield game.C_100302_ka game.C_100231_oc.field_102201_jc
		// @4B: goto @4F
		// @4E: athrow
		// @4F: iload #4
		// @51: ifne @7C
		// @54: iload_1
		// @55: iload_2
		// @56: isub
		// @57: iconst_m1
		// @58: ixor
		// @59: iload #5
		// @5B: iconst_m1
		// @5C: ixor
		// @5D: if_icmpgt @68
		// @60: goto @64
		// @63: athrow
		// @64: goto @6E
		// @67: athrow
		// @68: iload_2
		// @69: ineg
		// @6A: iload_1
		// @6B: iadd
		// @6C: istore #5
		// @6E: iload #5
		// @70: ifge @A2
		// @73: iconst_0
		// @74: istore #5
		// @76: getstatic int game.SteelSentinels.field_105275_O
		// @79: ifeq @A2
		// @7C: iload #5
		// @7E: iconst_m1
		// @7F: ixor
		// @80: iconst_m1
		// @81: if_icmpgt @8C
		// @84: goto @88
		// @87: athrow
		// @88: goto @8F
		// @8B: athrow
		// @8C: iconst_0
		// @8D: istore #5
		// @8F: iload #5
		// @91: iconst_m1
		// @92: ixor
		// @93: iload_2
		// @94: ineg
		// @95: iload_1
		// @96: iadd
		// @97: iconst_m1
		// @98: ixor
		// @99: if_icmpge @A2
		// @9C: iload_1
		// @9D: iload_2
		// @9E: ineg
		// @9F: iadd
		// @A0: istore #5
		// @A2: iload #5
		// @A4: ireturn
		// @A5: astore #5
		// @A7: aload #5
		// @A9: new java.lang.StringBuilder
		// @AC: dup
		// @AD: invokespecial java.lang.StringBuilder.<init>()void
		// @B0: getstatic java.lang.String[] game.C_100231_oc.field_102207_lc
		// @B3: iconst_1
		// @B4: aaload
		// @B5: invokevirtual java.lang.StringBuilder.append(java.lang.String)java.lang.StringBuilder
		// @B8: iload_1
		// @B9: invokevirtual java.lang.StringBuilder.append(int)java.lang.StringBuilder
		// @BC: bipush 44 (0x2C)
		// @BE: invokevirtual java.lang.StringBuilder.append(char)java.lang.StringBuilder
		// @C1: iload_2
		// @C2: invokevirtual java.lang.StringBuilder.append(int)java.lang.StringBuilder
		// @C5: bipush 44 (0x2C)
		// @C7: invokevirtual java.lang.StringBuilder.append(char)java.lang.StringBuilder
		// @CA: iload_3
		// @CB: invokevirtual java.lang.StringBuilder.append(int)java.lang.StringBuilder
		// @CE: bipush 44 (0x2C)
		// @D0: invokevirtual java.lang.StringBuilder.append(char)java.lang.StringBuilder
		// @D3: iload #4
		// @D5: invokevirtual java.lang.StringBuilder.append(boolean)java.lang.StringBuilder
		// @D8: bipush 41 (0x29)
		// @DA: invokevirtual java.lang.StringBuilder.append(char)java.lang.StringBuilder
		// @DD: invokevirtual java.lang.StringBuilder.toString()java.lang.String
		// @E0: invokestatic game.C_100181_cf.func_105695_a(java.lang.Throwable, java.lang.String)game.C_100170_cm
		// @E3: athrow
	}
	
	public static void func_102191_g(byte arg0)
	{
		// @00: aconst_null
		// @01: putstatic java.lang.String game.C_100231_oc.field_102209_cc
		// @04: iload_0
		// @05: bipush 28 (0x1C)
		// @07: if_icmpge @3C
		// @0A: bipush 102 (0x66)
		// @0C: aconst_null
		// @0D: checkcast game.C_100302_ka
		// @10: aconst_null
		// @11: checkcast game.C_100302_ka
		// @14: iconst_1
		// @15: aconst_null
		// @16: checkcast game.C_100302_ka
		// @19: aconst_null
		// @1A: checkcast game.C_100112_r
		// @1D: aconst_null
		// @1E: checkcast game.C_100302_ka
		// @21: aconst_null
		// @22: checkcast game.C_100302_ka
		// @25: aconst_null
		// @26: checkcast game.C_100302_ka
		// @29: aconst_null
		// @2A: checkcast game.C_100302_ka
		// @2D: aconst_null
		// @2E: checkcast game.C_100302_ka
		// @31: aconst_null
		// @32: checkcast game.C_100231_oc
		// @35: invokestatic game.C_100231_oc.func_102190_a(byte, game.C_100302_ka, game.C_100302_ka, boolean, game.C_100302_ka, game.C_100112_r, game.C_100302_ka, game.C_100302_ka, game.C_100302_ka, game.C_100302_ka, game.C_100302_ka, game.C_100231_oc)void
		// @38: goto @3C
		// @3B: athrow
		// @3C: aconst_null
		// @3D: putstatic game.C_100302_ka game.C_100231_oc.field_102208_bc
		// @40: aconst_null
		// @41: putstatic java.lang.String game.C_100231_oc.field_102205_kc
		// @44: aconst_null
		// @45: putstatic int[] game.C_100231_oc.field_102192_dc
		// @48: aconst_null
		// @49: putstatic java.lang.String game.C_100231_oc.field_102195_Xb
		// @4C: aconst_null
		// @4D: putstatic game.C_100202_qi game.C_100231_oc.field_102193_gc
		// @50: aconst_null
		// @51: checkcast int[][]
		// @54: putstatic int[][] game.C_100231_oc.field_102194_Zb
		// @57: goto @7B
		// @5A: astore_1
		// @5B: aload_1
		// @5C: new java.lang.StringBuilder
		// @5F: dup
		// @60: invokespecial java.lang.StringBuilder.<init>()void
		// @63: getstatic java.lang.String[] game.C_100231_oc.field_102207_lc
		// @66: iconst_3
		// @67: aaload
		// @68: invokevirtual java.lang.StringBuilder.append(java.lang.String)java.lang.StringBuilder
		// @6B: iload_0
		// @6C: invokevirtual java.lang.StringBuilder.append(int)java.lang.StringBuilder
		// @6F: bipush 41 (0x29)
		// @71: invokevirtual java.lang.StringBuilder.append(char)java.lang.StringBuilder
		// @74: invokevirtual java.lang.StringBuilder.toString()java.lang.String
		// @77: invokestatic game.C_100181_cf.func_105695_a(java.lang.Throwable, java.lang.String)game.C_100170_cm
		// @7A: athrow
		// @7B: return
	}
	
	C_100231_oc(long arg0, C_100231_oc arg1)
	{
		// @00: aload_0
		// @01: lload_1
		// @02: aload_3
		// @03: getfield game.C_100302_ka game.C_100231_oc.field_102204_Vb
		// @06: aload_3
		// @07: getfield game.C_100302_ka game.C_100231_oc.field_102206_ac
		// @0A: aload_3
		// @0B: getfield game.C_100302_ka game.C_100231_oc.field_102203_Ub
		// @0E: aload_3
		// @0F: getfield game.C_100302_ka game.C_100231_oc.field_102197_hc
		// @12: invokespecial game.C_100231_oc.<init>(long, game.C_100302_ka, game.C_100302_ka, game.C_100302_ka, game.C_100302_ka)void
		// @15: return
	}
	
	static final int func_102189_f(byte arg0)
	{
		// @00: iload_0
		// @01: bipush -58 (0xC6)
		// @03: if_icmpeq @09
		// @06: bipush 74 (0x4A)
		// @08: ireturn
		// @09: getstatic int game.C_100301_kb.field_107103_p
		// @0C: ireturn
		// @0D: astore_1
		// @0E: aload_1
		// @0F: new java.lang.StringBuilder
		// @12: dup
		// @13: invokespecial java.lang.StringBuilder.<init>()void
		// @16: getstatic java.lang.String[] game.C_100231_oc.field_102207_lc
		// @19: bipush 11 (0x0B)
		// @1B: aaload
		// @1C: invokevirtual java.lang.StringBuilder.append(java.lang.String)java.lang.StringBuilder
		// @1F: iload_0
		// @20: invokevirtual java.lang.StringBuilder.append(int)java.lang.StringBuilder
		// @23: bipush 41 (0x29)
		// @25: invokevirtual java.lang.StringBuilder.append(char)java.lang.StringBuilder
		// @28: invokevirtual java.lang.StringBuilder.toString()java.lang.String
		// @2B: invokestatic game.C_100181_cf.func_105695_a(java.lang.Throwable, java.lang.String)game.C_100170_cm
		// @2E: athrow
	}
	
	final boolean func_102186_n(int arg0)
	{
		// @00: iload_1
		// @01: aload_0
		// @02: getfield game.C_100302_ka game.C_100231_oc.field_102203_Ub
		// @05: getfield int game.C_100302_ka.field_101854_N
		// @08: if_icmpne @0F
		// @0B: goto @17
		// @0E: athrow
		// @0F: aload_0
		// @10: bipush 20 (0x14)
		// @12: putfield int game.C_100231_oc.field_102202_ic
		// @15: iconst_1
		// @16: ireturn
		// @17: aload_0
		// @18: getfield game.C_100302_ka game.C_100231_oc.field_102203_Ub
		// @1B: getfield int game.C_100302_ka.field_101879_Rb
		// @1E: iconst_m1
		// @1F: ixor
		// @20: iconst_m1
		// @21: if_icmpeq @6B
		// @24: aload_0
		// @25: getfield int game.C_100231_oc.field_102202_ic
		// @28: ifgt @33
		// @2B: goto @2F
		// @2E: athrow
		// @2F: goto @3D
		// @32: athrow
		// @33: aload_0
		// @34: dup
		// @35: getfield int game.C_100231_oc.field_102202_ic
		// @38: iconst_1
		// @39: isub
		// @3A: putfield int game.C_100231_oc.field_102202_ic
		// @3D: aload_0
		// @3E: getfield int game.C_100231_oc.field_102202_ic
		// @41: iconst_m1
		// @42: ixor
		// @43: iconst_m1
		// @44: if_icmpne @6B
		// @47: getstatic int game.C_100338_jc.field_105370_l
		// @4A: iconst_m1
		// @4B: ixor
		// @4C: aload_0
		// @4D: getfield game.C_100302_ka game.C_100231_oc.field_102197_hc
		// @50: getfield int game.C_100302_ka.field_101835_xb
		// @53: aload_0
		// @54: getfield game.C_100302_ka game.C_100231_oc.field_102197_hc
		// @57: getfield int game.C_100302_ka.field_101843_Tb
		// @5A: iadd
		// @5B: iconst_m1
		// @5C: ixor
		// @5D: if_icmple @6B
		// @60: goto @64
		// @63: athrow
		// @64: aload_0
		// @65: iconst_3
		// @66: putfield int game.C_100231_oc.field_102202_ic
		// @69: iconst_1
		// @6A: ireturn
		// @6B: iconst_0
		// @6C: ireturn
		// @6D: astore_2
		// @6E: aload_2
		// @6F: new java.lang.StringBuilder
		// @72: dup
		// @73: invokespecial java.lang.StringBuilder.<init>()void
		// @76: getstatic java.lang.String[] game.C_100231_oc.field_102207_lc
		// @79: bipush 8 (0x08)
		// @7B: aaload
		// @7C: invokevirtual java.lang.StringBuilder.append(java.lang.String)java.lang.StringBuilder
		// @7F: iload_1
		// @80: invokevirtual java.lang.StringBuilder.append(int)java.lang.StringBuilder
		// @83: bipush 41 (0x29)
		// @85: invokevirtual java.lang.StringBuilder.append(char)java.lang.StringBuilder
		// @88: invokevirtual java.lang.StringBuilder.toString()java.lang.String
		// @8B: invokestatic game.C_100181_cf.func_105695_a(java.lang.Throwable, java.lang.String)game.C_100170_cm
		// @8E: athrow
	}
	
	final boolean func_102178_h(byte arg0)
	{
		// @00: bipush -42 (0xD6)
		// @02: bipush 37 (0x25)
		// @04: iload_1
		// @05: isub
		// @06: bipush 40 (0x28)
		// @08: idiv
		// @09: idiv
		// @0A: istore_2
		// @0B: iconst_0
		// @0C: aload_0
		// @0D: getfield game.C_100302_ka game.C_100231_oc.field_102197_hc
		// @10: getfield int game.C_100302_ka.field_101879_Rb
		// @13: if_icmpeq @1B
		// @16: iconst_1
		// @17: goto @1C
		// @1A: athrow
		// @1B: iconst_0
		// @1C: ireturn
		// @1D: astore_2
		// @1E: aload_2
		// @1F: new java.lang.StringBuilder
		// @22: dup
		// @23: invokespecial java.lang.StringBuilder.<init>()void
		// @26: getstatic java.lang.String[] game.C_100231_oc.field_102207_lc
		// @29: bipush 10 (0x0A)
		// @2B: aaload
		// @2C: invokevirtual java.lang.StringBuilder.append(java.lang.String)java.lang.StringBuilder
		// @2F: iload_1
		// @30: invokevirtual java.lang.StringBuilder.append(int)java.lang.StringBuilder
		// @33: bipush 41 (0x29)
		// @35: invokevirtual java.lang.StringBuilder.append(char)java.lang.StringBuilder
		// @38: invokevirtual java.lang.StringBuilder.toString()java.lang.String
		// @3B: invokestatic game.C_100181_cf.func_105695_a(java.lang.Throwable, java.lang.String)game.C_100170_cm
		// @3E: athrow
	}
	
	C_100231_oc(String arg0, C_100302_ka arg1, C_100302_ka arg2, C_100302_ka arg3, C_100302_ka arg4)
	{
		// @00: aload_0
		// @01: aload_1
		// @02: sipush 4000 (0x0FA0)
		// @05: invokestatic game.C_100171_cn.func_105553_a(java.lang.CharSequence, int)long
		// @08: aload_2
		// @09: aload_3
		// @0A: aload #4
		// @0C: aload #5
		// @0E: invokespecial game.C_100231_oc.<init>(long, game.C_100302_ka, game.C_100302_ka, game.C_100302_ka, game.C_100302_ka)void
		// @11: return
	}
	
	final void func_102179_a(int arg0, byte arg1, int arg2, int arg3)
	{
		// @000: aload_0
		// @001: getfield int game.C_100231_oc.field_101848_lb
		// @004: iconst_m1
		// @005: ixor
		// @006: aload_0
		// @007: getfield int game.C_100231_oc.field_101886_Kb
		// @00A: iconst_2
		// @00B: imul
		// @00C: iconst_m1
		// @00D: ixor
		// @00E: if_icmple @022
		// @011: aload_0
		// @012: getfield int game.C_100231_oc.field_101848_lb
		// @015: iconst_2
		// @016: idiv
		// @017: dup
		// @018: istore #6
		// @01A: istore #5
		// @01C: getstatic int game.SteelSentinels.field_105275_O
		// @01F: ifeq @034
		// @022: aload_0
		// @023: getfield int game.C_100231_oc.field_101886_Kb
		// @026: ineg
		// @027: aload_0
		// @028: getfield int game.C_100231_oc.field_101848_lb
		// @02B: iadd
		// @02C: istore #6
		// @02E: aload_0
		// @02F: getfield int game.C_100231_oc.field_101886_Kb
		// @032: istore #5
		// @034: iload #5
		// @036: ineg
		// @037: iload #6
		// @039: iadd
		// @03A: istore #7
		// @03C: iload #7
		// @03E: istore #8
		// @040: iconst_0
		// @041: iload_1
		// @042: if_icmplt @049
		// @045: goto @06B
		// @048: athrow
		// @049: iload_3
		// @04A: iload #8
		// @04C: imul
		// @04D: iload_1
		// @04E: idiv
		// @04F: istore #8
		// @051: aload_0
		// @052: getfield int game.C_100231_oc.field_101886_Kb
		// @055: iload #8
		// @057: if_icmple @060
		// @05A: aload_0
		// @05B: getfield int game.C_100231_oc.field_101886_Kb
		// @05E: istore #8
		// @060: iload #8
		// @062: iload #7
		// @064: if_icmple @06B
		// @067: iload #7
		// @069: istore #8
		// @06B: iload_3
		// @06C: ineg
		// @06D: iload_1
		// @06E: iadd
		// @06F: istore #9
		// @071: iload #7
		// @073: iload #8
		// @075: isub
		// @076: istore #10
		// @078: iconst_0
		// @079: istore #11
		// @07B: iload #9
		// @07D: iconst_m1
		// @07E: ixor
		// @07F: iconst_m1
		// @080: if_icmplt @087
		// @083: goto @096
		// @086: athrow
		// @087: iload #4
		// @089: iload #10
		// @08B: imul
		// @08C: iload #9
		// @08E: iconst_2
		// @08F: idiv
		// @090: iadd
		// @091: iload #9
		// @093: idiv
		// @094: istore #11
		// @096: iload #8
		// @098: iconst_2
		// @099: idiv
		// @09A: iload #11
		// @09C: iadd
		// @09D: istore #12
		// @09F: aload_0
		// @0A0: getfield game.C_100302_ka game.C_100231_oc.field_102204_Vb
		// @0A3: astore #13
		// @0A5: aload #13
		// @0A7: iload #5
		// @0A9: putfield int game.C_100302_ka.field_101848_lb
		// @0AC: aload #13
		// @0AE: aload_0
		// @0AF: getfield int game.C_100231_oc.field_101886_Kb
		// @0B2: putfield int game.C_100302_ka.field_101886_Kb
		// @0B5: aload #13
		// @0B7: iconst_0
		// @0B8: putfield int game.C_100302_ka.field_101841_Pb
		// @0BB: aload #13
		// @0BD: iconst_0
		// @0BE: putfield int game.C_100302_ka.field_101880_Gb
		// @0C1: aload_0
		// @0C2: getfield game.C_100302_ka game.C_100231_oc.field_102206_ac
		// @0C5: astore #13
		// @0C7: aload #13
		// @0C9: aload_0
		// @0CA: getfield int game.C_100231_oc.field_101848_lb
		// @0CD: iload #6
		// @0CF: isub
		// @0D0: putfield int game.C_100302_ka.field_101848_lb
		// @0D3: aload #13
		// @0D5: aload_0
		// @0D6: getfield int game.C_100231_oc.field_101886_Kb
		// @0D9: putfield int game.C_100302_ka.field_101886_Kb
		// @0DC: aload #13
		// @0DE: iconst_0
		// @0DF: putfield int game.C_100302_ka.field_101841_Pb
		// @0E2: aload #13
		// @0E4: iload #6
		// @0E6: putfield int game.C_100302_ka.field_101880_Gb
		// @0E9: aload_0
		// @0EA: getfield game.C_100302_ka game.C_100231_oc.field_102199_fc
		// @0ED: astore #13
		// @0EF: aload #13
		// @0F1: aload_0
		// @0F2: getfield int game.C_100231_oc.field_101886_Kb
		// @0F5: putfield int game.C_100302_ka.field_101886_Kb
		// @0F8: aload #13
		// @0FA: iconst_0
		// @0FB: putfield int game.C_100302_ka.field_101841_Pb
		// @0FE: aload #13
		// @100: iload #7
		// @102: putfield int game.C_100302_ka.field_101848_lb
		// @105: aload #13
		// @107: iload #5
		// @109: putfield int game.C_100302_ka.field_101880_Gb
		// @10C: aload_0
		// @10D: getfield game.C_100302_ka game.C_100231_oc.field_102203_Ub
		// @110: astore #13
		// @112: aload #13
		// @114: iload #12
		// @116: putfield int game.C_100302_ka.field_101848_lb
		// @119: aload #13
		// @11B: iconst_0
		// @11C: putfield int game.C_100302_ka.field_101841_Pb
		// @11F: aload #13
		// @121: aload_0
		// @122: getfield int game.C_100231_oc.field_101886_Kb
		// @125: putfield int game.C_100302_ka.field_101886_Kb
		// @128: aload #13
		// @12A: iconst_0
		// @12B: putfield int game.C_100302_ka.field_101880_Gb
		// @12E: aload_0
		// @12F: getfield game.C_100302_ka game.C_100231_oc.field_102201_jc
		// @132: astore #13
		// @134: aload #13
		// @136: iload #7
		// @138: iload #12
		// @13A: ineg
		// @13B: iadd
		// @13C: putfield int game.C_100302_ka.field_101848_lb
		// @13F: aload #13
		// @141: iload #12
		// @143: putfield int game.C_100302_ka.field_101880_Gb
		// @146: aload #13
		// @148: aload_0
		// @149: getfield int game.C_100231_oc.field_101886_Kb
		// @14C: putfield int game.C_100302_ka.field_101886_Kb
		// @14F: iload_2
		// @150: bipush -63 (0xC1)
		// @152: if_icmpeq @156
		// @155: return
		// @156: aload #13
		// @158: iconst_0
		// @159: putfield int game.C_100302_ka.field_101841_Pb
		// @15C: aload_0
		// @15D: getfield game.C_100302_ka game.C_100231_oc.field_102197_hc
		// @160: astore #13
		// @162: aload_0
		// @163: getfield game.C_100302_ka game.C_100231_oc.field_102204_Vb
		// @166: aload_0
		// @167: getfield game.C_100302_ka game.C_100231_oc.field_102206_ac
		// @16A: aload_0
		// @16B: getfield game.C_100302_ka game.C_100231_oc.field_102199_fc
		// @16E: iload_3
		// @16F: iconst_m1
		// @170: ixor
		// @171: iload_1
		// @172: iconst_m1
		// @173: ixor
		// @174: if_icmple @17C
		// @177: iconst_1
		// @178: goto @17D
		// @17B: athrow
		// @17C: iconst_0
		// @17D: dup_x1
		// @17E: putfield boolean game.C_100302_ka.field_101864_W
		// @181: dup_x1
		// @182: putfield boolean game.C_100302_ka.field_101864_W
		// @185: putfield boolean game.C_100302_ka.field_101864_W
		// @188: aload #13
		// @18A: aload_0
		// @18B: getfield int game.C_100231_oc.field_101886_Kb
		// @18E: putfield int game.C_100302_ka.field_101886_Kb
		// @191: aload #13
		// @193: iload #11
		// @195: putfield int game.C_100302_ka.field_101880_Gb
		// @198: aload #13
		// @19A: iconst_0
		// @19B: putfield int game.C_100302_ka.field_101841_Pb
		// @19E: aload #13
		// @1A0: iload #8
		// @1A2: putfield int game.C_100302_ka.field_101848_lb
		// @1A5: goto @1E7
		// @1A8: astore #5
		// @1AA: aload #5
		// @1AC: new java.lang.StringBuilder
		// @1AF: dup
		// @1B0: invokespecial java.lang.StringBuilder.<init>()void
		// @1B3: getstatic java.lang.String[] game.C_100231_oc.field_102207_lc
		// @1B6: iconst_2
		// @1B7: aaload
		// @1B8: invokevirtual java.lang.StringBuilder.append(java.lang.String)java.lang.StringBuilder
		// @1BB: iload_1
		// @1BC: invokevirtual java.lang.StringBuilder.append(int)java.lang.StringBuilder
		// @1BF: bipush 44 (0x2C)
		// @1C1: invokevirtual java.lang.StringBuilder.append(char)java.lang.StringBuilder
		// @1C4: iload_2
		// @1C5: invokevirtual java.lang.StringBuilder.append(int)java.lang.StringBuilder
		// @1C8: bipush 44 (0x2C)
		// @1CA: invokevirtual java.lang.StringBuilder.append(char)java.lang.StringBuilder
		// @1CD: iload_3
		// @1CE: invokevirtual java.lang.StringBuilder.append(int)java.lang.StringBuilder
		// @1D1: bipush 44 (0x2C)
		// @1D3: invokevirtual java.lang.StringBuilder.append(char)java.lang.StringBuilder
		// @1D6: iload #4
		// @1D8: invokevirtual java.lang.StringBuilder.append(int)java.lang.StringBuilder
		// @1DB: bipush 41 (0x29)
		// @1DD: invokevirtual java.lang.StringBuilder.append(char)java.lang.StringBuilder
		// @1E0: invokevirtual java.lang.StringBuilder.toString()java.lang.String
		// @1E3: invokestatic game.C_100181_cf.func_105695_a(java.lang.Throwable, java.lang.String)game.C_100170_cm
		// @1E6: athrow
		// @1E7: return
	}
	
	final boolean func_102183_m(int arg0)
	{
		// @00: aload_0
		// @01: getfield game.C_100302_ka game.C_100231_oc.field_102204_Vb
		// @04: getfield int game.C_100302_ka.field_101854_N
		// @07: ifeq @12
		// @0A: aload_0
		// @0B: bipush 20 (0x14)
		// @0D: putfield int game.C_100231_oc.field_102202_ic
		// @10: iconst_1
		// @11: ireturn
		// @12: iload_1
		// @13: aload_0
		// @14: getfield game.C_100302_ka game.C_100231_oc.field_102204_Vb
		// @17: getfield int game.C_100302_ka.field_101879_Rb
		// @1A: if_icmpne @21
		// @1D: goto @4B
		// @20: athrow
		// @21: aload_0
		// @22: getfield int game.C_100231_oc.field_102202_ic
		// @25: ifle @36
		// @28: aload_0
		// @29: dup
		// @2A: getfield int game.C_100231_oc.field_102202_ic
		// @2D: iconst_1
		// @2E: isub
		// @2F: putfield int game.C_100231_oc.field_102202_ic
		// @32: goto @36
		// @35: athrow
		// @36: aload_0
		// @37: getfield int game.C_100231_oc.field_102202_ic
		// @3A: iconst_m1
		// @3B: ixor
		// @3C: iconst_m1
		// @3D: if_icmpeq @44
		// @40: goto @4B
		// @43: athrow
		// @44: aload_0
		// @45: iconst_3
		// @46: putfield int game.C_100231_oc.field_102202_ic
		// @49: iconst_1
		// @4A: ireturn
		// @4B: iconst_0
		// @4C: ireturn
		// @4D: astore_2
		// @4E: aload_2
		// @4F: new java.lang.StringBuilder
		// @52: dup
		// @53: invokespecial java.lang.StringBuilder.<init>()void
		// @56: getstatic java.lang.String[] game.C_100231_oc.field_102207_lc
		// @59: iconst_0
		// @5A: aaload
		// @5B: invokevirtual java.lang.StringBuilder.append(java.lang.String)java.lang.StringBuilder
		// @5E: iload_1
		// @5F: invokevirtual java.lang.StringBuilder.append(int)java.lang.StringBuilder
		// @62: bipush 41 (0x29)
		// @64: invokevirtual java.lang.StringBuilder.append(char)java.lang.StringBuilder
		// @67: invokevirtual java.lang.StringBuilder.toString()java.lang.String
		// @6A: invokestatic game.C_100181_cf.func_105695_a(java.lang.Throwable, java.lang.String)game.C_100170_cm
		// @6D: athrow
	}
	
	static final boolean func_102187_a(int arg0, int[] arg1)
	{
		// @000: getstatic int game.SteelSentinels.field_105275_O
		// @003: istore #7
		// @005: getstatic game.C_100268_mk game.C_100066_dl.field_101642_t
		// @008: getstatic game.C_100268_mk game.C_100046_vk.field_102763_sb
		// @00B: if_acmpeq @010
		// @00E: iconst_0
		// @00F: ireturn
		// @010: bipush 92 (0x5C)
		// @012: invokestatic game.C_100198_qn.func_105828_a(byte)long
		// @015: lstore_2
		// @016: iconst_0
		// @017: getstatic int game.C_100275_na.field_103096_p
		// @01A: if_icmpeq @0B0
		// @01D: iconst_0
		// @01E: getstatic int game.C_100128_ca.field_102808_S
		// @021: if_icmple @0B0
		// @024: goto @028
		// @027: athrow
		// @028: getstatic game.C_100202_qi game.C_100139_tb.field_100532_B
		// @02B: bipush 115 (0x73)
		// @02D: invokevirtual game.C_100202_qi.func_105899_c(int)game.C_100158_da
		// @030: checkcast game.C_100165_sh
		// @033: astore #4
		// @035: aload #4
		// @037: ifnull @0B0
		// @03A: aload #4
		// @03C: getfield long game.C_100165_sh.field_100775_l
		// @03F: lload_2
		// @040: lcmp
		// @041: iflt @04C
		// @044: goto @048
		// @047: athrow
		// @048: goto @0B0
		// @04B: athrow
		// @04C: aload #4
		// @04E: bipush 45 (0x2D)
		// @050: invokevirtual game.C_100165_sh.func_100583_c(int)void
		// @053: aload #4
		// @055: getfield byte[] game.C_100165_sh.field_100777_j
		// @058: arraylength
		// @059: putstatic int game.C_100056_de.field_103194_Y
		// @05C: getstatic game.C_100278_nd game.C_100288_jn.field_106839_f
		// @05F: iconst_0
		// @060: putfield int game.C_100278_nd.field_101177_n
		// @063: iconst_0
		// @064: istore #5
		// @066: getstatic int game.C_100056_de.field_103194_Y
		// @069: iconst_m1
		// @06A: ixor
		// @06B: iload #5
		// @06D: iconst_m1
		// @06E: ixor
		// @06F: if_icmpge @094
		// @072: getstatic game.C_100278_nd game.C_100288_jn.field_106839_f
		// @075: getfield byte[] game.C_100278_nd.field_101179_l
		// @078: iload #5
		// @07A: aload #4
		// @07C: getfield byte[] game.C_100165_sh.field_100777_j
		// @07F: iload #5
		// @081: baload
		// @082: bastore
		// @083: iinc #5 +1
		// @086: iload #7
		// @088: ifne @0AE
		// @08B: iload #7
		// @08D: ifeq @066
		// @090: goto @094
		// @093: athrow
		// @094: getstatic int game.C_100061_dh.field_101980_gc
		// @097: putstatic int game.C_100119_ua.field_104907_k
		// @09A: getstatic int game.C_100041_wf.field_104107_c
		// @09D: putstatic int game.C_100061_dh.field_101980_gc
		// @0A0: getstatic int game.C_100299_kd.field_107051_z
		// @0A3: putstatic int game.C_100041_wf.field_104107_c
		// @0A6: aload #4
		// @0A8: getfield int game.C_100165_sh.field_100770_r
		// @0AB: putstatic int game.C_100299_kd.field_107051_z
		// @0AE: iconst_1
		// @0AF: ireturn
		// @0B0: iload_0
		// @0B1: sipush 13118 (0x333E)
		// @0B4: if_icmpeq @0B9
		// @0B7: iconst_0
		// @0B8: ireturn
		// @0B9: iconst_0
		// @0BA: getstatic int game.C_100128_ca.field_102808_S
		// @0BD: if_icmple @0FA
		// @0C0: getstatic game.C_100278_nd game.C_100288_jn.field_106839_f
		// @0C3: iconst_0
		// @0C4: putfield int game.C_100278_nd.field_101177_n
		// @0C7: iconst_1
		// @0C8: bipush 51 (0x33)
		// @0CA: invokestatic game.C_100114_q.func_100483_a(int, byte)boolean
		// @0CD: iload #7
		// @0CF: ifne @0FE
		// @0D2: goto @0D6
		// @0D5: athrow
		// @0D6: ifne @0DF
		// @0D9: goto @0DD
		// @0DC: athrow
		// @0DD: iconst_0
		// @0DE: ireturn
		// @0DF: getstatic game.C_100278_nd game.C_100288_jn.field_106839_f
		// @0E2: sipush 255 (0x00FF)
		// @0E5: invokevirtual game.C_100278_nd.func_101194_o(int)int
		// @0E8: putstatic int game.C_100128_ca.field_102808_S
		// @0EB: getstatic game.C_100278_nd game.C_100288_jn.field_106839_f
		// @0EE: iconst_0
		// @0EF: putfield int game.C_100278_nd.field_101177_n
		// @0F2: aload_1
		// @0F3: getstatic int game.C_100128_ca.field_102808_S
		// @0F6: iaload
		// @0F7: putstatic int game.C_100056_de.field_103194_Y
		// @0FA: iconst_0
		// @0FB: invokestatic game.C_100149_bi.func_105150_b(int)boolean
		// @0FE: ifne @103
		// @101: iconst_0
		// @102: ireturn
		// @103: iconst_m1
		// @104: getstatic int game.C_100275_na.field_103096_p
		// @107: iconst_m1
		// @108: ixor
		// @109: if_icmpne @12A
		// @10C: getstatic int game.C_100061_dh.field_101980_gc
		// @10F: putstatic int game.C_100119_ua.field_104907_k
		// @112: getstatic int game.C_100041_wf.field_104107_c
		// @115: putstatic int game.C_100061_dh.field_101980_gc
		// @118: getstatic int game.C_100299_kd.field_107051_z
		// @11B: putstatic int game.C_100041_wf.field_104107_c
		// @11E: getstatic int game.C_100128_ca.field_102808_S
		// @121: putstatic int game.C_100299_kd.field_107051_z
		// @124: iconst_m1
		// @125: putstatic int game.C_100128_ca.field_102808_S
		// @128: iconst_1
		// @129: ireturn
		// @12A: getstatic int game.C_100275_na.field_103096_p
		// @12D: istore #4
		// @12F: getstatic double game.C_100000_gd.field_100357_e
		// @132: dconst_0
		// @133: dcmpl
		// @134: ifne @13B
		// @137: goto @154
		// @13A: athrow
		// @13B: iload #4
		// @13D: i2d
		// @13E: getstatic java.util.Random game.C_100067_vd.field_104322_k
		// @141: invokevirtual java.util.Random.nextGaussian()double
		// @144: getstatic double game.C_100000_gd.field_100357_e
		// @147: dmul
		// @148: dadd
		// @149: d2i
		// @14A: istore #4
		// @14C: iload #4
		// @14E: ifge @154
		// @151: iconst_0
		// @152: istore #4
		// @154: new game.C_100165_sh
		// @157: dup
		// @158: iload #4
		// @15A: i2l
		// @15B: lload_2
		// @15C: ladd
		// @15D: getstatic int game.C_100128_ca.field_102808_S
		// @160: getstatic int game.C_100056_de.field_103194_Y
		// @163: newarray byte[]
		// @165: invokespecial game.C_100165_sh.<init>(long, int, byte[])void
		// @168: astore #5
		// @16A: iconst_0
		// @16B: istore #6
		// @16D: iload #6
		// @16F: iconst_m1
		// @170: ixor
		// @171: getstatic int game.C_100056_de.field_103194_Y
		// @174: iconst_m1
		// @175: ixor
		// @176: if_icmple @19B
		// @179: aload #5
		// @17B: getfield byte[] game.C_100165_sh.field_100777_j
		// @17E: iload #6
		// @180: getstatic game.C_100278_nd game.C_100288_jn.field_106839_f
		// @183: getfield byte[] game.C_100278_nd.field_101179_l
		// @186: iload #6
		// @188: baload
		// @189: bastore
		// @18A: iinc #6 +1
		// @18D: iload #7
		// @18F: ifne @1A9
		// @192: iload #7
		// @194: ifeq @16D
		// @197: goto @19B
		// @19A: athrow
		// @19B: getstatic game.C_100202_qi game.C_100139_tb.field_100532_B
		// @19E: bipush 125 (0x7D)
		// @1A0: aload #5
		// @1A2: invokevirtual game.C_100202_qi.func_105901_a(int, game.C_100158_da)void
		// @1A5: iconst_m1
		// @1A6: putstatic int game.C_100128_ca.field_102808_S
		// @1A9: goto @0B9
		// @1AC: astore_2
		// @1AD: aload_2
		// @1AE: new java.lang.StringBuilder
		// @1B1: dup
		// @1B2: invokespecial java.lang.StringBuilder.<init>()void
		// @1B5: getstatic java.lang.String[] game.C_100231_oc.field_102207_lc
		// @1B8: iconst_4
		// @1B9: aaload
		// @1BA: invokevirtual java.lang.StringBuilder.append(java.lang.String)java.lang.StringBuilder
		// @1BD: iload_0
		// @1BE: invokevirtual java.lang.StringBuilder.append(int)java.lang.StringBuilder
		// @1C1: bipush 44 (0x2C)
		// @1C3: invokevirtual java.lang.StringBuilder.append(char)java.lang.StringBuilder
		// @1C6: aload_1
		// @1C7: ifnull @1D3
		// @1CA: getstatic java.lang.String[] game.C_100231_oc.field_102207_lc
		// @1CD: iconst_5
		// @1CE: aaload
		// @1CF: goto @1D9
		// @1D2: athrow
		// @1D3: getstatic java.lang.String[] game.C_100231_oc.field_102207_lc
		// @1D6: bipush 6 (0x06)
		// @1D8: aaload
		// @1D9: invokevirtual java.lang.StringBuilder.append(java.lang.String)java.lang.StringBuilder
		// @1DC: bipush 41 (0x29)
		// @1DE: invokevirtual java.lang.StringBuilder.append(char)java.lang.StringBuilder
		// @1E1: invokevirtual java.lang.StringBuilder.toString()java.lang.String
		// @1E4: invokestatic game.C_100181_cf.func_105695_a(java.lang.Throwable, java.lang.String)game.C_100170_cm
		// @1E7: athrow
	}
	
	final void func_102184_a(int arg0, int arg1, byte arg2, int arg3, int arg4, int arg5, int arg6, int arg7)
	{
		// @00: iload_3
		// @01: bipush -25 (0xE7)
		// @03: if_icmplt @07
		// @06: return
		// @07: aload_0
		// @08: iload #8
		// @0A: putfield int game.C_100231_oc.field_101848_lb
		// @0D: aload_0
		// @0E: iload #5
		// @10: putfield int game.C_100231_oc.field_101886_Kb
		// @13: aload_0
		// @14: iload #4
		// @16: putfield int game.C_100231_oc.field_101841_Pb
		// @19: aload_0
		// @1A: iload #7
		// @1C: putfield int game.C_100231_oc.field_101880_Gb
		// @1F: aload_0
		// @20: iload #6
		// @22: bipush -63 (0xC1)
		// @24: iload_1
		// @25: iload_2
		// @26: invokevirtual game.C_100231_oc.func_102179_a(int, byte, int, int)void
		// @29: goto @94
		// @2C: astore #9
		// @2E: aload #9
		// @30: new java.lang.StringBuilder
		// @33: dup
		// @34: invokespecial java.lang.StringBuilder.<init>()void
		// @37: getstatic java.lang.String[] game.C_100231_oc.field_102207_lc
		// @3A: bipush 7 (0x07)
		// @3C: aaload
		// @3D: invokevirtual java.lang.StringBuilder.append(java.lang.String)java.lang.StringBuilder
		// @40: iload_1
		// @41: invokevirtual java.lang.StringBuilder.append(int)java.lang.StringBuilder
		// @44: bipush 44 (0x2C)
		// @46: invokevirtual java.lang.StringBuilder.append(char)java.lang.StringBuilder
		// @49: iload_2
		// @4A: invokevirtual java.lang.StringBuilder.append(int)java.lang.StringBuilder
		// @4D: bipush 44 (0x2C)
		// @4F: invokevirtual java.lang.StringBuilder.append(char)java.lang.StringBuilder
		// @52: iload_3
		// @53: invokevirtual java.lang.StringBuilder.append(int)java.lang.StringBuilder
		// @56: bipush 44 (0x2C)
		// @58: invokevirtual java.lang.StringBuilder.append(char)java.lang.StringBuilder
		// @5B: iload #4
		// @5D: invokevirtual java.lang.StringBuilder.append(int)java.lang.StringBuilder
		// @60: bipush 44 (0x2C)
		// @62: invokevirtual java.lang.StringBuilder.append(char)java.lang.StringBuilder
		// @65: iload #5
		// @67: invokevirtual java.lang.StringBuilder.append(int)java.lang.StringBuilder
		// @6A: bipush 44 (0x2C)
		// @6C: invokevirtual java.lang.StringBuilder.append(char)java.lang.StringBuilder
		// @6F: iload #6
		// @71: invokevirtual java.lang.StringBuilder.append(int)java.lang.StringBuilder
		// @74: bipush 44 (0x2C)
		// @76: invokevirtual java.lang.StringBuilder.append(char)java.lang.StringBuilder
		// @79: iload #7
		// @7B: invokevirtual java.lang.StringBuilder.append(int)java.lang.StringBuilder
		// @7E: bipush 44 (0x2C)
		// @80: invokevirtual java.lang.StringBuilder.append(char)java.lang.StringBuilder
		// @83: iload #8
		// @85: invokevirtual java.lang.StringBuilder.append(int)java.lang.StringBuilder
		// @88: bipush 41 (0x29)
		// @8A: invokevirtual java.lang.StringBuilder.append(char)java.lang.StringBuilder
		// @8D: invokevirtual java.lang.StringBuilder.toString()java.lang.String
		// @90: invokestatic game.C_100181_cf.func_105695_a(java.lang.Throwable, java.lang.String)game.C_100170_cm
		// @93: athrow
		// @94: return
	}
	
	final boolean func_102181_l(int arg0)
	{
		// @00: iload_1
		// @01: sipush 18099 (0x46B3)
		// @04: if_icmpeq @09
		// @07: iconst_1
		// @08: ireturn
		// @09: aload_0
		// @0A: getfield game.C_100302_ka game.C_100231_oc.field_102206_ac
		// @0D: getfield int game.C_100302_ka.field_101854_N
		// @10: iconst_m1
		// @11: ixor
		// @12: iconst_m1
		// @13: if_icmpeq @1E
		// @16: aload_0
		// @17: bipush 20 (0x14)
		// @19: putfield int game.C_100231_oc.field_102202_ic
		// @1C: iconst_1
		// @1D: ireturn
		// @1E: iconst_0
		// @1F: aload_0
		// @20: getfield game.C_100302_ka game.C_100231_oc.field_102206_ac
		// @23: getfield int game.C_100302_ka.field_101879_Rb
		// @26: if_icmpeq @5A
		// @29: aload_0
		// @2A: getfield int game.C_100231_oc.field_102202_ic
		// @2D: iconst_m1
		// @2E: ixor
		// @2F: iconst_m1
		// @30: if_icmpge @45
		// @33: goto @37
		// @36: athrow
		// @37: aload_0
		// @38: dup
		// @39: getfield int game.C_100231_oc.field_102202_ic
		// @3C: iconst_1
		// @3D: isub
		// @3E: putfield int game.C_100231_oc.field_102202_ic
		// @41: goto @45
		// @44: athrow
		// @45: iconst_m1
		// @46: aload_0
		// @47: getfield int game.C_100231_oc.field_102202_ic
		// @4A: iconst_m1
		// @4B: ixor
		// @4C: if_icmpeq @53
		// @4F: goto @5A
		// @52: athrow
		// @53: aload_0
		// @54: iconst_3
		// @55: putfield int game.C_100231_oc.field_102202_ic
		// @58: iconst_1
		// @59: ireturn
		// @5A: iconst_0
		// @5B: ireturn
		// @5C: astore_2
		// @5D: aload_2
		// @5E: new java.lang.StringBuilder
		// @61: dup
		// @62: invokespecial java.lang.StringBuilder.<init>()void
		// @65: getstatic java.lang.String[] game.C_100231_oc.field_102207_lc
		// @68: bipush 13 (0x0D)
		// @6A: aaload
		// @6B: invokevirtual java.lang.StringBuilder.append(java.lang.String)java.lang.StringBuilder
		// @6E: iload_1
		// @6F: invokevirtual java.lang.StringBuilder.append(int)java.lang.StringBuilder
		// @72: bipush 41 (0x29)
		// @74: invokevirtual java.lang.StringBuilder.append(char)java.lang.StringBuilder
		// @77: invokevirtual java.lang.StringBuilder.toString()java.lang.String
		// @7A: invokestatic game.C_100181_cf.func_105695_a(java.lang.Throwable, java.lang.String)game.C_100170_cm
		// @7D: athrow
	}
	
	C_100231_oc(long arg0, C_100302_ka arg1, C_100302_ka arg2, C_100302_ka arg3, C_100302_ka arg4)
	{
		// @000: aload_0
		// @001: lload_1
		// @002: aconst_null
		// @003: invokespecial game.C_100302_ka.<init>(long, game.C_100302_ka)void
		// @006: aload_0
		// @007: new game.C_100302_ka
		// @00A: dup
		// @00B: lconst_0
		// @00C: aload_3
		// @00D: invokespecial game.C_100302_ka.<init>(long, game.C_100302_ka)void
		// @010: putfield game.C_100302_ka game.C_100231_oc.field_102204_Vb
		// @013: aload_0
		// @014: new game.C_100302_ka
		// @017: dup
		// @018: lconst_0
		// @019: aload #4
		// @01B: invokespecial game.C_100302_ka.<init>(long, game.C_100302_ka)void
		// @01E: putfield game.C_100302_ka game.C_100231_oc.field_102206_ac
		// @021: aload_0
		// @022: bipush -93 (0xA3)
		// @024: aload_0
		// @025: getfield game.C_100302_ka game.C_100231_oc.field_102204_Vb
		// @028: invokevirtual game.C_100231_oc.func_101824_b(int, game.C_100302_ka)void
		// @02B: aload_0
		// @02C: bipush -127 (0x81)
		// @02E: aload_0
		// @02F: getfield game.C_100302_ka game.C_100231_oc.field_102206_ac
		// @032: invokevirtual game.C_100231_oc.func_101824_b(int, game.C_100302_ka)void
		// @035: aload_0
		// @036: new game.C_100302_ka
		// @039: dup
		// @03A: lconst_0
		// @03B: aconst_null
		// @03C: invokespecial game.C_100302_ka.<init>(long, game.C_100302_ka)void
		// @03F: putfield game.C_100302_ka game.C_100231_oc.field_102199_fc
		// @042: aload_0
		// @043: bipush -70 (0xBA)
		// @045: aload_0
		// @046: getfield game.C_100302_ka game.C_100231_oc.field_102199_fc
		// @049: invokevirtual game.C_100231_oc.func_101824_b(int, game.C_100302_ka)void
		// @04C: aload_0
		// @04D: new game.C_100302_ka
		// @050: dup
		// @051: lconst_0
		// @052: aload #5
		// @054: invokespecial game.C_100302_ka.<init>(long, game.C_100302_ka)void
		// @057: putfield game.C_100302_ka game.C_100231_oc.field_102203_Ub
		// @05A: aload_0
		// @05B: new game.C_100302_ka
		// @05E: dup
		// @05F: lconst_0
		// @060: aload #5
		// @062: invokespecial game.C_100302_ka.<init>(long, game.C_100302_ka)void
		// @065: putfield game.C_100302_ka game.C_100231_oc.field_102201_jc
		// @068: aload_0
		// @069: getfield game.C_100302_ka game.C_100231_oc.field_102201_jc
		// @06C: iconst_1
		// @06D: putfield boolean game.C_100302_ka.field_101881_yb
		// @070: aload_0
		// @071: getfield game.C_100302_ka game.C_100231_oc.field_102203_Ub
		// @074: astore #7
		// @076: aload #7
		// @078: iconst_1
		// @079: putfield boolean game.C_100302_ka.field_101881_yb
		// @07C: aload_0
		// @07D: getfield game.C_100302_ka game.C_100231_oc.field_102199_fc
		// @080: bipush -105 (0x97)
		// @082: aload_0
		// @083: getfield game.C_100302_ka game.C_100231_oc.field_102203_Ub
		// @086: invokevirtual game.C_100302_ka.func_101824_b(int, game.C_100302_ka)void
		// @089: aload_0
		// @08A: getfield game.C_100302_ka game.C_100231_oc.field_102199_fc
		// @08D: bipush -88 (0xA8)
		// @08F: aload_0
		// @090: getfield game.C_100302_ka game.C_100231_oc.field_102201_jc
		// @093: invokevirtual game.C_100302_ka.func_101824_b(int, game.C_100302_ka)void
		// @096: aload_0
		// @097: new game.C_100302_ka
		// @09A: dup
		// @09B: lconst_0
		// @09C: aload #6
		// @09E: invokespecial game.C_100302_ka.<init>(long, game.C_100302_ka)void
		// @0A1: putfield game.C_100302_ka game.C_100231_oc.field_102197_hc
		// @0A4: aload_0
		// @0A5: getfield game.C_100302_ka game.C_100231_oc.field_102197_hc
		// @0A8: iconst_1
		// @0A9: putfield boolean game.C_100302_ka.field_101888_Bb
		// @0AC: aload_0
		// @0AD: getfield game.C_100302_ka game.C_100231_oc.field_102199_fc
		// @0B0: bipush -111 (0x91)
		// @0B2: aload_0
		// @0B3: getfield game.C_100302_ka game.C_100231_oc.field_102197_hc
		// @0B6: invokevirtual game.C_100302_ka.func_101824_b(int, game.C_100302_ka)void
		// @0B9: goto @14F
		// @0BC: astore #7
		// @0BE: aload #7
		// @0C0: new java.lang.StringBuilder
		// @0C3: dup
		// @0C4: invokespecial java.lang.StringBuilder.<init>()void
		// @0C7: getstatic java.lang.String[] game.C_100231_oc.field_102207_lc
		// @0CA: bipush 14 (0x0E)
		// @0CC: aaload
		// @0CD: invokevirtual java.lang.StringBuilder.append(java.lang.String)java.lang.StringBuilder
		// @0D0: lload_1
		// @0D1: invokevirtual java.lang.StringBuilder.append(long)java.lang.StringBuilder
		// @0D4: bipush 44 (0x2C)
		// @0D6: invokevirtual java.lang.StringBuilder.append(char)java.lang.StringBuilder
		// @0D9: aload_3
		// @0DA: ifnull @0E6
		// @0DD: getstatic java.lang.String[] game.C_100231_oc.field_102207_lc
		// @0E0: iconst_5
		// @0E1: aaload
		// @0E2: goto @0EC
		// @0E5: athrow
		// @0E6: getstatic java.lang.String[] game.C_100231_oc.field_102207_lc
		// @0E9: bipush 6 (0x06)
		// @0EB: aaload
		// @0EC: invokevirtual java.lang.StringBuilder.append(java.lang.String)java.lang.StringBuilder
		// @0EF: bipush 44 (0x2C)
		// @0F1: invokevirtual java.lang.StringBuilder.append(char)java.lang.StringBuilder
		// @0F4: aload #4
		// @0F6: ifnull @102
		// @0F9: getstatic java.lang.String[] game.C_100231_oc.field_102207_lc
		// @0FC: iconst_5
		// @0FD: aaload
		// @0FE: goto @108
		// @101: athrow
		// @102: getstatic java.lang.String[] game.C_100231_oc.field_102207_lc
		// @105: bipush 6 (0x06)
		// @107: aaload
		// @108: invokevirtual java.lang.StringBuilder.append(java.lang.String)java.lang.StringBuilder
		// @10B: bipush 44 (0x2C)
		// @10D: invokevirtual java.lang.StringBuilder.append(char)java.lang.StringBuilder
		// @110: aload #5
		// @112: ifnull @11E
		// @115: getstatic java.lang.String[] game.C_100231_oc.field_102207_lc
		// @118: iconst_5
		// @119: aaload
		// @11A: goto @124
		// @11D: athrow
		// @11E: getstatic java.lang.String[] game.C_100231_oc.field_102207_lc
		// @121: bipush 6 (0x06)
		// @123: aaload
		// @124: invokevirtual java.lang.StringBuilder.append(java.lang.String)java.lang.StringBuilder
		// @127: bipush 44 (0x2C)
		// @129: invokevirtual java.lang.StringBuilder.append(char)java.lang.StringBuilder
		// @12C: aload #6
		// @12E: ifnull @13A
		// @131: getstatic java.lang.String[] game.C_100231_oc.field_102207_lc
		// @134: iconst_5
		// @135: aaload
		// @136: goto @140
		// @139: athrow
		// @13A: getstatic java.lang.String[] game.C_100231_oc.field_102207_lc
		// @13D: bipush 6 (0x06)
		// @13F: aaload
		// @140: invokevirtual java.lang.StringBuilder.append(java.lang.String)java.lang.StringBuilder
		// @143: bipush 41 (0x29)
		// @145: invokevirtual java.lang.StringBuilder.append(char)java.lang.StringBuilder
		// @148: invokevirtual java.lang.StringBuilder.toString()java.lang.String
		// @14B: invokestatic game.C_100181_cf.func_105695_a(java.lang.Throwable, java.lang.String)game.C_100170_cm
		// @14E: athrow
		// @14F: return
	}
	
	final boolean func_102188_b(boolean arg0)
	{
		// @00: aload_0
		// @01: getfield game.C_100302_ka game.C_100231_oc.field_102201_jc
		// @04: getfield int game.C_100302_ka.field_101854_N
		// @07: iconst_m1
		// @08: ixor
		// @09: iconst_m1
		// @0A: if_icmpeq @15
		// @0D: aload_0
		// @0E: bipush 20 (0x14)
		// @10: putfield int game.C_100231_oc.field_102202_ic
		// @13: iconst_1
		// @14: ireturn
		// @15: iload_1
		// @16: ifeq @1B
		// @19: iconst_0
		// @1A: ireturn
		// @1B: aload_0
		// @1C: getfield game.C_100302_ka game.C_100231_oc.field_102201_jc
		// @1F: getfield int game.C_100302_ka.field_101879_Rb
		// @22: iconst_m1
		// @23: ixor
		// @24: iconst_m1
		// @25: if_icmpeq @83
		// @28: aload_0
		// @29: getfield int game.C_100231_oc.field_102202_ic
		// @2C: ifle @41
		// @2F: goto @33
		// @32: athrow
		// @33: aload_0
		// @34: dup
		// @35: getfield int game.C_100231_oc.field_102202_ic
		// @38: iconst_1
		// @39: isub
		// @3A: putfield int game.C_100231_oc.field_102202_ic
		// @3D: goto @41
		// @40: athrow
		// @41: iconst_0
		// @42: aload_0
		// @43: getfield int game.C_100231_oc.field_102202_ic
		// @46: if_icmpne @83
		// @49: getstatic int game.C_100338_jc.field_105370_l
		// @4C: iconst_m1
		// @4D: ixor
		// @4E: aload_0
		// @4F: getfield game.C_100302_ka game.C_100231_oc.field_102197_hc
		// @52: getfield int game.C_100302_ka.field_101835_xb
		// @55: aload_0
		// @56: getfield game.C_100302_ka game.C_100231_oc.field_102197_hc
		// @59: getfield int game.C_100302_ka.field_101843_Tb
		// @5C: ineg
		// @5D: isub
		// @5E: aload_0
		// @5F: getfield game.C_100302_ka game.C_100231_oc.field_102197_hc
		// @62: getfield int game.C_100302_ka.field_101848_lb
		// @65: ineg
		// @66: aload_0
		// @67: getfield game.C_100302_ka game.C_100231_oc.field_102197_hc
		// @6A: getfield int game.C_100302_ka.field_101832_tb
		// @6D: isub
		// @6E: isub
		// @6F: iconst_m1
		// @70: ixor
		// @71: if_icmple @7C
		// @74: goto @78
		// @77: athrow
		// @78: goto @83
		// @7B: athrow
		// @7C: aload_0
		// @7D: iconst_3
		// @7E: putfield int game.C_100231_oc.field_102202_ic
		// @81: iconst_1
		// @82: ireturn
		// @83: iconst_0
		// @84: ireturn
		// @85: astore_2
		// @86: aload_2
		// @87: new java.lang.StringBuilder
		// @8A: dup
		// @8B: invokespecial java.lang.StringBuilder.<init>()void
		// @8E: getstatic java.lang.String[] game.C_100231_oc.field_102207_lc
		// @91: bipush 12 (0x0C)
		// @93: aaload
		// @94: invokevirtual java.lang.StringBuilder.append(java.lang.String)java.lang.StringBuilder
		// @97: iload_1
		// @98: invokevirtual java.lang.StringBuilder.append(boolean)java.lang.StringBuilder
		// @9B: bipush 41 (0x29)
		// @9D: invokevirtual java.lang.StringBuilder.append(char)java.lang.StringBuilder
		// @A0: invokevirtual java.lang.StringBuilder.toString()java.lang.String
		// @A3: invokestatic game.C_100181_cf.func_105695_a(java.lang.Throwable, java.lang.String)game.C_100170_cm
		// @A6: athrow
	}
	
	static
	{
		// @00: bipush 15 (0x0F)
		// @02: anewarray java.lang.String
		// @05: dup
		// @06: iconst_0
		// @07: ldc "\u000eAD\u001b2"
		// @09: invokestatic game.C_100231_oc.func_102182_z(java.lang.String)char[]
		// @0C: invokestatic game.C_100231_oc.func_102180_z(char[])java.lang.String
		// @0F: aastore
		// @10: dup
		// @11: iconst_1
		// @12: ldc "\u000eAD\u00032"
		// @14: invokestatic game.C_100231_oc.func_102182_z(java.lang.String)char[]
		// @17: invokestatic game.C_100231_oc.func_102180_z(char[])java.lang.String
		// @1A: aastore
		// @1B: dup
		// @1C: iconst_2
		// @1D: ldc "\u000eAD\u00132"
		// @1F: invokestatic game.C_100231_oc.func_102182_z(java.lang.String)char[]
		// @22: invokestatic game.C_100231_oc.func_102180_z(char[])java.lang.String
		// @25: aastore
		// @26: dup
		// @27: iconst_3
		// @28: ldc "\u000eAD\u00162"
		// @2A: invokestatic game.C_100231_oc.func_102182_z(java.lang.String)char[]
		// @2D: invokestatic game.C_100231_oc.func_102180_z(char[])java.lang.String
		// @30: aastore
		// @31: dup
		// @32: iconst_4
		// @33: ldc "\u000eAD\u00002"
		// @35: invokestatic game.C_100231_oc.func_102182_z(java.lang.String)char[]
		// @38: invokestatic game.C_100231_oc.func_102180_z(char[])java.lang.String
		// @3B: aastore
		// @3C: dup
		// @3D: iconst_5
		// @3E: ldc "\u001a\u000cD|g"
		// @40: invokestatic game.C_100231_oc.func_102182_z(java.lang.String)char[]
		// @43: invokestatic game.C_100231_oc.func_102180_z(char[])java.lang.String
		// @46: aastore
		// @47: dup
		// @48: bipush 6 (0x06)
		// @4A: ldc "\u000fW\u0006>"
		// @4C: invokestatic game.C_100231_oc.func_102182_z(java.lang.String)char[]
		// @4F: invokestatic game.C_100231_oc.func_102180_z(char[])java.lang.String
		// @52: aastore
		// @53: dup
		// @54: bipush 7 (0x07)
		// @56: ldc "\u000eAD\u00172"
		// @58: invokestatic game.C_100231_oc.func_102182_z(java.lang.String)char[]
		// @5B: invokestatic game.C_100231_oc.func_102180_z(char[])java.lang.String
		// @5E: aastore
		// @5F: dup
		// @60: bipush 8 (0x08)
		// @62: ldc "\u000eAD\u001a2"
		// @64: invokestatic game.C_100231_oc.func_102182_z(java.lang.String)char[]
		// @67: invokestatic game.C_100231_oc.func_102180_z(char[])java.lang.String
		// @6A: aastore
		// @6B: dup
		// @6C: bipush 9 (0x09)
		// @6E: ldc "\u000eAD\u00142"
		// @70: invokestatic game.C_100231_oc.func_102182_z(java.lang.String)char[]
		// @73: invokestatic game.C_100231_oc.func_102180_z(char[])java.lang.String
		// @76: aastore
		// @77: dup
		// @78: bipush 10 (0x0A)
		// @7A: ldc "\u000eAD\u00012"
		// @7C: invokestatic game.C_100231_oc.func_102182_z(java.lang.String)char[]
		// @7F: invokestatic game.C_100231_oc.func_102180_z(char[])java.lang.String
		// @82: aastore
		// @83: dup
		// @84: bipush 11 (0x0B)
		// @86: ldc "\u000eAD\u00152"
		// @88: invokestatic game.C_100231_oc.func_102182_z(java.lang.String)char[]
		// @8B: invokestatic game.C_100231_oc.func_102180_z(char[])java.lang.String
		// @8E: aastore
		// @8F: dup
		// @90: bipush 12 (0x0C)
		// @92: ldc "\u000eAD\u00112"
		// @94: invokestatic game.C_100231_oc.func_102182_z(java.lang.String)char[]
		// @97: invokestatic game.C_100231_oc.func_102180_z(char[])java.lang.String
		// @9A: aastore
		// @9B: dup
		// @9C: bipush 13 (0x0D)
		// @9E: ldc "\u000eAD\u00102"
		// @A0: invokestatic game.C_100231_oc.func_102182_z(java.lang.String)char[]
		// @A3: invokestatic game.C_100231_oc.func_102180_z(char[])java.lang.String
		// @A6: aastore
		// @A7: dup
		// @A8: bipush 14 (0x0E)
		// @AA: ldc "\u000eADns\u000fK\u001el2"
		// @AC: invokestatic game.C_100231_oc.func_102182_z(java.lang.String)char[]
		// @AF: invokestatic game.C_100231_oc.func_102180_z(char[])java.lang.String
		// @B2: aastore
		// @B3: putstatic java.lang.String[] game.C_100231_oc.field_102207_lc
		// @B6: ldc " n>"
		// @B8: invokestatic game.C_100231_oc.func_102182_z(java.lang.String)char[]
		// @BB: invokestatic game.C_100231_oc.func_102180_z(char[])java.lang.String
		// @BE: putstatic java.lang.String game.C_100231_oc.field_102209_cc
		// @C1: iconst_0
		// @C2: putstatic int game.C_100231_oc.field_102200_Wb
		// @C5: new game.C_100202_qi
		// @C8: dup
		// @C9: invokespecial game.C_100202_qi.<init>()void
		// @CC: putstatic game.C_100202_qi game.C_100231_oc.field_102193_gc
		// @CF: iconst_m1
		// @D0: putstatic int game.C_100231_oc.field_102198_ec
		// @D3: ldc "8M\u001f :\u0008E\u0004=h\u0004\u0002\u0006;i\u0015\u0002\u0003!:\u0007W\u0006>4Ao\u000b*:\u000eDJc*Q\u0002\u0002;nO"
		// @D5: invokestatic game.C_100231_oc.func_102182_z(java.lang.String)char[]
		// @D8: invokestatic game.C_100231_oc.func_102180_z(char[])java.lang.String
		// @DB: putstatic java.lang.String game.C_100231_oc.field_102195_Xb
		// @DE: sipush 1024 (0x0400)
		// @E1: newarray int[]
		// @E3: putstatic int[] game.C_100231_oc.field_102192_dc
		// @E6: return
	}
	
	private static char[] func_102182_z(String arg0)
	{
		// @00: aload_0
		// @01: invokevirtual java.lang.String.toCharArray()char[]
		// @04: dup
		// @05: arraylength
		// @06: iconst_2
		// @07: if_icmpge @13
		// @0A: dup
		// @0B: iconst_0
		// @0C: dup2
		// @0D: caload
		// @0E: bipush 26 (0x1A)
		// @10: ixor
		// @11: i2c
		// @12: castore
		// @13: areturn
	}
	
	private static String func_102180_z(char[] arg0)
	{
		// @00: aload_0
		// @01: dup
		// @02: arraylength
		// @03: swap
		// @04: iconst_0
		// @05: istore_1
		// @06: goto @4C
		// @09: dup
		// @0A: iload_1
		// @0B: dup2
		// @0C: caload
		// @0D: iload_1
		// @0E: iconst_5
		// @0F: irem
		// @10: tableswitch def: @44, for 0: @30, for 1: @35, for 2: @3A, for 3: @3F
		// @30: bipush 97 (0x61)
		// @32: goto @46
		// @35: bipush 34 (0x22)
		// @37: goto @46
		// @3A: bipush 106 (0x6A)
		// @3C: goto @46
		// @3F: bipush 82 (0x52)
		// @41: goto @46
		// @44: bipush 26 (0x1A)
		// @46: ixor
		// @47: i2c
		// @48: castore
		// @49: iinc #1 +1
		// @4C: swap
		// @4D: dup_x1
		// @4E: iload_1
		// @4F: if_icmpgt @09
		// @52: new java.lang.String
		// @55: dup_x1
		// @56: swap
		// @57: invokespecial java.lang.String.<init>(char[])void
		// @5A: invokevirtual java.lang.String.intern()java.lang.String
		// @5D: areturn
	}
}
