package game;

final class C_100191_rg extends C_100158_da
{
	byte[] field_100846_l;
	static C_100202_qi field_100848_j;
	static String field_100843_p;
	static C_100068_vc field_100845_o;
	static C_100037_wb[] field_100850_k;
	static String field_100844_n;
	static boolean field_100847_m;
	private static final String[] field_100849_z;
	
	C_100191_rg(byte[] arg0)
	{
		// @00: aload_0
		// @01: invokespecial game.C_100158_da.<init>()void
		// @04: aload_0
		// @05: aload_1
		// @06: putfield byte[] game.C_100191_rg.field_100846_l
		// @09: goto @3E
		// @0C: astore_2
		// @0D: aload_2
		// @0E: new java.lang.StringBuilder
		// @11: dup
		// @12: invokespecial java.lang.StringBuilder.<init>()void
		// @15: getstatic java.lang.String[] game.C_100191_rg.field_100849_z
		// @18: iconst_5
		// @19: aaload
		// @1A: invokevirtual java.lang.StringBuilder.append(java.lang.String)java.lang.StringBuilder
		// @1D: aload_1
		// @1E: ifnull @2A
		// @21: getstatic java.lang.String[] game.C_100191_rg.field_100849_z
		// @24: iconst_2
		// @25: aaload
		// @26: goto @2F
		// @29: athrow
		// @2A: getstatic java.lang.String[] game.C_100191_rg.field_100849_z
		// @2D: iconst_3
		// @2E: aaload
		// @2F: invokevirtual java.lang.StringBuilder.append(java.lang.String)java.lang.StringBuilder
		// @32: bipush 41 (0x29)
		// @34: invokevirtual java.lang.StringBuilder.append(char)java.lang.StringBuilder
		// @37: invokevirtual java.lang.StringBuilder.toString()java.lang.String
		// @3A: invokestatic game.C_100181_cf.func_105695_a(java.lang.Throwable, java.lang.String)game.C_100170_cm
		// @3D: athrow
		// @3E: return
	}
	
	public static void func_100840_f(int arg0)
	{
		// @00: aconst_null
		// @01: putstatic java.lang.String game.C_100191_rg.field_100843_p
		// @04: aconst_null
		// @05: putstatic game.C_100202_qi game.C_100191_rg.field_100848_j
		// @08: aconst_null
		// @09: putstatic java.lang.String game.C_100191_rg.field_100844_n
		// @0C: aconst_null
		// @0D: putstatic game.C_100068_vc game.C_100191_rg.field_100845_o
		// @10: aconst_null
		// @11: putstatic game.C_100037_wb[] game.C_100191_rg.field_100850_k
		// @14: iload_0
		// @15: ifeq @1D
		// @18: bipush 31 (0x1F)
		// @1A: invokestatic game.C_100191_rg.func_100840_f(int)void
		// @1D: goto @41
		// @20: astore_1
		// @21: aload_1
		// @22: new java.lang.StringBuilder
		// @25: dup
		// @26: invokespecial java.lang.StringBuilder.<init>()void
		// @29: getstatic java.lang.String[] game.C_100191_rg.field_100849_z
		// @2C: iconst_0
		// @2D: aaload
		// @2E: invokevirtual java.lang.StringBuilder.append(java.lang.String)java.lang.StringBuilder
		// @31: iload_0
		// @32: invokevirtual java.lang.StringBuilder.append(int)java.lang.StringBuilder
		// @35: bipush 41 (0x29)
		// @37: invokevirtual java.lang.StringBuilder.append(char)java.lang.StringBuilder
		// @3A: invokevirtual java.lang.StringBuilder.toString()java.lang.String
		// @3D: invokestatic game.C_100181_cf.func_105695_a(java.lang.Throwable, java.lang.String)game.C_100170_cm
		// @40: athrow
		// @41: return
	}
	
	static final void func_100841_a(int arg0, int arg1, int arg2, C_100127_tl arg3)
	{
		// @00: aload_3
		// @01: putstatic game.C_100127_tl game.C_100309_lk.field_103263_T
		// @04: iload_0
		// @05: putstatic int game.C_100055_ed.field_104240_g
		// @08: iload_1
		// @09: ifeq @0D
		// @0C: return
		// @0D: iload_2
		// @0E: putstatic int game.C_100215_ai.field_106019_l
		// @11: goto @63
		// @14: astore #4
		// @16: aload #4
		// @18: new java.lang.StringBuilder
		// @1B: dup
		// @1C: invokespecial java.lang.StringBuilder.<init>()void
		// @1F: getstatic java.lang.String[] game.C_100191_rg.field_100849_z
		// @22: iconst_4
		// @23: aaload
		// @24: invokevirtual java.lang.StringBuilder.append(java.lang.String)java.lang.StringBuilder
		// @27: iload_0
		// @28: invokevirtual java.lang.StringBuilder.append(int)java.lang.StringBuilder
		// @2B: bipush 44 (0x2C)
		// @2D: invokevirtual java.lang.StringBuilder.append(char)java.lang.StringBuilder
		// @30: iload_1
		// @31: invokevirtual java.lang.StringBuilder.append(int)java.lang.StringBuilder
		// @34: bipush 44 (0x2C)
		// @36: invokevirtual java.lang.StringBuilder.append(char)java.lang.StringBuilder
		// @39: iload_2
		// @3A: invokevirtual java.lang.StringBuilder.append(int)java.lang.StringBuilder
		// @3D: bipush 44 (0x2C)
		// @3F: invokevirtual java.lang.StringBuilder.append(char)java.lang.StringBuilder
		// @42: aload_3
		// @43: ifnull @4F
		// @46: getstatic java.lang.String[] game.C_100191_rg.field_100849_z
		// @49: iconst_2
		// @4A: aaload
		// @4B: goto @54
		// @4E: athrow
		// @4F: getstatic java.lang.String[] game.C_100191_rg.field_100849_z
		// @52: iconst_3
		// @53: aaload
		// @54: invokevirtual java.lang.StringBuilder.append(java.lang.String)java.lang.StringBuilder
		// @57: bipush 41 (0x29)
		// @59: invokevirtual java.lang.StringBuilder.append(char)java.lang.StringBuilder
		// @5C: invokevirtual java.lang.StringBuilder.toString()java.lang.String
		// @5F: invokestatic game.C_100181_cf.func_105695_a(java.lang.Throwable, java.lang.String)game.C_100170_cm
		// @62: athrow
		// @63: return
	}
	
	static final boolean func_100842_e(int arg0)
	{
		// @00: iload_0
		// @01: ifeq @0D
		// @04: bipush 103 (0x67)
		// @06: invokestatic game.C_100191_rg.func_100840_f(int)void
		// @09: goto @0D
		// @0C: athrow
		// @0D: iload_0
		// @0E: bipush -114 (0x8E)
		// @10: iadd
		// @11: invokestatic game.C_100010_ff.func_103694_e(int)boolean
		// @14: ifeq @2A
		// @17: iconst_0
		// @18: bipush 8 (0x08)
		// @1A: getstatic int game.C_100066_dl.field_101636_H
		// @1D: iand
		// @1E: if_icmpne @2A
		// @21: goto @25
		// @24: athrow
		// @25: iconst_1
		// @26: goto @2B
		// @29: athrow
		// @2A: iconst_0
		// @2B: ireturn
		// @2C: astore_1
		// @2D: aload_1
		// @2E: new java.lang.StringBuilder
		// @31: dup
		// @32: invokespecial java.lang.StringBuilder.<init>()void
		// @35: getstatic java.lang.String[] game.C_100191_rg.field_100849_z
		// @38: iconst_1
		// @39: aaload
		// @3A: invokevirtual java.lang.StringBuilder.append(java.lang.String)java.lang.StringBuilder
		// @3D: iload_0
		// @3E: invokevirtual java.lang.StringBuilder.append(int)java.lang.StringBuilder
		// @41: bipush 41 (0x29)
		// @43: invokevirtual java.lang.StringBuilder.append(char)java.lang.StringBuilder
		// @46: invokevirtual java.lang.StringBuilder.toString()java.lang.String
		// @49: invokestatic game.C_100181_cf.func_105695_a(java.lang.Throwable, java.lang.String)game.C_100170_cm
		// @4C: athrow
	}
	
	static
	{
		// @00: bipush 6 (0x06)
		// @02: anewarray java.lang.String
		// @05: dup
		// @06: iconst_0
		// @07: ldc "\u0001v?s\u0011"
		// @09: invokestatic game.C_100191_rg.func_100839_z(java.lang.String)char[]
		// @0C: invokestatic game.C_100191_rg.func_100838_z(char[])java.lang.String
		// @0F: aastore
		// @10: dup
		// @11: iconst_1
		// @12: ldc "\u0001v?q\u0011"
		// @14: invokestatic game.C_100191_rg.func_100839_z(java.lang.String)char[]
		// @17: invokestatic game.C_100191_rg.func_100838_z(char[])java.lang.String
		// @1A: aastore
		// @1B: dup
		// @1C: iconst_2
		// @1D: ldc "\u0008??\u001eD"
		// @1F: invokestatic game.C_100191_rg.func_100839_z(java.lang.String)char[]
		// @22: invokestatic game.C_100191_rg.func_100838_z(char[])java.lang.String
		// @25: aastore
		// @26: dup
		// @27: iconst_3
		// @28: ldc "\u001dd}\\"
		// @2A: invokestatic game.C_100191_rg.func_100839_z(java.lang.String)char[]
		// @2D: invokestatic game.C_100191_rg.func_100838_z(char[])java.lang.String
		// @30: aastore
		// @31: dup
		// @32: iconst_4
		// @33: ldc "\u0001v?r\u0011"
		// @35: invokestatic game.C_100191_rg.func_100839_z(java.lang.String)char[]
		// @38: invokestatic game.C_100191_rg.func_100838_z(char[])java.lang.String
		// @3B: aastore
		// @3C: dup
		// @3D: iconst_5
		// @3E: ldc "\u0001v?\u000cP\u001dxe\u000e\u0011"
		// @40: invokestatic game.C_100191_rg.func_100839_z(java.lang.String)char[]
		// @43: invokestatic game.C_100191_rg.func_100838_z(char[])java.lang.String
		// @46: aastore
		// @47: putstatic java.lang.String[] game.C_100191_rg.field_100849_z
		// @4A: new game.C_100202_qi
		// @4D: dup
		// @4E: invokespecial game.C_100202_qi.<init>()void
		// @51: putstatic game.C_100202_qi game.C_100191_rg.field_100848_j
		// @54: ldc "5cxUW\u0017b"
		// @56: invokestatic game.C_100191_rg.func_100839_z(java.lang.String)char[]
		// @59: invokestatic game.C_100191_rg.func_100838_z(char[])java.lang.String
		// @5C: putstatic java.lang.String game.C_100191_rg.field_100843_p
		// @5F: ldc "'yt\u0010\u001eO4!\u000e\u001eSbtDM\u001a\u007fv\u0010W\u0016tuC\u0019\u0007~1R\\SryQW\u0014tu\u001e"
		// @61: invokestatic game.C_100191_rg.func_100839_z(java.lang.String)char[]
		// @64: invokestatic game.C_100191_rg.func_100838_z(char[])java.lang.String
		// @67: putstatic java.lang.String game.C_100191_rg.field_100844_n
		// @6A: iconst_0
		// @6B: putstatic boolean game.C_100191_rg.field_100847_m
		// @6E: return
	}
	
	private static char[] func_100839_z(String arg0)
	{
		// @00: aload_0
		// @01: invokevirtual java.lang.String.toCharArray()char[]
		// @04: dup
		// @05: arraylength
		// @06: iconst_2
		// @07: if_icmpge @13
		// @0A: dup
		// @0B: iconst_0
		// @0C: dup2
		// @0D: caload
		// @0E: bipush 57 (0x39)
		// @10: ixor
		// @11: i2c
		// @12: castore
		// @13: areturn
	}
	
	private static String func_100838_z(char[] arg0)
	{
		// @00: aload_0
		// @01: dup
		// @02: arraylength
		// @03: swap
		// @04: iconst_0
		// @05: istore_1
		// @06: goto @4C
		// @09: dup
		// @0A: iload_1
		// @0B: dup2
		// @0C: caload
		// @0D: iload_1
		// @0E: iconst_5
		// @0F: irem
		// @10: tableswitch def: @44, for 0: @30, for 1: @35, for 2: @3A, for 3: @3F
		// @30: bipush 115 (0x73)
		// @32: goto @46
		// @35: bipush 17 (0x11)
		// @37: goto @46
		// @3A: bipush 17 (0x11)
		// @3C: goto @46
		// @3F: bipush 48 (0x30)
		// @41: goto @46
		// @44: bipush 57 (0x39)
		// @46: ixor
		// @47: i2c
		// @48: castore
		// @49: iinc #1 +1
		// @4C: swap
		// @4D: dup_x1
		// @4E: iload_1
		// @4F: if_icmpgt @09
		// @52: new java.lang.String
		// @55: dup_x1
		// @56: swap
		// @57: invokespecial java.lang.String.<init>(char[])void
		// @5A: invokevirtual java.lang.String.intern()java.lang.String
		// @5D: areturn
	}
}
