package game;

import java.awt.Canvas;

final class C_100209_qb extends C_100079_e
{
	static int field_102691_Hb;
	static String field_102693_Lb;
	static int field_102688_Kb;
	static int[] field_102696_Ob;
	static String field_102695_Jb;
	static boolean field_102690_Ib;
	static int[] field_102692_Nb;
	static C_100037_wb field_102694_Mb;
	private static final String[] field_102689_Pb;
	
	static final Canvas func_102680_r(int arg0)
	{
		// @00: iload_0
		// @01: iconst_m1
		// @02: if_icmpeq @0E
		// @05: bipush -99 (0x9D)
		// @07: putstatic int game.C_100209_qb.field_102691_Hb
		// @0A: goto @0E
		// @0D: athrow
		// @0E: getstatic game.C_100009_fg game.C_100146_bf.field_105128_n
		// @11: ifnonnull @1B
		// @14: getstatic java.awt.Canvas game.C_100034_gi.field_104033_a
		// @17: goto @1E
		// @1A: athrow
		// @1B: getstatic game.C_100009_fg game.C_100146_bf.field_105128_n
		// @1E: areturn
		// @1F: astore_1
		// @20: aload_1
		// @21: new java.lang.StringBuilder
		// @24: dup
		// @25: invokespecial java.lang.StringBuilder.<init>()void
		// @28: getstatic java.lang.String[] game.C_100209_qb.field_102689_Pb
		// @2B: bipush 8 (0x08)
		// @2D: aaload
		// @2E: invokevirtual java.lang.StringBuilder.append(java.lang.String)java.lang.StringBuilder
		// @31: iload_0
		// @32: invokevirtual java.lang.StringBuilder.append(int)java.lang.StringBuilder
		// @35: bipush 41 (0x29)
		// @37: invokevirtual java.lang.StringBuilder.append(char)java.lang.StringBuilder
		// @3A: invokevirtual java.lang.StringBuilder.toString()java.lang.String
		// @3D: invokestatic game.C_100181_cf.func_105695_a(java.lang.Throwable, java.lang.String)game.C_100170_cm
		// @40: athrow
	}
	
	public static void func_102685_h(byte arg0)
	{
		// @00: bipush 69 (0x45)
		// @02: bipush -16 (0xF0)
		// @04: iload_0
		// @05: isub
		// @06: bipush 33 (0x21)
		// @08: idiv
		// @09: idiv
		// @0A: istore_1
		// @0B: aconst_null
		// @0C: putstatic int[] game.C_100209_qb.field_102696_Ob
		// @0F: aconst_null
		// @10: putstatic game.C_100037_wb game.C_100209_qb.field_102694_Mb
		// @13: aconst_null
		// @14: putstatic java.lang.String game.C_100209_qb.field_102693_Lb
		// @17: aconst_null
		// @18: putstatic int[] game.C_100209_qb.field_102692_Nb
		// @1B: aconst_null
		// @1C: putstatic java.lang.String game.C_100209_qb.field_102695_Jb
		// @1F: goto @43
		// @22: astore_1
		// @23: aload_1
		// @24: new java.lang.StringBuilder
		// @27: dup
		// @28: invokespecial java.lang.StringBuilder.<init>()void
		// @2B: getstatic java.lang.String[] game.C_100209_qb.field_102689_Pb
		// @2E: iconst_1
		// @2F: aaload
		// @30: invokevirtual java.lang.StringBuilder.append(java.lang.String)java.lang.StringBuilder
		// @33: iload_0
		// @34: invokevirtual java.lang.StringBuilder.append(int)java.lang.StringBuilder
		// @37: bipush 41 (0x29)
		// @39: invokevirtual java.lang.StringBuilder.append(char)java.lang.StringBuilder
		// @3C: invokevirtual java.lang.StringBuilder.toString()java.lang.String
		// @3F: invokestatic game.C_100181_cf.func_105695_a(java.lang.Throwable, java.lang.String)game.C_100170_cm
		// @42: athrow
		// @43: return
	}
	
	static final int func_102681_a(int arg0, boolean arg1, int arg2)
	{
		// @00: iload_1
		// @01: ifeq @07
		// @04: bipush -93 (0xA3)
		// @06: ireturn
		// @07: iconst_m1
		// @08: iload_0
		// @09: iconst_m1
		// @0A: ixor
		// @0B: if_icmpeq @69
		// @0E: iload_0
		// @0F: ifge @48
		// @12: goto @16
		// @15: athrow
		// @16: iconst_0
		// @17: iload_2
		// @18: if_icmpeq @23
		// @1B: goto @1F
		// @1E: athrow
		// @1F: goto @27
		// @22: athrow
		// @23: sipush 4096 (0x1000)
		// @26: ireturn
		// @27: iload_2
		// @28: iconst_m1
		// @29: ixor
		// @2A: iconst_m1
		// @2B: if_icmple @3B
		// @2E: sipush -4096 (0xF000)
		// @31: iload_0
		// @32: ineg
		// @33: iconst_3
		// @34: iload_2
		// @35: ineg
		// @36: invokestatic game.C_100119_ua.func_104892_a(int, byte, int)int
		// @39: iadd
		// @3A: ireturn
		// @3B: iload_0
		// @3C: ineg
		// @3D: iconst_3
		// @3E: iload_2
		// @3F: invokestatic game.C_100119_ua.func_104892_a(int, byte, int)int
		// @42: ineg
		// @43: sipush 4096 (0x1000)
		// @46: iadd
		// @47: ireturn
		// @48: iload_2
		// @49: ifeq @50
		// @4C: goto @52
		// @4F: athrow
		// @50: iconst_0
		// @51: ireturn
		// @52: iconst_m1
		// @53: iload_2
		// @54: iconst_m1
		// @55: ixor
		// @56: if_icmplt @60
		// @59: iload_0
		// @5A: iconst_3
		// @5B: iload_2
		// @5C: invokestatic game.C_100119_ua.func_104892_a(int, byte, int)int
		// @5F: ireturn
		// @60: iload_0
		// @61: iconst_3
		// @62: iload_2
		// @63: ineg
		// @64: invokestatic game.C_100119_ua.func_104892_a(int, byte, int)int
		// @67: ineg
		// @68: ireturn
		// @69: iload_2
		// @6A: iconst_m1
		// @6B: ixor
		// @6C: iconst_m1
		// @6D: if_icmpeq @83
		// @70: iload_2
		// @71: iconst_m1
		// @72: ixor
		// @73: iconst_m1
		// @74: if_icmpgt @7F
		// @77: goto @7B
		// @7A: athrow
		// @7B: sipush 2048 (0x0800)
		// @7E: ireturn
		// @7F: sipush -2048 (0xF800)
		// @82: ireturn
		// @83: iconst_0
		// @84: ireturn
		// @85: astore_3
		// @86: aload_3
		// @87: new java.lang.StringBuilder
		// @8A: dup
		// @8B: invokespecial java.lang.StringBuilder.<init>()void
		// @8E: getstatic java.lang.String[] game.C_100209_qb.field_102689_Pb
		// @91: iconst_2
		// @92: aaload
		// @93: invokevirtual java.lang.StringBuilder.append(java.lang.String)java.lang.StringBuilder
		// @96: iload_0
		// @97: invokevirtual java.lang.StringBuilder.append(int)java.lang.StringBuilder
		// @9A: bipush 44 (0x2C)
		// @9C: invokevirtual java.lang.StringBuilder.append(char)java.lang.StringBuilder
		// @9F: iload_1
		// @A0: invokevirtual java.lang.StringBuilder.append(boolean)java.lang.StringBuilder
		// @A3: bipush 44 (0x2C)
		// @A5: invokevirtual java.lang.StringBuilder.append(char)java.lang.StringBuilder
		// @A8: iload_2
		// @A9: invokevirtual java.lang.StringBuilder.append(int)java.lang.StringBuilder
		// @AC: bipush 41 (0x29)
		// @AE: invokevirtual java.lang.StringBuilder.append(char)java.lang.StringBuilder
		// @B1: invokevirtual java.lang.StringBuilder.toString()java.lang.String
		// @B4: invokestatic game.C_100181_cf.func_105695_a(java.lang.Throwable, java.lang.String)game.C_100170_cm
		// @B7: athrow
	}
	
	static final int func_102679_a(int arg0, int arg1, int arg2, boolean arg3)
	{
		// @00: iload_0
		// @01: iconst_2
		// @02: if_icmpeq @0E
		// @05: bipush -88 (0xA8)
		// @07: putstatic int game.C_100209_qb.field_102688_Kb
		// @0A: goto @0E
		// @0D: athrow
		// @0E: iload_0
		// @0F: sipush -18876 (0xB644)
		// @12: ixor
		// @13: invokestatic game.C_100283_ni.func_106752_a(int)int
		// @16: ireturn
		// @17: astore #4
		// @19: aload #4
		// @1B: new java.lang.StringBuilder
		// @1E: dup
		// @1F: invokespecial java.lang.StringBuilder.<init>()void
		// @22: getstatic java.lang.String[] game.C_100209_qb.field_102689_Pb
		// @25: bipush 7 (0x07)
		// @27: aaload
		// @28: invokevirtual java.lang.StringBuilder.append(java.lang.String)java.lang.StringBuilder
		// @2B: iload_0
		// @2C: invokevirtual java.lang.StringBuilder.append(int)java.lang.StringBuilder
		// @2F: bipush 44 (0x2C)
		// @31: invokevirtual java.lang.StringBuilder.append(char)java.lang.StringBuilder
		// @34: iload_1
		// @35: invokevirtual java.lang.StringBuilder.append(int)java.lang.StringBuilder
		// @38: bipush 44 (0x2C)
		// @3A: invokevirtual java.lang.StringBuilder.append(char)java.lang.StringBuilder
		// @3D: iload_2
		// @3E: invokevirtual java.lang.StringBuilder.append(int)java.lang.StringBuilder
		// @41: bipush 44 (0x2C)
		// @43: invokevirtual java.lang.StringBuilder.append(char)java.lang.StringBuilder
		// @46: iload_3
		// @47: invokevirtual java.lang.StringBuilder.append(boolean)java.lang.StringBuilder
		// @4A: bipush 41 (0x29)
		// @4C: invokevirtual java.lang.StringBuilder.append(char)java.lang.StringBuilder
		// @4F: invokevirtual java.lang.StringBuilder.toString()java.lang.String
		// @52: invokestatic game.C_100181_cf.func_105695_a(java.lang.Throwable, java.lang.String)game.C_100170_cm
		// @55: athrow
	}
	
	static final void func_102684_a(int arg0, int arg1, boolean arg2, int arg3, int arg4, C_100211_qd arg5, int arg6, int arg7)
	{
		// @000: getstatic int game.SteelSentinels.field_105275_O
		// @003: istore #15
		// @005: iload #4
		// @007: iconst_m1
		// @008: ixor
		// @009: iload #6
		// @00B: iconst_m1
		// @00C: ixor
		// @00D: if_icmpgt @13E
		// @010: iconst_1
		// @011: istore #8
		// @013: iconst_0
		// @014: istore #9
		// @016: iload #9
		// @018: getstatic int[][] game.C_100092_um.field_104539_i
		// @01B: arraylength
		// @01C: if_icmpge @12C
		// @01F: getstatic int[][] game.C_100092_um.field_104539_i
		// @022: iload #9
		// @024: aaload
		// @025: astore #10
		// @027: iconst_0
		// @028: istore #11
		// @02A: iconst_0
		// @02B: iload #15
		// @02D: ifne @12E
		// @030: istore #12
		// @032: aload #10
		// @034: arraylength
		// @035: iload #12
		// @037: if_icmple @0C4
		// @03A: aload #10
		// @03C: iload #12
		// @03E: iaload
		// @03F: istore #13
		// @041: aload #10
		// @043: iconst_1
		// @044: iload #12
		// @046: iadd
		// @047: iaload
		// @048: istore #14
		// @04A: iload #13
		// @04C: iconst_m1
		// @04D: iload #15
		// @04F: ifne @0E1
		// @052: if_icmpne @075
		// @055: goto @059
		// @058: athrow
		// @059: iload #14
		// @05B: iconst_m1
		// @05C: ixor
		// @05D: getstatic int[] game.C_100126_cb.field_103060_v
		// @060: iload #7
		// @062: iaload
		// @063: iconst_m1
		// @064: ixor
		// @065: if_icmpeq @0BC
		// @068: goto @06C
		// @06B: athrow
		// @06C: iload #15
		// @06E: ifeq @124
		// @071: goto @075
		// @074: athrow
		// @075: iload #4
		// @077: iload #13
		// @079: if_icmpne @08E
		// @07C: goto @080
		// @07F: athrow
		// @080: iload_0
		// @081: iconst_m1
		// @082: ixor
		// @083: iload #14
		// @085: iconst_m1
		// @086: ixor
		// @087: if_icmpeq @0B9
		// @08A: goto @08E
		// @08D: athrow
		// @08E: iload #4
		// @090: iconst_m1
		// @091: ixor
		// @092: iload #13
		// @094: iconst_m1
		// @095: ixor
		// @096: if_icmpge @124
		// @099: goto @09D
		// @09C: athrow
		// @09D: sipush 255 (0x00FF)
		// @0A0: getstatic byte[] game.C_100341_jd.field_102646_ib
		// @0A3: iload #13
		// @0A5: baload
		// @0A6: iand
		// @0A7: iload #14
		// @0A9: if_icmpeq @0BC
		// @0AC: goto @0B0
		// @0AF: athrow
		// @0B0: iload #15
		// @0B2: ifeq @124
		// @0B5: goto @0B9
		// @0B8: athrow
		// @0B9: iconst_1
		// @0BA: istore #11
		// @0BC: iinc #12 +2
		// @0BF: iload #15
		// @0C1: ifeq @032
		// @0C4: iload #11
		// @0C6: ifne @0D9
		// @0C9: getstatic int game.C_100137_bn.field_105038_l
		// @0CC: iconst_m1
		// @0CD: ixor
		// @0CE: iload #4
		// @0D0: iconst_m1
		// @0D1: ixor
		// @0D2: if_icmpne @124
		// @0D5: goto @0D9
		// @0D8: athrow
		// @0D9: iconst_0
		// @0DA: istore #12
		// @0DC: iload #12
		// @0DE: aload #10
		// @0E0: arraylength
		// @0E1: if_icmpge @121
		// @0E4: aload #10
		// @0E6: iload #12
		// @0E8: iaload
		// @0E9: istore #13
		// @0EB: iload #13
		// @0ED: iconst_m1
		// @0EE: iload #15
		// @0F0: ifne @01C
		// @0F3: if_icmpne @103
		// @0F6: iconst_1
		// @0F7: putstatic boolean game.C_100327_ib.field_102503_y
		// @0FA: iload #15
		// @0FC: ifeq @119
		// @0FF: goto @103
		// @102: athrow
		// @103: iload #4
		// @105: iload #13
		// @107: if_icmple @119
		// @10A: goto @10E
		// @10D: athrow
		// @10E: getstatic boolean[] game.C_100207_qh.field_102873_U
		// @111: iload #13
		// @113: iconst_1
		// @114: bastore
		// @115: goto @119
		// @118: athrow
		// @119: iinc #12 +2
		// @11C: iload #15
		// @11E: ifeq @0DC
		// @121: iconst_0
		// @122: istore #8
		// @124: iinc #9 +1
		// @127: iload #15
		// @129: ifeq @016
		// @12C: iload #8
		// @12E: ifeq @139
		// @131: iconst_1
		// @132: putstatic boolean game.C_100049_vf.field_104210_h
		// @135: goto @139
		// @138: athrow
		// @139: iload #15
		// @13B: ifeq @376
		// @13E: getstatic game.C_100144_bm[][] game.C_100272_mn.field_102434_J
		// @141: iconst_m1
		// @142: iload #4
		// @144: if_icmpeq @153
		// @147: goto @14B
		// @14A: athrow
		// @14B: iload #4
		// @14D: iconst_4
		// @14E: iadd
		// @14F: goto @154
		// @152: athrow
		// @153: iconst_1
		// @154: aaload
		// @155: astore #8
		// @157: iconst_1
		// @158: istore #9
		// @15A: iload_2
		// @15B: ifne @162
		// @15E: goto @209
		// @161: athrow
		// @162: iconst_m1
		// @163: iload #4
		// @165: if_icmpne @1B0
		// @168: iconst_0
		// @169: istore #10
		// @16B: getstatic int[] game.C_100126_cb.field_103060_v
		// @16E: arraylength
		// @16F: iload #10
		// @171: if_icmple @1AB
		// @174: getstatic byte[] game.C_100217_ao.field_106037_b
		// @177: iload #10
		// @179: bipush 8 (0x08)
		// @17B: idiv
		// @17C: baload
		// @17D: iconst_1
		// @17E: iload #10
		// @180: bipush 7 (0x07)
		// @182: iand
		// @183: ishl
		// @184: iand
		// @185: iconst_m1
		// @186: ixor
		// @187: iconst_m1
		// @188: iload #15
		// @18A: ifne @378
		// @18D: if_icmpne @197
		// @190: goto @194
		// @193: athrow
		// @194: goto @19F
		// @197: iconst_0
		// @198: istore #9
		// @19A: iload #15
		// @19C: ifeq @1AB
		// @19F: iinc #10 +1
		// @1A2: iload #15
		// @1A4: ifeq @16B
		// @1A7: goto @1AB
		// @1AA: athrow
		// @1AB: iload #15
		// @1AD: ifeq @209
		// @1B0: iconst_0
		// @1B1: istore #10
		// @1B3: iload #10
		// @1B5: iconst_m1
		// @1B6: ixor
		// @1B7: aload #8
		// @1B9: arraylength
		// @1BA: iconst_1
		// @1BB: isub
		// @1BC: iconst_m1
		// @1BD: ixor
		// @1BE: if_icmple @1FC
		// @1C1: getstatic byte[] game.C_100132_td.field_104970_f
		// @1C4: iload_1
		// @1C5: iload #10
		// @1C7: iadd
		// @1C8: bipush 8 (0x08)
		// @1CA: idiv
		// @1CB: baload
		// @1CC: iconst_1
		// @1CD: iload_1
		// @1CE: iload #10
		// @1D0: iadd
		// @1D1: bipush 7 (0x07)
		// @1D3: iand
		// @1D4: ishl
		// @1D5: iand
		// @1D6: iconst_m1
		// @1D7: ixor
		// @1D8: iconst_m1
		// @1D9: iload #15
		// @1DB: ifne @207
		// @1DE: if_icmpne @1E8
		// @1E1: goto @1E5
		// @1E4: athrow
		// @1E5: goto @1F0
		// @1E8: iconst_0
		// @1E9: istore #9
		// @1EB: iload #15
		// @1ED: ifeq @1FC
		// @1F0: iinc #10 +1
		// @1F3: iload #15
		// @1F5: ifeq @1B3
		// @1F8: goto @1FC
		// @1FB: athrow
		// @1FC: iload_1
		// @1FD: getstatic byte[] game.C_100019_wl.field_103840_f
		// @200: iload #4
		// @202: baload
		// @203: sipush 255 (0x00FF)
		// @206: iand
		// @207: iadd
		// @208: istore_1
		// @209: iconst_0
		// @20A: istore #10
		// @20C: iconst_0
		// @20D: istore #11
		// @20F: iconst_0
		// @210: iload #4
		// @212: iconst_m1
		// @213: ixor
		// @214: if_icmpeq @225
		// @217: iconst_m1
		// @218: aload #8
		// @21A: arraylength
		// @21B: iadd
		// @21C: iload #15
		// @21E: ifne @229
		// @221: goto @229
		// @224: athrow
		// @225: getstatic int[] game.C_100126_cb.field_103060_v
		// @228: arraylength
		// @229: iload #11
		// @22B: if_icmple @313
		// @22E: iconst_m1
		// @22F: iload #4
		// @231: if_icmpne @241
		// @234: goto @238
		// @237: athrow
		// @238: iload #11
		// @23A: istore #7
		// @23C: iload #15
		// @23E: ifeq @24E
		// @241: getstatic byte[] game.C_100341_jd.field_102646_ib
		// @244: iload #4
		// @246: iload #11
		// @248: i2b
		// @249: bastore
		// @24A: goto @24E
		// @24D: athrow
		// @24E: iload #4
		// @250: iconst_m1
		// @251: if_icmpne @268
		// @254: getstatic int[] game.C_100126_cb.field_103060_v
		// @257: arraylength
		// @258: iconst_1
		// @259: if_icmpne @268
		// @25C: goto @260
		// @25F: athrow
		// @260: iconst_1
		// @261: istore #12
		// @263: iload #15
		// @265: ifeq @2E5
		// @268: aload #8
		// @26A: iload #11
		// @26C: iconst_1
		// @26D: iadd
		// @26E: aaload
		// @26F: astore #13
		// @271: iload_2
		// @272: ifne @2BC
		// @275: iconst_0
		// @276: iload #4
		// @278: iconst_m1
		// @279: ixor
		// @27A: if_icmpne @29D
		// @27D: goto @281
		// @280: athrow
		// @281: getstatic int[] game.C_100126_cb.field_103060_v
		// @284: iload #11
		// @286: iaload
		// @287: getstatic game.C_100211_qd game.C_100068_vc.field_104342_d
		// @28A: getfield int game.C_100211_qd.field_102160_Zb
		// @28D: if_icmpne @299
		// @290: goto @294
		// @293: athrow
		// @294: iconst_1
		// @295: goto @2B5
		// @298: athrow
		// @299: iconst_0
		// @29A: goto @2B5
		// @29D: iload #11
		// @29F: getstatic game.C_100211_qd game.C_100068_vc.field_104342_d
		// @2A2: getfield byte[] game.C_100211_qd.field_102165_jc
		// @2A5: iload #4
		// @2A7: baload
		// @2A8: sipush 255 (0x00FF)
		// @2AB: iand
		// @2AC: if_icmpne @2B4
		// @2AF: iconst_1
		// @2B0: goto @2B5
		// @2B3: athrow
		// @2B4: iconst_0
		// @2B5: istore #12
		// @2B7: iload #15
		// @2B9: ifeq @2E5
		// @2BC: aload #13
		// @2BE: getfield boolean game.C_100144_bm.field_101861_U
		// @2C1: ifne @2DD
		// @2C4: goto @2C8
		// @2C7: athrow
		// @2C8: iload #9
		// @2CA: ifeq @2E2
		// @2CD: goto @2D1
		// @2D0: athrow
		// @2D1: aload #13
		// @2D3: getfield boolean game.C_100144_bm.field_101864_W
		// @2D6: ifeq @2E2
		// @2D9: goto @2DD
		// @2DC: athrow
		// @2DD: iconst_1
		// @2DE: goto @2E3
		// @2E1: athrow
		// @2E2: iconst_0
		// @2E3: istore #12
		// @2E5: iload #12
		// @2E7: ifeq @300
		// @2EA: iconst_1
		// @2EB: istore #10
		// @2ED: iload_0
		// @2EE: iload_1
		// @2EF: iload_2
		// @2F0: iload_3
		// @2F1: iconst_0
		// @2F2: iadd
		// @2F3: iconst_1
		// @2F4: iload #4
		// @2F6: iadd
		// @2F7: aload #5
		// @2F9: iload #6
		// @2FB: iload #7
		// @2FD: invokestatic game.C_100209_qb.func_102684_a(int, int, boolean, int, int, game.C_100211_qd, int, int)void
		// @300: getstatic boolean game.C_100049_vf.field_104210_h
		// @303: ifne @30A
		// @306: goto @30B
		// @309: athrow
		// @30A: return
		// @30B: iinc #11 +1
		// @30E: iload #15
		// @310: ifeq @20F
		// @313: iload #10
		// @315: ifeq @31C
		// @318: goto @376
		// @31B: athrow
		// @31C: iconst_0
		// @31D: istore #11
		// @31F: iload #11
		// @321: iconst_m1
		// @322: ixor
		// @323: iconst_m1
		// @324: aload #8
		// @326: arraylength
		// @327: iadd
		// @328: iconst_m1
		// @329: ixor
		// @32A: if_icmple @376
		// @32D: iload #4
		// @32F: iconst_m1
		// @330: iload #15
		// @332: ifne @378
		// @335: if_icmpeq @34E
		// @338: goto @33C
		// @33B: athrow
		// @33C: getstatic byte[] game.C_100341_jd.field_102646_ib
		// @33F: iload #4
		// @341: iload #11
		// @343: i2b
		// @344: bastore
		// @345: iload #15
		// @347: ifeq @352
		// @34A: goto @34E
		// @34D: athrow
		// @34E: iload #11
		// @350: istore #7
		// @352: iload_0
		// @353: iload_1
		// @354: iload_2
		// @355: iconst_1
		// @356: iconst_1
		// @357: iload #4
		// @359: iadd
		// @35A: aload #5
		// @35C: iload #6
		// @35E: iload #7
		// @360: invokestatic game.C_100209_qb.func_102684_a(int, int, boolean, int, int, game.C_100211_qd, int, int)void
		// @363: getstatic boolean game.C_100049_vf.field_104210_h
		// @366: ifne @36D
		// @369: goto @36E
		// @36C: athrow
		// @36D: return
		// @36E: iinc #11 +1
		// @371: iload #15
		// @373: ifeq @31F
		// @376: iload_3
		// @377: iconst_1
		// @378: if_icmpeq @386
		// @37B: aconst_null
		// @37C: checkcast int[]
		// @37F: putstatic int[] game.C_100209_qb.field_102696_Ob
		// @382: goto @386
		// @385: athrow
		// @386: goto @401
		// @389: astore #8
		// @38B: aload #8
		// @38D: new java.lang.StringBuilder
		// @390: dup
		// @391: invokespecial java.lang.StringBuilder.<init>()void
		// @394: getstatic java.lang.String[] game.C_100209_qb.field_102689_Pb
		// @397: bipush 6 (0x06)
		// @399: aaload
		// @39A: invokevirtual java.lang.StringBuilder.append(java.lang.String)java.lang.StringBuilder
		// @39D: iload_0
		// @39E: invokevirtual java.lang.StringBuilder.append(int)java.lang.StringBuilder
		// @3A1: bipush 44 (0x2C)
		// @3A3: invokevirtual java.lang.StringBuilder.append(char)java.lang.StringBuilder
		// @3A6: iload_1
		// @3A7: invokevirtual java.lang.StringBuilder.append(int)java.lang.StringBuilder
		// @3AA: bipush 44 (0x2C)
		// @3AC: invokevirtual java.lang.StringBuilder.append(char)java.lang.StringBuilder
		// @3AF: iload_2
		// @3B0: invokevirtual java.lang.StringBuilder.append(boolean)java.lang.StringBuilder
		// @3B3: bipush 44 (0x2C)
		// @3B5: invokevirtual java.lang.StringBuilder.append(char)java.lang.StringBuilder
		// @3B8: iload_3
		// @3B9: invokevirtual java.lang.StringBuilder.append(int)java.lang.StringBuilder
		// @3BC: bipush 44 (0x2C)
		// @3BE: invokevirtual java.lang.StringBuilder.append(char)java.lang.StringBuilder
		// @3C1: iload #4
		// @3C3: invokevirtual java.lang.StringBuilder.append(int)java.lang.StringBuilder
		// @3C6: bipush 44 (0x2C)
		// @3C8: invokevirtual java.lang.StringBuilder.append(char)java.lang.StringBuilder
		// @3CB: aload #5
		// @3CD: ifnull @3D9
		// @3D0: getstatic java.lang.String[] game.C_100209_qb.field_102689_Pb
		// @3D3: iconst_4
		// @3D4: aaload
		// @3D5: goto @3DE
		// @3D8: athrow
		// @3D9: getstatic java.lang.String[] game.C_100209_qb.field_102689_Pb
		// @3DC: iconst_5
		// @3DD: aaload
		// @3DE: invokevirtual java.lang.StringBuilder.append(java.lang.String)java.lang.StringBuilder
		// @3E1: bipush 44 (0x2C)
		// @3E3: invokevirtual java.lang.StringBuilder.append(char)java.lang.StringBuilder
		// @3E6: iload #6
		// @3E8: invokevirtual java.lang.StringBuilder.append(int)java.lang.StringBuilder
		// @3EB: bipush 44 (0x2C)
		// @3ED: invokevirtual java.lang.StringBuilder.append(char)java.lang.StringBuilder
		// @3F0: iload #7
		// @3F2: invokevirtual java.lang.StringBuilder.append(int)java.lang.StringBuilder
		// @3F5: bipush 41 (0x29)
		// @3F7: invokevirtual java.lang.StringBuilder.append(char)java.lang.StringBuilder
		// @3FA: invokevirtual java.lang.StringBuilder.toString()java.lang.String
		// @3FD: invokestatic game.C_100181_cf.func_105695_a(java.lang.Throwable, java.lang.String)game.C_100170_cm
		// @400: athrow
		// @401: return
	}
	
	static final C_100327_ib func_102686_b(int arg0, byte arg1)
	{
		// @00: getstatic int game.SteelSentinels.field_105275_O
		// @03: istore #4
		// @05: getstatic game.C_100202_qi game.C_100094_j.field_104551_a
		// @08: bipush 13 (0x0D)
		// @0A: invokevirtual game.C_100202_qi.func_105899_c(int)game.C_100158_da
		// @0D: checkcast game.C_100327_ib
		// @10: astore_2
		// @11: aconst_null
		// @12: aload_2
		// @13: if_acmpeq @3D
		// @16: aload_2
		// @17: getfield int game.C_100327_ib.field_102494_P
		// @1A: iload_0
		// @1B: iload #4
		// @1D: ifne @46
		// @20: if_icmpeq @2A
		// @23: goto @27
		// @26: athrow
		// @27: goto @2C
		// @2A: aload_2
		// @2B: areturn
		// @2C: getstatic game.C_100202_qi game.C_100094_j.field_104551_a
		// @2F: bipush 93 (0x5D)
		// @31: invokevirtual game.C_100202_qi.func_105907_c(byte)game.C_100158_da
		// @34: checkcast game.C_100327_ib
		// @37: astore_2
		// @38: iload #4
		// @3A: ifeq @11
		// @3D: bipush 30 (0x1E)
		// @3F: bipush 34 (0x22)
		// @41: iload_1
		// @42: isub
		// @43: bipush 50 (0x32)
		// @45: idiv
		// @46: idiv
		// @47: istore_3
		// @48: aconst_null
		// @49: areturn
		// @4A: astore_2
		// @4B: aload_2
		// @4C: new java.lang.StringBuilder
		// @4F: dup
		// @50: invokespecial java.lang.StringBuilder.<init>()void
		// @53: getstatic java.lang.String[] game.C_100209_qb.field_102689_Pb
		// @56: iconst_3
		// @57: aaload
		// @58: invokevirtual java.lang.StringBuilder.append(java.lang.String)java.lang.StringBuilder
		// @5B: iload_0
		// @5C: invokevirtual java.lang.StringBuilder.append(int)java.lang.StringBuilder
		// @5F: bipush 44 (0x2C)
		// @61: invokevirtual java.lang.StringBuilder.append(char)java.lang.StringBuilder
		// @64: iload_1
		// @65: invokevirtual java.lang.StringBuilder.append(int)java.lang.StringBuilder
		// @68: bipush 41 (0x29)
		// @6A: invokevirtual java.lang.StringBuilder.append(char)java.lang.StringBuilder
		// @6D: invokevirtual java.lang.StringBuilder.toString()java.lang.String
		// @70: invokestatic game.C_100181_cf.func_105695_a(java.lang.Throwable, java.lang.String)game.C_100170_cm
		// @73: athrow
	}
	
	static final void func_102687_b(int arg0, int arg1, int arg2, int arg3, int arg4)
	{
		// @00: bipush -55 (0xC9)
		// @02: bipush -55 (0xC9)
		// @04: iload_0
		// @05: isub
		// @06: bipush 62 (0x3E)
		// @08: idiv
		// @09: irem
		// @0A: istore #5
		// @0C: bipush -46 (0xD2)
		// @0E: invokestatic game.C_100328_ia.func_107254_b(byte)void
		// @11: iload #4
		// @13: iload_2
		// @14: iload_3
		// @15: iload_1
		// @16: invokestatic game.C_100196_rb.func_105779_e(int, int, int, int)void
		// @19: goto @64
		// @1C: astore #5
		// @1E: aload #5
		// @20: new java.lang.StringBuilder
		// @23: dup
		// @24: invokespecial java.lang.StringBuilder.<init>()void
		// @27: getstatic java.lang.String[] game.C_100209_qb.field_102689_Pb
		// @2A: iconst_0
		// @2B: aaload
		// @2C: invokevirtual java.lang.StringBuilder.append(java.lang.String)java.lang.StringBuilder
		// @2F: iload_0
		// @30: invokevirtual java.lang.StringBuilder.append(int)java.lang.StringBuilder
		// @33: bipush 44 (0x2C)
		// @35: invokevirtual java.lang.StringBuilder.append(char)java.lang.StringBuilder
		// @38: iload_1
		// @39: invokevirtual java.lang.StringBuilder.append(int)java.lang.StringBuilder
		// @3C: bipush 44 (0x2C)
		// @3E: invokevirtual java.lang.StringBuilder.append(char)java.lang.StringBuilder
		// @41: iload_2
		// @42: invokevirtual java.lang.StringBuilder.append(int)java.lang.StringBuilder
		// @45: bipush 44 (0x2C)
		// @47: invokevirtual java.lang.StringBuilder.append(char)java.lang.StringBuilder
		// @4A: iload_3
		// @4B: invokevirtual java.lang.StringBuilder.append(int)java.lang.StringBuilder
		// @4E: bipush 44 (0x2C)
		// @50: invokevirtual java.lang.StringBuilder.append(char)java.lang.StringBuilder
		// @53: iload #4
		// @55: invokevirtual java.lang.StringBuilder.append(int)java.lang.StringBuilder
		// @58: bipush 41 (0x29)
		// @5A: invokevirtual java.lang.StringBuilder.append(char)java.lang.StringBuilder
		// @5D: invokevirtual java.lang.StringBuilder.toString()java.lang.String
		// @60: invokestatic game.C_100181_cf.func_105695_a(java.lang.Throwable, java.lang.String)game.C_100170_cm
		// @63: athrow
		// @64: return
	}
	
	final void func_102660_a(C_100336_im arg0, byte arg1)
	{
		// @00: aload_0
		// @01: aload_1
		// @02: iload_2
		// @03: invokespecial game.C_100079_e.func_102660_a(game.C_100336_im, byte)void
		// @06: goto @45
		// @09: astore_3
		// @0A: aload_3
		// @0B: new java.lang.StringBuilder
		// @0E: dup
		// @0F: invokespecial java.lang.StringBuilder.<init>()void
		// @12: getstatic java.lang.String[] game.C_100209_qb.field_102689_Pb
		// @15: bipush 9 (0x09)
		// @17: aaload
		// @18: invokevirtual java.lang.StringBuilder.append(java.lang.String)java.lang.StringBuilder
		// @1B: aload_1
		// @1C: ifnull @28
		// @1F: getstatic java.lang.String[] game.C_100209_qb.field_102689_Pb
		// @22: iconst_4
		// @23: aaload
		// @24: goto @2D
		// @27: athrow
		// @28: getstatic java.lang.String[] game.C_100209_qb.field_102689_Pb
		// @2B: iconst_5
		// @2C: aaload
		// @2D: invokevirtual java.lang.StringBuilder.append(java.lang.String)java.lang.StringBuilder
		// @30: bipush 44 (0x2C)
		// @32: invokevirtual java.lang.StringBuilder.append(char)java.lang.StringBuilder
		// @35: iload_2
		// @36: invokevirtual java.lang.StringBuilder.append(int)java.lang.StringBuilder
		// @39: bipush 41 (0x29)
		// @3B: invokevirtual java.lang.StringBuilder.append(char)java.lang.StringBuilder
		// @3E: invokevirtual java.lang.StringBuilder.toString()java.lang.String
		// @41: invokestatic game.C_100181_cf.func_105695_a(java.lang.Throwable, java.lang.String)game.C_100170_cm
		// @44: athrow
		// @45: return
	}
	
	C_100209_qb(C_100029_gn arg0, C_100336_im arg1)
	{
		// @0: aload_0
		// @1: aload_1
		// @2: aload_2
		// @3: bipush 33 (0x21)
		// @5: bipush 20 (0x14)
		// @7: bipush 30 (0x1E)
		// @9: invokespecial game.C_100079_e.<init>(game.C_100029_gn, game.C_100336_im, int, int, int)void
		// @C: return
	}
	
	static
	{
		// @00: bipush 10 (0x0A)
		// @02: anewarray java.lang.String
		// @05: dup
		// @06: iconst_0
		// @07: ldc "\u001f/htXF"
		// @09: invokestatic game.C_100209_qb.func_102683_z(java.lang.String)char[]
		// @0C: invokestatic game.C_100209_qb.func_102682_z(char[])java.lang.String
		// @0F: aastore
		// @10: dup
		// @11: iconst_1
		// @12: ldc "\u001f/hqXF"
		// @14: invokestatic game.C_100209_qb.func_102683_z(java.lang.String)char[]
		// @17: invokestatic game.C_100209_qb.func_102682_z(char[])java.lang.String
		// @1A: aastore
		// @1B: dup
		// @1C: iconst_2
		// @1D: ldc "\u001f/hrXF"
		// @1F: invokestatic game.C_100209_qb.func_102683_z(java.lang.String)char[]
		// @22: invokestatic game.C_100209_qb.func_102682_z(char[])java.lang.String
		// @25: aastore
		// @26: dup
		// @27: iconst_3
		// @28: ldc "\u001f/hvXF"
		// @2A: invokestatic game.C_100209_qb.func_102683_z(java.lang.String)char[]
		// @2D: invokestatic game.C_100209_qb.func_102682_z(char[])java.lang.String
		// @30: aastore
		// @31: dup
		// @32: iconst_4
		// @33: ldc "\u0015ch\u0012d"
		// @35: invokestatic game.C_100209_qb.func_102683_z(java.lang.String)char[]
		// @38: invokestatic game.C_100209_qb.func_102682_z(char[])java.lang.String
		// @3B: aastore
		// @3C: dup
		// @3D: iconst_5
		// @3E: ldc "\u00008*P"
		// @40: invokestatic game.C_100209_qb.func_102683_z(java.lang.String)char[]
		// @43: invokestatic game.C_100209_qb.func_102682_z(char[])java.lang.String
		// @46: aastore
		// @47: dup
		// @48: bipush 6 (0x06)
		// @4A: ldc "\u001f/huXF"
		// @4C: invokestatic game.C_100209_qb.func_102683_z(java.lang.String)char[]
		// @4F: invokestatic game.C_100209_qb.func_102682_z(char[])java.lang.String
		// @52: aastore
		// @53: dup
		// @54: bipush 7 (0x07)
		// @56: ldc "\u001f/hsXF"
		// @58: invokestatic game.C_100209_qb.func_102683_z(java.lang.String)char[]
		// @5B: invokestatic game.C_100209_qb.func_102682_z(char[])java.lang.String
		// @5E: aastore
		// @5F: dup
		// @60: bipush 8 (0x08)
		// @62: ldc "\u001f/h{XF"
		// @64: invokestatic game.C_100209_qb.func_102683_z(java.lang.String)char[]
		// @67: invokestatic game.C_100209_qb.func_102682_z(char[])java.lang.String
		// @6A: aastore
		// @6B: dup
		// @6C: bipush 9 (0x09)
		// @6E: ldc "\u001f/hwXF"
		// @70: invokestatic game.C_100209_qb.func_102683_z(java.lang.String)char[]
		// @73: invokestatic game.C_100209_qb.func_102682_z(char[])java.lang.String
		// @76: aastore
		// @77: putstatic java.lang.String[] game.C_100209_qb.field_102689_Pb
		// @7A: ldc "=%)Nm\r82\u001cK\u000b+#N|\u0000.#"
		// @7C: invokestatic game.C_100209_qb.func_102683_z(java.lang.String)char[]
		// @7F: invokestatic game.C_100209_qb.func_102682_z(char[])java.lang.String
		// @82: putstatic java.lang.String game.C_100209_qb.field_102693_Lb
		// @85: bipush 11 (0x0B)
		// @87: newarray int[]
		// @89: dup
		// @8A: iconst_0
		// @8B: bipush 108 (0x6C)
		// @8D: iastore
		// @8E: dup
		// @8F: iconst_1
		// @90: iconst_m1
		// @91: iastore
		// @92: dup
		// @93: iconst_2
		// @94: iconst_m1
		// @95: iastore
		// @96: dup
		// @97: iconst_3
		// @98: bipush 28 (0x1C)
		// @9A: iastore
		// @9B: dup
		// @9C: iconst_4
		// @9D: iconst_m1
		// @9E: iastore
		// @9F: dup
		// @A0: iconst_5
		// @A1: iconst_m1
		// @A2: iastore
		// @A3: dup
		// @A4: bipush 6 (0x06)
		// @A6: iconst_m1
		// @A7: iastore
		// @A8: dup
		// @A9: bipush 7 (0x07)
		// @AB: iconst_m1
		// @AC: iastore
		// @AD: dup
		// @AE: bipush 8 (0x08)
		// @B0: iconst_m1
		// @B1: iastore
		// @B2: dup
		// @B3: bipush 9 (0x09)
		// @B5: iconst_m1
		// @B6: iastore
		// @B7: dup
		// @B8: bipush 10 (0x0A)
		// @BA: iconst_m1
		// @BB: iastore
		// @BC: putstatic int[] game.C_100209_qb.field_102692_Nb
		// @BF: ldc "F"
		// @C1: putstatic java.lang.String game.C_100209_qb.field_102695_Jb
		// @C4: iconst_m1
		// @C5: putstatic int game.C_100209_qb.field_102688_Kb
		// @C8: return
	}
	
	private static char[] func_102683_z(String arg0)
	{
		// @00: aload_0
		// @01: invokevirtual java.lang.String.toCharArray()char[]
		// @04: dup
		// @05: arraylength
		// @06: iconst_2
		// @07: if_icmpge @13
		// @0A: dup
		// @0B: iconst_0
		// @0C: dup2
		// @0D: caload
		// @0E: bipush 25 (0x19)
		// @10: ixor
		// @11: i2c
		// @12: castore
		// @13: areturn
	}
	
	private static String func_102682_z(char[] arg0)
	{
		// @00: aload_0
		// @01: dup
		// @02: arraylength
		// @03: swap
		// @04: iconst_0
		// @05: istore_1
		// @06: goto @4C
		// @09: dup
		// @0A: iload_1
		// @0B: dup2
		// @0C: caload
		// @0D: iload_1
		// @0E: iconst_5
		// @0F: irem
		// @10: tableswitch def: @44, for 0: @30, for 1: @35, for 2: @3A, for 3: @3F
		// @30: bipush 110 (0x6E)
		// @32: goto @46
		// @35: bipush 77 (0x4D)
		// @37: goto @46
		// @3A: bipush 70 (0x46)
		// @3C: goto @46
		// @3F: bipush 60 (0x3C)
		// @41: goto @46
		// @44: bipush 25 (0x19)
		// @46: ixor
		// @47: i2c
		// @48: castore
		// @49: iinc #1 +1
		// @4C: swap
		// @4D: dup_x1
		// @4E: iload_1
		// @4F: if_icmpgt @09
		// @52: new java.lang.String
		// @55: dup_x1
		// @56: swap
		// @57: invokespecial java.lang.String.<init>(char[])void
		// @5A: invokevirtual java.lang.String.intern()java.lang.String
		// @5D: areturn
	}
}
