package game;

import java.lang.reflect.Method;
import java.awt.Frame;
import java.net.URL;
import java.awt.EventQueue;

final class C_100201_qj implements Runnable
{
	private C_100331_ie field_105894_x;
	private static String field_105870_f;
	EventQueue field_105871_g;
	static String field_105886_v;
	private C_100331_ie field_105884_i;
	private static int field_105879_l;
	private Object field_105876_a;
	C_100005_fk field_105875_c;
	boolean field_105881_j;
	private C_100296_kg field_105891_q;
	private boolean field_105889_s;
	static String field_105872_d;
	private static volatile long field_105885_w;
	private static String field_105890_r;
	private boolean field_105882_k;
	static String field_105887_u;
	private Object field_105874_b;
	private C_100190_rh field_105873_e;
	private Thread field_105877_n;
	C_100005_fk[] field_105883_h;
	C_100005_fk field_105888_t;
	private static String field_105878_o;
	C_100005_fk field_105892_p;
	static Method field_105880_m;
	private static final String[] field_105893_z;
	
	final C_100331_ie func_105861_a(Class arg0, byte arg1, String arg2, Class[] arg3)
	{
		// @00: iload_2
		// @01: bipush 7 (0x07)
		// @03: if_icmpge @11
		// @06: aconst_null
		// @07: checkcast java.lang.String
		// @0A: putstatic java.lang.String game.C_100201_qj.field_105870_f
		// @0D: goto @11
		// @10: athrow
		// @11: aload_0
		// @12: iconst_0
		// @13: iconst_3
		// @14: anewarray java.lang.Object
		// @17: dup
		// @18: iconst_0
		// @19: aload_1
		// @1A: aastore
		// @1B: dup
		// @1C: iconst_1
		// @1D: aload_3
		// @1E: aastore
		// @1F: dup
		// @20: iconst_2
		// @21: aload #4
		// @23: aastore
		// @24: bipush 8 (0x08)
		// @26: iconst_0
		// @27: sipush -923 (0xFC65)
		// @2A: invokespecial game.C_100201_qj.func_105855_a(int, java.lang.Object, int, int, int)game.C_100331_ie
		// @2D: areturn
		// @2E: astore #5
		// @30: aload #5
		// @32: athrow
	}
	
	final C_100331_ie func_105868_a(Frame arg0, byte arg1)
	{
		// @00: iload_2
		// @01: bipush 104 (0x68)
		// @03: if_icmpeq @0B
		// @06: aconst_null
		// @07: checkcast game.C_100331_ie
		// @0A: areturn
		// @0B: aload_0
		// @0C: iconst_0
		// @0D: aload_1
		// @0E: bipush 7 (0x07)
		// @10: iconst_0
		// @11: sipush -923 (0xFC65)
		// @14: invokespecial game.C_100201_qj.func_105855_a(int, java.lang.Object, int, int, int)game.C_100331_ie
		// @17: areturn
		// @18: astore_3
		// @19: aload_3
		// @1A: athrow
	}
	
	final C_100331_ie func_105865_a(int arg0)
	{
		// @00: iload_1
		// @01: ifeq @09
		// @04: aconst_null
		// @05: checkcast game.C_100331_ie
		// @08: areturn
		// @09: aload_0
		// @0A: iconst_0
		// @0B: aconst_null
		// @0C: iconst_5
		// @0D: iconst_0
		// @0E: iload_1
		// @0F: sipush -923 (0xFC65)
		// @12: iadd
		// @13: invokespecial game.C_100201_qj.func_105855_a(int, java.lang.Object, int, int, int)game.C_100331_ie
		// @16: areturn
		// @17: astore_2
		// @18: aload_2
		// @19: athrow
	}
	
	final C_100331_ie func_105869_a(int arg0, int arg1, int arg2, int arg3, int arg4)
	{
		// @00: iload_1
		// @01: bipush 6 (0x06)
		// @03: if_icmpeq @0B
		// @06: aconst_null
		// @07: checkcast game.C_100331_ie
		// @0A: areturn
		// @0B: aload_0
		// @0C: iload #4
		// @0E: ldc -2040883184 (0x865a9810)
		// @10: ishl
		// @11: iload_2
		// @12: iadd
		// @13: aconst_null
		// @14: bipush 6 (0x06)
		// @16: iload #5
		// @18: iload_3
		// @19: ldc 802907216 (0x2fdb6450)
		// @1B: ishl
		// @1C: iadd
		// @1D: sipush -923 (0xFC65)
		// @20: invokespecial game.C_100201_qj.func_105855_a(int, java.lang.Object, int, int, int)game.C_100331_ie
		// @23: areturn
		// @24: astore #6
		// @26: aload #6
		// @28: athrow
	}
	
	private final C_100331_ie func_105855_a(int arg0, Object arg1, int arg2, int arg3, int arg4)
	{
		// @00: iload #5
		// @02: sipush -923 (0xFC65)
		// @05: if_icmpeq @0D
		// @08: aconst_null
		// @09: checkcast game.C_100331_ie
		// @0C: areturn
		// @0D: new game.C_100331_ie
		// @10: dup
		// @11: invokespecial game.C_100331_ie.<init>()void
		// @14: astore #6
		// @16: aload #6
		// @18: aload_2
		// @19: putfield java.lang.Object game.C_100331_ie.field_107299_a
		// @1C: aload #6
		// @1E: iload #4
		// @20: putfield int game.C_100331_ie.field_107296_e
		// @23: aload #6
		// @25: iload_3
		// @26: putfield int game.C_100331_ie.field_107295_d
		// @29: aload #6
		// @2B: iload_1
		// @2C: putfield int game.C_100331_ie.field_107298_c
		// @2F: aload_0
		// @30: dup
		// @31: astore #7
		// @33: monitorenter
		// @34: aload_0
		// @35: getfield game.C_100331_ie game.C_100201_qj.field_105894_x
		// @38: ifnull @4D
		// @3B: aload_0
		// @3C: getfield game.C_100331_ie game.C_100201_qj.field_105894_x
		// @3F: aload #6
		// @41: putfield game.C_100331_ie game.C_100331_ie.field_107297_b
		// @44: aload_0
		// @45: aload #6
		// @47: putfield game.C_100331_ie game.C_100201_qj.field_105894_x
		// @4A: goto @58
		// @4D: aload_0
		// @4E: aload_0
		// @4F: aload #6
		// @51: dup_x1
		// @52: putfield game.C_100331_ie game.C_100201_qj.field_105884_i
		// @55: putfield game.C_100331_ie game.C_100201_qj.field_105894_x
		// @58: aload_0
		// @59: invokevirtual java.lang.Object.notify()void
		// @5C: aload #7
		// @5E: monitorexit
		// @5F: goto @6A
		// @62: astore #8
		// @64: aload #7
		// @66: monitorexit
		// @67: aload #8
		// @69: athrow
		// @6A: aload #6
		// @6C: areturn
		// @6D: astore #6
		// @6F: aload #6
		// @71: athrow
	}
	
	final C_100331_ie func_105864_a(byte arg0, String arg1, Class arg2)
	{
		// @00: iload_1
		// @01: bipush -118 (0x8A)
		// @03: if_icmpeq @0B
		// @06: aconst_null
		// @07: checkcast game.C_100331_ie
		// @0A: areturn
		// @0B: aload_0
		// @0C: iconst_0
		// @0D: iconst_2
		// @0E: anewarray java.lang.Object
		// @11: dup
		// @12: iconst_0
		// @13: aload_3
		// @14: aastore
		// @15: dup
		// @16: iconst_1
		// @17: aload_2
		// @18: aastore
		// @19: bipush 9 (0x09)
		// @1B: iconst_0
		// @1C: iload_1
		// @1D: sipush -805 (0xFCDB)
		// @20: iadd
		// @21: invokespecial game.C_100201_qj.func_105855_a(int, java.lang.Object, int, int, int)game.C_100331_ie
		// @24: areturn
		// @25: astore #4
		// @27: aload #4
		// @29: athrow
	}
	
	final boolean func_105867_a(boolean arg0)
	{
		// @00: aload_0
		// @01: getfield boolean game.C_100201_qj.field_105881_j
		// @04: ifne @09
		// @07: iconst_0
		// @08: ireturn
		// @09: iload_1
		// @0A: iconst_1
		// @0B: if_icmpeq @18
		// @0E: aload_0
		// @0F: bipush -69 (0xBB)
		// @11: invokevirtual game.C_100201_qj.func_105858_b(int)void
		// @14: goto @18
		// @17: athrow
		// @18: aload_0
		// @19: getfield boolean game.C_100201_qj.field_105882_k
		// @1C: ifeq @31
		// @1F: aload_0
		// @20: getfield game.C_100190_rh game.C_100201_qj.field_105873_e
		// @23: ifnull @2F
		// @26: goto @2A
		// @29: athrow
		// @2A: iconst_1
		// @2B: goto @30
		// @2E: athrow
		// @2F: iconst_0
		// @30: ireturn
		// @31: aconst_null
		// @32: aload_0
		// @33: getfield java.lang.Object game.C_100201_qj.field_105876_a
		// @36: if_acmpeq @3E
		// @39: iconst_1
		// @3A: goto @3F
		// @3D: athrow
		// @3E: iconst_0
		// @3F: ireturn
		// @40: astore_2
		// @41: aload_2
		// @42: athrow
	}
	
	final C_100331_ie func_105856_a(int arg0, int arg1, Runnable arg2)
	{
		// @00: iload_2
		// @01: bipush 10 (0x0A)
		// @03: if_icmpge @10
		// @06: ldc2_w 20
		// @09: putstatic long game.C_100201_qj.field_105885_w
		// @0C: goto @10
		// @0F: athrow
		// @10: aload_0
		// @11: iload_1
		// @12: aload_3
		// @13: iconst_2
		// @14: iconst_0
		// @15: sipush -923 (0xFC65)
		// @18: invokespecial game.C_100201_qj.func_105855_a(int, java.lang.Object, int, int, int)game.C_100331_ie
		// @1B: areturn
		// @1C: astore #4
		// @1E: aload #4
		// @20: athrow
	}
	
	private static final C_100005_fk func_105862_a(String arg0, boolean arg1, String arg2, int arg3)
	{
		// @000: iload_3
		// @001: bipush 33 (0x21)
		// @003: if_icmpeq @072
		// @006: iload_3
		// @007: bipush 34 (0x22)
		// @009: if_icmpeq @041
		// @00C: goto @010
		// @00F: athrow
		// @010: new java.lang.StringBuilder
		// @013: dup
		// @014: invokespecial java.lang.StringBuilder.<init>()void
		// @017: getstatic java.lang.String[] game.C_100201_qj.field_105893_z
		// @01A: bipush 7 (0x07)
		// @01C: aaload
		// @01D: invokevirtual java.lang.StringBuilder.append(java.lang.String)java.lang.StringBuilder
		// @020: aload_0
		// @021: invokevirtual java.lang.StringBuilder.append(java.lang.String)java.lang.StringBuilder
		// @024: getstatic java.lang.String[] game.C_100201_qj.field_105893_z
		// @027: iconst_4
		// @028: aaload
		// @029: invokevirtual java.lang.StringBuilder.append(java.lang.String)java.lang.StringBuilder
		// @02C: aload_2
		// @02D: invokevirtual java.lang.StringBuilder.append(java.lang.String)java.lang.StringBuilder
		// @030: getstatic java.lang.String[] game.C_100201_qj.field_105893_z
		// @033: bipush 9 (0x09)
		// @035: aaload
		// @036: invokevirtual java.lang.StringBuilder.append(java.lang.String)java.lang.StringBuilder
		// @039: invokevirtual java.lang.StringBuilder.toString()java.lang.String
		// @03C: astore #4
		// @03E: goto @09F
		// @041: new java.lang.StringBuilder
		// @044: dup
		// @045: invokespecial java.lang.StringBuilder.<init>()void
		// @048: getstatic java.lang.String[] game.C_100201_qj.field_105893_z
		// @04B: bipush 7 (0x07)
		// @04D: aaload
		// @04E: invokevirtual java.lang.StringBuilder.append(java.lang.String)java.lang.StringBuilder
		// @051: aload_0
		// @052: invokevirtual java.lang.StringBuilder.append(java.lang.String)java.lang.StringBuilder
		// @055: getstatic java.lang.String[] game.C_100201_qj.field_105893_z
		// @058: iconst_4
		// @059: aaload
		// @05A: invokevirtual java.lang.StringBuilder.append(java.lang.String)java.lang.StringBuilder
		// @05D: aload_2
		// @05E: invokevirtual java.lang.StringBuilder.append(java.lang.String)java.lang.StringBuilder
		// @061: getstatic java.lang.String[] game.C_100201_qj.field_105893_z
		// @064: bipush 6 (0x06)
		// @066: aaload
		// @067: invokevirtual java.lang.StringBuilder.append(java.lang.String)java.lang.StringBuilder
		// @06A: invokevirtual java.lang.StringBuilder.toString()java.lang.String
		// @06D: astore #4
		// @06F: goto @09F
		// @072: new java.lang.StringBuilder
		// @075: dup
		// @076: invokespecial java.lang.StringBuilder.<init>()void
		// @079: getstatic java.lang.String[] game.C_100201_qj.field_105893_z
		// @07C: bipush 7 (0x07)
		// @07E: aaload
		// @07F: invokevirtual java.lang.StringBuilder.append(java.lang.String)java.lang.StringBuilder
		// @082: aload_0
		// @083: invokevirtual java.lang.StringBuilder.append(java.lang.String)java.lang.StringBuilder
		// @086: getstatic java.lang.String[] game.C_100201_qj.field_105893_z
		// @089: iconst_4
		// @08A: aaload
		// @08B: invokevirtual java.lang.StringBuilder.append(java.lang.String)java.lang.StringBuilder
		// @08E: aload_2
		// @08F: invokevirtual java.lang.StringBuilder.append(java.lang.String)java.lang.StringBuilder
		// @092: getstatic java.lang.String[] game.C_100201_qj.field_105893_z
		// @095: iconst_1
		// @096: aaload
		// @097: invokevirtual java.lang.StringBuilder.append(java.lang.String)java.lang.StringBuilder
		// @09A: invokevirtual java.lang.StringBuilder.toString()java.lang.String
		// @09D: astore #4
		// @09F: bipush 8 (0x08)
		// @0A1: anewarray java.lang.String
		// @0A4: dup
		// @0A5: iconst_0
		// @0A6: getstatic java.lang.String[] game.C_100201_qj.field_105893_z
		// @0A9: bipush 11 (0x0B)
		// @0AB: aaload
		// @0AC: aastore
		// @0AD: dup
		// @0AE: iconst_1
		// @0AF: getstatic java.lang.String[] game.C_100201_qj.field_105893_z
		// @0B2: iconst_5
		// @0B3: aaload
		// @0B4: aastore
		// @0B5: dup
		// @0B6: iconst_2
		// @0B7: getstatic java.lang.String game.C_100201_qj.field_105878_o
		// @0BA: aastore
		// @0BB: dup
		// @0BC: iconst_3
		// @0BD: getstatic java.lang.String[] game.C_100201_qj.field_105893_z
		// @0C0: iconst_0
		// @0C1: aaload
		// @0C2: aastore
		// @0C3: dup
		// @0C4: iconst_4
		// @0C5: getstatic java.lang.String[] game.C_100201_qj.field_105893_z
		// @0C8: bipush 10 (0x0A)
		// @0CA: aaload
		// @0CB: aastore
		// @0CC: dup
		// @0CD: iconst_5
		// @0CE: getstatic java.lang.String[] game.C_100201_qj.field_105893_z
		// @0D1: bipush 8 (0x08)
		// @0D3: aaload
		// @0D4: aastore
		// @0D5: dup
		// @0D6: bipush 6 (0x06)
		// @0D8: getstatic java.lang.String[] game.C_100201_qj.field_105893_z
		// @0DB: iconst_3
		// @0DC: aaload
		// @0DD: aastore
		// @0DE: dup
		// @0DF: bipush 7 (0x07)
		// @0E1: ldc ""
		// @0E3: aastore
		// @0E4: astore #5
		// @0E6: iconst_0
		// @0E7: istore #6
		// @0E9: aload #5
		// @0EB: arraylength
		// @0EC: iload #6
		// @0EE: if_icmple @13D
		// @0F1: aload #5
		// @0F3: iload #6
		// @0F5: aaload
		// @0F6: astore #7
		// @0F8: aload #7
		// @0FA: invokevirtual java.lang.String.length()int
		// @0FD: ifle @116
		// @100: new java.io.File
		// @103: dup
		// @104: aload #7
		// @106: invokespecial java.io.File.<init>(java.lang.String)void
		// @109: invokevirtual java.io.File.exists()boolean
		// @10C: ifne @116
		// @10F: goto @113
		// @112: athrow
		// @113: goto @137
		// @116: new game.C_100005_fk
		// @119: dup
		// @11A: new java.io.File
		// @11D: dup
		// @11E: aload #7
		// @120: aload #4
		// @122: invokespecial java.io.File.<init>(java.lang.String, java.lang.String)void
		// @125: getstatic java.lang.String[] game.C_100201_qj.field_105893_z
		// @128: iconst_2
		// @129: aaload
		// @12A: ldc2_w 10000
		// @12D: invokespecial game.C_100005_fk.<init>(java.io.File, java.lang.String, long)void
		// @130: astore #8
		// @132: aload #8
		// @134: areturn
		// @135: astore #8
		// @137: iinc #6 +1
		// @13A: goto @0E9
		// @13D: iload_1
		// @13E: iconst_1
		// @13F: if_icmpeq @147
		// @142: aconst_null
		// @143: checkcast game.C_100005_fk
		// @146: areturn
		// @147: aconst_null
		// @148: areturn
		// @149: astore #4
		// @14B: aload #4
		// @14D: athrow
	}
	
	public final void run()
	{
		// @000: aload_0
		// @001: dup
		// @002: astore_2
		// @003: monitorenter
		// @004: aload_0
		// @005: getfield boolean game.C_100201_qj.field_105889_s
		// @008: ifne @00F
		// @00B: goto @012
		// @00E: athrow
		// @00F: aload_2
		// @010: monitorexit
		// @011: return
		// @012: aconst_null
		// @013: aload_0
		// @014: getfield game.C_100331_ie game.C_100201_qj.field_105884_i
		// @017: if_acmpeq @03B
		// @01A: aload_0
		// @01B: getfield game.C_100331_ie game.C_100201_qj.field_105884_i
		// @01E: astore_1
		// @01F: aload_0
		// @020: aload_0
		// @021: getfield game.C_100331_ie game.C_100201_qj.field_105884_i
		// @024: getfield game.C_100331_ie game.C_100331_ie.field_107297_b
		// @027: putfield game.C_100331_ie game.C_100201_qj.field_105884_i
		// @02A: aconst_null
		// @02B: aload_0
		// @02C: getfield game.C_100331_ie game.C_100201_qj.field_105884_i
		// @02F: if_acmpne @046
		// @032: aload_0
		// @033: aconst_null
		// @034: putfield game.C_100331_ie game.C_100201_qj.field_105894_x
		// @037: goto @046
		// @03A: athrow
		// @03B: aload_0
		// @03C: invokevirtual java.lang.Object.wait()void
		// @03F: goto @004
		// @042: astore_3
		// @043: goto @004
		// @046: aload_2
		// @047: monitorexit
		// @048: goto @052
		// @04B: astore #4
		// @04D: aload_2
		// @04E: monitorexit
		// @04F: aload #4
		// @051: athrow
		// @052: aload_1
		// @053: getfield int game.C_100331_ie.field_107295_d
		// @056: istore_2
		// @057: iload_2
		// @058: iconst_m1
		// @059: ixor
		// @05A: bipush -2 (0xFE)
		// @05C: if_icmpeq @6D5
		// @05F: iload_2
		// @060: iconst_m1
		// @061: ixor
		// @062: bipush -23 (0xE9)
		// @064: if_icmpne @0B2
		// @067: goto @06B
		// @06A: athrow
		// @06B: getstatic long game.C_100201_qj.field_105885_w
		// @06E: ldc2_w -1
		// @071: lxor
		// @072: bipush -73 (0xB7)
		// @074: invokestatic game.C_100198_qn.func_105828_a(byte)long
		// @077: ldc2_w -1
		// @07A: lxor
		// @07B: lcmp
		// @07C: ifge @08C
		// @07F: goto @083
		// @082: athrow
		// @083: new java.io.IOException
		// @086: dup
		// @087: invokespecial java.io.IOException.<init>()void
		// @08A: athrow
		// @08B: athrow
		// @08C: aload_1
		// @08D: aload_1
		// @08E: getfield java.lang.Object game.C_100331_ie.field_107299_a
		// @091: checkcast java.lang.String
		// @094: bipush -91 (0xA5)
		// @096: aload_1
		// @097: getfield int game.C_100331_ie.field_107298_c
		// @09A: invokestatic game.C_100141_tc.func_105056_a(java.lang.String, byte, int)game.C_100157_db
		// @09D: iconst_0
		// @09E: invokevirtual game.C_100157_db.func_103555_b(int)java.net.Socket
		// @0A1: putfield java.lang.Object game.C_100331_ie.field_107294_g
		// @0A4: goto @703
		// @0A7: astore_3
		// @0A8: aload_1
		// @0A9: aload_3
		// @0AA: invokevirtual game.C_100257_ln.getMessage()java.lang.String
		// @0AD: putfield java.lang.Object game.C_100331_ie.field_107294_g
		// @0B0: aload_3
		// @0B1: athrow
		// @0B2: iload_2
		// @0B3: iconst_m1
		// @0B4: ixor
		// @0B5: bipush -3 (0xFD)
		// @0B7: if_icmpeq @6AD
		// @0BA: bipush -5 (0xFB)
		// @0BC: iload_2
		// @0BD: iconst_m1
		// @0BE: ixor
		// @0BF: if_icmpeq @678
		// @0C2: goto @0C6
		// @0C5: athrow
		// @0C6: bipush 8 (0x08)
		// @0C8: iload_2
		// @0C9: if_icmpne @11A
		// @0CC: goto @0D0
		// @0CF: athrow
		// @0D0: aload_1
		// @0D1: getfield java.lang.Object game.C_100331_ie.field_107299_a
		// @0D4: checkcast java.lang.Object[]
		// @0D7: checkcast java.lang.Object[]
		// @0DA: astore_3
		// @0DB: aload_0
		// @0DC: getfield boolean game.C_100201_qj.field_105881_j
		// @0DF: ifeq @0FB
		// @0E2: aload_3
		// @0E3: iconst_0
		// @0E4: aaload
		// @0E5: checkcast java.lang.Class
		// @0E8: invokevirtual java.lang.Class.getClassLoader()java.lang.ClassLoader
		// @0EB: ifnonnull @0FB
		// @0EE: goto @0F2
		// @0F1: athrow
		// @0F2: new java.lang.SecurityException
		// @0F5: dup
		// @0F6: invokespecial java.lang.SecurityException.<init>()void
		// @0F9: athrow
		// @0FA: athrow
		// @0FB: aload_1
		// @0FC: aload_3
		// @0FD: iconst_0
		// @0FE: aaload
		// @0FF: checkcast java.lang.Class
		// @102: aload_3
		// @103: iconst_1
		// @104: aaload
		// @105: checkcast java.lang.String
		// @108: aload_3
		// @109: iconst_2
		// @10A: aaload
		// @10B: checkcast java.lang.Class[]
		// @10E: checkcast java.lang.Class[]
		// @111: invokevirtual java.lang.Class.getDeclaredMethod(java.lang.String, java.lang.Class[])java.lang.reflect.Method
		// @114: putfield java.lang.Object game.C_100331_ie.field_107294_g
		// @117: goto @703
		// @11A: iload_2
		// @11B: iconst_m1
		// @11C: ixor
		// @11D: bipush -10 (0xF6)
		// @11F: if_icmpeq @636
		// @122: bipush -19 (0xED)
		// @124: iload_2
		// @125: iconst_m1
		// @126: ixor
		// @127: if_icmpeq @623
		// @12A: goto @12E
		// @12D: athrow
		// @12E: iload_2
		// @12F: bipush 19 (0x13)
		// @131: if_icmpne @152
		// @134: goto @138
		// @137: athrow
		// @138: aload_1
		// @139: getfield java.lang.Object game.C_100331_ie.field_107299_a
		// @13C: checkcast java.awt.datatransfer.Transferable
		// @13F: astore_3
		// @140: invokestatic java.awt.Toolkit.getDefaultToolkit()java.awt.Toolkit
		// @143: invokevirtual java.awt.Toolkit.getSystemClipboard()java.awt.datatransfer.Clipboard
		// @146: astore #4
		// @148: aload #4
		// @14A: aload_3
		// @14B: aconst_null
		// @14C: invokevirtual java.awt.datatransfer.Clipboard.setContents(java.awt.datatransfer.Transferable, java.awt.datatransfer.ClipboardOwner)void
		// @14F: goto @703
		// @152: aload_0
		// @153: getfield boolean game.C_100201_qj.field_105881_j
		// @156: ifne @164
		// @159: new java.lang.Exception
		// @15C: dup
		// @15D: ldc ""
		// @15F: invokespecial java.lang.Exception.<init>(java.lang.String)void
		// @162: athrow
		// @163: athrow
		// @164: bipush -4 (0xFC)
		// @166: iload_2
		// @167: iconst_m1
		// @168: ixor
		// @169: if_icmpne @1E8
		// @16C: bipush 115 (0x73)
		// @16E: invokestatic game.C_100198_qn.func_105828_a(byte)long
		// @171: ldc2_w -1
		// @174: lxor
		// @175: getstatic long game.C_100201_qj.field_105885_w
		// @178: ldc2_w -1
		// @17B: lxor
		// @17C: lcmp
		// @17D: ifle @18D
		// @180: goto @184
		// @183: athrow
		// @184: new java.io.IOException
		// @187: dup
		// @188: invokespecial java.io.IOException.<init>()void
		// @18B: athrow
		// @18C: athrow
		// @18D: new java.lang.StringBuilder
		// @190: dup
		// @191: invokespecial java.lang.StringBuilder.<init>()void
		// @194: aload_1
		// @195: getfield int game.C_100331_ie.field_107298_c
		// @198: ldc -145693544 (0xf750e498)
		// @19A: ishr
		// @19B: sipush 255 (0x00FF)
		// @19E: iand
		// @19F: invokevirtual java.lang.StringBuilder.append(int)java.lang.StringBuilder
		// @1A2: ldc "."
		// @1A4: invokevirtual java.lang.StringBuilder.append(java.lang.String)java.lang.StringBuilder
		// @1A7: aload_1
		// @1A8: getfield int game.C_100331_ie.field_107298_c
		// @1AB: ldc 16742949 (0xff7a25)
		// @1AD: iand
		// @1AE: ldc -462989968 (0xe4675570)
		// @1B0: ishr
		// @1B1: invokevirtual java.lang.StringBuilder.append(int)java.lang.StringBuilder
		// @1B4: ldc "."
		// @1B6: invokevirtual java.lang.StringBuilder.append(java.lang.String)java.lang.StringBuilder
		// @1B9: ldc 65506 (0xffe2)
		// @1BB: aload_1
		// @1BC: getfield int game.C_100331_ie.field_107298_c
		// @1BF: iand
		// @1C0: ldc -1403170872 (0xac5d4fc8)
		// @1C2: ishr
		// @1C3: invokevirtual java.lang.StringBuilder.append(int)java.lang.StringBuilder
		// @1C6: ldc "."
		// @1C8: invokevirtual java.lang.StringBuilder.append(java.lang.String)java.lang.StringBuilder
		// @1CB: aload_1
		// @1CC: getfield int game.C_100331_ie.field_107298_c
		// @1CF: sipush 255 (0x00FF)
		// @1D2: iand
		// @1D3: invokevirtual java.lang.StringBuilder.append(int)java.lang.StringBuilder
		// @1D6: invokevirtual java.lang.StringBuilder.toString()java.lang.String
		// @1D9: astore_3
		// @1DA: aload_1
		// @1DB: aload_3
		// @1DC: invokestatic java.net.InetAddress.getByName(java.lang.String)java.net.InetAddress
		// @1DF: invokevirtual java.net.InetAddress.getHostName()java.lang.String
		// @1E2: putfield java.lang.Object game.C_100331_ie.field_107294_g
		// @1E5: goto @703
		// @1E8: iload_2
		// @1E9: bipush 21 (0x15)
		// @1EB: if_icmpne @21B
		// @1EE: bipush -46 (0xD2)
		// @1F0: invokestatic game.C_100198_qn.func_105828_a(byte)long
		// @1F3: getstatic long game.C_100201_qj.field_105885_w
		// @1F6: lcmp
		// @1F7: ifge @207
		// @1FA: goto @1FE
		// @1FD: athrow
		// @1FE: new java.io.IOException
		// @201: dup
		// @202: invokespecial java.io.IOException.<init>()void
		// @205: athrow
		// @206: athrow
		// @207: aload_1
		// @208: aload_1
		// @209: getfield java.lang.Object game.C_100331_ie.field_107299_a
		// @20C: checkcast java.lang.String
		// @20F: invokestatic java.net.InetAddress.getByName(java.lang.String)java.net.InetAddress
		// @212: invokevirtual java.net.InetAddress.getAddress()byte[]
		// @215: putfield java.lang.Object game.C_100331_ie.field_107294_g
		// @218: goto @703
		// @21B: bipush -6 (0xFA)
		// @21D: iload_2
		// @21E: iconst_m1
		// @21F: ixor
		// @220: if_icmpne @267
		// @223: aload_0
		// @224: getfield boolean game.C_100201_qj.field_105882_k
		// @227: ifeq @23F
		// @22A: goto @22E
		// @22D: athrow
		// @22E: aload_1
		// @22F: aload_0
		// @230: getfield game.C_100190_rh game.C_100201_qj.field_105873_e
		// @233: bipush -28 (0xE4)
		// @235: invokevirtual game.C_100190_rh.func_105758_a(int)int[]
		// @238: putfield java.lang.Object game.C_100331_ie.field_107294_g
		// @23B: goto @703
		// @23E: athrow
		// @23F: aload_1
		// @240: getstatic java.lang.String[] game.C_100201_qj.field_105893_z
		// @243: bipush 27 (0x1B)
		// @245: aaload
		// @246: invokestatic java.lang.Class.forName(java.lang.String)java.lang.Class
		// @249: getstatic java.lang.String[] game.C_100201_qj.field_105893_z
		// @24C: bipush 38 (0x26)
		// @24E: aaload
		// @24F: iconst_0
		// @250: anewarray java.lang.Class
		// @253: invokevirtual java.lang.Class.getMethod(java.lang.String, java.lang.Class[])java.lang.reflect.Method
		// @256: aload_0
		// @257: getfield java.lang.Object game.C_100201_qj.field_105876_a
		// @25A: iconst_0
		// @25B: anewarray java.lang.Object
		// @25E: invokevirtual java.lang.reflect.Method.invoke(java.lang.Object, java.lang.Object[])java.lang.Object
		// @261: putfield java.lang.Object game.C_100331_ie.field_107294_g
		// @264: goto @703
		// @267: iload_2
		// @268: bipush 6 (0x06)
		// @26A: if_icmpeq @551
		// @26D: iload_2
		// @26E: bipush 7 (0x07)
		// @270: if_icmpne @2BA
		// @273: goto @277
		// @276: athrow
		// @277: aload_0
		// @278: getfield boolean game.C_100201_qj.field_105882_k
		// @27B: ifeq @295
		// @27E: goto @282
		// @281: athrow
		// @282: aload_0
		// @283: getfield game.C_100190_rh game.C_100201_qj.field_105873_e
		// @286: iconst_0
		// @287: aload_1
		// @288: getfield java.lang.Object game.C_100331_ie.field_107299_a
		// @28B: checkcast java.awt.Frame
		// @28E: invokevirtual game.C_100190_rh.func_105759_a(boolean, java.awt.Frame)void
		// @291: goto @703
		// @294: athrow
		// @295: getstatic java.lang.String[] game.C_100201_qj.field_105893_z
		// @298: bipush 27 (0x1B)
		// @29A: aaload
		// @29B: invokestatic java.lang.Class.forName(java.lang.String)java.lang.Class
		// @29E: getstatic java.lang.String[] game.C_100201_qj.field_105893_z
		// @2A1: bipush 33 (0x21)
		// @2A3: aaload
		// @2A4: iconst_0
		// @2A5: anewarray java.lang.Class
		// @2A8: invokevirtual java.lang.Class.getMethod(java.lang.String, java.lang.Class[])java.lang.reflect.Method
		// @2AB: aload_0
		// @2AC: getfield java.lang.Object game.C_100201_qj.field_105876_a
		// @2AF: iconst_0
		// @2B0: anewarray java.lang.Object
		// @2B3: invokevirtual java.lang.reflect.Method.invoke(java.lang.Object, java.lang.Object[])java.lang.Object
		// @2B6: pop
		// @2B7: goto @703
		// @2BA: iload_2
		// @2BB: iconst_m1
		// @2BC: ixor
		// @2BD: bipush -13 (0xF3)
		// @2BF: if_icmpne @2DC
		// @2C2: getstatic java.lang.String game.C_100201_qj.field_105870_f
		// @2C5: iconst_1
		// @2C6: aload_1
		// @2C7: getfield java.lang.Object game.C_100331_ie.field_107299_a
		// @2CA: checkcast java.lang.String
		// @2CD: getstatic int game.C_100201_qj.field_105879_l
		// @2D0: invokestatic game.C_100201_qj.func_105862_a(java.lang.String, boolean, java.lang.String, int)game.C_100005_fk
		// @2D3: astore_3
		// @2D4: aload_1
		// @2D5: aload_3
		// @2D6: putfield java.lang.Object game.C_100331_ie.field_107294_g
		// @2D9: goto @703
		// @2DC: bipush 13 (0x0D)
		// @2DE: iload_2
		// @2DF: if_icmpne @2FB
		// @2E2: ldc ""
		// @2E4: iconst_1
		// @2E5: aload_1
		// @2E6: getfield java.lang.Object game.C_100331_ie.field_107299_a
		// @2E9: checkcast java.lang.String
		// @2EC: getstatic int game.C_100201_qj.field_105879_l
		// @2EF: invokestatic game.C_100201_qj.func_105862_a(java.lang.String, boolean, java.lang.String, int)game.C_100005_fk
		// @2F2: astore_3
		// @2F3: aload_1
		// @2F4: aload_3
		// @2F5: putfield java.lang.Object game.C_100331_ie.field_107294_g
		// @2F8: goto @703
		// @2FB: aload_0
		// @2FC: getfield boolean game.C_100201_qj.field_105881_j
		// @2FF: ifeq @377
		// @302: bipush -15 (0xF1)
		// @304: iload_2
		// @305: iconst_m1
		// @306: ixor
		// @307: if_icmpne @377
		// @30A: goto @30E
		// @30D: athrow
		// @30E: aload_1
		// @30F: getfield int game.C_100331_ie.field_107298_c
		// @312: istore_3
		// @313: aload_1
		// @314: getfield int game.C_100331_ie.field_107296_e
		// @317: istore #4
		// @319: aload_0
		// @31A: getfield boolean game.C_100201_qj.field_105882_k
		// @31D: ifne @369
		// @320: getstatic java.lang.String[] game.C_100201_qj.field_105893_z
		// @323: bipush 17 (0x11)
		// @325: aaload
		// @326: invokestatic java.lang.Class.forName(java.lang.String)java.lang.Class
		// @329: getstatic java.lang.String[] game.C_100201_qj.field_105893_z
		// @32C: bipush 37 (0x25)
		// @32E: aaload
		// @32F: iconst_2
		// @330: anewarray java.lang.Class
		// @333: dup
		// @334: iconst_0
		// @335: getstatic java.lang.Class java.lang.Integer.TYPE
		// @338: aastore
		// @339: dup
		// @33A: iconst_1
		// @33B: getstatic java.lang.Class java.lang.Integer.TYPE
		// @33E: aastore
		// @33F: invokevirtual java.lang.Class.getDeclaredMethod(java.lang.String, java.lang.Class[])java.lang.reflect.Method
		// @342: aload_0
		// @343: getfield java.lang.Object game.C_100201_qj.field_105874_b
		// @346: iconst_2
		// @347: anewarray java.lang.Object
		// @34A: dup
		// @34B: iconst_0
		// @34C: new java.lang.Integer
		// @34F: dup
		// @350: iload_3
		// @351: invokespecial java.lang.Integer.<init>(int)void
		// @354: aastore
		// @355: dup
		// @356: iconst_1
		// @357: new java.lang.Integer
		// @35A: dup
		// @35B: iload #4
		// @35D: invokespecial java.lang.Integer.<init>(int)void
		// @360: aastore
		// @361: invokevirtual java.lang.reflect.Method.invoke(java.lang.Object, java.lang.Object[])java.lang.Object
		// @364: pop
		// @365: goto @374
		// @368: athrow
		// @369: aload_0
		// @36A: getfield game.C_100296_kg game.C_100201_qj.field_105891_q
		// @36D: iload #4
		// @36F: iconst_5
		// @370: iload_3
		// @371: invokevirtual game.C_100296_kg.func_107005_a(int, byte, int)void
		// @374: goto @703
		// @377: aload_0
		// @378: getfield boolean game.C_100201_qj.field_105881_j
		// @37B: ifeq @388
		// @37E: bipush 15 (0x0F)
		// @380: iload_2
		// @381: if_icmpeq @4DF
		// @384: goto @388
		// @387: athrow
		// @388: aload_0
		// @389: getfield boolean game.C_100201_qj.field_105882_k
		// @38C: ifne @416
		// @38F: goto @393
		// @392: athrow
		// @393: bipush 17 (0x11)
		// @395: iload_2
		// @396: if_icmpne @416
		// @399: goto @39D
		// @39C: athrow
		// @39D: aload_1
		// @39E: getfield java.lang.Object game.C_100331_ie.field_107299_a
		// @3A1: checkcast java.lang.Object[]
		// @3A4: checkcast java.lang.Object[]
		// @3A7: astore_3
		// @3A8: getstatic java.lang.String[] game.C_100201_qj.field_105893_z
		// @3AB: bipush 17 (0x11)
		// @3AD: aaload
		// @3AE: invokestatic java.lang.Class.forName(java.lang.String)java.lang.Class
		// @3B1: getstatic java.lang.String[] game.C_100201_qj.field_105893_z
		// @3B4: bipush 41 (0x29)
		// @3B6: aaload
		// @3B7: iconst_5
		// @3B8: anewarray java.lang.Class
		// @3BB: dup
		// @3BC: iconst_0
		// @3BD: ldc Class<java.awt.Component>
		// @3BF: aastore
		// @3C0: dup
		// @3C1: iconst_1
		// @3C2: ldc Class<[I>
		// @3C4: aastore
		// @3C5: dup
		// @3C6: iconst_2
		// @3C7: getstatic java.lang.Class java.lang.Integer.TYPE
		// @3CA: aastore
		// @3CB: dup
		// @3CC: iconst_3
		// @3CD: getstatic java.lang.Class java.lang.Integer.TYPE
		// @3D0: aastore
		// @3D1: dup
		// @3D2: iconst_4
		// @3D3: ldc Class<java.awt.Point>
		// @3D5: aastore
		// @3D6: invokevirtual java.lang.Class.getDeclaredMethod(java.lang.String, java.lang.Class[])java.lang.reflect.Method
		// @3D9: aload_0
		// @3DA: getfield java.lang.Object game.C_100201_qj.field_105874_b
		// @3DD: iconst_5
		// @3DE: anewarray java.lang.Object
		// @3E1: dup
		// @3E2: iconst_0
		// @3E3: aload_3
		// @3E4: iconst_0
		// @3E5: aaload
		// @3E6: aastore
		// @3E7: dup
		// @3E8: iconst_1
		// @3E9: aload_3
		// @3EA: iconst_1
		// @3EB: aaload
		// @3EC: aastore
		// @3ED: dup
		// @3EE: iconst_2
		// @3EF: new java.lang.Integer
		// @3F2: dup
		// @3F3: aload_1
		// @3F4: getfield int game.C_100331_ie.field_107298_c
		// @3F7: invokespecial java.lang.Integer.<init>(int)void
		// @3FA: aastore
		// @3FB: dup
		// @3FC: iconst_3
		// @3FD: new java.lang.Integer
		// @400: dup
		// @401: aload_1
		// @402: getfield int game.C_100331_ie.field_107296_e
		// @405: invokespecial java.lang.Integer.<init>(int)void
		// @408: aastore
		// @409: dup
		// @40A: iconst_4
		// @40B: aload_3
		// @40C: iconst_2
		// @40D: aaload
		// @40E: aastore
		// @40F: invokevirtual java.lang.reflect.Method.invoke(java.lang.Object, java.lang.Object[])java.lang.Object
		// @412: pop
		// @413: goto @703
		// @416: iload_2
		// @417: iconst_m1
		// @418: ixor
		// @419: bipush -17 (0xEF)
		// @41B: if_icmpeq @429
		// @41E: new java.lang.Exception
		// @421: dup
		// @422: ldc ""
		// @424: invokespecial java.lang.Exception.<init>(java.lang.String)void
		// @427: athrow
		// @428: athrow
		// @429: getstatic java.lang.String game.C_100201_qj.field_105872_d
		// @42C: getstatic java.lang.String[] game.C_100201_qj.field_105893_z
		// @42F: bipush 43 (0x2B)
		// @431: aaload
		// @432: invokevirtual java.lang.String.startsWith(java.lang.String)boolean
		// @435: ifne @441
		// @438: new java.lang.Exception
		// @43B: dup
		// @43C: invokespecial java.lang.Exception.<init>()void
		// @43F: athrow
		// @440: athrow
		// @441: aload_1
		// @442: getfield java.lang.Object game.C_100331_ie.field_107299_a
		// @445: checkcast java.lang.String
		// @448: astore_3
		// @449: aload_3
		// @44A: getstatic java.lang.String[] game.C_100201_qj.field_105893_z
		// @44D: bipush 40 (0x28)
		// @44F: aaload
		// @450: invokevirtual java.lang.String.startsWith(java.lang.String)boolean
		// @453: ifne @473
		// @456: aload_3
		// @457: getstatic java.lang.String[] game.C_100201_qj.field_105893_z
		// @45A: bipush 35 (0x23)
		// @45C: aaload
		// @45D: invokevirtual java.lang.String.startsWith(java.lang.String)boolean
		// @460: ifeq @46B
		// @463: goto @467
		// @466: athrow
		// @467: goto @473
		// @46A: athrow
		// @46B: new java.lang.Exception
		// @46E: dup
		// @46F: invokespecial java.lang.Exception.<init>()void
		// @472: athrow
		// @473: getstatic java.lang.String[] game.C_100201_qj.field_105893_z
		// @476: bipush 32 (0x20)
		// @478: aaload
		// @479: astore #4
		// @47B: iconst_0
		// @47C: istore #5
		// @47E: aload_3
		// @47F: invokevirtual java.lang.String.length()int
		// @482: iload #5
		// @484: if_icmple @4AC
		// @487: iconst_m1
		// @488: aload #4
		// @48A: aload_3
		// @48B: iload #5
		// @48D: invokevirtual java.lang.String.charAt(int)char
		// @490: invokevirtual java.lang.String.indexOf(int)int
		// @493: if_icmpeq @49E
		// @496: goto @49A
		// @499: athrow
		// @49A: goto @4A6
		// @49D: athrow
		// @49E: new java.lang.Exception
		// @4A1: dup
		// @4A2: invokespecial java.lang.Exception.<init>()void
		// @4A5: athrow
		// @4A6: iinc #5 +1
		// @4A9: goto @47E
		// @4AC: invokestatic java.lang.Runtime.getRuntime()java.lang.Runtime
		// @4AF: new java.lang.StringBuilder
		// @4B2: dup
		// @4B3: invokespecial java.lang.StringBuilder.<init>()void
		// @4B6: getstatic java.lang.String[] game.C_100201_qj.field_105893_z
		// @4B9: bipush 34 (0x22)
		// @4BB: aaload
		// @4BC: invokevirtual java.lang.StringBuilder.append(java.lang.String)java.lang.StringBuilder
		// @4BF: aload_3
		// @4C0: invokevirtual java.lang.StringBuilder.append(java.lang.String)java.lang.StringBuilder
		// @4C3: ldc "\""
		// @4C5: invokevirtual java.lang.StringBuilder.append(java.lang.String)java.lang.StringBuilder
		// @4C8: invokevirtual java.lang.StringBuilder.toString()java.lang.String
		// @4CB: invokevirtual java.lang.Runtime.exec(java.lang.String)java.lang.Process
		// @4CE: pop
		// @4CF: aload_1
		// @4D0: aconst_null
		// @4D1: putfield java.lang.Object game.C_100331_ie.field_107294_g
		// @4D4: goto @703
		// @4D7: astore_3
		// @4D8: aload_1
		// @4D9: aload_3
		// @4DA: putfield java.lang.Object game.C_100331_ie.field_107294_g
		// @4DD: aload_3
		// @4DE: athrow
		// @4DF: iconst_m1
		// @4E0: aload_1
		// @4E1: getfield int game.C_100331_ie.field_107298_c
		// @4E4: iconst_m1
		// @4E5: ixor
		// @4E6: if_icmpeq @4EE
		// @4E9: iconst_1
		// @4EA: goto @4EF
		// @4ED: athrow
		// @4EE: iconst_0
		// @4EF: istore_3
		// @4F0: aload_1
		// @4F1: getfield java.lang.Object game.C_100331_ie.field_107299_a
		// @4F4: checkcast java.awt.Component
		// @4F7: astore #4
		// @4F9: aload_0
		// @4FA: getfield boolean game.C_100201_qj.field_105882_k
		// @4FD: ifeq @511
		// @500: aload_0
		// @501: getfield game.C_100296_kg game.C_100201_qj.field_105891_q
		// @504: iload_3
		// @505: sipush -32353 (0x819F)
		// @508: aload #4
		// @50A: invokevirtual game.C_100296_kg.func_107006_a(boolean, int, java.awt.Component)void
		// @50D: goto @54E
		// @510: athrow
		// @511: getstatic java.lang.String[] game.C_100201_qj.field_105893_z
		// @514: bipush 17 (0x11)
		// @516: aaload
		// @517: invokestatic java.lang.Class.forName(java.lang.String)java.lang.Class
		// @51A: getstatic java.lang.String[] game.C_100201_qj.field_105893_z
		// @51D: bipush 42 (0x2A)
		// @51F: aaload
		// @520: iconst_2
		// @521: anewarray java.lang.Class
		// @524: dup
		// @525: iconst_0
		// @526: ldc Class<java.awt.Component>
		// @528: aastore
		// @529: dup
		// @52A: iconst_1
		// @52B: getstatic java.lang.Class java.lang.Boolean.TYPE
		// @52E: aastore
		// @52F: invokevirtual java.lang.Class.getDeclaredMethod(java.lang.String, java.lang.Class[])java.lang.reflect.Method
		// @532: aload_0
		// @533: getfield java.lang.Object game.C_100201_qj.field_105874_b
		// @536: iconst_2
		// @537: anewarray java.lang.Object
		// @53A: dup
		// @53B: iconst_0
		// @53C: aload #4
		// @53E: aastore
		// @53F: dup
		// @540: iconst_1
		// @541: new java.lang.Boolean
		// @544: dup
		// @545: iload_3
		// @546: invokespecial java.lang.Boolean.<init>(boolean)void
		// @549: aastore
		// @54A: invokevirtual java.lang.reflect.Method.invoke(java.lang.Object, java.lang.Object[])java.lang.Object
		// @54D: pop
		// @54E: goto @703
		// @551: new java.awt.Frame
		// @554: dup
		// @555: getstatic java.lang.String[] game.C_100201_qj.field_105893_z
		// @558: bipush 36 (0x24)
		// @55A: aaload
		// @55B: invokespecial java.awt.Frame.<init>(java.lang.String)void
		// @55E: astore_3
		// @55F: aload_1
		// @560: aload_3
		// @561: putfield java.lang.Object game.C_100331_ie.field_107294_g
		// @564: aload_3
		// @565: iconst_0
		// @566: invokevirtual java.awt.Frame.setResizable(boolean)void
		// @569: aload_0
		// @56A: getfield boolean game.C_100201_qj.field_105882_k
		// @56D: ifne @5FB
		// @570: getstatic java.lang.String[] game.C_100201_qj.field_105893_z
		// @573: bipush 27 (0x1B)
		// @575: aaload
		// @576: invokestatic java.lang.Class.forName(java.lang.String)java.lang.Class
		// @579: getstatic java.lang.String[] game.C_100201_qj.field_105893_z
		// @57C: bipush 39 (0x27)
		// @57E: aaload
		// @57F: iconst_5
		// @580: anewarray java.lang.Class
		// @583: dup
		// @584: iconst_0
		// @585: ldc Class<java.awt.Frame>
		// @587: aastore
		// @588: dup
		// @589: iconst_1
		// @58A: getstatic java.lang.Class java.lang.Integer.TYPE
		// @58D: aastore
		// @58E: dup
		// @58F: iconst_2
		// @590: getstatic java.lang.Class java.lang.Integer.TYPE
		// @593: aastore
		// @594: dup
		// @595: iconst_3
		// @596: getstatic java.lang.Class java.lang.Integer.TYPE
		// @599: aastore
		// @59A: dup
		// @59B: iconst_4
		// @59C: getstatic java.lang.Class java.lang.Integer.TYPE
		// @59F: aastore
		// @5A0: invokevirtual java.lang.Class.getMethod(java.lang.String, java.lang.Class[])java.lang.reflect.Method
		// @5A3: aload_0
		// @5A4: getfield java.lang.Object game.C_100201_qj.field_105876_a
		// @5A7: iconst_5
		// @5A8: anewarray java.lang.Object
		// @5AB: dup
		// @5AC: iconst_0
		// @5AD: aload_3
		// @5AE: aastore
		// @5AF: dup
		// @5B0: iconst_1
		// @5B1: new java.lang.Integer
		// @5B4: dup
		// @5B5: aload_1
		// @5B6: getfield int game.C_100331_ie.field_107298_c
		// @5B9: ldc 837798832 (0x31efcbb0)
		// @5BB: iushr
		// @5BC: invokespecial java.lang.Integer.<init>(int)void
		// @5BF: aastore
		// @5C0: dup
		// @5C1: iconst_2
		// @5C2: new java.lang.Integer
		// @5C5: dup
		// @5C6: ldc 65535 (0xffff)
		// @5C8: aload_1
		// @5C9: getfield int game.C_100331_ie.field_107298_c
		// @5CC: iand
		// @5CD: invokespecial java.lang.Integer.<init>(int)void
		// @5D0: aastore
		// @5D1: dup
		// @5D2: iconst_3
		// @5D3: new java.lang.Integer
		// @5D6: dup
		// @5D7: aload_1
		// @5D8: getfield int game.C_100331_ie.field_107296_e
		// @5DB: ldc -1411981488 (0xabd6df50)
		// @5DD: ishr
		// @5DE: invokespecial java.lang.Integer.<init>(int)void
		// @5E1: aastore
		// @5E2: dup
		// @5E3: iconst_4
		// @5E4: new java.lang.Integer
		// @5E7: dup
		// @5E8: aload_1
		// @5E9: getfield int game.C_100331_ie.field_107296_e
		// @5EC: ldc 65535 (0xffff)
		// @5EE: iand
		// @5EF: invokespecial java.lang.Integer.<init>(int)void
		// @5F2: aastore
		// @5F3: invokevirtual java.lang.reflect.Method.invoke(java.lang.Object, java.lang.Object[])java.lang.Object
		// @5F6: pop
		// @5F7: goto @620
		// @5FA: athrow
		// @5FB: aload_0
		// @5FC: getfield game.C_100190_rh game.C_100201_qj.field_105873_e
		// @5FF: aload_1
		// @600: getfield int game.C_100331_ie.field_107298_c
		// @603: ldc 65535 (0xffff)
		// @605: iand
		// @606: iconst_0
		// @607: aload_1
		// @608: getfield int game.C_100331_ie.field_107298_c
		// @60B: ldc -1148891120 (0xbb855010)
		// @60D: iushr
		// @60E: aload_1
		// @60F: getfield int game.C_100331_ie.field_107296_e
		// @612: ldc -1449386288 (0xa99c1ed0)
		// @614: ishr
		// @615: aload_3
		// @616: aload_1
		// @617: getfield int game.C_100331_ie.field_107296_e
		// @61A: ldc 65535 (0xffff)
		// @61C: iand
		// @61D: invokevirtual game.C_100190_rh.func_105760_a(int, int, int, int, java.awt.Frame, int)void
		// @620: goto @703
		// @623: invokestatic java.awt.Toolkit.getDefaultToolkit()java.awt.Toolkit
		// @626: invokevirtual java.awt.Toolkit.getSystemClipboard()java.awt.datatransfer.Clipboard
		// @629: astore_3
		// @62A: aload_1
		// @62B: aload_3
		// @62C: aconst_null
		// @62D: invokevirtual java.awt.datatransfer.Clipboard.getContents(java.lang.Object)java.awt.datatransfer.Transferable
		// @630: putfield java.lang.Object game.C_100331_ie.field_107294_g
		// @633: goto @703
		// @636: aload_1
		// @637: getfield java.lang.Object game.C_100331_ie.field_107299_a
		// @63A: checkcast java.lang.Object[]
		// @63D: checkcast java.lang.Object[]
		// @640: astore_3
		// @641: aload_0
		// @642: getfield boolean game.C_100201_qj.field_105881_j
		// @645: ifeq @662
		// @648: aconst_null
		// @649: aload_3
		// @64A: iconst_0
		// @64B: aaload
		// @64C: checkcast java.lang.Class
		// @64F: invokevirtual java.lang.Class.getClassLoader()java.lang.ClassLoader
		// @652: if_acmpne @662
		// @655: goto @659
		// @658: athrow
		// @659: new java.lang.SecurityException
		// @65C: dup
		// @65D: invokespecial java.lang.SecurityException.<init>()void
		// @660: athrow
		// @661: athrow
		// @662: aload_1
		// @663: aload_3
		// @664: iconst_0
		// @665: aaload
		// @666: checkcast java.lang.Class
		// @669: aload_3
		// @66A: iconst_1
		// @66B: aaload
		// @66C: checkcast java.lang.String
		// @66F: invokevirtual java.lang.Class.getDeclaredField(java.lang.String)java.lang.reflect.Field
		// @672: putfield java.lang.Object game.C_100331_ie.field_107294_g
		// @675: goto @703
		// @678: getstatic long game.C_100201_qj.field_105885_w
		// @67B: ldc2_w -1
		// @67E: lxor
		// @67F: bipush 59 (0x3B)
		// @681: invokestatic game.C_100198_qn.func_105828_a(byte)long
		// @684: ldc2_w -1
		// @687: lxor
		// @688: lcmp
		// @689: ifge @695
		// @68C: new java.io.IOException
		// @68F: dup
		// @690: invokespecial java.io.IOException.<init>()void
		// @693: athrow
		// @694: athrow
		// @695: aload_1
		// @696: new java.io.DataInputStream
		// @699: dup
		// @69A: aload_1
		// @69B: getfield java.lang.Object game.C_100331_ie.field_107299_a
		// @69E: checkcast java.net.URL
		// @6A1: invokevirtual java.net.URL.openStream()java.io.InputStream
		// @6A4: invokespecial java.io.DataInputStream.<init>(java.io.InputStream)void
		// @6A7: putfield java.lang.Object game.C_100331_ie.field_107294_g
		// @6AA: goto @703
		// @6AD: new java.lang.Thread
		// @6B0: dup
		// @6B1: aload_1
		// @6B2: getfield java.lang.Object game.C_100331_ie.field_107299_a
		// @6B5: checkcast java.lang.Runnable
		// @6B8: invokespecial java.lang.Thread.<init>(java.lang.Runnable)void
		// @6BB: astore_3
		// @6BC: aload_3
		// @6BD: iconst_1
		// @6BE: invokevirtual java.lang.Thread.setDaemon(boolean)void
		// @6C1: aload_3
		// @6C2: invokevirtual java.lang.Thread.start()void
		// @6C5: aload_3
		// @6C6: aload_1
		// @6C7: getfield int game.C_100331_ie.field_107298_c
		// @6CA: invokevirtual java.lang.Thread.setPriority(int)void
		// @6CD: aload_1
		// @6CE: aload_3
		// @6CF: putfield java.lang.Object game.C_100331_ie.field_107294_g
		// @6D2: goto @703
		// @6D5: bipush -37 (0xDB)
		// @6D7: invokestatic game.C_100198_qn.func_105828_a(byte)long
		// @6DA: getstatic long game.C_100201_qj.field_105885_w
		// @6DD: lcmp
		// @6DE: ifge @6EA
		// @6E1: new java.io.IOException
		// @6E4: dup
		// @6E5: invokespecial java.io.IOException.<init>()void
		// @6E8: athrow
		// @6E9: athrow
		// @6EA: aload_1
		// @6EB: new java.net.Socket
		// @6EE: dup
		// @6EF: aload_1
		// @6F0: getfield java.lang.Object game.C_100331_ie.field_107299_a
		// @6F3: checkcast java.lang.String
		// @6F6: invokestatic java.net.InetAddress.getByName(java.lang.String)java.net.InetAddress
		// @6F9: aload_1
		// @6FA: getfield int game.C_100331_ie.field_107298_c
		// @6FD: invokespecial java.net.Socket.<init>(java.net.InetAddress, int)void
		// @700: putfield java.lang.Object game.C_100331_ie.field_107294_g
		// @703: aload_1
		// @704: iconst_1
		// @705: putfield int game.C_100331_ie.field_107293_f
		// @708: goto @714
		// @70B: astore_2
		// @70C: aload_2
		// @70D: athrow
		// @70E: astore_2
		// @70F: aload_1
		// @710: iconst_2
		// @711: putfield int game.C_100331_ie.field_107293_f
		// @714: aload_1
		// @715: dup
		// @716: astore_2
		// @717: monitorenter
		// @718: aload_1
		// @719: invokevirtual java.lang.Object.notify()void
		// @71C: aload_2
		// @71D: monitorexit
		// @71E: goto @728
		// @721: astore #6
		// @723: aload_2
		// @724: monitorexit
		// @725: aload #6
		// @727: athrow
		// @728: goto @000
		// @72B: astore_1
		// @72C: aload_1
		// @72D: athrow
	}
	
	final C_100331_ie func_105857_a(byte arg0, int arg1, String arg2)
	{
		// @00: iload_1
		// @01: bipush 14 (0x0E)
		// @03: if_icmpgt @15
		// @06: aload_0
		// @07: aconst_null
		// @08: checkcast java.net.URL
		// @0B: bipush -2 (0xFE)
		// @0D: invokevirtual game.C_100201_qj.func_105863_a(java.net.URL, int)game.C_100331_ie
		// @10: pop
		// @11: goto @15
		// @14: athrow
		// @15: aload_0
		// @16: aload_3
		// @17: iload_2
		// @18: ldc 65535 (0xffff)
		// @1A: iconst_0
		// @1B: invokespecial game.C_100201_qj.func_105866_a(java.lang.String, int, int, boolean)game.C_100331_ie
		// @1E: areturn
		// @1F: astore #4
		// @21: aload #4
		// @23: athrow
	}
	
	private final C_100331_ie func_105866_a(String arg0, int arg1, int arg2, boolean arg3)
	{
		// @00: iload_3
		// @01: ldc 65535 (0xffff)
		// @03: if_icmpeq @12
		// @06: aload_0
		// @07: aconst_null
		// @08: checkcast game.C_100005_fk
		// @0B: putfield game.C_100005_fk game.C_100201_qj.field_105875_c
		// @0E: goto @12
		// @11: athrow
		// @12: aload_0
		// @13: iload_2
		// @14: aload_1
		// @15: iload #4
		// @17: ifeq @20
		// @1A: bipush 22 (0x16)
		// @1C: goto @21
		// @1F: athrow
		// @20: iconst_1
		// @21: iconst_0
		// @22: iload_3
		// @23: ldc -66458 (0xfffefc66)
		// @25: iadd
		// @26: invokespecial game.C_100201_qj.func_105855_a(int, java.lang.Object, int, int, int)game.C_100331_ie
		// @29: areturn
		// @2A: astore #5
		// @2C: aload #5
		// @2E: athrow
	}
	
	final C_100331_ie func_105863_a(URL arg0, int arg1)
	{
		// @00: iload_2
		// @01: sipush 2159 (0x086F)
		// @04: if_icmpeq @13
		// @07: aload_0
		// @08: aconst_null
		// @09: checkcast java.lang.Object
		// @0C: putfield java.lang.Object game.C_100201_qj.field_105874_b
		// @0F: goto @13
		// @12: athrow
		// @13: aload_0
		// @14: iconst_0
		// @15: aload_1
		// @16: iconst_4
		// @17: iconst_0
		// @18: sipush -923 (0xFC65)
		// @1B: invokespecial game.C_100201_qj.func_105855_a(int, java.lang.Object, int, int, int)game.C_100331_ie
		// @1E: areturn
		// @1F: astore_3
		// @20: aload_3
		// @21: athrow
	}
	
	final void func_105858_b(int arg0)
	{
		// @00: aload_0
		// @01: dup
		// @02: astore_2
		// @03: monitorenter
		// @04: bipush -33 (0xDF)
		// @06: iload_1
		// @07: bipush -16 (0xF0)
		// @09: isub
		// @0A: bipush 55 (0x37)
		// @0C: idiv
		// @0D: irem
		// @0E: istore_3
		// @0F: aload_0
		// @10: iconst_1
		// @11: putfield boolean game.C_100201_qj.field_105889_s
		// @14: aload_0
		// @15: invokevirtual java.lang.Object.notifyAll()void
		// @18: aload_2
		// @19: monitorexit
		// @1A: goto @24
		// @1D: astore #4
		// @1F: aload_2
		// @20: monitorexit
		// @21: aload #4
		// @23: athrow
		// @24: aload_0
		// @25: getfield java.lang.Thread game.C_100201_qj.field_105877_n
		// @28: invokevirtual java.lang.Thread.join()void
		// @2B: goto @2F
		// @2E: astore_2
		// @2F: aload_0
		// @30: getfield game.C_100005_fk game.C_100201_qj.field_105892_p
		// @33: ifnull @44
		// @36: aload_0
		// @37: getfield game.C_100005_fk game.C_100201_qj.field_105892_p
		// @3A: bipush 61 (0x3D)
		// @3C: invokevirtual game.C_100005_fk.func_103586_b(byte)void
		// @3F: goto @44
		// @42: athrow
		// @43: astore_2
		// @44: aload_0
		// @45: getfield game.C_100005_fk game.C_100201_qj.field_105888_t
		// @48: ifnull @59
		// @4B: aload_0
		// @4C: getfield game.C_100005_fk game.C_100201_qj.field_105888_t
		// @4F: bipush 61 (0x3D)
		// @51: invokevirtual game.C_100005_fk.func_103586_b(byte)void
		// @54: goto @59
		// @57: athrow
		// @58: astore_2
		// @59: aconst_null
		// @5A: aload_0
		// @5B: getfield game.C_100005_fk[] game.C_100201_qj.field_105883_h
		// @5E: if_acmpne @65
		// @61: goto @93
		// @64: athrow
		// @65: iconst_0
		// @66: istore_2
		// @67: aload_0
		// @68: getfield game.C_100005_fk[] game.C_100201_qj.field_105883_h
		// @6B: arraylength
		// @6C: iload_2
		// @6D: if_icmple @93
		// @70: aload_0
		// @71: getfield game.C_100005_fk[] game.C_100201_qj.field_105883_h
		// @74: iload_2
		// @75: aaload
		// @76: ifnull @8D
		// @79: goto @7D
		// @7C: athrow
		// @7D: aload_0
		// @7E: getfield game.C_100005_fk[] game.C_100201_qj.field_105883_h
		// @81: iload_2
		// @82: aaload
		// @83: bipush 61 (0x3D)
		// @85: invokevirtual game.C_100005_fk.func_103586_b(byte)void
		// @88: goto @8D
		// @8B: athrow
		// @8C: astore_3
		// @8D: iinc #2 +1
		// @90: goto @67
		// @93: aconst_null
		// @94: aload_0
		// @95: getfield game.C_100005_fk game.C_100201_qj.field_105875_c
		// @98: if_acmpeq @A9
		// @9B: aload_0
		// @9C: getfield game.C_100005_fk game.C_100201_qj.field_105875_c
		// @9F: bipush 61 (0x3D)
		// @A1: invokevirtual game.C_100005_fk.func_103586_b(byte)void
		// @A4: goto @A9
		// @A7: athrow
		// @A8: astore_2
		// @A9: goto @AF
		// @AC: astore_2
		// @AD: aload_2
		// @AE: athrow
		// @AF: return
	}
	
	C_100201_qj(int arg0, String arg1, int arg2, boolean arg3) throws Exception
	{
		// @000: aload_0
		// @001: invokespecial java.lang.Object.<init>()void
		// @004: aload_0
		// @005: iconst_0
		// @006: putfield boolean game.C_100201_qj.field_105881_j
		// @009: aload_0
		// @00A: aconst_null
		// @00B: putfield game.C_100331_ie game.C_100201_qj.field_105884_i
		// @00E: aload_0
		// @00F: aconst_null
		// @010: putfield game.C_100005_fk game.C_100201_qj.field_105875_c
		// @013: aload_0
		// @014: iconst_0
		// @015: putfield boolean game.C_100201_qj.field_105882_k
		// @018: aload_0
		// @019: aconst_null
		// @01A: putfield game.C_100005_fk game.C_100201_qj.field_105888_t
		// @01D: aload_0
		// @01E: aconst_null
		// @01F: putfield game.C_100331_ie game.C_100201_qj.field_105894_x
		// @022: aload_0
		// @023: iconst_0
		// @024: putfield boolean game.C_100201_qj.field_105889_s
		// @027: aload_0
		// @028: aconst_null
		// @029: putfield game.C_100005_fk game.C_100201_qj.field_105892_p
		// @02C: aload_0
		// @02D: iload #4
		// @02F: putfield boolean game.C_100201_qj.field_105881_j
		// @032: iload_1
		// @033: putstatic int game.C_100201_qj.field_105879_l
		// @036: getstatic java.lang.String[] game.C_100201_qj.field_105893_z
		// @039: bipush 25 (0x19)
		// @03B: aaload
		// @03C: putstatic java.lang.String game.C_100201_qj.field_105887_u
		// @03F: aload_2
		// @040: putstatic java.lang.String game.C_100201_qj.field_105870_f
		// @043: getstatic java.lang.String[] game.C_100201_qj.field_105893_z
		// @046: bipush 28 (0x1C)
		// @048: aaload
		// @049: putstatic java.lang.String game.C_100201_qj.field_105886_v
		// @04C: getstatic java.lang.String[] game.C_100201_qj.field_105893_z
		// @04F: bipush 19 (0x13)
		// @051: aaload
		// @052: invokestatic java.lang.System.getProperty(java.lang.String)java.lang.String
		// @055: putstatic java.lang.String game.C_100201_qj.field_105887_u
		// @058: getstatic java.lang.String[] game.C_100201_qj.field_105893_z
		// @05B: bipush 31 (0x1F)
		// @05D: aaload
		// @05E: invokestatic java.lang.System.getProperty(java.lang.String)java.lang.String
		// @061: putstatic java.lang.String game.C_100201_qj.field_105886_v
		// @064: goto @069
		// @067: astore #5
		// @069: iconst_0
		// @06A: getstatic java.lang.String game.C_100201_qj.field_105887_u
		// @06D: invokevirtual java.lang.String.toLowerCase()java.lang.String
		// @070: getstatic java.lang.String[] game.C_100201_qj.field_105893_z
		// @073: bipush 26 (0x1A)
		// @075: aaload
		// @076: invokevirtual java.lang.String.indexOf(java.lang.String)int
		// @079: iconst_m1
		// @07A: ixor
		// @07B: if_icmpne @082
		// @07E: goto @087
		// @081: athrow
		// @082: aload_0
		// @083: iconst_1
		// @084: putfield boolean game.C_100201_qj.field_105882_k
		// @087: getstatic java.lang.String[] game.C_100201_qj.field_105893_z
		// @08A: bipush 20 (0x14)
		// @08C: aaload
		// @08D: invokestatic java.lang.System.getProperty(java.lang.String)java.lang.String
		// @090: putstatic java.lang.String game.C_100201_qj.field_105890_r
		// @093: goto @0A1
		// @096: astore #5
		// @098: getstatic java.lang.String[] game.C_100201_qj.field_105893_z
		// @09B: bipush 25 (0x19)
		// @09D: aaload
		// @09E: putstatic java.lang.String game.C_100201_qj.field_105890_r
		// @0A1: getstatic java.lang.String game.C_100201_qj.field_105890_r
		// @0A4: invokevirtual java.lang.String.toLowerCase()java.lang.String
		// @0A7: putstatic java.lang.String game.C_100201_qj.field_105872_d
		// @0AA: getstatic java.lang.String[] game.C_100201_qj.field_105893_z
		// @0AD: bipush 12 (0x0C)
		// @0AF: aaload
		// @0B0: invokestatic java.lang.System.getProperty(java.lang.String)java.lang.String
		// @0B3: invokevirtual java.lang.String.toLowerCase()java.lang.String
		// @0B6: pop
		// @0B7: goto @0BC
		// @0BA: astore #5
		// @0BC: getstatic java.lang.String[] game.C_100201_qj.field_105893_z
		// @0BF: bipush 15 (0x0F)
		// @0C1: aaload
		// @0C2: invokestatic java.lang.System.getProperty(java.lang.String)java.lang.String
		// @0C5: invokevirtual java.lang.String.toLowerCase()java.lang.String
		// @0C8: pop
		// @0C9: goto @0CE
		// @0CC: astore #5
		// @0CE: getstatic java.lang.String[] game.C_100201_qj.field_105893_z
		// @0D1: bipush 30 (0x1E)
		// @0D3: aaload
		// @0D4: invokestatic java.lang.System.getProperty(java.lang.String)java.lang.String
		// @0D7: putstatic java.lang.String game.C_100201_qj.field_105878_o
		// @0DA: aconst_null
		// @0DB: getstatic java.lang.String game.C_100201_qj.field_105878_o
		// @0DE: if_acmpne @0E5
		// @0E1: goto @0FD
		// @0E4: athrow
		// @0E5: new java.lang.StringBuilder
		// @0E8: dup
		// @0E9: invokespecial java.lang.StringBuilder.<init>()void
		// @0EC: getstatic java.lang.String game.C_100201_qj.field_105878_o
		// @0EF: invokevirtual java.lang.StringBuilder.append(java.lang.String)java.lang.StringBuilder
		// @0F2: ldc "/"
		// @0F4: invokevirtual java.lang.StringBuilder.append(java.lang.String)java.lang.StringBuilder
		// @0F7: invokevirtual java.lang.StringBuilder.toString()java.lang.String
		// @0FA: putstatic java.lang.String game.C_100201_qj.field_105878_o
		// @0FD: goto @102
		// @100: astore #5
		// @102: getstatic java.lang.String game.C_100201_qj.field_105878_o
		// @105: ifnull @10C
		// @108: goto @115
		// @10B: athrow
		// @10C: getstatic java.lang.String[] game.C_100201_qj.field_105893_z
		// @10F: bipush 16 (0x10)
		// @111: aaload
		// @112: putstatic java.lang.String game.C_100201_qj.field_105878_o
		// @115: aload_0
		// @116: invokestatic java.awt.Toolkit.getDefaultToolkit()java.awt.Toolkit
		// @119: invokevirtual java.awt.Toolkit.getSystemEventQueue()java.awt.EventQueue
		// @11C: putfield java.awt.EventQueue game.C_100201_qj.field_105871_g
		// @11F: goto @124
		// @122: astore #5
		// @124: aload_0
		// @125: getfield boolean game.C_100201_qj.field_105882_k
		// @128: ifeq @12F
		// @12B: goto @175
		// @12E: athrow
		// @12F: getstatic java.lang.String[] game.C_100201_qj.field_105893_z
		// @132: bipush 18 (0x12)
		// @134: aaload
		// @135: invokestatic java.lang.Class.forName(java.lang.String)java.lang.Class
		// @138: getstatic java.lang.String[] game.C_100201_qj.field_105893_z
		// @13B: bipush 13 (0x0D)
		// @13D: aaload
		// @13E: iconst_1
		// @13F: anewarray java.lang.Class
		// @142: dup
		// @143: iconst_0
		// @144: getstatic java.lang.Class java.lang.Boolean.TYPE
		// @147: aastore
		// @148: invokevirtual java.lang.Class.getDeclaredMethod(java.lang.String, java.lang.Class[])java.lang.reflect.Method
		// @14B: pop
		// @14C: goto @151
		// @14F: astore #5
		// @151: getstatic java.lang.String[] game.C_100201_qj.field_105893_z
		// @154: bipush 14 (0x0E)
		// @156: aaload
		// @157: invokestatic java.lang.Class.forName(java.lang.String)java.lang.Class
		// @15A: getstatic java.lang.String[] game.C_100201_qj.field_105893_z
		// @15D: bipush 23 (0x17)
		// @15F: aaload
		// @160: iconst_1
		// @161: anewarray java.lang.Class
		// @164: dup
		// @165: iconst_0
		// @166: getstatic java.lang.Class java.lang.Boolean.TYPE
		// @169: aastore
		// @16A: invokevirtual java.lang.Class.getDeclaredMethod(java.lang.String, java.lang.Class[])java.lang.reflect.Method
		// @16D: putstatic java.lang.reflect.Method game.C_100201_qj.field_105880_m
		// @170: goto @175
		// @173: astore #5
		// @175: getstatic java.lang.String game.C_100201_qj.field_105870_f
		// @178: iconst_1
		// @179: getstatic int game.C_100201_qj.field_105879_l
		// @17C: invokestatic game.C_100040_wc.func_104086_a(java.lang.String, boolean, int)void
		// @17F: aload_0
		// @180: getfield boolean game.C_100201_qj.field_105881_j
		// @183: ifne @18A
		// @186: goto @2A5
		// @189: athrow
		// @18A: aload_0
		// @18B: new game.C_100005_fk
		// @18E: dup
		// @18F: getstatic int game.C_100201_qj.field_105879_l
		// @192: iconst_0
		// @193: aconst_null
		// @194: getstatic java.lang.String[] game.C_100201_qj.field_105893_z
		// @197: bipush 22 (0x16)
		// @199: aaload
		// @19A: invokestatic game.C_100040_wc.func_104090_a(int, int, java.lang.String, java.lang.String)java.io.File
		// @19D: getstatic java.lang.String[] game.C_100201_qj.field_105893_z
		// @1A0: iconst_2
		// @1A1: aaload
		// @1A2: ldc2_w 25
		// @1A5: invokespecial game.C_100005_fk.<init>(java.io.File, java.lang.String, long)void
		// @1A8: putfield game.C_100005_fk game.C_100201_qj.field_105875_c
		// @1AB: aload_0
		// @1AC: new game.C_100005_fk
		// @1AF: dup
		// @1B0: bipush -107 (0x95)
		// @1B2: getstatic java.lang.String[] game.C_100201_qj.field_105893_z
		// @1B5: bipush 29 (0x1D)
		// @1B7: aaload
		// @1B8: invokestatic game.C_100040_wc.func_104089_a(byte, java.lang.String)java.io.File
		// @1BB: getstatic java.lang.String[] game.C_100201_qj.field_105893_z
		// @1BE: iconst_2
		// @1BF: aaload
		// @1C0: ldc2_w 314572800
		// @1C3: invokespecial game.C_100005_fk.<init>(java.io.File, java.lang.String, long)void
		// @1C6: putfield game.C_100005_fk game.C_100201_qj.field_105892_p
		// @1C9: aload_0
		// @1CA: new game.C_100005_fk
		// @1CD: dup
		// @1CE: bipush -121 (0x87)
		// @1D0: getstatic java.lang.String[] game.C_100201_qj.field_105893_z
		// @1D3: bipush 24 (0x18)
		// @1D5: aaload
		// @1D6: invokestatic game.C_100040_wc.func_104089_a(byte, java.lang.String)java.io.File
		// @1D9: getstatic java.lang.String[] game.C_100201_qj.field_105893_z
		// @1DC: iconst_2
		// @1DD: aaload
		// @1DE: ldc2_w 1048576
		// @1E1: invokespecial game.C_100005_fk.<init>(java.io.File, java.lang.String, long)void
		// @1E4: putfield game.C_100005_fk game.C_100201_qj.field_105888_t
		// @1E7: aload_0
		// @1E8: iload_3
		// @1E9: anewarray game.C_100005_fk
		// @1EC: putfield game.C_100005_fk[] game.C_100201_qj.field_105883_h
		// @1EF: iconst_0
		// @1F0: istore #5
		// @1F2: iload #5
		// @1F4: iconst_m1
		// @1F5: ixor
		// @1F6: iload_3
		// @1F7: iconst_m1
		// @1F8: ixor
		// @1F9: if_icmple @236
		// @1FC: aload_0
		// @1FD: getfield game.C_100005_fk[] game.C_100201_qj.field_105883_h
		// @200: iload #5
		// @202: new game.C_100005_fk
		// @205: dup
		// @206: bipush -70 (0xBA)
		// @208: new java.lang.StringBuilder
		// @20B: dup
		// @20C: invokespecial java.lang.StringBuilder.<init>()void
		// @20F: getstatic java.lang.String[] game.C_100201_qj.field_105893_z
		// @212: bipush 21 (0x15)
		// @214: aaload
		// @215: invokevirtual java.lang.StringBuilder.append(java.lang.String)java.lang.StringBuilder
		// @218: iload #5
		// @21A: invokevirtual java.lang.StringBuilder.append(int)java.lang.StringBuilder
		// @21D: invokevirtual java.lang.StringBuilder.toString()java.lang.String
		// @220: invokestatic game.C_100040_wc.func_104089_a(byte, java.lang.String)java.io.File
		// @223: getstatic java.lang.String[] game.C_100201_qj.field_105893_z
		// @226: iconst_2
		// @227: aaload
		// @228: ldc2_w 1048576
		// @22B: invokespecial game.C_100005_fk.<init>(java.io.File, java.lang.String, long)void
		// @22E: aastore
		// @22F: iinc #5 +1
		// @232: goto @1F2
		// @235: athrow
		// @236: aload_0
		// @237: getfield boolean game.C_100201_qj.field_105882_k
		// @23A: ifne @241
		// @23D: goto @24F
		// @240: athrow
		// @241: ldc "game.C_100109_t"
		// @243: invokestatic java.lang.Class.forName(java.lang.String)java.lang.Class
		// @246: invokevirtual java.lang.Class.newInstance()java.lang.Object
		// @249: pop
		// @24A: goto @24F
		// @24D: astore #5
		// @24F: aload_0
		// @250: getfield boolean game.C_100201_qj.field_105882_k
		// @253: ifeq @265
		// @256: aload_0
		// @257: new game.C_100190_rh
		// @25A: dup
		// @25B: invokespecial game.C_100190_rh.<init>()void
		// @25E: putfield game.C_100190_rh game.C_100201_qj.field_105873_e
		// @261: goto @275
		// @264: athrow
		// @265: aload_0
		// @266: getstatic java.lang.String[] game.C_100201_qj.field_105893_z
		// @269: bipush 27 (0x1B)
		// @26B: aaload
		// @26C: invokestatic java.lang.Class.forName(java.lang.String)java.lang.Class
		// @26F: invokevirtual java.lang.Class.newInstance()java.lang.Object
		// @272: putfield java.lang.Object game.C_100201_qj.field_105876_a
		// @275: goto @27A
		// @278: astore #5
		// @27A: aload_0
		// @27B: getfield boolean game.C_100201_qj.field_105882_k
		// @27E: ifeq @290
		// @281: aload_0
		// @282: new game.C_100296_kg
		// @285: dup
		// @286: invokespecial game.C_100296_kg.<init>()void
		// @289: putfield game.C_100296_kg game.C_100201_qj.field_105891_q
		// @28C: goto @2A0
		// @28F: athrow
		// @290: aload_0
		// @291: getstatic java.lang.String[] game.C_100201_qj.field_105893_z
		// @294: bipush 17 (0x11)
		// @296: aaload
		// @297: invokestatic java.lang.Class.forName(java.lang.String)java.lang.Class
		// @29A: invokevirtual java.lang.Class.newInstance()java.lang.Object
		// @29D: putfield java.lang.Object game.C_100201_qj.field_105874_b
		// @2A0: goto @2A5
		// @2A3: astore #5
		// @2A5: aload_0
		// @2A6: iconst_0
		// @2A7: putfield boolean game.C_100201_qj.field_105889_s
		// @2AA: aload_0
		// @2AB: new java.lang.Thread
		// @2AE: dup
		// @2AF: aload_0
		// @2B0: invokespecial java.lang.Thread.<init>(java.lang.Runnable)void
		// @2B3: putfield java.lang.Thread game.C_100201_qj.field_105877_n
		// @2B6: aload_0
		// @2B7: getfield java.lang.Thread game.C_100201_qj.field_105877_n
		// @2BA: bipush 10 (0x0A)
		// @2BC: invokevirtual java.lang.Thread.setPriority(int)void
		// @2BF: aload_0
		// @2C0: getfield java.lang.Thread game.C_100201_qj.field_105877_n
		// @2C3: iconst_1
		// @2C4: invokevirtual java.lang.Thread.setDaemon(boolean)void
		// @2C7: aload_0
		// @2C8: getfield java.lang.Thread game.C_100201_qj.field_105877_n
		// @2CB: invokevirtual java.lang.Thread.start()void
		// @2CE: goto @2D6
		// @2D1: astore #5
		// @2D3: aload #5
		// @2D5: athrow
		// @2D6: return
	}
	
	static
	{
		// @000: bipush 44 (0x2C)
		// @002: anewarray java.lang.String
		// @005: dup
		// @006: iconst_0
		// @007: ldc "E\u00089RAHVyR[\t"
		// @009: invokestatic game.C_100201_qj.func_105860_z(java.lang.String)char[]
		// @00C: invokestatic game.C_100201_qj.func_105859_z(char[])java.lang.String
		// @00F: aastore
		// @010: dup
		// @011: iconst_1
		// @012: ldc "y@u\u000bLGF"
		// @014: invokestatic game.C_100201_qj.func_105860_z(java.lang.String)char[]
		// @017: invokestatic game.C_100201_qj.func_105859_z(char[])java.lang.String
		// @01A: aastore
		// @01B: dup
		// @01C: iconst_2
		// @01D: ldc "TE"
		// @01F: invokestatic game.C_100201_qj.func_105860_z(java.lang.String)char[]
		// @022: invokestatic game.C_100201_qj.func_105859_z(char[])java.lang.String
		// @025: aastore
		// @026: dup
		// @027: iconst_3
		// @028: ldc "\tF{U\u0007"
		// @02A: invokestatic game.C_100201_qj.func_105860_z(java.lang.String)char[]
		// @02D: invokestatic game.C_100201_qj.func_105859_z(char[])java.lang.String
		// @030: aastore
		// @031: dup
		// @032: iconst_4
		// @033: ldc "yBd@NC@sKKCA"
		// @035: invokestatic game.C_100201_qj.func_105860_z(java.lang.String)char[]
		// @038: invokestatic game.C_100201_qj.func_105859_z(char[])java.lang.String
		// @03B: aastore
		// @03C: dup
		// @03D: iconst_5
		// @03E: ldc "\t@eFIEZs\n"
		// @040: invokestatic game.C_100201_qj.func_105860_z(java.lang.String)char[]
		// @043: invokestatic game.C_100201_qj.func_105859_z(char[])java.lang.String
		// @046: aastore
		// @047: dup
		// @048: bipush 6 (0x06)
		// @04A: ldc "yE\u007fU\u0006BSb"
		// @04C: invokestatic game.C_100201_qj.func_105860_z(java.lang.String)char[]
		// @04F: invokestatic game.C_100201_qj.func_105859_z(char[])java.lang.String
		// @052: aastore
		// @053: dup
		// @054: bipush 7 (0x07)
		// @056: ldc "LSq@Py"
		// @058: invokestatic game.C_100201_qj.func_105860_z(java.lang.String)char[]
		// @05B: invokestatic game.C_100201_qj.func_105859_z(char[])java.lang.String
		// @05E: aastore
		// @05F: dup
		// @060: bipush 8 (0x08)
		// @062: ldc "E\u00089"
		// @064: invokestatic game.C_100201_qj.func_105860_z(java.lang.String)char[]
		// @067: invokestatic game.C_100201_qj.func_105859_z(char[])java.lang.String
		// @06A: aastore
		// @06B: dup
		// @06C: bipush 9 (0x09)
		// @06E: ldc "\u0008VwQ"
		// @070: invokestatic game.C_100201_qj.func_105860_z(java.lang.String)char[]
		// @073: invokestatic game.C_100201_qj.func_105859_z(char[])java.lang.String
		// @076: aastore
		// @077: dup
		// @078: bipush 10 (0x0A)
		// @07A: ldc "E\u00089RAH\\b\n"
		// @07C: invokestatic game.C_100201_qj.func_105860_z(java.lang.String)char[]
		// @07F: invokestatic game.C_100201_qj.func_105859_z(char[])java.lang.String
		// @082: aastore
		// @083: dup
		// @084: bipush 11 (0x0B)
		// @086: ldc "E\u00089W[ESuMM\t"
		// @088: invokestatic game.C_100201_qj.func_105860_z(java.lang.String)char[]
		// @08B: invokestatic game.C_100201_qj.func_105859_z(char[])java.lang.String
		// @08E: aastore
		// @08F: dup
		// @090: bipush 12 (0x0C)
		// @092: ldc "IA8DZEZ"
		// @094: invokestatic game.C_100201_qj.func_105860_z(java.lang.String)char[]
		// @097: invokestatic game.C_100201_qj.func_105859_z(char[])java.lang.String
		// @09A: aastore
		// @09B: dup
		// @09C: bipush 13 (0x0D)
		// @09E: ldc "UWbcGEGeqZGDsW[G^]@QUwxDJJWr"
		// @0A0: invokestatic game.C_100201_qj.func_105860_z(java.lang.String)char[]
		// @0A3: invokestatic game.C_100201_qj.func_105859_z(char[])java.lang.String
		// @0A6: aastore
		// @0A7: dup
		// @0A8: bipush 14 (0x0E)
		// @0AA: ldc "LS`D\u0006GEb\u000bkI\\bDAHWd"
		// @0AC: invokestatic game.C_100201_qj.func_105860_z(java.lang.String)char[]
		// @0AF: invokestatic game.C_100201_qj.func_105859_z(char[])java.lang.String
		// @0B2: aastore
		// @0B3: dup
		// @0B4: bipush 15 (0x0F)
		// @0B6: ldc "IA8SMTA\u007fJF"
		// @0B8: invokestatic game.C_100201_qj.func_105860_z(java.lang.String)char[]
		// @0BB: invokestatic game.C_100201_qj.func_105859_z(char[])java.lang.String
		// @0BE: aastore
		// @0BF: dup
		// @0C0: bipush 16 (0x10)
		// @0C2: ldc "X\u001d"
		// @0C4: invokestatic game.C_100201_qj.func_105860_z(java.lang.String)char[]
		// @0C7: invokestatic game.C_100201_qj.func_105859_z(char[])java.lang.String
		// @0CA: aastore
		// @0CB: dup
		// @0CC: bipush 17 (0x11)
		// @0CE: ldc "L["
		// @0D0: invokestatic game.C_100201_qj.func_105860_z(java.lang.String)char[]
		// @0D3: invokestatic game.C_100201_qj.func_105859_z(char[])java.lang.String
		// @0D6: aastore
		// @0D7: dup
		// @0D8: bipush 18 (0x12)
		// @0DA: ldc "LS`D\u0006GEb\u000bkI_fJFC\\b"
		// @0DC: invokestatic game.C_100201_qj.func_105860_z(java.lang.String)char[]
		// @0DF: invokestatic game.C_100201_qj.func_105859_z(char[])java.lang.String
		// @0E2: aastore
		// @0E3: dup
		// @0E4: bipush 19 (0x13)
		// @0E6: ldc "LS`D\u0006PWxAGT"
		// @0E8: invokestatic game.C_100201_qj.func_105860_z(java.lang.String)char[]
		// @0EB: invokestatic game.C_100201_qj.func_105859_z(char[])java.lang.String
		// @0EE: aastore
		// @0EF: dup
		// @0F0: bipush 20 (0x14)
		// @0F2: ldc "IA8KIKW"
		// @0F4: invokestatic game.C_100201_qj.func_105860_z(java.lang.String)char[]
		// @0F7: invokestatic game.C_100201_qj.func_105859_z(char[])java.lang.String
		// @0FA: aastore
		// @0FB: dup
		// @0FC: bipush 21 (0x15)
		// @0FE: ldc "KS\u007fKw@[z@wESuMM\u0008[r]"
		// @100: invokestatic game.C_100201_qj.func_105860_z(java.lang.String)char[]
		// @103: invokestatic game.C_100201_qj.func_105859_z(char[])java.lang.String
		// @106: aastore
		// @107: dup
		// @108: bipush 22 (0x16)
		// @10A: ldc "TSxAGK\u001crD\\"
		// @10C: invokestatic game.C_100201_qj.func_105860_z(java.lang.String)char[]
		// @10F: invokestatic game.C_100201_qj.func_105859_z(char[])java.lang.String
		// @112: aastore
		// @113: dup
		// @114: bipush 23 (0x17)
		// @116: ldc "UWbcGEGefQE^swGIF"
		// @118: invokestatic game.C_100201_qj.func_105860_z(java.lang.String)char[]
		// @11B: invokestatic game.C_100201_qj.func_105859_z(char[])java.lang.String
		// @11E: aastore
		// @11F: dup
		// @120: bipush 24 (0x18)
		// @122: ldc "KS\u007fKw@[z@wESuMM\u0008[r]\u001a\u0013\u0007"
		// @124: invokestatic game.C_100201_qj.func_105860_z(java.lang.String)char[]
		// @127: invokestatic game.C_100201_qj.func_105859_z(char[])java.lang.String
		// @12A: aastore
		// @12B: dup
		// @12C: bipush 25 (0x19)
		// @12E: ldc "s\\}KGQ\\"
		// @130: invokestatic game.C_100201_qj.func_105860_z(java.lang.String)char[]
		// @133: invokestatic game.C_100201_qj.func_105859_z(char[])java.lang.String
		// @136: aastore
		// @137: dup
		// @138: bipush 26 (0x1A)
		// @13A: ldc "K[uWGU]pQ"
		// @13C: invokestatic game.C_100201_qj.func_105860_z(java.lang.String)char[]
		// @13F: invokestatic game.C_100201_qj.func_105859_z(char[])java.lang.String
		// @142: aastore
		// @143: dup
		// @144: bipush 27 (0x1B)
		// @146: ldc "GV"
		// @148: invokestatic game.C_100201_qj.func_105860_z(java.lang.String)char[]
		// @14B: invokestatic game.C_100201_qj.func_105859_z(char[])java.lang.String
		// @14E: aastore
		// @14F: dup
		// @150: bipush 28 (0x1C)
		// @152: ldc "\u0017\u001c'"
		// @154: invokestatic game.C_100201_qj.func_105860_z(java.lang.String)char[]
		// @157: invokestatic game.C_100201_qj.func_105859_z(char[])java.lang.String
		// @15A: aastore
		// @15B: dup
		// @15C: bipush 29 (0x1D)
		// @15E: ldc "KS\u007fKw@[z@wESuMM\u0008VwQ\u001a"
		// @160: invokestatic game.C_100201_qj.func_105860_z(java.lang.String)char[]
		// @163: invokestatic game.C_100201_qj.func_105859_z(char[])java.lang.String
		// @166: aastore
		// @167: dup
		// @168: bipush 30 (0x1E)
		// @16A: ldc "SAsW\u0006N]{@"
		// @16C: invokestatic game.C_100201_qj.func_105860_z(java.lang.String)char[]
		// @16F: invokestatic game.C_100201_qj.func_105859_z(char[])java.lang.String
		// @172: aastore
		// @173: dup
		// @174: bipush 31 (0x1F)
		// @176: ldc "LS`D\u0006PWdVAI\\"
		// @178: invokestatic game.C_100201_qj.func_105860_z(java.lang.String)char[]
		// @17B: invokestatic game.C_100201_qj.func_105859_z(char[])java.lang.String
		// @17E: aastore
		// @17F: dup
		// @180: bipush 32 (0x20)
		// @182: ldc "GPuAM@U~LBM^{KGVCdV\\SDa]Q\\sTflctQmalyZhfibGw{rg@rp\u007fh&\u0014\u001a\u0015\u0006#\u0013\u001f\u001e\u000b)\u0003\u0015\n\u001c3\u000e\u0005y\u0011,\n\u0002"
		// @184: invokestatic game.C_100201_qj.func_105860_z(java.lang.String)char[]
		// @187: invokestatic game.C_100201_qj.func_105859_z(char[])java.lang.String
		// @18A: aastore
		// @18B: dup
		// @18C: bipush 33 (0x21)
		// @18E: ldc "CJ\u007fQ"
		// @190: invokestatic game.C_100201_qj.func_105860_z(java.lang.String)char[]
		// @193: invokestatic game.C_100201_qj.func_105859_z(char[])java.lang.String
		// @196: aastore
		// @197: dup
		// @198: bipush 34 (0x22)
		// @19A: ldc "E_r\u0005\u0007E\u0012eQITF6\u0007B\u0004\u00124"
		// @19C: invokestatic game.C_100201_qj.func_105860_z(java.lang.String)char[]
		// @19F: invokestatic game.C_100201_qj.func_105859_z(char[])java.lang.String
		// @1A2: aastore
		// @1A3: dup
		// @1A4: bipush 35 (0x23)
		// @1A6: ldc "NFbU[\u001c\u001d9"
		// @1A8: invokestatic game.C_100201_qj.func_105860_z(java.lang.String)char[]
		// @1AB: invokestatic game.C_100201_qj.func_105859_z(char[])java.lang.String
		// @1AE: aastore
		// @1AF: dup
		// @1B0: bipush 36 (0x24)
		// @1B2: ldc "lSq@P\u0006tcID\u0006auWMC\\"
		// @1B4: invokestatic game.C_100201_qj.func_105860_z(java.lang.String)char[]
		// @1B7: invokestatic game.C_100201_qj.func_105859_z(char[])java.lang.String
		// @1BA: aastore
		// @1BB: dup
		// @1BC: bipush 37 (0x25)
		// @1BE: ldc "K]`@EIGe@"
		// @1C0: invokestatic game.C_100201_qj.func_105860_z(java.lang.String)char[]
		// @1C3: invokestatic game.C_100201_qj.func_105859_z(char[])java.lang.String
		// @1C6: aastore
		// @1C7: dup
		// @1C8: bipush 38 (0x26)
		// @1CA: ldc "J[eQEIVsV"
		// @1CC: invokestatic game.C_100201_qj.func_105860_z(java.lang.String)char[]
		// @1CF: invokestatic game.C_100201_qj.func_105859_z(char[])java.lang.String
		// @1D2: aastore
		// @1D3: dup
		// @1D4: bipush 39 (0x27)
		// @1D6: ldc "C\\b@Z"
		// @1D8: invokestatic game.C_100201_qj.func_105860_z(java.lang.String)char[]
		// @1DB: invokestatic game.C_100201_qj.func_105859_z(char[])java.lang.String
		// @1DE: aastore
		// @1DF: dup
		// @1E0: bipush 40 (0x28)
		// @1E2: ldc "NFbU\u0012\t\u001d"
		// @1E4: invokestatic game.C_100201_qj.func_105860_z(java.lang.String)char[]
		// @1E7: invokestatic game.C_100201_qj.func_105859_z(char[])java.lang.String
		// @1EA: aastore
		// @1EB: dup
		// @1EC: bipush 41 (0x29)
		// @1EE: ldc "UWbF]UFyHKS@eJZ"
		// @1F0: invokestatic game.C_100201_qj.func_105860_z(java.lang.String)char[]
		// @1F3: invokestatic game.C_100201_qj.func_105859_z(char[])java.lang.String
		// @1F6: aastore
		// @1F7: dup
		// @1F8: bipush 42 (0x2A)
		// @1FA: ldc "UZyRKS@eJZ"
		// @1FC: invokestatic game.C_100201_qj.func_105860_z(java.lang.String)char[]
		// @1FF: invokestatic game.C_100201_qj.func_105859_z(char[])java.lang.String
		// @202: aastore
		// @203: dup
		// @204: bipush 43 (0x2B)
		// @206: ldc "Q[x"
		// @208: invokestatic game.C_100201_qj.func_105860_z(java.lang.String)char[]
		// @20B: invokestatic game.C_100201_qj.func_105859_z(char[])java.lang.String
		// @20E: aastore
		// @20F: putstatic java.lang.String[] game.C_100201_qj.field_105893_z
		// @212: lconst_0
		// @213: putstatic long game.C_100201_qj.field_105885_w
		// @216: return
	}
	
	private static char[] func_105860_z(String arg0)
	{
		// @00: aload_0
		// @01: invokevirtual java.lang.String.toCharArray()char[]
		// @04: dup
		// @05: arraylength
		// @06: iconst_2
		// @07: if_icmpge @13
		// @0A: dup
		// @0B: iconst_0
		// @0C: dup2
		// @0D: caload
		// @0E: bipush 40 (0x28)
		// @10: ixor
		// @11: i2c
		// @12: castore
		// @13: areturn
	}
	
	private static String func_105859_z(char[] arg0)
	{
		// @00: aload_0
		// @01: dup
		// @02: arraylength
		// @03: swap
		// @04: iconst_0
		// @05: istore_1
		// @06: goto @4C
		// @09: dup
		// @0A: iload_1
		// @0B: dup2
		// @0C: caload
		// @0D: iload_1
		// @0E: iconst_5
		// @0F: irem
		// @10: tableswitch def: @44, for 0: @30, for 1: @35, for 2: @3A, for 3: @3F
		// @30: bipush 38 (0x26)
		// @32: goto @46
		// @35: bipush 50 (0x32)
		// @37: goto @46
		// @3A: bipush 22 (0x16)
		// @3C: goto @46
		// @3F: bipush 37 (0x25)
		// @41: goto @46
		// @44: bipush 40 (0x28)
		// @46: ixor
		// @47: i2c
		// @48: castore
		// @49: iinc #1 +1
		// @4C: swap
		// @4D: dup_x1
		// @4E: iload_1
		// @4F: if_icmpgt @09
		// @52: new java.lang.String
		// @55: dup_x1
		// @56: swap
		// @57: invokespecial java.lang.String.<init>(char[])void
		// @5A: invokevirtual java.lang.String.intern()java.lang.String
		// @5D: areturn
	}
}
