package game;

final class C_100176_ci
{
	static C_100217_ao field_105625_c;
	static String[] field_105623_e;
	static C_100220_ac field_105624_b;
	static String field_105621_f;
	static int field_105626_a;
	static String field_105622_d;
	private static final String[] field_105627_z;
	
	public static void func_105618_a(byte arg0)
	{
		// @00: aconst_null
		// @01: putstatic java.lang.String[] game.C_100176_ci.field_105623_e
		// @04: aconst_null
		// @05: putstatic java.lang.String game.C_100176_ci.field_105622_d
		// @08: aconst_null
		// @09: putstatic game.C_100217_ao game.C_100176_ci.field_105625_c
		// @0C: aconst_null
		// @0D: putstatic game.C_100220_ac game.C_100176_ci.field_105624_b
		// @10: aconst_null
		// @11: putstatic java.lang.String game.C_100176_ci.field_105621_f
		// @14: iload_0
		// @15: bipush 18 (0x12)
		// @17: if_icmpeq @21
		// @1A: aconst_null
		// @1B: checkcast game.C_100220_ac
		// @1E: putstatic game.C_100220_ac game.C_100176_ci.field_105624_b
		// @21: goto @45
		// @24: astore_1
		// @25: aload_1
		// @26: new java.lang.StringBuilder
		// @29: dup
		// @2A: invokespecial java.lang.StringBuilder.<init>()void
		// @2D: getstatic java.lang.String[] game.C_100176_ci.field_105627_z
		// @30: iconst_2
		// @31: aaload
		// @32: invokevirtual java.lang.StringBuilder.append(java.lang.String)java.lang.StringBuilder
		// @35: iload_0
		// @36: invokevirtual java.lang.StringBuilder.append(int)java.lang.StringBuilder
		// @39: bipush 41 (0x29)
		// @3B: invokevirtual java.lang.StringBuilder.append(char)java.lang.StringBuilder
		// @3E: invokevirtual java.lang.StringBuilder.toString()java.lang.String
		// @41: invokestatic game.C_100181_cf.func_105695_a(java.lang.Throwable, java.lang.String)game.C_100170_cm
		// @44: athrow
		// @45: return
	}
	
	static final boolean func_105620_a(boolean arg0, int arg1)
	{
		// @00: iload_0
		// @01: ifeq @06
		// @04: iconst_0
		// @05: ireturn
		// @06: iload_1
		// @07: iflt @0F
		// @0A: iconst_1
		// @0B: goto @10
		// @0E: athrow
		// @0F: iconst_0
		// @10: ireturn
		// @11: astore_2
		// @12: aload_2
		// @13: new java.lang.StringBuilder
		// @16: dup
		// @17: invokespecial java.lang.StringBuilder.<init>()void
		// @1A: getstatic java.lang.String[] game.C_100176_ci.field_105627_z
		// @1D: iconst_1
		// @1E: aaload
		// @1F: invokevirtual java.lang.StringBuilder.append(java.lang.String)java.lang.StringBuilder
		// @22: iload_0
		// @23: invokevirtual java.lang.StringBuilder.append(boolean)java.lang.StringBuilder
		// @26: bipush 44 (0x2C)
		// @28: invokevirtual java.lang.StringBuilder.append(char)java.lang.StringBuilder
		// @2B: iload_1
		// @2C: invokevirtual java.lang.StringBuilder.append(int)java.lang.StringBuilder
		// @2F: bipush 41 (0x29)
		// @31: invokevirtual java.lang.StringBuilder.append(char)java.lang.StringBuilder
		// @34: invokevirtual java.lang.StringBuilder.toString()java.lang.String
		// @37: invokestatic game.C_100181_cf.func_105695_a(java.lang.Throwable, java.lang.String)game.C_100170_cm
		// @3A: athrow
	}
	
	static final C_100153_be[] func_105616_a(int arg0)
	{
		// @00: getstatic int game.SteelSentinels.field_105275_O
		// @03: istore_3
		// @04: getstatic int game.C_100277_nc.field_106744_y
		// @07: anewarray game.C_100153_be
		// @0A: astore_1
		// @0B: iconst_0
		// @0C: istore_2
		// @0D: getstatic int game.C_100277_nc.field_106744_y
		// @10: iconst_m1
		// @11: ixor
		// @12: iload_2
		// @13: iconst_m1
		// @14: ixor
		// @15: if_icmpge @53
		// @18: aload_1
		// @19: iload_2
		// @1A: new game.C_100153_be
		// @1D: dup
		// @1E: getstatic int game.C_100338_jc.field_105371_m
		// @21: getstatic int game.C_100277_nc.field_106702_C
		// @24: getstatic int[] game.C_100068_vc.field_104340_f
		// @27: iload_2
		// @28: iaload
		// @29: getstatic int[] game.C_100012_fh.field_100509_M
		// @2C: iload_2
		// @2D: iaload
		// @2E: getstatic int[] game.C_100213_ak.field_105994_d
		// @31: iload_2
		// @32: iaload
		// @33: getstatic int[] game.C_100312_ld.field_107156_c
		// @36: iload_2
		// @37: iaload
		// @38: getstatic byte[][] game.C_100107_u.field_104774_c
		// @3B: iload_2
		// @3C: aaload
		// @3D: getstatic int[] game.C_100085_a.field_102573_H
		// @40: invokespecial game.C_100153_be.<init>(int, int, int, int, int, int, byte[], int[])void
		// @43: aastore
		// @44: iinc #2 +1
		// @47: iload_3
		// @48: ifne @68
		// @4B: iload_3
		// @4C: ifeq @0D
		// @4F: goto @53
		// @52: athrow
		// @53: iload_0
		// @54: iconst_1
		// @55: if_icmpeq @63
		// @58: aconst_null
		// @59: checkcast game.C_100217_ao
		// @5C: putstatic game.C_100217_ao game.C_100176_ci.field_105625_c
		// @5F: goto @63
		// @62: athrow
		// @63: bipush 114 (0x72)
		// @65: invokestatic game.C_100030_gm.func_103336_a(byte)void
		// @68: aload_1
		// @69: areturn
		// @6A: astore_1
		// @6B: aload_1
		// @6C: new java.lang.StringBuilder
		// @6F: dup
		// @70: invokespecial java.lang.StringBuilder.<init>()void
		// @73: getstatic java.lang.String[] game.C_100176_ci.field_105627_z
		// @76: iconst_0
		// @77: aaload
		// @78: invokevirtual java.lang.StringBuilder.append(java.lang.String)java.lang.StringBuilder
		// @7B: iload_0
		// @7C: invokevirtual java.lang.StringBuilder.append(int)java.lang.StringBuilder
		// @7F: bipush 41 (0x29)
		// @81: invokevirtual java.lang.StringBuilder.append(char)java.lang.StringBuilder
		// @84: invokevirtual java.lang.StringBuilder.toString()java.lang.String
		// @87: invokestatic game.C_100181_cf.func_105695_a(java.lang.Throwable, java.lang.String)game.C_100170_cm
		// @8A: athrow
	}
	
	static
	{
		// @000: iconst_3
		// @001: anewarray java.lang.String
		// @004: dup
		// @005: iconst_0
		// @006: ldc "g\u001ajUK"
		// @008: invokestatic game.C_100176_ci.func_105619_z(java.lang.String)char[]
		// @00B: invokestatic game.C_100176_ci.func_105617_z(char[])java.lang.String
		// @00E: aastore
		// @00F: dup
		// @010: iconst_1
		// @011: ldc "g\u001ajWK"
		// @013: invokestatic game.C_100176_ci.func_105619_z(java.lang.String)char[]
		// @016: invokestatic game.C_100176_ci.func_105617_z(char[])java.lang.String
		// @019: aastore
		// @01A: dup
		// @01B: iconst_2
		// @01C: ldc "g\u001ajVK"
		// @01E: invokestatic game.C_100176_ci.func_105619_z(java.lang.String)char[]
		// @021: invokestatic game.C_100176_ci.func_105617_z(char[])java.lang.String
		// @024: aastore
		// @025: putstatic java.lang.String[] game.C_100176_ci.field_105627_z
		// @028: bipush 96 (0x60)
		// @02A: anewarray java.lang.String
		// @02D: dup
		// @02E: iconst_0
		// @02F: ldc "C\u001c(q\u000e$\u0010,u\u0010w\u001a7"
		// @031: invokestatic game.C_100176_ci.func_105619_z(java.lang.String)char[]
		// @034: invokestatic game.C_100176_ci.func_105617_z(char[])java.lang.String
		// @037: aastore
		// @038: dup
		// @039: iconst_1
		// @03A: ldc "R\u001a7{\u0011$\u001b!u\u0007"
		// @03C: invokestatic game.C_100176_ci.func_105619_z(java.lang.String)char[]
		// @03F: invokestatic game.C_100176_ci.func_105617_z(char[])java.lang.String
		// @042: aastore
		// @043: dup
		// @044: iconst_2
		// @045: ldc "E\u00010}\u0000q\u001f%`\u0006`S%f\u000e"
		// @047: invokestatic game.C_100176_ci.func_105619_z(java.lang.String)char[]
		// @04A: invokestatic game.C_100176_ci.func_105617_z(char[])java.lang.String
		// @04D: aastore
		// @04E: dup
		// @04F: iconst_3
		// @050: ldc "W\u001b+a\u000f`\u001664\u0013e\u0010/"
		// @052: invokestatic game.C_100176_ci.func_105619_z(java.lang.String)char[]
		// @055: invokestatic game.C_100176_ci.func_105617_z(char[])java.lang.String
		// @058: aastore
		// @059: dup
		// @05A: iconst_4
		// @05B: aconst_null
		// @05C: aastore
		// @05D: dup
		// @05E: iconst_5
		// @05F: aconst_null
		// @060: aastore
		// @061: dup
		// @062: bipush 6 (0x06)
		// @064: aconst_null
		// @065: aastore
		// @066: dup
		// @067: bipush 7 (0x07)
		// @069: aconst_null
		// @06A: aastore
		// @06B: dup
		// @06C: bipush 8 (0x08)
		// @06E: aconst_null
		// @06F: aastore
		// @070: dup
		// @071: bipush 9 (0x09)
		// @073: aconst_null
		// @074: aastore
		// @075: dup
		// @076: bipush 10 (0x0A)
		// @078: aconst_null
		// @079: aastore
		// @07A: dup
		// @07B: bipush 11 (0x0B)
		// @07D: aconst_null
		// @07E: aastore
		// @07F: dup
		// @080: bipush 12 (0x0C)
		// @082: aconst_null
		// @083: aastore
		// @084: dup
		// @085: bipush 13 (0x0D)
		// @087: aconst_null
		// @088: aastore
		// @089: dup
		// @08A: bipush 14 (0x0E)
		// @08C: aconst_null
		// @08D: aastore
		// @08E: dup
		// @08F: bipush 15 (0x0F)
		// @091: aconst_null
		// @092: aastore
		// @093: dup
		// @094: bipush 16 (0x10)
		// @096: aconst_null
		// @097: aastore
		// @098: dup
		// @099: bipush 17 (0x11)
		// @09B: ldc "B\u001f%\u007fCv\u00164q\u0002p\u00166"
		// @09D: invokestatic game.C_100176_ci.func_105619_z(java.lang.String)char[]
		// @0A0: invokestatic game.C_100176_ci.func_105617_z(char[])java.lang.String
		// @0A3: aastore
		// @0A4: dup
		// @0A5: bipush 18 (0x12)
		// @0A7: ldc "I\u001a*}\u0004q\u001d"
		// @0A9: invokestatic game.C_100176_ci.func_105619_z(java.lang.String)char[]
		// @0AC: invokestatic game.C_100176_ci.func_105617_z(char[])java.lang.String
		// @0AF: aastore
		// @0B0: dup
		// @0B1: bipush 19 (0x13)
		// @0B3: ldc "B\u001a6qCf\u001c)vCh\u00121z\u0000l\u00166"
		// @0B5: invokestatic game.C_100176_ci.func_105619_z(java.lang.String)char[]
		// @0B8: invokestatic game.C_100176_ci.func_105617_z(char[])java.lang.String
		// @0BB: aastore
		// @0BC: dup
		// @0BD: bipush 20 (0x14)
		// @0BF: ldc "C\u00121g\u0010$\u00141z"
		// @0C1: invokestatic game.C_100176_ci.func_105619_z(java.lang.String)char[]
		// @0C4: invokestatic game.C_100176_ci.func_105617_z(char[])java.lang.String
		// @0C7: aastore
		// @0C8: dup
		// @0C9: bipush 21 (0x15)
		// @0CB: ldc "T\u0006(g\u0006$\u001f%g\u0006v"
		// @0CD: invokestatic game.C_100176_ci.func_105619_z(java.lang.String)char[]
		// @0D0: invokestatic game.C_100176_ci.func_105617_z(char[])java.lang.String
		// @0D3: aastore
		// @0D4: dup
		// @0D5: bipush 22 (0x16)
		// @0D7: ldc "T\u001f%g\u000eeS7d\u0011e\n"
		// @0D9: invokestatic game.C_100176_ci.func_105619_z(java.lang.String)char[]
		// @0DC: invokestatic game.C_100176_ci.func_105617_z(char[])java.lang.String
		// @0DF: aastore
		// @0E0: dup
		// @0E1: bipush 23 (0x17)
		// @0E3: ldc "V\u00124}\u0006vS)}\u0010w\u001a(q"
		// @0E5: invokestatic game.C_100176_ci.func_105619_z(java.lang.String)char[]
		// @0E8: invokestatic game.C_100176_ci.func_105617_z(char[])java.lang.String
		// @0EB: aastore
		// @0EC: dup
		// @0ED: bipush 24 (0x18)
		// @0EF: ldc "T\u001a!f\u0000a\u0001df\u000cg\u0018!`"
		// @0F1: invokestatic game.C_100176_ci.func_105619_z(java.lang.String)char[]
		// @0F4: invokestatic game.C_100176_ci.func_105617_z(char[])java.lang.String
		// @0F7: aastore
		// @0F8: dup
		// @0F9: bipush 25 (0x19)
		// @0FB: ldc "A>\u00144\u0011k\u0010/q\u0017"
		// @0FD: invokestatic game.C_100176_ci.func_105619_z(java.lang.String)char[]
		// @100: invokestatic game.C_100176_ci.func_105617_z(char[])java.lang.String
		// @103: aastore
		// @104: dup
		// @105: bipush 26 (0x1A)
		// @107: ldc "E\u001a6v\u0016v\u000004\u0011k\u0010/q\u0017"
		// @109: invokestatic game.C_100176_ci.func_105619_z(java.lang.String)char[]
		// @10C: invokestatic game.C_100176_ci.func_105617_z(char[])java.lang.String
		// @10F: aastore
		// @110: dup
		// @111: bipush 27 (0x1B)
		// @113: ldc "A\u001f!w\u0017v\u001c*4\u0000e\u001d*{\r"
		// @115: invokestatic game.C_100176_ci.func_105619_z(java.lang.String)char[]
		// @118: invokestatic game.C_100176_ci.func_105617_z(char[])java.lang.String
		// @11B: aastore
		// @11C: dup
		// @11D: bipush 28 (0x1C)
		// @11F: ldc "B\u001f%\u007fCg\u0012*z\u000cj"
		// @121: invokestatic game.C_100176_ci.func_105619_z(java.lang.String)char[]
		// @124: invokestatic game.C_100176_ci.func_105617_z(char[])java.lang.String
		// @127: aastore
		// @128: dup
		// @129: bipush 29 (0x1D)
		// @12B: ldc "L\u0016%b\u001a$\u00141z"
		// @12D: invokestatic game.C_100176_ci.func_105619_z(java.lang.String)char[]
		// @130: invokestatic game.C_100176_ci.func_105617_z(char[])java.lang.String
		// @133: aastore
		// @134: dup
		// @135: bipush 30 (0x1E)
		// @137: ldc "L\u0016%b\u001a$\u0010%z\rk\u001d"
		// @139: invokestatic game.C_100176_ci.func_105619_z(java.lang.String)char[]
		// @13C: invokestatic game.C_100176_ci.func_105617_z(char[])java.lang.String
		// @13F: aastore
		// @140: dup
		// @141: bipush 31 (0x1F)
		// @143: ldc "I\u001c6`\u0002v"
		// @145: invokestatic game.C_100176_ci.func_105619_z(java.lang.String)char[]
		// @148: invokestatic game.C_100176_ci.func_105617_z(char[])java.lang.String
		// @14B: aastore
		// @14C: dup
		// @14D: bipush 32 (0x20)
		// @14F: ldc "V\u001a\"x\u0006`S7z\nt\u001664\u0000e\u001d*{\r"
		// @151: invokestatic game.C_100176_ci.func_105619_z(java.lang.String)char[]
		// @154: invokestatic game.C_100176_ci.func_105617_z(char[])java.lang.String
		// @157: aastore
		// @158: dup
		// @159: bipush 33 (0x21)
		// @15B: ldc "V\u0012-xCv\u00164q\u0002p\u00166"
		// @15D: invokestatic game.C_100176_ci.func_105619_z(java.lang.String)char[]
		// @160: invokestatic game.C_100176_ci.func_105617_z(char[])java.lang.String
		// @163: aastore
		// @164: dup
		// @165: bipush 34 (0x22)
		// @167: ldc "H\u00127q\u0011$\u0011!u\u000e"
		// @169: invokestatic game.C_100176_ci.func_105619_z(java.lang.String)char[]
		// @16C: invokestatic game.C_100176_ci.func_105617_z(char[])java.lang.String
		// @16F: aastore
		// @170: dup
		// @171: bipush 35 (0x23)
		// @173: ldc "T\u001f%g\u000eeS'u\rj\u001c*"
		// @175: invokestatic game.C_100176_ci.func_105619_z(java.lang.String)char[]
		// @178: invokestatic game.C_100176_ci.func_105617_z(char[])java.lang.String
		// @17B: aastore
		// @17C: dup
		// @17D: bipush 36 (0x24)
		// @17F: ldc "I\u0006(`\nv\u001c'\u007f\u0006p"
		// @181: invokestatic game.C_100176_ci.func_105619_z(java.lang.String)char[]
		// @184: invokestatic game.C_100176_ci.func_105617_z(char[])java.lang.String
		// @187: aastore
		// @188: dup
		// @189: bipush 37 (0x25)
		// @18B: ldc "L\u0016%b\u001a$\u0001+w\u0008a\u0007"
		// @18D: invokestatic game.C_100176_ci.func_105619_z(java.lang.String)char[]
		// @190: invokestatic game.C_100176_ci.func_105617_z(char[])java.lang.String
		// @193: aastore
		// @194: dup
		// @195: bipush 38 (0x26)
		// @197: ldc "H\u001a#|\u0017j\u001a*sCg\u0012*z\u000cj"
		// @199: invokestatic game.C_100176_ci.func_105619_z(java.lang.String)char[]
		// @19C: invokestatic game.C_100176_ci.func_105617_z(char[])java.lang.String
		// @19F: aastore
		// @1A0: dup
		// @1A1: bipush 39 (0x27)
		// @1A3: aconst_null
		// @1A4: aastore
		// @1A5: dup
		// @1A6: bipush 40 (0x28)
		// @1A8: aconst_null
		// @1A9: aastore
		// @1AA: dup
		// @1AB: bipush 41 (0x29)
		// @1AD: aconst_null
		// @1AE: aastore
		// @1AF: dup
		// @1B0: bipush 42 (0x2A)
		// @1B2: ldc "E\u001a64\u000em\u001d!4\u0011k\u0010/q\u0017"
		// @1B4: invokestatic game.C_100176_ci.func_105619_z(java.lang.String)char[]
		// @1B7: invokestatic game.C_100176_ci.func_105617_z(char[])java.lang.String
		// @1BA: aastore
		// @1BB: dup
		// @1BC: bipush 43 (0x2B)
		// @1BE: ldc "Q\u001f0f\u0002$\u00141z"
		// @1C0: invokestatic game.C_100176_ci.func_105619_z(java.lang.String)char[]
		// @1C3: invokestatic game.C_100176_ci.func_105617_z(char[])java.lang.String
		// @1C6: aastore
		// @1C7: dup
		// @1C8: bipush 44 (0x2C)
		// @1CA: ldc "@\u001c+y\u0010`\u0012=4\u0000e\u001d*{\r"
		// @1CC: invokestatic game.C_100176_ci.func_105619_z(java.lang.String)char[]
		// @1CF: invokestatic game.C_100176_ci.func_105617_z(char[])java.lang.String
		// @1D2: aastore
		// @1D3: dup
		// @1D4: bipush 45 (0x2D)
		// @1D6: ldc "L\u001c3}\u0017~\u00166"
		// @1D8: invokestatic game.C_100176_ci.func_105619_z(java.lang.String)char[]
		// @1DB: invokestatic game.C_100176_ci.func_105617_z(char[])java.lang.String
		// @1DE: aastore
		// @1DF: dup
		// @1E0: bipush 46 (0x2E)
		// @1E2: ldc "V\u0012-xCg\u0012*z\u000cj"
		// @1E4: invokestatic game.C_100176_ci.func_105619_z(java.lang.String)char[]
		// @1E7: invokestatic game.C_100176_ci.func_105617_z(char[])java.lang.String
		// @1EA: aastore
		// @1EB: dup
		// @1EC: bipush 47 (0x2F)
		// @1EE: ldc "W\u001c(u\u0011m\u0000dx\u0002w\u00166"
		// @1F0: invokestatic game.C_100176_ci.func_105619_z(java.lang.String)char[]
		// @1F3: invokestatic game.C_100176_ci.func_105617_z(char[])java.lang.String
		// @1F6: aastore
		// @1F7: dup
		// @1F8: bipush 48 (0x30)
		// @1FA: ldc "B\u00067}\u000cjS'u\rj\u001c*"
		// @1FC: invokestatic game.C_100176_ci.func_105619_z(java.lang.String)char[]
		// @1FF: invokestatic game.C_100176_ci.func_105617_z(char[])java.lang.String
		// @202: aastore
		// @203: dup
		// @204: bipush 49 (0x31)
		// @206: ldc "@6\u0005@+$\u001d1\u007f\u0006"
		// @208: invokestatic game.C_100176_ci.func_105619_z(java.lang.String)char[]
		// @20B: invokestatic game.C_100176_ci.func_105617_z(char[])java.lang.String
		// @20E: aastore
		// @20F: dup
		// @210: bipush 50 (0x32)
		// @212: ldc "@\u00167`\u0011q\u00100{\u0011$\u0001+w\u0008a\u0007"
		// @214: invokestatic game.C_100176_ci.func_105619_z(java.lang.String)char[]
		// @217: invokestatic game.C_100176_ci.func_105617_z(char[])java.lang.String
		// @21A: aastore
		// @21B: dup
		// @21C: bipush 51 (0x33)
		// @21E: ldc "E\u001a64\u0007a\u00120|Ci\u001a7g\nh\u0016"
		// @220: invokestatic game.C_100176_ci.func_105619_z(java.lang.String)char[]
		// @223: invokestatic game.C_100176_ci.func_105617_z(char[])java.lang.String
		// @226: aastore
		// @227: dup
		// @228: bipush 52 (0x34)
		// @22A: ldc "A>\u00144\u0000e\u001d*{\r"
		// @22C: invokestatic game.C_100176_ci.func_105619_z(java.lang.String)char[]
		// @22F: invokestatic game.C_100176_ci.func_105617_z(char[])java.lang.String
		// @232: aastore
		// @233: dup
		// @234: bipush 53 (0x35)
		// @236: ldc "W\u001b-q\u000f`S,q\u0002`"
		// @238: invokestatic game.C_100176_ci.func_105619_z(java.lang.String)char[]
		// @23B: invokestatic game.C_100176_ci.func_105617_z(char[])java.lang.String
		// @23E: aastore
		// @23F: dup
		// @240: bipush 54 (0x36)
		// @242: ldc "L\u0016%b\u001a$\u001e+a\rp\u001a*s"
		// @244: invokestatic game.C_100176_ci.func_105619_z(java.lang.String)char[]
		// @247: invokestatic game.C_100176_ci.func_105617_z(char[])java.lang.String
		// @24A: aastore
		// @24B: dup
		// @24C: bipush 55 (0x37)
		// @24E: ldc "W\u001f%b\u0006$\u0010,u\u0010w\u001a7"
		// @250: invokestatic game.C_100176_ci.func_105619_z(java.lang.String)char[]
		// @253: invokestatic game.C_100176_ci.func_105617_z(char[])java.lang.String
		// @256: aastore
		// @257: dup
		// @258: bipush 56 (0x38)
		// @25A: ldc "E\u0001){\u0016v\u0016 4\u0002v\u001e"
		// @25C: invokestatic game.C_100176_ci.func_105619_z(java.lang.String)char[]
		// @25F: invokestatic game.C_100176_ci.func_105617_z(char[])java.lang.String
		// @262: aastore
		// @263: dup
		// @264: bipush 57 (0x39)
		// @266: ldc "E\u00021}\u000feS'|\u0002w\u0000-g"
		// @268: invokestatic game.C_100176_ci.func_105619_z(java.lang.String)char[]
		// @26B: invokestatic game.C_100176_ci.func_105617_z(char[])java.lang.String
		// @26E: aastore
		// @26F: dup
		// @270: bipush 58 (0x3A)
		// @272: ldc "V\u0012>{\u0011$\u00126y"
		// @274: invokestatic game.C_100176_ci.func_105619_z(java.lang.String)char[]
		// @277: invokestatic game.C_100176_ci.func_105617_z(char[])java.lang.String
		// @27A: aastore
		// @27B: dup
		// @27C: bipush 59 (0x3B)
		// @27E: ldc "C\u0001%b\np\ndz\u0016h\u001f-r\na\u0001"
		// @280: invokestatic game.C_100176_ci.func_105619_z(java.lang.String)char[]
		// @283: invokestatic game.C_100176_ci.func_105617_z(char[])java.lang.String
		// @286: aastore
		// @287: dup
		// @288: bipush 60 (0x3C)
		// @28A: ldc "W\u0010+a\u0017$\u001b!u\u0007"
		// @28C: invokestatic game.C_100176_ci.func_105619_z(java.lang.String)char[]
		// @28F: invokestatic game.C_100176_ci.func_105617_z(char[])java.lang.String
		// @292: aastore
		// @293: dup
		// @294: bipush 61 (0x3D)
		// @296: ldc "P\u0012'`\ng\u0012(4\u000ee\u0004"
		// @298: invokestatic game.C_100176_ci.func_105619_z(java.lang.String)char[]
		// @29B: invokestatic game.C_100176_ci.func_105617_z(char[])java.lang.String
		// @29E: aastore
		// @29F: dup
		// @2A0: bipush 62 (0x3E)
		// @2A2: ldc "P\u00066`\u000faS'|\u0002w\u0000-g"
		// @2A4: invokestatic game.C_100176_ci.func_105619_z(java.lang.String)char[]
		// @2A7: invokestatic game.C_100176_ci.func_105617_z(char[])java.lang.String
		// @2AA: aastore
		// @2AB: dup
		// @2AC: bipush 63 (0x3F)
		// @2AE: aconst_null
		// @2AF: aastore
		// @2B0: dup
		// @2B1: bipush 64 (0x40)
		// @2B3: ldc "K\u0001%w\u000faS,q\u0002`"
		// @2B5: invokestatic game.C_100176_ci.func_105619_z(java.lang.String)char[]
		// @2B8: invokestatic game.C_100176_ci.func_105617_z(char[])java.lang.String
		// @2BB: aastore
		// @2BC: dup
		// @2BD: bipush 65 (0x41)
		// @2BF: ldc "G\u001c)y\u0002j\u0017+4\u0000l\u00127g\nw"
		// @2C1: invokestatic game.C_100176_ci.func_105619_z(java.lang.String)char[]
		// @2C4: invokestatic game.C_100176_ci.func_105617_z(char[])java.lang.String
		// @2C7: aastore
		// @2C8: dup
		// @2C9: bipush 66 (0x42)
		// @2CB: ldc "P\u001b1z\u0007a\u0001iv\u000fe\u0017!4\u0002v\u001e"
		// @2CD: invokestatic game.C_100176_ci.func_105619_z(java.lang.String)char[]
		// @2D0: invokestatic game.C_100176_ci.func_105617_z(char[])java.lang.String
		// @2D3: aastore
		// @2D4: dup
		// @2D5: bipush 67 (0x43)
		// @2D7: ldc "H\u001a#|\u0017$\u0000,{\u0016h\u0017!fCt\u0012'\u007f"
		// @2D9: invokestatic game.C_100176_ci.func_105619_z(java.lang.String)char[]
		// @2DC: invokestatic game.C_100176_ci.func_105617_z(char[])java.lang.String
		// @2DF: aastore
		// @2E0: dup
		// @2E1: bipush 68 (0x44)
		// @2E3: ldc "V\u00160}\u0000q\u001f%zCl\u0016%p"
		// @2E5: invokestatic game.C_100176_ci.func_105619_z(java.lang.String)char[]
		// @2E8: invokestatic game.C_100176_ci.func_105617_z(char[])java.lang.String
		// @2EB: aastore
		// @2EC: dup
		// @2ED: bipush 69 (0x45)
		// @2EF: ldc "L\u00066f\ng\u0012*qCg\u001b%g\u0010m\u0000"
		// @2F1: invokestatic game.C_100176_ci.func_105619_z(java.lang.String)char[]
		// @2F4: invokestatic game.C_100176_ci.func_105617_z(char[])java.lang.String
		// @2F7: aastore
		// @2F8: dup
		// @2F9: bipush 70 (0x46)
		// @2FB: ldc "I\u0006(`\nt\u0012'\u007fCe\u0001)"
		// @2FD: invokestatic game.C_100176_ci.func_105619_z(java.lang.String)char[]
		// @300: invokestatic game.C_100176_ci.func_105617_z(char[])java.lang.String
		// @303: aastore
		// @304: dup
		// @305: bipush 71 (0x47)
		// @307: ldc "P\u00066f\u0006pS){\u0016j\u0007-z\u0004"
		// @309: invokestatic game.C_100176_ci.func_105619_z(java.lang.String)char[]
		// @30C: invokestatic game.C_100176_ci.func_105617_z(char[])java.lang.String
		// @30F: aastore
		// @310: dup
		// @311: bipush 72 (0x48)
		// @313: ldc "W\u0010+f\u0013m\u001c*4\u0000l\u00127g\nw"
		// @315: invokestatic game.C_100176_ci.func_105619_z(java.lang.String)char[]
		// @318: invokestatic game.C_100176_ci.func_105617_z(char[])java.lang.String
		// @31B: aastore
		// @31C: dup
		// @31D: bipush 73 (0x49)
		// @31F: ldc "A\u000b4u\r`\u0016 4\u0013e\u0010/"
		// @321: invokestatic game.C_100176_ci.func_105619_z(java.lang.String)char[]
		// @324: invokestatic game.C_100176_ci.func_105617_z(char[])java.lang.String
		// @327: aastore
		// @328: dup
		// @329: bipush 74 (0x4A)
		// @32B: ldc "G\u0001+wCl\u0016%p"
		// @32D: invokestatic game.C_100176_ci.func_105619_z(java.lang.String)char[]
		// @330: invokestatic game.C_100176_ci.func_105617_z(char[])java.lang.String
		// @333: aastore
		// @334: dup
		// @335: bipush 75 (0x4B)
		// @337: ldc "G\u00011g\u000ba\u0001dw\u000be\u00007}\u0010"
		// @339: invokestatic game.C_100176_ci.func_105619_z(java.lang.String)char[]
		// @33C: invokestatic game.C_100176_ci.func_105617_z(char[])java.lang.String
		// @33F: aastore
		// @340: dup
		// @341: bipush 76 (0x4C)
		// @343: ldc "W\u0007+f\u000el\u0012)y\u0006vS%f\u000e"
		// @345: invokestatic game.C_100176_ci.func_105619_z(java.lang.String)char[]
		// @348: invokestatic game.C_100176_ci.func_105617_z(char[])java.lang.String
		// @34B: aastore
		// @34C: dup
		// @34D: bipush 77 (0x4D)
		// @34F: ldc "N\u0006)dCn\u00160"
		// @351: invokestatic game.C_100176_ci.func_105619_z(java.lang.String)char[]
		// @354: invokestatic game.C_100176_ci.func_105617_z(char[])java.lang.String
		// @357: aastore
		// @358: dup
		// @359: bipush 78 (0x4E)
		// @35B: ldc "I\u001a*{\u0017e\u000664\u000ba\u0012 "
		// @35D: invokestatic game.C_100176_ci.func_105619_z(java.lang.String)char[]
		// @360: invokestatic game.C_100176_ci.func_105617_z(char[])java.lang.String
		// @363: aastore
		// @364: dup
		// @365: bipush 79 (0x4F)
		// @367: ldc "F\u00166`\u000beS'|\u0002w\u0000-g"
		// @369: invokestatic game.C_100176_ci.func_105619_z(java.lang.String)char[]
		// @36C: invokestatic game.C_100176_ci.func_105617_z(char[])java.lang.String
		// @36F: aastore
		// @370: dup
		// @371: bipush 80 (0x50)
		// @373: ldc "P\u001a0u\rm\u0010df\u000cg\u0018!`Ct\u001c "
		// @375: invokestatic game.C_100176_ci.func_105619_z(java.lang.String)char[]
		// @378: invokestatic game.C_100176_ci.func_105617_z(char[])java.lang.String
		// @37B: aastore
		// @37C: dup
		// @37D: bipush 81 (0x51)
		// @37F: ldc "L\u0016%b\u001a$\u0000,{\u0016h\u0017!fCt\u0012'\u007f"
		// @381: invokestatic game.C_100176_ci.func_105619_z(java.lang.String)char[]
		// @384: invokestatic game.C_100176_ci.func_105617_z(char[])java.lang.String
		// @387: aastore
		// @388: dup
		// @389: bipush 82 (0x52)
		// @38B: ldc "W\u0012)a\u0011e\u001ad|\u0006e\u0017"
		// @38D: invokestatic game.C_100176_ci.func_105619_z(java.lang.String)char[]
		// @390: invokestatic game.C_100176_ci.func_105617_z(char[])java.lang.String
		// @393: aastore
		// @394: dup
		// @395: bipush 83 (0x53)
		// @397: ldc "@\u0006%xCi\u001c1z\u0017m\u001d#"
		// @399: invokestatic game.C_100176_ci.func_105619_z(java.lang.String)char[]
		// @39C: invokestatic game.C_100176_ci.func_105617_z(char[])java.lang.String
		// @39F: aastore
		// @3A0: dup
		// @3A1: bipush 84 (0x54)
		// @3A3: ldc "K\u0001&}\u0017e\u001fdw\u000be\u00007}\u0010"
		// @3A5: invokestatic game.C_100176_ci.func_105619_z(java.lang.String)char[]
		// @3A8: invokestatic game.C_100176_ci.func_105617_z(char[])java.lang.String
		// @3AB: aastore
		// @3AC: dup
		// @3AD: bipush 85 (0x55)
		// @3AF: ldc "K\u0001-{\r$\u00126y"
		// @3B1: invokestatic game.C_100176_ci.func_105619_z(java.lang.String)char[]
		// @3B4: invokestatic game.C_100176_ci.func_105617_z(char[])java.lang.String
		// @3B7: aastore
		// @3B8: dup
		// @3B9: bipush 86 (0x56)
		// @3BB: ldc "E\u0007){\u0010t\u001b!f\ngS3}\rc"
		// @3BD: invokestatic game.C_100176_ci.func_105619_z(java.lang.String)char[]
		// @3C0: invokestatic game.C_100176_ci.func_105617_z(char[])java.lang.String
		// @3C3: aastore
		// @3C4: dup
		// @3C5: bipush 87 (0x57)
		// @3C7: ldc "W\u001a*}\u0010p\u001264\u000ba\u0012 "
		// @3C9: invokestatic game.C_100176_ci.func_105619_z(java.lang.String)char[]
		// @3CC: invokestatic game.C_100176_ci.func_105617_z(char[])java.lang.String
		// @3CF: aastore
		// @3D0: dup
		// @3D1: bipush 88 (0x58)
		// @3D3: ldc "R\u0012(|\u0002h\u001f%4\u0000l\u00127g\nw"
		// @3D5: invokestatic game.C_100176_ci.func_105619_z(java.lang.String)char[]
		// @3D8: invokestatic game.C_100176_ci.func_105617_z(char[])java.lang.String
		// @3DB: aastore
		// @3DC: dup
		// @3DD: bipush 89 (0x59)
		// @3DF: ldc "B\u00067}\u000cjS&x\u0002`\u0016du\u0011i"
		// @3E1: invokestatic game.C_100176_ci.func_105619_z(java.lang.String)char[]
		// @3E4: invokestatic game.C_100176_ci.func_105617_z(char[])java.lang.String
		// @3E7: aastore
		// @3E8: dup
		// @3E9: bipush 90 (0x5A)
		// @3EB: ldc "K\u0001 z\u0002j\u0010!4\u000ek\u0006*`\nj\u0014"
		// @3ED: invokestatic game.C_100176_ci.func_105619_z(java.lang.String)char[]
		// @3F0: invokestatic game.C_100176_ci.func_105617_z(char[])java.lang.String
		// @3F3: aastore
		// @3F4: dup
		// @3F5: bipush 91 (0x5B)
		// @3F7: ldc "T\u0001!p\u0002p\u001c64\u000ba\u0012 "
		// @3F9: invokestatic game.C_100176_ci.func_105619_z(java.lang.String)char[]
		// @3FC: invokestatic game.C_100176_ci.func_105617_z(char[])java.lang.String
		// @3FF: aastore
		// @400: dup
		// @401: bipush 92 (0x5C)
		// @403: ldc "F\u0012&q\u000f$\u0010,u\u0010w\u001a7"
		// @405: invokestatic game.C_100176_ci.func_105619_z(java.lang.String)char[]
		// @408: invokestatic game.C_100176_ci.func_105617_z(char[])java.lang.String
		// @40B: aastore
		// @40C: dup
		// @40D: bipush 93 (0x5D)
		// @40F: ldc "E\u0001)4\u000cbS\u0003}\u000fc\u0012)q\u0010l"
		// @411: invokestatic game.C_100176_ci.func_105619_z(java.lang.String)char[]
		// @414: invokestatic game.C_100176_ci.func_105617_z(char[])java.lang.String
		// @417: aastore
		// @418: dup
		// @419: bipush 94 (0x5E)
		// @41B: aconst_null
		// @41C: aastore
		// @41D: dup
		// @41E: bipush 95 (0x5F)
		// @420: ldc "@\u001c+yDwS2}\u0010e\u0014!"
		// @422: invokestatic game.C_100176_ci.func_105619_z(java.lang.String)char[]
		// @425: invokestatic game.C_100176_ci.func_105617_z(char[])java.lang.String
		// @428: aastore
		// @429: putstatic java.lang.String[] game.C_100176_ci.field_105623_e
		// @42C: new game.C_100217_ao
		// @42F: dup
		// @430: bipush 12 (0x0C)
		// @432: iconst_0
		// @433: iconst_1
		// @434: iconst_0
		// @435: invokespecial game.C_100217_ao.<init>(int, int, int, int)void
		// @438: putstatic game.C_100217_ao game.C_100176_ci.field_105625_c
		// @43B: ldc "P\u0001%}\rm\u001d#"
		// @43D: invokestatic game.C_100176_ci.func_105619_z(java.lang.String)char[]
		// @440: invokestatic game.C_100176_ci.func_105617_z(char[])java.lang.String
		// @443: putstatic java.lang.String game.C_100176_ci.field_105621_f
		// @446: ldc "P\u0001=4\u0000l\u0012*s\nj\u0014d`\u000baS\"{\u000fh\u001c3}\rcS7q\u0017p\u001a*s\u0010>Sd"
		// @448: invokestatic game.C_100176_ci.func_105619_z(java.lang.String)char[]
		// @44B: invokestatic game.C_100176_ci.func_105617_z(char[])java.lang.String
		// @44E: putstatic java.lang.String game.C_100176_ci.field_105622_d
		// @451: return
	}
	
	private static char[] func_105619_z(String arg0)
	{
		// @00: aload_0
		// @01: invokevirtual java.lang.String.toCharArray()char[]
		// @04: dup
		// @05: arraylength
		// @06: iconst_2
		// @07: if_icmpge @13
		// @0A: dup
		// @0B: iconst_0
		// @0C: dup2
		// @0D: caload
		// @0E: bipush 99 (0x63)
		// @10: ixor
		// @11: i2c
		// @12: castore
		// @13: areturn
	}
	
	private static String func_105617_z(char[] arg0)
	{
		// @00: aload_0
		// @01: dup
		// @02: arraylength
		// @03: swap
		// @04: iconst_0
		// @05: istore_1
		// @06: goto @4B
		// @09: dup
		// @0A: iload_1
		// @0B: dup2
		// @0C: caload
		// @0D: iload_1
		// @0E: iconst_5
		// @0F: irem
		// @10: tableswitch def: @43, for 0: @30, for 1: @34, for 2: @39, for 3: @3E
		// @30: iconst_4
		// @31: goto @45
		// @34: bipush 115 (0x73)
		// @36: goto @45
		// @39: bipush 68 (0x44)
		// @3B: goto @45
		// @3E: bipush 20 (0x14)
		// @40: goto @45
		// @43: bipush 99 (0x63)
		// @45: ixor
		// @46: i2c
		// @47: castore
		// @48: iinc #1 +1
		// @4B: swap
		// @4C: dup_x1
		// @4D: iload_1
		// @4E: if_icmpgt @09
		// @51: new java.lang.String
		// @54: dup_x1
		// @55: swap
		// @56: invokespecial java.lang.String.<init>(char[])void
		// @59: invokevirtual java.lang.String.intern()java.lang.String
		// @5C: areturn
	}
}
