package game;

class C_100302_ka extends C_100148_bh
{
	String field_101890_ab;
	boolean field_101888_Bb;
	C_100037_wb[] field_101878_Jb;
	int field_101886_Kb;
	int field_101875_X;
	private int field_101837_bb;
	int field_101842_hb;
	int field_101858_J;
	static int field_101874_Y;
	C_100037_wb[] field_101883_qb;
	C_100112_r field_101845_sb;
	int field_101833_ob;
	int field_101880_Gb;
	int field_101848_lb;
	C_100037_wb field_101887_nb;
	boolean field_101861_U;
	int field_101867_P;
	int field_101850_Fb;
	int field_101832_tb;
	C_100037_wb field_101844_pb;
	String field_101856_I;
	int field_101877_Z;
	int field_101829_Db;
	C_100202_qi field_101891_Ob;
	boolean field_101881_yb;
	int field_101860_K;
	int field_101869_S;
	C_100037_wb field_101855_O;
	C_100037_wb[] field_101851_zb;
	int field_101830_gb;
	static String field_101870_R;
	C_100037_wb[] field_101862_T;
	private boolean field_101876_Sb;
	C_100037_wb field_101884_fb;
	private int field_101885_jb;
	int field_101841_Pb;
	int field_101854_N;
	private boolean field_101838_Lb;
	int field_101846_Ib;
	boolean field_101836_Hb;
	boolean field_101839_db;
	private int field_101849_Mb;
	int field_101868_Ab;
	private int field_101889_ub;
	int field_101843_Tb;
	int field_101871_mb;
	int field_101879_Rb;
	private int field_101857_eb;
	private boolean field_101827_cb;
	C_100037_wb[] field_101853_M;
	static String[] field_101873_vb;
	boolean field_101864_W;
	private int field_101834_kb;
	int field_101872_Nb;
	int field_101835_xb;
	int field_101840_Eb;
	C_100037_wb field_101852_L;
	int field_101859_rb;
	static C_100202_qi field_101828_Qb;
	int field_101866_Q;
	static String field_101865_V;
	static C_100137_bn field_101847_wb;
	static boolean field_101882_Cb;
	static String[] field_101863_ib;
	private static final String[] field_101831_Ub;
	
	final void func_101823_a(C_100302_ka arg0, boolean arg1, C_100302_ka arg2, int arg3)
	{
		// @00: iload_2
		// @01: ifeq @05
		// @04: return
		// @05: aload_3
		// @06: ifnonnull @1D
		// @09: aload_1
		// @0A: iconst_0
		// @0B: putfield int game.C_100302_ka.field_101843_Tb
		// @0E: aload_1
		// @0F: iconst_0
		// @10: putfield int game.C_100302_ka.field_101880_Gb
		// @13: getstatic int game.SteelSentinels.field_105275_O
		// @16: ifeq @3F
		// @19: goto @1D
		// @1C: athrow
		// @1D: aload_1
		// @1E: aload_3
		// @1F: getfield int game.C_100302_ka.field_101832_tb
		// @22: aload_3
		// @23: getfield int game.C_100302_ka.field_101843_Tb
		// @26: iadd
		// @27: putfield int game.C_100302_ka.field_101843_Tb
		// @2A: aload_1
		// @2B: aload_3
		// @2C: getfield int game.C_100302_ka.field_101848_lb
		// @2F: aload_3
		// @30: getfield int game.C_100302_ka.field_101880_Gb
		// @33: iadd
		// @34: iload #4
		// @36: ineg
		// @37: isub
		// @38: putfield int game.C_100302_ka.field_101880_Gb
		// @3B: goto @3F
		// @3E: athrow
		// @3F: goto @A4
		// @42: astore #5
		// @44: aload #5
		// @46: new java.lang.StringBuilder
		// @49: dup
		// @4A: invokespecial java.lang.StringBuilder.<init>()void
		// @4D: getstatic java.lang.String[] game.C_100302_ka.field_101831_Ub
		// @50: bipush 17 (0x11)
		// @52: aaload
		// @53: invokevirtual java.lang.StringBuilder.append(java.lang.String)java.lang.StringBuilder
		// @56: aload_1
		// @57: ifnull @63
		// @5A: getstatic java.lang.String[] game.C_100302_ka.field_101831_Ub
		// @5D: iconst_2
		// @5E: aaload
		// @5F: goto @68
		// @62: athrow
		// @63: getstatic java.lang.String[] game.C_100302_ka.field_101831_Ub
		// @66: iconst_3
		// @67: aaload
		// @68: invokevirtual java.lang.StringBuilder.append(java.lang.String)java.lang.StringBuilder
		// @6B: bipush 44 (0x2C)
		// @6D: invokevirtual java.lang.StringBuilder.append(char)java.lang.StringBuilder
		// @70: iload_2
		// @71: invokevirtual java.lang.StringBuilder.append(boolean)java.lang.StringBuilder
		// @74: bipush 44 (0x2C)
		// @76: invokevirtual java.lang.StringBuilder.append(char)java.lang.StringBuilder
		// @79: aload_3
		// @7A: ifnull @86
		// @7D: getstatic java.lang.String[] game.C_100302_ka.field_101831_Ub
		// @80: iconst_2
		// @81: aaload
		// @82: goto @8B
		// @85: athrow
		// @86: getstatic java.lang.String[] game.C_100302_ka.field_101831_Ub
		// @89: iconst_3
		// @8A: aaload
		// @8B: invokevirtual java.lang.StringBuilder.append(java.lang.String)java.lang.StringBuilder
		// @8E: bipush 44 (0x2C)
		// @90: invokevirtual java.lang.StringBuilder.append(char)java.lang.StringBuilder
		// @93: iload #4
		// @95: invokevirtual java.lang.StringBuilder.append(int)java.lang.StringBuilder
		// @98: bipush 41 (0x29)
		// @9A: invokevirtual java.lang.StringBuilder.append(char)java.lang.StringBuilder
		// @9D: invokevirtual java.lang.StringBuilder.toString()java.lang.String
		// @A0: invokestatic game.C_100181_cf.func_105695_a(java.lang.Throwable, java.lang.String)game.C_100170_cm
		// @A3: athrow
		// @A4: return
	}
	
	final int func_101818_j(int arg0)
	{
		// @00: iload_1
		// @01: ldc 218000 (0x35390)
		// @03: if_icmpeq @11
		// @06: aload_0
		// @07: iconst_1
		// @08: bipush 97 (0x61)
		// @0A: invokevirtual game.C_100302_ka.func_101819_a(boolean, byte)void
		// @0D: goto @11
		// @10: athrow
		// @11: aload_0
		// @12: bipush 46 (0x2E)
		// @14: ldc 2147483647 (0x7fffffff)
		// @16: invokevirtual game.C_100302_ka.func_101826_a(byte, int)int
		// @19: ireturn
		// @1A: astore_2
		// @1B: aload_2
		// @1C: new java.lang.StringBuilder
		// @1F: dup
		// @20: invokespecial java.lang.StringBuilder.<init>()void
		// @23: getstatic java.lang.String[] game.C_100302_ka.field_101831_Ub
		// @26: bipush 7 (0x07)
		// @28: aaload
		// @29: invokevirtual java.lang.StringBuilder.append(java.lang.String)java.lang.StringBuilder
		// @2C: iload_1
		// @2D: invokevirtual java.lang.StringBuilder.append(int)java.lang.StringBuilder
		// @30: bipush 41 (0x29)
		// @32: invokevirtual java.lang.StringBuilder.append(char)java.lang.StringBuilder
		// @35: invokevirtual java.lang.StringBuilder.toString()java.lang.String
		// @38: invokestatic game.C_100181_cf.func_105695_a(java.lang.Throwable, java.lang.String)game.C_100170_cm
		// @3B: athrow
	}
	
	static final int func_101815_e(byte arg0)
	{
		// @00: getstatic int game.SteelSentinels.field_105275_O
		// @03: istore_2
		// @04: iload_0
		// @05: bipush -14 (0xF2)
		// @07: if_icmpeq @13
		// @0A: bipush -100 (0x9C)
		// @0C: invokestatic game.C_100302_ka.func_101812_d(byte)void
		// @0F: goto @13
		// @12: athrow
		// @13: getstatic int game.C_100218_am.field_103115_N
		// @16: istore_1
		// @17: iload_1
		// @18: iconst_m1
		// @19: ixor
		// @1A: iconst_m1
		// @1B: if_icmpne @26
		// @1E: iload_2
		// @1F: ifeq @5A
		// @22: goto @26
		// @25: athrow
		// @26: bipush -2 (0xFE)
		// @28: iload_1
		// @29: iconst_m1
		// @2A: ixor
		// @2B: if_icmpne @3A
		// @2E: goto @32
		// @31: athrow
		// @32: iload_2
		// @33: ifeq @5D
		// @36: goto @3A
		// @39: athrow
		// @3A: bipush -8 (0xF8)
		// @3C: iload_1
		// @3D: iconst_m1
		// @3E: ixor
		// @3F: if_icmpeq @7C
		// @42: goto @46
		// @45: athrow
		// @46: iload_1
		// @47: iconst_m1
		// @48: ixor
		// @49: bipush -6 (0xFA)
		// @4B: if_icmpne @82
		// @4E: goto @52
		// @51: athrow
		// @52: iload_2
		// @53: ifeq @7F
		// @56: goto @5A
		// @59: athrow
		// @5A: ldc 90000 (0x15f90)
		// @5C: ireturn
		// @5D: getstatic int game.C_100181_cf.field_105704_e
		// @60: bipush 10 (0x0A)
		// @62: if_icmple @69
		// @65: goto @6C
		// @68: athrow
		// @69: ldc 218000 (0x35390)
		// @6B: ireturn
		// @6C: getstatic int game.C_100181_cf.field_105704_e
		// @6F: bipush 12 (0x0C)
		// @71: if_icmple @78
		// @74: goto @82
		// @77: athrow
		// @78: sipush 30000 (0x7530)
		// @7B: ireturn
		// @7C: ldc 218000 (0x35390)
		// @7E: ireturn
		// @7F: ldc 216000 (0x34bc0)
		// @81: ireturn
		// @82: iconst_m1
		// @83: ireturn
		// @84: astore_1
		// @85: aload_1
		// @86: new java.lang.StringBuilder
		// @89: dup
		// @8A: invokespecial java.lang.StringBuilder.<init>()void
		// @8D: getstatic java.lang.String[] game.C_100302_ka.field_101831_Ub
		// @90: bipush 6 (0x06)
		// @92: aaload
		// @93: invokevirtual java.lang.StringBuilder.append(java.lang.String)java.lang.StringBuilder
		// @96: iload_0
		// @97: invokevirtual java.lang.StringBuilder.append(int)java.lang.StringBuilder
		// @9A: bipush 41 (0x29)
		// @9C: invokevirtual java.lang.StringBuilder.append(char)java.lang.StringBuilder
		// @9F: invokevirtual java.lang.StringBuilder.toString()java.lang.String
		// @A2: invokestatic game.C_100181_cf.func_105695_a(java.lang.Throwable, java.lang.String)game.C_100170_cm
		// @A5: athrow
	}
	
	final void func_101819_a(boolean arg0, byte arg1)
	{
		// @00: iload_1
		// @01: ifne @09
		// @04: iconst_1
		// @05: goto @0A
		// @08: athrow
		// @09: iconst_0
		// @0A: putstatic boolean game.C_100318_hj.field_107205_i
		// @0D: iload_1
		// @0E: ifne @16
		// @11: iconst_1
		// @12: goto @17
		// @15: athrow
		// @16: iconst_0
		// @17: putstatic boolean game.C_100059_df.field_101613_u
		// @1A: bipush -74 (0xB6)
		// @1C: bipush -45 (0xD3)
		// @1E: iload_2
		// @1F: isub
		// @20: bipush 59 (0x3B)
		// @22: idiv
		// @23: irem
		// @24: istore_3
		// @25: aload_0
		// @26: getstatic int game.C_100196_rb.field_105821_c
		// @29: getstatic int game.C_100196_rb.field_105819_e
		// @2C: iconst_0
		// @2D: iconst_1
		// @2E: iconst_0
		// @2F: bipush -109 (0x93)
		// @31: invokespecial game.C_100302_ka.func_101816_a(int, int, int, boolean, int, int)void
		// @34: goto @62
		// @37: astore_3
		// @38: aload_3
		// @39: new java.lang.StringBuilder
		// @3C: dup
		// @3D: invokespecial java.lang.StringBuilder.<init>()void
		// @40: getstatic java.lang.String[] game.C_100302_ka.field_101831_Ub
		// @43: bipush 18 (0x12)
		// @45: aaload
		// @46: invokevirtual java.lang.StringBuilder.append(java.lang.String)java.lang.StringBuilder
		// @49: iload_1
		// @4A: invokevirtual java.lang.StringBuilder.append(boolean)java.lang.StringBuilder
		// @4D: bipush 44 (0x2C)
		// @4F: invokevirtual java.lang.StringBuilder.append(char)java.lang.StringBuilder
		// @52: iload_2
		// @53: invokevirtual java.lang.StringBuilder.append(int)java.lang.StringBuilder
		// @56: bipush 41 (0x29)
		// @58: invokevirtual java.lang.StringBuilder.append(char)java.lang.StringBuilder
		// @5B: invokevirtual java.lang.StringBuilder.toString()java.lang.String
		// @5E: invokestatic game.C_100181_cf.func_105695_a(java.lang.Throwable, java.lang.String)game.C_100170_cm
		// @61: athrow
		// @62: return
	}
	
	private final void func_101816_a(int arg0, int arg1, int arg2, boolean arg3, int arg4, int arg5)
	{
		// @000: getstatic int game.SteelSentinels.field_105275_O
		// @003: istore #15
		// @005: aload_0
		// @006: getfield int game.C_100302_ka.field_101885_jb
		// @009: ifgt @01A
		// @00C: aload_0
		// @00D: getfield int game.C_100302_ka.field_101885_jb
		// @010: ldc 1329072578 (0x4f3809c2)
		// @012: ishr
		// @013: istore #7
		// @015: iload #15
		// @017: ifeq @025
		// @01A: aload_0
		// @01B: getfield int game.C_100302_ka.field_101885_jb
		// @01E: ineg
		// @01F: ldc -2004239486 (0x8889bb82)
		// @021: ishr
		// @022: ineg
		// @023: istore #7
		// @025: aload_0
		// @026: dup
		// @027: getfield int game.C_100302_ka.field_101841_Pb
		// @02A: iload #7
		// @02C: iadd
		// @02D: putfield int game.C_100302_ka.field_101841_Pb
		// @030: aload_0
		// @031: dup
		// @032: getfield int game.C_100302_ka.field_101885_jb
		// @035: iload #7
		// @037: isub
		// @038: putfield int game.C_100302_ka.field_101885_jb
		// @03B: iconst_0
		// @03C: aload_0
		// @03D: getfield int game.C_100302_ka.field_101843_Tb
		// @040: if_icmpge @053
		// @043: aload_0
		// @044: getfield int game.C_100302_ka.field_101843_Tb
		// @047: ineg
		// @048: ldc 1877931970 (0x6feef7c2)
		// @04A: ishr
		// @04B: ineg
		// @04C: istore #7
		// @04E: iload #15
		// @050: ifeq @05C
		// @053: aload_0
		// @054: getfield int game.C_100302_ka.field_101843_Tb
		// @057: ldc -1271389438 (0xb4382302)
		// @059: ishr
		// @05A: istore #7
		// @05C: aload_0
		// @05D: dup
		// @05E: getfield int game.C_100302_ka.field_101880_Gb
		// @061: iload #7
		// @063: iadd
		// @064: putfield int game.C_100302_ka.field_101880_Gb
		// @067: aload_0
		// @068: dup
		// @069: getfield int game.C_100302_ka.field_101843_Tb
		// @06C: iload #7
		// @06E: isub
		// @06F: putfield int game.C_100302_ka.field_101843_Tb
		// @072: aload_0
		// @073: getfield int game.C_100302_ka.field_101889_ub
		// @076: iconst_m1
		// @077: ixor
		// @078: iconst_m1
		// @079: if_icmpge @08C
		// @07C: aload_0
		// @07D: getfield int game.C_100302_ka.field_101889_ub
		// @080: ineg
		// @081: ldc 527392002 (0x1f6f5d02)
		// @083: ishr
		// @084: ineg
		// @085: istore #7
		// @087: iload #15
		// @089: ifeq @095
		// @08C: aload_0
		// @08D: getfield int game.C_100302_ka.field_101889_ub
		// @090: ldc -863871422 (0xcc825e42)
		// @092: ishr
		// @093: istore #7
		// @095: aload_0
		// @096: dup
		// @097: getfield int game.C_100302_ka.field_101889_ub
		// @09A: iload #7
		// @09C: isub
		// @09D: putfield int game.C_100302_ka.field_101889_ub
		// @0A0: aload_0
		// @0A1: dup
		// @0A2: getfield int game.C_100302_ka.field_101886_Kb
		// @0A5: iload #7
		// @0A7: iadd
		// @0A8: putfield int game.C_100302_ka.field_101886_Kb
		// @0AB: aload_0
		// @0AC: getfield int game.C_100302_ka.field_101832_tb
		// @0AF: ifle @0C2
		// @0B2: aload_0
		// @0B3: getfield int game.C_100302_ka.field_101832_tb
		// @0B6: ineg
		// @0B7: ldc -261084798 (0xf0702982)
		// @0B9: ishr
		// @0BA: ineg
		// @0BB: istore #7
		// @0BD: iload #15
		// @0BF: ifeq @0CB
		// @0C2: aload_0
		// @0C3: getfield int game.C_100302_ka.field_101832_tb
		// @0C6: ldc 760931714 (0x2d5ae582)
		// @0C8: ishr
		// @0C9: istore #7
		// @0CB: bipush 105 (0x69)
		// @0CD: iload #6
		// @0CF: bipush 25 (0x19)
		// @0D1: isub
		// @0D2: bipush 43 (0x2B)
		// @0D4: idiv
		// @0D5: idiv
		// @0D6: istore #8
		// @0D8: iload #4
		// @0DA: aload_0
		// @0DB: getfield boolean game.C_100302_ka.field_101864_W
		// @0DE: iand
		// @0DF: istore #4
		// @0E1: aload_0
		// @0E2: aload_0
		// @0E3: getfield int game.C_100302_ka.field_101880_Gb
		// @0E6: iload #5
		// @0E8: iadd
		// @0E9: putfield int game.C_100302_ka.field_101835_xb
		// @0EC: aload_0
		// @0ED: dup
		// @0EE: getfield int game.C_100302_ka.field_101848_lb
		// @0F1: iload #7
		// @0F3: iadd
		// @0F4: putfield int game.C_100302_ka.field_101848_lb
		// @0F7: aload_0
		// @0F8: iload_3
		// @0F9: aload_0
		// @0FA: getfield int game.C_100302_ka.field_101841_Pb
		// @0FD: ineg
		// @0FE: isub
		// @0FF: putfield int game.C_100302_ka.field_101840_Eb
		// @102: aload_0
		// @103: dup
		// @104: getfield int game.C_100302_ka.field_101832_tb
		// @107: iload #7
		// @109: isub
		// @10A: putfield int game.C_100302_ka.field_101832_tb
		// @10D: getstatic int game.C_100196_rb.field_105827_i
		// @110: istore #9
		// @112: getstatic int game.C_100196_rb.field_105816_f
		// @115: istore #10
		// @117: getstatic int game.C_100196_rb.field_105820_b
		// @11A: istore #11
		// @11C: getstatic int game.C_100196_rb.field_105823_l
		// @11F: istore #12
		// @121: aload_0
		// @122: getfield int game.C_100302_ka.field_101840_Eb
		// @125: aload_0
		// @126: getfield int game.C_100302_ka.field_101835_xb
		// @129: aload_0
		// @12A: getfield int game.C_100302_ka.field_101886_Kb
		// @12D: aload_0
		// @12E: getfield int game.C_100302_ka.field_101840_Eb
		// @131: iadd
		// @132: aload_0
		// @133: getfield int game.C_100302_ka.field_101848_lb
		// @136: aload_0
		// @137: getfield int game.C_100302_ka.field_101835_xb
		// @13A: iadd
		// @13B: invokestatic game.C_100196_rb.func_105779_e(int, int, int, int)void
		// @13E: iconst_0
		// @13F: istore #13
		// @141: getstatic boolean game.C_100318_hj.field_107205_i
		// @144: ifne @1C7
		// @147: iload #4
		// @149: ifeq @1C7
		// @14C: goto @150
		// @14F: athrow
		// @150: getstatic int game.C_100102_w.field_104636_c
		// @153: iconst_m1
		// @154: ixor
		// @155: iconst_m1
		// @156: if_icmpeq @1C7
		// @159: goto @15D
		// @15C: athrow
		// @15D: getstatic int game.C_100340_je.field_102981_m
		// @160: getstatic int game.C_100196_rb.field_105827_i
		// @163: if_icmplt @1C7
		// @166: goto @16A
		// @169: athrow
		// @16A: getstatic int game.C_100340_je.field_102981_m
		// @16D: getstatic int game.C_100196_rb.field_105820_b
		// @170: if_icmpge @1C7
		// @173: goto @177
		// @176: athrow
		// @177: getstatic int game.C_100196_rb.field_105816_f
		// @17A: iconst_m1
		// @17B: ixor
		// @17C: getstatic int game.C_100125_tm.field_100745_p
		// @17F: iconst_m1
		// @180: ixor
		// @181: if_icmplt @1C7
		// @184: goto @188
		// @187: athrow
		// @188: getstatic int game.C_100196_rb.field_105823_l
		// @18B: iconst_m1
		// @18C: ixor
		// @18D: getstatic int game.C_100125_tm.field_100745_p
		// @190: iconst_m1
		// @191: ixor
		// @192: if_icmpge @1C7
		// @195: goto @199
		// @198: athrow
		// @199: aload_0
		// @19A: getstatic int game.C_100102_w.field_104636_c
		// @19D: putfield int game.C_100302_ka.field_101879_Rb
		// @1A0: aload_0
		// @1A1: getstatic int game.C_100102_w.field_104636_c
		// @1A4: putfield int game.C_100302_ka.field_101854_N
		// @1A7: aload_0
		// @1A8: getstatic int game.C_100340_je.field_102981_m
		// @1AB: aload_0
		// @1AC: getfield int game.C_100302_ka.field_101840_Eb
		// @1AF: isub
		// @1B0: putfield int game.C_100302_ka.field_101842_hb
		// @1B3: iconst_1
		// @1B4: istore #13
		// @1B6: aload_0
		// @1B7: getstatic int game.C_100125_tm.field_100745_p
		// @1BA: aload_0
		// @1BB: getfield int game.C_100302_ka.field_101835_xb
		// @1BE: isub
		// @1BF: putfield int game.C_100302_ka.field_101834_kb
		// @1C2: iload #15
		// @1C4: ifeq @1E2
		// @1C7: aload_0
		// @1C8: iconst_0
		// @1C9: putfield int game.C_100302_ka.field_101854_N
		// @1CC: iconst_m1
		// @1CD: getstatic int game.C_100102_w.field_104636_c
		// @1D0: iconst_m1
		// @1D1: ixor
		// @1D2: if_icmpeq @1E2
		// @1D5: goto @1D9
		// @1D8: athrow
		// @1D9: aload_0
		// @1DA: iconst_0
		// @1DB: putfield int game.C_100302_ka.field_101879_Rb
		// @1DE: goto @1E2
		// @1E1: athrow
		// @1E2: iconst_0
		// @1E3: getstatic int game.C_100083_c.field_103171_R
		// @1E6: if_icmpne @1F2
		// @1E9: aload_0
		// @1EA: iconst_0
		// @1EB: putfield int game.C_100302_ka.field_101879_Rb
		// @1EE: goto @1F2
		// @1F1: athrow
		// @1F2: aload_0
		// @1F3: getstatic boolean game.C_100059_df.field_101613_u
		// @1F6: ifne @23A
		// @1F9: getstatic int game.C_100015_wh.field_103781_g
		// @1FC: iconst_m1
		// @1FD: ixor
		// @1FE: getstatic int game.C_100196_rb.field_105827_i
		// @201: iconst_m1
		// @202: ixor
		// @203: if_icmpgt @23A
		// @206: goto @20A
		// @209: athrow
		// @20A: getstatic int game.C_100015_wh.field_103781_g
		// @20D: getstatic int game.C_100196_rb.field_105820_b
		// @210: if_icmpge @23A
		// @213: goto @217
		// @216: athrow
		// @217: getstatic int game.C_100338_jc.field_105370_l
		// @21A: iconst_m1
		// @21B: ixor
		// @21C: getstatic int game.C_100196_rb.field_105816_f
		// @21F: iconst_m1
		// @220: ixor
		// @221: if_icmpgt @23A
		// @224: goto @228
		// @227: athrow
		// @228: getstatic int game.C_100338_jc.field_105370_l
		// @22B: getstatic int game.C_100196_rb.field_105823_l
		// @22E: if_icmpge @23A
		// @231: goto @235
		// @234: athrow
		// @235: iconst_1
		// @236: goto @23B
		// @239: athrow
		// @23A: iconst_0
		// @23B: putfield boolean game.C_100302_ka.field_101836_Hb
		// @23E: aload_0
		// @23F: aload_0
		// @240: getfield boolean game.C_100302_ka.field_101836_Hb
		// @243: ifeq @262
		// @246: aload_0
		// @247: getfield int game.C_100302_ka.field_101879_Rb
		// @24A: getstatic int game.C_100083_c.field_103171_R
		// @24D: if_icmpne @262
		// @250: goto @254
		// @253: athrow
		// @254: iload #4
		// @256: ifeq @262
		// @259: goto @25D
		// @25C: athrow
		// @25D: iconst_1
		// @25E: goto @263
		// @261: athrow
		// @262: iconst_0
		// @263: putfield boolean game.C_100302_ka.field_101839_db
		// @266: aload_0
		// @267: getfield game.C_100202_qi game.C_100302_ka.field_101891_Ob
		// @26A: ifnonnull @271
		// @26D: goto @2B9
		// @270: athrow
		// @271: aload_0
		// @272: getfield game.C_100202_qi game.C_100302_ka.field_101891_Ob
		// @275: bipush -79 (0xB1)
		// @277: invokevirtual game.C_100202_qi.func_105906_b(int)game.C_100158_da
		// @27A: checkcast game.C_100302_ka
		// @27D: astore #14
		// @27F: aload #14
		// @281: ifnull @2B9
		// @284: aload #14
		// @286: aload_0
		// @287: getfield int game.C_100302_ka.field_101848_lb
		// @28A: aload_0
		// @28B: getfield int game.C_100302_ka.field_101886_Kb
		// @28E: aload_0
		// @28F: getfield int game.C_100302_ka.field_101840_Eb
		// @292: iload #4
		// @294: aload_0
		// @295: getfield int game.C_100302_ka.field_101835_xb
		// @298: bipush -81 (0xAF)
		// @29A: invokespecial game.C_100302_ka.func_101816_a(int, int, int, boolean, int, int)void
		// @29D: aload_0
		// @29E: getfield game.C_100202_qi game.C_100302_ka.field_101891_Ob
		// @2A1: bipush -115 (0x8D)
		// @2A3: invokevirtual game.C_100202_qi.func_105898_a(byte)game.C_100158_da
		// @2A6: checkcast game.C_100302_ka
		// @2A9: astore #14
		// @2AB: iload #15
		// @2AD: ifne @2C8
		// @2B0: iload #15
		// @2B2: ifeq @27F
		// @2B5: goto @2B9
		// @2B8: athrow
		// @2B9: aload_0
		// @2BA: getfield boolean game.C_100302_ka.field_101836_Hb
		// @2BD: ifeq @2C8
		// @2C0: iconst_1
		// @2C1: putstatic boolean game.C_100059_df.field_101613_u
		// @2C4: goto @2C8
		// @2C7: athrow
		// @2C8: iload #13
		// @2CA: ifeq @2D5
		// @2CD: iconst_1
		// @2CE: putstatic boolean game.C_100318_hj.field_107205_i
		// @2D1: goto @2D5
		// @2D4: athrow
		// @2D5: iload #9
		// @2D7: iload #10
		// @2D9: iload #11
		// @2DB: iload #12
		// @2DD: invokestatic game.C_100196_rb.func_105815_h(int, int, int, int)void
		// @2E0: iconst_0
		// @2E1: aload_0
		// @2E2: getfield int game.C_100302_ka.field_101879_Rb
		// @2E5: if_icmpeq @39A
		// @2E8: aload_0
		// @2E9: getfield boolean game.C_100302_ka.field_101888_Bb
		// @2EC: ifeq @39A
		// @2EF: goto @2F3
		// @2F2: athrow
		// @2F3: aload_0
		// @2F4: getstatic int game.C_100338_jc.field_105370_l
		// @2F7: aload_0
		// @2F8: getfield int game.C_100302_ka.field_101834_kb
		// @2FB: isub
		// @2FC: iload #5
		// @2FE: ineg
		// @2FF: iadd
		// @300: putfield int game.C_100302_ka.field_101880_Gb
		// @303: aload_0
		// @304: getstatic int game.C_100015_wh.field_103781_g
		// @307: aload_0
		// @308: getfield int game.C_100302_ka.field_101842_hb
		// @30B: isub
		// @30C: iload_3
		// @30D: isub
		// @30E: putfield int game.C_100302_ka.field_101841_Pb
		// @311: iconst_0
		// @312: aload_0
		// @313: getfield int game.C_100302_ka.field_101841_Pb
		// @316: if_icmple @326
		// @319: goto @31D
		// @31C: athrow
		// @31D: aload_0
		// @31E: iconst_0
		// @31F: putfield int game.C_100302_ka.field_101841_Pb
		// @322: goto @326
		// @325: athrow
		// @326: aload_0
		// @327: getfield int game.C_100302_ka.field_101886_Kb
		// @32A: ineg
		// @32B: iload_2
		// @32C: iadd
		// @32D: iconst_m1
		// @32E: ixor
		// @32F: aload_0
		// @330: getfield int game.C_100302_ka.field_101841_Pb
		// @333: iconst_m1
		// @334: ixor
		// @335: if_icmpgt @33C
		// @338: goto @347
		// @33B: athrow
		// @33C: aload_0
		// @33D: iload_2
		// @33E: aload_0
		// @33F: getfield int game.C_100302_ka.field_101886_Kb
		// @342: ineg
		// @343: iadd
		// @344: putfield int game.C_100302_ka.field_101841_Pb
		// @347: aload_0
		// @348: getfield int game.C_100302_ka.field_101880_Gb
		// @34B: iconst_m1
		// @34C: ixor
		// @34D: iconst_m1
		// @34E: if_icmpgt @355
		// @351: goto @35A
		// @354: athrow
		// @355: aload_0
		// @356: iconst_0
		// @357: putfield int game.C_100302_ka.field_101880_Gb
		// @35A: aload_0
		// @35B: iconst_0
		// @35C: putfield int game.C_100302_ka.field_101885_jb
		// @35F: aload_0
		// @360: getfield int game.C_100302_ka.field_101880_Gb
		// @363: iconst_m1
		// @364: ixor
		// @365: iload_1
		// @366: aload_0
		// @367: getfield int game.C_100302_ka.field_101848_lb
		// @36A: isub
		// @36B: iconst_m1
		// @36C: ixor
		// @36D: if_icmpge @37F
		// @370: aload_0
		// @371: aload_0
		// @372: getfield int game.C_100302_ka.field_101848_lb
		// @375: ineg
		// @376: iload_1
		// @377: iadd
		// @378: putfield int game.C_100302_ka.field_101880_Gb
		// @37B: goto @37F
		// @37E: athrow
		// @37F: aload_0
		// @380: iload_3
		// @381: aload_0
		// @382: getfield int game.C_100302_ka.field_101841_Pb
		// @385: ineg
		// @386: isub
		// @387: putfield int game.C_100302_ka.field_101840_Eb
		// @38A: aload_0
		// @38B: iconst_0
		// @38C: putfield int game.C_100302_ka.field_101843_Tb
		// @38F: aload_0
		// @390: aload_0
		// @391: getfield int game.C_100302_ka.field_101880_Gb
		// @394: iload #5
		// @396: iadd
		// @397: putfield int game.C_100302_ka.field_101835_xb
		// @39A: goto @3F1
		// @39D: astore #7
		// @39F: aload #7
		// @3A1: new java.lang.StringBuilder
		// @3A4: dup
		// @3A5: invokespecial java.lang.StringBuilder.<init>()void
		// @3A8: getstatic java.lang.String[] game.C_100302_ka.field_101831_Ub
		// @3AB: bipush 14 (0x0E)
		// @3AD: aaload
		// @3AE: invokevirtual java.lang.StringBuilder.append(java.lang.String)java.lang.StringBuilder
		// @3B1: iload_1
		// @3B2: invokevirtual java.lang.StringBuilder.append(int)java.lang.StringBuilder
		// @3B5: bipush 44 (0x2C)
		// @3B7: invokevirtual java.lang.StringBuilder.append(char)java.lang.StringBuilder
		// @3BA: iload_2
		// @3BB: invokevirtual java.lang.StringBuilder.append(int)java.lang.StringBuilder
		// @3BE: bipush 44 (0x2C)
		// @3C0: invokevirtual java.lang.StringBuilder.append(char)java.lang.StringBuilder
		// @3C3: iload_3
		// @3C4: invokevirtual java.lang.StringBuilder.append(int)java.lang.StringBuilder
		// @3C7: bipush 44 (0x2C)
		// @3C9: invokevirtual java.lang.StringBuilder.append(char)java.lang.StringBuilder
		// @3CC: iload #4
		// @3CE: invokevirtual java.lang.StringBuilder.append(boolean)java.lang.StringBuilder
		// @3D1: bipush 44 (0x2C)
		// @3D3: invokevirtual java.lang.StringBuilder.append(char)java.lang.StringBuilder
		// @3D6: iload #5
		// @3D8: invokevirtual java.lang.StringBuilder.append(int)java.lang.StringBuilder
		// @3DB: bipush 44 (0x2C)
		// @3DD: invokevirtual java.lang.StringBuilder.append(char)java.lang.StringBuilder
		// @3E0: iload #6
		// @3E2: invokevirtual java.lang.StringBuilder.append(int)java.lang.StringBuilder
		// @3E5: bipush 41 (0x29)
		// @3E7: invokevirtual java.lang.StringBuilder.append(char)java.lang.StringBuilder
		// @3EA: invokevirtual java.lang.StringBuilder.toString()java.lang.String
		// @3ED: invokestatic game.C_100181_cf.func_105695_a(java.lang.Throwable, java.lang.String)game.C_100170_cm
		// @3F0: athrow
		// @3F1: return
	}
	
	private final void func_101811_a(boolean arg0, int arg1, int arg2, boolean arg3, boolean arg4, boolean arg5, boolean arg6, int arg7, boolean arg8, int arg9, int arg10)
	{
		// @000: getstatic int game.SteelSentinels.field_105275_O
		// @003: istore #25
		// @005: aload_0
		// @006: iload_3
		// @007: aload_0
		// @008: getfield int game.C_100302_ka.field_101880_Gb
		// @00B: ineg
		// @00C: isub
		// @00D: putfield int game.C_100302_ka.field_101835_xb
		// @010: iload #8
		// @012: iconst_1
		// @013: if_icmpeq @017
		// @016: return
		// @017: aload_0
		// @018: aload_0
		// @019: getfield int game.C_100302_ka.field_101841_Pb
		// @01C: iload #11
		// @01E: iadd
		// @01F: putfield int game.C_100302_ka.field_101840_Eb
		// @022: getstatic int game.C_100196_rb.field_105827_i
		// @025: istore #12
		// @027: getstatic int game.C_100196_rb.field_105816_f
		// @02A: istore #13
		// @02C: getstatic int game.C_100196_rb.field_105820_b
		// @02F: istore #14
		// @031: getstatic int game.C_100196_rb.field_105823_l
		// @034: istore #15
		// @036: aload_0
		// @037: getfield int game.C_100302_ka.field_101840_Eb
		// @03A: aload_0
		// @03B: getfield int game.C_100302_ka.field_101835_xb
		// @03E: aload_0
		// @03F: getfield int game.C_100302_ka.field_101886_Kb
		// @042: aload_0
		// @043: getfield int game.C_100302_ka.field_101840_Eb
		// @046: iadd
		// @047: aload_0
		// @048: getfield int game.C_100302_ka.field_101848_lb
		// @04B: aload_0
		// @04C: getfield int game.C_100302_ka.field_101835_xb
		// @04F: iadd
		// @050: invokestatic game.C_100196_rb.func_105779_e(int, int, int, int)void
		// @053: iload #6
		// @055: aload_0
		// @056: getfield boolean game.C_100302_ka.field_101864_W
		// @059: iand
		// @05A: istore #6
		// @05C: aload_0
		// @05D: getfield boolean game.C_100302_ka.field_101876_Sb
		// @060: ifne @07D
		// @063: aload_0
		// @064: getfield boolean game.C_100302_ka.field_101839_db
		// @067: istore #5
		// @069: aload_0
		// @06A: getfield boolean game.C_100302_ka.field_101861_U
		// @06D: istore_1
		// @06E: aload_0
		// @06F: getfield int game.C_100302_ka.field_101879_Rb
		// @072: ifeq @07A
		// @075: iconst_1
		// @076: goto @07B
		// @079: athrow
		// @07A: iconst_0
		// @07B: istore #9
		// @07D: aload_0
		// @07E: getfield game.C_100037_wb[] game.C_100302_ka.field_101862_T
		// @081: astore #16
		// @083: aload_0
		// @084: getfield game.C_100037_wb game.C_100302_ka.field_101887_nb
		// @087: astore #17
		// @089: aload_0
		// @08A: getfield int game.C_100302_ka.field_101830_gb
		// @08D: istore #18
		// @08F: iconst_0
		// @090: istore #19
		// @092: iload #6
		// @094: ifeq @09B
		// @097: goto @0CD
		// @09A: athrow
		// @09B: aload_0
		// @09C: getfield game.C_100037_wb game.C_100302_ka.field_101852_L
		// @09F: ifnonnull @0A6
		// @0A2: goto @0AC
		// @0A5: athrow
		// @0A6: aload_0
		// @0A7: getfield game.C_100037_wb game.C_100302_ka.field_101852_L
		// @0AA: astore #17
		// @0AC: aload_0
		// @0AD: getfield int game.C_100302_ka.field_101859_rb
		// @0B0: iconst_m1
		// @0B1: ixor
		// @0B2: iconst_m1
		// @0B3: if_icmpgt @0BC
		// @0B6: aload_0
		// @0B7: getfield int game.C_100302_ka.field_101859_rb
		// @0BA: istore #18
		// @0BC: aload_0
		// @0BD: getfield game.C_100037_wb[] game.C_100302_ka.field_101853_M
		// @0C0: ifnonnull @0C7
		// @0C3: goto @0CD
		// @0C6: athrow
		// @0C7: aload_0
		// @0C8: getfield game.C_100037_wb[] game.C_100302_ka.field_101853_M
		// @0CB: astore #16
		// @0CD: iconst_0
		// @0CE: istore #20
		// @0D0: iload #5
		// @0D2: ifne @0D9
		// @0D5: goto @132
		// @0D8: athrow
		// @0D9: aload_0
		// @0DA: getfield int game.C_100302_ka.field_101849_Mb
		// @0DD: ldc -2147483648 (0x80000000)
		// @0DF: if_icmpne @0E6
		// @0E2: goto @0EC
		// @0E5: athrow
		// @0E6: aload_0
		// @0E7: getfield int game.C_100302_ka.field_101849_Mb
		// @0EA: istore #19
		// @0EC: aconst_null
		// @0ED: aload_0
		// @0EE: getfield game.C_100037_wb[] game.C_100302_ka.field_101883_qb
		// @0F1: if_acmpne @0F8
		// @0F4: goto @0FE
		// @0F7: athrow
		// @0F8: aload_0
		// @0F9: getfield game.C_100037_wb[] game.C_100302_ka.field_101883_qb
		// @0FC: astore #16
		// @0FE: aload_0
		// @0FF: getfield int game.C_100302_ka.field_101860_K
		// @102: iflt @10B
		// @105: aload_0
		// @106: getfield int game.C_100302_ka.field_101860_K
		// @109: istore #18
		// @10B: aconst_null
		// @10C: aload_0
		// @10D: getfield game.C_100037_wb game.C_100302_ka.field_101844_pb
		// @110: if_acmpne @117
		// @113: goto @11D
		// @116: athrow
		// @117: aload_0
		// @118: getfield game.C_100037_wb game.C_100302_ka.field_101844_pb
		// @11B: astore #17
		// @11D: ldc 2147483647 (0x7fffffff)
		// @11F: aload_0
		// @120: getfield int game.C_100302_ka.field_101837_bb
		// @123: iconst_m1
		// @124: ixor
		// @125: if_icmpne @12C
		// @128: goto @132
		// @12B: athrow
		// @12C: aload_0
		// @12D: getfield int game.C_100302_ka.field_101837_bb
		// @130: istore #20
		// @132: iload #9
		// @134: ifeq @195
		// @137: aload_0
		// @138: getfield game.C_100037_wb[] game.C_100302_ka.field_101851_zb
		// @13B: ifnonnull @146
		// @13E: goto @142
		// @141: athrow
		// @142: goto @14C
		// @145: athrow
		// @146: aload_0
		// @147: getfield game.C_100037_wb[] game.C_100302_ka.field_101851_zb
		// @14A: astore #16
		// @14C: aload_0
		// @14D: getfield int game.C_100302_ka.field_101869_S
		// @150: iconst_m1
		// @151: ixor
		// @152: ldc 2147483647 (0x7fffffff)
		// @154: if_icmpne @15B
		// @157: goto @161
		// @15A: athrow
		// @15B: aload_0
		// @15C: getfield int game.C_100302_ka.field_101869_S
		// @15F: istore #19
		// @161: aload_0
		// @162: getfield int game.C_100302_ka.field_101877_Z
		// @165: ldc -2147483648 (0x80000000)
		// @167: if_icmpeq @170
		// @16A: aload_0
		// @16B: getfield int game.C_100302_ka.field_101877_Z
		// @16E: istore #20
		// @170: aload_0
		// @171: getfield int game.C_100302_ka.field_101868_Ab
		// @174: iconst_m1
		// @175: ixor
		// @176: iconst_m1
		// @177: if_icmple @17E
		// @17A: goto @184
		// @17D: athrow
		// @17E: aload_0
		// @17F: getfield int game.C_100302_ka.field_101868_Ab
		// @182: istore #18
		// @184: aload_0
		// @185: getfield game.C_100037_wb game.C_100302_ka.field_101884_fb
		// @188: ifnonnull @18F
		// @18B: goto @195
		// @18E: athrow
		// @18F: aload_0
		// @190: getfield game.C_100037_wb game.C_100302_ka.field_101884_fb
		// @193: astore #17
		// @195: iload_1
		// @196: ifne @19D
		// @199: goto @1F8
		// @19C: athrow
		// @19D: aload_0
		// @19E: getfield int game.C_100302_ka.field_101866_Q
		// @1A1: iconst_m1
		// @1A2: ixor
		// @1A3: ldc 2147483647 (0x7fffffff)
		// @1A5: if_icmpne @1AC
		// @1A8: goto @1B2
		// @1AB: athrow
		// @1AC: aload_0
		// @1AD: getfield int game.C_100302_ka.field_101866_Q
		// @1B0: istore #20
		// @1B2: aload_0
		// @1B3: getfield game.C_100037_wb[] game.C_100302_ka.field_101878_Jb
		// @1B6: ifnonnull @1BD
		// @1B9: goto @1C3
		// @1BC: athrow
		// @1BD: aload_0
		// @1BE: getfield game.C_100037_wb[] game.C_100302_ka.field_101878_Jb
		// @1C1: astore #16
		// @1C3: aload_0
		// @1C4: getfield int game.C_100302_ka.field_101867_P
		// @1C7: ldc -2147483648 (0x80000000)
		// @1C9: if_icmpne @1D0
		// @1CC: goto @1D6
		// @1CF: athrow
		// @1D0: aload_0
		// @1D1: getfield int game.C_100302_ka.field_101867_P
		// @1D4: istore #19
		// @1D6: aconst_null
		// @1D7: aload_0
		// @1D8: getfield game.C_100037_wb game.C_100302_ka.field_101855_O
		// @1DB: if_acmpeq @1E4
		// @1DE: aload_0
		// @1DF: getfield game.C_100037_wb game.C_100302_ka.field_101855_O
		// @1E2: astore #17
		// @1E4: aload_0
		// @1E5: getfield int game.C_100302_ka.field_101872_Nb
		// @1E8: iconst_m1
		// @1E9: ixor
		// @1EA: iconst_m1
		// @1EB: if_icmple @1F2
		// @1EE: goto @1F8
		// @1F1: athrow
		// @1F2: aload_0
		// @1F3: getfield int game.C_100302_ka.field_101872_Nb
		// @1F6: istore #18
		// @1F8: aload_0
		// @1F9: getfield int game.C_100302_ka.field_101846_Ib
		// @1FC: iload #19
		// @1FE: iadd
		// @1FF: istore #21
		// @201: aload_0
		// @202: getfield int game.C_100302_ka.field_101875_X
		// @205: iload #20
		// @207: ineg
		// @208: isub
		// @209: istore #22
		// @20B: aload_0
		// @20C: getfield boolean game.C_100302_ka.field_101881_yb
		// @20F: ifne @235
		// @212: iload #8
		// @214: bipush -2 (0xFE)
		// @216: iadd
		// @217: aload_0
		// @218: getfield int game.C_100302_ka.field_101886_Kb
		// @21B: aload #16
		// @21D: aload_0
		// @21E: getfield int game.C_100302_ka.field_101840_Eb
		// @221: aload_0
		// @222: getfield int game.C_100302_ka.field_101848_lb
		// @225: aload_0
		// @226: getfield int game.C_100302_ka.field_101835_xb
		// @229: invokestatic game.C_100100_i.func_102009_a(int, int, game.C_100037_wb[], int, int, int)void
		// @22C: iload #25
		// @22E: ifeq @245
		// @231: goto @235
		// @234: athrow
		// @235: iconst_m1
		// @236: iload_2
		// @237: aload #16
		// @239: iload #11
		// @23B: iload #10
		// @23D: iload_3
		// @23E: invokestatic game.C_100100_i.func_102009_a(int, int, game.C_100037_wb[], int, int, int)void
		// @241: goto @245
		// @244: athrow
		// @245: aconst_null
		// @246: aload #17
		// @248: if_acmpeq @2FC
		// @24B: iload #21
		// @24D: aload_0
		// @24E: getfield int game.C_100302_ka.field_101840_Eb
		// @251: iadd
		// @252: istore #23
		// @254: iload #22
		// @256: aload_0
		// @257: getfield int game.C_100302_ka.field_101835_xb
		// @25A: iadd
		// @25B: istore #24
		// @25D: bipush -2 (0xFE)
		// @25F: aload_0
		// @260: getfield int game.C_100302_ka.field_101850_Fb
		// @263: iconst_m1
		// @264: ixor
		// @265: if_icmpeq @26C
		// @268: goto @27E
		// @26B: athrow
		// @26C: iload #23
		// @26E: aload #17
		// @270: getfield int game.C_100037_wb.field_102341_y
		// @273: ineg
		// @274: aload_0
		// @275: getfield int game.C_100302_ka.field_101886_Kb
		// @278: iadd
		// @279: iconst_2
		// @27A: idiv
		// @27B: iadd
		// @27C: istore #23
		// @27E: aload_0
		// @27F: getfield int game.C_100302_ka.field_101858_J
		// @282: iconst_1
		// @283: if_icmpeq @28A
		// @286: goto @29C
		// @289: athrow
		// @28A: iload #24
		// @28C: aload #17
		// @28E: getfield int game.C_100037_wb.field_102340_z
		// @291: ineg
		// @292: aload_0
		// @293: getfield int game.C_100302_ka.field_101848_lb
		// @296: iadd
		// @297: iconst_2
		// @298: idiv
		// @299: iadd
		// @29A: istore #24
		// @29C: iconst_2
		// @29D: aload_0
		// @29E: getfield int game.C_100302_ka.field_101850_Fb
		// @2A1: if_icmpne @2B4
		// @2A4: iload #23
		// @2A6: aload #17
		// @2A8: getfield int game.C_100037_wb.field_102341_y
		// @2AB: ineg
		// @2AC: aload_0
		// @2AD: getfield int game.C_100302_ka.field_101886_Kb
		// @2B0: iadd
		// @2B1: iadd
		// @2B2: istore #23
		// @2B4: bipush -3 (0xFD)
		// @2B6: aload_0
		// @2B7: getfield int game.C_100302_ka.field_101858_J
		// @2BA: iconst_m1
		// @2BB: ixor
		// @2BC: if_icmpne @2CF
		// @2BF: iload #24
		// @2C1: aload_0
		// @2C2: getfield int game.C_100302_ka.field_101848_lb
		// @2C5: aload #17
		// @2C7: getfield int game.C_100037_wb.field_102340_z
		// @2CA: ineg
		// @2CB: iadd
		// @2CC: iadd
		// @2CD: istore #24
		// @2CF: aload_0
		// @2D0: getfield int game.C_100302_ka.field_101857_eb
		// @2D3: sipush 256 (0x0100)
		// @2D6: if_icmplt @2EB
		// @2D9: aload #17
		// @2DB: iload #23
		// @2DD: iload #24
		// @2DF: invokevirtual game.C_100037_wb.func_102353_h(int, int)void
		// @2E2: iload #25
		// @2E4: ifeq @2FC
		// @2E7: goto @2EB
		// @2EA: athrow
		// @2EB: aload #17
		// @2ED: iload #23
		// @2EF: iload #24
		// @2F1: aload_0
		// @2F2: getfield int game.C_100302_ka.field_101857_eb
		// @2F5: invokevirtual game.C_100037_wb.func_102376_d(int, int, int)void
		// @2F8: goto @2FC
		// @2FB: athrow
		// @2FC: aload_0
		// @2FD: getfield java.lang.String game.C_100302_ka.field_101890_ab
		// @300: ifnull @52A
		// @303: aload_0
		// @304: getfield game.C_100112_r game.C_100302_ka.field_101845_sb
		// @307: ifnonnull @312
		// @30A: goto @30E
		// @30D: athrow
		// @30E: goto @52A
		// @311: athrow
		// @312: aload_0
		// @313: getfield java.lang.String game.C_100302_ka.field_101890_ab
		// @316: astore #23
		// @318: iload #4
		// @31A: ifeq @344
		// @31D: aload_0
		// @31E: getfield java.lang.String game.C_100302_ka.field_101856_I
		// @321: ifnonnull @32C
		// @324: goto @328
		// @327: athrow
		// @328: goto @344
		// @32B: athrow
		// @32C: new java.lang.StringBuilder
		// @32F: dup
		// @330: invokespecial java.lang.StringBuilder.<init>()void
		// @333: aload #23
		// @335: invokevirtual java.lang.StringBuilder.append(java.lang.String)java.lang.StringBuilder
		// @338: aload_0
		// @339: getfield java.lang.String game.C_100302_ka.field_101856_I
		// @33C: invokevirtual java.lang.StringBuilder.append(java.lang.String)java.lang.StringBuilder
		// @33F: invokevirtual java.lang.StringBuilder.toString()java.lang.String
		// @342: astore #23
		// @344: aload_0
		// @345: getfield game.C_100112_r game.C_100302_ka.field_101845_sb
		// @348: aload #23
		// @34A: invokevirtual game.C_100112_r.func_101739_b(java.lang.String)int
		// @34D: iconst_2
		// @34E: aload_0
		// @34F: getfield int game.C_100302_ka.field_101829_Db
		// @352: imul
		// @353: ineg
		// @354: aload_0
		// @355: getfield int game.C_100302_ka.field_101886_Kb
		// @358: iadd
		// @359: if_icmpgt @4E6
		// @35C: iconst_0
		// @35D: aload #23
		// @35F: getstatic java.lang.String[] game.C_100302_ka.field_101831_Ub
		// @362: bipush 12 (0x0C)
		// @364: aaload
		// @365: invokevirtual java.lang.String.indexOf(java.lang.String)int
		// @368: if_icmple @4E6
		// @36B: goto @36F
		// @36E: athrow
		// @36F: iconst_1
		// @370: aload_0
		// @371: getfield int game.C_100302_ka.field_101858_J
		// @374: if_icmpne @39D
		// @377: goto @37B
		// @37A: athrow
		// @37B: iload #22
		// @37D: aload_0
		// @37E: getfield game.C_100112_r game.C_100302_ka.field_101845_sb
		// @381: getfield int game.C_100112_r.field_101772_Q
		// @384: ineg
		// @385: aload_0
		// @386: getfield int game.C_100302_ka.field_101848_lb
		// @389: aload_0
		// @38A: getfield game.C_100112_r game.C_100302_ka.field_101845_sb
		// @38D: getfield int game.C_100112_r.field_101763_H
		// @390: ineg
		// @391: iadd
		// @392: iadd
		// @393: iconst_2
		// @394: idiv
		// @395: iadd
		// @396: istore #22
		// @398: iload #25
		// @39A: ifeq @3C3
		// @39D: iconst_2
		// @39E: aload_0
		// @39F: getfield int game.C_100302_ka.field_101858_J
		// @3A2: if_icmpne @3C3
		// @3A5: goto @3A9
		// @3A8: athrow
		// @3A9: iload #22
		// @3AB: aload_0
		// @3AC: getfield game.C_100112_r game.C_100302_ka.field_101845_sb
		// @3AF: getfield int game.C_100112_r.field_101763_H
		// @3B2: ineg
		// @3B3: aload_0
		// @3B4: getfield int game.C_100302_ka.field_101848_lb
		// @3B7: iadd
		// @3B8: aload_0
		// @3B9: getfield game.C_100112_r game.C_100302_ka.field_101845_sb
		// @3BC: getfield int game.C_100112_r.field_101772_Q
		// @3BF: isub
		// @3C0: iadd
		// @3C1: istore #22
		// @3C3: iconst_0
		// @3C4: aload_0
		// @3C5: getfield int game.C_100302_ka.field_101850_Fb
		// @3C8: if_icmpne @3FF
		// @3CB: aload_0
		// @3CC: getfield game.C_100112_r game.C_100302_ka.field_101845_sb
		// @3CF: aload #23
		// @3D1: iload #21
		// @3D3: aload_0
		// @3D4: getfield int game.C_100302_ka.field_101829_Db
		// @3D7: iadd
		// @3D8: aload_0
		// @3D9: getfield int game.C_100302_ka.field_101840_Eb
		// @3DC: iadd
		// @3DD: aload_0
		// @3DE: getfield game.C_100112_r game.C_100302_ka.field_101845_sb
		// @3E1: getfield int game.C_100112_r.field_101772_Q
		// @3E4: iload #22
		// @3E6: iadd
		// @3E7: aload_0
		// @3E8: getfield int game.C_100302_ka.field_101835_xb
		// @3EB: iadd
		// @3EC: iload #18
		// @3EE: iconst_m1
		// @3EF: aload_0
		// @3F0: getfield int game.C_100302_ka.field_101871_mb
		// @3F3: invokevirtual game.C_100112_r.func_101751_a(java.lang.String, int, int, int, int, int)void
		// @3F6: iload #25
		// @3F8: ifeq @52A
		// @3FB: goto @3FF
		// @3FE: athrow
		// @3FF: aload_0
		// @400: getfield int game.C_100302_ka.field_101850_Fb
		// @403: iconst_1
		// @404: if_icmpeq @4A2
		// @407: goto @40B
		// @40A: athrow
		// @40B: iconst_2
		// @40C: aload_0
		// @40D: getfield int game.C_100302_ka.field_101850_Fb
		// @410: if_icmpne @459
		// @413: goto @417
		// @416: athrow
		// @417: aload_0
		// @418: getfield game.C_100112_r game.C_100302_ka.field_101845_sb
		// @41B: aload #23
		// @41D: iload #21
		// @41F: aload_0
		// @420: getfield int game.C_100302_ka.field_101829_Db
		// @423: aload_0
		// @424: getfield int game.C_100302_ka.field_101840_Eb
		// @427: iadd
		// @428: aload_0
		// @429: getfield int game.C_100302_ka.field_101886_Kb
		// @42C: ineg
		// @42D: isub
		// @42E: iadd
		// @42F: aload_0
		// @430: getfield int game.C_100302_ka.field_101829_Db
		// @433: iconst_2
		// @434: imul
		// @435: isub
		// @436: aload_0
		// @437: getfield game.C_100112_r game.C_100302_ka.field_101845_sb
		// @43A: getfield int game.C_100112_r.field_101772_Q
		// @43D: aload_0
		// @43E: getfield int game.C_100302_ka.field_101835_xb
		// @441: iadd
		// @442: iload #22
		// @444: ineg
		// @445: isub
		// @446: iload #18
		// @448: iconst_m1
		// @449: aload_0
		// @44A: getfield int game.C_100302_ka.field_101871_mb
		// @44D: invokevirtual game.C_100112_r.func_101740_c(java.lang.String, int, int, int, int, int)void
		// @450: iload #25
		// @452: ifeq @52A
		// @455: goto @459
		// @458: athrow
		// @459: aload_0
		// @45A: getfield game.C_100112_r game.C_100302_ka.field_101845_sb
		// @45D: aload #23
		// @45F: iload #21
		// @461: aload_0
		// @462: getfield int game.C_100302_ka.field_101840_Eb
		// @465: aload_0
		// @466: getfield int game.C_100302_ka.field_101829_Db
		// @469: iadd
		// @46A: iadd
		// @46B: iload #22
		// @46D: aload_0
		// @46E: getfield int game.C_100302_ka.field_101835_xb
		// @471: iadd
		// @472: aload_0
		// @473: getfield int game.C_100302_ka.field_101829_Db
		// @476: iconst_2
		// @477: imul
		// @478: ineg
		// @479: aload_0
		// @47A: getfield int game.C_100302_ka.field_101886_Kb
		// @47D: iadd
		// @47E: aload_0
		// @47F: getfield int game.C_100302_ka.field_101848_lb
		// @482: iload #18
		// @484: iconst_m1
		// @485: aload_0
		// @486: getfield int game.C_100302_ka.field_101871_mb
		// @489: aload_0
		// @48A: getfield int game.C_100302_ka.field_101850_Fb
		// @48D: aload_0
		// @48E: getfield int game.C_100302_ka.field_101858_J
		// @491: aload_0
		// @492: getfield int game.C_100302_ka.field_101833_ob
		// @495: invokevirtual game.C_100112_r.func_101745_a(java.lang.String, int, int, int, int, int, int, int, int, int, int)int
		// @498: pop
		// @499: iload #25
		// @49B: ifeq @52A
		// @49E: goto @4A2
		// @4A1: athrow
		// @4A2: aload_0
		// @4A3: getfield game.C_100112_r game.C_100302_ka.field_101845_sb
		// @4A6: aload #23
		// @4A8: aload_0
		// @4A9: getfield int game.C_100302_ka.field_101886_Kb
		// @4AC: iconst_2
		// @4AD: aload_0
		// @4AE: getfield int game.C_100302_ka.field_101829_Db
		// @4B1: imul
		// @4B2: ineg
		// @4B3: iadd
		// @4B4: iconst_2
		// @4B5: idiv
		// @4B6: aload_0
		// @4B7: getfield int game.C_100302_ka.field_101840_Eb
		// @4BA: aload_0
		// @4BB: getfield int game.C_100302_ka.field_101829_Db
		// @4BE: ineg
		// @4BF: isub
		// @4C0: iload #21
		// @4C2: iadd
		// @4C3: iadd
		// @4C4: iload #22
		// @4C6: aload_0
		// @4C7: getfield int game.C_100302_ka.field_101835_xb
		// @4CA: aload_0
		// @4CB: getfield game.C_100112_r game.C_100302_ka.field_101845_sb
		// @4CE: getfield int game.C_100112_r.field_101772_Q
		// @4D1: iadd
		// @4D2: iadd
		// @4D3: iload #18
		// @4D5: iconst_m1
		// @4D6: aload_0
		// @4D7: getfield int game.C_100302_ka.field_101871_mb
		// @4DA: invokevirtual game.C_100112_r.func_101747_b(java.lang.String, int, int, int, int, int)void
		// @4DD: iload #25
		// @4DF: ifeq @52A
		// @4E2: goto @4E6
		// @4E5: athrow
		// @4E6: aload_0
		// @4E7: getfield game.C_100112_r game.C_100302_ka.field_101845_sb
		// @4EA: aload #23
		// @4EC: aload_0
		// @4ED: getfield int game.C_100302_ka.field_101840_Eb
		// @4F0: aload_0
		// @4F1: getfield int game.C_100302_ka.field_101829_Db
		// @4F4: ineg
		// @4F5: iload #21
		// @4F7: isub
		// @4F8: isub
		// @4F9: iload #22
		// @4FB: aload_0
		// @4FC: getfield int game.C_100302_ka.field_101835_xb
		// @4FF: iadd
		// @500: aload_0
		// @501: getfield int game.C_100302_ka.field_101886_Kb
		// @504: aload_0
		// @505: getfield int game.C_100302_ka.field_101829_Db
		// @508: iconst_2
		// @509: imul
		// @50A: isub
		// @50B: aload_0
		// @50C: getfield int game.C_100302_ka.field_101848_lb
		// @50F: iload #18
		// @511: iconst_m1
		// @512: aload_0
		// @513: getfield int game.C_100302_ka.field_101871_mb
		// @516: aload_0
		// @517: getfield int game.C_100302_ka.field_101850_Fb
		// @51A: aload_0
		// @51B: getfield int game.C_100302_ka.field_101858_J
		// @51E: aload_0
		// @51F: getfield int game.C_100302_ka.field_101833_ob
		// @522: invokevirtual game.C_100112_r.func_101745_a(java.lang.String, int, int, int, int, int, int, int, int, int, int)int
		// @525: pop
		// @526: goto @52A
		// @529: athrow
		// @52A: aconst_null
		// @52B: aload_0
		// @52C: getfield game.C_100202_qi game.C_100302_ka.field_101891_Ob
		// @52F: if_acmpne @536
		// @532: goto @593
		// @535: athrow
		// @536: aload_0
		// @537: getfield game.C_100202_qi game.C_100302_ka.field_101891_Ob
		// @53A: iload #8
		// @53C: bipush 36 (0x24)
		// @53E: iadd
		// @53F: invokevirtual game.C_100202_qi.func_105899_c(int)game.C_100158_da
		// @542: checkcast game.C_100302_ka
		// @545: astore #23
		// @547: aconst_null
		// @548: aload #23
		// @54A: if_acmpeq @593
		// @54D: aload #23
		// @54F: iload_1
		// @550: aload_0
		// @551: getfield int game.C_100302_ka.field_101886_Kb
		// @554: aload_0
		// @555: getfield int game.C_100302_ka.field_101835_xb
		// @558: iload #20
		// @55A: ineg
		// @55B: isub
		// @55C: iload #4
		// @55E: iload #5
		// @560: iload #6
		// @562: aload_0
		// @563: getfield boolean game.C_100302_ka.field_101827_cb
		// @566: iconst_1
		// @567: iload #9
		// @569: aload_0
		// @56A: getfield int game.C_100302_ka.field_101848_lb
		// @56D: aload_0
		// @56E: getfield int game.C_100302_ka.field_101840_Eb
		// @571: iload #19
		// @573: iadd
		// @574: invokespecial game.C_100302_ka.func_101811_a(boolean, int, int, boolean, boolean, boolean, boolean, int, boolean, int, int)void
		// @577: aload_0
		// @578: getfield game.C_100202_qi game.C_100302_ka.field_101891_Ob
		// @57B: bipush 29 (0x1D)
		// @57D: invokevirtual game.C_100202_qi.func_105907_c(byte)game.C_100158_da
		// @580: checkcast game.C_100302_ka
		// @583: astore #23
		// @585: iload #25
		// @587: ifne @59E
		// @58A: iload #25
		// @58C: ifeq @547
		// @58F: goto @593
		// @592: athrow
		// @593: iload #12
		// @595: iload #13
		// @597: iload #14
		// @599: iload #15
		// @59B: invokestatic game.C_100196_rb.func_105815_h(int, int, int, int)void
		// @59E: goto @627
		// @5A1: astore #12
		// @5A3: aload #12
		// @5A5: new java.lang.StringBuilder
		// @5A8: dup
		// @5A9: invokespecial java.lang.StringBuilder.<init>()void
		// @5AC: getstatic java.lang.String[] game.C_100302_ka.field_101831_Ub
		// @5AF: bipush 13 (0x0D)
		// @5B1: aaload
		// @5B2: invokevirtual java.lang.StringBuilder.append(java.lang.String)java.lang.StringBuilder
		// @5B5: iload_1
		// @5B6: invokevirtual java.lang.StringBuilder.append(boolean)java.lang.StringBuilder
		// @5B9: bipush 44 (0x2C)
		// @5BB: invokevirtual java.lang.StringBuilder.append(char)java.lang.StringBuilder
		// @5BE: iload_2
		// @5BF: invokevirtual java.lang.StringBuilder.append(int)java.lang.StringBuilder
		// @5C2: bipush 44 (0x2C)
		// @5C4: invokevirtual java.lang.StringBuilder.append(char)java.lang.StringBuilder
		// @5C7: iload_3
		// @5C8: invokevirtual java.lang.StringBuilder.append(int)java.lang.StringBuilder
		// @5CB: bipush 44 (0x2C)
		// @5CD: invokevirtual java.lang.StringBuilder.append(char)java.lang.StringBuilder
		// @5D0: iload #4
		// @5D2: invokevirtual java.lang.StringBuilder.append(boolean)java.lang.StringBuilder
		// @5D5: bipush 44 (0x2C)
		// @5D7: invokevirtual java.lang.StringBuilder.append(char)java.lang.StringBuilder
		// @5DA: iload #5
		// @5DC: invokevirtual java.lang.StringBuilder.append(boolean)java.lang.StringBuilder
		// @5DF: bipush 44 (0x2C)
		// @5E1: invokevirtual java.lang.StringBuilder.append(char)java.lang.StringBuilder
		// @5E4: iload #6
		// @5E6: invokevirtual java.lang.StringBuilder.append(boolean)java.lang.StringBuilder
		// @5E9: bipush 44 (0x2C)
		// @5EB: invokevirtual java.lang.StringBuilder.append(char)java.lang.StringBuilder
		// @5EE: iload #7
		// @5F0: invokevirtual java.lang.StringBuilder.append(boolean)java.lang.StringBuilder
		// @5F3: bipush 44 (0x2C)
		// @5F5: invokevirtual java.lang.StringBuilder.append(char)java.lang.StringBuilder
		// @5F8: iload #8
		// @5FA: invokevirtual java.lang.StringBuilder.append(int)java.lang.StringBuilder
		// @5FD: bipush 44 (0x2C)
		// @5FF: invokevirtual java.lang.StringBuilder.append(char)java.lang.StringBuilder
		// @602: iload #9
		// @604: invokevirtual java.lang.StringBuilder.append(boolean)java.lang.StringBuilder
		// @607: bipush 44 (0x2C)
		// @609: invokevirtual java.lang.StringBuilder.append(char)java.lang.StringBuilder
		// @60C: iload #10
		// @60E: invokevirtual java.lang.StringBuilder.append(int)java.lang.StringBuilder
		// @611: bipush 44 (0x2C)
		// @613: invokevirtual java.lang.StringBuilder.append(char)java.lang.StringBuilder
		// @616: iload #11
		// @618: invokevirtual java.lang.StringBuilder.append(int)java.lang.StringBuilder
		// @61B: bipush 41 (0x29)
		// @61D: invokevirtual java.lang.StringBuilder.append(char)java.lang.StringBuilder
		// @620: invokevirtual java.lang.StringBuilder.toString()java.lang.String
		// @623: invokestatic game.C_100181_cf.func_105695_a(java.lang.Throwable, java.lang.String)game.C_100170_cm
		// @626: athrow
		// @627: return
	}
	
	final void func_101821_k(int arg0)
	{
		// @00: getstatic int game.SteelSentinels.field_105275_O
		// @03: istore_3
		// @04: iload_1
		// @05: ifeq @17
		// @08: aload_0
		// @09: bipush -116 (0x8C)
		// @0B: bipush -112 (0x90)
		// @0D: iconst_1
		// @0E: bipush -46 (0xD2)
		// @10: invokevirtual game.C_100302_ka.func_101820_a(int, int, boolean, int)void
		// @13: goto @17
		// @16: athrow
		// @17: aload_0
		// @18: getfield game.C_100202_qi game.C_100302_ka.field_101891_Ob
		// @1B: ifnonnull @22
		// @1E: goto @56
		// @21: athrow
		// @22: aload_0
		// @23: getfield game.C_100202_qi game.C_100302_ka.field_101891_Ob
		// @26: bipush -84 (0xAC)
		// @28: invokevirtual game.C_100202_qi.func_105906_b(int)game.C_100158_da
		// @2B: checkcast game.C_100302_ka
		// @2E: astore_2
		// @2F: aload_2
		// @30: ifnull @56
		// @33: aload_2
		// @34: iconst_1
		// @35: putfield boolean game.C_100302_ka.field_101876_Sb
		// @38: aload_2
		// @39: iconst_0
		// @3A: invokevirtual game.C_100302_ka.func_101821_k(int)void
		// @3D: aload_0
		// @3E: getfield game.C_100202_qi game.C_100302_ka.field_101891_Ob
		// @41: bipush -113 (0x8F)
		// @43: invokevirtual game.C_100202_qi.func_105898_a(byte)game.C_100158_da
		// @46: checkcast game.C_100302_ka
		// @49: astore_2
		// @4A: iload_3
		// @4B: ifne @7B
		// @4E: iload_3
		// @4F: ifeq @2F
		// @52: goto @56
		// @55: athrow
		// @56: goto @7B
		// @59: astore_2
		// @5A: aload_2
		// @5B: new java.lang.StringBuilder
		// @5E: dup
		// @5F: invokespecial java.lang.StringBuilder.<init>()void
		// @62: getstatic java.lang.String[] game.C_100302_ka.field_101831_Ub
		// @65: bipush 15 (0x0F)
		// @67: aaload
		// @68: invokevirtual java.lang.StringBuilder.append(java.lang.String)java.lang.StringBuilder
		// @6B: iload_1
		// @6C: invokevirtual java.lang.StringBuilder.append(int)java.lang.StringBuilder
		// @6F: bipush 41 (0x29)
		// @71: invokevirtual java.lang.StringBuilder.append(char)java.lang.StringBuilder
		// @74: invokevirtual java.lang.StringBuilder.toString()java.lang.String
		// @77: invokestatic game.C_100181_cf.func_105695_a(java.lang.Throwable, java.lang.String)game.C_100170_cm
		// @7A: athrow
		// @7B: return
	}
	
	C_100302_ka(long arg0, C_100302_ka arg1, String arg2)
	{
		// @0: aload_0
		// @1: lload_1
		// @2: aload_3
		// @3: iconst_0
		// @4: iconst_0
		// @5: iconst_0
		// @6: iconst_0
		// @7: aload #4
		// @9: invokespecial game.C_100302_ka.<init>(long, game.C_100302_ka, int, int, int, int, java.lang.String)void
		// @C: return
	}
	
	public static void func_101812_d(byte arg0)
	{
		// @00: aconst_null
		// @01: putstatic java.lang.String game.C_100302_ka.field_101870_R
		// @04: aconst_null
		// @05: putstatic java.lang.String game.C_100302_ka.field_101865_V
		// @08: aconst_null
		// @09: putstatic game.C_100202_qi game.C_100302_ka.field_101828_Qb
		// @0C: aconst_null
		// @0D: putstatic java.lang.String[] game.C_100302_ka.field_101873_vb
		// @10: aconst_null
		// @11: putstatic game.C_100137_bn game.C_100302_ka.field_101847_wb
		// @14: aconst_null
		// @15: putstatic java.lang.String[] game.C_100302_ka.field_101863_ib
		// @18: iload_0
		// @19: bipush -79 (0xB1)
		// @1B: if_icmpeq @24
		// @1E: bipush -96 (0xA0)
		// @20: invokestatic game.C_100302_ka.func_101815_e(byte)int
		// @23: pop
		// @24: goto @48
		// @27: astore_1
		// @28: aload_1
		// @29: new java.lang.StringBuilder
		// @2C: dup
		// @2D: invokespecial java.lang.StringBuilder.<init>()void
		// @30: getstatic java.lang.String[] game.C_100302_ka.field_101831_Ub
		// @33: iconst_1
		// @34: aaload
		// @35: invokevirtual java.lang.StringBuilder.append(java.lang.String)java.lang.StringBuilder
		// @38: iload_0
		// @39: invokevirtual java.lang.StringBuilder.append(int)java.lang.StringBuilder
		// @3C: bipush 41 (0x29)
		// @3E: invokevirtual java.lang.StringBuilder.append(char)java.lang.StringBuilder
		// @41: invokevirtual java.lang.StringBuilder.toString()java.lang.String
		// @44: invokestatic game.C_100181_cf.func_105695_a(java.lang.Throwable, java.lang.String)game.C_100170_cm
		// @47: athrow
		// @48: return
	}
	
	final void func_101820_a(int arg0, int arg1, boolean arg2, int arg3)
	{
		// @000: getstatic int game.SteelSentinels.field_105275_O
		// @003: istore #11
		// @005: aload_0
		// @006: getfield int game.C_100302_ka.field_101880_Gb
		// @009: ineg
		// @00A: istore #5
		// @00C: aload_0
		// @00D: getfield int game.C_100302_ka.field_101843_Tb
		// @010: ineg
		// @011: iload #5
		// @013: iadd
		// @014: istore #6
		// @016: aload_0
		// @017: getfield int game.C_100302_ka.field_101848_lb
		// @01A: istore #7
		// @01C: iload #7
		// @01E: aload_0
		// @01F: getfield int game.C_100302_ka.field_101832_tb
		// @022: iadd
		// @023: istore #8
		// @025: iload_3
		// @026: ifne @082
		// @029: iconst_0
		// @02A: istore #9
		// @02C: aload_0
		// @02D: getfield game.C_100202_qi game.C_100302_ka.field_101891_Ob
		// @030: bipush 121 (0x79)
		// @032: invokevirtual game.C_100202_qi.func_105899_c(int)game.C_100158_da
		// @035: checkcast game.C_100302_ka
		// @038: astore #10
		// @03A: aload #10
		// @03C: ifnull @07C
		// @03F: aload #10
		// @041: aload #10
		// @043: getfield int game.C_100302_ka.field_101880_Gb
		// @046: ineg
		// @047: iload #9
		// @049: iadd
		// @04A: putfield int game.C_100302_ka.field_101843_Tb
		// @04D: iload #9
		// @04F: aload #10
		// @051: getfield int game.C_100302_ka.field_101832_tb
		// @054: aload #10
		// @056: getfield int game.C_100302_ka.field_101848_lb
		// @059: iload_2
		// @05A: ineg
		// @05B: isub
		// @05C: iadd
		// @05D: iadd
		// @05E: istore #9
		// @060: aload_0
		// @061: getfield game.C_100202_qi game.C_100302_ka.field_101891_Ob
		// @064: bipush 48 (0x30)
		// @066: invokevirtual game.C_100202_qi.func_105907_c(byte)game.C_100158_da
		// @069: checkcast game.C_100302_ka
		// @06C: astore #10
		// @06E: iload #11
		// @070: ifne @089
		// @073: iload #11
		// @075: ifeq @03A
		// @078: goto @07C
		// @07B: athrow
		// @07C: iload #9
		// @07E: iload_2
		// @07F: isub
		// @080: istore #8
		// @082: iload_1
		// @083: ineg
		// @084: iload #8
		// @086: iadd
		// @087: istore #9
		// @089: iload #9
		// @08B: iconst_m1
		// @08C: ixor
		// @08D: iload #6
		// @08F: iconst_m1
		// @090: ixor
		// @091: if_icmple @098
		// @094: iload #9
		// @096: istore #6
		// @098: iload #6
		// @09A: iconst_m1
		// @09B: ixor
		// @09C: iload #4
		// @09E: if_icmpgt @0A5
		// @0A1: goto @0A8
		// @0A4: athrow
		// @0A5: iconst_0
		// @0A6: istore #6
		// @0A8: iload #7
		// @0AA: iload_1
		// @0AB: isub
		// @0AC: istore #10
		// @0AE: iload #10
		// @0B0: iload #5
		// @0B2: if_icmpge @0B9
		// @0B5: iload #10
		// @0B7: istore #5
		// @0B9: iload #5
		// @0BB: ifge @0C1
		// @0BE: iconst_0
		// @0BF: istore #5
		// @0C1: aload_0
		// @0C2: iload #6
		// @0C4: ineg
		// @0C5: iload #5
		// @0C7: iadd
		// @0C8: putfield int game.C_100302_ka.field_101843_Tb
		// @0CB: aload_0
		// @0CC: iload #7
		// @0CE: ineg
		// @0CF: iload #8
		// @0D1: iadd
		// @0D2: putfield int game.C_100302_ka.field_101832_tb
		// @0D5: aload_0
		// @0D6: iload #7
		// @0D8: putfield int game.C_100302_ka.field_101848_lb
		// @0DB: aload_0
		// @0DC: iload #5
		// @0DE: ineg
		// @0DF: putfield int game.C_100302_ka.field_101880_Gb
		// @0E2: goto @124
		// @0E5: astore #5
		// @0E7: aload #5
		// @0E9: new java.lang.StringBuilder
		// @0EC: dup
		// @0ED: invokespecial java.lang.StringBuilder.<init>()void
		// @0F0: getstatic java.lang.String[] game.C_100302_ka.field_101831_Ub
		// @0F3: iconst_5
		// @0F4: aaload
		// @0F5: invokevirtual java.lang.StringBuilder.append(java.lang.String)java.lang.StringBuilder
		// @0F8: iload_1
		// @0F9: invokevirtual java.lang.StringBuilder.append(int)java.lang.StringBuilder
		// @0FC: bipush 44 (0x2C)
		// @0FE: invokevirtual java.lang.StringBuilder.append(char)java.lang.StringBuilder
		// @101: iload_2
		// @102: invokevirtual java.lang.StringBuilder.append(int)java.lang.StringBuilder
		// @105: bipush 44 (0x2C)
		// @107: invokevirtual java.lang.StringBuilder.append(char)java.lang.StringBuilder
		// @10A: iload_3
		// @10B: invokevirtual java.lang.StringBuilder.append(boolean)java.lang.StringBuilder
		// @10E: bipush 44 (0x2C)
		// @110: invokevirtual java.lang.StringBuilder.append(char)java.lang.StringBuilder
		// @113: iload #4
		// @115: invokevirtual java.lang.StringBuilder.append(int)java.lang.StringBuilder
		// @118: bipush 41 (0x29)
		// @11A: invokevirtual java.lang.StringBuilder.append(char)java.lang.StringBuilder
		// @11D: invokevirtual java.lang.StringBuilder.toString()java.lang.String
		// @120: invokestatic game.C_100181_cf.func_105695_a(java.lang.Throwable, java.lang.String)game.C_100170_cm
		// @123: athrow
		// @124: return
	}
	
	final void func_101825_a(int arg0, int arg1, int arg2, int arg3, int arg4)
	{
		// @00: aload_0
		// @01: iconst_0
		// @02: putfield int game.C_100302_ka.field_101885_jb
		// @05: aload_0
		// @06: iload_1
		// @07: putfield int game.C_100302_ka.field_101841_Pb
		// @0A: aload_0
		// @0B: iconst_0
		// @0C: putfield int game.C_100302_ka.field_101843_Tb
		// @0F: aload_0
		// @10: iconst_0
		// @11: putfield int game.C_100302_ka.field_101889_ub
		// @14: aload_0
		// @15: iload #4
		// @17: putfield int game.C_100302_ka.field_101880_Gb
		// @1A: aload_0
		// @1B: iload_2
		// @1C: putfield int game.C_100302_ka.field_101848_lb
		// @1F: aload_0
		// @20: iconst_0
		// @21: putfield int game.C_100302_ka.field_101832_tb
		// @24: aload_0
		// @25: iload #5
		// @27: putfield int game.C_100302_ka.field_101886_Kb
		// @2A: iload_3
		// @2B: iconst_m1
		// @2C: if_icmpeq @37
		// @2F: aload_0
		// @30: aconst_null
		// @31: checkcast game.C_100037_wb[]
		// @34: putfield game.C_100037_wb[] game.C_100302_ka.field_101883_qb
		// @37: goto @84
		// @3A: astore #6
		// @3C: aload #6
		// @3E: new java.lang.StringBuilder
		// @41: dup
		// @42: invokespecial java.lang.StringBuilder.<init>()void
		// @45: getstatic java.lang.String[] game.C_100302_ka.field_101831_Ub
		// @48: bipush 16 (0x10)
		// @4A: aaload
		// @4B: invokevirtual java.lang.StringBuilder.append(java.lang.String)java.lang.StringBuilder
		// @4E: iload_1
		// @4F: invokevirtual java.lang.StringBuilder.append(int)java.lang.StringBuilder
		// @52: bipush 44 (0x2C)
		// @54: invokevirtual java.lang.StringBuilder.append(char)java.lang.StringBuilder
		// @57: iload_2
		// @58: invokevirtual java.lang.StringBuilder.append(int)java.lang.StringBuilder
		// @5B: bipush 44 (0x2C)
		// @5D: invokevirtual java.lang.StringBuilder.append(char)java.lang.StringBuilder
		// @60: iload_3
		// @61: invokevirtual java.lang.StringBuilder.append(int)java.lang.StringBuilder
		// @64: bipush 44 (0x2C)
		// @66: invokevirtual java.lang.StringBuilder.append(char)java.lang.StringBuilder
		// @69: iload #4
		// @6B: invokevirtual java.lang.StringBuilder.append(int)java.lang.StringBuilder
		// @6E: bipush 44 (0x2C)
		// @70: invokevirtual java.lang.StringBuilder.append(char)java.lang.StringBuilder
		// @73: iload #5
		// @75: invokevirtual java.lang.StringBuilder.append(int)java.lang.StringBuilder
		// @78: bipush 41 (0x29)
		// @7A: invokevirtual java.lang.StringBuilder.append(char)java.lang.StringBuilder
		// @7D: invokevirtual java.lang.StringBuilder.toString()java.lang.String
		// @80: invokestatic game.C_100181_cf.func_105695_a(java.lang.Throwable, java.lang.String)game.C_100170_cm
		// @83: athrow
		// @84: return
	}
	
	final void func_101810_a(int arg0, C_100302_ka arg1)
	{
		// @000: iload_1
		// @001: sipush 32280 (0x7E18)
		// @004: if_icmpeq @011
		// @007: aload_0
		// @008: bipush -70 (0xBA)
		// @00A: putfield int game.C_100302_ka.field_101886_Kb
		// @00D: goto @011
		// @010: athrow
		// @011: aconst_null
		// @012: aload_2
		// @013: if_acmpne @01A
		// @016: goto @31F
		// @019: athrow
		// @01A: aload_2
		// @01B: getfield int game.C_100302_ka.field_101872_Nb
		// @01E: ifge @025
		// @021: goto @02D
		// @024: athrow
		// @025: aload_0
		// @026: aload_2
		// @027: getfield int game.C_100302_ka.field_101872_Nb
		// @02A: putfield int game.C_100302_ka.field_101872_Nb
		// @02D: aconst_null
		// @02E: aload_2
		// @02F: getfield game.C_100037_wb game.C_100302_ka.field_101844_pb
		// @032: if_acmpne @039
		// @035: goto @041
		// @038: athrow
		// @039: aload_0
		// @03A: aload_2
		// @03B: getfield game.C_100037_wb game.C_100302_ka.field_101844_pb
		// @03E: putfield game.C_100037_wb game.C_100302_ka.field_101844_pb
		// @041: aload_2
		// @042: getfield boolean game.C_100302_ka.field_101864_W
		// @045: ifne @054
		// @048: aload_0
		// @049: aload_2
		// @04A: getfield boolean game.C_100302_ka.field_101864_W
		// @04D: putfield boolean game.C_100302_ka.field_101864_W
		// @050: goto @054
		// @053: athrow
		// @054: iconst_m1
		// @055: aload_2
		// @056: getfield int game.C_100302_ka.field_101833_ob
		// @059: iconst_m1
		// @05A: ixor
		// @05B: if_icmpeq @06A
		// @05E: aload_0
		// @05F: aload_2
		// @060: getfield int game.C_100302_ka.field_101833_ob
		// @063: putfield int game.C_100302_ka.field_101833_ob
		// @066: goto @06A
		// @069: athrow
		// @06A: aconst_null
		// @06B: aload_2
		// @06C: getfield game.C_100037_wb[] game.C_100302_ka.field_101853_M
		// @06F: if_acmpeq @07E
		// @072: aload_0
		// @073: aload_2
		// @074: getfield game.C_100037_wb[] game.C_100302_ka.field_101853_M
		// @077: putfield game.C_100037_wb[] game.C_100302_ka.field_101853_M
		// @07A: goto @07E
		// @07D: athrow
		// @07E: aload_2
		// @07F: getfield int game.C_100302_ka.field_101868_Ab
		// @082: ifge @089
		// @085: goto @091
		// @088: athrow
		// @089: aload_0
		// @08A: aload_2
		// @08B: getfield int game.C_100302_ka.field_101868_Ab
		// @08E: putfield int game.C_100302_ka.field_101868_Ab
		// @091: aload_2
		// @092: getfield boolean game.C_100302_ka.field_101861_U
		// @095: ifne @09C
		// @098: goto @0A4
		// @09B: athrow
		// @09C: aload_0
		// @09D: aload_2
		// @09E: getfield boolean game.C_100302_ka.field_101861_U
		// @0A1: putfield boolean game.C_100302_ka.field_101861_U
		// @0A4: aconst_null
		// @0A5: aload_2
		// @0A6: getfield game.C_100037_wb[] game.C_100302_ka.field_101862_T
		// @0A9: if_acmpne @0B0
		// @0AC: goto @0B8
		// @0AF: athrow
		// @0B0: aload_0
		// @0B1: aload_2
		// @0B2: getfield game.C_100037_wb[] game.C_100302_ka.field_101862_T
		// @0B5: putfield game.C_100037_wb[] game.C_100302_ka.field_101862_T
		// @0B8: aconst_null
		// @0B9: aload_2
		// @0BA: getfield game.C_100037_wb game.C_100302_ka.field_101852_L
		// @0BD: if_acmpne @0C4
		// @0C0: goto @0CC
		// @0C3: athrow
		// @0C4: aload_0
		// @0C5: aload_2
		// @0C6: getfield game.C_100037_wb game.C_100302_ka.field_101852_L
		// @0C9: putfield game.C_100037_wb game.C_100302_ka.field_101852_L
		// @0CC: aconst_null
		// @0CD: aload_2
		// @0CE: getfield game.C_100037_wb game.C_100302_ka.field_101884_fb
		// @0D1: if_acmpne @0D8
		// @0D4: goto @0E0
		// @0D7: athrow
		// @0D8: aload_0
		// @0D9: aload_2
		// @0DA: getfield game.C_100037_wb game.C_100302_ka.field_101884_fb
		// @0DD: putfield game.C_100037_wb game.C_100302_ka.field_101884_fb
		// @0E0: aload_2
		// @0E1: getfield boolean game.C_100302_ka.field_101881_yb
		// @0E4: ifne @0EB
		// @0E7: goto @0F3
		// @0EA: athrow
		// @0EB: aload_0
		// @0EC: aload_2
		// @0ED: getfield boolean game.C_100302_ka.field_101881_yb
		// @0F0: putfield boolean game.C_100302_ka.field_101881_yb
		// @0F3: iconst_m1
		// @0F4: aload_2
		// @0F5: getfield int game.C_100302_ka.field_101860_K
		// @0F8: iconst_m1
		// @0F9: ixor
		// @0FA: if_icmplt @109
		// @0FD: aload_0
		// @0FE: aload_2
		// @0FF: getfield int game.C_100302_ka.field_101860_K
		// @102: putfield int game.C_100302_ka.field_101860_K
		// @105: goto @109
		// @108: athrow
		// @109: aconst_null
		// @10A: aload_2
		// @10B: getfield java.lang.String game.C_100302_ka.field_101856_I
		// @10E: if_acmpeq @11D
		// @111: aload_0
		// @112: aload_2
		// @113: getfield java.lang.String game.C_100302_ka.field_101856_I
		// @116: putfield java.lang.String game.C_100302_ka.field_101856_I
		// @119: goto @11D
		// @11C: athrow
		// @11D: aload_2
		// @11E: getfield boolean game.C_100302_ka.field_101838_Lb
		// @121: ifeq @130
		// @124: aload_0
		// @125: aload_2
		// @126: getfield boolean game.C_100302_ka.field_101838_Lb
		// @129: putfield boolean game.C_100302_ka.field_101838_Lb
		// @12C: goto @130
		// @12F: athrow
		// @130: aload_2
		// @131: getfield boolean game.C_100302_ka.field_101876_Sb
		// @134: ifeq @143
		// @137: aload_0
		// @138: aload_2
		// @139: getfield boolean game.C_100302_ka.field_101876_Sb
		// @13C: putfield boolean game.C_100302_ka.field_101876_Sb
		// @13F: goto @143
		// @142: athrow
		// @143: aload_2
		// @144: getfield game.C_100037_wb[] game.C_100302_ka.field_101883_qb
		// @147: ifnonnull @14E
		// @14A: goto @156
		// @14D: athrow
		// @14E: aload_0
		// @14F: aload_2
		// @150: getfield game.C_100037_wb[] game.C_100302_ka.field_101883_qb
		// @153: putfield game.C_100037_wb[] game.C_100302_ka.field_101883_qb
		// @156: aload_2
		// @157: getfield game.C_100037_wb game.C_100302_ka.field_101887_nb
		// @15A: ifnull @169
		// @15D: aload_0
		// @15E: aload_2
		// @15F: getfield game.C_100037_wb game.C_100302_ka.field_101887_nb
		// @162: putfield game.C_100037_wb game.C_100302_ka.field_101887_nb
		// @165: goto @169
		// @168: athrow
		// @169: aconst_null
		// @16A: aload_2
		// @16B: getfield game.C_100037_wb[] game.C_100302_ka.field_101878_Jb
		// @16E: if_acmpeq @17D
		// @171: aload_0
		// @172: aload_2
		// @173: getfield game.C_100037_wb[] game.C_100302_ka.field_101878_Jb
		// @176: putfield game.C_100037_wb[] game.C_100302_ka.field_101878_Jb
		// @179: goto @17D
		// @17C: athrow
		// @17D: aload_2
		// @17E: getfield int game.C_100302_ka.field_101859_rb
		// @181: iflt @190
		// @184: aload_0
		// @185: aload_2
		// @186: getfield int game.C_100302_ka.field_101859_rb
		// @189: putfield int game.C_100302_ka.field_101859_rb
		// @18C: goto @190
		// @18F: athrow
		// @190: aload_2
		// @191: getfield game.C_100037_wb[] game.C_100302_ka.field_101851_zb
		// @194: ifnull @1A3
		// @197: aload_0
		// @198: aload_2
		// @199: getfield game.C_100037_wb[] game.C_100302_ka.field_101851_zb
		// @19C: putfield game.C_100037_wb[] game.C_100302_ka.field_101851_zb
		// @19F: goto @1A3
		// @1A2: athrow
		// @1A3: sipush 256 (0x0100)
		// @1A6: aload_2
		// @1A7: getfield int game.C_100302_ka.field_101871_mb
		// @1AA: if_icmpne @1B1
		// @1AD: goto @1B9
		// @1B0: athrow
		// @1B1: aload_0
		// @1B2: aload_2
		// @1B3: getfield int game.C_100302_ka.field_101871_mb
		// @1B6: putfield int game.C_100302_ka.field_101871_mb
		// @1B9: aload_2
		// @1BA: getfield int game.C_100302_ka.field_101829_Db
		// @1BD: ifeq @1CC
		// @1C0: aload_0
		// @1C1: aload_2
		// @1C2: getfield int game.C_100302_ka.field_101829_Db
		// @1C5: putfield int game.C_100302_ka.field_101829_Db
		// @1C8: goto @1CC
		// @1CB: athrow
		// @1CC: aload_2
		// @1CD: getfield java.lang.String game.C_100302_ka.field_101890_ab
		// @1D0: ifnonnull @1D7
		// @1D3: goto @1DF
		// @1D6: athrow
		// @1D7: aload_0
		// @1D8: aload_2
		// @1D9: getfield java.lang.String game.C_100302_ka.field_101890_ab
		// @1DC: putfield java.lang.String game.C_100302_ka.field_101890_ab
		// @1DF: aload_2
		// @1E0: getfield game.C_100112_r game.C_100302_ka.field_101845_sb
		// @1E3: ifnull @1F2
		// @1E6: aload_0
		// @1E7: aload_2
		// @1E8: getfield game.C_100112_r game.C_100302_ka.field_101845_sb
		// @1EB: putfield game.C_100112_r game.C_100302_ka.field_101845_sb
		// @1EE: goto @1F2
		// @1F1: athrow
		// @1F2: iconst_0
		// @1F3: aload_2
		// @1F4: getfield int game.C_100302_ka.field_101830_gb
		// @1F7: if_icmpne @1FE
		// @1FA: goto @206
		// @1FD: athrow
		// @1FE: aload_0
		// @1FF: aload_2
		// @200: getfield int game.C_100302_ka.field_101830_gb
		// @203: putfield int game.C_100302_ka.field_101830_gb
		// @206: aload_2
		// @207: getfield game.C_100037_wb game.C_100302_ka.field_101855_O
		// @20A: ifnull @219
		// @20D: aload_0
		// @20E: aload_2
		// @20F: getfield game.C_100037_wb game.C_100302_ka.field_101855_O
		// @212: putfield game.C_100037_wb game.C_100302_ka.field_101855_O
		// @215: goto @219
		// @218: athrow
		// @219: aload_2
		// @21A: getfield int game.C_100302_ka.field_101850_Fb
		// @21D: ifne @224
		// @220: goto @22C
		// @223: athrow
		// @224: aload_0
		// @225: aload_2
		// @226: getfield int game.C_100302_ka.field_101850_Fb
		// @229: putfield int game.C_100302_ka.field_101850_Fb
		// @22C: aload_2
		// @22D: getfield int game.C_100302_ka.field_101867_P
		// @230: iconst_m1
		// @231: ixor
		// @232: ldc 2147483647 (0x7fffffff)
		// @234: if_icmpne @23B
		// @237: goto @243
		// @23A: athrow
		// @23B: aload_0
		// @23C: aload_2
		// @23D: getfield int game.C_100302_ka.field_101867_P
		// @240: putfield int game.C_100302_ka.field_101867_P
		// @243: ldc -2147483648 (0x80000000)
		// @245: aload_2
		// @246: getfield int game.C_100302_ka.field_101866_Q
		// @249: if_icmpne @250
		// @24C: goto @258
		// @24F: athrow
		// @250: aload_0
		// @251: aload_2
		// @252: getfield int game.C_100302_ka.field_101866_Q
		// @255: putfield int game.C_100302_ka.field_101866_Q
		// @258: ldc -2147483648 (0x80000000)
		// @25A: aload_2
		// @25B: getfield int game.C_100302_ka.field_101849_Mb
		// @25E: if_icmpne @265
		// @261: goto @26D
		// @264: athrow
		// @265: aload_0
		// @266: aload_2
		// @267: getfield int game.C_100302_ka.field_101849_Mb
		// @26A: putfield int game.C_100302_ka.field_101849_Mb
		// @26D: iconst_m1
		// @26E: aload_2
		// @26F: getfield int game.C_100302_ka.field_101858_J
		// @272: iconst_m1
		// @273: ixor
		// @274: if_icmpeq @283
		// @277: aload_0
		// @278: aload_2
		// @279: getfield int game.C_100302_ka.field_101858_J
		// @27C: putfield int game.C_100302_ka.field_101858_J
		// @27F: goto @283
		// @282: athrow
		// @283: iconst_m1
		// @284: aload_2
		// @285: getfield int game.C_100302_ka.field_101875_X
		// @288: iconst_m1
		// @289: ixor
		// @28A: if_icmpne @291
		// @28D: goto @299
		// @290: athrow
		// @291: aload_0
		// @292: aload_2
		// @293: getfield int game.C_100302_ka.field_101875_X
		// @296: putfield int game.C_100302_ka.field_101875_X
		// @299: aload_2
		// @29A: getfield int game.C_100302_ka.field_101869_S
		// @29D: ldc -2147483648 (0x80000000)
		// @29F: if_icmpeq @2AE
		// @2A2: aload_0
		// @2A3: aload_2
		// @2A4: getfield int game.C_100302_ka.field_101869_S
		// @2A7: putfield int game.C_100302_ka.field_101869_S
		// @2AA: goto @2AE
		// @2AD: athrow
		// @2AE: aload_2
		// @2AF: getfield int game.C_100302_ka.field_101837_bb
		// @2B2: iconst_m1
		// @2B3: ixor
		// @2B4: ldc 2147483647 (0x7fffffff)
		// @2B6: if_icmpne @2BD
		// @2B9: goto @2C5
		// @2BC: athrow
		// @2BD: aload_0
		// @2BE: aload_2
		// @2BF: getfield int game.C_100302_ka.field_101837_bb
		// @2C2: putfield int game.C_100302_ka.field_101837_bb
		// @2C5: aload_0
		// @2C6: aload_0
		// @2C7: getfield boolean game.C_100302_ka.field_101838_Lb
		// @2CA: ifeq @2DD
		// @2CD: aload_2
		// @2CE: getfield boolean game.C_100302_ka.field_101827_cb
		// @2D1: ifeq @2DD
		// @2D4: goto @2D8
		// @2D7: athrow
		// @2D8: iconst_1
		// @2D9: goto @2DE
		// @2DC: athrow
		// @2DD: iconst_0
		// @2DE: putfield boolean game.C_100302_ka.field_101827_cb
		// @2E1: iconst_0
		// @2E2: aload_2
		// @2E3: getfield int game.C_100302_ka.field_101846_Ib
		// @2E6: if_icmpne @2ED
		// @2E9: goto @2F5
		// @2EC: athrow
		// @2ED: aload_0
		// @2EE: aload_2
		// @2EF: getfield int game.C_100302_ka.field_101846_Ib
		// @2F2: putfield int game.C_100302_ka.field_101846_Ib
		// @2F5: ldc 2147483647 (0x7fffffff)
		// @2F7: aload_2
		// @2F8: getfield int game.C_100302_ka.field_101877_Z
		// @2FB: iconst_m1
		// @2FC: ixor
		// @2FD: if_icmpne @304
		// @300: goto @30C
		// @303: athrow
		// @304: aload_0
		// @305: aload_2
		// @306: getfield int game.C_100302_ka.field_101877_Z
		// @309: putfield int game.C_100302_ka.field_101877_Z
		// @30C: aload_2
		// @30D: getfield boolean game.C_100302_ka.field_101888_Bb
		// @310: ifne @317
		// @313: goto @31F
		// @316: athrow
		// @317: aload_0
		// @318: aload_2
		// @319: getfield boolean game.C_100302_ka.field_101888_Bb
		// @31C: putfield boolean game.C_100302_ka.field_101888_Bb
		// @31F: goto @35E
		// @322: astore_3
		// @323: aload_3
		// @324: new java.lang.StringBuilder
		// @327: dup
		// @328: invokespecial java.lang.StringBuilder.<init>()void
		// @32B: getstatic java.lang.String[] game.C_100302_ka.field_101831_Ub
		// @32E: bipush 9 (0x09)
		// @330: aaload
		// @331: invokevirtual java.lang.StringBuilder.append(java.lang.String)java.lang.StringBuilder
		// @334: iload_1
		// @335: invokevirtual java.lang.StringBuilder.append(int)java.lang.StringBuilder
		// @338: bipush 44 (0x2C)
		// @33A: invokevirtual java.lang.StringBuilder.append(char)java.lang.StringBuilder
		// @33D: aload_2
		// @33E: ifnull @34A
		// @341: getstatic java.lang.String[] game.C_100302_ka.field_101831_Ub
		// @344: iconst_2
		// @345: aaload
		// @346: goto @34F
		// @349: athrow
		// @34A: getstatic java.lang.String[] game.C_100302_ka.field_101831_Ub
		// @34D: iconst_3
		// @34E: aaload
		// @34F: invokevirtual java.lang.StringBuilder.append(java.lang.String)java.lang.StringBuilder
		// @352: bipush 41 (0x29)
		// @354: invokevirtual java.lang.StringBuilder.append(char)java.lang.StringBuilder
		// @357: invokevirtual java.lang.StringBuilder.toString()java.lang.String
		// @35A: invokestatic game.C_100181_cf.func_105695_a(java.lang.Throwable, java.lang.String)game.C_100170_cm
		// @35D: athrow
		// @35E: return
	}
	
	final void func_101824_b(int arg0, C_100302_ka arg1)
	{
		// @00: aload_0
		// @01: getfield game.C_100202_qi game.C_100302_ka.field_101891_Ob
		// @04: ifnull @0B
		// @07: goto @16
		// @0A: athrow
		// @0B: aload_0
		// @0C: new game.C_100202_qi
		// @0F: dup
		// @10: invokespecial game.C_100202_qi.<init>()void
		// @13: putfield game.C_100202_qi game.C_100302_ka.field_101891_Ob
		// @16: aload_0
		// @17: getfield game.C_100202_qi game.C_100302_ka.field_101891_Ob
		// @1A: bipush 126 (0x7E)
		// @1C: aload_2
		// @1D: invokevirtual game.C_100202_qi.func_105901_a(int, game.C_100158_da)void
		// @20: iload_1
		// @21: bipush -67 (0xBD)
		// @23: if_icmplt @39
		// @26: aload_0
		// @27: aconst_null
		// @28: checkcast game.C_100302_ka
		// @2B: iconst_1
		// @2C: aconst_null
		// @2D: checkcast game.C_100302_ka
		// @30: bipush -12 (0xF4)
		// @32: invokevirtual game.C_100302_ka.func_101823_a(game.C_100302_ka, boolean, game.C_100302_ka, int)void
		// @35: goto @39
		// @38: athrow
		// @39: goto @78
		// @3C: astore_3
		// @3D: aload_3
		// @3E: new java.lang.StringBuilder
		// @41: dup
		// @42: invokespecial java.lang.StringBuilder.<init>()void
		// @45: getstatic java.lang.String[] game.C_100302_ka.field_101831_Ub
		// @48: bipush 19 (0x13)
		// @4A: aaload
		// @4B: invokevirtual java.lang.StringBuilder.append(java.lang.String)java.lang.StringBuilder
		// @4E: iload_1
		// @4F: invokevirtual java.lang.StringBuilder.append(int)java.lang.StringBuilder
		// @52: bipush 44 (0x2C)
		// @54: invokevirtual java.lang.StringBuilder.append(char)java.lang.StringBuilder
		// @57: aload_2
		// @58: ifnull @64
		// @5B: getstatic java.lang.String[] game.C_100302_ka.field_101831_Ub
		// @5E: iconst_2
		// @5F: aaload
		// @60: goto @69
		// @63: athrow
		// @64: getstatic java.lang.String[] game.C_100302_ka.field_101831_Ub
		// @67: iconst_3
		// @68: aaload
		// @69: invokevirtual java.lang.StringBuilder.append(java.lang.String)java.lang.StringBuilder
		// @6C: bipush 41 (0x29)
		// @6E: invokevirtual java.lang.StringBuilder.append(char)java.lang.StringBuilder
		// @71: invokevirtual java.lang.StringBuilder.toString()java.lang.String
		// @74: invokestatic game.C_100181_cf.func_105695_a(java.lang.Throwable, java.lang.String)game.C_100170_cm
		// @77: athrow
		// @78: return
	}
	
	final C_100302_ka func_101822_a(String arg0, byte arg1)
	{
		// @00: iload_2
		// @01: bipush -65 (0xBF)
		// @03: if_icmple @0B
		// @06: aconst_null
		// @07: checkcast game.C_100302_ka
		// @0A: areturn
		// @0B: aload_0
		// @0C: bipush 118 (0x76)
		// @0E: aload_1
		// @0F: sipush 4000 (0x0FA0)
		// @12: invokestatic game.C_100171_cn.func_105553_a(java.lang.CharSequence, int)long
		// @15: invokespecial game.C_100302_ka.func_101817_b(int, long)game.C_100302_ka
		// @18: areturn
		// @19: astore_3
		// @1A: aload_3
		// @1B: new java.lang.StringBuilder
		// @1E: dup
		// @1F: invokespecial java.lang.StringBuilder.<init>()void
		// @22: getstatic java.lang.String[] game.C_100302_ka.field_101831_Ub
		// @25: iconst_4
		// @26: aaload
		// @27: invokevirtual java.lang.StringBuilder.append(java.lang.String)java.lang.StringBuilder
		// @2A: aload_1
		// @2B: ifnull @37
		// @2E: getstatic java.lang.String[] game.C_100302_ka.field_101831_Ub
		// @31: iconst_2
		// @32: aaload
		// @33: goto @3C
		// @36: athrow
		// @37: getstatic java.lang.String[] game.C_100302_ka.field_101831_Ub
		// @3A: iconst_3
		// @3B: aaload
		// @3C: invokevirtual java.lang.StringBuilder.append(java.lang.String)java.lang.StringBuilder
		// @3F: bipush 44 (0x2C)
		// @41: invokevirtual java.lang.StringBuilder.append(char)java.lang.StringBuilder
		// @44: iload_2
		// @45: invokevirtual java.lang.StringBuilder.append(int)java.lang.StringBuilder
		// @48: bipush 41 (0x29)
		// @4A: invokevirtual java.lang.StringBuilder.append(char)java.lang.StringBuilder
		// @4D: invokevirtual java.lang.StringBuilder.toString()java.lang.String
		// @50: invokestatic game.C_100181_cf.func_105695_a(java.lang.Throwable, java.lang.String)game.C_100170_cm
		// @53: athrow
	}
	
	C_100302_ka(String arg0, C_100302_ka arg1)
	{
		// @00: aload_0
		// @01: aload_1
		// @02: sipush 4000 (0x0FA0)
		// @05: invokestatic game.C_100171_cn.func_105553_a(java.lang.CharSequence, int)long
		// @08: aload_2
		// @09: iconst_0
		// @0A: iconst_0
		// @0B: iconst_0
		// @0C: iconst_0
		// @0D: aconst_null
		// @0E: invokespecial game.C_100302_ka.<init>(long, game.C_100302_ka, int, int, int, int, java.lang.String)void
		// @11: return
	}
	
	final void func_101809_a(byte arg0, boolean arg1)
	{
		// @00: iload_1
		// @01: bipush -125 (0x83)
		// @03: if_icmplt @1E
		// @06: aload_0
		// @07: iconst_1
		// @08: bipush 102 (0x66)
		// @0A: bipush 25 (0x19)
		// @0C: iconst_0
		// @0D: iconst_0
		// @0E: iconst_1
		// @0F: iconst_0
		// @10: bipush 42 (0x2A)
		// @12: iconst_0
		// @13: bipush 19 (0x13)
		// @15: bipush 36 (0x24)
		// @17: invokespecial game.C_100302_ka.func_101811_a(boolean, int, int, boolean, boolean, boolean, boolean, int, boolean, int, int)void
		// @1A: goto @1E
		// @1D: athrow
		// @1E: aload_0
		// @1F: iconst_0
		// @20: getstatic int game.C_100196_rb.field_105819_e
		// @23: iconst_0
		// @24: iload_2
		// @25: iconst_0
		// @26: iconst_1
		// @27: iconst_0
		// @28: iconst_1
		// @29: iconst_0
		// @2A: getstatic int game.C_100196_rb.field_105821_c
		// @2D: iconst_0
		// @2E: invokespecial game.C_100302_ka.func_101811_a(boolean, int, int, boolean, boolean, boolean, boolean, int, boolean, int, int)void
		// @31: goto @5F
		// @34: astore_3
		// @35: aload_3
		// @36: new java.lang.StringBuilder
		// @39: dup
		// @3A: invokespecial java.lang.StringBuilder.<init>()void
		// @3D: getstatic java.lang.String[] game.C_100302_ka.field_101831_Ub
		// @40: bipush 8 (0x08)
		// @42: aaload
		// @43: invokevirtual java.lang.StringBuilder.append(java.lang.String)java.lang.StringBuilder
		// @46: iload_1
		// @47: invokevirtual java.lang.StringBuilder.append(int)java.lang.StringBuilder
		// @4A: bipush 44 (0x2C)
		// @4C: invokevirtual java.lang.StringBuilder.append(char)java.lang.StringBuilder
		// @4F: iload_2
		// @50: invokevirtual java.lang.StringBuilder.append(boolean)java.lang.StringBuilder
		// @53: bipush 41 (0x29)
		// @55: invokevirtual java.lang.StringBuilder.append(char)java.lang.StringBuilder
		// @58: invokevirtual java.lang.StringBuilder.toString()java.lang.String
		// @5B: invokestatic game.C_100181_cf.func_105695_a(java.lang.Throwable, java.lang.String)game.C_100170_cm
		// @5E: athrow
		// @5F: return
	}
	
	final int func_101826_a(byte arg0, int arg1)
	{
		// @00: getstatic int game.SteelSentinels.field_105275_O
		// @03: istore #6
		// @05: iload_1
		// @06: bipush 46 (0x2E)
		// @08: if_icmpeq @15
		// @0B: aload_0
		// @0C: bipush -107 (0x95)
		// @0E: putfield int game.C_100302_ka.field_101834_kb
		// @11: goto @15
		// @14: athrow
		// @15: iconst_0
		// @16: istore_3
		// @17: aconst_null
		// @18: aload_0
		// @19: getfield java.lang.String game.C_100302_ka.field_101890_ab
		// @1C: if_acmpeq @4A
		// @1F: aconst_null
		// @20: aload_0
		// @21: getfield game.C_100112_r game.C_100302_ka.field_101845_sb
		// @24: if_acmpne @2F
		// @27: goto @2B
		// @2A: athrow
		// @2B: goto @4A
		// @2E: athrow
		// @2F: aload_0
		// @30: getfield game.C_100112_r game.C_100302_ka.field_101845_sb
		// @33: aload_0
		// @34: getfield java.lang.String game.C_100302_ka.field_101890_ab
		// @37: iload_2
		// @38: invokevirtual game.C_100112_r.func_101738_b(java.lang.String, int)int
		// @3B: istore #4
		// @3D: iload #4
		// @3F: iload_3
		// @40: if_icmpgt @47
		// @43: goto @4A
		// @46: athrow
		// @47: iload #4
		// @49: istore_3
		// @4A: aload_0
		// @4B: getfield game.C_100037_wb game.C_100302_ka.field_101887_nb
		// @4E: ifnull @67
		// @51: aload_0
		// @52: getfield game.C_100037_wb game.C_100302_ka.field_101887_nb
		// @55: getfield int game.C_100037_wb.field_102341_y
		// @58: istore #4
		// @5A: iload #4
		// @5C: iconst_m1
		// @5D: ixor
		// @5E: iload_3
		// @5F: iconst_m1
		// @60: ixor
		// @61: if_icmpge @67
		// @64: iload #4
		// @66: istore_3
		// @67: aload_0
		// @68: getfield game.C_100202_qi game.C_100302_ka.field_101891_Ob
		// @6B: ifnonnull @72
		// @6E: goto @BE
		// @71: athrow
		// @72: aload_0
		// @73: getfield game.C_100202_qi game.C_100302_ka.field_101891_Ob
		// @76: iload_1
		// @77: bipush 125 (0x7D)
		// @79: ixor
		// @7A: invokevirtual game.C_100202_qi.func_105899_c(int)game.C_100158_da
		// @7D: checkcast game.C_100302_ka
		// @80: astore #4
		// @82: aconst_null
		// @83: aload #4
		// @85: if_acmpeq @BE
		// @88: aload #4
		// @8A: getfield int game.C_100302_ka.field_101886_Kb
		// @8D: aload #4
		// @8F: getfield int game.C_100302_ka.field_101841_Pb
		// @92: iadd
		// @93: istore #5
		// @95: iload #5
		// @97: iload #6
		// @99: ifne @BF
		// @9C: iload_3
		// @9D: if_icmpgt @A8
		// @A0: goto @A4
		// @A3: athrow
		// @A4: goto @AB
		// @A7: athrow
		// @A8: iload #5
		// @AA: istore_3
		// @AB: aload_0
		// @AC: getfield game.C_100202_qi game.C_100302_ka.field_101891_Ob
		// @AF: bipush 120 (0x78)
		// @B1: invokevirtual game.C_100202_qi.func_105907_c(byte)game.C_100158_da
		// @B4: checkcast game.C_100302_ka
		// @B7: astore #4
		// @B9: iload #6
		// @BB: ifeq @82
		// @BE: iload_3
		// @BF: ireturn
		// @C0: astore_3
		// @C1: aload_3
		// @C2: new java.lang.StringBuilder
		// @C5: dup
		// @C6: invokespecial java.lang.StringBuilder.<init>()void
		// @C9: getstatic java.lang.String[] game.C_100302_ka.field_101831_Ub
		// @CC: bipush 11 (0x0B)
		// @CE: aaload
		// @CF: invokevirtual java.lang.StringBuilder.append(java.lang.String)java.lang.StringBuilder
		// @D2: iload_1
		// @D3: invokevirtual java.lang.StringBuilder.append(int)java.lang.StringBuilder
		// @D6: bipush 44 (0x2C)
		// @D8: invokevirtual java.lang.StringBuilder.append(char)java.lang.StringBuilder
		// @DB: iload_2
		// @DC: invokevirtual java.lang.StringBuilder.append(int)java.lang.StringBuilder
		// @DF: bipush 41 (0x29)
		// @E1: invokevirtual java.lang.StringBuilder.append(char)java.lang.StringBuilder
		// @E4: invokevirtual java.lang.StringBuilder.toString()java.lang.String
		// @E7: invokestatic game.C_100181_cf.func_105695_a(java.lang.Throwable, java.lang.String)game.C_100170_cm
		// @EA: athrow
	}
	
	C_100302_ka(long arg0, C_100302_ka arg1)
	{
		// @0: aload_0
		// @1: lload_1
		// @2: aload_3
		// @3: iconst_0
		// @4: iconst_0
		// @5: iconst_0
		// @6: iconst_0
		// @7: aconst_null
		// @8: invokespecial game.C_100302_ka.<init>(long, game.C_100302_ka, int, int, int, int, java.lang.String)void
		// @B: return
	}
	
	public C_100302_ka()
	{
		// @00: aload_0
		// @01: invokespecial game.C_100148_bh.<init>()void
		// @04: aload_0
		// @05: ldc -2147483648 (0x80000000)
		// @07: putfield int game.C_100302_ka.field_101867_P
		// @0A: aload_0
		// @0B: ldc -2147483648 (0x80000000)
		// @0D: putfield int game.C_100302_ka.field_101877_Z
		// @10: aload_0
		// @11: iconst_m1
		// @12: putfield int game.C_100302_ka.field_101860_K
		// @15: aload_0
		// @16: iconst_0
		// @17: putfield boolean game.C_100302_ka.field_101838_Lb
		// @1A: aload_0
		// @1B: ldc -2147483648 (0x80000000)
		// @1D: putfield int game.C_100302_ka.field_101849_Mb
		// @20: aload_0
		// @21: iconst_m1
		// @22: putfield int game.C_100302_ka.field_101868_Ab
		// @25: aload_0
		// @26: sipush 256 (0x0100)
		// @29: putfield int game.C_100302_ka.field_101871_mb
		// @2C: aload_0
		// @2D: ldc -2147483648 (0x80000000)
		// @2F: putfield int game.C_100302_ka.field_101837_bb
		// @32: aload_0
		// @33: sipush 256 (0x0100)
		// @36: putfield int game.C_100302_ka.field_101857_eb
		// @39: aload_0
		// @3A: iconst_m1
		// @3B: putfield int game.C_100302_ka.field_101859_rb
		// @3E: aload_0
		// @3F: iconst_0
		// @40: putfield boolean game.C_100302_ka.field_101827_cb
		// @43: aload_0
		// @44: ldc -2147483648 (0x80000000)
		// @46: putfield int game.C_100302_ka.field_101869_S
		// @49: aload_0
		// @4A: iconst_m1
		// @4B: putfield int game.C_100302_ka.field_101872_Nb
		// @4E: aload_0
		// @4F: iconst_1
		// @50: putfield boolean game.C_100302_ka.field_101864_W
		// @53: aload_0
		// @54: ldc -2147483648 (0x80000000)
		// @56: putfield int game.C_100302_ka.field_101866_Q
		// @59: return
	}
	
	private final C_100302_ka func_101817_b(int arg0, long arg1)
	{
		// @00: getstatic int game.SteelSentinels.field_105275_O
		// @03: istore #6
		// @05: aload_0
		// @06: getfield long game.C_100302_ka.field_100595_c
		// @09: ldc2_w -1
		// @0C: lxor
		// @0D: lload_2
		// @0E: ldc2_w -1
		// @11: lxor
		// @12: lcmp
		// @13: ifeq @1A
		// @16: goto @1C
		// @19: athrow
		// @1A: aload_0
		// @1B: areturn
		// @1C: aconst_null
		// @1D: aload_0
		// @1E: getfield game.C_100202_qi game.C_100302_ka.field_101891_Ob
		// @21: if_acmpne @28
		// @24: goto @6F
		// @27: athrow
		// @28: aload_0
		// @29: getfield game.C_100202_qi game.C_100302_ka.field_101891_Ob
		// @2C: bipush 83 (0x53)
		// @2E: invokevirtual game.C_100202_qi.func_105899_c(int)game.C_100158_da
		// @31: checkcast game.C_100302_ka
		// @34: astore #4
		// @36: aconst_null
		// @37: aload #4
		// @39: if_acmpeq @6F
		// @3C: aload #4
		// @3E: bipush 109 (0x6D)
		// @40: lload_2
		// @41: invokespecial game.C_100302_ka.func_101817_b(int, long)game.C_100302_ka
		// @44: astore #5
		// @46: aconst_null
		// @47: iload #6
		// @49: ifne @80
		// @4C: aload #5
		// @4E: if_acmpne @59
		// @51: goto @55
		// @54: athrow
		// @55: goto @5C
		// @58: athrow
		// @59: aload #5
		// @5B: areturn
		// @5C: aload_0
		// @5D: getfield game.C_100202_qi game.C_100302_ka.field_101891_Ob
		// @60: bipush 51 (0x33)
		// @62: invokevirtual game.C_100202_qi.func_105907_c(byte)game.C_100158_da
		// @65: checkcast game.C_100302_ka
		// @68: astore #4
		// @6A: iload #6
		// @6C: ifeq @36
		// @6F: iload_1
		// @70: bipush 98 (0x62)
		// @72: if_icmpgt @7F
		// @75: aload_0
		// @76: bipush -110 (0x92)
		// @78: putfield int game.C_100302_ka.field_101886_Kb
		// @7B: goto @7F
		// @7E: athrow
		// @7F: aconst_null
		// @80: areturn
		// @81: astore #4
		// @83: aload #4
		// @85: new java.lang.StringBuilder
		// @88: dup
		// @89: invokespecial java.lang.StringBuilder.<init>()void
		// @8C: getstatic java.lang.String[] game.C_100302_ka.field_101831_Ub
		// @8F: iconst_0
		// @90: aaload
		// @91: invokevirtual java.lang.StringBuilder.append(java.lang.String)java.lang.StringBuilder
		// @94: iload_1
		// @95: invokevirtual java.lang.StringBuilder.append(int)java.lang.StringBuilder
		// @98: bipush 44 (0x2C)
		// @9A: invokevirtual java.lang.StringBuilder.append(char)java.lang.StringBuilder
		// @9D: lload_2
		// @9E: invokevirtual java.lang.StringBuilder.append(long)java.lang.StringBuilder
		// @A1: bipush 41 (0x29)
		// @A3: invokevirtual java.lang.StringBuilder.append(char)java.lang.StringBuilder
		// @A6: invokevirtual java.lang.StringBuilder.toString()java.lang.String
		// @A9: invokestatic game.C_100181_cf.func_105695_a(java.lang.Throwable, java.lang.String)game.C_100170_cm
		// @AC: athrow
	}
	
	C_100302_ka(long arg0, C_100302_ka arg1, int arg2, int arg3, int arg4, int arg5, String arg6)
	{
		// @000: aload_0
		// @001: invokespecial game.C_100148_bh.<init>()void
		// @004: aload_0
		// @005: ldc -2147483648 (0x80000000)
		// @007: putfield int game.C_100302_ka.field_101867_P
		// @00A: aload_0
		// @00B: ldc -2147483648 (0x80000000)
		// @00D: putfield int game.C_100302_ka.field_101877_Z
		// @010: aload_0
		// @011: iconst_m1
		// @012: putfield int game.C_100302_ka.field_101860_K
		// @015: aload_0
		// @016: iconst_0
		// @017: putfield boolean game.C_100302_ka.field_101838_Lb
		// @01A: aload_0
		// @01B: ldc -2147483648 (0x80000000)
		// @01D: putfield int game.C_100302_ka.field_101849_Mb
		// @020: aload_0
		// @021: iconst_m1
		// @022: putfield int game.C_100302_ka.field_101868_Ab
		// @025: aload_0
		// @026: sipush 256 (0x0100)
		// @029: putfield int game.C_100302_ka.field_101871_mb
		// @02C: aload_0
		// @02D: ldc -2147483648 (0x80000000)
		// @02F: putfield int game.C_100302_ka.field_101837_bb
		// @032: aload_0
		// @033: sipush 256 (0x0100)
		// @036: putfield int game.C_100302_ka.field_101857_eb
		// @039: aload_0
		// @03A: iconst_m1
		// @03B: putfield int game.C_100302_ka.field_101859_rb
		// @03E: aload_0
		// @03F: iconst_0
		// @040: putfield boolean game.C_100302_ka.field_101827_cb
		// @043: aload_0
		// @044: ldc -2147483648 (0x80000000)
		// @046: putfield int game.C_100302_ka.field_101869_S
		// @049: aload_0
		// @04A: iconst_m1
		// @04B: putfield int game.C_100302_ka.field_101872_Nb
		// @04E: aload_0
		// @04F: iconst_1
		// @050: putfield boolean game.C_100302_ka.field_101864_W
		// @053: aload_0
		// @054: ldc -2147483648 (0x80000000)
		// @056: putfield int game.C_100302_ka.field_101866_Q
		// @059: aload_0
		// @05A: iload #7
		// @05C: putfield int game.C_100302_ka.field_101848_lb
		// @05F: aload_0
		// @060: iload #6
		// @062: putfield int game.C_100302_ka.field_101886_Kb
		// @065: aload_0
		// @066: iload #4
		// @068: putfield int game.C_100302_ka.field_101841_Pb
		// @06B: aload_0
		// @06C: iload #5
		// @06E: putfield int game.C_100302_ka.field_101880_Gb
		// @071: aload_0
		// @072: lload_1
		// @073: putfield long game.C_100302_ka.field_100595_c
		// @076: aload_0
		// @077: sipush 32280 (0x7E18)
		// @07A: aload_3
		// @07B: invokevirtual game.C_100302_ka.func_101810_a(int, game.C_100302_ka)void
		// @07E: aconst_null
		// @07F: aload #8
		// @081: if_acmpeq @08A
		// @084: aload_0
		// @085: aload #8
		// @087: putfield java.lang.String game.C_100302_ka.field_101890_ab
		// @08A: goto @10E
		// @08D: astore #9
		// @08F: aload #9
		// @091: new java.lang.StringBuilder
		// @094: dup
		// @095: invokespecial java.lang.StringBuilder.<init>()void
		// @098: getstatic java.lang.String[] game.C_100302_ka.field_101831_Ub
		// @09B: bipush 10 (0x0A)
		// @09D: aaload
		// @09E: invokevirtual java.lang.StringBuilder.append(java.lang.String)java.lang.StringBuilder
		// @0A1: lload_1
		// @0A2: invokevirtual java.lang.StringBuilder.append(long)java.lang.StringBuilder
		// @0A5: bipush 44 (0x2C)
		// @0A7: invokevirtual java.lang.StringBuilder.append(char)java.lang.StringBuilder
		// @0AA: aload_3
		// @0AB: ifnull @0B7
		// @0AE: getstatic java.lang.String[] game.C_100302_ka.field_101831_Ub
		// @0B1: iconst_2
		// @0B2: aaload
		// @0B3: goto @0BC
		// @0B6: athrow
		// @0B7: getstatic java.lang.String[] game.C_100302_ka.field_101831_Ub
		// @0BA: iconst_3
		// @0BB: aaload
		// @0BC: invokevirtual java.lang.StringBuilder.append(java.lang.String)java.lang.StringBuilder
		// @0BF: bipush 44 (0x2C)
		// @0C1: invokevirtual java.lang.StringBuilder.append(char)java.lang.StringBuilder
		// @0C4: iload #4
		// @0C6: invokevirtual java.lang.StringBuilder.append(int)java.lang.StringBuilder
		// @0C9: bipush 44 (0x2C)
		// @0CB: invokevirtual java.lang.StringBuilder.append(char)java.lang.StringBuilder
		// @0CE: iload #5
		// @0D0: invokevirtual java.lang.StringBuilder.append(int)java.lang.StringBuilder
		// @0D3: bipush 44 (0x2C)
		// @0D5: invokevirtual java.lang.StringBuilder.append(char)java.lang.StringBuilder
		// @0D8: iload #6
		// @0DA: invokevirtual java.lang.StringBuilder.append(int)java.lang.StringBuilder
		// @0DD: bipush 44 (0x2C)
		// @0DF: invokevirtual java.lang.StringBuilder.append(char)java.lang.StringBuilder
		// @0E2: iload #7
		// @0E4: invokevirtual java.lang.StringBuilder.append(int)java.lang.StringBuilder
		// @0E7: bipush 44 (0x2C)
		// @0E9: invokevirtual java.lang.StringBuilder.append(char)java.lang.StringBuilder
		// @0EC: aload #8
		// @0EE: ifnull @0FA
		// @0F1: getstatic java.lang.String[] game.C_100302_ka.field_101831_Ub
		// @0F4: iconst_2
		// @0F5: aaload
		// @0F6: goto @0FF
		// @0F9: athrow
		// @0FA: getstatic java.lang.String[] game.C_100302_ka.field_101831_Ub
		// @0FD: iconst_3
		// @0FE: aaload
		// @0FF: invokevirtual java.lang.StringBuilder.append(java.lang.String)java.lang.StringBuilder
		// @102: bipush 41 (0x29)
		// @104: invokevirtual java.lang.StringBuilder.append(char)java.lang.StringBuilder
		// @107: invokevirtual java.lang.StringBuilder.toString()java.lang.String
		// @10A: invokestatic game.C_100181_cf.func_105695_a(java.lang.Throwable, java.lang.String)game.C_100170_cm
		// @10D: athrow
		// @10E: return
	}
	
	static
	{
		// @000: bipush 20 (0x14)
		// @002: anewarray java.lang.String
		// @005: dup
		// @006: iconst_0
		// @007: ldc "*~\u001eREi"
		// @009: invokestatic game.C_100302_ka.func_101814_z(java.lang.String)char[]
		// @00C: invokestatic game.C_100302_ka.func_101813_z(char[])java.lang.String
		// @00F: aastore
		// @010: dup
		// @011: iconst_1
		// @012: ldc "*~\u001eVEi"
		// @014: invokestatic game.C_100302_ka.func_101814_z(java.lang.String)char[]
		// @017: invokestatic game.C_100302_ka.func_101813_z(char[])java.lang.String
		// @01A: aastore
		// @01B: dup
		// @01C: iconst_2
		// @01D: ldc ":1\u001e6y"
		// @01F: invokestatic game.C_100302_ka.func_101814_z(java.lang.String)char[]
		// @022: invokestatic game.C_100302_ka.func_101813_z(char[])java.lang.String
		// @025: aastore
		// @026: dup
		// @027: iconst_3
		// @028: ldc "/j\\t"
		// @02A: invokestatic game.C_100302_ka.func_101814_z(java.lang.String)char[]
		// @02D: invokestatic game.C_100302_ka.func_101813_z(char[])java.lang.String
		// @030: aastore
		// @031: dup
		// @032: iconst_4
		// @033: ldc "*~\u001eYFi"
		// @035: invokestatic game.C_100302_ka.func_101814_z(java.lang.String)char[]
		// @038: invokestatic game.C_100302_ka.func_101813_z(char[])java.lang.String
		// @03B: aastore
		// @03C: dup
		// @03D: iconst_5
		// @03E: ldc "*~\u001eTEi"
		// @040: invokestatic game.C_100302_ka.func_101814_z(java.lang.String)char[]
		// @043: invokestatic game.C_100302_ka.func_101813_z(char[])java.lang.String
		// @046: aastore
		// @047: dup
		// @048: bipush 6 (0x06)
		// @04A: ldc "*~\u001eUEi"
		// @04C: invokestatic game.C_100302_ka.func_101814_z(java.lang.String)char[]
		// @04F: invokestatic game.C_100302_ka.func_101813_z(char[])java.lang.String
		// @052: aastore
		// @053: dup
		// @054: bipush 7 (0x07)
		// @056: ldc "*~\u001eOEi"
		// @058: invokestatic game.C_100302_ka.func_101814_z(java.lang.String)char[]
		// @05B: invokestatic game.C_100302_ka.func_101813_z(char[])java.lang.String
		// @05E: aastore
		// @05F: dup
		// @060: bipush 8 (0x08)
		// @062: ldc "*~\u001eIEi"
		// @064: invokestatic game.C_100302_ka.func_101814_z(java.lang.String)char[]
		// @067: invokestatic game.C_100302_ka.func_101813_z(char[])java.lang.String
		// @06A: aastore
		// @06B: dup
		// @06C: bipush 9 (0x09)
		// @06E: ldc "*~\u001eJEi"
		// @070: invokestatic game.C_100302_ka.func_101814_z(java.lang.String)char[]
		// @073: invokestatic game.C_100302_ka.func_101813_z(char[])java.lang.String
		// @076: aastore
		// @077: dup
		// @078: bipush 10 (0x0A)
		// @07A: ldc "*~\u001e$m/vD&,"
		// @07C: invokestatic game.C_100302_ka.func_101814_z(java.lang.String)char[]
		// @07F: invokestatic game.C_100302_ka.func_101813_z(char[])java.lang.String
		// @082: aastore
		// @083: dup
		// @084: bipush 11 (0x0B)
		// @086: ldc "*~\u001eSEi"
		// @088: invokestatic game.C_100302_ka.func_101814_z(java.lang.String)char[]
		// @08B: invokestatic game.C_100302_ka.func_101813_z(char[])java.lang.String
		// @08E: aastore
		// @08F: dup
		// @090: bipush 12 (0x0C)
		// @092: ldc "}}B&"
		// @094: invokestatic game.C_100302_ka.func_101814_z(java.lang.String)char[]
		// @097: invokestatic game.C_100302_ka.func_101813_z(char[])java.lang.String
		// @09A: aastore
		// @09B: dup
		// @09C: bipush 13 (0x0D)
		// @09E: ldc "*~\u001eWEi"
		// @0A0: invokestatic game.C_100302_ka.func_101814_z(java.lang.String)char[]
		// @0A3: invokestatic game.C_100302_ka.func_101813_z(char[])java.lang.String
		// @0A6: aastore
		// @0A7: dup
		// @0A8: bipush 14 (0x0E)
		// @0AA: ldc "*~\u001eHEi"
		// @0AC: invokestatic game.C_100302_ka.func_101814_z(java.lang.String)char[]
		// @0AF: invokestatic game.C_100302_ka.func_101813_z(char[])java.lang.String
		// @0B2: aastore
		// @0B3: dup
		// @0B4: bipush 15 (0x0F)
		// @0B6: ldc "*~\u001eKEi"
		// @0B8: invokestatic game.C_100302_ka.func_101814_z(java.lang.String)char[]
		// @0BB: invokestatic game.C_100302_ka.func_101813_z(char[])java.lang.String
		// @0BE: aastore
		// @0BF: dup
		// @0C0: bipush 16 (0x10)
		// @0C2: ldc "*~\u001eNEi"
		// @0C4: invokestatic game.C_100302_ka.func_101814_z(java.lang.String)char[]
		// @0C7: invokestatic game.C_100302_ka.func_101813_z(char[])java.lang.String
		// @0CA: aastore
		// @0CB: dup
		// @0CC: bipush 17 (0x11)
		// @0CE: ldc "*~\u001eQEi"
		// @0D0: invokestatic game.C_100302_ka.func_101814_z(java.lang.String)char[]
		// @0D3: invokestatic game.C_100302_ka.func_101813_z(char[])java.lang.String
		// @0D6: aastore
		// @0D7: dup
		// @0D8: bipush 18 (0x12)
		// @0DA: ldc "*~\u001eLEi"
		// @0DC: invokestatic game.C_100302_ka.func_101814_z(java.lang.String)char[]
		// @0DF: invokestatic game.C_100302_ka.func_101813_z(char[])java.lang.String
		// @0E2: aastore
		// @0E3: dup
		// @0E4: bipush 19 (0x13)
		// @0E6: ldc "*~\u001eMEi"
		// @0E8: invokestatic game.C_100302_ka.func_101814_z(java.lang.String)char[]
		// @0EB: invokestatic game.C_100302_ka.func_101813_z(char[])java.lang.String
		// @0EE: aastore
		// @0EF: putstatic java.lang.String[] game.C_100302_ka.field_101831_Ub
		// @0F2: ldc "\u0011sQa$3~D}`axQua"
		// @0F4: invokestatic game.C_100302_ka.func_101814_z(java.lang.String)char[]
		// @0F7: invokestatic game.C_100302_ka.func_101813_z(char[])java.lang.String
		// @0FA: putstatic java.lang.String game.C_100302_ka.field_101870_R
		// @0FD: ldc "\u0002mUyp$?Evv kU|$&~]}"
		// @0FF: invokestatic game.C_100302_ka.func_101814_z(java.lang.String)char[]
		// @102: invokestatic game.C_100302_ka.func_101813_z(char[])java.lang.String
		// @105: putstatic java.lang.String game.C_100302_ka.field_101865_V
		// @108: new game.C_100202_qi
		// @10B: dup
		// @10C: invokespecial game.C_100202_qi.<init>()void
		// @10F: putstatic game.C_100202_qi game.C_100302_ka.field_101828_Qb
		// @112: iconst_1
		// @113: putstatic boolean game.C_100302_ka.field_101882_Cb
		// @116: bipush 34 (0x22)
		// @118: anewarray java.lang.String
		// @11B: dup
		// @11C: iconst_0
		// @11D: ldc "\u0008qSja lUk$8pEj$$qUjc8?Wym/?Ra$}v]\u007f9v!\u0010f5w?wR+21"
		// @11F: invokestatic game.C_100302_ka.func_101814_z(java.lang.String)char[]
		// @122: invokestatic game.C_100302_ka.func_101813_z(char[])java.lang.String
		// @125: aastore
		// @126: dup
		// @127: iconst_1
		// @128: ldc "\u0008qSja lUk$8pEj$$qUjc8?Wym/?Ra$}v]\u007f9v!\u0010f7r?wR+21"
		// @12A: invokestatic game.C_100302_ka.func_101814_z(java.lang.String)char[]
		// @12D: invokestatic game.C_100302_ka.func_101813_z(char[])java.lang.String
		// @130: aastore
		// @131: dup
		// @132: iconst_2
		// @133: ldc "\u0008qSja lUk$8pEj$$qUjc8?Wym/?Ra$}v]\u007f9v!\u0010f1q?wR+21"
		// @135: invokestatic game.C_100302_ka.func_101814_z(java.lang.String)char[]
		// @138: invokestatic game.C_100302_ka.func_101813_z(char[])java.lang.String
		// @13B: aastore
		// @13C: dup
		// @13D: iconst_3
		// @13E: ldc "\u0008qSja lUk$8pEj$$qUjc8?Wym/?Ra$}v]\u007f9v!\u0010f2w?wR+21"
		// @140: invokestatic game.C_100302_ka.func_101814_z(java.lang.String)char[]
		// @143: invokestatic game.C_100302_ka.func_101813_z(char[])java.lang.String
		// @146: aastore
		// @147: dup
		// @148: iconst_4
		// @149: ldc "\u0008qSja lUk$8pEj$$qUjc8?Wym/?Ra$}v]\u007f9v!\u0010f<r?wR+21"
		// @14B: invokestatic game.C_100302_ka.func_101814_z(java.lang.String)char[]
		// @14E: invokestatic game.C_100302_ka.func_101813_z(char[])java.lang.String
		// @151: aastore
		// @152: dup
		// @153: iconst_5
		// @154: ldc "\u0008qSja lU8}.jB8a/zB\u007f}alDwv xU8f8?\u000cqi&\"\u0004&$p?dR*"
		// @156: invokestatic game.C_100302_ka.func_101814_z(java.lang.String)char[]
		// @159: invokestatic game.C_100302_ka.func_101813_z(char[])java.lang.String
		// @15C: aastore
		// @15D: dup
		// @15E: bipush 6 (0x06)
		// @160: ldc "\u0008qSja lU8}.jB8a/zB\u007f}alDwv xU8f8?\u000cqi&\"\u0004&$s?dR*"
		// @162: invokestatic game.C_100302_ka.func_101814_z(java.lang.String)char[]
		// @165: invokestatic game.C_100302_ka.func_101813_z(char[])java.lang.String
		// @168: aastore
		// @169: dup
		// @16A: bipush 7 (0x07)
		// @16C: ldc "\u0008qSja lU8}.jB8a/zB\u007f}alDwv xU8f8?\u000cqi&\"\u0004&$r?dR*"
		// @16E: invokestatic game.C_100302_ka.func_101814_z(java.lang.String)char[]
		// @171: invokestatic game.C_100302_ka.func_101813_z(char[])java.lang.String
		// @174: aastore
		// @175: dup
		// @176: bipush 8 (0x08)
		// @178: ldc "\u0008qSja lU8}.jB8a/zB\u007f}alDwv xU8f8?\u000cqi&\"\u0004&$u?dR*"
		// @17A: invokestatic game.C_100302_ka.func_101814_z(java.lang.String)char[]
		// @17D: invokestatic game.C_100302_ka.func_101813_z(char[])java.lang.String
		// @180: aastore
		// @181: dup
		// @182: bipush 9 (0x09)
		// @184: ldc "\u0008qSja lU8}.jB8a/zB\u007f}alDwv xU8f8?\u000cqi&\"\u0004&$t?dR*"
		// @186: invokestatic game.C_100302_ka.func_101814_z(java.lang.String)char[]
		// @189: invokestatic game.C_100302_ka.func_101813_z(char[])java.lang.String
		// @18C: aastore
		// @18D: dup
		// @18E: bipush 10 (0x0A)
		// @190: ldc "\u0011m_nm%zC8ea#Yuc|*\u000e85q/\u0010_NalXqa-{\u0010ll k\u0010yf2pBzwaz^}v&f\u0010yp5~Sswa~^|$$g@tk2v_vwo"
		// @192: invokestatic game.C_100302_ka.func_101814_z(java.lang.String)char[]
		// @195: invokestatic game.C_100302_ka.func_101813_z(char[])java.lang.String
		// @198: aastore
		// @199: dup
		// @19A: bipush 11 (0x0B)
		// @19C: ldc "\u0011m_nm%zC8ea#Yuc|*\u000e86q/\u0010_NalXqa-{\u0010ll k\u0010yf2pBzwaz^}v&f\u0010yp5~Sswa~^|$$g@tk2v_vwo"
		// @19E: invokestatic game.C_100302_ka.func_101814_z(java.lang.String)char[]
		// @1A1: invokestatic game.C_100302_ka.func_101813_z(char[])java.lang.String
		// @1A4: aastore
		// @1A5: dup
		// @1A6: bipush 12 (0x0C)
		// @1A8: ldc "\u0011m_nm%zC8ea#Yuc|*\u000e81q/\u0010_NalXqa-{\u0010ll k\u0010yf2pBzwaz^}v&f\u0010yp5~Sswa~^|$$g@tk2v_vwo"
		// @1AA: invokestatic game.C_100302_ka.func_101814_z(java.lang.String)char[]
		// @1AD: invokestatic game.C_100302_ka.func_101813_z(char[])java.lang.String
		// @1B0: aastore
		// @1B1: dup
		// @1B2: bipush 13 (0x0D)
		// @1B4: ldc "\u0011m_nm%zC8ea#Yuc|*\u000e85m/\u0000($\u0006U\u0010kl(z\\|$5wQl$ }Cwv#l\u0010}j$mWa$ kDyg*l\u0010yj%?U`t-pCqk/l\u001e"
		// @1B6: invokestatic game.C_100302_ka.func_101814_z(java.lang.String)char[]
		// @1B9: invokestatic game.C_100302_ka.func_101813_z(char[])java.lang.String
		// @1BC: aastore
		// @1BD: dup
		// @1BE: bipush 14 (0x0E)
		// @1C0: ldc "\u0011m_nm%zC8ea#Yuc|*\u000e86m/\u0000($\u0006U\u0010kl(z\\|$5wQl$ }Cwv#l\u0010}j$mWa$ kDyg*l\u0010yj%?U`t-pCqk/l\u001e"
		// @1C2: invokestatic game.C_100302_ka.func_101814_z(java.lang.String)char[]
		// @1C5: invokestatic game.C_100302_ka.func_101813_z(char[])java.lang.String
		// @1C8: aastore
		// @1C9: dup
		// @1CA: bipush 15 (0x0F)
		// @1CC: ldc "\u0005zDwj kUk$ ?]yw2vF}$\u0004R`8a9o\\ww(p^8p)~D8s(s\\8`3~Yv$5wU8a/zB\u007f}apV8e/f\u0010ka/kYva-?Yv$5wU8r(|Yvm5f\u001e8Q2zC8e-s\u0010wbaf_mvalDwv${\u0010}j$mWa*"
		// @1CE: invokestatic game.C_100302_ka.func_101814_z(java.lang.String)char[]
		// @1D1: invokestatic game.C_100302_ka.func_101813_z(char[])java.lang.String
		// @1D4: aastore
		// @1D5: dup
		// @1D6: bipush 16 (0x10)
		// @1D8: ldc "\u0000s\\ws2?Iwqak_8c v^8eakQjc$k\u0010tk\"t\u0010wjaz^}i8?C}j5v^}h23\u0010mw(qW88(rW%0\u007f?\u00018P\u000b?_~$$qUjc81\u0010Tk\"tYvcap^8s(s\\8i tU8i(lCqh$l\u0010pk,z\u0010qjap^8p)z\u0010le3xUl$ qT8`(mU{pa~\\t$&j^8k3?\\yw$m\u0010~m3z\u001e"
		// @1DA: invokestatic game.C_100302_ka.func_101814_z(java.lang.String)char[]
		// @1DD: invokestatic game.C_100302_ka.func_101813_z(char[])java.lang.String
		// @1E0: aastore
		// @1E1: dup
		// @1E2: bipush 17 (0x11)
		// @1E4: ldc "\u0000jDwi kY{e-sI8p mW}p2?Yvg.rYvcarYkw(sUk$ qT8v.|[}p2?Gqp)?Qv}asY\u007fl5?G}e1p^k$\"~@yf-z\u0010wbalXwk5v^\u007f$5wUu$%pGv$iy\\yom?Wmja~^|$-~C}vahUyt.qC1*"
		// @1E6: invokestatic game.C_100302_ka.func_101814_z(java.lang.String)char[]
		// @1E9: invokestatic game.C_100302_ka.func_101813_z(char[])java.lang.String
		// @1EC: aastore
		// @1ED: dup
		// @1EE: bipush 18 (0x12)
		// @1F0: ldc "\u0012|Byi#sUk$5~B\u007fa5?\\wg*l\u0010wjaf_mvalUvp(qUt*"
		// @1F2: invokestatic game.C_100302_ka.func_101814_z(java.lang.String)char[]
		// @1F5: invokestatic game.C_100302_ka.func_101813_z(char[])java.lang.String
		// @1F8: aastore
		// @1F9: dup
		// @1FA: bipush 19 (0x13)
		// @1FC: ldc "\u0013z@ym3l\u0010ak4m\u0010ka/kYva-?Ctk6sI8k7zB8p(rU4$ l\u0010tk/x\u0010ywavD8m2?^wpakQsm/x\u0010|e,~W}*aKXqwar_|q-z\u0010{k/kYvq.jCt}a{Bys2?@ws$m\u0010~v.r\u0010ak4m\u0010ja |Dwv21"
		// @1FE: invokestatic game.C_100302_ka.func_101814_z(java.lang.String)char[]
		// @201: invokestatic game.C_100302_ka.func_101813_z(char[])java.lang.String
		// @204: aastore
		// @205: dup
		// @206: bipush 20 (0x14)
		// @208: ldc "\u0000?Xqc)?_mp1jD8v$~Slk3?Dpe5?Xywaq_l$8zD8g.r@ta5zT8p$lDqj&?VwvalDyf(sYl}o"
		// @20A: invokestatic game.C_100302_ka.func_101814_z(java.lang.String)char[]
		// @20D: invokestatic game.C_100302_ka.func_101813_z(char[])java.lang.String
		// @210: aastore
		// @211: dup
		// @212: bipush 21 (0x15)
		// @214: ldc "\u0012w_owar_jaav^~k3rQlm.q\u0010yf.jD8}.jB8k1o_va/kC4$2jSp$ l\u0010ll$vB8m/lDyh-zT8w8lD}i2?Qv`akQjc$k\u0010tk\"t\u0010kp kEk*a^\\kkazHla/{C8p)z\u0010je/xU8k'?Iwq3?Vqv(qW8e3|\u0010hv.uU{p(p^k*"
		// @216: invokestatic game.C_100302_ka.func_101814_z(java.lang.String)char[]
		// @219: invokestatic game.C_100302_ka.func_101813_z(char[])java.lang.String
		// @21C: aastore
		// @21D: dup
		// @21E: bipush 22 (0x16)
		// @220: ldc "\u0013zTmg$l\u0010ll$?B}h.~T8p(rU8k'?Bwg*zDk$ qT8i(lCqh$l\u0010z}awQtbo"
		// @222: invokestatic game.C_100302_ka.func_101814_z(java.lang.String)char[]
		// @225: invokestatic game.C_100302_ka.func_101813_z(char[])java.lang.String
		// @228: aastore
		// @229: dup
		// @22A: bipush 23 (0x17)
		// @22C: ldc "\t~\\na2?Dpaaz^}v&f\u0010ja0jYja,z^lwapV8t-~CueahUyt.qC6"
		// @22E: invokestatic game.C_100302_ka.func_101814_z(java.lang.String)char[]
		// @231: invokestatic game.C_100302_ka.func_101813_z(char[])java.lang.String
		// @234: aastore
		// @235: dup
		// @236: bipush 24 (0x18)
		// @238: ldc "\u0000s\\ws2?Iwqak_8p$sUhk3k\u0010yg3pCk$5wU8i o\u0010lka~\u0010ke'z\u0010tk\"~Dqk/1\u0010Ja0jYja2?Ql$-zQkpa#Yuc|+\u000e81aKz8k'?Uva3xI4$ qT8a9wQmw5l\u0010ak4m\u0010}j$mWa$#~^s$6wUv$ |Dqr kU|*"
		// @23A: invokestatic game.C_100302_ka.func_101814_z(java.lang.String)char[]
		// @23D: invokestatic game.C_100302_ka.func_101813_z(char[])java.lang.String
		// @240: aastore
		// @241: dup
		// @242: bipush 25 (0x19)
		// @244: ldc "\u0005pEzh$l\u0010ll$?Tyi xU8k4k@mpapV8}.jB8h lUj$6zQhk/l\u001c8f4k\u0010yh2p\u0010|k4}\\}wakX}m3?Uva3xI8q2z\u001e"
		// @246: invokestatic game.C_100302_ka.func_101814_z(java.lang.String)char[]
		// @249: invokestatic game.C_100302_ka.func_101813_z(char[])java.lang.String
		// @24C: aastore
		// @24D: dup
		// @24E: bipush 26 (0x1A)
		// @250: ldc "\u0013zSpe3xUk$8pEj$$qUjc8?Cpm$sT8s)z^8}.jB8w$qDqj$s\u0010le*zC8` rQ\u007fao"
		// @252: invokestatic game.C_100302_ka.func_101814_z(java.lang.String)char[]
		// @255: invokestatic game.C_100302_ka.func_101813_z(char[])java.lang.String
		// @258: aastore
		// @259: dup
		// @25A: bipush 27 (0x1B)
		// @25C: ldc "\u0013z]wr$l\u0010ll$?Uva3xI5w o@qj&?U~b$|Dk$.y\u0010]I\u0011?Qlp |[k*"
		// @25E: invokestatic game.C_100302_ka.func_101814_z(java.lang.String)char[]
		// @261: invokestatic game.C_100302_ka.func_101813_z(char[])java.lang.String
		// @264: aastore
		// @265: dup
		// @266: bipush 28 (0x1C)
		// @268: ldc "\u0008qSja lUk$8pEj$}v]\u007f9s!\u0010rq,oYvca~Rqh(kI8e/{\u0010ja%jS}wal[q`%v^\u007f*"
		// @26A: invokestatic game.C_100302_ka.func_101814_z(java.lang.String)char[]
		// @26D: invokestatic game.C_100302_ka.func_101813_z(char[])java.lang.String
		// @270: aastore
		// @271: dup
		// @272: bipush 29 (0x1D)
		// @274: ldc "\u0008qSja lUk$8pEj$}v]\u007f9r!\u0010ll3jClm/x\u0010}b'vSqa/|I8e/{\u0010yh-pGk$8pE8p.?Swj5v^maakXjq2kYvcazF}ja~Vla3?R}m/x\u0010pm5?Yv$5wU8e(m\u001e"
		// @276: invokestatic game.C_100302_ka.func_101814_z(java.lang.String)char[]
		// @279: invokestatic game.C_100302_ka.func_101813_z(char[])java.lang.String
		// @27C: aastore
		// @27D: dup
		// @27E: bipush 30 (0x1E)
		// @280: ldc "\u000c~[}waf_mvalUvp(qUt$)~B|$5p\u0010le3xUl$ qT8t(q@wm/k\u001c8f8?@jk7vTqj&?Q8g-pQsm/x\u0010k}2kUu*aKX}$\"s_yoahYtha{Uyg5vFyp$?Gpa/?Dyo(qW8` rQ\u007faapB8b(mYvco"
		// @282: invokestatic game.C_100302_ka.func_101814_z(java.lang.String)char[]
		// @285: invokestatic game.C_100302_ka.func_101813_z(char[])java.lang.String
		// @288: aastore
		// @289: dup
		// @28A: bipush 31 (0x1F)
		// @28C: ldc "\u0000s\\ws2?Qv}ahUyt.q\u0010lka}U8q2zT8s)v\\}$(q\u0010ll$?Qqvo"
		// @28E: invokestatic game.C_100302_ka.func_101814_z(java.lang.String)char[]
		// @291: invokestatic game.C_100302_ka.func_101813_z(char[])java.lang.String
		// @294: aastore
		// @295: dup
		// @296: bipush 32 (0x20)
		// @298: ldc "\u0000}Cwv#l\u0010sm/zDqga{Que&z\u0010~v.r\u0010zq-sUlwm?Vte*?Qv`atYva5vS8s$~@wj21"
		// @29A: invokestatic game.C_100302_ka.func_101814_z(java.lang.String)char[]
		// @29D: invokestatic game.C_100302_ka.func_101813_z(char[])java.lang.String
		// @2A0: aastore
		// @2A1: dup
		// @2A2: bipush 33 (0x21)
		// @2A4: ldc "\u0000}Cwv#l\u0010}|1s_km7z\u0010|e,~W}$'m_u$2wUth23\u0010um2lYta2?Qv`am_{o$kC6"
		// @2A6: invokestatic game.C_100302_ka.func_101814_z(java.lang.String)char[]
		// @2A9: invokestatic game.C_100302_ka.func_101813_z(char[])java.lang.String
		// @2AC: aastore
		// @2AD: putstatic java.lang.String[] game.C_100302_ka.field_101863_ib
		// @2B0: return
	}
	
	private static char[] func_101814_z(String arg0)
	{
		// @00: aload_0
		// @01: invokevirtual java.lang.String.toCharArray()char[]
		// @04: dup
		// @05: arraylength
		// @06: iconst_2
		// @07: if_icmpge @12
		// @0A: dup
		// @0B: iconst_0
		// @0C: dup2
		// @0D: caload
		// @0E: iconst_4
		// @0F: ixor
		// @10: i2c
		// @11: castore
		// @12: areturn
	}
	
	private static String func_101813_z(char[] arg0)
	{
		// @00: aload_0
		// @01: dup
		// @02: arraylength
		// @03: swap
		// @04: iconst_0
		// @05: istore_1
		// @06: goto @4B
		// @09: dup
		// @0A: iload_1
		// @0B: dup2
		// @0C: caload
		// @0D: iload_1
		// @0E: iconst_5
		// @0F: irem
		// @10: tableswitch def: @44, for 0: @30, for 1: @35, for 2: @3A, for 3: @3F
		// @30: bipush 65 (0x41)
		// @32: goto @45
		// @35: bipush 31 (0x1F)
		// @37: goto @45
		// @3A: bipush 48 (0x30)
		// @3C: goto @45
		// @3F: bipush 24 (0x18)
		// @41: goto @45
		// @44: iconst_4
		// @45: ixor
		// @46: i2c
		// @47: castore
		// @48: iinc #1 +1
		// @4B: swap
		// @4C: dup_x1
		// @4D: iload_1
		// @4E: if_icmpgt @09
		// @51: new java.lang.String
		// @54: dup_x1
		// @55: swap
		// @56: invokespecial java.lang.String.<init>(char[])void
		// @59: invokevirtual java.lang.String.intern()java.lang.String
		// @5C: areturn
	}
}
