package game;

final class C_100260_mc extends C_100302_ka
{
	static String[] field_102226_Zb;
	static int field_102234_jc;
	private C_100122_em field_102243_pc;
	private C_100302_ka field_102233_qc;
	static String[] field_102223_dc;
	private int field_102238_oc;
	private C_100302_ka field_102230_ec;
	static String field_102231_rc;
	static String field_102245_lc;
	static C_100153_be[] field_102235_Wb;
	static int field_102239_mc;
	private C_100302_ka field_102241_nc;
	static String field_102237_Ub;
	private StringBuilder field_102227_Xb;
	private C_100302_ka field_102232_fc;
	private C_100302_ka[] field_102229_hc;
	static String field_102242_kc;
	long field_102224_gc;
	static int field_102228_Yb;
	private C_100302_ka field_102246_bc;
	static String field_102247_cc;
	static String field_102244_ac;
	static C_100037_wb field_102236_ic;
	private C_100302_ka field_102240_Vb;
	private static final String[] field_102225_sc;
	
	private final int func_102216_a(int arg0, int arg1, C_100302_ka arg2, int arg3, C_100302_ka arg4, String arg5)
	{
		// @00: new game.C_100302_ka
		// @03: dup
		// @04: lconst_0
		// @05: aload_3
		// @06: iload_2
		// @07: iload #4
		// @09: iload_1
		// @0A: bipush 24 (0x18)
		// @0C: aload #6
		// @0E: invokespecial game.C_100302_ka.<init>(long, game.C_100302_ka, int, int, int, int, java.lang.String)void
		// @11: astore #7
		// @13: iinc #4 +32
		// @16: aload #5
		// @18: iload_2
		// @19: bipush -103 (0x99)
		// @1B: ixor
		// @1C: aload #7
		// @1E: invokevirtual game.C_100302_ka.func_101824_b(int, game.C_100302_ka)void
		// @21: iload #4
		// @23: ireturn
		// @24: astore #7
		// @26: aload #7
		// @28: new java.lang.StringBuilder
		// @2B: dup
		// @2C: invokespecial java.lang.StringBuilder.<init>()void
		// @2F: getstatic java.lang.String[] game.C_100260_mc.field_102225_sc
		// @32: iconst_4
		// @33: aaload
		// @34: invokevirtual java.lang.StringBuilder.append(java.lang.String)java.lang.StringBuilder
		// @37: iload_1
		// @38: invokevirtual java.lang.StringBuilder.append(int)java.lang.StringBuilder
		// @3B: bipush 44 (0x2C)
		// @3D: invokevirtual java.lang.StringBuilder.append(char)java.lang.StringBuilder
		// @40: iload_2
		// @41: invokevirtual java.lang.StringBuilder.append(int)java.lang.StringBuilder
		// @44: bipush 44 (0x2C)
		// @46: invokevirtual java.lang.StringBuilder.append(char)java.lang.StringBuilder
		// @49: aload_3
		// @4A: ifnull @56
		// @4D: getstatic java.lang.String[] game.C_100260_mc.field_102225_sc
		// @50: iconst_1
		// @51: aaload
		// @52: goto @5B
		// @55: athrow
		// @56: getstatic java.lang.String[] game.C_100260_mc.field_102225_sc
		// @59: iconst_0
		// @5A: aaload
		// @5B: invokevirtual java.lang.StringBuilder.append(java.lang.String)java.lang.StringBuilder
		// @5E: bipush 44 (0x2C)
		// @60: invokevirtual java.lang.StringBuilder.append(char)java.lang.StringBuilder
		// @63: iload #4
		// @65: invokevirtual java.lang.StringBuilder.append(int)java.lang.StringBuilder
		// @68: bipush 44 (0x2C)
		// @6A: invokevirtual java.lang.StringBuilder.append(char)java.lang.StringBuilder
		// @6D: aload #5
		// @6F: ifnull @7B
		// @72: getstatic java.lang.String[] game.C_100260_mc.field_102225_sc
		// @75: iconst_1
		// @76: aaload
		// @77: goto @80
		// @7A: athrow
		// @7B: getstatic java.lang.String[] game.C_100260_mc.field_102225_sc
		// @7E: iconst_0
		// @7F: aaload
		// @80: invokevirtual java.lang.StringBuilder.append(java.lang.String)java.lang.StringBuilder
		// @83: bipush 44 (0x2C)
		// @85: invokevirtual java.lang.StringBuilder.append(char)java.lang.StringBuilder
		// @88: aload #6
		// @8A: ifnull @96
		// @8D: getstatic java.lang.String[] game.C_100260_mc.field_102225_sc
		// @90: iconst_1
		// @91: aaload
		// @92: goto @9B
		// @95: athrow
		// @96: getstatic java.lang.String[] game.C_100260_mc.field_102225_sc
		// @99: iconst_0
		// @9A: aaload
		// @9B: invokevirtual java.lang.StringBuilder.append(java.lang.String)java.lang.StringBuilder
		// @9E: bipush 41 (0x29)
		// @A0: invokevirtual java.lang.StringBuilder.append(char)java.lang.StringBuilder
		// @A3: invokevirtual java.lang.StringBuilder.toString()java.lang.String
		// @A6: invokestatic game.C_100181_cf.func_105695_a(java.lang.Throwable, java.lang.String)game.C_100170_cm
		// @A9: athrow
	}
	
	final int func_102217_b(boolean arg0, byte arg1)
	{
		// @000: getstatic int game.SteelSentinels.field_105275_O
		// @003: istore #4
		// @005: iload_2
		// @006: bipush 71 (0x47)
		// @008: if_icmpeq @016
		// @00B: aconst_null
		// @00C: checkcast java.lang.String
		// @00F: putstatic java.lang.String game.C_100260_mc.field_102244_ac
		// @012: goto @016
		// @015: athrow
		// @016: aload_0
		// @017: iload_1
		// @018: bipush 22 (0x16)
		// @01A: invokevirtual game.C_100260_mc.func_101819_a(boolean, byte)void
		// @01D: aload_0
		// @01E: getfield game.C_100302_ka game.C_100260_mc.field_102232_fc
		// @021: ifnull @103
		// @024: aload_0
		// @025: getfield game.C_100302_ka game.C_100260_mc.field_102232_fc
		// @028: aload_0
		// @029: getfield java.lang.StringBuilder game.C_100260_mc.field_102227_Xb
		// @02C: invokevirtual java.lang.StringBuilder.toString()java.lang.String
		// @02F: putfield java.lang.String game.C_100302_ka.field_101890_ab
		// @032: aload_0
		// @033: getfield game.C_100302_ka game.C_100260_mc.field_102232_fc
		// @036: aload_0
		// @037: getfield int game.C_100260_mc.field_101886_Kb
		// @03A: aload_0
		// @03B: getfield game.C_100302_ka game.C_100260_mc.field_102232_fc
		// @03E: getfield game.C_100112_r game.C_100302_ka.field_101845_sb
		// @041: aload_0
		// @042: getfield game.C_100302_ka game.C_100260_mc.field_102232_fc
		// @045: getfield java.lang.String game.C_100302_ka.field_101890_ab
		// @048: invokevirtual game.C_100112_r.func_101739_b(java.lang.String)int
		// @04B: isub
		// @04C: iconst_2
		// @04D: idiv
		// @04E: putfield int game.C_100302_ka.field_101841_Pb
		// @051: aload_0
		// @052: getfield game.C_100122_em game.C_100260_mc.field_102243_pc
		// @055: ifnonnull @060
		// @058: goto @05C
		// @05B: athrow
		// @05C: goto @088
		// @05F: athrow
		// @060: iconst_m1
		// @061: aload_0
		// @062: getfield game.C_100122_em game.C_100260_mc.field_102243_pc
		// @065: getfield int game.C_100122_em.field_101854_N
		// @068: iconst_m1
		// @069: ixor
		// @06A: if_icmpne @071
		// @06D: goto @088
		// @070: athrow
		// @071: aload_0
		// @072: getfield game.C_100122_em game.C_100260_mc.field_102243_pc
		// @075: aload_0
		// @076: getfield game.C_100122_em game.C_100260_mc.field_102243_pc
		// @079: getfield boolean game.C_100122_em.field_101861_U
		// @07C: ifne @084
		// @07F: iconst_1
		// @080: goto @085
		// @083: athrow
		// @084: iconst_0
		// @085: putfield boolean game.C_100122_em.field_101861_U
		// @088: aload_0
		// @089: getfield game.C_100302_ka game.C_100260_mc.field_102232_fc
		// @08C: aload_0
		// @08D: getfield int game.C_100260_mc.field_101886_Kb
		// @090: aload_0
		// @091: getfield game.C_100302_ka game.C_100260_mc.field_102232_fc
		// @094: getfield int game.C_100302_ka.field_101841_Pb
		// @097: isub
		// @098: putfield int game.C_100302_ka.field_101886_Kb
		// @09B: iconst_0
		// @09C: istore_3
		// @09D: iload_3
		// @09E: iconst_m1
		// @09F: ixor
		// @0A0: getstatic int game.C_100049_vf.field_104204_n
		// @0A3: iconst_m1
		// @0A4: ixor
		// @0A5: if_icmple @103
		// @0A8: aload_0
		// @0A9: getfield game.C_100302_ka[] game.C_100260_mc.field_102229_hc
		// @0AC: iload_3
		// @0AD: aaload
		// @0AE: iload #4
		// @0B0: ifne @107
		// @0B3: ifnull @0FB
		// @0B6: goto @0BA
		// @0B9: athrow
		// @0BA: aload_0
		// @0BB: getfield game.C_100302_ka[] game.C_100260_mc.field_102229_hc
		// @0BE: iload_3
		// @0BF: aaload
		// @0C0: iconst_m1
		// @0C1: aload_0
		// @0C2: getfield java.lang.StringBuilder game.C_100260_mc.field_102227_Xb
		// @0C5: invokevirtual java.lang.StringBuilder.length()int
		// @0C8: iconst_m1
		// @0C9: ixor
		// @0CA: if_icmple @0D6
		// @0CD: goto @0D1
		// @0D0: athrow
		// @0D1: iconst_1
		// @0D2: goto @0D7
		// @0D5: athrow
		// @0D6: iconst_0
		// @0D7: putfield boolean game.C_100302_ka.field_101864_W
		// @0DA: aload_0
		// @0DB: getfield game.C_100302_ka[] game.C_100260_mc.field_102229_hc
		// @0DE: iload_3
		// @0DF: aaload
		// @0E0: getfield boolean game.C_100302_ka.field_101864_W
		// @0E3: ifeq @0FB
		// @0E6: iconst_m1
		// @0E7: aload_0
		// @0E8: getfield game.C_100302_ka[] game.C_100260_mc.field_102229_hc
		// @0EB: iload_3
		// @0EC: aaload
		// @0ED: getfield int game.C_100302_ka.field_101854_N
		// @0F0: iconst_m1
		// @0F1: ixor
		// @0F2: if_icmpeq @0FB
		// @0F5: goto @0F9
		// @0F8: athrow
		// @0F9: iload_3
		// @0FA: ireturn
		// @0FB: iinc #3 +1
		// @0FE: iload #4
		// @100: ifeq @09D
		// @103: aload_0
		// @104: getfield game.C_100302_ka game.C_100260_mc.field_102240_Vb
		// @107: getfield int game.C_100302_ka.field_101854_N
		// @10A: ifne @111
		// @10D: goto @113
		// @110: athrow
		// @111: iconst_m1
		// @112: ireturn
		// @113: iload_1
		// @114: ifeq @132
		// @117: iconst_m1
		// @118: getstatic int game.C_100102_w.field_104636_c
		// @11B: iconst_m1
		// @11C: ixor
		// @11D: if_icmpeq @132
		// @120: goto @124
		// @123: athrow
		// @124: iconst_0
		// @125: aload_0
		// @126: getfield int game.C_100260_mc.field_101854_N
		// @129: if_icmpne @132
		// @12C: goto @130
		// @12F: athrow
		// @130: iconst_m1
		// @131: ireturn
		// @132: aload_0
		// @133: getfield int game.C_100260_mc.field_102238_oc
		// @136: ireturn
		// @137: astore_3
		// @138: aload_3
		// @139: new java.lang.StringBuilder
		// @13C: dup
		// @13D: invokespecial java.lang.StringBuilder.<init>()void
		// @140: getstatic java.lang.String[] game.C_100260_mc.field_102225_sc
		// @143: iconst_3
		// @144: aaload
		// @145: invokevirtual java.lang.StringBuilder.append(java.lang.String)java.lang.StringBuilder
		// @148: iload_1
		// @149: invokevirtual java.lang.StringBuilder.append(boolean)java.lang.StringBuilder
		// @14C: bipush 44 (0x2C)
		// @14E: invokevirtual java.lang.StringBuilder.append(char)java.lang.StringBuilder
		// @151: iload_2
		// @152: invokevirtual java.lang.StringBuilder.append(int)java.lang.StringBuilder
		// @155: bipush 41 (0x29)
		// @157: invokevirtual java.lang.StringBuilder.append(char)java.lang.StringBuilder
		// @15A: invokevirtual java.lang.StringBuilder.toString()java.lang.String
		// @15D: invokestatic game.C_100181_cf.func_105695_a(java.lang.Throwable, java.lang.String)game.C_100170_cm
		// @160: athrow
	}
	
	static final void func_102222_a(boolean arg0, int arg1)
	{
		// @00: bipush -40 (0xD8)
		// @02: iload_1
		// @03: bipush 17 (0x11)
		// @05: isub
		// @06: bipush 55 (0x37)
		// @08: idiv
		// @09: idiv
		// @0A: istore_2
		// @0B: aconst_null
		// @0C: getstatic game.C_100265_mh game.C_100127_tl.field_104948_b
		// @0F: if_acmpeq @1F
		// @12: getstatic game.C_100265_mh game.C_100127_tl.field_104948_b
		// @15: iload_0
		// @16: bipush 111 (0x6F)
		// @18: invokevirtual game.C_100265_mh.func_106562_c(boolean, byte)void
		// @1B: goto @1F
		// @1E: athrow
		// @1F: aconst_null
		// @20: getstatic game.C_100265_mh game.C_100021_wn.field_103868_f
		// @23: if_acmpne @2A
		// @26: goto @33
		// @29: athrow
		// @2A: getstatic game.C_100265_mh game.C_100021_wn.field_103868_f
		// @2D: iload_0
		// @2E: bipush 107 (0x6B)
		// @30: invokevirtual game.C_100265_mh.func_106562_c(boolean, byte)void
		// @33: getstatic boolean game.C_100125_tm.field_100748_l
		// @36: ifeq @AC
		// @39: getstatic boolean game.C_100174_sb.field_105611_a
		// @3C: ifne @47
		// @3F: goto @43
		// @42: athrow
		// @43: goto @AC
		// @46: athrow
		// @47: getstatic boolean game.C_100192_rf.field_101680_H
		// @4A: ifne @57
		// @4D: getstatic boolean game.C_100205_qf.field_103681_c
		// @50: ifeq @66
		// @53: goto @57
		// @56: athrow
		// @57: getstatic boolean game.C_100230_of.field_106216_k
		// @5A: ifeq @66
		// @5D: goto @61
		// @60: athrow
		// @61: iconst_1
		// @62: goto @67
		// @65: athrow
		// @66: iconst_0
		// @67: istore_3
		// @68: iload_0
		// @69: ifeq @84
		// @6C: iconst_0
		// @6D: invokestatic game.C_100191_rg.func_100842_e(int)boolean
		// @70: ifeq @84
		// @73: goto @77
		// @76: athrow
		// @77: iload_3
		// @78: ifne @84
		// @7B: goto @7F
		// @7E: athrow
		// @7F: iconst_1
		// @80: goto @85
		// @83: athrow
		// @84: iconst_0
		// @85: bipush -108 (0x94)
		// @87: invokestatic game.C_100309_lk.func_103238_a(boolean, byte)void
		// @8A: iload_3
		// @8B: ifne @92
		// @8E: goto @AC
		// @91: athrow
		// @92: iload_0
		// @93: ifeq @A6
		// @96: iconst_0
		// @97: invokestatic game.C_100191_rg.func_100842_e(int)boolean
		// @9A: ifeq @A6
		// @9D: goto @A1
		// @A0: athrow
		// @A1: iconst_1
		// @A2: goto @A7
		// @A5: athrow
		// @A6: iconst_0
		// @A7: bipush 80 (0x50)
		// @A9: invokestatic game.C_100220_ac.func_106051_a(boolean, int)void
		// @AC: goto @DA
		// @AF: astore_2
		// @B0: aload_2
		// @B1: new java.lang.StringBuilder
		// @B4: dup
		// @B5: invokespecial java.lang.StringBuilder.<init>()void
		// @B8: getstatic java.lang.String[] game.C_100260_mc.field_102225_sc
		// @BB: bipush 9 (0x09)
		// @BD: aaload
		// @BE: invokevirtual java.lang.StringBuilder.append(java.lang.String)java.lang.StringBuilder
		// @C1: iload_0
		// @C2: invokevirtual java.lang.StringBuilder.append(boolean)java.lang.StringBuilder
		// @C5: bipush 44 (0x2C)
		// @C7: invokevirtual java.lang.StringBuilder.append(char)java.lang.StringBuilder
		// @CA: iload_1
		// @CB: invokevirtual java.lang.StringBuilder.append(int)java.lang.StringBuilder
		// @CE: bipush 41 (0x29)
		// @D0: invokevirtual java.lang.StringBuilder.append(char)java.lang.StringBuilder
		// @D3: invokevirtual java.lang.StringBuilder.toString()java.lang.String
		// @D6: invokestatic game.C_100181_cf.func_105695_a(java.lang.Throwable, java.lang.String)game.C_100170_cm
		// @D9: athrow
		// @DA: return
	}
	
	public static void func_102215_m(int arg0)
	{
		// @00: aconst_null
		// @01: putstatic java.lang.String game.C_100260_mc.field_102231_rc
		// @04: aconst_null
		// @05: putstatic java.lang.String game.C_100260_mc.field_102237_Ub
		// @08: aconst_null
		// @09: putstatic java.lang.String game.C_100260_mc.field_102247_cc
		// @0C: aconst_null
		// @0D: putstatic java.lang.String[] game.C_100260_mc.field_102223_dc
		// @10: aconst_null
		// @11: putstatic java.lang.String[] game.C_100260_mc.field_102226_Zb
		// @14: aconst_null
		// @15: putstatic java.lang.String game.C_100260_mc.field_102242_kc
		// @18: aconst_null
		// @19: putstatic game.C_100153_be[] game.C_100260_mc.field_102235_Wb
		// @1C: aconst_null
		// @1D: putstatic java.lang.String game.C_100260_mc.field_102244_ac
		// @20: aconst_null
		// @21: putstatic game.C_100037_wb game.C_100260_mc.field_102236_ic
		// @24: iload_0
		// @25: bipush 41 (0x29)
		// @27: if_icmpgt @35
		// @2A: aconst_null
		// @2B: checkcast java.lang.String
		// @2E: putstatic java.lang.String game.C_100260_mc.field_102231_rc
		// @31: goto @35
		// @34: athrow
		// @35: aconst_null
		// @36: putstatic java.lang.String game.C_100260_mc.field_102245_lc
		// @39: goto @5E
		// @3C: astore_1
		// @3D: aload_1
		// @3E: new java.lang.StringBuilder
		// @41: dup
		// @42: invokespecial java.lang.StringBuilder.<init>()void
		// @45: getstatic java.lang.String[] game.C_100260_mc.field_102225_sc
		// @48: bipush 12 (0x0C)
		// @4A: aaload
		// @4B: invokevirtual java.lang.StringBuilder.append(java.lang.String)java.lang.StringBuilder
		// @4E: iload_0
		// @4F: invokevirtual java.lang.StringBuilder.append(int)java.lang.StringBuilder
		// @52: bipush 41 (0x29)
		// @54: invokevirtual java.lang.StringBuilder.append(char)java.lang.StringBuilder
		// @57: invokevirtual java.lang.StringBuilder.toString()java.lang.String
		// @5A: invokestatic game.C_100181_cf.func_105695_a(java.lang.Throwable, java.lang.String)game.C_100170_cm
		// @5D: athrow
		// @5E: return
	}
	
	C_100260_mc(int arg0, int arg1, int arg2, int arg3, int arg4, C_100302_ka arg5, C_100302_ka arg6, C_100302_ka arg7, C_100302_ka arg8, C_100122_em arg9, C_100302_ka arg10, String arg11, long arg12)
	{
		// @000: getstatic int game.SteelSentinels.field_105275_O
		// @003: istore #27
		// @005: aload_0
		// @006: lconst_0
		// @007: aload #6
		// @009: invokespecial game.C_100302_ka.<init>(long, game.C_100302_ka)void
		// @00C: aload_0
		// @00D: bipush -2 (0xFE)
		// @00F: putfield int game.C_100260_mc.field_102238_oc
		// @012: aload_0
		// @013: lload #13
		// @015: putfield long game.C_100260_mc.field_102224_gc
		// @018: aload_0
		// @019: new game.C_100302_ka
		// @01C: dup
		// @01D: lconst_0
		// @01E: aload #7
		// @020: getstatic java.lang.String game.C_100148_bh.field_101805_s
		// @023: invokevirtual java.lang.String.toUpperCase()java.lang.String
		// @026: invokespecial game.C_100302_ka.<init>(long, game.C_100302_ka, java.lang.String)void
		// @029: putfield game.C_100302_ka game.C_100260_mc.field_102233_qc
		// @02C: aload_0
		// @02D: getfield game.C_100302_ka game.C_100260_mc.field_102233_qc
		// @030: iconst_1
		// @031: putfield int game.C_100302_ka.field_101850_Fb
		// @034: aload_0
		// @035: bipush -81 (0xAF)
		// @037: aload_0
		// @038: getfield game.C_100302_ka game.C_100260_mc.field_102233_qc
		// @03B: invokevirtual game.C_100260_mc.func_101824_b(int, game.C_100302_ka)void
		// @03E: aload_0
		// @03F: new game.C_100302_ka
		// @042: dup
		// @043: lconst_0
		// @044: aload #8
		// @046: invokespecial game.C_100302_ka.<init>(long, game.C_100302_ka)void
		// @049: putfield game.C_100302_ka game.C_100260_mc.field_102240_Vb
		// @04C: aload_0
		// @04D: getfield game.C_100302_ka game.C_100260_mc.field_102233_qc
		// @050: bipush -115 (0x8D)
		// @052: aload_0
		// @053: getfield game.C_100302_ka game.C_100260_mc.field_102240_Vb
		// @056: invokevirtual game.C_100302_ka.func_101824_b(int, game.C_100302_ka)void
		// @059: aload_0
		// @05A: new game.C_100302_ka
		// @05D: dup
		// @05E: lconst_0
		// @05F: aconst_null
		// @060: invokespecial game.C_100302_ka.<init>(long, game.C_100302_ka)void
		// @063: putfield game.C_100302_ka game.C_100260_mc.field_102246_bc
		// @066: aload_0
		// @067: bipush -120 (0x88)
		// @069: aload_0
		// @06A: getfield game.C_100302_ka game.C_100260_mc.field_102246_bc
		// @06D: invokevirtual game.C_100260_mc.func_101824_b(int, game.C_100302_ka)void
		// @070: aload #12
		// @072: ifnull @653
		// @075: aload_0
		// @076: new game.C_100302_ka
		// @079: dup
		// @07A: lconst_0
		// @07B: aload #9
		// @07D: getstatic java.lang.String game.C_100123_uc.field_104924_c
		// @080: invokespecial game.C_100302_ka.<init>(long, game.C_100302_ka, java.lang.String)void
		// @083: putfield game.C_100302_ka game.C_100260_mc.field_102241_nc
		// @086: aload_0
		// @087: getfield game.C_100302_ka game.C_100260_mc.field_102241_nc
		// @08A: ldc 11184810 (0xaaaaaa)
		// @08C: putfield int game.C_100302_ka.field_101830_gb
		// @08F: aload_0
		// @090: getfield game.C_100302_ka game.C_100260_mc.field_102241_nc
		// @093: iconst_1
		// @094: putfield int game.C_100302_ka.field_101850_Fb
		// @097: aload_0
		// @098: getfield game.C_100302_ka game.C_100260_mc.field_102246_bc
		// @09B: bipush -89 (0xA7)
		// @09D: aload_0
		// @09E: getfield game.C_100302_ka game.C_100260_mc.field_102241_nc
		// @0A1: invokevirtual game.C_100302_ka.func_101824_b(int, game.C_100302_ka)void
		// @0A4: aload_0
		// @0A5: new game.C_100302_ka
		// @0A8: dup
		// @0A9: lconst_0
		// @0AA: aload #9
		// @0AC: getstatic java.lang.String game.C_100103_eh.field_104663_g
		// @0AF: invokespecial game.C_100302_ka.<init>(long, game.C_100302_ka, java.lang.String)void
		// @0B2: putfield game.C_100302_ka game.C_100260_mc.field_102230_ec
		// @0B5: aload_0
		// @0B6: getfield game.C_100302_ka game.C_100260_mc.field_102230_ec
		// @0B9: iconst_1
		// @0BA: putfield int game.C_100302_ka.field_101850_Fb
		// @0BD: aload_0
		// @0BE: getfield game.C_100302_ka game.C_100260_mc.field_102230_ec
		// @0C1: ldc 11184810 (0xaaaaaa)
		// @0C3: putfield int game.C_100302_ka.field_101830_gb
		// @0C6: aload_0
		// @0C7: getfield game.C_100302_ka game.C_100260_mc.field_102246_bc
		// @0CA: bipush -70 (0xBA)
		// @0CC: aload_0
		// @0CD: getfield game.C_100302_ka game.C_100260_mc.field_102230_ec
		// @0D0: invokevirtual game.C_100302_ka.func_101824_b(int, game.C_100302_ka)void
		// @0D3: aload_0
		// @0D4: new game.C_100302_ka
		// @0D7: dup
		// @0D8: lconst_0
		// @0D9: aload #9
		// @0DB: invokespecial game.C_100302_ka.<init>(long, game.C_100302_ka)void
		// @0DE: putfield game.C_100302_ka game.C_100260_mc.field_102232_fc
		// @0E1: aload_0
		// @0E2: getfield game.C_100302_ka game.C_100260_mc.field_102232_fc
		// @0E5: ldc 16764006 (0xffcc66)
		// @0E7: putfield int game.C_100302_ka.field_101830_gb
		// @0EA: aload_0
		// @0EB: getfield game.C_100302_ka game.C_100260_mc.field_102246_bc
		// @0EE: bipush -87 (0xA9)
		// @0F0: aload_0
		// @0F1: getfield game.C_100302_ka game.C_100260_mc.field_102232_fc
		// @0F4: invokevirtual game.C_100302_ka.func_101824_b(int, game.C_100302_ka)void
		// @0F7: aload_0
		// @0F8: getfield game.C_100302_ka game.C_100260_mc.field_102232_fc
		// @0FB: ldc "|"
		// @0FD: putfield java.lang.String game.C_100302_ka.field_101856_I
		// @100: iconst_5
		// @101: getstatic int game.C_100244_pe.field_106379_a
		// @104: if_icmple @119
		// @107: bipush -3 (0xFD)
		// @109: getstatic int game.C_100107_u.field_104770_g
		// @10C: iconst_m1
		// @10D: ixor
		// @10E: if_icmpge @119
		// @111: goto @115
		// @114: athrow
		// @115: goto @155
		// @118: athrow
		// @119: aload_0
		// @11A: new game.C_100122_em
		// @11D: dup
		// @11E: lconst_0
		// @11F: aload #10
		// @121: bipush -8 (0xF8)
		// @123: getstatic int game.C_100244_pe.field_106379_a
		// @126: iconst_m1
		// @127: ixor
		// @128: if_icmpge @13F
		// @12B: bipush -3 (0xFD)
		// @12D: getstatic int game.C_100107_u.field_104770_g
		// @130: iconst_m1
		// @131: ixor
		// @132: if_icmpge @13F
		// @135: goto @139
		// @138: athrow
		// @139: getstatic java.lang.String game.C_100169_co.field_105524_d
		// @13C: goto @142
		// @13F: getstatic java.lang.String game.C_100327_ib.field_102479_F
		// @142: invokespecial game.C_100122_em.<init>(long, game.C_100122_em, java.lang.String)void
		// @145: putfield game.C_100122_em game.C_100260_mc.field_102243_pc
		// @148: aload_0
		// @149: getfield game.C_100302_ka game.C_100260_mc.field_102246_bc
		// @14C: bipush -89 (0xA7)
		// @14E: aload_0
		// @14F: getfield game.C_100122_em game.C_100260_mc.field_102243_pc
		// @152: invokevirtual game.C_100302_ka.func_101824_b(int, game.C_100302_ka)void
		// @155: iconst_3
		// @156: anewarray game.C_100302_ka
		// @159: astore #15
		// @15B: aload #15
		// @15D: iconst_0
		// @15E: new game.C_100302_ka
		// @161: dup
		// @162: lconst_0
		// @163: aconst_null
		// @164: invokespecial game.C_100302_ka.<init>(long, game.C_100302_ka)void
		// @167: aastore
		// @168: aload_0
		// @169: getfield game.C_100302_ka game.C_100260_mc.field_102246_bc
		// @16C: bipush -72 (0xB8)
		// @16E: aload #15
		// @170: iconst_0
		// @171: aaload
		// @172: invokevirtual game.C_100302_ka.func_101824_b(int, game.C_100302_ka)void
		// @175: aload #15
		// @177: iconst_1
		// @178: new game.C_100302_ka
		// @17B: dup
		// @17C: lconst_0
		// @17D: aconst_null
		// @17E: invokespecial game.C_100302_ka.<init>(long, game.C_100302_ka)void
		// @181: aastore
		// @182: aload_0
		// @183: getfield game.C_100302_ka game.C_100260_mc.field_102246_bc
		// @186: bipush -96 (0xA0)
		// @188: aload #15
		// @18A: iconst_1
		// @18B: aaload
		// @18C: invokevirtual game.C_100302_ka.func_101824_b(int, game.C_100302_ka)void
		// @18F: aload #15
		// @191: iconst_2
		// @192: new game.C_100302_ka
		// @195: dup
		// @196: lconst_0
		// @197: aconst_null
		// @198: invokespecial game.C_100302_ka.<init>(long, game.C_100302_ka)void
		// @19B: aastore
		// @19C: aload_0
		// @19D: getfield game.C_100302_ka game.C_100260_mc.field_102246_bc
		// @1A0: bipush -83 (0xAD)
		// @1A2: aload #15
		// @1A4: iconst_2
		// @1A5: aaload
		// @1A6: invokevirtual game.C_100302_ka.func_101824_b(int, game.C_100302_ka)void
		// @1A9: aload_0
		// @1AA: getstatic int game.C_100049_vf.field_104204_n
		// @1AD: anewarray game.C_100302_ka
		// @1B0: putfield game.C_100302_ka[] game.C_100260_mc.field_102229_hc
		// @1B3: iconst_0
		// @1B4: istore #16
		// @1B6: getstatic int game.C_100049_vf.field_104204_n
		// @1B9: iconst_m1
		// @1BA: ixor
		// @1BB: iload #16
		// @1BD: iconst_m1
		// @1BE: ixor
		// @1BF: if_icmpge @227
		// @1C2: iload #27
		// @1C4: ifne @234
		// @1C7: getstatic java.lang.String[] game.C_100166_sg.field_105467_c
		// @1CA: iload #16
		// @1CC: aaload
		// @1CD: ifnonnull @1D8
		// @1D0: goto @1D4
		// @1D3: athrow
		// @1D4: goto @21F
		// @1D7: athrow
		// @1D8: aload_0
		// @1D9: getfield game.C_100302_ka[] game.C_100260_mc.field_102229_hc
		// @1DC: iload #16
		// @1DE: new game.C_100302_ka
		// @1E1: dup
		// @1E2: lconst_0
		// @1E3: aload #11
		// @1E5: getstatic java.lang.String[] game.C_100166_sg.field_105467_c
		// @1E8: iload #16
		// @1EA: aaload
		// @1EB: invokespecial game.C_100302_ka.<init>(long, game.C_100302_ka, java.lang.String)void
		// @1EE: aastore
		// @1EF: aload_0
		// @1F0: getfield game.C_100302_ka[] game.C_100260_mc.field_102229_hc
		// @1F3: iload #16
		// @1F5: aaload
		// @1F6: iconst_0
		// @1F7: putfield int game.C_100302_ka.field_101850_Fb
		// @1FA: aload_0
		// @1FB: getfield game.C_100302_ka[] game.C_100260_mc.field_102229_hc
		// @1FE: iload #16
		// @200: aaload
		// @201: aload #12
		// @203: ifnull @20B
		// @206: iconst_1
		// @207: goto @20C
		// @20A: athrow
		// @20B: iconst_0
		// @20C: putfield boolean game.C_100302_ka.field_101864_W
		// @20F: aload_0
		// @210: getfield game.C_100302_ka game.C_100260_mc.field_102246_bc
		// @213: bipush -70 (0xBA)
		// @215: aload_0
		// @216: getfield game.C_100302_ka[] game.C_100260_mc.field_102229_hc
		// @219: iload #16
		// @21B: aaload
		// @21C: invokevirtual game.C_100302_ka.func_101824_b(int, game.C_100302_ka)void
		// @21F: iinc #16 +1
		// @222: iload #27
		// @224: ifeq @1B6
		// @227: aload_0
		// @228: new java.lang.StringBuilder
		// @22B: dup
		// @22C: bipush 12 (0x0C)
		// @22E: invokespecial java.lang.StringBuilder.<init>(int)void
		// @231: putfield java.lang.StringBuilder game.C_100260_mc.field_102227_Xb
		// @234: aconst_null
		// @235: aload #12
		// @237: if_acmpne @23E
		// @23A: goto @248
		// @23D: athrow
		// @23E: aload_0
		// @23F: getfield java.lang.StringBuilder game.C_100260_mc.field_102227_Xb
		// @242: aload #12
		// @244: invokevirtual java.lang.StringBuilder.append(java.lang.String)java.lang.StringBuilder
		// @247: pop
		// @248: iconst_0
		// @249: istore #16
		// @24B: aload #7
		// @24D: getfield game.C_100112_r game.C_100302_ka.field_101845_sb
		// @250: getstatic java.lang.String game.C_100091_m.field_104511_f
		// @253: invokevirtual game.C_100112_r.func_101739_b(java.lang.String)int
		// @256: istore #17
		// @258: iload #16
		// @25A: iload #17
		// @25C: if_icmpge @263
		// @25F: iload #17
		// @261: istore #16
		// @263: aload #7
		// @265: getfield game.C_100112_r game.C_100302_ka.field_101845_sb
		// @268: getstatic java.lang.String game.C_100320_hh.field_102917_R
		// @26B: invokevirtual game.C_100112_r.func_101739_b(java.lang.String)int
		// @26E: istore #17
		// @270: iload #17
		// @272: iload #16
		// @274: if_icmpgt @27B
		// @277: goto @27F
		// @27A: athrow
		// @27B: iload #17
		// @27D: istore #16
		// @27F: aload #7
		// @281: getfield game.C_100112_r game.C_100302_ka.field_101845_sb
		// @284: getstatic java.lang.String game.C_100215_ai.field_106012_f
		// @287: invokevirtual game.C_100112_r.func_101739_b(java.lang.String)int
		// @28A: istore #17
		// @28C: iload #17
		// @28E: iload #16
		// @290: if_icmple @297
		// @293: iload #17
		// @295: istore #16
		// @297: iconst_0
		// @298: istore #17
		// @29A: iload #17
		// @29C: getstatic int game.C_100049_vf.field_104204_n
		// @29F: if_icmpge @2DB
		// @2A2: iload #27
		// @2A4: ifne @2EB
		// @2A7: aconst_null
		// @2A8: aload_0
		// @2A9: getfield game.C_100302_ka[] game.C_100260_mc.field_102229_hc
		// @2AC: iload #17
		// @2AE: aaload
		// @2AF: if_acmpeq @2D3
		// @2B2: goto @2B6
		// @2B5: athrow
		// @2B6: aload_0
		// @2B7: getfield game.C_100302_ka[] game.C_100260_mc.field_102229_hc
		// @2BA: iload #17
		// @2BC: aaload
		// @2BD: ldc 218000 (0x35390)
		// @2BF: invokevirtual game.C_100302_ka.func_101818_j(int)int
		// @2C2: istore #18
		// @2C4: iload #16
		// @2C6: iload #18
		// @2C8: if_icmplt @2CF
		// @2CB: goto @2D3
		// @2CE: athrow
		// @2CF: iload #18
		// @2D1: istore #16
		// @2D3: iinc #17 +1
		// @2D6: iload #27
		// @2D8: ifeq @29A
		// @2DB: iload #16
		// @2DD: sipush 140 (0x008C)
		// @2E0: if_icmple @2E8
		// @2E3: sipush 140 (0x008C)
		// @2E6: istore #16
		// @2E8: iconst_0
		// @2E9: istore #17
		// @2EB: iconst_0
		// @2EC: istore #18
		// @2EE: iconst_0
		// @2EF: istore #18
		// @2F1: aload_0
		// @2F2: iload #16
		// @2F4: iconst_0
		// @2F5: aload #7
		// @2F7: iload #18
		// @2F9: aload #15
		// @2FB: iconst_0
		// @2FC: aaload
		// @2FD: getstatic java.lang.String game.C_100091_m.field_104511_f
		// @300: invokespecial game.C_100260_mc.func_102216_a(int, int, game.C_100302_ka, int, game.C_100302_ka, java.lang.String)int
		// @303: istore #18
		// @305: aload_0
		// @306: iload #16
		// @308: iload #18
		// @30A: aload_0
		// @30B: getfield game.C_100302_ka[] game.C_100260_mc.field_102229_hc
		// @30E: bipush 6 (0x06)
		// @310: aaload
		// @311: bipush -119 (0x89)
		// @313: aload #15
		// @315: iconst_0
		// @316: aaload
		// @317: invokespecial game.C_100260_mc.func_102210_a(int, int, game.C_100302_ka, byte, game.C_100302_ka)int
		// @31A: istore #18
		// @31C: aload_0
		// @31D: iload #16
		// @31F: iload #18
		// @321: aload_0
		// @322: getfield game.C_100302_ka[] game.C_100260_mc.field_102229_hc
		// @325: bipush 9 (0x09)
		// @327: aaload
		// @328: bipush -119 (0x89)
		// @32A: aload #15
		// @32C: iconst_0
		// @32D: aaload
		// @32E: invokespecial game.C_100260_mc.func_102210_a(int, int, game.C_100302_ka, byte, game.C_100302_ka)int
		// @331: istore #18
		// @333: aload_0
		// @334: iload #16
		// @336: iload #18
		// @338: aload_0
		// @339: getfield game.C_100302_ka[] game.C_100260_mc.field_102229_hc
		// @33C: iconst_5
		// @33D: aaload
		// @33E: bipush -119 (0x89)
		// @340: aload #15
		// @342: iconst_0
		// @343: aaload
		// @344: invokespecial game.C_100260_mc.func_102210_a(int, int, game.C_100302_ka, byte, game.C_100302_ka)int
		// @347: istore #18
		// @349: aload_0
		// @34A: iload #16
		// @34C: iload #18
		// @34E: aload_0
		// @34F: getfield game.C_100302_ka[] game.C_100260_mc.field_102229_hc
		// @352: bipush 7 (0x07)
		// @354: aaload
		// @355: bipush -119 (0x89)
		// @357: aload #15
		// @359: iconst_0
		// @35A: aaload
		// @35B: invokespecial game.C_100260_mc.func_102210_a(int, int, game.C_100302_ka, byte, game.C_100302_ka)int
		// @35E: istore #18
		// @360: aload_0
		// @361: iload #16
		// @363: iload #18
		// @365: aload_0
		// @366: getfield game.C_100302_ka[] game.C_100260_mc.field_102229_hc
		// @369: bipush 15 (0x0F)
		// @36B: aaload
		// @36C: bipush -119 (0x89)
		// @36E: aload #15
		// @370: iconst_0
		// @371: aaload
		// @372: invokespecial game.C_100260_mc.func_102210_a(int, int, game.C_100302_ka, byte, game.C_100302_ka)int
		// @375: istore #18
		// @377: aload_0
		// @378: iload #16
		// @37A: iload #18
		// @37C: aload_0
		// @37D: getfield game.C_100302_ka[] game.C_100260_mc.field_102229_hc
		// @380: iconst_4
		// @381: aaload
		// @382: bipush -119 (0x89)
		// @384: aload #15
		// @386: iconst_0
		// @387: aaload
		// @388: invokespecial game.C_100260_mc.func_102210_a(int, int, game.C_100302_ka, byte, game.C_100302_ka)int
		// @38B: istore #18
		// @38D: iload #18
		// @38F: iconst_m1
		// @390: ixor
		// @391: iload #17
		// @393: iconst_m1
		// @394: ixor
		// @395: if_icmplt @39C
		// @398: goto @3A0
		// @39B: athrow
		// @39C: iload #18
		// @39E: istore #17
		// @3A0: iconst_0
		// @3A1: istore #18
		// @3A3: aload_0
		// @3A4: iload #16
		// @3A6: iconst_0
		// @3A7: aload #7
		// @3A9: iload #18
		// @3AB: aload #15
		// @3AD: iconst_1
		// @3AE: aaload
		// @3AF: getstatic java.lang.String game.C_100320_hh.field_102917_R
		// @3B2: invokespecial game.C_100260_mc.func_102216_a(int, int, game.C_100302_ka, int, game.C_100302_ka, java.lang.String)int
		// @3B5: istore #18
		// @3B7: aload_0
		// @3B8: iload #16
		// @3BA: iload #18
		// @3BC: aload_0
		// @3BD: getfield game.C_100302_ka[] game.C_100260_mc.field_102229_hc
		// @3C0: bipush 16 (0x10)
		// @3C2: aaload
		// @3C3: bipush -119 (0x89)
		// @3C5: aload #15
		// @3C7: iconst_1
		// @3C8: aaload
		// @3C9: invokespecial game.C_100260_mc.func_102210_a(int, int, game.C_100302_ka, byte, game.C_100302_ka)int
		// @3CC: istore #18
		// @3CE: aload_0
		// @3CF: iload #16
		// @3D1: iload #18
		// @3D3: aload_0
		// @3D4: getfield game.C_100302_ka[] game.C_100260_mc.field_102229_hc
		// @3D7: bipush 17 (0x11)
		// @3D9: aaload
		// @3DA: bipush -119 (0x89)
		// @3DC: aload #15
		// @3DE: iconst_1
		// @3DF: aaload
		// @3E0: invokespecial game.C_100260_mc.func_102210_a(int, int, game.C_100302_ka, byte, game.C_100302_ka)int
		// @3E3: istore #18
		// @3E5: aload_0
		// @3E6: iload #16
		// @3E8: iload #18
		// @3EA: aload_0
		// @3EB: getfield game.C_100302_ka[] game.C_100260_mc.field_102229_hc
		// @3EE: bipush 18 (0x12)
		// @3F0: aaload
		// @3F1: bipush -119 (0x89)
		// @3F3: aload #15
		// @3F5: iconst_1
		// @3F6: aaload
		// @3F7: invokespecial game.C_100260_mc.func_102210_a(int, int, game.C_100302_ka, byte, game.C_100302_ka)int
		// @3FA: istore #18
		// @3FC: aload_0
		// @3FD: iload #16
		// @3FF: iload #18
		// @401: aload_0
		// @402: getfield game.C_100302_ka[] game.C_100260_mc.field_102229_hc
		// @405: bipush 19 (0x13)
		// @407: aaload
		// @408: bipush -119 (0x89)
		// @40A: aload #15
		// @40C: iconst_1
		// @40D: aaload
		// @40E: invokespecial game.C_100260_mc.func_102210_a(int, int, game.C_100302_ka, byte, game.C_100302_ka)int
		// @411: istore #18
		// @413: aload_0
		// @414: iload #16
		// @416: iload #18
		// @418: aload_0
		// @419: getfield game.C_100302_ka[] game.C_100260_mc.field_102229_hc
		// @41C: bipush 20 (0x14)
		// @41E: aaload
		// @41F: bipush -119 (0x89)
		// @421: aload #15
		// @423: iconst_1
		// @424: aaload
		// @425: invokespecial game.C_100260_mc.func_102210_a(int, int, game.C_100302_ka, byte, game.C_100302_ka)int
		// @428: istore #18
		// @42A: iload #17
		// @42C: iconst_m1
		// @42D: ixor
		// @42E: iload #18
		// @430: iconst_m1
		// @431: ixor
		// @432: if_icmpgt @439
		// @435: goto @43D
		// @438: athrow
		// @439: iload #18
		// @43B: istore #17
		// @43D: iconst_0
		// @43E: istore #18
		// @440: aload_0
		// @441: iload #16
		// @443: iconst_0
		// @444: aload #7
		// @446: iload #18
		// @448: aload #15
		// @44A: iconst_2
		// @44B: aaload
		// @44C: getstatic java.lang.String game.C_100215_ai.field_106012_f
		// @44F: invokespecial game.C_100260_mc.func_102216_a(int, int, game.C_100302_ka, int, game.C_100302_ka, java.lang.String)int
		// @452: istore #18
		// @454: aload_0
		// @455: iload #16
		// @457: iload #18
		// @459: aload_0
		// @45A: getfield game.C_100302_ka[] game.C_100260_mc.field_102229_hc
		// @45D: bipush 13 (0x0D)
		// @45F: aaload
		// @460: bipush -119 (0x89)
		// @462: aload #15
		// @464: iconst_2
		// @465: aaload
		// @466: invokespecial game.C_100260_mc.func_102210_a(int, int, game.C_100302_ka, byte, game.C_100302_ka)int
		// @469: istore #18
		// @46B: aload_0
		// @46C: iload #16
		// @46E: iload #18
		// @470: aload_0
		// @471: getfield game.C_100302_ka[] game.C_100260_mc.field_102229_hc
		// @474: bipush 21 (0x15)
		// @476: aaload
		// @477: bipush -119 (0x89)
		// @479: aload #15
		// @47B: iconst_2
		// @47C: aaload
		// @47D: invokespecial game.C_100260_mc.func_102210_a(int, int, game.C_100302_ka, byte, game.C_100302_ka)int
		// @480: istore #18
		// @482: aload_0
		// @483: iload #16
		// @485: iload #18
		// @487: aload_0
		// @488: getfield game.C_100302_ka[] game.C_100260_mc.field_102229_hc
		// @48B: bipush 11 (0x0B)
		// @48D: aaload
		// @48E: bipush -119 (0x89)
		// @490: aload #15
		// @492: iconst_2
		// @493: aaload
		// @494: invokespecial game.C_100260_mc.func_102210_a(int, int, game.C_100302_ka, byte, game.C_100302_ka)int
		// @497: istore #18
		// @499: iload #18
		// @49B: iload #17
		// @49D: if_icmple @4A4
		// @4A0: iload #18
		// @4A2: istore #17
		// @4A4: bipush 26 (0x1A)
		// @4A6: iconst_3
		// @4A7: iload #16
		// @4A9: imul
		// @4AA: iadd
		// @4AB: istore #19
		// @4AD: aload_0
		// @4AE: getfield game.C_100302_ka game.C_100260_mc.field_102233_qc
		// @4B1: ldc 218000 (0x35390)
		// @4B3: invokevirtual game.C_100302_ka.func_101818_j(int)int
		// @4B6: istore #20
		// @4B8: iload #20
		// @4BA: iconst_m1
		// @4BB: ixor
		// @4BC: iload #19
		// @4BE: iconst_m1
		// @4BF: ixor
		// @4C0: if_icmpge @4C7
		// @4C3: iload #20
		// @4C5: istore #19
		// @4C7: aload_0
		// @4C8: getfield game.C_100122_em game.C_100260_mc.field_102243_pc
		// @4CB: ifnull @4E5
		// @4CE: aload_0
		// @4CF: getfield game.C_100122_em game.C_100260_mc.field_102243_pc
		// @4D2: iconst_4
		// @4D3: bipush 8 (0x08)
		// @4D5: invokevirtual game.C_100122_em.func_102068_a(int, int)int
		// @4D8: istore #20
		// @4DA: iload #19
		// @4DC: iload #20
		// @4DE: if_icmpge @4E5
		// @4E1: iload #20
		// @4E3: istore #19
		// @4E5: aload_0
		// @4E6: getfield game.C_100302_ka game.C_100260_mc.field_102233_qc
		// @4E9: iconst_0
		// @4EA: bipush 24 (0x18)
		// @4EC: iconst_m1
		// @4ED: iconst_0
		// @4EE: bipush 26 (0x1A)
		// @4F0: iload #19
		// @4F2: iadd
		// @4F3: invokevirtual game.C_100302_ka.func_101825_a(int, int, int, int, int)void
		// @4F6: aload_0
		// @4F7: getfield game.C_100302_ka game.C_100260_mc.field_102240_Vb
		// @4FA: bipush -20 (0xEC)
		// @4FC: aload_0
		// @4FD: getfield game.C_100302_ka game.C_100260_mc.field_102233_qc
		// @500: getfield int game.C_100302_ka.field_101886_Kb
		// @503: iadd
		// @504: bipush 15 (0x0F)
		// @506: iconst_m1
		// @507: iconst_5
		// @508: bipush 15 (0x0F)
		// @50A: invokevirtual game.C_100302_ka.func_101825_a(int, int, int, int, int)void
		// @50D: bipush 10 (0x0A)
		// @50F: istore #21
		// @511: aload_0
		// @512: getfield game.C_100302_ka game.C_100260_mc.field_102241_nc
		// @515: bipush 13 (0x0D)
		// @517: iconst_2
		// @518: getstatic int game.C_100033_gj.field_101917_jc
		// @51B: imul
		// @51C: iconst_m1
		// @51D: iload #21
		// @51F: iload #19
		// @521: invokevirtual game.C_100302_ka.func_101825_a(int, int, int, int, int)void
		// @524: iload #21
		// @526: getstatic int game.C_100033_gj.field_101917_jc
		// @529: iconst_2
		// @52A: imul
		// @52B: iadd
		// @52C: istore #21
		// @52E: aload_0
		// @52F: getfield game.C_100302_ka game.C_100260_mc.field_102230_ec
		// @532: bipush 13 (0x0D)
		// @534: iconst_2
		// @535: getstatic int game.C_100033_gj.field_101917_jc
		// @538: imul
		// @539: iconst_m1
		// @53A: iload #21
		// @53C: iload #19
		// @53E: invokevirtual game.C_100302_ka.func_101825_a(int, int, int, int, int)void
		// @541: iload #21
		// @543: iconst_2
		// @544: getstatic int game.C_100033_gj.field_101917_jc
		// @547: imul
		// @548: bipush -10 (0xF6)
		// @54A: isub
		// @54B: iadd
		// @54C: istore #21
		// @54E: aload_0
		// @54F: getfield game.C_100302_ka game.C_100260_mc.field_102232_fc
		// @552: iconst_0
		// @553: getstatic int game.C_100033_gj.field_101917_jc
		// @556: iconst_m1
		// @557: iload #21
		// @559: iconst_0
		// @55A: invokevirtual game.C_100302_ka.func_101825_a(int, int, int, int, int)void
		// @55D: iload #21
		// @55F: bipush 10 (0x0A)
		// @561: getstatic int game.C_100033_gj.field_101917_jc
		// @564: iadd
		// @565: iadd
		// @566: istore #21
		// @568: aconst_null
		// @569: aload_0
		// @56A: getfield game.C_100122_em game.C_100260_mc.field_102243_pc
		// @56D: if_acmpeq @5A3
		// @570: aload_0
		// @571: getfield game.C_100122_em game.C_100260_mc.field_102243_pc
		// @574: iconst_4
		// @575: bipush 8 (0x08)
		// @577: invokevirtual game.C_100122_em.func_102068_a(int, int)int
		// @57A: istore #20
		// @57C: aload_0
		// @57D: getfield game.C_100122_em game.C_100260_mc.field_102243_pc
		// @580: iload #21
		// @582: bipush 81 (0x51)
		// @584: iconst_4
		// @585: iload #20
		// @587: getstatic int game.C_100033_gj.field_101917_jc
		// @58A: bipush 13 (0x0D)
		// @58C: iload #19
		// @58E: iload #20
		// @590: ineg
		// @591: iadd
		// @592: iconst_2
		// @593: idiv
		// @594: iadd
		// @595: invokevirtual game.C_100122_em.func_102065_a(int, int, int, int, int, int)void
		// @598: iload #21
		// @59A: bipush 10 (0x0A)
		// @59C: getstatic int game.C_100033_gj.field_101917_jc
		// @59F: iadd
		// @5A0: iadd
		// @5A1: istore #21
		// @5A3: aload #15
		// @5A5: iconst_0
		// @5A6: aaload
		// @5A7: bipush 13 (0x0D)
		// @5A9: iload #17
		// @5AB: iconst_m1
		// @5AC: iload #21
		// @5AE: iload #16
		// @5B0: invokevirtual game.C_100302_ka.func_101825_a(int, int, int, int, int)void
		// @5B3: aload #15
		// @5B5: iconst_1
		// @5B6: aaload
		// @5B7: iload #16
		// @5B9: bipush 13 (0x0D)
		// @5BB: iadd
		// @5BC: bipush 13 (0x0D)
		// @5BE: iadd
		// @5BF: iload #17
		// @5C1: iconst_m1
		// @5C2: iload #21
		// @5C4: iload #16
		// @5C6: invokevirtual game.C_100302_ka.func_101825_a(int, int, int, int, int)void
		// @5C9: aload #15
		// @5CB: iconst_2
		// @5CC: aaload
		// @5CD: iload #16
		// @5CF: iconst_2
		// @5D0: imul
		// @5D1: bipush 39 (0x27)
		// @5D3: iadd
		// @5D4: iload #17
		// @5D6: iconst_m1
		// @5D7: iload #21
		// @5D9: iload #16
		// @5DB: invokevirtual game.C_100302_ka.func_101825_a(int, int, int, int, int)void
		// @5DE: iload #21
		// @5E0: istore #22
		// @5E2: aload_0
		// @5E3: getfield game.C_100302_ka game.C_100260_mc.field_102246_bc
		// @5E6: iconst_0
		// @5E7: iload #22
		// @5E9: iload #17
		// @5EB: bipush -10 (0xF6)
		// @5ED: isub
		// @5EE: iadd
		// @5EF: iconst_m1
		// @5F0: bipush 24 (0x18)
		// @5F2: bipush 26 (0x1A)
		// @5F4: iload #19
		// @5F6: ineg
		// @5F7: isub
		// @5F8: invokevirtual game.C_100302_ka.func_101825_a(int, int, int, int, int)void
		// @5FB: aload_0
		// @5FC: getfield game.C_100302_ka game.C_100260_mc.field_102246_bc
		// @5FF: ldc 11579568 (0xb0b0b0)
		// @601: iconst_1
		// @602: ldc 8421504 (0x808080)
		// @604: iconst_3
		// @605: ldc 2105376 (0x202020)
		// @607: aload_0
		// @608: getfield game.C_100302_ka game.C_100260_mc.field_102246_bc
		// @60B: getfield int game.C_100302_ka.field_101848_lb
		// @60E: invokestatic game.C_100265_mh.func_106563_a(int, boolean, int, int, int, int)game.C_100037_wb[]
		// @611: putfield game.C_100037_wb[] game.C_100302_ka.field_101862_T
		// @614: bipush 26 (0x1A)
		// @616: iload #19
		// @618: ineg
		// @619: isub
		// @61A: istore #23
		// @61C: iload #17
		// @61E: bipush 24 (0x18)
		// @620: iadd
		// @621: iload #22
		// @623: ineg
		// @624: bipush 10 (0x0A)
		// @626: isub
		// @627: isub
		// @628: istore #24
		// @62A: iload_3
		// @62B: iload_1
		// @62C: iload #23
		// @62E: iconst_m1
		// @62F: invokestatic game.C_100211_qd.func_102123_a(int, int, int, int)int
		// @632: istore #25
		// @634: iload #4
		// @636: iload #24
		// @638: sipush -19295 (0xB4A1)
		// @63B: iload_2
		// @63C: invokestatic game.C_100257_ln.func_106471_a(int, int, int, int)int
		// @63F: istore #26
		// @641: aload_0
		// @642: iload #25
		// @644: iload #24
		// @646: iconst_m1
		// @647: iload #26
		// @649: iload #23
		// @64B: invokevirtual game.C_100260_mc.func_101825_a(int, int, int, int, int)void
		// @64E: iload #27
		// @650: ifeq @726
		// @653: aload_0
		// @654: new game.C_100302_ka
		// @657: dup
		// @658: lconst_0
		// @659: aload #9
		// @65B: getstatic java.lang.String game.C_100306_kn.field_107138_m
		// @65E: invokespecial game.C_100302_ka.<init>(long, game.C_100302_ka, java.lang.String)void
		// @661: putfield game.C_100302_ka game.C_100260_mc.field_102241_nc
		// @664: aload_0
		// @665: getfield game.C_100302_ka game.C_100260_mc.field_102241_nc
		// @668: iconst_1
		// @669: putfield int game.C_100302_ka.field_101850_Fb
		// @66C: aload_0
		// @66D: getfield game.C_100302_ka game.C_100260_mc.field_102241_nc
		// @670: ldc 11184810 (0xaaaaaa)
		// @672: putfield int game.C_100302_ka.field_101830_gb
		// @675: aload_0
		// @676: getfield game.C_100302_ka game.C_100260_mc.field_102246_bc
		// @679: bipush -72 (0xB8)
		// @67B: aload_0
		// @67C: getfield game.C_100302_ka game.C_100260_mc.field_102241_nc
		// @67F: invokevirtual game.C_100302_ka.func_101824_b(int, game.C_100302_ka)void
		// @682: sipush 226 (0x00E2)
		// @685: istore #15
		// @687: bipush 10 (0x0A)
		// @689: istore #16
		// @68B: aload_0
		// @68C: getfield game.C_100302_ka game.C_100260_mc.field_102241_nc
		// @68F: getfield game.C_100112_r game.C_100302_ka.field_101845_sb
		// @692: aload_0
		// @693: getfield game.C_100302_ka game.C_100260_mc.field_102241_nc
		// @696: getfield java.lang.String game.C_100302_ka.field_101890_ab
		// @699: iload #15
		// @69B: invokevirtual game.C_100112_r.func_101724_c(java.lang.String, int)int
		// @69E: istore #17
		// @6A0: aload_0
		// @6A1: getfield game.C_100302_ka game.C_100260_mc.field_102241_nc
		// @6A4: bipush 13 (0x0D)
		// @6A6: iload #17
		// @6A8: getstatic int game.C_100033_gj.field_101917_jc
		// @6AB: imul
		// @6AC: iconst_m1
		// @6AD: iload #16
		// @6AF: iload #15
		// @6B1: invokevirtual game.C_100302_ka.func_101825_a(int, int, int, int, int)void
		// @6B4: iload #16
		// @6B6: iload #17
		// @6B8: getstatic int game.C_100033_gj.field_101917_jc
		// @6BB: imul
		// @6BC: iadd
		// @6BD: istore #16
		// @6BF: aload_0
		// @6C0: getfield game.C_100302_ka game.C_100260_mc.field_102246_bc
		// @6C3: iconst_0
		// @6C4: bipush 10 (0x0A)
		// @6C6: iload #16
		// @6C8: iadd
		// @6C9: iconst_m1
		// @6CA: bipush 24 (0x18)
		// @6CC: bipush 13 (0x0D)
		// @6CE: bipush 13 (0x0D)
		// @6D0: iload #15
		// @6D2: iadd
		// @6D3: iadd
		// @6D4: invokevirtual game.C_100302_ka.func_101825_a(int, int, int, int, int)void
		// @6D7: aload_0
		// @6D8: getfield game.C_100302_ka game.C_100260_mc.field_102246_bc
		// @6DB: ldc 11579568 (0xb0b0b0)
		// @6DD: iconst_1
		// @6DE: ldc 8421504 (0x808080)
		// @6E0: iconst_3
		// @6E1: ldc 2105376 (0x202020)
		// @6E3: aload_0
		// @6E4: getfield game.C_100302_ka game.C_100260_mc.field_102246_bc
		// @6E7: getfield int game.C_100302_ka.field_101848_lb
		// @6EA: invokestatic game.C_100265_mh.func_106563_a(int, boolean, int, int, int, int)game.C_100037_wb[]
		// @6ED: putfield game.C_100037_wb[] game.C_100302_ka.field_101862_T
		// @6F0: bipush 13 (0x0D)
		// @6F2: iload #15
		// @6F4: ineg
		// @6F5: bipush 13 (0x0D)
		// @6F7: isub
		// @6F8: isub
		// @6F9: istore #18
		// @6FB: iload #16
		// @6FD: bipush 34 (0x22)
		// @6FF: iadd
		// @700: istore #19
		// @702: iload_3
		// @703: iload_1
		// @704: iload #18
		// @706: iconst_m1
		// @707: invokestatic game.C_100211_qd.func_102123_a(int, int, int, int)int
		// @70A: istore #20
		// @70C: iload #4
		// @70E: iload #19
		// @710: sipush -19295 (0xB4A1)
		// @713: iload_2
		// @714: invokestatic game.C_100257_ln.func_106471_a(int, int, int, int)int
		// @717: istore #21
		// @719: aload_0
		// @71A: iload #20
		// @71C: iload #19
		// @71E: iconst_m1
		// @71F: iload #21
		// @721: iload #18
		// @723: invokevirtual game.C_100260_mc.func_101825_a(int, int, int, int, int)void
		// @726: goto @83A
		// @729: astore #15
		// @72B: aload #15
		// @72D: new java.lang.StringBuilder
		// @730: dup
		// @731: invokespecial java.lang.StringBuilder.<init>()void
		// @734: getstatic java.lang.String[] game.C_100260_mc.field_102225_sc
		// @737: bipush 13 (0x0D)
		// @739: aaload
		// @73A: invokevirtual java.lang.StringBuilder.append(java.lang.String)java.lang.StringBuilder
		// @73D: iload_1
		// @73E: invokevirtual java.lang.StringBuilder.append(int)java.lang.StringBuilder
		// @741: bipush 44 (0x2C)
		// @743: invokevirtual java.lang.StringBuilder.append(char)java.lang.StringBuilder
		// @746: iload_2
		// @747: invokevirtual java.lang.StringBuilder.append(int)java.lang.StringBuilder
		// @74A: bipush 44 (0x2C)
		// @74C: invokevirtual java.lang.StringBuilder.append(char)java.lang.StringBuilder
		// @74F: iload_3
		// @750: invokevirtual java.lang.StringBuilder.append(int)java.lang.StringBuilder
		// @753: bipush 44 (0x2C)
		// @755: invokevirtual java.lang.StringBuilder.append(char)java.lang.StringBuilder
		// @758: iload #4
		// @75A: invokevirtual java.lang.StringBuilder.append(int)java.lang.StringBuilder
		// @75D: bipush 44 (0x2C)
		// @75F: invokevirtual java.lang.StringBuilder.append(char)java.lang.StringBuilder
		// @762: iload #5
		// @764: invokevirtual java.lang.StringBuilder.append(int)java.lang.StringBuilder
		// @767: bipush 44 (0x2C)
		// @769: invokevirtual java.lang.StringBuilder.append(char)java.lang.StringBuilder
		// @76C: aload #6
		// @76E: ifnull @77A
		// @771: getstatic java.lang.String[] game.C_100260_mc.field_102225_sc
		// @774: iconst_1
		// @775: aaload
		// @776: goto @77F
		// @779: athrow
		// @77A: getstatic java.lang.String[] game.C_100260_mc.field_102225_sc
		// @77D: iconst_0
		// @77E: aaload
		// @77F: invokevirtual java.lang.StringBuilder.append(java.lang.String)java.lang.StringBuilder
		// @782: bipush 44 (0x2C)
		// @784: invokevirtual java.lang.StringBuilder.append(char)java.lang.StringBuilder
		// @787: aload #7
		// @789: ifnull @795
		// @78C: getstatic java.lang.String[] game.C_100260_mc.field_102225_sc
		// @78F: iconst_1
		// @790: aaload
		// @791: goto @79A
		// @794: athrow
		// @795: getstatic java.lang.String[] game.C_100260_mc.field_102225_sc
		// @798: iconst_0
		// @799: aaload
		// @79A: invokevirtual java.lang.StringBuilder.append(java.lang.String)java.lang.StringBuilder
		// @79D: bipush 44 (0x2C)
		// @79F: invokevirtual java.lang.StringBuilder.append(char)java.lang.StringBuilder
		// @7A2: aload #8
		// @7A4: ifnull @7B0
		// @7A7: getstatic java.lang.String[] game.C_100260_mc.field_102225_sc
		// @7AA: iconst_1
		// @7AB: aaload
		// @7AC: goto @7B5
		// @7AF: athrow
		// @7B0: getstatic java.lang.String[] game.C_100260_mc.field_102225_sc
		// @7B3: iconst_0
		// @7B4: aaload
		// @7B5: invokevirtual java.lang.StringBuilder.append(java.lang.String)java.lang.StringBuilder
		// @7B8: bipush 44 (0x2C)
		// @7BA: invokevirtual java.lang.StringBuilder.append(char)java.lang.StringBuilder
		// @7BD: aload #9
		// @7BF: ifnull @7CB
		// @7C2: getstatic java.lang.String[] game.C_100260_mc.field_102225_sc
		// @7C5: iconst_1
		// @7C6: aaload
		// @7C7: goto @7D0
		// @7CA: athrow
		// @7CB: getstatic java.lang.String[] game.C_100260_mc.field_102225_sc
		// @7CE: iconst_0
		// @7CF: aaload
		// @7D0: invokevirtual java.lang.StringBuilder.append(java.lang.String)java.lang.StringBuilder
		// @7D3: bipush 44 (0x2C)
		// @7D5: invokevirtual java.lang.StringBuilder.append(char)java.lang.StringBuilder
		// @7D8: aload #10
		// @7DA: ifnull @7E6
		// @7DD: getstatic java.lang.String[] game.C_100260_mc.field_102225_sc
		// @7E0: iconst_1
		// @7E1: aaload
		// @7E2: goto @7EB
		// @7E5: athrow
		// @7E6: getstatic java.lang.String[] game.C_100260_mc.field_102225_sc
		// @7E9: iconst_0
		// @7EA: aaload
		// @7EB: invokevirtual java.lang.StringBuilder.append(java.lang.String)java.lang.StringBuilder
		// @7EE: bipush 44 (0x2C)
		// @7F0: invokevirtual java.lang.StringBuilder.append(char)java.lang.StringBuilder
		// @7F3: aload #11
		// @7F5: ifnull @801
		// @7F8: getstatic java.lang.String[] game.C_100260_mc.field_102225_sc
		// @7FB: iconst_1
		// @7FC: aaload
		// @7FD: goto @806
		// @800: athrow
		// @801: getstatic java.lang.String[] game.C_100260_mc.field_102225_sc
		// @804: iconst_0
		// @805: aaload
		// @806: invokevirtual java.lang.StringBuilder.append(java.lang.String)java.lang.StringBuilder
		// @809: bipush 44 (0x2C)
		// @80B: invokevirtual java.lang.StringBuilder.append(char)java.lang.StringBuilder
		// @80E: aload #12
		// @810: ifnull @81C
		// @813: getstatic java.lang.String[] game.C_100260_mc.field_102225_sc
		// @816: iconst_1
		// @817: aaload
		// @818: goto @821
		// @81B: athrow
		// @81C: getstatic java.lang.String[] game.C_100260_mc.field_102225_sc
		// @81F: iconst_0
		// @820: aaload
		// @821: invokevirtual java.lang.StringBuilder.append(java.lang.String)java.lang.StringBuilder
		// @824: bipush 44 (0x2C)
		// @826: invokevirtual java.lang.StringBuilder.append(char)java.lang.StringBuilder
		// @829: lload #13
		// @82B: invokevirtual java.lang.StringBuilder.append(long)java.lang.StringBuilder
		// @82E: bipush 41 (0x29)
		// @830: invokevirtual java.lang.StringBuilder.append(char)java.lang.StringBuilder
		// @833: invokevirtual java.lang.StringBuilder.toString()java.lang.String
		// @836: invokestatic game.C_100181_cf.func_105695_a(java.lang.Throwable, java.lang.String)game.C_100170_cm
		// @839: athrow
		// @83A: return
	}
	
	static final int[] func_102219_a(C_100327_ib arg0, int[] arg1, byte arg2)
	{
		// @00: getstatic int game.SteelSentinels.field_105275_O
		// @03: istore #8
		// @05: iconst_0
		// @06: istore_3
		// @07: sipush 1000 (0x03E8)
		// @0A: newarray int[]
		// @0C: astore #4
		// @0E: aload_0
		// @0F: iconst_m1
		// @10: iload_3
		// @11: aload #4
		// @13: invokevirtual game.C_100327_ib.func_102458_a(int, int, int[])int
		// @16: istore_3
		// @17: aload_0
		// @18: iload_2
		// @19: sipush 3174 (0x0C66)
		// @1C: ixor
		// @1D: invokevirtual game.C_100327_ib.func_102460_q(int)int
		// @20: istore #5
		// @22: iconst_0
		// @23: istore #6
		// @25: bipush -9 (0xF7)
		// @27: iload #6
		// @29: iconst_m1
		// @2A: ixor
		// @2B: if_icmpge @5A
		// @2E: aload #4
		// @30: iload #8
		// @32: ifne @68
		// @35: iload_3
		// @36: iinc #3 +1
		// @39: iload #5
		// @3B: iconst_m1
		// @3C: ixor
		// @3D: iload #6
		// @3F: iconst_m1
		// @40: ixor
		// @41: if_icmplt @4D
		// @44: goto @48
		// @47: athrow
		// @48: iconst_m1
		// @49: goto @51
		// @4C: athrow
		// @4D: aload_1
		// @4E: iload #6
		// @50: iaload
		// @51: iastore
		// @52: iinc #6 +1
		// @55: iload #8
		// @57: ifeq @25
		// @5A: iload_2
		// @5B: bipush -125 (0x83)
		// @5D: if_icmpeq @65
		// @60: aconst_null
		// @61: checkcast int[]
		// @64: areturn
		// @65: iload_3
		// @66: newarray int[]
		// @68: astore #6
		// @6A: iconst_0
		// @6B: istore #7
		// @6D: iload_3
		// @6E: iload #7
		// @70: if_icmple @8E
		// @73: aload #6
		// @75: iload #8
		// @77: ifne @90
		// @7A: iload #7
		// @7C: aload #4
		// @7E: iload #7
		// @80: iaload
		// @81: iastore
		// @82: iinc #7 +1
		// @85: iload #8
		// @87: ifeq @6D
		// @8A: goto @8E
		// @8D: athrow
		// @8E: aload #6
		// @90: areturn
		// @91: astore_3
		// @92: aload_3
		// @93: new java.lang.StringBuilder
		// @96: dup
		// @97: invokespecial java.lang.StringBuilder.<init>()void
		// @9A: getstatic java.lang.String[] game.C_100260_mc.field_102225_sc
		// @9D: iconst_2
		// @9E: aaload
		// @9F: invokevirtual java.lang.StringBuilder.append(java.lang.String)java.lang.StringBuilder
		// @A2: aload_0
		// @A3: ifnull @AF
		// @A6: getstatic java.lang.String[] game.C_100260_mc.field_102225_sc
		// @A9: iconst_1
		// @AA: aaload
		// @AB: goto @B4
		// @AE: athrow
		// @AF: getstatic java.lang.String[] game.C_100260_mc.field_102225_sc
		// @B2: iconst_0
		// @B3: aaload
		// @B4: invokevirtual java.lang.StringBuilder.append(java.lang.String)java.lang.StringBuilder
		// @B7: bipush 44 (0x2C)
		// @B9: invokevirtual java.lang.StringBuilder.append(char)java.lang.StringBuilder
		// @BC: aload_1
		// @BD: ifnull @C9
		// @C0: getstatic java.lang.String[] game.C_100260_mc.field_102225_sc
		// @C3: iconst_1
		// @C4: aaload
		// @C5: goto @CE
		// @C8: athrow
		// @C9: getstatic java.lang.String[] game.C_100260_mc.field_102225_sc
		// @CC: iconst_0
		// @CD: aaload
		// @CE: invokevirtual java.lang.StringBuilder.append(java.lang.String)java.lang.StringBuilder
		// @D1: bipush 44 (0x2C)
		// @D3: invokevirtual java.lang.StringBuilder.append(char)java.lang.StringBuilder
		// @D6: iload_2
		// @D7: invokevirtual java.lang.StringBuilder.append(int)java.lang.StringBuilder
		// @DA: bipush 41 (0x29)
		// @DC: invokevirtual java.lang.StringBuilder.append(char)java.lang.StringBuilder
		// @DF: invokevirtual java.lang.StringBuilder.toString()java.lang.String
		// @E2: invokestatic game.C_100181_cf.func_105695_a(java.lang.Throwable, java.lang.String)game.C_100170_cm
		// @E5: athrow
	}
	
	final String func_102220_o(int arg0)
	{
		// @00: iload_1
		// @01: iconst_m1
		// @02: if_icmpeq @11
		// @05: aload_0
		// @06: aconst_null
		// @07: checkcast game.C_100302_ka
		// @0A: putfield game.C_100302_ka game.C_100260_mc.field_102241_nc
		// @0D: goto @11
		// @10: athrow
		// @11: aload_0
		// @12: getfield java.lang.StringBuilder game.C_100260_mc.field_102227_Xb
		// @15: invokevirtual java.lang.StringBuilder.toString()java.lang.String
		// @18: areturn
		// @19: astore_2
		// @1A: aload_2
		// @1B: new java.lang.StringBuilder
		// @1E: dup
		// @1F: invokespecial java.lang.StringBuilder.<init>()void
		// @22: getstatic java.lang.String[] game.C_100260_mc.field_102225_sc
		// @25: bipush 8 (0x08)
		// @27: aaload
		// @28: invokevirtual java.lang.StringBuilder.append(java.lang.String)java.lang.StringBuilder
		// @2B: iload_1
		// @2C: invokevirtual java.lang.StringBuilder.append(int)java.lang.StringBuilder
		// @2F: bipush 41 (0x29)
		// @31: invokevirtual java.lang.StringBuilder.append(char)java.lang.StringBuilder
		// @34: invokevirtual java.lang.StringBuilder.toString()java.lang.String
		// @37: invokestatic game.C_100181_cf.func_105695_a(java.lang.Throwable, java.lang.String)game.C_100170_cm
		// @3A: athrow
	}
	
	static final boolean func_102218_n(int arg0)
	{
		// @00: iload_0
		// @01: bipush -88 (0xA8)
		// @03: if_icmpeq @0F
		// @06: bipush -75 (0xB5)
		// @08: putstatic int game.C_100260_mc.field_102234_jc
		// @0B: goto @0F
		// @0E: athrow
		// @0F: getstatic boolean game.C_100186_rl.field_105720_f
		// @12: ireturn
		// @13: astore_1
		// @14: aload_1
		// @15: new java.lang.StringBuilder
		// @18: dup
		// @19: invokespecial java.lang.StringBuilder.<init>()void
		// @1C: getstatic java.lang.String[] game.C_100260_mc.field_102225_sc
		// @1F: bipush 10 (0x0A)
		// @21: aaload
		// @22: invokevirtual java.lang.StringBuilder.append(java.lang.String)java.lang.StringBuilder
		// @25: iload_0
		// @26: invokevirtual java.lang.StringBuilder.append(int)java.lang.StringBuilder
		// @29: bipush 41 (0x29)
		// @2B: invokevirtual java.lang.StringBuilder.append(char)java.lang.StringBuilder
		// @2E: invokevirtual java.lang.StringBuilder.toString()java.lang.String
		// @31: invokestatic game.C_100181_cf.func_105695_a(java.lang.Throwable, java.lang.String)game.C_100170_cm
		// @34: athrow
	}
	
	final boolean func_102213_f(byte arg0)
	{
		// @00: bipush -74 (0xB6)
		// @02: iload_1
		// @03: bipush 69 (0x45)
		// @05: isub
		// @06: bipush 54 (0x36)
		// @08: idiv
		// @09: idiv
		// @0A: istore_2
		// @0B: aload_0
		// @0C: getfield game.C_100122_em game.C_100260_mc.field_102243_pc
		// @0F: ifnull @25
		// @12: aload_0
		// @13: getfield game.C_100122_em game.C_100260_mc.field_102243_pc
		// @16: getfield boolean game.C_100122_em.field_101861_U
		// @19: ifeq @25
		// @1C: goto @20
		// @1F: athrow
		// @20: iconst_1
		// @21: goto @26
		// @24: athrow
		// @25: iconst_0
		// @26: ireturn
		// @27: astore_2
		// @28: aload_2
		// @29: new java.lang.StringBuilder
		// @2C: dup
		// @2D: invokespecial java.lang.StringBuilder.<init>()void
		// @30: getstatic java.lang.String[] game.C_100260_mc.field_102225_sc
		// @33: iconst_5
		// @34: aaload
		// @35: invokevirtual java.lang.StringBuilder.append(java.lang.String)java.lang.StringBuilder
		// @38: iload_1
		// @39: invokevirtual java.lang.StringBuilder.append(int)java.lang.StringBuilder
		// @3C: bipush 41 (0x29)
		// @3E: invokevirtual java.lang.StringBuilder.append(char)java.lang.StringBuilder
		// @41: invokevirtual java.lang.StringBuilder.toString()java.lang.String
		// @44: invokestatic game.C_100181_cf.func_105695_a(java.lang.Throwable, java.lang.String)game.C_100170_cm
		// @47: athrow
	}
	
	static final void func_102211_l(int arg0)
	{
		// @000: getstatic int game.SteelSentinels.field_105275_O
		// @003: istore #12
		// @005: getstatic game.C_100278_nd game.C_100288_jn.field_106839_f
		// @008: astore_1
		// @009: aload_1
		// @00A: iconst_0
		// @00B: invokevirtual game.C_100278_nd.func_101156_c(boolean)int
		// @00E: istore_2
		// @00F: iload_0
		// @010: bipush 60 (0x3C)
		// @012: if_icmpgt @01E
		// @015: bipush 127 (0x7F)
		// @017: invokestatic game.C_100260_mc.func_102215_m(int)void
		// @01A: goto @01E
		// @01D: athrow
		// @01E: getstatic game.C_100202_qi game.C_100205_qf.field_103676_f
		// @021: bipush 17 (0x11)
		// @023: invokevirtual game.C_100202_qi.func_105899_c(int)game.C_100158_da
		// @026: checkcast game.C_100346_ja
		// @029: astore_3
		// @02A: aload_3
		// @02B: ifnull @05D
		// @02E: iload_2
		// @02F: iconst_m1
		// @030: ixor
		// @031: iload #12
		// @033: ifne @069
		// @036: aload_3
		// @037: getfield int game.C_100346_ja.field_103493_s
		// @03A: iconst_m1
		// @03B: ixor
		// @03C: if_icmpne @04C
		// @03F: goto @043
		// @042: athrow
		// @043: iload #12
		// @045: ifeq @05D
		// @048: goto @04C
		// @04B: athrow
		// @04C: getstatic game.C_100202_qi game.C_100205_qf.field_103676_f
		// @04F: bipush 113 (0x71)
		// @051: invokevirtual game.C_100202_qi.func_105907_c(byte)game.C_100158_da
		// @054: checkcast game.C_100346_ja
		// @057: astore_3
		// @058: iload #12
		// @05A: ifeq @02A
		// @05D: aconst_null
		// @05E: aload_3
		// @05F: if_acmpeq @066
		// @062: goto @06D
		// @065: athrow
		// @066: sipush 13313 (0x3401)
		// @069: invokestatic game.C_100095_fe.func_103371_l(int)void
		// @06C: return
		// @06D: aload_1
		// @06E: iconst_0
		// @06F: invokevirtual game.C_100278_nd.func_101156_c(boolean)int
		// @072: istore #4
		// @074: iload #4
		// @076: ifeq @2CD
		// @079: aload_3
		// @07A: getfield int game.C_100346_ja.field_103485_l
		// @07D: istore #5
		// @07F: getstatic java.lang.String[] game.C_100332_ii.field_107315_o
		// @082: iconst_0
		// @083: getstatic java.lang.String game.C_100339_jb.field_107391_h
		// @086: aastore
		// @087: iconst_1
		// @088: istore #6
		// @08A: iload #6
		// @08C: iload #4
		// @08E: if_icmpge @0AF
		// @091: getstatic java.lang.String[] game.C_100332_ii.field_107315_o
		// @094: iload #6
		// @096: aload_1
		// @097: sipush 9692 (0x25DC)
		// @09A: invokevirtual game.C_100278_nd.func_101164_f(int)java.lang.String
		// @09D: aastore
		// @09E: iinc #6 +1
		// @0A1: iload #12
		// @0A3: ifne @0B8
		// @0A6: iload #12
		// @0A8: ifeq @08A
		// @0AB: goto @0AF
		// @0AE: athrow
		// @0AF: iload #5
		// @0B1: bipush -109 (0x93)
		// @0B3: iload #4
		// @0B5: invokestatic game.C_100079_e.func_102656_a(int, byte, int)void
		// @0B8: iconst_0
		// @0B9: istore #6
		// @0BB: iload #6
		// @0BD: iconst_m1
		// @0BE: ixor
		// @0BF: iload #4
		// @0C1: iconst_m1
		// @0C2: ixor
		// @0C3: if_icmple @131
		// @0C6: aload_1
		// @0C7: bipush -63 (0xC1)
		// @0C9: invokestatic game.C_100213_ak.func_105989_a(game.C_100280_nf, byte)void
		// @0CC: iload #6
		// @0CE: iload #12
		// @0D0: ifne @133
		// @0D3: ifne @112
		// @0D6: goto @0DA
		// @0D9: athrow
		// @0DA: aload_3
		// @0DB: getstatic int game.C_100289_jl.field_102902_H
		// @0DE: putfield int game.C_100346_ja.field_103492_t
		// @0E1: aload_3
		// @0E2: getstatic int game.C_100096_un.field_104566_c
		// @0E5: putfield int game.C_100346_ja.field_103484_o
		// @0E8: aload_3
		// @0E9: getstatic int game.C_100101_fc.field_103401_S
		// @0EC: putfield int game.C_100346_ja.field_103483_n
		// @0EF: aload_3
		// @0F0: getstatic int game.C_100082_uf.field_100370_d
		// @0F3: putfield int game.C_100346_ja.field_103494_r
		// @0F6: getstatic int game.C_100101_fc.field_103401_S
		// @0F9: getstatic int game.C_100082_uf.field_100370_d
		// @0FC: bipush -111 (0x91)
		// @0FE: getstatic int game.C_100289_jl.field_102902_H
		// @101: iload #6
		// @103: getstatic int game.C_100096_un.field_104566_c
		// @106: invokestatic game.C_100310_lj.func_100540_a(int, int, byte, int, int, int)void
		// @109: iload #12
		// @10B: ifeq @129
		// @10E: goto @112
		// @111: athrow
		// @112: getstatic int game.C_100101_fc.field_103401_S
		// @115: getstatic int game.C_100082_uf.field_100370_d
		// @118: bipush 62 (0x3E)
		// @11A: getstatic int game.C_100289_jl.field_102902_H
		// @11D: iload #6
		// @11F: getstatic int game.C_100096_un.field_104566_c
		// @122: invokestatic game.C_100310_lj.func_100540_a(int, int, byte, int, int, int)void
		// @125: goto @129
		// @128: athrow
		// @129: iinc #6 +1
		// @12C: iload #12
		// @12E: ifeq @0BB
		// @131: iload #5
		// @133: sipush 8224 (0x2020)
		// @136: invokestatic game.C_100133_tk.func_104993_a(int, int)void
		// @139: aload_3
		// @13A: iconst_2
		// @13B: iload #5
		// @13D: multianewarray java.lang.String[][] (init: 2)
		// @141: dup_x1
		// @142: putfield java.lang.String[][] game.C_100346_ja.field_103480_A
		// @145: astore #6
		// @147: aload_3
		// @148: iconst_2
		// @149: iconst_4
		// @14A: iload #5
		// @14C: imul
		// @14D: multianewarray int[][] (init: 2)
		// @151: dup_x1
		// @152: putfield int[][] game.C_100346_ja.field_103495_q
		// @155: astore #7
		// @157: getstatic int game.C_100186_rl.field_105726_a
		// @15A: istore #8
		// @15C: iconst_0
		// @15D: istore #9
		// @15F: iconst_0
		// @160: istore #10
		// @162: iload #9
		// @164: iload #8
		// @166: if_icmpge @211
		// @169: getstatic int[] game.C_100219_an.field_100876_n
		// @16C: iload #9
		// @16E: iaload
		// @16F: istore #11
		// @171: aload #6
		// @173: iconst_0
		// @174: aaload
		// @175: iload #10
		// @177: getstatic java.lang.String[] game.C_100332_ii.field_107315_o
		// @17A: iload #11
		// @17C: aaload
		// @17D: aastore
		// @17E: aload #7
		// @180: iconst_0
		// @181: aaload
		// @182: iload #10
		// @184: iconst_4
		// @185: imul
		// @186: getstatic int[] game.C_100222_aa.field_106080_f
		// @189: iload #11
		// @18B: iaload
		// @18C: iastore
		// @18D: aload #7
		// @18F: iconst_0
		// @190: aaload
		// @191: iconst_1
		// @192: iconst_4
		// @193: iload #10
		// @195: imul
		// @196: iadd
		// @197: getstatic int[] game.C_100005_fk.field_103609_q
		// @19A: iload #11
		// @19C: iaload
		// @19D: iastore
		// @19E: aload #7
		// @1A0: iconst_0
		// @1A1: aaload
		// @1A2: iconst_2
		// @1A3: iconst_4
		// @1A4: iload #10
		// @1A6: imul
		// @1A7: iadd
		// @1A8: getstatic int[] game.C_100188_rj.field_105738_b
		// @1AB: iload #11
		// @1AD: iaload
		// @1AE: iastore
		// @1AF: aload #7
		// @1B1: iconst_0
		// @1B2: aaload
		// @1B3: iconst_4
		// @1B4: iload #10
		// @1B6: imul
		// @1B7: iconst_3
		// @1B8: iadd
		// @1B9: getstatic int[] game.C_100143_bl.field_105102_e
		// @1BC: iload #11
		// @1BE: iaload
		// @1BF: iastore
		// @1C0: getstatic java.lang.String[] game.C_100332_ii.field_107315_o
		// @1C3: iload #11
		// @1C5: aaload
		// @1C6: sipush -7290 (0xE386)
		// @1C9: invokestatic game.C_100050_vg.func_100621_a(java.lang.String, int)boolean
		// @1CC: iload #12
		// @1CE: ifne @215
		// @1D1: ifeq @206
		// @1D4: goto @1D8
		// @1D7: athrow
		// @1D8: getstatic int[] game.C_100188_rj.field_105738_b
		// @1DB: iload #11
		// @1DD: iaload
		// @1DE: getstatic int[] game.C_100005_fk.field_103609_q
		// @1E1: iload #11
		// @1E3: iaload
		// @1E4: getstatic int[] game.C_100143_bl.field_105102_e
		// @1E7: iload #11
		// @1E9: iaload
		// @1EA: ineg
		// @1EB: isub
		// @1EC: iadd
		// @1ED: iconst_m1
		// @1EE: ixor
		// @1EF: iconst_m1
		// @1F0: if_icmpne @206
		// @1F3: goto @1F7
		// @1F6: athrow
		// @1F7: aload #6
		// @1F9: iconst_0
		// @1FA: aaload
		// @1FB: iload #10
		// @1FD: aconst_null
		// @1FE: aastore
		// @1FF: iinc #10 +255
		// @202: goto @206
		// @205: athrow
		// @206: iinc #10 +1
		// @209: iinc #9 +1
		// @20C: iload #12
		// @20E: ifeq @162
		// @211: iconst_0
		// @212: istore #9
		// @214: iconst_0
		// @215: istore #10
		// @217: iload #9
		// @219: iconst_m1
		// @21A: ixor
		// @21B: iload #8
		// @21D: iconst_m1
		// @21E: ixor
		// @21F: if_icmple @2CD
		// @222: getstatic int[] game.C_100219_an.field_100876_n
		// @225: iload #5
		// @227: iload #9
		// @229: ineg
		// @22A: isub
		// @22B: iaload
		// @22C: istore #11
		// @22E: aload #6
		// @230: iconst_1
		// @231: aaload
		// @232: iload #10
		// @234: getstatic java.lang.String[] game.C_100332_ii.field_107315_o
		// @237: iload #11
		// @239: aaload
		// @23A: aastore
		// @23B: aload #7
		// @23D: iconst_1
		// @23E: aaload
		// @23F: iconst_4
		// @240: iload #10
		// @242: imul
		// @243: getstatic int[] game.C_100222_aa.field_106080_f
		// @246: iload #11
		// @248: iaload
		// @249: iastore
		// @24A: aload #7
		// @24C: iconst_1
		// @24D: aaload
		// @24E: iconst_1
		// @24F: iload #10
		// @251: iconst_4
		// @252: imul
		// @253: iadd
		// @254: getstatic int[] game.C_100005_fk.field_103609_q
		// @257: iload #11
		// @259: iaload
		// @25A: iastore
		// @25B: aload #7
		// @25D: iconst_1
		// @25E: aaload
		// @25F: iconst_2
		// @260: iconst_4
		// @261: iload #10
		// @263: imul
		// @264: iadd
		// @265: getstatic int[] game.C_100188_rj.field_105738_b
		// @268: iload #11
		// @26A: iaload
		// @26B: iastore
		// @26C: aload #7
		// @26E: iconst_1
		// @26F: aaload
		// @270: iconst_3
		// @271: iload #10
		// @273: iconst_4
		// @274: imul
		// @275: iadd
		// @276: getstatic int[] game.C_100143_bl.field_105102_e
		// @279: iload #11
		// @27B: iaload
		// @27C: iastore
		// @27D: iload #12
		// @27F: ifne @2D8
		// @282: getstatic java.lang.String[] game.C_100332_ii.field_107315_o
		// @285: iload #11
		// @287: aaload
		// @288: sipush -7290 (0xE386)
		// @28B: invokestatic game.C_100050_vg.func_100621_a(java.lang.String, int)boolean
		// @28E: ifeq @2C2
		// @291: goto @295
		// @294: athrow
		// @295: iconst_m1
		// @296: getstatic int[] game.C_100143_bl.field_105102_e
		// @299: iload #11
		// @29B: iaload
		// @29C: getstatic int[] game.C_100188_rj.field_105738_b
		// @29F: iload #11
		// @2A1: iaload
		// @2A2: getstatic int[] game.C_100005_fk.field_103609_q
		// @2A5: iload #11
		// @2A7: iaload
		// @2A8: iadd
		// @2A9: iadd
		// @2AA: iconst_m1
		// @2AB: ixor
		// @2AC: if_icmpeq @2B7
		// @2AF: goto @2B3
		// @2B2: athrow
		// @2B3: goto @2C2
		// @2B6: athrow
		// @2B7: aload #6
		// @2B9: iconst_1
		// @2BA: aaload
		// @2BB: iload #10
		// @2BD: aconst_null
		// @2BE: aastore
		// @2BF: iinc #10 +255
		// @2C2: iinc #10 +1
		// @2C5: iinc #9 +1
		// @2C8: iload #12
		// @2CA: ifeq @217
		// @2CD: aload_3
		// @2CE: iconst_1
		// @2CF: putfield boolean game.C_100346_ja.field_103499_x
		// @2D2: aload_3
		// @2D3: bipush 45 (0x2D)
		// @2D5: invokevirtual game.C_100346_ja.func_100583_c(int)void
		// @2D8: goto @2FD
		// @2DB: astore_1
		// @2DC: aload_1
		// @2DD: new java.lang.StringBuilder
		// @2E0: dup
		// @2E1: invokespecial java.lang.StringBuilder.<init>()void
		// @2E4: getstatic java.lang.String[] game.C_100260_mc.field_102225_sc
		// @2E7: bipush 7 (0x07)
		// @2E9: aaload
		// @2EA: invokevirtual java.lang.StringBuilder.append(java.lang.String)java.lang.StringBuilder
		// @2ED: iload_0
		// @2EE: invokevirtual java.lang.StringBuilder.append(int)java.lang.StringBuilder
		// @2F1: bipush 41 (0x29)
		// @2F3: invokevirtual java.lang.StringBuilder.append(char)java.lang.StringBuilder
		// @2F6: invokevirtual java.lang.StringBuilder.toString()java.lang.String
		// @2F9: invokestatic game.C_100181_cf.func_105695_a(java.lang.Throwable, java.lang.String)game.C_100170_cm
		// @2FC: athrow
		// @2FD: return
	}
	
	final boolean func_102221_b(boolean arg0)
	{
		// @00: iconst_1
		// @01: aload_0
		// @02: getfield int game.C_100260_mc.field_102238_oc
		// @05: iconst_m1
		// @06: ixor
		// @07: if_icmpeq @0C
		// @0A: iconst_0
		// @0B: ireturn
		// @0C: iload_1
		// @0D: iconst_1
		// @0E: if_icmpeq @1C
		// @11: aconst_null
		// @12: checkcast java.lang.String
		// @15: putstatic java.lang.String game.C_100260_mc.field_102237_Ub
		// @18: goto @1C
		// @1B: athrow
		// @1C: bipush 13 (0x0D)
		// @1E: getstatic int game.C_100293_kj.field_106890_c
		// @21: if_icmpne @2D
		// @24: aload_0
		// @25: iconst_m1
		// @26: putfield int game.C_100260_mc.field_102238_oc
		// @29: goto @2D
		// @2C: athrow
		// @2D: iconst_1
		// @2E: ireturn
		// @2F: astore_2
		// @30: aload_2
		// @31: new java.lang.StringBuilder
		// @34: dup
		// @35: invokespecial java.lang.StringBuilder.<init>()void
		// @38: getstatic java.lang.String[] game.C_100260_mc.field_102225_sc
		// @3B: bipush 11 (0x0B)
		// @3D: aaload
		// @3E: invokevirtual java.lang.StringBuilder.append(java.lang.String)java.lang.StringBuilder
		// @41: iload_1
		// @42: invokevirtual java.lang.StringBuilder.append(boolean)java.lang.StringBuilder
		// @45: bipush 41 (0x29)
		// @47: invokevirtual java.lang.StringBuilder.append(char)java.lang.StringBuilder
		// @4A: invokevirtual java.lang.StringBuilder.toString()java.lang.String
		// @4D: invokestatic game.C_100181_cf.func_105695_a(java.lang.Throwable, java.lang.String)game.C_100170_cm
		// @50: athrow
	}
	
	private final int func_102210_a(int arg0, int arg1, C_100302_ka arg2, byte arg3, C_100302_ka arg4)
	{
		// @00: iinc #2 +8
		// @03: iload #4
		// @05: bipush -119 (0x89)
		// @07: if_icmpeq @16
		// @0A: aload_0
		// @0B: iconst_1
		// @0C: bipush 29 (0x1D)
		// @0E: invokevirtual game.C_100260_mc.func_102217_b(boolean, byte)int
		// @11: pop
		// @12: goto @16
		// @15: athrow
		// @16: aload_3
		// @17: getfield game.C_100112_r game.C_100302_ka.field_101845_sb
		// @1A: aload_3
		// @1B: getfield java.lang.String game.C_100302_ka.field_101890_ab
		// @1E: iload_1
		// @1F: iconst_2
		// @20: aload_3
		// @21: getfield int game.C_100302_ka.field_101829_Db
		// @24: imul
		// @25: isub
		// @26: aload_3
		// @27: getfield int game.C_100302_ka.field_101833_ob
		// @2A: invokevirtual game.C_100112_r.func_101734_a(java.lang.String, int, int)int
		// @2D: istore #6
		// @2F: aload_3
		// @30: iconst_0
		// @31: iload #6
		// @33: iload #4
		// @35: bipush 118 (0x76)
		// @37: ixor
		// @38: iload_2
		// @39: iload_1
		// @3A: invokevirtual game.C_100302_ka.func_101825_a(int, int, int, int, int)void
		// @3D: iload_2
		// @3E: iconst_0
		// @3F: iload #6
		// @41: iadd
		// @42: iadd
		// @43: istore_2
		// @44: aload #5
		// @46: bipush -76 (0xB4)
		// @48: aload_3
		// @49: invokevirtual game.C_100302_ka.func_101824_b(int, game.C_100302_ka)void
		// @4C: iload_2
		// @4D: ireturn
		// @4E: astore #6
		// @50: aload #6
		// @52: new java.lang.StringBuilder
		// @55: dup
		// @56: invokespecial java.lang.StringBuilder.<init>()void
		// @59: getstatic java.lang.String[] game.C_100260_mc.field_102225_sc
		// @5C: bipush 6 (0x06)
		// @5E: aaload
		// @5F: invokevirtual java.lang.StringBuilder.append(java.lang.String)java.lang.StringBuilder
		// @62: iload_1
		// @63: invokevirtual java.lang.StringBuilder.append(int)java.lang.StringBuilder
		// @66: bipush 44 (0x2C)
		// @68: invokevirtual java.lang.StringBuilder.append(char)java.lang.StringBuilder
		// @6B: iload_2
		// @6C: invokevirtual java.lang.StringBuilder.append(int)java.lang.StringBuilder
		// @6F: bipush 44 (0x2C)
		// @71: invokevirtual java.lang.StringBuilder.append(char)java.lang.StringBuilder
		// @74: aload_3
		// @75: ifnull @81
		// @78: getstatic java.lang.String[] game.C_100260_mc.field_102225_sc
		// @7B: iconst_1
		// @7C: aaload
		// @7D: goto @86
		// @80: athrow
		// @81: getstatic java.lang.String[] game.C_100260_mc.field_102225_sc
		// @84: iconst_0
		// @85: aaload
		// @86: invokevirtual java.lang.StringBuilder.append(java.lang.String)java.lang.StringBuilder
		// @89: bipush 44 (0x2C)
		// @8B: invokevirtual java.lang.StringBuilder.append(char)java.lang.StringBuilder
		// @8E: iload #4
		// @90: invokevirtual java.lang.StringBuilder.append(int)java.lang.StringBuilder
		// @93: bipush 44 (0x2C)
		// @95: invokevirtual java.lang.StringBuilder.append(char)java.lang.StringBuilder
		// @98: aload #5
		// @9A: ifnull @A6
		// @9D: getstatic java.lang.String[] game.C_100260_mc.field_102225_sc
		// @A0: iconst_1
		// @A1: aaload
		// @A2: goto @AB
		// @A5: athrow
		// @A6: getstatic java.lang.String[] game.C_100260_mc.field_102225_sc
		// @A9: iconst_0
		// @AA: aaload
		// @AB: invokevirtual java.lang.StringBuilder.append(java.lang.String)java.lang.StringBuilder
		// @AE: bipush 41 (0x29)
		// @B0: invokevirtual java.lang.StringBuilder.append(char)java.lang.StringBuilder
		// @B3: invokevirtual java.lang.StringBuilder.toString()java.lang.String
		// @B6: invokestatic game.C_100181_cf.func_105695_a(java.lang.Throwable, java.lang.String)game.C_100170_cm
		// @B9: athrow
	}
	
	static
	{
		// @000: bipush 14 (0x0E)
		// @002: anewarray java.lang.String
		// @005: dup
		// @006: iconst_0
		// @007: ldc ":6n>"
		// @009: invokestatic game.C_100260_mc.func_102214_z(java.lang.String)char[]
		// @00C: invokestatic game.C_100260_mc.func_102212_z(char[])java.lang.String
		// @00F: aastore
		// @010: dup
		// @011: iconst_1
		// @012: ldc "/m,|\u000e"
		// @014: invokestatic game.C_100260_mc.func_102214_z(java.lang.String)char[]
		// @017: invokestatic game.C_100260_mc.func_102212_z(char[])java.lang.String
		// @01A: aastore
		// @01B: dup
		// @01C: iconst_2
		// @01D: ldc "9 ,\u0017["
		// @01F: invokestatic game.C_100260_mc.func_102214_z(java.lang.String)char[]
		// @022: invokestatic game.C_100260_mc.func_102212_z(char[])java.lang.String
		// @025: aastore
		// @026: dup
		// @027: iconst_3
		// @028: ldc "9 ,\u001a["
		// @02A: invokestatic game.C_100260_mc.func_102214_z(java.lang.String)char[]
		// @02D: invokestatic game.C_100260_mc.func_102212_z(char[])java.lang.String
		// @030: aastore
		// @031: dup
		// @032: iconst_4
		// @033: ldc "9 ,\u0000["
		// @035: invokestatic game.C_100260_mc.func_102214_z(java.lang.String)char[]
		// @038: invokestatic game.C_100260_mc.func_102212_z(char[])java.lang.String
		// @03B: aastore
		// @03C: dup
		// @03D: iconst_5
		// @03E: ldc "9 ,\u0011["
		// @040: invokestatic game.C_100260_mc.func_102214_z(java.lang.String)char[]
		// @043: invokestatic game.C_100260_mc.func_102212_z(char[])java.lang.String
		// @046: aastore
		// @047: dup
		// @048: bipush 6 (0x06)
		// @04A: ldc "9 ,\u0003["
		// @04C: invokestatic game.C_100260_mc.func_102214_z(java.lang.String)char[]
		// @04F: invokestatic game.C_100260_mc.func_102212_z(char[])java.lang.String
		// @052: aastore
		// @053: dup
		// @054: bipush 7 (0x07)
		// @056: ldc "9 ,\u0015["
		// @058: invokestatic game.C_100260_mc.func_102214_z(java.lang.String)char[]
		// @05B: invokestatic game.C_100260_mc.func_102212_z(char[])java.lang.String
		// @05E: aastore
		// @05F: dup
		// @060: bipush 8 (0x08)
		// @062: ldc "9 ,\u0010["
		// @064: invokestatic game.C_100260_mc.func_102214_z(java.lang.String)char[]
		// @067: invokestatic game.C_100260_mc.func_102212_z(char[])java.lang.String
		// @06A: aastore
		// @06B: dup
		// @06C: bipush 9 (0x09)
		// @06E: ldc "9 ,\u0016["
		// @070: invokestatic game.C_100260_mc.func_102214_z(java.lang.String)char[]
		// @073: invokestatic game.C_100260_mc.func_102212_z(char[])java.lang.String
		// @076: aastore
		// @077: dup
		// @078: bipush 10 (0x0A)
		// @07A: ldc "9 ,\u0013["
		// @07C: invokestatic game.C_100260_mc.func_102214_z(java.lang.String)char[]
		// @07F: invokestatic game.C_100260_mc.func_102212_z(char[])java.lang.String
		// @082: aastore
		// @083: dup
		// @084: bipush 11 (0x0B)
		// @086: ldc "9 ,\u0014["
		// @088: invokestatic game.C_100260_mc.func_102214_z(java.lang.String)char[]
		// @08B: invokestatic game.C_100260_mc.func_102212_z(char[])java.lang.String
		// @08E: aastore
		// @08F: dup
		// @090: bipush 12 (0x0C)
		// @092: ldc "9 ,\u001b["
		// @094: invokestatic game.C_100260_mc.func_102214_z(java.lang.String)char[]
		// @097: invokestatic game.C_100260_mc.func_102212_z(char[])java.lang.String
		// @09A: aastore
		// @09B: dup
		// @09C: bipush 13 (0x0D)
		// @09E: ldc "9 ,n\u001a:*vl["
		// @0A0: invokestatic game.C_100260_mc.func_102214_z(java.lang.String)char[]
		// @0A3: invokestatic game.C_100260_mc.func_102212_z(char[])java.lang.String
		// @0A6: aastore
		// @0A7: putstatic java.lang.String[] game.C_100260_mc.field_102225_sc
		// @0AA: bipush 30 (0x1E)
		// @0AC: anewarray java.lang.String
		// @0AF: dup
		// @0B0: iconst_0
		// @0B1: ldc "\u0019,t;\u001d3cc<\u0017t0j=\u001c *l5"
		// @0B3: invokestatic game.C_100260_mc.func_102214_z(java.lang.String)char[]
		// @0B6: invokestatic game.C_100260_mc.func_102212_z(char[])java.lang.String
		// @0B9: aastore
		// @0BA: dup
		// @0BB: iconst_1
		// @0BC: ldc "\u0006,a9\u0016 ca=\u001e6\"v"
		// @0BE: invokestatic game.C_100260_mc.func_102214_z(java.lang.String)char[]
		// @0C1: invokestatic game.C_100260_mc.func_102212_z(char[])java.lang.String
		// @0C4: aastore
		// @0C5: dup
		// @0C6: iconst_2
		// @0C7: ldc "\u0007/c$\u0016t%k7\u001f0cv7\u0000 "
		// @0C9: invokestatic game.C_100260_mc.func_102214_z(java.lang.String)char[]
		// @0CC: invokestatic game.C_100260_mc.func_102212_z(char[])java.lang.String
		// @0CF: aastore
		// @0D0: dup
		// @0D1: iconst_3
		// @0D2: ldc "\u0000+p'\u0000 cc<\u0017t&l7\u00013:"
		// @0D4: invokestatic game.C_100260_mc.func_102214_z(java.lang.String)char[]
		// @0D7: invokestatic game.C_100260_mc.func_102212_z(char[])java.lang.String
		// @0DA: aastore
		// @0DB: dup
		// @0DC: iconst_4
		// @0DD: ldc "\u0018\"q7\u0001t%k7\u001f0cv7\u0000 "
		// @0DF: invokestatic game.C_100260_mc.func_102214_z(java.lang.String)char[]
		// @0E2: invokestatic game.C_100260_mc.func_102212_z(char[])java.lang.String
		// @0E5: aastore
		// @0E6: dup
		// @0E7: iconst_5
		// @0E8: ldc "\u0000\"p5\u0016 *l5"
		// @0EA: invokestatic game.C_100260_mc.func_102214_z(java.lang.String)char[]
		// @0ED: invokestatic game.C_100260_mc.func_102212_z(char[])java.lang.String
		// @0F0: aastore
		// @0F1: dup
		// @0F2: bipush 6 (0x06)
		// @0F4: ldc "\u00152w;\u001f5cd;\u00168'\"&\u0016'7"
		// @0F6: invokestatic game.C_100260_mc.func_102214_z(java.lang.String)char[]
		// @0F9: invokestatic game.C_100260_mc.func_102212_z(char[])java.lang.String
		// @0FC: aastore
		// @0FD: dup
		// @0FE: bipush 7 (0x07)
		// @100: ldc "\u0016\"n>\u001a'7k1S#&c\"\u001c:0"
		// @102: invokestatic game.C_100260_mc.func_102214_z(java.lang.String)char[]
		// @105: invokestatic game.C_100260_mc.func_102212_z(char[])java.lang.String
		// @108: aastore
		// @109: dup
		// @10A: bipush 8 (0x08)
		// @10C: ldc "\u0016\"n>\u001a'7k1S2*g>\u0017t7g!\u0007"
		// @10E: invokestatic game.C_100260_mc.func_102214_z(java.lang.String)char[]
		// @111: invokestatic game.C_100260_mc.func_102212_z(char[])java.lang.String
		// @114: aastore
		// @115: dup
		// @116: bipush 9 (0x09)
		// @118: ldc "\u0012/c9"
		// @11A: invokestatic game.C_100260_mc.func_102214_z(java.lang.String)char[]
		// @11D: invokestatic game.C_100260_mc.func_102212_z(char[])java.lang.String
		// @120: aastore
		// @121: dup
		// @122: bipush 10 (0x0A)
		// @124: ldc "\u0012*p!\u0007t\u0010v \u001a?&"
		// @126: invokestatic game.C_100260_mc.func_102214_z(java.lang.String)char[]
		// @129: invokestatic game.C_100260_mc.func_102212_z(char[])java.lang.String
		// @12C: aastore
		// @12D: dup
		// @12E: bipush 11 (0x0B)
		// @130: ldc "\u001d-\"\u0011\u001c8'\"\u0010\u001f;,f"
		// @132: invokestatic game.C_100260_mc.func_102214_z(java.lang.String)char[]
		// @135: invokestatic game.C_100260_mc.func_102212_z(char[])java.lang.String
		// @138: aastore
		// @139: dup
		// @13A: bipush 12 (0x0C)
		// @13C: ldc "\u00171c1\u00181'\"\u0001\u001b1/n"
		// @13E: invokestatic game.C_100260_mc.func_102214_z(java.lang.String)char[]
		// @141: invokestatic game.C_100260_mc.func_102212_z(char[])java.lang.String
		// @144: aastore
		// @145: dup
		// @146: bipush 13 (0x0D)
		// @148: ldc "\u0000+gr?;-er0&\"u>"
		// @14A: invokestatic game.C_100260_mc.func_102214_z(java.lang.String)char[]
		// @14D: invokestatic game.C_100260_mc.func_102212_z(char[])java.lang.String
		// @150: aastore
		// @151: dup
		// @152: bipush 14 (0x0E)
		// @154: ldc "\u0016/w7S\u0012*p7"
		// @156: invokestatic game.C_100260_mc.func_102214_z(java.lang.String)char[]
		// @159: invokestatic game.C_100260_mc.func_102212_z(char[])java.lang.String
		// @15C: aastore
		// @15D: dup
		// @15E: bipush 15 (0x0F)
		// @160: ldc "\u0012/c!\u001b=-er18\"f7"
		// @162: invokestatic game.C_100260_mc.func_102214_z(java.lang.String)char[]
		// @165: invokestatic game.C_100260_mc.func_102212_z(char[])java.lang.String
		// @168: aastore
		// @169: dup
		// @16A: bipush 16 (0x10)
		// @16C: ldc "\u00171k!\u001a'"
		// @16E: invokestatic game.C_100260_mc.func_102214_z(java.lang.String)char[]
		// @171: invokestatic game.C_100260_mc.func_102212_z(char[])java.lang.String
		// @174: aastore
		// @175: dup
		// @176: bipush 17 (0x11)
		// @178: ldc "\u0011\"e>\u0016s0\"\u0006\u00128,l"
		// @17A: invokestatic game.C_100260_mc.func_102214_z(java.lang.String)char[]
		// @17D: invokestatic game.C_100260_mc.func_102212_z(char[])java.lang.String
		// @180: aastore
		// @181: dup
		// @182: bipush 18 (0x12)
		// @184: ldc "\u001c,n6S +gr?=-g"
		// @186: invokestatic game.C_100260_mc.func_102214_z(java.lang.String)char[]
		// @189: invokestatic game.C_100260_mc.func_102212_z(char[])java.lang.String
		// @18C: aastore
		// @18D: dup
		// @18E: bipush 19 (0x13)
		// @190: ldc "\u0012*p7\u0000 ,p?"
		// @192: invokestatic game.C_100260_mc.func_102214_z(java.lang.String)char[]
		// @195: invokestatic game.C_100260_mc.func_102212_z(char[])java.lang.String
		// @198: aastore
		// @199: dup
		// @19A: bipush 20 (0x14)
		// @19C: ldc "\u001b3g<\u001a:$\"\u0001\u0018=1o;\u0000<"
		// @19E: invokestatic game.C_100260_mc.func_102214_z(java.lang.String)char[]
		// @1A1: invokestatic game.C_100260_mc.func_102212_z(char[])java.lang.String
		// @1A4: aastore
		// @1A5: dup
		// @1A6: bipush 21 (0x15)
		// @1A8: ldc "\u0000+gr2\"*c \n"
		// @1AA: invokestatic game.C_100260_mc.func_102214_z(java.lang.String)char[]
		// @1AD: invokestatic game.C_100260_mc.func_102212_z(char[])java.lang.String
		// @1B0: aastore
		// @1B1: dup
		// @1B2: bipush 22 (0x16)
		// @1B4: ldc "\u0018\"q7\u0001t\rg!\u0007"
		// @1B6: invokestatic game.C_100260_mc.func_102214_z(java.lang.String)char[]
		// @1B9: invokestatic game.C_100260_mc.func_102212_z(char[])java.lang.String
		// @1BC: aastore
		// @1BD: dup
		// @1BE: bipush 23 (0x17)
		// @1C0: ldc "\u0002&l=\u001e;6qr!13p;\u00005/"
		// @1C2: invokestatic game.C_100260_mc.func_102214_z(java.lang.String)char[]
		// @1C5: invokestatic game.C_100260_mc.func_102212_z(char[])java.lang.String
		// @1C8: aastore
		// @1C9: dup
		// @1CA: bipush 24 (0x18)
		// @1CC: ldc "\u00077k<\u0014t,dr71%g3\u0007"
		// @1CE: invokestatic game.C_100260_mc.func_102214_z(java.lang.String)char[]
		// @1D1: invokestatic game.C_100260_mc.func_102212_z(char[])java.lang.String
		// @1D4: aastore
		// @1D5: dup
		// @1D6: bipush 25 (0x19)
		// @1D8: ldc "\u00131m'\u001d0cX7\u0001;"
		// @1DA: invokestatic game.C_100260_mc.func_102214_z(java.lang.String)char[]
		// @1DD: invokestatic game.C_100260_mc.func_102212_z(char[])java.lang.String
		// @1E0: aastore
		// @1E1: dup
		// @1E2: bipush 26 (0x1A)
		// @1E4: ldc "\u00186l3\u0001t\u0010g3"
		// @1E6: invokestatic game.C_100260_mc.func_102214_z(java.lang.String)char[]
		// @1E9: invokestatic game.C_100260_mc.func_102212_z(char[])java.lang.String
		// @1EC: aastore
		// @1ED: dup
		// @1EE: bipush 27 (0x1B)
		// @1F0: ldc "\u001a,u:\u0016&&\"&\u001ct\u0011w<"
		// @1F2: invokestatic game.C_100260_mc.func_102214_z(java.lang.String)char[]
		// @1F5: invokestatic game.C_100260_mc.func_102212_z(char[])java.lang.String
		// @1F8: aastore
		// @1F9: dup
		// @1FA: bipush 28 (0x1C)
		// @1FC: ldc "\u0011-fr\u001c2cv:\u0016t\u0011m3\u0017"
		// @1FE: invokestatic game.C_100260_mc.func_102214_z(java.lang.String)char[]
		// @201: invokestatic game.C_100260_mc.func_102212_z(char[])java.lang.String
		// @204: aastore
		// @205: dup
		// @206: bipush 29 (0x1D)
		// @208: ldc "\u001b6pr751i7\u0000 cJ=\u0006&"
		// @20A: invokestatic game.C_100260_mc.func_102214_z(java.lang.String)char[]
		// @20D: invokestatic game.C_100260_mc.func_102212_z(char[])java.lang.String
		// @210: aastore
		// @211: putstatic java.lang.String[] game.C_100260_mc.field_102226_Zb
		// @214: ldc "\u0010\u0011M\u0002"
		// @216: invokestatic game.C_100260_mc.func_102214_z(java.lang.String)char[]
		// @219: invokestatic game.C_100260_mc.func_102212_z(char[])java.lang.String
		// @21C: putstatic java.lang.String game.C_100260_mc.field_102242_kc
		// @21F: ldc "5!a6\u00162$j;\u0019?/o<\u001c$2p!\u0007!5u*\n.\u0002@\u00117\u0011\u0005E\u001a:\u001e\u0008N\u001f=\u001b\u0013S\u0000 \u0000\u0016T\u0005+\r\u00192cAgw7dDlz"
		// @221: invokestatic game.C_100260_mc.func_102214_z(java.lang.String)char[]
		// @224: invokestatic game.C_100260_mc.func_102212_z(char[])java.lang.String
		// @227: putstatic java.lang.String game.C_100260_mc.field_102237_Ub
		// @22A: iconst_5
		// @22B: anewarray java.lang.String
		// @22E: dup
		// @22F: iconst_0
		// @230: ldc "\u0010&d3\u000687\"!\u001b;6n6\u0016&cd=\u0001t7j7S"
		// @232: invokestatic game.C_100260_mc.func_102214_z(java.lang.String)char[]
		// @235: invokestatic game.C_100260_mc.func_102212_z(char[])java.lang.String
		// @238: aastore
		// @239: dup
		// @23A: iconst_1
		// @23B: ldc "h0j+Mxc"
		// @23D: invokestatic game.C_100260_mc.func_102214_z(java.lang.String)char[]
		// @240: invokestatic game.C_100260_mc.func_102212_z(char[])java.lang.String
		// @243: aastore
		// @244: dup
		// @245: iconst_2
		// @246: ldc "h0j+Mt\"l6S"
		// @248: invokestatic game.C_100260_mc.func_102214_z(java.lang.String)char[]
		// @24B: invokestatic game.C_100260_mc.func_102212_z(char[])java.lang.String
		// @24E: aastore
		// @24F: dup
		// @250: iconst_3
		// @251: ldc "y n3\u0000'cq7\u001d *l7\u001fz"
		// @253: invokestatic game.C_100260_mc.func_102214_z(java.lang.String)char[]
		// @256: invokestatic game.C_100260_mc.func_102212_z(char[])java.lang.String
		// @259: aastore
		// @25A: dup
		// @25B: iconst_4
		// @25C: ldc "y n3\u0000'cq7\u001d *l7\u001f'm"
		// @25E: invokestatic game.C_100260_mc.func_102214_z(java.lang.String)char[]
		// @261: invokestatic game.C_100260_mc.func_102212_z(char[])java.lang.String
		// @264: aastore
		// @265: putstatic java.lang.String[] game.C_100260_mc.field_102223_dc
		// @268: ldc "\u0010\u0006D\u0013&\u0018\u0017\"\u00016\u0000"
		// @26A: invokestatic game.C_100260_mc.func_102214_z(java.lang.String)char[]
		// @26D: invokestatic game.C_100260_mc.func_102212_z(char[])java.lang.String
		// @270: putstatic java.lang.String game.C_100260_mc.field_102231_rc
		// @273: ldc "\u0007&l6S$1k$\u0012 &\"?\u0016'0c5\u0016"
		// @275: invokestatic game.C_100260_mc.func_102214_z(java.lang.String)char[]
		// @278: invokestatic game.C_100260_mc.func_102212_z(char[])java.lang.String
		// @27B: putstatic java.lang.String game.C_100260_mc.field_102245_lc
		// @27E: ldc "\u0017+g1\u0018=-e"
		// @280: invokestatic game.C_100260_mc.func_102214_z(java.lang.String)char[]
		// @283: invokestatic game.C_100260_mc.func_102212_z(char[])java.lang.String
		// @286: putstatic java.lang.String game.C_100260_mc.field_102247_cc
		// @289: iconst_1
		// @28A: putstatic int game.C_100260_mc.field_102239_mc
		// @28D: iconst_m1
		// @28E: putstatic int game.C_100260_mc.field_102228_Yb
		// @291: return
	}
	
	private static char[] func_102214_z(String arg0)
	{
		// @00: aload_0
		// @01: invokevirtual java.lang.String.toCharArray()char[]
		// @04: dup
		// @05: arraylength
		// @06: iconst_2
		// @07: if_icmpge @13
		// @0A: dup
		// @0B: iconst_0
		// @0C: dup2
		// @0D: caload
		// @0E: bipush 115 (0x73)
		// @10: ixor
		// @11: i2c
		// @12: castore
		// @13: areturn
	}
	
	private static String func_102212_z(char[] arg0)
	{
		// @00: aload_0
		// @01: dup
		// @02: arraylength
		// @03: swap
		// @04: iconst_0
		// @05: istore_1
		// @06: goto @4B
		// @09: dup
		// @0A: iload_1
		// @0B: dup2
		// @0C: caload
		// @0D: iload_1
		// @0E: iconst_5
		// @0F: irem
		// @10: tableswitch def: @43, for 0: @30, for 1: @35, for 2: @3A, for 3: @3E
		// @30: bipush 84 (0x54)
		// @32: goto @45
		// @35: bipush 67 (0x43)
		// @37: goto @45
		// @3A: iconst_2
		// @3B: goto @45
		// @3E: bipush 82 (0x52)
		// @40: goto @45
		// @43: bipush 115 (0x73)
		// @45: ixor
		// @46: i2c
		// @47: castore
		// @48: iinc #1 +1
		// @4B: swap
		// @4C: dup_x1
		// @4D: iload_1
		// @4E: if_icmpgt @09
		// @51: new java.lang.String
		// @54: dup_x1
		// @55: swap
		// @56: invokespecial java.lang.String.<init>(char[])void
		// @59: invokevirtual java.lang.String.intern()java.lang.String
		// @5C: areturn
	}
}
