package game;

import java.awt.Font;

final class C_100081_ue extends C_100158_da
{
	static String field_100671_p;
	static String field_100667_t;
	static Font field_100673_o;
	int[] field_100669_r;
	static C_100302_ka field_100676_j;
	static String field_100675_m;
	static C_100115_ej field_100670_q;
	static C_100217_ao field_100672_n;
	static String field_100668_s;
	static C_100302_ka field_100678_k;
	static String field_100674_l;
	private static final String[] field_100677_z;
	
	public static void func_100664_a(byte arg0)
	{
		// @00: aconst_null
		// @01: putstatic game.C_100217_ao game.C_100081_ue.field_100672_n
		// @04: aconst_null
		// @05: putstatic game.C_100302_ka game.C_100081_ue.field_100678_k
		// @08: aconst_null
		// @09: putstatic game.C_100115_ej game.C_100081_ue.field_100670_q
		// @0C: aconst_null
		// @0D: putstatic java.lang.String game.C_100081_ue.field_100675_m
		// @10: iload_0
		// @11: bipush 82 (0x52)
		// @13: if_icmpgt @2C
		// @16: bipush 52 (0x34)
		// @18: bipush 26 (0x1A)
		// @1A: bipush 90 (0x5A)
		// @1C: bipush -48 (0xD0)
		// @1E: bipush 26 (0x1A)
		// @20: bipush -82 (0xAE)
		// @22: bipush -112 (0x90)
		// @24: invokestatic game.C_100081_ue.func_100666_a(int, int, int, int, int, int, int)boolean
		// @27: pop
		// @28: goto @2C
		// @2B: athrow
		// @2C: aconst_null
		// @2D: putstatic java.lang.String game.C_100081_ue.field_100668_s
		// @30: aconst_null
		// @31: putstatic java.lang.String game.C_100081_ue.field_100674_l
		// @34: aconst_null
		// @35: putstatic java.awt.Font game.C_100081_ue.field_100673_o
		// @38: aconst_null
		// @39: putstatic java.lang.String game.C_100081_ue.field_100671_p
		// @3C: aconst_null
		// @3D: putstatic game.C_100302_ka game.C_100081_ue.field_100676_j
		// @40: aconst_null
		// @41: putstatic java.lang.String game.C_100081_ue.field_100667_t
		// @44: goto @68
		// @47: astore_1
		// @48: aload_1
		// @49: new java.lang.StringBuilder
		// @4C: dup
		// @4D: invokespecial java.lang.StringBuilder.<init>()void
		// @50: getstatic java.lang.String[] game.C_100081_ue.field_100677_z
		// @53: iconst_1
		// @54: aaload
		// @55: invokevirtual java.lang.StringBuilder.append(java.lang.String)java.lang.StringBuilder
		// @58: iload_0
		// @59: invokevirtual java.lang.StringBuilder.append(int)java.lang.StringBuilder
		// @5C: bipush 41 (0x29)
		// @5E: invokevirtual java.lang.StringBuilder.append(char)java.lang.StringBuilder
		// @61: invokevirtual java.lang.StringBuilder.toString()java.lang.String
		// @64: invokestatic game.C_100181_cf.func_105695_a(java.lang.Throwable, java.lang.String)game.C_100170_cm
		// @67: athrow
		// @68: return
	}
	
	private C_100081_ue() throws Throwable
	{
		// @00: aload_0
		// @01: invokespecial game.C_100158_da.<init>()void
		// @04: new java.lang.Error
		// @07: dup
		// @08: invokespecial java.lang.Error.<init>()void
		// @0B: athrow
		// @0C: astore_1
		// @0D: aload_1
		// @0E: getstatic java.lang.String[] game.C_100081_ue.field_100677_z
		// @11: iconst_2
		// @12: aaload
		// @13: invokestatic game.C_100181_cf.func_105695_a(java.lang.Throwable, java.lang.String)game.C_100170_cm
		// @16: athrow
	}
	
	static final boolean func_100666_a(int arg0, int arg1, int arg2, int arg3, int arg4, int arg5, int arg6)
	{
		// @00: iload #5
		// @02: bipush -18 (0xEE)
		// @04: if_icmplt @09
		// @07: iconst_0
		// @08: ireturn
		// @09: iload_3
		// @0A: iconst_m1
		// @0B: ixor
		// @0C: iload_0
		// @0D: iconst_m1
		// @0E: ixor
		// @0F: if_icmplt @45
		// @12: iload #6
		// @14: iload_3
		// @15: iadd
		// @16: iconst_m1
		// @17: ixor
		// @18: iload_0
		// @19: iconst_m1
		// @1A: ixor
		// @1B: if_icmpge @45
		// @1E: goto @22
		// @21: athrow
		// @22: iload_1
		// @23: iconst_m1
		// @24: ixor
		// @25: iload_2
		// @26: iconst_m1
		// @27: ixor
		// @28: if_icmplt @45
		// @2B: goto @2F
		// @2E: athrow
		// @2F: iload_1
		// @30: iload #4
		// @32: ineg
		// @33: isub
		// @34: iconst_m1
		// @35: ixor
		// @36: iload_2
		// @37: iconst_m1
		// @38: ixor
		// @39: if_icmpge @45
		// @3C: goto @40
		// @3F: athrow
		// @40: iconst_1
		// @41: goto @46
		// @44: athrow
		// @45: iconst_0
		// @46: ireturn
		// @47: astore #7
		// @49: aload #7
		// @4B: new java.lang.StringBuilder
		// @4E: dup
		// @4F: invokespecial java.lang.StringBuilder.<init>()void
		// @52: getstatic java.lang.String[] game.C_100081_ue.field_100677_z
		// @55: iconst_0
		// @56: aaload
		// @57: invokevirtual java.lang.StringBuilder.append(java.lang.String)java.lang.StringBuilder
		// @5A: iload_0
		// @5B: invokevirtual java.lang.StringBuilder.append(int)java.lang.StringBuilder
		// @5E: bipush 44 (0x2C)
		// @60: invokevirtual java.lang.StringBuilder.append(char)java.lang.StringBuilder
		// @63: iload_1
		// @64: invokevirtual java.lang.StringBuilder.append(int)java.lang.StringBuilder
		// @67: bipush 44 (0x2C)
		// @69: invokevirtual java.lang.StringBuilder.append(char)java.lang.StringBuilder
		// @6C: iload_2
		// @6D: invokevirtual java.lang.StringBuilder.append(int)java.lang.StringBuilder
		// @70: bipush 44 (0x2C)
		// @72: invokevirtual java.lang.StringBuilder.append(char)java.lang.StringBuilder
		// @75: iload_3
		// @76: invokevirtual java.lang.StringBuilder.append(int)java.lang.StringBuilder
		// @79: bipush 44 (0x2C)
		// @7B: invokevirtual java.lang.StringBuilder.append(char)java.lang.StringBuilder
		// @7E: iload #4
		// @80: invokevirtual java.lang.StringBuilder.append(int)java.lang.StringBuilder
		// @83: bipush 44 (0x2C)
		// @85: invokevirtual java.lang.StringBuilder.append(char)java.lang.StringBuilder
		// @88: iload #5
		// @8A: invokevirtual java.lang.StringBuilder.append(int)java.lang.StringBuilder
		// @8D: bipush 44 (0x2C)
		// @8F: invokevirtual java.lang.StringBuilder.append(char)java.lang.StringBuilder
		// @92: iload #6
		// @94: invokevirtual java.lang.StringBuilder.append(int)java.lang.StringBuilder
		// @97: bipush 41 (0x29)
		// @99: invokevirtual java.lang.StringBuilder.append(char)java.lang.StringBuilder
		// @9C: invokevirtual java.lang.StringBuilder.toString()java.lang.String
		// @9F: invokestatic game.C_100181_cf.func_105695_a(java.lang.Throwable, java.lang.String)game.C_100170_cm
		// @A2: athrow
	}
	
	static
	{
		// @00: iconst_3
		// @01: anewarray java.lang.String
		// @04: dup
		// @05: iconst_0
		// @06: ldc "\u0005s`\u001fl"
		// @08: invokestatic game.C_100081_ue.func_100665_z(java.lang.String)char[]
		// @0B: invokestatic game.C_100081_ue.func_100663_z(char[])java.lang.String
		// @0E: aastore
		// @0F: dup
		// @10: iconst_1
		// @11: ldc "\u0005s`\u001cl"
		// @13: invokestatic game.C_100081_ue.func_100665_z(java.lang.String)char[]
		// @16: invokestatic game.C_100081_ue.func_100663_z(char[])java.lang.String
		// @19: aastore
		// @1A: dup
		// @1B: iconst_2
		// @1C: ldc "\u0005s`a-\u001e\u007f:clY"
		// @1E: invokestatic game.C_100081_ue.func_100665_z(java.lang.String)char[]
		// @21: invokestatic game.C_100081_ue.func_100663_z(char[])java.lang.String
		// @24: aastore
		// @25: putstatic java.lang.String[] game.C_100081_ue.field_100677_z
		// @28: ldc ")y;/d\u0015{/4(Pw*96\u0015e=}-\u00036;.!\u00146:2d\u0019r+30\u0019p7}0\u0018\u007f=}%\u0013u!(*\u0004"
		// @2A: invokestatic game.C_100081_ue.func_100665_z(java.lang.String)char[]
		// @2D: invokestatic game.C_100081_ue.func_100663_z(char[])java.lang.String
		// @30: putstatic java.lang.String game.C_100081_ue.field_100667_t
		// @33: ldc "$o>8d\ty;/d\u0015{/4(Pw*96\u0015e=}%\u0017w'3d\u0004yn0%\u001bsn.1\u0002sn40Wen>+\u0002d+>0"
		// @35: invokestatic game.C_100081_ue.func_100665_z(java.lang.String)char[]
		// @38: invokestatic game.C_100081_ue.func_100663_z(char[])java.lang.String
		// @3B: putstatic java.lang.String game.C_100081_ue.field_100671_p
		// @3E: ldc "4s:<-\u001c,n\u0011+\u0007"
		// @40: invokestatic game.C_100081_ue.func_100665_z(java.lang.String)char[]
		// @43: invokestatic game.C_100081_ue.func_100663_z(char[])java.lang.String
		// @46: putstatic java.lang.String game.C_100081_ue.field_100675_m
		// @49: ldc "?p(86Pd+0%\u0004u&"
		// @4B: invokestatic game.C_100081_ue.func_100665_z(java.lang.String)char[]
		// @4E: invokestatic game.C_100081_ue.func_100663_z(char[])java.lang.String
		// @51: putstatic java.lang.String game.C_100081_ue.field_100668_s
		// @54: new game.C_100217_ao
		// @57: dup
		// @58: bipush 15 (0x0F)
		// @5A: iconst_0
		// @5B: iconst_1
		// @5C: iconst_0
		// @5D: invokespecial game.C_100217_ao.<init>(int, int, int, int)void
		// @60: putstatic game.C_100217_ao game.C_100081_ue.field_100672_n
		// @63: ldc "L3\u007fcd\u0013y;1 \u001e1:}%\u0006y'9d\u0004~+})\u0019q&)=Ps 26\u001dyc1%\u0003s<"
		// @65: invokestatic game.C_100081_ue.func_100665_z(java.lang.String)char[]
		// @68: invokestatic game.C_100081_ue.func_100663_z(char[])java.lang.String
		// @6B: putstatic java.lang.String game.C_100081_ue.field_100674_l
		// @6E: return
	}
	
	private static char[] func_100665_z(String arg0)
	{
		// @00: aload_0
		// @01: invokevirtual java.lang.String.toCharArray()char[]
		// @04: dup
		// @05: arraylength
		// @06: iconst_2
		// @07: if_icmpge @13
		// @0A: dup
		// @0B: iconst_0
		// @0C: dup2
		// @0D: caload
		// @0E: bipush 68 (0x44)
		// @10: ixor
		// @11: i2c
		// @12: castore
		// @13: areturn
	}
	
	private static String func_100663_z(char[] arg0)
	{
		// @00: aload_0
		// @01: dup
		// @02: arraylength
		// @03: swap
		// @04: iconst_0
		// @05: istore_1
		// @06: goto @4C
		// @09: dup
		// @0A: iload_1
		// @0B: dup2
		// @0C: caload
		// @0D: iload_1
		// @0E: iconst_5
		// @0F: irem
		// @10: tableswitch def: @44, for 0: @30, for 1: @35, for 2: @3A, for 3: @3F
		// @30: bipush 112 (0x70)
		// @32: goto @46
		// @35: bipush 22 (0x16)
		// @37: goto @46
		// @3A: bipush 78 (0x4E)
		// @3C: goto @46
		// @3F: bipush 93 (0x5D)
		// @41: goto @46
		// @44: bipush 68 (0x44)
		// @46: ixor
		// @47: i2c
		// @48: castore
		// @49: iinc #1 +1
		// @4C: swap
		// @4D: dup_x1
		// @4E: iload_1
		// @4F: if_icmpgt @09
		// @52: new java.lang.String
		// @55: dup_x1
		// @56: swap
		// @57: invokespecial java.lang.String.<init>(char[])void
		// @5A: invokevirtual java.lang.String.intern()java.lang.String
		// @5D: areturn
	}
}
