package game;

final class C_100321_hi
{
	private String field_107222_n;
	static int field_107219_b;
	static String field_107220_c;
	static String field_107223_o;
	static C_100037_wb[] field_107228_h;
	private boolean field_107229_i;
	static int field_107224_l;
	static boolean[][] field_107225_m;
	static C_100317_lb field_107217_d;
	static String field_107221_a;
	static long field_107215_f;
	private boolean field_107216_g;
	static String field_107227_k;
	static C_100098_h field_107226_j;
	static char field_107218_e;
	private static final String[] field_107230_z;
	
	public static void func_107213_c(byte arg0)
	{
		// @00: aconst_null
		// @01: putstatic game.C_100317_lb game.C_100321_hi.field_107217_d
		// @04: aconst_null
		// @05: putstatic java.lang.String game.C_100321_hi.field_107220_c
		// @08: aconst_null
		// @09: checkcast boolean[][]
		// @0C: putstatic boolean[][] game.C_100321_hi.field_107225_m
		// @0F: aconst_null
		// @10: putstatic java.lang.String game.C_100321_hi.field_107221_a
		// @13: aconst_null
		// @14: putstatic game.C_100098_h game.C_100321_hi.field_107226_j
		// @17: aconst_null
		// @18: putstatic java.lang.String game.C_100321_hi.field_107223_o
		// @1B: iload_0
		// @1C: bipush -75 (0xB5)
		// @1E: if_icmplt @2F
		// @21: aconst_null
		// @22: checkcast boolean[][]
		// @25: checkcast boolean[][]
		// @28: putstatic boolean[][] game.C_100321_hi.field_107225_m
		// @2B: goto @2F
		// @2E: athrow
		// @2F: aconst_null
		// @30: putstatic game.C_100037_wb[] game.C_100321_hi.field_107228_h
		// @33: aconst_null
		// @34: putstatic java.lang.String game.C_100321_hi.field_107227_k
		// @37: goto @5C
		// @3A: astore_1
		// @3B: aload_1
		// @3C: new java.lang.StringBuilder
		// @3F: dup
		// @40: invokespecial java.lang.StringBuilder.<init>()void
		// @43: getstatic java.lang.String[] game.C_100321_hi.field_107230_z
		// @46: bipush 6 (0x06)
		// @48: aaload
		// @49: invokevirtual java.lang.StringBuilder.append(java.lang.String)java.lang.StringBuilder
		// @4C: iload_0
		// @4D: invokevirtual java.lang.StringBuilder.append(int)java.lang.StringBuilder
		// @50: bipush 41 (0x29)
		// @52: invokevirtual java.lang.StringBuilder.append(char)java.lang.StringBuilder
		// @55: invokevirtual java.lang.StringBuilder.toString()java.lang.String
		// @58: invokestatic game.C_100181_cf.func_105695_a(java.lang.Throwable, java.lang.String)game.C_100170_cm
		// @5B: athrow
		// @5C: return
	}
	
	static final void func_107207_a(int arg0)
	{
		// @00: getstatic int game.SteelSentinels.field_105275_O
		// @03: istore #4
		// @05: getstatic int[] game.C_100226_ae.field_106151_c
		// @08: astore_1
		// @09: iload_0
		// @0A: istore_2
		// @0B: aload_1
		// @0C: arraylength
		// @0D: istore_3
		// @0E: iload_2
		// @0F: iload_3
		// @10: if_icmpge @59
		// @13: aload_1
		// @14: iload_2
		// @15: iinc #2 +1
		// @18: iconst_0
		// @19: iastore
		// @1A: aload_1
		// @1B: iload_2
		// @1C: iinc #2 +1
		// @1F: iconst_0
		// @20: iastore
		// @21: aload_1
		// @22: iload_2
		// @23: iinc #2 +1
		// @26: iconst_0
		// @27: iastore
		// @28: aload_1
		// @29: iload_2
		// @2A: iinc #2 +1
		// @2D: iconst_0
		// @2E: iastore
		// @2F: aload_1
		// @30: iload_2
		// @31: iinc #2 +1
		// @34: iconst_0
		// @35: iastore
		// @36: aload_1
		// @37: iload_2
		// @38: iinc #2 +1
		// @3B: iconst_0
		// @3C: iastore
		// @3D: aload_1
		// @3E: iload_2
		// @3F: iinc #2 +1
		// @42: iconst_0
		// @43: iastore
		// @44: aload_1
		// @45: iload_2
		// @46: iinc #2 +1
		// @49: iconst_0
		// @4A: iastore
		// @4B: iload #4
		// @4D: ifne @7E
		// @50: iload #4
		// @52: ifeq @0E
		// @55: goto @59
		// @58: athrow
		// @59: goto @7E
		// @5C: astore_1
		// @5D: aload_1
		// @5E: new java.lang.StringBuilder
		// @61: dup
		// @62: invokespecial java.lang.StringBuilder.<init>()void
		// @65: getstatic java.lang.String[] game.C_100321_hi.field_107230_z
		// @68: bipush 10 (0x0A)
		// @6A: aaload
		// @6B: invokevirtual java.lang.StringBuilder.append(java.lang.String)java.lang.StringBuilder
		// @6E: iload_0
		// @6F: invokevirtual java.lang.StringBuilder.append(int)java.lang.StringBuilder
		// @72: bipush 41 (0x29)
		// @74: invokevirtual java.lang.StringBuilder.append(char)java.lang.StringBuilder
		// @77: invokevirtual java.lang.StringBuilder.toString()java.lang.String
		// @7A: invokestatic game.C_100181_cf.func_105695_a(java.lang.Throwable, java.lang.String)game.C_100170_cm
		// @7D: athrow
		// @7E: return
	}
	
	static final void func_107209_a(byte arg0)
	{
		// @000: getstatic int game.SteelSentinels.field_105275_O
		// @003: istore #8
		// @005: iload_0
		// @006: bipush -10 (0xF6)
		// @008: if_icmpeq @014
		// @00B: bipush 97 (0x61)
		// @00D: putstatic int game.C_100321_hi.field_107224_l
		// @010: goto @014
		// @013: athrow
		// @014: getstatic game.C_100278_nd game.C_100288_jn.field_106839_f
		// @017: astore_1
		// @018: aload_1
		// @019: iconst_0
		// @01A: invokevirtual game.C_100278_nd.func_101156_c(boolean)int
		// @01D: istore_2
		// @01E: aload_1
		// @01F: iconst_0
		// @020: invokevirtual game.C_100278_nd.func_101156_c(boolean)int
		// @023: istore_3
		// @024: iload_2
		// @025: ifeq @0D8
		// @028: bipush -2 (0xFE)
		// @02A: iload_2
		// @02B: iconst_m1
		// @02C: ixor
		// @02D: if_icmpeq @062
		// @030: goto @034
		// @033: athrow
		// @034: iconst_1
		// @035: new java.lang.StringBuilder
		// @038: dup
		// @039: invokespecial java.lang.StringBuilder.<init>()void
		// @03C: getstatic java.lang.String[] game.C_100321_hi.field_107230_z
		// @03F: iconst_2
		// @040: aaload
		// @041: invokevirtual java.lang.StringBuilder.append(java.lang.String)java.lang.StringBuilder
		// @044: bipush 69 (0x45)
		// @046: invokestatic game.C_100316_lc.func_102399_d(byte)java.lang.String
		// @049: invokevirtual java.lang.StringBuilder.append(java.lang.String)java.lang.StringBuilder
		// @04C: invokevirtual java.lang.StringBuilder.toString()java.lang.String
		// @04F: aconst_null
		// @050: invokestatic game.C_100036_gg.func_103142_a(int, java.lang.String, java.lang.Throwable)void
		// @053: sipush 13313 (0x3401)
		// @056: invokestatic game.C_100095_fe.func_103371_l(int)void
		// @059: iload #8
		// @05B: ifeq @15C
		// @05E: goto @062
		// @061: athrow
		// @062: aload_1
		// @063: bipush 49 (0x31)
		// @065: invokevirtual game.C_100278_nd.func_101138_a(byte)int
		// @068: istore #4
		// @06A: getstatic game.C_100202_qi game.C_100106_ef.field_104754_b
		// @06D: bipush 82 (0x52)
		// @06F: invokevirtual game.C_100202_qi.func_105899_c(int)game.C_100158_da
		// @072: checkcast game.C_100050_vg
		// @075: astore #5
		// @077: aconst_null
		// @078: aload #5
		// @07A: if_acmpeq @0BC
		// @07D: iload_3
		// @07E: iload #8
		// @080: ifne @0C8
		// @083: aload #5
		// @085: getfield int game.C_100050_vg.field_100627_n
		// @088: if_icmpne @0AA
		// @08B: goto @08F
		// @08E: athrow
		// @08F: aload #5
		// @091: getfield int game.C_100050_vg.field_100635_s
		// @094: iconst_m1
		// @095: ixor
		// @096: iload #4
		// @098: iconst_m1
		// @099: ixor
		// @09A: if_icmpne @0AA
		// @09D: goto @0A1
		// @0A0: athrow
		// @0A1: iload #8
		// @0A3: ifeq @0BC
		// @0A6: goto @0AA
		// @0A9: athrow
		// @0AA: getstatic game.C_100202_qi game.C_100106_ef.field_104754_b
		// @0AD: bipush 75 (0x4B)
		// @0AF: invokevirtual game.C_100202_qi.func_105907_c(byte)game.C_100158_da
		// @0B2: checkcast game.C_100050_vg
		// @0B5: astore #5
		// @0B7: iload #8
		// @0B9: ifeq @077
		// @0BC: aload #5
		// @0BE: ifnonnull @0CC
		// @0C1: sipush 13313 (0x3401)
		// @0C4: goto @0C8
		// @0C7: athrow
		// @0C8: invokestatic game.C_100095_fe.func_103371_l(int)void
		// @0CB: return
		// @0CC: aload #5
		// @0CE: bipush 45 (0x2D)
		// @0D0: invokevirtual game.C_100050_vg.func_100583_c(int)void
		// @0D3: iload #8
		// @0D5: ifeq @15C
		// @0D8: getstatic game.C_100202_qi game.C_100064_ve.field_103022_x
		// @0DB: bipush 112 (0x70)
		// @0DD: invokevirtual game.C_100202_qi.func_105899_c(int)game.C_100158_da
		// @0E0: checkcast game.C_100081_ue
		// @0E3: astore #4
		// @0E5: aconst_null
		// @0E6: aload #4
		// @0E8: if_acmpeq @0EF
		// @0EB: goto @0F6
		// @0EE: athrow
		// @0EF: sipush 13313 (0x3401)
		// @0F2: invokestatic game.C_100095_fe.func_103371_l(int)void
		// @0F5: return
		// @0F6: getstatic int game.C_100056_de.field_103194_Y
		// @0F9: aload_1
		// @0FA: getfield int game.C_100278_nd.field_101177_n
		// @0FD: isub
		// @0FE: istore #5
		// @100: aload #4
		// @102: getfield int[] game.C_100081_ue.field_100669_r
		// @105: astore #6
		// @107: iload #5
		// @109: iconst_m1
		// @10A: ixor
		// @10B: aload #6
		// @10D: arraylength
		// @10E: ldc 936959394 (0x37d8dda2)
		// @110: ishl
		// @111: iconst_m1
		// @112: ixor
		// @113: if_icmpge @11E
		// @116: aload #6
		// @118: arraylength
		// @119: ldc -1337947678 (0xb04089e2)
		// @11B: ishl
		// @11C: istore #5
		// @11E: iconst_0
		// @11F: istore #7
		// @121: iload #5
		// @123: iload #7
		// @125: if_icmple @155
		// @128: aload #6
		// @12A: iload #7
		// @12C: ldc 471732514 (0x1c1e1122)
		// @12E: ishr
		// @12F: dup2
		// @130: iaload
		// @131: aload_1
		// @132: iconst_0
		// @133: invokevirtual game.C_100278_nd.func_101156_c(boolean)int
		// @136: sipush 768 (0x0300)
		// @139: iload #7
		// @13B: ldc -366881112 (0xea21d6a8)
		// @13D: ishl
		// @13E: invokestatic game.C_100256_pk.func_100449_a(int, int)int
		// @141: ishl
		// @142: iadd
		// @143: iastore
		// @144: iinc #7 +1
		// @147: iload #8
		// @149: ifne @15C
		// @14C: iload #8
		// @14E: ifeq @121
		// @151: goto @155
		// @154: athrow
		// @155: aload #4
		// @157: bipush 45 (0x2D)
		// @159: invokevirtual game.C_100081_ue.func_100583_c(int)void
		// @15C: goto @180
		// @15F: astore_1
		// @160: aload_1
		// @161: new java.lang.StringBuilder
		// @164: dup
		// @165: invokespecial java.lang.StringBuilder.<init>()void
		// @168: getstatic java.lang.String[] game.C_100321_hi.field_107230_z
		// @16B: iconst_1
		// @16C: aaload
		// @16D: invokevirtual java.lang.StringBuilder.append(java.lang.String)java.lang.StringBuilder
		// @170: iload_0
		// @171: invokevirtual java.lang.StringBuilder.append(int)java.lang.StringBuilder
		// @174: bipush 41 (0x29)
		// @176: invokevirtual java.lang.StringBuilder.append(char)java.lang.StringBuilder
		// @179: invokevirtual java.lang.StringBuilder.toString()java.lang.String
		// @17C: invokestatic game.C_100181_cf.func_105695_a(java.lang.Throwable, java.lang.String)game.C_100170_cm
		// @17F: athrow
		// @180: return
	}
	
	final void func_107214_a(int arg0, boolean arg1)
	{
		// @00: aload_0
		// @01: iconst_1
		// @02: putfield boolean game.C_100321_hi.field_107216_g
		// @05: bipush -52 (0xCC)
		// @07: iload_1
		// @08: bipush -20 (0xEC)
		// @0A: isub
		// @0B: bipush 42 (0x2A)
		// @0D: idiv
		// @0E: idiv
		// @0F: istore_3
		// @10: aload_0
		// @11: iload_2
		// @12: putfield boolean game.C_100321_hi.field_107229_i
		// @15: goto @43
		// @18: astore_3
		// @19: aload_3
		// @1A: new java.lang.StringBuilder
		// @1D: dup
		// @1E: invokespecial java.lang.StringBuilder.<init>()void
		// @21: getstatic java.lang.String[] game.C_100321_hi.field_107230_z
		// @24: bipush 9 (0x09)
		// @26: aaload
		// @27: invokevirtual java.lang.StringBuilder.append(java.lang.String)java.lang.StringBuilder
		// @2A: iload_1
		// @2B: invokevirtual java.lang.StringBuilder.append(int)java.lang.StringBuilder
		// @2E: bipush 44 (0x2C)
		// @30: invokevirtual java.lang.StringBuilder.append(char)java.lang.StringBuilder
		// @33: iload_2
		// @34: invokevirtual java.lang.StringBuilder.append(boolean)java.lang.StringBuilder
		// @37: bipush 41 (0x29)
		// @39: invokevirtual java.lang.StringBuilder.append(char)java.lang.StringBuilder
		// @3C: invokevirtual java.lang.StringBuilder.toString()java.lang.String
		// @3F: invokestatic game.C_100181_cf.func_105695_a(java.lang.Throwable, java.lang.String)game.C_100170_cm
		// @42: athrow
		// @43: return
	}
	
	final boolean func_107212_b(byte arg0)
	{
		// @00: iload_1
		// @01: bipush -27 (0xE5)
		// @03: if_icmpeq @0F
		// @06: bipush -38 (0xDA)
		// @08: putstatic int game.C_100321_hi.field_107219_b
		// @0B: goto @0F
		// @0E: athrow
		// @0F: aload_0
		// @10: getfield boolean game.C_100321_hi.field_107229_i
		// @13: ireturn
		// @14: astore_2
		// @15: aload_2
		// @16: new java.lang.StringBuilder
		// @19: dup
		// @1A: invokespecial java.lang.StringBuilder.<init>()void
		// @1D: getstatic java.lang.String[] game.C_100321_hi.field_107230_z
		// @20: bipush 7 (0x07)
		// @22: aaload
		// @23: invokevirtual java.lang.StringBuilder.append(java.lang.String)java.lang.StringBuilder
		// @26: iload_1
		// @27: invokevirtual java.lang.StringBuilder.append(int)java.lang.StringBuilder
		// @2A: bipush 41 (0x29)
		// @2C: invokevirtual java.lang.StringBuilder.append(char)java.lang.StringBuilder
		// @2F: invokevirtual java.lang.StringBuilder.toString()java.lang.String
		// @32: invokestatic game.C_100181_cf.func_105695_a(java.lang.Throwable, java.lang.String)game.C_100170_cm
		// @35: athrow
	}
	
	final String func_107206_c(int arg0)
	{
		// @00: iload_1
		// @01: sipush -23813 (0xA2FB)
		// @04: if_icmpeq @0C
		// @07: aconst_null
		// @08: checkcast java.lang.String
		// @0B: areturn
		// @0C: aload_0
		// @0D: getfield java.lang.String game.C_100321_hi.field_107222_n
		// @10: areturn
		// @11: astore_2
		// @12: aload_2
		// @13: new java.lang.StringBuilder
		// @16: dup
		// @17: invokespecial java.lang.StringBuilder.<init>()void
		// @1A: getstatic java.lang.String[] game.C_100321_hi.field_107230_z
		// @1D: iconst_0
		// @1E: aaload
		// @1F: invokevirtual java.lang.StringBuilder.append(java.lang.String)java.lang.StringBuilder
		// @22: iload_1
		// @23: invokevirtual java.lang.StringBuilder.append(int)java.lang.StringBuilder
		// @26: bipush 41 (0x29)
		// @28: invokevirtual java.lang.StringBuilder.append(char)java.lang.StringBuilder
		// @2B: invokevirtual java.lang.StringBuilder.toString()java.lang.String
		// @2E: invokestatic game.C_100181_cf.func_105695_a(java.lang.Throwable, java.lang.String)game.C_100170_cm
		// @31: athrow
	}
	
	final boolean func_107211_b(int arg0)
	{
		// @00: iload_1
		// @01: bipush -2 (0xFE)
		// @03: if_icmpeq @0F
		// @06: bipush -104 (0x98)
		// @08: invokestatic game.C_100321_hi.func_107213_c(byte)void
		// @0B: goto @0F
		// @0E: athrow
		// @0F: aload_0
		// @10: getfield boolean game.C_100321_hi.field_107216_g
		// @13: ireturn
		// @14: astore_2
		// @15: aload_2
		// @16: new java.lang.StringBuilder
		// @19: dup
		// @1A: invokespecial java.lang.StringBuilder.<init>()void
		// @1D: getstatic java.lang.String[] game.C_100321_hi.field_107230_z
		// @20: bipush 8 (0x08)
		// @22: aaload
		// @23: invokevirtual java.lang.StringBuilder.append(java.lang.String)java.lang.StringBuilder
		// @26: iload_1
		// @27: invokevirtual java.lang.StringBuilder.append(int)java.lang.StringBuilder
		// @2A: bipush 41 (0x29)
		// @2C: invokevirtual java.lang.StringBuilder.append(char)java.lang.StringBuilder
		// @2F: invokevirtual java.lang.StringBuilder.toString()java.lang.String
		// @32: invokestatic game.C_100181_cf.func_105695_a(java.lang.Throwable, java.lang.String)game.C_100170_cm
		// @35: athrow
	}
	
	C_100321_hi(String arg0)
	{
		// @00: aload_0
		// @01: invokespecial java.lang.Object.<init>()void
		// @04: aload_0
		// @05: iconst_0
		// @06: putfield boolean game.C_100321_hi.field_107229_i
		// @09: aload_0
		// @0A: iconst_0
		// @0B: putfield boolean game.C_100321_hi.field_107216_g
		// @0E: aload_0
		// @0F: aload_1
		// @10: putfield java.lang.String game.C_100321_hi.field_107222_n
		// @13: goto @48
		// @16: astore_2
		// @17: aload_2
		// @18: new java.lang.StringBuilder
		// @1B: dup
		// @1C: invokespecial java.lang.StringBuilder.<init>()void
		// @1F: getstatic java.lang.String[] game.C_100321_hi.field_107230_z
		// @22: iconst_5
		// @23: aaload
		// @24: invokevirtual java.lang.StringBuilder.append(java.lang.String)java.lang.StringBuilder
		// @27: aload_1
		// @28: ifnull @34
		// @2B: getstatic java.lang.String[] game.C_100321_hi.field_107230_z
		// @2E: iconst_4
		// @2F: aaload
		// @30: goto @39
		// @33: athrow
		// @34: getstatic java.lang.String[] game.C_100321_hi.field_107230_z
		// @37: iconst_3
		// @38: aaload
		// @39: invokevirtual java.lang.StringBuilder.append(java.lang.String)java.lang.StringBuilder
		// @3C: bipush 41 (0x29)
		// @3E: invokevirtual java.lang.StringBuilder.append(char)java.lang.StringBuilder
		// @41: invokevirtual java.lang.StringBuilder.toString()java.lang.String
		// @44: invokestatic game.C_100181_cf.func_105695_a(java.lang.Throwable, java.lang.String)game.C_100170_cm
		// @47: athrow
		// @48: return
	}
	
	static
	{
		// @00: bipush 11 (0x0B)
		// @02: anewarray java.lang.String
		// @05: dup
		// @06: iconst_0
		// @07: ldc "WQ\u001e[\u001b"
		// @09: invokestatic game.C_100321_hi.func_107210_z(java.lang.String)char[]
		// @0C: invokestatic game.C_100321_hi.func_107208_z(char[])java.lang.String
		// @0F: aastore
		// @10: dup
		// @11: iconst_1
		// @12: ldc "WQ\u001eX\u001b"
		// @14: invokestatic game.C_100321_hi.func_107210_z(java.lang.String)char[]
		// @17: invokestatic game.C_100321_hi.func_107208_z(char[])java.lang.String
		// @1A: aastore
		// @1B: dup
		// @1C: iconst_2
		// @1D: ldc "sj\u0001'\u0013"
		// @1F: invokestatic game.C_100321_hi.func_107210_z(java.lang.String)char[]
		// @22: invokestatic game.C_100321_hi.func_107208_z(char[])java.lang.String
		// @25: aastore
		// @26: dup
		// @27: iconst_3
		// @28: ldc "QM\\q"
		// @2A: invokestatic game.C_100321_hi.func_107210_z(java.lang.String)char[]
		// @2D: invokestatic game.C_100321_hi.func_107208_z(char[])java.lang.String
		// @30: aastore
		// @31: dup
		// @32: iconst_4
		// @33: ldc "D\u0016\u001e3N"
		// @35: invokestatic game.C_100321_hi.func_107210_z(java.lang.String)char[]
		// @38: invokestatic game.C_100321_hi.func_107208_z(char[])java.lang.String
		// @3B: aastore
		// @3C: dup
		// @3D: iconst_5
		// @3E: ldc "WQ\u001e!ZQQD#\u001b"
		// @40: invokestatic game.C_100321_hi.func_107210_z(java.lang.String)char[]
		// @43: invokestatic game.C_100321_hi.func_107208_z(char[])java.lang.String
		// @46: aastore
		// @47: dup
		// @48: bipush 6 (0x06)
		// @4A: ldc "WQ\u001e\\\u001b"
		// @4C: invokestatic game.C_100321_hi.func_107210_z(java.lang.String)char[]
		// @4F: invokestatic game.C_100321_hi.func_107208_z(char[])java.lang.String
		// @52: aastore
		// @53: dup
		// @54: bipush 7 (0x07)
		// @56: ldc "WQ\u001e_\u001b"
		// @58: invokestatic game.C_100321_hi.func_107210_z(java.lang.String)char[]
		// @5B: invokestatic game.C_100321_hi.func_107208_z(char[])java.lang.String
		// @5E: aastore
		// @5F: dup
		// @60: bipush 8 (0x08)
		// @62: ldc "WQ\u001eZ\u001b"
		// @64: invokestatic game.C_100321_hi.func_107210_z(java.lang.String)char[]
		// @67: invokestatic game.C_100321_hi.func_107208_z(char[])java.lang.String
		// @6A: aastore
		// @6B: dup
		// @6C: bipush 9 (0x09)
		// @6E: ldc "WQ\u001e^\u001b"
		// @70: invokestatic game.C_100321_hi.func_107210_z(java.lang.String)char[]
		// @73: invokestatic game.C_100321_hi.func_107208_z(char[])java.lang.String
		// @76: aastore
		// @77: dup
		// @78: bipush 10 (0x0A)
		// @7A: ldc "WQ\u001eY\u001b"
		// @7C: invokestatic game.C_100321_hi.func_107210_z(java.lang.String)char[]
		// @7F: invokestatic game.C_100321_hi.func_107208_z(char[])java.lang.String
		// @82: aastore
		// @83: putstatic java.lang.String[] game.C_100321_hi.field_107230_z
		// @86: ldc "kPYn\u0013OJYkRK]\u0010pVLKQzV\u001fQC=CM]VtKZ\\\u0010jZKP\u0010?\u000f\\W\\ \n\u000f\u0001\u0000[u\u0001l_=\u000f\u001a\t\u000e'\u000f\u0010[_q\r\u001d\u0018_s\u0013FWEo\u0013L[BxVQ\u0016\u000c\u007fA\u0001w^=\u000f\u001a\t\u000e:@\u001fKSoVZV\u001c=ZK\u0018Gt_S\u0018Rx\u0013OJU{ZG]T=DVLX=\u0011\u0003[_q\u000ey~\u0006-\u0005\u000f\u0006vo\\R\u0018\u000c8\u0003\u0001\u0002\u000c2PPT\u000e?\u001f\u001fOXtPW\u0018Yn\u000f]J\u000e|\u0013[QV{VM]^i\u0013S]^zGW\u0018QsW\u001fUQd\u0013S]QkV\u001fTUn@\u001fJ_r^\u001f^_o\u0013KPU=^ZKC|TZ\u0018Yi@ZTV3\u000f]J\u000e!QM\u0006duZL\u0018CuR[Q^z\u0013\\WFxAL\u0018DuV\u001fYBxR\u001fOXtPW\u0018Yn\u0013QWD=RIYYqR]TU=\\Q\u0018\u000c8\u0002\u0001\u001fC=@\\JUx]\u0011\u0004Ro\roJ_kZ[]T=JPMB=^ZKC|TZ\u0018VtGL\u0018Dr\u0013KPU=_Z^D=\\Y\u0018DuV\u001fKX|WZ\\\u0010|AZY\u001c!QM\u0006\u000c8\u0002\u0001\u0018Cu\\JTT=QZ\u0018Q\u007f_Z\u0018Dr\u0013L]U=ZK\u0018Ys\u0013YM\\q\u001d\u0003ZB#\u000f]J\u000e5}PLU'\u0013KPYn\u0013RYI=QZ\u0018YsR\\[EoRK]\u0010tU\u001f\u0004\u0015,\r\u001fQC=CSYIt]X\u0018Ys\u0013^\u0018TtUY]Bx]K\u0004Ro\rSY^zF^_U=UMW]=JPM\u001e4"
		// @88: invokestatic game.C_100321_hi.func_107210_z(java.lang.String)char[]
		// @8B: invokestatic game.C_100321_hi.func_107208_z(char[])java.lang.String
		// @8E: putstatic java.lang.String game.C_100321_hi.field_107223_o
		// @91: sipush 500 (0x01F4)
		// @94: putstatic int game.C_100321_hi.field_107219_b
		// @97: ldc "zVDxA\u001fVQpV\u001fWV=UMQUsW\u001fL_=WZTUiV\u001f^Br^\u001fTYnG"
		// @99: invokestatic game.C_100321_hi.func_107210_z(java.lang.String)char[]
		// @9C: invokestatic game.C_100321_hi.func_107208_z(char[])java.lang.String
		// @9F: putstatic java.lang.String game.C_100321_hi.field_107221_a
		// @A2: ldc "|W^sV\\LYr]\u001fLYpV[\u0018_hG\u0011\u0018`qV^KU=GMA\u0010h@VVW=R\u001f\\Y{UZJUsG\u001fKUoEZJ\u001e"
		// @A4: invokestatic game.C_100321_hi.func_107210_z(java.lang.String)char[]
		// @A7: invokestatic game.C_100321_hi.func_107208_z(char[])java.lang.String
		// @AA: putstatic java.lang.String game.C_100321_hi.field_107227_k
		// @AD: iconst_3
		// @AE: anewarray boolean[]
		// @B1: dup
		// @B2: iconst_0
		// @B3: aconst_null
		// @B4: aastore
		// @B5: dup
		// @B6: iconst_1
		// @B7: aconst_null
		// @B8: aastore
		// @B9: dup
		// @BA: iconst_2
		// @BB: bipush 6 (0x06)
		// @BD: newarray boolean[]
		// @BF: dup
		// @C0: iconst_0
		// @C1: iconst_0
		// @C2: bastore
		// @C3: dup
		// @C4: iconst_1
		// @C5: iconst_0
		// @C6: bastore
		// @C7: dup
		// @C8: iconst_2
		// @C9: iconst_0
		// @CA: bastore
		// @CB: dup
		// @CC: iconst_3
		// @CD: iconst_0
		// @CE: bastore
		// @CF: dup
		// @D0: iconst_4
		// @D1: iconst_0
		// @D2: bastore
		// @D3: dup
		// @D4: iconst_5
		// @D5: iconst_1
		// @D6: bastore
		// @D7: aastore
		// @D8: putstatic boolean[][] game.C_100321_hi.field_107225_m
		// @DB: bipush 47 (0x2F)
		// @DD: putstatic char game.C_100321_hi.field_107218_e
		// @E0: return
	}
	
	private static char[] func_107210_z(String arg0)
	{
		// @00: aload_0
		// @01: invokevirtual java.lang.String.toCharArray()char[]
		// @04: dup
		// @05: arraylength
		// @06: iconst_2
		// @07: if_icmpge @13
		// @0A: dup
		// @0B: iconst_0
		// @0C: dup2
		// @0D: caload
		// @0E: bipush 51 (0x33)
		// @10: ixor
		// @11: i2c
		// @12: castore
		// @13: areturn
	}
	
	private static String func_107208_z(char[] arg0)
	{
		// @00: aload_0
		// @01: dup
		// @02: arraylength
		// @03: swap
		// @04: iconst_0
		// @05: istore_1
		// @06: goto @4C
		// @09: dup
		// @0A: iload_1
		// @0B: dup2
		// @0C: caload
		// @0D: iload_1
		// @0E: iconst_5
		// @0F: irem
		// @10: tableswitch def: @44, for 0: @30, for 1: @35, for 2: @3A, for 3: @3F
		// @30: bipush 63 (0x3F)
		// @32: goto @46
		// @35: bipush 56 (0x38)
		// @37: goto @46
		// @3A: bipush 48 (0x30)
		// @3C: goto @46
		// @3F: bipush 29 (0x1D)
		// @41: goto @46
		// @44: bipush 51 (0x33)
		// @46: ixor
		// @47: i2c
		// @48: castore
		// @49: iinc #1 +1
		// @4C: swap
		// @4D: dup_x1
		// @4E: iload_1
		// @4F: if_icmpgt @09
		// @52: new java.lang.String
		// @55: dup_x1
		// @56: swap
		// @57: invokespecial java.lang.String.<init>(char[])void
		// @5A: invokevirtual java.lang.String.intern()java.lang.String
		// @5D: areturn
	}
}
