package game;

final class C_100135_ti
{
	private static C_100299_kd field_105022_a;
	
	public static void func_105016_a()
	{
		// @0: aconst_null
		// @1: putstatic game.C_100299_kd game.C_100135_ti.field_105022_a
		// @4: return
	}
	
	private static final void func_105017_a(int[] arg0, int[] arg1, int[] arg2, byte[] arg3, int arg4, int arg5, int arg6)
	{
		// @00: iconst_0
		// @01: istore #7
		// @03: iload #4
		// @05: istore #8
		// @07: iload #8
		// @09: iload #5
		// @0B: if_icmpgt @36
		// @0E: iconst_0
		// @0F: istore #9
		// @11: iload #9
		// @13: iload #6
		// @15: if_icmpge @30
		// @18: aload_3
		// @19: iload #9
		// @1B: baload
		// @1C: iload #8
		// @1E: if_icmpne @2A
		// @21: aload_2
		// @22: iload #7
		// @24: iload #9
		// @26: iastore
		// @27: iinc #7 +1
		// @2A: iinc #9 +1
		// @2D: goto @11
		// @30: iinc #8 +1
		// @33: goto @07
		// @36: iconst_0
		// @37: istore #8
		// @39: iload #8
		// @3B: bipush 23 (0x17)
		// @3D: if_icmpge @4B
		// @40: aload_1
		// @41: iload #8
		// @43: iconst_0
		// @44: iastore
		// @45: iinc #8 +1
		// @48: goto @39
		// @4B: iconst_0
		// @4C: istore #8
		// @4E: iload #8
		// @50: iload #6
		// @52: if_icmpge @67
		// @55: aload_1
		// @56: aload_3
		// @57: iload #8
		// @59: baload
		// @5A: iconst_1
		// @5B: iadd
		// @5C: dup2
		// @5D: iaload
		// @5E: iconst_1
		// @5F: iadd
		// @60: iastore
		// @61: iinc #8 +1
		// @64: goto @4E
		// @67: iconst_1
		// @68: istore #8
		// @6A: iload #8
		// @6C: bipush 23 (0x17)
		// @6E: if_icmpge @84
		// @71: aload_1
		// @72: iload #8
		// @74: dup2
		// @75: iaload
		// @76: aload_1
		// @77: iload #8
		// @79: iconst_1
		// @7A: isub
		// @7B: iaload
		// @7C: iadd
		// @7D: iastore
		// @7E: iinc #8 +1
		// @81: goto @6A
		// @84: iconst_0
		// @85: istore #8
		// @87: iload #8
		// @89: bipush 23 (0x17)
		// @8B: if_icmpge @99
		// @8E: aload_0
		// @8F: iload #8
		// @91: iconst_0
		// @92: iastore
		// @93: iinc #8 +1
		// @96: goto @87
		// @99: iconst_0
		// @9A: istore #10
		// @9C: iload #4
		// @9E: istore #8
		// @A0: iload #8
		// @A2: iload #5
		// @A4: if_icmpgt @CB
		// @A7: iload #10
		// @A9: aload_1
		// @AA: iload #8
		// @AC: iconst_1
		// @AD: iadd
		// @AE: iaload
		// @AF: aload_1
		// @B0: iload #8
		// @B2: iaload
		// @B3: isub
		// @B4: iadd
		// @B5: istore #10
		// @B7: aload_0
		// @B8: iload #8
		// @BA: iload #10
		// @BC: iconst_1
		// @BD: isub
		// @BE: iastore
		// @BF: iload #10
		// @C1: iconst_1
		// @C2: ishl
		// @C3: istore #10
		// @C5: iinc #8 +1
		// @C8: goto @A0
		// @CB: iload #4
		// @CD: iconst_1
		// @CE: iadd
		// @CF: istore #8
		// @D1: iload #8
		// @D3: iload #5
		// @D5: if_icmpgt @F1
		// @D8: aload_1
		// @D9: iload #8
		// @DB: aload_0
		// @DC: iload #8
		// @DE: iconst_1
		// @DF: isub
		// @E0: iaload
		// @E1: iconst_1
		// @E2: iadd
		// @E3: iconst_1
		// @E4: ishl
		// @E5: aload_1
		// @E6: iload #8
		// @E8: iaload
		// @E9: isub
		// @EA: iastore
		// @EB: iinc #8 +1
		// @EE: goto @D1
		// @F1: return
	}
	
	private static final byte func_105013_c(C_100299_kd arg0)
	{
		// @0: iconst_1
		// @1: aload_0
		// @2: invokestatic game.C_100135_ti.func_105021_a(int, game.C_100299_kd)int
		// @5: i2b
		// @6: ireturn
	}
	
	private static final void func_105014_a(C_100299_kd arg0)
	{
		// @000: aload_0
		// @001: getfield byte game.C_100299_kd.field_107047_s
		// @004: istore_2
		// @005: aload_0
		// @006: getfield int game.C_100299_kd.field_107033_c
		// @009: istore_3
		// @00A: aload_0
		// @00B: getfield int game.C_100299_kd.field_107016_D
		// @00E: istore #4
		// @010: aload_0
		// @011: getfield int game.C_100299_kd.field_107021_B
		// @014: istore #5
		// @016: getstatic int[] game.C_100159_sn.field_105403_c
		// @019: astore #6
		// @01B: aload_0
		// @01C: getfield int game.C_100299_kd.field_107034_a
		// @01F: istore #7
		// @021: aload_0
		// @022: getfield byte[] game.C_100299_kd.field_107053_x
		// @025: astore #8
		// @027: aload_0
		// @028: getfield int game.C_100299_kd.field_107035_n
		// @02B: istore #9
		// @02D: aload_0
		// @02E: getfield int game.C_100299_kd.field_107044_v
		// @031: istore #10
		// @033: iload #10
		// @035: istore #11
		// @037: aload_0
		// @038: getfield int game.C_100299_kd.field_107020_A
		// @03B: iconst_1
		// @03C: iadd
		// @03D: istore #12
		// @03F: iload_3
		// @040: ifle @07B
		// @043: iload #10
		// @045: ifne @04B
		// @048: goto @172
		// @04B: iload_3
		// @04C: iconst_1
		// @04D: if_icmpne @053
		// @050: goto @065
		// @053: aload #8
		// @055: iload #9
		// @057: iload_2
		// @058: bastore
		// @059: iinc #3 +255
		// @05C: iinc #9 +1
		// @05F: iinc #10 +255
		// @062: goto @043
		// @065: iload #10
		// @067: ifne @06F
		// @06A: iconst_1
		// @06B: istore_3
		// @06C: goto @172
		// @06F: aload #8
		// @071: iload #9
		// @073: iload_2
		// @074: bastore
		// @075: iinc #9 +1
		// @078: iinc #10 +255
		// @07B: iload #4
		// @07D: iload #12
		// @07F: if_icmpne @087
		// @082: iconst_0
		// @083: istore_3
		// @084: goto @172
		// @087: iload #5
		// @089: i2b
		// @08A: istore_2
		// @08B: aload #6
		// @08D: iload #7
		// @08F: iaload
		// @090: istore #7
		// @092: iload #7
		// @094: i2b
		// @095: istore_1
		// @096: iload #7
		// @098: bipush 8 (0x08)
		// @09A: ishr
		// @09B: istore #7
		// @09D: iinc #4 +1
		// @0A0: iload_1
		// @0A1: iload #5
		// @0A3: if_icmpeq @0C2
		// @0A6: iload_1
		// @0A7: istore #5
		// @0A9: iload #10
		// @0AB: ifne @0B3
		// @0AE: iconst_1
		// @0AF: istore_3
		// @0B0: goto @172
		// @0B3: aload #8
		// @0B5: iload #9
		// @0B7: iload_2
		// @0B8: bastore
		// @0B9: iinc #9 +1
		// @0BC: iinc #10 +255
		// @0BF: goto @07B
		// @0C2: iload #4
		// @0C4: iload #12
		// @0C6: if_icmpne @0E2
		// @0C9: iload #10
		// @0CB: ifne @0D3
		// @0CE: iconst_1
		// @0CF: istore_3
		// @0D0: goto @172
		// @0D3: aload #8
		// @0D5: iload #9
		// @0D7: iload_2
		// @0D8: bastore
		// @0D9: iinc #9 +1
		// @0DC: iinc #10 +255
		// @0DF: goto @07B
		// @0E2: iconst_2
		// @0E3: istore_3
		// @0E4: aload #6
		// @0E6: iload #7
		// @0E8: iaload
		// @0E9: istore #7
		// @0EB: iload #7
		// @0ED: i2b
		// @0EE: istore_1
		// @0EF: iload #7
		// @0F1: bipush 8 (0x08)
		// @0F3: ishr
		// @0F4: istore #7
		// @0F6: iinc #4 +1
		// @0F9: iload #4
		// @0FB: iload #12
		// @0FD: if_icmpne @103
		// @100: goto @03F
		// @103: iload_1
		// @104: iload #5
		// @106: if_icmpeq @10F
		// @109: iload_1
		// @10A: istore #5
		// @10C: goto @03F
		// @10F: iconst_3
		// @110: istore_3
		// @111: aload #6
		// @113: iload #7
		// @115: iaload
		// @116: istore #7
		// @118: iload #7
		// @11A: i2b
		// @11B: istore_1
		// @11C: iload #7
		// @11E: bipush 8 (0x08)
		// @120: ishr
		// @121: istore #7
		// @123: iinc #4 +1
		// @126: iload #4
		// @128: iload #12
		// @12A: if_icmpne @130
		// @12D: goto @03F
		// @130: iload_1
		// @131: iload #5
		// @133: if_icmpeq @13C
		// @136: iload_1
		// @137: istore #5
		// @139: goto @03F
		// @13C: aload #6
		// @13E: iload #7
		// @140: iaload
		// @141: istore #7
		// @143: iload #7
		// @145: i2b
		// @146: istore_1
		// @147: iload #7
		// @149: bipush 8 (0x08)
		// @14B: ishr
		// @14C: istore #7
		// @14E: iinc #4 +1
		// @151: iload_1
		// @152: sipush 255 (0x00FF)
		// @155: iand
		// @156: iconst_4
		// @157: iadd
		// @158: istore_3
		// @159: aload #6
		// @15B: iload #7
		// @15D: iaload
		// @15E: istore #7
		// @160: iload #7
		// @162: i2b
		// @163: istore #5
		// @165: iload #7
		// @167: bipush 8 (0x08)
		// @169: ishr
		// @16A: istore #7
		// @16C: iinc #4 +1
		// @16F: goto @03F
		// @172: aload_0
		// @173: getfield int game.C_100299_kd.field_107041_h
		// @176: istore #13
		// @178: aload_0
		// @179: dup
		// @17A: getfield int game.C_100299_kd.field_107041_h
		// @17D: iload #11
		// @17F: iload #10
		// @181: isub
		// @182: iadd
		// @183: putfield int game.C_100299_kd.field_107041_h
		// @186: aload_0
		// @187: getfield int game.C_100299_kd.field_107041_h
		// @18A: iload #13
		// @18C: if_icmpge @18F
		// @18F: aload_0
		// @190: iload_2
		// @191: putfield byte game.C_100299_kd.field_107047_s
		// @194: aload_0
		// @195: iload_3
		// @196: putfield int game.C_100299_kd.field_107033_c
		// @199: aload_0
		// @19A: iload #4
		// @19C: putfield int game.C_100299_kd.field_107016_D
		// @19F: aload_0
		// @1A0: iload #5
		// @1A2: putfield int game.C_100299_kd.field_107021_B
		// @1A5: aload #6
		// @1A7: putstatic int[] game.C_100159_sn.field_105403_c
		// @1AA: aload_0
		// @1AB: iload #7
		// @1AD: putfield int game.C_100299_kd.field_107034_a
		// @1B0: aload_0
		// @1B1: aload #8
		// @1B3: putfield byte[] game.C_100299_kd.field_107053_x
		// @1B6: aload_0
		// @1B7: iload #9
		// @1B9: putfield int game.C_100299_kd.field_107035_n
		// @1BC: aload_0
		// @1BD: iload #10
		// @1BF: putfield int game.C_100299_kd.field_107044_v
		// @1C2: return
	}
	
	private static final byte func_105020_b(C_100299_kd arg0)
	{
		// @0: bipush 8 (0x08)
		// @2: aload_0
		// @3: invokestatic game.C_100135_ti.func_105021_a(int, game.C_100299_kd)int
		// @6: i2b
		// @7: ireturn
	}
	
	private static final int func_105021_a(int arg0, C_100299_kd arg1)
	{
		// @00: aload_1
		// @01: getfield int game.C_100299_kd.field_107037_l
		// @04: iload_0
		// @05: if_icmplt @26
		// @08: aload_1
		// @09: getfield int game.C_100299_kd.field_107042_i
		// @0C: aload_1
		// @0D: getfield int game.C_100299_kd.field_107037_l
		// @10: iload_0
		// @11: isub
		// @12: ishr
		// @13: iconst_1
		// @14: iload_0
		// @15: ishl
		// @16: iconst_1
		// @17: isub
		// @18: iand
		// @19: istore_2
		// @1A: aload_1
		// @1B: dup
		// @1C: getfield int game.C_100299_kd.field_107037_l
		// @1F: iload_0
		// @20: isub
		// @21: putfield int game.C_100299_kd.field_107037_l
		// @24: iload_2
		// @25: ireturn
		// @26: aload_1
		// @27: aload_1
		// @28: getfield int game.C_100299_kd.field_107042_i
		// @2B: bipush 8 (0x08)
		// @2D: ishl
		// @2E: aload_1
		// @2F: getfield byte[] game.C_100299_kd.field_107025_I
		// @32: aload_1
		// @33: getfield int game.C_100299_kd.field_107030_d
		// @36: baload
		// @37: sipush 255 (0x00FF)
		// @3A: iand
		// @3B: ior
		// @3C: putfield int game.C_100299_kd.field_107042_i
		// @3F: aload_1
		// @40: dup
		// @41: getfield int game.C_100299_kd.field_107037_l
		// @44: bipush 8 (0x08)
		// @46: iadd
		// @47: putfield int game.C_100299_kd.field_107037_l
		// @4A: aload_1
		// @4B: dup
		// @4C: getfield int game.C_100299_kd.field_107030_d
		// @4F: iconst_1
		// @50: iadd
		// @51: putfield int game.C_100299_kd.field_107030_d
		// @54: aload_1
		// @55: dup
		// @56: getfield int game.C_100299_kd.field_107026_J
		// @59: iconst_1
		// @5A: iadd
		// @5B: putfield int game.C_100299_kd.field_107026_J
		// @5E: aload_1
		// @5F: getfield int game.C_100299_kd.field_107026_J
		// @62: ifne @00
		// @65: goto @00
	}
	
	private static final void func_105015_e(C_100299_kd arg0)
	{
		// @000: iconst_0
		// @001: istore #4
		// @003: iconst_0
		// @004: istore #5
		// @006: iconst_0
		// @007: istore #6
		// @009: iconst_0
		// @00A: istore #7
		// @00C: iconst_0
		// @00D: istore #8
		// @00F: iconst_0
		// @010: istore #9
		// @012: iconst_0
		// @013: istore #10
		// @015: iconst_0
		// @016: istore #11
		// @018: iconst_0
		// @019: istore #12
		// @01B: iconst_0
		// @01C: istore #13
		// @01E: iconst_0
		// @01F: istore #14
		// @021: iconst_0
		// @022: istore #15
		// @024: iconst_0
		// @025: istore #16
		// @027: iconst_0
		// @028: istore #17
		// @02A: iconst_0
		// @02B: istore #18
		// @02D: iconst_0
		// @02E: istore #19
		// @030: iconst_0
		// @031: istore #20
		// @033: iconst_0
		// @034: istore #21
		// @036: iconst_0
		// @037: istore #22
		// @039: aconst_null
		// @03A: astore #23
		// @03C: aconst_null
		// @03D: astore #24
		// @03F: aconst_null
		// @040: astore #25
		// @042: aload_0
		// @043: iconst_1
		// @044: putfield int game.C_100299_kd.field_107017_E
		// @047: getstatic int[] game.C_100159_sn.field_105403_c
		// @04A: ifnonnull @059
		// @04D: aload_0
		// @04E: getfield int game.C_100299_kd.field_107017_E
		// @051: ldc 100000 (0x186a0)
		// @053: imul
		// @054: newarray int[]
		// @056: putstatic int[] game.C_100159_sn.field_105403_c
		// @059: iconst_1
		// @05A: istore #26
		// @05C: iload #26
		// @05E: ifeq @81C
		// @061: aload_0
		// @062: invokestatic game.C_100135_ti.func_105020_b(game.C_100299_kd)byte
		// @065: istore_1
		// @066: iload_1
		// @067: bipush 23 (0x17)
		// @069: if_icmpne @06D
		// @06C: return
		// @06D: aload_0
		// @06E: invokestatic game.C_100135_ti.func_105020_b(game.C_100299_kd)byte
		// @071: istore_1
		// @072: aload_0
		// @073: invokestatic game.C_100135_ti.func_105020_b(game.C_100299_kd)byte
		// @076: istore_1
		// @077: aload_0
		// @078: invokestatic game.C_100135_ti.func_105020_b(game.C_100299_kd)byte
		// @07B: istore_1
		// @07C: aload_0
		// @07D: invokestatic game.C_100135_ti.func_105020_b(game.C_100299_kd)byte
		// @080: istore_1
		// @081: aload_0
		// @082: invokestatic game.C_100135_ti.func_105020_b(game.C_100299_kd)byte
		// @085: istore_1
		// @086: aload_0
		// @087: invokestatic game.C_100135_ti.func_105020_b(game.C_100299_kd)byte
		// @08A: istore_1
		// @08B: aload_0
		// @08C: invokestatic game.C_100135_ti.func_105020_b(game.C_100299_kd)byte
		// @08F: istore_1
		// @090: aload_0
		// @091: invokestatic game.C_100135_ti.func_105020_b(game.C_100299_kd)byte
		// @094: istore_1
		// @095: aload_0
		// @096: invokestatic game.C_100135_ti.func_105020_b(game.C_100299_kd)byte
		// @099: istore_1
		// @09A: aload_0
		// @09B: invokestatic game.C_100135_ti.func_105013_c(game.C_100299_kd)byte
		// @09E: istore_1
		// @09F: iload_1
		// @0A0: ifeq @0A3
		// @0A3: aload_0
		// @0A4: iconst_0
		// @0A5: putfield int game.C_100299_kd.field_107024_H
		// @0A8: aload_0
		// @0A9: invokestatic game.C_100135_ti.func_105020_b(game.C_100299_kd)byte
		// @0AC: istore_1
		// @0AD: aload_0
		// @0AE: aload_0
		// @0AF: getfield int game.C_100299_kd.field_107024_H
		// @0B2: bipush 8 (0x08)
		// @0B4: ishl
		// @0B5: iload_1
		// @0B6: sipush 255 (0x00FF)
		// @0B9: iand
		// @0BA: ior
		// @0BB: putfield int game.C_100299_kd.field_107024_H
		// @0BE: aload_0
		// @0BF: invokestatic game.C_100135_ti.func_105020_b(game.C_100299_kd)byte
		// @0C2: istore_1
		// @0C3: aload_0
		// @0C4: aload_0
		// @0C5: getfield int game.C_100299_kd.field_107024_H
		// @0C8: bipush 8 (0x08)
		// @0CA: ishl
		// @0CB: iload_1
		// @0CC: sipush 255 (0x00FF)
		// @0CF: iand
		// @0D0: ior
		// @0D1: putfield int game.C_100299_kd.field_107024_H
		// @0D4: aload_0
		// @0D5: invokestatic game.C_100135_ti.func_105020_b(game.C_100299_kd)byte
		// @0D8: istore_1
		// @0D9: aload_0
		// @0DA: aload_0
		// @0DB: getfield int game.C_100299_kd.field_107024_H
		// @0DE: bipush 8 (0x08)
		// @0E0: ishl
		// @0E1: iload_1
		// @0E2: sipush 255 (0x00FF)
		// @0E5: iand
		// @0E6: ior
		// @0E7: putfield int game.C_100299_kd.field_107024_H
		// @0EA: iconst_0
		// @0EB: istore #4
		// @0ED: iload #4
		// @0EF: bipush 16 (0x10)
		// @0F1: if_icmpge @117
		// @0F4: aload_0
		// @0F5: invokestatic game.C_100135_ti.func_105013_c(game.C_100299_kd)byte
		// @0F8: istore_1
		// @0F9: iload_1
		// @0FA: iconst_1
		// @0FB: if_icmpne @109
		// @0FE: aload_0
		// @0FF: getfield boolean[] game.C_100299_kd.field_107039_j
		// @102: iload #4
		// @104: iconst_1
		// @105: bastore
		// @106: goto @111
		// @109: aload_0
		// @10A: getfield boolean[] game.C_100299_kd.field_107039_j
		// @10D: iload #4
		// @10F: iconst_0
		// @110: bastore
		// @111: iinc #4 +1
		// @114: goto @0ED
		// @117: iconst_0
		// @118: istore #4
		// @11A: iload #4
		// @11C: sipush 256 (0x0100)
		// @11F: if_icmpge @130
		// @122: aload_0
		// @123: getfield boolean[] game.C_100299_kd.field_107050_p
		// @126: iload #4
		// @128: iconst_0
		// @129: bastore
		// @12A: iinc #4 +1
		// @12D: goto @11A
		// @130: iconst_0
		// @131: istore #4
		// @133: iload #4
		// @135: bipush 16 (0x10)
		// @137: if_icmpge @172
		// @13A: aload_0
		// @13B: getfield boolean[] game.C_100299_kd.field_107039_j
		// @13E: iload #4
		// @140: baload
		// @141: ifeq @16C
		// @144: iconst_0
		// @145: istore #5
		// @147: iload #5
		// @149: bipush 16 (0x10)
		// @14B: if_icmpge @16C
		// @14E: aload_0
		// @14F: invokestatic game.C_100135_ti.func_105013_c(game.C_100299_kd)byte
		// @152: istore_1
		// @153: iload_1
		// @154: iconst_1
		// @155: if_icmpne @166
		// @158: aload_0
		// @159: getfield boolean[] game.C_100299_kd.field_107050_p
		// @15C: iload #4
		// @15E: bipush 16 (0x10)
		// @160: imul
		// @161: iload #5
		// @163: iadd
		// @164: iconst_1
		// @165: bastore
		// @166: iinc #5 +1
		// @169: goto @147
		// @16C: iinc #4 +1
		// @16F: goto @133
		// @172: aload_0
		// @173: invokestatic game.C_100135_ti.func_105018_d(game.C_100299_kd)void
		// @176: aload_0
		// @177: getfield int game.C_100299_kd.field_107036_o
		// @17A: iconst_2
		// @17B: iadd
		// @17C: istore #7
		// @17E: iconst_3
		// @17F: aload_0
		// @180: invokestatic game.C_100135_ti.func_105021_a(int, game.C_100299_kd)int
		// @183: istore #8
		// @185: bipush 15 (0x0F)
		// @187: aload_0
		// @188: invokestatic game.C_100135_ti.func_105021_a(int, game.C_100299_kd)int
		// @18B: istore #9
		// @18D: iconst_0
		// @18E: istore #4
		// @190: iload #4
		// @192: iload #9
		// @194: if_icmpge @1BC
		// @197: iconst_0
		// @198: istore #5
		// @19A: aload_0
		// @19B: invokestatic game.C_100135_ti.func_105013_c(game.C_100299_kd)byte
		// @19E: istore_1
		// @19F: iload_1
		// @1A0: ifne @1A6
		// @1A3: goto @1AC
		// @1A6: iinc #5 +1
		// @1A9: goto @19A
		// @1AC: aload_0
		// @1AD: getfield byte[] game.C_100299_kd.field_107052_y
		// @1B0: iload #4
		// @1B2: iload #5
		// @1B4: i2b
		// @1B5: bastore
		// @1B6: iinc #4 +1
		// @1B9: goto @190
		// @1BC: bipush 6 (0x06)
		// @1BE: newarray byte[]
		// @1C0: astore #27
		// @1C2: iconst_0
		// @1C3: istore #29
		// @1C5: iload #29
		// @1C7: iload #8
		// @1C9: if_icmpge @1DD
		// @1CC: aload #27
		// @1CE: iload #29
		// @1D0: iload #29
		// @1D2: bastore
		// @1D3: iload #29
		// @1D5: iconst_1
		// @1D6: iadd
		// @1D7: i2b
		// @1D8: istore #29
		// @1DA: goto @1C5
		// @1DD: iconst_0
		// @1DE: istore #4
		// @1E0: iload #4
		// @1E2: iload #9
		// @1E4: if_icmpge @227
		// @1E7: aload_0
		// @1E8: getfield byte[] game.C_100299_kd.field_107052_y
		// @1EB: iload #4
		// @1ED: baload
		// @1EE: istore #29
		// @1F0: aload #27
		// @1F2: iload #29
		// @1F4: baload
		// @1F5: istore #28
		// @1F7: iload #29
		// @1F9: ifle @212
		// @1FC: aload #27
		// @1FE: iload #29
		// @200: aload #27
		// @202: iload #29
		// @204: iconst_1
		// @205: isub
		// @206: baload
		// @207: bastore
		// @208: iload #29
		// @20A: iconst_1
		// @20B: isub
		// @20C: i2b
		// @20D: istore #29
		// @20F: goto @1F7
		// @212: aload #27
		// @214: iconst_0
		// @215: iload #28
		// @217: bastore
		// @218: aload_0
		// @219: getfield byte[] game.C_100299_kd.field_107031_e
		// @21C: iload #4
		// @21E: iload #28
		// @220: bastore
		// @221: iinc #4 +1
		// @224: goto @1E0
		// @227: iconst_0
		// @228: istore #6
		// @22A: iload #6
		// @22C: iload #8
		// @22E: if_icmpge @27C
		// @231: iconst_5
		// @232: aload_0
		// @233: invokestatic game.C_100135_ti.func_105021_a(int, game.C_100299_kd)int
		// @236: istore #17
		// @238: iconst_0
		// @239: istore #4
		// @23B: iload #4
		// @23D: iload #7
		// @23F: if_icmpge @276
		// @242: aload_0
		// @243: invokestatic game.C_100135_ti.func_105013_c(game.C_100299_kd)byte
		// @246: istore_1
		// @247: iload_1
		// @248: ifne @24E
		// @24B: goto @263
		// @24E: aload_0
		// @24F: invokestatic game.C_100135_ti.func_105013_c(game.C_100299_kd)byte
		// @252: istore_1
		// @253: iload_1
		// @254: ifne @25D
		// @257: iinc #17 +1
		// @25A: goto @242
		// @25D: iinc #17 +255
		// @260: goto @242
		// @263: aload_0
		// @264: getfield byte[][] game.C_100299_kd.field_107019_G
		// @267: iload #6
		// @269: aaload
		// @26A: iload #4
		// @26C: iload #17
		// @26E: i2b
		// @26F: bastore
		// @270: iinc #4 +1
		// @273: goto @23B
		// @276: iinc #6 +1
		// @279: goto @22A
		// @27C: iconst_0
		// @27D: istore #6
		// @27F: iload #6
		// @281: iload #8
		// @283: if_icmpge @2FE
		// @286: bipush 32 (0x20)
		// @288: istore_2
		// @289: iconst_0
		// @28A: istore_3
		// @28B: iconst_0
		// @28C: istore #4
		// @28E: iload #4
		// @290: iload #7
		// @292: if_icmpge @2CD
		// @295: aload_0
		// @296: getfield byte[][] game.C_100299_kd.field_107019_G
		// @299: iload #6
		// @29B: aaload
		// @29C: iload #4
		// @29E: baload
		// @29F: iload_3
		// @2A0: if_icmple @2AE
		// @2A3: aload_0
		// @2A4: getfield byte[][] game.C_100299_kd.field_107019_G
		// @2A7: iload #6
		// @2A9: aaload
		// @2AA: iload #4
		// @2AC: baload
		// @2AD: istore_3
		// @2AE: aload_0
		// @2AF: getfield byte[][] game.C_100299_kd.field_107019_G
		// @2B2: iload #6
		// @2B4: aaload
		// @2B5: iload #4
		// @2B7: baload
		// @2B8: iload_2
		// @2B9: if_icmpge @2C7
		// @2BC: aload_0
		// @2BD: getfield byte[][] game.C_100299_kd.field_107019_G
		// @2C0: iload #6
		// @2C2: aaload
		// @2C3: iload #4
		// @2C5: baload
		// @2C6: istore_2
		// @2C7: iinc #4 +1
		// @2CA: goto @28E
		// @2CD: aload_0
		// @2CE: getfield int[][] game.C_100299_kd.field_107032_b
		// @2D1: iload #6
		// @2D3: aaload
		// @2D4: aload_0
		// @2D5: getfield int[][] game.C_100299_kd.field_107038_m
		// @2D8: iload #6
		// @2DA: aaload
		// @2DB: aload_0
		// @2DC: getfield int[][] game.C_100299_kd.field_107028_f
		// @2DF: iload #6
		// @2E1: aaload
		// @2E2: aload_0
		// @2E3: getfield byte[][] game.C_100299_kd.field_107019_G
		// @2E6: iload #6
		// @2E8: aaload
		// @2E9: iload_2
		// @2EA: iload_3
		// @2EB: iload #7
		// @2ED: invokestatic game.C_100135_ti.func_105017_a(int[], int[], int[], byte[], int, int, int)void
		// @2F0: aload_0
		// @2F1: getfield int[] game.C_100299_kd.field_107045_u
		// @2F4: iload #6
		// @2F6: iload_2
		// @2F7: iastore
		// @2F8: iinc #6 +1
		// @2FB: goto @27F
		// @2FE: aload_0
		// @2FF: getfield int game.C_100299_kd.field_107036_o
		// @302: iconst_1
		// @303: iadd
		// @304: istore #10
		// @306: iconst_m1
		// @307: istore #11
		// @309: iconst_0
		// @30A: istore #12
		// @30C: iconst_0
		// @30D: istore #4
		// @30F: iload #4
		// @311: sipush 255 (0x00FF)
		// @314: if_icmpgt @325
		// @317: aload_0
		// @318: getfield int[] game.C_100299_kd.field_107049_q
		// @31B: iload #4
		// @31D: iconst_0
		// @31E: iastore
		// @31F: iinc #4 +1
		// @322: goto @30F
		// @325: sipush 4095 (0x0FFF)
		// @328: istore #29
		// @32A: bipush 15 (0x0F)
		// @32C: istore #27
		// @32E: iload #27
		// @330: iflt @366
		// @333: bipush 15 (0x0F)
		// @335: istore #28
		// @337: iload #28
		// @339: iflt @355
		// @33C: aload_0
		// @33D: getfield byte[] game.C_100299_kd.field_107040_k
		// @340: iload #29
		// @342: iload #27
		// @344: bipush 16 (0x10)
		// @346: imul
		// @347: iload #28
		// @349: iadd
		// @34A: i2b
		// @34B: bastore
		// @34C: iinc #29 +255
		// @34F: iinc #28 +255
		// @352: goto @337
		// @355: aload_0
		// @356: getfield int[] game.C_100299_kd.field_107046_t
		// @359: iload #27
		// @35B: iload #29
		// @35D: iconst_1
		// @35E: iadd
		// @35F: iastore
		// @360: iinc #27 +255
		// @363: goto @32E
		// @366: iconst_0
		// @367: istore #14
		// @369: iload #12
		// @36B: ifne @3A2
		// @36E: iinc #11 +1
		// @371: bipush 50 (0x32)
		// @373: istore #12
		// @375: aload_0
		// @376: getfield byte[] game.C_100299_kd.field_107031_e
		// @379: iload #11
		// @37B: baload
		// @37C: istore #21
		// @37E: aload_0
		// @37F: getfield int[] game.C_100299_kd.field_107045_u
		// @382: iload #21
		// @384: iaload
		// @385: istore #22
		// @387: aload_0
		// @388: getfield int[][] game.C_100299_kd.field_107032_b
		// @38B: iload #21
		// @38D: aaload
		// @38E: astore #23
		// @390: aload_0
		// @391: getfield int[][] game.C_100299_kd.field_107028_f
		// @394: iload #21
		// @396: aaload
		// @397: astore #25
		// @399: aload_0
		// @39A: getfield int[][] game.C_100299_kd.field_107038_m
		// @39D: iload #21
		// @39F: aaload
		// @3A0: astore #24
		// @3A2: iinc #12 +255
		// @3A5: iload #22
		// @3A7: istore #18
		// @3A9: iload #18
		// @3AB: aload_0
		// @3AC: invokestatic game.C_100135_ti.func_105021_a(int, game.C_100299_kd)int
		// @3AF: istore #19
		// @3B1: iload #19
		// @3B3: aload #23
		// @3B5: iload #18
		// @3B7: iaload
		// @3B8: if_icmpgt @3BE
		// @3BB: goto @3D3
		// @3BE: iinc #18 +1
		// @3C1: aload_0
		// @3C2: invokestatic game.C_100135_ti.func_105013_c(game.C_100299_kd)byte
		// @3C5: istore #20
		// @3C7: iload #19
		// @3C9: iconst_1
		// @3CA: ishl
		// @3CB: iload #20
		// @3CD: ior
		// @3CE: istore #19
		// @3D0: goto @3B1
		// @3D3: aload #25
		// @3D5: iload #19
		// @3D7: aload #24
		// @3D9: iload #18
		// @3DB: iaload
		// @3DC: isub
		// @3DD: iaload
		// @3DE: istore #13
		// @3E0: iload #13
		// @3E2: iload #10
		// @3E4: if_icmpne @3EA
		// @3E7: goto @71A
		// @3EA: iload #13
		// @3EC: ifeq @3F5
		// @3EF: iload #13
		// @3F1: iconst_1
		// @3F2: if_icmpne @4E3
		// @3F5: iconst_m1
		// @3F6: istore #15
		// @3F8: iconst_1
		// @3F9: istore #16
		// @3FB: iload #13
		// @3FD: ifne @40C
		// @400: iload #15
		// @402: iconst_1
		// @403: iload #16
		// @405: imul
		// @406: iadd
		// @407: istore #15
		// @409: goto @41B
		// @40C: iload #13
		// @40E: iconst_1
		// @40F: if_icmpne @41B
		// @412: iload #15
		// @414: iconst_2
		// @415: iload #16
		// @417: imul
		// @418: iadd
		// @419: istore #15
		// @41B: iload #16
		// @41D: iconst_2
		// @41E: imul
		// @41F: istore #16
		// @421: iload #12
		// @423: ifne @45A
		// @426: iinc #11 +1
		// @429: bipush 50 (0x32)
		// @42B: istore #12
		// @42D: aload_0
		// @42E: getfield byte[] game.C_100299_kd.field_107031_e
		// @431: iload #11
		// @433: baload
		// @434: istore #21
		// @436: aload_0
		// @437: getfield int[] game.C_100299_kd.field_107045_u
		// @43A: iload #21
		// @43C: iaload
		// @43D: istore #22
		// @43F: aload_0
		// @440: getfield int[][] game.C_100299_kd.field_107032_b
		// @443: iload #21
		// @445: aaload
		// @446: astore #23
		// @448: aload_0
		// @449: getfield int[][] game.C_100299_kd.field_107028_f
		// @44C: iload #21
		// @44E: aaload
		// @44F: astore #25
		// @451: aload_0
		// @452: getfield int[][] game.C_100299_kd.field_107038_m
		// @455: iload #21
		// @457: aaload
		// @458: astore #24
		// @45A: iinc #12 +255
		// @45D: iload #22
		// @45F: istore #18
		// @461: iload #18
		// @463: aload_0
		// @464: invokestatic game.C_100135_ti.func_105021_a(int, game.C_100299_kd)int
		// @467: istore #19
		// @469: iload #19
		// @46B: aload #23
		// @46D: iload #18
		// @46F: iaload
		// @470: if_icmpgt @476
		// @473: goto @48B
		// @476: iinc #18 +1
		// @479: aload_0
		// @47A: invokestatic game.C_100135_ti.func_105013_c(game.C_100299_kd)byte
		// @47D: istore #20
		// @47F: iload #19
		// @481: iconst_1
		// @482: ishl
		// @483: iload #20
		// @485: ior
		// @486: istore #19
		// @488: goto @469
		// @48B: aload #25
		// @48D: iload #19
		// @48F: aload #24
		// @491: iload #18
		// @493: iaload
		// @494: isub
		// @495: iaload
		// @496: istore #13
		// @498: iload #13
		// @49A: ifeq @3FB
		// @49D: iload #13
		// @49F: iconst_1
		// @4A0: if_icmpeq @3FB
		// @4A3: iinc #15 +1
		// @4A6: aload_0
		// @4A7: getfield byte[] game.C_100299_kd.field_107043_w
		// @4AA: aload_0
		// @4AB: getfield byte[] game.C_100299_kd.field_107040_k
		// @4AE: aload_0
		// @4AF: getfield int[] game.C_100299_kd.field_107046_t
		// @4B2: iconst_0
		// @4B3: iaload
		// @4B4: baload
		// @4B5: sipush 255 (0x00FF)
		// @4B8: iand
		// @4B9: baload
		// @4BA: istore_1
		// @4BB: aload_0
		// @4BC: getfield int[] game.C_100299_kd.field_107049_q
		// @4BF: iload_1
		// @4C0: sipush 255 (0x00FF)
		// @4C3: iand
		// @4C4: dup2
		// @4C5: iaload
		// @4C6: iload #15
		// @4C8: iadd
		// @4C9: iastore
		// @4CA: iload #15
		// @4CC: ifle @3E0
		// @4CF: getstatic int[] game.C_100159_sn.field_105403_c
		// @4D2: iload #14
		// @4D4: iload_1
		// @4D5: sipush 255 (0x00FF)
		// @4D8: iand
		// @4D9: iastore
		// @4DA: iinc #14 +1
		// @4DD: iinc #15 +255
		// @4E0: goto @4CA
		// @4E3: iload #13
		// @4E5: iconst_1
		// @4E6: isub
		// @4E7: istore #33
		// @4E9: iload #33
		// @4EB: bipush 16 (0x10)
		// @4ED: if_icmpge @588
		// @4F0: aload_0
		// @4F1: getfield int[] game.C_100299_kd.field_107046_t
		// @4F4: iconst_0
		// @4F5: iaload
		// @4F6: istore #30
		// @4F8: aload_0
		// @4F9: getfield byte[] game.C_100299_kd.field_107040_k
		// @4FC: iload #30
		// @4FE: iload #33
		// @500: iadd
		// @501: baload
		// @502: istore_1
		// @503: iload #33
		// @505: iconst_3
		// @506: if_icmple @55C
		// @509: iload #30
		// @50B: iload #33
		// @50D: iadd
		// @50E: istore #34
		// @510: aload_0
		// @511: getfield byte[] game.C_100299_kd.field_107040_k
		// @514: iload #34
		// @516: aload_0
		// @517: getfield byte[] game.C_100299_kd.field_107040_k
		// @51A: iload #34
		// @51C: iconst_1
		// @51D: isub
		// @51E: baload
		// @51F: bastore
		// @520: aload_0
		// @521: getfield byte[] game.C_100299_kd.field_107040_k
		// @524: iload #34
		// @526: iconst_1
		// @527: isub
		// @528: aload_0
		// @529: getfield byte[] game.C_100299_kd.field_107040_k
		// @52C: iload #34
		// @52E: iconst_2
		// @52F: isub
		// @530: baload
		// @531: bastore
		// @532: aload_0
		// @533: getfield byte[] game.C_100299_kd.field_107040_k
		// @536: iload #34
		// @538: iconst_2
		// @539: isub
		// @53A: aload_0
		// @53B: getfield byte[] game.C_100299_kd.field_107040_k
		// @53E: iload #34
		// @540: iconst_3
		// @541: isub
		// @542: baload
		// @543: bastore
		// @544: aload_0
		// @545: getfield byte[] game.C_100299_kd.field_107040_k
		// @548: iload #34
		// @54A: iconst_3
		// @54B: isub
		// @54C: aload_0
		// @54D: getfield byte[] game.C_100299_kd.field_107040_k
		// @550: iload #34
		// @552: iconst_4
		// @553: isub
		// @554: baload
		// @555: bastore
		// @556: iinc #33 +252
		// @559: goto @503
		// @55C: iload #33
		// @55E: ifle @57D
		// @561: aload_0
		// @562: getfield byte[] game.C_100299_kd.field_107040_k
		// @565: iload #30
		// @567: iload #33
		// @569: iadd
		// @56A: aload_0
		// @56B: getfield byte[] game.C_100299_kd.field_107040_k
		// @56E: iload #30
		// @570: iload #33
		// @572: iadd
		// @573: iconst_1
		// @574: isub
		// @575: baload
		// @576: bastore
		// @577: iinc #33 +255
		// @57A: goto @55C
		// @57D: aload_0
		// @57E: getfield byte[] game.C_100299_kd.field_107040_k
		// @581: iload #30
		// @583: iload_1
		// @584: bastore
		// @585: goto @672
		// @588: iload #33
		// @58A: bipush 16 (0x10)
		// @58C: idiv
		// @58D: istore #31
		// @58F: iload #33
		// @591: bipush 16 (0x10)
		// @593: irem
		// @594: istore #32
		// @596: aload_0
		// @597: getfield int[] game.C_100299_kd.field_107046_t
		// @59A: iload #31
		// @59C: iaload
		// @59D: iload #32
		// @59F: iadd
		// @5A0: istore #30
		// @5A2: aload_0
		// @5A3: getfield byte[] game.C_100299_kd.field_107040_k
		// @5A6: iload #30
		// @5A8: baload
		// @5A9: istore_1
		// @5AA: iload #30
		// @5AC: aload_0
		// @5AD: getfield int[] game.C_100299_kd.field_107046_t
		// @5B0: iload #31
		// @5B2: iaload
		// @5B3: if_icmple @5CC
		// @5B6: aload_0
		// @5B7: getfield byte[] game.C_100299_kd.field_107040_k
		// @5BA: iload #30
		// @5BC: aload_0
		// @5BD: getfield byte[] game.C_100299_kd.field_107040_k
		// @5C0: iload #30
		// @5C2: iconst_1
		// @5C3: isub
		// @5C4: baload
		// @5C5: bastore
		// @5C6: iinc #30 +255
		// @5C9: goto @5AA
		// @5CC: aload_0
		// @5CD: getfield int[] game.C_100299_kd.field_107046_t
		// @5D0: iload #31
		// @5D2: dup2
		// @5D3: iaload
		// @5D4: iconst_1
		// @5D5: iadd
		// @5D6: iastore
		// @5D7: iload #31
		// @5D9: ifle @60C
		// @5DC: aload_0
		// @5DD: getfield int[] game.C_100299_kd.field_107046_t
		// @5E0: iload #31
		// @5E2: dup2
		// @5E3: iaload
		// @5E4: iconst_1
		// @5E5: isub
		// @5E6: iastore
		// @5E7: aload_0
		// @5E8: getfield byte[] game.C_100299_kd.field_107040_k
		// @5EB: aload_0
		// @5EC: getfield int[] game.C_100299_kd.field_107046_t
		// @5EF: iload #31
		// @5F1: iaload
		// @5F2: aload_0
		// @5F3: getfield byte[] game.C_100299_kd.field_107040_k
		// @5F6: aload_0
		// @5F7: getfield int[] game.C_100299_kd.field_107046_t
		// @5FA: iload #31
		// @5FC: iconst_1
		// @5FD: isub
		// @5FE: iaload
		// @5FF: bipush 16 (0x10)
		// @601: iadd
		// @602: iconst_1
		// @603: isub
		// @604: baload
		// @605: bastore
		// @606: iinc #31 +255
		// @609: goto @5D7
		// @60C: aload_0
		// @60D: getfield int[] game.C_100299_kd.field_107046_t
		// @610: iconst_0
		// @611: dup2
		// @612: iaload
		// @613: iconst_1
		// @614: isub
		// @615: iastore
		// @616: aload_0
		// @617: getfield byte[] game.C_100299_kd.field_107040_k
		// @61A: aload_0
		// @61B: getfield int[] game.C_100299_kd.field_107046_t
		// @61E: iconst_0
		// @61F: iaload
		// @620: iload_1
		// @621: bastore
		// @622: aload_0
		// @623: getfield int[] game.C_100299_kd.field_107046_t
		// @626: iconst_0
		// @627: iaload
		// @628: ifne @672
		// @62B: sipush 4095 (0x0FFF)
		// @62E: istore #29
		// @630: bipush 15 (0x0F)
		// @632: istore #27
		// @634: iload #27
		// @636: iflt @672
		// @639: bipush 15 (0x0F)
		// @63B: istore #28
		// @63D: iload #28
		// @63F: iflt @661
		// @642: aload_0
		// @643: getfield byte[] game.C_100299_kd.field_107040_k
		// @646: iload #29
		// @648: aload_0
		// @649: getfield byte[] game.C_100299_kd.field_107040_k
		// @64C: aload_0
		// @64D: getfield int[] game.C_100299_kd.field_107046_t
		// @650: iload #27
		// @652: iaload
		// @653: iload #28
		// @655: iadd
		// @656: baload
		// @657: bastore
		// @658: iinc #29 +255
		// @65B: iinc #28 +255
		// @65E: goto @63D
		// @661: aload_0
		// @662: getfield int[] game.C_100299_kd.field_107046_t
		// @665: iload #27
		// @667: iload #29
		// @669: iconst_1
		// @66A: iadd
		// @66B: iastore
		// @66C: iinc #27 +255
		// @66F: goto @634
		// @672: aload_0
		// @673: getfield int[] game.C_100299_kd.field_107049_q
		// @676: aload_0
		// @677: getfield byte[] game.C_100299_kd.field_107043_w
		// @67A: iload_1
		// @67B: sipush 255 (0x00FF)
		// @67E: iand
		// @67F: baload
		// @680: sipush 255 (0x00FF)
		// @683: iand
		// @684: dup2
		// @685: iaload
		// @686: iconst_1
		// @687: iadd
		// @688: iastore
		// @689: getstatic int[] game.C_100159_sn.field_105403_c
		// @68C: iload #14
		// @68E: aload_0
		// @68F: getfield byte[] game.C_100299_kd.field_107043_w
		// @692: iload_1
		// @693: sipush 255 (0x00FF)
		// @696: iand
		// @697: baload
		// @698: sipush 255 (0x00FF)
		// @69B: iand
		// @69C: iastore
		// @69D: iinc #14 +1
		// @6A0: iload #12
		// @6A2: ifne @6D9
		// @6A5: iinc #11 +1
		// @6A8: bipush 50 (0x32)
		// @6AA: istore #12
		// @6AC: aload_0
		// @6AD: getfield byte[] game.C_100299_kd.field_107031_e
		// @6B0: iload #11
		// @6B2: baload
		// @6B3: istore #21
		// @6B5: aload_0
		// @6B6: getfield int[] game.C_100299_kd.field_107045_u
		// @6B9: iload #21
		// @6BB: iaload
		// @6BC: istore #22
		// @6BE: aload_0
		// @6BF: getfield int[][] game.C_100299_kd.field_107032_b
		// @6C2: iload #21
		// @6C4: aaload
		// @6C5: astore #23
		// @6C7: aload_0
		// @6C8: getfield int[][] game.C_100299_kd.field_107028_f
		// @6CB: iload #21
		// @6CD: aaload
		// @6CE: astore #25
		// @6D0: aload_0
		// @6D1: getfield int[][] game.C_100299_kd.field_107038_m
		// @6D4: iload #21
		// @6D6: aaload
		// @6D7: astore #24
		// @6D9: iinc #12 +255
		// @6DC: iload #22
		// @6DE: istore #18
		// @6E0: iload #18
		// @6E2: aload_0
		// @6E3: invokestatic game.C_100135_ti.func_105021_a(int, game.C_100299_kd)int
		// @6E6: istore #19
		// @6E8: iload #19
		// @6EA: aload #23
		// @6EC: iload #18
		// @6EE: iaload
		// @6EF: if_icmpgt @6F5
		// @6F2: goto @70A
		// @6F5: iinc #18 +1
		// @6F8: aload_0
		// @6F9: invokestatic game.C_100135_ti.func_105013_c(game.C_100299_kd)byte
		// @6FC: istore #20
		// @6FE: iload #19
		// @700: iconst_1
		// @701: ishl
		// @702: iload #20
		// @704: ior
		// @705: istore #19
		// @707: goto @6E8
		// @70A: aload #25
		// @70C: iload #19
		// @70E: aload #24
		// @710: iload #18
		// @712: iaload
		// @713: isub
		// @714: iaload
		// @715: istore #13
		// @717: goto @3E0
		// @71A: aload_0
		// @71B: iconst_0
		// @71C: putfield int game.C_100299_kd.field_107033_c
		// @71F: aload_0
		// @720: iconst_0
		// @721: putfield byte game.C_100299_kd.field_107047_s
		// @724: aload_0
		// @725: getfield int[] game.C_100299_kd.field_107048_r
		// @728: iconst_0
		// @729: iconst_0
		// @72A: iastore
		// @72B: iconst_1
		// @72C: istore #4
		// @72E: iload #4
		// @730: sipush 256 (0x0100)
		// @733: if_icmpgt @74C
		// @736: aload_0
		// @737: getfield int[] game.C_100299_kd.field_107048_r
		// @73A: iload #4
		// @73C: aload_0
		// @73D: getfield int[] game.C_100299_kd.field_107049_q
		// @740: iload #4
		// @742: iconst_1
		// @743: isub
		// @744: iaload
		// @745: iastore
		// @746: iinc #4 +1
		// @749: goto @72E
		// @74C: iconst_1
		// @74D: istore #4
		// @74F: iload #4
		// @751: sipush 256 (0x0100)
		// @754: if_icmpgt @770
		// @757: aload_0
		// @758: getfield int[] game.C_100299_kd.field_107048_r
		// @75B: iload #4
		// @75D: dup2
		// @75E: iaload
		// @75F: aload_0
		// @760: getfield int[] game.C_100299_kd.field_107048_r
		// @763: iload #4
		// @765: iconst_1
		// @766: isub
		// @767: iaload
		// @768: iadd
		// @769: iastore
		// @76A: iinc #4 +1
		// @76D: goto @74F
		// @770: iconst_0
		// @771: istore #4
		// @773: iload #4
		// @775: iload #14
		// @777: if_icmpge @7B0
		// @77A: getstatic int[] game.C_100159_sn.field_105403_c
		// @77D: iload #4
		// @77F: iaload
		// @780: sipush 255 (0x00FF)
		// @783: iand
		// @784: i2b
		// @785: istore_1
		// @786: getstatic int[] game.C_100159_sn.field_105403_c
		// @789: aload_0
		// @78A: getfield int[] game.C_100299_kd.field_107048_r
		// @78D: iload_1
		// @78E: sipush 255 (0x00FF)
		// @791: iand
		// @792: iaload
		// @793: dup2
		// @794: iaload
		// @795: iload #4
		// @797: bipush 8 (0x08)
		// @799: ishl
		// @79A: ior
		// @79B: iastore
		// @79C: aload_0
		// @79D: getfield int[] game.C_100299_kd.field_107048_r
		// @7A0: iload_1
		// @7A1: sipush 255 (0x00FF)
		// @7A4: iand
		// @7A5: dup2
		// @7A6: iaload
		// @7A7: iconst_1
		// @7A8: iadd
		// @7A9: iastore
		// @7AA: iinc #4 +1
		// @7AD: goto @773
		// @7B0: aload_0
		// @7B1: getstatic int[] game.C_100159_sn.field_105403_c
		// @7B4: aload_0
		// @7B5: getfield int game.C_100299_kd.field_107024_H
		// @7B8: iaload
		// @7B9: bipush 8 (0x08)
		// @7BB: ishr
		// @7BC: putfield int game.C_100299_kd.field_107034_a
		// @7BF: aload_0
		// @7C0: iconst_0
		// @7C1: putfield int game.C_100299_kd.field_107016_D
		// @7C4: aload_0
		// @7C5: getstatic int[] game.C_100159_sn.field_105403_c
		// @7C8: aload_0
		// @7C9: getfield int game.C_100299_kd.field_107034_a
		// @7CC: iaload
		// @7CD: putfield int game.C_100299_kd.field_107034_a
		// @7D0: aload_0
		// @7D1: aload_0
		// @7D2: getfield int game.C_100299_kd.field_107034_a
		// @7D5: sipush 255 (0x00FF)
		// @7D8: iand
		// @7D9: i2b
		// @7DA: putfield int game.C_100299_kd.field_107021_B
		// @7DD: aload_0
		// @7DE: dup
		// @7DF: getfield int game.C_100299_kd.field_107034_a
		// @7E2: bipush 8 (0x08)
		// @7E4: ishr
		// @7E5: putfield int game.C_100299_kd.field_107034_a
		// @7E8: aload_0
		// @7E9: dup
		// @7EA: getfield int game.C_100299_kd.field_107016_D
		// @7ED: iconst_1
		// @7EE: iadd
		// @7EF: putfield int game.C_100299_kd.field_107016_D
		// @7F2: aload_0
		// @7F3: iload #14
		// @7F5: putfield int game.C_100299_kd.field_107020_A
		// @7F8: aload_0
		// @7F9: invokestatic game.C_100135_ti.func_105014_a(game.C_100299_kd)void
		// @7FC: aload_0
		// @7FD: getfield int game.C_100299_kd.field_107016_D
		// @800: aload_0
		// @801: getfield int game.C_100299_kd.field_107020_A
		// @804: iconst_1
		// @805: iadd
		// @806: if_icmpne @816
		// @809: aload_0
		// @80A: getfield int game.C_100299_kd.field_107033_c
		// @80D: ifne @816
		// @810: iconst_1
		// @811: istore #26
		// @813: goto @05C
		// @816: iconst_0
		// @817: istore #26
		// @819: goto @05C
		// @81C: return
	}
	
	static final int func_105019_a(byte[] arg0, int arg1, byte[] arg2, int arg3, int arg4)
	{
		// @00: getstatic game.C_100299_kd game.C_100135_ti.field_105022_a
		// @03: dup
		// @04: astore #5
		// @06: monitorenter
		// @07: getstatic game.C_100299_kd game.C_100135_ti.field_105022_a
		// @0A: aload_2
		// @0B: putfield byte[] game.C_100299_kd.field_107025_I
		// @0E: getstatic game.C_100299_kd game.C_100135_ti.field_105022_a
		// @11: iload #4
		// @13: putfield int game.C_100299_kd.field_107030_d
		// @16: getstatic game.C_100299_kd game.C_100135_ti.field_105022_a
		// @19: aload_0
		// @1A: putfield byte[] game.C_100299_kd.field_107053_x
		// @1D: getstatic game.C_100299_kd game.C_100135_ti.field_105022_a
		// @20: iconst_0
		// @21: putfield int game.C_100299_kd.field_107035_n
		// @24: getstatic game.C_100299_kd game.C_100135_ti.field_105022_a
		// @27: iload_1
		// @28: putfield int game.C_100299_kd.field_107044_v
		// @2B: getstatic game.C_100299_kd game.C_100135_ti.field_105022_a
		// @2E: iconst_0
		// @2F: putfield int game.C_100299_kd.field_107037_l
		// @32: getstatic game.C_100299_kd game.C_100135_ti.field_105022_a
		// @35: iconst_0
		// @36: putfield int game.C_100299_kd.field_107042_i
		// @39: getstatic game.C_100299_kd game.C_100135_ti.field_105022_a
		// @3C: iconst_0
		// @3D: putfield int game.C_100299_kd.field_107026_J
		// @40: getstatic game.C_100299_kd game.C_100135_ti.field_105022_a
		// @43: iconst_0
		// @44: putfield int game.C_100299_kd.field_107041_h
		// @47: getstatic game.C_100299_kd game.C_100135_ti.field_105022_a
		// @4A: invokestatic game.C_100135_ti.func_105015_e(game.C_100299_kd)void
		// @4D: iload_1
		// @4E: getstatic game.C_100299_kd game.C_100135_ti.field_105022_a
		// @51: getfield int game.C_100299_kd.field_107044_v
		// @54: isub
		// @55: istore_1
		// @56: getstatic game.C_100299_kd game.C_100135_ti.field_105022_a
		// @59: aconst_null
		// @5A: putfield byte[] game.C_100299_kd.field_107025_I
		// @5D: getstatic game.C_100299_kd game.C_100135_ti.field_105022_a
		// @60: aconst_null
		// @61: putfield byte[] game.C_100299_kd.field_107053_x
		// @64: iload_1
		// @65: aload #5
		// @67: monitorexit
		// @68: ireturn
		// @69: astore #6
		// @6B: aload #5
		// @6D: monitorexit
		// @6E: aload #6
		// @70: athrow
	}
	
	private static final void func_105018_d(C_100299_kd arg0)
	{
		// @00: aload_0
		// @01: iconst_0
		// @02: putfield int game.C_100299_kd.field_107036_o
		// @05: iconst_0
		// @06: istore_1
		// @07: iload_1
		// @08: sipush 256 (0x0100)
		// @0B: if_icmpge @32
		// @0E: aload_0
		// @0F: getfield boolean[] game.C_100299_kd.field_107050_p
		// @12: iload_1
		// @13: baload
		// @14: ifeq @2C
		// @17: aload_0
		// @18: getfield byte[] game.C_100299_kd.field_107043_w
		// @1B: aload_0
		// @1C: getfield int game.C_100299_kd.field_107036_o
		// @1F: iload_1
		// @20: i2b
		// @21: bastore
		// @22: aload_0
		// @23: dup
		// @24: getfield int game.C_100299_kd.field_107036_o
		// @27: iconst_1
		// @28: iadd
		// @29: putfield int game.C_100299_kd.field_107036_o
		// @2C: iinc #1 +1
		// @2F: goto @07
		// @32: return
	}
	
	static
	{
		// @0: new game.C_100299_kd
		// @3: dup
		// @4: invokespecial game.C_100299_kd.<init>()void
		// @7: putstatic game.C_100299_kd game.C_100135_ti.field_105022_a
		// @A: return
	}
}
