package game;

final class C_100063_dj implements C_100199_qm
{
	static String field_104293_e;
	static int[][] field_104295_c;
	static String[] field_104292_d;
	static C_100302_ka[] field_104290_f;
	static String field_104294_b;
	static C_100006_fj field_104296_a;
	static C_100037_wb field_104291_g;
	private static final String field_104297_z;
	
	public static void func_104287_a(int arg0)
	{
		// @00: aconst_null
		// @01: checkcast int[][]
		// @04: putstatic int[][] game.C_100063_dj.field_104295_c
		// @07: aconst_null
		// @08: putstatic java.lang.String game.C_100063_dj.field_104293_e
		// @0B: aconst_null
		// @0C: putstatic java.lang.String[] game.C_100063_dj.field_104292_d
		// @0F: aconst_null
		// @10: putstatic game.C_100302_ka[] game.C_100063_dj.field_104290_f
		// @13: aconst_null
		// @14: putstatic game.C_100037_wb game.C_100063_dj.field_104291_g
		// @17: iload_0
		// @18: sipush -23845 (0xA2DB)
		// @1B: if_icmpeq @1F
		// @1E: return
		// @1F: aconst_null
		// @20: putstatic java.lang.String game.C_100063_dj.field_104294_b
		// @23: aconst_null
		// @24: putstatic game.C_100006_fj game.C_100063_dj.field_104296_a
		// @27: goto @49
		// @2A: astore_1
		// @2B: aload_1
		// @2C: new java.lang.StringBuilder
		// @2F: dup
		// @30: invokespecial java.lang.StringBuilder.<init>()void
		// @33: getstatic java.lang.String game.C_100063_dj.field_104297_z
		// @36: invokevirtual java.lang.StringBuilder.append(java.lang.String)java.lang.StringBuilder
		// @39: iload_0
		// @3A: invokevirtual java.lang.StringBuilder.append(int)java.lang.StringBuilder
		// @3D: bipush 41 (0x29)
		// @3F: invokevirtual java.lang.StringBuilder.append(char)java.lang.StringBuilder
		// @42: invokevirtual java.lang.StringBuilder.toString()java.lang.String
		// @45: invokestatic game.C_100181_cf.func_105695_a(java.lang.Throwable, java.lang.String)game.C_100170_cm
		// @48: athrow
		// @49: return
	}
	
	static
	{
		// @00: ldc "UL&@\u0013"
		// @02: invokestatic game.C_100063_dj.func_104289_z(java.lang.String)char[]
		// @05: invokestatic game.C_100063_dj.func_104288_z(char[])java.lang.String
		// @08: putstatic java.lang.String game.C_100063_dj.field_104297_z
		// @0B: bipush 11 (0x0B)
		// @0D: anewarray java.lang.String
		// @10: dup
		// @11: iconst_0
		// @12: ldc "y_xdI\u0011TmmTPBms"
		// @14: invokestatic game.C_100063_dj.func_104289_z(java.lang.String)char[]
		// @17: invokestatic game.C_100063_dj.func_104288_z(char[])java.lang.String
		// @1A: aastore
		// @1B: dup
		// @1C: iconst_1
		// @1D: ldc "yCimOY\u0006xmNB"
		// @1F: invokestatic game.C_100063_dj.func_104289_z(java.lang.String)char[]
		// @22: invokestatic game.C_100063_dj.func_104288_z(char[])java.lang.String
		// @25: aastore
		// @26: dup
		// @27: iconst_2
		// @28: ldc "xHnhUXRm!^_CzfB"
		// @2A: invokestatic game.C_100063_dj.func_104289_z(java.lang.String)char[]
		// @2D: invokestatic game.C_100063_dj.func_104288_z(char[])java.lang.String
		// @30: aastore
		// @31: dup
		// @32: iconst_3
		// @33: ldc "xKxdIGOgtH"
		// @35: invokestatic game.C_100063_dj.func_104289_z(java.lang.String)char[]
		// @38: invokestatic game.C_100063_dj.func_104288_z(char[])java.lang.String
		// @3B: aastore
		// @3C: dup
		// @3D: iconst_4
		// @3E: ldc "bVmd_"
		// @40: invokestatic game.C_100063_dj.func_104289_z(java.lang.String)char[]
		// @43: invokestatic game.C_100063_dj.func_104288_z(char[])java.lang.String
		// @46: aastore
		// @47: dup
		// @48: iconst_5
		// @49: ldc "`SieIP\u000bxmZEOff"
		// @4B: invokestatic game.C_100063_dj.func_104289_z(java.lang.String)char[]
		// @4E: invokestatic game.C_100063_dj.func_104288_z(char[])java.lang.String
		// @51: aastore
		// @52: dup
		// @53: bipush 6 (0x06)
		// @55: ldc "`SieIP\u000bl`VPAm"
		// @57: invokestatic game.C_100063_dj.func_104289_z(java.lang.String)char[]
		// @5A: invokestatic game.C_100063_dj.func_104288_z(char[])java.lang.String
		// @5D: aastore
		// @5E: dup
		// @5F: bipush 7 (0x07)
		// @61: ldc "tkX!LTGxnUB"
		// @63: invokestatic game.C_100063_dj.func_104289_z(java.lang.String)char[]
		// @66: invokestatic game.C_100063_dj.func_104288_z(char[])java.lang.String
		// @69: aastore
		// @6A: dup
		// @6B: bipush 8 (0x08)
		// @6D: ldc "|aNO"
		// @6F: invokestatic game.C_100063_dj.func_104289_z(java.lang.String)char[]
		// @72: invokestatic game.C_100063_dj.func_104288_z(char[])java.lang.String
		// @75: aastore
		// @76: dup
		// @77: bipush 9 (0x09)
		// @79: ldc "cIkj^E\u0006{uIXMm"
		// @7B: invokestatic game.C_100063_dj.func_104289_z(java.lang.String)char[]
		// @7E: invokestatic game.C_100063_dj.func_104288_z(char[])java.lang.String
		// @81: aastore
		// @82: dup
		// @83: bipush 10 (0x0A)
		// @85: ldc "\u0000\u000b]q"
		// @87: invokestatic game.C_100063_dj.func_104289_z(java.lang.String)char[]
		// @8A: invokestatic game.C_100063_dj.func_104288_z(char[])java.lang.String
		// @8D: aastore
		// @8E: putstatic java.lang.String[] game.C_100063_dj.field_104292_d
		// @91: ldc "eGzf^E\u0006dnXZ"
		// @93: invokestatic game.C_100063_dj.func_104289_z(java.lang.String)char[]
		// @96: invokestatic game.C_100063_dj.func_104288_z(char[])java.lang.String
		// @99: putstatic java.lang.String game.C_100063_dj.field_104294_b
		// @9C: ldc "cCenMT\u00064$\u000b\u000f\u0006nsT\\\u0006afU^Tm!WXU|"
		// @9E: invokestatic game.C_100063_dj.func_104289_z(java.lang.String)char[]
		// @A1: invokestatic game.C_100063_dj.func_104288_z(char[])java.lang.String
		// @A4: putstatic java.lang.String game.C_100063_dj.field_104293_e
		// @A7: bipush 110 (0x6E)
		// @A9: bipush 35 (0x23)
		// @AB: invokestatic java.lang.Math.max(int, int)int
		// @AE: anewarray game.C_100302_ka
		// @B1: putstatic game.C_100302_ka[] game.C_100063_dj.field_104290_f
		// @B4: new game.C_100006_fj
		// @B7: dup
		// @B8: invokespecial game.C_100006_fj.<init>()void
		// @BB: putstatic game.C_100006_fj game.C_100063_dj.field_104296_a
		// @BE: return
	}
	
	private static char[] func_104289_z(String arg0)
	{
		// @00: aload_0
		// @01: invokevirtual java.lang.String.toCharArray()char[]
		// @04: dup
		// @05: arraylength
		// @06: iconst_2
		// @07: if_icmpge @13
		// @0A: dup
		// @0B: iconst_0
		// @0C: dup2
		// @0D: caload
		// @0E: bipush 59 (0x3B)
		// @10: ixor
		// @11: i2c
		// @12: castore
		// @13: areturn
	}
	
	private static String func_104288_z(char[] arg0)
	{
		// @00: aload_0
		// @01: dup
		// @02: arraylength
		// @03: swap
		// @04: iconst_0
		// @05: istore_1
		// @06: goto @4B
		// @09: dup
		// @0A: iload_1
		// @0B: dup2
		// @0C: caload
		// @0D: iload_1
		// @0E: iconst_5
		// @0F: irem
		// @10: tableswitch def: @43, for 0: @30, for 1: @35, for 2: @3A, for 3: @3F
		// @30: bipush 49 (0x31)
		// @32: goto @45
		// @35: bipush 38 (0x26)
		// @37: goto @45
		// @3A: bipush 8 (0x08)
		// @3C: goto @45
		// @3F: iconst_1
		// @40: goto @45
		// @43: bipush 59 (0x3B)
		// @45: ixor
		// @46: i2c
		// @47: castore
		// @48: iinc #1 +1
		// @4B: swap
		// @4C: dup_x1
		// @4D: iload_1
		// @4E: if_icmpgt @09
		// @51: new java.lang.String
		// @54: dup_x1
		// @55: swap
		// @56: invokespecial java.lang.String.<init>(char[])void
		// @59: invokevirtual java.lang.String.intern()java.lang.String
		// @5C: areturn
	}
}
