package game;

import java.awt.event.FocusListener;
import java.awt.Frame;
import java.awt.Graphics;
import java.awt.event.FocusEvent;
import java.awt.Canvas;

final class C_100009_fg extends Canvas implements FocusListener
{
	static String field_103658_c;
	static C_100115_ej field_103654_g;
	static boolean field_103662_i;
	Frame field_103655_d;
	static String field_103653_f;
	static int field_103659_a;
	static String field_103656_e;
	static String field_103661_h;
	volatile boolean field_103657_b;
	private static final String[] field_103660_z;
	
	static final void func_103642_b(int arg0)
	{
		// @00: getstatic int[] game.C_100310_lj.field_100550_x
		// @03: bipush 47 (0x2F)
		// @05: bipush 73 (0x49)
		// @07: iastore
		// @08: getstatic int[] game.C_100310_lj.field_100550_x
		// @0B: bipush 46 (0x2E)
		// @0D: bipush 72 (0x48)
		// @0F: iastore
		// @10: getstatic int[] game.C_100310_lj.field_100550_x
		// @13: iload_0
		// @14: bipush 74 (0x4A)
		// @16: iastore
		// @17: getstatic int[] game.C_100310_lj.field_100550_x
		// @1A: sipush 222 (0x00DE)
		// @1D: bipush 58 (0x3A)
		// @1F: iastore
		// @20: getstatic int[] game.C_100310_lj.field_100550_x
		// @23: sipush 520 (0x0208)
		// @26: bipush 59 (0x3B)
		// @28: iastore
		// @29: getstatic int[] game.C_100310_lj.field_100550_x
		// @2C: sipush 192 (0x00C0)
		// @2F: bipush 28 (0x1C)
		// @31: iastore
		// @32: getstatic int[] game.C_100310_lj.field_100550_x
		// @35: bipush 45 (0x2D)
		// @37: bipush 26 (0x1A)
		// @39: iastore
		// @3A: getstatic int[] game.C_100310_lj.field_100550_x
		// @3D: bipush 44 (0x2C)
		// @3F: bipush 71 (0x47)
		// @41: iastore
		// @42: getstatic int[] game.C_100310_lj.field_100550_x
		// @45: bipush 93 (0x5D)
		// @47: bipush 43 (0x2B)
		// @49: iastore
		// @4A: getstatic int[] game.C_100310_lj.field_100550_x
		// @4D: bipush 59 (0x3B)
		// @4F: bipush 57 (0x39)
		// @51: iastore
		// @52: getstatic int[] game.C_100310_lj.field_100550_x
		// @55: bipush 91 (0x5B)
		// @57: bipush 42 (0x2A)
		// @59: iastore
		// @5A: getstatic int[] game.C_100310_lj.field_100550_x
		// @5D: bipush 61 (0x3D)
		// @5F: bipush 27 (0x1B)
		// @61: iastore
		// @62: goto @86
		// @65: astore_1
		// @66: aload_1
		// @67: new java.lang.StringBuilder
		// @6A: dup
		// @6B: invokespecial java.lang.StringBuilder.<init>()void
		// @6E: getstatic java.lang.String[] game.C_100009_fg.field_103660_z
		// @71: iconst_2
		// @72: aaload
		// @73: invokevirtual java.lang.StringBuilder.append(java.lang.String)java.lang.StringBuilder
		// @76: iload_0
		// @77: invokevirtual java.lang.StringBuilder.append(int)java.lang.StringBuilder
		// @7A: bipush 41 (0x29)
		// @7C: invokevirtual java.lang.StringBuilder.append(char)java.lang.StringBuilder
		// @7F: invokevirtual java.lang.StringBuilder.toString()java.lang.String
		// @82: invokestatic game.C_100181_cf.func_105695_a(java.lang.Throwable, java.lang.String)game.C_100170_cm
		// @85: athrow
		// @86: return
	}
	
	public final void paint(Graphics arg0)
	{
		// @0: return
	}
	
	public static void func_103645_a(byte arg0)
	{
		// @00: aconst_null
		// @01: putstatic java.lang.String game.C_100009_fg.field_103661_h
		// @04: aconst_null
		// @05: putstatic java.lang.String game.C_100009_fg.field_103653_f
		// @08: aconst_null
		// @09: putstatic java.lang.String game.C_100009_fg.field_103656_e
		// @0C: aconst_null
		// @0D: putstatic java.lang.String game.C_100009_fg.field_103658_c
		// @10: aconst_null
		// @11: putstatic game.C_100115_ej game.C_100009_fg.field_103654_g
		// @14: iload_0
		// @15: bipush 57 (0x39)
		// @17: if_icmpeq @1F
		// @1A: bipush 53 (0x35)
		// @1C: putstatic int game.C_100009_fg.field_103659_a
		// @1F: goto @44
		// @22: astore_1
		// @23: aload_1
		// @24: new java.lang.StringBuilder
		// @27: dup
		// @28: invokespecial java.lang.StringBuilder.<init>()void
		// @2B: getstatic java.lang.String[] game.C_100009_fg.field_103660_z
		// @2E: bipush 7 (0x07)
		// @30: aaload
		// @31: invokevirtual java.lang.StringBuilder.append(java.lang.String)java.lang.StringBuilder
		// @34: iload_0
		// @35: invokevirtual java.lang.StringBuilder.append(int)java.lang.StringBuilder
		// @38: bipush 41 (0x29)
		// @3A: invokevirtual java.lang.StringBuilder.append(char)java.lang.StringBuilder
		// @3D: invokevirtual java.lang.StringBuilder.toString()java.lang.String
		// @40: invokestatic game.C_100181_cf.func_105695_a(java.lang.Throwable, java.lang.String)game.C_100170_cm
		// @43: athrow
		// @44: return
	}
	
	static final int func_103641_a(int arg0, byte arg1)
	{
		// @000: getstatic int game.SteelSentinels.field_105275_O
		// @003: istore_3
		// @004: iload_1
		// @005: bipush 90 (0x5A)
		// @007: if_icmpeq @00D
		// @00A: bipush -90 (0xA6)
		// @00C: ireturn
		// @00D: iload_0
		// @00E: istore_2
		// @00F: iload_2
		// @010: iconst_1
		// @011: if_icmpne @01C
		// @014: iload_3
		// @015: ifeq @0DD
		// @018: goto @01C
		// @01B: athrow
		// @01C: iconst_2
		// @01D: iload_2
		// @01E: if_icmpne @02D
		// @021: goto @025
		// @024: athrow
		// @025: iload_3
		// @026: ifeq @0DF
		// @029: goto @02D
		// @02C: athrow
		// @02D: iload_2
		// @02E: iconst_m1
		// @02F: ixor
		// @030: bipush -4 (0xFC)
		// @032: if_icmpeq @0E1
		// @035: goto @039
		// @038: athrow
		// @039: bipush -5 (0xFB)
		// @03B: iload_2
		// @03C: iconst_m1
		// @03D: ixor
		// @03E: if_icmpeq @0E3
		// @041: goto @045
		// @044: athrow
		// @045: iload_2
		// @046: iconst_m1
		// @047: ixor
		// @048: bipush -21 (0xEB)
		// @04A: if_icmpne @059
		// @04D: goto @051
		// @050: athrow
		// @051: iload_3
		// @052: ifeq @0E5
		// @055: goto @059
		// @058: athrow
		// @059: iload_2
		// @05A: bipush 11 (0x0B)
		// @05C: if_icmpeq @0E7
		// @05F: goto @063
		// @062: athrow
		// @063: bipush -13 (0xF3)
		// @065: iload_2
		// @066: iconst_m1
		// @067: ixor
		// @068: if_icmpeq @0EA
		// @06B: goto @06F
		// @06E: athrow
		// @06F: iload_2
		// @070: bipush 13 (0x0D)
		// @072: if_icmpeq @0ED
		// @075: goto @079
		// @078: athrow
		// @079: iload_2
		// @07A: bipush 14 (0x0E)
		// @07C: if_icmpeq @0F0
		// @07F: goto @083
		// @082: athrow
		// @083: iload_2
		// @084: bipush 6 (0x06)
		// @086: if_icmpeq @0F3
		// @089: goto @08D
		// @08C: athrow
		// @08D: iload_2
		// @08E: iconst_m1
		// @08F: ixor
		// @090: bipush -8 (0xF8)
		// @092: if_icmpne @0A1
		// @095: goto @099
		// @098: athrow
		// @099: iload_3
		// @09A: ifeq @0F5
		// @09D: goto @0A1
		// @0A0: athrow
		// @0A1: iload_2
		// @0A2: bipush 8 (0x08)
		// @0A4: if_icmpne @0B3
		// @0A7: goto @0AB
		// @0AA: athrow
		// @0AB: iload_3
		// @0AC: ifeq @0F8
		// @0AF: goto @0B3
		// @0B2: athrow
		// @0B3: iload_2
		// @0B4: bipush 9 (0x09)
		// @0B6: if_icmpeq @0FB
		// @0B9: goto @0BD
		// @0BC: athrow
		// @0BD: bipush 26 (0x1A)
		// @0BF: iload_2
		// @0C0: if_icmpne @0CF
		// @0C3: goto @0C7
		// @0C6: athrow
		// @0C7: iload_3
		// @0C8: ifeq @0FE
		// @0CB: goto @0CF
		// @0CE: athrow
		// @0CF: iload_2
		// @0D0: bipush 15 (0x0F)
		// @0D2: if_icmpeq @101
		// @0D5: goto @0D9
		// @0D8: athrow
		// @0D9: goto @104
		// @0DC: athrow
		// @0DD: iconst_0
		// @0DE: ireturn
		// @0DF: iconst_1
		// @0E0: ireturn
		// @0E1: iconst_2
		// @0E2: ireturn
		// @0E3: iconst_3
		// @0E4: ireturn
		// @0E5: iconst_4
		// @0E6: ireturn
		// @0E7: bipush 10 (0x0A)
		// @0E9: ireturn
		// @0EA: bipush 11 (0x0B)
		// @0EC: ireturn
		// @0ED: bipush 12 (0x0C)
		// @0EF: ireturn
		// @0F0: bipush 13 (0x0D)
		// @0F2: ireturn
		// @0F3: iconst_5
		// @0F4: ireturn
		// @0F5: bipush 6 (0x06)
		// @0F7: ireturn
		// @0F8: bipush 7 (0x07)
		// @0FA: ireturn
		// @0FB: bipush 8 (0x08)
		// @0FD: ireturn
		// @0FE: bipush 10 (0x0A)
		// @100: ireturn
		// @101: bipush 27 (0x1B)
		// @103: ireturn
		// @104: iconst_m1
		// @105: ireturn
		// @106: astore_2
		// @107: aload_2
		// @108: new java.lang.StringBuilder
		// @10B: dup
		// @10C: invokespecial java.lang.StringBuilder.<init>()void
		// @10F: getstatic java.lang.String[] game.C_100009_fg.field_103660_z
		// @112: bipush 12 (0x0C)
		// @114: aaload
		// @115: invokevirtual java.lang.StringBuilder.append(java.lang.String)java.lang.StringBuilder
		// @118: iload_0
		// @119: invokevirtual java.lang.StringBuilder.append(int)java.lang.StringBuilder
		// @11C: bipush 44 (0x2C)
		// @11E: invokevirtual java.lang.StringBuilder.append(char)java.lang.StringBuilder
		// @121: iload_1
		// @122: invokevirtual java.lang.StringBuilder.append(int)java.lang.StringBuilder
		// @125: bipush 41 (0x29)
		// @127: invokevirtual java.lang.StringBuilder.append(char)java.lang.StringBuilder
		// @12A: invokevirtual java.lang.StringBuilder.toString()java.lang.String
		// @12D: invokestatic game.C_100181_cf.func_105695_a(java.lang.Throwable, java.lang.String)game.C_100170_cm
		// @130: athrow
	}
	
	static long func_103650_a(long arg0, long arg1)
	{
		// @00: lload_0
		// @01: lload_2
		// @02: lor
		// @03: lreturn
		// @04: astore #4
		// @06: aload #4
		// @08: new java.lang.StringBuilder
		// @0B: dup
		// @0C: invokespecial java.lang.StringBuilder.<init>()void
		// @0F: getstatic java.lang.String[] game.C_100009_fg.field_103660_z
		// @12: bipush 11 (0x0B)
		// @14: aaload
		// @15: invokevirtual java.lang.StringBuilder.append(java.lang.String)java.lang.StringBuilder
		// @18: lload_0
		// @19: invokevirtual java.lang.StringBuilder.append(long)java.lang.StringBuilder
		// @1C: bipush 44 (0x2C)
		// @1E: invokevirtual java.lang.StringBuilder.append(char)java.lang.StringBuilder
		// @21: lload_2
		// @22: invokevirtual java.lang.StringBuilder.append(long)java.lang.StringBuilder
		// @25: bipush 41 (0x29)
		// @27: invokevirtual java.lang.StringBuilder.append(char)java.lang.StringBuilder
		// @2A: invokevirtual java.lang.StringBuilder.toString()java.lang.String
		// @2D: invokestatic game.C_100181_cf.func_105695_a(java.lang.Throwable, java.lang.String)game.C_100170_cm
		// @30: athrow
	}
	
	static final boolean func_103647_b(byte arg0)
	{
		// @00: iload_0
		// @01: bipush -63 (0xC1)
		// @03: if_icmple @08
		// @06: iconst_0
		// @07: ireturn
		// @08: iconst_0
		// @09: invokestatic game.C_100206_qe.func_105938_b(boolean)java.applet.Applet
		// @0C: sipush 1134 (0x046E)
		// @0F: invokestatic game.C_100270_mi.func_102251_a(java.applet.Applet, int)boolean
		// @12: ireturn
		// @13: astore_1
		// @14: aload_1
		// @15: new java.lang.StringBuilder
		// @18: dup
		// @19: invokespecial java.lang.StringBuilder.<init>()void
		// @1C: getstatic java.lang.String[] game.C_100009_fg.field_103660_z
		// @1F: iconst_1
		// @20: aaload
		// @21: invokevirtual java.lang.StringBuilder.append(java.lang.String)java.lang.StringBuilder
		// @24: iload_0
		// @25: invokevirtual java.lang.StringBuilder.append(int)java.lang.StringBuilder
		// @28: bipush 41 (0x29)
		// @2A: invokevirtual java.lang.StringBuilder.append(char)java.lang.StringBuilder
		// @2D: invokevirtual java.lang.StringBuilder.toString()java.lang.String
		// @30: invokestatic game.C_100181_cf.func_105695_a(java.lang.Throwable, java.lang.String)game.C_100170_cm
		// @33: athrow
	}
	
	public final void focusGained(FocusEvent arg0)
	{
		// @0: return
	}
	
	public final void focusLost(FocusEvent arg0)
	{
		// @00: aload_0
		// @01: iconst_1
		// @02: putfield boolean game.C_100009_fg.field_103657_b
		// @05: goto @3B
		// @08: astore_2
		// @09: aload_2
		// @0A: new java.lang.StringBuilder
		// @0D: dup
		// @0E: invokespecial java.lang.StringBuilder.<init>()void
		// @11: getstatic java.lang.String[] game.C_100009_fg.field_103660_z
		// @14: iconst_4
		// @15: aaload
		// @16: invokevirtual java.lang.StringBuilder.append(java.lang.String)java.lang.StringBuilder
		// @19: aload_1
		// @1A: ifnull @27
		// @1D: getstatic java.lang.String[] game.C_100009_fg.field_103660_z
		// @20: bipush 6 (0x06)
		// @22: aaload
		// @23: goto @2C
		// @26: athrow
		// @27: getstatic java.lang.String[] game.C_100009_fg.field_103660_z
		// @2A: iconst_5
		// @2B: aaload
		// @2C: invokevirtual java.lang.StringBuilder.append(java.lang.String)java.lang.StringBuilder
		// @2F: bipush 41 (0x29)
		// @31: invokevirtual java.lang.StringBuilder.append(char)java.lang.StringBuilder
		// @34: invokevirtual java.lang.StringBuilder.toString()java.lang.String
		// @37: invokestatic game.C_100181_cf.func_105695_a(java.lang.Throwable, java.lang.String)game.C_100170_cm
		// @3A: athrow
		// @3B: return
	}
	
	static final void func_103649_c(int arg0)
	{
		// @00: iload_0
		// @01: bipush -52 (0xCC)
		// @03: if_icmplt @0F
		// @06: iconst_m1
		// @07: invokestatic game.C_100009_fg.func_103647_b(byte)boolean
		// @0A: pop
		// @0B: goto @0F
		// @0E: athrow
		// @0F: aconst_null
		// @10: getstatic java.lang.String game.C_100093_fd.field_102779_U
		// @13: if_acmpeq @34
		// @16: getstatic java.lang.String game.C_100093_fd.field_102779_U
		// @19: astore_1
		// @1A: bipush -61 (0xC3)
		// @1C: sipush -30945 (0x871F)
		// @1F: iconst_1
		// @20: anewarray java.lang.String
		// @23: dup
		// @24: iconst_0
		// @25: aload_1
		// @26: aastore
		// @27: getstatic java.lang.String game.C_100170_cm.field_105543_n
		// @2A: invokestatic game.C_100132_td.func_104965_a(int, java.lang.String[], java.lang.String)java.lang.String
		// @2D: invokestatic game.C_100253_ph.func_101087_a(byte, java.lang.String)void
		// @30: aconst_null
		// @31: putstatic java.lang.String game.C_100093_fd.field_102779_U
		// @34: goto @59
		// @37: astore_1
		// @38: aload_1
		// @39: new java.lang.StringBuilder
		// @3C: dup
		// @3D: invokespecial java.lang.StringBuilder.<init>()void
		// @40: getstatic java.lang.String[] game.C_100009_fg.field_103660_z
		// @43: bipush 10 (0x0A)
		// @45: aaload
		// @46: invokevirtual java.lang.StringBuilder.append(java.lang.String)java.lang.StringBuilder
		// @49: iload_0
		// @4A: invokevirtual java.lang.StringBuilder.append(int)java.lang.StringBuilder
		// @4D: bipush 41 (0x29)
		// @4F: invokevirtual java.lang.StringBuilder.append(char)java.lang.StringBuilder
		// @52: invokevirtual java.lang.StringBuilder.toString()java.lang.String
		// @55: invokestatic game.C_100181_cf.func_105695_a(java.lang.Throwable, java.lang.String)game.C_100170_cm
		// @58: athrow
		// @59: return
	}
	
	final void func_103652_a(C_100201_qj arg0, int arg1)
	{
		// @00: aload_1
		// @01: aload_0
		// @02: getfield java.awt.Frame game.C_100009_fg.field_103655_d
		// @05: sipush 8192 (0x2000)
		// @08: invokestatic game.C_100110_s.func_104842_a(game.C_100201_qj, java.awt.Frame, int)void
		// @0B: iload_2
		// @0C: bipush 55 (0x37)
		// @0E: if_icmpgt @18
		// @11: aconst_null
		// @12: checkcast java.lang.String
		// @15: putstatic java.lang.String game.C_100009_fg.field_103653_f
		// @18: goto @58
		// @1B: astore_3
		// @1C: aload_3
		// @1D: new java.lang.StringBuilder
		// @20: dup
		// @21: invokespecial java.lang.StringBuilder.<init>()void
		// @24: getstatic java.lang.String[] game.C_100009_fg.field_103660_z
		// @27: bipush 8 (0x08)
		// @29: aaload
		// @2A: invokevirtual java.lang.StringBuilder.append(java.lang.String)java.lang.StringBuilder
		// @2D: aload_1
		// @2E: ifnull @3B
		// @31: getstatic java.lang.String[] game.C_100009_fg.field_103660_z
		// @34: bipush 6 (0x06)
		// @36: aaload
		// @37: goto @40
		// @3A: athrow
		// @3B: getstatic java.lang.String[] game.C_100009_fg.field_103660_z
		// @3E: iconst_5
		// @3F: aaload
		// @40: invokevirtual java.lang.StringBuilder.append(java.lang.String)java.lang.StringBuilder
		// @43: bipush 44 (0x2C)
		// @45: invokevirtual java.lang.StringBuilder.append(char)java.lang.StringBuilder
		// @48: iload_2
		// @49: invokevirtual java.lang.StringBuilder.append(int)java.lang.StringBuilder
		// @4C: bipush 41 (0x29)
		// @4E: invokevirtual java.lang.StringBuilder.append(char)java.lang.StringBuilder
		// @51: invokevirtual java.lang.StringBuilder.toString()java.lang.String
		// @54: invokestatic game.C_100181_cf.func_105695_a(java.lang.Throwable, java.lang.String)game.C_100170_cm
		// @57: athrow
		// @58: return
	}
	
	public final void update(Graphics arg0)
	{
		// @0: return
	}
	
	static final int func_103648_a(int arg0)
	{
		// @00: getstatic int game.SteelSentinels.field_105275_O
		// @03: istore_3
		// @04: iload_0
		// @05: istore_1
		// @06: iconst_0
		// @07: istore_2
		// @08: getstatic int[] game.C_100075_uj.field_100655_u
		// @0B: arraylength
		// @0C: iconst_m1
		// @0D: ixor
		// @0E: iload_2
		// @0F: iconst_m1
		// @10: ixor
		// @11: if_icmpge @30
		// @14: iload_1
		// @15: getstatic int[] game.C_100075_uj.field_100655_u
		// @18: iload_2
		// @19: iaload
		// @1A: bipush -81 (0xAF)
		// @1C: invokestatic game.C_100303_kk.func_104778_a(int, byte)int
		// @1F: iadd
		// @20: istore_1
		// @21: iinc #2 +1
		// @24: iload_3
		// @25: ifne @32
		// @28: iload_3
		// @29: ifeq @08
		// @2C: goto @30
		// @2F: athrow
		// @30: iconst_0
		// @31: istore_2
		// @32: iload_2
		// @33: getstatic int[] game.C_100257_ln.field_106481_d
		// @36: arraylength
		// @37: if_icmpge @56
		// @3A: iload_1
		// @3B: getstatic int[] game.C_100257_ln.field_106481_d
		// @3E: iload_2
		// @3F: iaload
		// @40: bipush -83 (0xAD)
		// @42: invokestatic game.C_100303_kk.func_104778_a(int, byte)int
		// @45: iadd
		// @46: iload_3
		// @47: ifne @57
		// @4A: goto @4E
		// @4D: athrow
		// @4E: istore_1
		// @4F: iinc #2 +1
		// @52: iload_3
		// @53: ifeq @32
		// @56: iload_1
		// @57: ireturn
		// @58: astore_1
		// @59: aload_1
		// @5A: new java.lang.StringBuilder
		// @5D: dup
		// @5E: invokespecial java.lang.StringBuilder.<init>()void
		// @61: getstatic java.lang.String[] game.C_100009_fg.field_103660_z
		// @64: iconst_0
		// @65: aaload
		// @66: invokevirtual java.lang.StringBuilder.append(java.lang.String)java.lang.StringBuilder
		// @69: iload_0
		// @6A: invokevirtual java.lang.StringBuilder.append(int)java.lang.StringBuilder
		// @6D: bipush 41 (0x29)
		// @6F: invokevirtual java.lang.StringBuilder.append(char)java.lang.StringBuilder
		// @72: invokevirtual java.lang.StringBuilder.toString()java.lang.String
		// @75: invokestatic game.C_100181_cf.func_105695_a(java.lang.Throwable, java.lang.String)game.C_100170_cm
		// @78: athrow
	}
	
	static final void func_103651_a(boolean arg0, int arg1)
	{
		// @00: iload_0
		// @01: iconst_1
		// @02: if_icmpeq @10
		// @05: aconst_null
		// @06: checkcast java.lang.String
		// @09: putstatic java.lang.String game.C_100009_fg.field_103661_h
		// @0C: goto @10
		// @0F: athrow
		// @10: getstatic game.C_100278_nd game.C_100115_ej.field_102043_Yb
		// @13: astore_2
		// @14: aload_2
		// @15: iload_1
		// @16: bipush 117 (0x75)
		// @18: invokevirtual game.C_100278_nd.func_101189_h(int, int)void
		// @1B: aload_2
		// @1C: sipush 7838 (0x1E9E)
		// @1F: iconst_1
		// @20: invokevirtual game.C_100278_nd.func_101169_f(int, int)void
		// @23: aload_2
		// @24: sipush 7838 (0x1E9E)
		// @27: iconst_3
		// @28: invokevirtual game.C_100278_nd.func_101169_f(int, int)void
		// @2B: goto @58
		// @2E: astore_2
		// @2F: aload_2
		// @30: new java.lang.StringBuilder
		// @33: dup
		// @34: invokespecial java.lang.StringBuilder.<init>()void
		// @37: getstatic java.lang.String[] game.C_100009_fg.field_103660_z
		// @3A: iconst_3
		// @3B: aaload
		// @3C: invokevirtual java.lang.StringBuilder.append(java.lang.String)java.lang.StringBuilder
		// @3F: iload_0
		// @40: invokevirtual java.lang.StringBuilder.append(boolean)java.lang.StringBuilder
		// @43: bipush 44 (0x2C)
		// @45: invokevirtual java.lang.StringBuilder.append(char)java.lang.StringBuilder
		// @48: iload_1
		// @49: invokevirtual java.lang.StringBuilder.append(int)java.lang.StringBuilder
		// @4C: bipush 41 (0x29)
		// @4E: invokevirtual java.lang.StringBuilder.append(char)java.lang.StringBuilder
		// @51: invokevirtual java.lang.StringBuilder.toString()java.lang.String
		// @54: invokestatic game.C_100181_cf.func_105695_a(java.lang.Throwable, java.lang.String)game.C_100170_cm
		// @57: athrow
		// @58: return
	}
	
	static final void func_103643_a(int arg0, C_100280_nf arg1)
	{
		// @00: getstatic int game.SteelSentinels.field_105275_O
		// @03: istore #5
		// @05: bipush 24 (0x18)
		// @07: newarray byte[]
		// @09: astore_2
		// @0A: iload_0
		// @0B: bipush 15 (0x0F)
		// @0D: if_icmpeq @11
		// @10: return
		// @11: aconst_null
		// @12: getstatic game.C_100301_kb game.C_100280_nf.field_101183_k
		// @15: if_acmpne @1C
		// @18: goto @8F
		// @1B: athrow
		// @1C: getstatic game.C_100301_kb game.C_100280_nf.field_101183_k
		// @1F: lconst_0
		// @20: bipush 82 (0x52)
		// @22: invokevirtual game.C_100301_kb.func_107086_a(long, int)void
		// @25: getstatic game.C_100301_kb game.C_100280_nf.field_101183_k
		// @28: bipush 53 (0x35)
		// @2A: aload_2
		// @2B: invokevirtual game.C_100301_kb.func_107083_a(byte, byte[])void
		// @2E: iconst_0
		// @2F: istore_3
		// @30: iload_3
		// @31: iconst_m1
		// @32: ixor
		// @33: bipush -25 (0xE7)
		// @35: if_icmple @56
		// @38: aload_2
		// @39: iload_3
		// @3A: baload
		// @3B: iconst_m1
		// @3C: ixor
		// @3D: iconst_m1
		// @3E: iload #5
		// @40: ifne @5B
		// @43: if_icmpne @56
		// @46: goto @4A
		// @49: athrow
		// @4A: iinc #3 +1
		// @4D: iload #5
		// @4F: ifeq @30
		// @52: goto @56
		// @55: athrow
		// @56: iload_3
		// @57: iconst_m1
		// @58: ixor
		// @59: bipush -25 (0xE7)
		// @5B: if_icmple @61
		// @5E: goto @69
		// @61: new java.io.IOException
		// @64: dup
		// @65: invokespecial java.io.IOException.<init>()void
		// @68: athrow
		// @69: goto @8F
		// @6C: astore_3
		// @6D: iconst_0
		// @6E: istore #4
		// @70: bipush -25 (0xE7)
		// @72: iload #4
		// @74: iconst_m1
		// @75: ixor
		// @76: if_icmpge @8F
		// @79: aload_2
		// @7A: iload #4
		// @7C: iconst_m1
		// @7D: bastore
		// @7E: iinc #4 +1
		// @81: iload #5
		// @83: ifne @99
		// @86: iload #5
		// @88: ifeq @70
		// @8B: goto @8F
		// @8E: athrow
		// @8F: aload_1
		// @90: aload_2
		// @91: iconst_0
		// @92: bipush 24 (0x18)
		// @94: bipush -88 (0xA8)
		// @96: invokevirtual game.C_100280_nf.func_101165_b(byte[], int, int, int)void
		// @99: goto @D9
		// @9C: astore_2
		// @9D: aload_2
		// @9E: new java.lang.StringBuilder
		// @A1: dup
		// @A2: invokespecial java.lang.StringBuilder.<init>()void
		// @A5: getstatic java.lang.String[] game.C_100009_fg.field_103660_z
		// @A8: bipush 9 (0x09)
		// @AA: aaload
		// @AB: invokevirtual java.lang.StringBuilder.append(java.lang.String)java.lang.StringBuilder
		// @AE: iload_0
		// @AF: invokevirtual java.lang.StringBuilder.append(int)java.lang.StringBuilder
		// @B2: bipush 44 (0x2C)
		// @B4: invokevirtual java.lang.StringBuilder.append(char)java.lang.StringBuilder
		// @B7: aload_1
		// @B8: ifnull @C5
		// @BB: getstatic java.lang.String[] game.C_100009_fg.field_103660_z
		// @BE: bipush 6 (0x06)
		// @C0: aaload
		// @C1: goto @CA
		// @C4: athrow
		// @C5: getstatic java.lang.String[] game.C_100009_fg.field_103660_z
		// @C8: iconst_5
		// @C9: aaload
		// @CA: invokevirtual java.lang.StringBuilder.append(java.lang.String)java.lang.StringBuilder
		// @CD: bipush 41 (0x29)
		// @CF: invokevirtual java.lang.StringBuilder.append(char)java.lang.StringBuilder
		// @D2: invokevirtual java.lang.StringBuilder.toString()java.lang.String
		// @D5: invokestatic game.C_100181_cf.func_105695_a(java.lang.Throwable, java.lang.String)game.C_100170_cm
		// @D8: athrow
		// @D9: return
	}
	
	static
	{
		// @00: bipush 13 (0x0D)
		// @02: anewarray java.lang.String
		// @05: dup
		// @06: iconst_0
		// @07: ldc "\u000eLK7c"
		// @09: invokestatic game.C_100009_fg.func_103646_z(java.lang.String)char[]
		// @0C: invokestatic game.C_100009_fg.func_103644_z(char[])java.lang.String
		// @0F: aastore
		// @10: dup
		// @11: iconst_1
		// @12: ldc "\u000eLK4c"
		// @14: invokestatic game.C_100009_fg.func_103646_z(java.lang.String)char[]
		// @17: invokestatic game.C_100009_fg.func_103644_z(char[])java.lang.String
		// @1A: aastore
		// @1B: dup
		// @1C: iconst_2
		// @1D: ldc "\u000eLK9c"
		// @1F: invokestatic game.C_100009_fg.func_103646_z(java.lang.String)char[]
		// @22: invokestatic game.C_100009_fg.func_103644_z(char[])java.lang.String
		// @25: aastore
		// @26: dup
		// @27: iconst_3
		// @28: ldc "\u000eLK5c"
		// @2A: invokestatic game.C_100009_fg.func_103646_z(java.lang.String)char[]
		// @2D: invokestatic game.C_100009_fg.func_103644_z(char[])java.lang.String
		// @30: aastore
		// @31: dup
		// @32: iconst_4
		// @33: ldc "\u000eLK\u0017$\u000b^\u0016=$\u001b_M"
		// @35: invokestatic game.C_100009_fg.func_103646_z(java.lang.String)char[]
		// @38: invokestatic game.C_100009_fg.func_103644_z(char[])java.lang.String
		// @3B: aastore
		// @3C: dup
		// @3D: iconst_5
		// @3E: ldc "\u0006^\t\u001d"
		// @40: invokestatic game.C_100009_fg.func_103646_z(java.lang.String)char[]
		// @43: invokestatic game.C_100009_fg.func_103644_z(char[])java.lang.String
		// @46: aastore
		// @47: dup
		// @48: bipush 6 (0x06)
		// @4A: ldc "\u0013\u0005K_6"
		// @4C: invokestatic game.C_100009_fg.func_103646_z(java.lang.String)char[]
		// @4F: invokestatic game.C_100009_fg.func_103644_z(char[])java.lang.String
		// @52: aastore
		// @53: dup
		// @54: bipush 7 (0x07)
		// @56: ldc "\u000eLK0c"
		// @58: invokestatic game.C_100009_fg.func_103646_z(java.lang.String)char[]
		// @5B: invokestatic game.C_100009_fg.func_103644_z(char[])java.lang.String
		// @5E: aastore
		// @5F: dup
		// @60: bipush 8 (0x08)
		// @62: ldc "\u000eLK2c"
		// @64: invokestatic game.C_100009_fg.func_103646_z(java.lang.String)char[]
		// @67: invokestatic game.C_100009_fg.func_103644_z(char[])java.lang.String
		// @6A: aastore
		// @6B: dup
		// @6C: bipush 9 (0x09)
		// @6E: ldc "\u000eLK3c"
		// @70: invokestatic game.C_100009_fg.func_103646_z(java.lang.String)char[]
		// @73: invokestatic game.C_100009_fg.func_103644_z(char[])java.lang.String
		// @76: aastore
		// @77: dup
		// @78: bipush 10 (0x0A)
		// @7A: ldc "\u000eLK6c"
		// @7C: invokestatic game.C_100009_fg.func_103646_z(java.lang.String)char[]
		// @7F: invokestatic game.C_100009_fg.func_103644_z(char[])java.lang.String
		// @82: aastore
		// @83: dup
		// @84: bipush 11 (0x0B)
		// @86: ldc "\u000eLK8c"
		// @88: invokestatic game.C_100009_fg.func_103646_z(java.lang.String)char[]
		// @8B: invokestatic game.C_100009_fg.func_103644_z(char[])java.lang.String
		// @8E: aastore
		// @8F: dup
		// @90: bipush 12 (0x0C)
		// @92: ldc "\u000eLK;c"
		// @94: invokestatic game.C_100009_fg.func_103646_z(java.lang.String)char[]
		// @97: invokestatic game.C_100009_fg.func_103644_z(char[])java.lang.String
		// @9A: aastore
		// @9B: putstatic java.lang.String[] game.C_100009_fg.field_103660_z
		// @9E: ldc "*RE\u0012'\u0001H\u000e\u0018%\u000f\u000b&\u0003.\t_\u0000]k\u0011D\u0010Q*\u000fY\u0000\u0014k\u001cDE\u0005#\r\u000bYT{V\u0017\r\u001e?\u001b[\n\u0005vX\u00151\u00149\u0005XE\u001e-H~\u0016\u0014wGC\n\u00058\u0018D\u0011OwM\u001a[Q*\u0006OEMnX\u0015Y\u0019$\u001cX\u0015\u001e?U\u001a[!9\u0001]\u0004\u00122H{\n\u001d\"\u000bRY^#\u0007_\u0016\u0001$\u001c\u0015YTzV\u0005"
		// @A0: invokestatic game.C_100009_fg.func_103646_z(java.lang.String)char[]
		// @A3: invokestatic game.C_100009_fg.func_103644_z(char[])java.lang.String
		// @A6: putstatic java.lang.String game.C_100009_fg.field_103658_c
		// @A9: iconst_0
		// @AA: putstatic boolean game.C_100009_fg.field_103662_i
		// @AD: ldc "+D\u0008\u0001'\r_\u0000Q?\u0000Y\u0000\u0014k\u001cY\u0004\u0018%\u0001E\u0002Q&\u0001X\u0016\u0018$\u0006XE\u0005$H^\u000b\u001d$\u000b@E\u0008$\u001dYE\u0017\"\u001aX\u0011Q8\rE\u0011\u0018%\rGK"
		// @AF: invokestatic game.C_100009_fg.func_103646_z(java.lang.String)char[]
		// @B2: invokestatic game.C_100009_fg.func_103644_z(char[])java.lang.String
		// @B5: putstatic java.lang.String game.C_100009_fg.field_103656_e
		// @B8: ldc ":N\u0011\u00049\u0006\u000b\u0011\u001ek%J\u000c\u001fk%N\u000b\u0004"
		// @BA: invokestatic game.C_100009_fg.func_103646_z(java.lang.String)char[]
		// @BD: invokestatic game.C_100009_fg.func_103644_z(char[])java.lang.String
		// @C0: putstatic java.lang.String game.C_100009_fg.field_103661_h
		// @C3: ldc "-F\u0004\u0018'H\u0003)\u001e,\u0001ELK"
		// @C5: invokestatic game.C_100009_fg.func_103646_z(java.lang.String)char[]
		// @C8: invokestatic game.C_100009_fg.func_103644_z(char[])java.lang.String
		// @CB: putstatic java.lang.String game.C_100009_fg.field_103653_f
		// @CE: bipush 66 (0x42)
		// @D0: putstatic int game.C_100009_fg.field_103659_a
		// @D3: return
	}
	
	private static char[] func_103646_z(String arg0)
	{
		// @00: aload_0
		// @01: invokevirtual java.lang.String.toCharArray()char[]
		// @04: dup
		// @05: arraylength
		// @06: iconst_2
		// @07: if_icmpge @13
		// @0A: dup
		// @0B: iconst_0
		// @0C: dup2
		// @0D: caload
		// @0E: bipush 75 (0x4B)
		// @10: ixor
		// @11: i2c
		// @12: castore
		// @13: areturn
	}
	
	private static String func_103644_z(char[] arg0)
	{
		// @00: aload_0
		// @01: dup
		// @02: arraylength
		// @03: swap
		// @04: iconst_0
		// @05: istore_1
		// @06: goto @4C
		// @09: dup
		// @0A: iload_1
		// @0B: dup2
		// @0C: caload
		// @0D: iload_1
		// @0E: iconst_5
		// @0F: irem
		// @10: tableswitch def: @44, for 0: @30, for 1: @35, for 2: @3A, for 3: @3F
		// @30: bipush 104 (0x68)
		// @32: goto @46
		// @35: bipush 43 (0x2B)
		// @37: goto @46
		// @3A: bipush 101 (0x65)
		// @3C: goto @46
		// @3F: bipush 113 (0x71)
		// @41: goto @46
		// @44: bipush 75 (0x4B)
		// @46: ixor
		// @47: i2c
		// @48: castore
		// @49: iinc #1 +1
		// @4C: swap
		// @4D: dup_x1
		// @4E: iload_1
		// @4F: if_icmpgt @09
		// @52: new java.lang.String
		// @55: dup_x1
		// @56: swap
		// @57: invokespecial java.lang.String.<init>(char[])void
		// @5A: invokevirtual java.lang.String.intern()java.lang.String
		// @5D: areturn
	}
}
