package game;

final class C_100275_na extends C_100140_bj implements C_100224_ag, C_100147_bg
{
	static int[] field_103086_o;
	static int[] field_103095_q;
	C_100051_ea field_103094_r;
	static int[] field_103092_i;
	static String field_103089_j;
	static int[] field_103087_l;
	static int field_103093_s;
	static String field_103091_h;
	static String field_103090_k;
	static String field_103088_m;
	static int field_103096_p;
	static String field_103085_n;
	private static final String[] field_103097_z;
	
	static final void func_103083_b(byte arg0)
	{
		// @00: getstatic int game.SteelSentinels.field_105275_O
		// @03: istore_2
		// @04: iconst_0
		// @05: istore_1
		// @06: iload_0
		// @07: bipush 15 (0x0F)
		// @09: if_icmpeq @0D
		// @0C: return
		// @0D: sipush 10000 (0x2710)
		// @10: iload_1
		// @11: if_icmple @2D
		// @14: getstatic game.C_100059_df[] game.C_100277_nc.field_106737_u
		// @17: iload_1
		// @18: aaload
		// @19: bipush 102 (0x66)
		// @1B: invokevirtual game.C_100059_df.func_101591_j(int)void
		// @1E: iinc #1 +1
		// @21: iload_2
		// @22: ifne @52
		// @25: iload_2
		// @26: ifeq @0D
		// @29: goto @2D
		// @2C: athrow
		// @2D: goto @52
		// @30: astore_1
		// @31: aload_1
		// @32: new java.lang.StringBuilder
		// @35: dup
		// @36: invokespecial java.lang.StringBuilder.<init>()void
		// @39: getstatic java.lang.String[] game.C_100275_na.field_103097_z
		// @3C: bipush 8 (0x08)
		// @3E: aaload
		// @3F: invokevirtual java.lang.StringBuilder.append(java.lang.String)java.lang.StringBuilder
		// @42: iload_0
		// @43: invokevirtual java.lang.StringBuilder.append(int)java.lang.StringBuilder
		// @46: bipush 41 (0x29)
		// @48: invokevirtual java.lang.StringBuilder.append(char)java.lang.StringBuilder
		// @4B: invokevirtual java.lang.StringBuilder.toString()java.lang.String
		// @4E: invokestatic game.C_100181_cf.func_105695_a(java.lang.Throwable, java.lang.String)game.C_100170_cm
		// @51: athrow
		// @52: return
	}
	
	public final void func_102580_a(byte arg0, C_100309_lk arg1)
	{
		// @00: aload_0
		// @01: bipush -109 (0x93)
		// @03: invokevirtual game.C_100275_na.func_102951_b(int)void
		// @06: iload_1
		// @07: bipush 79 (0x4F)
		// @09: if_icmpge @16
		// @0C: aload_0
		// @0D: bipush -125 (0x83)
		// @0F: aconst_null
		// @10: checkcast game.C_100309_lk
		// @13: invokevirtual game.C_100275_na.func_102579_a(int, game.C_100309_lk)void
		// @16: goto @55
		// @19: astore_3
		// @1A: aload_3
		// @1B: new java.lang.StringBuilder
		// @1E: dup
		// @1F: invokespecial java.lang.StringBuilder.<init>()void
		// @22: getstatic java.lang.String[] game.C_100275_na.field_103097_z
		// @25: bipush 11 (0x0B)
		// @27: aaload
		// @28: invokevirtual java.lang.StringBuilder.append(java.lang.String)java.lang.StringBuilder
		// @2B: iload_1
		// @2C: invokevirtual java.lang.StringBuilder.append(int)java.lang.StringBuilder
		// @2F: bipush 44 (0x2C)
		// @31: invokevirtual java.lang.StringBuilder.append(char)java.lang.StringBuilder
		// @34: aload_2
		// @35: ifnull @41
		// @38: getstatic java.lang.String[] game.C_100275_na.field_103097_z
		// @3B: iconst_4
		// @3C: aaload
		// @3D: goto @46
		// @40: athrow
		// @41: getstatic java.lang.String[] game.C_100275_na.field_103097_z
		// @44: iconst_2
		// @45: aaload
		// @46: invokevirtual java.lang.StringBuilder.append(java.lang.String)java.lang.StringBuilder
		// @49: bipush 41 (0x29)
		// @4B: invokevirtual java.lang.StringBuilder.append(char)java.lang.StringBuilder
		// @4E: invokevirtual java.lang.StringBuilder.toString()java.lang.String
		// @51: invokestatic game.C_100181_cf.func_105695_a(java.lang.Throwable, java.lang.String)game.C_100170_cm
		// @54: athrow
		// @55: return
	}
	
	public static void func_103084_g(int arg0)
	{
		// @00: aconst_null
		// @01: putstatic int[] game.C_100275_na.field_103092_i
		// @04: aconst_null
		// @05: putstatic int[] game.C_100275_na.field_103086_o
		// @08: aconst_null
		// @09: putstatic int[] game.C_100275_na.field_103087_l
		// @0C: aconst_null
		// @0D: putstatic java.lang.String game.C_100275_na.field_103085_n
		// @10: aconst_null
		// @11: putstatic int[] game.C_100275_na.field_103095_q
		// @14: aconst_null
		// @15: putstatic java.lang.String game.C_100275_na.field_103091_h
		// @18: aconst_null
		// @19: putstatic java.lang.String game.C_100275_na.field_103089_j
		// @1C: aconst_null
		// @1D: putstatic java.lang.String game.C_100275_na.field_103088_m
		// @20: iload_0
		// @21: bipush 12 (0x0C)
		// @23: if_icmpeq @31
		// @26: aconst_null
		// @27: checkcast java.lang.String
		// @2A: putstatic java.lang.String game.C_100275_na.field_103089_j
		// @2D: goto @31
		// @30: athrow
		// @31: aconst_null
		// @32: putstatic java.lang.String game.C_100275_na.field_103090_k
		// @35: goto @59
		// @38: astore_1
		// @39: aload_1
		// @3A: new java.lang.StringBuilder
		// @3D: dup
		// @3E: invokespecial java.lang.StringBuilder.<init>()void
		// @41: getstatic java.lang.String[] game.C_100275_na.field_103097_z
		// @44: iconst_5
		// @45: aaload
		// @46: invokevirtual java.lang.StringBuilder.append(java.lang.String)java.lang.StringBuilder
		// @49: iload_0
		// @4A: invokevirtual java.lang.StringBuilder.append(int)java.lang.StringBuilder
		// @4D: bipush 41 (0x29)
		// @4F: invokevirtual java.lang.StringBuilder.append(char)java.lang.StringBuilder
		// @52: invokevirtual java.lang.StringBuilder.toString()java.lang.String
		// @55: invokestatic game.C_100181_cf.func_105695_a(java.lang.Throwable, java.lang.String)game.C_100170_cm
		// @58: athrow
		// @59: return
	}
	
	final C_100133_tk func_102955_b(boolean arg0)
	{
		// @00: iload_1
		// @01: ifeq @09
		// @04: aconst_null
		// @05: checkcast game.C_100133_tk
		// @08: areturn
		// @09: aload_0
		// @0A: getfield game.C_100051_ea game.C_100275_na.field_103094_r
		// @0D: bipush 98 (0x62)
		// @0F: invokevirtual game.C_100051_ea.func_103300_a(byte)int
		// @12: istore_2
		// @13: aload_0
		// @14: getfield game.C_100051_ea game.C_100275_na.field_103094_r
		// @17: bipush 119 (0x77)
		// @19: invokevirtual game.C_100051_ea.func_103299_k(int)int
		// @1C: istore_3
		// @1D: aload_0
		// @1E: getfield game.C_100051_ea game.C_100275_na.field_103094_r
		// @21: iconst_m1
		// @22: invokevirtual game.C_100051_ea.func_103303_n(int)int
		// @25: istore #4
		// @27: bipush 126 (0x7E)
		// @29: invokestatic game.C_100335_il.func_107363_b(byte)int
		// @2C: istore #5
		// @2E: sipush -1891 (0xF89D)
		// @31: iload #4
		// @33: iconst_m1
		// @34: ixor
		// @35: if_icmplt @3C
		// @38: goto @40
		// @3B: athrow
		// @3C: getstatic game.C_100133_tk game.C_100256_pk.field_100466_a
		// @3F: areturn
		// @40: iload #5
		// @42: iconst_3
		// @43: isub
		// @44: iload #4
		// @46: if_icmpge @4D
		// @49: getstatic game.C_100133_tk game.C_100256_pk.field_100466_a
		// @4C: areturn
		// @4D: bipush 119 (0x77)
		// @4F: iload #4
		// @51: iload_2
		// @52: iload_3
		// @53: invokestatic game.C_100071_va.func_101648_b(int, int, int, int)boolean
		// @56: ifeq @5D
		// @59: goto @61
		// @5C: athrow
		// @5D: getstatic game.C_100133_tk game.C_100256_pk.field_100466_a
		// @60: areturn
		// @61: goto @69
		// @64: astore_2
		// @65: getstatic game.C_100133_tk game.C_100256_pk.field_100466_a
		// @68: areturn
		// @69: getstatic game.C_100133_tk game.C_100079_e.field_102670_tb
		// @6C: areturn
		// @6D: astore_2
		// @6E: aload_2
		// @6F: new java.lang.StringBuilder
		// @72: dup
		// @73: invokespecial java.lang.StringBuilder.<init>()void
		// @76: getstatic java.lang.String[] game.C_100275_na.field_103097_z
		// @79: bipush 12 (0x0C)
		// @7B: aaload
		// @7C: invokevirtual java.lang.StringBuilder.append(java.lang.String)java.lang.StringBuilder
		// @7F: iload_1
		// @80: invokevirtual java.lang.StringBuilder.append(boolean)java.lang.StringBuilder
		// @83: bipush 41 (0x29)
		// @85: invokevirtual java.lang.StringBuilder.append(char)java.lang.StringBuilder
		// @88: invokevirtual java.lang.StringBuilder.toString()java.lang.String
		// @8B: invokestatic game.C_100181_cf.func_105695_a(java.lang.Throwable, java.lang.String)game.C_100170_cm
		// @8E: athrow
	}
	
	final String func_102957_d(int arg0)
	{
		// @00: aload_0
		// @01: getfield game.C_100051_ea game.C_100275_na.field_103094_r
		// @04: bipush 80 (0x50)
		// @06: invokevirtual game.C_100051_ea.func_103300_a(byte)int
		// @09: istore_2
		// @0A: aload_0
		// @0B: getfield game.C_100051_ea game.C_100275_na.field_103094_r
		// @0E: bipush -13 (0xF3)
		// @10: invokevirtual game.C_100051_ea.func_103299_k(int)int
		// @13: istore_3
		// @14: iload_1
		// @15: sipush -29062 (0x8E7A)
		// @18: if_icmpeq @20
		// @1B: aconst_null
		// @1C: checkcast java.lang.String
		// @1F: areturn
		// @20: aload_0
		// @21: getfield game.C_100051_ea game.C_100275_na.field_103094_r
		// @24: iload_1
		// @25: sipush 29061 (0x7185)
		// @28: iadd
		// @29: invokevirtual game.C_100051_ea.func_103303_n(int)int
		// @2C: istore #4
		// @2E: bipush 127 (0x7F)
		// @30: invokestatic game.C_100335_il.func_107363_b(byte)int
		// @33: istore #5
		// @35: sipush 1890 (0x0762)
		// @38: iload #4
		// @3A: if_icmpgt @53
		// @3D: bipush -3 (0xFD)
		// @3F: iload #5
		// @41: iadd
		// @42: iconst_m1
		// @43: ixor
		// @44: iload #4
		// @46: iconst_m1
		// @47: ixor
		// @48: if_icmpgt @53
		// @4B: goto @4F
		// @4E: athrow
		// @4F: goto @75
		// @52: athrow
		// @53: sipush -30945 (0x871F)
		// @56: iconst_2
		// @57: anewarray java.lang.String
		// @5A: dup
		// @5B: iconst_0
		// @5C: getstatic java.lang.String[] game.C_100275_na.field_103097_z
		// @5F: bipush 7 (0x07)
		// @61: aaload
		// @62: aastore
		// @63: dup
		// @64: iconst_1
		// @65: bipush -3 (0xFD)
		// @67: iload #5
		// @69: iadd
		// @6A: invokestatic java.lang.Integer.toString(int)java.lang.String
		// @6D: aastore
		// @6E: getstatic java.lang.String game.C_100313_lg.field_107168_a
		// @71: invokestatic game.C_100132_td.func_104965_a(int, java.lang.String[], java.lang.String)java.lang.String
		// @74: areturn
		// @75: bipush 122 (0x7A)
		// @77: iload #4
		// @79: iload_2
		// @7A: iload_3
		// @7B: invokestatic game.C_100071_va.func_101648_b(int, int, int, int)boolean
		// @7E: ifne @85
		// @81: goto @87
		// @84: athrow
		// @85: aconst_null
		// @86: areturn
		// @87: goto @8B
		// @8A: astore_2
		// @8B: getstatic java.lang.String game.C_100023_hg.field_103928_h
		// @8E: areturn
		// @8F: astore_2
		// @90: aload_2
		// @91: new java.lang.StringBuilder
		// @94: dup
		// @95: invokespecial java.lang.StringBuilder.<init>()void
		// @98: getstatic java.lang.String[] game.C_100275_na.field_103097_z
		// @9B: bipush 6 (0x06)
		// @9D: aaload
		// @9E: invokevirtual java.lang.StringBuilder.append(java.lang.String)java.lang.StringBuilder
		// @A1: iload_1
		// @A2: invokevirtual java.lang.StringBuilder.append(int)java.lang.StringBuilder
		// @A5: bipush 41 (0x29)
		// @A7: invokevirtual java.lang.StringBuilder.append(char)java.lang.StringBuilder
		// @AA: invokevirtual java.lang.StringBuilder.toString()java.lang.String
		// @AD: invokestatic game.C_100181_cf.func_105695_a(java.lang.Throwable, java.lang.String)game.C_100170_cm
		// @B0: athrow
	}
	
	static final void func_103081_f(int arg0)
	{
		// @000: new game.C_100037_wb
		// @003: dup
		// @004: bipush 120 (0x78)
		// @006: bipush 30 (0x1E)
		// @008: invokespecial game.C_100037_wb.<init>(int, int)void
		// @00B: astore_1
		// @00C: getstatic game.C_100153_be[] game.C_100312_ld.field_107157_a
		// @00F: iconst_0
		// @010: bipush -123 (0x85)
		// @012: aload_1
		// @013: getstatic java.lang.String game.C_100209_qb.field_102695_Jb
		// @016: invokestatic game.C_100271_mj.func_103431_a(int, game.C_100037_wb, java.lang.String)game.C_100153_be
		// @019: aastore
		// @01A: getstatic game.C_100153_be[] game.C_100312_ld.field_107157_a
		// @01D: iconst_1
		// @01E: bipush -127 (0x81)
		// @020: aload_1
		// @021: getstatic java.lang.String game.C_100266_me.field_106652_b
		// @024: invokestatic game.C_100271_mj.func_103431_a(int, game.C_100037_wb, java.lang.String)game.C_100153_be
		// @027: aastore
		// @028: iload_0
		// @029: sipush -20928 (0xAE40)
		// @02C: if_icmpeq @040
		// @02F: aconst_null
		// @030: checkcast game.C_100314_lf
		// @033: aconst_null
		// @034: checkcast game.C_100037_wb
		// @037: bipush -73 (0xB7)
		// @039: invokestatic game.C_100275_na.func_103078_a(game.C_100314_lf, game.C_100037_wb, byte)void
		// @03C: goto @040
		// @03F: athrow
		// @040: getstatic game.C_100153_be[] game.C_100312_ld.field_107157_a
		// @043: iconst_2
		// @044: bipush -120 (0x88)
		// @046: aload_1
		// @047: getstatic java.lang.String game.C_100044_vm.field_100953_x
		// @04A: invokestatic game.C_100271_mj.func_103431_a(int, game.C_100037_wb, java.lang.String)game.C_100153_be
		// @04D: aastore
		// @04E: getstatic game.C_100153_be[] game.C_100312_ld.field_107157_a
		// @051: iconst_3
		// @052: bipush 107 (0x6B)
		// @054: aload_1
		// @055: getstatic java.lang.String game.C_100122_em.field_102074_Yb
		// @058: invokestatic game.C_100271_mj.func_103431_a(int, game.C_100037_wb, java.lang.String)game.C_100153_be
		// @05B: aastore
		// @05C: getstatic game.C_100153_be[] game.C_100312_ld.field_107157_a
		// @05F: iconst_4
		// @060: bipush -124 (0x84)
		// @062: aload_1
		// @063: getstatic java.lang.String game.C_100042_we.field_104135_o
		// @066: invokestatic game.C_100271_mj.func_103431_a(int, game.C_100037_wb, java.lang.String)game.C_100153_be
		// @069: aastore
		// @06A: getstatic game.C_100153_be[] game.C_100312_ld.field_107157_a
		// @06D: iconst_5
		// @06E: bipush 121 (0x79)
		// @070: aload_1
		// @071: getstatic java.lang.String game.C_100332_ii.field_107320_h
		// @074: invokestatic game.C_100271_mj.func_103431_a(int, game.C_100037_wb, java.lang.String)game.C_100153_be
		// @077: aastore
		// @078: getstatic game.C_100153_be[] game.C_100312_ld.field_107157_a
		// @07B: bipush 9 (0x09)
		// @07D: iload_0
		// @07E: sipush 20929 (0x51C1)
		// @081: invokestatic game.C_100089_fa.func_103722_a(int, int)int
		// @084: aload_1
		// @085: getstatic java.lang.String game.C_100329_ih.field_107270_b
		// @088: invokestatic game.C_100271_mj.func_103431_a(int, game.C_100037_wb, java.lang.String)game.C_100153_be
		// @08B: aastore
		// @08C: getstatic game.C_100153_be[] game.C_100312_ld.field_107157_a
		// @08F: bipush 10 (0x0A)
		// @091: bipush -128 (0x80)
		// @093: aload_1
		// @094: getstatic java.lang.String game.C_100275_na.field_103090_k
		// @097: invokestatic game.C_100271_mj.func_103431_a(int, game.C_100037_wb, java.lang.String)game.C_100153_be
		// @09A: aastore
		// @09B: getstatic game.C_100153_be[] game.C_100312_ld.field_107157_a
		// @09E: bipush 11 (0x0B)
		// @0A0: bipush 31 (0x1F)
		// @0A2: aload_1
		// @0A3: getstatic java.lang.String game.C_100231_oc.field_102209_cc
		// @0A6: invokestatic game.C_100271_mj.func_103431_a(int, game.C_100037_wb, java.lang.String)game.C_100153_be
		// @0A9: aastore
		// @0AA: getstatic game.C_100153_be[] game.C_100312_ld.field_107157_a
		// @0AD: bipush 12 (0x0C)
		// @0AF: bipush -127 (0x81)
		// @0B1: aload_1
		// @0B2: getstatic java.lang.String game.C_100233_oa.field_106244_n
		// @0B5: invokestatic game.C_100271_mj.func_103431_a(int, game.C_100037_wb, java.lang.String)game.C_100153_be
		// @0B8: aastore
		// @0B9: getstatic game.C_100153_be[] game.C_100312_ld.field_107157_a
		// @0BC: bipush 13 (0x0D)
		// @0BE: bipush 34 (0x22)
		// @0C0: aload_1
		// @0C1: getstatic java.lang.String game.C_100093_fd.field_102786_R
		// @0C4: invokestatic game.C_100271_mj.func_103431_a(int, game.C_100037_wb, java.lang.String)game.C_100153_be
		// @0C7: aastore
		// @0C8: getstatic game.C_100153_be[] game.C_100312_ld.field_107157_a
		// @0CB: bipush 14 (0x0E)
		// @0CD: iload_0
		// @0CE: sipush 20801 (0x5141)
		// @0D1: iadd
		// @0D2: aload_1
		// @0D3: getstatic java.lang.String game.C_100160_sm.field_105417_a
		// @0D6: invokestatic game.C_100271_mj.func_103431_a(int, game.C_100037_wb, java.lang.String)game.C_100153_be
		// @0D9: aastore
		// @0DA: getstatic game.C_100153_be[] game.C_100312_ld.field_107157_a
		// @0DD: bipush 15 (0x0F)
		// @0DF: iload_0
		// @0E0: sipush 20800 (0x5140)
		// @0E3: iadd
		// @0E4: aload_1
		// @0E5: getstatic java.lang.String game.C_100343_jf.field_104833_q
		// @0E8: invokestatic game.C_100271_mj.func_103431_a(int, game.C_100037_wb, java.lang.String)game.C_100153_be
		// @0EB: aastore
		// @0EC: getstatic game.C_100153_be[] game.C_100312_ld.field_107157_a
		// @0EF: bipush 16 (0x10)
		// @0F1: bipush -117 (0x8B)
		// @0F3: aload_1
		// @0F4: getstatic java.lang.String game.C_100218_am.field_103117_H
		// @0F7: invokestatic game.C_100271_mj.func_103431_a(int, game.C_100037_wb, java.lang.String)game.C_100153_be
		// @0FA: aastore
		// @0FB: getstatic game.C_100153_be[] game.C_100312_ld.field_107157_a
		// @0FE: arraylength
		// @0FF: anewarray game.C_100153_be
		// @102: putstatic game.C_100153_be[] game.C_100094_j.field_104548_e
		// @105: getstatic game.C_100153_be[] game.C_100312_ld.field_107157_a
		// @108: iconst_0
		// @109: getstatic game.C_100153_be[] game.C_100094_j.field_104548_e
		// @10C: iconst_0
		// @10D: getstatic game.C_100153_be[] game.C_100312_ld.field_107157_a
		// @110: arraylength
		// @111: invokestatic game.C_100120_en.func_104912_a(java.lang.Object[], int, java.lang.Object[], int, int)void
		// @114: getstatic game.C_100153_be[] game.C_100094_j.field_104548_e
		// @117: bipush 8 (0x08)
		// @119: getstatic game.C_100153_be[] game.C_100312_ld.field_107157_a
		// @11C: bipush 7 (0x07)
		// @11E: aaload
		// @11F: aastore
		// @120: getstatic game.C_100153_be[] game.C_100094_j.field_104548_e
		// @123: iconst_5
		// @124: getstatic game.C_100153_be[] game.C_100312_ld.field_107157_a
		// @127: bipush 15 (0x0F)
		// @129: aaload
		// @12A: aastore
		// @12B: getstatic game.C_100153_be[] game.C_100094_j.field_104548_e
		// @12E: iconst_3
		// @12F: getstatic game.C_100153_be[] game.C_100312_ld.field_107157_a
		// @132: bipush 13 (0x0D)
		// @134: aaload
		// @135: aastore
		// @136: getstatic game.C_100153_be[] game.C_100094_j.field_104548_e
		// @139: iconst_4
		// @13A: getstatic game.C_100153_be[] game.C_100312_ld.field_107157_a
		// @13D: bipush 14 (0x0E)
		// @13F: aaload
		// @140: aastore
		// @141: getstatic game.C_100153_be[] game.C_100094_j.field_104548_e
		// @144: bipush 7 (0x07)
		// @146: getstatic game.C_100153_be[] game.C_100312_ld.field_107157_a
		// @149: bipush 12 (0x0C)
		// @14B: aaload
		// @14C: aastore
		// @14D: getstatic game.C_100153_be[] game.C_100094_j.field_104548_e
		// @150: bipush 15 (0x0F)
		// @152: aconst_null
		// @153: aastore
		// @154: getstatic game.C_100153_be[] game.C_100094_j.field_104548_e
		// @157: bipush 14 (0x0E)
		// @159: aconst_null
		// @15A: aastore
		// @15B: getstatic game.C_100153_be[] game.C_100094_j.field_104548_e
		// @15E: bipush 12 (0x0C)
		// @160: getstatic game.C_100153_be[] game.C_100312_ld.field_107157_a
		// @163: bipush 7 (0x07)
		// @165: aaload
		// @166: aastore
		// @167: getstatic game.C_100153_be[] game.C_100094_j.field_104548_e
		// @16A: bipush 13 (0x0D)
		// @16C: aconst_null
		// @16D: aastore
		// @16E: getstatic game.C_100037_wb[] game.C_100013_fn.field_103739_d
		// @171: bipush 6 (0x06)
		// @173: aaload
		// @174: invokevirtual game.C_100037_wb.func_102379_d()void
		// @177: getstatic game.C_100317_lb game.C_100311_le.field_104719_A
		// @17A: getstatic java.lang.String game.C_100266_me.field_106652_b
		// @17D: bipush 78 (0x4E)
		// @17F: bipush 26 (0x1A)
		// @181: iconst_0
		// @182: iconst_m1
		// @183: invokevirtual game.C_100317_lb.func_101744_b(java.lang.String, int, int, int, int)void
		// @186: getstatic game.C_100317_lb game.C_100311_le.field_104719_A
		// @189: getstatic java.lang.String game.C_100044_vm.field_100953_x
		// @18C: sipush 130 (0x0082)
		// @18F: bipush 26 (0x1A)
		// @191: iconst_0
		// @192: iconst_m1
		// @193: invokevirtual game.C_100317_lb.func_101744_b(java.lang.String, int, int, int, int)void
		// @196: getstatic game.C_100185_rm game.C_100049_vf.field_104206_l
		// @199: bipush 122 (0x7A)
		// @19B: invokevirtual game.C_100185_rm.func_105476_a(byte)void
		// @19E: goto @1C2
		// @1A1: astore_1
		// @1A2: aload_1
		// @1A3: new java.lang.StringBuilder
		// @1A6: dup
		// @1A7: invokespecial java.lang.StringBuilder.<init>()void
		// @1AA: getstatic java.lang.String[] game.C_100275_na.field_103097_z
		// @1AD: iconst_0
		// @1AE: aaload
		// @1AF: invokevirtual java.lang.StringBuilder.append(java.lang.String)java.lang.StringBuilder
		// @1B2: iload_0
		// @1B3: invokevirtual java.lang.StringBuilder.append(int)java.lang.StringBuilder
		// @1B6: bipush 41 (0x29)
		// @1B8: invokevirtual java.lang.StringBuilder.append(char)java.lang.StringBuilder
		// @1BB: invokevirtual java.lang.StringBuilder.toString()java.lang.String
		// @1BE: invokestatic game.C_100181_cf.func_105695_a(java.lang.Throwable, java.lang.String)game.C_100170_cm
		// @1C1: athrow
		// @1C2: return
	}
	
	static final void func_103082_h(int arg0)
	{
		// @00: getstatic int game.SteelSentinels.field_105275_O
		// @03: istore_2
		// @04: iload_0
		// @05: bipush -31 (0xE1)
		// @07: if_icmplt @0B
		// @0A: return
		// @0B: iconst_m1
		// @0C: iconst_1
		// @0D: getstatic int game.C_100055_ed.field_104245_a
		// @10: ishl
		// @11: getstatic game.C_100265_mh game.C_100127_tl.field_104948_b
		// @14: getfield game.C_100294_ki game.C_100265_mh.field_106591_B
		// @17: getfield int game.C_100294_ki.field_106984_n
		// @1A: iand
		// @1B: iconst_m1
		// @1C: ixor
		// @1D: if_icmpeq @31
		// @20: getstatic java.lang.String[] game.C_100268_mk.field_106669_b
		// @23: bipush 10 (0x0A)
		// @25: getstatic java.lang.String game.C_100061_dh.field_101988_jc
		// @28: aastore
		// @29: iload_2
		// @2A: ifeq @62
		// @2D: goto @31
		// @30: athrow
		// @31: iconst_m1
		// @32: getstatic game.C_100265_mh game.C_100127_tl.field_104948_b
		// @35: getfield game.C_100294_ki game.C_100265_mh.field_106591_B
		// @38: getfield int game.C_100294_ki.field_106984_n
		// @3B: iconst_m1
		// @3C: ixor
		// @3D: if_icmpne @55
		// @40: goto @44
		// @43: athrow
		// @44: getstatic java.lang.String[] game.C_100268_mk.field_106669_b
		// @47: bipush 10 (0x0A)
		// @49: getstatic java.lang.String game.C_100186_rl.field_105730_i
		// @4C: aastore
		// @4D: iload_2
		// @4E: ifeq @62
		// @51: goto @55
		// @54: athrow
		// @55: getstatic java.lang.String[] game.C_100268_mk.field_106669_b
		// @58: bipush 10 (0x0A)
		// @5A: getstatic java.lang.String game.C_100089_fa.field_103723_f
		// @5D: aastore
		// @5E: goto @62
		// @61: athrow
		// @62: goto @86
		// @65: astore_1
		// @66: aload_1
		// @67: new java.lang.StringBuilder
		// @6A: dup
		// @6B: invokespecial java.lang.StringBuilder.<init>()void
		// @6E: getstatic java.lang.String[] game.C_100275_na.field_103097_z
		// @71: iconst_1
		// @72: aaload
		// @73: invokevirtual java.lang.StringBuilder.append(java.lang.String)java.lang.StringBuilder
		// @76: iload_0
		// @77: invokevirtual java.lang.StringBuilder.append(int)java.lang.StringBuilder
		// @7A: bipush 41 (0x29)
		// @7C: invokevirtual java.lang.StringBuilder.append(char)java.lang.StringBuilder
		// @7F: invokevirtual java.lang.StringBuilder.toString()java.lang.String
		// @82: invokestatic game.C_100181_cf.func_105695_a(java.lang.Throwable, java.lang.String)game.C_100170_cm
		// @85: athrow
		// @86: return
	}
	
	public final void func_102579_a(int arg0, C_100309_lk arg1)
	{
		// @00: iload_1
		// @01: bipush 20 (0x14)
		// @03: if_icmpeq @0D
		// @06: aconst_null
		// @07: checkcast java.lang.String
		// @0A: putstatic java.lang.String game.C_100275_na.field_103085_n
		// @0D: goto @4B
		// @10: astore_3
		// @11: aload_3
		// @12: new java.lang.StringBuilder
		// @15: dup
		// @16: invokespecial java.lang.StringBuilder.<init>()void
		// @19: getstatic java.lang.String[] game.C_100275_na.field_103097_z
		// @1C: iconst_3
		// @1D: aaload
		// @1E: invokevirtual java.lang.StringBuilder.append(java.lang.String)java.lang.StringBuilder
		// @21: iload_1
		// @22: invokevirtual java.lang.StringBuilder.append(int)java.lang.StringBuilder
		// @25: bipush 44 (0x2C)
		// @27: invokevirtual java.lang.StringBuilder.append(char)java.lang.StringBuilder
		// @2A: aload_2
		// @2B: ifnull @37
		// @2E: getstatic java.lang.String[] game.C_100275_na.field_103097_z
		// @31: iconst_4
		// @32: aaload
		// @33: goto @3C
		// @36: athrow
		// @37: getstatic java.lang.String[] game.C_100275_na.field_103097_z
		// @3A: iconst_2
		// @3B: aaload
		// @3C: invokevirtual java.lang.StringBuilder.append(java.lang.String)java.lang.StringBuilder
		// @3F: bipush 41 (0x29)
		// @41: invokevirtual java.lang.StringBuilder.append(char)java.lang.StringBuilder
		// @44: invokevirtual java.lang.StringBuilder.toString()java.lang.String
		// @47: invokestatic game.C_100181_cf.func_105695_a(java.lang.Throwable, java.lang.String)game.C_100170_cm
		// @4A: athrow
		// @4B: return
	}
	
	static final void func_103078_a(C_100314_lf arg0, C_100037_wb arg1, byte arg2)
	{
		// @000: getstatic int game.SteelSentinels.field_105275_O
		// @003: istore #9
		// @005: iconst_0
		// @006: istore_3
		// @007: iconst_0
		// @008: istore #4
		// @00A: iload #4
		// @00C: iconst_m1
		// @00D: ixor
		// @00E: aload_1
		// @00F: getfield int game.C_100037_wb.field_102340_z
		// @012: iconst_m1
		// @013: ixor
		// @014: if_icmple @0DB
		// @017: iconst_0
		// @018: iload #9
		// @01A: ifne @0DC
		// @01D: istore #5
		// @01F: iload #5
		// @021: aload_1
		// @022: getfield int game.C_100037_wb.field_102341_y
		// @025: if_icmpge @0CC
		// @028: aload_1
		// @029: getfield int[] game.C_100037_wb.field_102388_J
		// @02C: iload #5
		// @02E: iload_3
		// @02F: ineg
		// @030: isub
		// @031: iaload
		// @032: istore #6
		// @034: iload #6
		// @036: ldc -2012535384 (0x880b25a8)
		// @038: ishr
		// @039: ldc 65535 (0xffff)
		// @03B: iload #6
		// @03D: iand
		// @03E: iload #9
		// @040: ifne @0D1
		// @043: if_icmpne @099
		// @046: goto @04A
		// @049: athrow
		// @04A: aload_0
		// @04B: iconst_m1
		// @04C: invokevirtual game.C_100314_lf.func_101253_j(int)int
		// @04F: istore #7
		// @051: iload #6
		// @053: sipush 255 (0x00FF)
		// @056: iand
		// @057: istore #8
		// @059: bipush -65 (0xBF)
		// @05B: iload #8
		// @05D: iconst_m1
		// @05E: ixor
		// @05F: if_icmpgt @066
		// @062: goto @094
		// @065: athrow
		// @066: aload_1
		// @067: getfield int[] game.C_100037_wb.field_102388_J
		// @06A: iload_3
		// @06B: iload #5
		// @06D: iadd
		// @06E: ldc 16711862 (0xff00b6)
		// @070: iload #8
		// @072: ldc 65280 (0xff00)
		// @074: iload #7
		// @076: invokestatic game.C_100256_pk.func_100449_a(int, int)int
		// @079: imul
		// @07A: invokestatic game.C_100256_pk.func_100449_a(int, int)int
		// @07D: ldc 569757256 (0x21f5ce48)
		// @07F: ishr
		// @080: iload #8
		// @082: ldc 16711935 (0xff00ff)
		// @084: iload #7
		// @086: invokestatic game.C_100256_pk.func_100449_a(int, int)int
		// @089: imul
		// @08A: ldc -503664376 (0xe1fab108)
		// @08C: ishr
		// @08D: ldc 16711935 (0xff00ff)
		// @08F: invokestatic game.C_100256_pk.func_100449_a(int, int)int
		// @092: iadd
		// @093: iastore
		// @094: iload #9
		// @096: ifeq @0C4
		// @099: sipush 255 (0x00FF)
		// @09C: iload #6
		// @09E: iand
		// @09F: istore #7
		// @0A1: iload #7
		// @0A3: iconst_2
		// @0A4: idiv
		// @0A5: istore #7
		// @0A7: bipush -33 (0xDF)
		// @0A9: iload #7
		// @0AB: iconst_m1
		// @0AC: ixor
		// @0AD: if_icmpgt @0B4
		// @0B0: goto @0C4
		// @0B3: athrow
		// @0B4: aload_1
		// @0B5: getfield int[] game.C_100037_wb.field_102388_J
		// @0B8: iload_3
		// @0B9: iload #5
		// @0BB: iadd
		// @0BC: iload #7
		// @0BE: aload_0
		// @0BF: getfield int game.C_100314_lf.field_101336_Q
		// @0C2: imul
		// @0C3: iastore
		// @0C4: iinc #5 +1
		// @0C7: iload #9
		// @0C9: ifeq @01F
		// @0CC: iload_3
		// @0CD: aload_1
		// @0CE: getfield int game.C_100037_wb.field_102341_y
		// @0D1: iadd
		// @0D2: istore_3
		// @0D3: iinc #4 +1
		// @0D6: iload #9
		// @0D8: ifeq @00A
		// @0DB: iload_2
		// @0DC: bipush -13 (0xF3)
		// @0DE: if_icmpeq @0EC
		// @0E1: aconst_null
		// @0E2: checkcast int[]
		// @0E5: putstatic int[] game.C_100275_na.field_103095_q
		// @0E8: goto @0EC
		// @0EB: athrow
		// @0EC: goto @145
		// @0EF: astore_3
		// @0F0: aload_3
		// @0F1: new java.lang.StringBuilder
		// @0F4: dup
		// @0F5: invokespecial java.lang.StringBuilder.<init>()void
		// @0F8: getstatic java.lang.String[] game.C_100275_na.field_103097_z
		// @0FB: bipush 10 (0x0A)
		// @0FD: aaload
		// @0FE: invokevirtual java.lang.StringBuilder.append(java.lang.String)java.lang.StringBuilder
		// @101: aload_0
		// @102: ifnull @10E
		// @105: getstatic java.lang.String[] game.C_100275_na.field_103097_z
		// @108: iconst_4
		// @109: aaload
		// @10A: goto @113
		// @10D: athrow
		// @10E: getstatic java.lang.String[] game.C_100275_na.field_103097_z
		// @111: iconst_2
		// @112: aaload
		// @113: invokevirtual java.lang.StringBuilder.append(java.lang.String)java.lang.StringBuilder
		// @116: bipush 44 (0x2C)
		// @118: invokevirtual java.lang.StringBuilder.append(char)java.lang.StringBuilder
		// @11B: aload_1
		// @11C: ifnull @128
		// @11F: getstatic java.lang.String[] game.C_100275_na.field_103097_z
		// @122: iconst_4
		// @123: aaload
		// @124: goto @12D
		// @127: athrow
		// @128: getstatic java.lang.String[] game.C_100275_na.field_103097_z
		// @12B: iconst_2
		// @12C: aaload
		// @12D: invokevirtual java.lang.StringBuilder.append(java.lang.String)java.lang.StringBuilder
		// @130: bipush 44 (0x2C)
		// @132: invokevirtual java.lang.StringBuilder.append(char)java.lang.StringBuilder
		// @135: iload_2
		// @136: invokevirtual java.lang.StringBuilder.append(int)java.lang.StringBuilder
		// @139: bipush 41 (0x29)
		// @13B: invokevirtual java.lang.StringBuilder.append(char)java.lang.StringBuilder
		// @13E: invokevirtual java.lang.StringBuilder.toString()java.lang.String
		// @141: invokestatic game.C_100181_cf.func_105695_a(java.lang.Throwable, java.lang.String)game.C_100170_cm
		// @144: athrow
		// @145: return
	}
	
	public final boolean func_102952_a(int arg0)
	{
		// @00: iload_1
		// @01: bipush -50 (0xCE)
		// @03: if_icmple @11
		// @06: aconst_null
		// @07: checkcast java.lang.String
		// @0A: putstatic java.lang.String game.C_100275_na.field_103090_k
		// @0D: goto @11
		// @10: athrow
		// @11: aload_0
		// @12: getfield game.C_100051_ea game.C_100275_na.field_103094_r
		// @15: bipush 68 (0x44)
		// @17: invokevirtual game.C_100051_ea.func_103293_l(int)boolean
		// @1A: ireturn
		// @1B: astore_2
		// @1C: aload_2
		// @1D: new java.lang.StringBuilder
		// @20: dup
		// @21: invokespecial java.lang.StringBuilder.<init>()void
		// @24: getstatic java.lang.String[] game.C_100275_na.field_103097_z
		// @27: bipush 9 (0x09)
		// @29: aaload
		// @2A: invokevirtual java.lang.StringBuilder.append(java.lang.String)java.lang.StringBuilder
		// @2D: iload_1
		// @2E: invokevirtual java.lang.StringBuilder.append(int)java.lang.StringBuilder
		// @31: bipush 41 (0x29)
		// @33: invokevirtual java.lang.StringBuilder.append(char)java.lang.StringBuilder
		// @36: invokevirtual java.lang.StringBuilder.toString()java.lang.String
		// @39: invokestatic game.C_100181_cf.func_105695_a(java.lang.Throwable, java.lang.String)game.C_100170_cm
		// @3C: athrow
	}
	
	static
	{
		// @000: bipush 13 (0x0D)
		// @002: anewarray java.lang.String
		// @005: dup
		// @006: iconst_0
		// @007: ldc "&Er+7`"
		// @009: invokestatic game.C_100275_na.func_103080_z(java.lang.String)char[]
		// @00C: invokestatic game.C_100275_na.func_103079_z(char[])java.lang.String
		// @00F: aastore
		// @010: dup
		// @011: iconst_1
		// @012: ldc "&Er)7`"
		// @014: invokestatic game.C_100275_na.func_103080_z(java.lang.String)char[]
		// @017: invokestatic game.C_100275_na.func_103079_z(char[])java.lang.String
		// @01A: aastore
		// @01B: dup
		// @01C: iconst_2
		// @01D: ldc "&Q0\u0017"
		// @01F: invokestatic game.C_100275_na.func_103080_z(java.lang.String)char[]
		// @022: invokestatic game.C_100275_na.func_103079_z(char[])java.lang.String
		// @025: aastore
		// @026: dup
		// @027: iconst_3
		// @028: ldc "&Er27`"
		// @02A: invokestatic game.C_100275_na.func_103080_z(java.lang.String)char[]
		// @02D: invokestatic game.C_100275_na.func_103079_z(char[])java.lang.String
		// @030: aastore
		// @031: dup
		// @032: iconst_4
		// @033: ldc "3\nrU\u000b"
		// @035: invokestatic game.C_100275_na.func_103080_z(java.lang.String)char[]
		// @038: invokestatic game.C_100275_na.func_103079_z(char[])java.lang.String
		// @03B: aastore
		// @03C: dup
		// @03D: iconst_5
		// @03E: ldc "&Er67`"
		// @040: invokestatic game.C_100275_na.func_103080_z(java.lang.String)char[]
		// @043: invokestatic game.C_100275_na.func_103079_z(char[])java.lang.String
		// @046: aastore
		// @047: dup
		// @048: bipush 6 (0x06)
		// @04A: ldc "&Er47`"
		// @04C: invokestatic game.C_100275_na.func_103080_z(java.lang.String)char[]
		// @04F: invokestatic game.C_100275_na.func_103079_z(char[])java.lang.String
		// @052: aastore
		// @053: dup
		// @054: bipush 7 (0x07)
		// @056: ldc "y\u001ceK"
		// @058: invokestatic game.C_100275_na.func_103080_z(java.lang.String)char[]
		// @05B: invokestatic game.C_100275_na.func_103079_z(char[])java.lang.String
		// @05E: aastore
		// @05F: dup
		// @060: bipush 8 (0x08)
		// @062: ldc "&Er*7`"
		// @064: invokestatic game.C_100275_na.func_103080_z(java.lang.String)char[]
		// @067: invokestatic game.C_100275_na.func_103079_z(char[])java.lang.String
		// @06A: aastore
		// @06B: dup
		// @06C: bipush 9 (0x09)
		// @06E: ldc "&Er57`"
		// @070: invokestatic game.C_100275_na.func_103080_z(java.lang.String)char[]
		// @073: invokestatic game.C_100275_na.func_103079_z(char[])java.lang.String
		// @076: aastore
		// @077: dup
		// @078: bipush 10 (0x0A)
		// @07A: ldc "&Er37`"
		// @07C: invokestatic game.C_100275_na.func_103080_z(java.lang.String)char[]
		// @07F: invokestatic game.C_100275_na.func_103079_z(char[])java.lang.String
		// @082: aastore
		// @083: dup
		// @084: bipush 11 (0x0B)
		// @086: ldc "&Er07`"
		// @088: invokestatic game.C_100275_na.func_103080_z(java.lang.String)char[]
		// @08B: invokestatic game.C_100275_na.func_103079_z(char[])java.lang.String
		// @08E: aastore
		// @08F: dup
		// @090: bipush 12 (0x0C)
		// @092: ldc "&Er<7`"
		// @094: invokestatic game.C_100275_na.func_103080_z(java.lang.String)char[]
		// @097: invokestatic game.C_100275_na.func_103079_z(char[])java.lang.String
		// @09A: aastore
		// @09B: putstatic java.lang.String[] game.C_100275_na.field_103097_z
		// @09E: iconst_2
		// @09F: invokestatic game.C_100015_wh.func_103779_b(int)int[]
		// @0A2: putstatic int[] game.C_100275_na.field_103095_q
		// @0A5: getstatic int[] game.C_100275_na.field_103095_q
		// @0A8: iconst_0
		// @0A9: ldc -410976256 (0xe7810000)
		// @0AB: iastore
		// @0AC: getstatic int[] game.C_100275_na.field_103095_q
		// @0AF: astore_0
		// @0B0: aload_0
		// @0B1: iconst_1
		// @0B2: aload_0
		// @0B3: iconst_1
		// @0B4: iaload
		// @0B5: bipush 32 (0x20)
		// @0B7: invokestatic game.C_100116_ei.func_104117_a(int, int)int
		// @0BA: iastore
		// @0BB: iconst_2
		// @0BC: invokestatic game.C_100015_wh.func_103779_b(int)int[]
		// @0BF: putstatic int[] game.C_100275_na.field_103086_o
		// @0C2: getstatic int[] game.C_100275_na.field_103086_o
		// @0C5: astore_0
		// @0C6: aload_0
		// @0C7: iconst_1
		// @0C8: aload_0
		// @0C9: iconst_1
		// @0CA: iaload
		// @0CB: bipush 8 (0x08)
		// @0CD: invokestatic game.C_100116_ei.func_104117_a(int, int)int
		// @0D0: iastore
		// @0D1: getstatic int[] game.C_100275_na.field_103086_o
		// @0D4: iconst_0
		// @0D5: ldc -1711275968 (0x9a000040)
		// @0D7: iastore
		// @0D8: getstatic int[] game.C_100275_na.field_103086_o
		// @0DB: astore_0
		// @0DC: aload_0
		// @0DD: iconst_1
		// @0DE: aload_0
		// @0DF: iconst_1
		// @0E0: iaload
		// @0E1: bipush 16 (0x10)
		// @0E3: invokestatic game.C_100116_ei.func_104117_a(int, int)int
		// @0E6: iastore
		// @0E7: iconst_2
		// @0E8: invokestatic game.C_100015_wh.func_103779_b(int)int[]
		// @0EB: putstatic int[] game.C_100275_na.field_103092_i
		// @0EE: getstatic int[] game.C_100275_na.field_103092_i
		// @0F1: iconst_0
		// @0F2: ldc 64712 (0xfcc8)
		// @0F4: iastore
		// @0F5: bipush 32 (0x20)
		// @0F7: istore_0
		// @0F8: iload_0
		// @0F9: iconst_m1
		// @0FA: ixor
		// @0FB: bipush -37 (0xDB)
		// @0FD: if_icmplt @123
		// @100: getstatic int[] game.C_100275_na.field_103092_i
		// @103: astore_1
		// @104: iload_0
		// @105: istore_2
		// @106: aload_1
		// @107: iload_2
		// @108: ldc 160114149 (0x98b25e5)
		// @10A: ishr
		// @10B: aload_1
		// @10C: iload_2
		// @10D: ldc 160114149 (0x98b25e5)
		// @10F: ishr
		// @110: iaload
		// @111: iconst_1
		// @112: bipush 31 (0x1F)
		// @114: iload_2
		// @115: invokestatic game.C_100256_pk.func_100449_a(int, int)int
		// @118: ishl
		// @119: invokestatic game.C_100116_ei.func_104117_a(int, int)int
		// @11C: iastore
		// @11D: iinc #0 +1
		// @120: goto @0F8
		// @123: getstatic int[] game.C_100275_na.field_103095_q
		// @126: astore_0
		// @127: aload_0
		// @128: iconst_1
		// @129: aload_0
		// @12A: iconst_1
		// @12B: iaload
		// @12C: bipush 64 (0x40)
		// @12E: invokestatic game.C_100116_ei.func_104117_a(int, int)int
		// @131: iastore
		// @132: ldc "\nA?\u0014\u001b-\u0004=[\u001b-I>\u001e\u0004hP3[\u0011-P|\u000f\u001e!W|\u001e\u000e8E2\u0008\u001f'J|\u001a\u0018,\nrU"
		// @134: invokestatic game.C_100275_na.func_103080_z(java.lang.String)char[]
		// @137: invokestatic game.C_100275_na.func_103079_z(char[])java.lang.String
		// @13A: putstatic java.lang.String game.C_100275_na.field_103089_j
		// @13D: iconst_3
		// @13E: newarray int[]
		// @140: putstatic int[] game.C_100275_na.field_103087_l
		// @143: ldc "\u001aA6\u001e\u0015<"
		// @145: invokestatic game.C_100275_na.func_103080_z(java.lang.String)char[]
		// @148: invokestatic game.C_100275_na.func_103079_z(char[])java.lang.String
		// @14B: putstatic java.lang.String game.C_100275_na.field_103088_m
		// @14E: ldc "\u001bl\u0015=\""
		// @150: invokestatic game.C_100275_na.func_103080_z(java.lang.String)char[]
		// @153: invokestatic game.C_100275_na.func_103079_z(char[])java.lang.String
		// @156: putstatic java.lang.String game.C_100275_na.field_103090_k
		// @159: ldc "\u0007V>[\u0015'M2\u0008Lh"
		// @15B: invokestatic game.C_100275_na.func_103080_z(java.lang.String)char[]
		// @15E: invokestatic game.C_100275_na.func_103079_z(char[])java.lang.String
		// @161: putstatic java.lang.String game.C_100275_na.field_103091_h
		// @164: ldc "\u001fA|\u0018\u001a'W9\u001fV<L9[\u0015'J2\u001e\u0015<M3\u0015V*A?\u001a\u0003;A|\u000f\u001e-\u0004;\u001a\u001b-\u0004+\u001a\u0005hH9\u001d\u0002hQ2\u001a\u0002<A2\u001f\u0013,\u0004:\u0014\u0004h\u0016l[\u001b!J)\u000f\u0013;\n|+\u001a-E/\u001eV.A9\u0017V.V9\u001eV<K|\t\u0013+K2\u0015\u0013+P|\u0012\u001b%A8\u0012\u0017<A0\u0002V!B|\u0002\u0019=\u0004=\t\u0013hP4\u001e\u0004-\n"
		// @166: invokestatic game.C_100275_na.func_103080_z(java.lang.String)char[]
		// @169: invokestatic game.C_100275_na.func_103079_z(char[])java.lang.String
		// @16C: putstatic java.lang.String game.C_100275_na.field_103085_n
		// @16F: iconst_0
		// @170: putstatic int game.C_100275_na.field_103096_p
		// @173: return
	}
	
	private static char[] func_103080_z(String arg0)
	{
		// @00: aload_0
		// @01: invokevirtual java.lang.String.toCharArray()char[]
		// @04: dup
		// @05: arraylength
		// @06: iconst_2
		// @07: if_icmpge @13
		// @0A: dup
		// @0B: iconst_0
		// @0C: dup2
		// @0D: caload
		// @0E: bipush 118 (0x76)
		// @10: ixor
		// @11: i2c
		// @12: castore
		// @13: areturn
	}
	
	private static String func_103079_z(char[] arg0)
	{
		// @00: aload_0
		// @01: dup
		// @02: arraylength
		// @03: swap
		// @04: iconst_0
		// @05: istore_1
		// @06: goto @4C
		// @09: dup
		// @0A: iload_1
		// @0B: dup2
		// @0C: caload
		// @0D: iload_1
		// @0E: iconst_5
		// @0F: irem
		// @10: tableswitch def: @44, for 0: @30, for 1: @35, for 2: @3A, for 3: @3F
		// @30: bipush 72 (0x48)
		// @32: goto @46
		// @35: bipush 36 (0x24)
		// @37: goto @46
		// @3A: bipush 92 (0x5C)
		// @3C: goto @46
		// @3F: bipush 123 (0x7B)
		// @41: goto @46
		// @44: bipush 118 (0x76)
		// @46: ixor
		// @47: i2c
		// @48: castore
		// @49: iinc #1 +1
		// @4C: swap
		// @4D: dup_x1
		// @4E: iload_1
		// @4F: if_icmpgt @09
		// @52: new java.lang.String
		// @55: dup_x1
		// @56: swap
		// @57: invokespecial java.lang.String.<init>(char[])void
		// @5A: invokevirtual java.lang.String.intern()java.lang.String
		// @5D: areturn
	}
}
