package game;

import java.util.Calendar;
import java.applet.Applet;

final class C_100254_pi
{
	static C_100037_wb[] field_106468_p;
	byte[][] field_106451_c;
	static String field_106463_u;
	private int field_106456_m;
	int[] field_106448_d;
	private int[] field_106467_q;
	static Applet field_106447_g;
	C_100263_mb[] field_106465_s;
	C_100263_mb field_106446_f;
	int[] field_106454_o;
	int field_106450_b;
	int[] field_106452_a;
	static C_100037_wb field_106457_j;
	int field_106462_v;
	int[] field_106455_l;
	int field_106461_w;
	int[][] field_106466_r;
	private int[][] field_106449_e;
	private byte[] field_106464_t;
	int[] field_106453_n;
	static Calendar field_106460_i;
	static C_100327_ib field_106459_h;
	static C_100228_nn field_106470_x;
	static int[] field_106458_k;
	private static final String[] field_106469_z;
	
	private final void func_106445_a(byte arg0, byte[] arg1)
	{
		// @000: getstatic int game.SteelSentinels.field_105275_O
		// @003: istore #16
		// @005: new game.C_100280_nf
		// @008: dup
		// @009: aload_2
		// @00A: bipush 77 (0x4D)
		// @00C: invokestatic game.C_100266_me.func_106647_a(byte[], int)byte[]
		// @00F: invokespecial game.C_100280_nf.<init>(byte[])void
		// @012: astore_3
		// @013: aload_3
		// @014: iconst_0
		// @015: invokevirtual game.C_100280_nf.func_101156_c(boolean)int
		// @018: istore #4
		// @01A: iconst_5
		// @01B: iload #4
		// @01D: if_icmpgt @031
		// @020: iload #4
		// @022: iconst_m1
		// @023: ixor
		// @024: bipush -8 (0xF8)
		// @026: if_icmplt @031
		// @029: goto @02D
		// @02C: athrow
		// @02D: goto @039
		// @030: athrow
		// @031: new java.lang.RuntimeException
		// @034: dup
		// @035: invokespecial java.lang.RuntimeException.<init>()void
		// @038: athrow
		// @039: iload #4
		// @03B: iconst_m1
		// @03C: ixor
		// @03D: bipush -7 (0xF9)
		// @03F: if_icmpgt @056
		// @042: aload_0
		// @043: aload_3
		// @044: sipush -1543 (0xF9F9)
		// @047: invokevirtual game.C_100280_nf.func_101171_e(int)int
		// @04A: putfield int game.C_100254_pi.field_106461_w
		// @04D: iload #16
		// @04F: ifeq @05F
		// @052: goto @056
		// @055: athrow
		// @056: aload_0
		// @057: iconst_0
		// @058: putfield int game.C_100254_pi.field_106461_w
		// @05B: goto @05F
		// @05E: athrow
		// @05F: aload_3
		// @060: iconst_0
		// @061: invokevirtual game.C_100280_nf.func_101156_c(boolean)int
		// @064: istore #5
		// @066: iload #5
		// @068: iconst_1
		// @069: iand
		// @06A: iconst_m1
		// @06B: ixor
		// @06C: iconst_m1
		// @06D: if_icmpeq @075
		// @070: iconst_1
		// @071: goto @076
		// @074: athrow
		// @075: iconst_0
		// @076: istore #6
		// @078: iload #4
		// @07A: bipush 7 (0x07)
		// @07C: if_icmpge @092
		// @07F: aload_0
		// @080: aload_3
		// @081: bipush -2 (0xFE)
		// @083: invokevirtual game.C_100280_nf.func_101143_l(int)int
		// @086: putfield int game.C_100254_pi.field_106456_m
		// @089: iload #16
		// @08B: ifeq @09F
		// @08E: goto @092
		// @091: athrow
		// @092: aload_0
		// @093: aload_3
		// @094: iconst_1
		// @095: invokevirtual game.C_100280_nf.func_101160_a(boolean)int
		// @098: putfield int game.C_100254_pi.field_106456_m
		// @09B: goto @09F
		// @09E: athrow
		// @09F: iconst_0
		// @0A0: iload #5
		// @0A2: iconst_2
		// @0A3: iand
		// @0A4: if_icmpeq @0AC
		// @0A7: iconst_1
		// @0A8: goto @0AD
		// @0AB: athrow
		// @0AC: iconst_0
		// @0AD: istore #7
		// @0AF: iconst_0
		// @0B0: istore #8
		// @0B2: aload_0
		// @0B3: aload_0
		// @0B4: getfield int game.C_100254_pi.field_106456_m
		// @0B7: newarray int[]
		// @0B9: putfield int[] game.C_100254_pi.field_106455_l
		// @0BC: iload_1
		// @0BD: bipush -71 (0xB9)
		// @0BF: if_icmpeq @0D0
		// @0C2: aload_0
		// @0C3: bipush -55 (0xC9)
		// @0C5: aconst_null
		// @0C6: checkcast byte[]
		// @0C9: invokespecial game.C_100254_pi.func_106445_a(byte, byte[])void
		// @0CC: goto @0D0
		// @0CF: athrow
		// @0D0: iconst_m1
		// @0D1: istore #9
		// @0D3: iload #4
		// @0D5: iconst_m1
		// @0D6: ixor
		// @0D7: bipush -8 (0xF8)
		// @0D9: if_icmpgt @129
		// @0DC: iconst_0
		// @0DD: istore #10
		// @0DF: aload_0
		// @0E0: getfield int game.C_100254_pi.field_106456_m
		// @0E3: iload #10
		// @0E5: if_icmple @124
		// @0E8: aload_0
		// @0E9: getfield int[] game.C_100254_pi.field_106455_l
		// @0EC: iload #10
		// @0EE: iload #8
		// @0F0: aload_3
		// @0F1: iconst_1
		// @0F2: invokevirtual game.C_100280_nf.func_101160_a(boolean)int
		// @0F5: iadd
		// @0F6: dup
		// @0F7: istore #8
		// @0F9: iastore
		// @0FA: aload_0
		// @0FB: getfield int[] game.C_100254_pi.field_106455_l
		// @0FE: iload #10
		// @100: iaload
		// @101: iconst_m1
		// @102: ixor
		// @103: iload #9
		// @105: iconst_m1
		// @106: ixor
		// @107: iload #16
		// @109: ifne @1E4
		// @10C: if_icmpge @11C
		// @10F: goto @113
		// @112: athrow
		// @113: aload_0
		// @114: getfield int[] game.C_100254_pi.field_106455_l
		// @117: iload #10
		// @119: iaload
		// @11A: istore #9
		// @11C: iinc #10 +1
		// @11F: iload #16
		// @121: ifeq @0DF
		// @124: iload #16
		// @126: ifeq @175
		// @129: iconst_0
		// @12A: istore #10
		// @12C: iload #10
		// @12E: iconst_m1
		// @12F: ixor
		// @130: aload_0
		// @131: getfield int game.C_100254_pi.field_106456_m
		// @134: iconst_m1
		// @135: ixor
		// @136: if_icmple @175
		// @139: aload_0
		// @13A: getfield int[] game.C_100254_pi.field_106455_l
		// @13D: iload #10
		// @13F: iload #8
		// @141: aload_3
		// @142: bipush -2 (0xFE)
		// @144: invokevirtual game.C_100280_nf.func_101143_l(int)int
		// @147: iadd
		// @148: dup
		// @149: istore #8
		// @14B: iastore
		// @14C: aload_0
		// @14D: getfield int[] game.C_100254_pi.field_106455_l
		// @150: iload #10
		// @152: iaload
		// @153: iload #9
		// @155: iload #16
		// @157: ifne @1E4
		// @15A: if_icmpgt @164
		// @15D: goto @161
		// @160: athrow
		// @161: goto @16D
		// @164: aload_0
		// @165: getfield int[] game.C_100254_pi.field_106455_l
		// @168: iload #10
		// @16A: iaload
		// @16B: istore #9
		// @16D: iinc #10 +1
		// @170: iload #16
		// @172: ifeq @12C
		// @175: aload_0
		// @176: iconst_1
		// @177: iload #9
		// @179: iadd
		// @17A: putfield int game.C_100254_pi.field_106462_v
		// @17D: iload #7
		// @17F: ifeq @191
		// @182: aload_0
		// @183: aload_0
		// @184: getfield int game.C_100254_pi.field_106462_v
		// @187: anewarray byte[]
		// @18A: putfield byte[][] game.C_100254_pi.field_106451_c
		// @18D: goto @191
		// @190: athrow
		// @191: aload_0
		// @192: aload_0
		// @193: getfield int game.C_100254_pi.field_106462_v
		// @196: newarray int[]
		// @198: putfield int[] game.C_100254_pi.field_106454_o
		// @19B: aload_0
		// @19C: aload_0
		// @19D: getfield int game.C_100254_pi.field_106462_v
		// @1A0: newarray int[]
		// @1A2: putfield int[] game.C_100254_pi.field_106453_n
		// @1A5: aload_0
		// @1A6: aload_0
		// @1A7: getfield int game.C_100254_pi.field_106462_v
		// @1AA: newarray int[]
		// @1AC: putfield int[] game.C_100254_pi.field_106448_d
		// @1AF: aload_0
		// @1B0: aload_0
		// @1B1: getfield int game.C_100254_pi.field_106462_v
		// @1B4: newarray int[]
		// @1B6: putfield int[] game.C_100254_pi.field_106452_a
		// @1B9: aload_0
		// @1BA: aload_0
		// @1BB: getfield int game.C_100254_pi.field_106462_v
		// @1BE: anewarray int[]
		// @1C1: putfield int[][] game.C_100254_pi.field_106466_r
		// @1C4: iload #6
		// @1C6: ifne @1CD
		// @1C9: goto @247
		// @1CC: athrow
		// @1CD: aload_0
		// @1CE: aload_0
		// @1CF: getfield int game.C_100254_pi.field_106462_v
		// @1D2: newarray int[]
		// @1D4: putfield int[] game.C_100254_pi.field_106467_q
		// @1D7: iconst_0
		// @1D8: istore #10
		// @1DA: iload #10
		// @1DC: iconst_m1
		// @1DD: ixor
		// @1DE: aload_0
		// @1DF: getfield int game.C_100254_pi.field_106462_v
		// @1E2: iconst_m1
		// @1E3: ixor
		// @1E4: if_icmple @204
		// @1E7: aload_0
		// @1E8: getfield int[] game.C_100254_pi.field_106467_q
		// @1EB: iload #10
		// @1ED: iconst_m1
		// @1EE: iastore
		// @1EF: iinc #10 +1
		// @1F2: iload #16
		// @1F4: ifne @207
		// @1F7: goto @1FB
		// @1FA: athrow
		// @1FB: iload #16
		// @1FD: ifeq @1DA
		// @200: goto @204
		// @203: athrow
		// @204: iconst_0
		// @205: istore #10
		// @207: iload #10
		// @209: aload_0
		// @20A: getfield int game.C_100254_pi.field_106456_m
		// @20D: if_icmpge @238
		// @210: aload_0
		// @211: getfield int[] game.C_100254_pi.field_106467_q
		// @214: aload_0
		// @215: getfield int[] game.C_100254_pi.field_106455_l
		// @218: iload #10
		// @21A: iaload
		// @21B: aload_3
		// @21C: sipush -1543 (0xF9F9)
		// @21F: invokevirtual game.C_100280_nf.func_101171_e(int)int
		// @222: iastore
		// @223: iinc #10 +1
		// @226: iload #16
		// @228: ifne @247
		// @22B: goto @22F
		// @22E: athrow
		// @22F: iload #16
		// @231: ifeq @207
		// @234: goto @238
		// @237: athrow
		// @238: aload_0
		// @239: new game.C_100263_mb
		// @23C: dup
		// @23D: aload_0
		// @23E: getfield int[] game.C_100254_pi.field_106467_q
		// @241: invokespecial game.C_100263_mb.<init>(int[])void
		// @244: putfield game.C_100263_mb game.C_100254_pi.field_106446_f
		// @247: iconst_0
		// @248: istore #10
		// @24A: aload_0
		// @24B: getfield int game.C_100254_pi.field_106456_m
		// @24E: iconst_m1
		// @24F: ixor
		// @250: iload #10
		// @252: iconst_m1
		// @253: ixor
		// @254: if_icmpge @27B
		// @257: aload_0
		// @258: getfield int[] game.C_100254_pi.field_106448_d
		// @25B: aload_0
		// @25C: getfield int[] game.C_100254_pi.field_106455_l
		// @25F: iload #10
		// @261: iaload
		// @262: aload_3
		// @263: sipush -1543 (0xF9F9)
		// @266: invokevirtual game.C_100280_nf.func_101171_e(int)int
		// @269: iastore
		// @26A: iinc #10 +1
		// @26D: iload #16
		// @26F: ifne @2C3
		// @272: iload #16
		// @274: ifeq @24A
		// @277: goto @27B
		// @27A: athrow
		// @27B: iload #7
		// @27D: ifeq @2C3
		// @280: iconst_0
		// @281: istore #10
		// @283: iload #10
		// @285: iconst_m1
		// @286: ixor
		// @287: aload_0
		// @288: getfield int game.C_100254_pi.field_106456_m
		// @28B: iconst_m1
		// @28C: ixor
		// @28D: if_icmple @2C3
		// @290: bipush 64 (0x40)
		// @292: newarray byte[]
		// @294: astore #11
		// @296: aload_3
		// @297: aload #11
		// @299: bipush 64 (0x40)
		// @29B: iconst_0
		// @29C: iload_1
		// @29D: sipush 7552 (0x1D80)
		// @2A0: ixor
		// @2A1: invokevirtual game.C_100280_nf.func_101149_a(byte[], int, int, int)void
		// @2A4: aload_0
		// @2A5: getfield byte[][] game.C_100254_pi.field_106451_c
		// @2A8: aload_0
		// @2A9: getfield int[] game.C_100254_pi.field_106455_l
		// @2AC: iload #10
		// @2AE: iaload
		// @2AF: aload #11
		// @2B1: aastore
		// @2B2: iinc #10 +1
		// @2B5: iload #16
		// @2B7: ifne @2C6
		// @2BA: iload #16
		// @2BC: ifeq @283
		// @2BF: goto @2C3
		// @2C2: athrow
		// @2C3: iconst_0
		// @2C4: istore #10
		// @2C6: aload_0
		// @2C7: getfield int game.C_100254_pi.field_106456_m
		// @2CA: iload #10
		// @2CC: if_icmple @2F7
		// @2CF: aload_0
		// @2D0: getfield int[] game.C_100254_pi.field_106452_a
		// @2D3: aload_0
		// @2D4: getfield int[] game.C_100254_pi.field_106455_l
		// @2D7: iload #10
		// @2D9: iaload
		// @2DA: aload_3
		// @2DB: sipush -1543 (0xF9F9)
		// @2DE: invokevirtual game.C_100280_nf.func_101171_e(int)int
		// @2E1: iastore
		// @2E2: iinc #10 +1
		// @2E5: iload #16
		// @2E7: ifne @3D4
		// @2EA: goto @2EE
		// @2ED: athrow
		// @2EE: iload #16
		// @2F0: ifeq @2C6
		// @2F3: goto @2F7
		// @2F6: athrow
		// @2F7: iload #4
		// @2F9: iconst_m1
		// @2FA: ixor
		// @2FB: bipush -8 (0xF8)
		// @2FD: if_icmpgt @3D4
		// @300: iconst_0
		// @301: istore #10
		// @303: iload #10
		// @305: aload_0
		// @306: getfield int game.C_100254_pi.field_106456_m
		// @309: if_icmpge @32E
		// @30C: aload_0
		// @30D: getfield int[] game.C_100254_pi.field_106453_n
		// @310: aload_0
		// @311: getfield int[] game.C_100254_pi.field_106455_l
		// @314: iload #10
		// @316: iaload
		// @317: aload_3
		// @318: iconst_1
		// @319: invokevirtual game.C_100280_nf.func_101160_a(boolean)int
		// @31C: iastore
		// @31D: iinc #10 +1
		// @320: iload #16
		// @322: ifne @331
		// @325: iload #16
		// @327: ifeq @303
		// @32A: goto @32E
		// @32D: athrow
		// @32E: iconst_0
		// @32F: istore #10
		// @331: aload_0
		// @332: getfield int game.C_100254_pi.field_106456_m
		// @335: iconst_m1
		// @336: ixor
		// @337: iload #10
		// @339: iconst_m1
		// @33A: ixor
		// @33B: if_icmpge @3CF
		// @33E: aload_0
		// @33F: getfield int[] game.C_100254_pi.field_106455_l
		// @342: iload #10
		// @344: iaload
		// @345: istore #11
		// @347: aload_0
		// @348: getfield int[] game.C_100254_pi.field_106453_n
		// @34B: iload #11
		// @34D: iaload
		// @34E: istore #12
		// @350: iconst_0
		// @351: istore #8
		// @353: aload_0
		// @354: getfield int[][] game.C_100254_pi.field_106466_r
		// @357: iload #11
		// @359: iload #12
		// @35B: newarray int[]
		// @35D: aastore
		// @35E: iconst_m1
		// @35F: istore #13
		// @361: iconst_0
		// @362: iload #16
		// @364: ifne @4AE
		// @367: istore #14
		// @369: iload #14
		// @36B: iload #12
		// @36D: if_icmpge @3A4
		// @370: aload_0
		// @371: getfield int[][] game.C_100254_pi.field_106466_r
		// @374: iload #11
		// @376: aaload
		// @377: iload #14
		// @379: iload #8
		// @37B: aload_3
		// @37C: iconst_1
		// @37D: invokevirtual game.C_100280_nf.func_101160_a(boolean)int
		// @380: iadd
		// @381: dup
		// @382: istore #8
		// @384: dup_x2
		// @385: iastore
		// @386: istore #15
		// @388: iload #13
		// @38A: iload #15
		// @38C: iload #16
		// @38E: ifne @3B9
		// @391: if_icmpge @39C
		// @394: goto @398
		// @397: athrow
		// @398: iload #15
		// @39A: istore #13
		// @39C: iinc #14 +1
		// @39F: iload #16
		// @3A1: ifeq @369
		// @3A4: aload_0
		// @3A5: getfield int[] game.C_100254_pi.field_106454_o
		// @3A8: iload #11
		// @3AA: iload #13
		// @3AC: iconst_m1
		// @3AD: isub
		// @3AE: iastore
		// @3AF: iload #12
		// @3B1: iconst_m1
		// @3B2: ixor
		// @3B3: iconst_1
		// @3B4: iload #13
		// @3B6: iadd
		// @3B7: iconst_m1
		// @3B8: ixor
		// @3B9: if_icmpeq @3BF
		// @3BC: goto @3C7
		// @3BF: aload_0
		// @3C0: getfield int[][] game.C_100254_pi.field_106466_r
		// @3C3: iload #11
		// @3C5: aconst_null
		// @3C6: aastore
		// @3C7: iinc #10 +1
		// @3CA: iload #16
		// @3CC: ifeq @331
		// @3CF: iload #16
		// @3D1: ifeq @4AC
		// @3D4: iconst_0
		// @3D5: istore #10
		// @3D7: aload_0
		// @3D8: getfield int game.C_100254_pi.field_106456_m
		// @3DB: iconst_m1
		// @3DC: ixor
		// @3DD: iload #10
		// @3DF: iconst_m1
		// @3E0: ixor
		// @3E1: if_icmpge @409
		// @3E4: aload_0
		// @3E5: getfield int[] game.C_100254_pi.field_106453_n
		// @3E8: aload_0
		// @3E9: getfield int[] game.C_100254_pi.field_106455_l
		// @3EC: iload #10
		// @3EE: iaload
		// @3EF: aload_3
		// @3F0: iload_1
		// @3F1: bipush 69 (0x45)
		// @3F3: iadd
		// @3F4: invokevirtual game.C_100280_nf.func_101143_l(int)int
		// @3F7: iastore
		// @3F8: iinc #10 +1
		// @3FB: iload #16
		// @3FD: ifne @40C
		// @400: iload #16
		// @402: ifeq @3D7
		// @405: goto @409
		// @408: athrow
		// @409: iconst_0
		// @40A: istore #10
		// @40C: iload #10
		// @40E: aload_0
		// @40F: getfield int game.C_100254_pi.field_106456_m
		// @412: if_icmpge @4AC
		// @415: aload_0
		// @416: getfield int[] game.C_100254_pi.field_106455_l
		// @419: iload #10
		// @41B: iaload
		// @41C: istore #11
		// @41E: aload_0
		// @41F: getfield int[] game.C_100254_pi.field_106453_n
		// @422: iload #11
		// @424: iaload
		// @425: istore #12
		// @427: iconst_0
		// @428: istore #8
		// @42A: aload_0
		// @42B: getfield int[][] game.C_100254_pi.field_106466_r
		// @42E: iload #11
		// @430: iload #12
		// @432: newarray int[]
		// @434: aastore
		// @435: iconst_m1
		// @436: istore #13
		// @438: iconst_0
		// @439: iload #16
		// @43B: ifne @4AE
		// @43E: istore #14
		// @440: iload #14
		// @442: iconst_m1
		// @443: ixor
		// @444: iload #12
		// @446: iconst_m1
		// @447: ixor
		// @448: if_icmple @484
		// @44B: aload_0
		// @44C: getfield int[][] game.C_100254_pi.field_106466_r
		// @44F: iload #11
		// @451: aaload
		// @452: iload #14
		// @454: iload #8
		// @456: aload_3
		// @457: bipush -2 (0xFE)
		// @459: invokevirtual game.C_100280_nf.func_101143_l(int)int
		// @45C: iadd
		// @45D: dup
		// @45E: istore #8
		// @460: dup_x2
		// @461: iastore
		// @462: istore #15
		// @464: iload #15
		// @466: iconst_m1
		// @467: ixor
		// @468: iload #13
		// @46A: iconst_m1
		// @46B: ixor
		// @46C: iload #16
		// @46E: ifne @495
		// @471: if_icmpge @47C
		// @474: goto @478
		// @477: athrow
		// @478: iload #15
		// @47A: istore #13
		// @47C: iinc #14 +1
		// @47F: iload #16
		// @481: ifeq @440
		// @484: aload_0
		// @485: getfield int[] game.C_100254_pi.field_106454_o
		// @488: iload #11
		// @48A: iload #13
		// @48C: iconst_1
		// @48D: iadd
		// @48E: iastore
		// @48F: iconst_1
		// @490: iload #13
		// @492: iadd
		// @493: iload #12
		// @495: if_icmpne @4A4
		// @498: aload_0
		// @499: getfield int[][] game.C_100254_pi.field_106466_r
		// @49C: iload #11
		// @49E: aconst_null
		// @49F: aastore
		// @4A0: goto @4A4
		// @4A3: athrow
		// @4A4: iinc #10 +1
		// @4A7: iload #16
		// @4A9: ifeq @40C
		// @4AC: iload #6
		// @4AE: ifeq @596
		// @4B1: aload_0
		// @4B2: iconst_1
		// @4B3: iload #9
		// @4B5: iadd
		// @4B6: anewarray game.C_100263_mb
		// @4B9: putfield game.C_100263_mb[] game.C_100254_pi.field_106465_s
		// @4BC: aload_0
		// @4BD: iconst_1
		// @4BE: iload #9
		// @4C0: iadd
		// @4C1: anewarray int[]
		// @4C4: putfield int[][] game.C_100254_pi.field_106449_e
		// @4C7: iconst_0
		// @4C8: istore #10
		// @4CA: iload #10
		// @4CC: aload_0
		// @4CD: getfield int game.C_100254_pi.field_106456_m
		// @4D0: if_icmpge @596
		// @4D3: aload_0
		// @4D4: getfield int[] game.C_100254_pi.field_106455_l
		// @4D7: iload #10
		// @4D9: iaload
		// @4DA: istore #11
		// @4DC: aload_0
		// @4DD: getfield int[] game.C_100254_pi.field_106453_n
		// @4E0: iload #11
		// @4E2: iaload
		// @4E3: istore #12
		// @4E5: aload_0
		// @4E6: getfield int[][] game.C_100254_pi.field_106449_e
		// @4E9: iload #11
		// @4EB: aload_0
		// @4EC: getfield int[] game.C_100254_pi.field_106454_o
		// @4EF: iload #11
		// @4F1: iaload
		// @4F2: newarray int[]
		// @4F4: aastore
		// @4F5: iload #16
		// @4F7: ifne @5D4
		// @4FA: iconst_0
		// @4FB: istore #13
		// @4FD: iload #13
		// @4FF: aload_0
		// @500: getfield int[] game.C_100254_pi.field_106454_o
		// @503: iload #11
		// @505: iaload
		// @506: if_icmpge @525
		// @509: aload_0
		// @50A: getfield int[][] game.C_100254_pi.field_106449_e
		// @50D: iload #11
		// @50F: aaload
		// @510: iload #13
		// @512: iconst_m1
		// @513: iastore
		// @514: iinc #13 +1
		// @517: iload #16
		// @519: ifne @528
		// @51C: iload #16
		// @51E: ifeq @4FD
		// @521: goto @525
		// @524: athrow
		// @525: iconst_0
		// @526: istore #13
		// @528: iload #13
		// @52A: iload #12
		// @52C: if_icmpge @579
		// @52F: iload #16
		// @531: ifne @591
		// @534: goto @538
		// @537: athrow
		// @538: aconst_null
		// @539: aload_0
		// @53A: getfield int[][] game.C_100254_pi.field_106466_r
		// @53D: iload #11
		// @53F: aaload
		// @540: if_acmpeq @558
		// @543: goto @547
		// @546: athrow
		// @547: aload_0
		// @548: getfield int[][] game.C_100254_pi.field_106466_r
		// @54B: iload #11
		// @54D: aaload
		// @54E: iload #13
		// @550: iaload
		// @551: istore #14
		// @553: iload #16
		// @555: ifeq @55C
		// @558: iload #13
		// @55A: istore #14
		// @55C: aload_0
		// @55D: getfield int[][] game.C_100254_pi.field_106449_e
		// @560: iload #11
		// @562: aaload
		// @563: iload #14
		// @565: aload_3
		// @566: iload_1
		// @567: sipush 1600 (0x0640)
		// @56A: invokestatic game.C_100089_fa.func_103722_a(int, int)int
		// @56D: invokevirtual game.C_100280_nf.func_101171_e(int)int
		// @570: iastore
		// @571: iinc #13 +1
		// @574: iload #16
		// @576: ifeq @528
		// @579: aload_0
		// @57A: getfield game.C_100263_mb[] game.C_100254_pi.field_106465_s
		// @57D: iload #11
		// @57F: new game.C_100263_mb
		// @582: dup
		// @583: aload_0
		// @584: getfield int[][] game.C_100254_pi.field_106449_e
		// @587: iload #11
		// @589: aaload
		// @58A: invokespecial game.C_100263_mb.<init>(int[])void
		// @58D: aastore
		// @58E: iinc #10 +1
		// @591: iload #16
		// @593: ifeq @4CA
		// @596: goto @5D4
		// @599: astore_3
		// @59A: aload_3
		// @59B: new java.lang.StringBuilder
		// @59E: dup
		// @59F: invokespecial java.lang.StringBuilder.<init>()void
		// @5A2: getstatic java.lang.String[] game.C_100254_pi.field_106469_z
		// @5A5: iconst_3
		// @5A6: aaload
		// @5A7: invokevirtual java.lang.StringBuilder.append(java.lang.String)java.lang.StringBuilder
		// @5AA: iload_1
		// @5AB: invokevirtual java.lang.StringBuilder.append(int)java.lang.StringBuilder
		// @5AE: bipush 44 (0x2C)
		// @5B0: invokevirtual java.lang.StringBuilder.append(char)java.lang.StringBuilder
		// @5B3: aload_2
		// @5B4: ifnull @5C0
		// @5B7: getstatic java.lang.String[] game.C_100254_pi.field_106469_z
		// @5BA: iconst_1
		// @5BB: aaload
		// @5BC: goto @5C5
		// @5BF: athrow
		// @5C0: getstatic java.lang.String[] game.C_100254_pi.field_106469_z
		// @5C3: iconst_2
		// @5C4: aaload
		// @5C5: invokevirtual java.lang.StringBuilder.append(java.lang.String)java.lang.StringBuilder
		// @5C8: bipush 41 (0x29)
		// @5CA: invokevirtual java.lang.StringBuilder.append(char)java.lang.StringBuilder
		// @5CD: invokevirtual java.lang.StringBuilder.toString()java.lang.String
		// @5D0: invokestatic game.C_100181_cf.func_105695_a(java.lang.Throwable, java.lang.String)game.C_100170_cm
		// @5D3: athrow
		// @5D4: return
	}
	
	static final boolean func_106444_a(int arg0)
	{
		// @00: iload_0
		// @01: iconst_1
		// @02: if_icmpeq @07
		// @05: iconst_0
		// @06: ireturn
		// @07: bipush 55 (0x37)
		// @09: getstatic int[] game.C_100257_ln.field_106481_d
		// @0C: bipush -97 (0x9F)
		// @0E: invokestatic game.C_100097_k.func_104572_a(int, int[], int)boolean
		// @11: ireturn
		// @12: astore_1
		// @13: aload_1
		// @14: new java.lang.StringBuilder
		// @17: dup
		// @18: invokespecial java.lang.StringBuilder.<init>()void
		// @1B: getstatic java.lang.String[] game.C_100254_pi.field_106469_z
		// @1E: iconst_4
		// @1F: aaload
		// @20: invokevirtual java.lang.StringBuilder.append(java.lang.String)java.lang.StringBuilder
		// @23: iload_0
		// @24: invokevirtual java.lang.StringBuilder.append(int)java.lang.StringBuilder
		// @27: bipush 41 (0x29)
		// @29: invokevirtual java.lang.StringBuilder.append(char)java.lang.StringBuilder
		// @2C: invokevirtual java.lang.StringBuilder.toString()java.lang.String
		// @2F: invokestatic game.C_100181_cf.func_105695_a(java.lang.Throwable, java.lang.String)game.C_100170_cm
		// @32: athrow
	}
	
	static final void func_106443_a(boolean arg0)
	{
		// @00: getstatic boolean game.C_100186_rl.field_105720_f
		// @03: ifeq @0A
		// @06: goto @12
		// @09: athrow
		// @0A: new java.lang.IllegalStateException
		// @0D: dup
		// @0E: invokespecial java.lang.IllegalStateException.<init>()void
		// @11: athrow
		// @12: getstatic game.C_100282_nh game.C_100027_hc.field_102598_S
		// @15: ifnonnull @1C
		// @18: goto @24
		// @1B: athrow
		// @1C: getstatic game.C_100282_nh game.C_100027_hc.field_102598_S
		// @1F: bipush 119 (0x77)
		// @21: invokevirtual game.C_100282_nh.func_102701_r(int)void
		// @24: bipush -95 (0xA1)
		// @26: invokestatic game.C_100180_ce.func_104801_c(byte)java.lang.String
		// @29: astore_1
		// @2A: new game.C_100151_bc
		// @2D: dup
		// @2E: aload_1
		// @2F: aconst_null
		// @30: iconst_1
		// @31: iconst_0
		// @32: iload_0
		// @33: invokespecial game.C_100151_bc.<init>(java.lang.String, java.lang.String, boolean, boolean, boolean)void
		// @36: putstatic game.C_100151_bc game.C_100099_fb.field_103039_E
		// @39: getstatic game.C_100029_gn game.C_100085_a.field_102576_K
		// @3C: getstatic game.C_100209_qb game.C_100318_hj.field_107201_j
		// @3F: sipush 2839 (0x0B17)
		// @42: invokevirtual game.C_100029_gn.func_103359_a(game.C_100336_im, int)void
		// @45: getstatic game.C_100209_qb game.C_100318_hj.field_107201_j
		// @48: getstatic game.C_100151_bc game.C_100099_fb.field_103039_E
		// @4B: bipush 75 (0x4B)
		// @4D: invokevirtual game.C_100209_qb.func_102660_a(game.C_100336_im, byte)void
		// @50: getstatic game.C_100209_qb game.C_100318_hj.field_107201_j
		// @53: bipush 78 (0x4E)
		// @55: invokevirtual game.C_100209_qb.func_102635_m(int)void
		// @58: goto @7D
		// @5B: astore_1
		// @5C: aload_1
		// @5D: new java.lang.StringBuilder
		// @60: dup
		// @61: invokespecial java.lang.StringBuilder.<init>()void
		// @64: getstatic java.lang.String[] game.C_100254_pi.field_106469_z
		// @67: bipush 6 (0x06)
		// @69: aaload
		// @6A: invokevirtual java.lang.StringBuilder.append(java.lang.String)java.lang.StringBuilder
		// @6D: iload_0
		// @6E: invokevirtual java.lang.StringBuilder.append(boolean)java.lang.StringBuilder
		// @71: bipush 41 (0x29)
		// @73: invokevirtual java.lang.StringBuilder.append(char)java.lang.StringBuilder
		// @76: invokevirtual java.lang.StringBuilder.toString()java.lang.String
		// @79: invokestatic game.C_100181_cf.func_105695_a(java.lang.Throwable, java.lang.String)game.C_100170_cm
		// @7C: athrow
		// @7D: return
	}
	
	public static void func_106441_a(byte arg0)
	{
		// @00: aconst_null
		// @01: putstatic int[] game.C_100254_pi.field_106458_k
		// @04: iload_0
		// @05: bipush 115 (0x73)
		// @07: if_icmpgt @0B
		// @0A: return
		// @0B: aconst_null
		// @0C: putstatic game.C_100037_wb game.C_100254_pi.field_106457_j
		// @0F: aconst_null
		// @10: putstatic game.C_100327_ib game.C_100254_pi.field_106459_h
		// @13: aconst_null
		// @14: putstatic game.C_100228_nn game.C_100254_pi.field_106470_x
		// @17: aconst_null
		// @18: putstatic java.applet.Applet game.C_100254_pi.field_106447_g
		// @1B: aconst_null
		// @1C: putstatic game.C_100037_wb[] game.C_100254_pi.field_106468_p
		// @1F: aconst_null
		// @20: putstatic java.lang.String game.C_100254_pi.field_106463_u
		// @23: aconst_null
		// @24: putstatic java.util.Calendar game.C_100254_pi.field_106460_i
		// @27: goto @4B
		// @2A: astore_1
		// @2B: aload_1
		// @2C: new java.lang.StringBuilder
		// @2F: dup
		// @30: invokespecial java.lang.StringBuilder.<init>()void
		// @33: getstatic java.lang.String[] game.C_100254_pi.field_106469_z
		// @36: iconst_5
		// @37: aaload
		// @38: invokevirtual java.lang.StringBuilder.append(java.lang.String)java.lang.StringBuilder
		// @3B: iload_0
		// @3C: invokevirtual java.lang.StringBuilder.append(int)java.lang.StringBuilder
		// @3F: bipush 41 (0x29)
		// @41: invokevirtual java.lang.StringBuilder.append(char)java.lang.StringBuilder
		// @44: invokevirtual java.lang.StringBuilder.toString()java.lang.String
		// @47: invokestatic game.C_100181_cf.func_105695_a(java.lang.Throwable, java.lang.String)game.C_100170_cm
		// @4A: athrow
		// @4B: return
	}
	
	C_100254_pi(byte[] arg0, int arg1, byte[] arg2)
	{
		// @00: getstatic int game.SteelSentinels.field_105275_O
		// @03: istore #5
		// @05: aload_0
		// @06: invokespecial java.lang.Object.<init>()void
		// @09: aload_0
		// @0A: aload_1
		// @0B: iconst_0
		// @0C: aload_1
		// @0D: arraylength
		// @0E: invokestatic game.C_100289_jl.func_102885_a(byte[], int, int)int
		// @11: putfield int game.C_100254_pi.field_106450_b
		// @14: iload_2
		// @15: iconst_m1
		// @16: ixor
		// @17: aload_0
		// @18: getfield int game.C_100254_pi.field_106450_b
		// @1B: iconst_m1
		// @1C: ixor
		// @1D: if_icmpne @23
		// @20: goto @2B
		// @23: new java.lang.RuntimeException
		// @26: dup
		// @27: invokespecial java.lang.RuntimeException.<init>()void
		// @2A: athrow
		// @2B: aload_3
		// @2C: ifnull @89
		// @2F: bipush 64 (0x40)
		// @31: aload_3
		// @32: arraylength
		// @33: if_icmpeq @43
		// @36: goto @3A
		// @39: athrow
		// @3A: new java.lang.RuntimeException
		// @3D: dup
		// @3E: invokespecial java.lang.RuntimeException.<init>()void
		// @41: athrow
		// @42: athrow
		// @43: aload_0
		// @44: aload_1
		// @45: arraylength
		// @46: bipush 36 (0x24)
		// @48: iconst_0
		// @49: aload_1
		// @4A: invokestatic game.C_100087_n.func_100681_a(int, byte, int, byte[])byte[]
		// @4D: putfield byte[] game.C_100254_pi.field_106464_t
		// @50: iconst_0
		// @51: istore #4
		// @53: bipush 64 (0x40)
		// @55: iload #4
		// @57: if_icmple @89
		// @5A: iload #5
		// @5C: ifne @90
		// @5F: aload_3
		// @60: iload #4
		// @62: baload
		// @63: iconst_m1
		// @64: ixor
		// @65: aload_0
		// @66: getfield byte[] game.C_100254_pi.field_106464_t
		// @69: iload #4
		// @6B: baload
		// @6C: iconst_m1
		// @6D: ixor
		// @6E: if_icmpne @79
		// @71: goto @75
		// @74: athrow
		// @75: goto @81
		// @78: athrow
		// @79: new java.lang.RuntimeException
		// @7C: dup
		// @7D: invokespecial java.lang.RuntimeException.<init>()void
		// @80: athrow
		// @81: iinc #4 +1
		// @84: iload #5
		// @86: ifeq @53
		// @89: aload_0
		// @8A: bipush -71 (0xB9)
		// @8C: aload_1
		// @8D: invokespecial game.C_100254_pi.func_106445_a(byte, byte[])void
		// @90: goto @EA
		// @93: astore #4
		// @95: aload #4
		// @97: new java.lang.StringBuilder
		// @9A: dup
		// @9B: invokespecial java.lang.StringBuilder.<init>()void
		// @9E: getstatic java.lang.String[] game.C_100254_pi.field_106469_z
		// @A1: iconst_0
		// @A2: aaload
		// @A3: invokevirtual java.lang.StringBuilder.append(java.lang.String)java.lang.StringBuilder
		// @A6: aload_1
		// @A7: ifnull @B3
		// @AA: getstatic java.lang.String[] game.C_100254_pi.field_106469_z
		// @AD: iconst_1
		// @AE: aaload
		// @AF: goto @B8
		// @B2: athrow
		// @B3: getstatic java.lang.String[] game.C_100254_pi.field_106469_z
		// @B6: iconst_2
		// @B7: aaload
		// @B8: invokevirtual java.lang.StringBuilder.append(java.lang.String)java.lang.StringBuilder
		// @BB: bipush 44 (0x2C)
		// @BD: invokevirtual java.lang.StringBuilder.append(char)java.lang.StringBuilder
		// @C0: iload_2
		// @C1: invokevirtual java.lang.StringBuilder.append(int)java.lang.StringBuilder
		// @C4: bipush 44 (0x2C)
		// @C6: invokevirtual java.lang.StringBuilder.append(char)java.lang.StringBuilder
		// @C9: aload_3
		// @CA: ifnull @D6
		// @CD: getstatic java.lang.String[] game.C_100254_pi.field_106469_z
		// @D0: iconst_1
		// @D1: aaload
		// @D2: goto @DB
		// @D5: athrow
		// @D6: getstatic java.lang.String[] game.C_100254_pi.field_106469_z
		// @D9: iconst_2
		// @DA: aaload
		// @DB: invokevirtual java.lang.StringBuilder.append(java.lang.String)java.lang.StringBuilder
		// @DE: bipush 41 (0x29)
		// @E0: invokevirtual java.lang.StringBuilder.append(char)java.lang.StringBuilder
		// @E3: invokevirtual java.lang.StringBuilder.toString()java.lang.String
		// @E6: invokestatic game.C_100181_cf.func_105695_a(java.lang.Throwable, java.lang.String)game.C_100170_cm
		// @E9: athrow
		// @EA: return
	}
	
	static
	{
		// @00: bipush 7 (0x07)
		// @02: anewarray java.lang.String
		// @05: dup
		// @06: iconst_0
		// @07: ldc "r3#(:l3y*{"
		// @09: invokestatic game.C_100254_pi.func_106442_z(java.lang.String)char[]
		// @0C: invokestatic game.C_100254_pi.func_106440_z(char[])java.lang.String
		// @0F: aastore
		// @10: dup
		// @11: iconst_1
		// @12: ldc "yt#:."
		// @14: invokestatic game.C_100254_pi.func_106442_z(java.lang.String)char[]
		// @17: invokestatic game.C_100254_pi.func_106440_z(char[])java.lang.String
		// @1A: aastore
		// @1B: dup
		// @1C: iconst_2
		// @1D: ldc "l/ax"
		// @1F: invokestatic game.C_100254_pi.func_106442_z(java.lang.String)char[]
		// @22: invokestatic game.C_100254_pi.func_106440_z(char[])java.lang.String
		// @25: aastore
		// @26: dup
		// @27: iconst_3
		// @28: ldc "r3#U{"
		// @2A: invokestatic game.C_100254_pi.func_106442_z(java.lang.String)char[]
		// @2D: invokestatic game.C_100254_pi.func_106440_z(char[])java.lang.String
		// @30: aastore
		// @31: dup
		// @32: iconst_4
		// @33: ldc "r3#P{"
		// @35: invokestatic game.C_100254_pi.func_106442_z(java.lang.String)char[]
		// @38: invokestatic game.C_100254_pi.func_106440_z(char[])java.lang.String
		// @3B: aastore
		// @3C: dup
		// @3D: iconst_5
		// @3E: ldc "r3#V{"
		// @40: invokestatic game.C_100254_pi.func_106442_z(java.lang.String)char[]
		// @43: invokestatic game.C_100254_pi.func_106440_z(char[])java.lang.String
		// @46: aastore
		// @47: dup
		// @48: bipush 6 (0x06)
		// @4A: ldc "r3#W{"
		// @4C: invokestatic game.C_100254_pi.func_106442_z(java.lang.String)char[]
		// @4F: invokestatic game.C_100254_pi.func_106440_z(char[])java.lang.String
		// @52: aastore
		// @53: putstatic java.lang.String[] game.C_100254_pi.field_106469_z
		// @56: ldc "[5x4>w)y46l=dz6g(-`;gz1w<ng=$5d<k*o'j3(|a5a*s`?k{!gzt{&\"9lzsg4j}=g?\u007f4'j?-(v3d#"
		// @58: invokestatic game.C_100254_pi.func_106442_z(java.lang.String)char[]
		// @5B: invokestatic game.C_100254_pi.func_106440_z(char[])java.lang.String
		// @5E: putstatic java.lang.String game.C_100254_pi.field_106463_u
		// @61: new game.C_100037_wb
		// @64: dup
		// @65: bipush 28 (0x1C)
		// @67: bipush 28 (0x1C)
		// @69: invokespecial game.C_100037_wb.<init>(int, int)void
		// @6C: putstatic game.C_100037_wb game.C_100254_pi.field_106457_j
		// @6F: bipush 12 (0x0C)
		// @71: newarray int[]
		// @73: dup
		// @74: iconst_0
		// @75: bipush 40 (0x28)
		// @77: iastore
		// @78: dup
		// @79: iconst_1
		// @7A: sipush 150 (0x0096)
		// @7D: iastore
		// @7E: dup
		// @7F: iconst_2
		// @80: sipush 135 (0x0087)
		// @83: iastore
		// @84: dup
		// @85: iconst_3
		// @86: bipush 40 (0x28)
		// @88: iastore
		// @89: dup
		// @8A: iconst_4
		// @8B: bipush 85 (0x55)
		// @8D: iastore
		// @8E: dup
		// @8F: iconst_5
		// @90: bipush 75 (0x4B)
		// @92: iastore
		// @93: dup
		// @94: bipush 6 (0x06)
		// @96: bipush 70 (0x46)
		// @98: iastore
		// @99: dup
		// @9A: bipush 7 (0x07)
		// @9C: bipush 30 (0x1E)
		// @9E: iastore
		// @9F: dup
		// @A0: bipush 8 (0x08)
		// @A2: iconst_0
		// @A3: iastore
		// @A4: dup
		// @A5: bipush 9 (0x09)
		// @A7: bipush 70 (0x46)
		// @A9: iastore
		// @AA: dup
		// @AB: bipush 10 (0x0A)
		// @AD: bipush 100 (0x64)
		// @AF: iastore
		// @B0: dup
		// @B1: bipush 11 (0x0B)
		// @B3: bipush 90 (0x5A)
		// @B5: iastore
		// @B6: putstatic int[] game.C_100254_pi.field_106458_k
		// @B9: ldc "E\u0017Y"
		// @BB: invokestatic game.C_100254_pi.func_106442_z(java.lang.String)char[]
		// @BE: invokestatic game.C_100254_pi.func_106440_z(char[])java.lang.String
		// @C1: invokestatic java.util.TimeZone.getTimeZone(java.lang.String)java.util.TimeZone
		// @C4: invokestatic java.util.Calendar.getInstance(java.util.TimeZone)java.util.Calendar
		// @C7: putstatic java.util.Calendar game.C_100254_pi.field_106460_i
		// @CA: return
	}
	
	private static char[] func_106442_z(String arg0)
	{
		// @00: aload_0
		// @01: invokevirtual java.lang.String.toCharArray()char[]
		// @04: dup
		// @05: arraylength
		// @06: iconst_2
		// @07: if_icmpge @13
		// @0A: dup
		// @0B: iconst_0
		// @0C: dup2
		// @0D: caload
		// @0E: bipush 83 (0x53)
		// @10: ixor
		// @11: i2c
		// @12: castore
		// @13: areturn
	}
	
	private static String func_106440_z(char[] arg0)
	{
		// @00: aload_0
		// @01: dup
		// @02: arraylength
		// @03: swap
		// @04: iconst_0
		// @05: istore_1
		// @06: goto @4B
		// @09: dup
		// @0A: iload_1
		// @0B: dup2
		// @0C: caload
		// @0D: iload_1
		// @0E: iconst_5
		// @0F: irem
		// @10: tableswitch def: @43, for 0: @30, for 1: @34, for 2: @39, for 3: @3E
		// @30: iconst_2
		// @31: goto @45
		// @34: bipush 90 (0x5A)
		// @36: goto @45
		// @39: bipush 13 (0x0D)
		// @3B: goto @45
		// @3E: bipush 20 (0x14)
		// @40: goto @45
		// @43: bipush 83 (0x53)
		// @45: ixor
		// @46: i2c
		// @47: castore
		// @48: iinc #1 +1
		// @4B: swap
		// @4C: dup_x1
		// @4D: iload_1
		// @4E: if_icmpgt @09
		// @51: new java.lang.String
		// @54: dup_x1
		// @55: swap
		// @56: invokespecial java.lang.String.<init>(char[])void
		// @59: invokevirtual java.lang.String.intern()java.lang.String
		// @5C: areturn
	}
}
