package game;

final class C_100053_vn extends C_100085_a implements C_100237_ok, C_100334_ik, C_100276_nb
{
	static int field_102830_fb;
	private C_100078_ul field_102829_eb;
	private C_100078_ul field_102841_ab;
	private C_100078_ul field_102828_hb;
	static C_100217_ao field_102837_Q;
	static C_100112_r field_102827_cb;
	static String field_102840_R;
	private C_100078_ul field_102838_P;
	private C_100036_gg field_102826_db;
	private C_100218_am field_102843_bb;
	C_100162_sc field_102839_S;
	private C_100078_ul field_102844_X;
	static C_100105_eg field_102832_U;
	private C_100083_c field_102835_W;
	private C_100218_am field_102831_gb;
	private C_100078_ul field_102836_V;
	static C_100037_wb[] field_102833_T;
	static C_100037_wb[] field_102845_Z;
	static C_100302_ka field_102842_Y;
	private static final String[] field_102834_ib;
	
	private final boolean func_102816_a(C_100267_mf arg0, byte arg1)
	{
		// @00: aload_1
		// @01: iconst_1
		// @02: invokeinterface game.C_100267_mf.func_103100_a(boolean)game.C_100308_lh
		// @07: astore_3
		// @08: aload_3
		// @09: ifnull @10
		// @0C: goto @12
		// @0F: athrow
		// @10: iconst_1
		// @11: ireturn
		// @12: aload_3
		// @13: bipush 77 (0x4D)
		// @15: invokeinterface game.C_100308_lh.func_102950_a(byte)game.C_100133_tk
		// @1A: astore #4
		// @1C: getstatic game.C_100133_tk game.C_100256_pk.field_100466_a
		// @1F: aload #4
		// @21: if_acmpeq @28
		// @24: goto @2A
		// @27: athrow
		// @28: iconst_0
		// @29: ireturn
		// @2A: getstatic game.C_100133_tk game.C_100297_kf.field_101234_s
		// @2D: aload #4
		// @2F: if_acmpne @34
		// @32: iconst_0
		// @33: ireturn
		// @34: aload #4
		// @36: getstatic game.C_100133_tk game.C_100034_gi.field_104034_l
		// @39: if_acmpeq @40
		// @3C: goto @42
		// @3F: athrow
		// @40: iconst_0
		// @41: ireturn
		// @42: bipush -26 (0xE6)
		// @44: iload_2
		// @45: iconst_4
		// @46: isub
		// @47: bipush 60 (0x3C)
		// @49: idiv
		// @4A: irem
		// @4B: istore #5
		// @4D: iconst_1
		// @4E: ireturn
		// @4F: astore_3
		// @50: aload_3
		// @51: new java.lang.StringBuilder
		// @54: dup
		// @55: invokespecial java.lang.StringBuilder.<init>()void
		// @58: getstatic java.lang.String[] game.C_100053_vn.field_102834_ib
		// @5B: bipush 8 (0x08)
		// @5D: aaload
		// @5E: invokevirtual java.lang.StringBuilder.append(java.lang.String)java.lang.StringBuilder
		// @61: aload_1
		// @62: ifnull @6E
		// @65: getstatic java.lang.String[] game.C_100053_vn.field_102834_ib
		// @68: iconst_1
		// @69: aaload
		// @6A: goto @73
		// @6D: athrow
		// @6E: getstatic java.lang.String[] game.C_100053_vn.field_102834_ib
		// @71: iconst_2
		// @72: aaload
		// @73: invokevirtual java.lang.StringBuilder.append(java.lang.String)java.lang.StringBuilder
		// @76: bipush 44 (0x2C)
		// @78: invokevirtual java.lang.StringBuilder.append(char)java.lang.StringBuilder
		// @7B: iload_2
		// @7C: invokevirtual java.lang.StringBuilder.append(int)java.lang.StringBuilder
		// @7F: bipush 41 (0x29)
		// @81: invokevirtual java.lang.StringBuilder.append(char)java.lang.StringBuilder
		// @84: invokevirtual java.lang.StringBuilder.toString()java.lang.String
		// @87: invokestatic game.C_100181_cf.func_105695_a(java.lang.Throwable, java.lang.String)game.C_100170_cm
		// @8A: athrow
	}
	
	final boolean func_102506_a(char arg0, int arg1, int arg2, C_100336_im arg3)
	{
		// @00: aload_0
		// @01: iload_1
		// @02: iload_2
		// @03: iload_3
		// @04: aload #4
		// @06: invokespecial game.C_100085_a.func_102506_a(char, int, int, game.C_100336_im)boolean
		// @09: ifeq @0E
		// @0C: iconst_1
		// @0D: ireturn
		// @0E: iload_2
		// @0F: bipush 98 (0x62)
		// @11: if_icmpne @20
		// @14: aload_0
		// @15: aload #4
		// @17: iload_3
		// @18: sipush 22629 (0x5865)
		// @1B: ixor
		// @1C: invokevirtual game.C_100053_vn.func_102555_a(game.C_100336_im, int)boolean
		// @1F: ireturn
		// @20: iload_2
		// @21: bipush 99 (0x63)
		// @23: if_icmpne @31
		// @26: aload_0
		// @27: iload_3
		// @28: ldc -40088 (0xffff6368)
		// @2A: iadd
		// @2B: aload #4
		// @2D: invokevirtual game.C_100053_vn.func_102558_b(int, game.C_100336_im)boolean
		// @30: ireturn
		// @31: iconst_0
		// @32: ireturn
		// @33: astore #5
		// @35: aload #5
		// @37: new java.lang.StringBuilder
		// @3A: dup
		// @3B: invokespecial java.lang.StringBuilder.<init>()void
		// @3E: getstatic java.lang.String[] game.C_100053_vn.field_102834_ib
		// @41: bipush 11 (0x0B)
		// @43: aaload
		// @44: invokevirtual java.lang.StringBuilder.append(java.lang.String)java.lang.StringBuilder
		// @47: iload_1
		// @48: invokevirtual java.lang.StringBuilder.append(char)java.lang.StringBuilder
		// @4B: bipush 44 (0x2C)
		// @4D: invokevirtual java.lang.StringBuilder.append(char)java.lang.StringBuilder
		// @50: iload_2
		// @51: invokevirtual java.lang.StringBuilder.append(int)java.lang.StringBuilder
		// @54: bipush 44 (0x2C)
		// @56: invokevirtual java.lang.StringBuilder.append(char)java.lang.StringBuilder
		// @59: iload_3
		// @5A: invokevirtual java.lang.StringBuilder.append(int)java.lang.StringBuilder
		// @5D: bipush 44 (0x2C)
		// @5F: invokevirtual java.lang.StringBuilder.append(char)java.lang.StringBuilder
		// @62: aload #4
		// @64: ifnull @70
		// @67: getstatic java.lang.String[] game.C_100053_vn.field_102834_ib
		// @6A: iconst_1
		// @6B: aaload
		// @6C: goto @75
		// @6F: athrow
		// @70: getstatic java.lang.String[] game.C_100053_vn.field_102834_ib
		// @73: iconst_2
		// @74: aaload
		// @75: invokevirtual java.lang.StringBuilder.append(java.lang.String)java.lang.StringBuilder
		// @78: bipush 41 (0x29)
		// @7A: invokevirtual java.lang.StringBuilder.append(char)java.lang.StringBuilder
		// @7D: invokevirtual java.lang.StringBuilder.toString()java.lang.String
		// @80: invokestatic game.C_100181_cf.func_105695_a(java.lang.Throwable, java.lang.String)game.C_100170_cm
		// @83: athrow
	}
	
	private final boolean func_102824_k(int arg0)
	{
		// @00: iload_1
		// @01: bipush -65 (0xBF)
		// @03: if_icmplt @11
		// @06: aconst_null
		// @07: checkcast game.C_100217_ao
		// @0A: putstatic game.C_100217_ao game.C_100053_vn.field_102837_Q
		// @0D: goto @11
		// @10: athrow
		// @11: aload_0
		// @12: aload_0
		// @13: getfield game.C_100078_ul game.C_100053_vn.field_102829_eb
		// @16: bipush 102 (0x66)
		// @18: invokespecial game.C_100053_vn.func_102816_a(game.C_100267_mf, byte)boolean
		// @1B: ifeq @73
		// @1E: aload_0
		// @1F: aload_0
		// @20: getfield game.C_100078_ul game.C_100053_vn.field_102838_P
		// @23: bipush -80 (0xB0)
		// @25: invokespecial game.C_100053_vn.func_102816_a(game.C_100267_mf, byte)boolean
		// @28: ifeq @73
		// @2B: goto @2F
		// @2E: athrow
		// @2F: aload_0
		// @30: aload_0
		// @31: getfield game.C_100078_ul game.C_100053_vn.field_102836_V
		// @34: bipush -79 (0xB1)
		// @36: invokespecial game.C_100053_vn.func_102816_a(game.C_100267_mf, byte)boolean
		// @39: ifeq @73
		// @3C: goto @40
		// @3F: athrow
		// @40: aload_0
		// @41: aload_0
		// @42: getfield game.C_100078_ul game.C_100053_vn.field_102841_ab
		// @45: bipush 109 (0x6D)
		// @47: invokespecial game.C_100053_vn.func_102816_a(game.C_100267_mf, byte)boolean
		// @4A: ifeq @73
		// @4D: goto @51
		// @50: athrow
		// @51: aload_0
		// @52: aload_0
		// @53: getfield game.C_100078_ul game.C_100053_vn.field_102844_X
		// @56: bipush -108 (0x94)
		// @58: invokespecial game.C_100053_vn.func_102816_a(game.C_100267_mf, byte)boolean
		// @5B: ifeq @73
		// @5E: goto @62
		// @61: athrow
		// @62: aload_0
		// @63: aload_0
		// @64: getfield game.C_100078_ul game.C_100053_vn.field_102828_hb
		// @67: bipush 80 (0x50)
		// @69: invokespecial game.C_100053_vn.func_102816_a(game.C_100267_mf, byte)boolean
		// @6C: ifne @75
		// @6F: goto @73
		// @72: athrow
		// @73: iconst_0
		// @74: ireturn
		// @75: iconst_1
		// @76: ireturn
		// @77: astore_2
		// @78: aload_2
		// @79: new java.lang.StringBuilder
		// @7C: dup
		// @7D: invokespecial java.lang.StringBuilder.<init>()void
		// @80: getstatic java.lang.String[] game.C_100053_vn.field_102834_ib
		// @83: bipush 9 (0x09)
		// @85: aaload
		// @86: invokevirtual java.lang.StringBuilder.append(java.lang.String)java.lang.StringBuilder
		// @89: iload_1
		// @8A: invokevirtual java.lang.StringBuilder.append(int)java.lang.StringBuilder
		// @8D: bipush 41 (0x29)
		// @8F: invokevirtual java.lang.StringBuilder.append(char)java.lang.StringBuilder
		// @92: invokevirtual java.lang.StringBuilder.toString()java.lang.String
		// @95: invokestatic game.C_100181_cf.func_105695_a(java.lang.Throwable, java.lang.String)game.C_100170_cm
		// @98: athrow
	}
	
	static final boolean func_102812_a(int arg0, char arg1)
	{
		// @00: iload_0
		// @01: bipush -96 (0xA0)
		// @03: if_icmpeq @0F
		// @06: bipush -82 (0xAE)
		// @08: putstatic int game.C_100053_vn.field_102830_fb
		// @0B: goto @0F
		// @0E: athrow
		// @0F: iload_1
		// @10: sipush 160 (0x00A0)
		// @13: if_icmpeq @38
		// @16: iload_1
		// @17: iconst_m1
		// @18: ixor
		// @19: bipush -33 (0xDF)
		// @1B: if_icmpeq @38
		// @1E: goto @22
		// @21: athrow
		// @22: iload_1
		// @23: iconst_m1
		// @24: ixor
		// @25: bipush -96 (0xA0)
		// @27: if_icmpeq @38
		// @2A: goto @2E
		// @2D: athrow
		// @2E: bipush 45 (0x2D)
		// @30: iload_1
		// @31: if_icmpne @3D
		// @34: goto @38
		// @37: athrow
		// @38: iconst_1
		// @39: goto @3E
		// @3C: athrow
		// @3D: iconst_0
		// @3E: ireturn
		// @3F: astore_2
		// @40: aload_2
		// @41: new java.lang.StringBuilder
		// @44: dup
		// @45: invokespecial java.lang.StringBuilder.<init>()void
		// @48: getstatic java.lang.String[] game.C_100053_vn.field_102834_ib
		// @4B: bipush 13 (0x0D)
		// @4D: aaload
		// @4E: invokevirtual java.lang.StringBuilder.append(java.lang.String)java.lang.StringBuilder
		// @51: iload_0
		// @52: invokevirtual java.lang.StringBuilder.append(int)java.lang.StringBuilder
		// @55: bipush 44 (0x2C)
		// @57: invokevirtual java.lang.StringBuilder.append(char)java.lang.StringBuilder
		// @5A: iload_1
		// @5B: invokevirtual java.lang.StringBuilder.append(char)java.lang.StringBuilder
		// @5E: bipush 41 (0x29)
		// @60: invokevirtual java.lang.StringBuilder.append(char)java.lang.StringBuilder
		// @63: invokevirtual java.lang.StringBuilder.toString()java.lang.String
		// @66: invokestatic game.C_100181_cf.func_105695_a(java.lang.Throwable, java.lang.String)game.C_100170_cm
		// @69: athrow
	}
	
	public final void func_102581_a(int arg0, int arg1, byte arg2, C_100218_am arg3, int arg4)
	{
		// @00: aload_0
		// @01: getfield game.C_100218_am game.C_100053_vn.field_102831_gb
		// @04: aload #4
		// @06: if_acmpeq @26
		// @09: aload #4
		// @0B: aload_0
		// @0C: getfield game.C_100218_am game.C_100053_vn.field_102843_bb
		// @0F: if_acmpne @2F
		// @12: goto @16
		// @15: athrow
		// @16: aload_0
		// @17: iconst_0
		// @18: invokespecial game.C_100053_vn.func_102820_a(boolean)boolean
		// @1B: pop
		// @1C: getstatic int game.SteelSentinels.field_105275_O
		// @1F: ifeq @2F
		// @22: goto @26
		// @25: athrow
		// @26: bipush -101 (0x9B)
		// @28: invokestatic game.C_100158_da.func_100588_b(byte)void
		// @2B: goto @2F
		// @2E: athrow
		// @2F: bipush 85 (0x55)
		// @31: iload_3
		// @32: bipush -2 (0xFE)
		// @34: isub
		// @35: bipush 52 (0x34)
		// @37: idiv
		// @38: idiv
		// @39: istore #6
		// @3B: goto @98
		// @3E: astore #6
		// @40: aload #6
		// @42: new java.lang.StringBuilder
		// @45: dup
		// @46: invokespecial java.lang.StringBuilder.<init>()void
		// @49: getstatic java.lang.String[] game.C_100053_vn.field_102834_ib
		// @4C: iconst_0
		// @4D: aaload
		// @4E: invokevirtual java.lang.StringBuilder.append(java.lang.String)java.lang.StringBuilder
		// @51: iload_1
		// @52: invokevirtual java.lang.StringBuilder.append(int)java.lang.StringBuilder
		// @55: bipush 44 (0x2C)
		// @57: invokevirtual java.lang.StringBuilder.append(char)java.lang.StringBuilder
		// @5A: iload_2
		// @5B: invokevirtual java.lang.StringBuilder.append(int)java.lang.StringBuilder
		// @5E: bipush 44 (0x2C)
		// @60: invokevirtual java.lang.StringBuilder.append(char)java.lang.StringBuilder
		// @63: iload_3
		// @64: invokevirtual java.lang.StringBuilder.append(int)java.lang.StringBuilder
		// @67: bipush 44 (0x2C)
		// @69: invokevirtual java.lang.StringBuilder.append(char)java.lang.StringBuilder
		// @6C: aload #4
		// @6E: ifnull @7A
		// @71: getstatic java.lang.String[] game.C_100053_vn.field_102834_ib
		// @74: iconst_1
		// @75: aaload
		// @76: goto @7F
		// @79: athrow
		// @7A: getstatic java.lang.String[] game.C_100053_vn.field_102834_ib
		// @7D: iconst_2
		// @7E: aaload
		// @7F: invokevirtual java.lang.StringBuilder.append(java.lang.String)java.lang.StringBuilder
		// @82: bipush 44 (0x2C)
		// @84: invokevirtual java.lang.StringBuilder.append(char)java.lang.StringBuilder
		// @87: iload #5
		// @89: invokevirtual java.lang.StringBuilder.append(int)java.lang.StringBuilder
		// @8C: bipush 41 (0x29)
		// @8E: invokevirtual java.lang.StringBuilder.append(char)java.lang.StringBuilder
		// @91: invokevirtual java.lang.StringBuilder.toString()java.lang.String
		// @94: invokestatic game.C_100181_cf.func_105695_a(java.lang.Throwable, java.lang.String)game.C_100170_cm
		// @97: athrow
		// @98: return
	}
	
	private final int func_102817_a(String arg0, int arg1, String arg2, int arg3, int arg4, C_100336_im arg5)
	{
		// @00: iload_2
		// @01: sipush -3554 (0xF21E)
		// @04: if_icmpeq @12
		// @07: aload_0
		// @08: bipush -114 (0x8E)
		// @0A: invokespecial game.C_100053_vn.func_102815_g(byte)java.lang.String
		// @0D: pop
		// @0E: goto @12
		// @11: athrow
		// @12: aload_0
		// @13: sipush 19996 (0x4E1C)
		// @16: aload_3
		// @17: aload #6
		// @19: bipush 35 (0x23)
		// @1B: iload #5
		// @1D: aload_1
		// @1E: iload #4
		// @20: invokespecial game.C_100053_vn.func_102819_a(int, java.lang.String, game.C_100336_im, int, int, java.lang.String, int)int
		// @23: ireturn
		// @24: astore #7
		// @26: aload #7
		// @28: new java.lang.StringBuilder
		// @2B: dup
		// @2C: invokespecial java.lang.StringBuilder.<init>()void
		// @2F: getstatic java.lang.String[] game.C_100053_vn.field_102834_ib
		// @32: bipush 24 (0x18)
		// @34: aaload
		// @35: invokevirtual java.lang.StringBuilder.append(java.lang.String)java.lang.StringBuilder
		// @38: aload_1
		// @39: ifnull @45
		// @3C: getstatic java.lang.String[] game.C_100053_vn.field_102834_ib
		// @3F: iconst_1
		// @40: aaload
		// @41: goto @4A
		// @44: athrow
		// @45: getstatic java.lang.String[] game.C_100053_vn.field_102834_ib
		// @48: iconst_2
		// @49: aaload
		// @4A: invokevirtual java.lang.StringBuilder.append(java.lang.String)java.lang.StringBuilder
		// @4D: bipush 44 (0x2C)
		// @4F: invokevirtual java.lang.StringBuilder.append(char)java.lang.StringBuilder
		// @52: iload_2
		// @53: invokevirtual java.lang.StringBuilder.append(int)java.lang.StringBuilder
		// @56: bipush 44 (0x2C)
		// @58: invokevirtual java.lang.StringBuilder.append(char)java.lang.StringBuilder
		// @5B: aload_3
		// @5C: ifnull @68
		// @5F: getstatic java.lang.String[] game.C_100053_vn.field_102834_ib
		// @62: iconst_1
		// @63: aaload
		// @64: goto @6D
		// @67: athrow
		// @68: getstatic java.lang.String[] game.C_100053_vn.field_102834_ib
		// @6B: iconst_2
		// @6C: aaload
		// @6D: invokevirtual java.lang.StringBuilder.append(java.lang.String)java.lang.StringBuilder
		// @70: bipush 44 (0x2C)
		// @72: invokevirtual java.lang.StringBuilder.append(char)java.lang.StringBuilder
		// @75: iload #4
		// @77: invokevirtual java.lang.StringBuilder.append(int)java.lang.StringBuilder
		// @7A: bipush 44 (0x2C)
		// @7C: invokevirtual java.lang.StringBuilder.append(char)java.lang.StringBuilder
		// @7F: iload #5
		// @81: invokevirtual java.lang.StringBuilder.append(int)java.lang.StringBuilder
		// @84: bipush 44 (0x2C)
		// @86: invokevirtual java.lang.StringBuilder.append(char)java.lang.StringBuilder
		// @89: aload #6
		// @8B: ifnull @97
		// @8E: getstatic java.lang.String[] game.C_100053_vn.field_102834_ib
		// @91: iconst_1
		// @92: aaload
		// @93: goto @9C
		// @96: athrow
		// @97: getstatic java.lang.String[] game.C_100053_vn.field_102834_ib
		// @9A: iconst_2
		// @9B: aaload
		// @9C: invokevirtual java.lang.StringBuilder.append(java.lang.String)java.lang.StringBuilder
		// @9F: bipush 41 (0x29)
		// @A1: invokevirtual java.lang.StringBuilder.append(char)java.lang.StringBuilder
		// @A4: invokevirtual java.lang.StringBuilder.toString()java.lang.String
		// @A7: invokestatic game.C_100181_cf.func_105695_a(java.lang.Throwable, java.lang.String)game.C_100170_cm
		// @AA: athrow
	}
	
	private final int func_102819_a(int arg0, String arg1, C_100336_im arg2, int arg3, int arg4, String arg5, int arg6)
	{
		// @000: new game.C_100271_mj
		// @003: dup
		// @004: bipush 20 (0x14)
		// @006: iload #7
		// @008: bipush 120 (0x78)
		// @00A: iload #5
		// @00C: ineg
		// @00D: isub
		// @00E: bipush 25 (0x19)
		// @010: aload_3
		// @011: iconst_0
		// @012: bipush 120 (0x78)
		// @014: iconst_3
		// @015: getstatic game.C_100112_r game.C_100230_of.field_106205_g
		// @018: ldc 16777215 (0xffffff)
		// @01A: aload #6
		// @01C: invokespecial game.C_100271_mj.<init>(int, int, int, int, game.C_100336_im, boolean, int, int, game.C_100112_r, int, java.lang.String)void
		// @01F: astore #8
		// @021: aload_0
		// @022: aload #8
		// @024: iload_1
		// @025: sipush 19997 (0x4E1D)
		// @028: ixor
		// @029: invokevirtual game.C_100053_vn.func_102561_b(game.C_100336_im, int)void
		// @02C: iload_1
		// @02D: sipush 19996 (0x4E1C)
		// @030: if_icmpeq @03D
		// @033: aload_0
		// @034: iconst_1
		// @035: invokespecial game.C_100053_vn.func_102820_a(boolean)boolean
		// @038: pop
		// @039: goto @03D
		// @03C: athrow
		// @03D: new game.C_100056_de
		// @040: dup
		// @041: aload_3
		// @042: checkcast game.C_100267_mf
		// @045: iconst_1
		// @046: invokeinterface game.C_100267_mf.func_103100_a(boolean)game.C_100308_lh
		// @04B: aload_2
		// @04C: bipush 126 (0x7E)
		// @04E: iload #7
		// @050: aload #8
		// @052: getfield int game.C_100271_mj.field_102544_t
		// @055: iadd
		// @056: bipush 50 (0x32)
		// @058: iload #5
		// @05A: iadd
		// @05B: iload #4
		// @05D: invokespecial game.C_100056_de.<init>(game.C_100308_lh, java.lang.String, int, int, int, int)void
		// @060: astore #9
		// @062: aload #9
		// @064: aload_0
		// @065: putfield game.C_100337_in game.C_100056_de.field_102543_u
		// @068: aload_0
		// @069: aload #9
		// @06B: iconst_1
		// @06C: invokevirtual game.C_100053_vn.func_102561_b(game.C_100336_im, int)void
		// @06F: aload #8
		// @071: getfield int game.C_100271_mj.field_102544_t
		// @074: aload #9
		// @076: getfield int game.C_100056_de.field_102544_t
		// @079: iadd
		// @07A: ireturn
		// @07B: astore #8
		// @07D: aload #8
		// @07F: new java.lang.StringBuilder
		// @082: dup
		// @083: invokespecial java.lang.StringBuilder.<init>()void
		// @086: getstatic java.lang.String[] game.C_100053_vn.field_102834_ib
		// @089: bipush 23 (0x17)
		// @08B: aaload
		// @08C: invokevirtual java.lang.StringBuilder.append(java.lang.String)java.lang.StringBuilder
		// @08F: iload_1
		// @090: invokevirtual java.lang.StringBuilder.append(int)java.lang.StringBuilder
		// @093: bipush 44 (0x2C)
		// @095: invokevirtual java.lang.StringBuilder.append(char)java.lang.StringBuilder
		// @098: aload_2
		// @099: ifnull @0A5
		// @09C: getstatic java.lang.String[] game.C_100053_vn.field_102834_ib
		// @09F: iconst_1
		// @0A0: aaload
		// @0A1: goto @0AA
		// @0A4: athrow
		// @0A5: getstatic java.lang.String[] game.C_100053_vn.field_102834_ib
		// @0A8: iconst_2
		// @0A9: aaload
		// @0AA: invokevirtual java.lang.StringBuilder.append(java.lang.String)java.lang.StringBuilder
		// @0AD: bipush 44 (0x2C)
		// @0AF: invokevirtual java.lang.StringBuilder.append(char)java.lang.StringBuilder
		// @0B2: aload_3
		// @0B3: ifnull @0BF
		// @0B6: getstatic java.lang.String[] game.C_100053_vn.field_102834_ib
		// @0B9: iconst_1
		// @0BA: aaload
		// @0BB: goto @0C4
		// @0BE: athrow
		// @0BF: getstatic java.lang.String[] game.C_100053_vn.field_102834_ib
		// @0C2: iconst_2
		// @0C3: aaload
		// @0C4: invokevirtual java.lang.StringBuilder.append(java.lang.String)java.lang.StringBuilder
		// @0C7: bipush 44 (0x2C)
		// @0C9: invokevirtual java.lang.StringBuilder.append(char)java.lang.StringBuilder
		// @0CC: iload #4
		// @0CE: invokevirtual java.lang.StringBuilder.append(int)java.lang.StringBuilder
		// @0D1: bipush 44 (0x2C)
		// @0D3: invokevirtual java.lang.StringBuilder.append(char)java.lang.StringBuilder
		// @0D6: iload #5
		// @0D8: invokevirtual java.lang.StringBuilder.append(int)java.lang.StringBuilder
		// @0DB: bipush 44 (0x2C)
		// @0DD: invokevirtual java.lang.StringBuilder.append(char)java.lang.StringBuilder
		// @0E0: aload #6
		// @0E2: ifnull @0EE
		// @0E5: getstatic java.lang.String[] game.C_100053_vn.field_102834_ib
		// @0E8: iconst_1
		// @0E9: aaload
		// @0EA: goto @0F3
		// @0ED: athrow
		// @0EE: getstatic java.lang.String[] game.C_100053_vn.field_102834_ib
		// @0F1: iconst_2
		// @0F2: aaload
		// @0F3: invokevirtual java.lang.StringBuilder.append(java.lang.String)java.lang.StringBuilder
		// @0F6: bipush 44 (0x2C)
		// @0F8: invokevirtual java.lang.StringBuilder.append(char)java.lang.StringBuilder
		// @0FB: iload #7
		// @0FD: invokevirtual java.lang.StringBuilder.append(int)java.lang.StringBuilder
		// @100: bipush 41 (0x29)
		// @102: invokevirtual java.lang.StringBuilder.append(char)java.lang.StringBuilder
		// @105: invokevirtual java.lang.StringBuilder.toString()java.lang.String
		// @108: invokestatic game.C_100181_cf.func_105695_a(java.lang.Throwable, java.lang.String)game.C_100170_cm
		// @10B: athrow
	}
	
	private final boolean func_102820_a(boolean arg0)
	{
		// @00: aload_0
		// @01: bipush -99 (0x9D)
		// @03: invokespecial game.C_100053_vn.func_102824_k(int)boolean
		// @06: ifeq @0D
		// @09: goto @0F
		// @0C: athrow
		// @0D: iconst_0
		// @0E: ireturn
		// @0F: iconst_m1
		// @10: istore_2
		// @11: iload_1
		// @12: ifeq @20
		// @15: aconst_null
		// @16: checkcast game.C_100037_wb[]
		// @19: putstatic game.C_100037_wb[] game.C_100053_vn.field_102845_Z
		// @1C: goto @20
		// @1F: athrow
		// @20: aload_0
		// @21: getfield game.C_100078_ul game.C_100053_vn.field_102828_hb
		// @24: getfield java.lang.String game.C_100078_ul.field_102534_C
		// @27: invokestatic java.lang.Integer.parseInt(java.lang.String)int
		// @2A: istore_2
		// @2B: goto @2F
		// @2E: astore_3
		// @2F: aload_0
		// @30: getfield game.C_100078_ul game.C_100053_vn.field_102829_eb
		// @33: getfield java.lang.String game.C_100078_ul.field_102534_C
		// @36: aload_0
		// @37: getfield game.C_100036_gg game.C_100053_vn.field_102826_db
		// @3A: getfield boolean game.C_100036_gg.field_103120_K
		// @3D: sipush 250 (0x00FA)
		// @40: aload_0
		// @41: aload_0
		// @42: getfield game.C_100078_ul game.C_100053_vn.field_102838_P
		// @45: getfield java.lang.String game.C_100078_ul.field_102534_C
		// @48: iload_2
		// @49: aload_0
		// @4A: getfield game.C_100078_ul game.C_100053_vn.field_102841_ab
		// @4D: getfield java.lang.String game.C_100078_ul.field_102534_C
		// @50: invokestatic game.C_100111_el.func_104857_a(java.lang.String, boolean, int, game.C_100053_vn, java.lang.String, int, java.lang.String)boolean
		// @53: ireturn
		// @54: astore_2
		// @55: aload_2
		// @56: new java.lang.StringBuilder
		// @59: dup
		// @5A: invokespecial java.lang.StringBuilder.<init>()void
		// @5D: getstatic java.lang.String[] game.C_100053_vn.field_102834_ib
		// @60: bipush 12 (0x0C)
		// @62: aaload
		// @63: invokevirtual java.lang.StringBuilder.append(java.lang.String)java.lang.StringBuilder
		// @66: iload_1
		// @67: invokevirtual java.lang.StringBuilder.append(boolean)java.lang.StringBuilder
		// @6A: bipush 41 (0x29)
		// @6C: invokevirtual java.lang.StringBuilder.append(char)java.lang.StringBuilder
		// @6F: invokevirtual java.lang.StringBuilder.toString()java.lang.String
		// @72: invokestatic game.C_100181_cf.func_105695_a(java.lang.Throwable, java.lang.String)game.C_100170_cm
		// @75: athrow
	}
	
	private final int func_102823_a(int arg0, C_100336_im arg1, int arg2, int arg3, String arg4)
	{
		// @00: new game.C_100271_mj
		// @03: dup
		// @04: bipush 20 (0x14)
		// @06: iload_3
		// @07: bipush 120 (0x78)
		// @09: iload_1
		// @0A: iadd
		// @0B: bipush 25 (0x19)
		// @0D: aload_2
		// @0E: iconst_0
		// @0F: bipush 120 (0x78)
		// @11: iconst_3
		// @12: getstatic game.C_100112_r game.C_100230_of.field_106205_g
		// @15: ldc 16777215 (0xffffff)
		// @17: aload #5
		// @19: invokespecial game.C_100271_mj.<init>(int, int, int, int, game.C_100336_im, boolean, int, int, game.C_100112_r, int, java.lang.String)void
		// @1C: astore #6
		// @1E: iload #4
		// @20: sipush -6781 (0xE583)
		// @23: if_icmpeq @31
		// @26: aconst_null
		// @27: checkcast game.C_100105_eg
		// @2A: putstatic game.C_100105_eg game.C_100053_vn.field_102832_U
		// @2D: goto @31
		// @30: athrow
		// @31: aload_0
		// @32: aload #6
		// @34: iload #4
		// @36: sipush 6782 (0x1A7E)
		// @39: iadd
		// @3A: invokevirtual game.C_100053_vn.func_102561_b(game.C_100336_im, int)void
		// @3D: new game.C_100305_km
		// @40: dup
		// @41: aload_2
		// @42: checkcast game.C_100267_mf
		// @45: iconst_1
		// @46: invokeinterface game.C_100267_mf.func_103100_a(boolean)game.C_100308_lh
		// @4B: invokespecial game.C_100305_km.<init>(game.C_100308_lh)void
		// @4E: astore #7
		// @50: aload_0
		// @51: aload #7
		// @53: iload #4
		// @55: sipush -6782 (0xE582)
		// @58: ixor
		// @59: invokevirtual game.C_100053_vn.func_102561_b(game.C_100336_im, int)void
		// @5C: aload #7
		// @5E: bipush 15 (0x0F)
		// @60: bipush -15 (0xF1)
		// @62: aload #6
		// @64: getfield int game.C_100271_mj.field_102544_t
		// @67: iadd
		// @68: ldc 241092961 (0xe5ec961)
		// @6A: ishr
		// @6B: aload #6
		// @6D: getfield int game.C_100271_mj.field_102541_w
		// @70: iadd
		// @71: aload #6
		// @73: getfield int game.C_100271_mj.field_102537_l
		// @76: aload #6
		// @78: getfield int game.C_100271_mj.field_102538_m
		// @7B: iconst_3
		// @7C: iadd
		// @7D: iadd
		// @7E: bipush 15 (0x0F)
		// @80: bipush -93 (0xA3)
		// @82: invokevirtual game.C_100305_km.func_102524_a(int, int, int, int, byte)void
		// @85: aload #6
		// @87: getfield int game.C_100271_mj.field_102544_t
		// @8A: ireturn
		// @8B: astore #6
		// @8D: aload #6
		// @8F: new java.lang.StringBuilder
		// @92: dup
		// @93: invokespecial java.lang.StringBuilder.<init>()void
		// @96: getstatic java.lang.String[] game.C_100053_vn.field_102834_ib
		// @99: bipush 15 (0x0F)
		// @9B: aaload
		// @9C: invokevirtual java.lang.StringBuilder.append(java.lang.String)java.lang.StringBuilder
		// @9F: iload_1
		// @A0: invokevirtual java.lang.StringBuilder.append(int)java.lang.StringBuilder
		// @A3: bipush 44 (0x2C)
		// @A5: invokevirtual java.lang.StringBuilder.append(char)java.lang.StringBuilder
		// @A8: aload_2
		// @A9: ifnull @B5
		// @AC: getstatic java.lang.String[] game.C_100053_vn.field_102834_ib
		// @AF: iconst_1
		// @B0: aaload
		// @B1: goto @BA
		// @B4: athrow
		// @B5: getstatic java.lang.String[] game.C_100053_vn.field_102834_ib
		// @B8: iconst_2
		// @B9: aaload
		// @BA: invokevirtual java.lang.StringBuilder.append(java.lang.String)java.lang.StringBuilder
		// @BD: bipush 44 (0x2C)
		// @BF: invokevirtual java.lang.StringBuilder.append(char)java.lang.StringBuilder
		// @C2: iload_3
		// @C3: invokevirtual java.lang.StringBuilder.append(int)java.lang.StringBuilder
		// @C6: bipush 44 (0x2C)
		// @C8: invokevirtual java.lang.StringBuilder.append(char)java.lang.StringBuilder
		// @CB: iload #4
		// @CD: invokevirtual java.lang.StringBuilder.append(int)java.lang.StringBuilder
		// @D0: bipush 44 (0x2C)
		// @D2: invokevirtual java.lang.StringBuilder.append(char)java.lang.StringBuilder
		// @D5: aload #5
		// @D7: ifnull @E3
		// @DA: getstatic java.lang.String[] game.C_100053_vn.field_102834_ib
		// @DD: iconst_1
		// @DE: aaload
		// @DF: goto @E8
		// @E2: athrow
		// @E3: getstatic java.lang.String[] game.C_100053_vn.field_102834_ib
		// @E6: iconst_2
		// @E7: aaload
		// @E8: invokevirtual java.lang.StringBuilder.append(java.lang.String)java.lang.StringBuilder
		// @EB: bipush 41 (0x29)
		// @ED: invokevirtual java.lang.StringBuilder.append(char)java.lang.StringBuilder
		// @F0: invokevirtual java.lang.StringBuilder.toString()java.lang.String
		// @F3: invokestatic game.C_100181_cf.func_105695_a(java.lang.Throwable, java.lang.String)game.C_100170_cm
		// @F6: athrow
	}
	
	final void func_102513_a(C_100336_im arg0, int arg1, int arg2, int arg3)
	{
		// @00: aload_0
		// @01: aload_1
		// @02: iload_2
		// @03: iload_3
		// @04: iconst_0
		// @05: iadd
		// @06: iload #4
		// @08: invokespecial game.C_100085_a.func_102513_a(game.C_100336_im, int, int, int)void
		// @0B: iload_3
		// @0C: iconst_2
		// @0D: if_icmpeq @11
		// @10: return
		// @11: aload_0
		// @12: getfield game.C_100218_am game.C_100053_vn.field_102843_bb
		// @15: aload_0
		// @16: bipush -109 (0x93)
		// @18: invokespecial game.C_100053_vn.func_102824_k(int)boolean
		// @1B: putfield boolean game.C_100218_am.field_103113_L
		// @1E: goto @72
		// @21: astore #5
		// @23: aload #5
		// @25: new java.lang.StringBuilder
		// @28: dup
		// @29: invokespecial java.lang.StringBuilder.<init>()void
		// @2C: getstatic java.lang.String[] game.C_100053_vn.field_102834_ib
		// @2F: bipush 29 (0x1D)
		// @31: aaload
		// @32: invokevirtual java.lang.StringBuilder.append(java.lang.String)java.lang.StringBuilder
		// @35: aload_1
		// @36: ifnull @42
		// @39: getstatic java.lang.String[] game.C_100053_vn.field_102834_ib
		// @3C: iconst_1
		// @3D: aaload
		// @3E: goto @47
		// @41: athrow
		// @42: getstatic java.lang.String[] game.C_100053_vn.field_102834_ib
		// @45: iconst_2
		// @46: aaload
		// @47: invokevirtual java.lang.StringBuilder.append(java.lang.String)java.lang.StringBuilder
		// @4A: bipush 44 (0x2C)
		// @4C: invokevirtual java.lang.StringBuilder.append(char)java.lang.StringBuilder
		// @4F: iload_2
		// @50: invokevirtual java.lang.StringBuilder.append(int)java.lang.StringBuilder
		// @53: bipush 44 (0x2C)
		// @55: invokevirtual java.lang.StringBuilder.append(char)java.lang.StringBuilder
		// @58: iload_3
		// @59: invokevirtual java.lang.StringBuilder.append(int)java.lang.StringBuilder
		// @5C: bipush 44 (0x2C)
		// @5E: invokevirtual java.lang.StringBuilder.append(char)java.lang.StringBuilder
		// @61: iload #4
		// @63: invokevirtual java.lang.StringBuilder.append(int)java.lang.StringBuilder
		// @66: bipush 41 (0x29)
		// @68: invokevirtual java.lang.StringBuilder.append(char)java.lang.StringBuilder
		// @6B: invokevirtual java.lang.StringBuilder.toString()java.lang.String
		// @6E: invokestatic game.C_100181_cf.func_105695_a(java.lang.Throwable, java.lang.String)game.C_100170_cm
		// @71: athrow
		// @72: return
	}
	
	public final void func_102789_a(String arg0, boolean arg1)
	{
		// @00: aload_0
		// @01: getfield game.C_100078_ul game.C_100053_vn.field_102829_eb
		// @04: astore_3
		// @05: aload_1
		// @06: astore #4
		// @08: aload_3
		// @09: iload_2
		// @0A: iconst_1
		// @0B: aload #4
		// @0D: invokevirtual game.C_100309_lk.func_103251_a(boolean, boolean, java.lang.String)void
		// @10: goto @4E
		// @13: astore_3
		// @14: aload_3
		// @15: new java.lang.StringBuilder
		// @18: dup
		// @19: invokespecial java.lang.StringBuilder.<init>()void
		// @1C: getstatic java.lang.String[] game.C_100053_vn.field_102834_ib
		// @1F: iconst_4
		// @20: aaload
		// @21: invokevirtual java.lang.StringBuilder.append(java.lang.String)java.lang.StringBuilder
		// @24: aload_1
		// @25: ifnull @31
		// @28: getstatic java.lang.String[] game.C_100053_vn.field_102834_ib
		// @2B: iconst_1
		// @2C: aaload
		// @2D: goto @36
		// @30: athrow
		// @31: getstatic java.lang.String[] game.C_100053_vn.field_102834_ib
		// @34: iconst_2
		// @35: aaload
		// @36: invokevirtual java.lang.StringBuilder.append(java.lang.String)java.lang.StringBuilder
		// @39: bipush 44 (0x2C)
		// @3B: invokevirtual java.lang.StringBuilder.append(char)java.lang.StringBuilder
		// @3E: iload_2
		// @3F: invokevirtual java.lang.StringBuilder.append(boolean)java.lang.StringBuilder
		// @42: bipush 41 (0x29)
		// @44: invokevirtual java.lang.StringBuilder.append(char)java.lang.StringBuilder
		// @47: invokevirtual java.lang.StringBuilder.toString()java.lang.String
		// @4A: invokestatic game.C_100181_cf.func_105695_a(java.lang.Throwable, java.lang.String)game.C_100170_cm
		// @4D: athrow
		// @4E: return
	}
	
	public static void func_102822_c(boolean arg0)
	{
		// @00: aconst_null
		// @01: putstatic game.C_100105_eg game.C_100053_vn.field_102832_U
		// @04: aconst_null
		// @05: putstatic java.lang.String game.C_100053_vn.field_102840_R
		// @08: aconst_null
		// @09: putstatic game.C_100037_wb[] game.C_100053_vn.field_102845_Z
		// @0C: aconst_null
		// @0D: putstatic game.C_100112_r game.C_100053_vn.field_102827_cb
		// @10: iload_0
		// @11: iconst_1
		// @12: if_icmpeq @16
		// @15: return
		// @16: aconst_null
		// @17: putstatic game.C_100217_ao game.C_100053_vn.field_102837_Q
		// @1A: aconst_null
		// @1B: putstatic game.C_100302_ka game.C_100053_vn.field_102842_Y
		// @1E: aconst_null
		// @1F: putstatic game.C_100037_wb[] game.C_100053_vn.field_102833_T
		// @22: goto @46
		// @25: astore_1
		// @26: aload_1
		// @27: new java.lang.StringBuilder
		// @2A: dup
		// @2B: invokespecial java.lang.StringBuilder.<init>()void
		// @2E: getstatic java.lang.String[] game.C_100053_vn.field_102834_ib
		// @31: iconst_3
		// @32: aaload
		// @33: invokevirtual java.lang.StringBuilder.append(java.lang.String)java.lang.StringBuilder
		// @36: iload_0
		// @37: invokevirtual java.lang.StringBuilder.append(boolean)java.lang.StringBuilder
		// @3A: bipush 41 (0x29)
		// @3C: invokevirtual java.lang.StringBuilder.append(char)java.lang.StringBuilder
		// @3F: invokevirtual java.lang.StringBuilder.toString()java.lang.String
		// @42: invokestatic game.C_100181_cf.func_105695_a(java.lang.Throwable, java.lang.String)game.C_100170_cm
		// @45: athrow
		// @46: return
	}
	
	private final int func_102814_a(String arg0, int arg1, int arg2, int arg3, C_100336_im arg4)
	{
		// @00: iload_2
		// @01: bipush -70 (0xBA)
		// @03: if_icmple @12
		// @06: aload_0
		// @07: aconst_null
		// @08: checkcast game.C_100078_ul
		// @0B: putfield game.C_100078_ul game.C_100053_vn.field_102828_hb
		// @0E: goto @12
		// @11: athrow
		// @12: new game.C_100271_mj
		// @15: dup
		// @16: bipush 20 (0x14)
		// @18: iload_3
		// @19: iload #4
		// @1B: bipush 120 (0x78)
		// @1D: iadd
		// @1E: bipush 25 (0x19)
		// @20: aload #5
		// @22: iconst_0
		// @23: bipush 120 (0x78)
		// @25: iconst_3
		// @26: getstatic game.C_100112_r game.C_100230_of.field_106205_g
		// @29: ldc 16777215 (0xffffff)
		// @2B: aload_1
		// @2C: invokespecial game.C_100271_mj.<init>(int, int, int, int, game.C_100336_im, boolean, int, int, game.C_100112_r, int, java.lang.String)void
		// @2F: astore #6
		// @31: aload_0
		// @32: aload #6
		// @34: iconst_1
		// @35: invokevirtual game.C_100053_vn.func_102561_b(game.C_100336_im, int)void
		// @38: aload #6
		// @3A: getfield int game.C_100271_mj.field_102544_t
		// @3D: ireturn
		// @3E: astore #6
		// @40: aload #6
		// @42: new java.lang.StringBuilder
		// @45: dup
		// @46: invokespecial java.lang.StringBuilder.<init>()void
		// @49: getstatic java.lang.String[] game.C_100053_vn.field_102834_ib
		// @4C: bipush 10 (0x0A)
		// @4E: aaload
		// @4F: invokevirtual java.lang.StringBuilder.append(java.lang.String)java.lang.StringBuilder
		// @52: aload_1
		// @53: ifnull @5F
		// @56: getstatic java.lang.String[] game.C_100053_vn.field_102834_ib
		// @59: iconst_1
		// @5A: aaload
		// @5B: goto @64
		// @5E: athrow
		// @5F: getstatic java.lang.String[] game.C_100053_vn.field_102834_ib
		// @62: iconst_2
		// @63: aaload
		// @64: invokevirtual java.lang.StringBuilder.append(java.lang.String)java.lang.StringBuilder
		// @67: bipush 44 (0x2C)
		// @69: invokevirtual java.lang.StringBuilder.append(char)java.lang.StringBuilder
		// @6C: iload_2
		// @6D: invokevirtual java.lang.StringBuilder.append(int)java.lang.StringBuilder
		// @70: bipush 44 (0x2C)
		// @72: invokevirtual java.lang.StringBuilder.append(char)java.lang.StringBuilder
		// @75: iload_3
		// @76: invokevirtual java.lang.StringBuilder.append(int)java.lang.StringBuilder
		// @79: bipush 44 (0x2C)
		// @7B: invokevirtual java.lang.StringBuilder.append(char)java.lang.StringBuilder
		// @7E: iload #4
		// @80: invokevirtual java.lang.StringBuilder.append(int)java.lang.StringBuilder
		// @83: bipush 44 (0x2C)
		// @85: invokevirtual java.lang.StringBuilder.append(char)java.lang.StringBuilder
		// @88: aload #5
		// @8A: ifnull @96
		// @8D: getstatic java.lang.String[] game.C_100053_vn.field_102834_ib
		// @90: iconst_1
		// @91: aaload
		// @92: goto @9B
		// @95: athrow
		// @96: getstatic java.lang.String[] game.C_100053_vn.field_102834_ib
		// @99: iconst_2
		// @9A: aaload
		// @9B: invokevirtual java.lang.StringBuilder.append(java.lang.String)java.lang.StringBuilder
		// @9E: bipush 41 (0x29)
		// @A0: invokevirtual java.lang.StringBuilder.append(char)java.lang.StringBuilder
		// @A3: invokevirtual java.lang.StringBuilder.toString()java.lang.String
		// @A6: invokestatic game.C_100181_cf.func_105695_a(java.lang.Throwable, java.lang.String)game.C_100170_cm
		// @A9: athrow
	}
	
	private final String func_102821_f(byte arg0)
	{
		// @00: iload_1
		// @01: bipush -99 (0x9D)
		// @03: if_icmpeq @0B
		// @06: aconst_null
		// @07: checkcast java.lang.String
		// @0A: areturn
		// @0B: getstatic java.lang.String[] game.C_100053_vn.field_102834_ib
		// @0E: bipush 25 (0x19)
		// @10: aaload
		// @11: areturn
		// @12: astore_2
		// @13: aload_2
		// @14: new java.lang.StringBuilder
		// @17: dup
		// @18: invokespecial java.lang.StringBuilder.<init>()void
		// @1B: getstatic java.lang.String[] game.C_100053_vn.field_102834_ib
		// @1E: bipush 26 (0x1A)
		// @20: aaload
		// @21: invokevirtual java.lang.StringBuilder.append(java.lang.String)java.lang.StringBuilder
		// @24: iload_1
		// @25: invokevirtual java.lang.StringBuilder.append(int)java.lang.StringBuilder
		// @28: bipush 41 (0x29)
		// @2A: invokevirtual java.lang.StringBuilder.append(char)java.lang.StringBuilder
		// @2D: invokevirtual java.lang.StringBuilder.toString()java.lang.String
		// @30: invokestatic game.C_100181_cf.func_105695_a(java.lang.Throwable, java.lang.String)game.C_100170_cm
		// @33: athrow
	}
	
	private final String func_102815_g(byte arg0)
	{
		// @00: iload_1
		// @01: bipush -37 (0xDB)
		// @03: if_icmpeq @0B
		// @06: aconst_null
		// @07: checkcast java.lang.String
		// @0A: areturn
		// @0B: getstatic java.lang.String[] game.C_100053_vn.field_102834_ib
		// @0E: bipush 28 (0x1C)
		// @10: aaload
		// @11: areturn
		// @12: astore_2
		// @13: aload_2
		// @14: new java.lang.StringBuilder
		// @17: dup
		// @18: invokespecial java.lang.StringBuilder.<init>()void
		// @1B: getstatic java.lang.String[] game.C_100053_vn.field_102834_ib
		// @1E: bipush 27 (0x1B)
		// @20: aaload
		// @21: invokevirtual java.lang.StringBuilder.append(java.lang.String)java.lang.StringBuilder
		// @24: iload_1
		// @25: invokevirtual java.lang.StringBuilder.append(int)java.lang.StringBuilder
		// @28: bipush 41 (0x29)
		// @2A: invokevirtual java.lang.StringBuilder.append(char)java.lang.StringBuilder
		// @2D: invokevirtual java.lang.StringBuilder.toString()java.lang.String
		// @30: invokestatic game.C_100181_cf.func_105695_a(java.lang.Throwable, java.lang.String)game.C_100170_cm
		// @33: athrow
	}
	
	public final void func_102769_a(int arg0, int arg1, int arg2, C_100083_c arg3)
	{
		// @00: getstatic int game.SteelSentinels.field_105275_O
		// @03: istore #6
		// @05: iload_3
		// @06: iload_1
		// @07: iconst_m1
		// @08: ixor
		// @09: if_icmpeq @4E
		// @0C: iload_1
		// @0D: iconst_m1
		// @0E: ixor
		// @0F: bipush -2 (0xFE)
		// @11: if_icmpne @2E
		// @14: goto @18
		// @17: athrow
		// @18: getstatic java.lang.String[] game.C_100053_vn.field_102834_ib
		// @1B: bipush 19 (0x13)
		// @1D: aaload
		// @1E: iload_3
		// @1F: bipush 125 (0x7D)
		// @21: ixor
		// @22: invokestatic game.C_100101_fc.func_103392_a(java.lang.String, int)void
		// @25: iload #6
		// @27: ifeq @5D
		// @2A: goto @2E
		// @2D: athrow
		// @2E: bipush -3 (0xFD)
		// @30: iload_1
		// @31: iconst_m1
		// @32: ixor
		// @33: if_icmpne @5D
		// @36: goto @3A
		// @39: athrow
		// @3A: getstatic java.lang.String[] game.C_100053_vn.field_102834_ib
		// @3D: bipush 17 (0x11)
		// @3F: aaload
		// @40: bipush -63 (0xC1)
		// @42: invokestatic game.C_100101_fc.func_103392_a(java.lang.String, int)void
		// @45: iload #6
		// @47: ifeq @5D
		// @4A: goto @4E
		// @4D: athrow
		// @4E: getstatic java.lang.String[] game.C_100053_vn.field_102834_ib
		// @51: bipush 16 (0x10)
		// @53: aaload
		// @54: bipush -117 (0x8B)
		// @56: invokestatic game.C_100101_fc.func_103392_a(java.lang.String, int)void
		// @59: goto @5D
		// @5C: athrow
		// @5D: goto @B1
		// @60: astore #5
		// @62: aload #5
		// @64: new java.lang.StringBuilder
		// @67: dup
		// @68: invokespecial java.lang.StringBuilder.<init>()void
		// @6B: getstatic java.lang.String[] game.C_100053_vn.field_102834_ib
		// @6E: bipush 18 (0x12)
		// @70: aaload
		// @71: invokevirtual java.lang.StringBuilder.append(java.lang.String)java.lang.StringBuilder
		// @74: iload_1
		// @75: invokevirtual java.lang.StringBuilder.append(int)java.lang.StringBuilder
		// @78: bipush 44 (0x2C)
		// @7A: invokevirtual java.lang.StringBuilder.append(char)java.lang.StringBuilder
		// @7D: iload_2
		// @7E: invokevirtual java.lang.StringBuilder.append(int)java.lang.StringBuilder
		// @81: bipush 44 (0x2C)
		// @83: invokevirtual java.lang.StringBuilder.append(char)java.lang.StringBuilder
		// @86: iload_3
		// @87: invokevirtual java.lang.StringBuilder.append(int)java.lang.StringBuilder
		// @8A: bipush 44 (0x2C)
		// @8C: invokevirtual java.lang.StringBuilder.append(char)java.lang.StringBuilder
		// @8F: aload #4
		// @91: ifnull @9D
		// @94: getstatic java.lang.String[] game.C_100053_vn.field_102834_ib
		// @97: iconst_1
		// @98: aaload
		// @99: goto @A2
		// @9C: athrow
		// @9D: getstatic java.lang.String[] game.C_100053_vn.field_102834_ib
		// @A0: iconst_2
		// @A1: aaload
		// @A2: invokevirtual java.lang.StringBuilder.append(java.lang.String)java.lang.StringBuilder
		// @A5: bipush 41 (0x29)
		// @A7: invokevirtual java.lang.StringBuilder.append(char)java.lang.StringBuilder
		// @AA: invokevirtual java.lang.StringBuilder.toString()java.lang.String
		// @AD: invokestatic game.C_100181_cf.func_105695_a(java.lang.Throwable, java.lang.String)game.C_100170_cm
		// @B0: athrow
		// @B1: return
	}
	
	static final void func_102825_a(C_100314_lf arg0, byte arg1)
	{
		// @000: getstatic int game.SteelSentinels.field_105275_O
		// @003: istore #4
		// @005: bipush 107 (0x6B)
		// @007: bipush -51 (0xCD)
		// @009: iload_1
		// @00A: isub
		// @00B: bipush 47 (0x2F)
		// @00D: idiv
		// @00E: idiv
		// @00F: istore_2
		// @010: aload_0
		// @011: getfield int game.C_100314_lf.field_101343_vb
		// @014: istore_3
		// @015: iload_3
		// @016: bipush 10 (0x0A)
		// @018: if_icmpne @024
		// @01B: iload #4
		// @01D: ifeq @123
		// @020: goto @024
		// @023: athrow
		// @024: iload_3
		// @025: iconst_m1
		// @026: ixor
		// @027: bipush -12 (0xF4)
		// @029: if_icmpeq @133
		// @02C: goto @030
		// @02F: athrow
		// @030: bipush -13 (0xF3)
		// @032: iload_3
		// @033: iconst_m1
		// @034: ixor
		// @035: if_icmpne @045
		// @038: goto @03C
		// @03B: athrow
		// @03C: iload #4
		// @03E: ifeq @148
		// @041: goto @045
		// @044: athrow
		// @045: bipush -14 (0xF2)
		// @047: iload_3
		// @048: iconst_m1
		// @049: ixor
		// @04A: if_icmpeq @15D
		// @04D: goto @051
		// @050: athrow
		// @051: bipush 14 (0x0E)
		// @053: iload_3
		// @054: if_icmpne @064
		// @057: goto @05B
		// @05A: athrow
		// @05B: iload #4
		// @05D: ifeq @172
		// @060: goto @064
		// @063: athrow
		// @064: iload_3
		// @065: iconst_m1
		// @066: ixor
		// @067: iconst_m1
		// @068: if_icmpne @078
		// @06B: goto @06F
		// @06E: athrow
		// @06F: iload #4
		// @071: ifeq @187
		// @074: goto @078
		// @077: athrow
		// @078: iconst_1
		// @079: iload_3
		// @07A: if_icmpne @08A
		// @07D: goto @081
		// @080: athrow
		// @081: iload #4
		// @083: ifeq @19A
		// @086: goto @08A
		// @089: athrow
		// @08A: bipush -3 (0xFD)
		// @08C: iload_3
		// @08D: iconst_m1
		// @08E: ixor
		// @08F: if_icmpeq @1AD
		// @092: goto @096
		// @095: athrow
		// @096: iload_3
		// @097: iconst_3
		// @098: if_icmpne @0A8
		// @09B: goto @09F
		// @09E: athrow
		// @09F: iload #4
		// @0A1: ifeq @1C0
		// @0A4: goto @0A8
		// @0A7: athrow
		// @0A8: iload_3
		// @0A9: iconst_4
		// @0AA: if_icmpeq @1D3
		// @0AD: goto @0B1
		// @0B0: athrow
		// @0B1: bipush -21 (0xEB)
		// @0B3: iload_3
		// @0B4: iconst_m1
		// @0B5: ixor
		// @0B6: if_icmpne @0C6
		// @0B9: goto @0BD
		// @0BC: athrow
		// @0BD: iload #4
		// @0BF: ifeq @1E6
		// @0C2: goto @0C6
		// @0C5: athrow
		// @0C6: iload_3
		// @0C7: iconst_5
		// @0C8: if_icmpeq @1FA
		// @0CB: goto @0CF
		// @0CE: athrow
		// @0CF: iload_3
		// @0D0: bipush 6 (0x06)
		// @0D2: if_icmpeq @1FA
		// @0D5: goto @0D9
		// @0D8: athrow
		// @0D9: iload_3
		// @0DA: iconst_m1
		// @0DB: ixor
		// @0DC: bipush -8 (0xF8)
		// @0DE: if_icmpeq @1FA
		// @0E1: goto @0E5
		// @0E4: athrow
		// @0E5: iload_3
		// @0E6: bipush 8 (0x08)
		// @0E8: if_icmpne @0F8
		// @0EB: goto @0EF
		// @0EE: athrow
		// @0EF: iload #4
		// @0F1: ifeq @1FA
		// @0F4: goto @0F8
		// @0F7: athrow
		// @0F8: bipush 9 (0x09)
		// @0FA: iload_3
		// @0FB: if_icmpeq @1FA
		// @0FE: goto @102
		// @101: athrow
		// @102: iload_3
		// @103: bipush 29 (0x1D)
		// @105: if_icmpne @115
		// @108: goto @10C
		// @10B: athrow
		// @10C: iload #4
		// @10E: ifeq @215
		// @111: goto @115
		// @114: athrow
		// @115: iload_3
		// @116: bipush 28 (0x1C)
		// @118: if_icmpeq @228
		// @11B: goto @11F
		// @11E: athrow
		// @11F: goto @236
		// @122: athrow
		// @123: aload_0
		// @124: dup
		// @125: getfield int game.C_100314_lf.field_101358_u
		// @128: bipush 100 (0x64)
		// @12A: isub
		// @12B: putfield int game.C_100314_lf.field_101358_u
		// @12E: iload #4
		// @130: ifeq @236
		// @133: aload_0
		// @134: dup
		// @135: getfield int game.C_100314_lf.field_101358_u
		// @138: sipush 200 (0x00C8)
		// @13B: isub
		// @13C: putfield int game.C_100314_lf.field_101358_u
		// @13F: iload #4
		// @141: ifeq @236
		// @144: goto @148
		// @147: athrow
		// @148: aload_0
		// @149: dup
		// @14A: getfield int game.C_100314_lf.field_101358_u
		// @14D: sipush 300 (0x012C)
		// @150: isub
		// @151: putfield int game.C_100314_lf.field_101358_u
		// @154: iload #4
		// @156: ifeq @236
		// @159: goto @15D
		// @15C: athrow
		// @15D: aload_0
		// @15E: dup
		// @15F: getfield int game.C_100314_lf.field_101358_u
		// @162: sipush 400 (0x0190)
		// @165: isub
		// @166: putfield int game.C_100314_lf.field_101358_u
		// @169: iload #4
		// @16B: ifeq @236
		// @16E: goto @172
		// @171: athrow
		// @172: aload_0
		// @173: dup
		// @174: getfield int game.C_100314_lf.field_101358_u
		// @177: sipush 500 (0x01F4)
		// @17A: isub
		// @17B: putfield int game.C_100314_lf.field_101358_u
		// @17E: iload #4
		// @180: ifeq @236
		// @183: goto @187
		// @186: athrow
		// @187: aload_0
		// @188: dup
		// @189: getfield int game.C_100314_lf.field_101383_dc
		// @18C: iconst_1
		// @18D: isub
		// @18E: putfield int game.C_100314_lf.field_101383_dc
		// @191: iload #4
		// @193: ifeq @236
		// @196: goto @19A
		// @199: athrow
		// @19A: aload_0
		// @19B: dup
		// @19C: getfield int game.C_100314_lf.field_101383_dc
		// @19F: iconst_2
		// @1A0: isub
		// @1A1: putfield int game.C_100314_lf.field_101383_dc
		// @1A4: iload #4
		// @1A6: ifeq @236
		// @1A9: goto @1AD
		// @1AC: athrow
		// @1AD: aload_0
		// @1AE: dup
		// @1AF: getfield int game.C_100314_lf.field_101383_dc
		// @1B2: iconst_3
		// @1B3: isub
		// @1B4: putfield int game.C_100314_lf.field_101383_dc
		// @1B7: iload #4
		// @1B9: ifeq @236
		// @1BC: goto @1C0
		// @1BF: athrow
		// @1C0: aload_0
		// @1C1: dup
		// @1C2: getfield int game.C_100314_lf.field_101383_dc
		// @1C5: iconst_4
		// @1C6: isub
		// @1C7: putfield int game.C_100314_lf.field_101383_dc
		// @1CA: iload #4
		// @1CC: ifeq @236
		// @1CF: goto @1D3
		// @1D2: athrow
		// @1D3: aload_0
		// @1D4: dup
		// @1D5: getfield int game.C_100314_lf.field_101383_dc
		// @1D8: iconst_5
		// @1D9: isub
		// @1DA: putfield int game.C_100314_lf.field_101383_dc
		// @1DD: iload #4
		// @1DF: ifeq @236
		// @1E2: goto @1E6
		// @1E5: athrow
		// @1E6: aload_0
		// @1E7: dup
		// @1E8: getfield int game.C_100314_lf.field_101383_dc
		// @1EB: bipush 10 (0x0A)
		// @1ED: isub
		// @1EE: putfield int game.C_100314_lf.field_101383_dc
		// @1F1: iload #4
		// @1F3: ifeq @236
		// @1F6: goto @1FA
		// @1F9: athrow
		// @1FA: aload_0
		// @1FB: dup
		// @1FC: getfield int game.C_100314_lf.field_101373_cb
		// @1FF: aload_0
		// @200: getfield int game.C_100314_lf.field_101343_vb
		// @203: bipush -91 (0xA5)
		// @205: invokestatic game.C_100327_ib.func_102457_d(int, byte)int
		// @208: isub
		// @209: putfield int game.C_100314_lf.field_101373_cb
		// @20C: iload #4
		// @20E: ifeq @236
		// @211: goto @215
		// @214: athrow
		// @215: aload_0
		// @216: dup
		// @217: getfield int game.C_100314_lf.field_101412_Kb
		// @21A: iconst_2
		// @21B: idiv
		// @21C: putfield int game.C_100314_lf.field_101412_Kb
		// @21F: iload #4
		// @221: ifeq @236
		// @224: goto @228
		// @227: athrow
		// @228: aload_0
		// @229: dup
		// @22A: getfield int game.C_100314_lf.field_101334_V
		// @22D: iconst_2
		// @22E: idiv
		// @22F: putfield int game.C_100314_lf.field_101334_V
		// @232: goto @236
		// @235: athrow
		// @236: aload_0
		// @237: getfield int game.C_100314_lf.field_101358_u
		// @23A: iconst_m1
		// @23B: ixor
		// @23C: aload_0
		// @23D: getfield int game.C_100314_lf.field_101413_Bb
		// @240: iconst_m1
		// @241: ixor
		// @242: if_icmple @251
		// @245: aload_0
		// @246: aload_0
		// @247: getfield int game.C_100314_lf.field_101358_u
		// @24A: putfield int game.C_100314_lf.field_101413_Bb
		// @24D: goto @251
		// @250: athrow
		// @251: aload_0
		// @252: getfield int game.C_100314_lf.field_101373_cb
		// @255: iconst_m1
		// @256: ixor
		// @257: aload_0
		// @258: getfield int game.C_100314_lf.field_101310_Mb
		// @25B: iconst_m1
		// @25C: ixor
		// @25D: if_icmple @26B
		// @260: aload_0
		// @261: sipush 128 (0x0080)
		// @264: invokevirtual game.C_100314_lf.func_101278_g(int)void
		// @267: goto @26B
		// @26A: athrow
		// @26B: aload_0
		// @26C: iconst_m1
		// @26D: putfield int game.C_100314_lf.field_101343_vb
		// @270: goto @2AF
		// @273: astore_2
		// @274: aload_2
		// @275: new java.lang.StringBuilder
		// @278: dup
		// @279: invokespecial java.lang.StringBuilder.<init>()void
		// @27C: getstatic java.lang.String[] game.C_100053_vn.field_102834_ib
		// @27F: bipush 21 (0x15)
		// @281: aaload
		// @282: invokevirtual java.lang.StringBuilder.append(java.lang.String)java.lang.StringBuilder
		// @285: aload_0
		// @286: ifnull @292
		// @289: getstatic java.lang.String[] game.C_100053_vn.field_102834_ib
		// @28C: iconst_1
		// @28D: aaload
		// @28E: goto @297
		// @291: athrow
		// @292: getstatic java.lang.String[] game.C_100053_vn.field_102834_ib
		// @295: iconst_2
		// @296: aaload
		// @297: invokevirtual java.lang.StringBuilder.append(java.lang.String)java.lang.StringBuilder
		// @29A: bipush 44 (0x2C)
		// @29C: invokevirtual java.lang.StringBuilder.append(char)java.lang.StringBuilder
		// @29F: iload_1
		// @2A0: invokevirtual java.lang.StringBuilder.append(int)java.lang.StringBuilder
		// @2A3: bipush 41 (0x29)
		// @2A5: invokevirtual java.lang.StringBuilder.append(char)java.lang.StringBuilder
		// @2A8: invokevirtual java.lang.StringBuilder.toString()java.lang.String
		// @2AB: invokestatic game.C_100181_cf.func_105695_a(java.lang.Throwable, java.lang.String)game.C_100170_cm
		// @2AE: athrow
		// @2AF: return
	}
	
	static final void func_102810_l(int arg0)
	{
		// @00: getstatic int game.SteelSentinels.field_105275_O
		// @03: istore_3
		// @04: iload_0
		// @05: ifeq @13
		// @08: aconst_null
		// @09: checkcast game.C_100217_ao
		// @0C: putstatic game.C_100217_ao game.C_100053_vn.field_102837_Q
		// @0F: goto @13
		// @12: athrow
		// @13: getstatic game.C_100104_v game.C_100311_le.field_104714_w
		// @16: ifnonnull @1D
		// @19: goto @26
		// @1C: athrow
		// @1D: getstatic game.C_100104_v game.C_100311_le.field_104714_w
		// @20: sipush -3669 (0xF1AB)
		// @23: invokevirtual game.C_100104_v.func_104685_d(int)void
		// @26: getstatic game.C_100178_cg game.C_100163_sf.field_105439_c
		// @29: ifnonnull @30
		// @2C: goto @38
		// @2F: athrow
		// @30: getstatic game.C_100178_cg game.C_100163_sf.field_105439_c
		// @33: bipush -78 (0xB2)
		// @35: invokevirtual game.C_100178_cg.func_105679_b(byte)void
		// @38: aconst_null
		// @39: getstatic game.C_100301_kb game.C_100266_me.field_106657_h
		// @3C: if_acmpne @43
		// @3F: goto @4E
		// @42: athrow
		// @43: getstatic game.C_100301_kb game.C_100266_me.field_106657_h
		// @46: iconst_m1
		// @47: invokevirtual game.C_100301_kb.func_107075_b(int)void
		// @4A: goto @4E
		// @4D: astore_1
		// @4E: getstatic game.C_100301_kb[] game.C_100225_ah.field_106136_p
		// @51: ifnull @8A
		// @54: iconst_0
		// @55: istore_1
		// @56: iload_1
		// @57: iconst_m1
		// @58: ixor
		// @59: getstatic game.C_100301_kb[] game.C_100225_ah.field_106136_p
		// @5C: arraylength
		// @5D: iconst_m1
		// @5E: ixor
		// @5F: if_icmple @8A
		// @62: iload_3
		// @63: ifne @AF
		// @66: aconst_null
		// @67: getstatic game.C_100301_kb[] game.C_100225_ah.field_106136_p
		// @6A: iload_1
		// @6B: aaload
		// @6C: if_acmpeq @83
		// @6F: goto @73
		// @72: athrow
		// @73: getstatic game.C_100301_kb[] game.C_100225_ah.field_106136_p
		// @76: iload_1
		// @77: aaload
		// @78: iload_0
		// @79: iconst_m1
		// @7A: iadd
		// @7B: invokevirtual game.C_100301_kb.func_107075_b(int)void
		// @7E: goto @83
		// @81: athrow
		// @82: astore_2
		// @83: iinc #1 +1
		// @86: iload_3
		// @87: ifeq @56
		// @8A: goto @AF
		// @8D: astore_1
		// @8E: aload_1
		// @8F: new java.lang.StringBuilder
		// @92: dup
		// @93: invokespecial java.lang.StringBuilder.<init>()void
		// @96: getstatic java.lang.String[] game.C_100053_vn.field_102834_ib
		// @99: bipush 14 (0x0E)
		// @9B: aaload
		// @9C: invokevirtual java.lang.StringBuilder.append(java.lang.String)java.lang.StringBuilder
		// @9F: iload_0
		// @A0: invokevirtual java.lang.StringBuilder.append(int)java.lang.StringBuilder
		// @A3: bipush 41 (0x29)
		// @A5: invokevirtual java.lang.StringBuilder.append(char)java.lang.StringBuilder
		// @A8: invokevirtual java.lang.StringBuilder.toString()java.lang.String
		// @AB: invokestatic game.C_100181_cf.func_105695_a(java.lang.Throwable, java.lang.String)game.C_100170_cm
		// @AE: athrow
		// @AF: return
	}
	
	public C_100053_vn()
	{
		// @000: aload_0
		// @001: iconst_0
		// @002: iconst_0
		// @003: sipush 496 (0x01F0)
		// @006: iconst_0
		// @007: aconst_null
		// @008: invokespecial game.C_100085_a.<init>(int, int, int, int, game.C_100326_ic)void
		// @00B: aload_0
		// @00C: new game.C_100078_ul
		// @00F: dup
		// @010: ldc ""
		// @012: aconst_null
		// @013: bipush 12 (0x0C)
		// @015: invokespecial game.C_100078_ul.<init>(java.lang.String, game.C_100337_in, int)void
		// @018: putfield game.C_100078_ul game.C_100053_vn.field_102829_eb
		// @01B: aload_0
		// @01C: new game.C_100078_ul
		// @01F: dup
		// @020: ldc ""
		// @022: aconst_null
		// @023: bipush 100 (0x64)
		// @025: invokespecial game.C_100078_ul.<init>(java.lang.String, game.C_100337_in, int)void
		// @028: putfield game.C_100078_ul game.C_100053_vn.field_102838_P
		// @02B: aload_0
		// @02C: new game.C_100078_ul
		// @02F: dup
		// @030: ldc ""
		// @032: aconst_null
		// @033: bipush 100 (0x64)
		// @035: invokespecial game.C_100078_ul.<init>(java.lang.String, game.C_100337_in, int)void
		// @038: putfield game.C_100078_ul game.C_100053_vn.field_102836_V
		// @03B: aload_0
		// @03C: new game.C_100078_ul
		// @03F: dup
		// @040: ldc ""
		// @042: aconst_null
		// @043: bipush 20 (0x14)
		// @045: invokespecial game.C_100078_ul.<init>(java.lang.String, game.C_100337_in, int)void
		// @048: putfield game.C_100078_ul game.C_100053_vn.field_102841_ab
		// @04B: aload_0
		// @04C: new game.C_100078_ul
		// @04F: dup
		// @050: ldc ""
		// @052: aconst_null
		// @053: bipush 20 (0x14)
		// @055: invokespecial game.C_100078_ul.<init>(java.lang.String, game.C_100337_in, int)void
		// @058: putfield game.C_100078_ul game.C_100053_vn.field_102844_X
		// @05B: aload_0
		// @05C: new game.C_100078_ul
		// @05F: dup
		// @060: ldc ""
		// @062: aconst_null
		// @063: iconst_3
		// @064: invokespecial game.C_100078_ul.<init>(java.lang.String, game.C_100337_in, int)void
		// @067: putfield game.C_100078_ul game.C_100053_vn.field_102828_hb
		// @06A: iconst_1
		// @06B: istore_1
		// @06C: aload_0
		// @06D: new game.C_100036_gg
		// @070: dup
		// @071: ldc ""
		// @073: aconst_null
		// @074: iload_1
		// @075: invokespecial game.C_100036_gg.<init>(java.lang.String, game.C_100337_in, boolean)void
		// @078: putfield game.C_100036_gg game.C_100053_vn.field_102826_db
		// @07B: aload_0
		// @07C: new game.C_100218_am
		// @07F: dup
		// @080: getstatic java.lang.String game.C_100068_vc.field_104349_i
		// @083: aconst_null
		// @084: invokespecial game.C_100218_am.<init>(java.lang.String, game.C_100337_in)void
		// @087: putfield game.C_100218_am game.C_100053_vn.field_102843_bb
		// @08A: aload_0
		// @08B: new game.C_100218_am
		// @08E: dup
		// @08F: getstatic java.lang.String game.C_100207_qh.field_102882_Y
		// @092: aconst_null
		// @093: invokespecial game.C_100218_am.<init>(java.lang.String, game.C_100337_in)void
		// @096: putfield game.C_100218_am game.C_100053_vn.field_102831_gb
		// @099: aload_0
		// @09A: getfield game.C_100078_ul game.C_100053_vn.field_102829_eb
		// @09D: getstatic java.lang.String game.C_100106_ef.field_104758_h
		// @0A0: putfield java.lang.String game.C_100078_ul.field_102536_o
		// @0A3: aload_0
		// @0A4: getfield game.C_100078_ul game.C_100053_vn.field_102838_P
		// @0A7: getstatic java.lang.String game.C_100081_ue.field_100667_t
		// @0AA: putfield java.lang.String game.C_100078_ul.field_102536_o
		// @0AD: aload_0
		// @0AE: getfield game.C_100078_ul game.C_100053_vn.field_102836_V
		// @0B1: getstatic java.lang.String game.C_100081_ue.field_100671_p
		// @0B4: putfield java.lang.String game.C_100078_ul.field_102536_o
		// @0B7: aload_0
		// @0B8: getfield game.C_100078_ul game.C_100053_vn.field_102841_ab
		// @0BB: getstatic java.lang.String game.C_100030_gm.field_103346_M
		// @0BE: putfield java.lang.String game.C_100078_ul.field_102536_o
		// @0C1: aload_0
		// @0C2: getfield game.C_100078_ul game.C_100053_vn.field_102844_X
		// @0C5: getstatic java.lang.String game.C_100323_hl.field_107247_b
		// @0C8: putfield java.lang.String game.C_100078_ul.field_102536_o
		// @0CB: aload_0
		// @0CC: getfield game.C_100078_ul game.C_100053_vn.field_102828_hb
		// @0CF: getstatic java.lang.String game.C_100071_va.field_101668_y
		// @0D2: putfield java.lang.String game.C_100078_ul.field_102536_o
		// @0D5: aload_0
		// @0D6: getfield game.C_100036_gg game.C_100053_vn.field_102826_db
		// @0D9: getstatic java.lang.String game.C_100206_qe.field_105939_d
		// @0DC: putfield java.lang.String game.C_100036_gg.field_102536_o
		// @0DF: aload_0
		// @0E0: getfield game.C_100078_ul game.C_100053_vn.field_102829_eb
		// @0E3: bipush -81 (0xAF)
		// @0E5: new game.C_100064_ve
		// @0E8: dup
		// @0E9: aload_0
		// @0EA: getfield game.C_100078_ul game.C_100053_vn.field_102829_eb
		// @0ED: invokespecial game.C_100064_ve.<init>(game.C_100309_lk)void
		// @0F0: invokevirtual game.C_100078_ul.func_103279_a(byte, game.C_100308_lh)void
		// @0F3: aload_0
		// @0F4: getfield game.C_100078_ul game.C_100053_vn.field_102838_P
		// @0F7: bipush -123 (0x85)
		// @0F9: new game.C_100126_cb
		// @0FC: dup
		// @0FD: aload_0
		// @0FE: getfield game.C_100078_ul game.C_100053_vn.field_102838_P
		// @101: invokespecial game.C_100126_cb.<init>(game.C_100309_lk)void
		// @104: invokevirtual game.C_100078_ul.func_103279_a(byte, game.C_100308_lh)void
		// @107: aload_0
		// @108: getfield game.C_100078_ul game.C_100053_vn.field_102836_V
		// @10B: bipush -48 (0xD0)
		// @10D: new game.C_100099_fb
		// @110: dup
		// @111: aload_0
		// @112: getfield game.C_100078_ul game.C_100053_vn.field_102836_V
		// @115: aload_0
		// @116: getfield game.C_100078_ul game.C_100053_vn.field_102838_P
		// @119: invokespecial game.C_100099_fb.<init>(game.C_100309_lk, game.C_100309_lk)void
		// @11C: invokevirtual game.C_100078_ul.func_103279_a(byte, game.C_100308_lh)void
		// @11F: aload_0
		// @120: getfield game.C_100078_ul game.C_100053_vn.field_102841_ab
		// @123: bipush -51 (0xCD)
		// @125: new game.C_100024_hd
		// @128: dup
		// @129: aload_0
		// @12A: getfield game.C_100078_ul game.C_100053_vn.field_102841_ab
		// @12D: aload_0
		// @12E: getfield game.C_100078_ul game.C_100053_vn.field_102829_eb
		// @131: aload_0
		// @132: getfield game.C_100078_ul game.C_100053_vn.field_102838_P
		// @135: invokespecial game.C_100024_hd.<init>(game.C_100309_lk, game.C_100309_lk, game.C_100309_lk)void
		// @138: invokevirtual game.C_100078_ul.func_103279_a(byte, game.C_100308_lh)void
		// @13B: aload_0
		// @13C: getfield game.C_100078_ul game.C_100053_vn.field_102844_X
		// @13F: bipush -51 (0xCD)
		// @141: new game.C_100194_rd
		// @144: dup
		// @145: aload_0
		// @146: getfield game.C_100078_ul game.C_100053_vn.field_102844_X
		// @149: aload_0
		// @14A: getfield game.C_100078_ul game.C_100053_vn.field_102841_ab
		// @14D: invokespecial game.C_100194_rd.<init>(game.C_100309_lk, game.C_100309_lk)void
		// @150: invokevirtual game.C_100078_ul.func_103279_a(byte, game.C_100308_lh)void
		// @153: aload_0
		// @154: getfield game.C_100078_ul game.C_100053_vn.field_102828_hb
		// @157: bipush -41 (0xD7)
		// @159: new game.C_100086_uh
		// @15C: dup
		// @15D: aload_0
		// @15E: getfield game.C_100078_ul game.C_100053_vn.field_102828_hb
		// @161: invokespecial game.C_100086_uh.<init>(game.C_100309_lk)void
		// @164: invokevirtual game.C_100078_ul.func_103279_a(byte, game.C_100308_lh)void
		// @167: aload_0
		// @168: getfield game.C_100218_am game.C_100053_vn.field_102843_bb
		// @16B: iconst_0
		// @16C: putfield boolean game.C_100218_am.field_103113_L
		// @16F: aload_0
		// @170: getfield game.C_100218_am game.C_100053_vn.field_102843_bb
		// @173: new game.C_100310_lj
		// @176: dup
		// @177: invokespecial game.C_100310_lj.<init>()void
		// @17A: putfield game.C_100326_ic game.C_100218_am.field_102533_B
		// @17D: aload_0
		// @17E: getfield game.C_100218_am game.C_100053_vn.field_102831_gb
		// @181: new game.C_100082_uf
		// @184: dup
		// @185: invokespecial game.C_100082_uf.<init>()void
		// @188: putfield game.C_100326_ic game.C_100218_am.field_102533_B
		// @18B: aload_0
		// @18C: getfield game.C_100078_ul game.C_100053_vn.field_102829_eb
		// @18F: new game.C_100114_q
		// @192: dup
		// @193: ldc 10000536 (0x989898)
		// @195: invokespecial game.C_100114_q.<init>(int)void
		// @198: putfield game.C_100326_ic game.C_100078_ul.field_102533_B
		// @19B: aload_0
		// @19C: getfield game.C_100078_ul game.C_100053_vn.field_102838_P
		// @19F: aload_0
		// @1A0: getfield game.C_100078_ul game.C_100053_vn.field_102836_V
		// @1A3: new game.C_100114_q
		// @1A6: dup
		// @1A7: ldc 10000536 (0x989898)
		// @1A9: invokespecial game.C_100114_q.<init>(int)void
		// @1AC: dup_x1
		// @1AD: putfield game.C_100326_ic game.C_100078_ul.field_102533_B
		// @1B0: putfield game.C_100326_ic game.C_100078_ul.field_102533_B
		// @1B3: aload_0
		// @1B4: getfield game.C_100078_ul game.C_100053_vn.field_102828_hb
		// @1B7: new game.C_100114_q
		// @1BA: dup
		// @1BB: ldc 10000536 (0x989898)
		// @1BD: invokespecial game.C_100114_q.<init>(int)void
		// @1C0: putfield game.C_100326_ic game.C_100078_ul.field_102533_B
		// @1C3: aload_0
		// @1C4: getfield game.C_100036_gg game.C_100053_vn.field_102826_db
		// @1C7: new game.C_100108_ee
		// @1CA: dup
		// @1CB: invokespecial game.C_100108_ee.<init>()void
		// @1CE: putfield game.C_100326_ic game.C_100036_gg.field_102533_B
		// @1D1: aload_0
		// @1D2: getfield game.C_100078_ul game.C_100053_vn.field_102841_ab
		// @1D5: aload_0
		// @1D6: getfield game.C_100078_ul game.C_100053_vn.field_102844_X
		// @1D9: new game.C_100012_fh
		// @1DC: dup
		// @1DD: ldc 10000536 (0x989898)
		// @1DF: invokespecial game.C_100012_fh.<init>(int)void
		// @1E2: dup_x1
		// @1E3: putfield game.C_100326_ic game.C_100078_ul.field_102533_B
		// @1E6: putfield game.C_100326_ic game.C_100078_ul.field_102533_B
		// @1E9: sipush -30945 (0x871F)
		// @1EC: iconst_2
		// @1ED: anewarray java.lang.String
		// @1F0: dup
		// @1F1: iconst_0
		// @1F2: aload_0
		// @1F3: bipush -37 (0xDB)
		// @1F5: invokespecial game.C_100053_vn.func_102815_g(byte)java.lang.String
		// @1F8: aastore
		// @1F9: dup
		// @1FA: iconst_1
		// @1FB: aload_0
		// @1FC: bipush -99 (0x9D)
		// @1FE: invokespecial game.C_100053_vn.func_102821_f(byte)java.lang.String
		// @201: aastore
		// @202: getstatic java.lang.String game.C_100009_fg.field_103658_c
		// @205: invokestatic game.C_100132_td.func_104965_a(int, java.lang.String[], java.lang.String)java.lang.String
		// @208: astore_2
		// @209: bipush 20 (0x14)
		// @20B: istore_3
		// @20C: iload_3
		// @20D: aload_0
		// @20E: getstatic java.lang.String game.C_100009_fg.field_103653_f
		// @211: bipush -84 (0xAC)
		// @213: iload_3
		// @214: sipush 170 (0x00AA)
		// @217: aload_0
		// @218: getfield game.C_100078_ul game.C_100053_vn.field_102838_P
		// @21B: invokespecial game.C_100053_vn.func_102814_a(java.lang.String, int, int, int, game.C_100336_im)int
		// @21E: iadd
		// @21F: istore_3
		// @220: iload_3
		// @221: aload_0
		// @222: sipush 19996 (0x4E1C)
		// @225: ldc ""
		// @227: aload_0
		// @228: getfield game.C_100078_ul game.C_100053_vn.field_102836_V
		// @22B: bipush 20 (0x14)
		// @22D: sipush 170 (0x00AA)
		// @230: getstatic java.lang.String game.C_100297_kf.field_101237_p
		// @233: iload_3
		// @234: invokespecial game.C_100053_vn.func_102819_a(int, java.lang.String, game.C_100336_im, int, int, java.lang.String, int)int
		// @237: bipush -5 (0xFB)
		// @239: isub
		// @23A: iadd
		// @23B: istore_3
		// @23C: iload_3
		// @23D: aload_0
		// @23E: getstatic java.lang.String game.C_100003_ga.field_103531_j
		// @241: bipush -77 (0xB3)
		// @243: iload_3
		// @244: sipush 170 (0x00AA)
		// @247: aload_0
		// @248: getfield game.C_100078_ul game.C_100053_vn.field_102841_ab
		// @24B: invokespecial game.C_100053_vn.func_102814_a(java.lang.String, int, int, int, game.C_100336_im)int
		// @24E: iadd
		// @24F: istore_3
		// @250: iload_3
		// @251: iconst_5
		// @252: aload_0
		// @253: getstatic java.lang.String game.C_100339_jb.field_107383_b
		// @256: sipush -3554 (0xF21E)
		// @259: getstatic java.lang.String game.C_100015_wh.field_103794_i
		// @25C: iload_3
		// @25D: sipush 170 (0x00AA)
		// @260: aload_0
		// @261: getfield game.C_100078_ul game.C_100053_vn.field_102844_X
		// @264: invokespecial game.C_100053_vn.func_102817_a(java.lang.String, int, java.lang.String, int, int, game.C_100336_im)int
		// @267: iadd
		// @268: iadd
		// @269: istore_3
		// @26A: iload_3
		// @26B: iconst_5
		// @26C: aload_0
		// @26D: getstatic java.lang.String game.C_100315_la.field_107180_a
		// @270: sipush -3554 (0xF21E)
		// @273: getstatic java.lang.String game.C_100218_am.field_103118_I
		// @276: iload_3
		// @277: sipush 170 (0x00AA)
		// @27A: aload_0
		// @27B: getfield game.C_100078_ul game.C_100053_vn.field_102829_eb
		// @27E: invokespecial game.C_100053_vn.func_102817_a(java.lang.String, int, java.lang.String, int, int, game.C_100336_im)int
		// @281: iadd
		// @282: iadd
		// @283: istore_3
		// @284: iload_3
		// @285: aload_0
		// @286: sipush 170 (0x00AA)
		// @289: aload_0
		// @28A: getfield game.C_100078_ul game.C_100053_vn.field_102828_hb
		// @28D: iload_3
		// @28E: sipush -6781 (0xE583)
		// @291: getstatic java.lang.String game.C_100142_bk.field_105085_g
		// @294: invokespecial game.C_100053_vn.func_102823_a(int, game.C_100336_im, int, int, java.lang.String)int
		// @297: iadd
		// @298: istore_3
		// @299: new game.C_100271_mj
		// @29C: dup
		// @29D: bipush 46 (0x2E)
		// @29F: iload_3
		// @2A0: aload_0
		// @2A1: getfield int game.C_100053_vn.field_102537_l
		// @2A4: bipush -90 (0xA6)
		// @2A6: iadd
		// @2A7: bipush 25 (0x19)
		// @2A9: aload_0
		// @2AA: getfield game.C_100036_gg game.C_100053_vn.field_102826_db
		// @2AD: iconst_1
		// @2AE: bipush -120 (0x88)
		// @2B0: aload_0
		// @2B1: getfield int game.C_100053_vn.field_102537_l
		// @2B4: iadd
		// @2B5: iconst_5
		// @2B6: getstatic game.C_100112_r game.C_100318_hj.field_107198_b
		// @2B9: ldc 11579568 (0xb0b0b0)
		// @2BB: getstatic java.lang.String game.C_100212_qc.field_105977_c
		// @2BE: invokespecial game.C_100271_mj.<init>(int, int, int, int, game.C_100336_im, boolean, int, int, game.C_100112_r, int, java.lang.String)void
		// @2C1: astore #4
		// @2C3: aload_0
		// @2C4: aload #4
		// @2C6: iconst_1
		// @2C7: invokevirtual game.C_100053_vn.func_102561_b(game.C_100336_im, int)void
		// @2CA: iload_3
		// @2CB: aload #4
		// @2CD: getfield int game.C_100271_mj.field_102544_t
		// @2D0: iadd
		// @2D1: istore_3
		// @2D2: new game.C_100256_pk
		// @2D5: dup
		// @2D6: getstatic game.C_100112_r game.C_100230_of.field_106205_g
		// @2D9: iconst_0
		// @2DA: iconst_0
		// @2DB: iconst_0
		// @2DC: iconst_0
		// @2DD: ldc 16777215 (0xffffff)
		// @2DF: iconst_m1
		// @2E0: iconst_0
		// @2E1: iconst_0
		// @2E2: getstatic game.C_100112_r game.C_100230_of.field_106205_g
		// @2E5: getfield int game.C_100112_r.field_101772_Q
		// @2E8: iconst_m1
		// @2E9: ldc 2147483647 (0x7fffffff)
		// @2EB: iconst_1
		// @2EC: invokespecial game.C_100256_pk.<init>(game.C_100112_r, int, int, int, int, int, int, int, int, int, int, int, boolean)void
		// @2EF: astore #5
		// @2F1: aload_0
		// @2F2: new game.C_100083_c
		// @2F5: dup
		// @2F6: aload_2
		// @2F7: aload #5
		// @2F9: invokespecial game.C_100083_c.<init>(java.lang.String, game.C_100326_ic)void
		// @2FC: putfield game.C_100083_c game.C_100053_vn.field_102835_W
		// @2FF: aload_0
		// @300: getfield game.C_100083_c game.C_100053_vn.field_102835_W
		// @303: ldc ""
		// @305: putfield java.lang.String game.C_100083_c.field_102536_o
		// @308: aload_0
		// @309: getfield game.C_100083_c game.C_100053_vn.field_102835_W
		// @30C: getstatic java.lang.String game.C_100245_pf.field_106394_h
		// @30F: bipush 125 (0x7D)
		// @311: iconst_0
		// @312: invokevirtual game.C_100083_c.func_103158_a(java.lang.String, int, int)void
		// @315: aload_0
		// @316: getfield game.C_100083_c game.C_100053_vn.field_102835_W
		// @319: getstatic java.lang.String game.C_100245_pf.field_106394_h
		// @31C: bipush 59 (0x3B)
		// @31E: iconst_1
		// @31F: invokevirtual game.C_100083_c.func_103158_a(java.lang.String, int, int)void
		// @322: aload_0
		// @323: getfield game.C_100083_c game.C_100053_vn.field_102835_W
		// @326: aload_0
		// @327: putfield game.C_100337_in game.C_100083_c.field_102543_u
		// @32A: aload_0
		// @32B: getfield game.C_100083_c game.C_100053_vn.field_102835_W
		// @32E: bipush -90 (0xA6)
		// @330: aload_0
		// @331: getfield int game.C_100053_vn.field_102537_l
		// @334: iadd
		// @335: bipush 46 (0x2E)
		// @337: iload_3
		// @338: iconst_m1
		// @339: invokevirtual game.C_100083_c.func_103157_b(int, int, int, int)void
		// @33C: iload_3
		// @33D: bipush 15 (0x0F)
		// @33F: aload_0
		// @340: getfield game.C_100083_c game.C_100053_vn.field_102835_W
		// @343: getfield int game.C_100083_c.field_102544_t
		// @346: iadd
		// @347: iadd
		// @348: istore_3
		// @349: aload_0
		// @34A: aload_0
		// @34B: getfield game.C_100083_c game.C_100053_vn.field_102835_W
		// @34E: iconst_1
		// @34F: invokevirtual game.C_100053_vn.func_102561_b(game.C_100336_im, int)void
		// @352: iconst_4
		// @353: istore #6
		// @355: sipush 200 (0x00C8)
		// @358: istore #7
		// @35A: aload_0
		// @35B: getfield game.C_100218_am game.C_100053_vn.field_102843_bb
		// @35E: bipush 40 (0x28)
		// @360: iload_3
		// @361: iload #7
		// @363: ineg
		// @364: sipush 496 (0x01F0)
		// @367: iadd
		// @368: ldc -1937568415 (0x8c830d61)
		// @36A: ishr
		// @36B: iload #7
		// @36D: bipush 121 (0x79)
		// @36F: invokevirtual game.C_100218_am.func_102524_a(int, int, int, int, byte)void
		// @372: aload_0
		// @373: getfield game.C_100218_am game.C_100053_vn.field_102831_gb
		// @376: bipush 40 (0x28)
		// @378: bipush 15 (0x0F)
		// @37A: iload_3
		// @37B: iadd
		// @37C: iconst_3
		// @37D: iload #6
		// @37F: iadd
		// @380: bipush 60 (0x3C)
		// @382: bipush 54 (0x36)
		// @384: invokevirtual game.C_100218_am.func_102524_a(int, int, int, int, byte)void
		// @387: aload_0
		// @388: getfield game.C_100218_am game.C_100053_vn.field_102831_gb
		// @38B: aload_0
		// @38C: putfield game.C_100337_in game.C_100218_am.field_102543_u
		// @38F: aload_0
		// @390: getfield game.C_100218_am game.C_100053_vn.field_102843_bb
		// @393: aload_0
		// @394: putfield game.C_100337_in game.C_100218_am.field_102543_u
		// @397: aload_0
		// @398: aload_0
		// @399: getfield game.C_100218_am game.C_100053_vn.field_102843_bb
		// @39C: iconst_1
		// @39D: invokevirtual game.C_100053_vn.func_102561_b(game.C_100336_im, int)void
		// @3A0: aload_0
		// @3A1: aload_0
		// @3A2: getfield game.C_100218_am game.C_100053_vn.field_102831_gb
		// @3A5: iconst_1
		// @3A6: invokevirtual game.C_100053_vn.func_102561_b(game.C_100336_im, int)void
		// @3A9: aload_0
		// @3AA: new game.C_100162_sc
		// @3AD: dup
		// @3AE: aload_0
		// @3AF: invokespecial game.C_100162_sc.<init>(game.C_100276_nb)void
		// @3B2: putfield game.C_100162_sc game.C_100053_vn.field_102839_S
		// @3B5: aload_0
		// @3B6: getfield game.C_100162_sc game.C_100053_vn.field_102839_S
		// @3B9: sipush 150 (0x0096)
		// @3BC: bipush 20 (0x14)
		// @3BE: aload_0
		// @3BF: getfield game.C_100078_ul game.C_100053_vn.field_102829_eb
		// @3C2: getfield int game.C_100078_ul.field_102541_w
		// @3C5: iadd
		// @3C6: bipush 60 (0x3C)
		// @3C8: aload_0
		// @3C9: getfield game.C_100078_ul game.C_100053_vn.field_102829_eb
		// @3CC: getfield int game.C_100078_ul.field_102538_m
		// @3CF: aload_0
		// @3D0: getfield game.C_100078_ul game.C_100053_vn.field_102829_eb
		// @3D3: getfield int game.C_100078_ul.field_102537_l
		// @3D6: ineg
		// @3D7: isub
		// @3D8: iadd
		// @3D9: aload_0
		// @3DA: getfield game.C_100078_ul game.C_100053_vn.field_102829_eb
		// @3DD: getfield int game.C_100078_ul.field_102537_l
		// @3E0: ineg
		// @3E1: aload_0
		// @3E2: getfield int game.C_100053_vn.field_102537_l
		// @3E5: aload_0
		// @3E6: getfield game.C_100078_ul game.C_100053_vn.field_102829_eb
		// @3E9: getfield int game.C_100078_ul.field_102538_m
		// @3EC: bipush -60 (0xC4)
		// @3EE: isub
		// @3EF: isub
		// @3F0: iadd
		// @3F1: bipush -63 (0xC1)
		// @3F3: invokevirtual game.C_100162_sc.func_102524_a(int, int, int, int, byte)void
		// @3F6: aload_0
		// @3F7: aload_0
		// @3F8: getfield game.C_100162_sc game.C_100053_vn.field_102839_S
		// @3FB: iconst_1
		// @3FC: invokevirtual game.C_100053_vn.func_102561_b(game.C_100336_im, int)void
		// @3FF: aload_0
		// @400: bipush 55 (0x37)
		// @402: iload_3
		// @403: iadd
		// @404: iload #6
		// @406: ineg
		// @407: isub
		// @408: iconst_0
		// @409: iconst_0
		// @40A: sipush 496 (0x01F0)
		// @40D: bipush -95 (0xA1)
		// @40F: invokevirtual game.C_100053_vn.func_102524_a(int, int, int, int, byte)void
		// @412: goto @421
		// @415: astore_1
		// @416: aload_1
		// @417: getstatic java.lang.String[] game.C_100053_vn.field_102834_ib
		// @41A: bipush 20 (0x14)
		// @41C: aaload
		// @41D: invokestatic game.C_100181_cf.func_105695_a(java.lang.Throwable, java.lang.String)game.C_100170_cm
		// @420: athrow
		// @421: return
	}
	
	static final void func_102818_a(int arg0, int arg1, boolean arg2)
	{
		// @000: getstatic int game.SteelSentinels.field_105275_O
		// @003: istore #9
		// @005: iconst_1
		// @006: putstatic boolean game.C_100225_ah.field_106133_i
		// @009: iload_0
		// @00A: putstatic int game.C_100078_ul.field_103285_pb
		// @00D: iconst_0
		// @00E: getstatic int game.C_100078_ul.field_103285_pb
		// @011: if_icmpne @0D1
		// @014: getstatic java.lang.String[] game.C_100227_af.field_106174_i
		// @017: getstatic int game.C_100015_wh.field_103786_a
		// @01A: iconst_0
		// @01B: getstatic java.lang.String game.C_100280_nf.field_101174_r
		// @01E: getstatic game.C_100112_r game.C_100139_tb.field_100536_x
		// @021: invokestatic game.C_100087_n.func_100686_a(java.lang.String[], int, boolean, java.lang.String, game.C_100112_r)int
		// @024: istore_3
		// @025: iconst_3
		// @026: iload_3
		// @027: ineg
		// @028: isub
		// @029: istore #4
		// @02B: iload #4
		// @02D: newarray int[]
		// @02F: putstatic int[] game.C_100197_ra.field_100860_j
		// @032: iload #4
		// @034: anewarray java.lang.String
		// @037: putstatic java.lang.String[] game.C_100217_ao.field_106041_m
		// @03A: iconst_0
		// @03B: istore #5
		// @03D: iload #5
		// @03F: iload #4
		// @041: if_icmpge @05C
		// @044: getstatic int[] game.C_100197_ra.field_100860_j
		// @047: iload #5
		// @049: iconst_m1
		// @04A: iastore
		// @04B: iinc #5 +1
		// @04E: iload #9
		// @050: ifne @062
		// @053: iload #9
		// @055: ifeq @03D
		// @058: goto @05C
		// @05B: athrow
		// @05C: iconst_2
		// @05D: newarray int[]
		// @05F: putstatic int[] game.C_100064_ve.field_103014_w
		// @062: iconst_0
		// @063: istore #5
		// @065: iload_3
		// @066: iconst_m1
		// @067: ixor
		// @068: iload #5
		// @06A: iconst_m1
		// @06B: ixor
		// @06C: if_icmpge @08C
		// @06F: getstatic java.lang.String[] game.C_100217_ao.field_106041_m
		// @072: iload #5
		// @074: getstatic java.lang.String[] game.C_100227_af.field_106174_i
		// @077: iload #5
		// @079: aaload
		// @07A: aastore
		// @07B: iinc #5 +1
		// @07E: iload #9
		// @080: ifne @0CC
		// @083: iload #9
		// @085: ifeq @065
		// @088: goto @08C
		// @08B: athrow
		// @08C: getstatic java.lang.String[] game.C_100217_ao.field_106041_m
		// @08F: iload #4
		// @091: iconst_3
		// @092: isub
		// @093: ldc ""
		// @095: aastore
		// @096: getstatic java.lang.String[] game.C_100217_ao.field_106041_m
		// @099: bipush -2 (0xFE)
		// @09B: iload #4
		// @09D: iadd
		// @09E: getstatic java.lang.String game.C_100198_qn.field_105836_a
		// @0A1: aastore
		// @0A2: getstatic int[] game.C_100197_ra.field_100860_j
		// @0A5: bipush -2 (0xFE)
		// @0A7: iload #4
		// @0A9: iadd
		// @0AA: iconst_0
		// @0AB: iastore
		// @0AC: getstatic int[] game.C_100064_ve.field_103014_w
		// @0AF: iconst_0
		// @0B0: iconst_4
		// @0B1: iastore
		// @0B2: getstatic java.lang.String[] game.C_100217_ao.field_106041_m
		// @0B5: iload #4
		// @0B7: iconst_1
		// @0B8: isub
		// @0B9: getstatic java.lang.String game.C_100180_ce.field_104807_v
		// @0BC: aastore
		// @0BD: getstatic int[] game.C_100197_ra.field_100860_j
		// @0C0: iload #4
		// @0C2: iconst_m1
		// @0C3: iadd
		// @0C4: iconst_1
		// @0C5: iastore
		// @0C6: getstatic int[] game.C_100064_ve.field_103014_w
		// @0C9: iconst_1
		// @0CA: iconst_5
		// @0CB: iastore
		// @0CC: iload #9
		// @0CE: ifeq @697
		// @0D1: getstatic int game.C_100078_ul.field_103285_pb
		// @0D4: iconst_1
		// @0D5: if_icmpeq @5FF
		// @0D8: goto @0DC
		// @0DB: athrow
		// @0DC: iconst_2
		// @0DD: getstatic int game.C_100078_ul.field_103285_pb
		// @0E0: if_icmpeq @33B
		// @0E3: goto @0E7
		// @0E6: athrow
		// @0E7: getstatic int game.C_100078_ul.field_103285_pb
		// @0EA: iconst_m1
		// @0EB: ixor
		// @0EC: bipush -4 (0xFC)
		// @0EE: if_icmpne @1BD
		// @0F1: goto @0F5
		// @0F4: athrow
		// @0F5: getstatic game.C_100201_qj game.C_100178_cg.field_105692_a
		// @0F8: getfield boolean game.C_100201_qj.field_105881_j
		// @0FB: ifne @118
		// @0FE: goto @102
		// @101: athrow
		// @102: getstatic java.lang.String[] game.C_100227_af.field_106174_i
		// @105: getstatic int game.C_100015_wh.field_103786_a
		// @108: iconst_0
		// @109: getstatic java.lang.String game.C_100188_rj.field_105740_a
		// @10C: getstatic game.C_100112_r game.C_100139_tb.field_100536_x
		// @10F: invokestatic game.C_100087_n.func_100686_a(java.lang.String[], int, boolean, java.lang.String, game.C_100112_r)int
		// @112: istore_3
		// @113: iload #9
		// @115: ifeq @129
		// @118: getstatic java.lang.String[] game.C_100227_af.field_106174_i
		// @11B: getstatic int game.C_100015_wh.field_103786_a
		// @11E: iconst_0
		// @11F: getstatic java.lang.String game.C_100021_wn.field_103872_c
		// @122: getstatic game.C_100112_r game.C_100139_tb.field_100536_x
		// @125: invokestatic game.C_100087_n.func_100686_a(java.lang.String[], int, boolean, java.lang.String, game.C_100112_r)int
		// @128: istore_3
		// @129: iload_3
		// @12A: iconst_2
		// @12B: iadd
		// @12C: istore #4
		// @12E: iload #4
		// @130: newarray int[]
		// @132: putstatic int[] game.C_100197_ra.field_100860_j
		// @135: iload #4
		// @137: anewarray java.lang.String
		// @13A: putstatic java.lang.String[] game.C_100217_ao.field_106041_m
		// @13D: iconst_0
		// @13E: istore #5
		// @140: iload #4
		// @142: iconst_m1
		// @143: ixor
		// @144: iload #5
		// @146: iconst_m1
		// @147: ixor
		// @148: if_icmpge @163
		// @14B: getstatic int[] game.C_100197_ra.field_100860_j
		// @14E: iload #5
		// @150: iconst_m1
		// @151: iastore
		// @152: iinc #5 +1
		// @155: iload #9
		// @157: ifne @169
		// @15A: iload #9
		// @15C: ifeq @140
		// @15F: goto @163
		// @162: athrow
		// @163: iconst_1
		// @164: newarray int[]
		// @166: putstatic int[] game.C_100064_ve.field_103014_w
		// @169: iconst_0
		// @16A: istore #5
		// @16C: iload_3
		// @16D: iconst_m1
		// @16E: ixor
		// @16F: iload #5
		// @171: iconst_m1
		// @172: ixor
		// @173: if_icmpge @193
		// @176: getstatic java.lang.String[] game.C_100217_ao.field_106041_m
		// @179: iload #5
		// @17B: getstatic java.lang.String[] game.C_100227_af.field_106174_i
		// @17E: iload #5
		// @180: aaload
		// @181: aastore
		// @182: iinc #5 +1
		// @185: iload #9
		// @187: ifne @1B8
		// @18A: iload #9
		// @18C: ifeq @16C
		// @18F: goto @193
		// @192: athrow
		// @193: getstatic java.lang.String[] game.C_100217_ao.field_106041_m
		// @196: bipush -2 (0xFE)
		// @198: iload #4
		// @19A: iadd
		// @19B: ldc ""
		// @19D: aastore
		// @19E: getstatic java.lang.String[] game.C_100217_ao.field_106041_m
		// @1A1: iload #4
		// @1A3: iconst_1
		// @1A4: isub
		// @1A5: getstatic java.lang.String game.C_100180_ce.field_104807_v
		// @1A8: aastore
		// @1A9: getstatic int[] game.C_100197_ra.field_100860_j
		// @1AC: iload #4
		// @1AE: iconst_m1
		// @1AF: iadd
		// @1B0: iconst_0
		// @1B1: iastore
		// @1B2: getstatic int[] game.C_100064_ve.field_103014_w
		// @1B5: iconst_0
		// @1B6: iconst_5
		// @1B7: iastore
		// @1B8: iload #9
		// @1BA: ifeq @697
		// @1BD: bipush -5 (0xFB)
		// @1BF: getstatic int game.C_100078_ul.field_103285_pb
		// @1C2: iconst_m1
		// @1C3: ixor
		// @1C4: if_icmpeq @29E
		// @1C7: goto @1CB
		// @1CA: athrow
		// @1CB: getstatic int game.C_100078_ul.field_103285_pb
		// @1CE: iconst_m1
		// @1CF: ixor
		// @1D0: bipush -6 (0xFA)
		// @1D2: if_icmpeq @1E2
		// @1D5: goto @1D9
		// @1D8: athrow
		// @1D9: new java.lang.IllegalArgumentException
		// @1DC: dup
		// @1DD: invokespecial java.lang.IllegalArgumentException.<init>()void
		// @1E0: athrow
		// @1E1: athrow
		// @1E2: getstatic java.lang.String[] game.C_100227_af.field_106174_i
		// @1E5: getstatic int game.C_100015_wh.field_103786_a
		// @1E8: iconst_0
		// @1E9: getstatic java.lang.String game.C_100192_rf.field_101677_F
		// @1EC: getstatic game.C_100112_r game.C_100139_tb.field_100536_x
		// @1EF: invokestatic game.C_100087_n.func_100686_a(java.lang.String[], int, boolean, java.lang.String, game.C_100112_r)int
		// @1F2: istore_3
		// @1F3: iconst_3
		// @1F4: iload_3
		// @1F5: iadd
		// @1F6: istore #4
		// @1F8: iload #4
		// @1FA: anewarray java.lang.String
		// @1FD: putstatic java.lang.String[] game.C_100217_ao.field_106041_m
		// @200: iload #4
		// @202: newarray int[]
		// @204: putstatic int[] game.C_100197_ra.field_100860_j
		// @207: iconst_0
		// @208: istore #5
		// @20A: iload #4
		// @20C: iconst_m1
		// @20D: ixor
		// @20E: iload #5
		// @210: iconst_m1
		// @211: ixor
		// @212: if_icmpge @22D
		// @215: getstatic int[] game.C_100197_ra.field_100860_j
		// @218: iload #5
		// @21A: iconst_m1
		// @21B: iastore
		// @21C: iinc #5 +1
		// @21F: iload #9
		// @221: ifne @233
		// @224: iload #9
		// @226: ifeq @20A
		// @229: goto @22D
		// @22C: athrow
		// @22D: iconst_2
		// @22E: newarray int[]
		// @230: putstatic int[] game.C_100064_ve.field_103014_w
		// @233: iconst_0
		// @234: istore #5
		// @236: iload_3
		// @237: iload #5
		// @239: if_icmple @259
		// @23C: getstatic java.lang.String[] game.C_100217_ao.field_106041_m
		// @23F: iload #5
		// @241: getstatic java.lang.String[] game.C_100227_af.field_106174_i
		// @244: iload #5
		// @246: aaload
		// @247: aastore
		// @248: iinc #5 +1
		// @24B: iload #9
		// @24D: ifne @299
		// @250: iload #9
		// @252: ifeq @236
		// @255: goto @259
		// @258: athrow
		// @259: getstatic java.lang.String[] game.C_100217_ao.field_106041_m
		// @25C: bipush -3 (0xFD)
		// @25E: iload #4
		// @260: iadd
		// @261: ldc ""
		// @263: aastore
		// @264: getstatic java.lang.String[] game.C_100217_ao.field_106041_m
		// @267: iload #4
		// @269: iconst_2
		// @26A: isub
		// @26B: getstatic java.lang.String game.C_100252_pn.field_105514_q
		// @26E: aastore
		// @26F: getstatic int[] game.C_100197_ra.field_100860_j
		// @272: iload #4
		// @274: bipush -2 (0xFE)
		// @276: iadd
		// @277: iconst_0
		// @278: iastore
		// @279: getstatic int[] game.C_100064_ve.field_103014_w
		// @27C: iconst_0
		// @27D: iconst_3
		// @27E: iastore
		// @27F: getstatic java.lang.String[] game.C_100217_ao.field_106041_m
		// @282: iconst_m1
		// @283: iload #4
		// @285: iadd
		// @286: getstatic java.lang.String game.C_100180_ce.field_104807_v
		// @289: aastore
		// @28A: getstatic int[] game.C_100197_ra.field_100860_j
		// @28D: iload #4
		// @28F: iconst_1
		// @290: isub
		// @291: iconst_1
		// @292: iastore
		// @293: getstatic int[] game.C_100064_ve.field_103014_w
		// @296: iconst_1
		// @297: iconst_5
		// @298: iastore
		// @299: iload #9
		// @29B: ifeq @697
		// @29E: getstatic java.lang.String[] game.C_100227_af.field_106174_i
		// @2A1: getstatic int game.C_100015_wh.field_103786_a
		// @2A4: iconst_0
		// @2A5: getstatic java.lang.String game.C_100049_vf.field_104217_r
		// @2A8: getstatic game.C_100112_r game.C_100139_tb.field_100536_x
		// @2AB: invokestatic game.C_100087_n.func_100686_a(java.lang.String[], int, boolean, java.lang.String, game.C_100112_r)int
		// @2AE: istore_3
		// @2AF: iload_3
		// @2B0: iconst_2
		// @2B1: iadd
		// @2B2: istore #4
		// @2B4: iload #4
		// @2B6: anewarray java.lang.String
		// @2B9: putstatic java.lang.String[] game.C_100217_ao.field_106041_m
		// @2BC: iload #4
		// @2BE: newarray int[]
		// @2C0: putstatic int[] game.C_100197_ra.field_100860_j
		// @2C3: iconst_0
		// @2C4: istore #5
		// @2C6: iload #5
		// @2C8: iload #4
		// @2CA: if_icmpge @2E5
		// @2CD: getstatic int[] game.C_100197_ra.field_100860_j
		// @2D0: iload #5
		// @2D2: iconst_m1
		// @2D3: iastore
		// @2D4: iinc #5 +1
		// @2D7: iload #9
		// @2D9: ifne @2EB
		// @2DC: iload #9
		// @2DE: ifeq @2C6
		// @2E1: goto @2E5
		// @2E4: athrow
		// @2E5: iconst_1
		// @2E6: newarray int[]
		// @2E8: putstatic int[] game.C_100064_ve.field_103014_w
		// @2EB: iconst_0
		// @2EC: istore #5
		// @2EE: iload #5
		// @2F0: iload_3
		// @2F1: if_icmpge @311
		// @2F4: getstatic java.lang.String[] game.C_100217_ao.field_106041_m
		// @2F7: iload #5
		// @2F9: getstatic java.lang.String[] game.C_100227_af.field_106174_i
		// @2FC: iload #5
		// @2FE: aaload
		// @2FF: aastore
		// @300: iinc #5 +1
		// @303: iload #9
		// @305: ifne @336
		// @308: iload #9
		// @30A: ifeq @2EE
		// @30D: goto @311
		// @310: athrow
		// @311: getstatic java.lang.String[] game.C_100217_ao.field_106041_m
		// @314: iload #4
		// @316: bipush -2 (0xFE)
		// @318: iadd
		// @319: ldc ""
		// @31B: aastore
		// @31C: getstatic java.lang.String[] game.C_100217_ao.field_106041_m
		// @31F: iconst_m1
		// @320: iload #4
		// @322: iadd
		// @323: getstatic java.lang.String game.C_100180_ce.field_104807_v
		// @326: aastore
		// @327: getstatic int[] game.C_100197_ra.field_100860_j
		// @32A: iload #4
		// @32C: iconst_m1
		// @32D: iadd
		// @32E: iconst_0
		// @32F: iastore
		// @330: getstatic int[] game.C_100064_ve.field_103014_w
		// @333: iconst_0
		// @334: iconst_5
		// @335: iastore
		// @336: iload #9
		// @338: ifeq @697
		// @33B: getstatic java.lang.String[] game.C_100227_af.field_106174_i
		// @33E: getstatic int game.C_100015_wh.field_103786_a
		// @341: iconst_0
		// @342: iload_1
		// @343: sipush -30946 (0x871E)
		// @346: ixor
		// @347: iconst_1
		// @348: anewarray java.lang.String
		// @34B: dup
		// @34C: iconst_0
		// @34D: getstatic java.lang.String[] game.C_100053_vn.field_102834_ib
		// @350: bipush 6 (0x06)
		// @352: aaload
		// @353: aastore
		// @354: getstatic java.lang.String game.C_100024_hd.field_102998_t
		// @357: invokestatic game.C_100132_td.func_104965_a(int, java.lang.String[], java.lang.String)java.lang.String
		// @35A: getstatic game.C_100112_r game.C_100139_tb.field_100536_x
		// @35D: invokestatic game.C_100087_n.func_100686_a(java.lang.String[], int, boolean, java.lang.String, game.C_100112_r)int
		// @360: istore_3
		// @361: iconst_m1
		// @362: istore #4
		// @364: iconst_0
		// @365: istore #5
		// @367: iload #5
		// @369: iload_3
		// @36A: if_icmpge @39F
		// @36D: getstatic java.lang.String[] game.C_100053_vn.field_102834_ib
		// @370: iconst_5
		// @371: aaload
		// @372: getstatic java.lang.String[] game.C_100227_af.field_106174_i
		// @375: iload #5
		// @377: aaload
		// @378: invokevirtual java.lang.String.equals(java.lang.Object)boolean
		// @37B: iload #9
		// @37D: ifne @3A1
		// @380: ifne @38A
		// @383: goto @387
		// @386: athrow
		// @387: goto @393
		// @38A: iload #5
		// @38C: istore #4
		// @38E: iload #9
		// @390: ifeq @39F
		// @393: iinc #5 +1
		// @396: iload #9
		// @398: ifeq @367
		// @39B: goto @39F
		// @39E: athrow
		// @39F: iload #4
		// @3A1: iconst_m1
		// @3A2: if_icmpeq @3A9
		// @3A5: goto @3B1
		// @3A8: athrow
		// @3A9: new java.lang.IllegalStateException
		// @3AC: dup
		// @3AD: invokespecial java.lang.IllegalStateException.<init>()void
		// @3B0: athrow
		// @3B1: iload #4
		// @3B3: anewarray java.lang.String
		// @3B6: putstatic java.lang.String[] game.C_100264_mg.field_106519_g
		// @3B9: getstatic java.lang.String[] game.C_100227_af.field_106174_i
		// @3BC: iconst_0
		// @3BD: getstatic java.lang.String[] game.C_100264_mg.field_106519_g
		// @3C0: iconst_0
		// @3C1: iload #4
		// @3C3: invokestatic game.C_100120_en.func_104912_a(java.lang.Object[], int, java.lang.Object[], int, int)void
		// @3C6: iconst_m1
		// @3C7: iload #4
		// @3C9: ineg
		// @3CA: iadd
		// @3CB: iload_3
		// @3CC: iadd
		// @3CD: anewarray java.lang.String
		// @3D0: putstatic java.lang.String[] game.C_100080_b.field_104433_e
		// @3D3: getstatic java.lang.String[] game.C_100227_af.field_106174_i
		// @3D6: iload #4
		// @3D8: iconst_m1
		// @3D9: isub
		// @3DA: getstatic java.lang.String[] game.C_100080_b.field_104433_e
		// @3DD: iconst_0
		// @3DE: iconst_m1
		// @3DF: iload #4
		// @3E1: ineg
		// @3E2: iload_3
		// @3E3: iadd
		// @3E4: iadd
		// @3E5: invokestatic game.C_100120_en.func_104912_a(java.lang.Object[], int, java.lang.Object[], int, int)void
		// @3E8: getstatic java.lang.String[] game.C_100227_af.field_106174_i
		// @3EB: getstatic int game.C_100015_wh.field_103786_a
		// @3EE: iconst_0
		// @3EF: iload_1
		// @3F0: sipush -30946 (0x871E)
		// @3F3: iadd
		// @3F4: iconst_1
		// @3F5: anewarray java.lang.String
		// @3F8: dup
		// @3F9: iconst_0
		// @3FA: getstatic java.lang.String[] game.C_100053_vn.field_102834_ib
		// @3FD: bipush 6 (0x06)
		// @3FF: aaload
		// @400: aastore
		// @401: getstatic java.lang.String game.C_100227_af.field_106171_j
		// @404: invokestatic game.C_100132_td.func_104965_a(int, java.lang.String[], java.lang.String)java.lang.String
		// @407: getstatic game.C_100112_r game.C_100139_tb.field_100536_x
		// @40A: invokestatic game.C_100087_n.func_100686_a(java.lang.String[], int, boolean, java.lang.String, game.C_100112_r)int
		// @40D: istore_3
		// @40E: iconst_m1
		// @40F: istore #4
		// @411: iconst_0
		// @412: istore #5
		// @414: iload_3
		// @415: iconst_m1
		// @416: ixor
		// @417: iload #5
		// @419: iconst_m1
		// @41A: ixor
		// @41B: if_icmpge @450
		// @41E: getstatic java.lang.String[] game.C_100053_vn.field_102834_ib
		// @421: iconst_5
		// @422: aaload
		// @423: getstatic java.lang.String[] game.C_100227_af.field_106174_i
		// @426: iload #5
		// @428: aaload
		// @429: invokevirtual java.lang.String.equals(java.lang.Object)boolean
		// @42C: iload #9
		// @42E: ifne @454
		// @431: ifne @43B
		// @434: goto @438
		// @437: athrow
		// @438: goto @444
		// @43B: iload #5
		// @43D: istore #4
		// @43F: iload #9
		// @441: ifeq @450
		// @444: iinc #5 +1
		// @447: iload #9
		// @449: ifeq @414
		// @44C: goto @450
		// @44F: athrow
		// @450: iload #4
		// @452: iconst_m1
		// @453: ixor
		// @454: ifeq @45A
		// @457: goto @462
		// @45A: new java.lang.IllegalStateException
		// @45D: dup
		// @45E: invokespecial java.lang.IllegalStateException.<init>()void
		// @461: athrow
		// @462: iload #4
		// @464: anewarray java.lang.String
		// @467: putstatic java.lang.String[] game.C_100341_jd.field_102648_ob
		// @46A: getstatic java.lang.String[] game.C_100227_af.field_106174_i
		// @46D: iconst_0
		// @46E: getstatic java.lang.String[] game.C_100341_jd.field_102648_ob
		// @471: iconst_0
		// @472: iload #4
		// @474: invokestatic game.C_100120_en.func_104912_a(java.lang.Object[], int, java.lang.Object[], int, int)void
		// @477: iconst_m1
		// @478: iload #4
		// @47A: ineg
		// @47B: iadd
		// @47C: iload_3
		// @47D: iadd
		// @47E: anewarray java.lang.String
		// @481: putstatic java.lang.String[] game.C_100342_jg.field_102723_Tb
		// @484: getstatic java.lang.String[] game.C_100227_af.field_106174_i
		// @487: iload #4
		// @489: iconst_m1
		// @48A: isub
		// @48B: getstatic java.lang.String[] game.C_100342_jg.field_102723_Tb
		// @48E: iconst_0
		// @48F: iconst_m1
		// @490: iload #4
		// @492: ineg
		// @493: iload_3
		// @494: iadd
		// @495: iadd
		// @496: invokestatic game.C_100120_en.func_104912_a(java.lang.Object[], int, java.lang.Object[], int, int)void
		// @499: getstatic java.lang.String[] game.C_100341_jd.field_102648_ob
		// @49C: arraylength
		// @49D: getstatic java.lang.String[] game.C_100264_mg.field_106519_g
		// @4A0: arraylength
		// @4A1: if_icmpgt @4AC
		// @4A4: getstatic java.lang.String[] game.C_100264_mg.field_106519_g
		// @4A7: arraylength
		// @4A8: goto @4B0
		// @4AB: athrow
		// @4AC: getstatic java.lang.String[] game.C_100341_jd.field_102648_ob
		// @4AF: arraylength
		// @4B0: istore #5
		// @4B2: getstatic java.lang.String[] game.C_100080_b.field_104433_e
		// @4B5: arraylength
		// @4B6: iconst_m1
		// @4B7: ixor
		// @4B8: getstatic java.lang.String[] game.C_100342_jg.field_102723_Tb
		// @4BB: arraylength
		// @4BC: iconst_m1
		// @4BD: ixor
		// @4BE: if_icmpgt @4C9
		// @4C1: getstatic java.lang.String[] game.C_100080_b.field_104433_e
		// @4C4: arraylength
		// @4C5: goto @4CD
		// @4C8: athrow
		// @4C9: getstatic java.lang.String[] game.C_100342_jg.field_102723_Tb
		// @4CC: arraylength
		// @4CD: istore #6
		// @4CF: iload #6
		// @4D1: iload #5
		// @4D3: iadd
		// @4D4: bipush 7 (0x07)
		// @4D6: iadd
		// @4D7: istore #7
		// @4D9: iload #7
		// @4DB: anewarray java.lang.String
		// @4DE: putstatic java.lang.String[] game.C_100217_ao.field_106041_m
		// @4E1: iload #7
		// @4E3: newarray int[]
		// @4E5: putstatic int[] game.C_100197_ra.field_100860_j
		// @4E8: iconst_0
		// @4E9: istore #8
		// @4EB: iload #8
		// @4ED: iload #7
		// @4EF: if_icmpge @50A
		// @4F2: getstatic int[] game.C_100197_ra.field_100860_j
		// @4F5: iload #8
		// @4F7: iconst_m1
		// @4F8: iastore
		// @4F9: iinc #8 +1
		// @4FC: iload #9
		// @4FE: ifne @557
		// @501: iload #9
		// @503: ifeq @4EB
		// @506: goto @50A
		// @509: athrow
		// @50A: getstatic int[] game.C_100197_ra.field_100860_j
		// @50D: iconst_1
		// @50E: iconst_0
		// @50F: iastore
		// @510: getstatic java.lang.String[] game.C_100217_ao.field_106041_m
		// @513: iconst_1
		// @514: getstatic java.lang.String game.C_100186_rl.field_105722_d
		// @517: aastore
		// @518: iconst_2
		// @519: newarray int[]
		// @51B: putstatic int[] game.C_100064_ve.field_103014_w
		// @51E: getstatic java.lang.String[] game.C_100217_ao.field_106041_m
		// @521: iconst_0
		// @522: getstatic java.lang.String game.C_100113_ek.field_104879_e
		// @525: aastore
		// @526: getstatic int[] game.C_100064_ve.field_103014_w
		// @529: iconst_0
		// @52A: iconst_5
		// @52B: iastore
		// @52C: getstatic java.lang.String[] game.C_100217_ao.field_106041_m
		// @52F: iconst_5
		// @530: ldc ""
		// @532: aastore
		// @533: getstatic java.lang.String[] game.C_100217_ao.field_106041_m
		// @536: iconst_3
		// @537: getstatic java.lang.String game.C_100172_ck.field_102121_bc
		// @53A: aastore
		// @53B: getstatic int[] game.C_100064_ve.field_103014_w
		// @53E: iconst_1
		// @53F: iconst_2
		// @540: iastore
		// @541: getstatic java.lang.String[] game.C_100217_ao.field_106041_m
		// @544: iconst_4
		// @545: getstatic java.lang.String game.C_100041_wf.field_104103_g
		// @548: aastore
		// @549: getstatic int[] game.C_100197_ra.field_100860_j
		// @54C: iconst_3
		// @54D: iconst_1
		// @54E: iastore
		// @54F: getstatic java.lang.String[] game.C_100217_ao.field_106041_m
		// @552: iconst_2
		// @553: getstatic java.lang.String game.C_100104_v.field_104704_p
		// @556: aastore
		// @557: iconst_0
		// @558: istore #8
		// @55A: iload #5
		// @55C: iload #8
		// @55E: if_icmple @5A0
		// @561: getstatic java.lang.String[] game.C_100217_ao.field_106041_m
		// @564: iload #8
		// @566: bipush 6 (0x06)
		// @568: iadd
		// @569: iconst_m1
		// @56A: getstatic java.lang.String[] game.C_100341_jd.field_102648_ob
		// @56D: arraylength
		// @56E: iload #8
		// @570: iadd
		// @571: iload #5
		// @573: isub
		// @574: iconst_m1
		// @575: ixor
		// @576: iload #9
		// @578: ifne @5DA
		// @57B: if_icmplt @595
		// @57E: goto @582
		// @581: athrow
		// @582: getstatic java.lang.String[] game.C_100341_jd.field_102648_ob
		// @585: iload #5
		// @587: ineg
		// @588: iload #8
		// @58A: iadd
		// @58B: getstatic java.lang.String[] game.C_100341_jd.field_102648_ob
		// @58E: arraylength
		// @58F: iadd
		// @590: aaload
		// @591: goto @597
		// @594: athrow
		// @595: ldc ""
		// @597: aastore
		// @598: iinc #8 +1
		// @59B: iload #9
		// @59D: ifeq @55A
		// @5A0: getstatic java.lang.String[] game.C_100217_ao.field_106041_m
		// @5A3: bipush 6 (0x06)
		// @5A5: iload #5
		// @5A7: iadd
		// @5A8: aconst_null
		// @5A9: aastore
		// @5AA: getstatic int[] game.C_100197_ra.field_100860_j
		// @5AD: iload #5
		// @5AF: bipush 6 (0x06)
		// @5B1: iadd
		// @5B2: bipush -2 (0xFE)
		// @5B4: iastore
		// @5B5: iconst_0
		// @5B6: istore #8
		// @5B8: iload #6
		// @5BA: iload #8
		// @5BC: if_icmple @5F2
		// @5BF: getstatic java.lang.String[] game.C_100217_ao.field_106041_m
		// @5C2: bipush 7 (0x07)
		// @5C4: iload #5
		// @5C6: iload #8
		// @5C8: ineg
		// @5C9: isub
		// @5CA: iadd
		// @5CB: iload #9
		// @5CD: ifne @832
		// @5D0: getstatic java.lang.String[] game.C_100342_jg.field_102723_Tb
		// @5D3: arraylength
		// @5D4: iload #8
		// @5D6: goto @5DA
		// @5D9: athrow
		// @5DA: if_icmpgt @5E3
		// @5DD: ldc ""
		// @5DF: goto @5E9
		// @5E2: athrow
		// @5E3: getstatic java.lang.String[] game.C_100342_jg.field_102723_Tb
		// @5E6: iload #8
		// @5E8: aaload
		// @5E9: aastore
		// @5EA: iinc #8 +1
		// @5ED: iload #9
		// @5EF: ifeq @5B8
		// @5F2: bipush 43 (0x2B)
		// @5F4: invokestatic game.C_100198_qn.func_105828_a(byte)long
		// @5F7: putstatic long game.C_100015_wh.field_103780_f
		// @5FA: iload #9
		// @5FC: ifeq @697
		// @5FF: getstatic java.lang.String[] game.C_100227_af.field_106174_i
		// @602: getstatic int game.C_100015_wh.field_103786_a
		// @605: iconst_0
		// @606: getstatic java.lang.String game.C_100280_nf.field_101174_r
		// @609: getstatic game.C_100112_r game.C_100139_tb.field_100536_x
		// @60C: invokestatic game.C_100087_n.func_100686_a(java.lang.String[], int, boolean, java.lang.String, game.C_100112_r)int
		// @60F: istore_3
		// @610: iconst_2
		// @611: iload_3
		// @612: iadd
		// @613: istore #4
		// @615: iload #4
		// @617: newarray int[]
		// @619: putstatic int[] game.C_100197_ra.field_100860_j
		// @61C: iload #4
		// @61E: anewarray java.lang.String
		// @621: putstatic java.lang.String[] game.C_100217_ao.field_106041_m
		// @624: iconst_0
		// @625: istore #5
		// @627: iload #5
		// @629: iload #4
		// @62B: if_icmpge @646
		// @62E: getstatic int[] game.C_100197_ra.field_100860_j
		// @631: iload #5
		// @633: iconst_m1
		// @634: iastore
		// @635: iinc #5 +1
		// @638: iload #9
		// @63A: ifne @64C
		// @63D: iload #9
		// @63F: ifeq @627
		// @642: goto @646
		// @645: athrow
		// @646: iconst_1
		// @647: newarray int[]
		// @649: putstatic int[] game.C_100064_ve.field_103014_w
		// @64C: iconst_0
		// @64D: istore #5
		// @64F: iload_3
		// @650: iload #5
		// @652: if_icmple @672
		// @655: getstatic java.lang.String[] game.C_100217_ao.field_106041_m
		// @658: iload #5
		// @65A: getstatic java.lang.String[] game.C_100227_af.field_106174_i
		// @65D: iload #5
		// @65F: aaload
		// @660: aastore
		// @661: iinc #5 +1
		// @664: iload #9
		// @666: ifne @691
		// @669: iload #9
		// @66B: ifeq @64F
		// @66E: goto @672
		// @671: athrow
		// @672: getstatic java.lang.String[] game.C_100217_ao.field_106041_m
		// @675: bipush -2 (0xFE)
		// @677: iload #4
		// @679: iadd
		// @67A: ldc ""
		// @67C: aastore
		// @67D: getstatic java.lang.String[] game.C_100217_ao.field_106041_m
		// @680: iconst_m1
		// @681: iload #4
		// @683: iadd
		// @684: getstatic java.lang.String game.C_100180_ce.field_104807_v
		// @687: aastore
		// @688: getstatic int[] game.C_100197_ra.field_100860_j
		// @68B: iload #4
		// @68D: iconst_1
		// @68E: isub
		// @68F: iconst_0
		// @690: iastore
		// @691: getstatic int[] game.C_100064_ve.field_103014_w
		// @694: iconst_0
		// @695: iconst_5
		// @696: iastore
		// @697: getstatic game.C_100333_ij game.C_100102_w.field_104631_f
		// @69A: getstatic int[] game.C_100064_ve.field_103014_w
		// @69D: arraylength
		// @69E: putfield int game.C_100333_ij.field_107344_g
		// @6A1: iconst_0
		// @6A2: istore_3
		// @6A3: iconst_0
		// @6A4: istore #4
		// @6A6: iload #4
		// @6A8: iconst_m1
		// @6A9: ixor
		// @6AA: getstatic java.lang.String[] game.C_100217_ao.field_106041_m
		// @6AD: arraylength
		// @6AE: iconst_m1
		// @6AF: ixor
		// @6B0: if_icmple @6E8
		// @6B3: getstatic java.lang.String[] game.C_100217_ao.field_106041_m
		// @6B6: iload #9
		// @6B8: ifne @7E9
		// @6BB: iload #4
		// @6BD: aaload
		// @6BE: getstatic int[] game.C_100197_ra.field_100860_j
		// @6C1: iload #4
		// @6C3: iaload
		// @6C4: iflt @6D0
		// @6C7: goto @6CB
		// @6CA: athrow
		// @6CB: iconst_1
		// @6CC: goto @6D1
		// @6CF: athrow
		// @6D0: iconst_0
		// @6D1: iconst_1
		// @6D2: invokestatic game.C_100294_ki.func_106909_a(java.lang.String, boolean, boolean)int
		// @6D5: istore #5
		// @6D7: iload_3
		// @6D8: iload #5
		// @6DA: if_icmpge @6E0
		// @6DD: iload #5
		// @6DF: istore_3
		// @6E0: iinc #4 +1
		// @6E3: iload #9
		// @6E5: ifeq @6A6
		// @6E8: iconst_2
		// @6E9: getstatic int game.C_100078_ul.field_103285_pb
		// @6EC: if_icmpne @771
		// @6EF: getstatic java.lang.String[] game.C_100264_mg.field_106519_g
		// @6F2: astore #4
		// @6F4: iconst_0
		// @6F5: istore #5
		// @6F7: iload #5
		// @6F9: aload #4
		// @6FB: arraylength
		// @6FC: if_icmpge @72C
		// @6FF: aload #4
		// @701: iload #5
		// @703: aaload
		// @704: astore #6
		// @706: aload #6
		// @708: iconst_0
		// @709: iconst_1
		// @70A: invokestatic game.C_100294_ki.func_106909_a(java.lang.String, boolean, boolean)int
		// @70D: istore #7
		// @70F: iload_3
		// @710: iload #7
		// @712: iload #9
		// @714: ifne @73D
		// @717: if_icmplt @721
		// @71A: goto @71E
		// @71D: athrow
		// @71E: goto @724
		// @721: iload #7
		// @723: istore_3
		// @724: iinc #5 +1
		// @727: iload #9
		// @729: ifeq @6F7
		// @72C: getstatic java.lang.String[] game.C_100080_b.field_104433_e
		// @72F: astore #4
		// @731: iconst_0
		// @732: istore #5
		// @734: iload #5
		// @736: iconst_m1
		// @737: ixor
		// @738: aload #4
		// @73A: arraylength
		// @73B: iconst_m1
		// @73C: ixor
		// @73D: if_icmple @771
		// @740: aload #4
		// @742: iload #5
		// @744: aaload
		// @745: astore #6
		// @747: aload #6
		// @749: iconst_0
		// @74A: iconst_1
		// @74B: invokestatic game.C_100294_ki.func_106909_a(java.lang.String, boolean, boolean)int
		// @74E: istore #7
		// @750: iload #7
		// @752: iconst_m1
		// @753: ixor
		// @754: iload_3
		// @755: iconst_m1
		// @756: ixor
		// @757: iload #9
		// @759: ifne @79B
		// @75C: if_icmplt @766
		// @75F: goto @763
		// @762: athrow
		// @763: goto @769
		// @766: iload #7
		// @768: istore_3
		// @769: iinc #5 +1
		// @76C: iload #9
		// @76E: ifeq @734
		// @771: iload_3
		// @772: ldc -1581399647 (0xa1bdc1a1)
		// @774: ishr
		// @775: ineg
		// @776: getstatic int game.C_100022_hf.field_103894_g
		// @779: iadd
		// @77A: putstatic int game.C_100138_bo.field_100401_f
		// @77D: getstatic game.C_100333_ij game.C_100102_w.field_104631_f
		// @780: getfield int game.C_100333_ij.field_107344_g
		// @783: getstatic int game.C_100085_a.field_102575_J
		// @786: getstatic int game.C_100057_dd.field_104253_f
		// @789: iadd
		// @78A: ldc -17844575 (0xfeefb6a1)
		// @78C: ishl
		// @78D: imul
		// @78E: putstatic int game.C_100301_kb.field_107103_p
		// @791: iload_3
		// @792: ldc -1849395263 (0x91c477c1)
		// @794: ishr
		// @795: ineg
		// @796: iload_3
		// @797: getstatic int game.C_100022_hf.field_103894_g
		// @79A: iadd
		// @79B: iadd
		// @79C: putstatic int game.C_100057_dd.field_104258_c
		// @79F: iconst_0
		// @7A0: istore #4
		// @7A2: iload #4
		// @7A4: getstatic java.lang.String[] game.C_100217_ao.field_106041_m
		// @7A7: arraylength
		// @7A8: if_icmpge @7D7
		// @7AB: getstatic int game.C_100301_kb.field_107103_p
		// @7AE: iconst_0
		// @7AF: getstatic int[] game.C_100197_ra.field_100860_j
		// @7B2: iload #4
		// @7B4: iaload
		// @7B5: iload #9
		// @7B7: ifne @801
		// @7BA: if_icmpgt @7C8
		// @7BD: goto @7C1
		// @7C0: athrow
		// @7C1: getstatic int game.C_100200_ba.field_105850_e
		// @7C4: goto @7CB
		// @7C7: athrow
		// @7C8: getstatic int game.C_100098_h.field_104612_f
		// @7CB: iadd
		// @7CC: putstatic int game.C_100301_kb.field_107103_p
		// @7CF: iinc #4 +1
		// @7D2: iload #9
		// @7D4: ifeq @7A2
		// @7D7: getstatic int game.C_100301_kb.field_107103_p
		// @7DA: ldc_w -92759903 (0xfa7898a1)
		// @7DD: ishr
		// @7DE: ineg
		// @7DF: getstatic int game.C_100316_lc.field_102412_u
		// @7E2: iadd
		// @7E3: putstatic int game.C_100336_im.field_102540_k
		// @7E6: getstatic java.lang.String[] game.C_100217_ao.field_106041_m
		// @7E9: arraylength
		// @7EA: anewarray int[]
		// @7ED: putstatic int[][] game.C_100056_de.field_103192_lb
		// @7F0: iconst_0
		// @7F1: istore #4
		// @7F3: getstatic int game.C_100336_im.field_102540_k
		// @7F6: istore #5
		// @7F8: iload #4
		// @7FA: iconst_m1
		// @7FB: ixor
		// @7FC: getstatic java.lang.String[] game.C_100217_ao.field_106041_m
		// @7FF: arraylength
		// @800: iconst_m1
		// @801: ixor
		// @802: if_icmple @8B3
		// @805: getstatic int[] game.C_100197_ra.field_100860_j
		// @808: iload #4
		// @80A: iaload
		// @80B: istore #6
		// @80D: iconst_0
		// @80E: iload #6
		// @810: iload #9
		// @812: ifne @8B5
		// @815: if_icmple @829
		// @818: goto @81C
		// @81B: athrow
		// @81C: iload #5
		// @81E: getstatic int game.C_100098_h.field_104612_f
		// @821: iadd
		// @822: istore #5
		// @824: iload #9
		// @826: ifeq @8AB
		// @829: getstatic java.lang.String[] game.C_100217_ao.field_106041_m
		// @82C: iload #4
		// @82E: goto @832
		// @831: athrow
		// @832: aaload
		// @833: iconst_1
		// @834: iconst_1
		// @835: invokestatic game.C_100294_ki.func_106909_a(java.lang.String, boolean, boolean)int
		// @838: istore #7
		// @83A: iload #5
		// @83C: getstatic int game.C_100085_a.field_102575_J
		// @83F: iadd
		// @840: istore #5
		// @842: iload #7
		// @844: ldc_w -1886361055 (0x8f906a21)
		// @847: ishr
		// @848: ineg
		// @849: getstatic int game.C_100022_hf.field_103894_g
		// @84C: iadd
		// @84D: istore #8
		// @84F: getstatic int[][] game.C_100056_de.field_103192_lb
		// @852: iload #4
		// @854: iconst_4
		// @855: newarray int[]
		// @857: aastore
		// @858: getstatic int[][] game.C_100056_de.field_103192_lb
		// @85B: iload #4
		// @85D: aaload
		// @85E: iconst_0
		// @85F: getstatic int game.C_100314_lf.field_101381_bb
		// @862: ineg
		// @863: iload #8
		// @865: iadd
		// @866: iastore
		// @867: getstatic int[][] game.C_100056_de.field_103192_lb
		// @86A: iload #4
		// @86C: aaload
		// @86D: iconst_1
		// @86E: iload #5
		// @870: iastore
		// @871: getstatic int[][] game.C_100056_de.field_103192_lb
		// @874: iload #4
		// @876: aaload
		// @877: iconst_2
		// @878: getstatic int game.C_100314_lf.field_101381_bb
		// @87B: ldc_w -1102615423 (0xbe476c81)
		// @87E: ishl
		// @87F: iload #7
		// @881: iadd
		// @882: iastore
		// @883: getstatic int[][] game.C_100056_de.field_103192_lb
		// @886: iload #4
		// @888: aaload
		// @889: iconst_3
		// @88A: getstatic int game.C_100057_dd.field_104253_f
		// @88D: ldc_w -1656093759 (0x9d4a03c1)
		// @890: ishl
		// @891: getstatic int game.C_100200_ba.field_105850_e
		// @894: iadd
		// @895: iastore
		// @896: iload #5
		// @898: getstatic int game.C_100200_ba.field_105850_e
		// @89B: getstatic int game.C_100057_dd.field_104253_f
		// @89E: ldc_w 2088027041 (0x7c74c3a1)
		// @8A1: ishl
		// @8A2: getstatic int game.C_100085_a.field_102575_J
		// @8A5: ineg
		// @8A6: isub
		// @8A7: iadd
		// @8A8: iadd
		// @8A9: istore #5
		// @8AB: iinc #4 +1
		// @8AE: iload #9
		// @8B0: ifeq @7F8
		// @8B3: iload_1
		// @8B4: iconst_1
		// @8B5: if_icmpeq @8C1
		// @8B8: bipush -120 (0x88)
		// @8BA: putstatic int game.C_100053_vn.field_102830_fb
		// @8BD: goto @8C1
		// @8C0: athrow
		// @8C1: getstatic int game.C_100078_ul.field_103285_pb
		// @8C4: iconst_2
		// @8C5: if_icmpne @8DD
		// @8C8: getstatic game.C_100333_ij game.C_100102_w.field_104631_f
		// @8CB: iload_1
		// @8CC: iconst_m1
		// @8CD: iadd
		// @8CE: iconst_m1
		// @8CF: iconst_m1
		// @8D0: iload_2
		// @8D1: invokevirtual game.C_100333_ij.func_107340_a(int, int, int, boolean)void
		// @8D4: iload #9
		// @8D6: ifeq @8F6
		// @8D9: goto @8DD
		// @8DC: athrow
		// @8DD: getstatic game.C_100333_ij game.C_100102_w.field_104631_f
		// @8E0: iconst_0
		// @8E1: sipush 3939 (0x0F63)
		// @8E4: getstatic int game.C_100338_jc.field_105370_l
		// @8E7: getstatic int game.C_100015_wh.field_103781_g
		// @8EA: invokestatic game.C_100077_d.func_103315_b(int, int, int)int
		// @8ED: iconst_0
		// @8EE: iload_2
		// @8EF: invokevirtual game.C_100333_ij.func_107340_a(int, int, int, boolean)void
		// @8F2: goto @8F6
		// @8F5: athrow
		// @8F6: goto @92D
		// @8F9: astore_3
		// @8FA: aload_3
		// @8FB: new java.lang.StringBuilder
		// @8FE: dup
		// @8FF: invokespecial java.lang.StringBuilder.<init>()void
		// @902: getstatic java.lang.String[] game.C_100053_vn.field_102834_ib
		// @905: bipush 7 (0x07)
		// @907: aaload
		// @908: invokevirtual java.lang.StringBuilder.append(java.lang.String)java.lang.StringBuilder
		// @90B: iload_0
		// @90C: invokevirtual java.lang.StringBuilder.append(int)java.lang.StringBuilder
		// @90F: bipush 44 (0x2C)
		// @911: invokevirtual java.lang.StringBuilder.append(char)java.lang.StringBuilder
		// @914: iload_1
		// @915: invokevirtual java.lang.StringBuilder.append(int)java.lang.StringBuilder
		// @918: bipush 44 (0x2C)
		// @91A: invokevirtual java.lang.StringBuilder.append(char)java.lang.StringBuilder
		// @91D: iload_2
		// @91E: invokevirtual java.lang.StringBuilder.append(boolean)java.lang.StringBuilder
		// @921: bipush 41 (0x29)
		// @923: invokevirtual java.lang.StringBuilder.append(char)java.lang.StringBuilder
		// @926: invokevirtual java.lang.StringBuilder.toString()java.lang.String
		// @929: invokestatic game.C_100181_cf.func_105695_a(java.lang.Throwable, java.lang.String)game.C_100170_cm
		// @92C: athrow
		// @92D: return
	}
	
	public final void func_102790_a(byte arg0)
	{
		// @00: iload_1
		// @01: bipush 70 (0x46)
		// @03: if_icmpge @07
		// @06: return
		// @07: aload_0
		// @08: getfield game.C_100078_ul game.C_100053_vn.field_102829_eb
		// @0B: iconst_1
		// @0C: invokevirtual game.C_100078_ul.func_103100_a(boolean)game.C_100308_lh
		// @0F: checkcast game.C_100064_ve
		// @12: iconst_0
		// @13: invokevirtual game.C_100064_ve.func_103006_c(boolean)void
		// @16: goto @3B
		// @19: astore_2
		// @1A: aload_2
		// @1B: new java.lang.StringBuilder
		// @1E: dup
		// @1F: invokespecial java.lang.StringBuilder.<init>()void
		// @22: getstatic java.lang.String[] game.C_100053_vn.field_102834_ib
		// @25: bipush 22 (0x16)
		// @27: aaload
		// @28: invokevirtual java.lang.StringBuilder.append(java.lang.String)java.lang.StringBuilder
		// @2B: iload_1
		// @2C: invokevirtual java.lang.StringBuilder.append(int)java.lang.StringBuilder
		// @2F: bipush 41 (0x29)
		// @31: invokevirtual java.lang.StringBuilder.append(char)java.lang.StringBuilder
		// @34: invokevirtual java.lang.StringBuilder.toString()java.lang.String
		// @37: invokestatic game.C_100181_cf.func_105695_a(java.lang.Throwable, java.lang.String)game.C_100170_cm
		// @3A: athrow
		// @3B: return
	}
	
	static
	{
		// @000: bipush 30 (0x1E)
		// @002: anewarray java.lang.String
		// @005: dup
		// @006: iconst_0
		// @007: ldc "-<)d~s"
		// @009: invokestatic game.C_100053_vn.func_102813_z(java.lang.String)char[]
		// @00C: invokestatic game.C_100053_vn.func_102811_z(char[])java.lang.String
		// @00F: aastore
		// @010: dup
		// @011: iconst_1
		// @012: ldc " |)\u0000B"
		// @014: invokestatic game.C_100053_vn.func_102813_z(java.lang.String)char[]
		// @017: invokestatic game.C_100053_vn.func_102811_z(char[])java.lang.String
		// @01A: aastore
		// @01B: dup
		// @01C: iconst_2
		// @01D: ldc "5'kB"
		// @01F: invokestatic game.C_100053_vn.func_102813_z(java.lang.String)char[]
		// @022: invokestatic game.C_100053_vn.func_102811_z(char[])java.lang.String
		// @025: aastore
		// @026: dup
		// @027: iconst_3
		// @028: ldc "-<)c~s"
		// @02A: invokestatic game.C_100053_vn.func_102813_z(java.lang.String)char[]
		// @02D: invokestatic game.C_100053_vn.func_102811_z(char[])java.lang.String
		// @030: aastore
		// @031: dup
		// @032: iconst_4
		// @033: ldc "-<)i~s"
		// @035: invokestatic game.C_100053_vn.func_102813_z(java.lang.String)char[]
		// @038: invokestatic game.C_100053_vn.func_102811_z(char[])java.lang.String
		// @03B: aastore
		// @03C: dup
		// @03D: iconst_5
		// @03E: ldc "gw7\u0010"
		// @040: invokestatic game.C_100053_vn.func_102813_z(java.lang.String)char[]
		// @043: invokestatic game.C_100053_vn.func_102811_z(char[])java.lang.String
		// @046: aastore
		// @047: dup
		// @048: bipush 6 (0x06)
		// @04A: ldc "g0u\u0010\u0003~b9\u0012])l"
		// @04C: invokestatic game.C_100053_vn.func_102813_z(java.lang.String)char[]
		// @04F: invokestatic game.C_100053_vn.func_102811_z(char[])java.lang.String
		// @052: aastore
		// @053: dup
		// @054: bipush 7 (0x07)
		// @056: ldc_w "-<)o}s"
		// @059: invokestatic game.C_100053_vn.func_102813_z(java.lang.String)char[]
		// @05C: invokestatic game.C_100053_vn.func_102811_z(char[])java.lang.String
		// @05F: aastore
		// @060: dup
		// @061: bipush 8 (0x08)
		// @063: ldc "-<)l}s"
		// @065: invokestatic game.C_100053_vn.func_102813_z(java.lang.String)char[]
		// @068: invokestatic game.C_100053_vn.func_102811_z(char[])java.lang.String
		// @06B: aastore
		// @06C: dup
		// @06D: bipush 9 (0x09)
		// @06F: ldc "-<){~s"
		// @071: invokestatic game.C_100053_vn.func_102813_z(java.lang.String)char[]
		// @074: invokestatic game.C_100053_vn.func_102811_z(char[])java.lang.String
		// @077: aastore
		// @078: dup
		// @079: bipush 10 (0x0A)
		// @07B: ldc "-<)}~s"
		// @07D: invokestatic game.C_100053_vn.func_102813_z(java.lang.String)char[]
		// @080: invokestatic game.C_100053_vn.func_102811_z(char[])java.lang.String
		// @083: aastore
		// @084: dup
		// @085: bipush 11 (0x0B)
		// @087: ldc "-<)h~s"
		// @089: invokestatic game.C_100053_vn.func_102813_z(java.lang.String)char[]
		// @08C: invokestatic game.C_100053_vn.func_102811_z(char[])java.lang.String
		// @08F: aastore
		// @090: dup
		// @091: bipush 12 (0x0C)
		// @093: ldc "-<)y~s"
		// @095: invokestatic game.C_100053_vn.func_102813_z(java.lang.String)char[]
		// @098: invokestatic game.C_100053_vn.func_102811_z(char[])java.lang.String
		// @09B: aastore
		// @09C: dup
		// @09D: bipush 13 (0x0D)
		// @09F: ldc "-<)x~s"
		// @0A1: invokestatic game.C_100053_vn.func_102813_z(java.lang.String)char[]
		// @0A4: invokestatic game.C_100053_vn.func_102811_z(char[])java.lang.String
		// @0A7: aastore
		// @0A8: dup
		// @0A9: bipush 14 (0x0E)
		// @0AB: ldc "-<)a~s"
		// @0AD: invokestatic game.C_100053_vn.func_102813_z(java.lang.String)char[]
		// @0B0: invokestatic game.C_100053_vn.func_102811_z(char[])java.lang.String
		// @0B3: aastore
		// @0B4: dup
		// @0B5: bipush 15 (0x0F)
		// @0B7: ldc "-<)z~s"
		// @0B9: invokestatic game.C_100053_vn.func_102813_z(java.lang.String)char[]
		// @0BC: invokestatic game.C_100053_vn.func_102811_z(char[])java.lang.String
		// @0BF: aastore
		// @0C0: dup
		// @0C1: bipush 16 (0x10)
		// @0C3: ldc "/7uCLu%t"
		// @0C5: invokestatic game.C_100053_vn.func_102813_z(java.lang.String)char[]
		// @0C8: invokestatic game.C_100053_vn.func_102811_z(char[])java.lang.String
		// @0CB: aastore
		// @0CC: dup
		// @0CD: bipush 17 (0x11)
		// @0CF: ldc "8=iJJ8&)YL"
		// @0D1: invokestatic game.C_100053_vn.func_102813_z(java.lang.String)char[]
		// @0D4: invokestatic game.C_100053_vn.func_102811_z(char[])java.lang.String
		// @0D7: aastore
		// @0D8: dup
		// @0D9: bipush 18 (0x12)
		// @0DB: ldc "-<)`~s"
		// @0DD: invokestatic game.C_100053_vn.func_102813_z(java.lang.String)char[]
		// @0E0: invokestatic game.C_100053_vn.func_102811_z(char[])java.lang.String
		// @0E3: aastore
		// @0E4: dup
		// @0E5: bipush 19 (0x13)
		// @0E7: ldc "+ nX^8+)YL"
		// @0E9: invokestatic game.C_100053_vn.func_102813_z(java.lang.String)char[]
		// @0EC: invokestatic game.C_100053_vn.func_102811_z(char[])java.lang.String
		// @0EF: aastore
		// @0F0: dup
		// @0F1: bipush 20 (0x14)
		// @0F3: ldc "-<)\u0012V5;s\u0010\u0017r"
		// @0F5: invokestatic game.C_100053_vn.func_102813_z(java.lang.String)char[]
		// @0F8: invokestatic game.C_100053_vn.func_102811_z(char[])java.lang.String
		// @0FB: aastore
		// @0FC: dup
		// @0FD: bipush 21 (0x15)
		// @0FF: ldc "-<)|~s"
		// @101: invokestatic game.C_100053_vn.func_102813_z(java.lang.String)char[]
		// @104: invokestatic game.C_100053_vn.func_102811_z(char[])java.lang.String
		// @107: aastore
		// @108: dup
		// @109: bipush 22 (0x16)
		// @10B: ldc_w "-<)f~s"
		// @10E: invokestatic game.C_100053_vn.func_102813_z(java.lang.String)char[]
		// @111: invokestatic game.C_100053_vn.func_102811_z(char[])java.lang.String
		// @114: aastore
		// @115: dup
		// @116: bipush 23 (0x17)
		// @118: ldc "-<)g~s"
		// @11A: invokestatic game.C_100053_vn.func_102813_z(java.lang.String)char[]
		// @11D: invokestatic game.C_100053_vn.func_102811_z(char[])java.lang.String
		// @120: aastore
		// @121: dup
		// @122: bipush 24 (0x18)
		// @124: ldc "-<)\u007f~s"
		// @126: invokestatic game.C_100053_vn.func_102813_z(java.lang.String)char[]
		// @129: invokestatic game.C_100053_vn.func_102811_z(char[])java.lang.String
		// @12C: aastore
		// @12D: dup
		// @12E: bipush 25 (0x19)
		// @130: ldc "g}dASen([\u0001"
		// @132: invokestatic game.C_100053_vn.func_102813_z(java.lang.String)char[]
		// @135: invokestatic game.C_100053_vn.func_102811_z(char[])java.lang.String
		// @138: aastore
		// @139: dup
		// @13A: bipush 26 (0x1A)
		// @13C: ldc "-<)e~s"
		// @13E: invokestatic game.C_100053_vn.func_102813_z(java.lang.String)char[]
		// @141: invokestatic game.C_100053_vn.func_102811_z(char[])java.lang.String
		// @144: aastore
		// @145: dup
		// @146: bipush 27 (0x1B)
		// @148: ldc "-<)~~s"
		// @14A: invokestatic game.C_100053_vn.func_102813_z(java.lang.String)char[]
		// @14D: invokestatic game.C_100053_vn.func_102811_z(char[])java.lang.String
		// @150: aastore
		// @151: dup
		// @152: bipush 28 (0x1C)
		// @154: ldc "g':\u001c\u000emfF\u001c\u0001g1hB\u0002ic1\u001a~il"
		// @156: invokestatic game.C_100053_vn.func_102813_z(java.lang.String)char[]
		// @159: invokestatic game.C_100053_vn.func_102811_z(char[])java.lang.String
		// @15C: aastore
		// @15D: dup
		// @15E: bipush 29 (0x1D)
		// @160: ldc "-<)\u007f\u0017"
		// @162: invokestatic game.C_100053_vn.func_102813_z(java.lang.String)char[]
		// @165: invokestatic game.C_100053_vn.func_102811_z(char[])java.lang.String
		// @168: aastore
		// @169: putstatic java.lang.String[] game.C_100053_vn.field_102834_ib
		// @16C: ldc_w "\u000f:n]\u001f2!'WP. '|J57TM^+7'MS:<'GY{+h[\u001f33qK\u001f4<b\u0000"
		// @16F: invokestatic game.C_100053_vn.func_102813_z(java.lang.String)char[]
		// @172: invokestatic game.C_100053_vn.func_102811_z(char[])java.lang.String
		// @175: putstatic java.lang.String game.C_100053_vn.field_102840_R
		// @178: new game.C_100217_ao
		// @17B: dup
		// @17C: bipush 9 (0x09)
		// @17E: iconst_0
		// @17F: iconst_4
		// @180: iconst_1
		// @181: invokespecial game.C_100217_ao.<init>(int, int, int, int)void
		// @184: putstatic game.C_100217_ao game.C_100053_vn.field_102837_Q
		// @187: return
	}
	
	private static char[] func_102813_z(String arg0)
	{
		// @00: aload_0
		// @01: invokevirtual java.lang.String.toCharArray()char[]
		// @04: dup
		// @05: arraylength
		// @06: iconst_2
		// @07: if_icmpge @13
		// @0A: dup
		// @0B: iconst_0
		// @0C: dup2
		// @0D: caload
		// @0E: bipush 63 (0x3F)
		// @10: ixor
		// @11: i2c
		// @12: castore
		// @13: areturn
	}
	
	private static String func_102811_z(char[] arg0)
	{
		// @00: aload_0
		// @01: dup
		// @02: arraylength
		// @03: swap
		// @04: iconst_0
		// @05: istore_1
		// @06: goto @4C
		// @09: dup
		// @0A: iload_1
		// @0B: dup2
		// @0C: caload
		// @0D: iload_1
		// @0E: iconst_5
		// @0F: irem
		// @10: tableswitch def: @44, for 0: @30, for 1: @35, for 2: @3A, for 3: @3F
		// @30: bipush 91 (0x5B)
		// @32: goto @46
		// @35: bipush 82 (0x52)
		// @37: goto @46
		// @3A: bipush 7 (0x07)
		// @3C: goto @46
		// @3F: bipush 46 (0x2E)
		// @41: goto @46
		// @44: bipush 63 (0x3F)
		// @46: ixor
		// @47: i2c
		// @48: castore
		// @49: iinc #1 +1
		// @4C: swap
		// @4D: dup_x1
		// @4E: iload_1
		// @4F: if_icmpgt @09
		// @52: new java.lang.String
		// @55: dup_x1
		// @56: swap
		// @57: invokespecial java.lang.String.<init>(char[])void
		// @5A: invokevirtual java.lang.String.intern()java.lang.String
		// @5D: areturn
	}
}
