package game;

final class C_100129_tg extends C_100341_jd
{
	static int[] field_102747_tb;
	private C_100281_ng field_102751_ub;
	private boolean field_102742_zb;
	static int[] field_102753_wb;
	private boolean field_102746_Cb;
	static int[] field_102752_xb;
	private String field_102749_Bb;
	static int field_102754_vb;
	static C_100302_ka field_102750_sb;
	static String field_102745_Eb;
	static String field_102743_Db;
	static String field_102748_Ab;
	private String field_102744_yb;
	private static final String[] field_102741_Fb;
	
	C_100129_tg(C_100029_gn arg0, String arg1)
	{
		// @00: aload_0
		// @01: aload_1
		// @02: sipush 300 (0x012C)
		// @05: bipush 120 (0x78)
		// @07: invokespecial game.C_100341_jd.<init>(game.C_100029_gn, int, int)void
		// @0A: aload_0
		// @0B: aload_2
		// @0C: putfield java.lang.String game.C_100129_tg.field_102749_Bb
		// @0F: aload_0
		// @10: getfield java.lang.String game.C_100129_tg.field_102749_Bb
		// @13: ifnull @39
		// @16: getstatic game.C_100112_r game.C_100185_rm.field_105484_d
		// @19: aload_0
		// @1A: getfield java.lang.String game.C_100129_tg.field_102749_Bb
		// @1D: sipush 260 (0x0104)
		// @20: getstatic game.C_100112_r game.C_100185_rm.field_105484_d
		// @23: getfield int game.C_100112_r.field_101772_Q
		// @26: invokevirtual game.C_100112_r.func_101734_a(java.lang.String, int, int)int
		// @29: istore_3
		// @2A: aload_0
		// @2B: bipush -85 (0xAB)
		// @2D: sipush 150 (0x0096)
		// @30: iload_3
		// @31: ineg
		// @32: isub
		// @33: sipush 300 (0x012C)
		// @36: invokevirtual game.C_100129_tg.func_102615_b(byte, int, int)void
		// @39: aload_0
		// @3A: new game.C_100281_ng
		// @3D: dup
		// @3E: bipush 13 (0x0D)
		// @40: bipush 50 (0x32)
		// @42: sipush 274 (0x0112)
		// @45: bipush 30 (0x1E)
		// @47: bipush 15 (0x0F)
		// @49: ldc 2113632 (0x204060)
		// @4B: ldc 4210752 (0x404040)
		// @4D: invokespecial game.C_100281_ng.<init>(int, int, int, int, int, int, int)void
		// @50: putfield game.C_100281_ng game.C_100129_tg.field_102751_ub
		// @53: aload_0
		// @54: iconst_0
		// @55: putfield boolean game.C_100129_tg.field_102746_Cb
		// @58: aload_0
		// @59: getfield game.C_100281_ng game.C_100129_tg.field_102751_ub
		// @5C: iconst_1
		// @5D: putfield boolean game.C_100281_ng.field_103471_P
		// @60: aload_0
		// @61: iconst_0
		// @62: putfield boolean game.C_100129_tg.field_102742_zb
		// @65: aload_0
		// @66: aload_0
		// @67: getfield game.C_100281_ng game.C_100129_tg.field_102751_ub
		// @6A: iconst_1
		// @6B: invokevirtual game.C_100129_tg.func_102561_b(game.C_100336_im, int)void
		// @6E: goto @BF
		// @71: astore_3
		// @72: aload_3
		// @73: new java.lang.StringBuilder
		// @76: dup
		// @77: invokespecial java.lang.StringBuilder.<init>()void
		// @7A: getstatic java.lang.String[] game.C_100129_tg.field_102741_Fb
		// @7D: iconst_4
		// @7E: aaload
		// @7F: invokevirtual java.lang.StringBuilder.append(java.lang.String)java.lang.StringBuilder
		// @82: aload_1
		// @83: ifnull @8F
		// @86: getstatic java.lang.String[] game.C_100129_tg.field_102741_Fb
		// @89: iconst_5
		// @8A: aaload
		// @8B: goto @95
		// @8E: athrow
		// @8F: getstatic java.lang.String[] game.C_100129_tg.field_102741_Fb
		// @92: bipush 6 (0x06)
		// @94: aaload
		// @95: invokevirtual java.lang.StringBuilder.append(java.lang.String)java.lang.StringBuilder
		// @98: bipush 44 (0x2C)
		// @9A: invokevirtual java.lang.StringBuilder.append(char)java.lang.StringBuilder
		// @9D: aload_2
		// @9E: ifnull @AA
		// @A1: getstatic java.lang.String[] game.C_100129_tg.field_102741_Fb
		// @A4: iconst_5
		// @A5: aaload
		// @A6: goto @B0
		// @A9: athrow
		// @AA: getstatic java.lang.String[] game.C_100129_tg.field_102741_Fb
		// @AD: bipush 6 (0x06)
		// @AF: aaload
		// @B0: invokevirtual java.lang.StringBuilder.append(java.lang.String)java.lang.StringBuilder
		// @B3: bipush 41 (0x29)
		// @B5: invokevirtual java.lang.StringBuilder.append(char)java.lang.StringBuilder
		// @B8: invokevirtual java.lang.StringBuilder.toString()java.lang.String
		// @BB: invokestatic game.C_100181_cf.func_105695_a(java.lang.Throwable, java.lang.String)game.C_100170_cm
		// @BE: athrow
		// @BF: return
	}
	
	static final void func_102740_b(int arg0, byte arg1)
	{
		// @00: iload_1
		// @01: bipush -91 (0xA5)
		// @03: if_icmpeq @11
		// @06: bipush 83 (0x53)
		// @08: bipush -6 (0xFA)
		// @0A: invokestatic game.C_100129_tg.func_102740_b(int, byte)void
		// @0D: goto @11
		// @10: athrow
		// @11: getstatic game.C_100278_nd game.C_100115_ej.field_102043_Yb
		// @14: astore_2
		// @15: aload_2
		// @16: iload_0
		// @17: bipush 126 (0x7E)
		// @19: invokevirtual game.C_100278_nd.func_101189_h(int, int)void
		// @1C: aload_2
		// @1D: iload_1
		// @1E: sipush 7929 (0x1EF9)
		// @21: iadd
		// @22: iconst_1
		// @23: invokevirtual game.C_100278_nd.func_101169_f(int, int)void
		// @26: aload_2
		// @27: sipush 7838 (0x1E9E)
		// @2A: iconst_0
		// @2B: invokevirtual game.C_100278_nd.func_101169_f(int, int)void
		// @2E: goto @5B
		// @31: astore_2
		// @32: aload_2
		// @33: new java.lang.StringBuilder
		// @36: dup
		// @37: invokespecial java.lang.StringBuilder.<init>()void
		// @3A: getstatic java.lang.String[] game.C_100129_tg.field_102741_Fb
		// @3D: iconst_3
		// @3E: aaload
		// @3F: invokevirtual java.lang.StringBuilder.append(java.lang.String)java.lang.StringBuilder
		// @42: iload_0
		// @43: invokevirtual java.lang.StringBuilder.append(int)java.lang.StringBuilder
		// @46: bipush 44 (0x2C)
		// @48: invokevirtual java.lang.StringBuilder.append(char)java.lang.StringBuilder
		// @4B: iload_1
		// @4C: invokevirtual java.lang.StringBuilder.append(int)java.lang.StringBuilder
		// @4F: bipush 41 (0x29)
		// @51: invokevirtual java.lang.StringBuilder.append(char)java.lang.StringBuilder
		// @54: invokevirtual java.lang.StringBuilder.toString()java.lang.String
		// @57: invokestatic game.C_100181_cf.func_105695_a(java.lang.Throwable, java.lang.String)game.C_100170_cm
		// @5A: athrow
		// @5B: return
	}
	
	final void func_102735_a(String arg0, int arg1, float arg2, boolean arg3)
	{
		// @00: iload #4
		// @02: aload_0
		// @03: getfield boolean game.C_100129_tg.field_102742_zb
		// @06: if_icmpeq @5F
		// @09: aload_0
		// @0A: iload #4
		// @0C: putfield boolean game.C_100129_tg.field_102742_zb
		// @0F: aload_0
		// @10: getfield boolean game.C_100129_tg.field_102742_zb
		// @13: ifne @44
		// @16: goto @1A
		// @19: athrow
		// @1A: aload_0
		// @1B: getfield game.C_100281_ng game.C_100129_tg.field_102751_ub
		// @1E: ldc 4210752 (0x404040)
		// @20: ldc 2113632 (0x204060)
		// @22: ldc 16711935 (0xff00ff)
		// @24: invokevirtual game.C_100281_ng.func_103453_b(int, int, int)void
		// @27: aload_0
		// @28: getfield boolean game.C_100129_tg.field_102746_Cb
		// @2B: ifne @36
		// @2E: goto @32
		// @31: athrow
		// @32: goto @5F
		// @35: athrow
		// @36: aload_0
		// @37: getfield game.C_100281_ng game.C_100129_tg.field_102751_ub
		// @3A: iconst_0
		// @3B: putfield boolean game.C_100281_ng.field_103471_P
		// @3E: getstatic int game.SteelSentinels.field_105275_O
		// @41: ifeq @5F
		// @44: aload_0
		// @45: getfield game.C_100281_ng game.C_100129_tg.field_102751_ub
		// @48: ldc 4210752 (0x404040)
		// @4A: ldc 8405024 (0x804020)
		// @4C: iload_2
		// @4D: ldc 16711785 (0xff0069)
		// @4F: iadd
		// @50: invokevirtual game.C_100281_ng.func_103453_b(int, int, int)void
		// @53: aload_0
		// @54: getfield game.C_100281_ng game.C_100129_tg.field_102751_ub
		// @57: iconst_1
		// @58: putfield boolean game.C_100281_ng.field_103471_P
		// @5B: goto @5F
		// @5E: athrow
		// @5F: aload_0
		// @60: aload_1
		// @61: putfield java.lang.String game.C_100129_tg.field_102744_yb
		// @64: aload_0
		// @65: getfield game.C_100281_ng game.C_100129_tg.field_102751_ub
		// @68: fload_3
		// @69: ldc 100.0
		// @6B: fdiv
		// @6C: ldc 65536.0
		// @6E: fmul
		// @6F: f2i
		// @70: putfield int game.C_100281_ng.field_103454_D
		// @73: iload_2
		// @74: sipush 150 (0x0096)
		// @77: if_icmpeq @85
		// @7A: aconst_null
		// @7B: checkcast game.C_100302_ka
		// @7E: putstatic game.C_100302_ka game.C_100129_tg.field_102750_sb
		// @81: goto @85
		// @84: athrow
		// @85: goto @DA
		// @88: astore #5
		// @8A: aload #5
		// @8C: new java.lang.StringBuilder
		// @8F: dup
		// @90: invokespecial java.lang.StringBuilder.<init>()void
		// @93: getstatic java.lang.String[] game.C_100129_tg.field_102741_Fb
		// @96: bipush 7 (0x07)
		// @98: aaload
		// @99: invokevirtual java.lang.StringBuilder.append(java.lang.String)java.lang.StringBuilder
		// @9C: aload_1
		// @9D: ifnull @A9
		// @A0: getstatic java.lang.String[] game.C_100129_tg.field_102741_Fb
		// @A3: iconst_5
		// @A4: aaload
		// @A5: goto @AF
		// @A8: athrow
		// @A9: getstatic java.lang.String[] game.C_100129_tg.field_102741_Fb
		// @AC: bipush 6 (0x06)
		// @AE: aaload
		// @AF: invokevirtual java.lang.StringBuilder.append(java.lang.String)java.lang.StringBuilder
		// @B2: bipush 44 (0x2C)
		// @B4: invokevirtual java.lang.StringBuilder.append(char)java.lang.StringBuilder
		// @B7: iload_2
		// @B8: invokevirtual java.lang.StringBuilder.append(int)java.lang.StringBuilder
		// @BB: bipush 44 (0x2C)
		// @BD: invokevirtual java.lang.StringBuilder.append(char)java.lang.StringBuilder
		// @C0: fload_3
		// @C1: invokevirtual java.lang.StringBuilder.append(float)java.lang.StringBuilder
		// @C4: bipush 44 (0x2C)
		// @C6: invokevirtual java.lang.StringBuilder.append(char)java.lang.StringBuilder
		// @C9: iload #4
		// @CB: invokevirtual java.lang.StringBuilder.append(boolean)java.lang.StringBuilder
		// @CE: bipush 41 (0x29)
		// @D0: invokevirtual java.lang.StringBuilder.append(char)java.lang.StringBuilder
		// @D3: invokevirtual java.lang.StringBuilder.toString()java.lang.String
		// @D6: invokestatic game.C_100181_cf.func_105695_a(java.lang.Throwable, java.lang.String)game.C_100170_cm
		// @D9: athrow
		// @DA: return
	}
	
	final void func_102739_p(int arg0)
	{
		// @00: aload_0
		// @01: getfield game.C_100281_ng game.C_100129_tg.field_102751_ub
		// @04: iconst_0
		// @05: putfield boolean game.C_100281_ng.field_103471_P
		// @08: aload_0
		// @09: iconst_1
		// @0A: putfield boolean game.C_100129_tg.field_102746_Cb
		// @0D: iload_1
		// @0E: sipush 31865 (0x7C79)
		// @11: if_icmpeq @18
		// @14: iconst_1
		// @15: invokestatic game.C_100129_tg.func_102734_a(boolean)void
		// @18: goto @3C
		// @1B: astore_2
		// @1C: aload_2
		// @1D: new java.lang.StringBuilder
		// @20: dup
		// @21: invokespecial java.lang.StringBuilder.<init>()void
		// @24: getstatic java.lang.String[] game.C_100129_tg.field_102741_Fb
		// @27: iconst_2
		// @28: aaload
		// @29: invokevirtual java.lang.StringBuilder.append(java.lang.String)java.lang.StringBuilder
		// @2C: iload_1
		// @2D: invokevirtual java.lang.StringBuilder.append(int)java.lang.StringBuilder
		// @30: bipush 41 (0x29)
		// @32: invokevirtual java.lang.StringBuilder.append(char)java.lang.StringBuilder
		// @35: invokevirtual java.lang.StringBuilder.toString()java.lang.String
		// @38: invokestatic game.C_100181_cf.func_105695_a(java.lang.Throwable, java.lang.String)game.C_100170_cm
		// @3B: athrow
		// @3C: return
	}
	
	final void func_102607_a(byte arg0, int arg1, int arg2)
	{
		// @00: aload_0
		// @01: bipush -62 (0xC2)
		// @03: iload_2
		// @04: iload_3
		// @05: invokespecial game.C_100341_jd.func_102607_a(byte, int, int)void
		// @08: getstatic game.C_100112_r game.C_100185_rm.field_105484_d
		// @0B: aload_0
		// @0C: getfield java.lang.String game.C_100129_tg.field_102744_yb
		// @0F: aload_0
		// @10: getfield int game.C_100129_tg.field_102537_l
		// @13: ldc -1506387839 (0xa6365881)
		// @15: ishr
		// @16: iload_2
		// @17: iadd
		// @18: iload_3
		// @19: bipush 103 (0x67)
		// @1B: iadd
		// @1C: ldc 16777215 (0xffffff)
		// @1E: iconst_m1
		// @1F: invokevirtual game.C_100112_r.func_101744_b(java.lang.String, int, int, int, int)void
		// @22: iload_1
		// @23: bipush -7 (0xF9)
		// @25: if_icmplt @29
		// @28: return
		// @29: aload_0
		// @2A: getfield java.lang.String game.C_100129_tg.field_102749_Bb
		// @2D: ifnull @64
		// @30: bipush 20 (0x14)
		// @32: iload_2
		// @33: iadd
		// @34: bipush 113 (0x71)
		// @36: iload_3
		// @37: iadd
		// @38: sipush 260 (0x0104)
		// @3B: ldc 8421504 (0x808080)
		// @3D: invokestatic game.C_100196_rb.func_105807_g(int, int, int, int)void
		// @40: getstatic game.C_100112_r game.C_100185_rm.field_105484_d
		// @43: aload_0
		// @44: getfield java.lang.String game.C_100129_tg.field_102749_Bb
		// @47: bipush 20 (0x14)
		// @49: iload_2
		// @4A: iadd
		// @4B: sipush 128 (0x0080)
		// @4E: iload_3
		// @4F: iadd
		// @50: sipush 260 (0x0104)
		// @53: bipush 100 (0x64)
		// @55: ldc 16777215 (0xffffff)
		// @57: iconst_m1
		// @58: iconst_1
		// @59: iconst_0
		// @5A: getstatic game.C_100112_r game.C_100185_rm.field_105484_d
		// @5D: getfield int game.C_100112_r.field_101772_Q
		// @60: invokevirtual game.C_100112_r.func_101729_a(java.lang.String, int, int, int, int, int, int, int, int, int)int
		// @63: pop
		// @64: goto @9C
		// @67: astore #4
		// @69: aload #4
		// @6B: new java.lang.StringBuilder
		// @6E: dup
		// @6F: invokespecial java.lang.StringBuilder.<init>()void
		// @72: getstatic java.lang.String[] game.C_100129_tg.field_102741_Fb
		// @75: iconst_1
		// @76: aaload
		// @77: invokevirtual java.lang.StringBuilder.append(java.lang.String)java.lang.StringBuilder
		// @7A: iload_1
		// @7B: invokevirtual java.lang.StringBuilder.append(int)java.lang.StringBuilder
		// @7E: bipush 44 (0x2C)
		// @80: invokevirtual java.lang.StringBuilder.append(char)java.lang.StringBuilder
		// @83: iload_2
		// @84: invokevirtual java.lang.StringBuilder.append(int)java.lang.StringBuilder
		// @87: bipush 44 (0x2C)
		// @89: invokevirtual java.lang.StringBuilder.append(char)java.lang.StringBuilder
		// @8C: iload_3
		// @8D: invokevirtual java.lang.StringBuilder.append(int)java.lang.StringBuilder
		// @90: bipush 41 (0x29)
		// @92: invokevirtual java.lang.StringBuilder.append(char)java.lang.StringBuilder
		// @95: invokevirtual java.lang.StringBuilder.toString()java.lang.String
		// @98: invokestatic game.C_100181_cf.func_105695_a(java.lang.Throwable, java.lang.String)game.C_100170_cm
		// @9B: athrow
		// @9C: return
	}
	
	static final void func_102734_a(boolean arg0)
	{
		// @00: getstatic game.C_100185_rm game.C_100049_vf.field_104206_l
		// @03: getfield int game.C_100185_rm.field_105491_i
		// @06: getstatic int game.C_100280_nf.field_101173_s
		// @09: if_icmpeq @2B
		// @0C: getstatic int game.C_100303_kk.field_104788_o
		// @0F: getstatic int game.C_100280_nf.field_101173_s
		// @12: ineg
		// @13: getstatic game.C_100185_rm game.C_100049_vf.field_104206_l
		// @16: getfield int game.C_100185_rm.field_105491_i
		// @19: iadd
		// @1A: iadd
		// @1B: putstatic int game.C_100303_kk.field_104788_o
		// @1E: getstatic game.C_100185_rm game.C_100049_vf.field_104206_l
		// @21: getfield int game.C_100185_rm.field_105491_i
		// @24: putstatic int game.C_100280_nf.field_101173_s
		// @27: goto @2B
		// @2A: athrow
		// @2B: iconst_0
		// @2C: getstatic int game.C_100038_wa.field_104077_j
		// @2F: if_icmplt @36
		// @32: goto @3E
		// @35: athrow
		// @36: getstatic int game.C_100038_wa.field_104077_j
		// @39: iconst_1
		// @3A: isub
		// @3B: putstatic int game.C_100038_wa.field_104077_j
		// @3E: iconst_m1
		// @3F: getstatic int game.C_100038_wa.field_104077_j
		// @42: iconst_m1
		// @43: ixor
		// @44: if_icmpgt @4B
		// @47: goto @51
		// @4A: athrow
		// @4B: sipush 22547 (0x5813)
		// @4E: invokestatic game.C_100327_ib.func_102468_p(int)void
		// @51: iload_0
		// @52: ifeq @60
		// @55: bipush -10 (0xF6)
		// @57: bipush 102 (0x66)
		// @59: invokestatic game.C_100129_tg.func_102738_a(int, int)void
		// @5C: goto @60
		// @5F: athrow
		// @60: goto @84
		// @63: astore_1
		// @64: aload_1
		// @65: new java.lang.StringBuilder
		// @68: dup
		// @69: invokespecial java.lang.StringBuilder.<init>()void
		// @6C: getstatic java.lang.String[] game.C_100129_tg.field_102741_Fb
		// @6F: iconst_0
		// @70: aaload
		// @71: invokevirtual java.lang.StringBuilder.append(java.lang.String)java.lang.StringBuilder
		// @74: iload_0
		// @75: invokevirtual java.lang.StringBuilder.append(boolean)java.lang.StringBuilder
		// @78: bipush 41 (0x29)
		// @7A: invokevirtual java.lang.StringBuilder.append(char)java.lang.StringBuilder
		// @7D: invokevirtual java.lang.StringBuilder.toString()java.lang.String
		// @80: invokestatic game.C_100181_cf.func_105695_a(java.lang.Throwable, java.lang.String)game.C_100170_cm
		// @83: athrow
		// @84: return
	}
	
	static final boolean func_102732_a(char arg0, int arg1)
	{
		// @00: getstatic int game.SteelSentinels.field_105275_O
		// @03: istore #5
		// @05: iload_0
		// @06: invokestatic java.lang.Character.isISOControl(char)boolean
		// @09: ifne @10
		// @0C: goto @12
		// @0F: athrow
		// @10: iconst_0
		// @11: ireturn
		// @12: iload_1
		// @13: bipush 29 (0x1D)
		// @15: if_icmpge @23
		// @18: aconst_null
		// @19: checkcast int[]
		// @1C: putstatic int[] game.C_100129_tg.field_102753_wb
		// @1F: goto @23
		// @22: athrow
		// @23: iload_0
		// @24: sipush 28481 (0x6F41)
		// @27: invokestatic game.C_100007_fm.func_103626_a(char, int)boolean
		// @2A: ifeq @2F
		// @2D: iconst_1
		// @2E: ireturn
		// @2F: getstatic char[] game.C_100111_el.field_104865_j
		// @32: astore_2
		// @33: iconst_0
		// @34: istore_3
		// @35: aload_2
		// @36: arraylength
		// @37: iload_3
		// @38: if_icmple @60
		// @3B: aload_2
		// @3C: iload_3
		// @3D: caload
		// @3E: istore #4
		// @40: iload #4
		// @42: iconst_m1
		// @43: ixor
		// @44: iload_0
		// @45: iconst_m1
		// @46: ixor
		// @47: iload #5
		// @49: ifne @69
		// @4C: if_icmpeq @56
		// @4F: goto @53
		// @52: athrow
		// @53: goto @58
		// @56: iconst_1
		// @57: ireturn
		// @58: iinc #3 +1
		// @5B: iload #5
		// @5D: ifeq @35
		// @60: getstatic char[] game.C_100292_jk.field_101218_n
		// @63: astore_2
		// @64: iconst_0
		// @65: istore_3
		// @66: aload_2
		// @67: arraylength
		// @68: iload_3
		// @69: if_icmple @8E
		// @6C: aload_2
		// @6D: iload_3
		// @6E: caload
		// @6F: istore #4
		// @71: iload_0
		// @72: iconst_m1
		// @73: ixor
		// @74: iload #5
		// @76: ifne @8F
		// @79: iload #4
		// @7B: iconst_m1
		// @7C: ixor
		// @7D: if_icmpne @86
		// @80: goto @84
		// @83: athrow
		// @84: iconst_1
		// @85: ireturn
		// @86: iinc #3 +1
		// @89: iload #5
		// @8B: ifeq @66
		// @8E: iconst_0
		// @8F: ireturn
		// @90: astore_2
		// @91: aload_2
		// @92: new java.lang.StringBuilder
		// @95: dup
		// @96: invokespecial java.lang.StringBuilder.<init>()void
		// @99: getstatic java.lang.String[] game.C_100129_tg.field_102741_Fb
		// @9C: bipush 11 (0x0B)
		// @9E: aaload
		// @9F: invokevirtual java.lang.StringBuilder.append(java.lang.String)java.lang.StringBuilder
		// @A2: iload_0
		// @A3: invokevirtual java.lang.StringBuilder.append(char)java.lang.StringBuilder
		// @A6: bipush 44 (0x2C)
		// @A8: invokevirtual java.lang.StringBuilder.append(char)java.lang.StringBuilder
		// @AB: iload_1
		// @AC: invokevirtual java.lang.StringBuilder.append(int)java.lang.StringBuilder
		// @AF: bipush 41 (0x29)
		// @B1: invokevirtual java.lang.StringBuilder.append(char)java.lang.StringBuilder
		// @B4: invokevirtual java.lang.StringBuilder.toString()java.lang.String
		// @B7: invokestatic game.C_100181_cf.func_105695_a(java.lang.Throwable, java.lang.String)game.C_100170_cm
		// @BA: athrow
	}
	
	static final String func_102736_b(int arg0, int arg1)
	{
		// @00: iload_0
		// @01: bipush 41 (0x29)
		// @03: if_icmpgt @0B
		// @06: aconst_null
		// @07: checkcast java.lang.String
		// @0A: areturn
		// @0B: iload_1
		// @0C: istore_2
		// @0D: iload_2
		// @0E: iconst_m1
		// @0F: ixor
		// @10: bipush -90 (0xA6)
		// @12: if_icmpeq @2D
		// @15: iload_2
		// @16: bipush 66 (0x42)
		// @18: if_icmpeq @33
		// @1B: goto @1F
		// @1E: athrow
		// @1F: iload_2
		// @20: bipush 76 (0x4C)
		// @22: if_icmpeq @39
		// @25: goto @29
		// @28: athrow
		// @29: goto @3F
		// @2C: athrow
		// @2D: getstatic java.lang.String[] game.C_100197_ra.field_100858_l
		// @30: iconst_0
		// @31: aaload
		// @32: areturn
		// @33: getstatic java.lang.String[] game.C_100197_ra.field_100858_l
		// @36: iconst_1
		// @37: aaload
		// @38: areturn
		// @39: getstatic java.lang.String[] game.C_100197_ra.field_100858_l
		// @3C: iconst_2
		// @3D: aaload
		// @3E: areturn
		// @3F: aconst_null
		// @40: areturn
		// @41: astore_2
		// @42: aload_2
		// @43: new java.lang.StringBuilder
		// @46: dup
		// @47: invokespecial java.lang.StringBuilder.<init>()void
		// @4A: getstatic java.lang.String[] game.C_100129_tg.field_102741_Fb
		// @4D: bipush 9 (0x09)
		// @4F: aaload
		// @50: invokevirtual java.lang.StringBuilder.append(java.lang.String)java.lang.StringBuilder
		// @53: iload_0
		// @54: invokevirtual java.lang.StringBuilder.append(int)java.lang.StringBuilder
		// @57: bipush 44 (0x2C)
		// @59: invokevirtual java.lang.StringBuilder.append(char)java.lang.StringBuilder
		// @5C: iload_1
		// @5D: invokevirtual java.lang.StringBuilder.append(int)java.lang.StringBuilder
		// @60: bipush 41 (0x29)
		// @62: invokevirtual java.lang.StringBuilder.append(char)java.lang.StringBuilder
		// @65: invokevirtual java.lang.StringBuilder.toString()java.lang.String
		// @68: invokestatic game.C_100181_cf.func_105695_a(java.lang.Throwable, java.lang.String)game.C_100170_cm
		// @6B: athrow
	}
	
	public static void func_102737_h(byte arg0)
	{
		// @00: aconst_null
		// @01: putstatic int[] game.C_100129_tg.field_102753_wb
		// @04: aconst_null
		// @05: putstatic java.lang.String game.C_100129_tg.field_102743_Db
		// @08: aconst_null
		// @09: putstatic game.C_100302_ka game.C_100129_tg.field_102750_sb
		// @0C: aconst_null
		// @0D: putstatic int[] game.C_100129_tg.field_102747_tb
		// @10: aconst_null
		// @11: putstatic java.lang.String game.C_100129_tg.field_102745_Eb
		// @14: aconst_null
		// @15: putstatic java.lang.String game.C_100129_tg.field_102748_Ab
		// @18: aconst_null
		// @19: putstatic int[] game.C_100129_tg.field_102752_xb
		// @1C: iload_0
		// @1D: bipush 113 (0x71)
		// @1F: if_icmpeq @29
		// @22: bipush -39 (0xD9)
		// @24: bipush -28 (0xE4)
		// @26: invokestatic game.C_100129_tg.func_102738_a(int, int)void
		// @29: goto @4E
		// @2C: astore_1
		// @2D: aload_1
		// @2E: new java.lang.StringBuilder
		// @31: dup
		// @32: invokespecial java.lang.StringBuilder.<init>()void
		// @35: getstatic java.lang.String[] game.C_100129_tg.field_102741_Fb
		// @38: bipush 10 (0x0A)
		// @3A: aaload
		// @3B: invokevirtual java.lang.StringBuilder.append(java.lang.String)java.lang.StringBuilder
		// @3E: iload_0
		// @3F: invokevirtual java.lang.StringBuilder.append(int)java.lang.StringBuilder
		// @42: bipush 41 (0x29)
		// @44: invokevirtual java.lang.StringBuilder.append(char)java.lang.StringBuilder
		// @47: invokevirtual java.lang.StringBuilder.toString()java.lang.String
		// @4A: invokestatic game.C_100181_cf.func_105695_a(java.lang.Throwable, java.lang.String)game.C_100170_cm
		// @4D: athrow
		// @4E: return
	}
	
	static final void func_102738_a(int arg0, int arg1)
	{
		// @00: iload_0
		// @01: bipush 17 (0x11)
		// @03: if_icmpge @07
		// @06: return
		// @07: getstatic java.lang.String[] game.C_100263_mb.field_106510_c
		// @0A: iload_1
		// @0B: aaload
		// @0C: putstatic java.lang.String game.C_100123_uc.field_104919_f
		// @0F: getstatic java.lang.String[] game.C_100055_ed.field_104243_b
		// @12: iload_1
		// @13: aaload
		// @14: putstatic java.lang.String game.C_100219_an.field_100877_l
		// @17: getstatic java.lang.String[] game.C_100146_bf.field_105123_d
		// @1A: iload_1
		// @1B: aaload
		// @1C: putstatic java.lang.String game.C_100077_d.field_103321_V
		// @1F: goto @4D
		// @22: astore_2
		// @23: aload_2
		// @24: new java.lang.StringBuilder
		// @27: dup
		// @28: invokespecial java.lang.StringBuilder.<init>()void
		// @2B: getstatic java.lang.String[] game.C_100129_tg.field_102741_Fb
		// @2E: bipush 8 (0x08)
		// @30: aaload
		// @31: invokevirtual java.lang.StringBuilder.append(java.lang.String)java.lang.StringBuilder
		// @34: iload_0
		// @35: invokevirtual java.lang.StringBuilder.append(int)java.lang.StringBuilder
		// @38: bipush 44 (0x2C)
		// @3A: invokevirtual java.lang.StringBuilder.append(char)java.lang.StringBuilder
		// @3D: iload_1
		// @3E: invokevirtual java.lang.StringBuilder.append(int)java.lang.StringBuilder
		// @41: bipush 41 (0x29)
		// @43: invokevirtual java.lang.StringBuilder.append(char)java.lang.StringBuilder
		// @46: invokevirtual java.lang.StringBuilder.toString()java.lang.String
		// @49: invokestatic game.C_100181_cf.func_105695_a(java.lang.Throwable, java.lang.String)game.C_100170_cm
		// @4C: athrow
		// @4D: return
	}
	
	static
	{
		// @000: bipush 12 (0x0C)
		// @002: anewarray java.lang.String
		// @005: dup
		// @006: iconst_0
		// @007: ldc ")\u0003Kd\u0012u"
		// @009: invokestatic game.C_100129_tg.func_102733_z(java.lang.String)char[]
		// @00C: invokestatic game.C_100129_tg.func_102731_z(char[])java.lang.String
		// @00F: aastore
		// @010: dup
		// @011: iconst_1
		// @012: ldc ")\u0003Km\u0011u"
		// @014: invokestatic game.C_100129_tg.func_102733_z(java.lang.String)char[]
		// @017: invokestatic game.C_100129_tg.func_102731_z(char[])java.lang.String
		// @01A: aastore
		// @01B: dup
		// @01C: iconst_2
		// @01D: ldc ")\u0003Kg\u0012u"
		// @01F: invokestatic game.C_100129_tg.func_102733_z(java.lang.String)char[]
		// @022: invokestatic game.C_100129_tg.func_102731_z(char[])java.lang.String
		// @025: aastore
		// @026: dup
		// @027: iconst_3
		// @028: ldc ")\u0003Kc\u0012u"
		// @02A: invokestatic game.C_100129_tg.func_102733_z(java.lang.String)char[]
		// @02D: invokestatic game.C_100129_tg.func_102731_z(char[])java.lang.String
		// @030: aastore
		// @031: dup
		// @032: iconst_4
		// @033: ldc ")\u0003K\u0012:3\r\u0011\u0010{"
		// @035: invokestatic game.C_100129_tg.func_102733_z(java.lang.String)char[]
		// @038: invokestatic game.C_100129_tg.func_102731_z(char[])java.lang.String
		// @03B: aastore
		// @03C: dup
		// @03D: iconst_5
		// @03E: ldc "&JK\u0000."
		// @040: invokestatic game.C_100129_tg.func_102733_z(java.lang.String)char[]
		// @043: invokestatic game.C_100129_tg.func_102731_z(char[])java.lang.String
		// @046: aastore
		// @047: dup
		// @048: bipush 6 (0x06)
		// @04A: ldc "3\u0011\tB"
		// @04C: invokestatic game.C_100129_tg.func_102733_z(java.lang.String)char[]
		// @04F: invokestatic game.C_100129_tg.func_102731_z(char[])java.lang.String
		// @052: aastore
		// @053: dup
		// @054: bipush 7 (0x07)
		// @056: ldc ")\u0003Ki\u0012u"
		// @058: invokestatic game.C_100129_tg.func_102733_z(java.lang.String)char[]
		// @05B: invokestatic game.C_100129_tg.func_102731_z(char[])java.lang.String
		// @05E: aastore
		// @05F: dup
		// @060: bipush 8 (0x08)
		// @062: ldc ")\u0003Kf\u0012u"
		// @064: invokestatic game.C_100129_tg.func_102733_z(java.lang.String)char[]
		// @067: invokestatic game.C_100129_tg.func_102731_z(char[])java.lang.String
		// @06A: aastore
		// @06B: dup
		// @06C: bipush 9 (0x09)
		// @06E: ldc ")\u0003Ke\u0012u"
		// @070: invokestatic game.C_100129_tg.func_102733_z(java.lang.String)char[]
		// @073: invokestatic game.C_100129_tg.func_102731_z(char[])java.lang.String
		// @076: aastore
		// @077: dup
		// @078: bipush 10 (0x0A)
		// @07A: ldc ")\u0003K`\u0012u"
		// @07C: invokestatic game.C_100129_tg.func_102733_z(java.lang.String)char[]
		// @07F: invokestatic game.C_100129_tg.func_102731_z(char[])java.lang.String
		// @082: aastore
		// @083: dup
		// @084: bipush 11 (0x0B)
		// @086: ldc ")\u0003Ka\u0012u"
		// @088: invokestatic game.C_100129_tg.func_102733_z(java.lang.String)char[]
		// @08B: invokestatic game.C_100129_tg.func_102731_z(char[])java.lang.String
		// @08E: aastore
		// @08F: putstatic java.lang.String[] game.C_100129_tg.field_102741_Fb
		// @092: sipush 250 (0x00FA)
		// @095: newarray int[]
		// @097: putstatic int[] game.C_100129_tg.field_102753_wb
		// @09A: bipush 32 (0x20)
		// @09C: newarray int[]
		// @09E: putstatic int[] game.C_100129_tg.field_102747_tb
		// @0A1: bipush 32 (0x20)
		// @0A3: newarray int[]
		// @0A5: putstatic int[] game.C_100129_tg.field_102752_xb
		// @0A8: iconst_0
		// @0A9: istore_0
		// @0AA: iload_0
		// @0AB: bipush 32 (0x20)
		// @0AD: if_icmpge @0CA
		// @0B0: getstatic int[] game.C_100129_tg.field_102747_tb
		// @0B3: iload_0
		// @0B4: sipush 771 (0x0303)
		// @0B7: iload_0
		// @0B8: imul
		// @0B9: iastore
		// @0BA: getstatic int[] game.C_100129_tg.field_102752_xb
		// @0BD: iload_0
		// @0BE: iload_0
		// @0BF: ldc 197376 (0x30300)
		// @0C1: imul
		// @0C2: iastore
		// @0C3: iinc #0 +1
		// @0C6: goto @0AA
		// @0C9: athrow
		// @0CA: iconst_0
		// @0CB: istore_0
		// @0CC: iload_0
		// @0CD: bipush 16 (0x10)
		// @0CF: if_icmpge @107
		// @0D2: getstatic int[] game.C_100129_tg.field_102747_tb
		// @0D5: bipush 16 (0x10)
		// @0D7: iload_0
		// @0D8: iadd
		// @0D9: getstatic int[] game.C_100129_tg.field_102747_tb
		// @0DC: bipush 16 (0x10)
		// @0DE: iload_0
		// @0DF: iadd
		// @0E0: iaload
		// @0E1: ldc 393216 (0x60000)
		// @0E3: iload_0
		// @0E4: imul
		// @0E5: invokestatic game.C_100116_ei.func_104117_a(int, int)int
		// @0E8: iastore
		// @0E9: getstatic int[] game.C_100129_tg.field_102752_xb
		// @0EC: iload_0
		// @0ED: bipush 16 (0x10)
		// @0EF: iadd
		// @0F0: getstatic int[] game.C_100129_tg.field_102752_xb
		// @0F3: iload_0
		// @0F4: bipush 16 (0x10)
		// @0F6: iadd
		// @0F7: iaload
		// @0F8: bipush 6 (0x06)
		// @0FA: iload_0
		// @0FB: imul
		// @0FC: invokestatic game.C_100116_ei.func_104117_a(int, int)int
		// @0FF: iastore
		// @100: iinc #0 +1
		// @103: goto @0CC
		// @106: athrow
		// @107: iconst_0
		// @108: istore_0
		// @109: bipush -33 (0xDF)
		// @10B: iload_0
		// @10C: iconst_m1
		// @10D: ixor
		// @10E: if_icmpge @16D
		// @111: getstatic int[] game.C_100129_tg.field_102753_wb
		// @114: iload_0
		// @115: sipush 257 (0x0101)
		// @118: iload_0
		// @119: imul
		// @11A: iastore
		// @11B: getstatic int[] game.C_100129_tg.field_102753_wb
		// @11E: iload_0
		// @11F: ineg
		// @120: bipush 63 (0x3F)
		// @122: iadd
		// @123: sipush 257 (0x0101)
		// @126: iload_0
		// @127: imul
		// @128: iastore
		// @129: getstatic int[] game.C_100129_tg.field_102753_wb
		// @12C: sipush 249 (0x00F9)
		// @12F: iconst_2
		// @130: iload_0
		// @131: imul
		// @132: isub
		// @133: iload_0
		// @134: sipush 257 (0x0101)
		// @137: imul
		// @138: ineg
		// @139: sipush 8224 (0x2020)
		// @13C: iadd
		// @13D: iload_0
		// @13E: ineg
		// @13F: bipush 32 (0x20)
		// @141: iadd
		// @142: ldc 65536 (0x10000)
		// @144: imul
		// @145: iadd
		// @146: iastore
		// @147: getstatic int[] game.C_100129_tg.field_102753_wb
		// @14A: iconst_m1
		// @14B: iconst_2
		// @14C: iload_0
		// @14D: imul
		// @14E: ineg
		// @14F: iadd
		// @150: sipush 249 (0x00F9)
		// @153: iadd
		// @154: ldc 2097152 (0x200000)
		// @156: ldc 65536 (0x10000)
		// @158: iload_0
		// @159: imul
		// @15A: isub
		// @15B: sipush 257 (0x0101)
		// @15E: bipush 32 (0x20)
		// @160: iload_0
		// @161: ineg
		// @162: iadd
		// @163: imul
		// @164: iadd
		// @165: iastore
		// @166: iinc #0 +1
		// @169: goto @109
		// @16C: athrow
		// @16D: ldc "\u000e4$y\u001d} 7a\u001d\u00187"
		// @16F: invokestatic game.C_100129_tg.func_102733_z(java.lang.String)char[]
		// @172: invokestatic game.C_100129_tg.func_102731_z(char[])java.lang.String
		// @175: putstatic java.lang.String game.C_100129_tg.field_102745_Eb
		// @178: aconst_null
		// @179: putstatic java.lang.String game.C_100129_tg.field_102743_Db
		// @17C: ldc "aAU\u0010s0\u0011\u0016Zs-\u0008\u0004WslD\u0008A!8D\u0017O'8\u0000EI20\u0001EL6;\u000b\u0017Ks-\u0008\u0004W:3\u0003EY:)\u000cEZ;8D\u0006[!/\u0001\u000bZs2\u0014\u0011G<3\u0017K"
		// @17E: invokestatic game.C_100129_tg.func_102733_z(java.lang.String)char[]
		// @181: invokestatic game.C_100129_tg.func_102731_z(char[])java.lang.String
		// @184: putstatic java.lang.String game.C_100129_tg.field_102748_Ab
		// @187: return
	}
	
	private static char[] func_102733_z(String arg0)
	{
		// @00: aload_0
		// @01: invokevirtual java.lang.String.toCharArray()char[]
		// @04: dup
		// @05: arraylength
		// @06: iconst_2
		// @07: if_icmpge @13
		// @0A: dup
		// @0B: iconst_0
		// @0C: dup2
		// @0D: caload
		// @0E: bipush 83 (0x53)
		// @10: ixor
		// @11: i2c
		// @12: castore
		// @13: areturn
	}
	
	private static String func_102731_z(char[] arg0)
	{
		// @00: aload_0
		// @01: dup
		// @02: arraylength
		// @03: swap
		// @04: iconst_0
		// @05: istore_1
		// @06: goto @4C
		// @09: dup
		// @0A: iload_1
		// @0B: dup2
		// @0C: caload
		// @0D: iload_1
		// @0E: iconst_5
		// @0F: irem
		// @10: tableswitch def: @44, for 0: @30, for 1: @35, for 2: @3A, for 3: @3F
		// @30: bipush 93 (0x5D)
		// @32: goto @46
		// @35: bipush 100 (0x64)
		// @37: goto @46
		// @3A: bipush 101 (0x65)
		// @3C: goto @46
		// @3F: bipush 46 (0x2E)
		// @41: goto @46
		// @44: bipush 83 (0x53)
		// @46: ixor
		// @47: i2c
		// @48: castore
		// @49: iinc #1 +1
		// @4C: swap
		// @4D: dup_x1
		// @4E: iload_1
		// @4F: if_icmpgt @09
		// @52: new java.lang.String
		// @55: dup_x1
		// @56: swap
		// @57: invokespecial java.lang.String.<init>(char[])void
		// @5A: invokevirtual java.lang.String.intern()java.lang.String
		// @5D: areturn
	}
}
