package game;

final class C_100194_rd extends C_100340_je
{
	private C_100309_lk field_103074_t;
	static int[] field_103075_s;
	static String field_103073_u;
	static int[] field_103076_r;
	static int field_103072_v;
	private static final String[] field_103077_z;
	
	C_100194_rd(C_100309_lk arg0, C_100309_lk arg1)
	{
		// @00: aload_0
		// @01: aload_1
		// @02: invokespecial game.C_100340_je.<init>(game.C_100309_lk)void
		// @05: aload_0
		// @06: aload_2
		// @07: putfield game.C_100309_lk game.C_100194_rd.field_103074_t
		// @0A: goto @59
		// @0D: astore_3
		// @0E: aload_3
		// @0F: new java.lang.StringBuilder
		// @12: dup
		// @13: invokespecial java.lang.StringBuilder.<init>()void
		// @16: getstatic java.lang.String[] game.C_100194_rd.field_103077_z
		// @19: iconst_4
		// @1A: aaload
		// @1B: invokevirtual java.lang.StringBuilder.append(java.lang.String)java.lang.StringBuilder
		// @1E: aload_1
		// @1F: ifnull @2B
		// @22: getstatic java.lang.String[] game.C_100194_rd.field_103077_z
		// @25: iconst_3
		// @26: aaload
		// @27: goto @30
		// @2A: athrow
		// @2B: getstatic java.lang.String[] game.C_100194_rd.field_103077_z
		// @2E: iconst_1
		// @2F: aaload
		// @30: invokevirtual java.lang.StringBuilder.append(java.lang.String)java.lang.StringBuilder
		// @33: bipush 44 (0x2C)
		// @35: invokevirtual java.lang.StringBuilder.append(char)java.lang.StringBuilder
		// @38: aload_2
		// @39: ifnull @45
		// @3C: getstatic java.lang.String[] game.C_100194_rd.field_103077_z
		// @3F: iconst_3
		// @40: aaload
		// @41: goto @4A
		// @44: athrow
		// @45: getstatic java.lang.String[] game.C_100194_rd.field_103077_z
		// @48: iconst_1
		// @49: aaload
		// @4A: invokevirtual java.lang.StringBuilder.append(java.lang.String)java.lang.StringBuilder
		// @4D: bipush 41 (0x29)
		// @4F: invokevirtual java.lang.StringBuilder.append(char)java.lang.StringBuilder
		// @52: invokevirtual java.lang.StringBuilder.toString()java.lang.String
		// @55: invokestatic game.C_100181_cf.func_105695_a(java.lang.Throwable, java.lang.String)game.C_100170_cm
		// @58: athrow
		// @59: return
	}
	
	static final void func_103069_b(byte arg0)
	{
		// @00: aconst_null
		// @01: putstatic game.C_100302_ka game.C_100291_jj.field_106874_d
		// @04: iload_0
		// @05: bipush -106 (0x96)
		// @07: if_icmplt @15
		// @0A: aconst_null
		// @0B: checkcast int[]
		// @0E: putstatic int[] game.C_100194_rd.field_103075_s
		// @11: goto @15
		// @14: athrow
		// @15: aconst_null
		// @16: putstatic game.C_100302_ka game.C_100032_gk.field_103140_X
		// @19: iconst_1
		// @1A: putstatic boolean game.C_100230_of.field_106216_k
		// @1D: aconst_null
		// @1E: putstatic game.C_100302_ka game.C_100146_bf.field_105127_a
		// @21: getstatic game.C_100302_ka game.C_100266_me.field_106650_d
		// @24: ifnonnull @2B
		// @27: goto @4D
		// @2A: athrow
		// @2B: getstatic game.C_100302_ka game.C_100152_bd.field_105207_m
		// @2E: putstatic game.C_100302_ka game.C_100127_tl.field_104946_d
		// @31: getstatic game.C_100302_ka game.C_100266_me.field_106650_d
		// @34: putstatic game.C_100302_ka game.C_100235_om.field_106296_j
		// @37: getstatic game.C_100302_ka game.C_100235_om.field_106296_j
		// @3A: iconst_m1
		// @3B: putfield int game.C_100302_ka.field_101868_Ab
		// @3E: aconst_null
		// @3F: putstatic game.C_100302_ka game.C_100266_me.field_106650_d
		// @42: aconst_null
		// @43: putstatic game.C_100302_ka game.C_100152_bd.field_105207_m
		// @46: getstatic game.C_100302_ka game.C_100235_om.field_106296_j
		// @49: iconst_m1
		// @4A: putfield int game.C_100302_ka.field_101860_K
		// @4D: aconst_null
		// @4E: putstatic game.C_100302_ka game.C_100154_sl.field_105332_e
		// @51: aconst_null
		// @52: putstatic game.C_100302_ka game.C_100210_qa.field_101054_C
		// @55: goto @79
		// @58: astore_1
		// @59: aload_1
		// @5A: new java.lang.StringBuilder
		// @5D: dup
		// @5E: invokespecial java.lang.StringBuilder.<init>()void
		// @61: getstatic java.lang.String[] game.C_100194_rd.field_103077_z
		// @64: iconst_0
		// @65: aaload
		// @66: invokevirtual java.lang.StringBuilder.append(java.lang.String)java.lang.StringBuilder
		// @69: iload_0
		// @6A: invokevirtual java.lang.StringBuilder.append(int)java.lang.StringBuilder
		// @6D: bipush 41 (0x29)
		// @6F: invokevirtual java.lang.StringBuilder.append(char)java.lang.StringBuilder
		// @72: invokevirtual java.lang.StringBuilder.toString()java.lang.String
		// @75: invokestatic game.C_100181_cf.func_105695_a(java.lang.Throwable, java.lang.String)game.C_100170_cm
		// @78: athrow
		// @79: return
	}
	
	final String func_102975_a(byte arg0, String arg1)
	{
		// @00: iload_1
		// @01: bipush 16 (0x10)
		// @03: if_icmpeq @0B
		// @06: aconst_null
		// @07: checkcast java.lang.String
		// @0A: areturn
		// @0B: aload_0
		// @0C: getfield game.C_100309_lk game.C_100194_rd.field_103074_t
		// @0F: instanceof game.C_100267_mf
		// @12: ifeq @5D
		// @15: aload_0
		// @16: getfield game.C_100309_lk game.C_100194_rd.field_103074_t
		// @19: checkcast game.C_100267_mf
		// @1C: iconst_1
		// @1D: invokeinterface game.C_100267_mf.func_103100_a(boolean)game.C_100308_lh
		// @22: astore_3
		// @23: aconst_null
		// @24: aload_3
		// @25: if_acmpeq @5D
		// @28: aload_3
		// @29: bipush 77 (0x4D)
		// @2B: invokeinterface game.C_100308_lh.func_102950_a(byte)game.C_100133_tk
		// @30: getstatic game.C_100133_tk game.C_100079_e.field_102670_tb
		// @33: if_acmpne @54
		// @36: goto @3A
		// @39: athrow
		// @3A: aload_2
		// @3B: aload_0
		// @3C: getfield game.C_100309_lk game.C_100194_rd.field_103074_t
		// @3F: getfield java.lang.String game.C_100309_lk.field_102534_C
		// @42: invokevirtual java.lang.String.equals(java.lang.Object)boolean
		// @45: ifeq @50
		// @48: goto @4C
		// @4B: athrow
		// @4C: goto @54
		// @4F: athrow
		// @50: getstatic java.lang.String game.C_100174_sb.field_105608_e
		// @53: areturn
		// @54: aload_3
		// @55: bipush -123 (0x85)
		// @57: invokeinterface game.C_100308_lh.func_102949_c(int)java.lang.String
		// @5C: areturn
		// @5D: aload_2
		// @5E: aload_0
		// @5F: getfield game.C_100309_lk game.C_100194_rd.field_103074_t
		// @62: getfield java.lang.String game.C_100309_lk.field_102534_C
		// @65: invokevirtual java.lang.String.equals(java.lang.Object)boolean
		// @68: ifeq @6F
		// @6B: goto @73
		// @6E: athrow
		// @6F: getstatic java.lang.String game.C_100174_sb.field_105608_e
		// @72: areturn
		// @73: aconst_null
		// @74: areturn
		// @75: astore_3
		// @76: aload_3
		// @77: new java.lang.StringBuilder
		// @7A: dup
		// @7B: invokespecial java.lang.StringBuilder.<init>()void
		// @7E: getstatic java.lang.String[] game.C_100194_rd.field_103077_z
		// @81: iconst_5
		// @82: aaload
		// @83: invokevirtual java.lang.StringBuilder.append(java.lang.String)java.lang.StringBuilder
		// @86: iload_1
		// @87: invokevirtual java.lang.StringBuilder.append(int)java.lang.StringBuilder
		// @8A: bipush 44 (0x2C)
		// @8C: invokevirtual java.lang.StringBuilder.append(char)java.lang.StringBuilder
		// @8F: aload_2
		// @90: ifnull @9C
		// @93: getstatic java.lang.String[] game.C_100194_rd.field_103077_z
		// @96: iconst_3
		// @97: aaload
		// @98: goto @A1
		// @9B: athrow
		// @9C: getstatic java.lang.String[] game.C_100194_rd.field_103077_z
		// @9F: iconst_1
		// @A0: aaload
		// @A1: invokevirtual java.lang.StringBuilder.append(java.lang.String)java.lang.StringBuilder
		// @A4: bipush 41 (0x29)
		// @A6: invokevirtual java.lang.StringBuilder.append(char)java.lang.StringBuilder
		// @A9: invokevirtual java.lang.StringBuilder.toString()java.lang.String
		// @AC: invokestatic game.C_100181_cf.func_105695_a(java.lang.Throwable, java.lang.String)game.C_100170_cm
		// @AF: athrow
	}
	
	final C_100133_tk func_102974_b(String arg0, int arg1)
	{
		// @00: iload_2
		// @01: ifeq @09
		// @04: aconst_null
		// @05: checkcast game.C_100133_tk
		// @08: areturn
		// @09: aload_0
		// @0A: getfield game.C_100309_lk game.C_100194_rd.field_103074_t
		// @0D: instanceof game.C_100267_mf
		// @10: ifne @17
		// @13: goto @40
		// @16: athrow
		// @17: aload_0
		// @18: getfield game.C_100309_lk game.C_100194_rd.field_103074_t
		// @1B: checkcast game.C_100267_mf
		// @1E: iconst_1
		// @1F: invokeinterface game.C_100267_mf.func_103100_a(boolean)game.C_100308_lh
		// @24: astore_3
		// @25: aconst_null
		// @26: aload_3
		// @27: if_acmpeq @40
		// @2A: aload_3
		// @2B: bipush 77 (0x4D)
		// @2D: invokeinterface game.C_100308_lh.func_102950_a(byte)game.C_100133_tk
		// @32: getstatic game.C_100133_tk game.C_100079_e.field_102670_tb
		// @35: if_acmpeq @40
		// @38: goto @3C
		// @3B: athrow
		// @3C: getstatic game.C_100133_tk game.C_100256_pk.field_100466_a
		// @3F: areturn
		// @40: aload_1
		// @41: aload_0
		// @42: getfield game.C_100309_lk game.C_100194_rd.field_103074_t
		// @45: getfield java.lang.String game.C_100309_lk.field_102534_C
		// @48: invokevirtual java.lang.String.equals(java.lang.Object)boolean
		// @4B: ifeq @55
		// @4E: getstatic game.C_100133_tk game.C_100079_e.field_102670_tb
		// @51: goto @58
		// @54: athrow
		// @55: getstatic game.C_100133_tk game.C_100256_pk.field_100466_a
		// @58: areturn
		// @59: astore_3
		// @5A: aload_3
		// @5B: new java.lang.StringBuilder
		// @5E: dup
		// @5F: invokespecial java.lang.StringBuilder.<init>()void
		// @62: getstatic java.lang.String[] game.C_100194_rd.field_103077_z
		// @65: iconst_2
		// @66: aaload
		// @67: invokevirtual java.lang.StringBuilder.append(java.lang.String)java.lang.StringBuilder
		// @6A: aload_1
		// @6B: ifnull @77
		// @6E: getstatic java.lang.String[] game.C_100194_rd.field_103077_z
		// @71: iconst_3
		// @72: aaload
		// @73: goto @7C
		// @76: athrow
		// @77: getstatic java.lang.String[] game.C_100194_rd.field_103077_z
		// @7A: iconst_1
		// @7B: aaload
		// @7C: invokevirtual java.lang.StringBuilder.append(java.lang.String)java.lang.StringBuilder
		// @7F: bipush 44 (0x2C)
		// @81: invokevirtual java.lang.StringBuilder.append(char)java.lang.StringBuilder
		// @84: iload_2
		// @85: invokevirtual java.lang.StringBuilder.append(int)java.lang.StringBuilder
		// @88: bipush 41 (0x29)
		// @8A: invokevirtual java.lang.StringBuilder.append(char)java.lang.StringBuilder
		// @8D: invokevirtual java.lang.StringBuilder.toString()java.lang.String
		// @90: invokestatic game.C_100181_cf.func_105695_a(java.lang.Throwable, java.lang.String)game.C_100170_cm
		// @93: athrow
	}
	
	static final void func_103070_a(boolean arg0, int arg1)
	{
		// @00: iconst_0
		// @01: putstatic int game.C_100188_rj.field_105737_e
		// @04: iload_1
		// @05: bipush 15 (0x0F)
		// @07: imul
		// @08: anewarray game.C_100240_oj
		// @0B: putstatic game.C_100240_oj[] game.C_100006_fj.field_103617_g
		// @0E: iconst_3
		// @0F: newarray int[]
		// @11: putstatic int[] game.C_100332_ii.field_107313_a
		// @14: iload_1
		// @15: putstatic int game.C_100271_mj.field_103432_U
		// @18: iload_0
		// @19: ifeq @23
		// @1C: aconst_null
		// @1D: checkcast int[]
		// @20: putstatic int[] game.C_100194_rd.field_103075_s
		// @23: goto @51
		// @26: astore_2
		// @27: aload_2
		// @28: new java.lang.StringBuilder
		// @2B: dup
		// @2C: invokespecial java.lang.StringBuilder.<init>()void
		// @2F: getstatic java.lang.String[] game.C_100194_rd.field_103077_z
		// @32: bipush 7 (0x07)
		// @34: aaload
		// @35: invokevirtual java.lang.StringBuilder.append(java.lang.String)java.lang.StringBuilder
		// @38: iload_0
		// @39: invokevirtual java.lang.StringBuilder.append(boolean)java.lang.StringBuilder
		// @3C: bipush 44 (0x2C)
		// @3E: invokevirtual java.lang.StringBuilder.append(char)java.lang.StringBuilder
		// @41: iload_1
		// @42: invokevirtual java.lang.StringBuilder.append(int)java.lang.StringBuilder
		// @45: bipush 41 (0x29)
		// @47: invokevirtual java.lang.StringBuilder.append(char)java.lang.StringBuilder
		// @4A: invokevirtual java.lang.StringBuilder.toString()java.lang.String
		// @4D: invokestatic game.C_100181_cf.func_105695_a(java.lang.Throwable, java.lang.String)game.C_100170_cm
		// @50: athrow
		// @51: return
	}
	
	public static void func_103071_g(int arg0)
	{
		// @00: iload_0
		// @01: bipush 37 (0x25)
		// @03: if_icmpeq @0F
		// @06: bipush -15 (0xF1)
		// @08: putstatic int game.C_100194_rd.field_103072_v
		// @0B: goto @0F
		// @0E: athrow
		// @0F: aconst_null
		// @10: putstatic java.lang.String game.C_100194_rd.field_103073_u
		// @13: aconst_null
		// @14: putstatic int[] game.C_100194_rd.field_103075_s
		// @17: aconst_null
		// @18: putstatic int[] game.C_100194_rd.field_103076_r
		// @1B: goto @40
		// @1E: astore_1
		// @1F: aload_1
		// @20: new java.lang.StringBuilder
		// @23: dup
		// @24: invokespecial java.lang.StringBuilder.<init>()void
		// @27: getstatic java.lang.String[] game.C_100194_rd.field_103077_z
		// @2A: bipush 8 (0x08)
		// @2C: aaload
		// @2D: invokevirtual java.lang.StringBuilder.append(java.lang.String)java.lang.StringBuilder
		// @30: iload_0
		// @31: invokevirtual java.lang.StringBuilder.append(int)java.lang.StringBuilder
		// @34: bipush 41 (0x29)
		// @36: invokevirtual java.lang.StringBuilder.append(char)java.lang.StringBuilder
		// @39: invokevirtual java.lang.StringBuilder.toString()java.lang.String
		// @3C: invokestatic game.C_100181_cf.func_105695_a(java.lang.Throwable, java.lang.String)game.C_100170_cm
		// @3F: athrow
		// @40: return
	}
	
	static final C_100054_ec func_103068_a(int arg0, long arg1)
	{
		// @00: iload_0
		// @01: bipush 16 (0x10)
		// @03: if_icmpeq @11
		// @06: aconst_null
		// @07: checkcast int[]
		// @0A: putstatic int[] game.C_100194_rd.field_103075_s
		// @0D: goto @11
		// @10: athrow
		// @11: getstatic game.C_100105_eg game.C_100272_mn.field_102425_G
		// @14: iload_0
		// @15: sipush -16413 (0xBFE3)
		// @18: ixor
		// @19: lload_1
		// @1A: invokevirtual game.C_100105_eg.func_104724_a(int, long)game.C_100325_id
		// @1D: checkcast game.C_100054_ec
		// @20: areturn
		// @21: astore_3
		// @22: aload_3
		// @23: new java.lang.StringBuilder
		// @26: dup
		// @27: invokespecial java.lang.StringBuilder.<init>()void
		// @2A: getstatic java.lang.String[] game.C_100194_rd.field_103077_z
		// @2D: bipush 6 (0x06)
		// @2F: aaload
		// @30: invokevirtual java.lang.StringBuilder.append(java.lang.String)java.lang.StringBuilder
		// @33: iload_0
		// @34: invokevirtual java.lang.StringBuilder.append(int)java.lang.StringBuilder
		// @37: bipush 44 (0x2C)
		// @39: invokevirtual java.lang.StringBuilder.append(char)java.lang.StringBuilder
		// @3C: lload_1
		// @3D: invokevirtual java.lang.StringBuilder.append(long)java.lang.StringBuilder
		// @40: bipush 41 (0x29)
		// @42: invokevirtual java.lang.StringBuilder.append(char)java.lang.StringBuilder
		// @45: invokevirtual java.lang.StringBuilder.toString()java.lang.String
		// @48: invokestatic game.C_100181_cf.func_105695_a(java.lang.Throwable, java.lang.String)game.C_100170_cm
		// @4B: athrow
	}
	
	static
	{
		// @000: bipush 9 (0x09)
		// @002: anewarray java.lang.String
		// @005: dup
		// @006: iconst_0
		// @007: ldc ">^9`|"
		// @009: invokestatic game.C_100194_rd.func_103067_z(java.lang.String)char[]
		// @00C: invokestatic game.C_100194_rd.func_103066_z(char[])java.lang.String
		// @00F: aastore
		// @010: dup
		// @011: iconst_1
		// @012: ldc "\"O{M"
		// @014: invokestatic game.C_100194_rd.func_103067_z(java.lang.String)char[]
		// @017: invokestatic game.C_100194_rd.func_103066_z(char[])java.lang.String
		// @01A: aastore
		// @01B: dup
		// @01C: iconst_2
		// @01D: ldc ">^9g|"
		// @01F: invokestatic game.C_100194_rd.func_103067_z(java.lang.String)char[]
		// @022: invokestatic game.C_100194_rd.func_103066_z(char[])java.lang.String
		// @025: aastore
		// @026: dup
		// @027: iconst_3
		// @028: ldc "7\u00149\u000f)"
		// @02A: invokestatic game.C_100194_rd.func_103067_z(java.lang.String)char[]
		// @02D: invokestatic game.C_100194_rd.func_103066_z(char[])java.lang.String
		// @030: aastore
		// @031: dup
		// @032: iconst_4
		// @033: ldc ">^9\u001d=\"Sc\u001f|"
		// @035: invokestatic game.C_100194_rd.func_103067_z(java.lang.String)char[]
		// @038: invokestatic game.C_100194_rd.func_103066_z(char[])java.lang.String
		// @03B: aastore
		// @03C: dup
		// @03D: iconst_5
		// @03E: ldc ">^9c|"
		// @040: invokestatic game.C_100194_rd.func_103067_z(java.lang.String)char[]
		// @043: invokestatic game.C_100194_rd.func_103066_z(char[])java.lang.String
		// @046: aastore
		// @047: dup
		// @048: bipush 6 (0x06)
		// @04A: ldc ">^9d|"
		// @04C: invokestatic game.C_100194_rd.func_103067_z(java.lang.String)char[]
		// @04F: invokestatic game.C_100194_rd.func_103066_z(char[])java.lang.String
		// @052: aastore
		// @053: dup
		// @054: bipush 7 (0x07)
		// @056: ldc ">^9b|"
		// @058: invokestatic game.C_100194_rd.func_103067_z(java.lang.String)char[]
		// @05B: invokestatic game.C_100194_rd.func_103066_z(char[])java.lang.String
		// @05E: aastore
		// @05F: dup
		// @060: bipush 8 (0x08)
		// @062: ldc ">^9e|"
		// @064: invokestatic game.C_100194_rd.func_103067_z(java.lang.String)char[]
		// @067: invokestatic game.C_100194_rd.func_103066_z(char[])java.lang.String
		// @06A: aastore
		// @06B: putstatic java.lang.String[] game.C_100194_rd.field_103077_z
		// @06E: bipush 11 (0x0B)
		// @070: newarray int[]
		// @072: dup
		// @073: iconst_0
		// @074: bipush 108 (0x6C)
		// @076: iastore
		// @077: dup
		// @078: iconst_1
		// @079: iconst_m1
		// @07A: iastore
		// @07B: dup
		// @07C: iconst_2
		// @07D: bipush 34 (0x22)
		// @07F: iastore
		// @080: dup
		// @081: iconst_3
		// @082: iconst_4
		// @083: iastore
		// @084: dup
		// @085: iconst_4
		// @086: bipush 14 (0x0E)
		// @088: iastore
		// @089: dup
		// @08A: iconst_5
		// @08B: bipush 9 (0x09)
		// @08D: iastore
		// @08E: dup
		// @08F: bipush 6 (0x06)
		// @091: bipush 16 (0x10)
		// @093: iastore
		// @094: dup
		// @095: bipush 7 (0x07)
		// @097: iconst_m1
		// @098: iastore
		// @099: dup
		// @09A: bipush 8 (0x08)
		// @09C: iconst_m1
		// @09D: iastore
		// @09E: dup
		// @09F: bipush 9 (0x09)
		// @0A1: iconst_m1
		// @0A2: iastore
		// @0A3: dup
		// @0A4: bipush 10 (0x0A)
		// @0A6: iconst_m1
		// @0A7: iastore
		// @0A8: putstatic int[] game.C_100194_rd.field_103076_r
		// @0AB: bipush 24 (0x18)
		// @0AD: newarray int[]
		// @0AF: dup
		// @0B0: iconst_0
		// @0B1: bipush 92 (0x5C)
		// @0B3: iastore
		// @0B4: dup
		// @0B5: iconst_1
		// @0B6: bipush 106 (0x6A)
		// @0B8: iastore
		// @0B9: dup
		// @0BA: iconst_2
		// @0BB: bipush 48 (0x30)
		// @0BD: iastore
		// @0BE: dup
		// @0BF: iconst_3
		// @0C0: bipush 24 (0x18)
		// @0C2: iastore
		// @0C3: dup
		// @0C4: iconst_4
		// @0C5: bipush 24 (0x18)
		// @0C7: iastore
		// @0C8: dup
		// @0C9: iconst_5
		// @0CA: bipush 24 (0x18)
		// @0CC: iastore
		// @0CD: dup
		// @0CE: bipush 6 (0x06)
		// @0D0: bipush 95 (0x5F)
		// @0D2: iastore
		// @0D3: dup
		// @0D4: bipush 7 (0x07)
		// @0D6: bipush 24 (0x18)
		// @0D8: iastore
		// @0D9: dup
		// @0DA: bipush 8 (0x08)
		// @0DC: bipush 24 (0x18)
		// @0DE: iastore
		// @0DF: dup
		// @0E0: bipush 9 (0x09)
		// @0E2: bipush 24 (0x18)
		// @0E4: iastore
		// @0E5: dup
		// @0E6: bipush 10 (0x0A)
		// @0E8: bipush 24 (0x18)
		// @0EA: iastore
		// @0EB: dup
		// @0EC: bipush 11 (0x0B)
		// @0EE: bipush 93 (0x5D)
		// @0F0: iastore
		// @0F1: dup
		// @0F2: bipush 12 (0x0C)
		// @0F4: bipush 37 (0x25)
		// @0F6: iastore
		// @0F7: dup
		// @0F8: bipush 13 (0x0D)
		// @0FA: bipush 37 (0x25)
		// @0FC: iastore
		// @0FD: dup
		// @0FE: bipush 14 (0x0E)
		// @100: bipush 37 (0x25)
		// @102: iastore
		// @103: dup
		// @104: bipush 15 (0x0F)
		// @106: bipush 52 (0x34)
		// @108: iastore
		// @109: dup
		// @10A: bipush 16 (0x10)
		// @10C: bipush 9 (0x09)
		// @10E: iastore
		// @10F: dup
		// @110: bipush 17 (0x11)
		// @112: bipush 14 (0x0E)
		// @114: iastore
		// @115: dup
		// @116: bipush 18 (0x12)
		// @118: bipush 27 (0x1B)
		// @11A: iastore
		// @11B: dup
		// @11C: bipush 19 (0x13)
		// @11E: bipush 20 (0x14)
		// @120: iastore
		// @121: dup
		// @122: bipush 20 (0x14)
		// @124: bipush 34 (0x22)
		// @126: iastore
		// @127: dup
		// @128: bipush 21 (0x15)
		// @12A: iconst_4
		// @12B: iastore
		// @12C: dup
		// @12D: bipush 22 (0x16)
		// @12F: iconst_m1
		// @130: iastore
		// @131: dup
		// @132: bipush 23 (0x17)
		// @134: iconst_m1
		// @135: iastore
		// @136: putstatic int[] game.C_100194_rd.field_103075_s
		// @139: ldc "\u0003T{Xt?RxVt<H~W58_7B<-N7G&#W7L-l\\eH1\"^d\u00015\"^7N$<UyD:8I"
		// @13B: invokestatic game.C_100194_rd.func_103067_z(java.lang.String)char[]
		// @13E: invokestatic game.C_100194_rd.func_103066_z(char[])java.lang.String
		// @141: putstatic java.lang.String game.C_100194_rd.field_103073_u
		// @144: iconst_0
		// @145: putstatic int game.C_100194_rd.field_103072_v
		// @148: return
	}
	
	private static char[] func_103067_z(String arg0)
	{
		// @00: aload_0
		// @01: invokevirtual java.lang.String.toCharArray()char[]
		// @04: dup
		// @05: arraylength
		// @06: iconst_2
		// @07: if_icmpge @13
		// @0A: dup
		// @0B: iconst_0
		// @0C: dup2
		// @0D: caload
		// @0E: bipush 84 (0x54)
		// @10: ixor
		// @11: i2c
		// @12: castore
		// @13: areturn
	}
	
	private static String func_103066_z(char[] arg0)
	{
		// @00: aload_0
		// @01: dup
		// @02: arraylength
		// @03: swap
		// @04: iconst_0
		// @05: istore_1
		// @06: goto @4C
		// @09: dup
		// @0A: iload_1
		// @0B: dup2
		// @0C: caload
		// @0D: iload_1
		// @0E: iconst_5
		// @0F: irem
		// @10: tableswitch def: @44, for 0: @30, for 1: @35, for 2: @3A, for 3: @3F
		// @30: bipush 76 (0x4C)
		// @32: goto @46
		// @35: bipush 58 (0x3A)
		// @37: goto @46
		// @3A: bipush 23 (0x17)
		// @3C: goto @46
		// @3F: bipush 33 (0x21)
		// @41: goto @46
		// @44: bipush 84 (0x54)
		// @46: ixor
		// @47: i2c
		// @48: castore
		// @49: iinc #1 +1
		// @4C: swap
		// @4D: dup_x1
		// @4E: iload_1
		// @4F: if_icmpgt @09
		// @52: new java.lang.String
		// @55: dup_x1
		// @56: swap
		// @57: invokespecial java.lang.String.<init>(char[])void
		// @5A: invokevirtual java.lang.String.intern()java.lang.String
		// @5D: areturn
	}
}
