package game;

import java.applet.Applet;

final class C_100298_ke extends C_100218_am
{
	static C_100037_wb field_103220_X;
	private C_100023_hg field_103216_S;
	int field_103210_U;
	int field_103214_Q;
	private int field_103211_T;
	static int field_103218_O;
	static String field_103212_W;
	static String field_103213_V;
	static C_100002_gf field_103217_R;
	static String field_103215_P;
	private static final String[] field_103219_Y;
	
	static final C_100240_oj func_103207_b(int arg0, int arg1, int arg2, int arg3)
	{
		// @000: getstatic int game.SteelSentinels.field_105275_O
		// @003: istore #13
		// @005: aconst_null
		// @006: astore #4
		// @008: getstatic game.C_100115_ej game.C_100081_ue.field_100670_q
		// @00B: getfield game.C_100302_ka game.C_100115_ej.field_102036_Wb
		// @00E: getfield game.C_100202_qi game.C_100302_ka.field_101891_Ob
		// @011: bipush -88 (0xA8)
		// @013: invokevirtual game.C_100202_qi.func_105905_b(byte)void
		// @016: iconst_0
		// @017: istore #5
		// @019: iconst_0
		// @01A: istore #6
		// @01C: iconst_m1
		// @01D: getstatic int game.C_100188_rj.field_105737_e
		// @020: iadd
		// @021: istore #7
		// @023: iload #7
		// @025: iconst_m1
		// @026: ixor
		// @027: iconst_m1
		// @028: if_icmpgt @184
		// @02B: getstatic game.C_100240_oj[] game.C_100006_fj.field_103617_g
		// @02E: iload #7
		// @030: aaload
		// @031: astore #8
		// @033: iconst_0
		// @034: istore #9
		// @036: getstatic boolean game.C_100272_mn.field_102435_K
		// @039: iload #13
		// @03B: ifne @188
		// @03E: ifne @097
		// @041: goto @045
		// @044: athrow
		// @045: getstatic int game.C_100271_mj.field_103432_U
		// @048: iconst_m1
		// @049: ixor
		// @04A: iload #5
		// @04C: iconst_m1
		// @04D: ixor
		// @04E: if_icmplt @059
		// @051: goto @055
		// @054: athrow
		// @055: goto @097
		// @058: athrow
		// @059: iload_0
		// @05A: sipush 5303 (0x14B7)
		// @05D: iadd
		// @05E: aload #8
		// @060: getfield int game.C_100240_oj.field_106317_a
		// @063: invokestatic game.C_100218_am.func_103108_a(int, int)int
		// @066: istore #10
		// @068: aload #8
		// @06A: iconst_m1
		// @06B: invokevirtual game.C_100240_oj.func_106309_a(int)int
		// @06E: iload #10
		// @070: if_icmplt @097
		// @073: aload #8
		// @075: getfield boolean game.C_100240_oj.field_106311_f
		// @078: ifne @094
		// @07B: goto @07F
		// @07E: athrow
		// @07F: aload #8
		// @081: getfield java.lang.String game.C_100240_oj.field_106313_d
		// @084: bipush -45 (0xD3)
		// @086: invokestatic game.C_100032_gk.func_103125_a(java.lang.String, byte)boolean
		// @089: ifeq @094
		// @08C: goto @090
		// @08F: athrow
		// @090: goto @097
		// @093: athrow
		// @094: iconst_1
		// @095: istore #9
		// @097: iload #9
		// @099: ifne @0AB
		// @09C: aload #8
		// @09E: aconst_null
		// @09F: putfield game.C_100302_ka game.C_100240_oj.field_106314_e
		// @0A2: iload #13
		// @0A4: ifeq @17C
		// @0A7: goto @0AB
		// @0AA: athrow
		// @0AB: aload #8
		// @0AD: getfield game.C_100302_ka game.C_100240_oj.field_106314_e
		// @0B0: ifnull @0C5
		// @0B3: goto @0B7
		// @0B6: athrow
		// @0B7: getstatic boolean game.C_100101_fc.field_103396_T
		// @0BA: ifne @0C5
		// @0BD: goto @0C1
		// @0C0: athrow
		// @0C1: goto @179
		// @0C4: athrow
		// @0C5: aload #8
		// @0C7: getfield game.C_100302_ka game.C_100240_oj.field_106314_e
		// @0CA: ifnonnull @0D9
		// @0CD: getstatic int game.C_100220_ac.field_106062_j
		// @0D0: iconst_1
		// @0D1: iadd
		// @0D2: putstatic int game.C_100220_ac.field_106062_j
		// @0D5: goto @0D9
		// @0D8: athrow
		// @0D9: aload #8
		// @0DB: bipush -2 (0xFE)
		// @0DD: invokestatic game.C_100033_gj.func_101898_a(game.C_100240_oj, int)java.lang.String
		// @0E0: astore #10
		// @0E2: new java.lang.StringBuilder
		// @0E5: dup
		// @0E6: invokespecial java.lang.StringBuilder.<init>()void
		// @0E9: aload #10
		// @0EB: invokevirtual java.lang.StringBuilder.append(java.lang.String)java.lang.StringBuilder
		// @0EE: aload #8
		// @0F0: getfield java.lang.String game.C_100240_oj.field_106320_l
		// @0F3: invokestatic game.C_100112_r.func_101750_c(java.lang.String)java.lang.String
		// @0F6: invokevirtual java.lang.StringBuilder.append(java.lang.String)java.lang.StringBuilder
		// @0F9: invokevirtual java.lang.StringBuilder.toString()java.lang.String
		// @0FC: astore #11
		// @0FE: iload_0
		// @0FF: bipush -99 (0x9D)
		// @101: iadd
		// @102: aload #8
		// @104: invokestatic game.C_100180_ce.func_104795_a(int, game.C_100240_oj)int
		// @107: istore #12
		// @109: aload #8
		// @10B: new game.C_100302_ka
		// @10E: dup
		// @10F: lconst_0
		// @110: getstatic game.C_100302_ka game.C_100114_q.field_100494_y
		// @113: aload #11
		// @115: invokespecial game.C_100302_ka.<init>(long, game.C_100302_ka, java.lang.String)void
		// @118: putfield game.C_100302_ka game.C_100240_oj.field_106314_e
		// @11B: aload #8
		// @11D: getfield game.C_100302_ka game.C_100240_oj.field_106314_e
		// @120: ldc 8355711 (0x7f7f7f)
		// @122: iload #12
		// @124: ldc 1958307105 (0x74b96521)
		// @126: ishr
		// @127: iand
		// @128: ineg
		// @129: iload #12
		// @12B: iadd
		// @12C: getstatic game.C_100302_ka game.C_100114_q.field_100494_y
		// @12F: getfield int game.C_100302_ka.field_101860_K
		// @132: ldc 16711422 (0xfefefe)
		// @134: iand
		// @135: ldc 554461889 (0x210c6ac1)
		// @137: ishr
		// @138: ineg
		// @139: isub
		// @13A: putfield int game.C_100302_ka.field_101860_K
		// @13D: aload #8
		// @13F: getfield game.C_100302_ka game.C_100240_oj.field_106314_e
		// @142: iload #12
		// @144: putfield int game.C_100302_ka.field_101830_gb
		// @147: aload #8
		// @149: getfield game.C_100302_ka game.C_100240_oj.field_106314_e
		// @14C: iload #12
		// @14E: ldc 145238785 (0x8a82b01)
		// @150: ishr
		// @151: ldc 8355711 (0x7f7f7f)
		// @153: iand
		// @154: ineg
		// @155: iload #12
		// @157: ldc 8355711 (0x7f7f7f)
		// @159: getstatic game.C_100302_ka game.C_100114_q.field_100494_y
		// @15C: getfield int game.C_100302_ka.field_101868_Ab
		// @15F: ldc -1294014783 (0xb2dee6c1)
		// @161: ishr
		// @162: iand
		// @163: iadd
		// @164: iadd
		// @165: putfield int game.C_100302_ka.field_101868_Ab
		// @168: iload #6
		// @16A: iload_3
		// @16B: iadd
		// @16C: istore #6
		// @16E: aload #8
		// @170: getfield game.C_100302_ka game.C_100240_oj.field_106314_e
		// @173: getstatic game.C_100112_r game.C_100053_vn.field_102827_cb
		// @176: putfield game.C_100112_r game.C_100302_ka.field_101845_sb
		// @179: iinc #5 +1
		// @17C: iinc #7 +255
		// @17F: iload #13
		// @181: ifeq @023
		// @184: iconst_0
		// @185: istore #7
		// @187: iconst_0
		// @188: istore #8
		// @18A: getstatic int game.C_100188_rj.field_105737_e
		// @18D: iconst_m1
		// @18E: ixor
		// @18F: iload #8
		// @191: iconst_m1
		// @192: ixor
		// @193: if_icmpge @1F8
		// @196: getstatic game.C_100240_oj[] game.C_100006_fj.field_103617_g
		// @199: iload #8
		// @19B: aaload
		// @19C: astore #9
		// @19E: aload #9
		// @1A0: getfield game.C_100302_ka game.C_100240_oj.field_106314_e
		// @1A3: iload #13
		// @1A5: ifne @22C
		// @1A8: ifnull @1F0
		// @1AB: goto @1AF
		// @1AE: athrow
		// @1AF: getstatic game.C_100115_ej game.C_100081_ue.field_100670_q
		// @1B2: getfield game.C_100302_ka game.C_100115_ej.field_102036_Wb
		// @1B5: bipush -80 (0xB0)
		// @1B7: aload #9
		// @1B9: getfield game.C_100302_ka game.C_100240_oj.field_106314_e
		// @1BC: invokevirtual game.C_100302_ka.func_101824_b(int, game.C_100302_ka)void
		// @1BF: aload #9
		// @1C1: getfield game.C_100302_ka game.C_100240_oj.field_106314_e
		// @1C4: iload_2
		// @1C5: iload_3
		// @1C6: iconst_m1
		// @1C7: iload #7
		// @1C9: aload #9
		// @1CB: getfield game.C_100302_ka game.C_100240_oj.field_106314_e
		// @1CE: ldc 218000 (0x35390)
		// @1D0: invokevirtual game.C_100302_ka.func_101818_j(int)int
		// @1D3: invokevirtual game.C_100302_ka.func_101825_a(int, int, int, int, int)void
		// @1D6: iload #7
		// @1D8: iload_3
		// @1D9: iadd
		// @1DA: istore #7
		// @1DC: iconst_0
		// @1DD: aload #9
		// @1DF: getfield game.C_100302_ka game.C_100240_oj.field_106314_e
		// @1E2: getfield int game.C_100302_ka.field_101854_N
		// @1E5: if_icmpne @1EC
		// @1E8: goto @1F0
		// @1EB: athrow
		// @1EC: aload #9
		// @1EE: astore #4
		// @1F0: iinc #8 +1
		// @1F3: iload #13
		// @1F5: ifeq @18A
		// @1F8: iload #7
		// @1FA: ineg
		// @1FB: iload #6
		// @1FD: ineg
		// @1FE: getstatic game.C_100115_ej game.C_100081_ue.field_100670_q
		// @201: getfield game.C_100302_ka game.C_100115_ej.field_102036_Wb
		// @204: getfield int game.C_100302_ka.field_101848_lb
		// @207: isub
		// @208: isub
		// @209: getstatic game.C_100115_ej game.C_100081_ue.field_100670_q
		// @20C: getfield game.C_100302_ka game.C_100115_ej.field_102036_Wb
		// @20F: getfield int game.C_100302_ka.field_101832_tb
		// @212: ineg
		// @213: isub
		// @214: istore #8
		// @216: getstatic game.C_100115_ej game.C_100081_ue.field_100670_q
		// @219: getfield game.C_100302_ka game.C_100115_ej.field_102036_Wb
		// @21C: dup
		// @21D: getfield int game.C_100302_ka.field_101848_lb
		// @220: iload #8
		// @222: isub
		// @223: putfield int game.C_100302_ka.field_101848_lb
		// @226: getstatic game.C_100115_ej game.C_100081_ue.field_100670_q
		// @229: getfield game.C_100302_ka game.C_100115_ej.field_102036_Wb
		// @22C: dup
		// @22D: getfield int game.C_100302_ka.field_101880_Gb
		// @230: iload #8
		// @232: iadd
		// @233: putfield int game.C_100302_ka.field_101880_Gb
		// @236: getstatic boolean game.C_100101_fc.field_103396_T
		// @239: ifne @240
		// @23C: goto @24B
		// @23F: athrow
		// @240: getstatic game.C_100115_ej game.C_100081_ue.field_100670_q
		// @243: getfield game.C_100302_ka game.C_100115_ej.field_102036_Wb
		// @246: iload #7
		// @248: putfield int game.C_100302_ka.field_101848_lb
		// @24B: getstatic boolean game.C_100101_fc.field_103396_T
		// @24E: ifeq @284
		// @251: getstatic game.C_100115_ej game.C_100081_ue.field_100670_q
		// @254: getfield game.C_100302_ka game.C_100115_ej.field_102036_Wb
		// @257: iconst_0
		// @258: putfield int game.C_100302_ka.field_101843_Tb
		// @25B: getstatic game.C_100115_ej game.C_100081_ue.field_100670_q
		// @25E: getfield game.C_100302_ka game.C_100115_ej.field_102036_Wb
		// @261: getstatic game.C_100115_ej game.C_100081_ue.field_100670_q
		// @264: getfield game.C_100302_ka game.C_100115_ej.field_102036_Wb
		// @267: getfield int game.C_100302_ka.field_101848_lb
		// @26A: ineg
		// @26B: getstatic game.C_100115_ej game.C_100081_ue.field_100670_q
		// @26E: getfield game.C_100302_ka game.C_100115_ej.field_102040_Zb
		// @271: getfield int game.C_100302_ka.field_101848_lb
		// @274: iadd
		// @275: putfield int game.C_100302_ka.field_101880_Gb
		// @278: iconst_1
		// @279: putstatic boolean game.C_100149_bi.field_105158_a
		// @27C: iconst_0
		// @27D: putstatic boolean game.C_100101_fc.field_103396_T
		// @280: goto @284
		// @283: athrow
		// @284: getstatic game.C_100115_ej game.C_100081_ue.field_100670_q
		// @287: getfield game.C_100302_ka game.C_100115_ej.field_102036_Wb
		// @28A: iload #7
		// @28C: getstatic game.C_100115_ej game.C_100081_ue.field_100670_q
		// @28F: getfield game.C_100302_ka game.C_100115_ej.field_102036_Wb
		// @292: getfield int game.C_100302_ka.field_101848_lb
		// @295: isub
		// @296: putfield int game.C_100302_ka.field_101832_tb
		// @299: getstatic boolean game.C_100230_of.field_106216_k
		// @29C: ifeq @2B2
		// @29F: aconst_null
		// @2A0: getstatic game.C_100302_ka game.C_100154_sl.field_105332_e
		// @2A3: if_acmpeq @2B2
		// @2A6: goto @2AA
		// @2A9: athrow
		// @2AA: iconst_1
		// @2AB: putstatic boolean game.C_100149_bi.field_105158_a
		// @2AE: goto @2B2
		// @2B1: athrow
		// @2B2: getstatic game.C_100115_ej game.C_100081_ue.field_100670_q
		// @2B5: getfield game.C_100302_ka game.C_100115_ej.field_102040_Zb
		// @2B8: getfield int game.C_100302_ka.field_101848_lb
		// @2BB: getstatic game.C_100115_ej game.C_100081_ue.field_100670_q
		// @2BE: getfield game.C_100302_ka game.C_100115_ej.field_102036_Wb
		// @2C1: getfield int game.C_100302_ka.field_101848_lb
		// @2C4: ineg
		// @2C5: iadd
		// @2C6: getstatic game.C_100115_ej game.C_100081_ue.field_100670_q
		// @2C9: getfield game.C_100302_ka game.C_100115_ej.field_102036_Wb
		// @2CC: getfield int game.C_100302_ka.field_101832_tb
		// @2CF: ineg
		// @2D0: iadd
		// @2D1: istore #9
		// @2D3: getstatic boolean game.C_100149_bi.field_105158_a
		// @2D6: ifeq @2F3
		// @2D9: getstatic game.C_100115_ej game.C_100081_ue.field_100670_q
		// @2DC: getfield game.C_100302_ka game.C_100115_ej.field_102036_Wb
		// @2DF: getstatic game.C_100115_ej game.C_100081_ue.field_100670_q
		// @2E2: getfield game.C_100302_ka game.C_100115_ej.field_102036_Wb
		// @2E5: getfield int game.C_100302_ka.field_101880_Gb
		// @2E8: ineg
		// @2E9: iload #9
		// @2EB: iadd
		// @2EC: putfield int game.C_100302_ka.field_101843_Tb
		// @2EF: goto @2F3
		// @2F2: athrow
		// @2F3: iload_0
		// @2F4: iconst_5
		// @2F5: if_icmpeq @305
		// @2F8: iconst_0
		// @2F9: aconst_null
		// @2FA: checkcast java.lang.CharSequence
		// @2FD: invokestatic game.C_100298_ke.func_103205_a(boolean, java.lang.CharSequence)boolean
		// @300: pop
		// @301: goto @305
		// @304: athrow
		// @305: getstatic game.C_100115_ej game.C_100081_ue.field_100670_q
		// @308: iload_3
		// @309: iconst_1
		// @30A: bipush -128 (0x80)
		// @30C: iload_1
		// @30D: iload_3
		// @30E: imul
		// @30F: iconst_2
		// @310: imul
		// @311: invokevirtual game.C_100115_ej.func_102028_a(int, boolean, int, int)void
		// @314: iload #9
		// @316: iconst_m1
		// @317: ixor
		// @318: getstatic game.C_100115_ej game.C_100081_ue.field_100670_q
		// @31B: getfield game.C_100302_ka game.C_100115_ej.field_102036_Wb
		// @31E: getfield int game.C_100302_ka.field_101843_Tb
		// @321: getstatic game.C_100115_ej game.C_100081_ue.field_100670_q
		// @324: getfield game.C_100302_ka game.C_100115_ej.field_102036_Wb
		// @327: getfield int game.C_100302_ka.field_101880_Gb
		// @32A: iadd
		// @32B: iconst_m1
		// @32C: ixor
		// @32D: if_icmpne @335
		// @330: iconst_1
		// @331: goto @336
		// @334: athrow
		// @335: iconst_0
		// @336: putstatic boolean game.C_100149_bi.field_105158_a
		// @339: aload #4
		// @33B: areturn
		// @33C: astore #4
		// @33E: aload #4
		// @340: new java.lang.StringBuilder
		// @343: dup
		// @344: invokespecial java.lang.StringBuilder.<init>()void
		// @347: getstatic java.lang.String[] game.C_100298_ke.field_103219_Y
		// @34A: bipush 16 (0x10)
		// @34C: aaload
		// @34D: invokevirtual java.lang.StringBuilder.append(java.lang.String)java.lang.StringBuilder
		// @350: iload_0
		// @351: invokevirtual java.lang.StringBuilder.append(int)java.lang.StringBuilder
		// @354: bipush 44 (0x2C)
		// @356: invokevirtual java.lang.StringBuilder.append(char)java.lang.StringBuilder
		// @359: iload_1
		// @35A: invokevirtual java.lang.StringBuilder.append(int)java.lang.StringBuilder
		// @35D: bipush 44 (0x2C)
		// @35F: invokevirtual java.lang.StringBuilder.append(char)java.lang.StringBuilder
		// @362: iload_2
		// @363: invokevirtual java.lang.StringBuilder.append(int)java.lang.StringBuilder
		// @366: bipush 44 (0x2C)
		// @368: invokevirtual java.lang.StringBuilder.append(char)java.lang.StringBuilder
		// @36B: iload_3
		// @36C: invokevirtual java.lang.StringBuilder.append(int)java.lang.StringBuilder
		// @36F: bipush 41 (0x29)
		// @371: invokevirtual java.lang.StringBuilder.append(char)java.lang.StringBuilder
		// @374: invokevirtual java.lang.StringBuilder.toString()java.lang.String
		// @377: invokestatic game.C_100181_cf.func_105695_a(java.lang.Throwable, java.lang.String)game.C_100170_cm
		// @37A: athrow
	}
	
	public static void func_103209_e(byte arg0)
	{
		// @00: aconst_null
		// @01: putstatic java.lang.String game.C_100298_ke.field_103215_P
		// @04: aconst_null
		// @05: putstatic java.lang.String game.C_100298_ke.field_103213_V
		// @08: aconst_null
		// @09: putstatic java.lang.String game.C_100298_ke.field_103212_W
		// @0C: iload_0
		// @0D: bipush 115 (0x73)
		// @0F: if_icmpeq @23
		// @12: bipush 83 (0x53)
		// @14: aconst_null
		// @15: checkcast java.lang.String
		// @18: aconst_null
		// @19: checkcast java.applet.Applet
		// @1C: invokestatic game.C_100298_ke.func_103206_a(int, java.lang.String, java.applet.Applet)void
		// @1F: goto @23
		// @22: athrow
		// @23: aconst_null
		// @24: putstatic game.C_100002_gf game.C_100298_ke.field_103217_R
		// @27: aconst_null
		// @28: putstatic game.C_100037_wb game.C_100298_ke.field_103220_X
		// @2B: goto @50
		// @2E: astore_1
		// @2F: aload_1
		// @30: new java.lang.StringBuilder
		// @33: dup
		// @34: invokespecial java.lang.StringBuilder.<init>()void
		// @37: getstatic java.lang.String[] game.C_100298_ke.field_103219_Y
		// @3A: bipush 18 (0x12)
		// @3C: aaload
		// @3D: invokevirtual java.lang.StringBuilder.append(java.lang.String)java.lang.StringBuilder
		// @40: iload_0
		// @41: invokevirtual java.lang.StringBuilder.append(int)java.lang.StringBuilder
		// @44: bipush 41 (0x29)
		// @46: invokevirtual java.lang.StringBuilder.append(char)java.lang.StringBuilder
		// @49: invokevirtual java.lang.StringBuilder.toString()java.lang.String
		// @4C: invokestatic game.C_100181_cf.func_105695_a(java.lang.Throwable, java.lang.String)game.C_100170_cm
		// @4F: athrow
		// @50: return
	}
	
	final int func_103208_a(byte arg0, int arg1)
	{
		// @00: iload_2
		// @01: iflt @1C
		// @04: aload_0
		// @05: getfield game.C_100023_hg game.C_100298_ke.field_103216_S
		// @08: iconst_0
		// @09: invokevirtual game.C_100023_hg.func_103910_b(int)int
		// @0C: iconst_m1
		// @0D: ixor
		// @0E: iload_2
		// @0F: iconst_m1
		// @10: ixor
		// @11: if_icmpge @1C
		// @14: goto @18
		// @17: athrow
		// @18: goto @1E
		// @1B: athrow
		// @1C: iconst_m1
		// @1D: ireturn
		// @1E: iload_1
		// @1F: bipush 28 (0x1C)
		// @21: if_icmpge @31
		// @24: iconst_0
		// @25: aconst_null
		// @26: checkcast java.lang.CharSequence
		// @29: invokestatic game.C_100298_ke.func_103205_a(boolean, java.lang.CharSequence)boolean
		// @2C: pop
		// @2D: goto @31
		// @30: athrow
		// @31: aload_0
		// @32: getfield game.C_100023_hg game.C_100298_ke.field_103216_S
		// @35: iload_2
		// @36: bipush -48 (0xD0)
		// @38: invokevirtual game.C_100023_hg.func_103911_a(int, byte)int
		// @3B: ireturn
		// @3C: astore_3
		// @3D: aload_3
		// @3E: new java.lang.StringBuilder
		// @41: dup
		// @42: invokespecial java.lang.StringBuilder.<init>()void
		// @45: getstatic java.lang.String[] game.C_100298_ke.field_103219_Y
		// @48: bipush 11 (0x0B)
		// @4A: aaload
		// @4B: invokevirtual java.lang.StringBuilder.append(java.lang.String)java.lang.StringBuilder
		// @4E: iload_1
		// @4F: invokevirtual java.lang.StringBuilder.append(int)java.lang.StringBuilder
		// @52: bipush 44 (0x2C)
		// @54: invokevirtual java.lang.StringBuilder.append(char)java.lang.StringBuilder
		// @57: iload_2
		// @58: invokevirtual java.lang.StringBuilder.append(int)java.lang.StringBuilder
		// @5B: bipush 41 (0x29)
		// @5D: invokevirtual java.lang.StringBuilder.append(char)java.lang.StringBuilder
		// @60: invokevirtual java.lang.StringBuilder.toString()java.lang.String
		// @63: invokestatic game.C_100181_cf.func_105695_a(java.lang.Throwable, java.lang.String)game.C_100170_cm
		// @66: athrow
	}
	
	static final void func_103206_a(int arg0, String arg1, Applet arg2)
	{
		// @000: aload_1
		// @001: putstatic java.lang.String game.C_100186_rl.field_105723_e
		// @004: iload_0
		// @005: bipush -20 (0xEC)
		// @007: if_icmple @00B
		// @00A: return
		// @00B: aload_2
		// @00C: getstatic java.lang.String[] game.C_100298_ke.field_103219_Y
		// @00F: bipush 6 (0x06)
		// @011: aaload
		// @012: invokevirtual java.applet.Applet.getParameter(java.lang.String)java.lang.String
		// @015: astore_3
		// @016: aload_2
		// @017: getstatic java.lang.String[] game.C_100298_ke.field_103219_Y
		// @01A: iconst_4
		// @01B: aaload
		// @01C: invokevirtual java.applet.Applet.getParameter(java.lang.String)java.lang.String
		// @01F: astore #4
		// @021: new java.lang.StringBuilder
		// @024: dup
		// @025: invokespecial java.lang.StringBuilder.<init>()void
		// @028: aload_3
		// @029: invokevirtual java.lang.StringBuilder.append(java.lang.String)java.lang.StringBuilder
		// @02C: getstatic java.lang.String[] game.C_100298_ke.field_103219_Y
		// @02F: iconst_3
		// @030: aaload
		// @031: invokevirtual java.lang.StringBuilder.append(java.lang.String)java.lang.StringBuilder
		// @034: aload_1
		// @035: invokevirtual java.lang.StringBuilder.append(java.lang.String)java.lang.StringBuilder
		// @038: getstatic java.lang.String[] game.C_100298_ke.field_103219_Y
		// @03B: iconst_1
		// @03C: aaload
		// @03D: invokevirtual java.lang.StringBuilder.append(java.lang.String)java.lang.StringBuilder
		// @040: aload #4
		// @042: invokevirtual java.lang.StringBuilder.append(java.lang.String)java.lang.StringBuilder
		// @045: invokevirtual java.lang.StringBuilder.toString()java.lang.String
		// @048: astore #5
		// @04A: aload_1
		// @04B: invokevirtual java.lang.String.length()int
		// @04E: iconst_m1
		// @04F: ixor
		// @050: iconst_m1
		// @051: if_icmpne @074
		// @054: new java.lang.StringBuilder
		// @057: dup
		// @058: invokespecial java.lang.StringBuilder.<init>()void
		// @05B: aload #5
		// @05D: invokevirtual java.lang.StringBuilder.append(java.lang.String)java.lang.StringBuilder
		// @060: getstatic java.lang.String[] game.C_100298_ke.field_103219_Y
		// @063: bipush 10 (0x0A)
		// @065: aaload
		// @066: invokevirtual java.lang.StringBuilder.append(java.lang.String)java.lang.StringBuilder
		// @069: invokevirtual java.lang.StringBuilder.toString()java.lang.String
		// @06C: astore #5
		// @06E: getstatic int game.SteelSentinels.field_105275_O
		// @071: ifeq @0AD
		// @074: new java.lang.StringBuilder
		// @077: dup
		// @078: invokespecial java.lang.StringBuilder.<init>()void
		// @07B: aload #5
		// @07D: invokevirtual java.lang.StringBuilder.append(java.lang.String)java.lang.StringBuilder
		// @080: getstatic java.lang.String[] game.C_100298_ke.field_103219_Y
		// @083: iconst_5
		// @084: aaload
		// @085: invokevirtual java.lang.StringBuilder.append(java.lang.String)java.lang.StringBuilder
		// @088: bipush -46 (0xD2)
		// @08A: bipush -51 (0xCD)
		// @08C: invokestatic game.C_100198_qn.func_105828_a(byte)long
		// @08F: ldc2_w 94608000000
		// @092: ladd
		// @093: invokestatic game.C_100159_sn.func_105399_a(byte, long)java.lang.String
		// @096: invokevirtual java.lang.StringBuilder.append(java.lang.String)java.lang.StringBuilder
		// @099: getstatic java.lang.String[] game.C_100298_ke.field_103219_Y
		// @09C: bipush 7 (0x07)
		// @09E: aaload
		// @09F: invokevirtual java.lang.StringBuilder.append(java.lang.String)java.lang.StringBuilder
		// @0A2: ldc2_w 94608000
		// @0A5: invokevirtual java.lang.StringBuilder.append(long)java.lang.StringBuilder
		// @0A8: invokevirtual java.lang.StringBuilder.toString()java.lang.String
		// @0AB: astore #5
		// @0AD: new java.lang.StringBuilder
		// @0B0: dup
		// @0B1: invokespecial java.lang.StringBuilder.<init>()void
		// @0B4: getstatic java.lang.String[] game.C_100298_ke.field_103219_Y
		// @0B7: bipush 8 (0x08)
		// @0B9: aaload
		// @0BA: invokevirtual java.lang.StringBuilder.append(java.lang.String)java.lang.StringBuilder
		// @0BD: aload #5
		// @0BF: invokevirtual java.lang.StringBuilder.append(java.lang.String)java.lang.StringBuilder
		// @0C2: ldc "\""
		// @0C4: invokevirtual java.lang.StringBuilder.append(java.lang.String)java.lang.StringBuilder
		// @0C7: invokevirtual java.lang.StringBuilder.toString()java.lang.String
		// @0CA: sipush -1492 (0xFA2C)
		// @0CD: aload_2
		// @0CE: invokestatic game.C_100175_cl.func_105615_a(java.lang.String, int, java.applet.Applet)void
		// @0D1: goto @0D5
		// @0D4: astore_3
		// @0D5: iconst_0
		// @0D6: aload_2
		// @0D7: invokestatic game.C_100277_nc.func_106689_a(boolean, java.applet.Applet)void
		// @0DA: goto @134
		// @0DD: astore_3
		// @0DE: aload_3
		// @0DF: new java.lang.StringBuilder
		// @0E2: dup
		// @0E3: invokespecial java.lang.StringBuilder.<init>()void
		// @0E6: getstatic java.lang.String[] game.C_100298_ke.field_103219_Y
		// @0E9: iconst_0
		// @0EA: aaload
		// @0EB: invokevirtual java.lang.StringBuilder.append(java.lang.String)java.lang.StringBuilder
		// @0EE: iload_0
		// @0EF: invokevirtual java.lang.StringBuilder.append(int)java.lang.StringBuilder
		// @0F2: bipush 44 (0x2C)
		// @0F4: invokevirtual java.lang.StringBuilder.append(char)java.lang.StringBuilder
		// @0F7: aload_1
		// @0F8: ifnull @105
		// @0FB: getstatic java.lang.String[] game.C_100298_ke.field_103219_Y
		// @0FE: bipush 9 (0x09)
		// @100: aaload
		// @101: goto @10A
		// @104: athrow
		// @105: getstatic java.lang.String[] game.C_100298_ke.field_103219_Y
		// @108: iconst_2
		// @109: aaload
		// @10A: invokevirtual java.lang.StringBuilder.append(java.lang.String)java.lang.StringBuilder
		// @10D: bipush 44 (0x2C)
		// @10F: invokevirtual java.lang.StringBuilder.append(char)java.lang.StringBuilder
		// @112: aload_2
		// @113: ifnull @120
		// @116: getstatic java.lang.String[] game.C_100298_ke.field_103219_Y
		// @119: bipush 9 (0x09)
		// @11B: aaload
		// @11C: goto @125
		// @11F: athrow
		// @120: getstatic java.lang.String[] game.C_100298_ke.field_103219_Y
		// @123: iconst_2
		// @124: aaload
		// @125: invokevirtual java.lang.StringBuilder.append(java.lang.String)java.lang.StringBuilder
		// @128: bipush 41 (0x29)
		// @12A: invokevirtual java.lang.StringBuilder.append(char)java.lang.StringBuilder
		// @12D: invokevirtual java.lang.StringBuilder.toString()java.lang.String
		// @130: invokestatic game.C_100181_cf.func_105695_a(java.lang.Throwable, java.lang.String)game.C_100170_cm
		// @133: athrow
		// @134: return
	}
	
	static final int func_103201_b(int arg0, byte arg1)
	{
		// @00: getstatic int game.SteelSentinels.field_105275_O
		// @03: istore #4
		// @05: aconst_null
		// @06: putstatic game.C_100331_ie game.C_100075_uj.field_100654_v
		// @09: aconst_null
		// @0A: putstatic game.C_100286_nl game.C_100019_wl.field_103842_d
		// @0D: iconst_0
		// @0E: putstatic int game.C_100055_ed.field_104239_f
		// @11: getstatic int game.C_100209_qb.field_102691_Hb
		// @14: istore_2
		// @15: getstatic int game.C_100031_gl.field_103965_e
		// @18: putstatic int game.C_100209_qb.field_102691_Hb
		// @1B: iload_2
		// @1C: putstatic int game.C_100031_gl.field_103965_e
		// @1F: bipush 51 (0x33)
		// @21: iload_0
		// @22: if_icmpne @35
		// @25: getstatic game.C_100104_v game.C_100311_le.field_104714_w
		// @28: iconst_2
		// @29: putfield int game.C_100104_v.field_104694_n
		// @2C: iload #4
		// @2E: ifeq @5A
		// @31: goto @35
		// @34: athrow
		// @35: iload_0
		// @36: bipush 50 (0x32)
		// @38: if_icmpeq @4F
		// @3B: goto @3F
		// @3E: athrow
		// @3F: getstatic game.C_100104_v game.C_100311_le.field_104714_w
		// @42: iconst_1
		// @43: putfield int game.C_100104_v.field_104694_n
		// @46: iload #4
		// @48: ifeq @5A
		// @4B: goto @4F
		// @4E: athrow
		// @4F: getstatic game.C_100104_v game.C_100311_le.field_104714_w
		// @52: iconst_5
		// @53: putfield int game.C_100104_v.field_104694_n
		// @56: goto @5A
		// @59: athrow
		// @5A: getstatic game.C_100104_v game.C_100311_le.field_104714_w
		// @5D: dup
		// @5E: getfield int game.C_100104_v.field_104697_m
		// @61: iconst_1
		// @62: iadd
		// @63: putfield int game.C_100104_v.field_104697_m
		// @66: getstatic game.C_100104_v game.C_100311_le.field_104714_w
		// @69: getfield int game.C_100104_v.field_104697_m
		// @6C: iconst_2
		// @6D: if_icmplt @7C
		// @70: iload_0
		// @71: bipush 51 (0x33)
		// @73: if_icmpne @7C
		// @76: goto @7A
		// @79: athrow
		// @7A: iconst_2
		// @7B: ireturn
		// @7C: getstatic game.C_100104_v game.C_100311_le.field_104714_w
		// @7F: getfield int game.C_100104_v.field_104697_m
		// @82: iconst_2
		// @83: if_icmplt @98
		// @86: iload_0
		// @87: iconst_m1
		// @88: ixor
		// @89: bipush -51 (0xCD)
		// @8B: if_icmpeq @96
		// @8E: goto @92
		// @91: athrow
		// @92: goto @98
		// @95: athrow
		// @96: iconst_5
		// @97: ireturn
		// @98: iconst_4
		// @99: getstatic game.C_100104_v game.C_100311_le.field_104714_w
		// @9C: getfield int game.C_100104_v.field_104697_m
		// @9F: if_icmple @A6
		// @A2: goto @A8
		// @A5: athrow
		// @A6: iconst_1
		// @A7: ireturn
		// @A8: bipush -94 (0xA2)
		// @AA: bipush -31 (0xE1)
		// @AC: iload_1
		// @AD: isub
		// @AE: bipush 61 (0x3D)
		// @B0: idiv
		// @B1: idiv
		// @B2: istore_3
		// @B3: iconst_m1
		// @B4: ireturn
		// @B5: astore_2
		// @B6: aload_2
		// @B7: new java.lang.StringBuilder
		// @BA: dup
		// @BB: invokespecial java.lang.StringBuilder.<init>()void
		// @BE: getstatic java.lang.String[] game.C_100298_ke.field_103219_Y
		// @C1: bipush 14 (0x0E)
		// @C3: aaload
		// @C4: invokevirtual java.lang.StringBuilder.append(java.lang.String)java.lang.StringBuilder
		// @C7: iload_0
		// @C8: invokevirtual java.lang.StringBuilder.append(int)java.lang.StringBuilder
		// @CB: bipush 44 (0x2C)
		// @CD: invokevirtual java.lang.StringBuilder.append(char)java.lang.StringBuilder
		// @D0: iload_1
		// @D1: invokevirtual java.lang.StringBuilder.append(int)java.lang.StringBuilder
		// @D4: bipush 41 (0x29)
		// @D6: invokevirtual java.lang.StringBuilder.append(char)java.lang.StringBuilder
		// @D9: invokevirtual java.lang.StringBuilder.toString()java.lang.String
		// @DC: invokestatic game.C_100181_cf.func_105695_a(java.lang.Throwable, java.lang.String)game.C_100170_cm
		// @DF: athrow
	}
	
	final int func_103203_a(byte arg0)
	{
		// @00: iload_1
		// @01: bipush -123 (0x85)
		// @03: if_icmplt @09
		// @06: bipush -88 (0xA8)
		// @08: ireturn
		// @09: aload_0
		// @0A: getfield game.C_100023_hg game.C_100298_ke.field_103216_S
		// @0D: iconst_0
		// @0E: invokevirtual game.C_100023_hg.func_103910_b(int)int
		// @11: ireturn
		// @12: astore_2
		// @13: aload_2
		// @14: new java.lang.StringBuilder
		// @17: dup
		// @18: invokespecial java.lang.StringBuilder.<init>()void
		// @1B: getstatic java.lang.String[] game.C_100298_ke.field_103219_Y
		// @1E: bipush 12 (0x0C)
		// @20: aaload
		// @21: invokevirtual java.lang.StringBuilder.append(java.lang.String)java.lang.StringBuilder
		// @24: iload_1
		// @25: invokevirtual java.lang.StringBuilder.append(int)java.lang.StringBuilder
		// @28: bipush 41 (0x29)
		// @2A: invokevirtual java.lang.StringBuilder.append(char)java.lang.StringBuilder
		// @2D: invokevirtual java.lang.StringBuilder.toString()java.lang.String
		// @30: invokestatic game.C_100181_cf.func_105695_a(java.lang.Throwable, java.lang.String)game.C_100170_cm
		// @33: athrow
	}
	
	final boolean func_102520_a(int arg0, C_100336_im arg1, int arg2, int arg3, int arg4, int arg5, int arg6)
	{
		// @000: getstatic int game.SteelSentinels.field_105275_O
		// @003: istore #14
		// @005: aload_0
		// @006: iload_1
		// @007: aload_2
		// @008: bipush 92 (0x5C)
		// @00A: iload #4
		// @00C: iload #5
		// @00E: iload #6
		// @010: iload #7
		// @012: invokespecial game.C_100218_am.func_102520_a(int, game.C_100336_im, int, int, int, int, int)boolean
		// @015: ifeq @0EB
		// @018: aload_0
		// @019: getfield int game.C_100298_ke.field_103210_U
		// @01C: ineg
		// @01D: iload_1
		// @01E: iadd
		// @01F: iload #6
		// @021: ineg
		// @022: iadd
		// @023: istore #8
		// @025: iconst_2
		// @026: aload_0
		// @027: getfield int game.C_100298_ke.field_103210_U
		// @02A: imul
		// @02B: ineg
		// @02C: aload_0
		// @02D: getfield int game.C_100298_ke.field_102537_l
		// @030: iadd
		// @031: istore #9
		// @033: iload #9
		// @035: iload #8
		// @037: if_icmpge @03E
		// @03A: iload #9
		// @03C: istore #8
		// @03E: iconst_0
		// @03F: iload #8
		// @041: if_icmpgt @048
		// @044: goto @04B
		// @047: athrow
		// @048: iconst_0
		// @049: istore #8
		// @04B: aload_0
		// @04C: getfield int game.C_100298_ke.field_103211_T
		// @04F: iload #8
		// @051: imul
		// @052: iload #9
		// @054: idiv
		// @055: istore #8
		// @057: bipush -2 (0xFE)
		// @059: iload #7
		// @05B: iconst_m1
		// @05C: ixor
		// @05D: if_icmpne @074
		// @060: aload_0
		// @061: getfield game.C_100023_hg game.C_100298_ke.field_103216_S
		// @064: bipush -100 (0x9C)
		// @066: iload #8
		// @068: invokevirtual game.C_100023_hg.func_103916_a(byte, int)void
		// @06B: iload #14
		// @06D: ifeq @0E9
		// @070: goto @074
		// @073: athrow
		// @074: iconst_2
		// @075: iload #7
		// @077: if_icmpeq @082
		// @07A: goto @07E
		// @07D: athrow
		// @07E: goto @0E9
		// @081: athrow
		// @082: ldc 2147483647 (0x7fffffff)
		// @084: istore #10
		// @086: iconst_m1
		// @087: istore #11
		// @089: iconst_0
		// @08A: istore #12
		// @08C: iload #12
		// @08E: aload_0
		// @08F: getfield game.C_100023_hg game.C_100298_ke.field_103216_S
		// @092: iconst_0
		// @093: invokevirtual game.C_100023_hg.func_103910_b(int)int
		// @096: if_icmpge @0D4
		// @099: iload #8
		// @09B: ineg
		// @09C: aload_0
		// @09D: getfield game.C_100023_hg game.C_100298_ke.field_103216_S
		// @0A0: iload #12
		// @0A2: bipush 121 (0x79)
		// @0A4: invokevirtual game.C_100023_hg.func_103911_a(int, byte)int
		// @0A7: iadd
		// @0A8: istore #13
		// @0AA: iload #13
		// @0AC: iload #13
		// @0AE: imul
		// @0AF: istore #13
		// @0B1: iload #10
		// @0B3: iload #13
		// @0B5: iload #14
		// @0B7: ifne @0D9
		// @0BA: if_icmpgt @0C4
		// @0BD: goto @0C1
		// @0C0: athrow
		// @0C1: goto @0CC
		// @0C4: iload #13
		// @0C6: istore #10
		// @0C8: iload #12
		// @0CA: istore #11
		// @0CC: iinc #12 +1
		// @0CF: iload #14
		// @0D1: ifeq @08C
		// @0D4: iconst_m1
		// @0D5: iload #11
		// @0D7: iconst_m1
		// @0D8: ixor
		// @0D9: if_icmpge @0DF
		// @0DC: goto @0E9
		// @0DF: aload_0
		// @0E0: getfield game.C_100023_hg game.C_100298_ke.field_103216_S
		// @0E3: iload #11
		// @0E5: iconst_m1
		// @0E6: invokevirtual game.C_100023_hg.func_103917_a(int, int)void
		// @0E9: iconst_1
		// @0EA: ireturn
		// @0EB: bipush -119 (0x89)
		// @0ED: iload_3
		// @0EE: bipush 32 (0x20)
		// @0F0: isub
		// @0F1: bipush 52 (0x34)
		// @0F3: idiv
		// @0F4: idiv
		// @0F5: istore #8
		// @0F7: iconst_0
		// @0F8: ireturn
		// @0F9: astore #8
		// @0FB: aload #8
		// @0FD: new java.lang.StringBuilder
		// @100: dup
		// @101: invokespecial java.lang.StringBuilder.<init>()void
		// @104: getstatic java.lang.String[] game.C_100298_ke.field_103219_Y
		// @107: bipush 20 (0x14)
		// @109: aaload
		// @10A: invokevirtual java.lang.StringBuilder.append(java.lang.String)java.lang.StringBuilder
		// @10D: iload_1
		// @10E: invokevirtual java.lang.StringBuilder.append(int)java.lang.StringBuilder
		// @111: bipush 44 (0x2C)
		// @113: invokevirtual java.lang.StringBuilder.append(char)java.lang.StringBuilder
		// @116: aload_2
		// @117: ifnull @124
		// @11A: getstatic java.lang.String[] game.C_100298_ke.field_103219_Y
		// @11D: bipush 9 (0x09)
		// @11F: aaload
		// @120: goto @129
		// @123: athrow
		// @124: getstatic java.lang.String[] game.C_100298_ke.field_103219_Y
		// @127: iconst_2
		// @128: aaload
		// @129: invokevirtual java.lang.StringBuilder.append(java.lang.String)java.lang.StringBuilder
		// @12C: bipush 44 (0x2C)
		// @12E: invokevirtual java.lang.StringBuilder.append(char)java.lang.StringBuilder
		// @131: iload_3
		// @132: invokevirtual java.lang.StringBuilder.append(int)java.lang.StringBuilder
		// @135: bipush 44 (0x2C)
		// @137: invokevirtual java.lang.StringBuilder.append(char)java.lang.StringBuilder
		// @13A: iload #4
		// @13C: invokevirtual java.lang.StringBuilder.append(int)java.lang.StringBuilder
		// @13F: bipush 44 (0x2C)
		// @141: invokevirtual java.lang.StringBuilder.append(char)java.lang.StringBuilder
		// @144: iload #5
		// @146: invokevirtual java.lang.StringBuilder.append(int)java.lang.StringBuilder
		// @149: bipush 44 (0x2C)
		// @14B: invokevirtual java.lang.StringBuilder.append(char)java.lang.StringBuilder
		// @14E: iload #6
		// @150: invokevirtual java.lang.StringBuilder.append(int)java.lang.StringBuilder
		// @153: bipush 44 (0x2C)
		// @155: invokevirtual java.lang.StringBuilder.append(char)java.lang.StringBuilder
		// @158: iload #7
		// @15A: invokevirtual java.lang.StringBuilder.append(int)java.lang.StringBuilder
		// @15D: bipush 41 (0x29)
		// @15F: invokevirtual java.lang.StringBuilder.append(char)java.lang.StringBuilder
		// @162: invokevirtual java.lang.StringBuilder.toString()java.lang.String
		// @165: invokestatic game.C_100181_cf.func_105695_a(java.lang.Throwable, java.lang.String)game.C_100170_cm
		// @168: athrow
	}
	
	static final boolean func_103205_a(boolean arg0, CharSequence arg1)
	{
		// @00: iload_0
		// @01: iconst_1
		// @02: if_icmpeq @12
		// @05: iconst_1
		// @06: aconst_null
		// @07: checkcast java.lang.CharSequence
		// @0A: invokestatic game.C_100298_ke.func_103205_a(boolean, java.lang.CharSequence)boolean
		// @0D: pop
		// @0E: goto @12
		// @11: athrow
		// @12: bipush 10 (0x0A)
		// @14: aload_1
		// @15: iconst_1
		// @16: bipush 119 (0x77)
		// @18: invokestatic game.C_100257_ln.func_106478_a(int, java.lang.CharSequence, boolean, byte)boolean
		// @1B: ireturn
		// @1C: astore_2
		// @1D: aload_2
		// @1E: new java.lang.StringBuilder
		// @21: dup
		// @22: invokespecial java.lang.StringBuilder.<init>()void
		// @25: getstatic java.lang.String[] game.C_100298_ke.field_103219_Y
		// @28: bipush 22 (0x16)
		// @2A: aaload
		// @2B: invokevirtual java.lang.StringBuilder.append(java.lang.String)java.lang.StringBuilder
		// @2E: iload_0
		// @2F: invokevirtual java.lang.StringBuilder.append(boolean)java.lang.StringBuilder
		// @32: bipush 44 (0x2C)
		// @34: invokevirtual java.lang.StringBuilder.append(char)java.lang.StringBuilder
		// @37: aload_1
		// @38: ifnull @45
		// @3B: getstatic java.lang.String[] game.C_100298_ke.field_103219_Y
		// @3E: bipush 9 (0x09)
		// @40: aaload
		// @41: goto @4A
		// @44: athrow
		// @45: getstatic java.lang.String[] game.C_100298_ke.field_103219_Y
		// @48: iconst_2
		// @49: aaload
		// @4A: invokevirtual java.lang.StringBuilder.append(java.lang.String)java.lang.StringBuilder
		// @4D: bipush 41 (0x29)
		// @4F: invokevirtual java.lang.StringBuilder.append(char)java.lang.StringBuilder
		// @52: invokevirtual java.lang.StringBuilder.toString()java.lang.String
		// @55: invokestatic game.C_100181_cf.func_105695_a(java.lang.Throwable, java.lang.String)game.C_100170_cm
		// @58: athrow
	}
	
	static final byte[] func_103200_b(String arg0, int arg1)
	{
		// @00: iload_1
		// @01: bipush 104 (0x68)
		// @03: if_icmpgt @0F
		// @06: bipush -108 (0x94)
		// @08: invokestatic game.C_100298_ke.func_103209_e(byte)void
		// @0B: goto @0F
		// @0E: athrow
		// @0F: getstatic game.C_100098_h game.C_100265_mh.field_106633_q
		// @12: aload_0
		// @13: ldc ""
		// @15: bipush 123 (0x7B)
		// @17: invokevirtual game.C_100098_h.func_104608_a(java.lang.String, java.lang.String, int)byte[]
		// @1A: areturn
		// @1B: astore_2
		// @1C: aload_2
		// @1D: new java.lang.StringBuilder
		// @20: dup
		// @21: invokespecial java.lang.StringBuilder.<init>()void
		// @24: getstatic java.lang.String[] game.C_100298_ke.field_103219_Y
		// @27: bipush 13 (0x0D)
		// @29: aaload
		// @2A: invokevirtual java.lang.StringBuilder.append(java.lang.String)java.lang.StringBuilder
		// @2D: aload_0
		// @2E: ifnull @3B
		// @31: getstatic java.lang.String[] game.C_100298_ke.field_103219_Y
		// @34: bipush 9 (0x09)
		// @36: aaload
		// @37: goto @40
		// @3A: athrow
		// @3B: getstatic java.lang.String[] game.C_100298_ke.field_103219_Y
		// @3E: iconst_2
		// @3F: aaload
		// @40: invokevirtual java.lang.StringBuilder.append(java.lang.String)java.lang.StringBuilder
		// @43: bipush 44 (0x2C)
		// @45: invokevirtual java.lang.StringBuilder.append(char)java.lang.StringBuilder
		// @48: iload_1
		// @49: invokevirtual java.lang.StringBuilder.append(int)java.lang.StringBuilder
		// @4C: bipush 41 (0x29)
		// @4E: invokevirtual java.lang.StringBuilder.append(char)java.lang.StringBuilder
		// @51: invokevirtual java.lang.StringBuilder.toString()java.lang.String
		// @54: invokestatic game.C_100181_cf.func_105695_a(java.lang.Throwable, java.lang.String)game.C_100170_cm
		// @57: athrow
	}
	
	static final void func_103197_a(C_100098_h arg0, boolean arg1, C_100098_h arg2, boolean arg3, C_100098_h arg4)
	{
		// @00: bipush 44 (0x2C)
		// @02: ldc ""
		// @04: invokestatic game.C_100156_sk.func_105377_a(byte, java.lang.String)game.C_100321_hi
		// @07: putstatic game.C_100321_hi game.C_100106_ef.field_104753_e
		// @0A: getstatic game.C_100321_hi game.C_100106_ef.field_104753_e
		// @0D: bipush 122 (0x7A)
		// @0F: iload_3
		// @10: invokevirtual game.C_100321_hi.func_107214_a(int, boolean)void
		// @13: aload #4
		// @15: iconst_0
		// @16: aload_2
		// @17: aload_0
		// @18: invokestatic game.C_100244_pe.func_106372_a(game.C_100098_h, int, game.C_100098_h, game.C_100098_h)void
		// @1B: bipush 97 (0x61)
		// @1D: invokestatic game.C_100142_bk.func_105083_b(byte)void
		// @20: getstatic game.C_100068_vc game.C_100220_ac.field_106056_e
		// @23: putstatic game.C_100068_vc game.C_100191_rg.field_100845_o
		// @26: getstatic game.C_100068_vc game.C_100220_ac.field_106056_e
		// @29: putstatic game.C_100068_vc game.C_100222_aa.field_106086_a
		// @2C: goto @AE
		// @2F: astore #5
		// @31: aload #5
		// @33: new java.lang.StringBuilder
		// @36: dup
		// @37: invokespecial java.lang.StringBuilder.<init>()void
		// @3A: getstatic java.lang.String[] game.C_100298_ke.field_103219_Y
		// @3D: bipush 19 (0x13)
		// @3F: aaload
		// @40: invokevirtual java.lang.StringBuilder.append(java.lang.String)java.lang.StringBuilder
		// @43: aload_0
		// @44: ifnull @51
		// @47: getstatic java.lang.String[] game.C_100298_ke.field_103219_Y
		// @4A: bipush 9 (0x09)
		// @4C: aaload
		// @4D: goto @56
		// @50: athrow
		// @51: getstatic java.lang.String[] game.C_100298_ke.field_103219_Y
		// @54: iconst_2
		// @55: aaload
		// @56: invokevirtual java.lang.StringBuilder.append(java.lang.String)java.lang.StringBuilder
		// @59: bipush 44 (0x2C)
		// @5B: invokevirtual java.lang.StringBuilder.append(char)java.lang.StringBuilder
		// @5E: iload_1
		// @5F: invokevirtual java.lang.StringBuilder.append(boolean)java.lang.StringBuilder
		// @62: bipush 44 (0x2C)
		// @64: invokevirtual java.lang.StringBuilder.append(char)java.lang.StringBuilder
		// @67: aload_2
		// @68: ifnull @75
		// @6B: getstatic java.lang.String[] game.C_100298_ke.field_103219_Y
		// @6E: bipush 9 (0x09)
		// @70: aaload
		// @71: goto @7A
		// @74: athrow
		// @75: getstatic java.lang.String[] game.C_100298_ke.field_103219_Y
		// @78: iconst_2
		// @79: aaload
		// @7A: invokevirtual java.lang.StringBuilder.append(java.lang.String)java.lang.StringBuilder
		// @7D: bipush 44 (0x2C)
		// @7F: invokevirtual java.lang.StringBuilder.append(char)java.lang.StringBuilder
		// @82: iload_3
		// @83: invokevirtual java.lang.StringBuilder.append(boolean)java.lang.StringBuilder
		// @86: bipush 44 (0x2C)
		// @88: invokevirtual java.lang.StringBuilder.append(char)java.lang.StringBuilder
		// @8B: aload #4
		// @8D: ifnull @9A
		// @90: getstatic java.lang.String[] game.C_100298_ke.field_103219_Y
		// @93: bipush 9 (0x09)
		// @95: aaload
		// @96: goto @9F
		// @99: athrow
		// @9A: getstatic java.lang.String[] game.C_100298_ke.field_103219_Y
		// @9D: iconst_2
		// @9E: aaload
		// @9F: invokevirtual java.lang.StringBuilder.append(java.lang.String)java.lang.StringBuilder
		// @A2: bipush 41 (0x29)
		// @A4: invokevirtual java.lang.StringBuilder.append(char)java.lang.StringBuilder
		// @A7: invokevirtual java.lang.StringBuilder.toString()java.lang.String
		// @AA: invokestatic game.C_100181_cf.func_105695_a(java.lang.Throwable, java.lang.String)game.C_100170_cm
		// @AD: athrow
		// @AE: return
	}
	
	private C_100298_ke() throws Throwable
	{
		// @00: aload_0
		// @01: invokespecial game.C_100218_am.<init>()void
		// @04: new java.lang.Error
		// @07: dup
		// @08: invokespecial java.lang.Error.<init>()void
		// @0B: athrow
		// @0C: astore_1
		// @0D: aload_1
		// @0E: getstatic java.lang.String[] game.C_100298_ke.field_103219_Y
		// @11: bipush 15 (0x0F)
		// @13: aaload
		// @14: invokestatic game.C_100181_cf.func_105695_a(java.lang.Throwable, java.lang.String)game.C_100170_cm
		// @17: athrow
	}
	
	final int func_103202_j(int arg0)
	{
		// @00: iload_1
		// @01: bipush 86 (0x56)
		// @03: if_icmpge @11
		// @06: aconst_null
		// @07: checkcast java.lang.String
		// @0A: putstatic java.lang.String game.C_100298_ke.field_103213_V
		// @0D: goto @11
		// @10: athrow
		// @11: aload_0
		// @12: getfield int game.C_100298_ke.field_103211_T
		// @15: ireturn
		// @16: astore_2
		// @17: aload_2
		// @18: new java.lang.StringBuilder
		// @1B: dup
		// @1C: invokespecial java.lang.StringBuilder.<init>()void
		// @1F: getstatic java.lang.String[] game.C_100298_ke.field_103219_Y
		// @22: bipush 21 (0x15)
		// @24: aaload
		// @25: invokevirtual java.lang.StringBuilder.append(java.lang.String)java.lang.StringBuilder
		// @28: iload_1
		// @29: invokevirtual java.lang.StringBuilder.append(int)java.lang.StringBuilder
		// @2C: bipush 41 (0x29)
		// @2E: invokevirtual java.lang.StringBuilder.append(char)java.lang.StringBuilder
		// @31: invokevirtual java.lang.StringBuilder.toString()java.lang.String
		// @34: invokestatic game.C_100181_cf.func_105695_a(java.lang.Throwable, java.lang.String)game.C_100170_cm
		// @37: athrow
	}
	
	static final void func_103204_c(int arg0, byte arg1)
	{
		// @00: iload_1
		// @01: bipush -37 (0xDB)
		// @03: if_icmple @11
		// @06: aconst_null
		// @07: checkcast java.lang.String
		// @0A: putstatic java.lang.String game.C_100298_ke.field_103212_W
		// @0D: goto @11
		// @10: athrow
		// @11: getstatic game.C_100278_nd game.C_100115_ej.field_102043_Yb
		// @14: astore_2
		// @15: aload_2
		// @16: iload_0
		// @17: bipush 123 (0x7B)
		// @19: invokevirtual game.C_100278_nd.func_101189_h(int, int)void
		// @1C: aload_2
		// @1D: sipush 7838 (0x1E9E)
		// @20: iconst_1
		// @21: invokevirtual game.C_100278_nd.func_101169_f(int, int)void
		// @24: aload_2
		// @25: sipush 7838 (0x1E9E)
		// @28: iconst_2
		// @29: invokevirtual game.C_100278_nd.func_101169_f(int, int)void
		// @2C: goto @5A
		// @2F: astore_2
		// @30: aload_2
		// @31: new java.lang.StringBuilder
		// @34: dup
		// @35: invokespecial java.lang.StringBuilder.<init>()void
		// @38: getstatic java.lang.String[] game.C_100298_ke.field_103219_Y
		// @3B: bipush 17 (0x11)
		// @3D: aaload
		// @3E: invokevirtual java.lang.StringBuilder.append(java.lang.String)java.lang.StringBuilder
		// @41: iload_0
		// @42: invokevirtual java.lang.StringBuilder.append(int)java.lang.StringBuilder
		// @45: bipush 44 (0x2C)
		// @47: invokevirtual java.lang.StringBuilder.append(char)java.lang.StringBuilder
		// @4A: iload_1
		// @4B: invokevirtual java.lang.StringBuilder.append(int)java.lang.StringBuilder
		// @4E: bipush 41 (0x29)
		// @50: invokevirtual java.lang.StringBuilder.append(char)java.lang.StringBuilder
		// @53: invokevirtual java.lang.StringBuilder.toString()java.lang.String
		// @56: invokestatic game.C_100181_cf.func_105695_a(java.lang.Throwable, java.lang.String)game.C_100170_cm
		// @59: athrow
		// @5A: return
	}
	
	static
	{
		// @000: bipush 23 (0x17)
		// @002: anewarray java.lang.String
		// @005: dup
		// @006: iconst_0
		// @007: ldc "\u0014?1\u0014$"
		// @009: invokestatic game.C_100298_ke.func_103199_z(java.lang.String)char[]
		// @00C: invokestatic game.C_100298_ke.func_103198_z(char[])java.lang.String
		// @00F: aastore
		// @010: dup
		// @011: iconst_1
		// @012: ldc "Dzi4~\u000c3p?1Na?!m\u000b2\"~7_>p<m\u00164\""
		// @014: invokestatic game.C_100298_ke.func_103199_z(java.lang.String)char[]
		// @017: invokestatic game.C_100298_ke.func_103198_z(char[])java.lang.String
		// @01A: aastore
		// @01B: dup
		// @01C: iconst_2
		// @01D: ldc "\u0011/s="
		// @01F: invokestatic game.C_100298_ke.func_103199_z(java.lang.String)char[]
		// @022: invokestatic game.C_100298_ke.func_103198_z(char[])java.lang.String
		// @025: aastore
		// @026: dup
		// @027: iconst_3
		// @028: ldc "\u000c?k%e\u0011=ll"
		// @02A: invokestatic game.C_100298_ke.func_103199_z(java.lang.String)char[]
		// @02D: invokestatic game.C_100298_ke.func_103198_z(char[])java.lang.String
		// @030: aastore
		// @031: dup
		// @032: iconst_4
		// @033: ldc "\u001c5p:e\u001a2p\"x"
		// @035: invokestatic game.C_100298_ke.func_103199_z(java.lang.String)char[]
		// @038: invokestatic game.C_100298_ke.func_103198_z(char[])java.lang.String
		// @03B: aastore
		// @03C: dup
		// @03D: iconst_5
		// @03E: ldc "DzZ)|\u0016(z\"1"
		// @040: invokestatic game.C_100298_ke.func_103199_z(java.lang.String)char[]
		// @043: invokestatic game.C_100298_ke.func_103198_z(char[])java.lang.String
		// @046: aastore
		// @047: dup
		// @048: bipush 6 (0x06)
		// @04A: ldc "\u001c5p:e\u001a*m4j\u0016\""
		// @04C: invokestatic game.C_100298_ke.func_103199_z(java.lang.String)char[]
		// @04F: invokestatic game.C_100298_ke.func_103198_z(char[])java.lang.String
		// @052: aastore
		// @053: dup
		// @054: bipush 7 (0x07)
		// @056: ldc "DzR0tR\u001bx41"
		// @058: invokestatic game.C_100298_ke.func_103199_z(java.lang.String)char[]
		// @05B: invokestatic game.C_100298_ke.func_103198_z(char[])java.lang.String
		// @05E: aastore
		// @05F: dup
		// @060: bipush 8 (0x08)
		// @062: ldc "\u001b5|$a\u001a4k\u007fo\u00105t8iBx"
		// @064: invokestatic game.C_100298_ke.func_103199_z(java.lang.String)char[]
		// @067: invokestatic game.C_100298_ke.func_103198_z(char[])java.lang.String
		// @06A: aastore
		// @06B: dup
		// @06C: bipush 9 (0x09)
		// @06E: ldc "\u0004t1\u007fq"
		// @070: invokestatic game.C_100298_ke.func_103199_z(java.lang.String)char[]
		// @073: invokestatic game.C_100298_ke.func_103198_z(char[])java.lang.String
		// @076: aastore
		// @077: dup
		// @078: bipush 10 (0x0A)
		// @07A: ldc "DzZ)|\u0016(z\"1+2j},Ok2\u001bm\u0011w.h;Oz/a6Oj%a<_\u001dR\u00057_\u0017~)!>=zl<"
		// @07C: invokestatic game.C_100298_ke.func_103199_z(java.lang.String)char[]
		// @07F: invokestatic game.C_100298_ke.func_103198_z(char[])java.lang.String
		// @082: aastore
		// @083: dup
		// @084: bipush 11 (0x0B)
		// @086: ldc "\u0014?1\u0010$"
		// @088: invokestatic game.C_100298_ke.func_103199_z(java.lang.String)char[]
		// @08B: invokestatic game.C_100298_ke.func_103198_z(char[])java.lang.String
		// @08E: aastore
		// @08F: dup
		// @090: bipush 12 (0x0C)
		// @092: ldc "\u0014?1\u0013MW"
		// @094: invokestatic game.C_100298_ke.func_103199_z(java.lang.String)char[]
		// @097: invokestatic game.C_100298_ke.func_103198_z(char[])java.lang.String
		// @09A: aastore
		// @09B: dup
		// @09C: bipush 13 (0x0D)
		// @09E: ldc "\u0014?1\u0007$"
		// @0A0: invokestatic game.C_100298_ke.func_103199_z(java.lang.String)char[]
		// @0A3: invokestatic game.C_100298_ke.func_103198_z(char[])java.lang.String
		// @0A6: aastore
		// @0A7: dup
		// @0A8: bipush 14 (0x0E)
		// @0AA: ldc "\u0014?1\u0019$"
		// @0AC: invokestatic game.C_100298_ke.func_103199_z(java.lang.String)char[]
		// @0AF: invokestatic game.C_100298_ke.func_103198_z(char[])java.lang.String
		// @0B2: aastore
		// @0B3: dup
		// @0B4: bipush 15 (0x0F)
		// @0B6: ldc "\u0014?1me\u00113ko$V"
		// @0B8: invokestatic game.C_100298_ke.func_103199_z(java.lang.String)char[]
		// @0BB: invokestatic game.C_100298_ke.func_103198_z(char[])java.lang.String
		// @0BE: aastore
		// @0BF: dup
		// @0C0: bipush 16 (0x10)
		// @0C2: ldc "\u0014?1\u0015$"
		// @0C4: invokestatic game.C_100298_ke.func_103199_z(java.lang.String)char[]
		// @0C7: invokestatic game.C_100298_ke.func_103198_z(char[])java.lang.String
		// @0CA: aastore
		// @0CB: dup
		// @0CC: bipush 17 (0x11)
		// @0CE: ldc "\u0014?1\u0019MW"
		// @0D0: invokestatic game.C_100298_ke.func_103199_z(java.lang.String)char[]
		// @0D3: invokestatic game.C_100298_ke.func_103198_z(char[])java.lang.String
		// @0D6: aastore
		// @0D7: dup
		// @0D8: bipush 18 (0x12)
		// @0DA: ldc "\u0014?1\u0018$"
		// @0DC: invokestatic game.C_100298_ke.func_103199_z(java.lang.String)char[]
		// @0DF: invokestatic game.C_100298_ke.func_103198_z(char[])java.lang.String
		// @0E2: aastore
		// @0E3: dup
		// @0E4: bipush 19 (0x13)
		// @0E6: ldc "\u0014?1\u0016MW"
		// @0E8: invokestatic game.C_100298_ke.func_103199_z(java.lang.String)char[]
		// @0EB: invokestatic game.C_100298_ke.func_103198_z(char[])java.lang.String
		// @0EE: aastore
		// @0EF: dup
		// @0F0: bipush 20 (0x14)
		// @0F2: ldc "\u0014?1\u0004$"
		// @0F4: invokestatic game.C_100298_ke.func_103199_z(java.lang.String)char[]
		// @0F7: invokestatic game.C_100298_ke.func_103198_z(char[])java.lang.String
		// @0FA: aastore
		// @0FB: dup
		// @0FC: bipush 21 (0x15)
		// @0FE: ldc "\u0014?1\u0013$"
		// @100: invokestatic game.C_100298_ke.func_103199_z(java.lang.String)char[]
		// @103: invokestatic game.C_100298_ke.func_103198_z(char[])java.lang.String
		// @106: aastore
		// @107: dup
		// @108: bipush 22 (0x16)
		// @10A: ldc "\u0014?1\u0003$"
		// @10C: invokestatic game.C_100298_ke.func_103199_z(java.lang.String)char[]
		// @10F: invokestatic game.C_100298_ke.func_103198_z(char[])java.lang.String
		// @112: aastore
		// @113: putstatic java.lang.String[] game.C_100298_ke.field_103219_Y
		// @116: new game.C_100037_wb
		// @119: dup
		// @11A: sipush 540 (0x021C)
		// @11D: sipush 140 (0x008C)
		// @120: invokespecial game.C_100037_wb.<init>(int, int)void
		// @123: putstatic game.C_100037_wb game.C_100298_ke.field_103220_X
		// @126: ldc "+2v\",\u0010*k8c\u0011z|0b\u00115kqn\u001az|>a\u001d3q4h_-v%d_.w4,\u001c/m#i\u0011.?\"i\u000b.v?k\u000czy>~Ez?"
		// @128: invokestatic game.C_100298_ke.func_103199_z(java.lang.String)char[]
		// @12B: invokestatic game.C_100298_ke.func_103198_z(char[])java.lang.String
		// @12E: putstatic java.lang.String game.C_100298_ke.field_103212_W
		// @131: iconst_0
		// @132: putstatic int game.C_100298_ke.field_103218_O
		// @135: ldc ",*z2x\u001e.z"
		// @137: invokestatic game.C_100298_ke.func_103199_z(java.lang.String)char[]
		// @13A: invokestatic game.C_100298_ke.func_103198_z(char[])java.lang.String
		// @13D: putstatic java.lang.String game.C_100298_ke.field_103213_V
		// @140: ldc "15?9e\u00182l2c\r?l"
		// @142: invokestatic game.C_100298_ke.func_103199_z(java.lang.String)char[]
		// @145: invokestatic game.C_100298_ke.func_103198_z(char[])java.lang.String
		// @148: putstatic java.lang.String game.C_100298_ke.field_103215_P
		// @14B: return
	}
	
	private static char[] func_103199_z(String arg0)
	{
		// @00: aload_0
		// @01: invokevirtual java.lang.String.toCharArray()char[]
		// @04: dup
		// @05: arraylength
		// @06: iconst_2
		// @07: if_icmpge @13
		// @0A: dup
		// @0B: iconst_0
		// @0C: dup2
		// @0D: caload
		// @0E: bipush 12 (0x0C)
		// @10: ixor
		// @11: i2c
		// @12: castore
		// @13: areturn
	}
	
	private static String func_103198_z(char[] arg0)
	{
		// @00: aload_0
		// @01: dup
		// @02: arraylength
		// @03: swap
		// @04: iconst_0
		// @05: istore_1
		// @06: goto @4C
		// @09: dup
		// @0A: iload_1
		// @0B: dup2
		// @0C: caload
		// @0D: iload_1
		// @0E: iconst_5
		// @0F: irem
		// @10: tableswitch def: @44, for 0: @30, for 1: @35, for 2: @3A, for 3: @3F
		// @30: bipush 127 (0x7F)
		// @32: goto @46
		// @35: bipush 90 (0x5A)
		// @37: goto @46
		// @3A: bipush 31 (0x1F)
		// @3C: goto @46
		// @3F: bipush 81 (0x51)
		// @41: goto @46
		// @44: bipush 12 (0x0C)
		// @46: ixor
		// @47: i2c
		// @48: castore
		// @49: iinc #1 +1
		// @4C: swap
		// @4D: dup_x1
		// @4E: iload_1
		// @4F: if_icmpgt @09
		// @52: new java.lang.String
		// @55: dup_x1
		// @56: swap
		// @57: invokespecial java.lang.String.<init>(char[])void
		// @5A: invokevirtual java.lang.String.intern()java.lang.String
		// @5D: areturn
	}
}
