package game;

final class C_100115_ej extends C_100302_ka
{
	static C_100278_nd field_102043_Yb;
	C_100302_ka field_102040_Zb;
	C_100302_ka field_102036_Wb;
	static C_100153_be field_102041_Xb;
	C_100231_oc field_102038_Vb;
	static String field_102035_dc;
	static C_100130_tf field_102039_ac;
	static String field_102042_bc;
	static C_100302_ka field_102045_cc;
	static int field_102037_Ub;
	private static final String[] field_102044_ec;
	
	C_100115_ej(String arg0, C_100302_ka arg1, C_100302_ka arg2, C_100231_oc arg3)
	{
		// @00: aload_0
		// @01: aload_1
		// @02: sipush 4000 (0x0FA0)
		// @05: invokestatic game.C_100171_cn.func_105553_a(java.lang.CharSequence, int)long
		// @08: aload_2
		// @09: aload_3
		// @0A: aload #4
		// @0C: invokespecial game.C_100115_ej.<init>(long, game.C_100302_ka, game.C_100302_ka, game.C_100231_oc)void
		// @0F: return
	}
	
	final void func_102030_a(int arg0, int arg1, int arg2, int arg3, int arg4, int arg5, int arg6)
	{
		// @00: aload_0
		// @01: iload_2
		// @02: putfield int game.C_100115_ej.field_101848_lb
		// @05: aload_0
		// @06: iload #6
		// @08: putfield int game.C_100115_ej.field_101880_Gb
		// @0B: aload_0
		// @0C: iload_3
		// @0D: putfield int game.C_100115_ej.field_101841_Pb
		// @10: aload_0
		// @11: iload #5
		// @13: putfield int game.C_100115_ej.field_101886_Kb
		// @16: aload_0
		// @17: iload #7
		// @19: iload #4
		// @1B: bipush -75 (0xB5)
		// @1D: iadd
		// @1E: iload_1
		// @1F: invokespecial game.C_100115_ej.func_102033_a(int, int, int)void
		// @22: iload #4
		// @24: ifeq @2F
		// @27: aload_0
		// @28: aconst_null
		// @29: checkcast game.C_100302_ka
		// @2C: putfield game.C_100302_ka game.C_100115_ej.field_102040_Zb
		// @2F: goto @90
		// @32: astore #8
		// @34: aload #8
		// @36: new java.lang.StringBuilder
		// @39: dup
		// @3A: invokespecial java.lang.StringBuilder.<init>()void
		// @3D: getstatic java.lang.String[] game.C_100115_ej.field_102044_ec
		// @40: bipush 11 (0x0B)
		// @42: aaload
		// @43: invokevirtual java.lang.StringBuilder.append(java.lang.String)java.lang.StringBuilder
		// @46: iload_1
		// @47: invokevirtual java.lang.StringBuilder.append(int)java.lang.StringBuilder
		// @4A: bipush 44 (0x2C)
		// @4C: invokevirtual java.lang.StringBuilder.append(char)java.lang.StringBuilder
		// @4F: iload_2
		// @50: invokevirtual java.lang.StringBuilder.append(int)java.lang.StringBuilder
		// @53: bipush 44 (0x2C)
		// @55: invokevirtual java.lang.StringBuilder.append(char)java.lang.StringBuilder
		// @58: iload_3
		// @59: invokevirtual java.lang.StringBuilder.append(int)java.lang.StringBuilder
		// @5C: bipush 44 (0x2C)
		// @5E: invokevirtual java.lang.StringBuilder.append(char)java.lang.StringBuilder
		// @61: iload #4
		// @63: invokevirtual java.lang.StringBuilder.append(int)java.lang.StringBuilder
		// @66: bipush 44 (0x2C)
		// @68: invokevirtual java.lang.StringBuilder.append(char)java.lang.StringBuilder
		// @6B: iload #5
		// @6D: invokevirtual java.lang.StringBuilder.append(int)java.lang.StringBuilder
		// @70: bipush 44 (0x2C)
		// @72: invokevirtual java.lang.StringBuilder.append(char)java.lang.StringBuilder
		// @75: iload #6
		// @77: invokevirtual java.lang.StringBuilder.append(int)java.lang.StringBuilder
		// @7A: bipush 44 (0x2C)
		// @7C: invokevirtual java.lang.StringBuilder.append(char)java.lang.StringBuilder
		// @7F: iload #7
		// @81: invokevirtual java.lang.StringBuilder.append(int)java.lang.StringBuilder
		// @84: bipush 41 (0x29)
		// @86: invokevirtual java.lang.StringBuilder.append(char)java.lang.StringBuilder
		// @89: invokevirtual java.lang.StringBuilder.toString()java.lang.String
		// @8C: invokestatic game.C_100181_cf.func_105695_a(java.lang.Throwable, java.lang.String)game.C_100170_cm
		// @8F: athrow
		// @90: return
	}
	
	static final void func_102026_a(boolean arg0, byte arg1, int arg2, boolean arg3, boolean arg4)
	{
		// @000: getstatic int game.SteelSentinels.field_105275_O
		// @003: istore #19
		// @005: iconst_0
		// @006: getstatic int game.C_100100_i.field_102014_hc
		// @009: invokestatic game.C_100080_b.func_104428_a(boolean, int)void
		// @00C: aconst_null
		// @00D: getstatic game.C_100211_qd game.C_100068_vc.field_104342_d
		// @010: if_acmpeq @7B5
		// @013: getstatic game.C_100302_ka game.C_100200_ba.field_105847_f
		// @016: iconst_1
		// @017: putfield boolean game.C_100302_ka.field_101864_W
		// @01A: getstatic game.C_100302_ka game.C_100289_jl.field_102897_D
		// @01D: iconst_0
		// @01E: putfield int game.C_100302_ka.field_101848_lb
		// @021: getstatic game.C_100302_ka game.C_100289_jl.field_102897_D
		// @024: astore #5
		// @026: aload #5
		// @028: iconst_0
		// @029: putfield int game.C_100302_ka.field_101886_Kb
		// @02C: getstatic game.C_100302_ka game.C_100083_c.field_103164_U
		// @02F: astore #6
		// @031: getstatic game.C_100302_ka game.C_100083_c.field_103164_U
		// @034: iconst_0
		// @035: putfield int game.C_100302_ka.field_101848_lb
		// @038: aload #6
		// @03A: iconst_0
		// @03B: putfield int game.C_100302_ka.field_101886_Kb
		// @03E: getstatic game.C_100302_ka game.C_100084_ug.field_104481_e
		// @041: iconst_0
		// @042: putfield int game.C_100302_ka.field_101848_lb
		// @045: getstatic game.C_100302_ka game.C_100084_ug.field_104481_e
		// @048: astore #7
		// @04A: aload #7
		// @04C: iconst_0
		// @04D: putfield int game.C_100302_ka.field_101886_Kb
		// @050: bipush 88 (0x58)
		// @052: invokestatic game.C_100227_af.func_106156_a(byte)boolean
		// @055: ifne @0B6
		// @058: getstatic game.C_100211_qd game.C_100068_vc.field_104342_d
		// @05B: getfield java.lang.String game.C_100211_qd.field_102155_dc
		// @05E: astore #9
		// @060: getstatic game.C_100302_ka game.C_100250_pl.field_106436_b
		// @063: sipush -30945 (0x871F)
		// @066: iconst_1
		// @067: anewarray java.lang.String
		// @06A: dup
		// @06B: iconst_0
		// @06C: aload #9
		// @06E: aastore
		// @06F: getstatic java.lang.String game.C_100287_nm.field_106823_g
		// @072: invokestatic game.C_100132_td.func_104965_a(int, java.lang.String[], java.lang.String)java.lang.String
		// @075: invokevirtual java.lang.String.toUpperCase()java.lang.String
		// @078: putfield java.lang.String game.C_100302_ka.field_101890_ab
		// @07B: getstatic game.C_100302_ka game.C_100084_ug.field_104481_e
		// @07E: iconst_0
		// @07F: bipush 40 (0x28)
		// @081: iconst_m1
		// @082: bipush -40 (0xD8)
		// @084: getstatic game.C_100302_ka game.C_100318_hj.field_107196_d
		// @087: getfield int game.C_100302_ka.field_101848_lb
		// @08A: iadd
		// @08B: getstatic game.C_100302_ka game.C_100318_hj.field_107196_d
		// @08E: getfield int game.C_100302_ka.field_101886_Kb
		// @091: invokevirtual game.C_100302_ka.func_101825_a(int, int, int, int, int)void
		// @094: getstatic game.C_100302_ka game.C_100084_ug.field_104481_e
		// @097: sipush -30945 (0x871F)
		// @09A: iconst_1
		// @09B: anewarray java.lang.String
		// @09E: dup
		// @09F: iconst_0
		// @0A0: aload #9
		// @0A2: aastore
		// @0A3: getstatic java.lang.String game.C_100113_ek.field_104878_d
		// @0A6: invokestatic game.C_100132_td.func_104965_a(int, java.lang.String[], java.lang.String)java.lang.String
		// @0A9: putfield java.lang.String game.C_100302_ka.field_101890_ab
		// @0AC: getstatic game.C_100302_ka game.C_100084_ug.field_104481_e
		// @0AF: astore #8
		// @0B1: iload #19
		// @0B3: ifeq @742
		// @0B6: getstatic game.C_100302_ka game.C_100250_pl.field_106436_b
		// @0B9: getstatic java.lang.String game.C_100245_pf.field_106385_g
		// @0BC: invokevirtual java.lang.String.toUpperCase()java.lang.String
		// @0BF: putfield java.lang.String game.C_100302_ka.field_101890_ab
		// @0C2: iconst_2
		// @0C3: getstatic game.C_100302_ka game.C_100318_hj.field_107196_d
		// @0C6: getfield int game.C_100302_ka.field_101886_Kb
		// @0C9: iadd
		// @0CA: iconst_2
		// @0CB: idiv
		// @0CC: istore #9
		// @0CE: getstatic game.C_100302_ka game.C_100289_jl.field_102897_D
		// @0D1: iconst_0
		// @0D2: bipush 40 (0x28)
		// @0D4: iconst_m1
		// @0D5: getstatic game.C_100302_ka game.C_100318_hj.field_107196_d
		// @0D8: getfield int game.C_100302_ka.field_101848_lb
		// @0DB: bipush -40 (0xD8)
		// @0DD: iadd
		// @0DE: bipush -2 (0xFE)
		// @0E0: iload #9
		// @0E2: iadd
		// @0E3: invokevirtual game.C_100302_ka.func_101825_a(int, int, int, int, int)void
		// @0E6: getstatic game.C_100211_qd game.C_100068_vc.field_104342_d
		// @0E9: getfield int game.C_100211_qd.field_102160_Zb
		// @0EC: iconst_m1
		// @0ED: ixor
		// @0EE: getstatic game.C_100211_qd game.C_100068_vc.field_104342_d
		// @0F1: getfield int game.C_100211_qd.field_102138_ec
		// @0F4: iconst_m1
		// @0F5: ixor
		// @0F6: if_icmpge @115
		// @0F9: getstatic game.C_100302_ka game.C_100289_jl.field_102897_D
		// @0FC: getstatic java.lang.String game.C_100134_tj.field_105010_c
		// @0FF: invokevirtual java.lang.String.toUpperCase()java.lang.String
		// @102: putfield java.lang.String game.C_100302_ka.field_101890_ab
		// @105: getstatic game.C_100302_ka game.C_100289_jl.field_102897_D
		// @108: iconst_1
		// @109: putfield boolean game.C_100302_ka.field_101864_W
		// @10C: iload #19
		// @10E: ifeq @12C
		// @111: goto @115
		// @114: athrow
		// @115: getstatic game.C_100302_ka game.C_100289_jl.field_102897_D
		// @118: getstatic java.lang.String game.C_100320_hh.field_102911_U
		// @11B: invokevirtual java.lang.String.toUpperCase()java.lang.String
		// @11E: putfield java.lang.String game.C_100302_ka.field_101890_ab
		// @121: getstatic game.C_100302_ka game.C_100289_jl.field_102897_D
		// @124: iconst_0
		// @125: putfield boolean game.C_100302_ka.field_101864_W
		// @128: goto @12C
		// @12B: athrow
		// @12C: getstatic game.C_100302_ka game.C_100289_jl.field_102897_D
		// @12F: getstatic game.C_100302_ka game.C_100075_uj.field_100659_q
		// @132: getfield game.C_100037_wb[] game.C_100302_ka.field_101862_T
		// @135: putfield game.C_100037_wb[] game.C_100302_ka.field_101862_T
		// @138: iconst_0
		// @139: getstatic int game.C_100044_vm.field_100946_r
		// @13C: if_icmplt @143
		// @13F: goto @1BA
		// @142: athrow
		// @143: getstatic int game.C_100044_vm.field_100946_r
		// @146: iconst_1
		// @147: if_icmpne @154
		// @14A: getstatic java.lang.String game.C_100311_le.field_104717_t
		// @14D: astore #10
		// @14F: iload #19
		// @151: ifeq @16E
		// @154: iload_1
		// @155: sipush -31001 (0x86E7)
		// @158: iadd
		// @159: iconst_1
		// @15A: anewarray java.lang.String
		// @15D: dup
		// @15E: iconst_0
		// @15F: getstatic int game.C_100044_vm.field_100946_r
		// @162: invokestatic java.lang.Integer.toString(int)java.lang.String
		// @165: aastore
		// @166: getstatic java.lang.String game.C_100045_vj.field_100616_r
		// @169: invokestatic game.C_100132_td.func_104965_a(int, java.lang.String[], java.lang.String)java.lang.String
		// @16C: astore #10
		// @16E: getstatic game.C_100302_ka game.C_100289_jl.field_102897_D
		// @171: new java.lang.StringBuilder
		// @174: dup
		// @175: invokespecial java.lang.StringBuilder.<init>()void
		// @178: getstatic game.C_100302_ka game.C_100289_jl.field_102897_D
		// @17B: getfield java.lang.String game.C_100302_ka.field_101890_ab
		// @17E: invokevirtual java.lang.StringBuilder.append(java.lang.String)java.lang.StringBuilder
		// @181: getstatic java.lang.String[] game.C_100115_ej.field_102044_ec
		// @184: iconst_5
		// @185: aaload
		// @186: invokevirtual java.lang.StringBuilder.append(java.lang.String)java.lang.StringBuilder
		// @189: aload #10
		// @18B: invokevirtual java.lang.StringBuilder.append(java.lang.String)java.lang.StringBuilder
		// @18E: invokevirtual java.lang.StringBuilder.toString()java.lang.String
		// @191: putfield java.lang.String game.C_100302_ka.field_101890_ab
		// @194: iconst_m1
		// @195: bipush 16 (0x10)
		// @197: getstatic int game.C_100132_td.field_104984_i
		// @19A: iand
		// @19B: iconst_m1
		// @19C: ixor
		// @19D: if_icmpne @1BA
		// @1A0: getstatic boolean game.C_100003_ga.field_103535_w
		// @1A3: ifne @1BA
		// @1A6: goto @1AA
		// @1A9: athrow
		// @1AA: getstatic game.C_100302_ka game.C_100289_jl.field_102897_D
		// @1AD: getstatic game.C_100302_ka game.C_100075_uj.field_100659_q
		// @1B0: getfield game.C_100037_wb[] game.C_100302_ka.field_101883_qb
		// @1B3: putfield game.C_100037_wb[] game.C_100302_ka.field_101862_T
		// @1B6: goto @1BA
		// @1B9: athrow
		// @1BA: getstatic game.C_100302_ka game.C_100083_c.field_103164_U
		// @1BD: iload #9
		// @1BF: bipush 40 (0x28)
		// @1C1: iconst_m1
		// @1C2: bipush -40 (0xD8)
		// @1C4: getstatic game.C_100302_ka game.C_100318_hj.field_107196_d
		// @1C7: getfield int game.C_100302_ka.field_101848_lb
		// @1CA: iadd
		// @1CB: iload #9
		// @1CD: ineg
		// @1CE: getstatic game.C_100302_ka game.C_100318_hj.field_107196_d
		// @1D1: getfield int game.C_100302_ka.field_101886_Kb
		// @1D4: iadd
		// @1D5: invokevirtual game.C_100302_ka.func_101825_a(int, int, int, int, int)void
		// @1D8: getstatic game.C_100302_ka game.C_100083_c.field_103164_U
		// @1DB: getstatic java.lang.String game.C_100197_ra.field_100857_o
		// @1DE: invokevirtual java.lang.String.toUpperCase()java.lang.String
		// @1E1: putfield java.lang.String game.C_100302_ka.field_101890_ab
		// @1E4: getstatic game.C_100302_ka game.C_100083_c.field_103164_U
		// @1E7: astore #8
		// @1E9: getstatic game.C_100302_ka game.C_100083_c.field_103164_U
		// @1EC: iload_3
		// @1ED: ifeq @207
		// @1F0: ldc2_w -1
		// @1F3: getstatic long game.C_100315_la.field_107177_e
		// @1F6: ldc2_w -1
		// @1F9: lxor
		// @1FA: lcmp
		// @1FB: ifne @207
		// @1FE: goto @202
		// @201: athrow
		// @202: iconst_1
		// @203: goto @208
		// @206: athrow
		// @207: iconst_0
		// @208: putfield boolean game.C_100302_ka.field_101864_W
		// @20B: iconst_2
		// @20C: istore #10
		// @20E: getstatic int[][] game.C_100092_um.field_104539_i
		// @211: ifnull @37A
		// @214: getstatic byte[] game.C_100341_jd.field_102646_ib
		// @217: ifnull @222
		// @21A: goto @21E
		// @21D: athrow
		// @21E: goto @232
		// @221: athrow
		// @222: getstatic int game.C_100137_bn.field_105038_l
		// @225: newarray boolean[]
		// @227: putstatic boolean[] game.C_100207_qh.field_102873_U
		// @22A: getstatic int game.C_100137_bn.field_105038_l
		// @22D: newarray byte[]
		// @22F: putstatic byte[] game.C_100341_jd.field_102646_ib
		// @232: iconst_0
		// @233: istore #11
		// @235: getstatic int game.C_100137_bn.field_105038_l
		// @238: iconst_m1
		// @239: ixor
		// @23A: iload #11
		// @23C: iconst_m1
		// @23D: ixor
		// @23E: if_icmpge @259
		// @241: getstatic boolean[] game.C_100207_qh.field_102873_U
		// @244: iload #11
		// @246: iconst_0
		// @247: bastore
		// @248: iinc #11 +1
		// @24B: iload #19
		// @24D: ifne @25C
		// @250: iload #19
		// @252: ifeq @235
		// @255: goto @259
		// @258: athrow
		// @259: iconst_0
		// @25A: istore #10
		// @25C: iload #10
		// @25E: iconst_2
		// @25F: if_icmpge @363
		// @262: iconst_0
		// @263: istore #11
		// @265: iconst_0
		// @266: iload #19
		// @268: ifne @366
		// @26B: istore #12
		// @26D: getstatic int[][] game.C_100092_um.field_104539_i
		// @270: arraylength
		// @271: iload #12
		// @273: if_icmple @349
		// @276: getstatic int[][] game.C_100092_um.field_104539_i
		// @279: iload #12
		// @27B: aaload
		// @27C: astore #13
		// @27E: iconst_0
		// @27F: iload #19
		// @281: ifne @34B
		// @284: istore #14
		// @286: iload #14
		// @288: aload #13
		// @28A: arraylength
		// @28B: if_icmpge @303
		// @28E: aload #13
		// @290: iload #14
		// @292: iaload
		// @293: istore #15
		// @295: aload #13
		// @297: iconst_1
		// @298: iload #14
		// @29A: iadd
		// @29B: iaload
		// @29C: istore #16
		// @29E: iconst_m1
		// @29F: iload #15
		// @2A1: iload #19
		// @2A3: ifne @315
		// @2A6: if_icmpne @2D8
		// @2A9: goto @2AD
		// @2AC: athrow
		// @2AD: iload #10
		// @2AF: ifeq @2C0
		// @2B2: goto @2B6
		// @2B5: athrow
		// @2B6: getstatic game.C_100211_qd game.C_100068_vc.field_104342_d
		// @2B9: getfield int game.C_100211_qd.field_102138_ec
		// @2BC: goto @2C6
		// @2BF: athrow
		// @2C0: getstatic game.C_100211_qd game.C_100068_vc.field_104342_d
		// @2C3: getfield int game.C_100211_qd.field_102160_Zb
		// @2C6: istore #17
		// @2C8: iload #17
		// @2CA: iload #16
		// @2CC: if_icmpne @341
		// @2CF: iload #19
		// @2D1: ifeq @2F7
		// @2D4: goto @2D8
		// @2D7: athrow
		// @2D8: getstatic game.C_100211_qd game.C_100068_vc.field_104342_d
		// @2DB: getfield byte[] game.C_100211_qd.field_102165_jc
		// @2DE: iload #15
		// @2E0: baload
		// @2E1: sipush 255 (0x00FF)
		// @2E4: iand
		// @2E5: iload #16
		// @2E7: if_icmpeq @2F7
		// @2EA: goto @2EE
		// @2ED: athrow
		// @2EE: iload #19
		// @2F0: ifeq @341
		// @2F3: goto @2F7
		// @2F6: athrow
		// @2F7: iinc #14 +2
		// @2FA: iload #19
		// @2FC: ifeq @286
		// @2FF: goto @303
		// @302: athrow
		// @303: iconst_1
		// @304: istore #11
		// @306: iconst_m1
		// @307: istore #14
		// @309: iconst_0
		// @30A: istore #15
		// @30C: iload #15
		// @30E: iconst_m1
		// @30F: ixor
		// @310: aload #13
		// @312: arraylength
		// @313: iconst_m1
		// @314: ixor
		// @315: if_icmple @33A
		// @318: aload #13
		// @31A: iload #15
		// @31C: iaload
		// @31D: istore #16
		// @31F: iload #14
		// @321: iload #16
		// @323: iload #19
		// @325: ifne @273
		// @328: if_icmplt @32E
		// @32B: goto @332
		// @32E: iload #16
		// @330: istore #14
		// @332: iinc #15 +2
		// @335: iload #19
		// @337: ifeq @30C
		// @33A: getstatic boolean[] game.C_100207_qh.field_102873_U
		// @33D: iload #14
		// @33F: iconst_1
		// @340: bastore
		// @341: iinc #12 +1
		// @344: iload #19
		// @346: ifeq @26D
		// @349: iload #11
		// @34B: ifeq @357
		// @34E: iload #19
		// @350: ifeq @363
		// @353: goto @357
		// @356: athrow
		// @357: iinc #10 +1
		// @35A: iload #19
		// @35C: ifeq @25C
		// @35F: goto @363
		// @362: athrow
		// @363: getstatic int game.C_100107_u.field_104770_g
		// @366: iconst_2
		// @367: if_icmplt @37A
		// @36A: getstatic boolean[] game.C_100309_lk.field_103258_hb
		// @36D: bipush 12 (0x0C)
		// @36F: baload
		// @370: ifeq @37A
		// @373: goto @377
		// @376: athrow
		// @377: iconst_2
		// @378: istore #10
		// @37A: iload #10
		// @37C: iconst_m1
		// @37D: ixor
		// @37E: bipush -3 (0xFD)
		// @380: if_icmpgt @603
		// @383: getstatic boolean[][] game.C_100245_pf.field_106386_d
		// @386: ifnonnull @3B2
		// @389: goto @38D
		// @38C: athrow
		// @38D: aconst_null
		// @38E: getstatic int[][] game.C_100332_ii.field_107319_k
		// @391: if_acmpne @3B2
		// @394: goto @398
		// @397: athrow
		// @398: aconst_null
		// @399: getstatic int[][] game.C_100151_bc.field_102939_V
		// @39C: if_acmpne @3B2
		// @39F: goto @3A3
		// @3A2: athrow
		// @3A3: aconst_null
		// @3A4: getstatic int[][] game.C_100231_oc.field_102194_Zb
		// @3A7: if_acmpne @3B2
		// @3AA: goto @3AE
		// @3AD: athrow
		// @3AE: goto @742
		// @3B1: athrow
		// @3B2: iconst_0
		// @3B3: istore #11
		// @3B5: iconst_0
		// @3B6: istore #12
		// @3B8: iconst_0
		// @3B9: istore #13
		// @3BB: iconst_0
		// @3BC: istore #14
		// @3BE: iconst_0
		// @3BF: istore #15
		// @3C1: iconst_0
		// @3C2: istore #16
		// @3C4: getstatic int game.C_100137_bn.field_105038_l
		// @3C7: iload #16
		// @3C9: if_icmple @4C1
		// @3CC: sipush 255 (0x00FF)
		// @3CF: getstatic game.C_100211_qd game.C_100068_vc.field_104342_d
		// @3D2: getfield byte[] game.C_100211_qd.field_102165_jc
		// @3D5: iload #16
		// @3D7: baload
		// @3D8: iand
		// @3D9: istore #17
		// @3DB: iload #19
		// @3DD: ifne @4C4
		// @3E0: getstatic boolean[][] game.C_100245_pf.field_106386_d
		// @3E3: ifnull @40A
		// @3E6: goto @3EA
		// @3E9: athrow
		// @3EA: getstatic boolean[][] game.C_100245_pf.field_106386_d
		// @3ED: iload #16
		// @3EF: aaload
		// @3F0: ifnonnull @3FB
		// @3F3: goto @3F7
		// @3F6: athrow
		// @3F7: goto @40A
		// @3FA: athrow
		// @3FB: getstatic boolean[][] game.C_100245_pf.field_106386_d
		// @3FE: iload #16
		// @400: aaload
		// @401: iload #17
		// @403: baload
		// @404: ifeq @40A
		// @407: iconst_1
		// @408: istore #11
		// @40A: aconst_null
		// @40B: getstatic int[][] game.C_100332_ii.field_107319_k
		// @40E: if_acmpeq @456
		// @411: aconst_null
		// @412: getstatic int[][] game.C_100332_ii.field_107319_k
		// @415: iload #16
		// @417: aaload
		// @418: if_acmpne @423
		// @41B: goto @41F
		// @41E: athrow
		// @41F: goto @456
		// @422: athrow
		// @423: getstatic int[][] game.C_100332_ii.field_107319_k
		// @426: iload #16
		// @428: aaload
		// @429: iload #17
		// @42B: iaload
		// @42C: istore #18
		// @42E: iload #18
		// @430: iconst_m1
		// @431: ixor
		// @432: iconst_m1
		// @433: if_icmpeq @443
		// @436: getstatic boolean game.C_100154_sl.field_105330_g
		// @439: ifne @443
		// @43C: goto @440
		// @43F: athrow
		// @440: iconst_1
		// @441: istore #11
		// @443: iload #18
		// @445: iconst_m1
		// @446: ixor
		// @447: iload #13
		// @449: iconst_m1
		// @44A: ixor
		// @44B: if_icmplt @452
		// @44E: goto @456
		// @451: athrow
		// @452: iload #18
		// @454: istore #13
		// @456: aconst_null
		// @457: getstatic int[][] game.C_100231_oc.field_102194_Zb
		// @45A: if_acmpeq @479
		// @45D: aconst_null
		// @45E: getstatic int[][] game.C_100231_oc.field_102194_Zb
		// @461: iload #16
		// @463: aaload
		// @464: if_acmpeq @479
		// @467: goto @46B
		// @46A: athrow
		// @46B: iload #15
		// @46D: getstatic int[][] game.C_100231_oc.field_102194_Zb
		// @470: iload #16
		// @472: aaload
		// @473: iload #17
		// @475: iaload
		// @476: ior
		// @477: istore #15
		// @479: getstatic int[][] game.C_100151_bc.field_102939_V
		// @47C: ifnull @4B9
		// @47F: aconst_null
		// @480: getstatic int[][] game.C_100151_bc.field_102939_V
		// @483: iload #16
		// @485: aaload
		// @486: if_acmpeq @4B9
		// @489: goto @48D
		// @48C: athrow
		// @48D: getstatic int[][] game.C_100151_bc.field_102939_V
		// @490: iload #16
		// @492: aaload
		// @493: iload #17
		// @495: iaload
		// @496: istore #18
		// @498: iload #18
		// @49A: iconst_m1
		// @49B: ixor
		// @49C: iload #14
		// @49E: iconst_m1
		// @49F: ixor
		// @4A0: if_icmpge @4A7
		// @4A3: iload #18
		// @4A5: istore #14
		// @4A7: iload #18
		// @4A9: ifeq @4B9
		// @4AC: getstatic boolean game.C_100154_sl.field_105330_g
		// @4AF: ifne @4B9
		// @4B2: goto @4B6
		// @4B5: athrow
		// @4B6: iconst_1
		// @4B7: istore #11
		// @4B9: iinc #16 +1
		// @4BC: iload #19
		// @4BE: ifeq @3C4
		// @4C1: iconst_0
		// @4C2: istore #16
		// @4C4: getstatic game.C_100115_ej game.C_100009_fg.field_103654_g
		// @4C7: getfield game.C_100302_ka game.C_100115_ej.field_102036_Wb
		// @4CA: getfield game.C_100202_qi game.C_100302_ka.field_101891_Ob
		// @4CD: astore #17
		// @4CF: aload #17
		// @4D1: bipush 30 (0x1E)
		// @4D3: invokevirtual game.C_100202_qi.func_105899_c(int)game.C_100158_da
		// @4D6: checkcast game.C_100054_ec
		// @4D9: astore #18
		// @4DB: aload #18
		// @4DD: ifnull @58D
		// @4E0: aload #18
		// @4E2: bipush -119 (0x89)
		// @4E4: invokevirtual game.C_100054_ec.func_101951_m(int)boolean
		// @4E7: iload #19
		// @4E9: ifne @58F
		// @4EC: ifeq @4FC
		// @4EF: goto @4F3
		// @4F2: athrow
		// @4F3: iload #19
		// @4F5: ifeq @57C
		// @4F8: goto @4FC
		// @4FB: athrow
		// @4FC: iload #11
		// @4FE: ifeq @519
		// @501: goto @505
		// @504: athrow
		// @505: aload #18
		// @507: getfield boolean game.C_100054_ec.field_101958_ec
		// @50A: ifne @519
		// @50D: goto @511
		// @510: athrow
		// @511: iconst_1
		// @512: istore #16
		// @514: iload #19
		// @516: ifeq @58D
		// @519: iload #13
		// @51B: iconst_m1
		// @51C: ixor
		// @51D: aload #18
		// @51F: getfield int game.C_100054_ec.field_101966_Vb
		// @522: iconst_m1
		// @523: ixor
		// @524: if_icmplt @52F
		// @527: goto @52B
		// @52A: athrow
		// @52B: goto @537
		// @52E: athrow
		// @52F: iconst_1
		// @530: istore #16
		// @532: iload #19
		// @534: ifeq @58D
		// @537: iload #14
		// @539: aload #18
		// @53B: getfield int game.C_100054_ec.field_101972_cc
		// @53E: if_icmpgt @549
		// @541: goto @545
		// @544: athrow
		// @545: goto @551
		// @548: athrow
		// @549: iconst_1
		// @54A: istore #16
		// @54C: iload #19
		// @54E: ifeq @58D
		// @551: iconst_0
		// @552: iload #15
		// @554: aload #18
		// @556: getfield int game.C_100054_ec.field_101969_ac
		// @559: iconst_m1
		// @55A: ixor
		// @55B: iand
		// @55C: if_icmpge @56B
		// @55F: goto @563
		// @562: athrow
		// @563: iconst_1
		// @564: istore #16
		// @566: iload #19
		// @568: ifeq @58D
		// @56B: iload #12
		// @56D: ifeq @57C
		// @570: goto @574
		// @573: athrow
		// @574: iconst_1
		// @575: istore #16
		// @577: iload #19
		// @579: ifeq @58D
		// @57C: aload #17
		// @57E: bipush 87 (0x57)
		// @580: invokevirtual game.C_100202_qi.func_105907_c(byte)game.C_100158_da
		// @583: checkcast game.C_100054_ec
		// @586: astore #18
		// @588: iload #19
		// @58A: ifeq @4DB
		// @58D: bipush -3 (0xFD)
		// @58F: getstatic int game.C_100107_u.field_104770_g
		// @592: iconst_m1
		// @593: ixor
		// @594: if_icmplt @5A7
		// @597: getstatic boolean[] game.C_100309_lk.field_103258_hb
		// @59A: bipush 12 (0x0C)
		// @59C: baload
		// @59D: ifeq @5A7
		// @5A0: goto @5A4
		// @5A3: athrow
		// @5A4: iconst_0
		// @5A5: istore #16
		// @5A7: iload #16
		// @5A9: ifeq @5FE
		// @5AC: getstatic game.C_100302_ka game.C_100083_c.field_103164_U
		// @5AF: iconst_0
		// @5B0: putfield boolean game.C_100302_ka.field_101864_W
		// @5B3: getstatic game.C_100302_ka game.C_100083_c.field_103164_U
		// @5B6: getfield boolean game.C_100302_ka.field_101836_Hb
		// @5B9: ifne @5C4
		// @5BC: goto @5C0
		// @5BF: athrow
		// @5C0: goto @5FE
		// @5C3: athrow
		// @5C4: getstatic game.C_100220_ac game.C_100091_m.field_104516_c
		// @5C7: getfield game.C_100172_ck game.C_100220_ac.field_106059_a
		// @5CA: getfield int game.C_100172_ck.field_102113_Xb
		// @5CD: iconst_m1
		// @5CE: ixor
		// @5CF: iconst_m1
		// @5D0: if_icmpne @5E2
		// @5D3: getstatic java.lang.String game.C_100028_ha.field_103946_d
		// @5D6: putstatic java.lang.String game.C_100321_hi.field_107220_c
		// @5D9: iload #19
		// @5DB: ifeq @5FE
		// @5DE: goto @5E2
		// @5E1: athrow
		// @5E2: iload_1
		// @5E3: sipush -31001 (0x86E7)
		// @5E6: iadd
		// @5E7: iconst_1
		// @5E8: anewarray java.lang.String
		// @5EB: dup
		// @5EC: iconst_0
		// @5ED: getstatic java.lang.String game.C_100164_se.field_105450_d
		// @5F0: aastore
		// @5F1: getstatic java.lang.String game.C_100118_ub.field_102060_Yb
		// @5F4: invokestatic game.C_100132_td.func_104965_a(int, java.lang.String[], java.lang.String)java.lang.String
		// @5F7: putstatic java.lang.String game.C_100321_hi.field_107220_c
		// @5FA: goto @5FE
		// @5FD: athrow
		// @5FE: iload #19
		// @600: ifeq @742
		// @603: getstatic game.C_100302_ka game.C_100083_c.field_103164_U
		// @606: iconst_0
		// @607: putfield boolean game.C_100302_ka.field_101864_W
		// @60A: getstatic game.C_100302_ka game.C_100083_c.field_103164_U
		// @60D: getfield boolean game.C_100302_ka.field_101836_Hb
		// @610: ifeq @742
		// @613: goto @617
		// @616: athrow
		// @617: aconst_null
		// @618: astore #11
		// @61A: iconst_0
		// @61B: istore #12
		// @61D: iconst_0
		// @61E: istore #13
		// @620: iload #13
		// @622: getstatic int game.C_100137_bn.field_105038_l
		// @625: if_icmpge @69C
		// @628: getstatic boolean[] game.C_100207_qh.field_102873_U
		// @62B: iload #13
		// @62D: baload
		// @62E: iload #19
		// @630: ifne @69E
		// @633: ifne @63D
		// @636: goto @63A
		// @639: athrow
		// @63A: goto @694
		// @63D: new java.lang.StringBuilder
		// @640: dup
		// @641: invokespecial java.lang.StringBuilder.<init>()void
		// @644: getstatic java.lang.String[] game.C_100115_ej.field_102044_ec
		// @647: bipush 7 (0x07)
		// @649: aaload
		// @64A: invokevirtual java.lang.StringBuilder.append(java.lang.String)java.lang.StringBuilder
		// @64D: getstatic java.lang.String[] game.C_100036_gg.field_103155_R
		// @650: iload #13
		// @652: aaload
		// @653: invokevirtual java.lang.StringBuilder.append(java.lang.String)java.lang.StringBuilder
		// @656: getstatic java.lang.String[] game.C_100115_ej.field_102044_ec
		// @659: iconst_4
		// @65A: aaload
		// @65B: invokevirtual java.lang.StringBuilder.append(java.lang.String)java.lang.StringBuilder
		// @65E: invokevirtual java.lang.StringBuilder.toString()java.lang.String
		// @661: astore #14
		// @663: aconst_null
		// @664: aload #11
		// @666: if_acmpne @672
		// @669: aload #14
		// @66B: astore #11
		// @66D: iload #19
		// @66F: ifeq @694
		// @672: new java.lang.StringBuilder
		// @675: dup
		// @676: invokespecial java.lang.StringBuilder.<init>()void
		// @679: aload #11
		// @67B: invokevirtual java.lang.StringBuilder.append(java.lang.String)java.lang.StringBuilder
		// @67E: getstatic java.lang.String[] game.C_100115_ej.field_102044_ec
		// @681: bipush 6 (0x06)
		// @683: aaload
		// @684: invokevirtual java.lang.StringBuilder.append(java.lang.String)java.lang.StringBuilder
		// @687: aload #14
		// @689: invokevirtual java.lang.StringBuilder.append(java.lang.String)java.lang.StringBuilder
		// @68C: invokevirtual java.lang.StringBuilder.toString()java.lang.String
		// @68F: astore #11
		// @691: iconst_1
		// @692: istore #12
		// @694: iinc #13 +1
		// @697: iload #19
		// @699: ifeq @620
		// @69C: iload #10
		// @69E: ifne @6E0
		// @6A1: getstatic java.lang.String game.C_100212_qc.field_105983_i
		// @6A4: astore #13
		// @6A6: iload #12
		// @6A8: ifeq @6C7
		// @6AB: new java.lang.StringBuilder
		// @6AE: dup
		// @6AF: invokespecial java.lang.StringBuilder.<init>()void
		// @6B2: getstatic java.lang.String game.C_100000_gd.field_100354_f
		// @6B5: invokevirtual java.lang.StringBuilder.append(java.lang.String)java.lang.StringBuilder
		// @6B8: aload #11
		// @6BA: invokevirtual java.lang.StringBuilder.append(java.lang.String)java.lang.StringBuilder
		// @6BD: invokevirtual java.lang.StringBuilder.toString()java.lang.String
		// @6C0: astore #14
		// @6C2: iload #19
		// @6C4: ifeq @71A
		// @6C7: iload_1
		// @6C8: sipush -30937 (0x8727)
		// @6CB: ixor
		// @6CC: iconst_1
		// @6CD: anewarray java.lang.String
		// @6D0: dup
		// @6D1: iconst_0
		// @6D2: aload #11
		// @6D4: aastore
		// @6D5: getstatic java.lang.String game.C_100028_ha.field_103952_h
		// @6D8: invokestatic game.C_100132_td.func_104965_a(int, java.lang.String[], java.lang.String)java.lang.String
		// @6DB: astore #14
		// @6DD: goto @71A
		// @6E0: getstatic java.lang.String game.C_100030_gm.field_103352_K
		// @6E3: astore #13
		// @6E5: iload #12
		// @6E7: ifne @703
		// @6EA: sipush -30945 (0x871F)
		// @6ED: iconst_1
		// @6EE: anewarray java.lang.String
		// @6F1: dup
		// @6F2: iconst_0
		// @6F3: aload #11
		// @6F5: aastore
		// @6F6: getstatic java.lang.String game.C_100082_uf.field_100372_b
		// @6F9: invokestatic game.C_100132_td.func_104965_a(int, java.lang.String[], java.lang.String)java.lang.String
		// @6FC: astore #14
		// @6FE: iload #19
		// @700: ifeq @71A
		// @703: new java.lang.StringBuilder
		// @706: dup
		// @707: invokespecial java.lang.StringBuilder.<init>()void
		// @70A: getstatic java.lang.String game.C_100185_rm.field_105487_c
		// @70D: invokevirtual java.lang.StringBuilder.append(java.lang.String)java.lang.StringBuilder
		// @710: aload #11
		// @712: invokevirtual java.lang.StringBuilder.append(java.lang.String)java.lang.StringBuilder
		// @715: invokevirtual java.lang.StringBuilder.toString()java.lang.String
		// @718: astore #14
		// @71A: new java.lang.StringBuilder
		// @71D: dup
		// @71E: invokespecial java.lang.StringBuilder.<init>()void
		// @721: getstatic java.lang.String[] game.C_100115_ej.field_102044_ec
		// @724: bipush 7 (0x07)
		// @726: aaload
		// @727: invokevirtual java.lang.StringBuilder.append(java.lang.String)java.lang.StringBuilder
		// @72A: aload #13
		// @72C: invokevirtual java.lang.StringBuilder.append(java.lang.String)java.lang.StringBuilder
		// @72F: getstatic java.lang.String[] game.C_100115_ej.field_102044_ec
		// @732: iconst_5
		// @733: aaload
		// @734: invokevirtual java.lang.StringBuilder.append(java.lang.String)java.lang.StringBuilder
		// @737: aload #14
		// @739: invokevirtual java.lang.StringBuilder.append(java.lang.String)java.lang.StringBuilder
		// @73C: invokevirtual java.lang.StringBuilder.toString()java.lang.String
		// @73F: putstatic java.lang.String game.C_100321_hi.field_107220_c
		// @742: lconst_0
		// @743: getstatic long game.C_100315_la.field_107177_e
		// @746: lcmp
		// @747: ifne @74E
		// @74A: goto @78A
		// @74D: athrow
		// @74E: getstatic long game.C_100315_la.field_107177_e
		// @751: bipush -83 (0xAD)
		// @753: invokestatic game.C_100198_qn.func_105828_a(byte)long
		// @756: lneg
		// @757: ladd
		// @758: l2i
		// @759: istore #9
		// @75B: iload #9
		// @75D: sipush -999 (0xFC19)
		// @760: isub
		// @761: sipush 1000 (0x03E8)
		// @764: idiv
		// @765: istore #9
		// @767: iload #9
		// @769: iconst_1
		// @76A: if_icmpge @770
		// @76D: iconst_1
		// @76E: istore #9
		// @770: aload #8
		// @772: sipush -30945 (0x871F)
		// @775: iconst_1
		// @776: anewarray java.lang.String
		// @779: dup
		// @77A: iconst_0
		// @77B: iload #9
		// @77D: invokestatic java.lang.Integer.toString(int)java.lang.String
		// @780: aastore
		// @781: getstatic java.lang.String game.C_100322_hn.field_107237_e
		// @784: invokestatic game.C_100132_td.func_104965_a(int, java.lang.String[], java.lang.String)java.lang.String
		// @787: putfield java.lang.String game.C_100302_ka.field_101890_ab
		// @78A: getstatic game.C_100302_ka game.C_100095_fe.field_103385_S
		// @78D: sipush -30945 (0x871F)
		// @790: iconst_2
		// @791: anewarray java.lang.String
		// @794: dup
		// @795: iconst_0
		// @796: getstatic game.C_100211_qd game.C_100068_vc.field_104342_d
		// @799: getfield int game.C_100211_qd.field_102138_ec
		// @79C: invokestatic java.lang.Integer.toString(int)java.lang.String
		// @79F: aastore
		// @7A0: dup
		// @7A1: iconst_1
		// @7A2: getstatic game.C_100211_qd game.C_100068_vc.field_104342_d
		// @7A5: getfield int game.C_100211_qd.field_102160_Zb
		// @7A8: invokestatic java.lang.Integer.toString(int)java.lang.String
		// @7AB: aastore
		// @7AC: getstatic java.lang.String game.C_100024_hd.field_103000_r
		// @7AF: invokestatic game.C_100132_td.func_104965_a(int, java.lang.String[], java.lang.String)java.lang.String
		// @7B2: putfield java.lang.String game.C_100302_ka.field_101890_ab
		// @7B5: getstatic game.C_100302_ka game.C_100314_lf.field_101335_mc
		// @7B8: iload_0
		// @7B9: ifeq @7D4
		// @7BC: iload #4
		// @7BE: ifne @7D4
		// @7C1: goto @7C5
		// @7C4: athrow
		// @7C5: getstatic boolean game.C_100003_ga.field_103535_w
		// @7C8: ifne @7D4
		// @7CB: goto @7CF
		// @7CE: athrow
		// @7CF: iconst_1
		// @7D0: goto @7D5
		// @7D3: athrow
		// @7D4: iconst_0
		// @7D5: bipush -125 (0x83)
		// @7D7: invokevirtual game.C_100302_ka.func_101819_a(boolean, byte)void
		// @7DA: getstatic game.C_100302_ka game.C_100318_hj.field_107196_d
		// @7DD: iload_0
		// @7DE: ifeq @7F9
		// @7E1: iload #4
		// @7E3: ifne @7F9
		// @7E6: goto @7EA
		// @7E9: athrow
		// @7EA: getstatic boolean game.C_100003_ga.field_103535_w
		// @7ED: ifne @7F9
		// @7F0: goto @7F4
		// @7F3: athrow
		// @7F4: iconst_1
		// @7F5: goto @7FA
		// @7F8: athrow
		// @7F9: iconst_0
		// @7FA: bipush -115 (0x8D)
		// @7FC: invokevirtual game.C_100302_ka.func_101819_a(boolean, byte)void
		// @7FF: iload_1
		// @800: bipush 56 (0x38)
		// @802: if_icmpeq @806
		// @805: return
		// @806: getstatic game.C_100302_ka game.C_100159_sn.field_105402_b
		// @809: iload_0
		// @80A: ifeq @825
		// @80D: iload #4
		// @80F: ifne @825
		// @812: goto @816
		// @815: athrow
		// @816: getstatic boolean game.C_100003_ga.field_103535_w
		// @819: ifeq @825
		// @81C: goto @820
		// @81F: athrow
		// @820: iconst_1
		// @821: goto @826
		// @824: athrow
		// @825: iconst_0
		// @826: bipush 26 (0x1A)
		// @828: invokevirtual game.C_100302_ka.func_101819_a(boolean, byte)void
		// @82B: getstatic game.C_100220_ac game.C_100091_m.field_104516_c
		// @82E: getfield game.C_100172_ck game.C_100220_ac.field_106059_a
		// @831: iconst_0
		// @832: invokevirtual game.C_100172_ck.func_102099_b(boolean)void
		// @835: getstatic game.C_100211_qd game.C_100068_vc.field_104342_d
		// @838: ifnonnull @83F
		// @83B: goto @89C
		// @83E: athrow
		// @83F: iconst_0
		// @840: getstatic game.C_100302_ka game.C_100200_ba.field_105847_f
		// @843: getfield int game.C_100302_ka.field_101854_N
		// @846: if_icmpne @84D
		// @849: goto @85A
		// @84C: athrow
		// @84D: iload_2
		// @84E: bipush -73 (0xB7)
		// @850: getstatic game.C_100211_qd game.C_100068_vc.field_104342_d
		// @853: iconst_1
		// @854: invokevirtual game.C_100211_qd.func_102127_b(boolean)int
		// @857: invokestatic game.C_100066_dl.func_101622_a(int, byte, int)void
		// @85A: getstatic game.C_100302_ka game.C_100289_jl.field_102897_D
		// @85D: getfield int game.C_100302_ka.field_101854_N
		// @860: iconst_m1
		// @861: ixor
		// @862: iconst_m1
		// @863: if_icmpne @86A
		// @866: goto @86E
		// @869: athrow
		// @86A: iconst_1
		// @86B: putstatic boolean game.C_100003_ga.field_103535_w
		// @86E: getstatic game.C_100302_ka game.C_100083_c.field_103164_U
		// @871: getfield int game.C_100302_ka.field_101854_N
		// @874: ifeq @87F
		// @877: iconst_1
		// @878: putstatic boolean game.C_100265_mh.field_106616_b
		// @87B: goto @87F
		// @87E: athrow
		// @87F: iconst_0
		// @880: getstatic game.C_100302_ka game.C_100273_mm.field_106685_a
		// @883: getfield int game.C_100302_ka.field_101854_N
		// @886: if_icmpeq @891
		// @889: iconst_0
		// @88A: putstatic boolean game.C_100003_ga.field_103535_w
		// @88D: goto @891
		// @890: athrow
		// @891: iload_2
		// @892: iconst_0
		// @893: sipush -15837 (0xC223)
		// @896: getstatic game.C_100211_qd game.C_100068_vc.field_104342_d
		// @899: invokestatic game.C_100244_pe.func_106363_a(int, boolean, int, game.C_100211_qd)void
		// @89C: goto @8E7
		// @89F: astore #5
		// @8A1: aload #5
		// @8A3: new java.lang.StringBuilder
		// @8A6: dup
		// @8A7: invokespecial java.lang.StringBuilder.<init>()void
		// @8AA: getstatic java.lang.String[] game.C_100115_ej.field_102044_ec
		// @8AD: iconst_3
		// @8AE: aaload
		// @8AF: invokevirtual java.lang.StringBuilder.append(java.lang.String)java.lang.StringBuilder
		// @8B2: iload_0
		// @8B3: invokevirtual java.lang.StringBuilder.append(boolean)java.lang.StringBuilder
		// @8B6: bipush 44 (0x2C)
		// @8B8: invokevirtual java.lang.StringBuilder.append(char)java.lang.StringBuilder
		// @8BB: iload_1
		// @8BC: invokevirtual java.lang.StringBuilder.append(int)java.lang.StringBuilder
		// @8BF: bipush 44 (0x2C)
		// @8C1: invokevirtual java.lang.StringBuilder.append(char)java.lang.StringBuilder
		// @8C4: iload_2
		// @8C5: invokevirtual java.lang.StringBuilder.append(int)java.lang.StringBuilder
		// @8C8: bipush 44 (0x2C)
		// @8CA: invokevirtual java.lang.StringBuilder.append(char)java.lang.StringBuilder
		// @8CD: iload_3
		// @8CE: invokevirtual java.lang.StringBuilder.append(boolean)java.lang.StringBuilder
		// @8D1: bipush 44 (0x2C)
		// @8D3: invokevirtual java.lang.StringBuilder.append(char)java.lang.StringBuilder
		// @8D6: iload #4
		// @8D8: invokevirtual java.lang.StringBuilder.append(boolean)java.lang.StringBuilder
		// @8DB: bipush 41 (0x29)
		// @8DD: invokevirtual java.lang.StringBuilder.append(char)java.lang.StringBuilder
		// @8E0: invokevirtual java.lang.StringBuilder.toString()java.lang.String
		// @8E3: invokestatic game.C_100181_cf.func_105695_a(java.lang.Throwable, java.lang.String)game.C_100170_cm
		// @8E6: athrow
		// @8E7: return
	}
	
	private final void func_102033_a(int arg0, int arg1, int arg2)
	{
		// @00: aload_0
		// @01: getfield game.C_100302_ka game.C_100115_ej.field_102040_Zb
		// @04: iload_3
		// @05: ineg
		// @06: aload_0
		// @07: getfield int game.C_100115_ej.field_101886_Kb
		// @0A: iadd
		// @0B: iload_1
		// @0C: isub
		// @0D: putfield int game.C_100302_ka.field_101886_Kb
		// @10: aload_0
		// @11: getfield game.C_100302_ka game.C_100115_ej.field_102036_Wb
		// @14: iconst_0
		// @15: putfield int game.C_100302_ka.field_101841_Pb
		// @18: aload_0
		// @19: getfield game.C_100302_ka game.C_100115_ej.field_102040_Zb
		// @1C: aload_0
		// @1D: getfield int game.C_100115_ej.field_101848_lb
		// @20: putfield int game.C_100302_ka.field_101848_lb
		// @23: iload_2
		// @24: bipush -53 (0xCB)
		// @26: if_icmplt @3A
		// @29: aload_0
		// @2A: bipush -81 (0xAF)
		// @2C: bipush -98 (0x9E)
		// @2E: iconst_0
		// @2F: bipush -6 (0xFA)
		// @31: bipush -103 (0x99)
		// @33: invokevirtual game.C_100115_ej.func_102025_a(int, int, boolean, int, int)void
		// @36: goto @3A
		// @39: athrow
		// @3A: aload_0
		// @3B: getfield game.C_100302_ka game.C_100115_ej.field_102036_Wb
		// @3E: iload_3
		// @3F: ineg
		// @40: iload_1
		// @41: ineg
		// @42: iadd
		// @43: aload_0
		// @44: getfield int game.C_100115_ej.field_101886_Kb
		// @47: iadd
		// @48: putfield int game.C_100302_ka.field_101886_Kb
		// @4B: aload_0
		// @4C: getfield game.C_100231_oc game.C_100115_ej.field_102038_Vb
		// @4F: aload_0
		// @50: getfield game.C_100302_ka game.C_100115_ej.field_102040_Zb
		// @53: getfield int game.C_100302_ka.field_101848_lb
		// @56: aload_0
		// @57: getfield game.C_100302_ka game.C_100115_ej.field_102036_Wb
		// @5A: getfield int game.C_100302_ka.field_101880_Gb
		// @5D: ineg
		// @5E: bipush -51 (0xCD)
		// @60: aload_0
		// @61: getfield int game.C_100115_ej.field_101886_Kb
		// @64: iload_1
		// @65: ineg
		// @66: iadd
		// @67: iload_1
		// @68: aload_0
		// @69: getfield game.C_100302_ka game.C_100115_ej.field_102036_Wb
		// @6C: getfield int game.C_100302_ka.field_101848_lb
		// @6F: iconst_0
		// @70: aload_0
		// @71: getfield int game.C_100115_ej.field_101848_lb
		// @74: invokevirtual game.C_100231_oc.func_102184_a(int, int, byte, int, int, int, int, int)void
		// @77: goto @AF
		// @7A: astore #4
		// @7C: aload #4
		// @7E: new java.lang.StringBuilder
		// @81: dup
		// @82: invokespecial java.lang.StringBuilder.<init>()void
		// @85: getstatic java.lang.String[] game.C_100115_ej.field_102044_ec
		// @88: iconst_0
		// @89: aaload
		// @8A: invokevirtual java.lang.StringBuilder.append(java.lang.String)java.lang.StringBuilder
		// @8D: iload_1
		// @8E: invokevirtual java.lang.StringBuilder.append(int)java.lang.StringBuilder
		// @91: bipush 44 (0x2C)
		// @93: invokevirtual java.lang.StringBuilder.append(char)java.lang.StringBuilder
		// @96: iload_2
		// @97: invokevirtual java.lang.StringBuilder.append(int)java.lang.StringBuilder
		// @9A: bipush 44 (0x2C)
		// @9C: invokevirtual java.lang.StringBuilder.append(char)java.lang.StringBuilder
		// @9F: iload_3
		// @A0: invokevirtual java.lang.StringBuilder.append(int)java.lang.StringBuilder
		// @A3: bipush 41 (0x29)
		// @A5: invokevirtual java.lang.StringBuilder.append(char)java.lang.StringBuilder
		// @A8: invokevirtual java.lang.StringBuilder.toString()java.lang.String
		// @AB: invokestatic game.C_100181_cf.func_105695_a(java.lang.Throwable, java.lang.String)game.C_100170_cm
		// @AE: athrow
		// @AF: return
	}
	
	final void func_102025_a(int arg0, int arg1, boolean arg2, int arg3, int arg4)
	{
		// @000: aload_0
		// @001: getfield game.C_100231_oc game.C_100115_ej.field_102038_Vb
		// @004: iconst_0
		// @005: invokevirtual game.C_100231_oc.func_102183_m(int)boolean
		// @008: ifeq @01C
		// @00B: aload_0
		// @00C: getfield game.C_100302_ka game.C_100115_ej.field_102036_Wb
		// @00F: dup
		// @010: getfield int game.C_100302_ka.field_101843_Tb
		// @013: iload_1
		// @014: iadd
		// @015: putfield int game.C_100302_ka.field_101843_Tb
		// @018: goto @01C
		// @01B: athrow
		// @01C: aload_0
		// @01D: getfield game.C_100231_oc game.C_100115_ej.field_102038_Vb
		// @020: sipush 18099 (0x46B3)
		// @023: invokevirtual game.C_100231_oc.func_102181_l(int)boolean
		// @026: ifeq @03A
		// @029: aload_0
		// @02A: getfield game.C_100302_ka game.C_100115_ej.field_102036_Wb
		// @02D: dup
		// @02E: getfield int game.C_100302_ka.field_101843_Tb
		// @031: iload_1
		// @032: isub
		// @033: putfield int game.C_100302_ka.field_101843_Tb
		// @036: goto @03A
		// @039: athrow
		// @03A: aload_0
		// @03B: getfield game.C_100231_oc game.C_100115_ej.field_102038_Vb
		// @03E: iconst_0
		// @03F: invokevirtual game.C_100231_oc.func_102186_n(int)boolean
		// @042: ifeq @057
		// @045: aload_0
		// @046: getfield game.C_100302_ka game.C_100115_ej.field_102036_Wb
		// @049: dup
		// @04A: getfield int game.C_100302_ka.field_101843_Tb
		// @04D: iload #4
		// @04F: iadd
		// @050: putfield int game.C_100302_ka.field_101843_Tb
		// @053: goto @057
		// @056: athrow
		// @057: aload_0
		// @058: getfield game.C_100231_oc game.C_100115_ej.field_102038_Vb
		// @05B: iconst_0
		// @05C: invokevirtual game.C_100231_oc.func_102188_b(boolean)boolean
		// @05F: ifeq @074
		// @062: aload_0
		// @063: getfield game.C_100302_ka game.C_100115_ej.field_102036_Wb
		// @066: dup
		// @067: getfield int game.C_100302_ka.field_101843_Tb
		// @06A: iload #4
		// @06C: isub
		// @06D: putfield int game.C_100302_ka.field_101843_Tb
		// @070: goto @074
		// @073: athrow
		// @074: aload_0
		// @075: getfield boolean game.C_100115_ej.field_101839_db
		// @078: ifne @07F
		// @07B: goto @08D
		// @07E: athrow
		// @07F: aload_0
		// @080: getfield game.C_100302_ka game.C_100115_ej.field_102036_Wb
		// @083: dup
		// @084: getfield int game.C_100302_ka.field_101843_Tb
		// @087: iload #5
		// @089: isub
		// @08A: putfield int game.C_100302_ka.field_101843_Tb
		// @08D: iload_3
		// @08E: ifne @121
		// @091: aload_0
		// @092: getfield game.C_100302_ka game.C_100115_ej.field_102036_Wb
		// @095: getfield int game.C_100302_ka.field_101880_Gb
		// @098: aload_0
		// @099: getfield game.C_100302_ka game.C_100115_ej.field_102036_Wb
		// @09C: getfield int game.C_100302_ka.field_101843_Tb
		// @09F: ineg
		// @0A0: isub
		// @0A1: ineg
		// @0A2: iconst_m1
		// @0A3: ixor
		// @0A4: aload_0
		// @0A5: getfield game.C_100302_ka game.C_100115_ej.field_102040_Zb
		// @0A8: getfield int game.C_100302_ka.field_101848_lb
		// @0AB: ineg
		// @0AC: aload_0
		// @0AD: getfield game.C_100302_ka game.C_100115_ej.field_102036_Wb
		// @0B0: getfield int game.C_100302_ka.field_101832_tb
		// @0B3: aload_0
		// @0B4: getfield game.C_100302_ka game.C_100115_ej.field_102036_Wb
		// @0B7: getfield int game.C_100302_ka.field_101848_lb
		// @0BA: iadd
		// @0BB: iadd
		// @0BC: iconst_m1
		// @0BD: ixor
		// @0BE: if_icmplt @0C9
		// @0C1: goto @0C5
		// @0C4: athrow
		// @0C5: goto @0F2
		// @0C8: athrow
		// @0C9: aload_0
		// @0CA: getfield game.C_100302_ka game.C_100115_ej.field_102036_Wb
		// @0CD: aload_0
		// @0CE: getfield game.C_100302_ka game.C_100115_ej.field_102036_Wb
		// @0D1: getfield int game.C_100302_ka.field_101848_lb
		// @0D4: aload_0
		// @0D5: getfield game.C_100302_ka game.C_100115_ej.field_102036_Wb
		// @0D8: getfield int game.C_100302_ka.field_101832_tb
		// @0DB: iadd
		// @0DC: aload_0
		// @0DD: getfield game.C_100302_ka game.C_100115_ej.field_102040_Zb
		// @0E0: getfield int game.C_100302_ka.field_101848_lb
		// @0E3: ineg
		// @0E4: iadd
		// @0E5: ineg
		// @0E6: aload_0
		// @0E7: getfield game.C_100302_ka game.C_100115_ej.field_102036_Wb
		// @0EA: getfield int game.C_100302_ka.field_101880_Gb
		// @0ED: ineg
		// @0EE: iadd
		// @0EF: putfield int game.C_100302_ka.field_101843_Tb
		// @0F2: aload_0
		// @0F3: getfield game.C_100302_ka game.C_100115_ej.field_102036_Wb
		// @0F6: getfield int game.C_100302_ka.field_101843_Tb
		// @0F9: aload_0
		// @0FA: getfield game.C_100302_ka game.C_100115_ej.field_102036_Wb
		// @0FD: getfield int game.C_100302_ka.field_101880_Gb
		// @100: iadd
		// @101: ineg
		// @102: iconst_m1
		// @103: ixor
		// @104: iconst_m1
		// @105: if_icmpgt @10C
		// @108: goto @1A7
		// @10B: athrow
		// @10C: aload_0
		// @10D: getfield game.C_100302_ka game.C_100115_ej.field_102036_Wb
		// @110: aload_0
		// @111: getfield game.C_100302_ka game.C_100115_ej.field_102036_Wb
		// @114: getfield int game.C_100302_ka.field_101880_Gb
		// @117: ineg
		// @118: putfield int game.C_100302_ka.field_101843_Tb
		// @11B: getstatic int game.SteelSentinels.field_105275_O
		// @11E: ifeq @1A7
		// @121: aload_0
		// @122: getfield game.C_100302_ka game.C_100115_ej.field_102036_Wb
		// @125: getfield int game.C_100302_ka.field_101843_Tb
		// @128: aload_0
		// @129: getfield game.C_100302_ka game.C_100115_ej.field_102036_Wb
		// @12C: getfield int game.C_100302_ka.field_101880_Gb
		// @12F: iadd
		// @130: ineg
		// @131: ifge @14B
		// @134: goto @138
		// @137: athrow
		// @138: aload_0
		// @139: getfield game.C_100302_ka game.C_100115_ej.field_102036_Wb
		// @13C: aload_0
		// @13D: getfield game.C_100302_ka game.C_100115_ej.field_102036_Wb
		// @140: getfield int game.C_100302_ka.field_101880_Gb
		// @143: ineg
		// @144: putfield int game.C_100302_ka.field_101843_Tb
		// @147: goto @14B
		// @14A: athrow
		// @14B: aload_0
		// @14C: getfield game.C_100302_ka game.C_100115_ej.field_102036_Wb
		// @14F: getfield int game.C_100302_ka.field_101843_Tb
		// @152: aload_0
		// @153: getfield game.C_100302_ka game.C_100115_ej.field_102036_Wb
		// @156: getfield int game.C_100302_ka.field_101880_Gb
		// @159: iadd
		// @15A: ineg
		// @15B: iconst_m1
		// @15C: ixor
		// @15D: aload_0
		// @15E: getfield game.C_100302_ka game.C_100115_ej.field_102040_Zb
		// @161: getfield int game.C_100302_ka.field_101848_lb
		// @164: ineg
		// @165: aload_0
		// @166: getfield game.C_100302_ka game.C_100115_ej.field_102036_Wb
		// @169: getfield int game.C_100302_ka.field_101848_lb
		// @16C: iadd
		// @16D: aload_0
		// @16E: getfield game.C_100302_ka game.C_100115_ej.field_102036_Wb
		// @171: getfield int game.C_100302_ka.field_101832_tb
		// @174: iadd
		// @175: iconst_m1
		// @176: ixor
		// @177: if_icmpge @1A7
		// @17A: aload_0
		// @17B: getfield game.C_100302_ka game.C_100115_ej.field_102036_Wb
		// @17E: aload_0
		// @17F: getfield game.C_100302_ka game.C_100115_ej.field_102036_Wb
		// @182: getfield int game.C_100302_ka.field_101880_Gb
		// @185: ineg
		// @186: aload_0
		// @187: getfield game.C_100302_ka game.C_100115_ej.field_102040_Zb
		// @18A: getfield int game.C_100302_ka.field_101848_lb
		// @18D: ineg
		// @18E: aload_0
		// @18F: getfield game.C_100302_ka game.C_100115_ej.field_102036_Wb
		// @192: getfield int game.C_100302_ka.field_101832_tb
		// @195: aload_0
		// @196: getfield game.C_100302_ka game.C_100115_ej.field_102036_Wb
		// @199: getfield int game.C_100302_ka.field_101848_lb
		// @19C: iadd
		// @19D: iadd
		// @19E: ineg
		// @19F: iadd
		// @1A0: putfield int game.C_100302_ka.field_101843_Tb
		// @1A3: goto @1A7
		// @1A6: athrow
		// @1A7: aload_0
		// @1A8: getfield game.C_100231_oc game.C_100115_ej.field_102038_Vb
		// @1AB: bipush -82 (0xAE)
		// @1AD: invokevirtual game.C_100231_oc.func_102178_h(byte)boolean
		// @1B0: ifeq @1DF
		// @1B3: aload_0
		// @1B4: getfield game.C_100302_ka game.C_100115_ej.field_102036_Wb
		// @1B7: aload_0
		// @1B8: getfield game.C_100231_oc game.C_100115_ej.field_102038_Vb
		// @1BB: aload_0
		// @1BC: getfield game.C_100302_ka game.C_100115_ej.field_102036_Wb
		// @1BF: getfield int game.C_100302_ka.field_101848_lb
		// @1C2: aload_0
		// @1C3: getfield game.C_100302_ka game.C_100115_ej.field_102040_Zb
		// @1C6: getfield int game.C_100302_ka.field_101848_lb
		// @1C9: bipush -70 (0xBA)
		// @1CB: iload_3
		// @1CC: invokevirtual game.C_100231_oc.func_102185_a(int, int, int, boolean)int
		// @1CF: ineg
		// @1D0: putfield int game.C_100302_ka.field_101880_Gb
		// @1D3: aload_0
		// @1D4: getfield game.C_100302_ka game.C_100115_ej.field_102036_Wb
		// @1D7: iconst_0
		// @1D8: putfield int game.C_100302_ka.field_101843_Tb
		// @1DB: goto @1DF
		// @1DE: athrow
		// @1DF: iload_2
		// @1E0: bipush -79 (0xB1)
		// @1E2: if_icmplt @1E6
		// @1E5: return
		// @1E6: aload_0
		// @1E7: getfield game.C_100231_oc game.C_100115_ej.field_102038_Vb
		// @1EA: aload_0
		// @1EB: getfield game.C_100302_ka game.C_100115_ej.field_102036_Wb
		// @1EE: getfield int game.C_100302_ka.field_101848_lb
		// @1F1: bipush -63 (0xC1)
		// @1F3: aload_0
		// @1F4: getfield game.C_100302_ka game.C_100115_ej.field_102040_Zb
		// @1F7: getfield int game.C_100302_ka.field_101848_lb
		// @1FA: aload_0
		// @1FB: getfield game.C_100302_ka game.C_100115_ej.field_102036_Wb
		// @1FE: getfield int game.C_100302_ka.field_101880_Gb
		// @201: ineg
		// @202: invokevirtual game.C_100231_oc.func_102179_a(int, byte, int, int)void
		// @205: goto @251
		// @208: astore #6
		// @20A: aload #6
		// @20C: new java.lang.StringBuilder
		// @20F: dup
		// @210: invokespecial java.lang.StringBuilder.<init>()void
		// @213: getstatic java.lang.String[] game.C_100115_ej.field_102044_ec
		// @216: iconst_2
		// @217: aaload
		// @218: invokevirtual java.lang.StringBuilder.append(java.lang.String)java.lang.StringBuilder
		// @21B: iload_1
		// @21C: invokevirtual java.lang.StringBuilder.append(int)java.lang.StringBuilder
		// @21F: bipush 44 (0x2C)
		// @221: invokevirtual java.lang.StringBuilder.append(char)java.lang.StringBuilder
		// @224: iload_2
		// @225: invokevirtual java.lang.StringBuilder.append(int)java.lang.StringBuilder
		// @228: bipush 44 (0x2C)
		// @22A: invokevirtual java.lang.StringBuilder.append(char)java.lang.StringBuilder
		// @22D: iload_3
		// @22E: invokevirtual java.lang.StringBuilder.append(boolean)java.lang.StringBuilder
		// @231: bipush 44 (0x2C)
		// @233: invokevirtual java.lang.StringBuilder.append(char)java.lang.StringBuilder
		// @236: iload #4
		// @238: invokevirtual java.lang.StringBuilder.append(int)java.lang.StringBuilder
		// @23B: bipush 44 (0x2C)
		// @23D: invokevirtual java.lang.StringBuilder.append(char)java.lang.StringBuilder
		// @240: iload #5
		// @242: invokevirtual java.lang.StringBuilder.append(int)java.lang.StringBuilder
		// @245: bipush 41 (0x29)
		// @247: invokevirtual java.lang.StringBuilder.append(char)java.lang.StringBuilder
		// @24A: invokevirtual java.lang.StringBuilder.toString()java.lang.String
		// @24D: invokestatic game.C_100181_cf.func_105695_a(java.lang.Throwable, java.lang.String)game.C_100170_cm
		// @250: athrow
		// @251: return
	}
	
	final void func_102028_a(int arg0, boolean arg1, int arg2, int arg3)
	{
		// @00: iload_3
		// @01: bipush -127 (0x81)
		// @03: if_icmplt @17
		// @06: aload_0
		// @07: bipush -63 (0xC1)
		// @09: bipush 63 (0x3F)
		// @0B: iconst_0
		// @0C: bipush -93 (0xA3)
		// @0E: bipush -4 (0xFC)
		// @10: invokevirtual game.C_100115_ej.func_102025_a(int, int, boolean, int, int)void
		// @13: goto @17
		// @16: athrow
		// @17: aload_0
		// @18: iload_1
		// @19: bipush -120 (0x88)
		// @1B: iload_2
		// @1C: aload_0
		// @1D: getfield game.C_100302_ka game.C_100115_ej.field_102040_Zb
		// @20: getfield int game.C_100302_ka.field_101848_lb
		// @23: iload #4
		// @25: invokevirtual game.C_100115_ej.func_102025_a(int, int, boolean, int, int)void
		// @28: goto @6B
		// @2B: astore #5
		// @2D: aload #5
		// @2F: new java.lang.StringBuilder
		// @32: dup
		// @33: invokespecial java.lang.StringBuilder.<init>()void
		// @36: getstatic java.lang.String[] game.C_100115_ej.field_102044_ec
		// @39: bipush 12 (0x0C)
		// @3B: aaload
		// @3C: invokevirtual java.lang.StringBuilder.append(java.lang.String)java.lang.StringBuilder
		// @3F: iload_1
		// @40: invokevirtual java.lang.StringBuilder.append(int)java.lang.StringBuilder
		// @43: bipush 44 (0x2C)
		// @45: invokevirtual java.lang.StringBuilder.append(char)java.lang.StringBuilder
		// @48: iload_2
		// @49: invokevirtual java.lang.StringBuilder.append(boolean)java.lang.StringBuilder
		// @4C: bipush 44 (0x2C)
		// @4E: invokevirtual java.lang.StringBuilder.append(char)java.lang.StringBuilder
		// @51: iload_3
		// @52: invokevirtual java.lang.StringBuilder.append(int)java.lang.StringBuilder
		// @55: bipush 44 (0x2C)
		// @57: invokevirtual java.lang.StringBuilder.append(char)java.lang.StringBuilder
		// @5A: iload #4
		// @5C: invokevirtual java.lang.StringBuilder.append(int)java.lang.StringBuilder
		// @5F: bipush 41 (0x29)
		// @61: invokevirtual java.lang.StringBuilder.append(char)java.lang.StringBuilder
		// @64: invokevirtual java.lang.StringBuilder.toString()java.lang.String
		// @67: invokestatic game.C_100181_cf.func_105695_a(java.lang.Throwable, java.lang.String)game.C_100170_cm
		// @6A: athrow
		// @6B: return
	}
	
	final boolean func_102034_a(int arg0, int arg1, int arg2, boolean arg3, int arg4, boolean arg5)
	{
		// @00: iload_1
		// @01: iconst_m1
		// @02: if_icmpeq @13
		// @05: aload_0
		// @06: bipush -44 (0xD4)
		// @08: bipush 62 (0x3E)
		// @0A: bipush -128 (0x80)
		// @0C: invokespecial game.C_100115_ej.func_102033_a(int, int, int)void
		// @0F: goto @13
		// @12: athrow
		// @13: aload_0
		// @14: iload #6
		// @16: iconst_0
		// @17: iload_2
		// @18: iload #4
		// @1A: iload_3
		// @1B: iload #5
		// @1D: aload_0
		// @1E: getfield game.C_100302_ka game.C_100115_ej.field_102040_Zb
		// @21: getfield int game.C_100302_ka.field_101848_lb
		// @24: invokespecial game.C_100115_ej.func_102032_a(boolean, int, int, boolean, int, int, int)boolean
		// @27: ireturn
		// @28: astore #7
		// @2A: aload #7
		// @2C: new java.lang.StringBuilder
		// @2F: dup
		// @30: invokespecial java.lang.StringBuilder.<init>()void
		// @33: getstatic java.lang.String[] game.C_100115_ej.field_102044_ec
		// @36: bipush 14 (0x0E)
		// @38: aaload
		// @39: invokevirtual java.lang.StringBuilder.append(java.lang.String)java.lang.StringBuilder
		// @3C: iload_1
		// @3D: invokevirtual java.lang.StringBuilder.append(int)java.lang.StringBuilder
		// @40: bipush 44 (0x2C)
		// @42: invokevirtual java.lang.StringBuilder.append(char)java.lang.StringBuilder
		// @45: iload_2
		// @46: invokevirtual java.lang.StringBuilder.append(int)java.lang.StringBuilder
		// @49: bipush 44 (0x2C)
		// @4B: invokevirtual java.lang.StringBuilder.append(char)java.lang.StringBuilder
		// @4E: iload_3
		// @4F: invokevirtual java.lang.StringBuilder.append(int)java.lang.StringBuilder
		// @52: bipush 44 (0x2C)
		// @54: invokevirtual java.lang.StringBuilder.append(char)java.lang.StringBuilder
		// @57: iload #4
		// @59: invokevirtual java.lang.StringBuilder.append(boolean)java.lang.StringBuilder
		// @5C: bipush 44 (0x2C)
		// @5E: invokevirtual java.lang.StringBuilder.append(char)java.lang.StringBuilder
		// @61: iload #5
		// @63: invokevirtual java.lang.StringBuilder.append(int)java.lang.StringBuilder
		// @66: bipush 44 (0x2C)
		// @68: invokevirtual java.lang.StringBuilder.append(char)java.lang.StringBuilder
		// @6B: iload #6
		// @6D: invokevirtual java.lang.StringBuilder.append(boolean)java.lang.StringBuilder
		// @70: bipush 41 (0x29)
		// @72: invokevirtual java.lang.StringBuilder.append(char)java.lang.StringBuilder
		// @75: invokevirtual java.lang.StringBuilder.toString()java.lang.String
		// @78: invokestatic game.C_100181_cf.func_105695_a(java.lang.Throwable, java.lang.String)game.C_100170_cm
		// @7B: athrow
	}
	
	private final boolean func_102032_a(boolean arg0, int arg1, int arg2, boolean arg3, int arg4, int arg5, int arg6)
	{
		// @00: iload #4
		// @02: ifne @18
		// @05: aload_0
		// @06: getfield boolean game.C_100115_ej.field_101839_db
		// @09: ifeq @1D
		// @0C: goto @10
		// @0F: athrow
		// @10: iload_1
		// @11: ifne @1D
		// @14: goto @18
		// @17: athrow
		// @18: iconst_1
		// @19: goto @1E
		// @1C: athrow
		// @1D: iconst_0
		// @1E: istore #8
		// @20: aload_0
		// @21: getfield game.C_100302_ka game.C_100115_ej.field_102036_Wb
		// @24: aload_0
		// @25: getfield game.C_100302_ka game.C_100115_ej.field_102040_Zb
		// @28: getfield int game.C_100302_ka.field_101848_lb
		// @2B: iload #6
		// @2D: iload #8
		// @2F: iconst_m1
		// @30: invokevirtual game.C_100302_ka.func_101820_a(int, int, boolean, int)void
		// @33: aload_0
		// @34: iload_3
		// @35: bipush -101 (0x9B)
		// @37: iconst_0
		// @38: iload #7
		// @3A: iload #5
		// @3C: invokevirtual game.C_100115_ej.func_102025_a(int, int, boolean, int, int)void
		// @3F: iload_2
		// @40: ifeq @52
		// @43: aload_0
		// @44: bipush -10 (0xF6)
		// @46: iconst_1
		// @47: bipush 106 (0x6A)
		// @49: bipush 14 (0x0E)
		// @4B: invokevirtual game.C_100115_ej.func_102028_a(int, boolean, int, int)void
		// @4E: goto @52
		// @51: athrow
		// @52: iload #8
		// @54: ireturn
		// @55: astore #8
		// @57: aload #8
		// @59: new java.lang.StringBuilder
		// @5C: dup
		// @5D: invokespecial java.lang.StringBuilder.<init>()void
		// @60: getstatic java.lang.String[] game.C_100115_ej.field_102044_ec
		// @63: iconst_1
		// @64: aaload
		// @65: invokevirtual java.lang.StringBuilder.append(java.lang.String)java.lang.StringBuilder
		// @68: iload_1
		// @69: invokevirtual java.lang.StringBuilder.append(boolean)java.lang.StringBuilder
		// @6C: bipush 44 (0x2C)
		// @6E: invokevirtual java.lang.StringBuilder.append(char)java.lang.StringBuilder
		// @71: iload_2
		// @72: invokevirtual java.lang.StringBuilder.append(int)java.lang.StringBuilder
		// @75: bipush 44 (0x2C)
		// @77: invokevirtual java.lang.StringBuilder.append(char)java.lang.StringBuilder
		// @7A: iload_3
		// @7B: invokevirtual java.lang.StringBuilder.append(int)java.lang.StringBuilder
		// @7E: bipush 44 (0x2C)
		// @80: invokevirtual java.lang.StringBuilder.append(char)java.lang.StringBuilder
		// @83: iload #4
		// @85: invokevirtual java.lang.StringBuilder.append(boolean)java.lang.StringBuilder
		// @88: bipush 44 (0x2C)
		// @8A: invokevirtual java.lang.StringBuilder.append(char)java.lang.StringBuilder
		// @8D: iload #5
		// @8F: invokevirtual java.lang.StringBuilder.append(int)java.lang.StringBuilder
		// @92: bipush 44 (0x2C)
		// @94: invokevirtual java.lang.StringBuilder.append(char)java.lang.StringBuilder
		// @97: iload #6
		// @99: invokevirtual java.lang.StringBuilder.append(int)java.lang.StringBuilder
		// @9C: bipush 44 (0x2C)
		// @9E: invokevirtual java.lang.StringBuilder.append(char)java.lang.StringBuilder
		// @A1: iload #7
		// @A3: invokevirtual java.lang.StringBuilder.append(int)java.lang.StringBuilder
		// @A6: bipush 41 (0x29)
		// @A8: invokevirtual java.lang.StringBuilder.append(char)java.lang.StringBuilder
		// @AB: invokevirtual java.lang.StringBuilder.toString()java.lang.String
		// @AE: invokestatic game.C_100181_cf.func_105695_a(java.lang.Throwable, java.lang.String)game.C_100170_cm
		// @B1: athrow
	}
	
	public static void func_102027_l(int arg0)
	{
		// @00: aconst_null
		// @01: putstatic game.C_100278_nd game.C_100115_ej.field_102043_Yb
		// @04: bipush -81 (0xAF)
		// @06: iload_0
		// @07: bipush 51 (0x33)
		// @09: isub
		// @0A: bipush 32 (0x20)
		// @0C: idiv
		// @0D: irem
		// @0E: istore_1
		// @0F: aconst_null
		// @10: putstatic game.C_100302_ka game.C_100115_ej.field_102045_cc
		// @13: aconst_null
		// @14: putstatic java.lang.String game.C_100115_ej.field_102035_dc
		// @17: aconst_null
		// @18: putstatic game.C_100130_tf game.C_100115_ej.field_102039_ac
		// @1B: aconst_null
		// @1C: putstatic java.lang.String game.C_100115_ej.field_102042_bc
		// @1F: aconst_null
		// @20: putstatic game.C_100153_be game.C_100115_ej.field_102041_Xb
		// @23: goto @48
		// @26: astore_1
		// @27: aload_1
		// @28: new java.lang.StringBuilder
		// @2B: dup
		// @2C: invokespecial java.lang.StringBuilder.<init>()void
		// @2F: getstatic java.lang.String[] game.C_100115_ej.field_102044_ec
		// @32: bipush 13 (0x0D)
		// @34: aaload
		// @35: invokevirtual java.lang.StringBuilder.append(java.lang.String)java.lang.StringBuilder
		// @38: iload_0
		// @39: invokevirtual java.lang.StringBuilder.append(int)java.lang.StringBuilder
		// @3C: bipush 41 (0x29)
		// @3E: invokevirtual java.lang.StringBuilder.append(char)java.lang.StringBuilder
		// @41: invokevirtual java.lang.StringBuilder.toString()java.lang.String
		// @44: invokestatic game.C_100181_cf.func_105695_a(java.lang.Throwable, java.lang.String)game.C_100170_cm
		// @47: athrow
		// @48: return
	}
	
	C_100115_ej(long arg0, C_100302_ka arg1, C_100302_ka arg2, C_100231_oc arg3)
	{
		// @00: aload_0
		// @01: lload_1
		// @02: aconst_null
		// @03: invokespecial game.C_100302_ka.<init>(long, game.C_100302_ka)void
		// @06: aload_0
		// @07: new game.C_100302_ka
		// @0A: dup
		// @0B: lconst_0
		// @0C: aload #4
		// @0E: invokespecial game.C_100302_ka.<init>(long, game.C_100302_ka)void
		// @11: putfield game.C_100302_ka game.C_100115_ej.field_102040_Zb
		// @14: aload_0
		// @15: new game.C_100231_oc
		// @18: dup
		// @19: lconst_0
		// @1A: aload #5
		// @1C: invokespecial game.C_100231_oc.<init>(long, game.C_100231_oc)void
		// @1F: putfield game.C_100231_oc game.C_100115_ej.field_102038_Vb
		// @22: aload_0
		// @23: bipush -126 (0x82)
		// @25: aload_0
		// @26: getfield game.C_100302_ka game.C_100115_ej.field_102040_Zb
		// @29: invokevirtual game.C_100115_ej.func_101824_b(int, game.C_100302_ka)void
		// @2C: aload_0
		// @2D: bipush -123 (0x85)
		// @2F: aload_0
		// @30: getfield game.C_100231_oc game.C_100115_ej.field_102038_Vb
		// @33: invokevirtual game.C_100115_ej.func_101824_b(int, game.C_100302_ka)void
		// @36: aload_0
		// @37: aload_3
		// @38: putfield game.C_100302_ka game.C_100115_ej.field_102036_Wb
		// @3B: aload_0
		// @3C: getfield game.C_100302_ka game.C_100115_ej.field_102040_Zb
		// @3F: bipush -124 (0x84)
		// @41: aload_3
		// @42: invokevirtual game.C_100302_ka.func_101824_b(int, game.C_100302_ka)void
		// @45: goto @C2
		// @48: astore #6
		// @4A: aload #6
		// @4C: new java.lang.StringBuilder
		// @4F: dup
		// @50: invokespecial java.lang.StringBuilder.<init>()void
		// @53: getstatic java.lang.String[] game.C_100115_ej.field_102044_ec
		// @56: bipush 10 (0x0A)
		// @58: aaload
		// @59: invokevirtual java.lang.StringBuilder.append(java.lang.String)java.lang.StringBuilder
		// @5C: lload_1
		// @5D: invokevirtual java.lang.StringBuilder.append(long)java.lang.StringBuilder
		// @60: bipush 44 (0x2C)
		// @62: invokevirtual java.lang.StringBuilder.append(char)java.lang.StringBuilder
		// @65: aload_3
		// @66: ifnull @73
		// @69: getstatic java.lang.String[] game.C_100115_ej.field_102044_ec
		// @6C: bipush 8 (0x08)
		// @6E: aaload
		// @6F: goto @79
		// @72: athrow
		// @73: getstatic java.lang.String[] game.C_100115_ej.field_102044_ec
		// @76: bipush 9 (0x09)
		// @78: aaload
		// @79: invokevirtual java.lang.StringBuilder.append(java.lang.String)java.lang.StringBuilder
		// @7C: bipush 44 (0x2C)
		// @7E: invokevirtual java.lang.StringBuilder.append(char)java.lang.StringBuilder
		// @81: aload #4
		// @83: ifnull @90
		// @86: getstatic java.lang.String[] game.C_100115_ej.field_102044_ec
		// @89: bipush 8 (0x08)
		// @8B: aaload
		// @8C: goto @96
		// @8F: athrow
		// @90: getstatic java.lang.String[] game.C_100115_ej.field_102044_ec
		// @93: bipush 9 (0x09)
		// @95: aaload
		// @96: invokevirtual java.lang.StringBuilder.append(java.lang.String)java.lang.StringBuilder
		// @99: bipush 44 (0x2C)
		// @9B: invokevirtual java.lang.StringBuilder.append(char)java.lang.StringBuilder
		// @9E: aload #5
		// @A0: ifnull @AD
		// @A3: getstatic java.lang.String[] game.C_100115_ej.field_102044_ec
		// @A6: bipush 8 (0x08)
		// @A8: aaload
		// @A9: goto @B3
		// @AC: athrow
		// @AD: getstatic java.lang.String[] game.C_100115_ej.field_102044_ec
		// @B0: bipush 9 (0x09)
		// @B2: aaload
		// @B3: invokevirtual java.lang.StringBuilder.append(java.lang.String)java.lang.StringBuilder
		// @B6: bipush 41 (0x29)
		// @B8: invokevirtual java.lang.StringBuilder.append(char)java.lang.StringBuilder
		// @BB: invokevirtual java.lang.StringBuilder.toString()java.lang.String
		// @BE: invokestatic game.C_100181_cf.func_105695_a(java.lang.Throwable, java.lang.String)game.C_100170_cm
		// @C1: athrow
		// @C2: return
	}
	
	static
	{
		// @00: bipush 15 (0x0F)
		// @02: anewarray java.lang.String
		// @05: dup
		// @06: iconst_0
		// @07: ldc "w\u000e\u001af\u0004"
		// @09: invokestatic game.C_100115_ej.func_102031_z(java.lang.String)char[]
		// @0C: invokestatic game.C_100115_ej.func_102029_z(char[])java.lang.String
		// @0F: aastore
		// @10: dup
		// @11: iconst_1
		// @12: ldc "w\u000e\u001ac\u0004"
		// @14: invokestatic game.C_100115_ej.func_102031_z(java.lang.String)char[]
		// @17: invokestatic game.C_100115_ej.func_102029_z(char[])java.lang.String
		// @1A: aastore
		// @1B: dup
		// @1C: iconst_2
		// @1D: ldc "w\u000e\u001ab\u0004"
		// @1F: invokestatic game.C_100115_ej.func_102031_z(java.lang.String)char[]
		// @22: invokestatic game.C_100115_ej.func_102029_z(char[])java.lang.String
		// @25: aastore
		// @26: dup
		// @27: iconst_3
		// @28: ldc "w\u000e\u001ae\u0004"
		// @2A: invokestatic game.C_100115_ej.func_102031_z(java.lang.String)char[]
		// @2D: invokestatic game.C_100115_ej.func_102029_z(char[])java.lang.String
		// @30: aastore
		// @31: dup
		// @32: iconst_4
		// @33: ldc ".KWH@,"
		// @35: invokestatic game.C_100115_ej.func_102031_z(java.lang.String)char[]
		// @38: invokestatic game.C_100115_ej.func_102029_z(char[])java.lang.String
		// @3B: aastore
		// @3C: dup
		// @3D: iconst_5
		// @3E: ldc ".\u0006F\u0019"
		// @40: invokestatic game.C_100115_ej.func_102031_z(java.lang.String)char[]
		// @43: invokestatic game.C_100115_ej.func_102029_z(char[])java.lang.String
		// @46: aastore
		// @47: dup
		// @48: bipush 6 (0x06)
		// @4A: ldc ">D"
		// @4C: invokestatic game.C_100115_ej.func_102031_z(java.lang.String)char[]
		// @4F: invokestatic game.C_100115_ej.func_102029_z(char[])java.lang.String
		// @52: aastore
		// @53: dup
		// @54: bipush 7 (0x07)
		// @56: ldc ".\u0007[K\u0011ST\u0004\u0017\u001c\"Z"
		// @58: invokestatic game.C_100115_ej.func_102031_z(java.lang.String)char[]
		// @5B: invokestatic game.C_100115_ej.func_102029_z(char[])java.lang.String
		// @5E: aastore
		// @5F: dup
		// @60: bipush 8 (0x08)
		// @62: ldc "iJ\u001a\tQ"
		// @64: invokestatic game.C_100115_ej.func_102031_z(java.lang.String)char[]
		// @67: invokestatic game.C_100115_ej.func_102029_z(char[])java.lang.String
		// @6A: aastore
		// @6B: dup
		// @6C: bipush 9 (0x09)
		// @6E: ldc "|\u0011XK"
		// @70: invokestatic game.C_100115_ej.func_102031_z(java.lang.String)char[]
		// @73: invokestatic game.C_100115_ej.func_102029_z(char[])java.lang.String
		// @76: aastore
		// @77: dup
		// @78: bipush 10 (0x0A)
		// @7A: ldc "w\u000e\u001a\u001bE|\r@\u0019\u0004"
		// @7C: invokestatic game.C_100115_ej.func_102031_z(java.lang.String)char[]
		// @7F: invokestatic game.C_100115_ej.func_102029_z(char[])java.lang.String
		// @82: aastore
		// @83: dup
		// @84: bipush 11 (0x0B)
		// @86: ldc "w\u000e\u001a`\u0004"
		// @88: invokestatic game.C_100115_ej.func_102031_z(java.lang.String)char[]
		// @8B: invokestatic game.C_100115_ej.func_102029_z(char[])java.lang.String
		// @8E: aastore
		// @8F: dup
		// @90: bipush 12 (0x0C)
		// @92: ldc "w\u000e\u001ao\u0004"
		// @94: invokestatic game.C_100115_ej.func_102031_z(java.lang.String)char[]
		// @97: invokestatic game.C_100115_ej.func_102029_z(char[])java.lang.String
		// @9A: aastore
		// @9B: dup
		// @9C: bipush 13 (0x0D)
		// @9E: ldc "w\u000e\u001ad\u0004"
		// @A0: invokestatic game.C_100115_ej.func_102031_z(java.lang.String)char[]
		// @A3: invokestatic game.C_100115_ej.func_102029_z(char[])java.lang.String
		// @A6: aastore
		// @A7: dup
		// @A8: bipush 14 (0x0E)
		// @AA: ldc "w\u000e\u001aa\u0004"
		// @AC: invokestatic game.C_100115_ej.func_102031_z(java.lang.String)char[]
		// @AF: invokestatic game.C_100115_ej.func_102029_z(char[])java.lang.String
		// @B2: aastore
		// @B3: putstatic java.lang.String[] game.C_100115_ej.field_102044_ec
		// @B6: new game.C_100153_be
		// @B9: dup
		// @BA: iconst_1
		// @BB: iconst_1
		// @BC: iconst_1
		// @BD: invokespecial game.C_100153_be.<init>(int, int, int)void
		// @C0: putstatic game.C_100153_be game.C_100115_ej.field_102041_Xb
		// @C3: ldc "Z\rPB\u000cq\u000cUS"
		// @C5: invokestatic game.C_100115_ej.func_102031_z(java.lang.String)char[]
		// @C8: invokestatic game.C_100115_ej.func_102029_z(char[])java.lang.String
		// @CB: putstatic java.lang.String game.C_100115_ej.field_102042_bc
		// @CE: ldc "G\nDFOy\rZ@\u000c\u007f\u0011GNO"
		// @D0: invokestatic game.C_100115_ej.func_102031_z(java.lang.String)char[]
		// @D3: invokestatic game.C_100115_ej.func_102029_z(char[])java.lang.String
		// @D6: putstatic java.lang.String game.C_100115_ej.field_102035_dc
		// @D9: new game.C_100130_tf
		// @DC: dup
		// @DD: invokespecial game.C_100130_tf.<init>()void
		// @E0: putstatic game.C_100130_tf game.C_100115_ej.field_102039_ac
		// @E3: return
	}
	
	private static char[] func_102031_z(String arg0)
	{
		// @00: aload_0
		// @01: invokevirtual java.lang.String.toCharArray()char[]
		// @04: dup
		// @05: arraylength
		// @06: iconst_2
		// @07: if_icmpge @13
		// @0A: dup
		// @0B: iconst_0
		// @0C: dup2
		// @0D: caload
		// @0E: bipush 44 (0x2C)
		// @10: ixor
		// @11: i2c
		// @12: castore
		// @13: areturn
	}
	
	private static String func_102029_z(char[] arg0)
	{
		// @00: aload_0
		// @01: dup
		// @02: arraylength
		// @03: swap
		// @04: iconst_0
		// @05: istore_1
		// @06: goto @4C
		// @09: dup
		// @0A: iload_1
		// @0B: dup2
		// @0C: caload
		// @0D: iload_1
		// @0E: iconst_5
		// @0F: irem
		// @10: tableswitch def: @44, for 0: @30, for 1: @35, for 2: @3A, for 3: @3F
		// @30: bipush 18 (0x12)
		// @32: goto @46
		// @35: bipush 100 (0x64)
		// @37: goto @46
		// @3A: bipush 52 (0x34)
		// @3C: goto @46
		// @3F: bipush 39 (0x27)
		// @41: goto @46
		// @44: bipush 44 (0x2C)
		// @46: ixor
		// @47: i2c
		// @48: castore
		// @49: iinc #1 +1
		// @4C: swap
		// @4D: dup_x1
		// @4E: iload_1
		// @4F: if_icmpgt @09
		// @52: new java.lang.String
		// @55: dup_x1
		// @56: swap
		// @57: invokespecial java.lang.String.<init>(char[])void
		// @5A: invokevirtual java.lang.String.intern()java.lang.String
		// @5D: areturn
	}
}
