package game;

class C_100309_lk extends C_100218_am
{
	private int field_103257_O;
	static C_100037_wb field_103255_db;
	private long field_103265_W;
	static C_100037_wb field_103268_P;
	static String field_103269_S;
	static C_100127_tl field_103263_T;
	static C_100268_mk field_103259_eb;
	static boolean field_103271_ab;
	private int field_103261_gb;
	private int field_103274_X;
	static boolean[] field_103258_hb;
	static String field_103266_V;
	private int field_103270_R;
	private boolean field_103260_fb;
	private long field_103256_cb;
	static int field_103267_Q;
	private boolean field_103262_U;
	static C_100037_wb field_103275_Z;
	static int[] field_103273_Y;
	static C_100302_ka field_103272_bb;
	private static final String[] field_103264_ib;
	
	void func_103241_k(int arg0)
	{
		// @00: iload_1
		// @01: sipush -19211 (0xB4F5)
		// @04: if_icmpeq @12
		// @07: aconst_null
		// @08: checkcast game.C_100302_ka
		// @0B: putstatic game.C_100302_ka game.C_100309_lk.field_103272_bb
		// @0E: goto @12
		// @11: athrow
		// @12: aload_0
		// @13: getfield game.C_100337_in game.C_100309_lk.field_102543_u
		// @16: instanceof game.C_100224_ag
		// @19: ifne @20
		// @1C: goto @2F
		// @1F: athrow
		// @20: aload_0
		// @21: getfield game.C_100337_in game.C_100309_lk.field_102543_u
		// @24: checkcast game.C_100224_ag
		// @27: bipush 86 (0x56)
		// @29: aload_0
		// @2A: invokeinterface game.C_100224_ag.func_102580_a(byte, game.C_100309_lk)void
		// @2F: goto @54
		// @32: astore_2
		// @33: aload_2
		// @34: new java.lang.StringBuilder
		// @37: dup
		// @38: invokespecial java.lang.StringBuilder.<init>()void
		// @3B: getstatic java.lang.String[] game.C_100309_lk.field_103264_ib
		// @3E: bipush 20 (0x14)
		// @40: aaload
		// @41: invokevirtual java.lang.StringBuilder.append(java.lang.String)java.lang.StringBuilder
		// @44: iload_1
		// @45: invokevirtual java.lang.StringBuilder.append(int)java.lang.StringBuilder
		// @48: bipush 41 (0x29)
		// @4A: invokevirtual java.lang.StringBuilder.append(char)java.lang.StringBuilder
		// @4D: invokevirtual java.lang.StringBuilder.toString()java.lang.String
		// @50: invokestatic game.C_100181_cf.func_105695_a(java.lang.Throwable, java.lang.String)game.C_100170_cm
		// @53: athrow
		// @54: return
	}
	
	private final void func_103249_q(int arg0)
	{
		// @00: aload_0
		// @01: getfield game.C_100337_in game.C_100309_lk.field_102543_u
		// @04: instanceof game.C_100224_ag
		// @07: ifeq @1F
		// @0A: aload_0
		// @0B: getfield game.C_100337_in game.C_100309_lk.field_102543_u
		// @0E: checkcast game.C_100224_ag
		// @11: iload_1
		// @12: bipush 20 (0x14)
		// @14: ixor
		// @15: aload_0
		// @16: invokeinterface game.C_100224_ag.func_102579_a(int, game.C_100309_lk)void
		// @1B: goto @1F
		// @1E: athrow
		// @1F: iload_1
		// @20: ifeq @2E
		// @23: aconst_null
		// @24: checkcast int[]
		// @27: putstatic int[] game.C_100309_lk.field_103273_Y
		// @2A: goto @2E
		// @2D: athrow
		// @2E: goto @53
		// @31: astore_2
		// @32: aload_2
		// @33: new java.lang.StringBuilder
		// @36: dup
		// @37: invokespecial java.lang.StringBuilder.<init>()void
		// @3A: getstatic java.lang.String[] game.C_100309_lk.field_103264_ib
		// @3D: bipush 8 (0x08)
		// @3F: aaload
		// @40: invokevirtual java.lang.StringBuilder.append(java.lang.String)java.lang.StringBuilder
		// @43: iload_1
		// @44: invokevirtual java.lang.StringBuilder.append(int)java.lang.StringBuilder
		// @47: bipush 41 (0x29)
		// @49: invokevirtual java.lang.StringBuilder.append(char)java.lang.StringBuilder
		// @4C: invokevirtual java.lang.StringBuilder.toString()java.lang.String
		// @4F: invokestatic game.C_100181_cf.func_105695_a(java.lang.Throwable, java.lang.String)game.C_100170_cm
		// @52: athrow
		// @53: return
	}
	
	static final void func_103245_a(int arg0, int arg1, C_100026_hb arg2, C_100098_h arg3)
	{
		// @00: bipush 126 (0x7E)
		// @02: invokestatic game.C_100131_te.func_100753_a(byte)int
		// @05: iload_0
		// @06: imul
		// @07: sipush 1000 (0x03E8)
		// @0A: idiv
		// @0B: putstatic int game.C_100115_ej.field_102037_Ub
		// @0E: iload_1
		// @0F: bipush -102 (0x9A)
		// @11: if_icmple @15
		// @14: return
		// @15: aload_3
		// @16: iconst_0
		// @17: invokestatic game.C_100060_di.func_104264_a(game.C_100098_h, int)void
		// @1A: aload_3
		// @1B: bipush -102 (0x9A)
		// @1D: invokestatic game.C_100280_nf.func_101133_a(game.C_100098_h, byte)void
		// @20: aload_3
		// @21: iconst_0
		// @22: invokestatic game.C_100060_di.func_104263_b(game.C_100098_h, int)void
		// @25: bipush 106 (0x6A)
		// @27: invokestatic game.C_100012_fh.func_100500_e(int)void
		// @2A: sipush 255 (0x00FF)
		// @2D: invokestatic game.C_100332_ii.func_107302_a(int)void
		// @30: iconst_0
		// @31: getstatic int game.C_100115_ej.field_102037_Ub
		// @34: ineg
		// @35: iadd
		// @36: putstatic int game.C_100015_wh.field_103783_e
		// @39: goto @9D
		// @3C: astore #4
		// @3E: aload #4
		// @40: new java.lang.StringBuilder
		// @43: dup
		// @44: invokespecial java.lang.StringBuilder.<init>()void
		// @47: getstatic java.lang.String[] game.C_100309_lk.field_103264_ib
		// @4A: bipush 23 (0x17)
		// @4C: aaload
		// @4D: invokevirtual java.lang.StringBuilder.append(java.lang.String)java.lang.StringBuilder
		// @50: iload_0
		// @51: invokevirtual java.lang.StringBuilder.append(int)java.lang.StringBuilder
		// @54: bipush 44 (0x2C)
		// @56: invokevirtual java.lang.StringBuilder.append(char)java.lang.StringBuilder
		// @59: iload_1
		// @5A: invokevirtual java.lang.StringBuilder.append(int)java.lang.StringBuilder
		// @5D: bipush 44 (0x2C)
		// @5F: invokevirtual java.lang.StringBuilder.append(char)java.lang.StringBuilder
		// @62: aload_2
		// @63: ifnull @6F
		// @66: getstatic java.lang.String[] game.C_100309_lk.field_103264_ib
		// @69: iconst_1
		// @6A: aaload
		// @6B: goto @74
		// @6E: athrow
		// @6F: getstatic java.lang.String[] game.C_100309_lk.field_103264_ib
		// @72: iconst_2
		// @73: aaload
		// @74: invokevirtual java.lang.StringBuilder.append(java.lang.String)java.lang.StringBuilder
		// @77: bipush 44 (0x2C)
		// @79: invokevirtual java.lang.StringBuilder.append(char)java.lang.StringBuilder
		// @7C: aload_3
		// @7D: ifnull @89
		// @80: getstatic java.lang.String[] game.C_100309_lk.field_103264_ib
		// @83: iconst_1
		// @84: aaload
		// @85: goto @8E
		// @88: athrow
		// @89: getstatic java.lang.String[] game.C_100309_lk.field_103264_ib
		// @8C: iconst_2
		// @8D: aaload
		// @8E: invokevirtual java.lang.StringBuilder.append(java.lang.String)java.lang.StringBuilder
		// @91: bipush 41 (0x29)
		// @93: invokevirtual java.lang.StringBuilder.append(char)java.lang.StringBuilder
		// @96: invokevirtual java.lang.StringBuilder.toString()java.lang.String
		// @99: invokestatic game.C_100181_cf.func_105695_a(java.lang.Throwable, java.lang.String)game.C_100170_cm
		// @9C: athrow
		// @9D: return
	}
	
	private final void func_103246_a(byte arg0)
	{
		// @00: iload_1
		// @01: bipush 66 (0x42)
		// @03: if_icmpeq @11
		// @06: aconst_null
		// @07: checkcast game.C_100127_tl
		// @0A: putstatic game.C_100127_tl game.C_100309_lk.field_103263_T
		// @0D: goto @11
		// @10: athrow
		// @11: aload_0
		// @12: getfield int game.C_100309_lk.field_103270_R
		// @15: iconst_m1
		// @16: ixor
		// @17: aload_0
		// @18: getfield int game.C_100309_lk.field_103257_O
		// @1B: iconst_m1
		// @1C: ixor
		// @1D: if_icmpeq @99
		// @20: aload_0
		// @21: getfield int game.C_100309_lk.field_103257_O
		// @24: iconst_m1
		// @25: ixor
		// @26: aload_0
		// @27: getfield int game.C_100309_lk.field_103270_R
		// @2A: iconst_m1
		// @2B: ixor
		// @2C: if_icmple @3B
		// @2F: goto @33
		// @32: athrow
		// @33: aload_0
		// @34: getfield int game.C_100309_lk.field_103257_O
		// @37: goto @3F
		// @3A: athrow
		// @3B: aload_0
		// @3C: getfield int game.C_100309_lk.field_103270_R
		// @3F: istore_2
		// @40: aload_0
		// @41: getfield int game.C_100309_lk.field_103257_O
		// @44: iconst_m1
		// @45: ixor
		// @46: aload_0
		// @47: getfield int game.C_100309_lk.field_103270_R
		// @4A: iconst_m1
		// @4B: ixor
		// @4C: if_icmple @57
		// @4F: aload_0
		// @50: getfield int game.C_100309_lk.field_103270_R
		// @53: goto @5B
		// @56: athrow
		// @57: aload_0
		// @58: getfield int game.C_100309_lk.field_103257_O
		// @5B: istore_3
		// @5C: aload_0
		// @5D: iload_2
		// @5E: putfield int game.C_100309_lk.field_103257_O
		// @61: aload_0
		// @62: iload_2
		// @63: putfield int game.C_100309_lk.field_103270_R
		// @66: aload_0
		// @67: new java.lang.StringBuilder
		// @6A: dup
		// @6B: invokespecial java.lang.StringBuilder.<init>()void
		// @6E: aload_0
		// @6F: getfield java.lang.String game.C_100309_lk.field_102534_C
		// @72: iconst_0
		// @73: iload_2
		// @74: invokevirtual java.lang.String.substring(int, int)java.lang.String
		// @77: invokevirtual java.lang.StringBuilder.append(java.lang.String)java.lang.StringBuilder
		// @7A: aload_0
		// @7B: getfield java.lang.String game.C_100309_lk.field_102534_C
		// @7E: iload_3
		// @7F: aload_0
		// @80: getfield java.lang.String game.C_100309_lk.field_102534_C
		// @83: invokevirtual java.lang.String.length()int
		// @86: invokevirtual java.lang.String.substring(int, int)java.lang.String
		// @89: invokevirtual java.lang.StringBuilder.append(java.lang.String)java.lang.StringBuilder
		// @8C: invokevirtual java.lang.StringBuilder.toString()java.lang.String
		// @8F: putfield java.lang.String game.C_100309_lk.field_102534_C
		// @92: aload_0
		// @93: sipush -19211 (0xB4F5)
		// @96: invokevirtual game.C_100309_lk.func_103241_k(int)void
		// @99: goto @BE
		// @9C: astore_2
		// @9D: aload_2
		// @9E: new java.lang.StringBuilder
		// @A1: dup
		// @A2: invokespecial java.lang.StringBuilder.<init>()void
		// @A5: getstatic java.lang.String[] game.C_100309_lk.field_103264_ib
		// @A8: bipush 12 (0x0C)
		// @AA: aaload
		// @AB: invokevirtual java.lang.StringBuilder.append(java.lang.String)java.lang.StringBuilder
		// @AE: iload_1
		// @AF: invokevirtual java.lang.StringBuilder.append(int)java.lang.StringBuilder
		// @B2: bipush 41 (0x29)
		// @B4: invokevirtual java.lang.StringBuilder.append(char)java.lang.StringBuilder
		// @B7: invokevirtual java.lang.StringBuilder.toString()java.lang.String
		// @BA: invokestatic game.C_100181_cf.func_105695_a(java.lang.Throwable, java.lang.String)game.C_100170_cm
		// @BD: athrow
		// @BE: return
	}
	
	void func_102513_a(C_100336_im arg0, int arg1, int arg2, int arg3)
	{
		// @00: aload_0
		// @01: aload_1
		// @02: iload_2
		// @03: iload_3
		// @04: iload #4
		// @06: invokespecial game.C_100218_am.func_102513_a(game.C_100336_im, int, int, int)void
		// @09: aload_0
		// @0A: iconst_0
		// @0B: invokespecial game.C_100309_lk.func_103254_d(boolean)void
		// @0E: iconst_1
		// @0F: aload_0
		// @10: getfield int game.C_100309_lk.field_102532_A
		// @13: if_icmpne @8C
		// @16: aload_0
		// @17: getfield game.C_100326_ic game.C_100309_lk.field_102533_B
		// @1A: instanceof game.C_100184_rn
		// @1D: ifne @28
		// @20: goto @24
		// @23: athrow
		// @24: goto @83
		// @27: athrow
		// @28: aload_0
		// @29: getfield game.C_100326_ic game.C_100309_lk.field_102533_B
		// @2C: checkcast game.C_100184_rn
		// @2F: astore #5
		// @31: aload #5
		// @33: getstatic int game.C_100015_wh.field_103781_g
		// @36: iload #4
		// @38: getstatic int game.C_100338_jc.field_105370_l
		// @3B: aload_0
		// @3C: iload_2
		// @3D: iload_3
		// @3E: bipush 120 (0x78)
		// @40: iadd
		// @41: invokeinterface game.C_100184_rn.func_100443_a(int, int, int, game.C_100336_im, int, int)int
		// @46: istore #6
		// @48: iload #6
		// @4A: iconst_m1
		// @4B: if_icmpeq @83
		// @4E: aload_0
		// @4F: getfield boolean game.C_100309_lk.field_103260_fb
		// @52: ifeq @7D
		// @55: goto @59
		// @58: athrow
		// @59: aload_0
		// @5A: getfield int game.C_100309_lk.field_103261_gb
		// @5D: iload #6
		// @5F: if_icmple @7D
		// @62: goto @66
		// @65: athrow
		// @66: iload #6
		// @68: aload_0
		// @69: getfield int game.C_100309_lk.field_103257_O
		// @6C: if_icmpgt @77
		// @6F: goto @73
		// @72: athrow
		// @73: goto @7D
		// @76: athrow
		// @77: aload_0
		// @78: getfield int game.C_100309_lk.field_103261_gb
		// @7B: istore #6
		// @7D: aload_0
		// @7E: iload #6
		// @80: putfield int game.C_100309_lk.field_103270_R
		// @83: aload_0
		// @84: bipush 76 (0x4C)
		// @86: invokestatic game.C_100198_qn.func_105828_a(byte)long
		// @89: putfield long game.C_100309_lk.field_103256_cb
		// @8C: goto @DF
		// @8F: astore #5
		// @91: aload #5
		// @93: new java.lang.StringBuilder
		// @96: dup
		// @97: invokespecial java.lang.StringBuilder.<init>()void
		// @9A: getstatic java.lang.String[] game.C_100309_lk.field_103264_ib
		// @9D: iconst_0
		// @9E: aaload
		// @9F: invokevirtual java.lang.StringBuilder.append(java.lang.String)java.lang.StringBuilder
		// @A2: aload_1
		// @A3: ifnull @AF
		// @A6: getstatic java.lang.String[] game.C_100309_lk.field_103264_ib
		// @A9: iconst_1
		// @AA: aaload
		// @AB: goto @B4
		// @AE: athrow
		// @AF: getstatic java.lang.String[] game.C_100309_lk.field_103264_ib
		// @B2: iconst_2
		// @B3: aaload
		// @B4: invokevirtual java.lang.StringBuilder.append(java.lang.String)java.lang.StringBuilder
		// @B7: bipush 44 (0x2C)
		// @B9: invokevirtual java.lang.StringBuilder.append(char)java.lang.StringBuilder
		// @BC: iload_2
		// @BD: invokevirtual java.lang.StringBuilder.append(int)java.lang.StringBuilder
		// @C0: bipush 44 (0x2C)
		// @C2: invokevirtual java.lang.StringBuilder.append(char)java.lang.StringBuilder
		// @C5: iload_3
		// @C6: invokevirtual java.lang.StringBuilder.append(int)java.lang.StringBuilder
		// @C9: bipush 44 (0x2C)
		// @CB: invokevirtual java.lang.StringBuilder.append(char)java.lang.StringBuilder
		// @CE: iload #4
		// @D0: invokevirtual java.lang.StringBuilder.append(int)java.lang.StringBuilder
		// @D3: bipush 41 (0x29)
		// @D5: invokevirtual java.lang.StringBuilder.append(char)java.lang.StringBuilder
		// @D8: invokevirtual java.lang.StringBuilder.toString()java.lang.String
		// @DB: invokestatic game.C_100181_cf.func_105695_a(java.lang.Throwable, java.lang.String)game.C_100170_cm
		// @DE: athrow
		// @DF: return
	}
	
	final boolean func_102520_a(int arg0, C_100336_im arg1, int arg2, int arg3, int arg4, int arg5, int arg6)
	{
		// @000: bipush -123 (0x85)
		// @002: bipush 32 (0x20)
		// @004: iload_3
		// @005: isub
		// @006: bipush 52 (0x34)
		// @008: idiv
		// @009: irem
		// @00A: istore #8
		// @00C: aload_0
		// @00D: iload_1
		// @00E: aload_2
		// @00F: bipush 107 (0x6B)
		// @011: iload #4
		// @013: iload #5
		// @015: iload #6
		// @017: iload #7
		// @019: invokespecial game.C_100218_am.func_102520_a(int, game.C_100336_im, int, int, int, int, int)boolean
		// @01C: ifne @023
		// @01F: goto @0DB
		// @022: athrow
		// @023: aload_0
		// @024: getfield game.C_100326_ic game.C_100309_lk.field_102533_B
		// @027: instanceof game.C_100184_rn
		// @02A: ifeq @0DB
		// @02D: aload_0
		// @02E: getfield game.C_100326_ic game.C_100309_lk.field_102533_B
		// @031: checkcast game.C_100184_rn
		// @034: getstatic int game.C_100015_wh.field_103781_g
		// @037: iload #6
		// @039: getstatic int game.C_100338_jc.field_105370_l
		// @03C: aload_0
		// @03D: iload #5
		// @03F: bipush 95 (0x5F)
		// @041: invokeinterface game.C_100184_rn.func_100443_a(int, int, int, game.C_100336_im, int, int)int
		// @046: istore #9
		// @048: aload_0
		// @049: iload #9
		// @04B: iconst_m1
		// @04C: ixor
		// @04D: ifne @055
		// @050: iconst_0
		// @051: goto @057
		// @054: athrow
		// @055: iload #9
		// @057: bipush 96 (0x60)
		// @059: invokespecial game.C_100309_lk.func_103250_b(int, int)void
		// @05C: bipush 61 (0x3D)
		// @05E: invokestatic game.C_100198_qn.func_105828_a(byte)long
		// @061: lstore #9
		// @063: aload_0
		// @064: ldc2_w 250
		// @067: aload_0
		// @068: getfield long game.C_100309_lk.field_103265_W
		// @06B: lneg
		// @06C: lload #9
		// @06E: ladd
		// @06F: lcmp
		// @070: ifle @078
		// @073: iconst_1
		// @074: goto @079
		// @077: athrow
		// @078: iconst_0
		// @079: putfield boolean game.C_100309_lk.field_103260_fb
		// @07C: aload_0
		// @07D: getfield boolean game.C_100309_lk.field_103260_fb
		// @080: ifne @087
		// @083: goto @0D3
		// @086: athrow
		// @087: aload_0
		// @088: aload_0
		// @089: sipush -27931 (0x92E5)
		// @08C: invokespecial game.C_100309_lk.func_103243_n(int)int
		// @08F: putfield int game.C_100309_lk.field_103257_O
		// @092: aload_0
		// @093: aload_0
		// @094: sipush -17562 (0xBB66)
		// @097: invokespecial game.C_100309_lk.func_103237_l(int)int
		// @09A: putfield int game.C_100309_lk.field_103270_R
		// @09D: iconst_m1
		// @09E: aload_0
		// @09F: getfield int game.C_100309_lk.field_103270_R
		// @0A2: iconst_m1
		// @0A3: ixor
		// @0A4: if_icmple @0CB
		// @0A7: aload_0
		// @0A8: getfield java.lang.String game.C_100309_lk.field_102534_C
		// @0AB: aload_0
		// @0AC: getfield int game.C_100309_lk.field_103270_R
		// @0AF: iconst_1
		// @0B0: isub
		// @0B1: invokevirtual java.lang.String.charAt(int)char
		// @0B4: bipush 32 (0x20)
		// @0B6: if_icmpne @0CB
		// @0B9: goto @0BD
		// @0BC: athrow
		// @0BD: aload_0
		// @0BE: dup
		// @0BF: getfield int game.C_100309_lk.field_103270_R
		// @0C2: iconst_1
		// @0C3: isub
		// @0C4: putfield int game.C_100309_lk.field_103270_R
		// @0C7: goto @0CB
		// @0CA: athrow
		// @0CB: aload_0
		// @0CC: aload_0
		// @0CD: getfield int game.C_100309_lk.field_103270_R
		// @0D0: putfield int game.C_100309_lk.field_103261_gb
		// @0D3: aload_0
		// @0D4: lload #9
		// @0D6: putfield long game.C_100309_lk.field_103265_W
		// @0D9: iconst_1
		// @0DA: ireturn
		// @0DB: iconst_0
		// @0DC: ireturn
		// @0DD: astore #8
		// @0DF: aload #8
		// @0E1: new java.lang.StringBuilder
		// @0E4: dup
		// @0E5: invokespecial java.lang.StringBuilder.<init>()void
		// @0E8: getstatic java.lang.String[] game.C_100309_lk.field_103264_ib
		// @0EB: iconst_5
		// @0EC: aaload
		// @0ED: invokevirtual java.lang.StringBuilder.append(java.lang.String)java.lang.StringBuilder
		// @0F0: iload_1
		// @0F1: invokevirtual java.lang.StringBuilder.append(int)java.lang.StringBuilder
		// @0F4: bipush 44 (0x2C)
		// @0F6: invokevirtual java.lang.StringBuilder.append(char)java.lang.StringBuilder
		// @0F9: aload_2
		// @0FA: ifnull @106
		// @0FD: getstatic java.lang.String[] game.C_100309_lk.field_103264_ib
		// @100: iconst_1
		// @101: aaload
		// @102: goto @10B
		// @105: athrow
		// @106: getstatic java.lang.String[] game.C_100309_lk.field_103264_ib
		// @109: iconst_2
		// @10A: aaload
		// @10B: invokevirtual java.lang.StringBuilder.append(java.lang.String)java.lang.StringBuilder
		// @10E: bipush 44 (0x2C)
		// @110: invokevirtual java.lang.StringBuilder.append(char)java.lang.StringBuilder
		// @113: iload_3
		// @114: invokevirtual java.lang.StringBuilder.append(int)java.lang.StringBuilder
		// @117: bipush 44 (0x2C)
		// @119: invokevirtual java.lang.StringBuilder.append(char)java.lang.StringBuilder
		// @11C: iload #4
		// @11E: invokevirtual java.lang.StringBuilder.append(int)java.lang.StringBuilder
		// @121: bipush 44 (0x2C)
		// @123: invokevirtual java.lang.StringBuilder.append(char)java.lang.StringBuilder
		// @126: iload #5
		// @128: invokevirtual java.lang.StringBuilder.append(int)java.lang.StringBuilder
		// @12B: bipush 44 (0x2C)
		// @12D: invokevirtual java.lang.StringBuilder.append(char)java.lang.StringBuilder
		// @130: iload #6
		// @132: invokevirtual java.lang.StringBuilder.append(int)java.lang.StringBuilder
		// @135: bipush 44 (0x2C)
		// @137: invokevirtual java.lang.StringBuilder.append(char)java.lang.StringBuilder
		// @13A: iload #7
		// @13C: invokevirtual java.lang.StringBuilder.append(int)java.lang.StringBuilder
		// @13F: bipush 41 (0x29)
		// @141: invokevirtual java.lang.StringBuilder.append(char)java.lang.StringBuilder
		// @144: invokevirtual java.lang.StringBuilder.toString()java.lang.String
		// @147: invokestatic game.C_100181_cf.func_105695_a(java.lang.Throwable, java.lang.String)game.C_100170_cm
		// @14A: athrow
	}
	
	private final String func_103240_p(int arg0)
	{
		// @00: bipush -98 (0x9E)
		// @02: bipush -84 (0xAC)
		// @04: iload_1
		// @05: isub
		// @06: bipush 38 (0x26)
		// @08: idiv
		// @09: idiv
		// @0A: istore_3
		// @0B: aload_0
		// @0C: getfield int game.C_100309_lk.field_103270_R
		// @0F: iconst_m1
		// @10: ixor
		// @11: aload_0
		// @12: getfield int game.C_100309_lk.field_103257_O
		// @15: iconst_m1
		// @16: ixor
		// @17: if_icmplt @22
		// @1A: aload_0
		// @1B: getfield int game.C_100309_lk.field_103270_R
		// @1E: goto @26
		// @21: athrow
		// @22: aload_0
		// @23: getfield int game.C_100309_lk.field_103257_O
		// @26: istore_2
		// @27: aload_0
		// @28: getfield int game.C_100309_lk.field_103257_O
		// @2B: aload_0
		// @2C: getfield int game.C_100309_lk.field_103270_R
		// @2F: if_icmpge @3A
		// @32: aload_0
		// @33: getfield int game.C_100309_lk.field_103270_R
		// @36: goto @3E
		// @39: athrow
		// @3A: aload_0
		// @3B: getfield int game.C_100309_lk.field_103257_O
		// @3E: istore #4
		// @40: aload_0
		// @41: getfield java.lang.String game.C_100309_lk.field_102534_C
		// @44: iload_2
		// @45: iload #4
		// @47: invokevirtual java.lang.String.substring(int, int)java.lang.String
		// @4A: areturn
		// @4B: astore_2
		// @4C: aload_2
		// @4D: new java.lang.StringBuilder
		// @50: dup
		// @51: invokespecial java.lang.StringBuilder.<init>()void
		// @54: getstatic java.lang.String[] game.C_100309_lk.field_103264_ib
		// @57: bipush 22 (0x16)
		// @59: aaload
		// @5A: invokevirtual java.lang.StringBuilder.append(java.lang.String)java.lang.StringBuilder
		// @5D: iload_1
		// @5E: invokevirtual java.lang.StringBuilder.append(int)java.lang.StringBuilder
		// @61: bipush 41 (0x29)
		// @63: invokevirtual java.lang.StringBuilder.append(char)java.lang.StringBuilder
		// @66: invokevirtual java.lang.StringBuilder.toString()java.lang.String
		// @69: invokestatic game.C_100181_cf.func_105695_a(java.lang.Throwable, java.lang.String)game.C_100170_cm
		// @6C: athrow
	}
	
	static final C_100098_h func_103236_a(int arg0, boolean arg1, int arg2, byte arg3, boolean arg4)
	{
		// @00: iload_3
		// @01: bipush -104 (0x98)
		// @03: if_icmpeq @14
		// @06: bipush 113 (0x71)
		// @08: bipush -20 (0xEC)
		// @0A: bipush -45 (0xD3)
		// @0C: invokestatic game.C_100309_lk.func_103242_b(int, int, int)boolean
		// @0F: pop
		// @10: goto @14
		// @13: athrow
		// @14: iconst_1
		// @15: iconst_0
		// @16: iload_1
		// @17: iload_0
		// @18: iload #4
		// @1A: iload_2
		// @1B: invokestatic game.C_100122_em.func_102067_a(boolean, boolean, boolean, int, boolean, int)game.C_100098_h
		// @1E: areturn
		// @1F: astore #5
		// @21: aload #5
		// @23: new java.lang.StringBuilder
		// @26: dup
		// @27: invokespecial java.lang.StringBuilder.<init>()void
		// @2A: getstatic java.lang.String[] game.C_100309_lk.field_103264_ib
		// @2D: bipush 18 (0x12)
		// @2F: aaload
		// @30: invokevirtual java.lang.StringBuilder.append(java.lang.String)java.lang.StringBuilder
		// @33: iload_0
		// @34: invokevirtual java.lang.StringBuilder.append(int)java.lang.StringBuilder
		// @37: bipush 44 (0x2C)
		// @39: invokevirtual java.lang.StringBuilder.append(char)java.lang.StringBuilder
		// @3C: iload_1
		// @3D: invokevirtual java.lang.StringBuilder.append(boolean)java.lang.StringBuilder
		// @40: bipush 44 (0x2C)
		// @42: invokevirtual java.lang.StringBuilder.append(char)java.lang.StringBuilder
		// @45: iload_2
		// @46: invokevirtual java.lang.StringBuilder.append(int)java.lang.StringBuilder
		// @49: bipush 44 (0x2C)
		// @4B: invokevirtual java.lang.StringBuilder.append(char)java.lang.StringBuilder
		// @4E: iload_3
		// @4F: invokevirtual java.lang.StringBuilder.append(int)java.lang.StringBuilder
		// @52: bipush 44 (0x2C)
		// @54: invokevirtual java.lang.StringBuilder.append(char)java.lang.StringBuilder
		// @57: iload #4
		// @59: invokevirtual java.lang.StringBuilder.append(boolean)java.lang.StringBuilder
		// @5C: bipush 41 (0x29)
		// @5E: invokevirtual java.lang.StringBuilder.append(char)java.lang.StringBuilder
		// @61: invokevirtual java.lang.StringBuilder.toString()java.lang.String
		// @64: invokestatic game.C_100181_cf.func_105695_a(java.lang.Throwable, java.lang.String)game.C_100170_cm
		// @67: athrow
	}
	
	private final void func_103250_b(int arg0, int arg1)
	{
		// @00: iload_2
		// @01: bipush 96 (0x60)
		// @03: if_icmpeq @10
		// @06: aload_0
		// @07: bipush 46 (0x2E)
		// @09: invokespecial game.C_100309_lk.func_103246_a(byte)void
		// @0C: goto @10
		// @0F: athrow
		// @10: aload_0
		// @11: iload_1
		// @12: putfield int game.C_100309_lk.field_103270_R
		// @15: getstatic boolean[] game.C_100309_lk.field_103258_hb
		// @18: bipush 81 (0x51)
		// @1A: baload
		// @1B: ifeq @22
		// @1E: goto @2A
		// @21: athrow
		// @22: aload_0
		// @23: aload_0
		// @24: getfield int game.C_100309_lk.field_103270_R
		// @27: putfield int game.C_100309_lk.field_103257_O
		// @2A: goto @58
		// @2D: astore_3
		// @2E: aload_3
		// @2F: new java.lang.StringBuilder
		// @32: dup
		// @33: invokespecial java.lang.StringBuilder.<init>()void
		// @36: getstatic java.lang.String[] game.C_100309_lk.field_103264_ib
		// @39: bipush 16 (0x10)
		// @3B: aaload
		// @3C: invokevirtual java.lang.StringBuilder.append(java.lang.String)java.lang.StringBuilder
		// @3F: iload_1
		// @40: invokevirtual java.lang.StringBuilder.append(int)java.lang.StringBuilder
		// @43: bipush 44 (0x2C)
		// @45: invokevirtual java.lang.StringBuilder.append(char)java.lang.StringBuilder
		// @48: iload_2
		// @49: invokevirtual java.lang.StringBuilder.append(int)java.lang.StringBuilder
		// @4C: bipush 41 (0x29)
		// @4E: invokevirtual java.lang.StringBuilder.append(char)java.lang.StringBuilder
		// @51: invokevirtual java.lang.StringBuilder.toString()java.lang.String
		// @54: invokestatic game.C_100181_cf.func_105695_a(java.lang.Throwable, java.lang.String)game.C_100170_cm
		// @57: athrow
		// @58: return
	}
	
	final boolean func_102506_a(char arg0, int arg1, int arg2, C_100336_im arg3)
	{
		// @000: iload_3
		// @001: sipush 22545 (0x5811)
		// @004: if_icmpeq @012
		// @007: aload_0
		// @008: ldc2_w 88
		// @00B: putfield long game.C_100309_lk.field_103256_cb
		// @00E: goto @012
		// @011: athrow
		// @012: aload_0
		// @013: bipush 125 (0x7D)
		// @015: invokestatic game.C_100198_qn.func_105828_a(byte)long
		// @018: putfield long game.C_100309_lk.field_103256_cb
		// @01B: iload_1
		// @01C: bipush 60 (0x3C)
		// @01E: if_icmpeq @02D
		// @021: iload_1
		// @022: iconst_m1
		// @023: ixor
		// @024: bipush -63 (0xC1)
		// @026: if_icmpne @02F
		// @029: goto @02D
		// @02C: athrow
		// @02D: iconst_0
		// @02E: ireturn
		// @02F: iload_1
		// @030: bipush 32 (0x20)
		// @032: if_icmplt @119
		// @035: bipush -127 (0x81)
		// @037: iload_1
		// @038: iconst_m1
		// @039: ixor
		// @03A: if_icmpgt @119
		// @03D: goto @041
		// @040: athrow
		// @041: aload_0
		// @042: getfield int game.C_100309_lk.field_103270_R
		// @045: aload_0
		// @046: getfield int game.C_100309_lk.field_103257_O
		// @049: if_icmpne @054
		// @04C: goto @050
		// @04F: athrow
		// @050: goto @05A
		// @053: athrow
		// @054: aload_0
		// @055: bipush 66 (0x42)
		// @057: invokespecial game.C_100309_lk.func_103246_a(byte)void
		// @05A: aload_0
		// @05B: getfield int game.C_100309_lk.field_103274_X
		// @05E: iconst_m1
		// @05F: ixor
		// @060: ifeq @079
		// @063: aload_0
		// @064: getfield java.lang.String game.C_100309_lk.field_102534_C
		// @067: invokevirtual java.lang.String.length()int
		// @06A: iconst_m1
		// @06B: ixor
		// @06C: aload_0
		// @06D: getfield int game.C_100309_lk.field_103274_X
		// @070: iconst_m1
		// @071: ixor
		// @072: if_icmple @117
		// @075: goto @079
		// @078: athrow
		// @079: aload_0
		// @07A: getfield int game.C_100309_lk.field_103270_R
		// @07D: iconst_m1
		// @07E: ixor
		// @07F: aload_0
		// @080: getfield java.lang.String game.C_100309_lk.field_102534_C
		// @083: invokevirtual java.lang.String.length()int
		// @086: iconst_m1
		// @087: ixor
		// @088: if_icmpgt @0C2
		// @08B: goto @08F
		// @08E: athrow
		// @08F: new java.lang.StringBuilder
		// @092: dup
		// @093: invokespecial java.lang.StringBuilder.<init>()void
		// @096: aload_0
		// @097: dup_x1
		// @098: getfield java.lang.String game.C_100309_lk.field_102534_C
		// @09B: invokevirtual java.lang.StringBuilder.append(java.lang.String)java.lang.StringBuilder
		// @09E: iload_1
		// @09F: invokevirtual java.lang.StringBuilder.append(char)java.lang.StringBuilder
		// @0A2: invokevirtual java.lang.StringBuilder.toString()java.lang.String
		// @0A5: putfield java.lang.String game.C_100309_lk.field_102534_C
		// @0A8: aload_0
		// @0A9: aload_0
		// @0AA: aload_0
		// @0AB: getfield java.lang.String game.C_100309_lk.field_102534_C
		// @0AE: invokevirtual java.lang.String.length()int
		// @0B1: dup_x1
		// @0B2: putfield int game.C_100309_lk.field_103270_R
		// @0B5: putfield int game.C_100309_lk.field_103257_O
		// @0B8: getstatic int game.SteelSentinels.field_105275_O
		// @0BB: ifeq @10E
		// @0BE: goto @0C2
		// @0C1: athrow
		// @0C2: aload_0
		// @0C3: new java.lang.StringBuilder
		// @0C6: dup
		// @0C7: invokespecial java.lang.StringBuilder.<init>()void
		// @0CA: aload_0
		// @0CB: getfield java.lang.String game.C_100309_lk.field_102534_C
		// @0CE: iconst_0
		// @0CF: aload_0
		// @0D0: getfield int game.C_100309_lk.field_103270_R
		// @0D3: invokevirtual java.lang.String.substring(int, int)java.lang.String
		// @0D6: invokevirtual java.lang.StringBuilder.append(java.lang.String)java.lang.StringBuilder
		// @0D9: iload_1
		// @0DA: invokevirtual java.lang.StringBuilder.append(char)java.lang.StringBuilder
		// @0DD: aload_0
		// @0DE: getfield java.lang.String game.C_100309_lk.field_102534_C
		// @0E1: aload_0
		// @0E2: getfield int game.C_100309_lk.field_103270_R
		// @0E5: aload_0
		// @0E6: getfield java.lang.String game.C_100309_lk.field_102534_C
		// @0E9: invokevirtual java.lang.String.length()int
		// @0EC: invokevirtual java.lang.String.substring(int, int)java.lang.String
		// @0EF: invokevirtual java.lang.StringBuilder.append(java.lang.String)java.lang.StringBuilder
		// @0F2: invokevirtual java.lang.StringBuilder.toString()java.lang.String
		// @0F5: putfield java.lang.String game.C_100309_lk.field_102534_C
		// @0F8: aload_0
		// @0F9: dup
		// @0FA: getfield int game.C_100309_lk.field_103270_R
		// @0FD: iconst_1
		// @0FE: iadd
		// @0FF: putfield int game.C_100309_lk.field_103270_R
		// @102: aload_0
		// @103: aload_0
		// @104: getfield int game.C_100309_lk.field_103270_R
		// @107: putfield int game.C_100309_lk.field_103257_O
		// @10A: goto @10E
		// @10D: athrow
		// @10E: aload_0
		// @10F: iload_3
		// @110: sipush -4892 (0xECE4)
		// @113: ixor
		// @114: invokevirtual game.C_100309_lk.func_103241_k(int)void
		// @117: iconst_1
		// @118: ireturn
		// @119: iload_2
		// @11A: iconst_m1
		// @11B: ixor
		// @11C: bipush -86 (0xAA)
		// @11E: if_icmpne @158
		// @121: aload_0
		// @122: getfield int game.C_100309_lk.field_103257_O
		// @125: iconst_m1
		// @126: ixor
		// @127: aload_0
		// @128: getfield int game.C_100309_lk.field_103270_R
		// @12B: iconst_m1
		// @12C: ixor
		// @12D: if_icmpeq @13C
		// @130: goto @134
		// @133: athrow
		// @134: aload_0
		// @135: bipush 66 (0x42)
		// @137: invokespecial game.C_100309_lk.func_103246_a(byte)void
		// @13A: iconst_1
		// @13B: ireturn
		// @13C: iconst_m1
		// @13D: aload_0
		// @13E: getfield int game.C_100309_lk.field_103270_R
		// @141: iconst_m1
		// @142: ixor
		// @143: if_icmple @2C0
		// @146: aload_0
		// @147: iconst_m1
		// @148: aload_0
		// @149: getfield int game.C_100309_lk.field_103270_R
		// @14C: iadd
		// @14D: putfield int game.C_100309_lk.field_103257_O
		// @150: aload_0
		// @151: bipush 66 (0x42)
		// @153: invokespecial game.C_100309_lk.func_103246_a(byte)void
		// @156: iconst_1
		// @157: ireturn
		// @158: bipush 101 (0x65)
		// @15A: iload_2
		// @15B: if_icmpeq @289
		// @15E: iload_2
		// @15F: iconst_m1
		// @160: ixor
		// @161: bipush -14 (0xF2)
		// @163: if_icmpeq @282
		// @166: goto @16A
		// @169: athrow
		// @16A: bipush 96 (0x60)
		// @16C: iload_2
		// @16D: if_icmpne @1A6
		// @170: goto @174
		// @173: athrow
		// @174: iconst_0
		// @175: aload_0
		// @176: getfield int game.C_100309_lk.field_103270_R
		// @179: if_icmplt @184
		// @17C: goto @180
		// @17F: athrow
		// @180: goto @2C0
		// @183: athrow
		// @184: aload_0
		// @185: getstatic boolean[] game.C_100309_lk.field_103258_hb
		// @188: bipush 82 (0x52)
		// @18A: baload
		// @18B: ifeq @199
		// @18E: aload_0
		// @18F: sipush -27931 (0x92E5)
		// @192: invokespecial game.C_100309_lk.func_103243_n(int)int
		// @195: goto @19F
		// @198: athrow
		// @199: aload_0
		// @19A: getfield int game.C_100309_lk.field_103270_R
		// @19D: iconst_m1
		// @19E: iadd
		// @19F: bipush 96 (0x60)
		// @1A1: invokespecial game.C_100309_lk.func_103250_b(int, int)void
		// @1A4: iconst_1
		// @1A5: ireturn
		// @1A6: iload_2
		// @1A7: bipush 97 (0x61)
		// @1A9: if_icmpeq @24A
		// @1AC: bipush 102 (0x66)
		// @1AE: iload_2
		// @1AF: if_icmpeq @23E
		// @1B2: goto @1B6
		// @1B5: athrow
		// @1B6: bipush 103 (0x67)
		// @1B8: iload_2
		// @1B9: if_icmpne @1CF
		// @1BC: goto @1C0
		// @1BF: athrow
		// @1C0: aload_0
		// @1C1: aload_0
		// @1C2: getfield java.lang.String game.C_100309_lk.field_102534_C
		// @1C5: invokevirtual java.lang.String.length()int
		// @1C8: bipush 96 (0x60)
		// @1CA: invokespecial game.C_100309_lk.func_103250_b(int, int)void
		// @1CD: iconst_1
		// @1CE: ireturn
		// @1CF: bipush 84 (0x54)
		// @1D1: iload_2
		// @1D2: if_icmpeq @237
		// @1D5: getstatic boolean[] game.C_100309_lk.field_103258_hb
		// @1D8: bipush 82 (0x52)
		// @1DA: baload
		// @1DB: ifeq @1F5
		// @1DE: goto @1E2
		// @1E1: athrow
		// @1E2: iload_2
		// @1E3: iconst_m1
		// @1E4: ixor
		// @1E5: bipush -66 (0xBE)
		// @1E7: if_icmpne @1F5
		// @1EA: goto @1EE
		// @1ED: athrow
		// @1EE: aload_0
		// @1EF: iconst_1
		// @1F0: invokespecial game.C_100309_lk.func_103248_e(boolean)void
		// @1F3: iconst_1
		// @1F4: ireturn
		// @1F5: getstatic boolean[] game.C_100309_lk.field_103258_hb
		// @1F8: bipush 82 (0x52)
		// @1FA: baload
		// @1FB: ifeq @20A
		// @1FE: bipush -67 (0xBD)
		// @200: iload_2
		// @201: iconst_m1
		// @202: ixor
		// @203: if_icmpeq @22C
		// @206: goto @20A
		// @209: athrow
		// @20A: getstatic boolean[] game.C_100309_lk.field_103258_hb
		// @20D: bipush 82 (0x52)
		// @20F: baload
		// @210: ifeq @2C0
		// @213: goto @217
		// @216: athrow
		// @217: iload_2
		// @218: iconst_m1
		// @219: ixor
		// @21A: bipush -68 (0xBC)
		// @21C: if_icmpne @2C0
		// @21F: goto @223
		// @222: athrow
		// @223: aload_0
		// @224: sipush -12366 (0xCFB2)
		// @227: invokespecial game.C_100309_lk.func_103244_j(int)void
		// @22A: iconst_1
		// @22B: ireturn
		// @22C: aload_0
		// @22D: iload_3
		// @22E: sipush -22632 (0xA798)
		// @231: ixor
		// @232: invokespecial game.C_100309_lk.func_103235_m(int)void
		// @235: iconst_1
		// @236: ireturn
		// @237: aload_0
		// @238: iconst_0
		// @239: invokespecial game.C_100309_lk.func_103249_q(int)void
		// @23C: iconst_1
		// @23D: ireturn
		// @23E: aload_0
		// @23F: iconst_0
		// @240: iload_3
		// @241: sipush -22449 (0xA84F)
		// @244: iadd
		// @245: invokespecial game.C_100309_lk.func_103250_b(int, int)void
		// @248: iconst_1
		// @249: ireturn
		// @24A: aload_0
		// @24B: getfield int game.C_100309_lk.field_103270_R
		// @24E: iconst_m1
		// @24F: ixor
		// @250: aload_0
		// @251: getfield java.lang.String game.C_100309_lk.field_102534_C
		// @254: invokevirtual java.lang.String.length()int
		// @257: iconst_m1
		// @258: ixor
		// @259: if_icmpgt @260
		// @25C: goto @2C0
		// @25F: athrow
		// @260: aload_0
		// @261: getstatic boolean[] game.C_100309_lk.field_103258_hb
		// @264: bipush 82 (0x52)
		// @266: baload
		// @267: ifeq @275
		// @26A: aload_0
		// @26B: sipush -17562 (0xBB66)
		// @26E: invokespecial game.C_100309_lk.func_103237_l(int)int
		// @271: goto @27B
		// @274: athrow
		// @275: iconst_1
		// @276: aload_0
		// @277: getfield int game.C_100309_lk.field_103270_R
		// @27A: iadd
		// @27B: bipush 96 (0x60)
		// @27D: invokespecial game.C_100309_lk.func_103250_b(int, int)void
		// @280: iconst_1
		// @281: ireturn
		// @282: aload_0
		// @283: iconst_0
		// @284: invokevirtual game.C_100309_lk.func_103239_c(boolean)void
		// @287: iconst_1
		// @288: ireturn
		// @289: aload_0
		// @28A: getfield int game.C_100309_lk.field_103270_R
		// @28D: aload_0
		// @28E: getfield int game.C_100309_lk.field_103257_O
		// @291: if_icmpne @2B8
		// @294: aload_0
		// @295: getfield int game.C_100309_lk.field_103270_R
		// @298: aload_0
		// @299: getfield java.lang.String game.C_100309_lk.field_102534_C
		// @29C: invokevirtual java.lang.String.length()int
		// @29F: if_icmpge @2C0
		// @2A2: goto @2A6
		// @2A5: athrow
		// @2A6: aload_0
		// @2A7: aload_0
		// @2A8: getfield int game.C_100309_lk.field_103270_R
		// @2AB: iconst_m1
		// @2AC: isub
		// @2AD: putfield int game.C_100309_lk.field_103257_O
		// @2B0: aload_0
		// @2B1: bipush 66 (0x42)
		// @2B3: invokespecial game.C_100309_lk.func_103246_a(byte)void
		// @2B6: iconst_1
		// @2B7: ireturn
		// @2B8: aload_0
		// @2B9: bipush 66 (0x42)
		// @2BB: invokespecial game.C_100309_lk.func_103246_a(byte)void
		// @2BE: iconst_1
		// @2BF: ireturn
		// @2C0: iconst_0
		// @2C1: ireturn
		// @2C2: astore #5
		// @2C4: aload #5
		// @2C6: new java.lang.StringBuilder
		// @2C9: dup
		// @2CA: invokespecial java.lang.StringBuilder.<init>()void
		// @2CD: getstatic java.lang.String[] game.C_100309_lk.field_103264_ib
		// @2D0: iconst_4
		// @2D1: aaload
		// @2D2: invokevirtual java.lang.StringBuilder.append(java.lang.String)java.lang.StringBuilder
		// @2D5: iload_1
		// @2D6: invokevirtual java.lang.StringBuilder.append(char)java.lang.StringBuilder
		// @2D9: bipush 44 (0x2C)
		// @2DB: invokevirtual java.lang.StringBuilder.append(char)java.lang.StringBuilder
		// @2DE: iload_2
		// @2DF: invokevirtual java.lang.StringBuilder.append(int)java.lang.StringBuilder
		// @2E2: bipush 44 (0x2C)
		// @2E4: invokevirtual java.lang.StringBuilder.append(char)java.lang.StringBuilder
		// @2E7: iload_3
		// @2E8: invokevirtual java.lang.StringBuilder.append(int)java.lang.StringBuilder
		// @2EB: bipush 44 (0x2C)
		// @2ED: invokevirtual java.lang.StringBuilder.append(char)java.lang.StringBuilder
		// @2F0: aload #4
		// @2F2: ifnull @2FE
		// @2F5: getstatic java.lang.String[] game.C_100309_lk.field_103264_ib
		// @2F8: iconst_1
		// @2F9: aaload
		// @2FA: goto @303
		// @2FD: athrow
		// @2FE: getstatic java.lang.String[] game.C_100309_lk.field_103264_ib
		// @301: iconst_2
		// @302: aaload
		// @303: invokevirtual java.lang.StringBuilder.append(java.lang.String)java.lang.StringBuilder
		// @306: bipush 41 (0x29)
		// @308: invokevirtual java.lang.StringBuilder.append(char)java.lang.StringBuilder
		// @30B: invokevirtual java.lang.StringBuilder.toString()java.lang.String
		// @30E: invokestatic game.C_100181_cf.func_105695_a(java.lang.Throwable, java.lang.String)game.C_100170_cm
		// @311: athrow
	}
	
	private final void func_103248_e(boolean arg0)
	{
		// @00: iload_1
		// @01: iconst_1
		// @02: if_icmpeq @0E
		// @05: aload_0
		// @06: iconst_1
		// @07: putfield boolean game.C_100309_lk.field_103262_U
		// @0A: goto @0E
		// @0D: athrow
		// @0E: aload_0
		// @0F: bipush -122 (0x86)
		// @11: invokespecial game.C_100309_lk.func_103235_m(int)void
		// @14: aload_0
		// @15: bipush 66 (0x42)
		// @17: invokespecial game.C_100309_lk.func_103246_a(byte)void
		// @1A: goto @3F
		// @1D: astore_2
		// @1E: aload_2
		// @1F: new java.lang.StringBuilder
		// @22: dup
		// @23: invokespecial java.lang.StringBuilder.<init>()void
		// @26: getstatic java.lang.String[] game.C_100309_lk.field_103264_ib
		// @29: bipush 11 (0x0B)
		// @2B: aaload
		// @2C: invokevirtual java.lang.StringBuilder.append(java.lang.String)java.lang.StringBuilder
		// @2F: iload_1
		// @30: invokevirtual java.lang.StringBuilder.append(boolean)java.lang.StringBuilder
		// @33: bipush 41 (0x29)
		// @35: invokevirtual java.lang.StringBuilder.append(char)java.lang.StringBuilder
		// @38: invokevirtual java.lang.StringBuilder.toString()java.lang.String
		// @3B: invokestatic game.C_100181_cf.func_105695_a(java.lang.Throwable, java.lang.String)game.C_100170_cm
		// @3E: athrow
		// @3F: return
	}
	
	static final boolean func_103242_b(int arg0, int arg1, int arg2)
	{
		// @000: aconst_null
		// @001: getstatic game.C_100211_qd game.SteelSentinels.field_105274_N
		// @004: if_acmpeq @00C
		// @007: iconst_1
		// @008: goto @00D
		// @00B: athrow
		// @00C: iconst_0
		// @00D: istore_3
		// @00E: getstatic int game.C_100293_kj.field_106890_c
		// @011: iconst_m1
		// @012: ixor
		// @013: bipush -10 (0xF6)
		// @015: if_icmpne @056
		// @018: getstatic int game.C_100149_bi.field_105154_d
		// @01B: iconst_2
		// @01C: getstatic java.lang.String game.C_100215_ai.field_106022_h
		// @01F: getstatic int[] game.C_100315_la.field_107178_b
		// @022: getstatic long game.C_100050_vg.field_100633_u
		// @025: invokestatic game.C_100297_kf.func_101232_a(int, int, java.lang.String, int[], long)boolean
		// @028: ifne @033
		// @02B: goto @02F
		// @02E: athrow
		// @02F: goto @056
		// @032: athrow
		// @033: getstatic int game.C_100149_bi.field_105154_d
		// @036: iconst_2
		// @037: if_icmpeq @044
		// @03A: iload_3
		// @03B: ifeq @044
		// @03E: goto @042
		// @041: athrow
		// @042: iconst_0
		// @043: ireturn
		// @044: bipush -122 (0x86)
		// @046: getstatic int[] game.C_100315_la.field_107178_b
		// @049: getstatic long game.C_100050_vg.field_100633_u
		// @04C: getstatic java.lang.String game.C_100215_ai.field_106022_h
		// @04F: getstatic int game.C_100149_bi.field_105154_d
		// @052: invokestatic game.C_100297_kf.func_101227_a(byte, int[], long, java.lang.String, int)boolean
		// @055: ireturn
		// @056: iload_2
		// @057: iconst_2
		// @058: if_icmpeq @05D
		// @05B: iconst_1
		// @05C: ireturn
		// @05D: getstatic int game.C_100293_kj.field_106890_c
		// @060: iconst_m1
		// @061: ixor
		// @062: bipush -11 (0xF5)
		// @064: if_icmpeq @06B
		// @067: goto @077
		// @06A: athrow
		// @06B: iload_3
		// @06C: ifeq @071
		// @06F: iconst_0
		// @070: ireturn
		// @071: iconst_0
		// @072: invokestatic game.C_100078_ul.func_103276_f(boolean)void
		// @075: iconst_1
		// @076: ireturn
		// @077: getstatic int game.C_100293_kj.field_106890_c
		// @07A: iconst_m1
		// @07B: ixor
		// @07C: bipush -12 (0xF4)
		// @07E: if_icmpne @0E2
		// @081: getstatic boolean game.C_100211_qd.field_102158_yc
		// @084: ifeq @0E2
		// @087: goto @08B
		// @08A: athrow
		// @08B: getstatic int game.C_100333_ij.field_107350_n
		// @08E: iconst_m1
		// @08F: ixor
		// @090: bipush -3 (0xFD)
		// @092: if_icmpne @0B1
		// @095: goto @099
		// @098: athrow
		// @099: getstatic long game.C_100217_ao.field_106035_d
		// @09C: getstatic java.lang.String game.C_100253_ph.field_101100_C
		// @09F: bipush 70 (0x46)
		// @0A1: invokestatic game.C_100256_pk.func_100444_a(long, java.lang.String, byte)boolean
		// @0A4: ifeq @0AF
		// @0A7: goto @0AB
		// @0AA: athrow
		// @0AB: goto @0B1
		// @0AE: athrow
		// @0AF: iconst_0
		// @0B0: ireturn
		// @0B1: getstatic int game.C_100333_ij.field_107350_n
		// @0B4: iconst_2
		// @0B5: if_icmpeq @0C2
		// @0B8: iload_3
		// @0B9: ifeq @0C2
		// @0BC: goto @0C0
		// @0BF: athrow
		// @0C0: iconst_0
		// @0C1: ireturn
		// @0C2: iload_2
		// @0C3: bipush -2 (0xFE)
		// @0C5: iadd
		// @0C6: invokestatic game.C_100020_wm.func_103852_a(int)boolean
		// @0C9: ifne @0D0
		// @0CC: goto @0E0
		// @0CF: athrow
		// @0D0: getstatic java.lang.String game.C_100253_ph.field_101100_C
		// @0D3: getstatic int game.C_100333_ij.field_107350_n
		// @0D6: bipush 6 (0x06)
		// @0D8: aconst_null
		// @0D9: iload_0
		// @0DA: getstatic int game.C_100291_jj.field_106876_b
		// @0DD: invokestatic game.C_100263_mb.func_106503_a(java.lang.String, int, byte, java.lang.String, int, int)void
		// @0E0: iconst_1
		// @0E1: ireturn
		// @0E2: iconst_0
		// @0E3: ireturn
		// @0E4: astore_3
		// @0E5: aload_3
		// @0E6: new java.lang.StringBuilder
		// @0E9: dup
		// @0EA: invokespecial java.lang.StringBuilder.<init>()void
		// @0ED: getstatic java.lang.String[] game.C_100309_lk.field_103264_ib
		// @0F0: bipush 14 (0x0E)
		// @0F2: aaload
		// @0F3: invokevirtual java.lang.StringBuilder.append(java.lang.String)java.lang.StringBuilder
		// @0F6: iload_0
		// @0F7: invokevirtual java.lang.StringBuilder.append(int)java.lang.StringBuilder
		// @0FA: bipush 44 (0x2C)
		// @0FC: invokevirtual java.lang.StringBuilder.append(char)java.lang.StringBuilder
		// @0FF: iload_1
		// @100: invokevirtual java.lang.StringBuilder.append(int)java.lang.StringBuilder
		// @103: bipush 44 (0x2C)
		// @105: invokevirtual java.lang.StringBuilder.append(char)java.lang.StringBuilder
		// @108: iload_2
		// @109: invokevirtual java.lang.StringBuilder.append(int)java.lang.StringBuilder
		// @10C: bipush 41 (0x29)
		// @10E: invokevirtual java.lang.StringBuilder.append(char)java.lang.StringBuilder
		// @111: invokevirtual java.lang.StringBuilder.toString()java.lang.String
		// @114: invokestatic game.C_100181_cf.func_105695_a(java.lang.Throwable, java.lang.String)game.C_100170_cm
		// @117: athrow
	}
	
	private final int func_103237_l(int arg0)
	{
		// @00: getstatic int game.SteelSentinels.field_105275_O
		// @03: istore #4
		// @05: iload_1
		// @06: sipush -17562 (0xBB66)
		// @09: if_icmpeq @0F
		// @0C: bipush -26 (0xE6)
		// @0E: ireturn
		// @0F: aload_0
		// @10: getfield java.lang.String game.C_100309_lk.field_102534_C
		// @13: invokevirtual java.lang.String.length()int
		// @16: istore_2
		// @17: iload_2
		// @18: iconst_m1
		// @19: ixor
		// @1A: aload_0
		// @1B: getfield int game.C_100309_lk.field_103270_R
		// @1E: iconst_m1
		// @1F: ixor
		// @20: if_icmpeq @27
		// @23: goto @2C
		// @26: athrow
		// @27: aload_0
		// @28: getfield int game.C_100309_lk.field_103270_R
		// @2B: ireturn
		// @2C: aload_0
		// @2D: getfield int game.C_100309_lk.field_103270_R
		// @30: iconst_1
		// @31: iadd
		// @32: istore_3
		// @33: iload_3
		// @34: iload_2
		// @35: if_icmpge @5E
		// @38: aload_0
		// @39: getfield java.lang.String game.C_100309_lk.field_102534_C
		// @3C: iload_3
		// @3D: iconst_1
		// @3E: isub
		// @3F: invokevirtual java.lang.String.charAt(int)char
		// @42: iconst_m1
		// @43: ixor
		// @44: iload #4
		// @46: ifne @5F
		// @49: bipush -33 (0xDF)
		// @4B: if_icmpeq @5E
		// @4E: goto @52
		// @51: athrow
		// @52: iinc #3 +1
		// @55: iload #4
		// @57: ifeq @33
		// @5A: goto @5E
		// @5D: athrow
		// @5E: iload_3
		// @5F: ireturn
		// @60: astore_2
		// @61: aload_2
		// @62: new java.lang.StringBuilder
		// @65: dup
		// @66: invokespecial java.lang.StringBuilder.<init>()void
		// @69: getstatic java.lang.String[] game.C_100309_lk.field_103264_ib
		// @6C: bipush 24 (0x18)
		// @6E: aaload
		// @6F: invokevirtual java.lang.StringBuilder.append(java.lang.String)java.lang.StringBuilder
		// @72: iload_1
		// @73: invokevirtual java.lang.StringBuilder.append(int)java.lang.StringBuilder
		// @76: bipush 41 (0x29)
		// @78: invokevirtual java.lang.StringBuilder.append(char)java.lang.StringBuilder
		// @7B: invokevirtual java.lang.StringBuilder.toString()java.lang.String
		// @7E: invokestatic game.C_100181_cf.func_105695_a(java.lang.Throwable, java.lang.String)game.C_100170_cm
		// @81: athrow
	}
	
	private final void func_103252_a(int arg0, String arg1)
	{
		// @00: iload_1
		// @01: aload_0
		// @02: getfield int game.C_100309_lk.field_103274_X
		// @05: if_icmpne @0C
		// @08: goto @28
		// @0B: athrow
		// @0C: aload_0
		// @0D: getfield int game.C_100309_lk.field_103274_X
		// @10: aload_0
		// @11: getfield java.lang.String game.C_100309_lk.field_102534_C
		// @14: invokevirtual java.lang.String.length()int
		// @17: isub
		// @18: istore_3
		// @19: iconst_m1
		// @1A: iload_3
		// @1B: iconst_m1
		// @1C: ixor
		// @1D: if_icmplt @21
		// @20: return
		// @21: aload_2
		// @22: iconst_0
		// @23: iload_3
		// @24: invokevirtual java.lang.String.substring(int, int)java.lang.String
		// @27: astore_2
		// @28: aload_0
		// @29: getfield int game.C_100309_lk.field_103270_R
		// @2C: aload_0
		// @2D: getfield java.lang.String game.C_100309_lk.field_102534_C
		// @30: invokevirtual java.lang.String.length()int
		// @33: if_icmpeq @76
		// @36: aload_0
		// @37: new java.lang.StringBuilder
		// @3A: dup
		// @3B: invokespecial java.lang.StringBuilder.<init>()void
		// @3E: aload_0
		// @3F: getfield java.lang.String game.C_100309_lk.field_102534_C
		// @42: iconst_0
		// @43: aload_0
		// @44: getfield int game.C_100309_lk.field_103270_R
		// @47: invokevirtual java.lang.String.substring(int, int)java.lang.String
		// @4A: invokevirtual java.lang.StringBuilder.append(java.lang.String)java.lang.StringBuilder
		// @4D: aload_2
		// @4E: invokevirtual java.lang.StringBuilder.append(java.lang.String)java.lang.StringBuilder
		// @51: aload_0
		// @52: getfield java.lang.String game.C_100309_lk.field_102534_C
		// @55: aload_0
		// @56: getfield int game.C_100309_lk.field_103270_R
		// @59: aload_0
		// @5A: getfield java.lang.String game.C_100309_lk.field_102534_C
		// @5D: invokevirtual java.lang.String.length()int
		// @60: invokevirtual java.lang.String.substring(int, int)java.lang.String
		// @63: invokevirtual java.lang.StringBuilder.append(java.lang.String)java.lang.StringBuilder
		// @66: invokevirtual java.lang.StringBuilder.toString()java.lang.String
		// @69: putfield java.lang.String game.C_100309_lk.field_102534_C
		// @6C: getstatic int game.SteelSentinels.field_105275_O
		// @6F: ifeq @93
		// @72: goto @76
		// @75: athrow
		// @76: new java.lang.StringBuilder
		// @79: dup
		// @7A: invokespecial java.lang.StringBuilder.<init>()void
		// @7D: aload_0
		// @7E: dup_x1
		// @7F: getfield java.lang.String game.C_100309_lk.field_102534_C
		// @82: invokevirtual java.lang.StringBuilder.append(java.lang.String)java.lang.StringBuilder
		// @85: aload_2
		// @86: invokevirtual java.lang.StringBuilder.append(java.lang.String)java.lang.StringBuilder
		// @89: invokevirtual java.lang.StringBuilder.toString()java.lang.String
		// @8C: putfield java.lang.String game.C_100309_lk.field_102534_C
		// @8F: goto @93
		// @92: athrow
		// @93: aload_0
		// @94: dup
		// @95: getfield int game.C_100309_lk.field_103270_R
		// @98: aload_2
		// @99: invokevirtual java.lang.String.length()int
		// @9C: iadd
		// @9D: putfield int game.C_100309_lk.field_103270_R
		// @A0: aload_0
		// @A1: aload_0
		// @A2: getfield int game.C_100309_lk.field_103270_R
		// @A5: putfield int game.C_100309_lk.field_103257_O
		// @A8: aload_0
		// @A9: sipush -19211 (0xB4F5)
		// @AC: invokevirtual game.C_100309_lk.func_103241_k(int)void
		// @AF: goto @EE
		// @B2: astore_3
		// @B3: aload_3
		// @B4: new java.lang.StringBuilder
		// @B7: dup
		// @B8: invokespecial java.lang.StringBuilder.<init>()void
		// @BB: getstatic java.lang.String[] game.C_100309_lk.field_103264_ib
		// @BE: bipush 13 (0x0D)
		// @C0: aaload
		// @C1: invokevirtual java.lang.StringBuilder.append(java.lang.String)java.lang.StringBuilder
		// @C4: iload_1
		// @C5: invokevirtual java.lang.StringBuilder.append(int)java.lang.StringBuilder
		// @C8: bipush 44 (0x2C)
		// @CA: invokevirtual java.lang.StringBuilder.append(char)java.lang.StringBuilder
		// @CD: aload_2
		// @CE: ifnull @DA
		// @D1: getstatic java.lang.String[] game.C_100309_lk.field_103264_ib
		// @D4: iconst_1
		// @D5: aaload
		// @D6: goto @DF
		// @D9: athrow
		// @DA: getstatic java.lang.String[] game.C_100309_lk.field_103264_ib
		// @DD: iconst_2
		// @DE: aaload
		// @DF: invokevirtual java.lang.StringBuilder.append(java.lang.String)java.lang.StringBuilder
		// @E2: bipush 41 (0x29)
		// @E4: invokevirtual java.lang.StringBuilder.append(char)java.lang.StringBuilder
		// @E7: invokevirtual java.lang.StringBuilder.toString()java.lang.String
		// @EA: invokestatic game.C_100181_cf.func_105695_a(java.lang.Throwable, java.lang.String)game.C_100170_cm
		// @ED: athrow
		// @EE: return
	}
	
	C_100309_lk(String arg0, C_100337_in arg1, int arg2)
	{
		// @00: aload_0
		// @01: aload_1
		// @02: aload_2
		// @03: invokespecial game.C_100218_am.<init>(java.lang.String, game.C_100337_in)void
		// @06: aload_0
		// @07: lconst_0
		// @08: putfield long game.C_100309_lk.field_103265_W
		// @0B: aload_0
		// @0C: iconst_0
		// @0D: putfield boolean game.C_100309_lk.field_103260_fb
		// @10: aload_0
		// @11: iconst_m1
		// @12: putfield int game.C_100309_lk.field_103261_gb
		// @15: aload_0
		// @16: getstatic game.C_100233_oa game.C_100043_vl.field_101945_cc
		// @19: getfield game.C_100326_ic game.C_100233_oa.field_106260_z
		// @1C: putfield game.C_100326_ic game.C_100309_lk.field_102533_B
		// @1F: aload_0
		// @20: iload_3
		// @21: putfield int game.C_100309_lk.field_103274_X
		// @24: aload_0
		// @25: iconst_1
		// @26: iconst_1
		// @27: aload_1
		// @28: invokevirtual game.C_100309_lk.func_103251_a(boolean, boolean, java.lang.String)void
		// @2B: aload_0
		// @2C: iconst_1
		// @2D: putfield boolean game.C_100309_lk.field_103262_U
		// @30: aload_0
		// @31: bipush 55 (0x37)
		// @33: invokestatic game.C_100198_qn.func_105828_a(byte)long
		// @36: putfield long game.C_100309_lk.field_103256_cb
		// @39: goto @94
		// @3C: astore #4
		// @3E: aload #4
		// @40: new java.lang.StringBuilder
		// @43: dup
		// @44: invokespecial java.lang.StringBuilder.<init>()void
		// @47: getstatic java.lang.String[] game.C_100309_lk.field_103264_ib
		// @4A: bipush 25 (0x19)
		// @4C: aaload
		// @4D: invokevirtual java.lang.StringBuilder.append(java.lang.String)java.lang.StringBuilder
		// @50: aload_1
		// @51: ifnull @5D
		// @54: getstatic java.lang.String[] game.C_100309_lk.field_103264_ib
		// @57: iconst_1
		// @58: aaload
		// @59: goto @62
		// @5C: athrow
		// @5D: getstatic java.lang.String[] game.C_100309_lk.field_103264_ib
		// @60: iconst_2
		// @61: aaload
		// @62: invokevirtual java.lang.StringBuilder.append(java.lang.String)java.lang.StringBuilder
		// @65: bipush 44 (0x2C)
		// @67: invokevirtual java.lang.StringBuilder.append(char)java.lang.StringBuilder
		// @6A: aload_2
		// @6B: ifnull @77
		// @6E: getstatic java.lang.String[] game.C_100309_lk.field_103264_ib
		// @71: iconst_1
		// @72: aaload
		// @73: goto @7C
		// @76: athrow
		// @77: getstatic java.lang.String[] game.C_100309_lk.field_103264_ib
		// @7A: iconst_2
		// @7B: aaload
		// @7C: invokevirtual java.lang.StringBuilder.append(java.lang.String)java.lang.StringBuilder
		// @7F: bipush 44 (0x2C)
		// @81: invokevirtual java.lang.StringBuilder.append(char)java.lang.StringBuilder
		// @84: iload_3
		// @85: invokevirtual java.lang.StringBuilder.append(int)java.lang.StringBuilder
		// @88: bipush 41 (0x29)
		// @8A: invokevirtual java.lang.StringBuilder.append(char)java.lang.StringBuilder
		// @8D: invokevirtual java.lang.StringBuilder.toString()java.lang.String
		// @90: invokestatic game.C_100181_cf.func_105695_a(java.lang.Throwable, java.lang.String)game.C_100170_cm
		// @93: athrow
		// @94: return
	}
	
	private final void func_103244_j(int arg0)
	{
		// @00: iload_1
		// @01: sipush -12366 (0xCFB2)
		// @04: if_icmpeq @08
		// @07: return
		// @08: invokestatic java.awt.Toolkit.getDefaultToolkit()java.awt.Toolkit
		// @0B: invokevirtual java.awt.Toolkit.getSystemClipboard()java.awt.datatransfer.Clipboard
		// @0E: aconst_null
		// @0F: invokevirtual java.awt.datatransfer.Clipboard.getContents(java.lang.Object)java.awt.datatransfer.Transferable
		// @12: getstatic java.awt.datatransfer.DataFlavor java.awt.datatransfer.DataFlavor.stringFlavor
		// @15: invokeinterface java.awt.datatransfer.Transferable.getTransferData(java.awt.datatransfer.DataFlavor)java.lang.Object
		// @1A: checkcast java.lang.String
		// @1D: astore_2
		// @1E: aload_0
		// @1F: bipush 66 (0x42)
		// @21: invokespecial game.C_100309_lk.func_103246_a(byte)void
		// @24: aload_0
		// @25: iconst_m1
		// @26: aload_2
		// @27: invokespecial game.C_100309_lk.func_103252_a(int, java.lang.String)void
		// @2A: goto @2E
		// @2D: astore_2
		// @2E: goto @53
		// @31: astore_2
		// @32: aload_2
		// @33: new java.lang.StringBuilder
		// @36: dup
		// @37: invokespecial java.lang.StringBuilder.<init>()void
		// @3A: getstatic java.lang.String[] game.C_100309_lk.field_103264_ib
		// @3D: bipush 15 (0x0F)
		// @3F: aaload
		// @40: invokevirtual java.lang.StringBuilder.append(java.lang.String)java.lang.StringBuilder
		// @43: iload_1
		// @44: invokevirtual java.lang.StringBuilder.append(int)java.lang.StringBuilder
		// @47: bipush 41 (0x29)
		// @49: invokevirtual java.lang.StringBuilder.append(char)java.lang.StringBuilder
		// @4C: invokevirtual java.lang.StringBuilder.toString()java.lang.String
		// @4F: invokestatic game.C_100181_cf.func_105695_a(java.lang.Throwable, java.lang.String)game.C_100170_cm
		// @52: athrow
		// @53: return
	}
	
	private final void func_103235_m(int arg0)
	{
		// @00: iload_1
		// @01: bipush -87 (0xA9)
		// @03: if_icmplt @18
		// @06: aload_0
		// @07: bipush 24 (0x18)
		// @09: bipush -75 (0xB5)
		// @0B: iconst_2
		// @0C: aconst_null
		// @0D: checkcast game.C_100336_im
		// @10: invokevirtual game.C_100309_lk.func_102506_a(char, int, int, game.C_100336_im)boolean
		// @13: pop
		// @14: goto @18
		// @17: athrow
		// @18: aload_0
		// @19: bipush -126 (0x82)
		// @1B: invokespecial game.C_100309_lk.func_103240_p(int)java.lang.String
		// @1E: astore_2
		// @1F: iconst_0
		// @20: aload_2
		// @21: invokevirtual java.lang.String.length()int
		// @24: if_icmplt @2B
		// @27: goto @42
		// @2A: athrow
		// @2B: invokestatic java.awt.Toolkit.getDefaultToolkit()java.awt.Toolkit
		// @2E: invokevirtual java.awt.Toolkit.getSystemClipboard()java.awt.datatransfer.Clipboard
		// @31: new java.awt.datatransfer.StringSelection
		// @34: dup
		// @35: aload_0
		// @36: bipush -124 (0x84)
		// @38: invokespecial game.C_100309_lk.func_103240_p(int)java.lang.String
		// @3B: invokespecial java.awt.datatransfer.StringSelection.<init>(java.lang.String)void
		// @3E: aconst_null
		// @3F: invokevirtual java.awt.datatransfer.Clipboard.setContents(java.awt.datatransfer.Transferable, java.awt.datatransfer.ClipboardOwner)void
		// @42: goto @67
		// @45: astore_2
		// @46: aload_2
		// @47: new java.lang.StringBuilder
		// @4A: dup
		// @4B: invokespecial java.lang.StringBuilder.<init>()void
		// @4E: getstatic java.lang.String[] game.C_100309_lk.field_103264_ib
		// @51: bipush 6 (0x06)
		// @53: aaload
		// @54: invokevirtual java.lang.StringBuilder.append(java.lang.String)java.lang.StringBuilder
		// @57: iload_1
		// @58: invokevirtual java.lang.StringBuilder.append(int)java.lang.StringBuilder
		// @5B: bipush 41 (0x29)
		// @5D: invokevirtual java.lang.StringBuilder.append(char)java.lang.StringBuilder
		// @60: invokevirtual java.lang.StringBuilder.toString()java.lang.String
		// @63: invokestatic game.C_100181_cf.func_105695_a(java.lang.Throwable, java.lang.String)game.C_100170_cm
		// @66: athrow
		// @67: return
	}
	
	private final int func_103243_n(int arg0)
	{
		// @00: getstatic int game.SteelSentinels.field_105275_O
		// @03: istore_3
		// @04: iconst_m1
		// @05: aload_0
		// @06: getfield int game.C_100309_lk.field_103270_R
		// @09: iconst_m1
		// @0A: ixor
		// @0B: if_icmpne @13
		// @0E: aload_0
		// @0F: getfield int game.C_100309_lk.field_103270_R
		// @12: ireturn
		// @13: aload_0
		// @14: getfield int game.C_100309_lk.field_103270_R
		// @17: iconst_1
		// @18: isub
		// @19: istore_2
		// @1A: iload_1
		// @1B: sipush -27931 (0x92E5)
		// @1E: if_icmpeq @24
		// @21: bipush 66 (0x42)
		// @23: ireturn
		// @24: iload_2
		// @25: iconst_m1
		// @26: ixor
		// @27: iconst_m1
		// @28: if_icmpge @4D
		// @2B: aload_0
		// @2C: getfield java.lang.String game.C_100309_lk.field_102534_C
		// @2F: iconst_m1
		// @30: iload_2
		// @31: iadd
		// @32: invokevirtual java.lang.String.charAt(int)char
		// @35: iload_3
		// @36: ifne @4E
		// @39: bipush 32 (0x20)
		// @3B: if_icmpeq @4D
		// @3E: goto @42
		// @41: athrow
		// @42: iinc #2 +255
		// @45: iload_3
		// @46: ifeq @24
		// @49: goto @4D
		// @4C: athrow
		// @4D: iload_2
		// @4E: ireturn
		// @4F: astore_2
		// @50: aload_2
		// @51: new java.lang.StringBuilder
		// @54: dup
		// @55: invokespecial java.lang.StringBuilder.<init>()void
		// @58: getstatic java.lang.String[] game.C_100309_lk.field_103264_ib
		// @5B: bipush 19 (0x13)
		// @5D: aaload
		// @5E: invokevirtual java.lang.StringBuilder.append(java.lang.String)java.lang.StringBuilder
		// @61: iload_1
		// @62: invokevirtual java.lang.StringBuilder.append(int)java.lang.StringBuilder
		// @65: bipush 41 (0x29)
		// @67: invokevirtual java.lang.StringBuilder.append(char)java.lang.StringBuilder
		// @6A: invokevirtual java.lang.StringBuilder.toString()java.lang.String
		// @6D: invokestatic game.C_100181_cf.func_105695_a(java.lang.Throwable, java.lang.String)game.C_100170_cm
		// @70: athrow
	}
	
	static final void func_103238_a(boolean arg0, byte arg1)
	{
		// @00: bipush -8 (0xF8)
		// @02: iload_0
		// @03: invokestatic game.C_100138_bo.func_100400_a(int, boolean)void
		// @06: iload_0
		// @07: sipush -11371 (0xD395)
		// @0A: invokestatic game.C_100318_hj.func_107191_a(boolean, int)void
		// @0D: bipush 82 (0x52)
		// @0F: bipush 14 (0x0E)
		// @11: iload_1
		// @12: isub
		// @13: bipush 61 (0x3D)
		// @15: idiv
		// @16: irem
		// @17: istore_2
		// @18: goto @45
		// @1B: astore_2
		// @1C: aload_2
		// @1D: new java.lang.StringBuilder
		// @20: dup
		// @21: invokespecial java.lang.StringBuilder.<init>()void
		// @24: getstatic java.lang.String[] game.C_100309_lk.field_103264_ib
		// @27: iconst_3
		// @28: aaload
		// @29: invokevirtual java.lang.StringBuilder.append(java.lang.String)java.lang.StringBuilder
		// @2C: iload_0
		// @2D: invokevirtual java.lang.StringBuilder.append(boolean)java.lang.StringBuilder
		// @30: bipush 44 (0x2C)
		// @32: invokevirtual java.lang.StringBuilder.append(char)java.lang.StringBuilder
		// @35: iload_1
		// @36: invokevirtual java.lang.StringBuilder.append(int)java.lang.StringBuilder
		// @39: bipush 41 (0x29)
		// @3B: invokevirtual java.lang.StringBuilder.append(char)java.lang.StringBuilder
		// @3E: invokevirtual java.lang.StringBuilder.toString()java.lang.String
		// @41: invokestatic game.C_100181_cf.func_105695_a(java.lang.Throwable, java.lang.String)game.C_100170_cm
		// @44: athrow
		// @45: return
	}
	
	final void func_103239_c(boolean arg0)
	{
		// @00: aload_0
		// @01: ldc ""
		// @03: putfield java.lang.String game.C_100309_lk.field_102534_C
		// @06: iload_1
		// @07: ifeq @0B
		// @0A: return
		// @0B: aload_0
		// @0C: iconst_0
		// @0D: putfield int game.C_100309_lk.field_103270_R
		// @10: aload_0
		// @11: iconst_0
		// @12: putfield int game.C_100309_lk.field_103257_O
		// @15: aload_0
		// @16: sipush -19211 (0xB4F5)
		// @19: invokevirtual game.C_100309_lk.func_103241_k(int)void
		// @1C: goto @41
		// @1F: astore_2
		// @20: aload_2
		// @21: new java.lang.StringBuilder
		// @24: dup
		// @25: invokespecial java.lang.StringBuilder.<init>()void
		// @28: getstatic java.lang.String[] game.C_100309_lk.field_103264_ib
		// @2B: bipush 10 (0x0A)
		// @2D: aaload
		// @2E: invokevirtual java.lang.StringBuilder.append(java.lang.String)java.lang.StringBuilder
		// @31: iload_1
		// @32: invokevirtual java.lang.StringBuilder.append(boolean)java.lang.StringBuilder
		// @35: bipush 41 (0x29)
		// @37: invokevirtual java.lang.StringBuilder.append(char)java.lang.StringBuilder
		// @3A: invokevirtual java.lang.StringBuilder.toString()java.lang.String
		// @3D: invokestatic game.C_100181_cf.func_105695_a(java.lang.Throwable, java.lang.String)game.C_100170_cm
		// @40: athrow
		// @41: return
	}
	
	private final void func_103254_d(boolean arg0)
	{
		// @000: getstatic int game.SteelSentinels.field_105275_O
		// @003: istore #8
		// @005: aload_0
		// @006: getfield boolean game.C_100309_lk.field_103262_U
		// @009: ifeq @010
		// @00C: goto @01B
		// @00F: athrow
		// @010: aload_0
		// @011: iconst_0
		// @012: putfield int game.C_100309_lk.field_102550_y
		// @015: aload_0
		// @016: iconst_0
		// @017: putfield int game.C_100309_lk.field_102551_x
		// @01A: return
		// @01B: iload_1
		// @01C: ifeq @02D
		// @01F: aload_0
		// @020: bipush 26 (0x1A)
		// @022: aconst_null
		// @023: checkcast java.lang.String
		// @026: invokespecial game.C_100309_lk.func_103252_a(int, java.lang.String)void
		// @029: goto @02D
		// @02C: athrow
		// @02D: aload_0
		// @02E: getfield game.C_100326_ic game.C_100309_lk.field_102533_B
		// @031: instanceof game.C_100184_rn
		// @034: ifne @038
		// @037: return
		// @038: aload_0
		// @039: getfield game.C_100326_ic game.C_100309_lk.field_102533_B
		// @03C: checkcast game.C_100184_rn
		// @03F: astore_2
		// @040: aload_2
		// @041: bipush 116 (0x74)
		// @043: aload_0
		// @044: invokeinterface game.C_100184_rn.func_100434_b(int, game.C_100336_im)game.C_100205_qf
		// @049: astore_3
		// @04A: aload_3
		// @04B: bipush 56 (0x38)
		// @04D: invokevirtual game.C_100205_qf.func_103663_c(int)int
		// @050: istore #4
		// @052: aload_2
		// @053: aload_0
		// @054: bipush 79 (0x4F)
		// @056: invokeinterface game.C_100184_rn.func_100435_a(game.C_100336_im, byte)int
		// @05B: istore #5
		// @05D: aload_2
		// @05E: iconst_1
		// @05F: invokeinterface game.C_100184_rn.func_100437_a(boolean)int
		// @064: ldc -664408895 (0xd865ecc1)
		// @066: ishr
		// @067: istore #6
		// @069: iload #5
		// @06B: iload #6
		// @06D: ineg
		// @06E: iadd
		// @06F: iload #4
		// @071: if_icmpgt @078
		// @074: goto @083
		// @077: athrow
		// @078: aload_0
		// @079: iconst_0
		// @07A: putfield int game.C_100309_lk.field_102550_y
		// @07D: aload_0
		// @07E: iconst_0
		// @07F: putfield int game.C_100309_lk.field_102551_x
		// @082: return
		// @083: aload_0
		// @084: getfield int game.C_100309_lk.field_102551_x
		// @087: aload_3
		// @088: aload_0
		// @089: getfield int game.C_100309_lk.field_103270_R
		// @08C: ldc 6316128 (0x606060)
		// @08E: invokevirtual game.C_100205_qf.func_103665_b(int, int)int
		// @091: ineg
		// @092: isub
		// @093: istore #7
		// @095: iload #6
		// @097: ineg
		// @098: iload #5
		// @09A: iadd
		// @09B: iconst_m1
		// @09C: ixor
		// @09D: iload #7
		// @09F: iconst_m1
		// @0A0: ixor
		// @0A1: if_icmple @0C0
		// @0A4: aload_0
		// @0A5: aload_0
		// @0A6: getfield int game.C_100309_lk.field_102551_x
		// @0A9: iload #6
		// @0AB: ineg
		// @0AC: iadd
		// @0AD: iload #5
		// @0AF: iload #7
		// @0B1: ineg
		// @0B2: iadd
		// @0B3: iadd
		// @0B4: putfield int game.C_100309_lk.field_102551_x
		// @0B7: iload #8
		// @0B9: ifeq @0E2
		// @0BC: goto @0C0
		// @0BF: athrow
		// @0C0: iload #6
		// @0C2: iconst_m1
		// @0C3: ixor
		// @0C4: iload #7
		// @0C6: iconst_m1
		// @0C7: ixor
		// @0C8: if_icmpge @0E2
		// @0CB: goto @0CF
		// @0CE: athrow
		// @0CF: aload_0
		// @0D0: aload_0
		// @0D1: getfield int game.C_100309_lk.field_102551_x
		// @0D4: iload #7
		// @0D6: ineg
		// @0D7: iload #6
		// @0D9: iadd
		// @0DA: iadd
		// @0DB: putfield int game.C_100309_lk.field_102551_x
		// @0DE: goto @0E2
		// @0E1: athrow
		// @0E2: iconst_m1
		// @0E3: aload_0
		// @0E4: getfield int game.C_100309_lk.field_102551_x
		// @0E7: iconst_m1
		// @0E8: ixor
		// @0E9: if_icmpgt @110
		// @0EC: iload #6
		// @0EE: iload #5
		// @0F0: ineg
		// @0F1: iadd
		// @0F2: aload_0
		// @0F3: getfield int game.C_100309_lk.field_102551_x
		// @0F6: if_icmple @119
		// @0F9: goto @0FD
		// @0FC: athrow
		// @0FD: aload_0
		// @0FE: iload #6
		// @100: iload #5
		// @102: ineg
		// @103: iadd
		// @104: putfield int game.C_100309_lk.field_102551_x
		// @107: iload #8
		// @109: ifeq @119
		// @10C: goto @110
		// @10F: athrow
		// @110: aload_0
		// @111: iconst_0
		// @112: putfield int game.C_100309_lk.field_102551_x
		// @115: goto @119
		// @118: athrow
		// @119: goto @13E
		// @11C: astore_2
		// @11D: aload_2
		// @11E: new java.lang.StringBuilder
		// @121: dup
		// @122: invokespecial java.lang.StringBuilder.<init>()void
		// @125: getstatic java.lang.String[] game.C_100309_lk.field_103264_ib
		// @128: bipush 7 (0x07)
		// @12A: aaload
		// @12B: invokevirtual java.lang.StringBuilder.append(java.lang.String)java.lang.StringBuilder
		// @12E: iload_1
		// @12F: invokevirtual java.lang.StringBuilder.append(boolean)java.lang.StringBuilder
		// @132: bipush 41 (0x29)
		// @134: invokevirtual java.lang.StringBuilder.append(char)java.lang.StringBuilder
		// @137: invokevirtual java.lang.StringBuilder.toString()java.lang.String
		// @13A: invokestatic game.C_100181_cf.func_105695_a(java.lang.Throwable, java.lang.String)game.C_100170_cm
		// @13D: athrow
		// @13E: return
	}
	
	final void func_102528_a(int arg0, int arg1, int arg2, byte arg3)
	{
		// @00: iload #4
		// @02: bipush -126 (0x82)
		// @04: if_icmple @11
		// @07: aload_0
		// @08: bipush -21 (0xEB)
		// @0A: putfield int game.C_100309_lk.field_103274_X
		// @0D: goto @11
		// @10: athrow
		// @11: aconst_null
		// @12: aload_0
		// @13: getfield game.C_100326_ic game.C_100309_lk.field_102533_B
		// @16: if_acmpeq @A2
		// @19: iconst_m1
		// @1A: iload_1
		// @1B: iconst_m1
		// @1C: ixor
		// @1D: if_icmpeq @28
		// @20: goto @24
		// @23: athrow
		// @24: goto @A2
		// @27: athrow
		// @28: aload_0
		// @29: getfield game.C_100326_ic game.C_100309_lk.field_102533_B
		// @2C: aload_0
		// @2D: getfield boolean game.C_100309_lk.field_103113_L
		// @30: sipush -26568 (0x9838)
		// @33: iload_3
		// @34: iload_2
		// @35: aload_0
		// @36: invokeinterface game.C_100326_ic.func_100362_a(boolean, int, int, int, game.C_100336_im)void
		// @3B: aload_0
		// @3C: getfield game.C_100326_ic game.C_100309_lk.field_102533_B
		// @3F: instanceof game.C_100184_rn
		// @42: ifeq @A2
		// @45: aload_0
		// @46: getfield game.C_100326_ic game.C_100309_lk.field_102533_B
		// @49: checkcast game.C_100184_rn
		// @4C: astore #5
		// @4E: aload_0
		// @4F: getfield int game.C_100309_lk.field_103270_R
		// @52: aload_0
		// @53: getfield int game.C_100309_lk.field_103257_O
		// @56: if_icmpeq @71
		// @59: aload #5
		// @5B: bipush -127 (0x81)
		// @5D: aload_0
		// @5E: getfield int game.C_100309_lk.field_103257_O
		// @61: iload_3
		// @62: aload_0
		// @63: getfield int game.C_100309_lk.field_103270_R
		// @66: iload_2
		// @67: aload_0
		// @68: invokeinterface game.C_100184_rn.func_100441_a(int, int, int, int, int, game.C_100336_im)void
		// @6D: goto @71
		// @70: athrow
		// @71: bipush -42 (0xD6)
		// @73: invokestatic game.C_100198_qn.func_105828_a(byte)long
		// @76: lstore #6
		// @78: aload_0
		// @79: getfield long game.C_100309_lk.field_103256_cb
		// @7C: lneg
		// @7D: lload #6
		// @7F: ladd
		// @80: ldc2_w 1000
		// @83: lrem
		// @84: ldc2_w -1
		// @87: lxor
		// @88: ldc2_w -501
		// @8B: lcmp
		// @8C: ifgt @93
		// @8F: goto @A2
		// @92: athrow
		// @93: aload #5
		// @95: iload_2
		// @96: iconst_1
		// @97: aload_0
		// @98: aload_0
		// @99: getfield int game.C_100309_lk.field_103270_R
		// @9C: iload_3
		// @9D: invokeinterface game.C_100184_rn.func_100439_a(int, boolean, game.C_100336_im, int, int)void
		// @A2: goto @E5
		// @A5: astore #5
		// @A7: aload #5
		// @A9: new java.lang.StringBuilder
		// @AC: dup
		// @AD: invokespecial java.lang.StringBuilder.<init>()void
		// @B0: getstatic java.lang.String[] game.C_100309_lk.field_103264_ib
		// @B3: bipush 21 (0x15)
		// @B5: aaload
		// @B6: invokevirtual java.lang.StringBuilder.append(java.lang.String)java.lang.StringBuilder
		// @B9: iload_1
		// @BA: invokevirtual java.lang.StringBuilder.append(int)java.lang.StringBuilder
		// @BD: bipush 44 (0x2C)
		// @BF: invokevirtual java.lang.StringBuilder.append(char)java.lang.StringBuilder
		// @C2: iload_2
		// @C3: invokevirtual java.lang.StringBuilder.append(int)java.lang.StringBuilder
		// @C6: bipush 44 (0x2C)
		// @C8: invokevirtual java.lang.StringBuilder.append(char)java.lang.StringBuilder
		// @CB: iload_3
		// @CC: invokevirtual java.lang.StringBuilder.append(int)java.lang.StringBuilder
		// @CF: bipush 44 (0x2C)
		// @D1: invokevirtual java.lang.StringBuilder.append(char)java.lang.StringBuilder
		// @D4: iload #4
		// @D6: invokevirtual java.lang.StringBuilder.append(int)java.lang.StringBuilder
		// @D9: bipush 41 (0x29)
		// @DB: invokevirtual java.lang.StringBuilder.append(char)java.lang.StringBuilder
		// @DE: invokevirtual java.lang.StringBuilder.toString()java.lang.String
		// @E1: invokestatic game.C_100181_cf.func_105695_a(java.lang.Throwable, java.lang.String)game.C_100170_cm
		// @E4: athrow
		// @E5: return
	}
	
	public static void func_103253_o(int arg0)
	{
		// @00: aconst_null
		// @01: putstatic game.C_100037_wb game.C_100309_lk.field_103268_P
		// @04: iload_0
		// @05: ifeq @16
		// @08: bipush -12 (0xF4)
		// @0A: bipush 13 (0x0D)
		// @0C: bipush 78 (0x4E)
		// @0E: invokestatic game.C_100309_lk.func_103242_b(int, int, int)boolean
		// @11: pop
		// @12: goto @16
		// @15: athrow
		// @16: aconst_null
		// @17: putstatic game.C_100127_tl game.C_100309_lk.field_103263_T
		// @1A: aconst_null
		// @1B: putstatic game.C_100037_wb game.C_100309_lk.field_103275_Z
		// @1E: aconst_null
		// @1F: putstatic game.C_100037_wb game.C_100309_lk.field_103255_db
		// @22: aconst_null
		// @23: putstatic java.lang.String game.C_100309_lk.field_103266_V
		// @26: aconst_null
		// @27: putstatic boolean[] game.C_100309_lk.field_103258_hb
		// @2A: aconst_null
		// @2B: putstatic java.lang.String game.C_100309_lk.field_103269_S
		// @2E: aconst_null
		// @2F: putstatic game.C_100268_mk game.C_100309_lk.field_103259_eb
		// @32: aconst_null
		// @33: putstatic int[] game.C_100309_lk.field_103273_Y
		// @36: aconst_null
		// @37: putstatic game.C_100302_ka game.C_100309_lk.field_103272_bb
		// @3A: goto @5F
		// @3D: astore_1
		// @3E: aload_1
		// @3F: new java.lang.StringBuilder
		// @42: dup
		// @43: invokespecial java.lang.StringBuilder.<init>()void
		// @46: getstatic java.lang.String[] game.C_100309_lk.field_103264_ib
		// @49: bipush 17 (0x11)
		// @4B: aaload
		// @4C: invokevirtual java.lang.StringBuilder.append(java.lang.String)java.lang.StringBuilder
		// @4F: iload_0
		// @50: invokevirtual java.lang.StringBuilder.append(int)java.lang.StringBuilder
		// @53: bipush 41 (0x29)
		// @55: invokevirtual java.lang.StringBuilder.append(char)java.lang.StringBuilder
		// @58: invokevirtual java.lang.StringBuilder.toString()java.lang.String
		// @5B: invokestatic game.C_100181_cf.func_105695_a(java.lang.Throwable, java.lang.String)game.C_100170_cm
		// @5E: athrow
		// @5F: return
	}
	
	final void func_103251_a(boolean arg0, boolean arg1, String arg2)
	{
		// @00: aload_3
		// @01: ifnonnull @07
		// @04: ldc ""
		// @06: astore_3
		// @07: iload_2
		// @08: iconst_1
		// @09: if_icmpeq @1C
		// @0C: aload_0
		// @0D: bipush 50 (0x32)
		// @0F: bipush 34 (0x22)
		// @11: bipush 83 (0x53)
		// @13: bipush 15 (0x0F)
		// @15: invokevirtual game.C_100309_lk.func_102528_a(int, int, int, byte)void
		// @18: goto @1C
		// @1B: athrow
		// @1C: aload_0
		// @1D: aload_3
		// @1E: putfield java.lang.String game.C_100309_lk.field_102534_C
		// @21: aload_3
		// @22: invokevirtual java.lang.String.length()int
		// @25: istore #4
		// @27: iconst_m1
		// @28: aload_0
		// @29: getfield int game.C_100309_lk.field_103274_X
		// @2C: if_icmpeq @50
		// @2F: iload #4
		// @31: aload_0
		// @32: getfield int game.C_100309_lk.field_103274_X
		// @35: if_icmple @50
		// @38: goto @3C
		// @3B: athrow
		// @3C: aload_0
		// @3D: aload_0
		// @3E: getfield java.lang.String game.C_100309_lk.field_102534_C
		// @41: iconst_0
		// @42: aload_0
		// @43: getfield int game.C_100309_lk.field_103274_X
		// @46: invokevirtual java.lang.String.substring(int, int)java.lang.String
		// @49: putfield java.lang.String game.C_100309_lk.field_102534_C
		// @4C: goto @50
		// @4F: athrow
		// @50: aload_0
		// @51: aload_0
		// @52: aload_0
		// @53: getfield java.lang.String game.C_100309_lk.field_102534_C
		// @56: invokevirtual java.lang.String.length()int
		// @59: dup_x1
		// @5A: putfield int game.C_100309_lk.field_103257_O
		// @5D: putfield int game.C_100309_lk.field_103270_R
		// @60: iload_1
		// @61: ifeq @68
		// @64: goto @6F
		// @67: athrow
		// @68: aload_0
		// @69: sipush -19211 (0xB4F5)
		// @6C: invokevirtual game.C_100309_lk.func_103241_k(int)void
		// @6F: goto @B9
		// @72: astore #4
		// @74: aload #4
		// @76: new java.lang.StringBuilder
		// @79: dup
		// @7A: invokespecial java.lang.StringBuilder.<init>()void
		// @7D: getstatic java.lang.String[] game.C_100309_lk.field_103264_ib
		// @80: bipush 9 (0x09)
		// @82: aaload
		// @83: invokevirtual java.lang.StringBuilder.append(java.lang.String)java.lang.StringBuilder
		// @86: iload_1
		// @87: invokevirtual java.lang.StringBuilder.append(boolean)java.lang.StringBuilder
		// @8A: bipush 44 (0x2C)
		// @8C: invokevirtual java.lang.StringBuilder.append(char)java.lang.StringBuilder
		// @8F: iload_2
		// @90: invokevirtual java.lang.StringBuilder.append(boolean)java.lang.StringBuilder
		// @93: bipush 44 (0x2C)
		// @95: invokevirtual java.lang.StringBuilder.append(char)java.lang.StringBuilder
		// @98: aload_3
		// @99: ifnull @A5
		// @9C: getstatic java.lang.String[] game.C_100309_lk.field_103264_ib
		// @9F: iconst_1
		// @A0: aaload
		// @A1: goto @AA
		// @A4: athrow
		// @A5: getstatic java.lang.String[] game.C_100309_lk.field_103264_ib
		// @A8: iconst_2
		// @A9: aaload
		// @AA: invokevirtual java.lang.StringBuilder.append(java.lang.String)java.lang.StringBuilder
		// @AD: bipush 41 (0x29)
		// @AF: invokevirtual java.lang.StringBuilder.append(char)java.lang.StringBuilder
		// @B2: invokevirtual java.lang.StringBuilder.toString()java.lang.String
		// @B5: invokestatic game.C_100181_cf.func_105695_a(java.lang.Throwable, java.lang.String)game.C_100170_cm
		// @B8: athrow
		// @B9: return
	}
	
	static
	{
		// @000: bipush 26 (0x1A)
		// @002: anewarray java.lang.String
		// @005: dup
		// @006: iconst_0
		// @007: ldc "\nVss "
		// @009: invokestatic game.C_100309_lk.func_103247_z(java.lang.String)char[]
		// @00C: invokestatic game.C_100309_lk.func_103234_z(char[])java.lang.String
		// @00F: aastore
		// @010: dup
		// @011: iconst_1
		// @012: ldc "\u001d\u0013s\u000cu"
		// @014: invokestatic game.C_100309_lk.func_103247_z(java.lang.String)char[]
		// @017: invokestatic game.C_100309_lk.func_103234_z(char[])java.lang.String
		// @01A: aastore
		// @01B: dup
		// @01C: iconst_2
		// @01D: ldc "\u0008H1N"
		// @01F: invokestatic game.C_100309_lk.func_103247_z(java.lang.String)char[]
		// @022: invokestatic game.C_100309_lk.func_103234_z(char[])java.lang.String
		// @025: aastore
		// @026: dup
		// @027: iconst_3
		// @028: ldc "\nVssIN"
		// @02A: invokestatic game.C_100309_lk.func_103247_z(java.lang.String)char[]
		// @02D: invokestatic game.C_100309_lk.func_103234_z(char[])java.lang.String
		// @030: aastore
		// @031: dup
		// @032: iconst_4
		// @033: ldc "\nVsdIN"
		// @035: invokestatic game.C_100309_lk.func_103247_z(java.lang.String)char[]
		// @038: invokestatic game.C_100309_lk.func_103234_z(char[])java.lang.String
		// @03B: aastore
		// @03C: dup
		// @03D: iconst_5
		// @03E: ldc "\nVsw "
		// @040: invokestatic game.C_100309_lk.func_103247_z(java.lang.String)char[]
		// @043: invokestatic game.C_100309_lk.func_103234_z(char[])java.lang.String
		// @046: aastore
		// @047: dup
		// @048: bipush 6 (0x06)
		// @04A: ldc "\nVshIN"
		// @04C: invokestatic game.C_100309_lk.func_103247_z(java.lang.String)char[]
		// @04F: invokestatic game.C_100309_lk.func_103234_z(char[])java.lang.String
		// @052: aastore
		// @053: dup
		// @054: bipush 7 (0x07)
		// @056: ldc "\nVst "
		// @058: invokestatic game.C_100309_lk.func_103247_z(java.lang.String)char[]
		// @05B: invokestatic game.C_100309_lk.func_103234_z(char[])java.lang.String
		// @05E: aastore
		// @05F: dup
		// @060: bipush 8 (0x08)
		// @062: ldc "\nVsiIN"
		// @064: invokestatic game.C_100309_lk.func_103247_z(java.lang.String)char[]
		// @067: invokestatic game.C_100309_lk.func_103234_z(char[])java.lang.String
		// @06A: aastore
		// @06B: dup
		// @06C: bipush 9 (0x09)
		// @06E: ldc "\nVsf "
		// @070: invokestatic game.C_100309_lk.func_103247_z(java.lang.String)char[]
		// @073: invokestatic game.C_100309_lk.func_103234_z(char[])java.lang.String
		// @076: aastore
		// @077: dup
		// @078: bipush 10 (0x0A)
		// @07A: ldc "\nVsp "
		// @07C: invokestatic game.C_100309_lk.func_103247_z(java.lang.String)char[]
		// @07F: invokestatic game.C_100309_lk.func_103234_z(char[])java.lang.String
		// @082: aastore
		// @083: dup
		// @084: bipush 11 (0x0B)
		// @086: ldc "\nVsk "
		// @088: invokestatic game.C_100309_lk.func_103247_z(java.lang.String)char[]
		// @08B: invokestatic game.C_100309_lk.func_103234_z(char[])java.lang.String
		// @08E: aastore
		// @08F: dup
		// @090: bipush 12 (0x0C)
		// @092: ldc "\nVslIN"
		// @094: invokestatic game.C_100309_lk.func_103247_z(java.lang.String)char[]
		// @097: invokestatic game.C_100309_lk.func_103234_z(char[])java.lang.String
		// @09A: aastore
		// @09B: dup
		// @09C: bipush 13 (0x0D)
		// @09E: ldc "\nVsmIN"
		// @0A0: invokestatic game.C_100309_lk.func_103247_z(java.lang.String)char[]
		// @0A3: invokestatic game.C_100309_lk.func_103234_z(char[])java.lang.String
		// @0A6: aastore
		// @0A7: dup
		// @0A8: bipush 14 (0x0E)
		// @0AA: ldc "\nVsj "
		// @0AC: invokestatic game.C_100309_lk.func_103247_z(java.lang.String)char[]
		// @0AF: invokestatic game.C_100309_lk.func_103234_z(char[])java.lang.String
		// @0B2: aastore
		// @0B3: dup
		// @0B4: bipush 15 (0x0F)
		// @0B6: ldc "\nVsg "
		// @0B8: invokestatic game.C_100309_lk.func_103247_z(java.lang.String)char[]
		// @0BB: invokestatic game.C_100309_lk.func_103234_z(char[])java.lang.String
		// @0BE: aastore
		// @0BF: dup
		// @0C0: bipush 16 (0x10)
		// @0C2: ldc "\nVsjIN"
		// @0C4: invokestatic game.C_100309_lk.func_103247_z(java.lang.String)char[]
		// @0C7: invokestatic game.C_100309_lk.func_103234_z(char[])java.lang.String
		// @0CA: aastore
		// @0CB: dup
		// @0CC: bipush 17 (0x11)
		// @0CE: ldc "\nVs` "
		// @0D0: invokestatic game.C_100309_lk.func_103247_z(java.lang.String)char[]
		// @0D3: invokestatic game.C_100309_lk.func_103234_z(char[])java.lang.String
		// @0D6: aastore
		// @0D7: dup
		// @0D8: bipush 18 (0x12)
		// @0DA: ldc "\nVsrIN"
		// @0DC: invokestatic game.C_100309_lk.func_103247_z(java.lang.String)char[]
		// @0DF: invokestatic game.C_100309_lk.func_103234_z(char[])java.lang.String
		// @0E2: aastore
		// @0E3: dup
		// @0E4: bipush 19 (0x13)
		// @0E6: ldc "\nVs`IN"
		// @0E8: invokestatic game.C_100309_lk.func_103247_z(java.lang.String)char[]
		// @0EB: invokestatic game.C_100309_lk.func_103234_z(char[])java.lang.String
		// @0EE: aastore
		// @0EF: dup
		// @0F0: bipush 20 (0x14)
		// @0F2: ldc "\nVskIN"
		// @0F4: invokestatic game.C_100309_lk.func_103247_z(java.lang.String)char[]
		// @0F7: invokestatic game.C_100309_lk.func_103234_z(char[])java.lang.String
		// @0FA: aastore
		// @0FB: dup
		// @0FC: bipush 21 (0x15)
		// @0FE: ldc "\nVsa "
		// @100: invokestatic game.C_100309_lk.func_103247_z(java.lang.String)char[]
		// @103: invokestatic game.C_100309_lk.func_103234_z(char[])java.lang.String
		// @106: aastore
		// @107: dup
		// @108: bipush 22 (0x16)
		// @10A: ldc "\nVsoIN"
		// @10C: invokestatic game.C_100309_lk.func_103247_z(java.lang.String)char[]
		// @10F: invokestatic game.C_100309_lk.func_103234_z(char[])java.lang.String
		// @112: aastore
		// @113: dup
		// @114: bipush 23 (0x17)
		// @116: ldc "\nVsc "
		// @118: invokestatic game.C_100309_lk.func_103247_z(java.lang.String)char[]
		// @11B: invokestatic game.C_100309_lk.func_103234_z(char[])java.lang.String
		// @11E: aastore
		// @11F: dup
		// @120: bipush 24 (0x18)
		// @122: ldc "\nVseIN"
		// @124: invokestatic game.C_100309_lk.func_103247_z(java.lang.String)char[]
		// @127: invokestatic game.C_100309_lk.func_103234_z(char[])java.lang.String
		// @12A: aastore
		// @12B: dup
		// @12C: bipush 25 (0x19)
		// @12E: ldc "\nVs\u001ea\u0008T)\u001c "
		// @130: invokestatic game.C_100309_lk.func_103247_z(java.lang.String)char[]
		// @133: invokestatic game.C_100309_lk.func_103234_z(char[])java.lang.String
		// @136: aastore
		// @137: putstatic java.lang.String[] game.C_100309_lk.field_103264_ib
		// @13A: ldc "?R(\u0002i\u0014X}MfF\u0001x\u00126"
		// @13C: invokestatic game.C_100309_lk.func_103247_z(java.lang.String)char[]
		// @13F: invokestatic game.C_100309_lk.func_103234_z(char[])java.lang.String
		// @142: putstatic java.lang.String game.C_100309_lk.field_103269_S
		// @145: aconst_null
		// @146: putstatic java.lang.String game.C_100309_lk.field_103266_V
		// @149: bipush 112 (0x70)
		// @14B: newarray boolean[]
		// @14D: putstatic boolean[] game.C_100309_lk.field_103258_hb
		// @150: iconst_2
		// @151: putstatic int game.C_100309_lk.field_103267_Q
		// @154: new game.C_100268_mk
		// @157: dup
		// @158: invokespecial game.C_100268_mk.<init>()void
		// @15B: putstatic game.C_100268_mk game.C_100309_lk.field_103259_eb
		// @15E: return
	}
	
	private static char[] func_103247_z(String arg0)
	{
		// @00: aload_0
		// @01: invokevirtual java.lang.String.toCharArray()char[]
		// @04: dup
		// @05: arraylength
		// @06: iconst_2
		// @07: if_icmpge @13
		// @0A: dup
		// @0B: iconst_0
		// @0C: dup2
		// @0D: caload
		// @0E: bipush 8 (0x08)
		// @10: ixor
		// @11: i2c
		// @12: castore
		// @13: areturn
	}
	
	private static String func_103234_z(char[] arg0)
	{
		// @00: aload_0
		// @01: dup
		// @02: arraylength
		// @03: swap
		// @04: iconst_0
		// @05: istore_1
		// @06: goto @4C
		// @09: dup
		// @0A: iload_1
		// @0B: dup2
		// @0C: caload
		// @0D: iload_1
		// @0E: iconst_5
		// @0F: irem
		// @10: tableswitch def: @44, for 0: @30, for 1: @35, for 2: @3A, for 3: @3F
		// @30: bipush 102 (0x66)
		// @32: goto @46
		// @35: bipush 61 (0x3D)
		// @37: goto @46
		// @3A: bipush 93 (0x5D)
		// @3C: goto @46
		// @3F: bipush 34 (0x22)
		// @41: goto @46
		// @44: bipush 8 (0x08)
		// @46: ixor
		// @47: i2c
		// @48: castore
		// @49: iinc #1 +1
		// @4C: swap
		// @4D: dup_x1
		// @4E: iload_1
		// @4F: if_icmpgt @09
		// @52: new java.lang.String
		// @55: dup_x1
		// @56: swap
		// @57: invokespecial java.lang.String.<init>(char[])void
		// @5A: invokevirtual java.lang.String.intern()java.lang.String
		// @5D: areturn
	}
}
