package game;

final class C_100210_qa extends C_100261_md
{
	int[] field_101081_y;
	private C_100014_wg field_101072_w;
	private C_100119_ua field_101057_N;
	private int[] field_101062_K;
	private int[] field_101075_t;
	static C_100302_ka field_101054_C;
	private int[] field_101053_B;
	private C_100121_ud[][] field_101078_q;
	private int[] field_101077_r;
	private int[] field_101058_O;
	int[] field_101059_H;
	static C_100302_ka[] field_101063_U;
	private int[] field_101074_u;
	private int[] field_101061_J;
	private int[] field_101079_p;
	private int[] field_101052_A;
	int[] field_101060_I;
	private int[] field_101071_o;
	private C_100121_ud[][] field_101070_n;
	private int field_101064_T;
	private int[] field_101066_Q;
	private int[] field_101069_R;
	private int[] field_101073_v;
	private int field_101067_P;
	static String field_101049_E;
	private long field_101076_s;
	private long field_101068_S;
	private int field_101056_M;
	private boolean field_101055_L;
	private int field_101048_D;
	private C_100044_vm field_101051_G;
	private int field_101080_z;
	private C_100002_gf field_101082_x;
	private boolean field_101050_F;
	private static final String[] field_101065_V;
	
	final synchronized void func_101034_d(int arg0, int arg1, int arg2)
	{
		// @00: aload_0
		// @01: bipush 120 (0x78)
		// @03: iload_2
		// @04: iload_3
		// @05: invokespecial game.C_100210_qa.func_101032_a(int, int, int)void
		// @08: iload_1
		// @09: ifeq @14
		// @0C: aload_0
		// @0D: aconst_null
		// @0E: checkcast int[]
		// @11: putfield int[] game.C_100210_qa.field_101081_y
		// @14: goto @4D
		// @17: astore #4
		// @19: aload #4
		// @1B: new java.lang.StringBuilder
		// @1E: dup
		// @1F: invokespecial java.lang.StringBuilder.<init>()void
		// @22: getstatic java.lang.String[] game.C_100210_qa.field_101065_V
		// @25: bipush 22 (0x16)
		// @27: aaload
		// @28: invokevirtual java.lang.StringBuilder.append(java.lang.String)java.lang.StringBuilder
		// @2B: iload_1
		// @2C: invokevirtual java.lang.StringBuilder.append(int)java.lang.StringBuilder
		// @2F: bipush 44 (0x2C)
		// @31: invokevirtual java.lang.StringBuilder.append(char)java.lang.StringBuilder
		// @34: iload_2
		// @35: invokevirtual java.lang.StringBuilder.append(int)java.lang.StringBuilder
		// @38: bipush 44 (0x2C)
		// @3A: invokevirtual java.lang.StringBuilder.append(char)java.lang.StringBuilder
		// @3D: iload_3
		// @3E: invokevirtual java.lang.StringBuilder.append(int)java.lang.StringBuilder
		// @41: bipush 41 (0x29)
		// @43: invokevirtual java.lang.StringBuilder.append(char)java.lang.StringBuilder
		// @46: invokevirtual java.lang.StringBuilder.toString()java.lang.String
		// @49: invokestatic game.C_100181_cf.func_105695_a(java.lang.Throwable, java.lang.String)game.C_100170_cm
		// @4C: athrow
		// @4D: return
	}
	
	private final void func_101018_a(boolean arg0, int arg1, int arg2)
	{
		// @00: getstatic int game.SteelSentinels.field_105275_O
		// @03: istore #5
		// @05: iload_1
		// @06: iconst_1
		// @07: if_icmpeq @16
		// @0A: aload_0
		// @0B: aconst_null
		// @0C: checkcast int[]
		// @0F: putfield int[] game.C_100210_qa.field_101066_Q
		// @12: goto @16
		// @15: athrow
		// @16: aload_0
		// @17: getfield int[] game.C_100210_qa.field_101062_K
		// @1A: iload_2
		// @1B: iaload
		// @1C: iload_3
		// @1D: if_icmpeq @4D
		// @20: aload_0
		// @21: getfield int[] game.C_100210_qa.field_101062_K
		// @24: iload_2
		// @25: iload_3
		// @26: iastore
		// @27: iconst_0
		// @28: istore #4
		// @2A: sipush 128 (0x0080)
		// @2D: iload #4
		// @2F: if_icmple @4D
		// @32: aload_0
		// @33: getfield game.C_100121_ud[][] game.C_100210_qa.field_101078_q
		// @36: iload_2
		// @37: aaload
		// @38: iload #4
		// @3A: aconst_null
		// @3B: aastore
		// @3C: iinc #4 +1
		// @3F: iload #5
		// @41: ifne @86
		// @44: iload #5
		// @46: ifeq @2A
		// @49: goto @4D
		// @4C: athrow
		// @4D: goto @86
		// @50: astore #4
		// @52: aload #4
		// @54: new java.lang.StringBuilder
		// @57: dup
		// @58: invokespecial java.lang.StringBuilder.<init>()void
		// @5B: getstatic java.lang.String[] game.C_100210_qa.field_101065_V
		// @5E: bipush 11 (0x0B)
		// @60: aaload
		// @61: invokevirtual java.lang.StringBuilder.append(java.lang.String)java.lang.StringBuilder
		// @64: iload_1
		// @65: invokevirtual java.lang.StringBuilder.append(boolean)java.lang.StringBuilder
		// @68: bipush 44 (0x2C)
		// @6A: invokevirtual java.lang.StringBuilder.append(char)java.lang.StringBuilder
		// @6D: iload_2
		// @6E: invokevirtual java.lang.StringBuilder.append(int)java.lang.StringBuilder
		// @71: bipush 44 (0x2C)
		// @73: invokevirtual java.lang.StringBuilder.append(char)java.lang.StringBuilder
		// @76: iload_3
		// @77: invokevirtual java.lang.StringBuilder.append(int)java.lang.StringBuilder
		// @7A: bipush 41 (0x29)
		// @7C: invokevirtual java.lang.StringBuilder.append(char)java.lang.StringBuilder
		// @7F: invokevirtual java.lang.StringBuilder.toString()java.lang.String
		// @82: invokestatic game.C_100181_cf.func_105695_a(java.lang.Throwable, java.lang.String)game.C_100170_cm
		// @85: athrow
		// @86: return
	}
	
	private final void func_101021_a(int arg0, int arg1, byte arg2, int arg3)
	{
		// @000: getstatic int game.SteelSentinels.field_105275_O
		// @003: istore #7
		// @005: aload_0
		// @006: getfield game.C_100121_ud[][] game.C_100210_qa.field_101070_n
		// @009: iload #4
		// @00B: aaload
		// @00C: iload_1
		// @00D: aaload
		// @00E: astore #5
		// @010: aload #5
		// @012: ifnull @019
		// @015: goto @01A
		// @018: athrow
		// @019: return
		// @01A: aload_0
		// @01B: getfield game.C_100121_ud[][] game.C_100210_qa.field_101070_n
		// @01E: iload #4
		// @020: aaload
		// @021: iload_1
		// @022: aconst_null
		// @023: aastore
		// @024: iconst_0
		// @025: aload_0
		// @026: getfield int[] game.C_100210_qa.field_101060_I
		// @029: iload #4
		// @02B: iaload
		// @02C: iconst_2
		// @02D: iand
		// @02E: if_icmpeq @0A1
		// @031: aload_0
		// @032: getfield game.C_100044_vm game.C_100210_qa.field_101051_G
		// @035: getfield game.C_100202_qi game.C_100044_vm.field_100943_u
		// @038: bipush 35 (0x23)
		// @03A: invokevirtual game.C_100202_qi.func_105899_c(int)game.C_100158_da
		// @03D: checkcast game.C_100121_ud
		// @040: astore #6
		// @042: aload #6
		// @044: ifnull @09C
		// @047: aload #6
		// @049: getfield int game.C_100121_ud.field_100725_m
		// @04C: aload #5
		// @04E: getfield int game.C_100121_ud.field_100725_m
		// @051: iload #7
		// @053: ifne @0AE
		// @056: if_icmpne @086
		// @059: goto @05D
		// @05C: athrow
		// @05D: aload #6
		// @05F: getfield int game.C_100121_ud.field_100733_r
		// @062: iconst_m1
		// @063: ixor
		// @064: iconst_m1
		// @065: if_icmple @086
		// @068: goto @06C
		// @06B: athrow
		// @06C: aload #5
		// @06E: aload #6
		// @070: if_acmpeq @086
		// @073: goto @077
		// @076: athrow
		// @077: aload #5
		// @079: iconst_0
		// @07A: putfield int game.C_100121_ud.field_100733_r
		// @07D: iload #7
		// @07F: ifeq @09C
		// @082: goto @086
		// @085: athrow
		// @086: aload_0
		// @087: getfield game.C_100044_vm game.C_100210_qa.field_101051_G
		// @08A: getfield game.C_100202_qi game.C_100044_vm.field_100943_u
		// @08D: bipush 108 (0x6C)
		// @08F: invokevirtual game.C_100202_qi.func_105907_c(byte)game.C_100158_da
		// @092: checkcast game.C_100121_ud
		// @095: astore #6
		// @097: iload #7
		// @099: ifeq @042
		// @09C: iload #7
		// @09E: ifeq @0AB
		// @0A1: aload #5
		// @0A3: iconst_0
		// @0A4: putfield int game.C_100121_ud.field_100733_r
		// @0A7: goto @0AB
		// @0AA: athrow
		// @0AB: iload_3
		// @0AC: bipush -7 (0xF9)
		// @0AE: if_icmplt @0BD
		// @0B1: aload_0
		// @0B2: aconst_null
		// @0B3: checkcast game.C_100044_vm
		// @0B6: putfield game.C_100044_vm game.C_100210_qa.field_101051_G
		// @0B9: goto @0BD
		// @0BC: athrow
		// @0BD: goto @100
		// @0C0: astore #5
		// @0C2: aload #5
		// @0C4: new java.lang.StringBuilder
		// @0C7: dup
		// @0C8: invokespecial java.lang.StringBuilder.<init>()void
		// @0CB: getstatic java.lang.String[] game.C_100210_qa.field_101065_V
		// @0CE: bipush 16 (0x10)
		// @0D0: aaload
		// @0D1: invokevirtual java.lang.StringBuilder.append(java.lang.String)java.lang.StringBuilder
		// @0D4: iload_1
		// @0D5: invokevirtual java.lang.StringBuilder.append(int)java.lang.StringBuilder
		// @0D8: bipush 44 (0x2C)
		// @0DA: invokevirtual java.lang.StringBuilder.append(char)java.lang.StringBuilder
		// @0DD: iload_2
		// @0DE: invokevirtual java.lang.StringBuilder.append(int)java.lang.StringBuilder
		// @0E1: bipush 44 (0x2C)
		// @0E3: invokevirtual java.lang.StringBuilder.append(char)java.lang.StringBuilder
		// @0E6: iload_3
		// @0E7: invokevirtual java.lang.StringBuilder.append(int)java.lang.StringBuilder
		// @0EA: bipush 44 (0x2C)
		// @0EC: invokevirtual java.lang.StringBuilder.append(char)java.lang.StringBuilder
		// @0EF: iload #4
		// @0F1: invokevirtual java.lang.StringBuilder.append(int)java.lang.StringBuilder
		// @0F4: bipush 41 (0x29)
		// @0F6: invokevirtual java.lang.StringBuilder.append(char)java.lang.StringBuilder
		// @0F9: invokevirtual java.lang.StringBuilder.toString()java.lang.String
		// @0FC: invokestatic game.C_100181_cf.func_105695_a(java.lang.Throwable, java.lang.String)game.C_100170_cm
		// @0FF: athrow
		// @100: return
	}
	
	final synchronized void func_101031_c(byte arg0)
	{
		// @00: getstatic int game.SteelSentinels.field_105275_O
		// @03: istore_3
		// @04: iload_1
		// @05: bipush -112 (0x90)
		// @07: if_icmple @14
		// @0A: aload_0
		// @0B: bipush 115 (0x73)
		// @0D: invokevirtual game.C_100210_qa.func_101028_a(byte)void
		// @10: goto @14
		// @13: athrow
		// @14: aload_0
		// @15: getfield game.C_100119_ua game.C_100210_qa.field_101057_N
		// @18: bipush 113 (0x71)
		// @1A: invokevirtual game.C_100119_ua.func_104885_d(byte)game.C_100158_da
		// @1D: checkcast game.C_100236_on
		// @20: astore_2
		// @21: aconst_null
		// @22: aload_2
		// @23: if_acmpeq @46
		// @26: aload_2
		// @27: sipush -129 (0xFF7F)
		// @2A: invokevirtual game.C_100236_on.func_100892_e(int)void
		// @2D: aload_0
		// @2E: getfield game.C_100119_ua game.C_100210_qa.field_101057_N
		// @31: bipush -120 (0x88)
		// @33: invokevirtual game.C_100119_ua.func_104894_a(int)game.C_100158_da
		// @36: checkcast game.C_100236_on
		// @39: astore_2
		// @3A: iload_3
		// @3B: ifne @6B
		// @3E: iload_3
		// @3F: ifeq @21
		// @42: goto @46
		// @45: athrow
		// @46: goto @6B
		// @49: astore_2
		// @4A: aload_2
		// @4B: new java.lang.StringBuilder
		// @4E: dup
		// @4F: invokespecial java.lang.StringBuilder.<init>()void
		// @52: getstatic java.lang.String[] game.C_100210_qa.field_101065_V
		// @55: bipush 25 (0x19)
		// @57: aaload
		// @58: invokevirtual java.lang.StringBuilder.append(java.lang.String)java.lang.StringBuilder
		// @5B: iload_1
		// @5C: invokevirtual java.lang.StringBuilder.append(int)java.lang.StringBuilder
		// @5F: bipush 41 (0x29)
		// @61: invokevirtual java.lang.StringBuilder.append(char)java.lang.StringBuilder
		// @64: invokevirtual java.lang.StringBuilder.toString()java.lang.String
		// @67: invokestatic game.C_100181_cf.func_105695_a(java.lang.Throwable, java.lang.String)game.C_100170_cm
		// @6A: athrow
		// @6B: return
	}
	
	final synchronized void func_101017_c(int arg0, byte arg1)
	{
		// @00: iload_2
		// @01: bipush -57 (0xC7)
		// @03: if_icmpeq @07
		// @06: return
		// @07: aload_0
		// @08: iload_1
		// @09: putfield int game.C_100210_qa.field_101067_P
		// @0C: goto @3A
		// @0F: astore_3
		// @10: aload_3
		// @11: new java.lang.StringBuilder
		// @14: dup
		// @15: invokespecial java.lang.StringBuilder.<init>()void
		// @18: getstatic java.lang.String[] game.C_100210_qa.field_101065_V
		// @1B: bipush 21 (0x15)
		// @1D: aaload
		// @1E: invokevirtual java.lang.StringBuilder.append(java.lang.String)java.lang.StringBuilder
		// @21: iload_1
		// @22: invokevirtual java.lang.StringBuilder.append(int)java.lang.StringBuilder
		// @25: bipush 44 (0x2C)
		// @27: invokevirtual java.lang.StringBuilder.append(char)java.lang.StringBuilder
		// @2A: iload_2
		// @2B: invokevirtual java.lang.StringBuilder.append(int)java.lang.StringBuilder
		// @2E: bipush 41 (0x29)
		// @30: invokevirtual java.lang.StringBuilder.append(char)java.lang.StringBuilder
		// @33: invokevirtual java.lang.StringBuilder.toString()java.lang.String
		// @36: invokestatic game.C_100181_cf.func_105695_a(java.lang.Throwable, java.lang.String)game.C_100170_cm
		// @39: athrow
		// @3A: return
	}
	
	final synchronized C_100261_md func_100916_d()
	{
		// @0: aconst_null
		// @1: areturn
		// @2: astore_1
		// @3: aload_1
		// @4: getstatic java.lang.String[] game.C_100210_qa.field_101065_V
		// @7: bipush 38 (0x26)
		// @9: aaload
		// @A: invokestatic game.C_100181_cf.func_105695_a(java.lang.Throwable, java.lang.String)game.C_100170_cm
		// @D: athrow
	}
	
	final synchronized void func_101028_a(byte arg0)
	{
		// @00: iload_1
		// @01: bipush 46 (0x2E)
		// @03: if_icmpgt @11
		// @06: aconst_null
		// @07: checkcast java.lang.String
		// @0A: putstatic java.lang.String game.C_100210_qa.field_101049_E
		// @0D: goto @11
		// @10: athrow
		// @11: aload_0
		// @12: sipush -14140 (0xC8C4)
		// @15: iconst_1
		// @16: invokespecial game.C_100210_qa.func_101037_a(int, boolean)void
		// @19: goto @3D
		// @1C: astore_2
		// @1D: aload_2
		// @1E: new java.lang.StringBuilder
		// @21: dup
		// @22: invokespecial java.lang.StringBuilder.<init>()void
		// @25: getstatic java.lang.String[] game.C_100210_qa.field_101065_V
		// @28: iconst_3
		// @29: aaload
		// @2A: invokevirtual java.lang.StringBuilder.append(java.lang.String)java.lang.StringBuilder
		// @2D: iload_1
		// @2E: invokevirtual java.lang.StringBuilder.append(int)java.lang.StringBuilder
		// @31: bipush 41 (0x29)
		// @33: invokevirtual java.lang.StringBuilder.append(char)java.lang.StringBuilder
		// @36: invokevirtual java.lang.StringBuilder.toString()java.lang.String
		// @39: invokestatic game.C_100181_cf.func_105695_a(java.lang.Throwable, java.lang.String)game.C_100170_cm
		// @3C: athrow
		// @3D: return
	}
	
	final boolean func_101044_b(C_100121_ud arg0, int arg1)
	{
		// @00: aload_1
		// @01: getfield game.C_100117_p game.C_100121_ud.field_100730_u
		// @04: ifnull @0B
		// @07: goto @54
		// @0A: athrow
		// @0B: aload_1
		// @0C: getfield int game.C_100121_ud.field_100733_r
		// @0F: iconst_m1
		// @10: ixor
		// @11: iconst_m1
		// @12: if_icmpgt @52
		// @15: aload_1
		// @16: iload_2
		// @17: bipush 45 (0x2D)
		// @19: ixor
		// @1A: invokevirtual game.C_100121_ud.func_100583_c(int)void
		// @1D: iconst_0
		// @1E: aload_1
		// @1F: getfield int game.C_100121_ud.field_100722_n
		// @22: if_icmpge @52
		// @25: goto @29
		// @28: athrow
		// @29: aload_0
		// @2A: getfield game.C_100121_ud[][] game.C_100210_qa.field_101078_q
		// @2D: aload_1
		// @2E: getfield int game.C_100121_ud.field_100725_m
		// @31: aaload
		// @32: aload_1
		// @33: getfield int game.C_100121_ud.field_100722_n
		// @36: aaload
		// @37: aload_1
		// @38: if_acmpeq @43
		// @3B: goto @3F
		// @3E: athrow
		// @3F: goto @52
		// @42: athrow
		// @43: aload_0
		// @44: getfield game.C_100121_ud[][] game.C_100210_qa.field_101078_q
		// @47: aload_1
		// @48: getfield int game.C_100121_ud.field_100725_m
		// @4B: aaload
		// @4C: aload_1
		// @4D: getfield int game.C_100121_ud.field_100722_n
		// @50: aconst_null
		// @51: aastore
		// @52: iconst_1
		// @53: ireturn
		// @54: iload_2
		// @55: ifeq @63
		// @58: aload_0
		// @59: iconst_0
		// @5A: bipush 126 (0x7E)
		// @5C: invokespecial game.C_100210_qa.func_101022_a(boolean, int)void
		// @5F: goto @63
		// @62: athrow
		// @63: iconst_0
		// @64: ireturn
		// @65: astore_3
		// @66: aload_3
		// @67: new java.lang.StringBuilder
		// @6A: dup
		// @6B: invokespecial java.lang.StringBuilder.<init>()void
		// @6E: getstatic java.lang.String[] game.C_100210_qa.field_101065_V
		// @71: bipush 43 (0x2B)
		// @73: aaload
		// @74: invokevirtual java.lang.StringBuilder.append(java.lang.String)java.lang.StringBuilder
		// @77: aload_1
		// @78: ifnull @84
		// @7B: getstatic java.lang.String[] game.C_100210_qa.field_101065_V
		// @7E: iconst_0
		// @7F: aaload
		// @80: goto @89
		// @83: athrow
		// @84: getstatic java.lang.String[] game.C_100210_qa.field_101065_V
		// @87: iconst_2
		// @88: aaload
		// @89: invokevirtual java.lang.StringBuilder.append(java.lang.String)java.lang.StringBuilder
		// @8C: bipush 44 (0x2C)
		// @8E: invokevirtual java.lang.StringBuilder.append(char)java.lang.StringBuilder
		// @91: iload_2
		// @92: invokevirtual java.lang.StringBuilder.append(int)java.lang.StringBuilder
		// @95: bipush 41 (0x29)
		// @97: invokevirtual java.lang.StringBuilder.append(char)java.lang.StringBuilder
		// @9A: invokevirtual java.lang.StringBuilder.toString()java.lang.String
		// @9D: invokestatic game.C_100181_cf.func_105695_a(java.lang.Throwable, java.lang.String)game.C_100170_cm
		// @A0: athrow
	}
	
	final synchronized int func_100913_a()
	{
		// @0: iconst_0
		// @1: ireturn
		// @2: astore_1
		// @3: aload_1
		// @4: getstatic java.lang.String[] game.C_100210_qa.field_101065_V
		// @7: bipush 6 (0x06)
		// @9: aaload
		// @A: invokestatic game.C_100181_cf.func_105695_a(java.lang.Throwable, java.lang.String)game.C_100170_cm
		// @D: athrow
	}
	
	final synchronized void func_101025_c(int arg0, int arg1, int arg2)
	{
		// @00: getstatic int game.SteelSentinels.field_105275_O
		// @03: istore #5
		// @05: iload_3
		// @06: sipush 8192 (0x2000)
		// @09: if_icmpeq @19
		// @0C: aload_0
		// @0D: bipush -82 (0xAE)
		// @0F: bipush 94 (0x5E)
		// @11: iconst_1
		// @12: invokespecial game.C_100210_qa.func_101016_a(int, int, boolean)void
		// @15: goto @19
		// @18: athrow
		// @19: iconst_0
		// @1A: iload_2
		// @1B: if_icmpgt @2E
		// @1E: aload_0
		// @1F: getfield int[] game.C_100210_qa.field_101079_p
		// @22: iload_2
		// @23: iload_1
		// @24: iastore
		// @25: iload #5
		// @27: ifeq @53
		// @2A: goto @2E
		// @2D: athrow
		// @2E: iconst_0
		// @2F: istore #4
		// @31: bipush -17 (0xEF)
		// @33: iload #4
		// @35: iconst_m1
		// @36: ixor
		// @37: if_icmpge @53
		// @3A: aload_0
		// @3B: getfield int[] game.C_100210_qa.field_101079_p
		// @3E: iload #4
		// @40: iload_1
		// @41: iastore
		// @42: iinc #4 +1
		// @45: iload #5
		// @47: ifne @8C
		// @4A: iload #5
		// @4C: ifeq @31
		// @4F: goto @53
		// @52: athrow
		// @53: goto @8C
		// @56: astore #4
		// @58: aload #4
		// @5A: new java.lang.StringBuilder
		// @5D: dup
		// @5E: invokespecial java.lang.StringBuilder.<init>()void
		// @61: getstatic java.lang.String[] game.C_100210_qa.field_101065_V
		// @64: bipush 27 (0x1B)
		// @66: aaload
		// @67: invokevirtual java.lang.StringBuilder.append(java.lang.String)java.lang.StringBuilder
		// @6A: iload_1
		// @6B: invokevirtual java.lang.StringBuilder.append(int)java.lang.StringBuilder
		// @6E: bipush 44 (0x2C)
		// @70: invokevirtual java.lang.StringBuilder.append(char)java.lang.StringBuilder
		// @73: iload_2
		// @74: invokevirtual java.lang.StringBuilder.append(int)java.lang.StringBuilder
		// @77: bipush 44 (0x2C)
		// @79: invokevirtual java.lang.StringBuilder.append(char)java.lang.StringBuilder
		// @7C: iload_3
		// @7D: invokevirtual java.lang.StringBuilder.append(int)java.lang.StringBuilder
		// @80: bipush 41 (0x29)
		// @82: invokevirtual java.lang.StringBuilder.append(char)java.lang.StringBuilder
		// @85: invokevirtual java.lang.StringBuilder.toString()java.lang.String
		// @88: invokestatic game.C_100181_cf.func_105695_a(java.lang.Throwable, java.lang.String)game.C_100170_cm
		// @8B: athrow
		// @8C: return
	}
	
	public static void func_101033_g(int arg0)
	{
		// @00: aconst_null
		// @01: putstatic java.lang.String game.C_100210_qa.field_101049_E
		// @04: aconst_null
		// @05: putstatic game.C_100302_ka[] game.C_100210_qa.field_101063_U
		// @08: aconst_null
		// @09: putstatic game.C_100302_ka game.C_100210_qa.field_101054_C
		// @0C: iload_0
		// @0D: bipush -4 (0xFC)
		// @0F: if_icmpeq @19
		// @12: aconst_null
		// @13: checkcast java.lang.String
		// @16: putstatic java.lang.String game.C_100210_qa.field_101049_E
		// @19: goto @3E
		// @1C: astore_1
		// @1D: aload_1
		// @1E: new java.lang.StringBuilder
		// @21: dup
		// @22: invokespecial java.lang.StringBuilder.<init>()void
		// @25: getstatic java.lang.String[] game.C_100210_qa.field_101065_V
		// @28: bipush 15 (0x0F)
		// @2A: aaload
		// @2B: invokevirtual java.lang.StringBuilder.append(java.lang.String)java.lang.StringBuilder
		// @2E: iload_0
		// @2F: invokevirtual java.lang.StringBuilder.append(int)java.lang.StringBuilder
		// @32: bipush 41 (0x29)
		// @34: invokevirtual java.lang.StringBuilder.append(char)java.lang.StringBuilder
		// @37: invokevirtual java.lang.StringBuilder.toString()java.lang.String
		// @3A: invokestatic game.C_100181_cf.func_105695_a(java.lang.Throwable, java.lang.String)game.C_100170_cm
		// @3D: athrow
		// @3E: return
	}
	
	static final int func_101027_h(int arg0)
	{
		// @000: getstatic game.C_100104_v game.C_100311_le.field_104714_w
		// @003: getfield int game.C_100104_v.field_104697_m
		// @006: iconst_m1
		// @007: ixor
		// @008: bipush -5 (0xFB)
		// @00A: if_icmpgt @035
		// @00D: getstatic game.C_100104_v game.C_100311_le.field_104714_w
		// @010: getfield int game.C_100104_v.field_104694_n
		// @013: iconst_m1
		// @014: ixor
		// @015: ifeq @020
		// @018: goto @01C
		// @01B: athrow
		// @01C: goto @022
		// @01F: athrow
		// @020: iconst_3
		// @021: ireturn
		// @022: getstatic game.C_100104_v game.C_100311_le.field_104714_w
		// @025: getfield int game.C_100104_v.field_104694_n
		// @028: bipush -2 (0xFE)
		// @02A: if_icmpeq @031
		// @02D: goto @033
		// @030: athrow
		// @031: iconst_4
		// @032: ireturn
		// @033: iconst_1
		// @034: ireturn
		// @035: iconst_m1
		// @036: getstatic int game.C_100055_ed.field_104239_f
		// @039: iconst_m1
		// @03A: ixor
		// @03B: if_icmpne @05B
		// @03E: getstatic game.C_100201_qj game.C_100252_pn.field_105504_l
		// @041: bipush 103 (0x67)
		// @043: getstatic int game.C_100209_qb.field_102691_Hb
		// @046: getstatic java.lang.String game.C_100260_mc.field_102244_ac
		// @049: invokevirtual game.C_100201_qj.func_105857_a(byte, int, java.lang.String)game.C_100331_ie
		// @04C: putstatic game.C_100331_ie game.C_100075_uj.field_100654_v
		// @04F: getstatic int game.C_100055_ed.field_104239_f
		// @052: iconst_1
		// @053: iadd
		// @054: putstatic int game.C_100055_ed.field_104239_f
		// @057: goto @05B
		// @05A: athrow
		// @05B: iload_0
		// @05C: getstatic int game.C_100055_ed.field_104239_f
		// @05F: if_icmpne @094
		// @062: bipush -3 (0xFD)
		// @064: getstatic game.C_100331_ie game.C_100075_uj.field_100654_v
		// @067: getfield int game.C_100331_ie.field_107293_f
		// @06A: iconst_m1
		// @06B: ixor
		// @06C: if_icmpeq @077
		// @06F: goto @073
		// @072: athrow
		// @073: goto @07E
		// @076: athrow
		// @077: iconst_m1
		// @078: bipush 42 (0x2A)
		// @07A: invokestatic game.C_100298_ke.func_103201_b(int, byte)int
		// @07D: ireturn
		// @07E: iconst_1
		// @07F: getstatic game.C_100331_ie game.C_100075_uj.field_100654_v
		// @082: getfield int game.C_100331_ie.field_107293_f
		// @085: if_icmpne @094
		// @088: getstatic int game.C_100055_ed.field_104239_f
		// @08B: iconst_1
		// @08C: iadd
		// @08D: putstatic int game.C_100055_ed.field_104239_f
		// @090: goto @094
		// @093: athrow
		// @094: bipush -3 (0xFD)
		// @096: getstatic int game.C_100055_ed.field_104239_f
		// @099: iconst_m1
		// @09A: ixor
		// @09B: if_icmpne @105
		// @09E: new game.C_100286_nl
		// @0A1: dup
		// @0A2: getstatic game.C_100331_ie game.C_100075_uj.field_100654_v
		// @0A5: getfield java.lang.Object game.C_100331_ie.field_107294_g
		// @0A8: checkcast java.net.Socket
		// @0AB: getstatic game.C_100201_qj game.C_100252_pn.field_105504_l
		// @0AE: invokespecial game.C_100286_nl.<init>(java.net.Socket, game.C_100201_qj)void
		// @0B1: putstatic game.C_100286_nl game.C_100019_wl.field_103842_d
		// @0B4: new game.C_100280_nf
		// @0B7: dup
		// @0B8: bipush 13 (0x0D)
		// @0BA: invokespecial game.C_100280_nf.<init>(int)void
		// @0BD: astore_1
		// @0BE: aload_1
		// @0BF: iconst_1
		// @0C0: getstatic int game.C_100325_id.field_101487_j
		// @0C3: getstatic int game.C_100030_gm.field_103344_G
		// @0C6: getstatic int game.C_100187_rk.field_100834_r
		// @0C9: invokestatic game.C_100244_pe.func_106365_a(game.C_100280_nf, boolean, int, int, int)void
		// @0CC: aload_1
		// @0CD: sipush 7838 (0x1E9E)
		// @0D0: bipush 15 (0x0F)
		// @0D2: invokevirtual game.C_100280_nf.func_101169_f(int, int)void
		// @0D5: aload_1
		// @0D6: getstatic int game.C_100146_bf.field_105131_m
		// @0D9: iload_0
		// @0DA: bipush -119 (0x89)
		// @0DC: iadd
		// @0DD: invokevirtual game.C_100280_nf.func_101154_d(int, int)void
		// @0E0: getstatic game.C_100286_nl game.C_100019_wl.field_103842_d
		// @0E3: iload_0
		// @0E4: bipush 123 (0x7B)
		// @0E6: iadd
		// @0E7: aload_1
		// @0E8: getfield byte[] game.C_100280_nf.field_101179_l
		// @0EB: iconst_0
		// @0EC: bipush 13 (0x0D)
		// @0EE: invokevirtual game.C_100286_nl.func_106798_a(int, byte[], int, int)void
		// @0F1: getstatic int game.C_100055_ed.field_104239_f
		// @0F4: iconst_1
		// @0F5: iadd
		// @0F6: putstatic int game.C_100055_ed.field_104239_f
		// @0F9: bipush 96 (0x60)
		// @0FB: invokestatic game.C_100198_qn.func_105828_a(byte)long
		// @0FE: ldc2_w 30000
		// @101: ladd
		// @102: putstatic long game.C_100033_gj.field_101912_Yb
		// @105: getstatic int game.C_100055_ed.field_104239_f
		// @108: iconst_m1
		// @109: ixor
		// @10A: bipush -4 (0xFC)
		// @10C: if_icmpne @159
		// @10F: iconst_m1
		// @110: getstatic game.C_100286_nl game.C_100019_wl.field_103842_d
		// @113: iconst_1
		// @114: invokevirtual game.C_100286_nl.func_106796_f(int)int
		// @117: iconst_m1
		// @118: ixor
		// @119: if_icmple @141
		// @11C: goto @120
		// @11F: athrow
		// @120: getstatic game.C_100286_nl game.C_100019_wl.field_103842_d
		// @123: iconst_0
		// @124: invokevirtual game.C_100286_nl.func_106800_b(int)int
		// @127: istore_1
		// @128: iload_1
		// @129: ifeq @133
		// @12C: iload_1
		// @12D: bipush -127 (0x81)
		// @12F: invokestatic game.C_100298_ke.func_103201_b(int, byte)int
		// @132: ireturn
		// @133: getstatic int game.C_100055_ed.field_104239_f
		// @136: iconst_1
		// @137: iadd
		// @138: putstatic int game.C_100055_ed.field_104239_f
		// @13B: getstatic int game.SteelSentinels.field_105275_O
		// @13E: ifeq @159
		// @141: bipush 124 (0x7C)
		// @143: invokestatic game.C_100198_qn.func_105828_a(byte)long
		// @146: getstatic long game.C_100033_gj.field_101912_Yb
		// @149: lcmp
		// @14A: ifle @159
		// @14D: goto @151
		// @150: athrow
		// @151: bipush -2 (0xFE)
		// @153: bipush -92 (0xA4)
		// @155: invokestatic game.C_100298_ke.func_103201_b(int, byte)int
		// @158: ireturn
		// @159: bipush -5 (0xFB)
		// @15B: getstatic int game.C_100055_ed.field_104239_f
		// @15E: iconst_m1
		// @15F: ixor
		// @160: if_icmpne @17F
		// @163: getstatic game.C_100104_v game.C_100311_le.field_104714_w
		// @166: getstatic boolean game.C_100172_ck.field_102117_Wb
		// @169: getstatic game.C_100286_nl game.C_100019_wl.field_103842_d
		// @16C: bipush -105 (0x97)
		// @16E: invokevirtual game.C_100104_v.func_104677_a(boolean, java.lang.Object, byte)void
		// @171: aconst_null
		// @172: putstatic game.C_100331_ie game.C_100075_uj.field_100654_v
		// @175: aconst_null
		// @176: putstatic game.C_100286_nl game.C_100019_wl.field_103842_d
		// @179: iconst_0
		// @17A: putstatic int game.C_100055_ed.field_104239_f
		// @17D: iconst_0
		// @17E: ireturn
		// @17F: iconst_m1
		// @180: ireturn
		// @181: astore_1
		// @182: bipush -3 (0xFD)
		// @184: bipush 117 (0x75)
		// @186: invokestatic game.C_100298_ke.func_103201_b(int, byte)int
		// @189: ireturn
		// @18A: astore_1
		// @18B: aload_1
		// @18C: new java.lang.StringBuilder
		// @18F: dup
		// @190: invokespecial java.lang.StringBuilder.<init>()void
		// @193: getstatic java.lang.String[] game.C_100210_qa.field_101065_V
		// @196: bipush 28 (0x1C)
		// @198: aaload
		// @199: invokevirtual java.lang.StringBuilder.append(java.lang.String)java.lang.StringBuilder
		// @19C: iload_0
		// @19D: invokevirtual java.lang.StringBuilder.append(int)java.lang.StringBuilder
		// @1A0: bipush 41 (0x29)
		// @1A2: invokevirtual java.lang.StringBuilder.append(char)java.lang.StringBuilder
		// @1A5: invokevirtual java.lang.StringBuilder.toString()java.lang.String
		// @1A8: invokestatic game.C_100181_cf.func_105695_a(java.lang.Throwable, java.lang.String)game.C_100170_cm
		// @1AB: athrow
	}
	
	final synchronized void func_100910_a(int[] arg0, int arg1, int arg2)
	{
		// @00: getstatic int game.SteelSentinels.field_105275_O
		// @03: istore #8
		// @05: aload_0
		// @06: getfield game.C_100014_wg game.C_100210_qa.field_101072_w
		// @09: invokevirtual game.C_100014_wg.func_103757_d()boolean
		// @0C: ifeq @A9
		// @0F: aload_0
		// @10: getfield game.C_100014_wg game.C_100210_qa.field_101072_w
		// @13: getfield int game.C_100014_wg.field_103765_g
		// @16: aload_0
		// @17: getfield int game.C_100210_qa.field_101067_P
		// @1A: imul
		// @1B: getstatic int game.C_100177_cj.field_105660_u
		// @1E: idiv
		// @1F: istore #4
		// @21: aload_0
		// @22: getfield long game.C_100210_qa.field_101076_s
		// @25: iload_3
		// @26: i2l
		// @27: iload #4
		// @29: i2l
		// @2A: lmul
		// @2B: lneg
		// @2C: lsub
		// @2D: lstore #5
		// @2F: lconst_0
		// @30: lload #5
		// @32: lneg
		// @33: aload_0
		// @34: getfield long game.C_100210_qa.field_101068_S
		// @37: ladd
		// @38: lcmp
		// @39: ifle @3F
		// @3C: goto @4A
		// @3F: aload_0
		// @40: lload #5
		// @42: putfield long game.C_100210_qa.field_101076_s
		// @45: iload #8
		// @47: ifeq @A9
		// @4A: ldc2_w -1
		// @4D: iload #4
		// @4F: i2l
		// @50: ladd
		// @51: aload_0
		// @52: getfield long game.C_100210_qa.field_101076_s
		// @55: lneg
		// @56: aload_0
		// @57: getfield long game.C_100210_qa.field_101068_S
		// @5A: ladd
		// @5B: ladd
		// @5C: iload #4
		// @5E: i2l
		// @5F: ldiv
		// @60: l2i
		// @61: istore #7
		// @63: aload_0
		// @64: dup
		// @65: getfield long game.C_100210_qa.field_101076_s
		// @68: iload #4
		// @6A: i2l
		// @6B: iload #7
		// @6D: i2l
		// @6E: lmul
		// @6F: ladd
		// @70: putfield long game.C_100210_qa.field_101076_s
		// @73: aload_0
		// @74: getfield game.C_100044_vm game.C_100210_qa.field_101051_G
		// @77: aload_1
		// @78: iload_2
		// @79: iload #7
		// @7B: invokevirtual game.C_100044_vm.func_100910_a(int[], int, int)void
		// @7E: iload_2
		// @7F: iload #7
		// @81: iadd
		// @82: istore_2
		// @83: iload_3
		// @84: iload #7
		// @86: isub
		// @87: istore_3
		// @88: aload_0
		// @89: iconst_0
		// @8A: invokespecial game.C_100210_qa.func_101019_a(boolean)void
		// @8D: aload_0
		// @8E: getfield game.C_100014_wg game.C_100210_qa.field_101072_w
		// @91: invokevirtual game.C_100014_wg.func_103757_d()boolean
		// @94: ifne @A0
		// @97: iload #8
		// @99: ifeq @A9
		// @9C: goto @A0
		// @9F: athrow
		// @A0: iload #8
		// @A2: ifeq @21
		// @A5: goto @A9
		// @A8: athrow
		// @A9: aload_0
		// @AA: getfield game.C_100044_vm game.C_100210_qa.field_101051_G
		// @AD: aload_1
		// @AE: iload_2
		// @AF: iload_3
		// @B0: invokevirtual game.C_100044_vm.func_100910_a(int[], int, int)void
		// @B3: goto @FD
		// @B6: astore #4
		// @B8: aload #4
		// @BA: new java.lang.StringBuilder
		// @BD: dup
		// @BE: invokespecial java.lang.StringBuilder.<init>()void
		// @C1: getstatic java.lang.String[] game.C_100210_qa.field_101065_V
		// @C4: bipush 35 (0x23)
		// @C6: aaload
		// @C7: invokevirtual java.lang.StringBuilder.append(java.lang.String)java.lang.StringBuilder
		// @CA: aload_1
		// @CB: ifnull @D7
		// @CE: getstatic java.lang.String[] game.C_100210_qa.field_101065_V
		// @D1: iconst_0
		// @D2: aaload
		// @D3: goto @DC
		// @D6: athrow
		// @D7: getstatic java.lang.String[] game.C_100210_qa.field_101065_V
		// @DA: iconst_2
		// @DB: aaload
		// @DC: invokevirtual java.lang.StringBuilder.append(java.lang.String)java.lang.StringBuilder
		// @DF: bipush 44 (0x2C)
		// @E1: invokevirtual java.lang.StringBuilder.append(char)java.lang.StringBuilder
		// @E4: iload_2
		// @E5: invokevirtual java.lang.StringBuilder.append(int)java.lang.StringBuilder
		// @E8: bipush 44 (0x2C)
		// @EA: invokevirtual java.lang.StringBuilder.append(char)java.lang.StringBuilder
		// @ED: iload_3
		// @EE: invokevirtual java.lang.StringBuilder.append(int)java.lang.StringBuilder
		// @F1: bipush 41 (0x29)
		// @F3: invokevirtual java.lang.StringBuilder.append(char)java.lang.StringBuilder
		// @F6: invokevirtual java.lang.StringBuilder.toString()java.lang.String
		// @F9: invokestatic game.C_100181_cf.func_105695_a(java.lang.Throwable, java.lang.String)game.C_100170_cm
		// @FC: athrow
		// @FD: return
	}
	
	private final void func_101022_a(boolean arg0, int arg1)
	{
		// @00: getstatic int game.SteelSentinels.field_105275_O
		// @03: istore #4
		// @05: iload_1
		// @06: ifne @1A
		// @09: aload_0
		// @0A: iconst_m1
		// @0B: sipush -5752 (0xE988)
		// @0E: invokespecial game.C_100210_qa.func_101015_e(int, int)void
		// @11: iload #4
		// @13: ifeq @25
		// @16: goto @1A
		// @19: athrow
		// @1A: aload_0
		// @1B: iconst_m1
		// @1C: bipush -121 (0x87)
		// @1E: invokespecial game.C_100210_qa.func_101047_b(int, byte)void
		// @21: goto @25
		// @24: athrow
		// @25: aload_0
		// @26: bipush 65 (0x41)
		// @28: iconst_m1
		// @29: invokespecial game.C_100210_qa.func_101030_a(byte, int)void
		// @2C: iconst_0
		// @2D: istore_3
		// @2E: bipush -17 (0xEF)
		// @30: iload_3
		// @31: iconst_m1
		// @32: ixor
		// @33: if_icmpge @53
		// @36: aload_0
		// @37: getfield int[] game.C_100210_qa.field_101062_K
		// @3A: iload_3
		// @3B: aload_0
		// @3C: getfield int[] game.C_100210_qa.field_101077_r
		// @3F: iload_3
		// @40: iaload
		// @41: iastore
		// @42: iinc #3 +1
		// @45: iload #4
		// @47: ifne @55
		// @4A: iload #4
		// @4C: ifeq @2E
		// @4F: goto @53
		// @52: athrow
		// @53: iconst_0
		// @54: istore_3
		// @55: iload_3
		// @56: bipush 16 (0x10)
		// @58: if_icmpge @81
		// @5B: aload_0
		// @5C: getfield int[] game.C_100210_qa.field_101052_A
		// @5F: iload_3
		// @60: bipush -128 (0x80)
		// @62: aload_0
		// @63: getfield int[] game.C_100210_qa.field_101077_r
		// @66: iload_3
		// @67: iaload
		// @68: invokestatic game.C_100256_pk.func_100449_a(int, int)int
		// @6B: iastore
		// @6C: iinc #3 +1
		// @6F: iload #4
		// @71: ifne @95
		// @74: goto @78
		// @77: athrow
		// @78: iload #4
		// @7A: ifeq @55
		// @7D: goto @81
		// @80: athrow
		// @81: iload_2
		// @82: bipush -59 (0xC5)
		// @84: if_icmplt @95
		// @87: aload_0
		// @88: bipush 62 (0x3E)
		// @8A: bipush 125 (0x7D)
		// @8C: bipush -102 (0x9A)
		// @8E: invokevirtual game.C_100210_qa.func_101025_c(int, int, int)void
		// @91: goto @95
		// @94: athrow
		// @95: goto @C2
		// @98: astore_3
		// @99: aload_3
		// @9A: new java.lang.StringBuilder
		// @9D: dup
		// @9E: invokespecial java.lang.StringBuilder.<init>()void
		// @A1: getstatic java.lang.String[] game.C_100210_qa.field_101065_V
		// @A4: iconst_4
		// @A5: aaload
		// @A6: invokevirtual java.lang.StringBuilder.append(java.lang.String)java.lang.StringBuilder
		// @A9: iload_1
		// @AA: invokevirtual java.lang.StringBuilder.append(boolean)java.lang.StringBuilder
		// @AD: bipush 44 (0x2C)
		// @AF: invokevirtual java.lang.StringBuilder.append(char)java.lang.StringBuilder
		// @B2: iload_2
		// @B3: invokevirtual java.lang.StringBuilder.append(int)java.lang.StringBuilder
		// @B6: bipush 41 (0x29)
		// @B8: invokevirtual java.lang.StringBuilder.append(char)java.lang.StringBuilder
		// @BB: invokevirtual java.lang.StringBuilder.toString()java.lang.String
		// @BE: invokestatic game.C_100181_cf.func_105695_a(java.lang.Throwable, java.lang.String)game.C_100170_cm
		// @C1: athrow
		// @C2: return
	}
	
	final boolean func_101045_a(int arg0, int arg1, int arg2, C_100121_ud arg3, int[] arg4)
	{
		// @000: getstatic int game.SteelSentinels.field_105275_O
		// @003: istore #11
		// @005: aload #4
		// @007: getstatic int game.C_100177_cj.field_105660_u
		// @00A: bipush 100 (0x64)
		// @00C: idiv
		// @00D: putfield int game.C_100121_ud.field_100727_k
		// @010: iconst_m1
		// @011: aload #4
		// @013: getfield int game.C_100121_ud.field_100733_r
		// @016: iconst_m1
		// @017: ixor
		// @018: if_icmplt @083
		// @01B: aconst_null
		// @01C: aload #4
		// @01E: getfield game.C_100117_p game.C_100121_ud.field_100730_u
		// @021: if_acmpeq @037
		// @024: goto @028
		// @027: athrow
		// @028: aload #4
		// @02A: getfield game.C_100117_p game.C_100121_ud.field_100730_u
		// @02D: invokevirtual game.C_100117_p.func_100977_f()boolean
		// @030: ifeq @083
		// @033: goto @037
		// @036: athrow
		// @037: aload #4
		// @039: iconst_0
		// @03A: invokevirtual game.C_100121_ud.func_100712_c(byte)void
		// @03D: aload #4
		// @03F: iload_3
		// @040: ldc 25751779 (0x188f0e3)
		// @042: ixor
		// @043: invokevirtual game.C_100121_ud.func_100583_c(int)void
		// @046: iconst_0
		// @047: aload #4
		// @049: getfield int game.C_100121_ud.field_100722_n
		// @04C: if_icmpge @081
		// @04F: goto @053
		// @052: athrow
		// @053: aload #4
		// @055: aload_0
		// @056: getfield game.C_100121_ud[][] game.C_100210_qa.field_101078_q
		// @059: aload #4
		// @05B: getfield int game.C_100121_ud.field_100725_m
		// @05E: aaload
		// @05F: aload #4
		// @061: getfield int game.C_100121_ud.field_100722_n
		// @064: aaload
		// @065: if_acmpne @081
		// @068: goto @06C
		// @06B: athrow
		// @06C: aload_0
		// @06D: getfield game.C_100121_ud[][] game.C_100210_qa.field_101078_q
		// @070: aload #4
		// @072: getfield int game.C_100121_ud.field_100725_m
		// @075: aaload
		// @076: aload #4
		// @078: getfield int game.C_100121_ud.field_100722_n
		// @07B: aconst_null
		// @07C: aastore
		// @07D: goto @081
		// @080: athrow
		// @081: iconst_1
		// @082: ireturn
		// @083: aload #4
		// @085: getfield int game.C_100121_ud.field_100719_C
		// @088: istore #6
		// @08A: iconst_m1
		// @08B: iload #6
		// @08D: iconst_m1
		// @08E: ixor
		// @08F: if_icmple @0C7
		// @092: iload #6
		// @094: ldc2_w 0.5
		// @097: ldc2_w 16.0
		// @09A: ldc2_w 2.0
		// @09D: aload_0
		// @09E: getfield int[] game.C_100210_qa.field_101058_O
		// @0A1: aload #4
		// @0A3: getfield int game.C_100121_ud.field_100725_m
		// @0A6: iaload
		// @0A7: i2d
		// @0A8: ldc2_w 4.921259842519685E-4
		// @0AB: dmul
		// @0AC: invokestatic java.lang.Math.pow(double, double)double
		// @0AF: dmul
		// @0B0: dadd
		// @0B1: d2i
		// @0B2: isub
		// @0B3: istore #6
		// @0B5: iconst_m1
		// @0B6: iload #6
		// @0B8: iconst_m1
		// @0B9: ixor
		// @0BA: if_icmpge @0C0
		// @0BD: iconst_0
		// @0BE: istore #6
		// @0C0: aload #4
		// @0C2: iload #6
		// @0C4: putfield int game.C_100121_ud.field_100719_C
		// @0C7: aload #4
		// @0C9: getfield game.C_100117_p game.C_100121_ud.field_100730_u
		// @0CC: aload_0
		// @0CD: aload #4
		// @0CF: bipush 126 (0x7E)
		// @0D1: invokespecial game.C_100210_qa.func_101009_a(game.C_100121_ud, int)int
		// @0D4: invokevirtual game.C_100117_p.func_100987_f(int)void
		// @0D7: aload #4
		// @0D9: getfield game.C_100132_td game.C_100121_ud.field_100738_x
		// @0DC: astore #7
		// @0DE: aload #4
		// @0E0: dup
		// @0E1: getfield int game.C_100121_ud.field_100723_o
		// @0E4: aload #7
		// @0E6: getfield int game.C_100132_td.field_104982_k
		// @0E9: iadd
		// @0EA: putfield int game.C_100121_ud.field_100723_o
		// @0ED: aload #4
		// @0EF: dup
		// @0F0: getfield int game.C_100121_ud.field_100735_p
		// @0F3: iconst_1
		// @0F4: iadd
		// @0F5: putfield int game.C_100121_ud.field_100735_p
		// @0F8: iconst_0
		// @0F9: istore #8
		// @0FB: iload_3
		// @0FC: ldc 25751758 (0x188f0ce)
		// @0FE: if_icmpeq @103
		// @101: iconst_1
		// @102: ireturn
		// @103: aload #4
		// @105: getfield int game.C_100121_ud.field_100719_C
		// @108: aload #4
		// @10A: getfield int game.C_100121_ud.field_100717_A
		// @10D: imul
		// @10E: ldc 1553304396 (0x5c958b4c)
		// @110: ishr
		// @111: bipush -60 (0xC4)
		// @113: aload #4
		// @115: getfield int game.C_100121_ud.field_100736_z
		// @118: iadd
		// @119: ldc 510121704 (0x1e67d6e8)
		// @11B: ishl
		// @11C: iadd
		// @11D: i2d
		// @11E: ldc2_w 5.086263020833333E-6
		// @121: dmul
		// @122: dstore #9
		// @124: aload #7
		// @126: getfield int game.C_100132_td.field_104971_g
		// @129: ifgt @130
		// @12C: goto @189
		// @12F: athrow
		// @130: aload #7
		// @132: getfield int game.C_100132_td.field_104974_b
		// @135: ifle @163
		// @138: aload #4
		// @13A: dup
		// @13B: getfield int game.C_100121_ud.field_100728_w
		// @13E: ldc2_w 0.5
		// @141: ldc2_w 128.0
		// @144: ldc2_w 2.0
		// @147: dload #9
		// @149: aload #7
		// @14B: getfield int game.C_100132_td.field_104974_b
		// @14E: i2d
		// @14F: dmul
		// @150: invokestatic java.lang.Math.pow(double, double)double
		// @153: dmul
		// @154: dadd
		// @155: d2i
		// @156: iadd
		// @157: putfield int game.C_100121_ud.field_100728_w
		// @15A: iload #11
		// @15C: ifeq @174
		// @15F: goto @163
		// @162: athrow
		// @163: aload #4
		// @165: dup
		// @166: getfield int game.C_100121_ud.field_100728_w
		// @169: sipush 128 (0x0080)
		// @16C: iadd
		// @16D: putfield int game.C_100121_ud.field_100728_w
		// @170: goto @174
		// @173: athrow
		// @174: ldc -819201 (0xfff37fff)
		// @176: aload #7
		// @178: getfield int game.C_100132_td.field_104971_g
		// @17B: aload #4
		// @17D: getfield int game.C_100121_ud.field_100728_w
		// @180: imul
		// @181: iconst_m1
		// @182: ixor
		// @183: if_icmplt @189
		// @186: iconst_1
		// @187: istore #8
		// @189: aload #7
		// @18B: getfield byte[] game.C_100132_td.field_104981_j
		// @18E: ifnull @257
		// @191: iconst_0
		// @192: aload #7
		// @194: getfield int game.C_100132_td.field_104983_h
		// @197: if_icmpge @1C9
		// @19A: goto @19E
		// @19D: athrow
		// @19E: aload #4
		// @1A0: dup
		// @1A1: getfield int game.C_100121_ud.field_100729_v
		// @1A4: ldc2_w 0.5
		// @1A7: ldc2_w 128.0
		// @1AA: ldc2_w 2.0
		// @1AD: aload #7
		// @1AF: getfield int game.C_100132_td.field_104983_h
		// @1B2: i2d
		// @1B3: dload #9
		// @1B5: dmul
		// @1B6: invokestatic java.lang.Math.pow(double, double)double
		// @1B9: dmul
		// @1BA: dadd
		// @1BB: d2i
		// @1BC: iadd
		// @1BD: putfield int game.C_100121_ud.field_100729_v
		// @1C0: iload #11
		// @1C2: ifeq @1DA
		// @1C5: goto @1C9
		// @1C8: athrow
		// @1C9: aload #4
		// @1CB: dup
		// @1CC: getfield int game.C_100121_ud.field_100729_v
		// @1CF: sipush 128 (0x0080)
		// @1D2: iadd
		// @1D3: putfield int game.C_100121_ud.field_100729_v
		// @1D6: goto @1DA
		// @1D9: athrow
		// @1DA: aload #4
		// @1DC: getfield int game.C_100121_ud.field_100732_s
		// @1DF: iconst_m1
		// @1E0: ixor
		// @1E1: bipush -2 (0xFE)
		// @1E3: aload #7
		// @1E5: getfield byte[] game.C_100132_td.field_104981_j
		// @1E8: arraylength
		// @1E9: iadd
		// @1EA: iconst_m1
		// @1EB: ixor
		// @1EC: if_icmple @22C
		// @1EF: aload #7
		// @1F1: getfield byte[] game.C_100132_td.field_104981_j
		// @1F4: iconst_2
		// @1F5: aload #4
		// @1F7: getfield int game.C_100121_ud.field_100732_s
		// @1FA: iadd
		// @1FB: baload
		// @1FC: sipush 255 (0x00FF)
		// @1FF: iand
		// @200: ldc 183739176 (0xaf3a328)
		// @202: ishl
		// @203: iconst_m1
		// @204: ixor
		// @205: aload #4
		// @207: getfield int game.C_100121_ud.field_100729_v
		// @20A: iconst_m1
		// @20B: ixor
		// @20C: iload #11
		// @20E: ifne @23A
		// @211: if_icmple @22C
		// @214: goto @218
		// @217: athrow
		// @218: aload #4
		// @21A: dup
		// @21B: getfield int game.C_100121_ud.field_100732_s
		// @21E: iconst_2
		// @21F: iadd
		// @220: putfield int game.C_100121_ud.field_100732_s
		// @223: iload #11
		// @225: ifeq @1DA
		// @228: goto @22C
		// @22B: athrow
		// @22C: aload #7
		// @22E: getfield byte[] game.C_100132_td.field_104981_j
		// @231: arraylength
		// @232: bipush -2 (0xFE)
		// @234: iadd
		// @235: aload #4
		// @237: getfield int game.C_100121_ud.field_100732_s
		// @23A: if_icmpne @257
		// @23D: iconst_m1
		// @23E: aload #7
		// @240: getfield byte[] game.C_100132_td.field_104981_j
		// @243: iconst_1
		// @244: aload #4
		// @246: getfield int game.C_100121_ud.field_100732_s
		// @249: iadd
		// @24A: baload
		// @24B: iconst_m1
		// @24C: ixor
		// @24D: if_icmpne @257
		// @250: goto @254
		// @253: athrow
		// @254: iconst_1
		// @255: istore #8
		// @257: aload #4
		// @259: getfield int game.C_100121_ud.field_100733_r
		// @25C: iflt @35D
		// @25F: aload #7
		// @261: getfield byte[] game.C_100132_td.field_104985_q
		// @264: ifnull @35D
		// @267: goto @26B
		// @26A: athrow
		// @26B: aload_0
		// @26C: getfield int[] game.C_100210_qa.field_101060_I
		// @26F: aload #4
		// @271: getfield int game.C_100121_ud.field_100725_m
		// @274: iaload
		// @275: iconst_1
		// @276: iand
		// @277: ifeq @282
		// @27A: goto @27E
		// @27D: athrow
		// @27E: goto @35D
		// @281: athrow
		// @282: aload #4
		// @284: getfield int game.C_100121_ud.field_100722_n
		// @287: iconst_m1
		// @288: ixor
		// @289: iconst_m1
		// @28A: if_icmpgt @2AA
		// @28D: aload_0
		// @28E: getfield game.C_100121_ud[][] game.C_100210_qa.field_101078_q
		// @291: aload #4
		// @293: getfield int game.C_100121_ud.field_100725_m
		// @296: aaload
		// @297: aload #4
		// @299: getfield int game.C_100121_ud.field_100722_n
		// @29C: aaload
		// @29D: aload #4
		// @29F: if_acmpne @2AA
		// @2A2: goto @2A6
		// @2A5: athrow
		// @2A6: goto @35D
		// @2A9: athrow
		// @2AA: aload #7
		// @2AC: getfield int game.C_100132_td.field_104973_e
		// @2AF: iconst_m1
		// @2B0: ixor
		// @2B1: iconst_m1
		// @2B2: if_icmplt @2CB
		// @2B5: aload #4
		// @2B7: dup
		// @2B8: getfield int game.C_100121_ud.field_100733_r
		// @2BB: sipush 128 (0x0080)
		// @2BE: iadd
		// @2BF: putfield int game.C_100121_ud.field_100733_r
		// @2C2: iload #11
		// @2C4: ifeq @2F1
		// @2C7: goto @2CB
		// @2CA: athrow
		// @2CB: aload #4
		// @2CD: dup
		// @2CE: getfield int game.C_100121_ud.field_100733_r
		// @2D1: ldc2_w 2.0
		// @2D4: dload #9
		// @2D6: aload #7
		// @2D8: getfield int game.C_100132_td.field_104973_e
		// @2DB: i2d
		// @2DC: dmul
		// @2DD: invokestatic java.lang.Math.pow(double, double)double
		// @2E0: ldc2_w 128.0
		// @2E3: dmul
		// @2E4: ldc2_w 0.5
		// @2E7: dadd
		// @2E8: d2i
		// @2E9: iadd
		// @2EA: putfield int game.C_100121_ud.field_100733_r
		// @2ED: goto @2F1
		// @2F0: athrow
		// @2F1: aload #4
		// @2F3: getfield int game.C_100121_ud.field_100718_B
		// @2F6: iconst_m1
		// @2F7: ixor
		// @2F8: aload #7
		// @2FA: getfield byte[] game.C_100132_td.field_104985_q
		// @2FD: arraylength
		// @2FE: bipush -2 (0xFE)
		// @300: iadd
		// @301: iconst_m1
		// @302: ixor
		// @303: if_icmple @342
		// @306: aload #4
		// @308: getfield int game.C_100121_ud.field_100733_r
		// @30B: iconst_m1
		// @30C: ixor
		// @30D: aload #7
		// @30F: getfield byte[] game.C_100132_td.field_104985_q
		// @312: aload #4
		// @314: getfield int game.C_100121_ud.field_100718_B
		// @317: iconst_2
		// @318: iadd
		// @319: baload
		// @31A: ldc 1839697512 (0x6da78e68)
		// @31C: ishl
		// @31D: ldc 65280 (0xff00)
		// @31F: iand
		// @320: iconst_m1
		// @321: ixor
		// @322: iload #11
		// @324: ifne @354
		// @327: if_icmpge @342
		// @32A: goto @32E
		// @32D: athrow
		// @32E: aload #4
		// @330: dup
		// @331: getfield int game.C_100121_ud.field_100718_B
		// @334: iconst_2
		// @335: iadd
		// @336: putfield int game.C_100121_ud.field_100718_B
		// @339: iload #11
		// @33B: ifeq @2F1
		// @33E: goto @342
		// @341: athrow
		// @342: aload #4
		// @344: getfield int game.C_100121_ud.field_100718_B
		// @347: iconst_m1
		// @348: ixor
		// @349: bipush -2 (0xFE)
		// @34B: aload #7
		// @34D: getfield byte[] game.C_100132_td.field_104985_q
		// @350: arraylength
		// @351: iadd
		// @352: iconst_m1
		// @353: ixor
		// @354: if_icmpeq @35A
		// @357: goto @35D
		// @35A: iconst_1
		// @35B: istore #8
		// @35D: iload #8
		// @35F: ifne @366
		// @362: goto @40C
		// @365: athrow
		// @366: aload #4
		// @368: getfield game.C_100117_p game.C_100121_ud.field_100730_u
		// @36B: aload #4
		// @36D: getfield int game.C_100121_ud.field_100727_k
		// @370: invokevirtual game.C_100117_p.func_100972_g(int)void
		// @373: aload #5
		// @375: ifnonnull @38A
		// @378: aload #4
		// @37A: getfield game.C_100117_p game.C_100121_ud.field_100730_u
		// @37D: iload_1
		// @37E: invokevirtual game.C_100117_p.func_100914_e(int)void
		// @381: iload #11
		// @383: ifeq @39A
		// @386: goto @38A
		// @389: athrow
		// @38A: aload #4
		// @38C: getfield game.C_100117_p game.C_100121_ud.field_100730_u
		// @38F: aload #5
		// @391: iload_2
		// @392: iload_1
		// @393: invokevirtual game.C_100117_p.func_100910_a(int[], int, int)void
		// @396: goto @39A
		// @399: athrow
		// @39A: aload #4
		// @39C: getfield game.C_100117_p game.C_100121_ud.field_100730_u
		// @39F: invokevirtual game.C_100117_p.func_100979_e()boolean
		// @3A2: ifeq @3B8
		// @3A5: aload_0
		// @3A6: getfield game.C_100044_vm game.C_100210_qa.field_101051_G
		// @3A9: getfield game.C_100026_hb game.C_100044_vm.field_100949_n
		// @3AC: aload #4
		// @3AE: getfield game.C_100117_p game.C_100121_ud.field_100730_u
		// @3B1: invokevirtual game.C_100026_hb.func_100924_b(game.C_100261_md)void
		// @3B4: goto @3B8
		// @3B7: athrow
		// @3B8: aload #4
		// @3BA: iconst_0
		// @3BB: invokevirtual game.C_100121_ud.func_100712_c(byte)void
		// @3BE: aload #4
		// @3C0: getfield int game.C_100121_ud.field_100733_r
		// @3C3: iflt @40A
		// @3C6: aload #4
		// @3C8: bipush 45 (0x2D)
		// @3CA: invokevirtual game.C_100121_ud.func_100583_c(int)void
		// @3CD: aload #4
		// @3CF: getfield int game.C_100121_ud.field_100722_n
		// @3D2: iconst_m1
		// @3D3: ixor
		// @3D4: iconst_m1
		// @3D5: if_icmpge @40A
		// @3D8: goto @3DC
		// @3DB: athrow
		// @3DC: aload_0
		// @3DD: getfield game.C_100121_ud[][] game.C_100210_qa.field_101078_q
		// @3E0: aload #4
		// @3E2: getfield int game.C_100121_ud.field_100725_m
		// @3E5: aaload
		// @3E6: aload #4
		// @3E8: getfield int game.C_100121_ud.field_100722_n
		// @3EB: aaload
		// @3EC: aload #4
		// @3EE: if_acmpne @40A
		// @3F1: goto @3F5
		// @3F4: athrow
		// @3F5: aload_0
		// @3F6: getfield game.C_100121_ud[][] game.C_100210_qa.field_101078_q
		// @3F9: aload #4
		// @3FB: getfield int game.C_100121_ud.field_100725_m
		// @3FE: aaload
		// @3FF: aload #4
		// @401: getfield int game.C_100121_ud.field_100722_n
		// @404: aconst_null
		// @405: aastore
		// @406: goto @40A
		// @409: athrow
		// @40A: iconst_1
		// @40B: ireturn
		// @40C: aload #4
		// @40E: getfield game.C_100117_p game.C_100121_ud.field_100730_u
		// @411: aload #4
		// @413: getfield int game.C_100121_ud.field_100727_k
		// @416: aload_0
		// @417: bipush 88 (0x58)
		// @419: aload #4
		// @41B: invokespecial game.C_100210_qa.func_101040_a(byte, game.C_100121_ud)int
		// @41E: aload_0
		// @41F: aload #4
		// @421: sipush -12169 (0xD077)
		// @424: invokespecial game.C_100210_qa.func_101038_c(game.C_100121_ud, int)int
		// @427: invokevirtual game.C_100117_p.func_100974_a(int, int, int)void
		// @42A: iconst_0
		// @42B: ireturn
		// @42C: astore #6
		// @42E: aload #6
		// @430: new java.lang.StringBuilder
		// @433: dup
		// @434: invokespecial java.lang.StringBuilder.<init>()void
		// @437: getstatic java.lang.String[] game.C_100210_qa.field_101065_V
		// @43A: bipush 34 (0x22)
		// @43C: aaload
		// @43D: invokevirtual java.lang.StringBuilder.append(java.lang.String)java.lang.StringBuilder
		// @440: iload_1
		// @441: invokevirtual java.lang.StringBuilder.append(int)java.lang.StringBuilder
		// @444: bipush 44 (0x2C)
		// @446: invokevirtual java.lang.StringBuilder.append(char)java.lang.StringBuilder
		// @449: iload_2
		// @44A: invokevirtual java.lang.StringBuilder.append(int)java.lang.StringBuilder
		// @44D: bipush 44 (0x2C)
		// @44F: invokevirtual java.lang.StringBuilder.append(char)java.lang.StringBuilder
		// @452: iload_3
		// @453: invokevirtual java.lang.StringBuilder.append(int)java.lang.StringBuilder
		// @456: bipush 44 (0x2C)
		// @458: invokevirtual java.lang.StringBuilder.append(char)java.lang.StringBuilder
		// @45B: aload #4
		// @45D: ifnull @469
		// @460: getstatic java.lang.String[] game.C_100210_qa.field_101065_V
		// @463: iconst_0
		// @464: aaload
		// @465: goto @46E
		// @468: athrow
		// @469: getstatic java.lang.String[] game.C_100210_qa.field_101065_V
		// @46C: iconst_2
		// @46D: aaload
		// @46E: invokevirtual java.lang.StringBuilder.append(java.lang.String)java.lang.StringBuilder
		// @471: bipush 44 (0x2C)
		// @473: invokevirtual java.lang.StringBuilder.append(char)java.lang.StringBuilder
		// @476: aload #5
		// @478: ifnull @484
		// @47B: getstatic java.lang.String[] game.C_100210_qa.field_101065_V
		// @47E: iconst_0
		// @47F: aaload
		// @480: goto @489
		// @483: athrow
		// @484: getstatic java.lang.String[] game.C_100210_qa.field_101065_V
		// @487: iconst_2
		// @488: aaload
		// @489: invokevirtual java.lang.StringBuilder.append(java.lang.String)java.lang.StringBuilder
		// @48C: bipush 41 (0x29)
		// @48E: invokevirtual java.lang.StringBuilder.append(char)java.lang.StringBuilder
		// @491: invokevirtual java.lang.StringBuilder.toString()java.lang.String
		// @494: invokestatic game.C_100181_cf.func_105695_a(java.lang.Throwable, java.lang.String)game.C_100170_cm
		// @497: athrow
	}
	
	private final void func_101015_e(int arg0, int arg1)
	{
		// @00: getstatic int game.SteelSentinels.field_105275_O
		// @03: istore #4
		// @05: iload_2
		// @06: sipush -5752 (0xE988)
		// @09: if_icmpeq @1A
		// @0C: aload_0
		// @0D: bipush 80 (0x50)
		// @0F: bipush 105 (0x69)
		// @11: bipush -111 (0x91)
		// @13: invokespecial game.C_100210_qa.func_101032_a(int, int, int)void
		// @16: goto @1A
		// @19: athrow
		// @1A: aload_0
		// @1B: getfield game.C_100044_vm game.C_100210_qa.field_101051_G
		// @1E: getfield game.C_100202_qi game.C_100044_vm.field_100943_u
		// @21: bipush 30 (0x1E)
		// @23: invokevirtual game.C_100202_qi.func_105899_c(int)game.C_100158_da
		// @26: checkcast game.C_100121_ud
		// @29: astore_3
		// @2A: aconst_null
		// @2B: aload_3
		// @2C: if_acmpeq @8A
		// @2F: iload #4
		// @31: ifne @B8
		// @34: iload_1
		// @35: iconst_m1
		// @36: ixor
		// @37: iconst_m1
		// @38: if_icmpgt @4F
		// @3B: goto @3F
		// @3E: athrow
		// @3F: iload_1
		// @40: iconst_m1
		// @41: ixor
		// @42: aload_3
		// @43: getfield int game.C_100121_ud.field_100725_m
		// @46: iconst_m1
		// @47: ixor
		// @48: if_icmpne @75
		// @4B: goto @4F
		// @4E: athrow
		// @4F: iconst_m1
		// @50: aload_3
		// @51: getfield int game.C_100121_ud.field_100733_r
		// @54: iconst_m1
		// @55: ixor
		// @56: if_icmplt @61
		// @59: goto @5D
		// @5C: athrow
		// @5D: goto @75
		// @60: athrow
		// @61: aload_0
		// @62: getfield game.C_100121_ud[][] game.C_100210_qa.field_101070_n
		// @65: aload_3
		// @66: getfield int game.C_100121_ud.field_100725_m
		// @69: aaload
		// @6A: aload_3
		// @6B: getfield int game.C_100121_ud.field_100736_z
		// @6E: aconst_null
		// @6F: aastore
		// @70: aload_3
		// @71: iconst_0
		// @72: putfield int game.C_100121_ud.field_100733_r
		// @75: aload_0
		// @76: getfield game.C_100044_vm game.C_100210_qa.field_101051_G
		// @79: getfield game.C_100202_qi game.C_100044_vm.field_100943_u
		// @7C: bipush 43 (0x2B)
		// @7E: invokevirtual game.C_100202_qi.func_105907_c(byte)game.C_100158_da
		// @81: checkcast game.C_100121_ud
		// @84: astore_3
		// @85: iload #4
		// @87: ifeq @2A
		// @8A: goto @B8
		// @8D: astore_3
		// @8E: aload_3
		// @8F: new java.lang.StringBuilder
		// @92: dup
		// @93: invokespecial java.lang.StringBuilder.<init>()void
		// @96: getstatic java.lang.String[] game.C_100210_qa.field_101065_V
		// @99: bipush 10 (0x0A)
		// @9B: aaload
		// @9C: invokevirtual java.lang.StringBuilder.append(java.lang.String)java.lang.StringBuilder
		// @9F: iload_1
		// @A0: invokevirtual java.lang.StringBuilder.append(int)java.lang.StringBuilder
		// @A3: bipush 44 (0x2C)
		// @A5: invokevirtual java.lang.StringBuilder.append(char)java.lang.StringBuilder
		// @A8: iload_2
		// @A9: invokevirtual java.lang.StringBuilder.append(int)java.lang.StringBuilder
		// @AC: bipush 41 (0x29)
		// @AE: invokevirtual java.lang.StringBuilder.append(char)java.lang.StringBuilder
		// @B1: invokevirtual java.lang.StringBuilder.toString()java.lang.String
		// @B4: invokestatic game.C_100181_cf.func_105695_a(java.lang.Throwable, java.lang.String)game.C_100170_cm
		// @B7: athrow
		// @B8: return
	}
	
	final synchronized boolean func_101043_f(int arg0)
	{
		// @00: iload_1
		// @01: bipush -48 (0xD0)
		// @03: if_icmplt @12
		// @06: aload_0
		// @07: bipush 64 (0x40)
		// @09: bipush 111 (0x6F)
		// @0B: invokespecial game.C_100210_qa.func_101047_b(int, byte)void
		// @0E: goto @12
		// @11: athrow
		// @12: aload_0
		// @13: getfield game.C_100014_wg game.C_100210_qa.field_101072_w
		// @16: invokevirtual game.C_100014_wg.func_103757_d()boolean
		// @19: ireturn
		// @1A: astore_2
		// @1B: aload_2
		// @1C: new java.lang.StringBuilder
		// @1F: dup
		// @20: invokespecial java.lang.StringBuilder.<init>()void
		// @23: getstatic java.lang.String[] game.C_100210_qa.field_101065_V
		// @26: bipush 9 (0x09)
		// @28: aaload
		// @29: invokevirtual java.lang.StringBuilder.append(java.lang.String)java.lang.StringBuilder
		// @2C: iload_1
		// @2D: invokevirtual java.lang.StringBuilder.append(int)java.lang.StringBuilder
		// @30: bipush 41 (0x29)
		// @32: invokevirtual java.lang.StringBuilder.append(char)java.lang.StringBuilder
		// @35: invokevirtual java.lang.StringBuilder.toString()java.lang.String
		// @38: invokestatic game.C_100181_cf.func_105695_a(java.lang.Throwable, java.lang.String)game.C_100170_cm
		// @3B: athrow
	}
	
	private final void func_101011_a(int arg0, int arg1, int arg2, int arg3)
	{
		// @000: getstatic int game.SteelSentinels.field_105275_O
		// @003: istore #10
		// @005: aload_0
		// @006: iload #4
		// @008: bipush 64 (0x40)
		// @00A: bipush -67 (0xBD)
		// @00C: iload_2
		// @00D: invokespecial game.C_100210_qa.func_101021_a(int, int, byte, int)void
		// @010: iconst_0
		// @011: aload_0
		// @012: getfield int[] game.C_100210_qa.field_101060_I
		// @015: iload_2
		// @016: iaload
		// @017: iconst_2
		// @018: iand
		// @019: if_icmpeq @0C9
		// @01C: aload_0
		// @01D: getfield game.C_100044_vm game.C_100210_qa.field_101051_G
		// @020: getfield game.C_100202_qi game.C_100044_vm.field_100943_u
		// @023: bipush -72 (0xB8)
		// @025: invokevirtual game.C_100202_qi.func_105906_b(int)game.C_100158_da
		// @028: checkcast game.C_100121_ud
		// @02B: astore #5
		// @02D: aload #5
		// @02F: ifnull @0C9
		// @032: aload #5
		// @034: iload #10
		// @036: ifne @0D9
		// @039: getfield int game.C_100121_ud.field_100725_m
		// @03C: iload_2
		// @03D: if_icmpne @0B3
		// @040: goto @044
		// @043: athrow
		// @044: iconst_m1
		// @045: aload #5
		// @047: getfield int game.C_100121_ud.field_100733_r
		// @04A: iconst_m1
		// @04B: ixor
		// @04C: if_icmpge @0B3
		// @04F: goto @053
		// @052: athrow
		// @053: aload_0
		// @054: getfield game.C_100121_ud[][] game.C_100210_qa.field_101070_n
		// @057: iload_2
		// @058: aaload
		// @059: aload #5
		// @05B: getfield int game.C_100121_ud.field_100736_z
		// @05E: aconst_null
		// @05F: aastore
		// @060: aload_0
		// @061: getfield game.C_100121_ud[][] game.C_100210_qa.field_101070_n
		// @064: iload_2
		// @065: aaload
		// @066: iload #4
		// @068: aload #5
		// @06A: aastore
		// @06B: aload #5
		// @06D: getfield int game.C_100121_ud.field_100719_C
		// @070: aload #5
		// @072: getfield int game.C_100121_ud.field_100717_A
		// @075: imul
		// @076: ldc 1219306732 (0x48ad24ec)
		// @078: ishr
		// @079: aload #5
		// @07B: getfield int game.C_100121_ud.field_100720_H
		// @07E: iadd
		// @07F: istore #6
		// @081: aload #5
		// @083: dup
		// @084: getfield int game.C_100121_ud.field_100720_H
		// @087: iload #4
		// @089: aload #5
		// @08B: getfield int game.C_100121_ud.field_100736_z
		// @08E: isub
		// @08F: ldc -1078098648 (0xbfbd8528)
		// @091: ishl
		// @092: iadd
		// @093: putfield int game.C_100121_ud.field_100720_H
		// @096: aload #5
		// @098: iload #4
		// @09A: putfield int game.C_100121_ud.field_100736_z
		// @09D: aload #5
		// @09F: iload #6
		// @0A1: aload #5
		// @0A3: getfield int game.C_100121_ud.field_100720_H
		// @0A6: isub
		// @0A7: putfield int game.C_100121_ud.field_100717_A
		// @0AA: aload #5
		// @0AC: sipush 4096 (0x1000)
		// @0AF: putfield int game.C_100121_ud.field_100719_C
		// @0B2: return
		// @0B3: aload_0
		// @0B4: getfield game.C_100044_vm game.C_100210_qa.field_101051_G
		// @0B7: getfield game.C_100202_qi game.C_100044_vm.field_100943_u
		// @0BA: bipush 97 (0x61)
		// @0BC: invokevirtual game.C_100202_qi.func_105898_a(byte)game.C_100158_da
		// @0BF: checkcast game.C_100121_ud
		// @0C2: astore #5
		// @0C4: iload #10
		// @0C6: ifeq @02D
		// @0C9: aload_0
		// @0CA: getfield game.C_100119_ua game.C_100210_qa.field_101057_N
		// @0CD: aload_0
		// @0CE: getfield int[] game.C_100210_qa.field_101062_K
		// @0D1: iload_2
		// @0D2: iaload
		// @0D3: i2l
		// @0D4: bipush 93 (0x5D)
		// @0D6: invokevirtual game.C_100119_ua.func_104891_a(long, int)game.C_100158_da
		// @0D9: checkcast game.C_100236_on
		// @0DC: astore #5
		// @0DE: aload #5
		// @0E0: ifnonnull @0E4
		// @0E3: return
		// @0E4: aload #5
		// @0E6: getfield game.C_100214_al[] game.C_100236_on.field_100901_w
		// @0E9: iload #4
		// @0EB: aaload
		// @0EC: astore #6
		// @0EE: aload #6
		// @0F0: ifnonnull @0F4
		// @0F3: return
		// @0F4: bipush 20 (0x14)
		// @0F6: bipush -50 (0xCE)
		// @0F8: iload_1
		// @0F9: isub
		// @0FA: bipush 36 (0x24)
		// @0FC: idiv
		// @0FD: idiv
		// @0FE: istore #8
		// @100: new game.C_100121_ud
		// @103: dup
		// @104: invokespecial game.C_100121_ud.<init>()void
		// @107: astore #7
		// @109: aload #7
		// @10B: aload #6
		// @10D: putfield game.C_100214_al game.C_100121_ud.field_100731_t
		// @110: aload #7
		// @112: aload #5
		// @114: putfield game.C_100236_on game.C_100121_ud.field_100726_j
		// @117: aload #7
		// @119: iload_2
		// @11A: putfield int game.C_100121_ud.field_100725_m
		// @11D: aload #7
		// @11F: aload #5
		// @121: getfield game.C_100132_td[] game.C_100236_on.field_100905_s
		// @124: iload #4
		// @126: aaload
		// @127: putfield game.C_100132_td game.C_100121_ud.field_100738_x
		// @12A: aload #7
		// @12C: aload #5
		// @12E: getfield byte[] game.C_100236_on.field_100903_u
		// @131: iload #4
		// @133: baload
		// @134: putfield int game.C_100121_ud.field_100722_n
		// @137: aload #7
		// @139: iload #4
		// @13B: putfield int game.C_100121_ud.field_100736_z
		// @13E: aload #7
		// @140: iload_3
		// @141: iload_3
		// @142: aload #5
		// @144: getfield int game.C_100236_on.field_100895_n
		// @147: imul
		// @148: imul
		// @149: aload #5
		// @14B: getfield byte[] game.C_100236_on.field_100902_v
		// @14E: iload #4
		// @150: baload
		// @151: imul
		// @152: sipush -1024 (0xFC00)
		// @155: isub
		// @156: ldc 1905980395 (0x719af3eb)
		// @158: ishr
		// @159: putfield int game.C_100121_ud.field_100724_l
		// @15C: aload #7
		// @15E: aload #5
		// @160: getfield byte[] game.C_100236_on.field_100904_t
		// @163: iload #4
		// @165: baload
		// @166: sipush 255 (0x00FF)
		// @169: iand
		// @16A: putfield int game.C_100121_ud.field_100737_y
		// @16D: aload #7
		// @16F: sipush 32767 (0x7FFF)
		// @172: aload #5
		// @174: getfield short[] game.C_100236_on.field_100907_q
		// @177: iload #4
		// @179: saload
		// @17A: iand
		// @17B: ineg
		// @17C: iload #4
		// @17E: ldc -401708536 (0xe80e6a08)
		// @180: ishl
		// @181: iadd
		// @182: putfield int game.C_100121_ud.field_100720_H
		// @185: aload #7
		// @187: iconst_0
		// @188: putfield int game.C_100121_ud.field_100732_s
		// @18B: aload #7
		// @18D: iconst_0
		// @18E: putfield int game.C_100121_ud.field_100729_v
		// @191: aload #7
		// @193: iconst_0
		// @194: putfield int game.C_100121_ud.field_100718_B
		// @197: aload #7
		// @199: iconst_m1
		// @19A: putfield int game.C_100121_ud.field_100733_r
		// @19D: aload #7
		// @19F: iconst_0
		// @1A0: putfield int game.C_100121_ud.field_100728_w
		// @1A3: iconst_m1
		// @1A4: aload_0
		// @1A5: getfield int[] game.C_100210_qa.field_101059_H
		// @1A8: iload_2
		// @1A9: iaload
		// @1AA: iconst_m1
		// @1AB: ixor
		// @1AC: if_icmpeq @1EE
		// @1AF: aload #7
		// @1B1: aload #6
		// @1B3: aload_0
		// @1B4: aload #7
		// @1B6: bipush 54 (0x36)
		// @1B8: invokespecial game.C_100210_qa.func_101009_a(game.C_100121_ud, int)int
		// @1BB: iconst_0
		// @1BC: aload_0
		// @1BD: aload #7
		// @1BF: sipush -12169 (0xD077)
		// @1C2: invokespecial game.C_100210_qa.func_101038_c(game.C_100121_ud, int)int
		// @1C5: invokestatic game.C_100117_p.func_100978_a(game.C_100214_al, int, int, int)game.C_100117_p
		// @1C8: putfield game.C_100117_p game.C_100121_ud.field_100730_u
		// @1CB: aload_0
		// @1CC: iconst_0
		// @1CD: aload #5
		// @1CF: getfield short[] game.C_100236_on.field_100907_q
		// @1D2: iload #4
		// @1D4: saload
		// @1D5: if_icmple @1E1
		// @1D8: goto @1DC
		// @1DB: athrow
		// @1DC: iconst_1
		// @1DD: goto @1E2
		// @1E0: athrow
		// @1E1: iconst_0
		// @1E2: aload #7
		// @1E4: bipush 94 (0x5E)
		// @1E6: invokevirtual game.C_100210_qa.func_101046_a(boolean, game.C_100121_ud, int)void
		// @1E9: iload #10
		// @1EB: ifeq @215
		// @1EE: aload #7
		// @1F0: aload #6
		// @1F2: aload_0
		// @1F3: aload #7
		// @1F5: bipush 75 (0x4B)
		// @1F7: invokespecial game.C_100210_qa.func_101009_a(game.C_100121_ud, int)int
		// @1FA: aload_0
		// @1FB: bipush 88 (0x58)
		// @1FD: aload #7
		// @1FF: invokespecial game.C_100210_qa.func_101040_a(byte, game.C_100121_ud)int
		// @202: aload_0
		// @203: aload #7
		// @205: sipush -12169 (0xD077)
		// @208: invokespecial game.C_100210_qa.func_101038_c(game.C_100121_ud, int)int
		// @20B: invokestatic game.C_100117_p.func_100978_a(game.C_100214_al, int, int, int)game.C_100117_p
		// @20E: putfield game.C_100117_p game.C_100121_ud.field_100730_u
		// @211: goto @215
		// @214: athrow
		// @215: iconst_m1
		// @216: aload #5
		// @218: getfield short[] game.C_100236_on.field_100907_q
		// @21B: iload #4
		// @21D: saload
		// @21E: iconst_m1
		// @21F: ixor
		// @220: if_icmplt @227
		// @223: goto @230
		// @226: athrow
		// @227: aload #7
		// @229: getfield game.C_100117_p game.C_100121_ud.field_100730_u
		// @22C: iconst_m1
		// @22D: invokevirtual game.C_100117_p.func_100966_j(int)void
		// @230: iconst_m1
		// @231: aload #7
		// @233: getfield int game.C_100121_ud.field_100722_n
		// @236: iconst_m1
		// @237: ixor
		// @238: if_icmpge @23F
		// @23B: goto @283
		// @23E: athrow
		// @23F: aload_0
		// @240: getfield game.C_100121_ud[][] game.C_100210_qa.field_101078_q
		// @243: iload_2
		// @244: aaload
		// @245: aload #7
		// @247: getfield int game.C_100121_ud.field_100722_n
		// @24A: aaload
		// @24B: astore #9
		// @24D: aload #9
		// @24F: ifnull @275
		// @252: aload #9
		// @254: getfield int game.C_100121_ud.field_100733_r
		// @257: iflt @262
		// @25A: goto @25E
		// @25D: athrow
		// @25E: goto @275
		// @261: athrow
		// @262: aload_0
		// @263: getfield game.C_100121_ud[][] game.C_100210_qa.field_101070_n
		// @266: iload_2
		// @267: aaload
		// @268: aload #9
		// @26A: getfield int game.C_100121_ud.field_100736_z
		// @26D: aconst_null
		// @26E: aastore
		// @26F: aload #9
		// @271: iconst_0
		// @272: putfield int game.C_100121_ud.field_100733_r
		// @275: aload_0
		// @276: getfield game.C_100121_ud[][] game.C_100210_qa.field_101078_q
		// @279: iload_2
		// @27A: aaload
		// @27B: aload #7
		// @27D: getfield int game.C_100121_ud.field_100722_n
		// @280: aload #7
		// @282: aastore
		// @283: aload_0
		// @284: getfield game.C_100044_vm game.C_100210_qa.field_101051_G
		// @287: getfield game.C_100202_qi game.C_100044_vm.field_100943_u
		// @28A: bipush 125 (0x7D)
		// @28C: aload #7
		// @28E: invokevirtual game.C_100202_qi.func_105901_a(int, game.C_100158_da)void
		// @291: aload_0
		// @292: getfield game.C_100121_ud[][] game.C_100210_qa.field_101070_n
		// @295: iload_2
		// @296: aaload
		// @297: iload #4
		// @299: aload #7
		// @29B: aastore
		// @29C: goto @2DF
		// @29F: astore #5
		// @2A1: aload #5
		// @2A3: new java.lang.StringBuilder
		// @2A6: dup
		// @2A7: invokespecial java.lang.StringBuilder.<init>()void
		// @2AA: getstatic java.lang.String[] game.C_100210_qa.field_101065_V
		// @2AD: bipush 37 (0x25)
		// @2AF: aaload
		// @2B0: invokevirtual java.lang.StringBuilder.append(java.lang.String)java.lang.StringBuilder
		// @2B3: iload_1
		// @2B4: invokevirtual java.lang.StringBuilder.append(int)java.lang.StringBuilder
		// @2B7: bipush 44 (0x2C)
		// @2B9: invokevirtual java.lang.StringBuilder.append(char)java.lang.StringBuilder
		// @2BC: iload_2
		// @2BD: invokevirtual java.lang.StringBuilder.append(int)java.lang.StringBuilder
		// @2C0: bipush 44 (0x2C)
		// @2C2: invokevirtual java.lang.StringBuilder.append(char)java.lang.StringBuilder
		// @2C5: iload_3
		// @2C6: invokevirtual java.lang.StringBuilder.append(int)java.lang.StringBuilder
		// @2C9: bipush 44 (0x2C)
		// @2CB: invokevirtual java.lang.StringBuilder.append(char)java.lang.StringBuilder
		// @2CE: iload #4
		// @2D0: invokevirtual java.lang.StringBuilder.append(int)java.lang.StringBuilder
		// @2D3: bipush 41 (0x29)
		// @2D5: invokevirtual java.lang.StringBuilder.append(char)java.lang.StringBuilder
		// @2D8: invokevirtual java.lang.StringBuilder.toString()java.lang.String
		// @2DB: invokestatic game.C_100181_cf.func_105695_a(java.lang.Throwable, java.lang.String)game.C_100170_cm
		// @2DE: athrow
		// @2DF: return
	}
	
	private final void func_101019_a(boolean arg0)
	{
		// @000: getstatic int game.SteelSentinels.field_105275_O
		// @003: istore #7
		// @005: aload_0
		// @006: getfield int game.C_100210_qa.field_101048_D
		// @009: istore_2
		// @00A: aload_0
		// @00B: getfield int game.C_100210_qa.field_101056_M
		// @00E: istore_3
		// @00F: aload_0
		// @010: getfield long game.C_100210_qa.field_101068_S
		// @013: lstore #4
		// @015: aconst_null
		// @016: aload_0
		// @017: getfield game.C_100002_gf game.C_100210_qa.field_101082_x
		// @01A: if_acmpeq @049
		// @01D: iload_3
		// @01E: iconst_m1
		// @01F: ixor
		// @020: aload_0
		// @021: getfield int game.C_100210_qa.field_101080_z
		// @024: iconst_m1
		// @025: ixor
		// @026: if_icmpeq @031
		// @029: goto @02D
		// @02C: athrow
		// @02D: goto @049
		// @030: athrow
		// @031: aload_0
		// @032: bipush 71 (0x47)
		// @034: aload_0
		// @035: getfield boolean game.C_100210_qa.field_101050_F
		// @038: aload_0
		// @039: getfield boolean game.C_100210_qa.field_101055_L
		// @03C: aload_0
		// @03D: getfield game.C_100002_gf game.C_100210_qa.field_101082_x
		// @040: invokespecial game.C_100210_qa.func_101014_a(byte, boolean, boolean, game.C_100002_gf)void
		// @043: aload_0
		// @044: iconst_0
		// @045: invokespecial game.C_100210_qa.func_101019_a(boolean)void
		// @048: return
		// @049: iload_3
		// @04A: iconst_m1
		// @04B: ixor
		// @04C: aload_0
		// @04D: getfield int game.C_100210_qa.field_101056_M
		// @050: iconst_m1
		// @051: ixor
		// @052: if_icmpne @13F
		// @055: aload_0
		// @056: getfield game.C_100014_wg game.C_100210_qa.field_101072_w
		// @059: getfield int[] game.C_100014_wg.field_103768_b
		// @05C: iload_2
		// @05D: iaload
		// @05E: iconst_m1
		// @05F: ixor
		// @060: iload_3
		// @061: iconst_m1
		// @062: ixor
		// @063: iload #7
		// @065: ifne @173
		// @068: if_icmpne @11E
		// @06B: aload_0
		// @06C: getfield game.C_100014_wg game.C_100210_qa.field_101072_w
		// @06F: iload_2
		// @070: invokevirtual game.C_100014_wg.func_103756_c(int)void
		// @073: aload_0
		// @074: getfield game.C_100014_wg game.C_100210_qa.field_101072_w
		// @077: iload_2
		// @078: invokevirtual game.C_100014_wg.func_103760_d(int)int
		// @07B: istore #6
		// @07D: iconst_1
		// @07E: iload #6
		// @080: iload #7
		// @082: ifne @052
		// @085: if_icmpeq @08B
		// @088: goto @0F3
		// @08B: aload_0
		// @08C: getfield game.C_100014_wg game.C_100210_qa.field_101072_w
		// @08F: invokevirtual game.C_100014_wg.func_103759_b()void
		// @092: aload_0
		// @093: getfield game.C_100014_wg game.C_100210_qa.field_101072_w
		// @096: iload_2
		// @097: invokevirtual game.C_100014_wg.func_103748_b(int)void
		// @09A: aload_0
		// @09B: getfield game.C_100014_wg game.C_100210_qa.field_101072_w
		// @09E: invokevirtual game.C_100014_wg.func_103753_g()boolean
		// @0A1: ifeq @11E
		// @0A4: aload_0
		// @0A5: getfield game.C_100002_gf game.C_100210_qa.field_101082_x
		// @0A8: ifnull @0C2
		// @0AB: goto @0AF
		// @0AE: athrow
		// @0AF: aload_0
		// @0B0: aload_0
		// @0B1: getfield boolean game.C_100210_qa.field_101055_L
		// @0B4: iconst_0
		// @0B5: aload_0
		// @0B6: getfield game.C_100002_gf game.C_100210_qa.field_101082_x
		// @0B9: invokevirtual game.C_100210_qa.func_101035_a(boolean, boolean, game.C_100002_gf)void
		// @0BC: aload_0
		// @0BD: iconst_0
		// @0BE: invokespecial game.C_100210_qa.func_101019_a(boolean)void
		// @0C1: return
		// @0C2: aload_0
		// @0C3: getfield boolean game.C_100210_qa.field_101055_L
		// @0C6: ifeq @0E4
		// @0C9: iconst_0
		// @0CA: iload_3
		// @0CB: if_icmpne @0D6
		// @0CE: goto @0D2
		// @0D1: athrow
		// @0D2: goto @0E4
		// @0D5: athrow
		// @0D6: aload_0
		// @0D7: getfield game.C_100014_wg game.C_100210_qa.field_101072_w
		// @0DA: lload #4
		// @0DC: invokevirtual game.C_100014_wg.func_103761_a(long)void
		// @0DF: iload #7
		// @0E1: ifeq @11E
		// @0E4: aload_0
		// @0E5: iconst_1
		// @0E6: bipush -109 (0x93)
		// @0E8: invokespecial game.C_100210_qa.func_101022_a(boolean, int)void
		// @0EB: aload_0
		// @0EC: getfield game.C_100014_wg game.C_100210_qa.field_101072_w
		// @0EF: invokevirtual game.C_100014_wg.func_103762_c()void
		// @0F2: return
		// @0F3: iconst_0
		// @0F4: iload #6
		// @0F6: sipush 128 (0x0080)
		// @0F9: iand
		// @0FA: if_icmpeq @109
		// @0FD: aload_0
		// @0FE: iload #6
		// @100: bipush -6 (0xFA)
		// @102: invokespecial game.C_100210_qa.func_101026_d(int, int)void
		// @105: goto @109
		// @108: athrow
		// @109: aload_0
		// @10A: getfield game.C_100014_wg game.C_100210_qa.field_101072_w
		// @10D: iload_2
		// @10E: invokevirtual game.C_100014_wg.func_103751_a(int)void
		// @111: aload_0
		// @112: getfield game.C_100014_wg game.C_100210_qa.field_101072_w
		// @115: iload_2
		// @116: invokevirtual game.C_100014_wg.func_103748_b(int)void
		// @119: iload #7
		// @11B: ifeq @055
		// @11E: aload_0
		// @11F: getfield game.C_100014_wg game.C_100210_qa.field_101072_w
		// @122: invokevirtual game.C_100014_wg.func_103758_a()int
		// @125: istore_2
		// @126: aload_0
		// @127: getfield game.C_100014_wg game.C_100210_qa.field_101072_w
		// @12A: getfield int[] game.C_100014_wg.field_103768_b
		// @12D: iload_2
		// @12E: iaload
		// @12F: istore_3
		// @130: aload_0
		// @131: getfield game.C_100014_wg game.C_100210_qa.field_101072_w
		// @134: iload_3
		// @135: invokevirtual game.C_100014_wg.func_103750_f(int)long
		// @138: lstore #4
		// @13A: iload #7
		// @13C: ifeq @049
		// @13F: aload_0
		// @140: iload_3
		// @141: putfield int game.C_100210_qa.field_101056_M
		// @144: aload_0
		// @145: lload #4
		// @147: putfield long game.C_100210_qa.field_101068_S
		// @14A: iload_1
		// @14B: ifeq @15A
		// @14E: aload_0
		// @14F: aconst_null
		// @150: checkcast int[]
		// @153: putfield int[] game.C_100210_qa.field_101069_R
		// @156: goto @15A
		// @159: athrow
		// @15A: aload_0
		// @15B: iload_2
		// @15C: putfield int game.C_100210_qa.field_101048_D
		// @15F: aload_0
		// @160: getfield game.C_100002_gf game.C_100210_qa.field_101082_x
		// @163: ifnull @195
		// @166: iload_3
		// @167: iconst_m1
		// @168: ixor
		// @169: aload_0
		// @16A: getfield int game.C_100210_qa.field_101080_z
		// @16D: iconst_m1
		// @16E: ixor
		// @16F: goto @173
		// @172: athrow
		// @173: if_icmplt @179
		// @176: goto @195
		// @179: aload_0
		// @17A: iconst_m1
		// @17B: putfield int game.C_100210_qa.field_101048_D
		// @17E: aload_0
		// @17F: aload_0
		// @180: getfield int game.C_100210_qa.field_101080_z
		// @183: putfield int game.C_100210_qa.field_101056_M
		// @186: aload_0
		// @187: aload_0
		// @188: getfield game.C_100014_wg game.C_100210_qa.field_101072_w
		// @18B: aload_0
		// @18C: getfield int game.C_100210_qa.field_101056_M
		// @18F: invokevirtual game.C_100014_wg.func_103750_f(int)long
		// @192: putfield long game.C_100210_qa.field_101068_S
		// @195: goto @1B9
		// @198: astore_2
		// @199: aload_2
		// @19A: new java.lang.StringBuilder
		// @19D: dup
		// @19E: invokespecial java.lang.StringBuilder.<init>()void
		// @1A1: getstatic java.lang.String[] game.C_100210_qa.field_101065_V
		// @1A4: iconst_5
		// @1A5: aaload
		// @1A6: invokevirtual java.lang.StringBuilder.append(java.lang.String)java.lang.StringBuilder
		// @1A9: iload_1
		// @1AA: invokevirtual java.lang.StringBuilder.append(boolean)java.lang.StringBuilder
		// @1AD: bipush 41 (0x29)
		// @1AF: invokevirtual java.lang.StringBuilder.append(char)java.lang.StringBuilder
		// @1B2: invokevirtual java.lang.StringBuilder.toString()java.lang.String
		// @1B5: invokestatic game.C_100181_cf.func_105695_a(java.lang.Throwable, java.lang.String)game.C_100170_cm
		// @1B8: athrow
		// @1B9: return
	}
	
	final void func_101046_a(boolean arg0, C_100121_ud arg1, int arg2)
	{
		// @00: aload_2
		// @01: getfield game.C_100214_al game.C_100121_ud.field_100731_t
		// @04: getfield byte[] game.C_100214_al.field_100885_l
		// @07: arraylength
		// @08: istore #4
		// @0A: iload_1
		// @0B: ifeq @6C
		// @0E: aload_2
		// @0F: getfield game.C_100214_al game.C_100121_ud.field_100731_t
		// @12: getfield boolean game.C_100214_al.field_100886_m
		// @15: ifeq @6C
		// @18: goto @1C
		// @1B: athrow
		// @1C: iload #4
		// @1E: iload #4
		// @20: iadd
		// @21: aload_2
		// @22: getfield game.C_100214_al game.C_100121_ud.field_100731_t
		// @25: getfield int game.C_100214_al.field_100887_k
		// @28: isub
		// @29: istore #6
		// @2B: iload #4
		// @2D: bipush 8 (0x08)
		// @2F: ishl
		// @30: istore #4
		// @32: aload_0
		// @33: getfield int[] game.C_100210_qa.field_101059_H
		// @36: aload_2
		// @37: getfield int game.C_100121_ud.field_100725_m
		// @3A: iaload
		// @3B: i2l
		// @3C: iload #6
		// @3E: i2l
		// @3F: lmul
		// @40: ldc -510466682 (0xe192e586)
		// @42: lshr
		// @43: l2i
		// @44: istore #5
		// @46: iload #5
		// @48: iconst_m1
		// @49: ixor
		// @4A: iload #4
		// @4C: iconst_m1
		// @4D: ixor
		// @4E: if_icmpgt @66
		// @51: iload #5
		// @53: ineg
		// @54: iload #4
		// @56: iload #4
		// @58: iadd
		// @59: iconst_1
		// @5A: isub
		// @5B: iadd
		// @5C: istore #5
		// @5E: aload_2
		// @5F: getfield game.C_100117_p game.C_100121_ud.field_100730_u
		// @62: iconst_1
		// @63: invokevirtual game.C_100117_p.func_100963_a(boolean)void
		// @66: getstatic int game.SteelSentinels.field_105275_O
		// @69: ifeq @80
		// @6C: aload_0
		// @6D: getfield int[] game.C_100210_qa.field_101059_H
		// @70: aload_2
		// @71: getfield int game.C_100121_ud.field_100725_m
		// @74: iaload
		// @75: i2l
		// @76: iload #4
		// @78: i2l
		// @79: lmul
		// @7A: ldc 14308038 (0xda52c6)
		// @7C: lshr
		// @7D: l2i
		// @7E: istore #5
		// @80: iload_3
		// @81: bipush 65 (0x41)
		// @83: if_icmpge @9D
		// @86: aload_0
		// @87: bipush 107 (0x6B)
		// @89: bipush 33 (0x21)
		// @8B: bipush -23 (0xE9)
		// @8D: aconst_null
		// @8E: checkcast game.C_100121_ud
		// @91: aconst_null
		// @92: checkcast int[]
		// @95: invokevirtual game.C_100210_qa.func_101045_a(int, int, int, game.C_100121_ud, int[])boolean
		// @98: pop
		// @99: goto @9D
		// @9C: athrow
		// @9D: aload_2
		// @9E: getfield game.C_100117_p game.C_100121_ud.field_100730_u
		// @A1: iload #5
		// @A3: invokevirtual game.C_100117_p.func_100989_h(int)void
		// @A6: goto @F0
		// @A9: astore #4
		// @AB: aload #4
		// @AD: new java.lang.StringBuilder
		// @B0: dup
		// @B1: invokespecial java.lang.StringBuilder.<init>()void
		// @B4: getstatic java.lang.String[] game.C_100210_qa.field_101065_V
		// @B7: bipush 33 (0x21)
		// @B9: aaload
		// @BA: invokevirtual java.lang.StringBuilder.append(java.lang.String)java.lang.StringBuilder
		// @BD: iload_1
		// @BE: invokevirtual java.lang.StringBuilder.append(boolean)java.lang.StringBuilder
		// @C1: bipush 44 (0x2C)
		// @C3: invokevirtual java.lang.StringBuilder.append(char)java.lang.StringBuilder
		// @C6: aload_2
		// @C7: ifnull @D3
		// @CA: getstatic java.lang.String[] game.C_100210_qa.field_101065_V
		// @CD: iconst_0
		// @CE: aaload
		// @CF: goto @D8
		// @D2: athrow
		// @D3: getstatic java.lang.String[] game.C_100210_qa.field_101065_V
		// @D6: iconst_2
		// @D7: aaload
		// @D8: invokevirtual java.lang.StringBuilder.append(java.lang.String)java.lang.StringBuilder
		// @DB: bipush 44 (0x2C)
		// @DD: invokevirtual java.lang.StringBuilder.append(char)java.lang.StringBuilder
		// @E0: iload_3
		// @E1: invokevirtual java.lang.StringBuilder.append(int)java.lang.StringBuilder
		// @E4: bipush 41 (0x29)
		// @E6: invokevirtual java.lang.StringBuilder.append(char)java.lang.StringBuilder
		// @E9: invokevirtual java.lang.StringBuilder.toString()java.lang.String
		// @EC: invokestatic game.C_100181_cf.func_105695_a(java.lang.Throwable, java.lang.String)game.C_100170_cm
		// @EF: athrow
		// @F0: return
	}
	
	final synchronized void func_101039_b(int arg0, int arg1)
	{
		// @00: aload_0
		// @01: iload_2
		// @02: putfield int game.C_100210_qa.field_101064_T
		// @05: iload_1
		// @06: bipush -81 (0xAF)
		// @08: if_icmplt @13
		// @0B: aload_0
		// @0C: aconst_null
		// @0D: checkcast game.C_100119_ua
		// @10: putfield game.C_100119_ua game.C_100210_qa.field_101057_N
		// @13: goto @41
		// @16: astore_3
		// @17: aload_3
		// @18: new java.lang.StringBuilder
		// @1B: dup
		// @1C: invokespecial java.lang.StringBuilder.<init>()void
		// @1F: getstatic java.lang.String[] game.C_100210_qa.field_101065_V
		// @22: bipush 40 (0x28)
		// @24: aaload
		// @25: invokevirtual java.lang.StringBuilder.append(java.lang.String)java.lang.StringBuilder
		// @28: iload_1
		// @29: invokevirtual java.lang.StringBuilder.append(int)java.lang.StringBuilder
		// @2C: bipush 44 (0x2C)
		// @2E: invokevirtual java.lang.StringBuilder.append(char)java.lang.StringBuilder
		// @31: iload_2
		// @32: invokevirtual java.lang.StringBuilder.append(int)java.lang.StringBuilder
		// @35: bipush 41 (0x29)
		// @37: invokevirtual java.lang.StringBuilder.append(char)java.lang.StringBuilder
		// @3A: invokevirtual java.lang.StringBuilder.toString()java.lang.String
		// @3D: invokestatic game.C_100181_cf.func_105695_a(java.lang.Throwable, java.lang.String)game.C_100170_cm
		// @40: athrow
		// @41: return
	}
	
	private final void func_101042_a(int arg0, byte arg1, int arg2)
	{
		// @00: iload_2
		// @01: bipush 114 (0x72)
		// @03: if_icmpge @0D
		// @06: aload_0
		// @07: ldc2_w -89
		// @0A: putfield long game.C_100210_qa.field_101076_s
		// @0D: goto @46
		// @10: astore #4
		// @12: aload #4
		// @14: new java.lang.StringBuilder
		// @17: dup
		// @18: invokespecial java.lang.StringBuilder.<init>()void
		// @1B: getstatic java.lang.String[] game.C_100210_qa.field_101065_V
		// @1E: bipush 14 (0x0E)
		// @20: aaload
		// @21: invokevirtual java.lang.StringBuilder.append(java.lang.String)java.lang.StringBuilder
		// @24: iload_1
		// @25: invokevirtual java.lang.StringBuilder.append(int)java.lang.StringBuilder
		// @28: bipush 44 (0x2C)
		// @2A: invokevirtual java.lang.StringBuilder.append(char)java.lang.StringBuilder
		// @2D: iload_2
		// @2E: invokevirtual java.lang.StringBuilder.append(int)java.lang.StringBuilder
		// @31: bipush 44 (0x2C)
		// @33: invokevirtual java.lang.StringBuilder.append(char)java.lang.StringBuilder
		// @36: iload_3
		// @37: invokevirtual java.lang.StringBuilder.append(int)java.lang.StringBuilder
		// @3A: bipush 41 (0x29)
		// @3C: invokevirtual java.lang.StringBuilder.append(char)java.lang.StringBuilder
		// @3F: invokevirtual java.lang.StringBuilder.toString()java.lang.String
		// @42: invokestatic game.C_100181_cf.func_105695_a(java.lang.Throwable, java.lang.String)game.C_100170_cm
		// @45: athrow
		// @46: return
	}
	
	private final void func_101026_d(int arg0, int arg1)
	{
		// @000: getstatic int game.SteelSentinels.field_105275_O
		// @003: istore #8
		// @005: sipush 240 (0x00F0)
		// @008: iload_1
		// @009: iand
		// @00A: istore_3
		// @00B: sipush 128 (0x0080)
		// @00E: iload_3
		// @00F: if_icmpeq @016
		// @012: goto @03C
		// @015: athrow
		// @016: bipush 15 (0x0F)
		// @018: iload_1
		// @019: iand
		// @01A: istore #4
		// @01C: iload_1
		// @01D: sipush 32653 (0x7F8D)
		// @020: iand
		// @021: ldc -615335832 (0xdb52b868)
		// @023: ishr
		// @024: istore #5
		// @026: iload_1
		// @027: ldc 1546937520 (0x5c3464b0)
		// @029: ishr
		// @02A: bipush 127 (0x7F)
		// @02C: iand
		// @02D: istore #6
		// @02F: aload_0
		// @030: iload #5
		// @032: iload #6
		// @034: bipush -111 (0x91)
		// @036: iload #4
		// @038: invokespecial game.C_100210_qa.func_101021_a(int, int, byte, int)void
		// @03B: return
		// @03C: sipush -145 (0xFF6F)
		// @03F: iload_3
		// @040: iconst_m1
		// @041: ixor
		// @042: if_icmpeq @049
		// @045: goto @08F
		// @048: athrow
		// @049: bipush 15 (0x0F)
		// @04B: iload_1
		// @04C: iand
		// @04D: istore #4
		// @04F: iload_1
		// @050: ldc -807481912 (0xcfdecdc8)
		// @052: ishr
		// @053: bipush 127 (0x7F)
		// @055: iand
		// @056: istore #5
		// @058: iload_1
		// @059: ldc -482870416 (0xe337fb70)
		// @05B: ishr
		// @05C: bipush 127 (0x7F)
		// @05E: iand
		// @05F: istore #6
		// @061: iconst_m1
		// @062: iload #6
		// @064: iconst_m1
		// @065: ixor
		// @066: if_icmpgt @07E
		// @069: aload_0
		// @06A: iload #5
		// @06C: bipush 64 (0x40)
		// @06E: bipush -65 (0xBF)
		// @070: iload #4
		// @072: invokespecial game.C_100210_qa.func_101021_a(int, int, byte, int)void
		// @075: iload #8
		// @077: ifeq @08E
		// @07A: goto @07E
		// @07D: athrow
		// @07E: aload_0
		// @07F: bipush 108 (0x6C)
		// @081: iload #4
		// @083: iload #6
		// @085: iload #5
		// @087: invokespecial game.C_100210_qa.func_101011_a(int, int, int, int)void
		// @08A: goto @08E
		// @08D: athrow
		// @08E: return
		// @08F: iload_2
		// @090: bipush -6 (0xFA)
		// @092: if_icmpeq @0A1
		// @095: aload_0
		// @096: aconst_null
		// @097: checkcast int[]
		// @09A: putfield int[] game.C_100210_qa.field_101061_J
		// @09D: goto @0A1
		// @0A0: athrow
		// @0A1: sipush -161 (0xFF5F)
		// @0A4: iload_3
		// @0A5: iconst_m1
		// @0A6: ixor
		// @0A7: if_icmpne @0D0
		// @0AA: iload_1
		// @0AB: bipush 15 (0x0F)
		// @0AD: iand
		// @0AE: istore #4
		// @0B0: iload_1
		// @0B1: sipush 32646 (0x7F86)
		// @0B4: iand
		// @0B5: ldc -1689230840 (0x9b506208)
		// @0B7: ishr
		// @0B8: istore #5
		// @0BA: bipush 127 (0x7F)
		// @0BC: iload_1
		// @0BD: ldc 236772656 (0xe1cdd30)
		// @0BF: ishr
		// @0C0: iand
		// @0C1: istore #6
		// @0C3: aload_0
		// @0C4: iload #4
		// @0C6: bipush -81 (0xAF)
		// @0C8: iload #6
		// @0CA: iload #5
		// @0CC: invokespecial game.C_100210_qa.func_101010_a(int, byte, int, int)void
		// @0CF: return
		// @0D0: sipush -177 (0xFF4F)
		// @0D3: iload_3
		// @0D4: iconst_m1
		// @0D5: ixor
		// @0D6: if_icmpeq @0DD
		// @0D9: goto @563
		// @0DC: athrow
		// @0DD: bipush 15 (0x0F)
		// @0DF: iload_1
		// @0E0: iand
		// @0E1: istore #4
		// @0E3: bipush 127 (0x7F)
		// @0E5: iload_1
		// @0E6: ldc -1585539096 (0xa17e97e8)
		// @0E8: ishr
		// @0E9: iand
		// @0EA: istore #5
		// @0EC: iload_1
		// @0ED: ldc 8324151 (0x7f0437)
		// @0EF: iand
		// @0F0: ldc 705756912 (0x2a10fef0)
		// @0F2: ishr
		// @0F3: istore #6
		// @0F5: iload #5
		// @0F7: iconst_m1
		// @0F8: ixor
		// @0F9: iconst_m1
		// @0FA: if_icmpne @11A
		// @0FD: aload_0
		// @0FE: getfield int[] game.C_100210_qa.field_101052_A
		// @101: iload #4
		// @103: ldc -2080769 (0xffe03fff)
		// @105: aload_0
		// @106: getfield int[] game.C_100210_qa.field_101052_A
		// @109: iload #4
		// @10B: iaload
		// @10C: invokestatic game.C_100256_pk.func_100449_a(int, int)int
		// @10F: iload #6
		// @111: ldc 25751758 (0x188f0ce)
		// @113: ishl
		// @114: iadd
		// @115: iastore
		// @116: goto @11A
		// @119: athrow
		// @11A: bipush 32 (0x20)
		// @11C: iload #5
		// @11E: if_icmpeq @125
		// @121: goto @13F
		// @124: athrow
		// @125: aload_0
		// @126: getfield int[] game.C_100210_qa.field_101052_A
		// @129: iload #4
		// @12B: aload_0
		// @12C: getfield int[] game.C_100210_qa.field_101052_A
		// @12F: iload #4
		// @131: iaload
		// @132: sipush -16257 (0xC07F)
		// @135: invokestatic game.C_100256_pk.func_100449_a(int, int)int
		// @138: iload #6
		// @13A: ldc 1179757799 (0x4651ace7)
		// @13C: ishl
		// @13D: iadd
		// @13E: iastore
		// @13F: iload #5
		// @141: iconst_m1
		// @142: ixor
		// @143: bipush -2 (0xFE)
		// @145: if_icmpeq @14C
		// @148: goto @167
		// @14B: athrow
		// @14C: aload_0
		// @14D: getfield int[] game.C_100210_qa.field_101074_u
		// @150: iload #4
		// @152: sipush -16257 (0xC07F)
		// @155: aload_0
		// @156: getfield int[] game.C_100210_qa.field_101074_u
		// @159: iload #4
		// @15B: iaload
		// @15C: invokestatic game.C_100256_pk.func_100449_a(int, int)int
		// @15F: iload #6
		// @161: ldc -1445763001 (0xa9d36847)
		// @163: ishl
		// @164: ineg
		// @165: isub
		// @166: iastore
		// @167: iload #5
		// @169: iconst_m1
		// @16A: ixor
		// @16B: bipush -34 (0xDE)
		// @16D: if_icmpeq @174
		// @170: goto @18A
		// @173: athrow
		// @174: aload_0
		// @175: getfield int[] game.C_100210_qa.field_101074_u
		// @178: iload #4
		// @17A: iload #6
		// @17C: aload_0
		// @17D: getfield int[] game.C_100210_qa.field_101074_u
		// @180: iload #4
		// @182: iaload
		// @183: bipush -128 (0x80)
		// @185: invokestatic game.C_100256_pk.func_100449_a(int, int)int
		// @188: iadd
		// @189: iastore
		// @18A: bipush -6 (0xFA)
		// @18C: iload #5
		// @18E: iconst_m1
		// @18F: ixor
		// @190: if_icmpne @1B2
		// @193: aload_0
		// @194: getfield int[] game.C_100210_qa.field_101058_O
		// @197: iload #4
		// @199: aload_0
		// @19A: getfield int[] game.C_100210_qa.field_101058_O
		// @19D: iload #4
		// @19F: iaload
		// @1A0: sipush -16257 (0xC07F)
		// @1A3: invokestatic game.C_100256_pk.func_100449_a(int, int)int
		// @1A6: iload #6
		// @1A8: ldc 1766771463 (0x694ecb07)
		// @1AA: ishl
		// @1AB: ineg
		// @1AC: isub
		// @1AD: iastore
		// @1AE: goto @1B2
		// @1B1: athrow
		// @1B2: iload #5
		// @1B4: iconst_m1
		// @1B5: ixor
		// @1B6: bipush -38 (0xDA)
		// @1B8: if_icmpeq @1BF
		// @1BB: goto @1D5
		// @1BE: athrow
		// @1BF: aload_0
		// @1C0: getfield int[] game.C_100210_qa.field_101058_O
		// @1C3: iload #4
		// @1C5: iload #6
		// @1C7: aload_0
		// @1C8: getfield int[] game.C_100210_qa.field_101058_O
		// @1CB: iload #4
		// @1CD: iaload
		// @1CE: bipush -128 (0x80)
		// @1D0: invokestatic game.C_100256_pk.func_100449_a(int, int)int
		// @1D3: iadd
		// @1D4: iastore
		// @1D5: bipush -8 (0xF8)
		// @1D7: iload #5
		// @1D9: iconst_m1
		// @1DA: ixor
		// @1DB: if_icmpne @1FC
		// @1DE: aload_0
		// @1DF: getfield int[] game.C_100210_qa.field_101071_o
		// @1E2: iload #4
		// @1E4: iload #6
		// @1E6: ldc -1905547353 (0x8e6ba7a7)
		// @1E8: ishl
		// @1E9: aload_0
		// @1EA: getfield int[] game.C_100210_qa.field_101071_o
		// @1ED: iload #4
		// @1EF: iaload
		// @1F0: sipush -16257 (0xC07F)
		// @1F3: invokestatic game.C_100256_pk.func_100449_a(int, int)int
		// @1F6: iadd
		// @1F7: iastore
		// @1F8: goto @1FC
		// @1FB: athrow
		// @1FC: iload #5
		// @1FE: iconst_m1
		// @1FF: ixor
		// @200: bipush -40 (0xD8)
		// @202: if_icmpeq @209
		// @205: goto @220
		// @208: athrow
		// @209: aload_0
		// @20A: getfield int[] game.C_100210_qa.field_101071_o
		// @20D: iload #4
		// @20F: aload_0
		// @210: getfield int[] game.C_100210_qa.field_101071_o
		// @213: iload #4
		// @215: iaload
		// @216: bipush -128 (0x80)
		// @218: invokestatic game.C_100256_pk.func_100449_a(int, int)int
		// @21B: iload #6
		// @21D: ineg
		// @21E: isub
		// @21F: iastore
		// @220: bipush -11 (0xF5)
		// @222: iload #5
		// @224: iconst_m1
		// @225: ixor
		// @226: if_icmpne @247
		// @229: aload_0
		// @22A: getfield int[] game.C_100210_qa.field_101053_B
		// @22D: iload #4
		// @22F: iload #6
		// @231: ldc 744635015 (0x2c623a87)
		// @233: ishl
		// @234: aload_0
		// @235: getfield int[] game.C_100210_qa.field_101053_B
		// @238: iload #4
		// @23A: iaload
		// @23B: sipush -16257 (0xC07F)
		// @23E: invokestatic game.C_100256_pk.func_100449_a(int, int)int
		// @241: iadd
		// @242: iastore
		// @243: goto @247
		// @246: athrow
		// @247: iload #5
		// @249: bipush 42 (0x2A)
		// @24B: if_icmpeq @252
		// @24E: goto @268
		// @251: athrow
		// @252: aload_0
		// @253: getfield int[] game.C_100210_qa.field_101053_B
		// @256: iload #4
		// @258: iload #6
		// @25A: bipush -128 (0x80)
		// @25C: aload_0
		// @25D: getfield int[] game.C_100210_qa.field_101053_B
		// @260: iload #4
		// @262: iaload
		// @263: invokestatic game.C_100256_pk.func_100449_a(int, int)int
		// @266: iadd
		// @267: iastore
		// @268: iload #5
		// @26A: iconst_m1
		// @26B: ixor
		// @26C: bipush -12 (0xF4)
		// @26E: if_icmpne @28F
		// @271: aload_0
		// @272: getfield int[] game.C_100210_qa.field_101066_Q
		// @275: iload #4
		// @277: aload_0
		// @278: getfield int[] game.C_100210_qa.field_101066_Q
		// @27B: iload #4
		// @27D: iaload
		// @27E: sipush -16257 (0xC07F)
		// @281: invokestatic game.C_100256_pk.func_100449_a(int, int)int
		// @284: iload #6
		// @286: ldc -220906169 (0xf2d53d47)
		// @288: ishl
		// @289: iadd
		// @28A: iastore
		// @28B: goto @28F
		// @28E: athrow
		// @28F: iload #5
		// @291: iconst_m1
		// @292: ixor
		// @293: bipush -44 (0xD4)
		// @295: if_icmpeq @29C
		// @298: goto @2B2
		// @29B: athrow
		// @29C: aload_0
		// @29D: getfield int[] game.C_100210_qa.field_101066_Q
		// @2A0: iload #4
		// @2A2: iload #6
		// @2A4: aload_0
		// @2A5: getfield int[] game.C_100210_qa.field_101066_Q
		// @2A8: iload #4
		// @2AA: iaload
		// @2AB: bipush -128 (0x80)
		// @2AD: invokestatic game.C_100256_pk.func_100449_a(int, int)int
		// @2B0: iadd
		// @2B1: iastore
		// @2B2: bipush 64 (0x40)
		// @2B4: iload #5
		// @2B6: if_icmpeq @2BD
		// @2B9: goto @2F6
		// @2BC: athrow
		// @2BD: iload #6
		// @2BF: bipush 64 (0x40)
		// @2C1: if_icmplt @2DF
		// @2C4: aload_0
		// @2C5: getfield int[] game.C_100210_qa.field_101060_I
		// @2C8: iload #4
		// @2CA: aload_0
		// @2CB: getfield int[] game.C_100210_qa.field_101060_I
		// @2CE: iload #4
		// @2D0: iaload
		// @2D1: iconst_1
		// @2D2: invokestatic game.C_100116_ei.func_104117_a(int, int)int
		// @2D5: iastore
		// @2D6: iload #8
		// @2D8: ifeq @2F6
		// @2DB: goto @2DF
		// @2DE: athrow
		// @2DF: aload_0
		// @2E0: getfield int[] game.C_100210_qa.field_101060_I
		// @2E3: iload #4
		// @2E5: aload_0
		// @2E6: getfield int[] game.C_100210_qa.field_101060_I
		// @2E9: iload #4
		// @2EB: iaload
		// @2EC: bipush -2 (0xFE)
		// @2EE: invokestatic game.C_100256_pk.func_100449_a(int, int)int
		// @2F1: iastore
		// @2F2: goto @2F6
		// @2F5: athrow
		// @2F6: bipush -66 (0xBE)
		// @2F8: iload #5
		// @2FA: iconst_m1
		// @2FB: ixor
		// @2FC: if_icmpne @346
		// @2FF: iload #6
		// @301: bipush 64 (0x40)
		// @303: if_icmplt @325
		// @306: goto @30A
		// @309: athrow
		// @30A: aload_0
		// @30B: getfield int[] game.C_100210_qa.field_101060_I
		// @30E: iload #4
		// @310: aload_0
		// @311: getfield int[] game.C_100210_qa.field_101060_I
		// @314: iload #4
		// @316: iaload
		// @317: iconst_2
		// @318: invokestatic game.C_100116_ei.func_104117_a(int, int)int
		// @31B: iastore
		// @31C: iload #8
		// @31E: ifeq @346
		// @321: goto @325
		// @324: athrow
		// @325: aload_0
		// @326: iload #4
		// @328: iload_2
		// @329: bipush 107 (0x6B)
		// @32B: ixor
		// @32C: invokespecial game.C_100210_qa.func_101020_a(int, int)void
		// @32F: aload_0
		// @330: getfield int[] game.C_100210_qa.field_101060_I
		// @333: iload #4
		// @335: aload_0
		// @336: getfield int[] game.C_100210_qa.field_101060_I
		// @339: iload #4
		// @33B: iaload
		// @33C: bipush -3 (0xFD)
		// @33E: invokestatic game.C_100256_pk.func_100449_a(int, int)int
		// @341: iastore
		// @342: goto @346
		// @345: athrow
		// @346: iload #5
		// @348: iconst_m1
		// @349: ixor
		// @34A: bipush -100 (0x9C)
		// @34C: if_icmpeq @353
		// @34F: goto @36D
		// @352: athrow
		// @353: aload_0
		// @354: getfield int[] game.C_100210_qa.field_101069_R
		// @357: iload #4
		// @359: aload_0
		// @35A: getfield int[] game.C_100210_qa.field_101069_R
		// @35D: iload #4
		// @35F: iaload
		// @360: bipush 127 (0x7F)
		// @362: invokestatic game.C_100256_pk.func_100449_a(int, int)int
		// @365: iload #6
		// @367: ldc_w -258432729 (0xf098a127)
		// @36A: ishl
		// @36B: iadd
		// @36C: iastore
		// @36D: iload #5
		// @36F: bipush 98 (0x62)
		// @371: if_icmpne @38F
		// @374: aload_0
		// @375: getfield int[] game.C_100210_qa.field_101069_R
		// @378: iload #4
		// @37A: iload #6
		// @37C: aload_0
		// @37D: getfield int[] game.C_100210_qa.field_101069_R
		// @380: iload #4
		// @382: iaload
		// @383: sipush 16256 (0x3F80)
		// @386: invokestatic game.C_100256_pk.func_100449_a(int, int)int
		// @389: iadd
		// @38A: iastore
		// @38B: goto @38F
		// @38E: athrow
		// @38F: bipush 101 (0x65)
		// @391: iload #5
		// @393: if_icmpeq @39A
		// @396: goto @3B8
		// @399: athrow
		// @39A: aload_0
		// @39B: getfield int[] game.C_100210_qa.field_101069_R
		// @39E: iload #4
		// @3A0: iload #6
		// @3A2: ldc_w 1847336903 (0x6e1c1fc7)
		// @3A5: ishl
		// @3A6: bipush 127 (0x7F)
		// @3A8: aload_0
		// @3A9: getfield int[] game.C_100210_qa.field_101069_R
		// @3AC: iload #4
		// @3AE: iaload
		// @3AF: invokestatic game.C_100256_pk.func_100449_a(int, int)int
		// @3B2: sipush 16384 (0x4000)
		// @3B5: iadd
		// @3B6: iadd
		// @3B7: iastore
		// @3B8: iload #5
		// @3BA: bipush 100 (0x64)
		// @3BC: if_icmpeq @3C3
		// @3BF: goto @3DE
		// @3C2: athrow
		// @3C3: aload_0
		// @3C4: getfield int[] game.C_100210_qa.field_101069_R
		// @3C7: iload #4
		// @3C9: iload #6
		// @3CB: sipush 16384 (0x4000)
		// @3CE: aload_0
		// @3CF: getfield int[] game.C_100210_qa.field_101069_R
		// @3D2: iload #4
		// @3D4: iaload
		// @3D5: sipush 16256 (0x3F80)
		// @3D8: invokestatic game.C_100256_pk.func_100449_a(int, int)int
		// @3DB: iadd
		// @3DC: iadd
		// @3DD: iastore
		// @3DE: iload #5
		// @3E0: bipush 120 (0x78)
		// @3E2: if_icmpeq @3E9
		// @3E5: goto @3F1
		// @3E8: athrow
		// @3E9: aload_0
		// @3EA: iload #4
		// @3EC: bipush -121 (0x87)
		// @3EE: invokespecial game.C_100210_qa.func_101047_b(int, byte)void
		// @3F1: iload #5
		// @3F3: bipush 121 (0x79)
		// @3F5: if_icmpne @404
		// @3F8: aload_0
		// @3F9: bipush 65 (0x41)
		// @3FB: iload #4
		// @3FD: invokespecial game.C_100210_qa.func_101030_a(byte, int)void
		// @400: goto @404
		// @403: athrow
		// @404: iload #5
		// @406: iconst_m1
		// @407: ixor
		// @408: bipush -124 (0x84)
		// @40A: if_icmpeq @411
		// @40D: goto @41C
		// @410: athrow
		// @411: aload_0
		// @412: iload #4
		// @414: iload_2
		// @415: sipush 5746 (0x1672)
		// @418: ixor
		// @419: invokespecial game.C_100210_qa.func_101015_e(int, int)void
		// @41C: iload #5
		// @41E: bipush 6 (0x06)
		// @420: if_icmpne @455
		// @423: aload_0
		// @424: getfield int[] game.C_100210_qa.field_101069_R
		// @427: iload #4
		// @429: iaload
		// @42A: istore #7
		// @42C: sipush -16385 (0xBFFF)
		// @42F: iload #7
		// @431: iconst_m1
		// @432: ixor
		// @433: if_icmpne @455
		// @436: aload_0
		// @437: getfield int[] game.C_100210_qa.field_101061_J
		// @43A: iload #4
		// @43C: iload #6
		// @43E: ldc_w -1272732377 (0xb423a527)
		// @441: ishl
		// @442: aload_0
		// @443: getfield int[] game.C_100210_qa.field_101061_J
		// @446: iload #4
		// @448: iaload
		// @449: sipush -16257 (0xC07F)
		// @44C: invokestatic game.C_100256_pk.func_100449_a(int, int)int
		// @44F: iadd
		// @450: iastore
		// @451: goto @455
		// @454: athrow
		// @455: iload #5
		// @457: bipush 38 (0x26)
		// @459: if_icmpne @487
		// @45C: aload_0
		// @45D: getfield int[] game.C_100210_qa.field_101069_R
		// @460: iload #4
		// @462: iaload
		// @463: istore #7
		// @465: iload #7
		// @467: sipush 16384 (0x4000)
		// @46A: if_icmpeq @471
		// @46D: goto @487
		// @470: athrow
		// @471: aload_0
		// @472: getfield int[] game.C_100210_qa.field_101061_J
		// @475: iload #4
		// @477: iload #6
		// @479: bipush -128 (0x80)
		// @47B: aload_0
		// @47C: getfield int[] game.C_100210_qa.field_101061_J
		// @47F: iload #4
		// @481: iaload
		// @482: invokestatic game.C_100256_pk.func_100449_a(int, int)int
		// @485: iadd
		// @486: iastore
		// @487: bipush 16 (0x10)
		// @489: iload #5
		// @48B: if_icmpne @4AD
		// @48E: aload_0
		// @48F: getfield int[] game.C_100210_qa.field_101059_H
		// @492: iload #4
		// @494: aload_0
		// @495: getfield int[] game.C_100210_qa.field_101059_H
		// @498: iload #4
		// @49A: iaload
		// @49B: sipush -16257 (0xC07F)
		// @49E: invokestatic game.C_100256_pk.func_100449_a(int, int)int
		// @4A1: iload #6
		// @4A3: ldc_w -760551481 (0xd2aae7c7)
		// @4A6: ishl
		// @4A7: iadd
		// @4A8: iastore
		// @4A9: goto @4AD
		// @4AC: athrow
		// @4AD: iload #5
		// @4AF: bipush 48 (0x30)
		// @4B1: if_icmpne @4CE
		// @4B4: aload_0
		// @4B5: getfield int[] game.C_100210_qa.field_101059_H
		// @4B8: iload #4
		// @4BA: iload #6
		// @4BC: aload_0
		// @4BD: getfield int[] game.C_100210_qa.field_101059_H
		// @4C0: iload #4
		// @4C2: iaload
		// @4C3: bipush -128 (0x80)
		// @4C5: invokestatic game.C_100256_pk.func_100449_a(int, int)int
		// @4C8: iadd
		// @4C9: iastore
		// @4CA: goto @4CE
		// @4CD: athrow
		// @4CE: bipush 81 (0x51)
		// @4D0: iload #5
		// @4D2: if_icmpne @51D
		// @4D5: iload #6
		// @4D7: bipush 64 (0x40)
		// @4D9: if_icmpge @507
		// @4DC: goto @4E0
		// @4DF: athrow
		// @4E0: aload_0
		// @4E1: iload_2
		// @4E2: sipush 21352 (0x5368)
		// @4E5: iadd
		// @4E6: iload #4
		// @4E8: invokespecial game.C_100210_qa.func_101024_c(int, int)void
		// @4EB: aload_0
		// @4EC: getfield int[] game.C_100210_qa.field_101060_I
		// @4EF: iload #4
		// @4F1: aload_0
		// @4F2: getfield int[] game.C_100210_qa.field_101060_I
		// @4F5: iload #4
		// @4F7: iaload
		// @4F8: bipush -5 (0xFB)
		// @4FA: invokestatic game.C_100256_pk.func_100449_a(int, int)int
		// @4FD: iastore
		// @4FE: iload #8
		// @500: ifeq @51D
		// @503: goto @507
		// @506: athrow
		// @507: aload_0
		// @508: getfield int[] game.C_100210_qa.field_101060_I
		// @50B: iload #4
		// @50D: aload_0
		// @50E: getfield int[] game.C_100210_qa.field_101060_I
		// @511: iload #4
		// @513: iaload
		// @514: iconst_4
		// @515: invokestatic game.C_100116_ei.func_104117_a(int, int)int
		// @518: iastore
		// @519: goto @51D
		// @51C: athrow
		// @51D: bipush 17 (0x11)
		// @51F: iload #5
		// @521: if_icmpeq @528
		// @524: goto @541
		// @527: athrow
		// @528: aload_0
		// @529: iload #4
		// @52B: iload #6
		// @52D: ldc_w -1578856217 (0xa1e490e7)
		// @530: ishl
		// @531: aload_0
		// @532: getfield int[] game.C_100210_qa.field_101075_t
		// @535: iload #4
		// @537: iaload
		// @538: sipush -16257 (0xC07F)
		// @53B: iand
		// @53C: iadd
		// @53D: iconst_1
		// @53E: invokespecial game.C_100210_qa.func_101016_a(int, int, boolean)void
		// @541: iload #5
		// @543: iconst_m1
		// @544: ixor
		// @545: bipush -50 (0xCE)
		// @547: if_icmpeq @54E
		// @54A: goto @562
		// @54D: athrow
		// @54E: aload_0
		// @54F: iload #4
		// @551: iload #6
		// @553: aload_0
		// @554: getfield int[] game.C_100210_qa.field_101075_t
		// @557: iload #4
		// @559: iaload
		// @55A: bipush -128 (0x80)
		// @55C: iand
		// @55D: iadd
		// @55E: iconst_1
		// @55F: invokespecial game.C_100210_qa.func_101016_a(int, int, boolean)void
		// @562: return
		// @563: sipush 192 (0x00C0)
		// @566: iload_3
		// @567: if_icmpne @58D
		// @56A: iload_1
		// @56B: bipush 15 (0x0F)
		// @56D: iand
		// @56E: istore #4
		// @570: iload_1
		// @571: sipush 32569 (0x7F39)
		// @574: iand
		// @575: ldc_w 776377832 (0x2e4695e8)
		// @578: ishr
		// @579: istore #5
		// @57B: aload_0
		// @57C: iconst_1
		// @57D: iload #4
		// @57F: iload #5
		// @581: aload_0
		// @582: getfield int[] game.C_100210_qa.field_101052_A
		// @585: iload #4
		// @587: iaload
		// @588: iadd
		// @589: invokespecial game.C_100210_qa.func_101018_a(boolean, int, int)void
		// @58C: return
		// @58D: sipush -209 (0xFF2F)
		// @590: iload_3
		// @591: iconst_m1
		// @592: ixor
		// @593: if_icmpeq @59A
		// @596: goto @5B5
		// @599: athrow
		// @59A: bipush 15 (0x0F)
		// @59C: iload_1
		// @59D: iand
		// @59E: istore #4
		// @5A0: iload_1
		// @5A1: ldc_w -429441944 (0xe6673c68)
		// @5A4: ishr
		// @5A5: bipush 127 (0x7F)
		// @5A7: iand
		// @5A8: istore #5
		// @5AA: aload_0
		// @5AB: iload #4
		// @5AD: bipush 121 (0x79)
		// @5AF: iload #5
		// @5B1: invokespecial game.C_100210_qa.func_101042_a(int, byte, int)void
		// @5B4: return
		// @5B5: sipush 224 (0x00E0)
		// @5B8: iload_3
		// @5B9: if_icmpeq @5C0
		// @5BC: goto @5E5
		// @5BF: athrow
		// @5C0: bipush 15 (0x0F)
		// @5C2: iload_1
		// @5C3: iand
		// @5C4: istore #4
		// @5C6: iload_1
		// @5C7: ldc_w -1631597591 (0x9ebfcbe9)
		// @5CA: ishr
		// @5CB: sipush 16256 (0x3F80)
		// @5CE: iand
		// @5CF: sipush 32760 (0x7FF8)
		// @5D2: iload_1
		// @5D3: iand
		// @5D4: ldc_w -1991280568 (0x894f7848)
		// @5D7: ishr
		// @5D8: iadd
		// @5D9: istore #5
		// @5DB: aload_0
		// @5DC: iload #5
		// @5DE: iload #4
		// @5E0: iconst_4
		// @5E1: invokespecial game.C_100210_qa.func_101023_b(int, int, int)void
		// @5E4: return
		// @5E5: iload_1
		// @5E6: sipush 255 (0x00FF)
		// @5E9: iand
		// @5EA: istore_3
		// @5EB: iload_3
		// @5EC: iconst_m1
		// @5ED: ixor
		// @5EE: sipush -256 (0xFF00)
		// @5F1: if_icmpeq @5F8
		// @5F4: goto @600
		// @5F7: athrow
		// @5F8: aload_0
		// @5F9: iconst_1
		// @5FA: bipush -104 (0x98)
		// @5FC: invokespecial game.C_100210_qa.func_101022_a(boolean, int)void
		// @5FF: return
		// @600: goto @62E
		// @603: astore_3
		// @604: aload_3
		// @605: new java.lang.StringBuilder
		// @608: dup
		// @609: invokespecial java.lang.StringBuilder.<init>()void
		// @60C: getstatic java.lang.String[] game.C_100210_qa.field_101065_V
		// @60F: bipush 17 (0x11)
		// @611: aaload
		// @612: invokevirtual java.lang.StringBuilder.append(java.lang.String)java.lang.StringBuilder
		// @615: iload_1
		// @616: invokevirtual java.lang.StringBuilder.append(int)java.lang.StringBuilder
		// @619: bipush 44 (0x2C)
		// @61B: invokevirtual java.lang.StringBuilder.append(char)java.lang.StringBuilder
		// @61E: iload_2
		// @61F: invokevirtual java.lang.StringBuilder.append(int)java.lang.StringBuilder
		// @622: bipush 41 (0x29)
		// @624: invokevirtual java.lang.StringBuilder.append(char)java.lang.StringBuilder
		// @627: invokevirtual java.lang.StringBuilder.toString()java.lang.String
		// @62A: invokestatic game.C_100181_cf.func_105695_a(java.lang.Throwable, java.lang.String)game.C_100170_cm
		// @62D: athrow
		// @62E: return
	}
	
	private final synchronized void func_101037_a(int arg0, boolean arg1)
	{
		// @00: aload_0
		// @01: getfield game.C_100014_wg game.C_100210_qa.field_101072_w
		// @04: invokevirtual game.C_100014_wg.func_103762_c()void
		// @07: aload_0
		// @08: aconst_null
		// @09: putfield game.C_100002_gf game.C_100210_qa.field_101082_x
		// @0C: aload_0
		// @0D: iload_2
		// @0E: iload_1
		// @0F: sipush 14055 (0x36E7)
		// @12: iadd
		// @13: invokespecial game.C_100210_qa.func_101022_a(boolean, int)void
		// @16: iload_1
		// @17: sipush -14140 (0xC8C4)
		// @1A: if_icmpeq @24
		// @1D: aload_0
		// @1E: iconst_2
		// @1F: bipush 89 (0x59)
		// @21: invokevirtual game.C_100210_qa.func_101017_c(int, byte)void
		// @24: goto @52
		// @27: astore_3
		// @28: aload_3
		// @29: new java.lang.StringBuilder
		// @2C: dup
		// @2D: invokespecial java.lang.StringBuilder.<init>()void
		// @30: getstatic java.lang.String[] game.C_100210_qa.field_101065_V
		// @33: bipush 32 (0x20)
		// @35: aaload
		// @36: invokevirtual java.lang.StringBuilder.append(java.lang.String)java.lang.StringBuilder
		// @39: iload_1
		// @3A: invokevirtual java.lang.StringBuilder.append(int)java.lang.StringBuilder
		// @3D: bipush 44 (0x2C)
		// @3F: invokevirtual java.lang.StringBuilder.append(char)java.lang.StringBuilder
		// @42: iload_2
		// @43: invokevirtual java.lang.StringBuilder.append(boolean)java.lang.StringBuilder
		// @46: bipush 41 (0x29)
		// @48: invokevirtual java.lang.StringBuilder.append(char)java.lang.StringBuilder
		// @4B: invokevirtual java.lang.StringBuilder.toString()java.lang.String
		// @4E: invokestatic game.C_100181_cf.func_105695_a(java.lang.Throwable, java.lang.String)game.C_100170_cm
		// @51: athrow
		// @52: return
	}
	
	private final synchronized void func_101014_a(byte arg0, boolean arg1, boolean arg2, C_100002_gf arg3)
	{
		// @00: getstatic int game.SteelSentinels.field_105275_O
		// @03: istore #7
		// @05: aload_0
		// @06: sipush -14140 (0xC8C4)
		// @09: iload_2
		// @0A: invokespecial game.C_100210_qa.func_101037_a(int, boolean)void
		// @0D: aload_0
		// @0E: getfield game.C_100014_wg game.C_100210_qa.field_101072_w
		// @11: aload #4
		// @13: getfield byte[] game.C_100002_gf.field_103503_j
		// @16: invokevirtual game.C_100014_wg.func_103752_a(byte[])void
		// @19: aload_0
		// @1A: iload_3
		// @1B: putfield boolean game.C_100210_qa.field_101055_L
		// @1E: aload_0
		// @1F: lconst_0
		// @20: putfield long game.C_100210_qa.field_101076_s
		// @23: aload_0
		// @24: getfield game.C_100014_wg game.C_100210_qa.field_101072_w
		// @27: invokevirtual game.C_100014_wg.func_103749_e()int
		// @2A: istore #5
		// @2C: iconst_0
		// @2D: istore #6
		// @2F: iload #5
		// @31: iload #6
		// @33: if_icmple @62
		// @36: aload_0
		// @37: getfield game.C_100014_wg game.C_100210_qa.field_101072_w
		// @3A: iload #6
		// @3C: invokevirtual game.C_100014_wg.func_103756_c(int)void
		// @3F: aload_0
		// @40: getfield game.C_100014_wg game.C_100210_qa.field_101072_w
		// @43: iload #6
		// @45: invokevirtual game.C_100014_wg.func_103751_a(int)void
		// @48: aload_0
		// @49: getfield game.C_100014_wg game.C_100210_qa.field_101072_w
		// @4C: iload #6
		// @4E: invokevirtual game.C_100014_wg.func_103748_b(int)void
		// @51: iinc #6 +1
		// @54: iload #7
		// @56: ifne @98
		// @59: iload #7
		// @5B: ifeq @2F
		// @5E: goto @62
		// @61: athrow
		// @62: aload_0
		// @63: aload_0
		// @64: getfield game.C_100014_wg game.C_100210_qa.field_101072_w
		// @67: invokevirtual game.C_100014_wg.func_103758_a()int
		// @6A: putfield int game.C_100210_qa.field_101048_D
		// @6D: aload_0
		// @6E: aload_0
		// @6F: getfield game.C_100014_wg game.C_100210_qa.field_101072_w
		// @72: getfield int[] game.C_100014_wg.field_103768_b
		// @75: aload_0
		// @76: getfield int game.C_100210_qa.field_101048_D
		// @79: iaload
		// @7A: putfield int game.C_100210_qa.field_101056_M
		// @7D: bipush 41 (0x29)
		// @7F: iload_1
		// @80: bipush -33 (0xDF)
		// @82: isub
		// @83: bipush 57 (0x39)
		// @85: idiv
		// @86: idiv
		// @87: istore #6
		// @89: aload_0
		// @8A: aload_0
		// @8B: getfield game.C_100014_wg game.C_100210_qa.field_101072_w
		// @8E: aload_0
		// @8F: getfield int game.C_100210_qa.field_101056_M
		// @92: invokevirtual game.C_100014_wg.func_103750_f(int)long
		// @95: putfield long game.C_100210_qa.field_101068_S
		// @98: goto @EC
		// @9B: astore #5
		// @9D: aload #5
		// @9F: new java.lang.StringBuilder
		// @A2: dup
		// @A3: invokespecial java.lang.StringBuilder.<init>()void
		// @A6: getstatic java.lang.String[] game.C_100210_qa.field_101065_V
		// @A9: bipush 7 (0x07)
		// @AB: aaload
		// @AC: invokevirtual java.lang.StringBuilder.append(java.lang.String)java.lang.StringBuilder
		// @AF: iload_1
		// @B0: invokevirtual java.lang.StringBuilder.append(int)java.lang.StringBuilder
		// @B3: bipush 44 (0x2C)
		// @B5: invokevirtual java.lang.StringBuilder.append(char)java.lang.StringBuilder
		// @B8: iload_2
		// @B9: invokevirtual java.lang.StringBuilder.append(boolean)java.lang.StringBuilder
		// @BC: bipush 44 (0x2C)
		// @BE: invokevirtual java.lang.StringBuilder.append(char)java.lang.StringBuilder
		// @C1: iload_3
		// @C2: invokevirtual java.lang.StringBuilder.append(boolean)java.lang.StringBuilder
		// @C5: bipush 44 (0x2C)
		// @C7: invokevirtual java.lang.StringBuilder.append(char)java.lang.StringBuilder
		// @CA: aload #4
		// @CC: ifnull @D8
		// @CF: getstatic java.lang.String[] game.C_100210_qa.field_101065_V
		// @D2: iconst_0
		// @D3: aaload
		// @D4: goto @DD
		// @D7: athrow
		// @D8: getstatic java.lang.String[] game.C_100210_qa.field_101065_V
		// @DB: iconst_2
		// @DC: aaload
		// @DD: invokevirtual java.lang.StringBuilder.append(java.lang.String)java.lang.StringBuilder
		// @E0: bipush 41 (0x29)
		// @E2: invokevirtual java.lang.StringBuilder.append(char)java.lang.StringBuilder
		// @E5: invokevirtual java.lang.StringBuilder.toString()java.lang.String
		// @E8: invokestatic game.C_100181_cf.func_105695_a(java.lang.Throwable, java.lang.String)game.C_100170_cm
		// @EB: athrow
		// @EC: return
	}
	
	final synchronized C_100261_md func_100912_c()
	{
		// @00: aload_0
		// @01: getfield game.C_100044_vm game.C_100210_qa.field_101051_G
		// @04: areturn
		// @05: astore_1
		// @06: aload_1
		// @07: getstatic java.lang.String[] game.C_100210_qa.field_101065_V
		// @0A: bipush 26 (0x1A)
		// @0C: aaload
		// @0D: invokestatic game.C_100181_cf.func_105695_a(java.lang.Throwable, java.lang.String)game.C_100170_cm
		// @10: athrow
	}
	
	final synchronized void func_100914_e(int arg0)
	{
		// @00: getstatic int game.SteelSentinels.field_105275_O
		// @03: istore #6
		// @05: aload_0
		// @06: getfield game.C_100014_wg game.C_100210_qa.field_101072_w
		// @09: invokevirtual game.C_100014_wg.func_103757_d()boolean
		// @0C: ifeq @A4
		// @0F: aload_0
		// @10: getfield game.C_100014_wg game.C_100210_qa.field_101072_w
		// @13: getfield int game.C_100014_wg.field_103765_g
		// @16: aload_0
		// @17: getfield int game.C_100210_qa.field_101067_P
		// @1A: imul
		// @1B: getstatic int game.C_100177_cj.field_105660_u
		// @1E: idiv
		// @1F: istore_2
		// @20: aload_0
		// @21: getfield long game.C_100210_qa.field_101076_s
		// @24: iload_2
		// @25: i2l
		// @26: iload_1
		// @27: i2l
		// @28: lmul
		// @29: lneg
		// @2A: lsub
		// @2B: lstore_3
		// @2C: ldc2_w -1
		// @2F: lload_3
		// @30: lneg
		// @31: aload_0
		// @32: getfield long game.C_100210_qa.field_101068_S
		// @35: ladd
		// @36: ldc2_w -1
		// @39: lxor
		// @3A: lcmp
		// @3B: iflt @51
		// @3E: aload_0
		// @3F: lload_3
		// @40: putfield long game.C_100210_qa.field_101076_s
		// @43: iload #6
		// @45: ifne @AC
		// @48: iload #6
		// @4A: ifeq @A4
		// @4D: goto @51
		// @50: athrow
		// @51: iload_2
		// @52: i2l
		// @53: aload_0
		// @54: getfield long game.C_100210_qa.field_101076_s
		// @57: lneg
		// @58: ladd
		// @59: aload_0
		// @5A: getfield long game.C_100210_qa.field_101068_S
		// @5D: ladd
		// @5E: lconst_1
		// @5F: lsub
		// @60: iload_2
		// @61: i2l
		// @62: ldiv
		// @63: l2i
		// @64: istore #5
		// @66: aload_0
		// @67: dup
		// @68: getfield long game.C_100210_qa.field_101076_s
		// @6B: iload #5
		// @6D: i2l
		// @6E: iload_2
		// @6F: i2l
		// @70: lmul
		// @71: ladd
		// @72: putfield long game.C_100210_qa.field_101076_s
		// @75: iload_1
		// @76: iload #5
		// @78: isub
		// @79: istore_1
		// @7A: aload_0
		// @7B: getfield game.C_100044_vm game.C_100210_qa.field_101051_G
		// @7E: iload #5
		// @80: invokevirtual game.C_100044_vm.func_100914_e(int)void
		// @83: aload_0
		// @84: iconst_0
		// @85: invokespecial game.C_100210_qa.func_101019_a(boolean)void
		// @88: aload_0
		// @89: getfield game.C_100014_wg game.C_100210_qa.field_101072_w
		// @8C: invokevirtual game.C_100014_wg.func_103757_d()boolean
		// @8F: ifne @9B
		// @92: iload #6
		// @94: ifeq @A4
		// @97: goto @9B
		// @9A: athrow
		// @9B: iload #6
		// @9D: ifeq @20
		// @A0: goto @A4
		// @A3: athrow
		// @A4: aload_0
		// @A5: getfield game.C_100044_vm game.C_100210_qa.field_101051_G
		// @A8: iload_1
		// @A9: invokevirtual game.C_100044_vm.func_100914_e(int)void
		// @AC: goto @D1
		// @AF: astore_2
		// @B0: aload_2
		// @B1: new java.lang.StringBuilder
		// @B4: dup
		// @B5: invokespecial java.lang.StringBuilder.<init>()void
		// @B8: getstatic java.lang.String[] game.C_100210_qa.field_101065_V
		// @BB: bipush 29 (0x1D)
		// @BD: aaload
		// @BE: invokevirtual java.lang.StringBuilder.append(java.lang.String)java.lang.StringBuilder
		// @C1: iload_1
		// @C2: invokevirtual java.lang.StringBuilder.append(int)java.lang.StringBuilder
		// @C5: bipush 41 (0x29)
		// @C7: invokevirtual java.lang.StringBuilder.append(char)java.lang.StringBuilder
		// @CA: invokevirtual java.lang.StringBuilder.toString()java.lang.String
		// @CD: invokestatic game.C_100181_cf.func_105695_a(java.lang.Throwable, java.lang.String)game.C_100170_cm
		// @D0: athrow
		// @D1: return
	}
	
	private final void func_101016_a(int arg0, int arg1, boolean arg2)
	{
		// @00: aload_0
		// @01: getfield int[] game.C_100210_qa.field_101075_t
		// @04: iload_1
		// @05: iload_2
		// @06: iastore
		// @07: aload_0
		// @08: getfield int[] game.C_100210_qa.field_101081_y
		// @0B: iload_1
		// @0C: ldc2_w 2097152.0
		// @0F: ldc2_w 2.0
		// @12: iload_2
		// @13: i2d
		// @14: ldc2_w 5.4931640625E-4
		// @17: dmul
		// @18: invokestatic java.lang.Math.pow(double, double)double
		// @1B: dmul
		// @1C: ldc2_w 0.5
		// @1F: dadd
		// @20: d2i
		// @21: iastore
		// @22: iload_3
		// @23: iconst_1
		// @24: if_icmpeq @32
		// @27: aload_0
		// @28: aconst_null
		// @29: checkcast game.C_100121_ud[][]
		// @2C: checkcast game.C_100121_ud[][]
		// @2F: putfield game.C_100121_ud[][] game.C_100210_qa.field_101070_n
		// @32: goto @6B
		// @35: astore #4
		// @37: aload #4
		// @39: new java.lang.StringBuilder
		// @3C: dup
		// @3D: invokespecial java.lang.StringBuilder.<init>()void
		// @40: getstatic java.lang.String[] game.C_100210_qa.field_101065_V
		// @43: bipush 30 (0x1E)
		// @45: aaload
		// @46: invokevirtual java.lang.StringBuilder.append(java.lang.String)java.lang.StringBuilder
		// @49: iload_1
		// @4A: invokevirtual java.lang.StringBuilder.append(int)java.lang.StringBuilder
		// @4D: bipush 44 (0x2C)
		// @4F: invokevirtual java.lang.StringBuilder.append(char)java.lang.StringBuilder
		// @52: iload_2
		// @53: invokevirtual java.lang.StringBuilder.append(int)java.lang.StringBuilder
		// @56: bipush 44 (0x2C)
		// @58: invokevirtual java.lang.StringBuilder.append(char)java.lang.StringBuilder
		// @5B: iload_3
		// @5C: invokevirtual java.lang.StringBuilder.append(boolean)java.lang.StringBuilder
		// @5F: bipush 41 (0x29)
		// @61: invokevirtual java.lang.StringBuilder.append(char)java.lang.StringBuilder
		// @64: invokevirtual java.lang.StringBuilder.toString()java.lang.String
		// @67: invokestatic game.C_100181_cf.func_105695_a(java.lang.Throwable, java.lang.String)game.C_100170_cm
		// @6A: athrow
		// @6B: return
	}
	
	private final void func_101032_a(int arg0, int arg1, int arg2)
	{
		// @00: bipush 21 (0x15)
		// @02: iload_1
		// @03: bipush 62 (0x3E)
		// @05: isub
		// @06: bipush 49 (0x31)
		// @08: idiv
		// @09: idiv
		// @0A: istore #4
		// @0C: aload_0
		// @0D: getfield int[] game.C_100210_qa.field_101077_r
		// @10: iload_3
		// @11: iload_2
		// @12: iastore
		// @13: aload_0
		// @14: getfield int[] game.C_100210_qa.field_101052_A
		// @17: iload_3
		// @18: bipush -128 (0x80)
		// @1A: iload_2
		// @1B: invokestatic game.C_100256_pk.func_100449_a(int, int)int
		// @1E: iastore
		// @1F: aload_0
		// @20: iconst_1
		// @21: iload_3
		// @22: iload_2
		// @23: invokespecial game.C_100210_qa.func_101018_a(boolean, int, int)void
		// @26: goto @5F
		// @29: astore #4
		// @2B: aload #4
		// @2D: new java.lang.StringBuilder
		// @30: dup
		// @31: invokespecial java.lang.StringBuilder.<init>()void
		// @34: getstatic java.lang.String[] game.C_100210_qa.field_101065_V
		// @37: bipush 18 (0x12)
		// @39: aaload
		// @3A: invokevirtual java.lang.StringBuilder.append(java.lang.String)java.lang.StringBuilder
		// @3D: iload_1
		// @3E: invokevirtual java.lang.StringBuilder.append(int)java.lang.StringBuilder
		// @41: bipush 44 (0x2C)
		// @43: invokevirtual java.lang.StringBuilder.append(char)java.lang.StringBuilder
		// @46: iload_2
		// @47: invokevirtual java.lang.StringBuilder.append(int)java.lang.StringBuilder
		// @4A: bipush 44 (0x2C)
		// @4C: invokevirtual java.lang.StringBuilder.append(char)java.lang.StringBuilder
		// @4F: iload_3
		// @50: invokevirtual java.lang.StringBuilder.append(int)java.lang.StringBuilder
		// @53: bipush 41 (0x29)
		// @55: invokevirtual java.lang.StringBuilder.append(char)java.lang.StringBuilder
		// @58: invokevirtual java.lang.StringBuilder.toString()java.lang.String
		// @5B: invokestatic game.C_100181_cf.func_105695_a(java.lang.Throwable, java.lang.String)game.C_100170_cm
		// @5E: athrow
		// @5F: return
	}
	
	static final C_100302_ka func_101012_a(int arg0, int arg1, int arg2, int arg3, C_100112_r arg4, int arg5, int arg6, int arg7, int arg8, int arg9, int arg10, int arg11, int arg12)
	{
		// @000: new game.C_100302_ka
		// @003: dup
		// @004: iload #6
		// @006: i2l
		// @007: aconst_null
		// @008: invokespecial game.C_100302_ka.<init>(long, game.C_100302_ka)void
		// @00B: astore #13
		// @00D: aload #13
		// @00F: iload_3
		// @010: iload #7
		// @012: iconst_m1
		// @013: invokestatic game.C_100333_ij.func_107331_b(int, int, int)game.C_100037_wb[]
		// @016: putfield game.C_100037_wb[] game.C_100302_ka.field_101862_T
		// @019: aload #13
		// @01B: iload_1
		// @01C: iload #5
		// @01E: iload #6
		// @020: iconst_m1
		// @021: iadd
		// @022: invokestatic game.C_100333_ij.func_107331_b(int, int, int)game.C_100037_wb[]
		// @025: putfield game.C_100037_wb[] game.C_100302_ka.field_101883_qb
		// @028: aload #13
		// @02A: iload #8
		// @02C: iload #9
		// @02E: iconst_m1
		// @02F: invokestatic game.C_100333_ij.func_107331_b(int, int, int)game.C_100037_wb[]
		// @032: putfield game.C_100037_wb[] game.C_100302_ka.field_101851_zb
		// @035: aload #13
		// @037: iload #12
		// @039: iload_0
		// @03A: iconst_m1
		// @03B: invokestatic game.C_100333_ij.func_107331_b(int, int, int)game.C_100037_wb[]
		// @03E: putfield game.C_100037_wb[] game.C_100302_ka.field_101878_Jb
		// @041: aload #13
		// @043: iload_2
		// @044: iload #10
		// @046: iload #6
		// @048: iconst_m1
		// @049: iadd
		// @04A: invokestatic game.C_100333_ij.func_107331_b(int, int, int)game.C_100037_wb[]
		// @04D: putfield game.C_100037_wb[] game.C_100302_ka.field_101853_M
		// @050: aload #13
		// @052: iload #11
		// @054: putfield int game.C_100302_ka.field_101830_gb
		// @057: aload #13
		// @059: aload #4
		// @05B: putfield game.C_100112_r game.C_100302_ka.field_101845_sb
		// @05E: aload #13
		// @060: areturn
		// @061: astore #13
		// @063: aload #13
		// @065: new java.lang.StringBuilder
		// @068: dup
		// @069: invokespecial java.lang.StringBuilder.<init>()void
		// @06C: getstatic java.lang.String[] game.C_100210_qa.field_101065_V
		// @06F: bipush 12 (0x0C)
		// @071: aaload
		// @072: invokevirtual java.lang.StringBuilder.append(java.lang.String)java.lang.StringBuilder
		// @075: iload_0
		// @076: invokevirtual java.lang.StringBuilder.append(int)java.lang.StringBuilder
		// @079: bipush 44 (0x2C)
		// @07B: invokevirtual java.lang.StringBuilder.append(char)java.lang.StringBuilder
		// @07E: iload_1
		// @07F: invokevirtual java.lang.StringBuilder.append(int)java.lang.StringBuilder
		// @082: bipush 44 (0x2C)
		// @084: invokevirtual java.lang.StringBuilder.append(char)java.lang.StringBuilder
		// @087: iload_2
		// @088: invokevirtual java.lang.StringBuilder.append(int)java.lang.StringBuilder
		// @08B: bipush 44 (0x2C)
		// @08D: invokevirtual java.lang.StringBuilder.append(char)java.lang.StringBuilder
		// @090: iload_3
		// @091: invokevirtual java.lang.StringBuilder.append(int)java.lang.StringBuilder
		// @094: bipush 44 (0x2C)
		// @096: invokevirtual java.lang.StringBuilder.append(char)java.lang.StringBuilder
		// @099: aload #4
		// @09B: ifnull @0A7
		// @09E: getstatic java.lang.String[] game.C_100210_qa.field_101065_V
		// @0A1: iconst_0
		// @0A2: aaload
		// @0A3: goto @0AC
		// @0A6: athrow
		// @0A7: getstatic java.lang.String[] game.C_100210_qa.field_101065_V
		// @0AA: iconst_2
		// @0AB: aaload
		// @0AC: invokevirtual java.lang.StringBuilder.append(java.lang.String)java.lang.StringBuilder
		// @0AF: bipush 44 (0x2C)
		// @0B1: invokevirtual java.lang.StringBuilder.append(char)java.lang.StringBuilder
		// @0B4: iload #5
		// @0B6: invokevirtual java.lang.StringBuilder.append(int)java.lang.StringBuilder
		// @0B9: bipush 44 (0x2C)
		// @0BB: invokevirtual java.lang.StringBuilder.append(char)java.lang.StringBuilder
		// @0BE: iload #6
		// @0C0: invokevirtual java.lang.StringBuilder.append(int)java.lang.StringBuilder
		// @0C3: bipush 44 (0x2C)
		// @0C5: invokevirtual java.lang.StringBuilder.append(char)java.lang.StringBuilder
		// @0C8: iload #7
		// @0CA: invokevirtual java.lang.StringBuilder.append(int)java.lang.StringBuilder
		// @0CD: bipush 44 (0x2C)
		// @0CF: invokevirtual java.lang.StringBuilder.append(char)java.lang.StringBuilder
		// @0D2: iload #8
		// @0D4: invokevirtual java.lang.StringBuilder.append(int)java.lang.StringBuilder
		// @0D7: bipush 44 (0x2C)
		// @0D9: invokevirtual java.lang.StringBuilder.append(char)java.lang.StringBuilder
		// @0DC: iload #9
		// @0DE: invokevirtual java.lang.StringBuilder.append(int)java.lang.StringBuilder
		// @0E1: bipush 44 (0x2C)
		// @0E3: invokevirtual java.lang.StringBuilder.append(char)java.lang.StringBuilder
		// @0E6: iload #10
		// @0E8: invokevirtual java.lang.StringBuilder.append(int)java.lang.StringBuilder
		// @0EB: bipush 44 (0x2C)
		// @0ED: invokevirtual java.lang.StringBuilder.append(char)java.lang.StringBuilder
		// @0F0: iload #11
		// @0F2: invokevirtual java.lang.StringBuilder.append(int)java.lang.StringBuilder
		// @0F5: bipush 44 (0x2C)
		// @0F7: invokevirtual java.lang.StringBuilder.append(char)java.lang.StringBuilder
		// @0FA: iload #12
		// @0FC: invokevirtual java.lang.StringBuilder.append(int)java.lang.StringBuilder
		// @0FF: bipush 41 (0x29)
		// @101: invokevirtual java.lang.StringBuilder.append(char)java.lang.StringBuilder
		// @104: invokevirtual java.lang.StringBuilder.toString()java.lang.String
		// @107: invokestatic game.C_100181_cf.func_105695_a(java.lang.Throwable, java.lang.String)game.C_100170_cm
		// @10A: athrow
	}
	
	private final int func_101038_c(C_100121_ud arg0, int arg1)
	{
		// @00: iload_2
		// @01: sipush -12169 (0xD077)
		// @04: if_icmpeq @0A
		// @07: bipush 124 (0x7C)
		// @09: ireturn
		// @0A: aload_0
		// @0B: getfield int[] game.C_100210_qa.field_101053_B
		// @0E: aload_1
		// @0F: getfield int game.C_100121_ud.field_100725_m
		// @12: iaload
		// @13: istore_3
		// @14: sipush 8192 (0x2000)
		// @17: iload_3
		// @18: if_icmple @29
		// @1B: iload_3
		// @1C: aload_1
		// @1D: getfield int game.C_100121_ud.field_100737_y
		// @20: imul
		// @21: bipush -32 (0xE0)
		// @23: isub
		// @24: ldc_w -561191738 (0xde8ce4c6)
		// @27: ishr
		// @28: ireturn
		// @29: sipush 16384 (0x4000)
		// @2C: sipush 16384 (0x4000)
		// @2F: iload_3
		// @30: ineg
		// @31: iadd
		// @32: sipush 128 (0x0080)
		// @35: aload_1
		// @36: getfield int game.C_100121_ud.field_100737_y
		// @39: ineg
		// @3A: iadd
		// @3B: imul
		// @3C: bipush -32 (0xE0)
		// @3E: isub
		// @3F: ldc_w -1657892314 (0x9d2e9226)
		// @42: ishr
		// @43: ineg
		// @44: iadd
		// @45: ireturn
		// @46: astore_3
		// @47: aload_3
		// @48: new java.lang.StringBuilder
		// @4B: dup
		// @4C: invokespecial java.lang.StringBuilder.<init>()void
		// @4F: getstatic java.lang.String[] game.C_100210_qa.field_101065_V
		// @52: iconst_1
		// @53: aaload
		// @54: invokevirtual java.lang.StringBuilder.append(java.lang.String)java.lang.StringBuilder
		// @57: aload_1
		// @58: ifnull @64
		// @5B: getstatic java.lang.String[] game.C_100210_qa.field_101065_V
		// @5E: iconst_0
		// @5F: aaload
		// @60: goto @69
		// @63: athrow
		// @64: getstatic java.lang.String[] game.C_100210_qa.field_101065_V
		// @67: iconst_2
		// @68: aaload
		// @69: invokevirtual java.lang.StringBuilder.append(java.lang.String)java.lang.StringBuilder
		// @6C: bipush 44 (0x2C)
		// @6E: invokevirtual java.lang.StringBuilder.append(char)java.lang.StringBuilder
		// @71: iload_2
		// @72: invokevirtual java.lang.StringBuilder.append(int)java.lang.StringBuilder
		// @75: bipush 41 (0x29)
		// @77: invokevirtual java.lang.StringBuilder.append(char)java.lang.StringBuilder
		// @7A: invokevirtual java.lang.StringBuilder.toString()java.lang.String
		// @7D: invokestatic game.C_100181_cf.func_105695_a(java.lang.Throwable, java.lang.String)game.C_100170_cm
		// @80: athrow
	}
	
	private final int func_101009_a(C_100121_ud arg0, int arg1)
	{
		// @000: aload_1
		// @001: getfield int game.C_100121_ud.field_100719_C
		// @004: aload_1
		// @005: getfield int game.C_100121_ud.field_100717_A
		// @008: imul
		// @009: ldc_w -1363714484 (0xaeb75e4c)
		// @00C: ishr
		// @00D: aload_1
		// @00E: getfield int game.C_100121_ud.field_100720_H
		// @011: iadd
		// @012: istore_3
		// @013: iload_3
		// @014: aload_0
		// @015: getfield int[] game.C_100210_qa.field_101061_J
		// @018: aload_1
		// @019: getfield int game.C_100121_ud.field_100725_m
		// @01C: iaload
		// @01D: sipush -8192 (0xE000)
		// @020: aload_0
		// @021: getfield int[] game.C_100210_qa.field_101073_v
		// @024: aload_1
		// @025: getfield int game.C_100121_ud.field_100725_m
		// @028: iaload
		// @029: iadd
		// @02A: imul
		// @02B: ldc_w 1058577100 (0x3f189acc)
		// @02E: ishr
		// @02F: iadd
		// @030: istore_3
		// @031: iload_2
		// @032: bipush 26 (0x1A)
		// @034: if_icmpgt @043
		// @037: aload_0
		// @038: aconst_null
		// @039: checkcast int[]
		// @03C: putfield int[] game.C_100210_qa.field_101061_J
		// @03F: goto @043
		// @042: athrow
		// @043: aload_1
		// @044: getfield game.C_100132_td game.C_100121_ud.field_100738_x
		// @047: astore #4
		// @049: aload #4
		// @04B: getfield int game.C_100132_td.field_104982_k
		// @04E: ifle @0D2
		// @051: iconst_0
		// @052: aload #4
		// @054: getfield int game.C_100132_td.field_104978_o
		// @057: if_icmplt @071
		// @05A: goto @05E
		// @05D: athrow
		// @05E: iconst_m1
		// @05F: aload_0
		// @060: getfield int[] game.C_100210_qa.field_101074_u
		// @063: aload_1
		// @064: getfield int game.C_100121_ud.field_100725_m
		// @067: iaload
		// @068: iconst_m1
		// @069: ixor
		// @06A: if_icmple @0D2
		// @06D: goto @071
		// @070: athrow
		// @071: aload #4
		// @073: getfield int game.C_100132_td.field_104978_o
		// @076: ldc_w -1338511614 (0xb037ef02)
		// @079: ishl
		// @07A: istore #5
		// @07C: aload #4
		// @07E: getfield int game.C_100132_td.field_104980_m
		// @081: ldc_w 718463361 (0x2ad2e181)
		// @084: ishl
		// @085: istore #6
		// @087: aload_1
		// @088: getfield int game.C_100121_ud.field_100735_p
		// @08B: iconst_m1
		// @08C: ixor
		// @08D: iload #6
		// @08F: iconst_m1
		// @090: ixor
		// @091: if_icmpgt @098
		// @094: goto @0A4
		// @097: athrow
		// @098: iload #5
		// @09A: aload_1
		// @09B: getfield int game.C_100121_ud.field_100735_p
		// @09E: imul
		// @09F: iload #6
		// @0A1: idiv
		// @0A2: istore #5
		// @0A4: iload #5
		// @0A6: aload_0
		// @0A7: getfield int[] game.C_100210_qa.field_101074_u
		// @0AA: aload_1
		// @0AB: getfield int game.C_100121_ud.field_100725_m
		// @0AE: iaload
		// @0AF: ldc_w -932391353 (0xc86cd647)
		// @0B2: ishr
		// @0B3: iadd
		// @0B4: istore #5
		// @0B6: ldc2_w 0.01227184630308513
		// @0B9: sipush 511 (0x01FF)
		// @0BC: aload_1
		// @0BD: getfield int game.C_100121_ud.field_100723_o
		// @0C0: iand
		// @0C1: i2d
		// @0C2: dmul
		// @0C3: invokestatic java.lang.Math.sin(double)double
		// @0C6: dstore #7
		// @0C8: iload_3
		// @0C9: iload #5
		// @0CB: i2d
		// @0CC: dload #7
		// @0CE: dmul
		// @0CF: d2i
		// @0D0: iadd
		// @0D1: istore_3
		// @0D2: aload_1
		// @0D3: getfield game.C_100214_al game.C_100121_ud.field_100731_t
		// @0D6: getfield int game.C_100214_al.field_100884_o
		// @0D9: sipush 256 (0x0100)
		// @0DC: imul
		// @0DD: i2d
		// @0DE: ldc2_w 2.0
		// @0E1: ldc2_w 3.255208333333333E-4
		// @0E4: iload_3
		// @0E5: i2d
		// @0E6: dmul
		// @0E7: invokestatic java.lang.Math.pow(double, double)double
		// @0EA: dmul
		// @0EB: getstatic int game.C_100177_cj.field_105660_u
		// @0EE: i2d
		// @0EF: ddiv
		// @0F0: ldc2_w 0.5
		// @0F3: dadd
		// @0F4: d2i
		// @0F5: istore #5
		// @0F7: bipush -2 (0xFE)
		// @0F9: iload #5
		// @0FB: iconst_m1
		// @0FC: ixor
		// @0FD: if_icmpge @105
		// @100: iconst_1
		// @101: goto @107
		// @104: athrow
		// @105: iload #5
		// @107: ireturn
		// @108: astore_3
		// @109: aload_3
		// @10A: new java.lang.StringBuilder
		// @10D: dup
		// @10E: invokespecial java.lang.StringBuilder.<init>()void
		// @111: getstatic java.lang.String[] game.C_100210_qa.field_101065_V
		// @114: bipush 13 (0x0D)
		// @116: aaload
		// @117: invokevirtual java.lang.StringBuilder.append(java.lang.String)java.lang.StringBuilder
		// @11A: aload_1
		// @11B: ifnull @127
		// @11E: getstatic java.lang.String[] game.C_100210_qa.field_101065_V
		// @121: iconst_0
		// @122: aaload
		// @123: goto @12C
		// @126: athrow
		// @127: getstatic java.lang.String[] game.C_100210_qa.field_101065_V
		// @12A: iconst_2
		// @12B: aaload
		// @12C: invokevirtual java.lang.StringBuilder.append(java.lang.String)java.lang.StringBuilder
		// @12F: bipush 44 (0x2C)
		// @131: invokevirtual java.lang.StringBuilder.append(char)java.lang.StringBuilder
		// @134: iload_2
		// @135: invokevirtual java.lang.StringBuilder.append(int)java.lang.StringBuilder
		// @138: bipush 41 (0x29)
		// @13A: invokevirtual java.lang.StringBuilder.append(char)java.lang.StringBuilder
		// @13D: invokevirtual java.lang.StringBuilder.toString()java.lang.String
		// @140: invokestatic game.C_100181_cf.func_105695_a(java.lang.Throwable, java.lang.String)game.C_100170_cm
		// @143: athrow
	}
	
	private final void func_101020_a(int arg0, int arg1)
	{
		// @00: getstatic int game.SteelSentinels.field_105275_O
		// @03: istore #4
		// @05: aload_0
		// @06: getfield int[] game.C_100210_qa.field_101060_I
		// @09: iload_1
		// @0A: iaload
		// @0B: iconst_2
		// @0C: iand
		// @0D: ifne @14
		// @10: goto @7B
		// @13: athrow
		// @14: aload_0
		// @15: getfield game.C_100044_vm game.C_100210_qa.field_101051_G
		// @18: getfield game.C_100202_qi game.C_100044_vm.field_100943_u
		// @1B: bipush 11 (0x0B)
		// @1D: invokevirtual game.C_100202_qi.func_105899_c(int)game.C_100158_da
		// @20: checkcast game.C_100121_ud
		// @23: astore_3
		// @24: aload_3
		// @25: ifnull @7B
		// @28: aload_3
		// @29: getfield int game.C_100121_ud.field_100725_m
		// @2C: iconst_m1
		// @2D: ixor
		// @2E: iload_1
		// @2F: iconst_m1
		// @30: ixor
		// @31: iload #4
		// @33: ifne @7E
		// @36: if_icmpne @66
		// @39: goto @3D
		// @3C: athrow
		// @3D: aload_0
		// @3E: getfield game.C_100121_ud[][] game.C_100210_qa.field_101070_n
		// @41: iload_1
		// @42: aaload
		// @43: aload_3
		// @44: getfield int game.C_100121_ud.field_100736_z
		// @47: aaload
		// @48: ifnonnull @66
		// @4B: goto @4F
		// @4E: athrow
		// @4F: aload_3
		// @50: getfield int game.C_100121_ud.field_100733_r
		// @53: iconst_m1
		// @54: ixor
		// @55: iconst_m1
		// @56: if_icmple @66
		// @59: goto @5D
		// @5C: athrow
		// @5D: aload_3
		// @5E: iconst_0
		// @5F: putfield int game.C_100121_ud.field_100733_r
		// @62: goto @66
		// @65: athrow
		// @66: aload_0
		// @67: getfield game.C_100044_vm game.C_100210_qa.field_101051_G
		// @6A: getfield game.C_100202_qi game.C_100044_vm.field_100943_u
		// @6D: bipush 123 (0x7B)
		// @6F: invokevirtual game.C_100202_qi.func_105907_c(byte)game.C_100158_da
		// @72: checkcast game.C_100121_ud
		// @75: astore_3
		// @76: iload #4
		// @78: ifeq @24
		// @7B: iload_2
		// @7C: bipush -49 (0xCF)
		// @7E: if_icmplt @8A
		// @81: bipush -106 (0x96)
		// @83: invokestatic game.C_100210_qa.func_101033_g(int)void
		// @86: goto @8A
		// @89: athrow
		// @8A: goto @B8
		// @8D: astore_3
		// @8E: aload_3
		// @8F: new java.lang.StringBuilder
		// @92: dup
		// @93: invokespecial java.lang.StringBuilder.<init>()void
		// @96: getstatic java.lang.String[] game.C_100210_qa.field_101065_V
		// @99: bipush 44 (0x2C)
		// @9B: aaload
		// @9C: invokevirtual java.lang.StringBuilder.append(java.lang.String)java.lang.StringBuilder
		// @9F: iload_1
		// @A0: invokevirtual java.lang.StringBuilder.append(int)java.lang.StringBuilder
		// @A3: bipush 44 (0x2C)
		// @A5: invokevirtual java.lang.StringBuilder.append(char)java.lang.StringBuilder
		// @A8: iload_2
		// @A9: invokevirtual java.lang.StringBuilder.append(int)java.lang.StringBuilder
		// @AC: bipush 41 (0x29)
		// @AE: invokevirtual java.lang.StringBuilder.append(char)java.lang.StringBuilder
		// @B1: invokevirtual java.lang.StringBuilder.toString()java.lang.String
		// @B4: invokestatic game.C_100181_cf.func_105695_a(java.lang.Throwable, java.lang.String)game.C_100170_cm
		// @B7: athrow
		// @B8: return
	}
	
	private final void func_101024_c(int arg0, int arg1)
	{
		// @00: getstatic int game.SteelSentinels.field_105275_O
		// @03: istore #4
		// @05: iload_1
		// @06: sipush 21346 (0x5362)
		// @09: if_icmpeq @17
		// @0C: aconst_null
		// @0D: checkcast java.lang.String
		// @10: putstatic java.lang.String game.C_100210_qa.field_101049_E
		// @13: goto @17
		// @16: athrow
		// @17: iconst_0
		// @18: iconst_4
		// @19: aload_0
		// @1A: getfield int[] game.C_100210_qa.field_101060_I
		// @1D: iload_2
		// @1E: iaload
		// @1F: iand
		// @20: if_icmpeq @67
		// @23: aload_0
		// @24: getfield game.C_100044_vm game.C_100210_qa.field_101051_G
		// @27: getfield game.C_100202_qi game.C_100044_vm.field_100943_u
		// @2A: bipush 117 (0x75)
		// @2C: invokevirtual game.C_100202_qi.func_105899_c(int)game.C_100158_da
		// @2F: checkcast game.C_100121_ud
		// @32: astore_3
		// @33: aconst_null
		// @34: aload_3
		// @35: if_acmpeq @67
		// @38: iload #4
		// @3A: ifne @95
		// @3D: aload_3
		// @3E: getfield int game.C_100121_ud.field_100725_m
		// @41: iload_2
		// @42: if_icmpne @52
		// @45: goto @49
		// @48: athrow
		// @49: aload_3
		// @4A: iconst_0
		// @4B: putfield int game.C_100121_ud.field_100713_D
		// @4E: goto @52
		// @51: athrow
		// @52: aload_0
		// @53: getfield game.C_100044_vm game.C_100210_qa.field_101051_G
		// @56: getfield game.C_100202_qi game.C_100044_vm.field_100943_u
		// @59: bipush 22 (0x16)
		// @5B: invokevirtual game.C_100202_qi.func_105907_c(byte)game.C_100158_da
		// @5E: checkcast game.C_100121_ud
		// @61: astore_3
		// @62: iload #4
		// @64: ifeq @33
		// @67: goto @95
		// @6A: astore_3
		// @6B: aload_3
		// @6C: new java.lang.StringBuilder
		// @6F: dup
		// @70: invokespecial java.lang.StringBuilder.<init>()void
		// @73: getstatic java.lang.String[] game.C_100210_qa.field_101065_V
		// @76: bipush 8 (0x08)
		// @78: aaload
		// @79: invokevirtual java.lang.StringBuilder.append(java.lang.String)java.lang.StringBuilder
		// @7C: iload_1
		// @7D: invokevirtual java.lang.StringBuilder.append(int)java.lang.StringBuilder
		// @80: bipush 44 (0x2C)
		// @82: invokevirtual java.lang.StringBuilder.append(char)java.lang.StringBuilder
		// @85: iload_2
		// @86: invokevirtual java.lang.StringBuilder.append(int)java.lang.StringBuilder
		// @89: bipush 41 (0x29)
		// @8B: invokevirtual java.lang.StringBuilder.append(char)java.lang.StringBuilder
		// @8E: invokevirtual java.lang.StringBuilder.toString()java.lang.String
		// @91: invokestatic game.C_100181_cf.func_105695_a(java.lang.Throwable, java.lang.String)game.C_100170_cm
		// @94: athrow
		// @95: return
	}
	
	private final void func_101047_b(int arg0, byte arg1)
	{
		// @00: getstatic int game.SteelSentinels.field_105275_O
		// @03: istore #4
		// @05: iload_2
		// @06: bipush -121 (0x87)
		// @08: if_icmpeq @17
		// @0B: aload_0
		// @0C: aconst_null
		// @0D: checkcast int[]
		// @10: putfield int[] game.C_100210_qa.field_101075_t
		// @13: goto @17
		// @16: athrow
		// @17: aload_0
		// @18: getfield game.C_100044_vm game.C_100210_qa.field_101051_G
		// @1B: getfield game.C_100202_qi game.C_100044_vm.field_100943_u
		// @1E: bipush 38 (0x26)
		// @20: invokevirtual game.C_100202_qi.func_105899_c(int)game.C_100158_da
		// @23: checkcast game.C_100121_ud
		// @26: astore_3
		// @27: aconst_null
		// @28: aload_3
		// @29: if_acmpeq @B8
		// @2C: iload #4
		// @2E: ifne @E6
		// @31: iload_1
		// @32: iflt @45
		// @35: goto @39
		// @38: athrow
		// @39: aload_3
		// @3A: getfield int game.C_100121_ud.field_100725_m
		// @3D: iload_1
		// @3E: if_icmpne @A3
		// @41: goto @45
		// @44: athrow
		// @45: aload_3
		// @46: getfield game.C_100117_p game.C_100121_ud.field_100730_u
		// @49: ifnull @82
		// @4C: goto @50
		// @4F: athrow
		// @50: aload_3
		// @51: getfield game.C_100117_p game.C_100121_ud.field_100730_u
		// @54: getstatic int game.C_100177_cj.field_105660_u
		// @57: bipush 100 (0x64)
		// @59: idiv
		// @5A: invokevirtual game.C_100117_p.func_100972_g(int)void
		// @5D: aload_3
		// @5E: getfield game.C_100117_p game.C_100121_ud.field_100730_u
		// @61: invokevirtual game.C_100117_p.func_100979_e()boolean
		// @64: ifeq @7D
		// @67: goto @6B
		// @6A: athrow
		// @6B: aload_0
		// @6C: getfield game.C_100044_vm game.C_100210_qa.field_101051_G
		// @6F: getfield game.C_100026_hb game.C_100044_vm.field_100949_n
		// @72: aload_3
		// @73: getfield game.C_100117_p game.C_100121_ud.field_100730_u
		// @76: invokevirtual game.C_100026_hb.func_100924_b(game.C_100261_md)void
		// @79: goto @7D
		// @7C: athrow
		// @7D: aload_3
		// @7E: iconst_0
		// @7F: invokevirtual game.C_100121_ud.func_100712_c(byte)void
		// @82: iconst_0
		// @83: aload_3
		// @84: getfield int game.C_100121_ud.field_100733_r
		// @87: if_icmple @9D
		// @8A: aload_0
		// @8B: getfield game.C_100121_ud[][] game.C_100210_qa.field_101070_n
		// @8E: aload_3
		// @8F: getfield int game.C_100121_ud.field_100725_m
		// @92: aaload
		// @93: aload_3
		// @94: getfield int game.C_100121_ud.field_100736_z
		// @97: aconst_null
		// @98: aastore
		// @99: goto @9D
		// @9C: athrow
		// @9D: aload_3
		// @9E: bipush 45 (0x2D)
		// @A0: invokevirtual game.C_100121_ud.func_100583_c(int)void
		// @A3: aload_0
		// @A4: getfield game.C_100044_vm game.C_100210_qa.field_101051_G
		// @A7: getfield game.C_100202_qi game.C_100044_vm.field_100943_u
		// @AA: bipush 73 (0x49)
		// @AC: invokevirtual game.C_100202_qi.func_105907_c(byte)game.C_100158_da
		// @AF: checkcast game.C_100121_ud
		// @B2: astore_3
		// @B3: iload #4
		// @B5: ifeq @27
		// @B8: goto @E6
		// @BB: astore_3
		// @BC: aload_3
		// @BD: new java.lang.StringBuilder
		// @C0: dup
		// @C1: invokespecial java.lang.StringBuilder.<init>()void
		// @C4: getstatic java.lang.String[] game.C_100210_qa.field_101065_V
		// @C7: bipush 24 (0x18)
		// @C9: aaload
		// @CA: invokevirtual java.lang.StringBuilder.append(java.lang.String)java.lang.StringBuilder
		// @CD: iload_1
		// @CE: invokevirtual java.lang.StringBuilder.append(int)java.lang.StringBuilder
		// @D1: bipush 44 (0x2C)
		// @D3: invokevirtual java.lang.StringBuilder.append(char)java.lang.StringBuilder
		// @D6: iload_2
		// @D7: invokevirtual java.lang.StringBuilder.append(int)java.lang.StringBuilder
		// @DA: bipush 41 (0x29)
		// @DC: invokevirtual java.lang.StringBuilder.append(char)java.lang.StringBuilder
		// @DF: invokevirtual java.lang.StringBuilder.toString()java.lang.String
		// @E2: invokestatic game.C_100181_cf.func_105695_a(java.lang.Throwable, java.lang.String)game.C_100170_cm
		// @E5: athrow
		// @E6: return
	}
	
	final synchronized boolean func_101036_a(int arg0, C_100098_h arg1, C_100002_gf arg2, int arg3, C_100228_nn arg4)
	{
		// @000: getstatic int game.SteelSentinels.field_105275_O
		// @003: istore #11
		// @005: aload_3
		// @006: invokevirtual game.C_100002_gf.func_103501_a()void
		// @009: iconst_1
		// @00A: istore #6
		// @00C: aconst_null
		// @00D: astore #7
		// @00F: iload_1
		// @010: iload #4
		// @012: if_icmple @01E
		// @015: iconst_1
		// @016: newarray int[]
		// @018: dup
		// @019: iconst_0
		// @01A: iload_1
		// @01B: iastore
		// @01C: astore #7
		// @01E: aload_3
		// @01F: getfield game.C_100119_ua game.C_100002_gf.field_103504_k
		// @022: bipush 117 (0x75)
		// @024: invokevirtual game.C_100119_ua.func_104885_d(byte)game.C_100158_da
		// @027: checkcast game.C_100191_rg
		// @02A: astore #8
		// @02C: aload #8
		// @02E: ifnull @0B2
		// @031: aload #8
		// @033: getfield long game.C_100191_rg.field_100595_c
		// @036: l2i
		// @037: istore #9
		// @039: aload_0
		// @03A: getfield game.C_100119_ua game.C_100210_qa.field_101057_N
		// @03D: iload #9
		// @03F: i2l
		// @040: bipush 109 (0x6D)
		// @042: invokevirtual game.C_100119_ua.func_104891_a(long, int)game.C_100158_da
		// @045: checkcast game.C_100236_on
		// @048: astore #10
		// @04A: iload #11
		// @04C: ifne @0BB
		// @04F: aconst_null
		// @050: aload #10
		// @052: if_acmpne @085
		// @055: goto @059
		// @058: athrow
		// @059: bipush -118 (0x8A)
		// @05B: iload #9
		// @05D: aload_2
		// @05E: invokestatic game.C_100189_ri.func_105750_a(int, int, game.C_100098_h)game.C_100236_on
		// @061: astore #10
		// @063: aload #10
		// @065: ifnull @06C
		// @068: goto @074
		// @06B: athrow
		// @06C: iconst_0
		// @06D: istore #6
		// @06F: iload #11
		// @071: ifeq @09F
		// @074: aload_0
		// @075: getfield game.C_100119_ua game.C_100210_qa.field_101057_N
		// @078: aload #10
		// @07A: iload #9
		// @07C: i2l
		// @07D: iconst_1
		// @07E: invokevirtual game.C_100119_ua.func_104893_a(game.C_100158_da, long, boolean)void
		// @081: goto @085
		// @084: athrow
		// @085: aload #10
		// @087: aload #8
		// @089: getfield byte[] game.C_100191_rg.field_100846_l
		// @08C: bipush 113 (0x71)
		// @08E: aload #7
		// @090: aload #5
		// @092: invokevirtual game.C_100236_on.func_100893_a(byte[], byte, int[], game.C_100228_nn)boolean
		// @095: ifeq @09C
		// @098: goto @09F
		// @09B: athrow
		// @09C: iconst_0
		// @09D: istore #6
		// @09F: aload_3
		// @0A0: getfield game.C_100119_ua game.C_100002_gf.field_103504_k
		// @0A3: bipush 97 (0x61)
		// @0A5: invokevirtual game.C_100119_ua.func_104894_a(int)game.C_100158_da
		// @0A8: checkcast game.C_100191_rg
		// @0AB: astore #8
		// @0AD: iload #11
		// @0AF: ifeq @02C
		// @0B2: iload #6
		// @0B4: ifne @0BB
		// @0B7: goto @0BF
		// @0BA: athrow
		// @0BB: aload_3
		// @0BC: invokevirtual game.C_100002_gf.func_103502_b()void
		// @0BF: iload #6
		// @0C1: ireturn
		// @0C2: astore #6
		// @0C4: aload #6
		// @0C6: new java.lang.StringBuilder
		// @0C9: dup
		// @0CA: invokespecial java.lang.StringBuilder.<init>()void
		// @0CD: getstatic java.lang.String[] game.C_100210_qa.field_101065_V
		// @0D0: bipush 19 (0x13)
		// @0D2: aaload
		// @0D3: invokevirtual java.lang.StringBuilder.append(java.lang.String)java.lang.StringBuilder
		// @0D6: iload_1
		// @0D7: invokevirtual java.lang.StringBuilder.append(int)java.lang.StringBuilder
		// @0DA: bipush 44 (0x2C)
		// @0DC: invokevirtual java.lang.StringBuilder.append(char)java.lang.StringBuilder
		// @0DF: aload_2
		// @0E0: ifnull @0EC
		// @0E3: getstatic java.lang.String[] game.C_100210_qa.field_101065_V
		// @0E6: iconst_0
		// @0E7: aaload
		// @0E8: goto @0F1
		// @0EB: athrow
		// @0EC: getstatic java.lang.String[] game.C_100210_qa.field_101065_V
		// @0EF: iconst_2
		// @0F0: aaload
		// @0F1: invokevirtual java.lang.StringBuilder.append(java.lang.String)java.lang.StringBuilder
		// @0F4: bipush 44 (0x2C)
		// @0F6: invokevirtual java.lang.StringBuilder.append(char)java.lang.StringBuilder
		// @0F9: aload_3
		// @0FA: ifnull @106
		// @0FD: getstatic java.lang.String[] game.C_100210_qa.field_101065_V
		// @100: iconst_0
		// @101: aaload
		// @102: goto @10B
		// @105: athrow
		// @106: getstatic java.lang.String[] game.C_100210_qa.field_101065_V
		// @109: iconst_2
		// @10A: aaload
		// @10B: invokevirtual java.lang.StringBuilder.append(java.lang.String)java.lang.StringBuilder
		// @10E: bipush 44 (0x2C)
		// @110: invokevirtual java.lang.StringBuilder.append(char)java.lang.StringBuilder
		// @113: iload #4
		// @115: invokevirtual java.lang.StringBuilder.append(int)java.lang.StringBuilder
		// @118: bipush 44 (0x2C)
		// @11A: invokevirtual java.lang.StringBuilder.append(char)java.lang.StringBuilder
		// @11D: aload #5
		// @11F: ifnull @12B
		// @122: getstatic java.lang.String[] game.C_100210_qa.field_101065_V
		// @125: iconst_0
		// @126: aaload
		// @127: goto @130
		// @12A: athrow
		// @12B: getstatic java.lang.String[] game.C_100210_qa.field_101065_V
		// @12E: iconst_2
		// @12F: aaload
		// @130: invokevirtual java.lang.StringBuilder.append(java.lang.String)java.lang.StringBuilder
		// @133: bipush 41 (0x29)
		// @135: invokevirtual java.lang.StringBuilder.append(char)java.lang.StringBuilder
		// @138: invokevirtual java.lang.StringBuilder.toString()java.lang.String
		// @13B: invokestatic game.C_100181_cf.func_105695_a(java.lang.Throwable, java.lang.String)game.C_100170_cm
		// @13E: athrow
	}
	
	private final int func_101040_a(byte arg0, C_100121_ud arg1)
	{
		// @000: iconst_0
		// @001: aload_0
		// @002: getfield int[] game.C_100210_qa.field_101079_p
		// @005: aload_2
		// @006: getfield int game.C_100121_ud.field_100725_m
		// @009: iaload
		// @00A: if_icmpeq @011
		// @00D: goto @013
		// @010: athrow
		// @011: iconst_0
		// @012: ireturn
		// @013: aload_2
		// @014: getfield game.C_100132_td game.C_100121_ud.field_100738_x
		// @017: astore_3
		// @018: sipush 4096 (0x1000)
		// @01B: aload_0
		// @01C: getfield int[] game.C_100210_qa.field_101071_o
		// @01F: aload_2
		// @020: getfield int game.C_100121_ud.field_100725_m
		// @023: iaload
		// @024: aload_0
		// @025: getfield int[] game.C_100210_qa.field_101066_Q
		// @028: aload_2
		// @029: getfield int game.C_100121_ud.field_100725_m
		// @02C: iaload
		// @02D: imul
		// @02E: iadd
		// @02F: ldc_w 65853997 (0x3ecda2d)
		// @032: ishr
		// @033: istore #4
		// @035: iload #4
		// @037: iload #4
		// @039: imul
		// @03A: sipush 16384 (0x4000)
		// @03D: iadd
		// @03E: ldc_w 876120303 (0x343888ef)
		// @041: ishr
		// @042: istore #4
		// @044: iload_1
		// @045: bipush 88 (0x58)
		// @047: if_icmpeq @053
		// @04A: aload_0
		// @04B: invokevirtual game.C_100210_qa.func_100916_d()game.C_100261_md
		// @04E: pop
		// @04F: goto @053
		// @052: athrow
		// @053: iload #4
		// @055: aload_2
		// @056: getfield int game.C_100121_ud.field_100724_l
		// @059: imul
		// @05A: sipush -16384 (0xC000)
		// @05D: isub
		// @05E: ldc_w 631638927 (0x25a60b8f)
		// @061: ishr
		// @062: istore #4
		// @064: sipush 128 (0x0080)
		// @067: iload #4
		// @069: aload_0
		// @06A: getfield int game.C_100210_qa.field_101064_T
		// @06D: imul
		// @06E: iadd
		// @06F: ldc_w 479298472 (0x1c9183a8)
		// @072: ishr
		// @073: istore #4
		// @075: sipush 128 (0x0080)
		// @078: iload #4
		// @07A: aload_0
		// @07B: getfield int[] game.C_100210_qa.field_101079_p
		// @07E: aload_2
		// @07F: getfield int game.C_100121_ud.field_100725_m
		// @082: iaload
		// @083: imul
		// @084: iadd
		// @085: ldc_w -267129432 (0xf013eda8)
		// @088: ishr
		// @089: istore #4
		// @08B: iconst_m1
		// @08C: aload_3
		// @08D: getfield int game.C_100132_td.field_104971_g
		// @090: iconst_m1
		// @091: ixor
		// @092: if_icmpgt @099
		// @095: goto @0B9
		// @098: athrow
		// @099: ldc2_w 0.5
		// @09C: aload_3
		// @09D: getfield int game.C_100132_td.field_104971_g
		// @0A0: i2d
		// @0A1: aload_2
		// @0A2: getfield int game.C_100121_ud.field_100728_w
		// @0A5: i2d
		// @0A6: ldc2_w 1.953125E-5
		// @0A9: dmul
		// @0AA: dmul
		// @0AB: invokestatic java.lang.Math.pow(double, double)double
		// @0AE: iload #4
		// @0B0: i2d
		// @0B1: dmul
		// @0B2: ldc2_w 0.5
		// @0B5: dadd
		// @0B6: d2i
		// @0B7: istore #4
		// @0B9: aload_3
		// @0BA: getfield byte[] game.C_100132_td.field_104981_j
		// @0BD: ifnull @136
		// @0C0: aload_2
		// @0C1: getfield int game.C_100121_ud.field_100729_v
		// @0C4: istore #5
		// @0C6: aload_3
		// @0C7: getfield byte[] game.C_100132_td.field_104981_j
		// @0CA: aload_2
		// @0CB: getfield int game.C_100121_ud.field_100732_s
		// @0CE: iconst_m1
		// @0CF: isub
		// @0D0: baload
		// @0D1: istore #6
		// @0D3: aload_2
		// @0D4: getfield int game.C_100121_ud.field_100732_s
		// @0D7: aload_3
		// @0D8: getfield byte[] game.C_100132_td.field_104981_j
		// @0DB: arraylength
		// @0DC: bipush -2 (0xFE)
		// @0DE: iadd
		// @0DF: if_icmpge @128
		// @0E2: ldc 65280 (0xff00)
		// @0E4: aload_3
		// @0E5: getfield byte[] game.C_100132_td.field_104981_j
		// @0E8: aload_2
		// @0E9: getfield int game.C_100121_ud.field_100732_s
		// @0EC: baload
		// @0ED: ldc_w 491768680 (0x1d4fcb68)
		// @0F0: ishl
		// @0F1: iand
		// @0F2: istore #7
		// @0F4: aload_3
		// @0F5: getfield byte[] game.C_100132_td.field_104981_j
		// @0F8: iconst_2
		// @0F9: aload_2
		// @0FA: getfield int game.C_100121_ud.field_100732_s
		// @0FD: iadd
		// @0FE: baload
		// @0FF: ldc_w -773291288 (0xd1e882e8)
		// @102: ishl
		// @103: ldc 65280 (0xff00)
		// @105: iand
		// @106: istore #8
		// @108: iload #6
		// @10A: aload_3
		// @10B: getfield byte[] game.C_100132_td.field_104981_j
		// @10E: iconst_3
		// @10F: aload_2
		// @110: getfield int game.C_100121_ud.field_100732_s
		// @113: iadd
		// @114: baload
		// @115: iload #6
		// @117: ineg
		// @118: iadd
		// @119: iload #5
		// @11B: iload #7
		// @11D: isub
		// @11E: imul
		// @11F: iload #8
		// @121: iload #7
		// @123: isub
		// @124: idiv
		// @125: iadd
		// @126: istore #6
		// @128: iload #6
		// @12A: iload #4
		// @12C: imul
		// @12D: bipush 32 (0x20)
		// @12F: iadd
		// @130: ldc_w -367676666 (0xea15b306)
		// @133: ishr
		// @134: istore #4
		// @136: iconst_m1
		// @137: aload_2
		// @138: getfield int game.C_100121_ud.field_100733_r
		// @13B: iconst_m1
		// @13C: ixor
		// @13D: if_icmple @1D0
		// @140: aload_3
		// @141: getfield byte[] game.C_100132_td.field_104985_q
		// @144: ifnonnull @14F
		// @147: goto @14B
		// @14A: athrow
		// @14B: goto @1D0
		// @14E: athrow
		// @14F: aload_2
		// @150: getfield int game.C_100121_ud.field_100733_r
		// @153: istore #5
		// @155: aload_3
		// @156: getfield byte[] game.C_100132_td.field_104985_q
		// @159: aload_2
		// @15A: getfield int game.C_100121_ud.field_100718_B
		// @15D: iconst_m1
		// @15E: isub
		// @15F: baload
		// @160: istore #6
		// @162: aload_2
		// @163: getfield int game.C_100121_ud.field_100718_B
		// @166: iconst_m1
		// @167: ixor
		// @168: bipush -2 (0xFE)
		// @16A: aload_3
		// @16B: getfield byte[] game.C_100132_td.field_104985_q
		// @16E: arraylength
		// @16F: iadd
		// @170: iconst_m1
		// @171: ixor
		// @172: if_icmpgt @179
		// @175: goto @1C2
		// @178: athrow
		// @179: aload_3
		// @17A: getfield byte[] game.C_100132_td.field_104985_q
		// @17D: aload_2
		// @17E: getfield int game.C_100121_ud.field_100718_B
		// @181: baload
		// @182: sipush 255 (0x00FF)
		// @185: iand
		// @186: ldc_w 1920189160 (0x7273c2e8)
		// @189: ishl
		// @18A: istore #7
		// @18C: aload_3
		// @18D: getfield byte[] game.C_100132_td.field_104985_q
		// @190: iconst_2
		// @191: aload_2
		// @192: getfield int game.C_100121_ud.field_100718_B
		// @195: iadd
		// @196: baload
		// @197: sipush 255 (0x00FF)
		// @19A: iand
		// @19B: ldc_w -1437081400 (0xaa57e0c8)
		// @19E: ishl
		// @19F: istore #8
		// @1A1: iload #6
		// @1A3: iload #7
		// @1A5: ineg
		// @1A6: iload #5
		// @1A8: iadd
		// @1A9: aload_3
		// @1AA: getfield byte[] game.C_100132_td.field_104985_q
		// @1AD: aload_2
		// @1AE: getfield int game.C_100121_ud.field_100718_B
		// @1B1: iconst_3
		// @1B2: iadd
		// @1B3: baload
		// @1B4: iload #6
		// @1B6: isub
		// @1B7: imul
		// @1B8: iload #8
		// @1BA: iload #7
		// @1BC: ineg
		// @1BD: iadd
		// @1BE: idiv
		// @1BF: iadd
		// @1C0: istore #6
		// @1C2: bipush 32 (0x20)
		// @1C4: iload #4
		// @1C6: iload #6
		// @1C8: imul
		// @1C9: iadd
		// @1CA: ldc_w 1939212518 (0x739608e6)
		// @1CD: ishr
		// @1CE: istore #4
		// @1D0: iload #4
		// @1D2: ireturn
		// @1D3: astore_3
		// @1D4: aload_3
		// @1D5: new java.lang.StringBuilder
		// @1D8: dup
		// @1D9: invokespecial java.lang.StringBuilder.<init>()void
		// @1DC: getstatic java.lang.String[] game.C_100210_qa.field_101065_V
		// @1DF: bipush 23 (0x17)
		// @1E1: aaload
		// @1E2: invokevirtual java.lang.StringBuilder.append(java.lang.String)java.lang.StringBuilder
		// @1E5: iload_1
		// @1E6: invokevirtual java.lang.StringBuilder.append(int)java.lang.StringBuilder
		// @1E9: bipush 44 (0x2C)
		// @1EB: invokevirtual java.lang.StringBuilder.append(char)java.lang.StringBuilder
		// @1EE: aload_2
		// @1EF: ifnull @1FB
		// @1F2: getstatic java.lang.String[] game.C_100210_qa.field_101065_V
		// @1F5: iconst_0
		// @1F6: aaload
		// @1F7: goto @200
		// @1FA: athrow
		// @1FB: getstatic java.lang.String[] game.C_100210_qa.field_101065_V
		// @1FE: iconst_2
		// @1FF: aaload
		// @200: invokevirtual java.lang.StringBuilder.append(java.lang.String)java.lang.StringBuilder
		// @203: bipush 41 (0x29)
		// @205: invokevirtual java.lang.StringBuilder.append(char)java.lang.StringBuilder
		// @208: invokevirtual java.lang.StringBuilder.toString()java.lang.String
		// @20B: invokestatic game.C_100181_cf.func_105695_a(java.lang.Throwable, java.lang.String)game.C_100170_cm
		// @20E: athrow
	}
	
	private final void func_101010_a(int arg0, byte arg1, int arg2, int arg3)
	{
		// @00: iload_2
		// @01: bipush -81 (0xAF)
		// @03: if_icmpeq @26
		// @06: bipush 106 (0x6A)
		// @08: bipush 23 (0x17)
		// @0A: bipush 52 (0x34)
		// @0C: bipush 85 (0x55)
		// @0E: aconst_null
		// @0F: checkcast game.C_100112_r
		// @12: bipush 33 (0x21)
		// @14: bipush -27 (0xE5)
		// @16: bipush -119 (0x89)
		// @18: bipush 114 (0x72)
		// @1A: bipush 70 (0x46)
		// @1C: bipush -35 (0xDD)
		// @1E: bipush -105 (0x97)
		// @20: bipush 28 (0x1C)
		// @22: invokestatic game.C_100210_qa.func_101012_a(int, int, int, int, game.C_100112_r, int, int, int, int, int, int, int, int)game.C_100302_ka
		// @25: pop
		// @26: goto @69
		// @29: astore #5
		// @2B: aload #5
		// @2D: new java.lang.StringBuilder
		// @30: dup
		// @31: invokespecial java.lang.StringBuilder.<init>()void
		// @34: getstatic java.lang.String[] game.C_100210_qa.field_101065_V
		// @37: bipush 31 (0x1F)
		// @39: aaload
		// @3A: invokevirtual java.lang.StringBuilder.append(java.lang.String)java.lang.StringBuilder
		// @3D: iload_1
		// @3E: invokevirtual java.lang.StringBuilder.append(int)java.lang.StringBuilder
		// @41: bipush 44 (0x2C)
		// @43: invokevirtual java.lang.StringBuilder.append(char)java.lang.StringBuilder
		// @46: iload_2
		// @47: invokevirtual java.lang.StringBuilder.append(int)java.lang.StringBuilder
		// @4A: bipush 44 (0x2C)
		// @4C: invokevirtual java.lang.StringBuilder.append(char)java.lang.StringBuilder
		// @4F: iload_3
		// @50: invokevirtual java.lang.StringBuilder.append(int)java.lang.StringBuilder
		// @53: bipush 44 (0x2C)
		// @55: invokevirtual java.lang.StringBuilder.append(char)java.lang.StringBuilder
		// @58: iload #4
		// @5A: invokevirtual java.lang.StringBuilder.append(int)java.lang.StringBuilder
		// @5D: bipush 41 (0x29)
		// @5F: invokevirtual java.lang.StringBuilder.append(char)java.lang.StringBuilder
		// @62: invokevirtual java.lang.StringBuilder.toString()java.lang.String
		// @65: invokestatic game.C_100181_cf.func_105695_a(java.lang.Throwable, java.lang.String)game.C_100170_cm
		// @68: athrow
		// @69: return
	}
	
	private final void func_101030_a(byte arg0, int arg1)
	{
		// @00: getstatic int game.SteelSentinels.field_105275_O
		// @03: istore #4
		// @05: iconst_0
		// @06: iload_2
		// @07: if_icmpgt @0E
		// @0A: goto @26
		// @0D: athrow
		// @0E: iconst_0
		// @0F: istore_2
		// @10: iload_2
		// @11: bipush 16 (0x10)
		// @13: if_icmpge @25
		// @16: aload_0
		// @17: bipush 65 (0x41)
		// @19: iload_2
		// @1A: invokespecial game.C_100210_qa.func_101030_a(byte, int)void
		// @1D: iinc #2 +1
		// @20: iload #4
		// @22: ifeq @10
		// @25: return
		// @26: aload_0
		// @27: getfield int[] game.C_100210_qa.field_101071_o
		// @2A: iload_2
		// @2B: sipush 12800 (0x3200)
		// @2E: iastore
		// @2F: aload_0
		// @30: getfield int[] game.C_100210_qa.field_101053_B
		// @33: iload_2
		// @34: sipush 8192 (0x2000)
		// @37: iastore
		// @38: aload_0
		// @39: getfield int[] game.C_100210_qa.field_101066_Q
		// @3C: iload_2
		// @3D: sipush 16383 (0x3FFF)
		// @40: iastore
		// @41: aload_0
		// @42: getfield int[] game.C_100210_qa.field_101073_v
		// @45: iload_2
		// @46: sipush 8192 (0x2000)
		// @49: iastore
		// @4A: aload_0
		// @4B: getfield int[] game.C_100210_qa.field_101074_u
		// @4E: iload_2
		// @4F: iconst_0
		// @50: iastore
		// @51: aload_0
		// @52: getfield int[] game.C_100210_qa.field_101058_O
		// @55: iload_2
		// @56: sipush 8192 (0x2000)
		// @59: iastore
		// @5A: aload_0
		// @5B: iload_2
		// @5C: bipush -95 (0xA1)
		// @5E: invokespecial game.C_100210_qa.func_101020_a(int, int)void
		// @61: aload_0
		// @62: sipush 21346 (0x5362)
		// @65: iload_2
		// @66: invokespecial game.C_100210_qa.func_101024_c(int, int)void
		// @69: aload_0
		// @6A: getfield int[] game.C_100210_qa.field_101060_I
		// @6D: iload_2
		// @6E: iconst_0
		// @6F: iastore
		// @70: iload_1
		// @71: bipush 65 (0x41)
		// @73: if_icmpeq @85
		// @76: aload_0
		// @77: aconst_null
		// @78: checkcast game.C_100121_ud[][]
		// @7B: checkcast game.C_100121_ud[][]
		// @7E: putfield game.C_100121_ud[][] game.C_100210_qa.field_101070_n
		// @81: goto @85
		// @84: athrow
		// @85: aload_0
		// @86: getfield int[] game.C_100210_qa.field_101069_R
		// @89: iload_2
		// @8A: sipush 32767 (0x7FFF)
		// @8D: iastore
		// @8E: aload_0
		// @8F: getfield int[] game.C_100210_qa.field_101061_J
		// @92: iload_2
		// @93: sipush 256 (0x0100)
		// @96: iastore
		// @97: aload_0
		// @98: getfield int[] game.C_100210_qa.field_101059_H
		// @9B: iload_2
		// @9C: iconst_0
		// @9D: iastore
		// @9E: aload_0
		// @9F: iload_2
		// @A0: sipush 8192 (0x2000)
		// @A3: iconst_1
		// @A4: invokespecial game.C_100210_qa.func_101016_a(int, int, boolean)void
		// @A7: goto @D5
		// @AA: astore_3
		// @AB: aload_3
		// @AC: new java.lang.StringBuilder
		// @AF: dup
		// @B0: invokespecial java.lang.StringBuilder.<init>()void
		// @B3: getstatic java.lang.String[] game.C_100210_qa.field_101065_V
		// @B6: bipush 20 (0x14)
		// @B8: aaload
		// @B9: invokevirtual java.lang.StringBuilder.append(java.lang.String)java.lang.StringBuilder
		// @BC: iload_1
		// @BD: invokevirtual java.lang.StringBuilder.append(int)java.lang.StringBuilder
		// @C0: bipush 44 (0x2C)
		// @C2: invokevirtual java.lang.StringBuilder.append(char)java.lang.StringBuilder
		// @C5: iload_2
		// @C6: invokevirtual java.lang.StringBuilder.append(int)java.lang.StringBuilder
		// @C9: bipush 41 (0x29)
		// @CB: invokevirtual java.lang.StringBuilder.append(char)java.lang.StringBuilder
		// @CE: invokevirtual java.lang.StringBuilder.toString()java.lang.String
		// @D1: invokestatic game.C_100181_cf.func_105695_a(java.lang.Throwable, java.lang.String)game.C_100170_cm
		// @D4: athrow
		// @D5: return
	}
	
	private final void func_101023_b(int arg0, int arg1, int arg2)
	{
		// @00: iload_3
		// @01: iconst_4
		// @02: if_icmpeq @11
		// @05: aload_0
		// @06: bipush -41 (0xD7)
		// @08: bipush -58 (0xC6)
		// @0A: invokespecial game.C_100210_qa.func_101030_a(byte, int)void
		// @0D: goto @11
		// @10: athrow
		// @11: aload_0
		// @12: getfield int[] game.C_100210_qa.field_101073_v
		// @15: iload_2
		// @16: iload_1
		// @17: iastore
		// @18: goto @51
		// @1B: astore #4
		// @1D: aload #4
		// @1F: new java.lang.StringBuilder
		// @22: dup
		// @23: invokespecial java.lang.StringBuilder.<init>()void
		// @26: getstatic java.lang.String[] game.C_100210_qa.field_101065_V
		// @29: bipush 39 (0x27)
		// @2B: aaload
		// @2C: invokevirtual java.lang.StringBuilder.append(java.lang.String)java.lang.StringBuilder
		// @2F: iload_1
		// @30: invokevirtual java.lang.StringBuilder.append(int)java.lang.StringBuilder
		// @33: bipush 44 (0x2C)
		// @35: invokevirtual java.lang.StringBuilder.append(char)java.lang.StringBuilder
		// @38: iload_2
		// @39: invokevirtual java.lang.StringBuilder.append(int)java.lang.StringBuilder
		// @3C: bipush 44 (0x2C)
		// @3E: invokevirtual java.lang.StringBuilder.append(char)java.lang.StringBuilder
		// @41: iload_3
		// @42: invokevirtual java.lang.StringBuilder.append(int)java.lang.StringBuilder
		// @45: bipush 41 (0x29)
		// @47: invokevirtual java.lang.StringBuilder.append(char)java.lang.StringBuilder
		// @4A: invokevirtual java.lang.StringBuilder.toString()java.lang.String
		// @4D: invokestatic game.C_100181_cf.func_105695_a(java.lang.Throwable, java.lang.String)game.C_100170_cm
		// @50: athrow
		// @51: return
	}
	
	static final boolean func_101041_a(C_100278_nd arg0, int arg1)
	{
		// @00: iload_1
		// @01: bipush 72 (0x48)
		// @03: if_icmpge @11
		// @06: aconst_null
		// @07: checkcast game.C_100302_ka
		// @0A: putstatic game.C_100302_ka game.C_100210_qa.field_101054_C
		// @0D: goto @11
		// @10: athrow
		// @11: aload_0
		// @12: iconst_1
		// @13: sipush 15738 (0x3D7A)
		// @16: invokevirtual game.C_100278_nd.func_101195_i(int, int)int
		// @19: iconst_m1
		// @1A: ixor
		// @1B: bipush -2 (0xFE)
		// @1D: if_icmpne @25
		// @20: iconst_1
		// @21: goto @26
		// @24: athrow
		// @25: iconst_0
		// @26: ireturn
		// @27: astore_2
		// @28: aload_2
		// @29: new java.lang.StringBuilder
		// @2C: dup
		// @2D: invokespecial java.lang.StringBuilder.<init>()void
		// @30: getstatic java.lang.String[] game.C_100210_qa.field_101065_V
		// @33: bipush 41 (0x29)
		// @35: aaload
		// @36: invokevirtual java.lang.StringBuilder.append(java.lang.String)java.lang.StringBuilder
		// @39: aload_0
		// @3A: ifnull @46
		// @3D: getstatic java.lang.String[] game.C_100210_qa.field_101065_V
		// @40: iconst_0
		// @41: aaload
		// @42: goto @4B
		// @45: athrow
		// @46: getstatic java.lang.String[] game.C_100210_qa.field_101065_V
		// @49: iconst_2
		// @4A: aaload
		// @4B: invokevirtual java.lang.StringBuilder.append(java.lang.String)java.lang.StringBuilder
		// @4E: bipush 44 (0x2C)
		// @50: invokevirtual java.lang.StringBuilder.append(char)java.lang.StringBuilder
		// @53: iload_1
		// @54: invokevirtual java.lang.StringBuilder.append(int)java.lang.StringBuilder
		// @57: bipush 41 (0x29)
		// @59: invokevirtual java.lang.StringBuilder.append(char)java.lang.StringBuilder
		// @5C: invokevirtual java.lang.StringBuilder.toString()java.lang.String
		// @5F: invokestatic game.C_100181_cf.func_105695_a(java.lang.Throwable, java.lang.String)game.C_100170_cm
		// @62: athrow
	}
	
	final synchronized void func_101035_a(boolean arg0, boolean arg1, C_100002_gf arg2)
	{
		// @00: iload_2
		// @01: ifeq @05
		// @04: return
		// @05: aload_0
		// @06: bipush -101 (0x9B)
		// @08: iconst_1
		// @09: iload_1
		// @0A: aload_3
		// @0B: invokespecial game.C_100210_qa.func_101014_a(byte, boolean, boolean, game.C_100002_gf)void
		// @0E: goto @58
		// @11: astore #4
		// @13: aload #4
		// @15: new java.lang.StringBuilder
		// @18: dup
		// @19: invokespecial java.lang.StringBuilder.<init>()void
		// @1C: getstatic java.lang.String[] game.C_100210_qa.field_101065_V
		// @1F: bipush 36 (0x24)
		// @21: aaload
		// @22: invokevirtual java.lang.StringBuilder.append(java.lang.String)java.lang.StringBuilder
		// @25: iload_1
		// @26: invokevirtual java.lang.StringBuilder.append(boolean)java.lang.StringBuilder
		// @29: bipush 44 (0x2C)
		// @2B: invokevirtual java.lang.StringBuilder.append(char)java.lang.StringBuilder
		// @2E: iload_2
		// @2F: invokevirtual java.lang.StringBuilder.append(boolean)java.lang.StringBuilder
		// @32: bipush 44 (0x2C)
		// @34: invokevirtual java.lang.StringBuilder.append(char)java.lang.StringBuilder
		// @37: aload_3
		// @38: ifnull @44
		// @3B: getstatic java.lang.String[] game.C_100210_qa.field_101065_V
		// @3E: iconst_0
		// @3F: aaload
		// @40: goto @49
		// @43: athrow
		// @44: getstatic java.lang.String[] game.C_100210_qa.field_101065_V
		// @47: iconst_2
		// @48: aaload
		// @49: invokevirtual java.lang.StringBuilder.append(java.lang.String)java.lang.StringBuilder
		// @4C: bipush 41 (0x29)
		// @4E: invokevirtual java.lang.StringBuilder.append(char)java.lang.StringBuilder
		// @51: invokevirtual java.lang.StringBuilder.toString()java.lang.String
		// @54: invokestatic game.C_100181_cf.func_105695_a(java.lang.Throwable, java.lang.String)game.C_100170_cm
		// @57: athrow
		// @58: return
	}
	
	public C_100210_qa()
	{
		// @00: aload_0
		// @01: invokespecial game.C_100261_md.<init>()void
		// @04: aload_0
		// @05: bipush 16 (0x10)
		// @07: sipush 128 (0x0080)
		// @0A: multianewarray game.C_100121_ud[][] (init: 2)
		// @0E: putfield game.C_100121_ud[][] game.C_100210_qa.field_101078_q
		// @11: aload_0
		// @12: bipush 16 (0x10)
		// @14: newarray int[]
		// @16: putfield int[] game.C_100210_qa.field_101075_t
		// @19: aload_0
		// @1A: bipush 16 (0x10)
		// @1C: newarray int[]
		// @1E: putfield int[] game.C_100210_qa.field_101053_B
		// @21: aload_0
		// @22: bipush 16 (0x10)
		// @24: newarray int[]
		// @26: putfield int[] game.C_100210_qa.field_101077_r
		// @29: aload_0
		// @2A: bipush 16 (0x10)
		// @2C: newarray int[]
		// @2E: putfield int[] game.C_100210_qa.field_101079_p
		// @31: aload_0
		// @32: bipush 16 (0x10)
		// @34: newarray int[]
		// @36: putfield int[] game.C_100210_qa.field_101059_H
		// @39: aload_0
		// @3A: bipush 16 (0x10)
		// @3C: newarray int[]
		// @3E: putfield int[] game.C_100210_qa.field_101060_I
		// @41: aload_0
		// @42: bipush 16 (0x10)
		// @44: newarray int[]
		// @46: putfield int[] game.C_100210_qa.field_101062_K
		// @49: aload_0
		// @4A: sipush 256 (0x0100)
		// @4D: putfield int game.C_100210_qa.field_101064_T
		// @50: aload_0
		// @51: bipush 16 (0x10)
		// @53: newarray int[]
		// @55: putfield int[] game.C_100210_qa.field_101066_Q
		// @58: aload_0
		// @59: bipush 16 (0x10)
		// @5B: sipush 128 (0x0080)
		// @5E: multianewarray game.C_100121_ud[][] (init: 2)
		// @62: putfield game.C_100121_ud[][] game.C_100210_qa.field_101070_n
		// @65: aload_0
		// @66: bipush 16 (0x10)
		// @68: newarray int[]
		// @6A: putfield int[] game.C_100210_qa.field_101058_O
		// @6D: aload_0
		// @6E: bipush 16 (0x10)
		// @70: newarray int[]
		// @72: putfield int[] game.C_100210_qa.field_101052_A
		// @75: aload_0
		// @76: bipush 16 (0x10)
		// @78: newarray int[]
		// @7A: putfield int[] game.C_100210_qa.field_101081_y
		// @7D: aload_0
		// @7E: ldc_w 1000000 (0xf4240)
		// @81: putfield int game.C_100210_qa.field_101067_P
		// @84: aload_0
		// @85: bipush 16 (0x10)
		// @87: newarray int[]
		// @89: putfield int[] game.C_100210_qa.field_101074_u
		// @8C: aload_0
		// @8D: bipush 16 (0x10)
		// @8F: newarray int[]
		// @91: putfield int[] game.C_100210_qa.field_101073_v
		// @94: aload_0
		// @95: bipush 16 (0x10)
		// @97: newarray int[]
		// @99: putfield int[] game.C_100210_qa.field_101061_J
		// @9C: aload_0
		// @9D: bipush 16 (0x10)
		// @9F: newarray int[]
		// @A1: putfield int[] game.C_100210_qa.field_101069_R
		// @A4: aload_0
		// @A5: bipush 16 (0x10)
		// @A7: newarray int[]
		// @A9: putfield int[] game.C_100210_qa.field_101071_o
		// @AC: aload_0
		// @AD: new game.C_100014_wg
		// @B0: dup
		// @B1: invokespecial game.C_100014_wg.<init>()void
		// @B4: putfield game.C_100014_wg game.C_100210_qa.field_101072_w
		// @B7: aload_0
		// @B8: new game.C_100044_vm
		// @BB: dup
		// @BC: aload_0
		// @BD: invokespecial game.C_100044_vm.<init>(game.C_100210_qa)void
		// @C0: putfield game.C_100044_vm game.C_100210_qa.field_101051_G
		// @C3: aload_0
		// @C4: new game.C_100119_ua
		// @C7: dup
		// @C8: sipush 128 (0x0080)
		// @CB: invokespecial game.C_100119_ua.<init>(int)void
		// @CE: putfield game.C_100119_ua game.C_100210_qa.field_101057_N
		// @D1: aload_0
		// @D2: sipush 256 (0x0100)
		// @D5: iconst_m1
		// @D6: sipush 8192 (0x2000)
		// @D9: invokevirtual game.C_100210_qa.func_101025_c(int, int, int)void
		// @DC: aload_0
		// @DD: iconst_1
		// @DE: bipush -61 (0xC3)
		// @E0: invokespecial game.C_100210_qa.func_101022_a(boolean, int)void
		// @E3: goto @F2
		// @E6: astore_1
		// @E7: aload_1
		// @E8: getstatic java.lang.String[] game.C_100210_qa.field_101065_V
		// @EB: bipush 42 (0x2A)
		// @ED: aaload
		// @EE: invokestatic game.C_100181_cf.func_105695_a(java.lang.Throwable, java.lang.String)game.C_100170_cm
		// @F1: athrow
		// @F2: return
	}
	
	static
	{
		// @000: bipush 45 (0x2D)
		// @002: anewarray java.lang.String
		// @005: dup
		// @006: iconst_0
		// @007: ldc "\u001e2\n\u0001s"
		// @009: invokestatic game.C_100210_qa.func_101029_z(java.lang.String)char[]
		// @00C: invokestatic game.C_100210_qa.func_101013_z(char[])java.lang.String
		// @00F: aastore
		// @010: dup
		// @011: iconst_1
		// @012: ldc_w "\u0014}\n{OM"
		// @015: invokestatic game.C_100210_qa.func_101029_z(java.lang.String)char[]
		// @018: invokestatic game.C_100210_qa.func_101013_z(char[])java.lang.String
		// @01B: aastore
		// @01C: dup
		// @01D: iconst_2
		// @01E: ldc "\u000biHC"
		// @020: invokestatic game.C_100210_qa.func_101029_z(java.lang.String)char[]
		// @023: invokestatic game.C_100210_qa.func_101013_z(char[])java.lang.String
		// @026: aastore
		// @027: dup
		// @028: iconst_3
		// @029: ldc "\u0014}\nmLM"
		// @02B: invokestatic game.C_100210_qa.func_101029_z(java.lang.String)char[]
		// @02E: invokestatic game.C_100210_qa.func_101013_z(char[])java.lang.String
		// @031: aastore
		// @032: dup
		// @033: iconst_4
		// @034: ldc "\u0014}\n|OM"
		// @036: invokestatic game.C_100210_qa.func_101029_z(java.lang.String)char[]
		// @039: invokestatic game.C_100210_qa.func_101013_z(char[])java.lang.String
		// @03C: aastore
		// @03D: dup
		// @03E: iconst_5
		// @03F: ldc "\u0014}\nlLM"
		// @041: invokestatic game.C_100210_qa.func_101029_z(java.lang.String)char[]
		// @044: invokestatic game.C_100210_qa.func_101013_z(char[])java.lang.String
		// @047: aastore
		// @048: dup
		// @049: bipush 6 (0x06)
		// @04B: ldc "\u0014}\nk&L"
		// @04D: invokestatic game.C_100210_qa.func_101029_z(java.lang.String)char[]
		// @050: invokestatic game.C_100210_qa.func_101013_z(char[])java.lang.String
		// @053: aastore
		// @054: dup
		// @055: bipush 7 (0x07)
		// @057: ldc_w "\u0014}\naOM"
		// @05A: invokestatic game.C_100210_qa.func_101029_z(java.lang.String)char[]
		// @05D: invokestatic game.C_100210_qa.func_101013_z(char[])java.lang.String
		// @060: aastore
		// @061: dup
		// @062: bipush 8 (0x08)
		// @064: ldc_w "\u0014}\nf&"
		// @067: invokestatic game.C_100210_qa.func_101029_z(java.lang.String)char[]
		// @06A: invokestatic game.C_100210_qa.func_101013_z(char[])java.lang.String
		// @06D: aastore
		// @06E: dup
		// @06F: bipush 9 (0x09)
		// @071: ldc "\u0014}\n~&"
		// @073: invokestatic game.C_100210_qa.func_101029_z(java.lang.String)char[]
		// @076: invokestatic game.C_100210_qa.func_101013_z(char[])java.lang.String
		// @079: aastore
		// @07A: dup
		// @07B: bipush 10 (0x0A)
		// @07D: ldc "\u0014}\neOM"
		// @07F: invokestatic game.C_100210_qa.func_101029_z(java.lang.String)char[]
		// @082: invokestatic game.C_100210_qa.func_101013_z(char[])java.lang.String
		// @085: aastore
		// @086: dup
		// @087: bipush 11 (0x0B)
		// @089: ldc "\u0014}\ncOM"
		// @08B: invokestatic game.C_100210_qa.func_101029_z(java.lang.String)char[]
		// @08E: invokestatic game.C_100210_qa.func_101013_z(char[])java.lang.String
		// @091: aastore
		// @092: dup
		// @093: bipush 12 (0x0C)
		// @095: ldc_w "\u0014}\ngOM"
		// @098: invokestatic game.C_100210_qa.func_101029_z(java.lang.String)char[]
		// @09B: invokestatic game.C_100210_qa.func_101013_z(char[])java.lang.String
		// @09E: aastore
		// @09F: dup
		// @0A0: bipush 13 (0x0D)
		// @0A2: ldc_w "\u0014}\ny&"
		// @0A5: invokestatic game.C_100210_qa.func_101029_z(java.lang.String)char[]
		// @0A8: invokestatic game.C_100210_qa.func_101013_z(char[])java.lang.String
		// @0AB: aastore
		// @0AC: dup
		// @0AD: bipush 14 (0x0E)
		// @0AF: ldc "\u0014}\ndOM"
		// @0B1: invokestatic game.C_100210_qa.func_101029_z(java.lang.String)char[]
		// @0B4: invokestatic game.C_100210_qa.func_101013_z(char[])java.lang.String
		// @0B7: aastore
		// @0B8: dup
		// @0B9: bipush 15 (0x0F)
		// @0BB: ldc "\u0014}\nkLM"
		// @0BD: invokestatic game.C_100210_qa.func_101029_z(java.lang.String)char[]
		// @0C0: invokestatic game.C_100210_qa.func_101013_z(char[])java.lang.String
		// @0C3: aastore
		// @0C4: dup
		// @0C5: bipush 16 (0x10)
		// @0C7: ldc "\u0014}\nnOM"
		// @0C9: invokestatic game.C_100210_qa.func_101029_z(java.lang.String)char[]
		// @0CC: invokestatic game.C_100210_qa.func_101013_z(char[])java.lang.String
		// @0CF: aastore
		// @0D0: dup
		// @0D1: bipush 17 (0x11)
		// @0D3: ldc_w "\u0014}\n}&"
		// @0D6: invokestatic game.C_100210_qa.func_101029_z(java.lang.String)char[]
		// @0D9: invokestatic game.C_100210_qa.func_101013_z(char[])java.lang.String
		// @0DC: aastore
		// @0DD: dup
		// @0DE: bipush 18 (0x12)
		// @0E0: ldc_w "\u0014}\nnLM"
		// @0E3: invokestatic game.C_100210_qa.func_101029_z(java.lang.String)char[]
		// @0E6: invokestatic game.C_100210_qa.func_101013_z(char[])java.lang.String
		// @0E9: aastore
		// @0EA: dup
		// @0EB: bipush 19 (0x13)
		// @0ED: ldc_w "\u0014}\ng&"
		// @0F0: invokestatic game.C_100210_qa.func_101029_z(java.lang.String)char[]
		// @0F3: invokestatic game.C_100210_qa.func_101013_z(char[])java.lang.String
		// @0F6: aastore
		// @0F7: dup
		// @0F8: bipush 20 (0x14)
		// @0FA: ldc_w "\u0014}\nhOM"
		// @0FD: invokestatic game.C_100210_qa.func_101029_z(java.lang.String)char[]
		// @100: invokestatic game.C_100210_qa.func_101013_z(char[])java.lang.String
		// @103: aastore
		// @104: dup
		// @105: bipush 21 (0x15)
		// @107: ldc "\u0014}\n~OM"
		// @109: invokestatic game.C_100210_qa.func_101029_z(java.lang.String)char[]
		// @10C: invokestatic game.C_100210_qa.func_101013_z(char[])java.lang.String
		// @10F: aastore
		// @110: dup
		// @111: bipush 22 (0x16)
		// @113: ldc "\u0014}\njLM"
		// @115: invokestatic game.C_100210_qa.func_101029_z(java.lang.String)char[]
		// @118: invokestatic game.C_100210_qa.func_101013_z(char[])java.lang.String
		// @11B: aastore
		// @11C: dup
		// @11D: bipush 23 (0x17)
		// @11F: ldc_w "\u0014}\n`OM"
		// @122: invokestatic game.C_100210_qa.func_101029_z(java.lang.String)char[]
		// @125: invokestatic game.C_100210_qa.func_101013_z(char[])java.lang.String
		// @128: aastore
		// @129: dup
		// @12A: bipush 24 (0x18)
		// @12C: ldc_w "\u0014}\nkOM"
		// @12F: invokestatic game.C_100210_qa.func_101029_z(java.lang.String)char[]
		// @132: invokestatic game.C_100210_qa.func_101013_z(char[])java.lang.String
		// @135: aastore
		// @136: dup
		// @137: bipush 25 (0x19)
		// @139: ldc "\u0014}\nx&"
		// @13B: invokestatic game.C_100210_qa.func_101029_z(java.lang.String)char[]
		// @13E: invokestatic game.C_100210_qa.func_101013_z(char[])java.lang.String
		// @141: aastore
		// @142: dup
		// @143: bipush 26 (0x1A)
		// @145: ldc_w "\u0014}\nj&L"
		// @148: invokestatic game.C_100210_qa.func_101029_z(java.lang.String)char[]
		// @14B: invokestatic game.C_100210_qa.func_101013_z(char[])java.lang.String
		// @14E: aastore
		// @14F: dup
		// @150: bipush 27 (0x1B)
		// @152: ldc "\u0014}\nbOM"
		// @154: invokestatic game.C_100210_qa.func_101029_z(java.lang.String)char[]
		// @157: invokestatic game.C_100210_qa.func_101013_z(char[])java.lang.String
		// @15A: aastore
		// @15B: dup
		// @15C: bipush 28 (0x1C)
		// @15E: ldc "\u0014}\nzOM"
		// @160: invokestatic game.C_100210_qa.func_101029_z(java.lang.String)char[]
		// @163: invokestatic game.C_100210_qa.func_101013_z(char[])java.lang.String
		// @166: aastore
		// @167: dup
		// @168: bipush 29 (0x1D)
		// @16A: ldc_w "\u0014}\nm&"
		// @16D: invokestatic game.C_100210_qa.func_101029_z(java.lang.String)char[]
		// @170: invokestatic game.C_100210_qa.func_101013_z(char[])java.lang.String
		// @173: aastore
		// @174: dup
		// @175: bipush 30 (0x1E)
		// @177: ldc_w "\u0014}\n|&"
		// @17A: invokestatic game.C_100210_qa.func_101029_z(java.lang.String)char[]
		// @17D: invokestatic game.C_100210_qa.func_101013_z(char[])java.lang.String
		// @180: aastore
		// @181: dup
		// @182: bipush 31 (0x1F)
		// @184: ldc_w "\u0014}\nz&"
		// @187: invokestatic game.C_100210_qa.func_101029_z(java.lang.String)char[]
		// @18A: invokestatic game.C_100210_qa.func_101013_z(char[])java.lang.String
		// @18D: aastore
		// @18E: dup
		// @18F: bipush 32 (0x20)
		// @191: ldc_w "\u0014}\nmOM"
		// @194: invokestatic game.C_100210_qa.func_101029_z(java.lang.String)char[]
		// @197: invokestatic game.C_100210_qa.func_101013_z(char[])java.lang.String
		// @19A: aastore
		// @19B: dup
		// @19C: bipush 33 (0x21)
		// @19E: ldc "\u0014}\nlOM"
		// @1A0: invokestatic game.C_100210_qa.func_101029_z(java.lang.String)char[]
		// @1A3: invokestatic game.C_100210_qa.func_101013_z(char[])java.lang.String
		// @1A6: aastore
		// @1A7: dup
		// @1A8: bipush 34 (0x22)
		// @1AA: ldc "\u0014}\niOM"
		// @1AC: invokestatic game.C_100210_qa.func_101029_z(java.lang.String)char[]
		// @1AF: invokestatic game.C_100210_qa.func_101013_z(char[])java.lang.String
		// @1B2: aastore
		// @1B3: dup
		// @1B4: bipush 35 (0x23)
		// @1B6: ldc "\u0014}\nn&"
		// @1B8: invokestatic game.C_100210_qa.func_101029_z(java.lang.String)char[]
		// @1BB: invokestatic game.C_100210_qa.func_101013_z(char[])java.lang.String
		// @1BE: aastore
		// @1BF: dup
		// @1C0: bipush 36 (0x24)
		// @1C2: ldc_w "\u0014}\nyOM"
		// @1C5: invokestatic game.C_100210_qa.func_101029_z(java.lang.String)char[]
		// @1C8: invokestatic game.C_100210_qa.func_101013_z(char[])java.lang.String
		// @1CB: aastore
		// @1CC: dup
		// @1CD: bipush 37 (0x25)
		// @1CF: ldc "\u0014}\n{&"
		// @1D1: invokestatic game.C_100210_qa.func_101029_z(java.lang.String)char[]
		// @1D4: invokestatic game.C_100210_qa.func_101013_z(char[])java.lang.String
		// @1D7: aastore
		// @1D8: dup
		// @1D9: bipush 38 (0x26)
		// @1DB: ldc "\u0014}\ni&L"
		// @1DD: invokestatic game.C_100210_qa.func_101029_z(java.lang.String)char[]
		// @1E0: invokestatic game.C_100210_qa.func_101013_z(char[])java.lang.String
		// @1E3: aastore
		// @1E4: dup
		// @1E5: bipush 39 (0x27)
		// @1E7: ldc_w "\u0014}\nfOM"
		// @1EA: invokestatic game.C_100210_qa.func_101029_z(java.lang.String)char[]
		// @1ED: invokestatic game.C_100210_qa.func_101013_z(char[])java.lang.String
		// @1F0: aastore
		// @1F1: dup
		// @1F2: bipush 40 (0x28)
		// @1F4: ldc "\u0014}\njOM"
		// @1F6: invokestatic game.C_100210_qa.func_101029_z(java.lang.String)char[]
		// @1F9: invokestatic game.C_100210_qa.func_101013_z(char[])java.lang.String
		// @1FC: aastore
		// @1FD: dup
		// @1FE: bipush 41 (0x29)
		// @200: ldc_w "\u0014}\nxOM"
		// @203: invokestatic game.C_100210_qa.func_101029_z(java.lang.String)char[]
		// @206: invokestatic game.C_100210_qa.func_101013_z(char[])java.lang.String
		// @209: aastore
		// @20A: dup
		// @20B: bipush 42 (0x2A)
		// @20D: ldc_w "\u0014}\n\u0013g\u000buP\u0011&L"
		// @210: invokestatic game.C_100210_qa.func_101029_z(java.lang.String)char[]
		// @213: invokestatic game.C_100210_qa.func_101013_z(char[])java.lang.String
		// @216: aastore
		// @217: dup
		// @218: bipush 43 (0x2B)
		// @21A: ldc "\u0014}\n\u007fOM"
		// @21C: invokestatic game.C_100210_qa.func_101029_z(java.lang.String)char[]
		// @21F: invokestatic game.C_100210_qa.func_101013_z(char[])java.lang.String
		// @222: aastore
		// @223: dup
		// @224: bipush 44 (0x2C)
		// @226: ldc_w "\u0014}\n}OM"
		// @229: invokestatic game.C_100210_qa.func_101029_z(java.lang.String)char[]
		// @22C: invokestatic game.C_100210_qa.func_101013_z(char[])java.lang.String
		// @22F: aastore
		// @230: putstatic java.lang.String[] game.C_100210_qa.field_101065_V
		// @233: ldc_w "7yPZ|\u000b<P@.\u0002}IJ"
		// @236: invokestatic game.C_100210_qa.func_101029_z(java.lang.String)char[]
		// @239: invokestatic game.C_100210_qa.func_101013_z(char[])java.lang.String
		// @23C: putstatic java.lang.String game.C_100210_qa.field_101049_E
		// @23F: return
	}
	
	private static char[] func_101029_z(String arg0)
	{
		// @00: aload_0
		// @01: invokevirtual java.lang.String.toCharArray()char[]
		// @04: dup
		// @05: arraylength
		// @06: iconst_2
		// @07: if_icmpge @13
		// @0A: dup
		// @0B: iconst_0
		// @0C: dup2
		// @0D: caload
		// @0E: bipush 14 (0x0E)
		// @10: ixor
		// @11: i2c
		// @12: castore
		// @13: areturn
	}
	
	private static String func_101013_z(char[] arg0)
	{
		// @00: aload_0
		// @01: dup
		// @02: arraylength
		// @03: swap
		// @04: iconst_0
		// @05: istore_1
		// @06: goto @4C
		// @09: dup
		// @0A: iload_1
		// @0B: dup2
		// @0C: caload
		// @0D: iload_1
		// @0E: iconst_5
		// @0F: irem
		// @10: tableswitch def: @44, for 0: @30, for 1: @35, for 2: @3A, for 3: @3F
		// @30: bipush 101 (0x65)
		// @32: goto @46
		// @35: bipush 28 (0x1C)
		// @37: goto @46
		// @3A: bipush 36 (0x24)
		// @3C: goto @46
		// @3F: bipush 47 (0x2F)
		// @41: goto @46
		// @44: bipush 14 (0x0E)
		// @46: ixor
		// @47: i2c
		// @48: castore
		// @49: iinc #1 +1
		// @4C: swap
		// @4D: dup_x1
		// @4E: iload_1
		// @4F: if_icmpgt @09
		// @52: new java.lang.String
		// @55: dup_x1
		// @56: swap
		// @57: invokespecial java.lang.String.<init>(char[])void
		// @5A: invokevirtual java.lang.String.intern()java.lang.String
		// @5D: areturn
	}
}
