package game;

abstract class C_100316_lc extends C_100325_id
{
	static int field_102412_u;
	static String field_102413_t;
	static C_100037_wb[] field_102411_v;
	static int field_102407_A;
	static C_100302_ka field_102409_C;
	static String field_102415_z;
	int field_102414_s;
	static int field_102416_y;
	static String field_102408_B;
	static C_100115_ej field_102410_w;
	static int[] field_102405_E;
	static C_100302_ka field_102404_D;
	static C_100201_qj field_102417_x;
	private static final String[] field_102406_F;
	
	abstract boolean func_102402_i(int arg0);
	
	public static void func_102403_e(byte arg0)
	{
		// @00: aconst_null
		// @01: putstatic java.lang.String game.C_100316_lc.field_102413_t
		// @04: aconst_null
		// @05: putstatic game.C_100302_ka game.C_100316_lc.field_102404_D
		// @08: aconst_null
		// @09: putstatic game.C_100201_qj game.C_100316_lc.field_102417_x
		// @0C: iload_0
		// @0D: bipush 47 (0x2F)
		// @0F: if_icmpgt @1D
		// @12: aconst_null
		// @13: checkcast game.C_100201_qj
		// @16: putstatic game.C_100201_qj game.C_100316_lc.field_102417_x
		// @19: goto @1D
		// @1C: athrow
		// @1D: aconst_null
		// @1E: putstatic game.C_100302_ka game.C_100316_lc.field_102409_C
		// @21: aconst_null
		// @22: putstatic int[] game.C_100316_lc.field_102405_E
		// @25: aconst_null
		// @26: putstatic java.lang.String game.C_100316_lc.field_102415_z
		// @29: aconst_null
		// @2A: putstatic game.C_100115_ej game.C_100316_lc.field_102410_w
		// @2D: aconst_null
		// @2E: putstatic game.C_100037_wb[] game.C_100316_lc.field_102411_v
		// @31: aconst_null
		// @32: putstatic java.lang.String game.C_100316_lc.field_102408_B
		// @35: goto @59
		// @38: astore_1
		// @39: aload_1
		// @3A: new java.lang.StringBuilder
		// @3D: dup
		// @3E: invokespecial java.lang.StringBuilder.<init>()void
		// @41: getstatic java.lang.String[] game.C_100316_lc.field_102406_F
		// @44: iconst_4
		// @45: aaload
		// @46: invokevirtual java.lang.StringBuilder.append(java.lang.String)java.lang.StringBuilder
		// @49: iload_0
		// @4A: invokevirtual java.lang.StringBuilder.append(int)java.lang.StringBuilder
		// @4D: bipush 41 (0x29)
		// @4F: invokevirtual java.lang.StringBuilder.append(char)java.lang.StringBuilder
		// @52: invokevirtual java.lang.StringBuilder.toString()java.lang.String
		// @55: invokestatic game.C_100181_cf.func_105695_a(java.lang.Throwable, java.lang.String)game.C_100170_cm
		// @58: athrow
		// @59: return
	}
	
	static final String func_102399_d(byte arg0)
	{
		// @000: getstatic int game.SteelSentinels.field_105275_O
		// @003: istore #5
		// @005: new java.lang.StringBuilder
		// @008: dup
		// @009: invokespecial java.lang.StringBuilder.<init>()void
		// @00C: ldc "("
		// @00E: invokevirtual java.lang.StringBuilder.append(java.lang.String)java.lang.StringBuilder
		// @011: getstatic int game.C_100119_ua.field_104907_k
		// @014: invokevirtual java.lang.StringBuilder.append(int)java.lang.StringBuilder
		// @017: ldc " "
		// @019: invokevirtual java.lang.StringBuilder.append(java.lang.String)java.lang.StringBuilder
		// @01C: getstatic int game.C_100061_dh.field_101980_gc
		// @01F: invokevirtual java.lang.StringBuilder.append(int)java.lang.StringBuilder
		// @022: ldc " "
		// @024: invokevirtual java.lang.StringBuilder.append(java.lang.String)java.lang.StringBuilder
		// @027: getstatic int game.C_100041_wf.field_104107_c
		// @02A: invokevirtual java.lang.StringBuilder.append(int)java.lang.StringBuilder
		// @02D: getstatic java.lang.String[] game.C_100316_lc.field_102406_F
		// @030: bipush 6 (0x06)
		// @032: aaload
		// @033: invokevirtual java.lang.StringBuilder.append(java.lang.String)java.lang.StringBuilder
		// @036: getstatic int game.C_100299_kd.field_107051_z
		// @039: invokevirtual java.lang.StringBuilder.append(int)java.lang.StringBuilder
		// @03C: invokevirtual java.lang.StringBuilder.toString()java.lang.String
		// @03F: astore_1
		// @040: iload_0
		// @041: bipush 56 (0x38)
		// @043: if_icmpgt @051
		// @046: aconst_null
		// @047: checkcast int[]
		// @04A: putstatic int[] game.C_100316_lc.field_102405_E
		// @04D: goto @051
		// @050: athrow
		// @051: getstatic int game.C_100056_de.field_103194_Y
		// @054: ifgt @05B
		// @057: goto @115
		// @05A: athrow
		// @05B: new java.lang.StringBuilder
		// @05E: dup
		// @05F: invokespecial java.lang.StringBuilder.<init>()void
		// @062: aload_1
		// @063: invokevirtual java.lang.StringBuilder.append(java.lang.String)java.lang.StringBuilder
		// @066: ldc ":"
		// @068: invokevirtual java.lang.StringBuilder.append(java.lang.String)java.lang.StringBuilder
		// @06B: invokevirtual java.lang.StringBuilder.toString()java.lang.String
		// @06E: astore_1
		// @06F: iconst_0
		// @070: istore_2
		// @071: iload_2
		// @072: iconst_m1
		// @073: ixor
		// @074: getstatic int game.C_100056_de.field_103194_Y
		// @077: iconst_m1
		// @078: ixor
		// @079: if_icmple @115
		// @07C: new java.lang.StringBuilder
		// @07F: dup
		// @080: invokespecial java.lang.StringBuilder.<init>()void
		// @083: aload_1
		// @084: invokevirtual java.lang.StringBuilder.append(java.lang.String)java.lang.StringBuilder
		// @087: bipush 32 (0x20)
		// @089: invokevirtual java.lang.StringBuilder.append(char)java.lang.StringBuilder
		// @08C: invokevirtual java.lang.StringBuilder.toString()java.lang.String
		// @08F: iload #5
		// @091: ifne @116
		// @094: astore_1
		// @095: sipush 255 (0x00FF)
		// @098: getstatic game.C_100278_nd game.C_100288_jn.field_106839_f
		// @09B: getfield byte[] game.C_100278_nd.field_101179_l
		// @09E: iload_2
		// @09F: baload
		// @0A0: iand
		// @0A1: istore_3
		// @0A2: iload_3
		// @0A3: ldc 480023012 (0x1c9c91e4)
		// @0A5: ishr
		// @0A6: istore #4
		// @0A8: iload_3
		// @0A9: bipush 15 (0x0F)
		// @0AB: iand
		// @0AC: istore_3
		// @0AD: bipush -11 (0xF5)
		// @0AF: iload #4
		// @0B1: iconst_m1
		// @0B2: ixor
		// @0B3: if_icmpge @0C2
		// @0B6: iinc #4 +48
		// @0B9: iload #5
		// @0BB: ifeq @0C9
		// @0BE: goto @0C2
		// @0C1: athrow
		// @0C2: iinc #4 +55
		// @0C5: goto @0C9
		// @0C8: athrow
		// @0C9: new java.lang.StringBuilder
		// @0CC: dup
		// @0CD: invokespecial java.lang.StringBuilder.<init>()void
		// @0D0: aload_1
		// @0D1: invokevirtual java.lang.StringBuilder.append(java.lang.String)java.lang.StringBuilder
		// @0D4: iload #4
		// @0D6: i2c
		// @0D7: invokevirtual java.lang.StringBuilder.append(char)java.lang.StringBuilder
		// @0DA: invokevirtual java.lang.StringBuilder.toString()java.lang.String
		// @0DD: astore_1
		// @0DE: iload_3
		// @0DF: iconst_m1
		// @0E0: ixor
		// @0E1: bipush -11 (0xF5)
		// @0E3: if_icmpgt @0F2
		// @0E6: iinc #3 +55
		// @0E9: iload #5
		// @0EB: ifeq @0F9
		// @0EE: goto @0F2
		// @0F1: athrow
		// @0F2: iinc #3 +48
		// @0F5: goto @0F9
		// @0F8: athrow
		// @0F9: new java.lang.StringBuilder
		// @0FC: dup
		// @0FD: invokespecial java.lang.StringBuilder.<init>()void
		// @100: aload_1
		// @101: invokevirtual java.lang.StringBuilder.append(java.lang.String)java.lang.StringBuilder
		// @104: iload_3
		// @105: i2c
		// @106: invokevirtual java.lang.StringBuilder.append(char)java.lang.StringBuilder
		// @109: invokevirtual java.lang.StringBuilder.toString()java.lang.String
		// @10C: astore_1
		// @10D: iinc #2 +1
		// @110: iload #5
		// @112: ifeq @071
		// @115: aload_1
		// @116: areturn
		// @117: astore_1
		// @118: aload_1
		// @119: new java.lang.StringBuilder
		// @11C: dup
		// @11D: invokespecial java.lang.StringBuilder.<init>()void
		// @120: getstatic java.lang.String[] game.C_100316_lc.field_102406_F
		// @123: iconst_5
		// @124: aaload
		// @125: invokevirtual java.lang.StringBuilder.append(java.lang.String)java.lang.StringBuilder
		// @128: iload_0
		// @129: invokevirtual java.lang.StringBuilder.append(int)java.lang.StringBuilder
		// @12C: bipush 41 (0x29)
		// @12E: invokevirtual java.lang.StringBuilder.append(char)java.lang.StringBuilder
		// @131: invokevirtual java.lang.StringBuilder.toString()java.lang.String
		// @134: invokestatic game.C_100181_cf.func_105695_a(java.lang.Throwable, java.lang.String)game.C_100170_cm
		// @137: athrow
	}
	
	static final void func_102397_a(int arg0, int arg1, String arg2)
	{
		// @00: getstatic int game.C_100260_mc.field_102239_mc
		// @03: putstatic int game.C_100342_jg.field_102722_Ub
		// @06: iload_0
		// @07: putstatic int game.C_100211_qd.field_102163_qc
		// @0A: iload_1
		// @0B: bipush -111 (0x91)
		// @0D: if_icmplt @17
		// @10: aconst_null
		// @11: checkcast game.C_100302_ka
		// @14: putstatic game.C_100302_ka game.C_100316_lc.field_102404_D
		// @17: goto @5E
		// @1A: astore_3
		// @1B: aload_3
		// @1C: new java.lang.StringBuilder
		// @1F: dup
		// @20: invokespecial java.lang.StringBuilder.<init>()void
		// @23: getstatic java.lang.String[] game.C_100316_lc.field_102406_F
		// @26: iconst_1
		// @27: aaload
		// @28: invokevirtual java.lang.StringBuilder.append(java.lang.String)java.lang.StringBuilder
		// @2B: iload_0
		// @2C: invokevirtual java.lang.StringBuilder.append(int)java.lang.StringBuilder
		// @2F: bipush 44 (0x2C)
		// @31: invokevirtual java.lang.StringBuilder.append(char)java.lang.StringBuilder
		// @34: iload_1
		// @35: invokevirtual java.lang.StringBuilder.append(int)java.lang.StringBuilder
		// @38: bipush 44 (0x2C)
		// @3A: invokevirtual java.lang.StringBuilder.append(char)java.lang.StringBuilder
		// @3D: aload_2
		// @3E: ifnull @4A
		// @41: getstatic java.lang.String[] game.C_100316_lc.field_102406_F
		// @44: iconst_2
		// @45: aaload
		// @46: goto @4F
		// @49: athrow
		// @4A: getstatic java.lang.String[] game.C_100316_lc.field_102406_F
		// @4D: iconst_3
		// @4E: aaload
		// @4F: invokevirtual java.lang.StringBuilder.append(java.lang.String)java.lang.StringBuilder
		// @52: bipush 41 (0x29)
		// @54: invokevirtual java.lang.StringBuilder.append(char)java.lang.StringBuilder
		// @57: invokevirtual java.lang.StringBuilder.toString()java.lang.String
		// @5A: invokestatic game.C_100181_cf.func_105695_a(java.lang.Throwable, java.lang.String)game.C_100170_cm
		// @5D: athrow
		// @5E: return
	}
	
	C_100316_lc(int arg0)
	{
		// @00: aload_0
		// @01: invokespecial game.C_100325_id.<init>()void
		// @04: aload_0
		// @05: iload_1
		// @06: putfield int game.C_100316_lc.field_102414_s
		// @09: goto @2D
		// @0C: astore_2
		// @0D: aload_2
		// @0E: new java.lang.StringBuilder
		// @11: dup
		// @12: invokespecial java.lang.StringBuilder.<init>()void
		// @15: getstatic java.lang.String[] game.C_100316_lc.field_102406_F
		// @18: iconst_0
		// @19: aaload
		// @1A: invokevirtual java.lang.StringBuilder.append(java.lang.String)java.lang.StringBuilder
		// @1D: iload_1
		// @1E: invokevirtual java.lang.StringBuilder.append(int)java.lang.StringBuilder
		// @21: bipush 41 (0x29)
		// @23: invokevirtual java.lang.StringBuilder.append(char)java.lang.StringBuilder
		// @26: invokevirtual java.lang.StringBuilder.toString()java.lang.String
		// @29: invokestatic game.C_100181_cf.func_105695_a(java.lang.Throwable, java.lang.String)game.C_100170_cm
		// @2C: athrow
		// @2D: return
	}
	
	abstract Object func_102398_j(int arg0);
	
	static
	{
		// @00: bipush 7 (0x07)
		// @02: anewarray java.lang.String
		// @05: dup
		// @06: iconst_0
		// @07: ldc "ft,OGd~vM\u0006"
		// @09: invokestatic game.C_100316_lc.func_102401_z(java.lang.String)char[]
		// @0C: invokestatic game.C_100316_lc.func_102400_z(char[])java.lang.String
		// @0F: aastore
		// @10: dup
		// @11: iconst_1
		// @12: ldc "ft,4\u0006"
		// @14: invokestatic game.C_100316_lc.func_102401_z(java.lang.String)char[]
		// @17: invokestatic game.C_100316_lc.func_102400_z(char[])java.lang.String
		// @1A: aastore
		// @1B: dup
		// @1C: iconst_2
		// @1D: ldc "q9,]S"
		// @1F: invokestatic game.C_100316_lc.func_102401_z(java.lang.String)char[]
		// @22: invokestatic game.C_100316_lc.func_102400_z(char[])java.lang.String
		// @25: aastore
		// @26: dup
		// @27: iconst_3
		// @28: ldc "dbn\u001f"
		// @2A: invokestatic game.C_100316_lc.func_102401_z(java.lang.String)char[]
		// @2D: invokestatic game.C_100316_lc.func_102400_z(char[])java.lang.String
		// @30: aastore
		// @31: dup
		// @32: iconst_4
		// @33: ldc "ft,;\u0006"
		// @35: invokestatic game.C_100316_lc.func_102401_z(java.lang.String)char[]
		// @38: invokestatic game.C_100316_lc.func_102400_z(char[])java.lang.String
		// @3B: aastore
		// @3C: dup
		// @3D: iconst_5
		// @3E: ldc "ft,:\u0006"
		// @40: invokestatic game.C_100316_lc.func_102401_z(java.lang.String)char[]
		// @43: invokestatic game.C_100316_lc.func_102400_z(char[])java.lang.String
		// @46: aastore
		// @47: dup
		// @48: bipush 6 (0x06)
		// @4A: ldc "#7"
		// @4C: invokestatic game.C_100316_lc.func_102401_z(java.lang.String)char[]
		// @4F: invokestatic game.C_100316_lc.func_102400_z(char[])java.lang.String
		// @52: aastore
		// @53: putstatic java.lang.String[] game.C_100316_lc.field_102406_F
		// @56: ldc "Nrv\u0012Gf-\";Gm\u007f"
		// @58: invokestatic game.C_100316_lc.func_102401_z(java.lang.String)char[]
		// @5B: invokestatic game.C_100316_lc.func_102400_z(char[])java.lang.String
		// @5E: putstatic java.lang.String game.C_100316_lc.field_102413_t
		// @61: ldc "ee"
		// @63: invokestatic game.C_100316_lc.func_102401_z(java.lang.String)char[]
		// @66: invokestatic game.C_100316_lc.func_102400_z(char[])java.lang.String
		// @69: putstatic java.lang.String game.C_100316_lc.field_102415_z
		// @6C: ldc "KeoS]fxv"
		// @6E: invokestatic game.C_100316_lc.func_102401_z(java.lang.String)char[]
		// @71: invokestatic game.C_100316_lc.func_102400_z(char[])java.lang.String
		// @74: putstatic java.lang.String game.C_100316_lc.field_102408_B
		// @77: aconst_null
		// @78: putstatic game.C_100115_ej game.C_100316_lc.field_102410_w
		// @7B: sipush 8192 (0x2000)
		// @7E: newarray int[]
		// @80: putstatic int[] game.C_100316_lc.field_102405_E
		// @83: return
	}
	
	private static char[] func_102401_z(String arg0)
	{
		// @00: aload_0
		// @01: invokevirtual java.lang.String.toCharArray()char[]
		// @04: dup
		// @05: arraylength
		// @06: iconst_2
		// @07: if_icmpge @13
		// @0A: dup
		// @0B: iconst_0
		// @0C: dup2
		// @0D: caload
		// @0E: bipush 46 (0x2E)
		// @10: ixor
		// @11: i2c
		// @12: castore
		// @13: areturn
	}
	
	private static String func_102400_z(char[] arg0)
	{
		// @00: aload_0
		// @01: dup
		// @02: arraylength
		// @03: swap
		// @04: iconst_0
		// @05: istore_1
		// @06: goto @4B
		// @09: dup
		// @0A: iload_1
		// @0B: dup2
		// @0C: caload
		// @0D: iload_1
		// @0E: iconst_5
		// @0F: irem
		// @10: tableswitch def: @43, for 0: @30, for 1: @35, for 2: @3A, for 3: @3E
		// @30: bipush 10 (0x0A)
		// @32: goto @45
		// @35: bipush 23 (0x17)
		// @37: goto @45
		// @3A: iconst_2
		// @3B: goto @45
		// @3E: bipush 115 (0x73)
		// @40: goto @45
		// @43: bipush 46 (0x2E)
		// @45: ixor
		// @46: i2c
		// @47: castore
		// @48: iinc #1 +1
		// @4B: swap
		// @4C: dup_x1
		// @4D: iload_1
		// @4E: if_icmpgt @09
		// @51: new java.lang.String
		// @54: dup_x1
		// @55: swap
		// @56: invokespecial java.lang.String.<init>(char[])void
		// @59: invokevirtual java.lang.String.intern()java.lang.String
		// @5C: areturn
	}
}
