package game;

abstract class C_100079_e extends C_100341_jd
{
	private C_100183_cd field_102674_ub;
	private C_100006_fj field_102667_yb;
	private int field_102671_Ab;
	private int field_102663_Fb;
	private int field_102664_zb;
	private int field_102676_xb;
	static C_100133_tk field_102670_tb;
	private C_100336_im field_102678_vb;
	static String field_102677_wb;
	private int field_102666_Db;
	static String field_102665_Gb;
	static int field_102668_Eb;
	static String field_102669_Cb;
	static String[] field_102673_sb;
	static int field_102672_Bb;
	private static final String[] field_102675_Hb;
	
	public static void func_102662_p(int arg0)
	{
		// @00: aconst_null
		// @01: putstatic java.lang.String[] game.C_100079_e.field_102673_sb
		// @04: aconst_null
		// @05: putstatic java.lang.String game.C_100079_e.field_102665_Gb
		// @08: iload_0
		// @09: ldc -2147483648 (0x80000000)
		// @0B: if_icmpeq @0F
		// @0E: return
		// @0F: aconst_null
		// @10: putstatic game.C_100133_tk game.C_100079_e.field_102670_tb
		// @13: aconst_null
		// @14: putstatic java.lang.String game.C_100079_e.field_102677_wb
		// @17: aconst_null
		// @18: putstatic java.lang.String game.C_100079_e.field_102669_Cb
		// @1B: goto @40
		// @1E: astore_1
		// @1F: aload_1
		// @20: new java.lang.StringBuilder
		// @23: dup
		// @24: invokespecial java.lang.StringBuilder.<init>()void
		// @27: getstatic java.lang.String[] game.C_100079_e.field_102675_Hb
		// @2A: bipush 11 (0x0B)
		// @2C: aaload
		// @2D: invokevirtual java.lang.StringBuilder.append(java.lang.String)java.lang.StringBuilder
		// @30: iload_0
		// @31: invokevirtual java.lang.StringBuilder.append(int)java.lang.StringBuilder
		// @34: bipush 41 (0x29)
		// @36: invokevirtual java.lang.StringBuilder.append(char)java.lang.StringBuilder
		// @39: invokevirtual java.lang.StringBuilder.toString()java.lang.String
		// @3C: invokestatic game.C_100181_cf.func_105695_a(java.lang.Throwable, java.lang.String)game.C_100170_cm
		// @3F: athrow
		// @40: return
	}
	
	final boolean func_102606_a(byte arg0)
	{
		// @00: bipush -115 (0x8D)
		// @02: bipush -51 (0xCD)
		// @04: iload_1
		// @05: isub
		// @06: bipush 43 (0x2B)
		// @08: idiv
		// @09: irem
		// @0A: istore_2
		// @0B: aload_0
		// @0C: bipush 98 (0x62)
		// @0E: invokevirtual game.C_100079_e.func_102635_m(int)void
		// @11: aload_0
		// @12: bipush -121 (0x87)
		// @14: invokespecial game.C_100341_jd.func_102606_a(byte)boolean
		// @17: ireturn
		// @18: astore_2
		// @19: aload_2
		// @1A: new java.lang.StringBuilder
		// @1D: dup
		// @1E: invokespecial java.lang.StringBuilder.<init>()void
		// @21: getstatic java.lang.String[] game.C_100079_e.field_102675_Hb
		// @24: bipush 8 (0x08)
		// @26: aaload
		// @27: invokevirtual java.lang.StringBuilder.append(java.lang.String)java.lang.StringBuilder
		// @2A: iload_1
		// @2B: invokevirtual java.lang.StringBuilder.append(int)java.lang.StringBuilder
		// @2E: bipush 41 (0x29)
		// @30: invokevirtual java.lang.StringBuilder.append(char)java.lang.StringBuilder
		// @33: invokevirtual java.lang.StringBuilder.toString()java.lang.String
		// @36: invokestatic game.C_100181_cf.func_105695_a(java.lang.Throwable, java.lang.String)game.C_100170_cm
		// @39: athrow
	}
	
	static final void func_102656_a(int arg0, byte arg1, int arg2)
	{
		// @000: iload_1
		// @001: bipush -5 (0xFB)
		// @003: if_icmplt @00F
		// @006: bipush -123 (0x85)
		// @008: invokestatic game.C_100079_e.func_102662_p(int)void
		// @00B: goto @00F
		// @00E: athrow
		// @00F: aconst_null
		// @010: getstatic int[] game.C_100309_lk.field_103273_Y
		// @013: if_acmpeq @022
		// @016: getstatic int[] game.C_100309_lk.field_103273_Y
		// @019: arraylength
		// @01A: iload_2
		// @01B: if_icmpge @02E
		// @01E: goto @022
		// @021: athrow
		// @022: iconst_2
		// @023: iload_2
		// @024: imul
		// @025: newarray int[]
		// @027: putstatic int[] game.C_100309_lk.field_103273_Y
		// @02A: goto @02E
		// @02D: athrow
		// @02E: aconst_null
		// @02F: getstatic int[] game.C_100222_aa.field_106080_f
		// @032: if_acmpeq @049
		// @035: iload_2
		// @036: iconst_m1
		// @037: ixor
		// @038: getstatic int[] game.C_100222_aa.field_106080_f
		// @03B: arraylength
		// @03C: iconst_m1
		// @03D: ixor
		// @03E: if_icmplt @049
		// @041: goto @045
		// @044: athrow
		// @045: goto @051
		// @048: athrow
		// @049: iconst_2
		// @04A: iload_2
		// @04B: imul
		// @04C: newarray int[]
		// @04E: putstatic int[] game.C_100222_aa.field_106080_f
		// @051: getstatic int[] game.C_100005_fk.field_103609_q
		// @054: ifnull @06B
		// @057: iload_2
		// @058: iconst_m1
		// @059: ixor
		// @05A: getstatic int[] game.C_100005_fk.field_103609_q
		// @05D: arraylength
		// @05E: iconst_m1
		// @05F: ixor
		// @060: if_icmplt @06B
		// @063: goto @067
		// @066: athrow
		// @067: goto @073
		// @06A: athrow
		// @06B: iload_2
		// @06C: iconst_2
		// @06D: imul
		// @06E: newarray int[]
		// @070: putstatic int[] game.C_100005_fk.field_103609_q
		// @073: aconst_null
		// @074: getstatic int[] game.C_100188_rj.field_105738_b
		// @077: if_acmpeq @086
		// @07A: getstatic int[] game.C_100188_rj.field_105738_b
		// @07D: arraylength
		// @07E: iload_2
		// @07F: if_icmpge @092
		// @082: goto @086
		// @085: athrow
		// @086: iload_2
		// @087: iconst_2
		// @088: imul
		// @089: newarray int[]
		// @08B: putstatic int[] game.C_100188_rj.field_105738_b
		// @08E: goto @092
		// @091: athrow
		// @092: getstatic int[] game.C_100143_bl.field_105102_e
		// @095: ifnull @0A4
		// @098: getstatic int[] game.C_100143_bl.field_105102_e
		// @09B: arraylength
		// @09C: iload_2
		// @09D: if_icmpge @0B0
		// @0A0: goto @0A4
		// @0A3: athrow
		// @0A4: iconst_2
		// @0A5: iload_2
		// @0A6: imul
		// @0A7: newarray int[]
		// @0A9: putstatic int[] game.C_100143_bl.field_105102_e
		// @0AC: goto @0B0
		// @0AF: athrow
		// @0B0: aconst_null
		// @0B1: getstatic int[] game.C_100268_mk.field_106670_c
		// @0B4: if_acmpeq @0C7
		// @0B7: iload_2
		// @0B8: iconst_m1
		// @0B9: ixor
		// @0BA: getstatic int[] game.C_100268_mk.field_106670_c
		// @0BD: arraylength
		// @0BE: iconst_m1
		// @0BF: ixor
		// @0C0: if_icmpge @0D3
		// @0C3: goto @0C7
		// @0C6: athrow
		// @0C7: iload_2
		// @0C8: iconst_2
		// @0C9: imul
		// @0CA: newarray int[]
		// @0CC: putstatic int[] game.C_100268_mk.field_106670_c
		// @0CF: goto @0D3
		// @0D2: athrow
		// @0D3: getstatic int[] game.C_100219_an.field_100876_n
		// @0D6: ifnull @0E7
		// @0D9: getstatic int[] game.C_100219_an.field_100876_n
		// @0DC: arraylength
		// @0DD: iload_0
		// @0DE: iload_2
		// @0DF: iadd
		// @0E0: if_icmpge @0F5
		// @0E3: goto @0E7
		// @0E6: athrow
		// @0E7: iconst_2
		// @0E8: iload_0
		// @0E9: iload_2
		// @0EA: iadd
		// @0EB: imul
		// @0EC: newarray int[]
		// @0EE: putstatic int[] game.C_100219_an.field_100876_n
		// @0F1: goto @0F5
		// @0F4: athrow
		// @0F5: aconst_null
		// @0F6: getstatic boolean[] game.C_100020_wm.field_103854_d
		// @0F9: if_acmpeq @10C
		// @0FC: iload_2
		// @0FD: getstatic boolean[] game.C_100020_wm.field_103854_d
		// @100: arraylength
		// @101: if_icmpgt @10C
		// @104: goto @108
		// @107: athrow
		// @108: goto @114
		// @10B: athrow
		// @10C: iload_2
		// @10D: iconst_2
		// @10E: imul
		// @10F: newarray boolean[]
		// @111: putstatic boolean[] game.C_100020_wm.field_103854_d
		// @114: ldc 2147483647 (0x7fffffff)
		// @116: putstatic int game.C_100161_sd.field_105426_b
		// @119: ldc 2147483647 (0x7fffffff)
		// @11B: putstatic int game.C_100118_ub.field_102061_bc
		// @11E: ldc -2147483648 (0x80000000)
		// @120: putstatic int game.C_100321_hi.field_107224_l
		// @123: ldc -2147483648 (0x80000000)
		// @125: putstatic int game.C_100255_pj.y
		// @128: iconst_0
		// @129: putstatic int game.C_100186_rl.field_105726_a
		// @12C: goto @162
		// @12F: astore_3
		// @130: aload_3
		// @131: new java.lang.StringBuilder
		// @134: dup
		// @135: invokespecial java.lang.StringBuilder.<init>()void
		// @138: getstatic java.lang.String[] game.C_100079_e.field_102675_Hb
		// @13B: iconst_4
		// @13C: aaload
		// @13D: invokevirtual java.lang.StringBuilder.append(java.lang.String)java.lang.StringBuilder
		// @140: iload_0
		// @141: invokevirtual java.lang.StringBuilder.append(int)java.lang.StringBuilder
		// @144: bipush 44 (0x2C)
		// @146: invokevirtual java.lang.StringBuilder.append(char)java.lang.StringBuilder
		// @149: iload_1
		// @14A: invokevirtual java.lang.StringBuilder.append(int)java.lang.StringBuilder
		// @14D: bipush 44 (0x2C)
		// @14F: invokevirtual java.lang.StringBuilder.append(char)java.lang.StringBuilder
		// @152: iload_2
		// @153: invokevirtual java.lang.StringBuilder.append(int)java.lang.StringBuilder
		// @156: bipush 41 (0x29)
		// @158: invokevirtual java.lang.StringBuilder.append(char)java.lang.StringBuilder
		// @15B: invokevirtual java.lang.StringBuilder.toString()java.lang.String
		// @15E: invokestatic game.C_100181_cf.func_105695_a(java.lang.Throwable, java.lang.String)game.C_100170_cm
		// @161: athrow
		// @162: return
	}
	
	final void func_102635_m(int arg0)
	{
		// @00: aconst_null
		// @01: aload_0
		// @02: getfield game.C_100006_fj game.C_100079_e.field_102667_yb
		// @05: if_acmpeq @53
		// @08: aload_0
		// @09: getfield game.C_100006_fj game.C_100079_e.field_102667_yb
		// @0C: getstatic game.C_100006_fj game.C_100063_dj.field_104296_a
		// @0F: if_acmpeq @44
		// @12: goto @16
		// @15: athrow
		// @16: aload_0
		// @17: bipush -110 (0x92)
		// @19: aload_0
		// @1A: getfield game.C_100336_im game.C_100079_e.field_102678_vb
		// @1D: getfield int game.C_100336_im.field_102544_t
		// @20: aload_0
		// @21: getfield int game.C_100079_e.field_102676_xb
		// @24: iadd
		// @25: bipush 12 (0x0C)
		// @27: iadd
		// @28: bipush 12 (0x0C)
		// @2A: aload_0
		// @2B: getfield game.C_100336_im game.C_100079_e.field_102678_vb
		// @2E: getfield int game.C_100336_im.field_102537_l
		// @31: ineg
		// @32: isub
		// @33: invokevirtual game.C_100079_e.func_102615_b(byte, int, int)void
		// @36: aload_0
		// @37: bipush 92 (0x5C)
		// @39: aload_0
		// @3A: getfield game.C_100336_im game.C_100079_e.field_102678_vb
		// @3D: invokespecial game.C_100079_e.func_102655_c(int, game.C_100336_im)void
		// @40: goto @44
		// @43: athrow
		// @44: aload_0
		// @45: aconst_null
		// @46: putfield game.C_100006_fj game.C_100079_e.field_102667_yb
		// @49: aload_0
		// @4A: getfield game.C_100183_cd game.C_100079_e.field_102674_ub
		// @4D: sipush 256 (0x0100)
		// @50: putfield int game.C_100183_cd.field_103418_Q
		// @53: iload_1
		// @54: bipush 71 (0x47)
		// @56: if_icmpge @67
		// @59: aload_0
		// @5A: aconst_null
		// @5B: checkcast game.C_100336_im
		// @5E: bipush 8 (0x08)
		// @60: invokevirtual game.C_100079_e.func_102660_a(game.C_100336_im, byte)void
		// @63: goto @67
		// @66: athrow
		// @67: aload_0
		// @68: bipush 97 (0x61)
		// @6A: invokespecial game.C_100341_jd.func_102635_m(int)void
		// @6D: goto @92
		// @70: astore_2
		// @71: aload_2
		// @72: new java.lang.StringBuilder
		// @75: dup
		// @76: invokespecial java.lang.StringBuilder.<init>()void
		// @79: getstatic java.lang.String[] game.C_100079_e.field_102675_Hb
		// @7C: bipush 13 (0x0D)
		// @7E: aaload
		// @7F: invokevirtual java.lang.StringBuilder.append(java.lang.String)java.lang.StringBuilder
		// @82: iload_1
		// @83: invokevirtual java.lang.StringBuilder.append(int)java.lang.StringBuilder
		// @86: bipush 41 (0x29)
		// @88: invokevirtual java.lang.StringBuilder.append(char)java.lang.StringBuilder
		// @8B: invokevirtual java.lang.StringBuilder.toString()java.lang.String
		// @8E: invokestatic game.C_100181_cf.func_105695_a(java.lang.Throwable, java.lang.String)game.C_100170_cm
		// @91: athrow
		// @92: return
	}
	
	C_100079_e(C_100029_gn arg0, C_100336_im arg1, int arg2, int arg3, int arg4)
	{
		// @00: aload_0
		// @01: aload_1
		// @02: bipush 12 (0x0C)
		// @04: aload_2
		// @05: getfield int game.C_100336_im.field_102537_l
		// @08: iadd
		// @09: bipush 12 (0x0C)
		// @0B: iload_3
		// @0C: ineg
		// @0D: aload_2
		// @0E: getfield int game.C_100336_im.field_102544_t
		// @11: ineg
		// @12: iadd
		// @13: isub
		// @14: invokespecial game.C_100341_jd.<init>(game.C_100029_gn, int, int)void
		// @17: aload_0
		// @18: iload #5
		// @1A: putfield int game.C_100079_e.field_102666_Db
		// @1D: aload_0
		// @1E: aload_0
		// @1F: iload #4
		// @21: dup_x1
		// @22: putfield int game.C_100079_e.field_102663_Fb
		// @25: putfield int game.C_100079_e.field_102671_Ab
		// @28: aload_0
		// @29: iload_3
		// @2A: putfield int game.C_100079_e.field_102676_xb
		// @2D: aload_0
		// @2E: bipush -27 (0xE5)
		// @30: aload_2
		// @31: invokespecial game.C_100079_e.func_102655_c(int, game.C_100336_im)void
		// @34: goto @A3
		// @37: astore #6
		// @39: aload #6
		// @3B: new java.lang.StringBuilder
		// @3E: dup
		// @3F: invokespecial java.lang.StringBuilder.<init>()void
		// @42: getstatic java.lang.String[] game.C_100079_e.field_102675_Hb
		// @45: bipush 6 (0x06)
		// @47: aaload
		// @48: invokevirtual java.lang.StringBuilder.append(java.lang.String)java.lang.StringBuilder
		// @4B: aload_1
		// @4C: ifnull @58
		// @4F: getstatic java.lang.String[] game.C_100079_e.field_102675_Hb
		// @52: iconst_1
		// @53: aaload
		// @54: goto @5D
		// @57: athrow
		// @58: getstatic java.lang.String[] game.C_100079_e.field_102675_Hb
		// @5B: iconst_0
		// @5C: aaload
		// @5D: invokevirtual java.lang.StringBuilder.append(java.lang.String)java.lang.StringBuilder
		// @60: bipush 44 (0x2C)
		// @62: invokevirtual java.lang.StringBuilder.append(char)java.lang.StringBuilder
		// @65: aload_2
		// @66: ifnull @72
		// @69: getstatic java.lang.String[] game.C_100079_e.field_102675_Hb
		// @6C: iconst_1
		// @6D: aaload
		// @6E: goto @77
		// @71: athrow
		// @72: getstatic java.lang.String[] game.C_100079_e.field_102675_Hb
		// @75: iconst_0
		// @76: aaload
		// @77: invokevirtual java.lang.StringBuilder.append(java.lang.String)java.lang.StringBuilder
		// @7A: bipush 44 (0x2C)
		// @7C: invokevirtual java.lang.StringBuilder.append(char)java.lang.StringBuilder
		// @7F: iload_3
		// @80: invokevirtual java.lang.StringBuilder.append(int)java.lang.StringBuilder
		// @83: bipush 44 (0x2C)
		// @85: invokevirtual java.lang.StringBuilder.append(char)java.lang.StringBuilder
		// @88: iload #4
		// @8A: invokevirtual java.lang.StringBuilder.append(int)java.lang.StringBuilder
		// @8D: bipush 44 (0x2C)
		// @8F: invokevirtual java.lang.StringBuilder.append(char)java.lang.StringBuilder
		// @92: iload #5
		// @94: invokevirtual java.lang.StringBuilder.append(int)java.lang.StringBuilder
		// @97: bipush 41 (0x29)
		// @99: invokevirtual java.lang.StringBuilder.append(char)java.lang.StringBuilder
		// @9C: invokevirtual java.lang.StringBuilder.toString()java.lang.String
		// @9F: invokestatic game.C_100181_cf.func_105695_a(java.lang.Throwable, java.lang.String)game.C_100170_cm
		// @A2: athrow
		// @A3: return
	}
	
	boolean func_102506_a(char arg0, int arg1, int arg2, C_100336_im arg3)
	{
		// @00: aload_0
		// @01: iload_1
		// @02: iload_2
		// @03: iload_3
		// @04: aload #4
		// @06: invokespecial game.C_100341_jd.func_102506_a(char, int, int, game.C_100336_im)boolean
		// @09: ifeq @0E
		// @0C: iconst_1
		// @0D: ireturn
		// @0E: aconst_null
		// @0F: aload_0
		// @10: getfield game.C_100183_cd game.C_100079_e.field_102674_ub
		// @13: if_acmpne @1A
		// @16: goto @46
		// @19: athrow
		// @1A: bipush 98 (0x62)
		// @1C: iload_2
		// @1D: if_icmpne @2F
		// @20: aload_0
		// @21: getfield game.C_100183_cd game.C_100079_e.field_102674_ub
		// @24: iconst_1
		// @25: aload #4
		// @27: invokevirtual game.C_100183_cd.func_102522_a(int, game.C_100336_im)boolean
		// @2A: pop
		// @2B: goto @2F
		// @2E: athrow
		// @2F: iload_2
		// @30: iconst_m1
		// @31: ixor
		// @32: bipush -100 (0x9C)
		// @34: if_icmpeq @3B
		// @37: goto @46
		// @3A: athrow
		// @3B: aload_0
		// @3C: getfield game.C_100183_cd game.C_100079_e.field_102674_ub
		// @3F: iconst_1
		// @40: aload #4
		// @42: invokevirtual game.C_100183_cd.func_102522_a(int, game.C_100336_im)boolean
		// @45: pop
		// @46: iconst_0
		// @47: ireturn
		// @48: astore #5
		// @4A: aload #5
		// @4C: new java.lang.StringBuilder
		// @4F: dup
		// @50: invokespecial java.lang.StringBuilder.<init>()void
		// @53: getstatic java.lang.String[] game.C_100079_e.field_102675_Hb
		// @56: iconst_5
		// @57: aaload
		// @58: invokevirtual java.lang.StringBuilder.append(java.lang.String)java.lang.StringBuilder
		// @5B: iload_1
		// @5C: invokevirtual java.lang.StringBuilder.append(char)java.lang.StringBuilder
		// @5F: bipush 44 (0x2C)
		// @61: invokevirtual java.lang.StringBuilder.append(char)java.lang.StringBuilder
		// @64: iload_2
		// @65: invokevirtual java.lang.StringBuilder.append(int)java.lang.StringBuilder
		// @68: bipush 44 (0x2C)
		// @6A: invokevirtual java.lang.StringBuilder.append(char)java.lang.StringBuilder
		// @6D: iload_3
		// @6E: invokevirtual java.lang.StringBuilder.append(int)java.lang.StringBuilder
		// @71: bipush 44 (0x2C)
		// @73: invokevirtual java.lang.StringBuilder.append(char)java.lang.StringBuilder
		// @76: aload #4
		// @78: ifnull @84
		// @7B: getstatic java.lang.String[] game.C_100079_e.field_102675_Hb
		// @7E: iconst_1
		// @7F: aaload
		// @80: goto @89
		// @83: athrow
		// @84: getstatic java.lang.String[] game.C_100079_e.field_102675_Hb
		// @87: iconst_0
		// @88: aaload
		// @89: invokevirtual java.lang.StringBuilder.append(java.lang.String)java.lang.StringBuilder
		// @8C: bipush 41 (0x29)
		// @8E: invokevirtual java.lang.StringBuilder.append(char)java.lang.StringBuilder
		// @91: invokevirtual java.lang.StringBuilder.toString()java.lang.String
		// @94: invokestatic game.C_100181_cf.func_105695_a(java.lang.Throwable, java.lang.String)game.C_100170_cm
		// @97: athrow
	}
	
	boolean func_102613_k(int arg0)
	{
		// @000: getstatic int game.SteelSentinels.field_105275_O
		// @003: istore_3
		// @004: iload_1
		// @005: sipush 248 (0x00F8)
		// @008: if_icmpeq @019
		// @00B: aconst_null
		// @00C: checkcast java.lang.String
		// @00F: bipush -62 (0xC2)
		// @011: invokestatic game.C_100079_e.func_102661_a(java.lang.String, byte)boolean
		// @014: pop
		// @015: goto @019
		// @018: athrow
		// @019: aload_0
		// @01A: getfield game.C_100006_fj game.C_100079_e.field_102667_yb
		// @01D: ifnull @0FB
		// @020: getstatic game.C_100006_fj game.C_100052_eb.field_104233_a
		// @023: aload_0
		// @024: getfield game.C_100006_fj game.C_100079_e.field_102667_yb
		// @027: if_acmpne @0A5
		// @02A: goto @02E
		// @02D: athrow
		// @02E: aload_0
		// @02F: getfield int game.C_100079_e.field_102671_Ab
		// @032: aload_0
		// @033: dup
		// @034: getfield int game.C_100079_e.field_102664_zb
		// @037: iconst_1
		// @038: iadd
		// @039: dup_x1
		// @03A: putfield int game.C_100079_e.field_102664_zb
		// @03D: if_icmpeq @064
		// @040: goto @044
		// @043: athrow
		// @044: aload_0
		// @045: getfield game.C_100183_cd game.C_100079_e.field_102674_ub
		// @048: sipush 256 (0x0100)
		// @04B: aload_0
		// @04C: getfield int game.C_100079_e.field_102664_zb
		// @04F: ldc -1551980600 (0xa37ea7c8)
		// @051: ishl
		// @052: aload_0
		// @053: getfield int game.C_100079_e.field_102671_Ab
		// @056: idiv
		// @057: ineg
		// @058: iadd
		// @059: putfield int game.C_100183_cd.field_103418_Q
		// @05C: iload_3
		// @05D: ifeq @0FB
		// @060: goto @064
		// @063: athrow
		// @064: aload_0
		// @065: getstatic game.C_100006_fj game.C_100145_ta.field_100424_c
		// @068: putfield game.C_100006_fj game.C_100079_e.field_102667_yb
		// @06B: aload_0
		// @06C: sipush 8013 (0x1F4D)
		// @06F: aload_0
		// @070: getfield game.C_100336_im game.C_100079_e.field_102678_vb
		// @073: getfield int game.C_100336_im.field_102537_l
		// @076: bipush 12 (0x0C)
		// @078: iadd
		// @079: aload_0
		// @07A: getfield int game.C_100079_e.field_102676_xb
		// @07D: bipush 12 (0x0C)
		// @07F: aload_0
		// @080: getfield game.C_100336_im game.C_100079_e.field_102678_vb
		// @083: getfield int game.C_100336_im.field_102544_t
		// @086: ineg
		// @087: isub
		// @088: iadd
		// @089: aload_0
		// @08A: getfield int game.C_100079_e.field_102666_Db
		// @08D: invokevirtual game.C_100079_e.func_102629_a(int, int, int, int)void
		// @090: aload_0
		// @091: getfield game.C_100183_cd game.C_100079_e.field_102674_ub
		// @094: iconst_0
		// @095: putfield int game.C_100183_cd.field_103418_Q
		// @098: aload_0
		// @099: iconst_0
		// @09A: putfield int game.C_100079_e.field_102664_zb
		// @09D: iload_3
		// @09E: ifeq @0FB
		// @0A1: goto @0A5
		// @0A4: athrow
		// @0A5: aload_0
		// @0A6: getfield game.C_100006_fj game.C_100079_e.field_102667_yb
		// @0A9: getstatic game.C_100006_fj game.C_100063_dj.field_104296_a
		// @0AC: if_acmpne @0FB
		// @0AF: goto @0B3
		// @0B2: athrow
		// @0B3: aload_0
		// @0B4: getfield int game.C_100079_e.field_102663_Fb
		// @0B7: iconst_m1
		// @0B8: ixor
		// @0B9: aload_0
		// @0BA: dup
		// @0BB: getfield int game.C_100079_e.field_102664_zb
		// @0BE: iconst_1
		// @0BF: iadd
		// @0C0: dup_x1
		// @0C1: putfield int game.C_100079_e.field_102664_zb
		// @0C4: iconst_m1
		// @0C5: ixor
		// @0C6: if_icmpeq @0E8
		// @0C9: goto @0CD
		// @0CC: athrow
		// @0CD: aload_0
		// @0CE: getfield game.C_100183_cd game.C_100079_e.field_102674_ub
		// @0D1: aload_0
		// @0D2: getfield int game.C_100079_e.field_102664_zb
		// @0D5: ldc -936049528 (0xc8350488)
		// @0D7: ishl
		// @0D8: aload_0
		// @0D9: getfield int game.C_100079_e.field_102663_Fb
		// @0DC: idiv
		// @0DD: putfield int game.C_100183_cd.field_103418_Q
		// @0E0: iload_3
		// @0E1: ifeq @0FB
		// @0E4: goto @0E8
		// @0E7: athrow
		// @0E8: aload_0
		// @0E9: getfield game.C_100183_cd game.C_100079_e.field_102674_ub
		// @0EC: sipush 256 (0x0100)
		// @0EF: putfield int game.C_100183_cd.field_103418_Q
		// @0F2: aload_0
		// @0F3: aconst_null
		// @0F4: putfield game.C_100006_fj game.C_100079_e.field_102667_yb
		// @0F7: goto @0FB
		// @0FA: athrow
		// @0FB: aload_0
		// @0FC: sipush 248 (0x00F8)
		// @0FF: invokespecial game.C_100341_jd.func_102613_k(int)boolean
		// @102: ireturn
		// @103: astore_2
		// @104: aload_2
		// @105: new java.lang.StringBuilder
		// @108: dup
		// @109: invokespecial java.lang.StringBuilder.<init>()void
		// @10C: getstatic java.lang.String[] game.C_100079_e.field_102675_Hb
		// @10F: bipush 7 (0x07)
		// @111: aaload
		// @112: invokevirtual java.lang.StringBuilder.append(java.lang.String)java.lang.StringBuilder
		// @115: iload_1
		// @116: invokevirtual java.lang.StringBuilder.append(int)java.lang.StringBuilder
		// @119: bipush 41 (0x29)
		// @11B: invokevirtual java.lang.StringBuilder.append(char)java.lang.StringBuilder
		// @11E: invokevirtual java.lang.StringBuilder.toString()java.lang.String
		// @121: invokestatic game.C_100181_cf.func_105695_a(java.lang.Throwable, java.lang.String)game.C_100170_cm
		// @124: athrow
	}
	
	static final boolean func_102659_q(int arg0)
	{
		// @00: iload_0
		// @01: bipush 12 (0x0C)
		// @03: if_icmpeq @13
		// @06: bipush 41 (0x29)
		// @08: bipush 27 (0x1B)
		// @0A: bipush 8 (0x08)
		// @0C: invokestatic game.C_100079_e.func_102656_a(int, byte, int)void
		// @0F: goto @13
		// @12: athrow
		// @13: aconst_null
		// @14: getstatic game.C_100043_vl game.C_100343_jf.field_104825_l
		// @17: if_acmpne @24
		// @1A: getstatic boolean game.C_100021_wn.field_103871_b
		// @1D: ifeq @29
		// @20: goto @24
		// @23: athrow
		// @24: iconst_1
		// @25: goto @2A
		// @28: athrow
		// @29: iconst_0
		// @2A: ireturn
		// @2B: astore_1
		// @2C: aload_1
		// @2D: new java.lang.StringBuilder
		// @30: dup
		// @31: invokespecial java.lang.StringBuilder.<init>()void
		// @34: getstatic java.lang.String[] game.C_100079_e.field_102675_Hb
		// @37: bipush 9 (0x09)
		// @39: aaload
		// @3A: invokevirtual java.lang.StringBuilder.append(java.lang.String)java.lang.StringBuilder
		// @3D: iload_0
		// @3E: invokevirtual java.lang.StringBuilder.append(int)java.lang.StringBuilder
		// @41: bipush 41 (0x29)
		// @43: invokevirtual java.lang.StringBuilder.append(char)java.lang.StringBuilder
		// @46: invokevirtual java.lang.StringBuilder.toString()java.lang.String
		// @49: invokestatic game.C_100181_cf.func_105695_a(java.lang.Throwable, java.lang.String)game.C_100170_cm
		// @4C: athrow
	}
	
	static final boolean func_102661_a(String arg0, byte arg1)
	{
		// @00: bipush 40 (0x28)
		// @02: iload_1
		// @03: bipush 77 (0x4D)
		// @05: isub
		// @06: bipush 33 (0x21)
		// @08: idiv
		// @09: irem
		// @0A: istore_2
		// @0B: aconst_null
		// @0C: aload_0
		// @0D: if_acmpeq @34
		// @10: aload_0
		// @11: invokevirtual java.lang.String.length()int
		// @14: iconst_m1
		// @15: ixor
		// @16: getstatic int game.C_100008_fl.field_103638_b
		// @19: iconst_m1
		// @1A: ixor
		// @1B: if_icmpgt @34
		// @1E: goto @22
		// @21: athrow
		// @22: aload_0
		// @23: invokevirtual java.lang.String.length()int
		// @26: getstatic int game.C_100142_bk.field_105088_b
		// @29: if_icmpgt @34
		// @2C: goto @30
		// @2F: athrow
		// @30: goto @36
		// @33: athrow
		// @34: iconst_1
		// @35: ireturn
		// @36: iconst_0
		// @37: ireturn
		// @38: astore_2
		// @39: aload_2
		// @3A: new java.lang.StringBuilder
		// @3D: dup
		// @3E: invokespecial java.lang.StringBuilder.<init>()void
		// @41: getstatic java.lang.String[] game.C_100079_e.field_102675_Hb
		// @44: iconst_3
		// @45: aaload
		// @46: invokevirtual java.lang.StringBuilder.append(java.lang.String)java.lang.StringBuilder
		// @49: aload_0
		// @4A: ifnull @56
		// @4D: getstatic java.lang.String[] game.C_100079_e.field_102675_Hb
		// @50: iconst_1
		// @51: aaload
		// @52: goto @5B
		// @55: athrow
		// @56: getstatic java.lang.String[] game.C_100079_e.field_102675_Hb
		// @59: iconst_0
		// @5A: aaload
		// @5B: invokevirtual java.lang.StringBuilder.append(java.lang.String)java.lang.StringBuilder
		// @5E: bipush 44 (0x2C)
		// @60: invokevirtual java.lang.StringBuilder.append(char)java.lang.StringBuilder
		// @63: iload_1
		// @64: invokevirtual java.lang.StringBuilder.append(int)java.lang.StringBuilder
		// @67: bipush 41 (0x29)
		// @69: invokevirtual java.lang.StringBuilder.append(char)java.lang.StringBuilder
		// @6C: invokevirtual java.lang.StringBuilder.toString()java.lang.String
		// @6F: invokestatic game.C_100181_cf.func_105695_a(java.lang.Throwable, java.lang.String)game.C_100170_cm
		// @72: athrow
	}
	
	private final void func_102655_c(int arg0, C_100336_im arg1)
	{
		// @00: aload_0
		// @01: getfield game.C_100183_cd game.C_100079_e.field_102674_ub
		// @04: ifnonnull @0B
		// @07: goto @14
		// @0A: athrow
		// @0B: aload_0
		// @0C: getfield game.C_100183_cd game.C_100079_e.field_102674_ub
		// @0F: bipush 45 (0x2D)
		// @11: invokevirtual game.C_100183_cd.func_100583_c(int)void
		// @14: aload_2
		// @15: ifnonnull @2D
		// @18: aload_0
		// @19: new game.C_100183_cd
		// @1C: dup
		// @1D: invokespecial game.C_100183_cd.<init>()void
		// @20: putfield game.C_100183_cd game.C_100079_e.field_102674_ub
		// @23: getstatic int game.SteelSentinels.field_105275_O
		// @26: ifeq @54
		// @29: goto @2D
		// @2C: athrow
		// @2D: aload_2
		// @2E: aload_2
		// @2F: getfield int game.C_100336_im.field_102544_t
		// @32: aload_0
		// @33: getfield int game.C_100079_e.field_102676_xb
		// @36: bipush 6 (0x06)
		// @38: iadd
		// @39: bipush 6 (0x06)
		// @3B: aload_2
		// @3C: getfield int game.C_100336_im.field_102537_l
		// @3F: bipush 43 (0x2B)
		// @41: invokevirtual game.C_100336_im.func_102524_a(int, int, int, int, byte)void
		// @44: aload_0
		// @45: new game.C_100183_cd
		// @48: dup
		// @49: aload_2
		// @4A: invokespecial game.C_100183_cd.<init>(game.C_100336_im)void
		// @4D: putfield game.C_100183_cd game.C_100079_e.field_102674_ub
		// @50: goto @54
		// @53: athrow
		// @54: aload_0
		// @55: aload_0
		// @56: getfield game.C_100183_cd game.C_100079_e.field_102674_ub
		// @59: iconst_1
		// @5A: invokevirtual game.C_100079_e.func_102561_b(game.C_100336_im, int)void
		// @5D: aload_0
		// @5E: aconst_null
		// @5F: putfield game.C_100336_im game.C_100079_e.field_102678_vb
		// @62: bipush -30 (0xE2)
		// @64: bipush 53 (0x35)
		// @66: iload_1
		// @67: isub
		// @68: bipush 32 (0x20)
		// @6A: idiv
		// @6B: irem
		// @6C: istore_3
		// @6D: goto @AB
		// @70: astore_3
		// @71: aload_3
		// @72: new java.lang.StringBuilder
		// @75: dup
		// @76: invokespecial java.lang.StringBuilder.<init>()void
		// @79: getstatic java.lang.String[] game.C_100079_e.field_102675_Hb
		// @7C: iconst_2
		// @7D: aaload
		// @7E: invokevirtual java.lang.StringBuilder.append(java.lang.String)java.lang.StringBuilder
		// @81: iload_1
		// @82: invokevirtual java.lang.StringBuilder.append(int)java.lang.StringBuilder
		// @85: bipush 44 (0x2C)
		// @87: invokevirtual java.lang.StringBuilder.append(char)java.lang.StringBuilder
		// @8A: aload_2
		// @8B: ifnull @97
		// @8E: getstatic java.lang.String[] game.C_100079_e.field_102675_Hb
		// @91: iconst_1
		// @92: aaload
		// @93: goto @9C
		// @96: athrow
		// @97: getstatic java.lang.String[] game.C_100079_e.field_102675_Hb
		// @9A: iconst_0
		// @9B: aaload
		// @9C: invokevirtual java.lang.StringBuilder.append(java.lang.String)java.lang.StringBuilder
		// @9F: bipush 41 (0x29)
		// @A1: invokevirtual java.lang.StringBuilder.append(char)java.lang.StringBuilder
		// @A4: invokevirtual java.lang.StringBuilder.toString()java.lang.String
		// @A7: invokestatic game.C_100181_cf.func_105695_a(java.lang.Throwable, java.lang.String)game.C_100170_cm
		// @AA: athrow
		// @AB: return
	}
	
	void func_102660_a(C_100336_im arg0, byte arg1)
	{
		// @00: aload_0
		// @01: aload_1
		// @02: putfield game.C_100336_im game.C_100079_e.field_102678_vb
		// @05: iload_2
		// @06: bipush 75 (0x4B)
		// @08: if_icmpeq @19
		// @0B: aconst_null
		// @0C: checkcast java.lang.String
		// @0F: bipush 59 (0x3B)
		// @11: invokestatic game.C_100079_e.func_102661_a(java.lang.String, byte)boolean
		// @14: pop
		// @15: goto @19
		// @18: athrow
		// @19: getstatic game.C_100006_fj game.C_100145_ta.field_100424_c
		// @1C: aload_0
		// @1D: getfield game.C_100006_fj game.C_100079_e.field_102667_yb
		// @20: if_acmpeq @47
		// @23: aload_0
		// @24: getfield game.C_100006_fj game.C_100079_e.field_102667_yb
		// @27: getstatic game.C_100006_fj game.C_100052_eb.field_104233_a
		// @2A: if_acmpne @35
		// @2D: goto @31
		// @30: athrow
		// @31: goto @77
		// @34: athrow
		// @35: aload_0
		// @36: iconst_0
		// @37: putfield int game.C_100079_e.field_102664_zb
		// @3A: aload_0
		// @3B: getstatic game.C_100006_fj game.C_100052_eb.field_104233_a
		// @3E: putfield game.C_100006_fj game.C_100079_e.field_102667_yb
		// @41: getstatic int game.SteelSentinels.field_105275_O
		// @44: ifeq @77
		// @47: aload_0
		// @48: iload_2
		// @49: sipush 7938 (0x1F02)
		// @4C: iadd
		// @4D: aload_0
		// @4E: getfield game.C_100336_im game.C_100079_e.field_102678_vb
		// @51: getfield int game.C_100336_im.field_102537_l
		// @54: bipush 12 (0x0C)
		// @56: iadd
		// @57: aload_0
		// @58: getfield game.C_100336_im game.C_100079_e.field_102678_vb
		// @5B: getfield int game.C_100336_im.field_102544_t
		// @5E: bipush 12 (0x0C)
		// @60: aload_0
		// @61: getfield int game.C_100079_e.field_102676_xb
		// @64: ineg
		// @65: isub
		// @66: iadd
		// @67: aload_0
		// @68: getfield int game.C_100079_e.field_102666_Db
		// @6B: invokevirtual game.C_100079_e.func_102629_a(int, int, int, int)void
		// @6E: aload_0
		// @6F: iconst_0
		// @70: putfield int game.C_100079_e.field_102664_zb
		// @73: goto @77
		// @76: athrow
		// @77: goto @B6
		// @7A: astore_3
		// @7B: aload_3
		// @7C: new java.lang.StringBuilder
		// @7F: dup
		// @80: invokespecial java.lang.StringBuilder.<init>()void
		// @83: getstatic java.lang.String[] game.C_100079_e.field_102675_Hb
		// @86: bipush 10 (0x0A)
		// @88: aaload
		// @89: invokevirtual java.lang.StringBuilder.append(java.lang.String)java.lang.StringBuilder
		// @8C: aload_1
		// @8D: ifnull @99
		// @90: getstatic java.lang.String[] game.C_100079_e.field_102675_Hb
		// @93: iconst_1
		// @94: aaload
		// @95: goto @9E
		// @98: athrow
		// @99: getstatic java.lang.String[] game.C_100079_e.field_102675_Hb
		// @9C: iconst_0
		// @9D: aaload
		// @9E: invokevirtual java.lang.StringBuilder.append(java.lang.String)java.lang.StringBuilder
		// @A1: bipush 44 (0x2C)
		// @A3: invokevirtual java.lang.StringBuilder.append(char)java.lang.StringBuilder
		// @A6: iload_2
		// @A7: invokevirtual java.lang.StringBuilder.append(int)java.lang.StringBuilder
		// @AA: bipush 41 (0x29)
		// @AC: invokevirtual java.lang.StringBuilder.append(char)java.lang.StringBuilder
		// @AF: invokevirtual java.lang.StringBuilder.toString()java.lang.String
		// @B2: invokestatic game.C_100181_cf.func_105695_a(java.lang.Throwable, java.lang.String)game.C_100170_cm
		// @B5: athrow
		// @B6: return
	}
	
	final void func_102636_o(int arg0)
	{
		// @00: aload_0
		// @01: getfield game.C_100006_fj game.C_100079_e.field_102667_yb
		// @04: getstatic game.C_100006_fj game.C_100052_eb.field_104233_a
		// @07: if_acmpne @0B
		// @0A: return
		// @0B: aload_0
		// @0C: getstatic game.C_100006_fj game.C_100063_dj.field_104296_a
		// @0F: putfield game.C_100006_fj game.C_100079_e.field_102667_yb
		// @12: aload_0
		// @13: iconst_0
		// @14: putfield int game.C_100079_e.field_102664_zb
		// @17: aload_0
		// @18: bipush -92 (0xA4)
		// @1A: aload_0
		// @1B: getfield game.C_100336_im game.C_100079_e.field_102678_vb
		// @1E: invokespecial game.C_100079_e.func_102655_c(int, game.C_100336_im)void
		// @21: aload_0
		// @22: getfield game.C_100183_cd game.C_100079_e.field_102674_ub
		// @25: iconst_0
		// @26: putfield int game.C_100183_cd.field_103418_Q
		// @29: aload_0
		// @2A: aconst_null
		// @2B: putfield game.C_100336_im game.C_100079_e.field_102678_vb
		// @2E: iload_1
		// @2F: sipush 18323 (0x4793)
		// @32: if_icmpeq @3B
		// @35: aload_0
		// @36: bipush 64 (0x40)
		// @38: invokevirtual game.C_100079_e.func_102636_o(int)void
		// @3B: goto @60
		// @3E: astore_2
		// @3F: aload_2
		// @40: new java.lang.StringBuilder
		// @43: dup
		// @44: invokespecial java.lang.StringBuilder.<init>()void
		// @47: getstatic java.lang.String[] game.C_100079_e.field_102675_Hb
		// @4A: bipush 12 (0x0C)
		// @4C: aaload
		// @4D: invokevirtual java.lang.StringBuilder.append(java.lang.String)java.lang.StringBuilder
		// @50: iload_1
		// @51: invokevirtual java.lang.StringBuilder.append(int)java.lang.StringBuilder
		// @54: bipush 41 (0x29)
		// @56: invokevirtual java.lang.StringBuilder.append(char)java.lang.StringBuilder
		// @59: invokevirtual java.lang.StringBuilder.toString()java.lang.String
		// @5C: invokestatic game.C_100181_cf.func_105695_a(java.lang.Throwable, java.lang.String)game.C_100170_cm
		// @5F: athrow
		// @60: return
	}
	
	static
	{
		// @000: bipush 14 (0x0E)
		// @002: anewarray java.lang.String
		// @005: dup
		// @006: iconst_0
		// @007: ldc "\u0000[=)"
		// @009: invokestatic game.C_100079_e.func_102658_z(java.lang.String)char[]
		// @00C: invokestatic game.C_100079_e.func_102657_z(char[])java.lang.String
		// @00F: aastore
		// @010: dup
		// @011: iconst_1
		// @012: ldc "\u0015\u0000\u007fkL"
		// @014: invokestatic game.C_100079_e.func_102658_z(java.lang.String)char[]
		// @017: invokestatic game.C_100079_e.func_102657_z(char[])java.lang.String
		// @01A: aastore
		// @01B: dup
		// @01C: iconst_2
		// @01D: ldc "\u000b\u0000\u0007\u0004\u0019"
		// @01F: invokestatic game.C_100079_e.func_102658_z(java.lang.String)char[]
		// @022: invokestatic game.C_100079_e.func_102657_z(char[])java.lang.String
		// @025: aastore
		// @026: dup
		// @027: iconst_3
		// @028: ldc "\u000b\u0000\u0006\u0004\u0019"
		// @02A: invokestatic game.C_100079_e.func_102658_z(java.lang.String)char[]
		// @02D: invokestatic game.C_100079_e.func_102657_z(char[])java.lang.String
		// @030: aastore
		// @031: dup
		// @032: iconst_4
		// @033: ldc "\u000b\u0000\u0003\u0004\u0019"
		// @035: invokestatic game.C_100079_e.func_102658_z(java.lang.String)char[]
		// @038: invokestatic game.C_100079_e.func_102657_z(char[])java.lang.String
		// @03B: aastore
		// @03C: dup
		// @03D: iconst_5
		// @03E: ldc "\u000b\u0000\u0017\u0004\u0019"
		// @040: invokestatic game.C_100079_e.func_102658_z(java.lang.String)char[]
		// @043: invokestatic game.C_100079_e.func_102657_z(char[])java.lang.String
		// @046: aastore
		// @047: dup
		// @048: bipush 6 (0x06)
		// @04A: ldc "\u000b\u0000m,_\u0007Zom"
		// @04C: invokestatic game.C_100079_e.func_102658_z(java.lang.String)char[]
		// @04F: invokestatic game.C_100079_e.func_102657_z(char[])java.lang.String
		// @052: aastore
		// @053: dup
		// @054: bipush 7 (0x07)
		// @056: ldc "\u000b\u0000\u0005\u0004\u0019"
		// @058: invokestatic game.C_100079_e.func_102658_z(java.lang.String)char[]
		// @05B: invokestatic game.C_100079_e.func_102657_z(char[])java.lang.String
		// @05E: aastore
		// @05F: dup
		// @060: bipush 8 (0x08)
		// @062: ldc "\u000b\u0000\u0010\u0007\u0019"
		// @064: invokestatic game.C_100079_e.func_102658_z(java.lang.String)char[]
		// @067: invokestatic game.C_100079_e.func_102657_z(char[])java.lang.String
		// @06A: aastore
		// @06B: dup
		// @06C: bipush 9 (0x09)
		// @06E: ldc "\u000b\u0000\u0002\u0004\u0019"
		// @070: invokestatic game.C_100079_e.func_102658_z(java.lang.String)char[]
		// @073: invokestatic game.C_100079_e.func_102657_z(char[])java.lang.String
		// @076: aastore
		// @077: dup
		// @078: bipush 10 (0x0A)
		// @07A: ldc "\u000b\u0000\u001a\u0004\u0019"
		// @07C: invokestatic game.C_100079_e.func_102658_z(java.lang.String)char[]
		// @07F: invokestatic game.C_100079_e.func_102657_z(char[])java.lang.String
		// @082: aastore
		// @083: dup
		// @084: bipush 11 (0x0B)
		// @086: ldc "\u000b\u0000\u0004\u0004\u0019"
		// @088: invokestatic game.C_100079_e.func_102658_z(java.lang.String)char[]
		// @08B: invokestatic game.C_100079_e.func_102657_z(char[])java.lang.String
		// @08E: aastore
		// @08F: dup
		// @090: bipush 12 (0x0C)
		// @092: ldc "\u000b\u0000\u0001\u0004\u0019"
		// @094: invokestatic game.C_100079_e.func_102658_z(java.lang.String)char[]
		// @097: invokestatic game.C_100079_e.func_102657_z(char[])java.lang.String
		// @09A: aastore
		// @09B: dup
		// @09C: bipush 13 (0x0D)
		// @09E: ldc "\u000b\u0000\u0000\u0004\u0019"
		// @0A0: invokestatic game.C_100079_e.func_102658_z(java.lang.String)char[]
		// @0A3: invokestatic game.C_100079_e.func_102657_z(char[])java.lang.String
		// @0A6: aastore
		// @0A7: putstatic java.lang.String[] game.C_100079_e.field_102675_Hb
		// @0AA: ldc "#A?1Y"
		// @0AC: invokestatic game.C_100079_e.func_102658_z(java.lang.String)char[]
		// @0AF: invokestatic game.C_100079_e.func_102657_z(char[])java.lang.String
		// @0B2: putstatic java.lang.String game.C_100079_e.field_102677_wb
		// @0B5: new game.C_100133_tk
		// @0B8: dup
		// @0B9: invokespecial game.C_100133_tk.<init>()void
		// @0BC: putstatic game.C_100133_tk game.C_100079_e.field_102670_tb
		// @0BF: ldc ":F4eP\rM>0_\u001a\u000e?$\\\u000b\u000e(*DN[\" \u0011\u001aAq$R\rK\"6\u0011<[? b\rO! \u0011\u000f@5e^\u001aF47\u0011$O6 I@M>(\u0011\tO< B"
		// @0C1: invokestatic game.C_100079_e.func_102658_z(java.lang.String)char[]
		// @0C4: invokestatic game.C_100079_e.func_102657_z(char[])java.lang.String
		// @0C7: putstatic java.lang.String game.C_100079_e.field_102665_Gb
		// @0CA: ldc "/M2*D\u0000Zq&C\u000bO% UN]$&R\u000b]\"#D\u0002B(d"
		// @0CC: invokestatic game.C_100079_e.func_102658_z(java.lang.String)char[]
		// @0CF: invokestatic game.C_100079_e.func_102657_z(char[])java.lang.String
		// @0D2: putstatic java.lang.String game.C_100079_e.field_102669_Cb
		// @0D5: iconst_m1
		// @0D6: putstatic int game.C_100079_e.field_102672_Bb
		// @0D9: bipush 9 (0x09)
		// @0DB: anewarray java.lang.String
		// @0DE: dup
		// @0DF: iconst_0
		// @0E0: ldc "<O?\"T"
		// @0E2: invokestatic game.C_100079_e.func_102658_z(java.lang.String)char[]
		// @0E5: invokestatic game.C_100079_e.func_102657_z(char[])java.lang.String
		// @0E8: aastore
		// @0E9: dup
		// @0EA: iconst_1
		// @0EB: ldc "<O% \u0011\u0001Hq#X\u001cK"
		// @0ED: invokestatic game.C_100079_e.func_102658_z(java.lang.String)char[]
		// @0F0: invokestatic game.C_100079_e.func_102657_z(char[])java.lang.String
		// @0F3: aastore
		// @0F4: dup
		// @0F5: iconst_2
		// @0F6: ldc "<K=*P\n\u000e\"5T\u000bJ"
		// @0F8: invokestatic game.C_100079_e.func_102658_z(java.lang.String)char[]
		// @0FB: invokestatic game.C_100079_e.func_102657_z(char[])java.lang.String
		// @0FE: aastore
		// @0FF: dup
		// @100: iconst_3
		// @101: ldc "/\\4$\u0011\u0001Hq W\u0008K21"
		// @103: invokestatic game.C_100079_e.func_102658_z(java.lang.String)char[]
		// @106: invokestatic game.C_100079_e.func_102657_z(char[])java.lang.String
		// @109: aastore
		// @10A: dup
		// @10B: iconst_4
		// @10C: ldc "+@47V\u0017\u000e4#W\u0007M8 _\rW"
		// @10E: invokestatic game.C_100079_e.func_102658_z(java.lang.String)char[]
		// @111: invokestatic game.C_100079_e.func_102657_z(char[])java.lang.String
		// @114: aastore
		// @115: dup
		// @116: iconst_5
		// @117: ldc "%G? E\u0007Mq!P\u0003O6 "
		// @119: invokestatic game.C_100079_e.func_102658_z(java.lang.String)char[]
		// @11C: invokestatic game.C_100079_e.func_102657_z(char[])java.lang.String
		// @11F: aastore
		// @120: dup
		// @121: bipush 6 (0x06)
		// @123: ldc "+V!)^\u001dG' \u0011\nO<$V\u000b"
		// @125: invokestatic game.C_100079_e.func_102658_z(java.lang.String)char[]
		// @128: invokestatic game.C_100079_e.func_102657_z(char[])java.lang.String
		// @12B: aastore
		// @12C: dup
		// @12D: bipush 7 (0x07)
		// @12F: ldc "+@47V\u0017\u000e5$\\\u000fI4"
		// @131: invokestatic game.C_100079_e.func_102658_z(java.lang.String)char[]
		// @134: invokestatic game.C_100079_e.func_102657_z(char[])java.lang.String
		// @137: aastore
		// @138: dup
		// @139: bipush 8 (0x08)
		// @13B: ldc "+c\u0001"
		// @13D: invokestatic game.C_100079_e.func_102658_z(java.lang.String)char[]
		// @140: invokestatic game.C_100079_e.func_102657_z(char[])java.lang.String
		// @143: aastore
		// @144: putstatic java.lang.String[] game.C_100079_e.field_102673_sb
		// @147: return
	}
	
	private static char[] func_102658_z(String arg0)
	{
		// @00: aload_0
		// @01: invokevirtual java.lang.String.toCharArray()char[]
		// @04: dup
		// @05: arraylength
		// @06: iconst_2
		// @07: if_icmpge @13
		// @0A: dup
		// @0B: iconst_0
		// @0C: dup2
		// @0D: caload
		// @0E: bipush 49 (0x31)
		// @10: ixor
		// @11: i2c
		// @12: castore
		// @13: areturn
	}
	
	private static String func_102657_z(char[] arg0)
	{
		// @00: aload_0
		// @01: dup
		// @02: arraylength
		// @03: swap
		// @04: iconst_0
		// @05: istore_1
		// @06: goto @4C
		// @09: dup
		// @0A: iload_1
		// @0B: dup2
		// @0C: caload
		// @0D: iload_1
		// @0E: iconst_5
		// @0F: irem
		// @10: tableswitch def: @44, for 0: @30, for 1: @35, for 2: @3A, for 3: @3F
		// @30: bipush 110 (0x6E)
		// @32: goto @46
		// @35: bipush 46 (0x2E)
		// @37: goto @46
		// @3A: bipush 81 (0x51)
		// @3C: goto @46
		// @3F: bipush 69 (0x45)
		// @41: goto @46
		// @44: bipush 49 (0x31)
		// @46: ixor
		// @47: i2c
		// @48: castore
		// @49: iinc #1 +1
		// @4C: swap
		// @4D: dup_x1
		// @4E: iload_1
		// @4F: if_icmpgt @09
		// @52: new java.lang.String
		// @55: dup_x1
		// @56: swap
		// @57: invokespecial java.lang.String.<init>(char[])void
		// @5A: invokevirtual java.lang.String.intern()java.lang.String
		// @5D: areturn
	}
}
