package game;

final class C_100118_ub extends C_100302_ka
{
	private int field_102058_Zb;
	static int field_102061_bc;
	static String[] field_102062_cc;
	static String field_102057_ac;
	static int field_102054_Wb;
	static String field_102060_Yb;
	private StringBuilder field_102059_Xb;
	private C_100302_ka field_102056_Vb;
	private C_100302_ka field_102055_Ub;
	private static final String[] field_102053_dc;
	
	public static void func_102046_l(int arg0)
	{
		// @00: iload_0
		// @01: ifeq @17
		// @04: aconst_null
		// @05: checkcast java.lang.String
		// @08: iconst_1
		// @09: aconst_null
		// @0A: checkcast java.lang.String
		// @0D: bipush 32 (0x20)
		// @0F: invokestatic game.C_100118_ub.func_102051_a(java.lang.String, char, java.lang.String, int)java.lang.String
		// @12: pop
		// @13: goto @17
		// @16: athrow
		// @17: aconst_null
		// @18: putstatic java.lang.String[] game.C_100118_ub.field_102062_cc
		// @1B: aconst_null
		// @1C: putstatic java.lang.String game.C_100118_ub.field_102057_ac
		// @1F: aconst_null
		// @20: putstatic java.lang.String game.C_100118_ub.field_102060_Yb
		// @23: goto @48
		// @26: astore_1
		// @27: aload_1
		// @28: new java.lang.StringBuilder
		// @2B: dup
		// @2C: invokespecial java.lang.StringBuilder.<init>()void
		// @2F: getstatic java.lang.String[] game.C_100118_ub.field_102053_dc
		// @32: bipush 7 (0x07)
		// @34: aaload
		// @35: invokevirtual java.lang.StringBuilder.append(java.lang.String)java.lang.StringBuilder
		// @38: iload_0
		// @39: invokevirtual java.lang.StringBuilder.append(int)java.lang.StringBuilder
		// @3C: bipush 41 (0x29)
		// @3E: invokevirtual java.lang.StringBuilder.append(char)java.lang.StringBuilder
		// @41: invokevirtual java.lang.StringBuilder.toString()java.lang.String
		// @44: invokestatic game.C_100181_cf.func_105695_a(java.lang.Throwable, java.lang.String)game.C_100170_cm
		// @47: athrow
		// @48: return
	}
	
	final boolean func_102050_m(int arg0)
	{
		// @000: aload_0
		// @001: getfield int game.C_100118_ub.field_102058_Zb
		// @004: ifne @00B
		// @007: goto @00D
		// @00A: athrow
		// @00B: iconst_0
		// @00C: ireturn
		// @00D: getstatic int game.C_100293_kj.field_106890_c
		// @010: iconst_m1
		// @011: ixor
		// @012: bipush -86 (0xAA)
		// @014: if_icmpne @041
		// @017: aload_0
		// @018: getfield java.lang.StringBuilder game.C_100118_ub.field_102059_Xb
		// @01B: invokevirtual java.lang.StringBuilder.length()int
		// @01E: iconst_m1
		// @01F: ixor
		// @020: iconst_m1
		// @021: if_icmplt @02C
		// @024: goto @028
		// @027: athrow
		// @028: goto @041
		// @02B: athrow
		// @02C: bipush 32 (0x20)
		// @02E: bipush 92 (0x5C)
		// @030: aload_0
		// @031: getfield java.lang.StringBuilder game.C_100118_ub.field_102059_Xb
		// @034: aload_0
		// @035: getfield java.lang.StringBuilder game.C_100118_ub.field_102059_Xb
		// @038: invokevirtual java.lang.StringBuilder.length()int
		// @03B: iconst_m1
		// @03C: iadd
		// @03D: invokestatic game.C_100062_dk.func_104278_a(char, byte, java.lang.StringBuilder, int)java.lang.StringBuilder
		// @040: pop
		// @041: bipush -13 (0xF3)
		// @043: aload_0
		// @044: getfield java.lang.StringBuilder game.C_100118_ub.field_102059_Xb
		// @047: invokevirtual java.lang.StringBuilder.length()int
		// @04A: iconst_m1
		// @04B: ixor
		// @04C: if_icmpge @0A6
		// @04F: getstatic char game.C_100012_fh.field_100517_Q
		// @052: invokestatic java.lang.Character.toLowerCase(char)char
		// @055: istore_2
		// @056: iload_2
		// @057: bipush 32 (0x20)
		// @059: if_icmpne @05F
		// @05C: bipush 95 (0x5F)
		// @05E: istore_2
		// @05F: bipush -96 (0xA0)
		// @061: iload_2
		// @062: iconst_m1
		// @063: ixor
		// @064: if_icmpne @083
		// @067: iconst_0
		// @068: aload_0
		// @069: getfield java.lang.StringBuilder game.C_100118_ub.field_102059_Xb
		// @06C: invokevirtual java.lang.StringBuilder.length()int
		// @06F: if_icmplt @07A
		// @072: goto @076
		// @075: athrow
		// @076: goto @083
		// @079: athrow
		// @07A: aload_0
		// @07B: getfield java.lang.StringBuilder game.C_100118_ub.field_102059_Xb
		// @07E: iload_2
		// @07F: invokevirtual java.lang.StringBuilder.append(char)java.lang.StringBuilder
		// @082: pop
		// @083: bipush -63 (0xC1)
		// @085: iload_2
		// @086: invokestatic game.C_100137_bn.func_105027_a(int, char)boolean
		// @089: ifne @099
		// @08C: iload_2
		// @08D: bipush -100 (0x9C)
		// @08F: invokestatic game.C_100064_ve.func_103007_a(char, byte)boolean
		// @092: ifeq @0A6
		// @095: goto @099
		// @098: athrow
		// @099: aload_0
		// @09A: getfield java.lang.StringBuilder game.C_100118_ub.field_102059_Xb
		// @09D: iload_2
		// @09E: invokevirtual java.lang.StringBuilder.append(char)java.lang.StringBuilder
		// @0A1: pop
		// @0A2: goto @0A6
		// @0A5: athrow
		// @0A6: getstatic int game.C_100293_kj.field_106890_c
		// @0A9: iconst_m1
		// @0AA: ixor
		// @0AB: bipush -85 (0xAB)
		// @0AD: if_icmpne @0E4
		// @0B0: iconst_m1
		// @0B1: aload_0
		// @0B2: getfield java.lang.StringBuilder game.C_100118_ub.field_102059_Xb
		// @0B5: invokevirtual java.lang.StringBuilder.length()int
		// @0B8: iconst_m1
		// @0B9: ixor
		// @0BA: if_icmple @0DB
		// @0BD: goto @0C1
		// @0C0: athrow
		// @0C1: aload_0
		// @0C2: aload_0
		// @0C3: getfield java.lang.StringBuilder game.C_100118_ub.field_102059_Xb
		// @0C6: invokevirtual java.lang.StringBuilder.toString()java.lang.String
		// @0C9: putfield java.lang.String game.C_100118_ub.field_101890_ab
		// @0CC: aload_0
		// @0CD: iconst_2
		// @0CE: putfield int game.C_100118_ub.field_102058_Zb
		// @0D1: getstatic int game.SteelSentinels.field_105275_O
		// @0D4: ifeq @0E4
		// @0D7: goto @0DB
		// @0DA: athrow
		// @0DB: aload_0
		// @0DC: iconst_1
		// @0DD: putfield int game.C_100118_ub.field_102058_Zb
		// @0E0: goto @0E4
		// @0E3: athrow
		// @0E4: getstatic int game.C_100293_kj.field_106890_c
		// @0E7: iconst_m1
		// @0E8: ixor
		// @0E9: bipush -14 (0xF2)
		// @0EB: if_icmpeq @0F2
		// @0EE: goto @0F7
		// @0F1: athrow
		// @0F2: aload_0
		// @0F3: iconst_1
		// @0F4: putfield int game.C_100118_ub.field_102058_Zb
		// @0F7: iload_1
		// @0F8: iconst_2
		// @0F9: if_icmpeq @107
		// @0FC: aconst_null
		// @0FD: checkcast java.lang.String
		// @100: putstatic java.lang.String game.C_100118_ub.field_102057_ac
		// @103: goto @107
		// @106: athrow
		// @107: iconst_1
		// @108: ireturn
		// @109: astore_2
		// @10A: aload_2
		// @10B: new java.lang.StringBuilder
		// @10E: dup
		// @10F: invokespecial java.lang.StringBuilder.<init>()void
		// @112: getstatic java.lang.String[] game.C_100118_ub.field_102053_dc
		// @115: iconst_5
		// @116: aaload
		// @117: invokevirtual java.lang.StringBuilder.append(java.lang.String)java.lang.StringBuilder
		// @11A: iload_1
		// @11B: invokevirtual java.lang.StringBuilder.append(int)java.lang.StringBuilder
		// @11E: bipush 41 (0x29)
		// @120: invokevirtual java.lang.StringBuilder.append(char)java.lang.StringBuilder
		// @123: invokevirtual java.lang.StringBuilder.toString()java.lang.String
		// @126: invokestatic game.C_100181_cf.func_105695_a(java.lang.Throwable, java.lang.String)game.C_100170_cm
		// @129: athrow
	}
	
	static final String func_102051_a(String arg0, char arg1, String arg2, int arg3)
	{
		// @000: getstatic int game.SteelSentinels.field_105275_O
		// @003: istore #11
		// @005: aload_0
		// @006: invokevirtual java.lang.String.length()int
		// @009: istore #4
		// @00B: aload_2
		// @00C: invokevirtual java.lang.String.length()int
		// @00F: istore #5
		// @011: iload #4
		// @013: istore #6
		// @015: iload #5
		// @017: iconst_m1
		// @018: iadd
		// @019: istore #7
		// @01B: iload #7
		// @01D: ifeq @051
		// @020: iconst_0
		// @021: istore #8
		// @023: aload_0
		// @024: iload_1
		// @025: iload #8
		// @027: invokevirtual java.lang.String.indexOf(int, int)int
		// @02A: istore #8
		// @02C: iload #8
		// @02E: iconst_m1
		// @02F: ixor
		// @030: iconst_m1
		// @031: if_icmple @042
		// @034: iload #11
		// @036: ifne @04C
		// @039: iload #11
		// @03B: ifeq @051
		// @03E: goto @042
		// @041: athrow
		// @042: iload #6
		// @044: iload #7
		// @046: iadd
		// @047: istore #6
		// @049: iinc #8 +1
		// @04C: iload #11
		// @04E: ifeq @023
		// @051: new java.lang.StringBuilder
		// @054: dup
		// @055: iload #6
		// @057: invokespecial java.lang.StringBuilder.<init>(int)void
		// @05A: astore #8
		// @05C: iload_3
		// @05D: istore #9
		// @05F: aload_0
		// @060: iload_1
		// @061: iload #9
		// @063: invokevirtual java.lang.String.indexOf(int, int)int
		// @066: istore #10
		// @068: iload #10
		// @06A: iconst_m1
		// @06B: ixor
		// @06C: iconst_m1
		// @06D: if_icmpgt @099
		// @070: aload #8
		// @072: aload_0
		// @073: iload #9
		// @075: iload #10
		// @077: invokevirtual java.lang.String.substring(int, int)java.lang.String
		// @07A: invokevirtual java.lang.StringBuilder.append(java.lang.String)java.lang.StringBuilder
		// @07D: pop
		// @07E: aload #8
		// @080: aload_2
		// @081: invokevirtual java.lang.StringBuilder.append(java.lang.String)java.lang.StringBuilder
		// @084: pop
		// @085: iconst_1
		// @086: iload #10
		// @088: iadd
		// @089: istore #9
		// @08B: iload #11
		// @08D: ifne @0A5
		// @090: iload #11
		// @092: ifeq @05F
		// @095: goto @099
		// @098: athrow
		// @099: aload #8
		// @09B: aload_0
		// @09C: iload #9
		// @09E: invokevirtual java.lang.String.substring(int)java.lang.String
		// @0A1: invokevirtual java.lang.StringBuilder.append(java.lang.String)java.lang.StringBuilder
		// @0A4: pop
		// @0A5: aload #8
		// @0A7: invokevirtual java.lang.StringBuilder.toString()java.lang.String
		// @0AA: areturn
		// @0AB: astore #4
		// @0AD: aload #4
		// @0AF: new java.lang.StringBuilder
		// @0B2: dup
		// @0B3: invokespecial java.lang.StringBuilder.<init>()void
		// @0B6: getstatic java.lang.String[] game.C_100118_ub.field_102053_dc
		// @0B9: iconst_2
		// @0BA: aaload
		// @0BB: invokevirtual java.lang.StringBuilder.append(java.lang.String)java.lang.StringBuilder
		// @0BE: aload_0
		// @0BF: ifnull @0CB
		// @0C2: getstatic java.lang.String[] game.C_100118_ub.field_102053_dc
		// @0C5: iconst_1
		// @0C6: aaload
		// @0C7: goto @0D0
		// @0CA: athrow
		// @0CB: getstatic java.lang.String[] game.C_100118_ub.field_102053_dc
		// @0CE: iconst_0
		// @0CF: aaload
		// @0D0: invokevirtual java.lang.StringBuilder.append(java.lang.String)java.lang.StringBuilder
		// @0D3: bipush 44 (0x2C)
		// @0D5: invokevirtual java.lang.StringBuilder.append(char)java.lang.StringBuilder
		// @0D8: iload_1
		// @0D9: invokevirtual java.lang.StringBuilder.append(char)java.lang.StringBuilder
		// @0DC: bipush 44 (0x2C)
		// @0DE: invokevirtual java.lang.StringBuilder.append(char)java.lang.StringBuilder
		// @0E1: aload_2
		// @0E2: ifnull @0EE
		// @0E5: getstatic java.lang.String[] game.C_100118_ub.field_102053_dc
		// @0E8: iconst_1
		// @0E9: aaload
		// @0EA: goto @0F3
		// @0ED: athrow
		// @0EE: getstatic java.lang.String[] game.C_100118_ub.field_102053_dc
		// @0F1: iconst_0
		// @0F2: aaload
		// @0F3: invokevirtual java.lang.StringBuilder.append(java.lang.String)java.lang.StringBuilder
		// @0F6: bipush 44 (0x2C)
		// @0F8: invokevirtual java.lang.StringBuilder.append(char)java.lang.StringBuilder
		// @0FB: iload_3
		// @0FC: invokevirtual java.lang.StringBuilder.append(int)java.lang.StringBuilder
		// @0FF: bipush 41 (0x29)
		// @101: invokevirtual java.lang.StringBuilder.append(char)java.lang.StringBuilder
		// @104: invokevirtual java.lang.StringBuilder.toString()java.lang.String
		// @107: invokestatic game.C_100181_cf.func_105695_a(java.lang.Throwable, java.lang.String)game.C_100170_cm
		// @10A: athrow
	}
	
	static final void func_102049_a(C_100179_ch arg0, byte arg1)
	{
		// @00: getstatic game.C_100026_hb game.C_100059_df.field_101599_L
		// @03: aload_0
		// @04: getfield game.C_100117_p game.C_100179_ch.field_100808_r
		// @07: invokevirtual game.C_100026_hb.func_100925_a(game.C_100261_md)void
		// @0A: iload_1
		// @0B: bipush -112 (0x90)
		// @0D: if_icmple @15
		// @10: bipush -9 (0xF7)
		// @12: invokestatic game.C_100118_ub.func_102046_l(int)void
		// @15: goto @53
		// @18: astore_2
		// @19: aload_2
		// @1A: new java.lang.StringBuilder
		// @1D: dup
		// @1E: invokespecial java.lang.StringBuilder.<init>()void
		// @21: getstatic java.lang.String[] game.C_100118_ub.field_102053_dc
		// @24: iconst_4
		// @25: aaload
		// @26: invokevirtual java.lang.StringBuilder.append(java.lang.String)java.lang.StringBuilder
		// @29: aload_0
		// @2A: ifnull @36
		// @2D: getstatic java.lang.String[] game.C_100118_ub.field_102053_dc
		// @30: iconst_1
		// @31: aaload
		// @32: goto @3B
		// @35: athrow
		// @36: getstatic java.lang.String[] game.C_100118_ub.field_102053_dc
		// @39: iconst_0
		// @3A: aaload
		// @3B: invokevirtual java.lang.StringBuilder.append(java.lang.String)java.lang.StringBuilder
		// @3E: bipush 44 (0x2C)
		// @40: invokevirtual java.lang.StringBuilder.append(char)java.lang.StringBuilder
		// @43: iload_1
		// @44: invokevirtual java.lang.StringBuilder.append(int)java.lang.StringBuilder
		// @47: bipush 41 (0x29)
		// @49: invokevirtual java.lang.StringBuilder.append(char)java.lang.StringBuilder
		// @4C: invokevirtual java.lang.StringBuilder.toString()java.lang.String
		// @4F: invokestatic game.C_100181_cf.func_105695_a(java.lang.Throwable, java.lang.String)game.C_100170_cm
		// @52: athrow
		// @53: return
	}
	
	C_100118_ub(int arg0, int arg1, int arg2, int arg3, String arg4, C_100302_ka arg5, C_100302_ka arg6, C_100302_ka arg7)
	{
		// @000: aload_0
		// @001: lconst_0
		// @002: aload #6
		// @004: invokespecial game.C_100302_ka.<init>(long, game.C_100302_ka)void
		// @007: aload_0
		// @008: iconst_0
		// @009: putfield int game.C_100118_ub.field_102058_Zb
		// @00C: aload_0
		// @00D: new game.C_100302_ka
		// @010: dup
		// @011: lconst_0
		// @012: aload #7
		// @014: aload #5
		// @016: invokespecial game.C_100302_ka.<init>(long, game.C_100302_ka, java.lang.String)void
		// @019: putfield game.C_100302_ka game.C_100118_ub.field_102056_Vb
		// @01C: aload_0
		// @01D: bipush -70 (0xBA)
		// @01F: aload_0
		// @020: getfield game.C_100302_ka game.C_100118_ub.field_102056_Vb
		// @023: invokevirtual game.C_100118_ub.func_101824_b(int, game.C_100302_ka)void
		// @026: aload_0
		// @027: new game.C_100302_ka
		// @02A: dup
		// @02B: lconst_0
		// @02C: aload #8
		// @02E: invokespecial game.C_100302_ka.<init>(long, game.C_100302_ka)void
		// @031: putfield game.C_100302_ka game.C_100118_ub.field_102055_Ub
		// @034: aload_0
		// @035: getfield game.C_100302_ka game.C_100118_ub.field_102055_Ub
		// @038: ldc 16764006 (0xffcc66)
		// @03A: putfield int game.C_100302_ka.field_101830_gb
		// @03D: aload_0
		// @03E: bipush -116 (0x8C)
		// @040: aload_0
		// @041: getfield game.C_100302_ka game.C_100118_ub.field_102055_Ub
		// @044: invokevirtual game.C_100118_ub.func_101824_b(int, game.C_100302_ka)void
		// @047: aload_0
		// @048: getfield game.C_100302_ka game.C_100118_ub.field_102055_Ub
		// @04B: ldc "|"
		// @04D: putfield java.lang.String game.C_100302_ka.field_101856_I
		// @050: aload_0
		// @051: new java.lang.StringBuilder
		// @054: dup
		// @055: bipush 12 (0x0C)
		// @057: invokespecial java.lang.StringBuilder.<init>(int)void
		// @05A: putfield java.lang.StringBuilder game.C_100118_ub.field_102059_Xb
		// @05D: aload_0
		// @05E: getfield game.C_100302_ka game.C_100118_ub.field_102056_Vb
		// @061: ldc 218000 (0x35390)
		// @063: invokevirtual game.C_100302_ka.func_101818_j(int)int
		// @066: istore #9
		// @068: aload_0
		// @069: getfield game.C_100302_ka game.C_100118_ub.field_102056_Vb
		// @06C: iconst_5
		// @06D: getstatic int game.C_100033_gj.field_101917_jc
		// @070: iconst_m1
		// @071: iconst_3
		// @072: iload #9
		// @074: invokevirtual game.C_100302_ka.func_101825_a(int, int, int, int, int)void
		// @077: aload_0
		// @078: getfield game.C_100302_ka game.C_100118_ub.field_102055_Ub
		// @07B: iconst_5
		// @07C: getstatic int game.C_100033_gj.field_101917_jc
		// @07F: iconst_m1
		// @080: getstatic int game.C_100033_gj.field_101917_jc
		// @083: iconst_3
		// @084: iadd
		// @085: iload #9
		// @087: invokevirtual game.C_100302_ka.func_101825_a(int, int, int, int, int)void
		// @08A: iload #9
		// @08C: bipush 10 (0x0A)
		// @08E: iadd
		// @08F: istore #10
		// @091: iconst_3
		// @092: getstatic int game.C_100033_gj.field_101917_jc
		// @095: iconst_2
		// @096: imul
		// @097: iconst_3
		// @098: iadd
		// @099: iadd
		// @09A: istore #11
		// @09C: iload_3
		// @09D: iload_1
		// @09E: iload #10
		// @0A0: iconst_m1
		// @0A1: invokestatic game.C_100211_qd.func_102123_a(int, int, int, int)int
		// @0A4: istore #12
		// @0A6: iload #4
		// @0A8: iload #11
		// @0AA: sipush -19295 (0xB4A1)
		// @0AD: iload_2
		// @0AE: invokestatic game.C_100257_ln.func_106471_a(int, int, int, int)int
		// @0B1: istore #13
		// @0B3: aload_0
		// @0B4: iload #12
		// @0B6: iload #11
		// @0B8: iconst_m1
		// @0B9: iload #13
		// @0BB: iload #10
		// @0BD: invokevirtual game.C_100118_ub.func_101825_a(int, int, int, int, int)void
		// @0C0: goto @16E
		// @0C3: astore #9
		// @0C5: aload #9
		// @0C7: new java.lang.StringBuilder
		// @0CA: dup
		// @0CB: invokespecial java.lang.StringBuilder.<init>()void
		// @0CE: getstatic java.lang.String[] game.C_100118_ub.field_102053_dc
		// @0D1: iconst_3
		// @0D2: aaload
		// @0D3: invokevirtual java.lang.StringBuilder.append(java.lang.String)java.lang.StringBuilder
		// @0D6: iload_1
		// @0D7: invokevirtual java.lang.StringBuilder.append(int)java.lang.StringBuilder
		// @0DA: bipush 44 (0x2C)
		// @0DC: invokevirtual java.lang.StringBuilder.append(char)java.lang.StringBuilder
		// @0DF: iload_2
		// @0E0: invokevirtual java.lang.StringBuilder.append(int)java.lang.StringBuilder
		// @0E3: bipush 44 (0x2C)
		// @0E5: invokevirtual java.lang.StringBuilder.append(char)java.lang.StringBuilder
		// @0E8: iload_3
		// @0E9: invokevirtual java.lang.StringBuilder.append(int)java.lang.StringBuilder
		// @0EC: bipush 44 (0x2C)
		// @0EE: invokevirtual java.lang.StringBuilder.append(char)java.lang.StringBuilder
		// @0F1: iload #4
		// @0F3: invokevirtual java.lang.StringBuilder.append(int)java.lang.StringBuilder
		// @0F6: bipush 44 (0x2C)
		// @0F8: invokevirtual java.lang.StringBuilder.append(char)java.lang.StringBuilder
		// @0FB: aload #5
		// @0FD: ifnull @109
		// @100: getstatic java.lang.String[] game.C_100118_ub.field_102053_dc
		// @103: iconst_1
		// @104: aaload
		// @105: goto @10E
		// @108: athrow
		// @109: getstatic java.lang.String[] game.C_100118_ub.field_102053_dc
		// @10C: iconst_0
		// @10D: aaload
		// @10E: invokevirtual java.lang.StringBuilder.append(java.lang.String)java.lang.StringBuilder
		// @111: bipush 44 (0x2C)
		// @113: invokevirtual java.lang.StringBuilder.append(char)java.lang.StringBuilder
		// @116: aload #6
		// @118: ifnull @124
		// @11B: getstatic java.lang.String[] game.C_100118_ub.field_102053_dc
		// @11E: iconst_1
		// @11F: aaload
		// @120: goto @129
		// @123: athrow
		// @124: getstatic java.lang.String[] game.C_100118_ub.field_102053_dc
		// @127: iconst_0
		// @128: aaload
		// @129: invokevirtual java.lang.StringBuilder.append(java.lang.String)java.lang.StringBuilder
		// @12C: bipush 44 (0x2C)
		// @12E: invokevirtual java.lang.StringBuilder.append(char)java.lang.StringBuilder
		// @131: aload #7
		// @133: ifnull @13F
		// @136: getstatic java.lang.String[] game.C_100118_ub.field_102053_dc
		// @139: iconst_1
		// @13A: aaload
		// @13B: goto @144
		// @13E: athrow
		// @13F: getstatic java.lang.String[] game.C_100118_ub.field_102053_dc
		// @142: iconst_0
		// @143: aaload
		// @144: invokevirtual java.lang.StringBuilder.append(java.lang.String)java.lang.StringBuilder
		// @147: bipush 44 (0x2C)
		// @149: invokevirtual java.lang.StringBuilder.append(char)java.lang.StringBuilder
		// @14C: aload #8
		// @14E: ifnull @15A
		// @151: getstatic java.lang.String[] game.C_100118_ub.field_102053_dc
		// @154: iconst_1
		// @155: aaload
		// @156: goto @15F
		// @159: athrow
		// @15A: getstatic java.lang.String[] game.C_100118_ub.field_102053_dc
		// @15D: iconst_0
		// @15E: aaload
		// @15F: invokevirtual java.lang.StringBuilder.append(java.lang.String)java.lang.StringBuilder
		// @162: bipush 41 (0x29)
		// @164: invokevirtual java.lang.StringBuilder.append(char)java.lang.StringBuilder
		// @167: invokevirtual java.lang.StringBuilder.toString()java.lang.String
		// @16A: invokestatic game.C_100181_cf.func_105695_a(java.lang.Throwable, java.lang.String)game.C_100170_cm
		// @16D: athrow
		// @16E: return
	}
	
	final int func_102052_b(boolean arg0, byte arg1)
	{
		// @000: getstatic int game.SteelSentinels.field_105275_O
		// @003: istore #4
		// @005: aload_0
		// @006: iload_1
		// @007: bipush -128 (0x80)
		// @009: invokevirtual game.C_100118_ub.func_101819_a(boolean, byte)void
		// @00C: iload_1
		// @00D: ifne @014
		// @010: goto @0F5
		// @013: athrow
		// @014: bipush 64 (0x40)
		// @016: invokestatic game.C_100189_ri.func_105748_a(int)boolean
		// @019: ifeq @0F5
		// @01C: bipush 85 (0x55)
		// @01E: getstatic int game.C_100293_kj.field_106890_c
		// @021: iload #4
		// @023: ifne @0F8
		// @026: goto @02A
		// @029: athrow
		// @02A: if_icmpne @059
		// @02D: goto @031
		// @030: athrow
		// @031: iconst_0
		// @032: aload_0
		// @033: getfield java.lang.StringBuilder game.C_100118_ub.field_102059_Xb
		// @036: invokevirtual java.lang.StringBuilder.length()int
		// @039: if_icmpge @059
		// @03C: goto @040
		// @03F: athrow
		// @040: bipush 32 (0x20)
		// @042: bipush 112 (0x70)
		// @044: aload_0
		// @045: getfield java.lang.StringBuilder game.C_100118_ub.field_102059_Xb
		// @048: iconst_m1
		// @049: aload_0
		// @04A: getfield java.lang.StringBuilder game.C_100118_ub.field_102059_Xb
		// @04D: invokevirtual java.lang.StringBuilder.length()int
		// @050: iadd
		// @051: invokestatic game.C_100062_dk.func_104278_a(char, byte, java.lang.StringBuilder, int)java.lang.StringBuilder
		// @054: pop
		// @055: goto @059
		// @058: athrow
		// @059: aload_0
		// @05A: getfield java.lang.StringBuilder game.C_100118_ub.field_102059_Xb
		// @05D: iconst_1
		// @05E: getstatic char game.C_100012_fh.field_100517_Q
		// @061: invokestatic game.C_100234_ob.func_106269_a(java.lang.CharSequence, boolean, char)boolean
		// @064: ifne @0B2
		// @067: aload_0
		// @068: getfield java.lang.StringBuilder game.C_100118_ub.field_102059_Xb
		// @06B: invokevirtual java.lang.StringBuilder.length()int
		// @06E: ifne @083
		// @071: goto @075
		// @074: athrow
		// @075: bipush -92 (0xA4)
		// @077: getstatic char game.C_100012_fh.field_100517_Q
		// @07A: iconst_m1
		// @07B: ixor
		// @07C: if_icmpeq @0B2
		// @07F: goto @083
		// @082: athrow
		// @083: iconst_1
		// @084: aload_0
		// @085: getfield java.lang.StringBuilder game.C_100118_ub.field_102059_Xb
		// @088: invokevirtual java.lang.StringBuilder.length()int
		// @08B: if_icmpne @0A0
		// @08E: goto @092
		// @091: athrow
		// @092: bipush -36 (0xDC)
		// @094: getstatic char game.C_100012_fh.field_100517_Q
		// @097: iconst_m1
		// @098: ixor
		// @099: if_icmpeq @0B2
		// @09C: goto @0A0
		// @09F: athrow
		// @0A0: getstatic char game.C_100012_fh.field_100517_Q
		// @0A3: iconst_m1
		// @0A4: ixor
		// @0A5: bipush -94 (0xA2)
		// @0A7: if_icmpeq @0B2
		// @0AA: goto @0AE
		// @0AD: athrow
		// @0AE: goto @0BD
		// @0B1: athrow
		// @0B2: aload_0
		// @0B3: getfield java.lang.StringBuilder game.C_100118_ub.field_102059_Xb
		// @0B6: getstatic char game.C_100012_fh.field_100517_Q
		// @0B9: invokevirtual java.lang.StringBuilder.append(char)java.lang.StringBuilder
		// @0BC: pop
		// @0BD: bipush -85 (0xAB)
		// @0BF: getstatic int game.C_100293_kj.field_106890_c
		// @0C2: iconst_m1
		// @0C3: ixor
		// @0C4: if_icmpeq @0CB
		// @0C7: goto @0E5
		// @0CA: athrow
		// @0CB: iconst_0
		// @0CC: aload_0
		// @0CD: getfield java.lang.StringBuilder game.C_100118_ub.field_102059_Xb
		// @0D0: invokevirtual java.lang.StringBuilder.length()int
		// @0D3: if_icmpge @0E3
		// @0D6: aload_0
		// @0D7: aload_0
		// @0D8: getfield java.lang.StringBuilder game.C_100118_ub.field_102059_Xb
		// @0DB: invokevirtual java.lang.StringBuilder.toString()java.lang.String
		// @0DE: putfield java.lang.String game.C_100118_ub.field_101890_ab
		// @0E1: iconst_2
		// @0E2: ireturn
		// @0E3: iconst_1
		// @0E4: ireturn
		// @0E5: getstatic int game.C_100293_kj.field_106890_c
		// @0E8: iconst_m1
		// @0E9: ixor
		// @0EA: bipush -14 (0xF2)
		// @0EC: if_icmpeq @0F3
		// @0EF: goto @014
		// @0F2: athrow
		// @0F3: iconst_1
		// @0F4: ireturn
		// @0F5: iload_2
		// @0F6: bipush 13 (0x0D)
		// @0F8: if_icmpeq @0FE
		// @0FB: bipush -81 (0xAF)
		// @0FD: ireturn
		// @0FE: aload_0
		// @0FF: getfield game.C_100302_ka game.C_100118_ub.field_102055_Ub
		// @102: aload_0
		// @103: getfield java.lang.StringBuilder game.C_100118_ub.field_102059_Xb
		// @106: invokevirtual java.lang.StringBuilder.toString()java.lang.String
		// @109: putfield java.lang.String game.C_100302_ka.field_101890_ab
		// @10C: iload_1
		// @10D: ifeq @131
		// @110: getstatic int game.C_100102_w.field_104636_c
		// @113: ifeq @131
		// @116: goto @11A
		// @119: athrow
		// @11A: iconst_m1
		// @11B: aload_0
		// @11C: getfield int game.C_100118_ub.field_101854_N
		// @11F: iconst_m1
		// @120: ixor
		// @121: if_icmpeq @12C
		// @124: goto @128
		// @127: athrow
		// @128: goto @131
		// @12B: athrow
		// @12C: aload_0
		// @12D: iconst_1
		// @12E: putfield int game.C_100118_ub.field_102058_Zb
		// @131: aload_0
		// @132: getfield int game.C_100118_ub.field_102058_Zb
		// @135: ireturn
		// @136: astore_3
		// @137: aload_3
		// @138: new java.lang.StringBuilder
		// @13B: dup
		// @13C: invokespecial java.lang.StringBuilder.<init>()void
		// @13F: getstatic java.lang.String[] game.C_100118_ub.field_102053_dc
		// @142: bipush 6 (0x06)
		// @144: aaload
		// @145: invokevirtual java.lang.StringBuilder.append(java.lang.String)java.lang.StringBuilder
		// @148: iload_1
		// @149: invokevirtual java.lang.StringBuilder.append(boolean)java.lang.StringBuilder
		// @14C: bipush 44 (0x2C)
		// @14E: invokevirtual java.lang.StringBuilder.append(char)java.lang.StringBuilder
		// @151: iload_2
		// @152: invokevirtual java.lang.StringBuilder.append(int)java.lang.StringBuilder
		// @155: bipush 41 (0x29)
		// @157: invokevirtual java.lang.StringBuilder.append(char)java.lang.StringBuilder
		// @15A: invokevirtual java.lang.StringBuilder.toString()java.lang.String
		// @15D: invokestatic game.C_100181_cf.func_105695_a(java.lang.Throwable, java.lang.String)game.C_100170_cm
		// @160: athrow
	}
	
	static
	{
		// @00: bipush 8 (0x08)
		// @02: anewarray java.lang.String
		// @05: dup
		// @06: iconst_0
		// @07: ldc "I\u007f&\u0018"
		// @09: invokestatic game.C_100118_ub.func_102048_z(java.lang.String)char[]
		// @0C: invokestatic game.C_100118_ub.func_102047_z(char[])java.lang.String
		// @0F: aastore
		// @10: dup
		// @11: iconst_1
		// @12: ldc "\\$dZo"
		// @14: invokestatic game.C_100118_ub.func_102048_z(java.lang.String)char[]
		// @17: invokestatic game.C_100118_ub.func_102047_z(char[])java.lang.String
		// @1A: aastore
		// @1B: dup
		// @1C: iconst_2
		// @1D: ldc "Rhd0:"
		// @1F: invokestatic game.C_100118_ub.func_102048_z(java.lang.String)char[]
		// @22: invokestatic game.C_100118_ub.func_102047_z(char[])java.lang.String
		// @25: aastore
		// @26: dup
		// @27: iconst_3
		// @28: ldc "RhdH{Ic>J:"
		// @2A: invokestatic game.C_100118_ub.func_102048_z(java.lang.String)char[]
		// @2D: invokestatic game.C_100118_ub.func_102047_z(char[])java.lang.String
		// @30: aastore
		// @31: dup
		// @32: iconst_4
		// @33: ldc "Rhd5:"
		// @35: invokestatic game.C_100118_ub.func_102048_z(java.lang.String)char[]
		// @38: invokestatic game.C_100118_ub.func_102047_z(char[])java.lang.String
		// @3B: aastore
		// @3C: dup
		// @3D: iconst_5
		// @3E: ldc "Rhd7:"
		// @40: invokestatic game.C_100118_ub.func_102048_z(java.lang.String)char[]
		// @43: invokestatic game.C_100118_ub.func_102047_z(char[])java.lang.String
		// @46: aastore
		// @47: dup
		// @48: bipush 6 (0x06)
		// @4A: ldc "Rhd1:"
		// @4C: invokestatic game.C_100118_ub.func_102048_z(java.lang.String)char[]
		// @4F: invokestatic game.C_100118_ub.func_102047_z(char[])java.lang.String
		// @52: aastore
		// @53: dup
		// @54: bipush 7 (0x07)
		// @56: ldc "Rhd6:"
		// @58: invokestatic game.C_100118_ub.func_102048_z(java.lang.String)char[]
		// @5B: invokestatic game.C_100118_ub.func_102047_z(char[])java.lang.String
		// @5E: aastore
		// @5F: putstatic java.lang.String[] game.C_100118_ub.field_102053_dc
		// @62: bipush 8 (0x08)
		// @64: anewarray java.lang.String
		// @67: dup
		// @68: iconst_0
		// @69: aconst_null
		// @6A: aastore
		// @6B: dup
		// @6C: iconst_1
		// @6D: ldc "hxj\u0017~Ni!"
		// @6F: invokestatic game.C_100118_ub.func_102048_z(java.lang.String)char[]
		// @72: invokestatic game.C_100118_ub.func_102047_z(char[])java.lang.String
		// @75: aastore
		// @76: dup
		// @77: iconst_2
		// @78: ldc "hxj\u0017~Ni!"
		// @7A: invokestatic game.C_100118_ub.func_102048_z(java.lang.String)char[]
		// @7D: invokestatic game.C_100118_ub.func_102047_z(char[])java.lang.String
		// @80: aastore
		// @81: dup
		// @82: iconst_3
		// @83: ldc "hxj\u0017~Ni!"
		// @85: invokestatic game.C_100118_ub.func_102048_z(java.lang.String)char[]
		// @88: invokestatic game.C_100118_ub.func_102047_z(char[])java.lang.String
		// @8B: aastore
		// @8C: dup
		// @8D: iconst_4
		// @8E: ldc "hxj\u0017~Ni!"
		// @90: invokestatic game.C_100118_ub.func_102048_z(java.lang.String)char[]
		// @93: invokestatic game.C_100118_ub.func_102047_z(char[])java.lang.String
		// @96: aastore
		// @97: dup
		// @98: iconst_5
		// @99: ldc "hxj\u0017~Ni!"
		// @9B: invokestatic game.C_100118_ub.func_102048_z(java.lang.String)char[]
		// @9E: invokestatic game.C_100118_ub.func_102047_z(char[])java.lang.String
		// @A1: aastore
		// @A2: dup
		// @A3: bipush 6 (0x06)
		// @A5: ldc "hxj\u0017~Ni!"
		// @A7: invokestatic game.C_100118_ub.func_102048_z(java.lang.String)char[]
		// @AA: invokestatic game.C_100118_ub.func_102047_z(char[])java.lang.String
		// @AD: aastore
		// @AE: dup
		// @AF: bipush 7 (0x07)
		// @B1: ldc "hxj\u0017~Ni!"
		// @B3: invokestatic game.C_100118_ub.func_102048_z(java.lang.String)char[]
		// @B6: invokestatic game.C_100118_ub.func_102047_z(char[])java.lang.String
		// @B9: aastore
		// @BA: putstatic java.lang.String[] game.C_100118_ub.field_102062_cc
		// @BD: ldc "te'\u00112Wf+\rwUyj\u001csQo$Sf\u0007\u007f$\u0018}Da/\u00102Sb/TqRx8\u0011|Sf3TaBf/\u0017fBnj\u0013sJoj\u001bbSc%\u001aa\t6(\u0006,wf/\u0015aB*<\u001dwP*>\u001cw\u0007-vQ\"\u0019-j\u0000sE*%\u001a2Sb/T~Bl>TtHxj\u0010wSk#\u0018a\t"
		// @BF: invokestatic game.C_100118_ub.func_102048_z(java.lang.String)char[]
		// @C2: invokestatic game.C_100118_ub.func_102047_z(char[])java.lang.String
		// @C5: putstatic java.lang.String game.C_100118_ub.field_102060_Yb
		// @C8: ldc "co,\u0015gK~j\u0015`J*,\u001b`\u0007~\"\u00112\u001b/zJ?Df+\u0007a\u0007y/\u001afNd/\u0018<"
		// @CA: invokestatic game.C_100118_ub.func_102048_z(java.lang.String)char[]
		// @CD: invokestatic game.C_100118_ub.func_102047_z(char[])java.lang.String
		// @D0: putstatic java.lang.String game.C_100118_ub.field_102057_ac
		// @D3: return
	}
	
	private static char[] func_102048_z(String arg0)
	{
		// @00: aload_0
		// @01: invokevirtual java.lang.String.toCharArray()char[]
		// @04: dup
		// @05: arraylength
		// @06: iconst_2
		// @07: if_icmpge @13
		// @0A: dup
		// @0B: iconst_0
		// @0C: dup2
		// @0D: caload
		// @0E: bipush 18 (0x12)
		// @10: ixor
		// @11: i2c
		// @12: castore
		// @13: areturn
	}
	
	private static String func_102047_z(char[] arg0)
	{
		// @00: aload_0
		// @01: dup
		// @02: arraylength
		// @03: swap
		// @04: iconst_0
		// @05: istore_1
		// @06: goto @4C
		// @09: dup
		// @0A: iload_1
		// @0B: dup2
		// @0C: caload
		// @0D: iload_1
		// @0E: iconst_5
		// @0F: irem
		// @10: tableswitch def: @44, for 0: @30, for 1: @35, for 2: @3A, for 3: @3F
		// @30: bipush 39 (0x27)
		// @32: goto @46
		// @35: bipush 10 (0x0A)
		// @37: goto @46
		// @3A: bipush 74 (0x4A)
		// @3C: goto @46
		// @3F: bipush 116 (0x74)
		// @41: goto @46
		// @44: bipush 18 (0x12)
		// @46: ixor
		// @47: i2c
		// @48: castore
		// @49: iinc #1 +1
		// @4C: swap
		// @4D: dup_x1
		// @4E: iload_1
		// @4F: if_icmpgt @09
		// @52: new java.lang.String
		// @55: dup_x1
		// @56: swap
		// @57: invokespecial java.lang.String.<init>(char[])void
		// @5A: invokevirtual java.lang.String.intern()java.lang.String
		// @5D: areturn
	}
}
