package game;

abstract class C_100051_ea extends C_100085_a implements C_100267_mf
{
	static String field_103308_P;
	static String field_103306_T;
	private C_100275_na field_103309_S;
	static String field_103310_R;
	static C_100037_wb[][] field_103307_Q;
	private static final String[] field_103305_U;
	
	public final C_100308_lh func_103100_a(boolean arg0)
	{
		// @00: iload_1
		// @01: iconst_1
		// @02: if_icmpeq @10
		// @05: aload_0
		// @06: bipush 123 (0x7B)
		// @08: invokevirtual game.C_100051_ea.func_103299_k(int)int
		// @0B: pop
		// @0C: goto @10
		// @0F: athrow
		// @10: aload_0
		// @11: getfield game.C_100275_na game.C_100051_ea.field_103309_S
		// @14: areturn
		// @15: astore_2
		// @16: aload_2
		// @17: new java.lang.StringBuilder
		// @1A: dup
		// @1B: invokespecial java.lang.StringBuilder.<init>()void
		// @1E: getstatic java.lang.String[] game.C_100051_ea.field_103305_U
		// @21: iconst_5
		// @22: aaload
		// @23: invokevirtual java.lang.StringBuilder.append(java.lang.String)java.lang.StringBuilder
		// @26: iload_1
		// @27: invokevirtual java.lang.StringBuilder.append(boolean)java.lang.StringBuilder
		// @2A: bipush 41 (0x29)
		// @2C: invokevirtual java.lang.StringBuilder.append(char)java.lang.StringBuilder
		// @2F: invokevirtual java.lang.StringBuilder.toString()java.lang.String
		// @32: invokestatic game.C_100181_cf.func_105695_a(java.lang.Throwable, java.lang.String)game.C_100170_cm
		// @35: athrow
	}
	
	public static void func_103295_m(int arg0)
	{
		// @00: aconst_null
		// @01: checkcast game.C_100037_wb[][]
		// @04: putstatic game.C_100037_wb[][] game.C_100051_ea.field_103307_Q
		// @07: aconst_null
		// @08: putstatic java.lang.String game.C_100051_ea.field_103310_R
		// @0B: aconst_null
		// @0C: putstatic java.lang.String game.C_100051_ea.field_103308_P
		// @0F: iload_0
		// @10: iconst_m1
		// @11: if_icmpeq @27
		// @14: iconst_0
		// @15: bipush -13 (0xF3)
		// @17: iconst_2
		// @18: bipush -21 (0xEB)
		// @1A: bipush -83 (0xAD)
		// @1C: bipush -115 (0x8D)
		// @1E: bipush -70 (0xBA)
		// @20: invokestatic game.C_100051_ea.func_103297_a(boolean, byte, int, int, int, int, int)void
		// @23: goto @27
		// @26: athrow
		// @27: aconst_null
		// @28: putstatic java.lang.String game.C_100051_ea.field_103306_T
		// @2B: goto @50
		// @2E: astore_1
		// @2F: aload_1
		// @30: new java.lang.StringBuilder
		// @33: dup
		// @34: invokespecial java.lang.StringBuilder.<init>()void
		// @37: getstatic java.lang.String[] game.C_100051_ea.field_103305_U
		// @3A: bipush 7 (0x07)
		// @3C: aaload
		// @3D: invokevirtual java.lang.StringBuilder.append(java.lang.String)java.lang.StringBuilder
		// @40: iload_0
		// @41: invokevirtual java.lang.StringBuilder.append(int)java.lang.StringBuilder
		// @44: bipush 41 (0x29)
		// @46: invokevirtual java.lang.StringBuilder.append(char)java.lang.StringBuilder
		// @49: invokevirtual java.lang.StringBuilder.toString()java.lang.String
		// @4C: invokestatic game.C_100181_cf.func_105695_a(java.lang.Throwable, java.lang.String)game.C_100170_cm
		// @4F: athrow
		// @50: return
	}
	
	static final boolean func_103301_a(int arg0, int arg1, byte arg2, int arg3)
	{
		// @00: getstatic boolean game.C_100272_mn.field_102435_K
		// @03: ifeq @14
		// @06: getstatic game.C_100320_hh game.C_100047_vh.field_104150_d
		// @09: getstatic int game.C_100293_kj.field_106890_c
		// @0C: getstatic char game.C_100012_fh.field_100517_Q
		// @0F: iconst_1
		// @10: invokevirtual game.C_100320_hh.func_102511_a(int, char, boolean)boolean
		// @13: ireturn
		// @14: iload_2
		// @15: bipush 88 (0x58)
		// @17: if_icmpge @25
		// @1A: aconst_null
		// @1B: checkcast java.lang.String
		// @1E: putstatic java.lang.String game.C_100051_ea.field_103306_T
		// @21: goto @25
		// @24: athrow
		// @25: getstatic boolean game.C_100021_wn.field_103871_b
		// @28: ifne @2F
		// @2B: goto @36
		// @2E: athrow
		// @2F: iload_3
		// @30: iconst_1
		// @31: iload_1
		// @32: invokestatic game.C_100164_se.func_105447_a(int, boolean, int)boolean
		// @35: ireturn
		// @36: iload_1
		// @37: iload_3
		// @38: iconst_2
		// @39: invokestatic game.C_100309_lk.func_103242_b(int, int, int)boolean
		// @3C: ifne @43
		// @3F: goto @45
		// @42: athrow
		// @43: iconst_1
		// @44: ireturn
		// @45: getstatic boolean game.C_100164_se.field_105449_g
		// @48: ifne @4F
		// @4B: goto @51
		// @4E: athrow
		// @4F: iconst_0
		// @50: ireturn
		// @51: iload_0
		// @52: sipush -32533 (0x80EB)
		// @55: iload_3
		// @56: invokestatic game.C_100010_ff.func_103693_b(int, int, int)boolean
		// @59: ireturn
		// @5A: astore #4
		// @5C: aload #4
		// @5E: new java.lang.StringBuilder
		// @61: dup
		// @62: invokespecial java.lang.StringBuilder.<init>()void
		// @65: getstatic java.lang.String[] game.C_100051_ea.field_103305_U
		// @68: bipush 8 (0x08)
		// @6A: aaload
		// @6B: invokevirtual java.lang.StringBuilder.append(java.lang.String)java.lang.StringBuilder
		// @6E: iload_0
		// @6F: invokevirtual java.lang.StringBuilder.append(int)java.lang.StringBuilder
		// @72: bipush 44 (0x2C)
		// @74: invokevirtual java.lang.StringBuilder.append(char)java.lang.StringBuilder
		// @77: iload_1
		// @78: invokevirtual java.lang.StringBuilder.append(int)java.lang.StringBuilder
		// @7B: bipush 44 (0x2C)
		// @7D: invokevirtual java.lang.StringBuilder.append(char)java.lang.StringBuilder
		// @80: iload_2
		// @81: invokevirtual java.lang.StringBuilder.append(int)java.lang.StringBuilder
		// @84: bipush 44 (0x2C)
		// @86: invokevirtual java.lang.StringBuilder.append(char)java.lang.StringBuilder
		// @89: iload_3
		// @8A: invokevirtual java.lang.StringBuilder.append(int)java.lang.StringBuilder
		// @8D: bipush 41 (0x29)
		// @8F: invokevirtual java.lang.StringBuilder.append(char)java.lang.StringBuilder
		// @92: invokevirtual java.lang.StringBuilder.toString()java.lang.String
		// @95: invokestatic game.C_100181_cf.func_105695_a(java.lang.Throwable, java.lang.String)game.C_100170_cm
		// @98: athrow
	}
	
	abstract int func_103303_n(int arg0);
	
	static final void func_103304_a(int arg0, int arg1, int[] arg2, int[][] arg3, int arg4, int arg5, byte arg6)
	{
		// @00: getstatic int game.C_100005_fk.field_103599_m
		// @03: iconst_m1
		// @04: ixor
		// @05: bipush -31 (0xE1)
		// @07: if_icmpgt @13
		// @0A: getstatic int game.C_100005_fk.field_103599_m
		// @0D: iconst_1
		// @0E: iadd
		// @0F: putstatic int game.C_100005_fk.field_103599_m
		// @12: return
		// @13: getstatic int[][] game.C_100005_fk.field_103596_n
		// @16: getstatic int game.C_100005_fk.field_103599_m
		// @19: aaload
		// @1A: iconst_0
		// @1B: iload_0
		// @1C: iastore
		// @1D: getstatic int[][] game.C_100005_fk.field_103596_n
		// @20: getstatic int game.C_100005_fk.field_103599_m
		// @23: aaload
		// @24: iconst_1
		// @25: iload #4
		// @27: iastore
		// @28: getstatic int[][] game.C_100005_fk.field_103596_n
		// @2B: getstatic int game.C_100005_fk.field_103599_m
		// @2E: aaload
		// @2F: iconst_2
		// @30: iload_1
		// @31: iastore
		// @32: getstatic int[][] game.C_100005_fk.field_103596_n
		// @35: getstatic int game.C_100005_fk.field_103599_m
		// @38: aaload
		// @39: iconst_3
		// @3A: iload #5
		// @3C: iastore
		// @3D: iload #6
		// @3F: bipush 125 (0x7D)
		// @41: if_icmpge @45
		// @44: return
		// @45: getstatic int[][] game.C_100005_fk.field_103608_r
		// @48: getstatic int game.C_100005_fk.field_103599_m
		// @4B: aload_2
		// @4C: aastore
		// @4D: getstatic int[][][] game.C_100005_fk.field_103595_a
		// @50: getstatic int game.C_100005_fk.field_103599_m
		// @53: aload_3
		// @54: aastore
		// @55: getstatic int game.C_100005_fk.field_103599_m
		// @58: iconst_1
		// @59: iadd
		// @5A: putstatic int game.C_100005_fk.field_103599_m
		// @5D: goto @DF
		// @60: astore #7
		// @62: aload #7
		// @64: new java.lang.StringBuilder
		// @67: dup
		// @68: invokespecial java.lang.StringBuilder.<init>()void
		// @6B: getstatic java.lang.String[] game.C_100051_ea.field_103305_U
		// @6E: bipush 6 (0x06)
		// @70: aaload
		// @71: invokevirtual java.lang.StringBuilder.append(java.lang.String)java.lang.StringBuilder
		// @74: iload_0
		// @75: invokevirtual java.lang.StringBuilder.append(int)java.lang.StringBuilder
		// @78: bipush 44 (0x2C)
		// @7A: invokevirtual java.lang.StringBuilder.append(char)java.lang.StringBuilder
		// @7D: iload_1
		// @7E: invokevirtual java.lang.StringBuilder.append(int)java.lang.StringBuilder
		// @81: bipush 44 (0x2C)
		// @83: invokevirtual java.lang.StringBuilder.append(char)java.lang.StringBuilder
		// @86: aload_2
		// @87: ifnull @93
		// @8A: getstatic java.lang.String[] game.C_100051_ea.field_103305_U
		// @8D: iconst_3
		// @8E: aaload
		// @8F: goto @98
		// @92: athrow
		// @93: getstatic java.lang.String[] game.C_100051_ea.field_103305_U
		// @96: iconst_1
		// @97: aaload
		// @98: invokevirtual java.lang.StringBuilder.append(java.lang.String)java.lang.StringBuilder
		// @9B: bipush 44 (0x2C)
		// @9D: invokevirtual java.lang.StringBuilder.append(char)java.lang.StringBuilder
		// @A0: aload_3
		// @A1: ifnull @AD
		// @A4: getstatic java.lang.String[] game.C_100051_ea.field_103305_U
		// @A7: iconst_3
		// @A8: aaload
		// @A9: goto @B2
		// @AC: athrow
		// @AD: getstatic java.lang.String[] game.C_100051_ea.field_103305_U
		// @B0: iconst_1
		// @B1: aaload
		// @B2: invokevirtual java.lang.StringBuilder.append(java.lang.String)java.lang.StringBuilder
		// @B5: bipush 44 (0x2C)
		// @B7: invokevirtual java.lang.StringBuilder.append(char)java.lang.StringBuilder
		// @BA: iload #4
		// @BC: invokevirtual java.lang.StringBuilder.append(int)java.lang.StringBuilder
		// @BF: bipush 44 (0x2C)
		// @C1: invokevirtual java.lang.StringBuilder.append(char)java.lang.StringBuilder
		// @C4: iload #5
		// @C6: invokevirtual java.lang.StringBuilder.append(int)java.lang.StringBuilder
		// @C9: bipush 44 (0x2C)
		// @CB: invokevirtual java.lang.StringBuilder.append(char)java.lang.StringBuilder
		// @CE: iload #6
		// @D0: invokevirtual java.lang.StringBuilder.append(int)java.lang.StringBuilder
		// @D3: bipush 41 (0x29)
		// @D5: invokevirtual java.lang.StringBuilder.append(char)java.lang.StringBuilder
		// @D8: invokevirtual java.lang.StringBuilder.toString()java.lang.String
		// @DB: invokestatic game.C_100181_cf.func_105695_a(java.lang.Throwable, java.lang.String)game.C_100170_cm
		// @DE: athrow
		// @DF: return
	}
	
	abstract boolean func_103293_l(int arg0);
	
	void func_103296_a(C_100275_na arg0, int arg1)
	{
		// @00: iload_2
		// @01: bipush -104 (0x98)
		// @03: if_icmplt @16
		// @06: bipush -54 (0xCA)
		// @08: bipush 117 (0x75)
		// @0A: bipush -122 (0x86)
		// @0C: bipush 122 (0x7A)
		// @0E: invokestatic game.C_100051_ea.func_103301_a(int, int, byte, int)boolean
		// @11: pop
		// @12: goto @16
		// @15: athrow
		// @16: aload_0
		// @17: aload_1
		// @18: putfield game.C_100275_na game.C_100051_ea.field_103309_S
		// @1B: aload_0
		// @1C: getfield game.C_100275_na game.C_100051_ea.field_103309_S
		// @1F: aload_0
		// @20: putfield game.C_100051_ea game.C_100275_na.field_103094_r
		// @23: goto @61
		// @26: astore_3
		// @27: aload_3
		// @28: new java.lang.StringBuilder
		// @2B: dup
		// @2C: invokespecial java.lang.StringBuilder.<init>()void
		// @2F: getstatic java.lang.String[] game.C_100051_ea.field_103305_U
		// @32: iconst_2
		// @33: aaload
		// @34: invokevirtual java.lang.StringBuilder.append(java.lang.String)java.lang.StringBuilder
		// @37: aload_1
		// @38: ifnull @44
		// @3B: getstatic java.lang.String[] game.C_100051_ea.field_103305_U
		// @3E: iconst_3
		// @3F: aaload
		// @40: goto @49
		// @43: athrow
		// @44: getstatic java.lang.String[] game.C_100051_ea.field_103305_U
		// @47: iconst_1
		// @48: aaload
		// @49: invokevirtual java.lang.StringBuilder.append(java.lang.String)java.lang.StringBuilder
		// @4C: bipush 44 (0x2C)
		// @4E: invokevirtual java.lang.StringBuilder.append(char)java.lang.StringBuilder
		// @51: iload_2
		// @52: invokevirtual java.lang.StringBuilder.append(int)java.lang.StringBuilder
		// @55: bipush 41 (0x29)
		// @57: invokevirtual java.lang.StringBuilder.append(char)java.lang.StringBuilder
		// @5A: invokevirtual java.lang.StringBuilder.toString()java.lang.String
		// @5D: invokestatic game.C_100181_cf.func_105695_a(java.lang.Throwable, java.lang.String)game.C_100170_cm
		// @60: athrow
		// @61: return
	}
	
	C_100051_ea(int arg0, int arg1, int arg2, int arg3, C_100326_ic arg4)
	{
		// @0: aload_0
		// @1: iload_1
		// @2: iload_2
		// @3: iload_3
		// @4: iload #4
		// @6: aload #5
		// @8: invokespecial game.C_100085_a.<init>(int, int, int, int, game.C_100326_ic)void
		// @B: return
	}
	
	static final boolean func_103302_a(boolean arg0, int arg1)
	{
		// @00: getstatic game.C_100331_ie game.C_100124_tn.field_104937_a
		// @03: ifnull @0A
		// @06: goto @1B
		// @09: athrow
		// @0A: getstatic game.C_100201_qj game.C_100316_lc.field_102417_x
		// @0D: bipush 26 (0x1A)
		// @0F: getstatic int game.C_100180_ce.field_104810_s
		// @12: getstatic java.lang.String game.C_100225_ah.field_106134_r
		// @15: invokevirtual game.C_100201_qj.func_105857_a(byte, int, java.lang.String)game.C_100331_ie
		// @18: putstatic game.C_100331_ie game.C_100124_tn.field_104937_a
		// @1B: getstatic game.C_100331_ie game.C_100124_tn.field_104937_a
		// @1E: getfield int game.C_100331_ie.field_107293_f
		// @21: iload_1
		// @22: if_icmpne @27
		// @25: iconst_0
		// @26: ireturn
		// @27: bipush 66 (0x42)
		// @29: invokestatic game.C_100198_qn.func_105828_a(byte)long
		// @2C: dup2
		// @2D: putstatic long game.C_100174_sb.field_105606_f
		// @30: putstatic long game.C_100236_on.field_100908_p
		// @33: getstatic game.C_100331_ie game.C_100124_tn.field_104937_a
		// @36: getfield int game.C_100331_ie.field_107293_f
		// @39: iconst_m1
		// @3A: ixor
		// @3B: bipush -2 (0xFE)
		// @3D: if_icmpeq @50
		// @40: getstatic game.C_100268_mk game.C_100343_jf.field_104828_k
		// @43: putstatic game.C_100268_mk game.C_100066_dl.field_101642_t
		// @46: getstatic int game.SteelSentinels.field_105275_O
		// @49: ifeq @B2
		// @4C: goto @50
		// @4F: athrow
		// @50: new game.C_100286_nl
		// @53: dup
		// @54: getstatic game.C_100331_ie game.C_100124_tn.field_104937_a
		// @57: getfield java.lang.Object game.C_100331_ie.field_107294_g
		// @5A: checkcast java.net.Socket
		// @5D: getstatic game.C_100201_qj game.C_100316_lc.field_102417_x
		// @60: invokespecial game.C_100286_nl.<init>(java.net.Socket, game.C_100201_qj)void
		// @63: putstatic game.C_100286_nl game.C_100318_hj.field_107194_f
		// @66: getstatic game.C_100278_nd game.C_100115_ej.field_102043_Yb
		// @69: iconst_0
		// @6A: putfield int game.C_100278_nd.field_101177_n
		// @6D: getstatic game.C_100278_nd game.C_100288_jn.field_106839_f
		// @70: astore_2
		// @71: aload_2
		// @72: iconst_0
		// @73: putfield int game.C_100278_nd.field_101177_n
		// @76: getstatic game.C_100268_mk game.C_100293_kj.field_106891_a
		// @79: putstatic game.C_100268_mk game.C_100066_dl.field_101642_t
		// @7C: iload_0
		// @7D: ifne @85
		// @80: iconst_m1
		// @81: goto @87
		// @84: athrow
		// @85: bipush -2 (0xFE)
		// @87: dup
		// @88: putstatic int game.C_100119_ua.field_104907_k
		// @8B: dup
		// @8C: putstatic int game.C_100061_dh.field_101980_gc
		// @8F: putstatic int game.C_100041_wf.field_104107_c
		// @92: getstatic game.C_100278_nd game.C_100115_ej.field_102043_Yb
		// @95: iconst_1
		// @96: getstatic int game.C_100311_le.field_104721_z
		// @99: getstatic int game.C_100022_hf.field_103899_a
		// @9C: getstatic int game.C_100212_qc.field_105982_h
		// @9F: invokestatic game.C_100244_pe.func_106365_a(game.C_100280_nf, boolean, int, int, int)void
		// @A2: iconst_m1
		// @A3: bipush -77 (0xB3)
		// @A5: invokestatic game.C_100306_kn.func_107128_a(int, byte)void
		// @A8: goto @B2
		// @AB: astore_2
		// @AC: getstatic game.C_100268_mk game.C_100343_jf.field_104828_k
		// @AF: putstatic game.C_100268_mk game.C_100066_dl.field_101642_t
		// @B2: aconst_null
		// @B3: putstatic game.C_100331_ie game.C_100124_tn.field_104937_a
		// @B6: iconst_1
		// @B7: ireturn
		// @B8: astore_2
		// @B9: aload_2
		// @BA: new java.lang.StringBuilder
		// @BD: dup
		// @BE: invokespecial java.lang.StringBuilder.<init>()void
		// @C1: getstatic java.lang.String[] game.C_100051_ea.field_103305_U
		// @C4: bipush 9 (0x09)
		// @C6: aaload
		// @C7: invokevirtual java.lang.StringBuilder.append(java.lang.String)java.lang.StringBuilder
		// @CA: iload_0
		// @CB: invokevirtual java.lang.StringBuilder.append(boolean)java.lang.StringBuilder
		// @CE: bipush 44 (0x2C)
		// @D0: invokevirtual java.lang.StringBuilder.append(char)java.lang.StringBuilder
		// @D3: iload_1
		// @D4: invokevirtual java.lang.StringBuilder.append(int)java.lang.StringBuilder
		// @D7: bipush 41 (0x29)
		// @D9: invokevirtual java.lang.StringBuilder.append(char)java.lang.StringBuilder
		// @DC: invokevirtual java.lang.StringBuilder.toString()java.lang.String
		// @DF: invokestatic game.C_100181_cf.func_105695_a(java.lang.Throwable, java.lang.String)game.C_100170_cm
		// @E2: athrow
	}
	
	static final void func_103297_a(boolean arg0, byte arg1, int arg2, int arg3, int arg4, int arg5, int arg6)
	{
		// @000: getstatic int game.SteelSentinels.field_105275_O
		// @003: istore #14
		// @005: iload_3
		// @006: iconst_m1
		// @007: ixor
		// @008: iload #5
		// @00A: iconst_m1
		// @00B: ixor
		// @00C: if_icmpgt @010
		// @00F: return
		// @010: iload #6
		// @012: iload_3
		// @013: iconst_m1
		// @014: isub
		// @015: if_icmpgt @019
		// @018: return
		// @019: iload #6
		// @01B: iconst_5
		// @01C: iload_3
		// @01D: iadd
		// @01E: if_icmple @02F
		// @021: iload #4
		// @023: iload_2
		// @024: if_icmpeq @02F
		// @027: goto @02B
		// @02A: athrow
		// @02B: goto @095
		// @02E: athrow
		// @02F: iconst_m1
		// @030: iload #6
		// @032: iadd
		// @033: istore #7
		// @035: iload #7
		// @037: iload_3
		// @038: if_icmple @094
		// @03B: iload_3
		// @03C: istore #8
		// @03E: iload #8
		// @040: iconst_m1
		// @041: ixor
		// @042: iload #7
		// @044: iconst_m1
		// @045: ixor
		// @046: if_icmple @08C
		// @049: getstatic int[] game.C_100219_an.field_100876_n
		// @04C: iload #8
		// @04E: iaload
		// @04F: istore #9
		// @051: getstatic int[] game.C_100219_an.field_100876_n
		// @054: iload #8
		// @056: iconst_m1
		// @057: isub
		// @058: iaload
		// @059: istore #10
		// @05B: iload #10
		// @05D: iload_0
		// @05E: iload #9
		// @060: sipush 858 (0x035A)
		// @063: invokestatic game.C_100311_le.func_104711_a(int, boolean, int, int)boolean
		// @066: iload #14
		// @068: ifne @037
		// @06B: ifeq @084
		// @06E: getstatic int[] game.C_100219_an.field_100876_n
		// @071: iload #8
		// @073: iload #10
		// @075: iastore
		// @076: getstatic int[] game.C_100219_an.field_100876_n
		// @079: iload #8
		// @07B: iconst_1
		// @07C: iadd
		// @07D: iload #9
		// @07F: iastore
		// @080: goto @084
		// @083: athrow
		// @084: iinc #8 +1
		// @087: iload #14
		// @089: ifeq @03E
		// @08C: iinc #7 +255
		// @08F: iload #14
		// @091: ifeq @035
		// @094: return
		// @095: iload_2
		// @096: ldc 1253582465 (0x4ab82681)
		// @098: ishr
		// @099: iload #4
		// @09B: ldc 720520161 (0x2af243e1)
		// @09D: ishr
		// @09E: iconst_1
		// @09F: iload_2
		// @0A0: iload #4
		// @0A2: iand
		// @0A3: iand
		// @0A4: ineg
		// @0A5: isub
		// @0A6: iadd
		// @0A7: istore #7
		// @0A9: iload_3
		// @0AA: istore #8
		// @0AC: iload #4
		// @0AE: istore #9
		// @0B0: iload_2
		// @0B1: istore #10
		// @0B3: iload_3
		// @0B4: istore #11
		// @0B6: iload #6
		// @0B8: iconst_m1
		// @0B9: ixor
		// @0BA: iload #11
		// @0BC: iconst_m1
		// @0BD: ixor
		// @0BE: if_icmpge @13D
		// @0C1: getstatic int[] game.C_100219_an.field_100876_n
		// @0C4: iload #11
		// @0C6: iaload
		// @0C7: istore #12
		// @0C9: iload_0
		// @0CA: iload #14
		// @0CC: ifne @14D
		// @0CF: ifne @0E0
		// @0D2: goto @0D6
		// @0D5: athrow
		// @0D6: getstatic int[] game.C_100268_mk.field_106670_c
		// @0D9: iload #12
		// @0DB: iaload
		// @0DC: goto @0E6
		// @0DF: athrow
		// @0E0: getstatic int[] game.C_100222_aa.field_106080_f
		// @0E3: iload #12
		// @0E5: iaload
		// @0E6: istore #13
		// @0E8: iload #13
		// @0EA: iconst_m1
		// @0EB: ixor
		// @0EC: iload #7
		// @0EE: iconst_m1
		// @0EF: ixor
		// @0F0: if_icmplt @10F
		// @0F3: iload #13
		// @0F5: iconst_m1
		// @0F6: ixor
		// @0F7: iload #10
		// @0F9: iconst_m1
		// @0FA: ixor
		// @0FB: if_icmplt @106
		// @0FE: goto @102
		// @101: athrow
		// @102: goto @135
		// @105: athrow
		// @106: iload #13
		// @108: istore #10
		// @10A: iload #14
		// @10C: ifeq @135
		// @10F: getstatic int[] game.C_100219_an.field_100876_n
		// @112: iload #11
		// @114: getstatic int[] game.C_100219_an.field_100876_n
		// @117: iload #8
		// @119: iaload
		// @11A: iastore
		// @11B: iload #13
		// @11D: iload #9
		// @11F: if_icmpge @12A
		// @122: goto @126
		// @125: athrow
		// @126: iload #13
		// @128: istore #9
		// @12A: getstatic int[] game.C_100219_an.field_100876_n
		// @12D: iload #8
		// @12F: iinc #8 +1
		// @132: iload #12
		// @134: iastore
		// @135: iinc #11 +1
		// @138: iload #14
		// @13A: ifeq @0B6
		// @13D: iload_0
		// @13E: bipush 89 (0x59)
		// @140: iload #9
		// @142: iload_3
		// @143: iload #4
		// @145: iload #5
		// @147: iload #8
		// @149: invokestatic game.C_100051_ea.func_103297_a(boolean, byte, int, int, int, int, int)void
		// @14C: iload_0
		// @14D: iload_1
		// @14E: iload_2
		// @14F: iload #8
		// @151: iload #10
		// @153: iload #5
		// @155: iload #6
		// @157: invokestatic game.C_100051_ea.func_103297_a(boolean, byte, int, int, int, int, int)void
		// @15A: goto @1B9
		// @15D: astore #7
		// @15F: aload #7
		// @161: new java.lang.StringBuilder
		// @164: dup
		// @165: invokespecial java.lang.StringBuilder.<init>()void
		// @168: getstatic java.lang.String[] game.C_100051_ea.field_103305_U
		// @16B: iconst_4
		// @16C: aaload
		// @16D: invokevirtual java.lang.StringBuilder.append(java.lang.String)java.lang.StringBuilder
		// @170: iload_0
		// @171: invokevirtual java.lang.StringBuilder.append(boolean)java.lang.StringBuilder
		// @174: bipush 44 (0x2C)
		// @176: invokevirtual java.lang.StringBuilder.append(char)java.lang.StringBuilder
		// @179: iload_1
		// @17A: invokevirtual java.lang.StringBuilder.append(int)java.lang.StringBuilder
		// @17D: bipush 44 (0x2C)
		// @17F: invokevirtual java.lang.StringBuilder.append(char)java.lang.StringBuilder
		// @182: iload_2
		// @183: invokevirtual java.lang.StringBuilder.append(int)java.lang.StringBuilder
		// @186: bipush 44 (0x2C)
		// @188: invokevirtual java.lang.StringBuilder.append(char)java.lang.StringBuilder
		// @18B: iload_3
		// @18C: invokevirtual java.lang.StringBuilder.append(int)java.lang.StringBuilder
		// @18F: bipush 44 (0x2C)
		// @191: invokevirtual java.lang.StringBuilder.append(char)java.lang.StringBuilder
		// @194: iload #4
		// @196: invokevirtual java.lang.StringBuilder.append(int)java.lang.StringBuilder
		// @199: bipush 44 (0x2C)
		// @19B: invokevirtual java.lang.StringBuilder.append(char)java.lang.StringBuilder
		// @19E: iload #5
		// @1A0: invokevirtual java.lang.StringBuilder.append(int)java.lang.StringBuilder
		// @1A3: bipush 44 (0x2C)
		// @1A5: invokevirtual java.lang.StringBuilder.append(char)java.lang.StringBuilder
		// @1A8: iload #6
		// @1AA: invokevirtual java.lang.StringBuilder.append(int)java.lang.StringBuilder
		// @1AD: bipush 41 (0x29)
		// @1AF: invokevirtual java.lang.StringBuilder.append(char)java.lang.StringBuilder
		// @1B2: invokevirtual java.lang.StringBuilder.toString()java.lang.String
		// @1B5: invokestatic game.C_100181_cf.func_105695_a(java.lang.Throwable, java.lang.String)game.C_100170_cm
		// @1B8: athrow
		// @1B9: return
	}
	
	abstract int func_103300_a(byte arg0);
	
	abstract int func_103299_k(int arg0);
	
	static final C_100153_be func_103298_o(int arg0)
	{
		// @00: new game.C_100153_be
		// @03: dup
		// @04: getstatic int game.C_100338_jc.field_105371_m
		// @07: getstatic int game.C_100277_nc.field_106702_C
		// @0A: getstatic int[] game.C_100068_vc.field_104340_f
		// @0D: iconst_0
		// @0E: iaload
		// @0F: getstatic int[] game.C_100012_fh.field_100509_M
		// @12: iconst_0
		// @13: iaload
		// @14: getstatic int[] game.C_100213_ak.field_105994_d
		// @17: iconst_0
		// @18: iaload
		// @19: getstatic int[] game.C_100312_ld.field_107156_c
		// @1C: iconst_0
		// @1D: iaload
		// @1E: getstatic byte[][] game.C_100107_u.field_104774_c
		// @21: iconst_0
		// @22: aaload
		// @23: getstatic int[] game.C_100085_a.field_102573_H
		// @26: invokespecial game.C_100153_be.<init>(int, int, int, int, int, int, byte[], int[])void
		// @29: astore_1
		// @2A: bipush 82 (0x52)
		// @2C: invokestatic game.C_100030_gm.func_103336_a(byte)void
		// @2F: iload_0
		// @30: iconst_1
		// @31: if_icmpeq @44
		// @34: bipush -69 (0xBB)
		// @36: bipush -3 (0xFD)
		// @38: bipush 118 (0x76)
		// @3A: bipush -57 (0xC7)
		// @3C: invokestatic game.C_100051_ea.func_103301_a(int, int, byte, int)boolean
		// @3F: pop
		// @40: goto @44
		// @43: athrow
		// @44: aload_1
		// @45: areturn
		// @46: astore_1
		// @47: aload_1
		// @48: new java.lang.StringBuilder
		// @4B: dup
		// @4C: invokespecial java.lang.StringBuilder.<init>()void
		// @4F: getstatic java.lang.String[] game.C_100051_ea.field_103305_U
		// @52: iconst_0
		// @53: aaload
		// @54: invokevirtual java.lang.StringBuilder.append(java.lang.String)java.lang.StringBuilder
		// @57: iload_0
		// @58: invokevirtual java.lang.StringBuilder.append(int)java.lang.StringBuilder
		// @5B: bipush 41 (0x29)
		// @5D: invokevirtual java.lang.StringBuilder.append(char)java.lang.StringBuilder
		// @60: invokevirtual java.lang.StringBuilder.toString()java.lang.String
		// @63: invokestatic game.C_100181_cf.func_105695_a(java.lang.Throwable, java.lang.String)game.C_100170_cm
		// @66: athrow
	}
	
	static
	{
		// @00: bipush 10 (0x0A)
		// @02: anewarray java.lang.String
		// @05: dup
		// @06: iconst_0
		// @07: ldc "+yT\u0002Xf"
		// @09: invokestatic game.C_100051_ea.func_103294_z(java.lang.String)char[]
		// @0C: invokestatic game.C_100051_ea.func_103292_z(char[])java.lang.String
		// @0F: aastore
		// @10: dup
		// @11: iconst_1
		// @12: ldc " m\u0016="
		// @14: invokestatic game.C_100051_ea.func_103294_z(java.lang.String)char[]
		// @17: invokestatic game.C_100051_ea.func_103292_z(char[])java.lang.String
		// @1A: aastore
		// @1B: dup
		// @1C: iconst_2
		// @1D: ldc "+yT\u0016Xf"
		// @1F: invokestatic game.C_100051_ea.func_103294_z(java.lang.String)char[]
		// @22: invokestatic game.C_100051_ea.func_103292_z(char[])java.lang.String
		// @25: aastore
		// @26: dup
		// @27: iconst_3
		// @28: ldc "56T\u007fd"
		// @2A: invokestatic game.C_100051_ea.func_103294_z(java.lang.String)char[]
		// @2D: invokestatic game.C_100051_ea.func_103292_z(char[])java.lang.String
		// @30: aastore
		// @31: dup
		// @32: iconst_4
		// @33: ldc "+yT\u0007Xf"
		// @35: invokestatic game.C_100051_ea.func_103294_z(java.lang.String)char[]
		// @38: invokestatic game.C_100051_ea.func_103292_z(char[])java.lang.String
		// @3B: aastore
		// @3C: dup
		// @3D: iconst_5
		// @3E: ldc "+yT\u0005Xf"
		// @40: invokestatic game.C_100051_ea.func_103294_z(java.lang.String)char[]
		// @43: invokestatic game.C_100051_ea.func_103292_z(char[])java.lang.String
		// @46: aastore
		// @47: dup
		// @48: bipush 6 (0x06)
		// @4A: ldc "+yT\u0006Xf"
		// @4C: invokestatic game.C_100051_ea.func_103294_z(java.lang.String)char[]
		// @4F: invokestatic game.C_100051_ea.func_103292_z(char[])java.lang.String
		// @52: aastore
		// @53: dup
		// @54: bipush 7 (0x07)
		// @56: ldc "+yT\u0000Xf"
		// @58: invokestatic game.C_100051_ea.func_103294_z(java.lang.String)char[]
		// @5B: invokestatic game.C_100051_ea.func_103292_z(char[])java.lang.String
		// @5E: aastore
		// @5F: dup
		// @60: bipush 8 (0x08)
		// @62: ldc "+yT\u0003Xf"
		// @64: invokestatic game.C_100051_ea.func_103294_z(java.lang.String)char[]
		// @67: invokestatic game.C_100051_ea.func_103292_z(char[])java.lang.String
		// @6A: aastore
		// @6B: dup
		// @6C: bipush 9 (0x09)
		// @6E: ldc "+yT\u0004Xf"
		// @70: invokestatic game.C_100051_ea.func_103294_z(java.lang.String)char[]
		// @73: invokestatic game.C_100051_ea.func_103292_z(char[])java.lang.String
		// @76: aastore
		// @77: putstatic java.lang.String[] game.C_100051_ea.field_103305_U
		// @7A: ldc "r=Jo9&y\tqw!lZ(|:8\u000f?u!{\u00114}nl\u00128jnw\n%p!vZ7v<8\u000f\"|`"
		// @7C: invokestatic game.C_100051_ea.func_103294_z(java.lang.String)char[]
		// @7F: invokestatic game.C_100051_ea.func_103292_z(char[])java.lang.String
		// @82: putstatic java.lang.String game.C_100051_ea.field_103310_R
		// @85: ldc "\u001dw\u000f?}t8"
		// @87: invokestatic game.C_100051_ea.func_103294_z(java.lang.String)char[]
		// @8A: invokestatic game.C_100051_ea.func_103292_z(char[])java.lang.String
		// @8D: putstatic java.lang.String game.C_100051_ea.field_103306_T
		// @90: ldc "r=Jo9#m\t%9>t\u001b(9r=Ko9#w\u000849<y\u000e4}n\u007f\u001b<|=8\u00184\u007f!j\u001fqi\"y\u00038w)8\r8m&8\u000e9|n{\u000f#k+v\u000eqv>l\u0013>w=6"
		// @92: invokestatic game.C_100051_ea.func_103294_z(java.lang.String)char[]
		// @95: invokestatic game.C_100051_ea.func_103292_z(char[])java.lang.String
		// @98: putstatic java.lang.String game.C_100051_ea.field_103308_P
		// @9B: return
	}
	
	private static char[] func_103294_z(String arg0)
	{
		// @00: aload_0
		// @01: invokevirtual java.lang.String.toCharArray()char[]
		// @04: dup
		// @05: arraylength
		// @06: iconst_2
		// @07: if_icmpge @13
		// @0A: dup
		// @0B: iconst_0
		// @0C: dup2
		// @0D: caload
		// @0E: bipush 25 (0x19)
		// @10: ixor
		// @11: i2c
		// @12: castore
		// @13: areturn
	}
	
	private static String func_103292_z(char[] arg0)
	{
		// @00: aload_0
		// @01: dup
		// @02: arraylength
		// @03: swap
		// @04: iconst_0
		// @05: istore_1
		// @06: goto @4C
		// @09: dup
		// @0A: iload_1
		// @0B: dup2
		// @0C: caload
		// @0D: iload_1
		// @0E: iconst_5
		// @0F: irem
		// @10: tableswitch def: @44, for 0: @30, for 1: @35, for 2: @3A, for 3: @3F
		// @30: bipush 78 (0x4E)
		// @32: goto @46
		// @35: bipush 24 (0x18)
		// @37: goto @46
		// @3A: bipush 122 (0x7A)
		// @3C: goto @46
		// @3F: bipush 81 (0x51)
		// @41: goto @46
		// @44: bipush 25 (0x19)
		// @46: ixor
		// @47: i2c
		// @48: castore
		// @49: iinc #1 +1
		// @4C: swap
		// @4D: dup_x1
		// @4E: iload_1
		// @4F: if_icmpgt @09
		// @52: new java.lang.String
		// @55: dup_x1
		// @56: swap
		// @57: invokespecial java.lang.String.<init>(char[])void
		// @5A: invokevirtual java.lang.String.intern()java.lang.String
		// @5D: areturn
	}
}
