package game;

import java.applet.Applet;

final class C_100186_rl
{
	static C_100153_be[] field_105725_c;
	static int field_105724_b;
	static String field_105723_e;
	static String field_105721_g;
	static String field_105727_j;
	static String field_105730_i;
	static boolean field_105720_f;
	static boolean field_105729_h;
	static int field_105726_a;
	static String field_105722_d;
	private static final String[] field_105728_z;
	
	static final void func_105716_b(int arg0, Applet arg1)
	{
		// @00: iload_0
		// @01: ifeq @05
		// @04: return
		// @05: bipush -109 (0x93)
		// @07: aload_1
		// @08: ldc ""
		// @0A: invokestatic game.C_100295_kh.func_105280_a(byte, java.applet.Applet, java.lang.String)void
		// @0D: bipush -128 (0x80)
		// @0F: aload_1
		// @10: invokestatic game.C_100183_cd.func_103408_a(byte, java.applet.Applet)void
		// @13: goto @51
		// @16: astore_2
		// @17: aload_2
		// @18: new java.lang.StringBuilder
		// @1B: dup
		// @1C: invokespecial java.lang.StringBuilder.<init>()void
		// @1F: getstatic java.lang.String[] game.C_100186_rl.field_105728_z
		// @22: iconst_5
		// @23: aaload
		// @24: invokevirtual java.lang.StringBuilder.append(java.lang.String)java.lang.StringBuilder
		// @27: iload_0
		// @28: invokevirtual java.lang.StringBuilder.append(int)java.lang.StringBuilder
		// @2B: bipush 44 (0x2C)
		// @2D: invokevirtual java.lang.StringBuilder.append(char)java.lang.StringBuilder
		// @30: aload_1
		// @31: ifnull @3D
		// @34: getstatic java.lang.String[] game.C_100186_rl.field_105728_z
		// @37: iconst_2
		// @38: aaload
		// @39: goto @42
		// @3C: athrow
		// @3D: getstatic java.lang.String[] game.C_100186_rl.field_105728_z
		// @40: iconst_0
		// @41: aaload
		// @42: invokevirtual java.lang.StringBuilder.append(java.lang.String)java.lang.StringBuilder
		// @45: bipush 41 (0x29)
		// @47: invokevirtual java.lang.StringBuilder.append(char)java.lang.StringBuilder
		// @4A: invokevirtual java.lang.StringBuilder.toString()java.lang.String
		// @4D: invokestatic game.C_100181_cf.func_105695_a(java.lang.Throwable, java.lang.String)game.C_100170_cm
		// @50: athrow
		// @51: return
	}
	
	static final void func_105718_a(int arg0, int arg1, int arg2, int arg3, C_100037_wb arg4, int arg5, int arg6, int arg7, int arg8)
	{
		// @000: iload #5
		// @002: ineg
		// @003: aload #4
		// @005: getfield int game.C_100037_wb.field_102335_w
		// @008: iadd
		// @009: iload_0
		// @00A: ineg
		// @00B: iload_2
		// @00C: ineg
		// @00D: iadd
		// @00E: isub
		// @00F: istore #9
		// @011: iload #7
		// @013: iload_2
		// @014: iadd
		// @015: iload_0
		// @016: aload #4
		// @018: getfield int game.C_100037_wb.field_102335_w
		// @01B: iadd
		// @01C: iadd
		// @01D: istore #10
		// @01F: iload #6
		// @021: aload #4
		// @023: getfield int game.C_100037_wb.field_102332_H
		// @026: aload #4
		// @028: getfield int game.C_100037_wb.field_102337_u
		// @02B: ldc -423771743 (0xe6bdc1a1)
		// @02D: ishr
		// @02E: iadd
		// @02F: iadd
		// @030: istore #11
		// @032: iload #9
		// @034: iconst_0
		// @035: iload #10
		// @037: iload #11
		// @039: iload_3
		// @03A: iadd
		// @03B: invokestatic game.C_100196_rb.func_105779_e(int, int, int, int)void
		// @03E: aload #4
		// @040: iload_0
		// @041: iconst_1
		// @042: isub
		// @043: iconst_m1
		// @044: iload #6
		// @046: iadd
		// @047: iload #8
		// @049: invokevirtual game.C_100037_wb.func_102367_c(int, int, int)void
		// @04C: aload #4
		// @04E: iload_0
		// @04F: iconst_1
		// @050: isub
		// @051: iload #6
		// @053: iconst_m1
		// @054: isub
		// @055: iload #8
		// @057: invokevirtual game.C_100037_wb.func_102367_c(int, int, int)void
		// @05A: getstatic int[] game.C_100032_gk.field_103129_U
		// @05D: invokestatic game.C_100196_rb.func_105777_b(int[])void
		// @060: iconst_1
		// @061: iload #9
		// @063: iadd
		// @064: iconst_0
		// @065: iconst_1
		// @066: iload #10
		// @068: iadd
		// @069: iload #11
		// @06B: iload_3
		// @06C: ineg
		// @06D: isub
		// @06E: invokestatic game.C_100196_rb.func_105779_e(int, int, int, int)void
		// @071: aload #4
		// @073: iconst_1
		// @074: iload_0
		// @075: iadd
		// @076: iload #6
		// @078: iconst_1
		// @079: isub
		// @07A: iload #8
		// @07C: invokevirtual game.C_100037_wb.func_102367_c(int, int, int)void
		// @07F: aload #4
		// @081: iconst_1
		// @082: iload_0
		// @083: iadd
		// @084: iload_1
		// @085: iload #6
		// @087: iadd
		// @088: iload #8
		// @08A: invokevirtual game.C_100037_wb.func_102367_c(int, int, int)void
		// @08D: getstatic int[] game.C_100032_gk.field_103129_U
		// @090: invokestatic game.C_100196_rb.func_105777_b(int[])void
		// @093: iload #7
		// @095: ineg
		// @096: iload_0
		// @097: aload #4
		// @099: getfield int game.C_100037_wb.field_102335_w
		// @09C: iadd
		// @09D: aload #4
		// @09F: getfield int game.C_100037_wb.field_102339_s
		// @0A2: iload_2
		// @0A3: ineg
		// @0A4: iadd
		// @0A5: iadd
		// @0A6: iadd
		// @0A7: istore #9
		// @0A9: iload_2
		// @0AA: ineg
		// @0AB: iload_0
		// @0AC: iadd
		// @0AD: aload #4
		// @0AF: getfield int game.C_100037_wb.field_102339_s
		// @0B2: aload #4
		// @0B4: getfield int game.C_100037_wb.field_102335_w
		// @0B7: iload #5
		// @0B9: ineg
		// @0BA: iadd
		// @0BB: iadd
		// @0BC: iadd
		// @0BD: istore #10
		// @0BF: iload #9
		// @0C1: iload_3
		// @0C2: ineg
		// @0C3: iload #11
		// @0C5: iadd
		// @0C6: iload #10
		// @0C8: sipush 480 (0x01E0)
		// @0CB: invokestatic game.C_100196_rb.func_105779_e(int, int, int, int)void
		// @0CE: aload #4
		// @0D0: iconst_m1
		// @0D1: iload_0
		// @0D2: iadd
		// @0D3: iload #6
		// @0D5: iconst_1
		// @0D6: isub
		// @0D7: iload #8
		// @0D9: invokevirtual game.C_100037_wb.func_102367_c(int, int, int)void
		// @0DC: aload #4
		// @0DE: iconst_m1
		// @0DF: iload_0
		// @0E0: iadd
		// @0E1: iconst_1
		// @0E2: iload #6
		// @0E4: iadd
		// @0E5: iload #8
		// @0E7: invokevirtual game.C_100037_wb.func_102367_c(int, int, int)void
		// @0EA: getstatic int[] game.C_100032_gk.field_103129_U
		// @0ED: invokestatic game.C_100196_rb.func_105777_b(int[])void
		// @0F0: iload #9
		// @0F2: iconst_1
		// @0F3: iadd
		// @0F4: iload #11
		// @0F6: iload_3
		// @0F7: ineg
		// @0F8: iadd
		// @0F9: iload #10
		// @0FB: iconst_1
		// @0FC: iadd
		// @0FD: sipush 480 (0x01E0)
		// @100: invokestatic game.C_100196_rb.func_105779_e(int, int, int, int)void
		// @103: aload #4
		// @105: iload_0
		// @106: iconst_1
		// @107: iadd
		// @108: iconst_m1
		// @109: iload #6
		// @10B: iadd
		// @10C: iload #8
		// @10E: invokevirtual game.C_100037_wb.func_102367_c(int, int, int)void
		// @111: aload #4
		// @113: iload_0
		// @114: iconst_m1
		// @115: isub
		// @116: iconst_1
		// @117: iload #6
		// @119: iadd
		// @11A: iload #8
		// @11C: invokevirtual game.C_100037_wb.func_102367_c(int, int, int)void
		// @11F: getstatic int[] game.C_100032_gk.field_103129_U
		// @122: invokestatic game.C_100196_rb.func_105777_b(int[])void
		// @125: goto @1AA
		// @128: astore #9
		// @12A: aload #9
		// @12C: new java.lang.StringBuilder
		// @12F: dup
		// @130: invokespecial java.lang.StringBuilder.<init>()void
		// @133: getstatic java.lang.String[] game.C_100186_rl.field_105728_z
		// @136: bipush 9 (0x09)
		// @138: aaload
		// @139: invokevirtual java.lang.StringBuilder.append(java.lang.String)java.lang.StringBuilder
		// @13C: iload_0
		// @13D: invokevirtual java.lang.StringBuilder.append(int)java.lang.StringBuilder
		// @140: bipush 44 (0x2C)
		// @142: invokevirtual java.lang.StringBuilder.append(char)java.lang.StringBuilder
		// @145: iload_1
		// @146: invokevirtual java.lang.StringBuilder.append(int)java.lang.StringBuilder
		// @149: bipush 44 (0x2C)
		// @14B: invokevirtual java.lang.StringBuilder.append(char)java.lang.StringBuilder
		// @14E: iload_2
		// @14F: invokevirtual java.lang.StringBuilder.append(int)java.lang.StringBuilder
		// @152: bipush 44 (0x2C)
		// @154: invokevirtual java.lang.StringBuilder.append(char)java.lang.StringBuilder
		// @157: iload_3
		// @158: invokevirtual java.lang.StringBuilder.append(int)java.lang.StringBuilder
		// @15B: bipush 44 (0x2C)
		// @15D: invokevirtual java.lang.StringBuilder.append(char)java.lang.StringBuilder
		// @160: aload #4
		// @162: ifnull @16E
		// @165: getstatic java.lang.String[] game.C_100186_rl.field_105728_z
		// @168: iconst_2
		// @169: aaload
		// @16A: goto @173
		// @16D: athrow
		// @16E: getstatic java.lang.String[] game.C_100186_rl.field_105728_z
		// @171: iconst_0
		// @172: aaload
		// @173: invokevirtual java.lang.StringBuilder.append(java.lang.String)java.lang.StringBuilder
		// @176: bipush 44 (0x2C)
		// @178: invokevirtual java.lang.StringBuilder.append(char)java.lang.StringBuilder
		// @17B: iload #5
		// @17D: invokevirtual java.lang.StringBuilder.append(int)java.lang.StringBuilder
		// @180: bipush 44 (0x2C)
		// @182: invokevirtual java.lang.StringBuilder.append(char)java.lang.StringBuilder
		// @185: iload #6
		// @187: invokevirtual java.lang.StringBuilder.append(int)java.lang.StringBuilder
		// @18A: bipush 44 (0x2C)
		// @18C: invokevirtual java.lang.StringBuilder.append(char)java.lang.StringBuilder
		// @18F: iload #7
		// @191: invokevirtual java.lang.StringBuilder.append(int)java.lang.StringBuilder
		// @194: bipush 44 (0x2C)
		// @196: invokevirtual java.lang.StringBuilder.append(char)java.lang.StringBuilder
		// @199: iload #8
		// @19B: invokevirtual java.lang.StringBuilder.append(int)java.lang.StringBuilder
		// @19E: bipush 41 (0x29)
		// @1A0: invokevirtual java.lang.StringBuilder.append(char)java.lang.StringBuilder
		// @1A3: invokevirtual java.lang.StringBuilder.toString()java.lang.String
		// @1A6: invokestatic game.C_100181_cf.func_105695_a(java.lang.Throwable, java.lang.String)game.C_100170_cm
		// @1A9: athrow
		// @1AA: return
	}
	
	static final C_100113_ek func_105717_a(int arg0, Applet arg1)
	{
		// @00: getstatic int game.SteelSentinels.field_105275_O
		// @03: istore #6
		// @05: getstatic java.lang.String[] game.C_100186_rl.field_105728_z
		// @08: iconst_1
		// @09: aaload
		// @0A: aload_1
		// @0B: iconst_0
		// @0C: invokestatic game.C_100325_id.func_101468_a(java.lang.String, java.applet.Applet, int)java.lang.String
		// @0F: astore_2
		// @10: aconst_null
		// @11: aload_2
		// @12: if_acmpeq @19
		// @15: goto @1D
		// @18: athrow
		// @19: getstatic game.C_100113_ek game.C_100144_bm.field_102096_Xb
		// @1C: areturn
		// @1D: iconst_1
		// @1E: invokestatic game.C_100217_ao.func_106029_a(boolean)game.C_100113_ek[]
		// @21: astore_3
		// @22: iconst_0
		// @23: istore #4
		// @25: iload_0
		// @26: iconst_1
		// @27: if_icmpeq @33
		// @2A: bipush 57 (0x39)
		// @2C: invokestatic game.C_100186_rl.func_105712_b(int)void
		// @2F: goto @33
		// @32: athrow
		// @33: aload_3
		// @34: arraylength
		// @35: iload #4
		// @37: if_icmple @60
		// @3A: aload_3
		// @3B: iload #4
		// @3D: aaload
		// @3E: astore #5
		// @40: aload #5
		// @42: iload #6
		// @44: ifne @63
		// @47: aload_2
		// @48: sipush 26736 (0x6870)
		// @4B: invokevirtual game.C_100113_ek.func_104871_a(java.lang.String, int)boolean
		// @4E: ifeq @58
		// @51: goto @55
		// @54: athrow
		// @55: aload #5
		// @57: areturn
		// @58: iinc #4 +1
		// @5B: iload #6
		// @5D: ifeq @33
		// @60: getstatic game.C_100113_ek game.C_100144_bm.field_102096_Xb
		// @63: areturn
		// @64: astore_2
		// @65: aload_2
		// @66: new java.lang.StringBuilder
		// @69: dup
		// @6A: invokespecial java.lang.StringBuilder.<init>()void
		// @6D: getstatic java.lang.String[] game.C_100186_rl.field_105728_z
		// @70: iconst_3
		// @71: aaload
		// @72: invokevirtual java.lang.StringBuilder.append(java.lang.String)java.lang.StringBuilder
		// @75: iload_0
		// @76: invokevirtual java.lang.StringBuilder.append(int)java.lang.StringBuilder
		// @79: bipush 44 (0x2C)
		// @7B: invokevirtual java.lang.StringBuilder.append(char)java.lang.StringBuilder
		// @7E: aload_1
		// @7F: ifnull @8B
		// @82: getstatic java.lang.String[] game.C_100186_rl.field_105728_z
		// @85: iconst_2
		// @86: aaload
		// @87: goto @90
		// @8A: athrow
		// @8B: getstatic java.lang.String[] game.C_100186_rl.field_105728_z
		// @8E: iconst_0
		// @8F: aaload
		// @90: invokevirtual java.lang.StringBuilder.append(java.lang.String)java.lang.StringBuilder
		// @93: bipush 41 (0x29)
		// @95: invokevirtual java.lang.StringBuilder.append(char)java.lang.StringBuilder
		// @98: invokevirtual java.lang.StringBuilder.toString()java.lang.String
		// @9B: invokestatic game.C_100181_cf.func_105695_a(java.lang.Throwable, java.lang.String)game.C_100170_cm
		// @9E: athrow
	}
	
	static final int func_105719_a(int arg0, int arg1)
	{
		// @00: getstatic int game.SteelSentinels.field_105275_O
		// @03: istore_3
		// @04: iload_1
		// @05: bipush 89 (0x59)
		// @07: if_icmpeq @15
		// @0A: aconst_null
		// @0B: checkcast java.lang.String
		// @0E: putstatic java.lang.String game.C_100186_rl.field_105730_i
		// @11: goto @15
		// @14: athrow
		// @15: iload_0
		// @16: istore_2
		// @17: iload_2
		// @18: iconst_m1
		// @19: ixor
		// @1A: bipush -97 (0x9F)
		// @1C: if_icmpeq @99
		// @1F: bipush 97 (0x61)
		// @21: iload_2
		// @22: if_icmpeq @9B
		// @25: goto @29
		// @28: athrow
		// @29: bipush -99 (0x9D)
		// @2B: iload_2
		// @2C: iconst_m1
		// @2D: ixor
		// @2E: if_icmpne @3D
		// @31: goto @35
		// @34: athrow
		// @35: iload_3
		// @36: ifeq @9E
		// @39: goto @3D
		// @3C: athrow
		// @3D: bipush -100 (0x9C)
		// @3F: iload_2
		// @40: iconst_m1
		// @41: ixor
		// @42: if_icmpeq @A1
		// @45: goto @49
		// @48: athrow
		// @49: iload_2
		// @4A: iconst_m1
		// @4B: ixor
		// @4C: bipush -101 (0x9B)
		// @4E: if_icmpeq @A4
		// @51: goto @55
		// @54: athrow
		// @55: iload_2
		// @56: bipush 102 (0x66)
		// @58: if_icmpne @67
		// @5B: goto @5F
		// @5E: athrow
		// @5F: iload_3
		// @60: ifeq @A7
		// @63: goto @67
		// @66: athrow
		// @67: bipush 103 (0x67)
		// @69: iload_2
		// @6A: if_icmpeq @AA
		// @6D: goto @71
		// @70: athrow
		// @71: iload_2
		// @72: iconst_m1
		// @73: ixor
		// @74: bipush -105 (0x97)
		// @76: if_icmpeq @AD
		// @79: goto @7D
		// @7C: athrow
		// @7D: bipush 105 (0x69)
		// @7F: iload_2
		// @80: if_icmpeq @B0
		// @83: goto @87
		// @86: athrow
		// @87: bipush 106 (0x6A)
		// @89: iload_2
		// @8A: if_icmpne @B6
		// @8D: goto @91
		// @90: athrow
		// @91: iload_3
		// @92: ifeq @B3
		// @95: goto @99
		// @98: athrow
		// @99: iconst_2
		// @9A: ireturn
		// @9B: bipush 56 (0x38)
		// @9D: ireturn
		// @9E: bipush 58 (0x3A)
		// @A0: ireturn
		// @A1: bipush 66 (0x42)
		// @A3: ireturn
		// @A4: bipush 70 (0x46)
		// @A6: ireturn
		// @A7: bipush 76 (0x4C)
		// @A9: ireturn
		// @AA: bipush 80 (0x50)
		// @AC: ireturn
		// @AD: bipush 85 (0x55)
		// @AF: ireturn
		// @B0: bipush 89 (0x59)
		// @B2: ireturn
		// @B3: bipush 93 (0x5D)
		// @B5: ireturn
		// @B6: iconst_m1
		// @B7: ireturn
		// @B8: astore_2
		// @B9: aload_2
		// @BA: new java.lang.StringBuilder
		// @BD: dup
		// @BE: invokespecial java.lang.StringBuilder.<init>()void
		// @C1: getstatic java.lang.String[] game.C_100186_rl.field_105728_z
		// @C4: bipush 7 (0x07)
		// @C6: aaload
		// @C7: invokevirtual java.lang.StringBuilder.append(java.lang.String)java.lang.StringBuilder
		// @CA: iload_0
		// @CB: invokevirtual java.lang.StringBuilder.append(int)java.lang.StringBuilder
		// @CE: bipush 44 (0x2C)
		// @D0: invokevirtual java.lang.StringBuilder.append(char)java.lang.StringBuilder
		// @D3: iload_1
		// @D4: invokevirtual java.lang.StringBuilder.append(int)java.lang.StringBuilder
		// @D7: bipush 41 (0x29)
		// @D9: invokevirtual java.lang.StringBuilder.append(char)java.lang.StringBuilder
		// @DC: invokevirtual java.lang.StringBuilder.toString()java.lang.String
		// @DF: invokestatic game.C_100181_cf.func_105695_a(java.lang.Throwable, java.lang.String)game.C_100170_cm
		// @E2: athrow
	}
	
	public final String toString()
	{
		// @00: new java.lang.IllegalStateException
		// @03: dup
		// @04: invokespecial java.lang.IllegalStateException.<init>()void
		// @07: athrow
		// @08: astore_1
		// @09: aload_1
		// @0A: getstatic java.lang.String[] game.C_100186_rl.field_105728_z
		// @0D: bipush 6 (0x06)
		// @0F: aaload
		// @10: invokestatic game.C_100181_cf.func_105695_a(java.lang.Throwable, java.lang.String)game.C_100170_cm
		// @13: athrow
	}
	
	public static void func_105712_b(int arg0)
	{
		// @00: aconst_null
		// @01: putstatic java.lang.String game.C_100186_rl.field_105730_i
		// @04: aconst_null
		// @05: putstatic java.lang.String game.C_100186_rl.field_105721_g
		// @08: aconst_null
		// @09: putstatic java.lang.String game.C_100186_rl.field_105722_d
		// @0C: iload_0
		// @0D: bipush -105 (0x97)
		// @0F: if_icmpeq @1D
		// @12: aconst_null
		// @13: checkcast java.lang.String
		// @16: putstatic java.lang.String game.C_100186_rl.field_105721_g
		// @19: goto @1D
		// @1C: athrow
		// @1D: aconst_null
		// @1E: putstatic game.C_100153_be[] game.C_100186_rl.field_105725_c
		// @21: aconst_null
		// @22: putstatic java.lang.String game.C_100186_rl.field_105727_j
		// @25: aconst_null
		// @26: putstatic java.lang.String game.C_100186_rl.field_105723_e
		// @29: goto @4E
		// @2C: astore_1
		// @2D: aload_1
		// @2E: new java.lang.StringBuilder
		// @31: dup
		// @32: invokespecial java.lang.StringBuilder.<init>()void
		// @35: getstatic java.lang.String[] game.C_100186_rl.field_105728_z
		// @38: bipush 8 (0x08)
		// @3A: aaload
		// @3B: invokevirtual java.lang.StringBuilder.append(java.lang.String)java.lang.StringBuilder
		// @3E: iload_0
		// @3F: invokevirtual java.lang.StringBuilder.append(int)java.lang.StringBuilder
		// @42: bipush 41 (0x29)
		// @44: invokevirtual java.lang.StringBuilder.append(char)java.lang.StringBuilder
		// @47: invokevirtual java.lang.StringBuilder.toString()java.lang.String
		// @4A: invokestatic game.C_100181_cf.func_105695_a(java.lang.Throwable, java.lang.String)game.C_100170_cm
		// @4D: athrow
		// @4E: return
	}
	
	static final void func_105713_a(int arg0)
	{
		// @00: getstatic boolean game.C_100010_ff.field_103697_l
		// @03: ifeq @0A
		// @06: goto @12
		// @09: athrow
		// @0A: new java.lang.IllegalStateException
		// @0D: dup
		// @0E: invokespecial java.lang.IllegalStateException.<init>()void
		// @11: athrow
		// @12: iconst_1
		// @13: putstatic boolean game.C_100244_pe.field_106377_b
		// @16: iload_0
		// @17: bipush -20 (0xEC)
		// @19: if_icmplt @2A
		// @1C: bipush -25 (0xE7)
		// @1E: aconst_null
		// @1F: checkcast java.applet.Applet
		// @22: invokestatic game.C_100186_rl.func_105717_a(int, java.applet.Applet)game.C_100113_ek
		// @25: pop
		// @26: goto @2A
		// @29: athrow
		// @2A: iconst_1
		// @2B: bipush 17 (0x11)
		// @2D: invokestatic game.C_100143_bl.func_105093_a(boolean, byte)void
		// @30: iconst_0
		// @31: putstatic int game.C_100087_n.field_100697_v
		// @34: goto @58
		// @37: astore_1
		// @38: aload_1
		// @39: new java.lang.StringBuilder
		// @3C: dup
		// @3D: invokespecial java.lang.StringBuilder.<init>()void
		// @40: getstatic java.lang.String[] game.C_100186_rl.field_105728_z
		// @43: iconst_4
		// @44: aaload
		// @45: invokevirtual java.lang.StringBuilder.append(java.lang.String)java.lang.StringBuilder
		// @48: iload_0
		// @49: invokevirtual java.lang.StringBuilder.append(int)java.lang.StringBuilder
		// @4C: bipush 41 (0x29)
		// @4E: invokevirtual java.lang.StringBuilder.append(char)java.lang.StringBuilder
		// @51: invokevirtual java.lang.StringBuilder.toString()java.lang.String
		// @54: invokestatic game.C_100181_cf.func_105695_a(java.lang.Throwable, java.lang.String)game.C_100170_cm
		// @57: athrow
		// @58: return
	}
	
	static
	{
		// @00: bipush 10 (0x0A)
		// @02: anewarray java.lang.String
		// @05: dup
		// @06: iconst_0
		// @07: ldc "\tD\u000e+"
		// @09: invokestatic game.C_100186_rl.func_105715_z(java.lang.String)char[]
		// @0C: invokestatic game.C_100186_rl.func_105714_z(char[])java.lang.String
		// @0F: aastore
		// @10: dup
		// @11: iconst_1
		// @12: ldc "\rP\u0005\"#J]\u00034/J]\r 2\t\u001c\u000f\"/\u000f^\u0006"
		// @14: invokestatic game.C_100186_rl.func_105715_z(java.lang.String)char[]
		// @17: invokestatic game.C_100186_rl.func_105714_z(char[])java.lang.String
		// @1A: aastore
		// @1B: dup
		// @1C: iconst_2
		// @1D: ldc "\u001c\u001fLi&"
		// @1F: invokestatic game.C_100186_rl.func_105715_z(java.lang.String)char[]
		// @22: invokestatic game.C_100186_rl.func_105714_z(char[])java.lang.String
		// @25: aastore
		// @26: dup
		// @27: iconst_3
		// @28: ldc "\u0015]L\u0001s"
		// @2A: invokestatic game.C_100186_rl.func_105715_z(java.lang.String)char[]
		// @2D: invokestatic game.C_100186_rl.func_105714_z(char[])java.lang.String
		// @30: aastore
		// @31: dup
		// @32: iconst_4
		// @33: ldc "\u0015]L\u0004s"
		// @35: invokestatic game.C_100186_rl.func_105715_z(java.lang.String)char[]
		// @38: invokestatic game.C_100186_rl.func_105714_z(char[])java.lang.String
		// @3B: aastore
		// @3C: dup
		// @3D: iconst_5
		// @3E: ldc "\u0015]L\u0005s"
		// @40: invokestatic game.C_100186_rl.func_105715_z(java.lang.String)char[]
		// @43: invokestatic game.C_100186_rl.func_105714_z(char[])java.lang.String
		// @46: aastore
		// @47: dup
		// @48: bipush 6 (0x06)
		// @4A: ldc "\u0015]L344E\u0010.5\u0000\u0019K"
		// @4C: invokestatic game.C_100186_rl.func_105715_z(java.lang.String)char[]
		// @4F: invokestatic game.C_100186_rl.func_105714_z(char[])java.lang.String
		// @52: aastore
		// @53: dup
		// @54: bipush 7 (0x07)
		// @56: ldc "\u0015]L\u0002s"
		// @58: invokestatic game.C_100186_rl.func_105715_z(java.lang.String)char[]
		// @5B: invokestatic game.C_100186_rl.func_105714_z(char[])java.lang.String
		// @5E: aastore
		// @5F: dup
		// @60: bipush 8 (0x08)
		// @62: ldc "\u0015]L\u0003s"
		// @64: invokestatic game.C_100186_rl.func_105715_z(java.lang.String)char[]
		// @67: invokestatic game.C_100186_rl.func_105714_z(char[])java.lang.String
		// @6A: aastore
		// @6B: dup
		// @6C: bipush 9 (0x09)
		// @6E: ldc "\u0015]L\u0006s"
		// @70: invokestatic game.C_100186_rl.func_105715_z(java.lang.String)char[]
		// @73: invokestatic game.C_100186_rl.func_105714_z(char[])java.lang.String
		// @76: aastore
		// @77: putstatic java.lang.String[] game.C_100186_rl.field_105728_z
		// @7A: ldc ">^\u0017g6\u0012B\u0016g+\u000bP\u001bgjG\\\r5>GC\u00033>\u0003\u0011\u0005&6\u0002\u0011\u0000\"=\u0008C\u0007g+\u000bP\u001b.5\u0000\u0011\u0015./\u000f\u0011\u0016/>GR\u00175)\u0002_\u0016g4\u0017E\u000b(5\u0014\u001f"
		// @7C: invokestatic game.C_100186_rl.func_105715_z(java.lang.String)char[]
		// @7F: invokestatic game.C_100186_rl.func_105714_z(char[])java.lang.String
		// @82: putstatic java.lang.String game.C_100186_rl.field_105727_j
		// @85: ldc "+T\u00031>GE\u00074/GW\u000b\"7\u0003"
		// @87: invokestatic game.C_100186_rl.func_105715_z(java.lang.String)char[]
		// @8A: invokestatic game.C_100186_rl.func_105714_z(char[])java.lang.String
		// @8D: putstatic java.lang.String game.C_100186_rl.field_105721_g
		// @90: iconst_0
		// @91: putstatic boolean game.C_100186_rl.field_105729_h
		// @94: iconst_0
		// @95: putstatic int game.C_100186_rl.field_105724_b
		// @98: ldc "(W\u0004\")GU\u0010&,"
		// @9A: invokestatic game.C_100186_rl.func_105715_z(java.lang.String)char[]
		// @9D: invokestatic game.C_100186_rl.func_105714_z(char[])java.lang.String
		// @A0: putstatic java.lang.String game.C_100186_rl.field_105730_i
		// @A3: ldc "&R\u0001\"+\u0013"
		// @A5: invokestatic game.C_100186_rl.func_105715_z(java.lang.String)char[]
		// @A8: invokestatic game.C_100186_rl.func_105714_z(char[])java.lang.String
		// @AB: putstatic java.lang.String game.C_100186_rl.field_105722_d
		// @AE: return
	}
	
	private static char[] func_105715_z(String arg0)
	{
		// @00: aload_0
		// @01: invokevirtual java.lang.String.toCharArray()char[]
		// @04: dup
		// @05: arraylength
		// @06: iconst_2
		// @07: if_icmpge @13
		// @0A: dup
		// @0B: iconst_0
		// @0C: dup2
		// @0D: caload
		// @0E: bipush 91 (0x5B)
		// @10: ixor
		// @11: i2c
		// @12: castore
		// @13: areturn
	}
	
	private static String func_105714_z(char[] arg0)
	{
		// @00: aload_0
		// @01: dup
		// @02: arraylength
		// @03: swap
		// @04: iconst_0
		// @05: istore_1
		// @06: goto @4C
		// @09: dup
		// @0A: iload_1
		// @0B: dup2
		// @0C: caload
		// @0D: iload_1
		// @0E: iconst_5
		// @0F: irem
		// @10: tableswitch def: @44, for 0: @30, for 1: @35, for 2: @3A, for 3: @3F
		// @30: bipush 103 (0x67)
		// @32: goto @46
		// @35: bipush 49 (0x31)
		// @37: goto @46
		// @3A: bipush 98 (0x62)
		// @3C: goto @46
		// @3F: bipush 71 (0x47)
		// @41: goto @46
		// @44: bipush 91 (0x5B)
		// @46: ixor
		// @47: i2c
		// @48: castore
		// @49: iinc #1 +1
		// @4C: swap
		// @4D: dup_x1
		// @4E: iload_1
		// @4F: if_icmpgt @09
		// @52: new java.lang.String
		// @55: dup_x1
		// @56: swap
		// @57: invokespecial java.lang.String.<init>(char[])void
		// @5A: invokevirtual java.lang.String.intern()java.lang.String
		// @5D: areturn
	}
}
