package game;

final class C_100263_mb
{
	static String[] field_106510_c;
	static byte[][] field_106507_d;
	static C_100037_wb[] field_106505_f;
	static String field_106506_g;
	private int[] field_106508_e;
	static String field_106509_b;
	static String field_106511_a;
	private static final String[] field_106512_z;
	
	static final void func_106503_a(String arg0, int arg1, byte arg2, String arg3, int arg4, int arg5)
	{
		// @000: getstatic game.C_100278_nd game.C_100115_ej.field_102043_Yb
		// @003: astore #6
		// @005: aload #6
		// @007: iload #4
		// @009: bipush 114 (0x72)
		// @00B: invokevirtual game.C_100278_nd.func_101189_h(int, int)void
		// @00E: aload #6
		// @010: dup
		// @011: getfield int game.C_100278_nd.field_101177_n
		// @014: iconst_1
		// @015: iadd
		// @016: putfield int game.C_100278_nd.field_101177_n
		// @019: aload #6
		// @01B: getfield int game.C_100278_nd.field_101177_n
		// @01E: istore #7
		// @020: aload #6
		// @022: iload_2
		// @023: sipush 7832 (0x1E98)
		// @026: iadd
		// @027: iload_1
		// @028: invokevirtual game.C_100278_nd.func_101169_f(int, int)void
		// @02B: bipush -3 (0xFD)
		// @02D: iload_1
		// @02E: iconst_m1
		// @02F: ixor
		// @030: if_icmpeq @037
		// @033: goto @040
		// @036: athrow
		// @037: aload #6
		// @039: sipush -28365 (0x9133)
		// @03C: aload_0
		// @03D: invokevirtual game.C_100278_nd.func_101167_a(int, java.lang.String)void
		// @040: aload_3
		// @041: ifnull @058
		// @044: sipush -26944 (0x96C0)
		// @047: aload_3
		// @048: aload #6
		// @04A: invokestatic game.C_100043_vl.func_101931_a(int, java.lang.String, game.C_100280_nf)int
		// @04D: pop
		// @04E: getstatic int game.SteelSentinels.field_105275_O
		// @051: ifeq @065
		// @054: goto @058
		// @057: athrow
		// @058: aload #6
		// @05A: iload #5
		// @05C: bipush -87 (0xA9)
		// @05E: invokevirtual game.C_100278_nd.func_101141_d(int, byte)void
		// @061: goto @065
		// @064: athrow
		// @065: aload #6
		// @067: aload #6
		// @069: getfield int game.C_100278_nd.field_101177_n
		// @06C: iload #7
		// @06E: isub
		// @06F: bipush -96 (0xA0)
		// @071: invokevirtual game.C_100278_nd.func_101139_c(int, byte)void
		// @074: iload_2
		// @075: bipush 6 (0x06)
		// @077: if_icmpeq @090
		// @07A: bipush 20 (0x14)
		// @07C: aconst_null
		// @07D: checkcast java.lang.String
		// @080: aconst_null
		// @081: checkcast java.lang.String
		// @084: aconst_null
		// @085: checkcast java.lang.String
		// @088: invokestatic game.C_100263_mb.func_106497_a(int, java.lang.String, java.lang.String, java.lang.String)java.lang.String
		// @08B: pop
		// @08C: goto @090
		// @08F: athrow
		// @090: goto @107
		// @093: astore #6
		// @095: aload #6
		// @097: new java.lang.StringBuilder
		// @09A: dup
		// @09B: invokespecial java.lang.StringBuilder.<init>()void
		// @09E: getstatic java.lang.String[] game.C_100263_mb.field_106512_z
		// @0A1: iconst_5
		// @0A2: aaload
		// @0A3: invokevirtual java.lang.StringBuilder.append(java.lang.String)java.lang.StringBuilder
		// @0A6: aload_0
		// @0A7: ifnull @0B3
		// @0AA: getstatic java.lang.String[] game.C_100263_mb.field_106512_z
		// @0AD: iconst_0
		// @0AE: aaload
		// @0AF: goto @0B8
		// @0B2: athrow
		// @0B3: getstatic java.lang.String[] game.C_100263_mb.field_106512_z
		// @0B6: iconst_2
		// @0B7: aaload
		// @0B8: invokevirtual java.lang.StringBuilder.append(java.lang.String)java.lang.StringBuilder
		// @0BB: bipush 44 (0x2C)
		// @0BD: invokevirtual java.lang.StringBuilder.append(char)java.lang.StringBuilder
		// @0C0: iload_1
		// @0C1: invokevirtual java.lang.StringBuilder.append(int)java.lang.StringBuilder
		// @0C4: bipush 44 (0x2C)
		// @0C6: invokevirtual java.lang.StringBuilder.append(char)java.lang.StringBuilder
		// @0C9: iload_2
		// @0CA: invokevirtual java.lang.StringBuilder.append(int)java.lang.StringBuilder
		// @0CD: bipush 44 (0x2C)
		// @0CF: invokevirtual java.lang.StringBuilder.append(char)java.lang.StringBuilder
		// @0D2: aload_3
		// @0D3: ifnull @0DF
		// @0D6: getstatic java.lang.String[] game.C_100263_mb.field_106512_z
		// @0D9: iconst_0
		// @0DA: aaload
		// @0DB: goto @0E4
		// @0DE: athrow
		// @0DF: getstatic java.lang.String[] game.C_100263_mb.field_106512_z
		// @0E2: iconst_2
		// @0E3: aaload
		// @0E4: invokevirtual java.lang.StringBuilder.append(java.lang.String)java.lang.StringBuilder
		// @0E7: bipush 44 (0x2C)
		// @0E9: invokevirtual java.lang.StringBuilder.append(char)java.lang.StringBuilder
		// @0EC: iload #4
		// @0EE: invokevirtual java.lang.StringBuilder.append(int)java.lang.StringBuilder
		// @0F1: bipush 44 (0x2C)
		// @0F3: invokevirtual java.lang.StringBuilder.append(char)java.lang.StringBuilder
		// @0F6: iload #5
		// @0F8: invokevirtual java.lang.StringBuilder.append(int)java.lang.StringBuilder
		// @0FB: bipush 41 (0x29)
		// @0FD: invokevirtual java.lang.StringBuilder.append(char)java.lang.StringBuilder
		// @100: invokevirtual java.lang.StringBuilder.toString()java.lang.String
		// @103: invokestatic game.C_100181_cf.func_105695_a(java.lang.Throwable, java.lang.String)game.C_100170_cm
		// @106: athrow
		// @107: return
	}
	
	static final void func_106500_a(byte arg0)
	{
		// @00: new game.C_100302_ka
		// @03: dup
		// @04: lconst_0
		// @05: aconst_null
		// @06: invokespecial game.C_100302_ka.<init>(long, game.C_100302_ka)void
		// @09: putstatic game.C_100302_ka game.C_100033_gj.field_101928_lc
		// @0C: getstatic boolean game.C_100273_mm.field_106682_e
		// @0F: ifne @16
		// @12: goto @21
		// @15: athrow
		// @16: getstatic game.C_100302_ka game.C_100033_gj.field_101928_lc
		// @19: bipush -119 (0x89)
		// @1B: getstatic game.C_100302_ka game.C_100297_kf.field_101240_l
		// @1E: invokevirtual game.C_100302_ka.func_101824_b(int, game.C_100302_ka)void
		// @21: getstatic game.C_100302_ka game.C_100033_gj.field_101928_lc
		// @24: bipush -71 (0xB9)
		// @26: getstatic game.C_100302_ka game.C_100099_fb.field_103050_z
		// @29: invokevirtual game.C_100302_ka.func_101824_b(int, game.C_100302_ka)void
		// @2C: new game.C_100220_ac
		// @2F: dup
		// @30: getstatic java.lang.String game.C_100272_mn.field_102432_H
		// @33: getstatic game.C_100302_ka game.C_100033_gj.field_101928_lc
		// @36: invokespecial game.C_100220_ac.<init>(java.lang.String, game.C_100302_ka)void
		// @39: putstatic game.C_100220_ac game.C_100176_ci.field_105624_b
		// @3C: new game.C_100302_ka
		// @3F: dup
		// @40: lconst_0
		// @41: aconst_null
		// @42: invokespecial game.C_100302_ka.<init>(long, game.C_100302_ka)void
		// @45: putstatic game.C_100302_ka game.C_100231_oc.field_102208_bc
		// @48: bipush -9 (0xF7)
		// @4A: bipush -70 (0xBA)
		// @4C: iload_0
		// @4D: isub
		// @4E: bipush 36 (0x24)
		// @50: idiv
		// @51: idiv
		// @52: istore_1
		// @53: getstatic game.C_100302_ka game.C_100231_oc.field_102208_bc
		// @56: bipush -81 (0xAF)
		// @58: getstatic game.C_100220_ac game.C_100176_ci.field_105624_b
		// @5B: getfield game.C_100172_ck game.C_100220_ac.field_106059_a
		// @5E: invokevirtual game.C_100302_ka.func_101824_b(int, game.C_100302_ka)void
		// @61: getstatic game.C_100302_ka game.C_100231_oc.field_102208_bc
		// @64: bipush -111 (0x91)
		// @66: getstatic game.C_100302_ka game.C_100080_b.field_104431_f
		// @69: invokevirtual game.C_100302_ka.func_101824_b(int, game.C_100302_ka)void
		// @6C: bipush 121 (0x79)
		// @6E: invokestatic game.C_100303_kk.func_104785_b(byte)void
		// @71: goto @96
		// @74: astore_1
		// @75: aload_1
		// @76: new java.lang.StringBuilder
		// @79: dup
		// @7A: invokespecial java.lang.StringBuilder.<init>()void
		// @7D: getstatic java.lang.String[] game.C_100263_mb.field_106512_z
		// @80: bipush 6 (0x06)
		// @82: aaload
		// @83: invokevirtual java.lang.StringBuilder.append(java.lang.String)java.lang.StringBuilder
		// @86: iload_0
		// @87: invokevirtual java.lang.StringBuilder.append(int)java.lang.StringBuilder
		// @8A: bipush 41 (0x29)
		// @8C: invokevirtual java.lang.StringBuilder.append(char)java.lang.StringBuilder
		// @8F: invokevirtual java.lang.StringBuilder.toString()java.lang.String
		// @92: invokestatic game.C_100181_cf.func_105695_a(java.lang.Throwable, java.lang.String)game.C_100170_cm
		// @95: athrow
		// @96: return
	}
	
	static final C_100193_re func_106502_a(C_100098_h arg0, int arg1, int arg2, C_100098_h arg3, int arg4)
	{
		// @00: bipush 95 (0x5F)
		// @02: iload_2
		// @03: bipush 50 (0x32)
		// @05: isub
		// @06: bipush 45 (0x2D)
		// @08: idiv
		// @09: idiv
		// @0A: istore #5
		// @0C: iload_1
		// @0D: iconst_1
		// @0E: aload_0
		// @0F: iload #4
		// @11: invokestatic game.C_100333_ij.func_107341_a(int, boolean, game.C_100098_h, int)boolean
		// @14: ifne @19
		// @17: aconst_null
		// @18: areturn
		// @19: iconst_1
		// @1A: aload_3
		// @1B: iload #4
		// @1D: iconst_0
		// @1E: iload_1
		// @1F: invokevirtual game.C_100098_h.func_104610_b(int, int, int)byte[]
		// @22: invokestatic game.C_100189_ri.func_105744_a(boolean, byte[])game.C_100193_re
		// @25: areturn
		// @26: astore #5
		// @28: aload #5
		// @2A: new java.lang.StringBuilder
		// @2D: dup
		// @2E: invokespecial java.lang.StringBuilder.<init>()void
		// @31: getstatic java.lang.String[] game.C_100263_mb.field_106512_z
		// @34: iconst_1
		// @35: aaload
		// @36: invokevirtual java.lang.StringBuilder.append(java.lang.String)java.lang.StringBuilder
		// @39: aload_0
		// @3A: ifnull @46
		// @3D: getstatic java.lang.String[] game.C_100263_mb.field_106512_z
		// @40: iconst_0
		// @41: aaload
		// @42: goto @4B
		// @45: athrow
		// @46: getstatic java.lang.String[] game.C_100263_mb.field_106512_z
		// @49: iconst_2
		// @4A: aaload
		// @4B: invokevirtual java.lang.StringBuilder.append(java.lang.String)java.lang.StringBuilder
		// @4E: bipush 44 (0x2C)
		// @50: invokevirtual java.lang.StringBuilder.append(char)java.lang.StringBuilder
		// @53: iload_1
		// @54: invokevirtual java.lang.StringBuilder.append(int)java.lang.StringBuilder
		// @57: bipush 44 (0x2C)
		// @59: invokevirtual java.lang.StringBuilder.append(char)java.lang.StringBuilder
		// @5C: iload_2
		// @5D: invokevirtual java.lang.StringBuilder.append(int)java.lang.StringBuilder
		// @60: bipush 44 (0x2C)
		// @62: invokevirtual java.lang.StringBuilder.append(char)java.lang.StringBuilder
		// @65: aload_3
		// @66: ifnull @72
		// @69: getstatic java.lang.String[] game.C_100263_mb.field_106512_z
		// @6C: iconst_0
		// @6D: aaload
		// @6E: goto @77
		// @71: athrow
		// @72: getstatic java.lang.String[] game.C_100263_mb.field_106512_z
		// @75: iconst_2
		// @76: aaload
		// @77: invokevirtual java.lang.StringBuilder.append(java.lang.String)java.lang.StringBuilder
		// @7A: bipush 44 (0x2C)
		// @7C: invokevirtual java.lang.StringBuilder.append(char)java.lang.StringBuilder
		// @7F: iload #4
		// @81: invokevirtual java.lang.StringBuilder.append(int)java.lang.StringBuilder
		// @84: bipush 41 (0x29)
		// @86: invokevirtual java.lang.StringBuilder.append(char)java.lang.StringBuilder
		// @89: invokevirtual java.lang.StringBuilder.toString()java.lang.String
		// @8C: invokestatic game.C_100181_cf.func_105695_a(java.lang.Throwable, java.lang.String)game.C_100170_cm
		// @8F: athrow
	}
	
	static final String func_106497_a(int arg0, String arg1, String arg2, String arg3)
	{
		// @00: getstatic int game.SteelSentinels.field_105275_O
		// @03: istore #5
		// @05: iload_0
		// @06: iconst_1
		// @07: if_icmpeq @21
		// @0A: aconst_null
		// @0B: checkcast java.lang.String
		// @0E: bipush 65 (0x41)
		// @10: bipush -18 (0xEE)
		// @12: aconst_null
		// @13: checkcast java.lang.String
		// @16: bipush 93 (0x5D)
		// @18: bipush -96 (0xA0)
		// @1A: invokestatic game.C_100263_mb.func_106503_a(java.lang.String, int, byte, java.lang.String, int, int)void
		// @1D: goto @21
		// @20: athrow
		// @21: aload_1
		// @22: aload_3
		// @23: invokevirtual java.lang.String.indexOf(java.lang.String)int
		// @26: istore #4
		// @28: iload #4
		// @2A: iconst_m1
		// @2B: if_icmpeq @6E
		// @2E: new java.lang.StringBuilder
		// @31: dup
		// @32: invokespecial java.lang.StringBuilder.<init>()void
		// @35: aload_1
		// @36: iconst_0
		// @37: iload #4
		// @39: invokevirtual java.lang.String.substring(int, int)java.lang.String
		// @3C: invokevirtual java.lang.StringBuilder.append(java.lang.String)java.lang.StringBuilder
		// @3F: aload_2
		// @40: invokevirtual java.lang.StringBuilder.append(java.lang.String)java.lang.StringBuilder
		// @43: aload_1
		// @44: iload #4
		// @46: aload_3
		// @47: invokevirtual java.lang.String.length()int
		// @4A: ineg
		// @4B: isub
		// @4C: invokevirtual java.lang.String.substring(int)java.lang.String
		// @4F: invokevirtual java.lang.StringBuilder.append(java.lang.String)java.lang.StringBuilder
		// @52: invokevirtual java.lang.StringBuilder.toString()java.lang.String
		// @55: astore_1
		// @56: aload_1
		// @57: iload #5
		// @59: ifne @6F
		// @5C: aload_3
		// @5D: iload #4
		// @5F: aload_2
		// @60: invokevirtual java.lang.String.length()int
		// @63: iadd
		// @64: invokevirtual java.lang.String.indexOf(java.lang.String, int)int
		// @67: istore #4
		// @69: iload #5
		// @6B: ifeq @28
		// @6E: aload_1
		// @6F: areturn
		// @70: astore #4
		// @72: aload #4
		// @74: athrow
	}
	
	public static void func_106498_a(int arg0)
	{
		// @00: aconst_null
		// @01: putstatic java.lang.String[] game.C_100263_mb.field_106510_c
		// @04: aconst_null
		// @05: putstatic java.lang.String game.C_100263_mb.field_106509_b
		// @08: aconst_null
		// @09: putstatic java.lang.String game.C_100263_mb.field_106511_a
		// @0C: aconst_null
		// @0D: checkcast byte[][]
		// @10: putstatic byte[][] game.C_100263_mb.field_106507_d
		// @13: aconst_null
		// @14: putstatic game.C_100037_wb[] game.C_100263_mb.field_106505_f
		// @17: aconst_null
		// @18: putstatic java.lang.String game.C_100263_mb.field_106506_g
		// @1B: iload_0
		// @1C: ifeq @31
		// @1F: aconst_null
		// @20: checkcast game.C_100098_h
		// @23: bipush 28 (0x1C)
		// @25: bipush 35 (0x23)
		// @27: aconst_null
		// @28: checkcast game.C_100098_h
		// @2B: bipush -120 (0x88)
		// @2D: invokestatic game.C_100263_mb.func_106502_a(game.C_100098_h, int, int, game.C_100098_h, int)game.C_100193_re
		// @30: pop
		// @31: goto @55
		// @34: astore_1
		// @35: aload_1
		// @36: new java.lang.StringBuilder
		// @39: dup
		// @3A: invokespecial java.lang.StringBuilder.<init>()void
		// @3D: getstatic java.lang.String[] game.C_100263_mb.field_106512_z
		// @40: iconst_4
		// @41: aaload
		// @42: invokevirtual java.lang.StringBuilder.append(java.lang.String)java.lang.StringBuilder
		// @45: iload_0
		// @46: invokevirtual java.lang.StringBuilder.append(int)java.lang.StringBuilder
		// @49: bipush 41 (0x29)
		// @4B: invokevirtual java.lang.StringBuilder.append(char)java.lang.StringBuilder
		// @4E: invokevirtual java.lang.StringBuilder.toString()java.lang.String
		// @51: invokestatic game.C_100181_cf.func_105695_a(java.lang.Throwable, java.lang.String)game.C_100170_cm
		// @54: athrow
		// @55: return
	}
	
	C_100263_mb(int[] arg0)
	{
		// @00: getstatic int game.SteelSentinels.field_105275_O
		// @03: istore #5
		// @05: aload_0
		// @06: invokespecial java.lang.Object.<init>()void
		// @09: iconst_1
		// @0A: istore_2
		// @0B: iload_2
		// @0C: iconst_m1
		// @0D: ixor
		// @0E: aload_1
		// @0F: arraylength
		// @10: aload_1
		// @11: arraylength
		// @12: ldc -1839029631 (0x9262a281)
		// @14: ishr
		// @15: iadd
		// @16: iconst_m1
		// @17: ixor
		// @18: if_icmplt @2D
		// @1B: iload_2
		// @1C: iconst_1
		// @1D: ishl
		// @1E: istore_2
		// @1F: iload #5
		// @21: ifne @37
		// @24: iload #5
		// @26: ifeq @0B
		// @29: goto @2D
		// @2C: athrow
		// @2D: aload_0
		// @2E: iload_2
		// @2F: iload_2
		// @30: ineg
		// @31: isub
		// @32: newarray int[]
		// @34: putfield int[] game.C_100263_mb.field_106508_e
		// @37: iconst_0
		// @38: istore_3
		// @39: iload_3
		// @3A: iconst_m1
		// @3B: ixor
		// @3C: iload_2
		// @3D: iload_2
		// @3E: ineg
		// @3F: isub
		// @40: iconst_m1
		// @41: ixor
		// @42: if_icmple @5D
		// @45: aload_0
		// @46: getfield int[] game.C_100263_mb.field_106508_e
		// @49: iload_3
		// @4A: iconst_m1
		// @4B: iastore
		// @4C: iinc #3 +1
		// @4F: iload #5
		// @51: ifne @5F
		// @54: iload #5
		// @56: ifeq @39
		// @59: goto @5D
		// @5C: athrow
		// @5D: iconst_0
		// @5E: istore_3
		// @5F: iload_3
		// @60: iconst_m1
		// @61: ixor
		// @62: aload_1
		// @63: arraylength
		// @64: iconst_m1
		// @65: ixor
		// @66: if_icmple @C6
		// @69: iload #5
		// @6B: ifne @FB
		// @6E: goto @72
		// @71: athrow
		// @72: iconst_m1
		// @73: iload_2
		// @74: iadd
		// @75: aload_1
		// @76: iload_3
		// @77: iaload
		// @78: iand
		// @79: istore #4
		// @7B: aload_0
		// @7C: getfield int[] game.C_100263_mb.field_106508_e
		// @7F: iload #4
		// @81: iload #4
		// @83: iadd
		// @84: iconst_1
		// @85: iadd
		// @86: iaload
		// @87: iconst_m1
		// @88: ixor
		// @89: ifeq @A4
		// @8C: iconst_1
		// @8D: iload #4
		// @8F: iadd
		// @90: iconst_m1
		// @91: iload_2
		// @92: iadd
		// @93: iand
		// @94: istore #4
		// @96: iload #5
		// @98: ifne @C1
		// @9B: iload #5
		// @9D: ifeq @7B
		// @A0: goto @A4
		// @A3: athrow
		// @A4: aload_0
		// @A5: getfield int[] game.C_100263_mb.field_106508_e
		// @A8: iload #4
		// @AA: iload #4
		// @AC: iadd
		// @AD: aload_1
		// @AE: iload_3
		// @AF: iaload
		// @B0: iastore
		// @B1: aload_0
		// @B2: getfield int[] game.C_100263_mb.field_106508_e
		// @B5: iconst_1
		// @B6: iload #4
		// @B8: iload #4
		// @BA: iadd
		// @BB: iadd
		// @BC: iload_3
		// @BD: iastore
		// @BE: iinc #3 +1
		// @C1: iload #5
		// @C3: ifeq @5F
		// @C6: goto @FB
		// @C9: astore_2
		// @CA: aload_2
		// @CB: new java.lang.StringBuilder
		// @CE: dup
		// @CF: invokespecial java.lang.StringBuilder.<init>()void
		// @D2: getstatic java.lang.String[] game.C_100263_mb.field_106512_z
		// @D5: iconst_3
		// @D6: aaload
		// @D7: invokevirtual java.lang.StringBuilder.append(java.lang.String)java.lang.StringBuilder
		// @DA: aload_1
		// @DB: ifnull @E7
		// @DE: getstatic java.lang.String[] game.C_100263_mb.field_106512_z
		// @E1: iconst_0
		// @E2: aaload
		// @E3: goto @EC
		// @E6: athrow
		// @E7: getstatic java.lang.String[] game.C_100263_mb.field_106512_z
		// @EA: iconst_2
		// @EB: aaload
		// @EC: invokevirtual java.lang.StringBuilder.append(java.lang.String)java.lang.StringBuilder
		// @EF: bipush 41 (0x29)
		// @F1: invokevirtual java.lang.StringBuilder.append(char)java.lang.StringBuilder
		// @F4: invokevirtual java.lang.StringBuilder.toString()java.lang.String
		// @F7: invokestatic game.C_100181_cf.func_105695_a(java.lang.Throwable, java.lang.String)game.C_100170_cm
		// @FA: athrow
		// @FB: return
	}
	
	final int func_106504_a(int arg0, int arg1)
	{
		// @00: getstatic int game.SteelSentinels.field_105275_O
		// @03: istore #6
		// @05: iconst_m1
		// @06: aload_0
		// @07: getfield int[] game.C_100263_mb.field_106508_e
		// @0A: arraylength
		// @0B: ldc 537407905 (0x200831a1)
		// @0D: ishr
		// @0E: iadd
		// @0F: istore_3
		// @10: iload_3
		// @11: iload_2
		// @12: iand
		// @13: istore #4
		// @15: iload_1
		// @16: bipush 68 (0x44)
		// @18: if_icmpge @24
		// @1B: bipush -94 (0xA2)
		// @1D: invokestatic game.C_100263_mb.func_106500_a(byte)void
		// @20: goto @24
		// @23: athrow
		// @24: aload_0
		// @25: getfield int[] game.C_100263_mb.field_106508_e
		// @28: iload #4
		// @2A: iload #4
		// @2C: iadd
		// @2D: iconst_1
		// @2E: iadd
		// @2F: iaload
		// @30: istore #5
		// @32: iload #5
		// @34: iconst_m1
		// @35: ixor
		// @36: ifne @40
		// @39: iconst_m1
		// @3A: iload #6
		// @3C: ifne @4A
		// @3F: ireturn
		// @40: aload_0
		// @41: getfield int[] game.C_100263_mb.field_106508_e
		// @44: iload #4
		// @46: iload #4
		// @48: iadd
		// @49: iaload
		// @4A: iload_2
		// @4B: if_icmpeq @52
		// @4E: goto @55
		// @51: athrow
		// @52: iload #5
		// @54: ireturn
		// @55: iload #4
		// @57: iconst_m1
		// @58: isub
		// @59: iload_3
		// @5A: iand
		// @5B: istore #4
		// @5D: goto @24
		// @60: astore_3
		// @61: aload_3
		// @62: new java.lang.StringBuilder
		// @65: dup
		// @66: invokespecial java.lang.StringBuilder.<init>()void
		// @69: getstatic java.lang.String[] game.C_100263_mb.field_106512_z
		// @6C: bipush 7 (0x07)
		// @6E: aaload
		// @6F: invokevirtual java.lang.StringBuilder.append(java.lang.String)java.lang.StringBuilder
		// @72: iload_1
		// @73: invokevirtual java.lang.StringBuilder.append(int)java.lang.StringBuilder
		// @76: bipush 44 (0x2C)
		// @78: invokevirtual java.lang.StringBuilder.append(char)java.lang.StringBuilder
		// @7B: iload_2
		// @7C: invokevirtual java.lang.StringBuilder.append(int)java.lang.StringBuilder
		// @7F: bipush 41 (0x29)
		// @81: invokevirtual java.lang.StringBuilder.append(char)java.lang.StringBuilder
		// @84: invokevirtual java.lang.StringBuilder.toString()java.lang.String
		// @87: invokestatic game.C_100181_cf.func_105695_a(java.lang.Throwable, java.lang.String)game.C_100170_cm
		// @8A: athrow
	}
	
	static
	{
		// @00: bipush 8 (0x08)
		// @02: anewarray java.lang.String
		// @05: dup
		// @06: iconst_0
		// @07: ldc "\u0004v=9e"
		// @09: invokestatic game.C_100263_mb.func_106501_z(java.lang.String)char[]
		// @0C: invokestatic game.C_100263_mb.func_106499_z(char[])java.lang.String
		// @0F: aastore
		// @10: dup
		// @11: iconst_1
		// @12: ldc "\u0012:=Q0"
		// @14: invokestatic game.C_100263_mb.func_106501_z(java.lang.String)char[]
		// @17: invokestatic game.C_100263_mb.func_106499_z(char[])java.lang.String
		// @1A: aastore
		// @1B: dup
		// @1C: iconst_2
		// @1D: ldc "\u0011-\u007f{"
		// @1F: invokestatic game.C_100263_mb.func_106501_z(java.lang.String)char[]
		// @22: invokestatic game.C_100263_mb.func_106499_z(char[])java.lang.String
		// @25: aastore
		// @26: dup
		// @27: iconst_3
		// @28: ldc "\u0012:=+q\u00111g)0"
		// @2A: invokestatic game.C_100263_mb.func_106501_z(java.lang.String)char[]
		// @2D: invokestatic game.C_100263_mb.func_106499_z(char[])java.lang.String
		// @30: aastore
		// @31: dup
		// @32: iconst_4
		// @33: ldc "\u0012:=S0"
		// @35: invokestatic game.C_100263_mb.func_106501_z(java.lang.String)char[]
		// @38: invokestatic game.C_100263_mb.func_106499_z(char[])java.lang.String
		// @3B: aastore
		// @3C: dup
		// @3D: iconst_5
		// @3E: ldc "\u0012:=U0"
		// @40: invokestatic game.C_100263_mb.func_106501_z(java.lang.String)char[]
		// @43: invokestatic game.C_100263_mb.func_106499_z(char[])java.lang.String
		// @46: aastore
		// @47: dup
		// @48: bipush 6 (0x06)
		// @4A: ldc "\u0012:=R0"
		// @4C: invokestatic game.C_100263_mb.func_106501_z(java.lang.String)char[]
		// @4F: invokestatic game.C_100263_mb.func_106499_z(char[])java.lang.String
		// @52: aastore
		// @53: dup
		// @54: bipush 7 (0x07)
		// @56: ldc "\u0012:=T0"
		// @58: invokestatic game.C_100263_mb.func_106501_z(java.lang.String)char[]
		// @5B: invokestatic game.C_100263_mb.func_106499_z(char[])java.lang.String
		// @5E: aastore
		// @5F: putstatic java.lang.String[] game.C_100263_mb.field_106512_z
		// @62: bipush 6 (0x06)
		// @64: anewarray java.lang.String
		// @67: dup
		// @68: iconst_0
		// @69: ldc "<7}y}\u001c,zy\u007f_,|7m\u000f<rc}_+ven\u001a*"
		// @6B: invokestatic game.C_100263_mb.func_106501_z(java.lang.String)char[]
		// @6E: invokestatic game.C_100263_mb.func_106499_z(char[])java.lang.String
		// @71: aastore
		// @72: dup
		// @73: iconst_1
		// @74: ldc ")=auq\u0011<v7u\u0016,3Vs\u000b-r{q\u000c1vem\u0011?`d}\r.ve"
		// @76: invokestatic game.C_100263_mb.func_106501_z(java.lang.String)char[]
		// @79: invokestatic game.C_100263_mb.func_106499_z(char[])java.lang.String
		// @7C: aastore
		// @7D: dup
		// @7E: iconst_2
		// @7F: ldc "<7}y}\u00071|y8\u001e-3d}\r.vbj_<v7u\u0016+v7\u00f8_2|bj"
		// @81: invokestatic game.C_100263_mb.func_106501_z(java.lang.String)char[]
		// @84: invokestatic game.C_100263_mb.func_106499_z(char[])java.lang.String
		// @87: aastore
		// @88: dup
		// @89: iconst_3
		// @8A: ldc "<7}r{\u000b9}sw_9|7k\u001a*e~|\u0010*3s}_9gby\u00131iv\u00ff\u009c7"
		// @8C: invokestatic game.C_100263_mb.func_106501_z(java.lang.String)char[]
		// @8F: invokestatic game.C_100263_mb.func_106499_z(char[])java.lang.String
		// @92: aastore
		// @93: dup
		// @94: iconst_4
		// @95: ldc "2=g7m\u000f<rc}\u000c=aa}\rxerj\u001d1}s}\u0011"
		// @97: invokestatic game.C_100263_mb.func_106501_z(java.lang.String)char[]
		// @9A: invokestatic game.C_100263_mb.func_106499_z(char[])java.lang.String
		// @9D: aastore
		// @9E: dup
		// @9F: iconst_5
		// @A0: ldc "<7}y}\u001c,zy\u007f_,|7m\u000f<rc}_+ven\u001a*3?m\u0011,avv\u000c4rc}\u001bq"
		// @A2: invokestatic game.C_100263_mb.func_106501_z(java.lang.String)char[]
		// @A5: invokestatic game.C_100263_mb.func_106499_z(char[])java.lang.String
		// @A8: aastore
		// @A9: putstatic java.lang.String[] game.C_100263_mb.field_106510_c
		// @AC: ldc "/4vvk\u001axp\u007f}\u001c33~~_9wsj\u001a+`7q\u000cxpxj\r=pc"
		// @AE: invokestatic game.C_100263_mb.func_106501_z(java.lang.String)char[]
		// @B1: invokestatic game.C_100263_mb.func_106499_z(char[])java.lang.String
		// @B4: putstatic java.lang.String game.C_100263_mb.field_106506_g
		// @B7: sipush 250 (0x00FA)
		// @BA: anewarray byte[]
		// @BD: putstatic byte[][] game.C_100263_mb.field_106507_d
		// @C0: ldc "+0v7q\u0011.zcy\u000b1|y8\u00179`7z\u001a=}7o\u0016,{sj\u001e/}9"
		// @C2: invokestatic game.C_100263_mb.func_106501_z(java.lang.String)char[]
		// @C5: invokestatic game.C_100263_mb.func_106499_z(char[])java.lang.String
		// @C8: putstatic java.lang.String game.C_100263_mb.field_106509_b
		// @CB: ldc ",\u0017_VJ6\u000cV7]>\n]R\\Ex/~u\u0018e!#&C;|{%C}\")&C}#)$P;|{&"
		// @CD: invokestatic game.C_100263_mb.func_106501_z(java.lang.String)char[]
		// @D0: invokestatic game.C_100263_mb.func_106499_z(char[])java.lang.String
		// @D3: putstatic java.lang.String game.C_100263_mb.field_106511_a
		// @D6: return
	}
	
	private static char[] func_106501_z(String arg0)
	{
		// @00: aload_0
		// @01: invokevirtual java.lang.String.toCharArray()char[]
		// @04: dup
		// @05: arraylength
		// @06: iconst_2
		// @07: if_icmpge @13
		// @0A: dup
		// @0B: iconst_0
		// @0C: dup2
		// @0D: caload
		// @0E: bipush 24 (0x18)
		// @10: ixor
		// @11: i2c
		// @12: castore
		// @13: areturn
	}
	
	private static String func_106499_z(char[] arg0)
	{
		// @00: aload_0
		// @01: dup
		// @02: arraylength
		// @03: swap
		// @04: iconst_0
		// @05: istore_1
		// @06: goto @4C
		// @09: dup
		// @0A: iload_1
		// @0B: dup2
		// @0C: caload
		// @0D: iload_1
		// @0E: iconst_5
		// @0F: irem
		// @10: tableswitch def: @44, for 0: @30, for 1: @35, for 2: @3A, for 3: @3F
		// @30: bipush 127 (0x7F)
		// @32: goto @46
		// @35: bipush 88 (0x58)
		// @37: goto @46
		// @3A: bipush 19 (0x13)
		// @3C: goto @46
		// @3F: bipush 23 (0x17)
		// @41: goto @46
		// @44: bipush 24 (0x18)
		// @46: ixor
		// @47: i2c
		// @48: castore
		// @49: iinc #1 +1
		// @4C: swap
		// @4D: dup_x1
		// @4E: iload_1
		// @4F: if_icmpgt @09
		// @52: new java.lang.String
		// @55: dup_x1
		// @56: swap
		// @57: invokespecial java.lang.String.<init>(char[])void
		// @5A: invokevirtual java.lang.String.intern()java.lang.String
		// @5D: areturn
	}
}
