package game;

final class C_100159_sn
{
	static C_100302_ka field_105402_b;
	static C_100033_gj field_105401_e;
	static String field_105400_d;
	static int[] field_105404_a;
	static int[] field_105403_c;
	private static final String[] field_105405_z;
	
	public static void func_105396_a(byte arg0)
	{
		// @00: aconst_null
		// @01: putstatic game.C_100033_gj game.C_100159_sn.field_105401_e
		// @04: aconst_null
		// @05: putstatic java.lang.String game.C_100159_sn.field_105400_d
		// @08: iload_0
		// @09: bipush -97 (0x9F)
		// @0B: if_icmple @0F
		// @0E: return
		// @0F: aconst_null
		// @10: putstatic game.C_100302_ka game.C_100159_sn.field_105402_b
		// @13: aconst_null
		// @14: putstatic int[] game.C_100159_sn.field_105404_a
		// @17: aconst_null
		// @18: putstatic int[] game.C_100159_sn.field_105403_c
		// @1B: goto @3F
		// @1E: astore_1
		// @1F: aload_1
		// @20: new java.lang.StringBuilder
		// @23: dup
		// @24: invokespecial java.lang.StringBuilder.<init>()void
		// @27: getstatic java.lang.String[] game.C_100159_sn.field_105405_z
		// @2A: iconst_1
		// @2B: aaload
		// @2C: invokevirtual java.lang.StringBuilder.append(java.lang.String)java.lang.StringBuilder
		// @2F: iload_0
		// @30: invokevirtual java.lang.StringBuilder.append(int)java.lang.StringBuilder
		// @33: bipush 41 (0x29)
		// @35: invokevirtual java.lang.StringBuilder.append(char)java.lang.StringBuilder
		// @38: invokevirtual java.lang.StringBuilder.toString()java.lang.String
		// @3B: invokestatic game.C_100181_cf.func_105695_a(java.lang.Throwable, java.lang.String)game.C_100170_cm
		// @3E: athrow
		// @3F: return
	}
	
	static final boolean func_105398_a(int arg0, int arg1, byte arg2, int arg3)
	{
		// @000: iload_2
		// @001: bipush -13 (0xF3)
		// @003: if_icmple @008
		// @006: iconst_1
		// @007: ireturn
		// @008: getstatic game.C_100043_vl game.C_100343_jf.field_104825_l
		// @00B: ifnull @020
		// @00E: getstatic int game.C_100293_kj.field_106890_c
		// @011: bipush 13 (0x0D)
		// @013: if_icmpne @020
		// @016: goto @01A
		// @019: athrow
		// @01A: aconst_null
		// @01B: putstatic game.C_100043_vl game.C_100343_jf.field_104825_l
		// @01E: iconst_1
		// @01F: ireturn
		// @020: getstatic boolean game.C_100230_of.field_106216_k
		// @023: ifne @07E
		// @026: getstatic boolean game.C_100021_wn.field_103871_b
		// @029: ifne @058
		// @02C: goto @030
		// @02F: athrow
		// @030: bipush -10 (0xF6)
		// @032: getstatic int game.C_100293_kj.field_106890_c
		// @035: iconst_m1
		// @036: ixor
		// @037: if_icmpeq @058
		// @03A: goto @03E
		// @03D: athrow
		// @03E: getstatic int game.C_100293_kj.field_106890_c
		// @041: bipush 10 (0x0A)
		// @043: if_icmpeq @058
		// @046: goto @04A
		// @049: athrow
		// @04A: getstatic int game.C_100293_kj.field_106890_c
		// @04D: iconst_m1
		// @04E: ixor
		// @04F: bipush -12 (0xF4)
		// @051: if_icmpne @05F
		// @054: goto @058
		// @057: athrow
		// @058: iload_0
		// @059: iconst_1
		// @05A: iload_1
		// @05B: invokestatic game.C_100164_se.func_105447_a(int, boolean, int)boolean
		// @05E: ireturn
		// @05F: bipush -81 (0xAF)
		// @061: getstatic int game.C_100293_kj.field_106890_c
		// @064: iconst_m1
		// @065: ixor
		// @066: if_icmpne @07C
		// @069: sipush -10684 (0xD644)
		// @06C: invokestatic game.C_100256_pk.func_100451_a(int)boolean
		// @06F: ifeq @07C
		// @072: goto @076
		// @075: athrow
		// @076: iconst_1
		// @077: putstatic boolean game.C_100230_of.field_106216_k
		// @07A: iconst_1
		// @07B: ireturn
		// @07C: iconst_0
		// @07D: ireturn
		// @07E: sipush -10684 (0xD644)
		// @081: invokestatic game.C_100256_pk.func_100451_a(int)boolean
		// @084: ifne @089
		// @087: iconst_0
		// @088: ireturn
		// @089: iload_3
		// @08A: sipush -32533 (0x80EB)
		// @08D: iload_0
		// @08E: invokestatic game.C_100010_ff.func_103693_b(int, int, int)boolean
		// @091: istore #4
		// @093: getstatic int game.C_100293_kj.field_106890_c
		// @096: iconst_m1
		// @097: ixor
		// @098: bipush -81 (0xAF)
		// @09A: if_icmpeq @0AF
		// @09D: getstatic int game.C_100293_kj.field_106890_c
		// @0A0: iconst_m1
		// @0A1: ixor
		// @0A2: bipush -85 (0xAB)
		// @0A4: if_icmpeq @0AF
		// @0A7: goto @0AB
		// @0AA: athrow
		// @0AB: goto @0B6
		// @0AE: athrow
		// @0AF: iconst_1
		// @0B0: istore #4
		// @0B2: iconst_0
		// @0B3: putstatic boolean game.C_100230_of.field_106216_k
		// @0B6: getstatic int game.C_100293_kj.field_106890_c
		// @0B9: bipush 13 (0x0D)
		// @0BB: if_icmpne @0CA
		// @0BE: bipush 62 (0x3E)
		// @0C0: invokestatic game.C_100233_oa.func_106223_b(int)void
		// @0C3: iconst_1
		// @0C4: istore #4
		// @0C6: iconst_0
		// @0C7: putstatic boolean game.C_100230_of.field_106216_k
		// @0CA: iload #4
		// @0CC: ireturn
		// @0CD: astore #4
		// @0CF: aload #4
		// @0D1: new java.lang.StringBuilder
		// @0D4: dup
		// @0D5: invokespecial java.lang.StringBuilder.<init>()void
		// @0D8: getstatic java.lang.String[] game.C_100159_sn.field_105405_z
		// @0DB: iconst_0
		// @0DC: aaload
		// @0DD: invokevirtual java.lang.StringBuilder.append(java.lang.String)java.lang.StringBuilder
		// @0E0: iload_0
		// @0E1: invokevirtual java.lang.StringBuilder.append(int)java.lang.StringBuilder
		// @0E4: bipush 44 (0x2C)
		// @0E6: invokevirtual java.lang.StringBuilder.append(char)java.lang.StringBuilder
		// @0E9: iload_1
		// @0EA: invokevirtual java.lang.StringBuilder.append(int)java.lang.StringBuilder
		// @0ED: bipush 44 (0x2C)
		// @0EF: invokevirtual java.lang.StringBuilder.append(char)java.lang.StringBuilder
		// @0F2: iload_2
		// @0F3: invokevirtual java.lang.StringBuilder.append(int)java.lang.StringBuilder
		// @0F6: bipush 44 (0x2C)
		// @0F8: invokevirtual java.lang.StringBuilder.append(char)java.lang.StringBuilder
		// @0FB: iload_3
		// @0FC: invokevirtual java.lang.StringBuilder.append(int)java.lang.StringBuilder
		// @0FF: bipush 41 (0x29)
		// @101: invokevirtual java.lang.StringBuilder.append(char)java.lang.StringBuilder
		// @104: invokevirtual java.lang.StringBuilder.toString()java.lang.String
		// @107: invokestatic game.C_100181_cf.func_105695_a(java.lang.Throwable, java.lang.String)game.C_100170_cm
		// @10A: athrow
	}
	
	static final String func_105399_a(byte arg0, long arg1)
	{
		// @000: getstatic java.util.Calendar game.C_100254_pi.field_106460_i
		// @003: new java.util.Date
		// @006: dup
		// @007: lload_1
		// @008: invokespecial java.util.Date.<init>(long)void
		// @00B: invokevirtual java.util.Calendar.setTime(java.util.Date)void
		// @00E: getstatic java.util.Calendar game.C_100254_pi.field_106460_i
		// @011: bipush 7 (0x07)
		// @013: invokevirtual java.util.Calendar.get(int)int
		// @016: istore_3
		// @017: getstatic java.util.Calendar game.C_100254_pi.field_106460_i
		// @01A: iconst_5
		// @01B: invokevirtual java.util.Calendar.get(int)int
		// @01E: istore #4
		// @020: getstatic java.util.Calendar game.C_100254_pi.field_106460_i
		// @023: iconst_2
		// @024: invokevirtual java.util.Calendar.get(int)int
		// @027: istore #5
		// @029: iload_0
		// @02A: bipush -46 (0xD2)
		// @02C: if_icmpeq @03A
		// @02F: aconst_null
		// @030: checkcast int[]
		// @033: putstatic int[] game.C_100159_sn.field_105404_a
		// @036: goto @03A
		// @039: athrow
		// @03A: getstatic java.util.Calendar game.C_100254_pi.field_106460_i
		// @03D: iconst_1
		// @03E: invokevirtual java.util.Calendar.get(int)int
		// @041: istore #6
		// @043: getstatic java.util.Calendar game.C_100254_pi.field_106460_i
		// @046: bipush 11 (0x0B)
		// @048: invokevirtual java.util.Calendar.get(int)int
		// @04B: istore #7
		// @04D: getstatic java.util.Calendar game.C_100254_pi.field_106460_i
		// @050: bipush 12 (0x0C)
		// @052: invokevirtual java.util.Calendar.get(int)int
		// @055: istore #8
		// @057: getstatic java.util.Calendar game.C_100254_pi.field_106460_i
		// @05A: bipush 13 (0x0D)
		// @05C: invokevirtual java.util.Calendar.get(int)int
		// @05F: istore #9
		// @061: new java.lang.StringBuilder
		// @064: dup
		// @065: invokespecial java.lang.StringBuilder.<init>()void
		// @068: getstatic java.lang.String[] game.C_100228_nn.field_106188_b
		// @06B: iconst_m1
		// @06C: iload_3
		// @06D: iadd
		// @06E: aaload
		// @06F: invokevirtual java.lang.StringBuilder.append(java.lang.String)java.lang.StringBuilder
		// @072: getstatic java.lang.String[] game.C_100159_sn.field_105405_z
		// @075: iconst_3
		// @076: aaload
		// @077: invokevirtual java.lang.StringBuilder.append(java.lang.String)java.lang.StringBuilder
		// @07A: iload #4
		// @07C: bipush 10 (0x0A)
		// @07E: idiv
		// @07F: invokevirtual java.lang.StringBuilder.append(int)java.lang.StringBuilder
		// @082: iload #4
		// @084: bipush 10 (0x0A)
		// @086: irem
		// @087: invokevirtual java.lang.StringBuilder.append(int)java.lang.StringBuilder
		// @08A: ldc "-"
		// @08C: invokevirtual java.lang.StringBuilder.append(java.lang.String)java.lang.StringBuilder
		// @08F: getstatic java.lang.String[] game.C_100287_nm.field_106822_f
		// @092: iload #5
		// @094: aaload
		// @095: invokevirtual java.lang.StringBuilder.append(java.lang.String)java.lang.StringBuilder
		// @098: ldc "-"
		// @09A: invokevirtual java.lang.StringBuilder.append(java.lang.String)java.lang.StringBuilder
		// @09D: iload #6
		// @09F: invokevirtual java.lang.StringBuilder.append(int)java.lang.StringBuilder
		// @0A2: ldc " "
		// @0A4: invokevirtual java.lang.StringBuilder.append(java.lang.String)java.lang.StringBuilder
		// @0A7: iload #7
		// @0A9: bipush 10 (0x0A)
		// @0AB: idiv
		// @0AC: invokevirtual java.lang.StringBuilder.append(int)java.lang.StringBuilder
		// @0AF: iload #7
		// @0B1: bipush 10 (0x0A)
		// @0B3: irem
		// @0B4: invokevirtual java.lang.StringBuilder.append(int)java.lang.StringBuilder
		// @0B7: ldc ":"
		// @0B9: invokevirtual java.lang.StringBuilder.append(java.lang.String)java.lang.StringBuilder
		// @0BC: iload #8
		// @0BE: bipush 10 (0x0A)
		// @0C0: idiv
		// @0C1: invokevirtual java.lang.StringBuilder.append(int)java.lang.StringBuilder
		// @0C4: iload #8
		// @0C6: bipush 10 (0x0A)
		// @0C8: irem
		// @0C9: invokevirtual java.lang.StringBuilder.append(int)java.lang.StringBuilder
		// @0CC: ldc ":"
		// @0CE: invokevirtual java.lang.StringBuilder.append(java.lang.String)java.lang.StringBuilder
		// @0D1: iload #9
		// @0D3: bipush 10 (0x0A)
		// @0D5: idiv
		// @0D6: invokevirtual java.lang.StringBuilder.append(int)java.lang.StringBuilder
		// @0D9: iload #9
		// @0DB: bipush 10 (0x0A)
		// @0DD: irem
		// @0DE: invokevirtual java.lang.StringBuilder.append(int)java.lang.StringBuilder
		// @0E1: getstatic java.lang.String[] game.C_100159_sn.field_105405_z
		// @0E4: iconst_4
		// @0E5: aaload
		// @0E6: invokevirtual java.lang.StringBuilder.append(java.lang.String)java.lang.StringBuilder
		// @0E9: invokevirtual java.lang.StringBuilder.toString()java.lang.String
		// @0EC: areturn
		// @0ED: astore_3
		// @0EE: aload_3
		// @0EF: new java.lang.StringBuilder
		// @0F2: dup
		// @0F3: invokespecial java.lang.StringBuilder.<init>()void
		// @0F6: getstatic java.lang.String[] game.C_100159_sn.field_105405_z
		// @0F9: iconst_2
		// @0FA: aaload
		// @0FB: invokevirtual java.lang.StringBuilder.append(java.lang.String)java.lang.StringBuilder
		// @0FE: iload_0
		// @0FF: invokevirtual java.lang.StringBuilder.append(int)java.lang.StringBuilder
		// @102: bipush 44 (0x2C)
		// @104: invokevirtual java.lang.StringBuilder.append(char)java.lang.StringBuilder
		// @107: lload_1
		// @108: invokevirtual java.lang.StringBuilder.append(long)java.lang.StringBuilder
		// @10B: bipush 41 (0x29)
		// @10D: invokevirtual java.lang.StringBuilder.append(char)java.lang.StringBuilder
		// @110: invokevirtual java.lang.StringBuilder.toString()java.lang.String
		// @113: invokestatic game.C_100181_cf.func_105695_a(java.lang.Throwable, java.lang.String)game.C_100170_cm
		// @116: athrow
	}
	
	static
	{
		// @00: iconst_5
		// @01: anewarray java.lang.String
		// @04: dup
		// @05: iconst_0
		// @06: ldc "/q\u0000m4"
		// @08: invokestatic game.C_100159_sn.func_105397_z(java.lang.String)char[]
		// @0B: invokestatic game.C_100159_sn.func_105395_z(char[])java.lang.String
		// @0E: aastore
		// @0F: dup
		// @10: iconst_1
		// @11: ldc "/q\u0000o4"
		// @13: invokestatic game.C_100159_sn.func_105397_z(java.lang.String)char[]
		// @16: invokestatic game.C_100159_sn.func_105395_z(char[])java.lang.String
		// @19: aastore
		// @1A: dup
		// @1B: iconst_2
		// @1C: ldc "/q\u0000n4"
		// @1E: invokestatic game.C_100159_sn.func_105397_z(java.lang.String)char[]
		// @21: invokestatic game.C_100159_sn.func_105395_z(char[])java.lang.String
		// @24: aastore
		// @25: dup
		// @26: iconst_3
		// @27: ldc "p?"
		// @29: invokestatic game.C_100159_sn.func_105397_z(java.lang.String)char[]
		// @2C: invokestatic game.C_100159_sn.func_105395_z(char[])java.lang.String
		// @2F: aastore
		// @30: dup
		// @31: iconst_4
		// @32: ldc "|Xcx"
		// @34: invokestatic game.C_100159_sn.func_105397_z(java.lang.String)char[]
		// @37: invokestatic game.C_100159_sn.func_105395_z(char[])java.lang.String
		// @3A: aastore
		// @3B: putstatic java.lang.String[] game.C_100159_sn.field_105405_z
		// @3E: ldc "\u0008PzmPf?\u0012Eq;\"\u001c\u0018\"`|A@!`:\u001f\u0012\"`:\u001e\u0012 s|A@\""
		// @40: invokestatic game.C_100159_sn.func_105397_z(java.lang.String)char[]
		// @43: invokestatic game.C_100159_sn.func_105395_z(char[])java.lang.String
		// @46: putstatic java.lang.String game.C_100159_sn.field_105400_d
		// @49: bipush 6 (0x06)
		// @4B: newarray int[]
		// @4D: dup
		// @4E: iconst_0
		// @4F: bipush 17 (0x11)
		// @51: iastore
		// @52: dup
		// @53: iconst_1
		// @54: bipush 18 (0x12)
		// @56: iastore
		// @57: dup
		// @58: iconst_2
		// @59: bipush 22 (0x16)
		// @5B: iastore
		// @5C: dup
		// @5D: iconst_3
		// @5E: iconst_m1
		// @5F: iastore
		// @60: dup
		// @61: iconst_4
		// @62: iconst_m1
		// @63: iastore
		// @64: dup
		// @65: iconst_5
		// @66: bipush 8 (0x08)
		// @68: iastore
		// @69: putstatic int[] game.C_100159_sn.field_105404_a
		// @6C: return
	}
	
	private static char[] func_105397_z(String arg0)
	{
		// @00: aload_0
		// @01: invokevirtual java.lang.String.toCharArray()char[]
		// @04: dup
		// @05: arraylength
		// @06: iconst_2
		// @07: if_icmpge @13
		// @0A: dup
		// @0B: iconst_0
		// @0C: dup2
		// @0D: caload
		// @0E: bipush 28 (0x1C)
		// @10: ixor
		// @11: i2c
		// @12: castore
		// @13: areturn
	}
	
	private static String func_105395_z(char[] arg0)
	{
		// @00: aload_0
		// @01: dup
		// @02: arraylength
		// @03: swap
		// @04: iconst_0
		// @05: istore_1
		// @06: goto @4C
		// @09: dup
		// @0A: iload_1
		// @0B: dup2
		// @0C: caload
		// @0D: iload_1
		// @0E: iconst_5
		// @0F: irem
		// @10: tableswitch def: @44, for 0: @30, for 1: @35, for 2: @3A, for 3: @3F
		// @30: bipush 92 (0x5C)
		// @32: goto @46
		// @35: bipush 31 (0x1F)
		// @37: goto @46
		// @3A: bipush 46 (0x2E)
		// @3C: goto @46
		// @3F: bipush 44 (0x2C)
		// @41: goto @46
		// @44: bipush 28 (0x1C)
		// @46: ixor
		// @47: i2c
		// @48: castore
		// @49: iinc #1 +1
		// @4C: swap
		// @4D: dup_x1
		// @4E: iload_1
		// @4F: if_icmpgt @09
		// @52: new java.lang.String
		// @55: dup_x1
		// @56: swap
		// @57: invokespecial java.lang.String.<init>(char[])void
		// @5A: invokevirtual java.lang.String.intern()java.lang.String
		// @5D: areturn
	}
}
