package game;

final class C_100300_kc
{
	static C_100146_bf field_107069_e;
	static String field_107068_d;
	private C_100325_id field_107067_g;
	static String field_107070_b;
	static C_100098_h field_107066_f;
	static int field_107071_c;
	private C_100325_id field_107072_a;
	private static final String[] field_107073_z;
	
	final C_100325_id func_107059_f(int arg0)
	{
		// @00: iload_1
		// @01: bipush -28 (0xE4)
		// @03: if_icmplt @11
		// @06: aconst_null
		// @07: checkcast game.C_100098_h
		// @0A: putstatic game.C_100098_h game.C_100300_kc.field_107066_f
		// @0D: goto @11
		// @10: athrow
		// @11: aload_0
		// @12: getfield game.C_100325_id game.C_100300_kc.field_107067_g
		// @15: getfield game.C_100325_id game.C_100325_id.field_101483_n
		// @18: astore_2
		// @19: aload_2
		// @1A: aload_0
		// @1B: getfield game.C_100325_id game.C_100300_kc.field_107067_g
		// @1E: if_acmpne @23
		// @21: aconst_null
		// @22: areturn
		// @23: aload_2
		// @24: bipush 8 (0x08)
		// @26: invokevirtual game.C_100325_id.func_101479_c(byte)void
		// @29: aload_2
		// @2A: areturn
		// @2B: astore_2
		// @2C: aload_2
		// @2D: new java.lang.StringBuilder
		// @30: dup
		// @31: invokespecial java.lang.StringBuilder.<init>()void
		// @34: getstatic java.lang.String[] game.C_100300_kc.field_107073_z
		// @37: iconst_0
		// @38: aaload
		// @39: invokevirtual java.lang.StringBuilder.append(java.lang.String)java.lang.StringBuilder
		// @3C: iload_1
		// @3D: invokevirtual java.lang.StringBuilder.append(int)java.lang.StringBuilder
		// @40: bipush 41 (0x29)
		// @42: invokevirtual java.lang.StringBuilder.append(char)java.lang.StringBuilder
		// @45: invokevirtual java.lang.StringBuilder.toString()java.lang.String
		// @48: invokestatic game.C_100181_cf.func_105695_a(java.lang.Throwable, java.lang.String)game.C_100170_cm
		// @4B: athrow
	}
	
	final void func_107054_b(int arg0)
	{
		// @00: getstatic int game.SteelSentinels.field_105275_O
		// @03: istore_3
		// @04: aload_0
		// @05: getfield game.C_100325_id game.C_100300_kc.field_107067_g
		// @08: getfield game.C_100325_id game.C_100325_id.field_101483_n
		// @0B: astore_2
		// @0C: aload_0
		// @0D: getfield game.C_100325_id game.C_100300_kc.field_107067_g
		// @10: aload_2
		// @11: if_acmpne @20
		// @14: iload_3
		// @15: ifne @2A
		// @18: iload_3
		// @19: ifeq @2E
		// @1C: goto @20
		// @1F: athrow
		// @20: aload_2
		// @21: bipush 8 (0x08)
		// @23: invokevirtual game.C_100325_id.func_101479_c(byte)void
		// @26: goto @2A
		// @29: athrow
		// @2A: iload_3
		// @2B: ifeq @04
		// @2E: aload_0
		// @2F: aconst_null
		// @30: putfield game.C_100325_id game.C_100300_kc.field_107072_a
		// @33: iload_1
		// @34: bipush -110 (0x92)
		// @36: if_icmplt @44
		// @39: aload_0
		// @3A: bipush -122 (0x86)
		// @3C: invokevirtual game.C_100300_kc.func_107059_f(int)game.C_100325_id
		// @3F: pop
		// @40: goto @44
		// @43: athrow
		// @44: goto @68
		// @47: astore_2
		// @48: aload_2
		// @49: new java.lang.StringBuilder
		// @4C: dup
		// @4D: invokespecial java.lang.StringBuilder.<init>()void
		// @50: getstatic java.lang.String[] game.C_100300_kc.field_107073_z
		// @53: iconst_3
		// @54: aaload
		// @55: invokevirtual java.lang.StringBuilder.append(java.lang.String)java.lang.StringBuilder
		// @58: iload_1
		// @59: invokevirtual java.lang.StringBuilder.append(int)java.lang.StringBuilder
		// @5C: bipush 41 (0x29)
		// @5E: invokevirtual java.lang.StringBuilder.append(char)java.lang.StringBuilder
		// @61: invokevirtual java.lang.StringBuilder.toString()java.lang.String
		// @64: invokestatic game.C_100181_cf.func_105695_a(java.lang.Throwable, java.lang.String)game.C_100170_cm
		// @67: athrow
		// @68: return
	}
	
	static final void func_107064_a(int arg0, int arg1, byte[] arg2, int[] arg3, boolean arg4)
	{
		// @00: getstatic int game.SteelSentinels.field_105275_O
		// @03: istore #7
		// @05: iconst_0
		// @06: istore #5
		// @08: iload #4
		// @0A: ifeq @18
		// @0D: aconst_null
		// @0E: checkcast java.lang.String
		// @11: putstatic java.lang.String game.C_100300_kc.field_107068_d
		// @14: goto @18
		// @17: athrow
		// @18: iload #5
		// @1A: getstatic int[] game.C_100231_oc.field_102192_dc
		// @1D: arraylength
		// @1E: if_icmpge @6B
		// @21: getstatic int[] game.C_100231_oc.field_102192_dc
		// @24: iload #5
		// @26: iaload
		// @27: istore_0
		// @28: iload #7
		// @2A: ifne @D9
		// @2D: iload #5
		// @2F: ldc 319238052 (0x13072fa4)
		// @31: ishl
		// @32: istore #6
		// @34: iconst_0
		// @35: iload_0
		// @36: iinc #0 +255
		// @39: if_icmpeq @63
		// @3C: getstatic int[] game.C_100093_fd.field_102781_W
		// @3F: iload #6
		// @41: iinc #6 +1
		// @44: iaload
		// @45: istore_1
		// @46: getstatic int[] game.C_100093_fd.field_102781_W
		// @49: aload_3
		// @4A: aload_2
		// @4B: iload_1
		// @4C: baload
		// @4D: dup2
		// @4E: iaload
		// @4F: dup_x2
		// @50: iconst_1
		// @51: iadd
		// @52: iastore
		// @53: iload_1
		// @54: iastore
		// @55: iload #7
		// @57: ifne @66
		// @5A: iload #7
		// @5C: ifeq @34
		// @5F: goto @63
		// @62: athrow
		// @63: iinc #5 +1
		// @66: iload #7
		// @68: ifeq @18
		// @6B: goto @D9
		// @6E: astore #5
		// @70: aload #5
		// @72: new java.lang.StringBuilder
		// @75: dup
		// @76: invokespecial java.lang.StringBuilder.<init>()void
		// @79: getstatic java.lang.String[] game.C_100300_kc.field_107073_z
		// @7C: bipush 6 (0x06)
		// @7E: aaload
		// @7F: invokevirtual java.lang.StringBuilder.append(java.lang.String)java.lang.StringBuilder
		// @82: iload_0
		// @83: invokevirtual java.lang.StringBuilder.append(int)java.lang.StringBuilder
		// @86: bipush 44 (0x2C)
		// @88: invokevirtual java.lang.StringBuilder.append(char)java.lang.StringBuilder
		// @8B: iload_1
		// @8C: invokevirtual java.lang.StringBuilder.append(int)java.lang.StringBuilder
		// @8F: bipush 44 (0x2C)
		// @91: invokevirtual java.lang.StringBuilder.append(char)java.lang.StringBuilder
		// @94: aload_2
		// @95: ifnull @A1
		// @98: getstatic java.lang.String[] game.C_100300_kc.field_107073_z
		// @9B: iconst_5
		// @9C: aaload
		// @9D: goto @A6
		// @A0: athrow
		// @A1: getstatic java.lang.String[] game.C_100300_kc.field_107073_z
		// @A4: iconst_4
		// @A5: aaload
		// @A6: invokevirtual java.lang.StringBuilder.append(java.lang.String)java.lang.StringBuilder
		// @A9: bipush 44 (0x2C)
		// @AB: invokevirtual java.lang.StringBuilder.append(char)java.lang.StringBuilder
		// @AE: aload_3
		// @AF: ifnull @BB
		// @B2: getstatic java.lang.String[] game.C_100300_kc.field_107073_z
		// @B5: iconst_5
		// @B6: aaload
		// @B7: goto @C0
		// @BA: athrow
		// @BB: getstatic java.lang.String[] game.C_100300_kc.field_107073_z
		// @BE: iconst_4
		// @BF: aaload
		// @C0: invokevirtual java.lang.StringBuilder.append(java.lang.String)java.lang.StringBuilder
		// @C3: bipush 44 (0x2C)
		// @C5: invokevirtual java.lang.StringBuilder.append(char)java.lang.StringBuilder
		// @C8: iload #4
		// @CA: invokevirtual java.lang.StringBuilder.append(boolean)java.lang.StringBuilder
		// @CD: bipush 41 (0x29)
		// @CF: invokevirtual java.lang.StringBuilder.append(char)java.lang.StringBuilder
		// @D2: invokevirtual java.lang.StringBuilder.toString()java.lang.String
		// @D5: invokestatic game.C_100181_cf.func_105695_a(java.lang.Throwable, java.lang.String)game.C_100170_cm
		// @D8: athrow
		// @D9: return
	}
	
	static final void func_107061_a(int arg0, String arg1, int arg2)
	{
		// @00: getstatic int game.SteelSentinels.field_105275_O
		// @03: istore #4
		// @05: iconst_5
		// @06: istore_3
		// @07: iload_0
		// @08: bipush 82 (0x52)
		// @0A: if_icmpgt @1E
		// @0D: bipush 10 (0x0A)
		// @0F: bipush 116 (0x74)
		// @11: bipush -57 (0xC7)
		// @13: bipush 57 (0x39)
		// @15: bipush -118 (0x8A)
		// @17: invokestatic game.C_100300_kc.func_107060_a(int, int, int, int, int)void
		// @1A: goto @1E
		// @1D: athrow
		// @1E: iconst_0
		// @1F: iload_3
		// @20: if_icmpge @58
		// @23: getstatic java.lang.String[] game.C_100124_tn.field_104932_g
		// @26: iload_3
		// @27: getstatic java.lang.String[] game.C_100124_tn.field_104932_g
		// @2A: iconst_m1
		// @2B: iload_3
		// @2C: iadd
		// @2D: aaload
		// @2E: aastore
		// @2F: getstatic int[] game.C_100075_uj.field_100657_s
		// @32: iload_3
		// @33: getstatic int[] game.C_100075_uj.field_100657_s
		// @36: iload_3
		// @37: iconst_m1
		// @38: iadd
		// @39: iaload
		// @3A: iastore
		// @3B: getstatic int[] game.C_100130_tf.field_104960_e
		// @3E: iload_3
		// @3F: getstatic int[] game.C_100130_tf.field_104960_e
		// @42: iconst_m1
		// @43: iload_3
		// @44: iadd
		// @45: iaload
		// @46: iastore
		// @47: iinc #3 +255
		// @4A: iload #4
		// @4C: ifne @70
		// @4F: iload #4
		// @51: ifeq @1E
		// @54: goto @58
		// @57: athrow
		// @58: getstatic java.lang.String[] game.C_100124_tn.field_104932_g
		// @5B: iconst_0
		// @5C: aload_1
		// @5D: iconst_0
		// @5E: invokestatic game.C_100096_un.func_104560_a(java.lang.String, boolean)java.lang.String
		// @61: aastore
		// @62: getstatic int[] game.C_100075_uj.field_100657_s
		// @65: iconst_0
		// @66: sipush 750 (0x02EE)
		// @69: iastore
		// @6A: getstatic int[] game.C_100130_tf.field_104960_e
		// @6D: iconst_0
		// @6E: iload_2
		// @6F: iastore
		// @70: goto @B8
		// @73: astore_3
		// @74: aload_3
		// @75: new java.lang.StringBuilder
		// @78: dup
		// @79: invokespecial java.lang.StringBuilder.<init>()void
		// @7C: getstatic java.lang.String[] game.C_100300_kc.field_107073_z
		// @7F: bipush 8 (0x08)
		// @81: aaload
		// @82: invokevirtual java.lang.StringBuilder.append(java.lang.String)java.lang.StringBuilder
		// @85: iload_0
		// @86: invokevirtual java.lang.StringBuilder.append(int)java.lang.StringBuilder
		// @89: bipush 44 (0x2C)
		// @8B: invokevirtual java.lang.StringBuilder.append(char)java.lang.StringBuilder
		// @8E: aload_1
		// @8F: ifnull @9B
		// @92: getstatic java.lang.String[] game.C_100300_kc.field_107073_z
		// @95: iconst_5
		// @96: aaload
		// @97: goto @A0
		// @9A: athrow
		// @9B: getstatic java.lang.String[] game.C_100300_kc.field_107073_z
		// @9E: iconst_4
		// @9F: aaload
		// @A0: invokevirtual java.lang.StringBuilder.append(java.lang.String)java.lang.StringBuilder
		// @A3: bipush 44 (0x2C)
		// @A5: invokevirtual java.lang.StringBuilder.append(char)java.lang.StringBuilder
		// @A8: iload_2
		// @A9: invokevirtual java.lang.StringBuilder.append(int)java.lang.StringBuilder
		// @AC: bipush 41 (0x29)
		// @AE: invokevirtual java.lang.StringBuilder.append(char)java.lang.StringBuilder
		// @B1: invokevirtual java.lang.StringBuilder.toString()java.lang.String
		// @B4: invokestatic game.C_100181_cf.func_105695_a(java.lang.Throwable, java.lang.String)game.C_100170_cm
		// @B7: athrow
		// @B8: return
	}
	
	static final void func_107060_a(int arg0, int arg1, int arg2, int arg3, int arg4)
	{
		// @00: iload #4
		// @02: putstatic int game.C_100312_ld.field_107152_g
		// @05: iload_2
		// @06: putstatic int game.C_100200_ba.field_105850_e
		// @09: iload_1
		// @0A: putstatic int game.C_100098_h.field_104612_f
		// @0D: iload_3
		// @0E: putstatic int game.C_100123_uc.field_104920_g
		// @11: iload_0
		// @12: sipush 1235 (0x04D3)
		// @15: if_icmpeq @1F
		// @18: aconst_null
		// @19: checkcast java.lang.String
		// @1C: putstatic java.lang.String game.C_100300_kc.field_107068_d
		// @1F: goto @6B
		// @22: astore #5
		// @24: aload #5
		// @26: new java.lang.StringBuilder
		// @29: dup
		// @2A: invokespecial java.lang.StringBuilder.<init>()void
		// @2D: getstatic java.lang.String[] game.C_100300_kc.field_107073_z
		// @30: bipush 11 (0x0B)
		// @32: aaload
		// @33: invokevirtual java.lang.StringBuilder.append(java.lang.String)java.lang.StringBuilder
		// @36: iload_0
		// @37: invokevirtual java.lang.StringBuilder.append(int)java.lang.StringBuilder
		// @3A: bipush 44 (0x2C)
		// @3C: invokevirtual java.lang.StringBuilder.append(char)java.lang.StringBuilder
		// @3F: iload_1
		// @40: invokevirtual java.lang.StringBuilder.append(int)java.lang.StringBuilder
		// @43: bipush 44 (0x2C)
		// @45: invokevirtual java.lang.StringBuilder.append(char)java.lang.StringBuilder
		// @48: iload_2
		// @49: invokevirtual java.lang.StringBuilder.append(int)java.lang.StringBuilder
		// @4C: bipush 44 (0x2C)
		// @4E: invokevirtual java.lang.StringBuilder.append(char)java.lang.StringBuilder
		// @51: iload_3
		// @52: invokevirtual java.lang.StringBuilder.append(int)java.lang.StringBuilder
		// @55: bipush 44 (0x2C)
		// @57: invokevirtual java.lang.StringBuilder.append(char)java.lang.StringBuilder
		// @5A: iload #4
		// @5C: invokevirtual java.lang.StringBuilder.append(int)java.lang.StringBuilder
		// @5F: bipush 41 (0x29)
		// @61: invokevirtual java.lang.StringBuilder.append(char)java.lang.StringBuilder
		// @64: invokevirtual java.lang.StringBuilder.toString()java.lang.String
		// @67: invokestatic game.C_100181_cf.func_105695_a(java.lang.Throwable, java.lang.String)game.C_100170_cm
		// @6A: athrow
		// @6B: return
	}
	
	final C_100325_id func_107063_c(int arg0)
	{
		// @00: aload_0
		// @01: getfield game.C_100325_id game.C_100300_kc.field_107072_a
		// @04: astore_2
		// @05: aload_2
		// @06: aload_0
		// @07: getfield game.C_100325_id game.C_100300_kc.field_107067_g
		// @0A: if_acmpne @14
		// @0D: aload_0
		// @0E: aconst_null
		// @0F: putfield game.C_100325_id game.C_100300_kc.field_107072_a
		// @12: aconst_null
		// @13: areturn
		// @14: iload_1
		// @15: ifeq @1D
		// @18: aconst_null
		// @19: checkcast game.C_100325_id
		// @1C: areturn
		// @1D: aload_0
		// @1E: aload_2
		// @1F: getfield game.C_100325_id game.C_100325_id.field_101483_n
		// @22: putfield game.C_100325_id game.C_100300_kc.field_107072_a
		// @25: aload_2
		// @26: areturn
		// @27: astore_2
		// @28: aload_2
		// @29: new java.lang.StringBuilder
		// @2C: dup
		// @2D: invokespecial java.lang.StringBuilder.<init>()void
		// @30: getstatic java.lang.String[] game.C_100300_kc.field_107073_z
		// @33: iconst_2
		// @34: aaload
		// @35: invokevirtual java.lang.StringBuilder.append(java.lang.String)java.lang.StringBuilder
		// @38: iload_1
		// @39: invokevirtual java.lang.StringBuilder.append(int)java.lang.StringBuilder
		// @3C: bipush 41 (0x29)
		// @3E: invokevirtual java.lang.StringBuilder.append(char)java.lang.StringBuilder
		// @41: invokevirtual java.lang.StringBuilder.toString()java.lang.String
		// @44: invokestatic game.C_100181_cf.func_105695_a(java.lang.Throwable, java.lang.String)game.C_100170_cm
		// @47: athrow
	}
	
	public static void func_107062_e(int arg0)
	{
		// @00: aconst_null
		// @01: putstatic game.C_100146_bf game.C_100300_kc.field_107069_e
		// @04: iload_0
		// @05: bipush -78 (0xB2)
		// @07: if_icmplt @19
		// @0A: bipush 21 (0x15)
		// @0C: aconst_null
		// @0D: checkcast java.lang.String
		// @10: bipush 74 (0x4A)
		// @12: invokestatic game.C_100300_kc.func_107061_a(int, java.lang.String, int)void
		// @15: goto @19
		// @18: athrow
		// @19: aconst_null
		// @1A: putstatic java.lang.String game.C_100300_kc.field_107068_d
		// @1D: aconst_null
		// @1E: putstatic java.lang.String game.C_100300_kc.field_107070_b
		// @21: aconst_null
		// @22: putstatic game.C_100098_h game.C_100300_kc.field_107066_f
		// @25: goto @4A
		// @28: astore_1
		// @29: aload_1
		// @2A: new java.lang.StringBuilder
		// @2D: dup
		// @2E: invokespecial java.lang.StringBuilder.<init>()void
		// @31: getstatic java.lang.String[] game.C_100300_kc.field_107073_z
		// @34: bipush 7 (0x07)
		// @36: aaload
		// @37: invokevirtual java.lang.StringBuilder.append(java.lang.String)java.lang.StringBuilder
		// @3A: iload_0
		// @3B: invokevirtual java.lang.StringBuilder.append(int)java.lang.StringBuilder
		// @3E: bipush 41 (0x29)
		// @40: invokevirtual java.lang.StringBuilder.append(char)java.lang.StringBuilder
		// @43: invokevirtual java.lang.StringBuilder.toString()java.lang.String
		// @46: invokestatic game.C_100181_cf.func_105695_a(java.lang.Throwable, java.lang.String)game.C_100170_cm
		// @49: athrow
		// @4A: return
	}
	
	final void func_107058_a(int arg0, C_100325_id arg1)
	{
		// @00: aload_2
		// @01: getfield game.C_100325_id game.C_100325_id.field_101486_m
		// @04: ifnonnull @0B
		// @07: goto @11
		// @0A: athrow
		// @0B: aload_2
		// @0C: bipush 8 (0x08)
		// @0E: invokevirtual game.C_100325_id.func_101479_c(byte)void
		// @11: aload_2
		// @12: aload_0
		// @13: getfield game.C_100325_id game.C_100300_kc.field_107067_g
		// @16: putfield game.C_100325_id game.C_100325_id.field_101483_n
		// @19: aload_2
		// @1A: aload_0
		// @1B: getfield game.C_100325_id game.C_100300_kc.field_107067_g
		// @1E: getfield game.C_100325_id game.C_100325_id.field_101486_m
		// @21: putfield game.C_100325_id game.C_100325_id.field_101486_m
		// @24: aload_2
		// @25: getfield game.C_100325_id game.C_100325_id.field_101486_m
		// @28: aload_2
		// @29: putfield game.C_100325_id game.C_100325_id.field_101483_n
		// @2C: aload_2
		// @2D: getfield game.C_100325_id game.C_100325_id.field_101483_n
		// @30: aload_2
		// @31: putfield game.C_100325_id game.C_100325_id.field_101486_m
		// @34: iload_1
		// @35: bipush 123 (0x7B)
		// @37: if_icmpgt @45
		// @3A: aconst_null
		// @3B: checkcast game.C_100098_h
		// @3E: putstatic game.C_100098_h game.C_100300_kc.field_107066_f
		// @41: goto @45
		// @44: athrow
		// @45: goto @84
		// @48: astore_3
		// @49: aload_3
		// @4A: new java.lang.StringBuilder
		// @4D: dup
		// @4E: invokespecial java.lang.StringBuilder.<init>()void
		// @51: getstatic java.lang.String[] game.C_100300_kc.field_107073_z
		// @54: bipush 10 (0x0A)
		// @56: aaload
		// @57: invokevirtual java.lang.StringBuilder.append(java.lang.String)java.lang.StringBuilder
		// @5A: iload_1
		// @5B: invokevirtual java.lang.StringBuilder.append(int)java.lang.StringBuilder
		// @5E: bipush 44 (0x2C)
		// @60: invokevirtual java.lang.StringBuilder.append(char)java.lang.StringBuilder
		// @63: aload_2
		// @64: ifnull @70
		// @67: getstatic java.lang.String[] game.C_100300_kc.field_107073_z
		// @6A: iconst_5
		// @6B: aaload
		// @6C: goto @75
		// @6F: athrow
		// @70: getstatic java.lang.String[] game.C_100300_kc.field_107073_z
		// @73: iconst_4
		// @74: aaload
		// @75: invokevirtual java.lang.StringBuilder.append(java.lang.String)java.lang.StringBuilder
		// @78: bipush 41 (0x29)
		// @7A: invokevirtual java.lang.StringBuilder.append(char)java.lang.StringBuilder
		// @7D: invokevirtual java.lang.StringBuilder.toString()java.lang.String
		// @80: invokestatic game.C_100181_cf.func_105695_a(java.lang.Throwable, java.lang.String)game.C_100170_cm
		// @83: athrow
		// @84: return
	}
	
	final C_100325_id func_107065_a(int arg0)
	{
		// @00: iload_1
		// @01: sipush -9190 (0xDC1A)
		// @04: if_icmpeq @12
		// @07: aconst_null
		// @08: checkcast java.lang.String
		// @0B: putstatic java.lang.String game.C_100300_kc.field_107070_b
		// @0E: goto @12
		// @11: athrow
		// @12: aload_0
		// @13: getfield game.C_100325_id game.C_100300_kc.field_107067_g
		// @16: getfield game.C_100325_id game.C_100325_id.field_101483_n
		// @19: astore_2
		// @1A: aload_2
		// @1B: aload_0
		// @1C: getfield game.C_100325_id game.C_100300_kc.field_107067_g
		// @1F: if_acmpeq @26
		// @22: goto @2D
		// @25: athrow
		// @26: aload_0
		// @27: aconst_null
		// @28: putfield game.C_100325_id game.C_100300_kc.field_107072_a
		// @2B: aconst_null
		// @2C: areturn
		// @2D: aload_0
		// @2E: aload_2
		// @2F: getfield game.C_100325_id game.C_100325_id.field_101483_n
		// @32: putfield game.C_100325_id game.C_100300_kc.field_107072_a
		// @35: aload_2
		// @36: areturn
		// @37: astore_2
		// @38: aload_2
		// @39: new java.lang.StringBuilder
		// @3C: dup
		// @3D: invokespecial java.lang.StringBuilder.<init>()void
		// @40: getstatic java.lang.String[] game.C_100300_kc.field_107073_z
		// @43: bipush 12 (0x0C)
		// @45: aaload
		// @46: invokevirtual java.lang.StringBuilder.append(java.lang.String)java.lang.StringBuilder
		// @49: iload_1
		// @4A: invokevirtual java.lang.StringBuilder.append(int)java.lang.StringBuilder
		// @4D: bipush 41 (0x29)
		// @4F: invokevirtual java.lang.StringBuilder.append(char)java.lang.StringBuilder
		// @52: invokevirtual java.lang.StringBuilder.toString()java.lang.String
		// @55: invokestatic game.C_100181_cf.func_105695_a(java.lang.Throwable, java.lang.String)game.C_100170_cm
		// @58: athrow
	}
	
	final int func_107057_d(int arg0)
	{
		// @00: getstatic int game.SteelSentinels.field_105275_O
		// @03: istore #4
		// @05: iload_1
		// @06: bipush 94 (0x5E)
		// @08: if_icmpge @16
		// @0B: aconst_null
		// @0C: checkcast java.lang.String
		// @0F: putstatic java.lang.String game.C_100300_kc.field_107070_b
		// @12: goto @16
		// @15: athrow
		// @16: iconst_0
		// @17: istore_2
		// @18: aload_0
		// @19: getfield game.C_100325_id game.C_100300_kc.field_107067_g
		// @1C: getfield game.C_100325_id game.C_100325_id.field_101483_n
		// @1F: astore_3
		// @20: aload_0
		// @21: getfield game.C_100325_id game.C_100300_kc.field_107067_g
		// @24: aload_3
		// @25: if_acmpeq @35
		// @28: iinc #2 +1
		// @2B: aload_3
		// @2C: getfield game.C_100325_id game.C_100325_id.field_101483_n
		// @2F: astore_3
		// @30: iload #4
		// @32: ifeq @20
		// @35: iload_2
		// @36: ireturn
		// @37: astore_2
		// @38: aload_2
		// @39: new java.lang.StringBuilder
		// @3C: dup
		// @3D: invokespecial java.lang.StringBuilder.<init>()void
		// @40: getstatic java.lang.String[] game.C_100300_kc.field_107073_z
		// @43: iconst_1
		// @44: aaload
		// @45: invokevirtual java.lang.StringBuilder.append(java.lang.String)java.lang.StringBuilder
		// @48: iload_1
		// @49: invokevirtual java.lang.StringBuilder.append(int)java.lang.StringBuilder
		// @4C: bipush 41 (0x29)
		// @4E: invokevirtual java.lang.StringBuilder.append(char)java.lang.StringBuilder
		// @51: invokevirtual java.lang.StringBuilder.toString()java.lang.String
		// @54: invokestatic game.C_100181_cf.func_105695_a(java.lang.Throwable, java.lang.String)game.C_100170_cm
		// @57: athrow
	}
	
	public C_100300_kc()
	{
		// @00: aload_0
		// @01: invokespecial java.lang.Object.<init>()void
		// @04: aload_0
		// @05: new game.C_100325_id
		// @08: dup
		// @09: invokespecial game.C_100325_id.<init>()void
		// @0C: putfield game.C_100325_id game.C_100300_kc.field_107067_g
		// @0F: aload_0
		// @10: getfield game.C_100325_id game.C_100300_kc.field_107067_g
		// @13: aload_0
		// @14: getfield game.C_100325_id game.C_100300_kc.field_107067_g
		// @17: putfield game.C_100325_id game.C_100325_id.field_101483_n
		// @1A: aload_0
		// @1B: getfield game.C_100325_id game.C_100300_kc.field_107067_g
		// @1E: aload_0
		// @1F: getfield game.C_100325_id game.C_100300_kc.field_107067_g
		// @22: putfield game.C_100325_id game.C_100325_id.field_101486_m
		// @25: goto @34
		// @28: astore_1
		// @29: aload_1
		// @2A: getstatic java.lang.String[] game.C_100300_kc.field_107073_z
		// @2D: bipush 9 (0x09)
		// @2F: aaload
		// @30: invokestatic game.C_100181_cf.func_105695_a(java.lang.Throwable, java.lang.String)game.C_100170_cm
		// @33: athrow
		// @34: return
	}
	
	static
	{
		// @00: bipush 13 (0x0D)
		// @02: anewarray java.lang.String
		// @05: dup
		// @06: iconst_0
		// @07: ldc "\u001cQJjf"
		// @09: invokestatic game.C_100300_kc.func_107056_z(java.lang.String)char[]
		// @0C: invokestatic game.C_100300_kc.func_107055_z(char[])java.lang.String
		// @0F: aastore
		// @10: dup
		// @11: iconst_1
		// @12: ldc "\u001cQJaf"
		// @14: invokestatic game.C_100300_kc.func_107056_z(java.lang.String)char[]
		// @17: invokestatic game.C_100300_kc.func_107055_z(char[])java.lang.String
		// @1A: aastore
		// @1B: dup
		// @1C: iconst_2
		// @1D: ldc "\u001cQJlf"
		// @1F: invokestatic game.C_100300_kc.func_107056_z(java.lang.String)char[]
		// @22: invokestatic game.C_100300_kc.func_107055_z(char[])java.lang.String
		// @25: aastore
		// @26: dup
		// @27: iconst_3
		// @28: ldc "\u001cQJmf"
		// @2A: invokestatic game.C_100300_kc.func_107056_z(java.lang.String)char[]
		// @2D: invokestatic game.C_100300_kc.func_107055_z(char[])java.lang.String
		// @30: aastore
		// @31: dup
		// @32: iconst_4
		// @33: ldc "\u0019G\u0008G"
		// @35: invokestatic game.C_100300_kc.func_107056_z(java.lang.String)char[]
		// @38: invokestatic game.C_100300_kc.func_107055_z(char[])java.lang.String
		// @3B: aastore
		// @3C: dup
		// @3D: iconst_5
		// @3E: ldc "\u000c\u001cJ\u00053"
		// @40: invokestatic game.C_100300_kc.func_107056_z(java.lang.String)char[]
		// @43: invokestatic game.C_100300_kc.func_107055_z(char[])java.lang.String
		// @46: aastore
		// @47: dup
		// @48: bipush 6 (0x06)
		// @4A: ldc "\u001cQJbf"
		// @4C: invokestatic game.C_100300_kc.func_107056_z(java.lang.String)char[]
		// @4F: invokestatic game.C_100300_kc.func_107055_z(char[])java.lang.String
		// @52: aastore
		// @53: dup
		// @54: bipush 7 (0x07)
		// @56: ldc "\u001cQJif"
		// @58: invokestatic game.C_100300_kc.func_107056_z(java.lang.String)char[]
		// @5B: invokestatic game.C_100300_kc.func_107055_z(char[])java.lang.String
		// @5E: aastore
		// @5F: dup
		// @60: bipush 8 (0x08)
		// @62: ldc "\u001cQJof"
		// @64: invokestatic game.C_100300_kc.func_107056_z(java.lang.String)char[]
		// @67: invokestatic game.C_100300_kc.func_107055_z(char[])java.lang.String
		// @6A: aastore
		// @6B: dup
		// @6C: bipush 9 (0x09)
		// @6E: ldc "\u001cQJ\u0017'\u0019[\u0010\u0015f^"
		// @70: invokestatic game.C_100300_kc.func_107056_z(java.lang.String)char[]
		// @73: invokestatic game.C_100300_kc.func_107055_z(char[])java.lang.String
		// @76: aastore
		// @77: dup
		// @78: bipush 10 (0x0A)
		// @7A: ldc "\u001cQJnf"
		// @7C: invokestatic game.C_100300_kc.func_107056_z(java.lang.String)char[]
		// @7F: invokestatic game.C_100300_kc.func_107055_z(char[])java.lang.String
		// @82: aastore
		// @83: dup
		// @84: bipush 11 (0x0B)
		// @86: ldc "\u001cQJhf"
		// @88: invokestatic game.C_100300_kc.func_107056_z(java.lang.String)char[]
		// @8B: invokestatic game.C_100300_kc.func_107055_z(char[])java.lang.String
		// @8E: aastore
		// @8F: dup
		// @90: bipush 12 (0x0C)
		// @92: ldc "\u001cQJcf"
		// @94: invokestatic game.C_100300_kc.func_107056_z(java.lang.String)char[]
		// @97: invokestatic game.C_100300_kc.func_107055_z(char[])java.lang.String
		// @9A: aastore
		// @9B: putstatic java.lang.String[] game.C_100300_kc.field_107073_z
		// @9E: ldc "4`'\u000b#\u001eA\tJ:\u0014ZD\u0006n\u0002\\\u0005I\"\u0012\u0012\u0010Dn\u0010W\u0010\u000b/WD\u0005G'\u0013\u0012\u0000D9\u0019^\u000bJ*Y\u00124G+\u0016A\u0001\u000b-\u001fW\u0007@n\u0016\\\u001d\u000b(\u001e@\u0001\\/\u001b^KJ \u0003[\u0012B<\u0002AKM'\u001bF\u0001Y'\u0019UDX!\u0011F\u0013J<\u0012\u001c"
		// @A0: invokestatic game.C_100300_kc.func_107056_z(java.lang.String)char[]
		// @A3: invokestatic game.C_100300_kc.func_107055_z(char[])java.lang.String
		// @A6: putstatic java.lang.String game.C_100300_kc.field_107068_d
		// @A9: ldc ":[\u0017X'\u0018\\Dh!\u001aB\u0008N:\u0012"
		// @AB: invokestatic game.C_100300_kc.func_107056_z(java.lang.String)char[]
		// @AE: invokestatic game.C_100300_kc.func_107055_z(char[])java.lang.String
		// @B1: putstatic java.lang.String game.C_100300_kc.field_107070_b
		// @B4: return
	}
	
	private static char[] func_107056_z(String arg0)
	{
		// @00: aload_0
		// @01: invokevirtual java.lang.String.toCharArray()char[]
		// @04: dup
		// @05: arraylength
		// @06: iconst_2
		// @07: if_icmpge @13
		// @0A: dup
		// @0B: iconst_0
		// @0C: dup2
		// @0D: caload
		// @0E: bipush 78 (0x4E)
		// @10: ixor
		// @11: i2c
		// @12: castore
		// @13: areturn
	}
	
	private static String func_107055_z(char[] arg0)
	{
		// @00: aload_0
		// @01: dup
		// @02: arraylength
		// @03: swap
		// @04: iconst_0
		// @05: istore_1
		// @06: goto @4C
		// @09: dup
		// @0A: iload_1
		// @0B: dup2
		// @0C: caload
		// @0D: iload_1
		// @0E: iconst_5
		// @0F: irem
		// @10: tableswitch def: @44, for 0: @30, for 1: @35, for 2: @3A, for 3: @3F
		// @30: bipush 119 (0x77)
		// @32: goto @46
		// @35: bipush 50 (0x32)
		// @37: goto @46
		// @3A: bipush 100 (0x64)
		// @3C: goto @46
		// @3F: bipush 43 (0x2B)
		// @41: goto @46
		// @44: bipush 78 (0x4E)
		// @46: ixor
		// @47: i2c
		// @48: castore
		// @49: iinc #1 +1
		// @4C: swap
		// @4D: dup_x1
		// @4E: iload_1
		// @4F: if_icmpgt @09
		// @52: new java.lang.String
		// @55: dup_x1
		// @56: swap
		// @57: invokespecial java.lang.String.<init>(char[])void
		// @5A: invokevirtual java.lang.String.intern()java.lang.String
		// @5D: areturn
	}
}
