package game;

final class C_100215_ai
{
	static String field_106023_i;
	static String[] field_106016_b;
	static String field_106020_j;
	static String field_106012_f;
	static String field_106015_e;
	static String field_106014_d;
	static String field_106013_g;
	static String field_106018_a;
	static C_100302_ka field_106017_c;
	static int field_106019_l;
	static int field_106021_k;
	static String field_106022_h;
	private static final String[] field_106024_z;
	
	static final void func_106005_c(int arg0)
	{
		// @00: iload_0
		// @01: ifeq @0F
		// @04: aconst_null
		// @05: checkcast java.lang.String
		// @08: putstatic java.lang.String game.C_100215_ai.field_106013_g
		// @0B: goto @0F
		// @0E: athrow
		// @0F: getstatic int game.C_100346_ja.field_103498_y
		// @12: bipush 32 (0x20)
		// @14: if_icmple @39
		// @17: getstatic int game.C_100346_ja.field_103498_y
		// @1A: bipush 32 (0x20)
		// @1C: irem
		// @1D: istore_1
		// @1E: iconst_m1
		// @1F: iload_1
		// @20: iconst_m1
		// @21: ixor
		// @22: if_icmpne @28
		// @25: bipush 32 (0x20)
		// @27: istore_1
		// @28: bipush 110 (0x6E)
		// @2A: iload_1
		// @2B: ineg
		// @2C: getstatic int game.C_100346_ja.field_103498_y
		// @2F: iadd
		// @30: invokestatic game.C_100266_me.func_106646_a(int, int)void
		// @33: getstatic int game.SteelSentinels.field_105275_O
		// @36: ifeq @43
		// @39: bipush 112 (0x70)
		// @3B: iconst_0
		// @3C: invokestatic game.C_100266_me.func_106646_a(int, int)void
		// @3F: goto @43
		// @42: athrow
		// @43: goto @68
		// @46: astore_1
		// @47: aload_1
		// @48: new java.lang.StringBuilder
		// @4B: dup
		// @4C: invokespecial java.lang.StringBuilder.<init>()void
		// @4F: getstatic java.lang.String[] game.C_100215_ai.field_106024_z
		// @52: bipush 8 (0x08)
		// @54: aaload
		// @55: invokevirtual java.lang.StringBuilder.append(java.lang.String)java.lang.StringBuilder
		// @58: iload_0
		// @59: invokevirtual java.lang.StringBuilder.append(int)java.lang.StringBuilder
		// @5C: bipush 41 (0x29)
		// @5E: invokevirtual java.lang.StringBuilder.append(char)java.lang.StringBuilder
		// @61: invokevirtual java.lang.StringBuilder.toString()java.lang.String
		// @64: invokestatic game.C_100181_cf.func_105695_a(java.lang.Throwable, java.lang.String)game.C_100170_cm
		// @67: athrow
		// @68: return
	}
	
	static final C_100037_wb[] func_106004_a(C_100037_wb[] arg0, byte arg1)
	{
		// @00: getstatic int game.SteelSentinels.field_105275_O
		// @03: istore #4
		// @05: iconst_0
		// @06: istore_2
		// @07: iload_1
		// @08: bipush 109 (0x6D)
		// @0A: if_icmpge @1B
		// @0D: aconst_null
		// @0E: checkcast game.C_100037_wb[]
		// @11: bipush 14 (0x0E)
		// @13: invokestatic game.C_100215_ai.func_106004_a(game.C_100037_wb[], byte)game.C_100037_wb[]
		// @16: pop
		// @17: goto @1B
		// @1A: athrow
		// @1B: aload_0
		// @1C: arraylength
		// @1D: iconst_m1
		// @1E: ixor
		// @1F: iload_2
		// @20: iconst_m1
		// @21: ixor
		// @22: if_icmpge @5E
		// @25: aload_0
		// @26: iload_2
		// @27: aaload
		// @28: astore_3
		// @29: aload_0
		// @2A: iload_2
		// @2B: aaload
		// @2C: iconst_0
		// @2D: putfield int game.C_100037_wb.field_102332_H
		// @30: aload_3
		// @31: iconst_0
		// @32: putfield int game.C_100037_wb.field_102335_w
		// @35: aload_0
		// @36: iload_2
		// @37: aaload
		// @38: aload_0
		// @39: iload_2
		// @3A: aaload
		// @3B: getfield int game.C_100037_wb.field_102339_s
		// @3E: putfield int game.C_100037_wb.field_102341_y
		// @41: aload_0
		// @42: iload #4
		// @44: ifne @5F
		// @47: iload_2
		// @48: aaload
		// @49: aload_0
		// @4A: iload_2
		// @4B: aaload
		// @4C: getfield int game.C_100037_wb.field_102337_u
		// @4F: putfield int game.C_100037_wb.field_102340_z
		// @52: iinc #2 +1
		// @55: iload #4
		// @57: ifeq @1B
		// @5A: goto @5E
		// @5D: athrow
		// @5E: aload_0
		// @5F: areturn
		// @60: astore_2
		// @61: aload_2
		// @62: new java.lang.StringBuilder
		// @65: dup
		// @66: invokespecial java.lang.StringBuilder.<init>()void
		// @69: getstatic java.lang.String[] game.C_100215_ai.field_106024_z
		// @6C: iconst_5
		// @6D: aaload
		// @6E: invokevirtual java.lang.StringBuilder.append(java.lang.String)java.lang.StringBuilder
		// @71: aload_0
		// @72: ifnull @7E
		// @75: getstatic java.lang.String[] game.C_100215_ai.field_106024_z
		// @78: iconst_3
		// @79: aaload
		// @7A: goto @83
		// @7D: athrow
		// @7E: getstatic java.lang.String[] game.C_100215_ai.field_106024_z
		// @81: iconst_4
		// @82: aaload
		// @83: invokevirtual java.lang.StringBuilder.append(java.lang.String)java.lang.StringBuilder
		// @86: bipush 44 (0x2C)
		// @88: invokevirtual java.lang.StringBuilder.append(char)java.lang.StringBuilder
		// @8B: iload_1
		// @8C: invokevirtual java.lang.StringBuilder.append(int)java.lang.StringBuilder
		// @8F: bipush 41 (0x29)
		// @91: invokevirtual java.lang.StringBuilder.append(char)java.lang.StringBuilder
		// @94: invokevirtual java.lang.StringBuilder.toString()java.lang.String
		// @97: invokestatic game.C_100181_cf.func_105695_a(java.lang.Throwable, java.lang.String)game.C_100170_cm
		// @9A: athrow
	}
	
	static final String func_106008_a(String arg0, boolean arg1, int arg2)
	{
		// @000: getstatic int game.SteelSentinels.field_105275_O
		// @003: istore #6
		// @005: aload_0
		// @006: bipush -100 (0x9C)
		// @008: invokestatic game.C_100240_oj.func_106310_a(java.lang.CharSequence, byte)boolean
		// @00B: ifeq @012
		// @00E: goto @016
		// @011: athrow
		// @012: getstatic java.lang.String game.C_100315_la.field_107175_g
		// @015: areturn
		// @016: getstatic int game.C_100062_dk.field_104281_d
		// @019: iconst_m1
		// @01A: ixor
		// @01B: bipush -3 (0xFD)
		// @01D: if_icmpne @024
		// @020: goto @028
		// @023: athrow
		// @024: getstatic java.lang.String game.C_100167_sj.field_100801_x
		// @027: areturn
		// @028: aload_0
		// @029: bipush 92 (0x5C)
		// @02B: invokestatic game.C_100278_nd.func_101197_b(java.lang.String, int)game.C_100061_dh
		// @02E: astore_3
		// @02F: aconst_null
		// @030: aload_3
		// @031: if_acmpne @046
		// @034: sipush -30945 (0x871F)
		// @037: iconst_1
		// @038: anewarray java.lang.String
		// @03B: dup
		// @03C: iconst_0
		// @03D: aload_0
		// @03E: aastore
		// @03F: getstatic java.lang.String game.C_100343_jf.field_104824_o
		// @042: invokestatic game.C_100132_td.func_104965_a(int, java.lang.String[], java.lang.String)java.lang.String
		// @045: areturn
		// @046: getstatic game.C_100202_qi game.C_100085_a.field_102569_L
		// @049: bipush 8 (0x08)
		// @04B: aload_3
		// @04C: invokevirtual game.C_100202_qi.func_105909_a(byte, game.C_100158_da)game.C_100158_da
		// @04F: pop
		// @050: getstatic game.C_100202_qi game.C_100085_a.field_102569_L
		// @053: bipush 67 (0x43)
		// @055: invokevirtual game.C_100202_qi.func_105907_c(byte)game.C_100158_da
		// @058: checkcast game.C_100061_dh
		// @05B: astore #4
		// @05D: aconst_null
		// @05E: aload #4
		// @060: if_acmpeq @07C
		// @063: aload #4
		// @065: dup
		// @066: getfield int game.C_100061_dh.field_101984_hc
		// @069: iconst_1
		// @06A: isub
		// @06B: putfield int game.C_100061_dh.field_101984_hc
		// @06E: iload #6
		// @070: ifne @090
		// @073: iload #6
		// @075: ifeq @050
		// @078: goto @07C
		// @07B: athrow
		// @07C: aload_3
		// @07D: bipush 45 (0x2D)
		// @07F: invokevirtual game.C_100061_dh.func_100583_c(int)void
		// @082: aload_3
		// @083: bipush 8 (0x08)
		// @085: invokevirtual game.C_100061_dh.func_101479_c(byte)void
		// @088: getstatic int game.C_100291_jj.field_106878_a
		// @08B: iconst_1
		// @08C: isub
		// @08D: putstatic int game.C_100291_jj.field_106878_a
		// @090: iload_1
		// @091: ifeq @09D
		// @094: bipush -80 (0xB0)
		// @096: invokestatic game.C_100215_ai.func_106011_d(int)void
		// @099: goto @09D
		// @09C: athrow
		// @09D: getstatic game.C_100278_nd game.C_100115_ej.field_102043_Yb
		// @0A0: astore #4
		// @0A2: aload #4
		// @0A4: iload_2
		// @0A5: bipush 125 (0x7D)
		// @0A7: invokevirtual game.C_100278_nd.func_101189_h(int, int)void
		// @0AA: aload #4
		// @0AC: dup
		// @0AD: getfield int game.C_100278_nd.field_101177_n
		// @0B0: iconst_1
		// @0B1: iadd
		// @0B2: putfield int game.C_100278_nd.field_101177_n
		// @0B5: aload #4
		// @0B7: getfield int game.C_100278_nd.field_101177_n
		// @0BA: istore #5
		// @0BC: aload #4
		// @0BE: sipush 7838 (0x1E9E)
		// @0C1: iconst_1
		// @0C2: invokevirtual game.C_100278_nd.func_101169_f(int, int)void
		// @0C5: aload #4
		// @0C7: sipush -28365 (0x9133)
		// @0CA: aload_0
		// @0CB: invokevirtual game.C_100278_nd.func_101167_a(int, java.lang.String)void
		// @0CE: aload #4
		// @0D0: iload #5
		// @0D2: ineg
		// @0D3: aload #4
		// @0D5: getfield int game.C_100278_nd.field_101177_n
		// @0D8: iadd
		// @0D9: bipush -83 (0xAD)
		// @0DB: invokevirtual game.C_100278_nd.func_101139_c(int, byte)void
		// @0DE: aconst_null
		// @0DF: areturn
		// @0E0: astore_3
		// @0E1: aload_3
		// @0E2: new java.lang.StringBuilder
		// @0E5: dup
		// @0E6: invokespecial java.lang.StringBuilder.<init>()void
		// @0E9: getstatic java.lang.String[] game.C_100215_ai.field_106024_z
		// @0EC: iconst_2
		// @0ED: aaload
		// @0EE: invokevirtual java.lang.StringBuilder.append(java.lang.String)java.lang.StringBuilder
		// @0F1: aload_0
		// @0F2: ifnull @0FE
		// @0F5: getstatic java.lang.String[] game.C_100215_ai.field_106024_z
		// @0F8: iconst_3
		// @0F9: aaload
		// @0FA: goto @103
		// @0FD: athrow
		// @0FE: getstatic java.lang.String[] game.C_100215_ai.field_106024_z
		// @101: iconst_4
		// @102: aaload
		// @103: invokevirtual java.lang.StringBuilder.append(java.lang.String)java.lang.StringBuilder
		// @106: bipush 44 (0x2C)
		// @108: invokevirtual java.lang.StringBuilder.append(char)java.lang.StringBuilder
		// @10B: iload_1
		// @10C: invokevirtual java.lang.StringBuilder.append(boolean)java.lang.StringBuilder
		// @10F: bipush 44 (0x2C)
		// @111: invokevirtual java.lang.StringBuilder.append(char)java.lang.StringBuilder
		// @114: iload_2
		// @115: invokevirtual java.lang.StringBuilder.append(int)java.lang.StringBuilder
		// @118: bipush 41 (0x29)
		// @11A: invokevirtual java.lang.StringBuilder.append(char)java.lang.StringBuilder
		// @11D: invokevirtual java.lang.StringBuilder.toString()java.lang.String
		// @120: invokestatic game.C_100181_cf.func_105695_a(java.lang.Throwable, java.lang.String)game.C_100170_cm
		// @123: athrow
	}
	
	public static void func_106003_b(int arg0)
	{
		// @00: aconst_null
		// @01: putstatic java.lang.String game.C_100215_ai.field_106013_g
		// @04: aconst_null
		// @05: putstatic java.lang.String game.C_100215_ai.field_106015_e
		// @08: aconst_null
		// @09: putstatic java.lang.String game.C_100215_ai.field_106012_f
		// @0C: aconst_null
		// @0D: putstatic java.lang.String game.C_100215_ai.field_106018_a
		// @10: aconst_null
		// @11: putstatic java.lang.String game.C_100215_ai.field_106020_j
		// @14: aconst_null
		// @15: putstatic java.lang.String game.C_100215_ai.field_106023_i
		// @18: aconst_null
		// @19: putstatic java.lang.String[] game.C_100215_ai.field_106016_b
		// @1C: aconst_null
		// @1D: putstatic game.C_100302_ka game.C_100215_ai.field_106017_c
		// @20: aconst_null
		// @21: putstatic java.lang.String game.C_100215_ai.field_106022_h
		// @24: aconst_null
		// @25: putstatic java.lang.String game.C_100215_ai.field_106014_d
		// @28: iload_0
		// @29: bipush -19 (0xED)
		// @2B: if_icmple @33
		// @2E: bipush -28 (0xE4)
		// @30: invokestatic game.C_100215_ai.func_106005_c(int)void
		// @33: goto @58
		// @36: astore_1
		// @37: aload_1
		// @38: new java.lang.StringBuilder
		// @3B: dup
		// @3C: invokespecial java.lang.StringBuilder.<init>()void
		// @3F: getstatic java.lang.String[] game.C_100215_ai.field_106024_z
		// @42: bipush 6 (0x06)
		// @44: aaload
		// @45: invokevirtual java.lang.StringBuilder.append(java.lang.String)java.lang.StringBuilder
		// @48: iload_0
		// @49: invokevirtual java.lang.StringBuilder.append(int)java.lang.StringBuilder
		// @4C: bipush 41 (0x29)
		// @4E: invokevirtual java.lang.StringBuilder.append(char)java.lang.StringBuilder
		// @51: invokevirtual java.lang.StringBuilder.toString()java.lang.String
		// @54: invokestatic game.C_100181_cf.func_105695_a(java.lang.Throwable, java.lang.String)game.C_100170_cm
		// @57: athrow
		// @58: return
	}
	
	static final void func_106002_a(int arg0, boolean arg1, int arg2, boolean arg3, int arg4, int arg5, boolean arg6, boolean arg7, int arg8, boolean arg9, int arg10, int arg11, byte arg12, int arg13)
	{
		// @00: aconst_null
		// @01: putstatic java.lang.String game.C_100321_hi.field_107220_c
		// @04: bipush 101 (0x65)
		// @06: iload #12
		// @08: bipush -7 (0xF9)
		// @0A: isub
		// @0B: bipush 62 (0x3E)
		// @0D: idiv
		// @0E: idiv
		// @0F: istore #14
		// @11: bipush -71 (0xB9)
		// @13: invokestatic game.C_100009_fg.func_103649_c(int)void
		// @16: iload #11
		// @18: iload #10
		// @1A: iload #13
		// @1C: iload #9
		// @1E: iload_2
		// @1F: sipush -16671 (0xBEE1)
		// @22: iload #8
		// @24: invokestatic game.C_100140_bj.func_102959_a(int, int, int, boolean, int, int, int)boolean
		// @27: istore #9
		// @29: iload_0
		// @2A: iload #4
		// @2C: iload #5
		// @2E: bipush -121 (0x87)
		// @30: iload #13
		// @32: iload #9
		// @34: iload #7
		// @36: iload #6
		// @38: iload_1
		// @39: iload_3
		// @3A: invokestatic game.C_100252_pn.func_105500_a(int, int, int, byte, int, boolean, boolean, boolean, boolean, boolean)void
		// @3D: bipush 110 (0x6E)
		// @3F: iload_0
		// @40: iload #6
		// @42: invokestatic game.C_100268_mk.func_106664_a(int, int, boolean)void
		// @45: iload #9
		// @47: iload_0
		// @48: bipush 86 (0x56)
		// @4A: iload_2
		// @4B: invokestatic game.C_100320_hh.func_102910_a(boolean, int, byte, int)void
		// @4E: goto @F4
		// @51: astore #14
		// @53: aload #14
		// @55: new java.lang.StringBuilder
		// @58: dup
		// @59: invokespecial java.lang.StringBuilder.<init>()void
		// @5C: getstatic java.lang.String[] game.C_100215_ai.field_106024_z
		// @5F: bipush 9 (0x09)
		// @61: aaload
		// @62: invokevirtual java.lang.StringBuilder.append(java.lang.String)java.lang.StringBuilder
		// @65: iload_0
		// @66: invokevirtual java.lang.StringBuilder.append(int)java.lang.StringBuilder
		// @69: bipush 44 (0x2C)
		// @6B: invokevirtual java.lang.StringBuilder.append(char)java.lang.StringBuilder
		// @6E: iload_1
		// @6F: invokevirtual java.lang.StringBuilder.append(boolean)java.lang.StringBuilder
		// @72: bipush 44 (0x2C)
		// @74: invokevirtual java.lang.StringBuilder.append(char)java.lang.StringBuilder
		// @77: iload_2
		// @78: invokevirtual java.lang.StringBuilder.append(int)java.lang.StringBuilder
		// @7B: bipush 44 (0x2C)
		// @7D: invokevirtual java.lang.StringBuilder.append(char)java.lang.StringBuilder
		// @80: iload_3
		// @81: invokevirtual java.lang.StringBuilder.append(boolean)java.lang.StringBuilder
		// @84: bipush 44 (0x2C)
		// @86: invokevirtual java.lang.StringBuilder.append(char)java.lang.StringBuilder
		// @89: iload #4
		// @8B: invokevirtual java.lang.StringBuilder.append(int)java.lang.StringBuilder
		// @8E: bipush 44 (0x2C)
		// @90: invokevirtual java.lang.StringBuilder.append(char)java.lang.StringBuilder
		// @93: iload #5
		// @95: invokevirtual java.lang.StringBuilder.append(int)java.lang.StringBuilder
		// @98: bipush 44 (0x2C)
		// @9A: invokevirtual java.lang.StringBuilder.append(char)java.lang.StringBuilder
		// @9D: iload #6
		// @9F: invokevirtual java.lang.StringBuilder.append(boolean)java.lang.StringBuilder
		// @A2: bipush 44 (0x2C)
		// @A4: invokevirtual java.lang.StringBuilder.append(char)java.lang.StringBuilder
		// @A7: iload #7
		// @A9: invokevirtual java.lang.StringBuilder.append(boolean)java.lang.StringBuilder
		// @AC: bipush 44 (0x2C)
		// @AE: invokevirtual java.lang.StringBuilder.append(char)java.lang.StringBuilder
		// @B1: iload #8
		// @B3: invokevirtual java.lang.StringBuilder.append(int)java.lang.StringBuilder
		// @B6: bipush 44 (0x2C)
		// @B8: invokevirtual java.lang.StringBuilder.append(char)java.lang.StringBuilder
		// @BB: iload #9
		// @BD: invokevirtual java.lang.StringBuilder.append(boolean)java.lang.StringBuilder
		// @C0: bipush 44 (0x2C)
		// @C2: invokevirtual java.lang.StringBuilder.append(char)java.lang.StringBuilder
		// @C5: iload #10
		// @C7: invokevirtual java.lang.StringBuilder.append(int)java.lang.StringBuilder
		// @CA: bipush 44 (0x2C)
		// @CC: invokevirtual java.lang.StringBuilder.append(char)java.lang.StringBuilder
		// @CF: iload #11
		// @D1: invokevirtual java.lang.StringBuilder.append(int)java.lang.StringBuilder
		// @D4: bipush 44 (0x2C)
		// @D6: invokevirtual java.lang.StringBuilder.append(char)java.lang.StringBuilder
		// @D9: iload #12
		// @DB: invokevirtual java.lang.StringBuilder.append(int)java.lang.StringBuilder
		// @DE: bipush 44 (0x2C)
		// @E0: invokevirtual java.lang.StringBuilder.append(char)java.lang.StringBuilder
		// @E3: iload #13
		// @E5: invokevirtual java.lang.StringBuilder.append(int)java.lang.StringBuilder
		// @E8: bipush 41 (0x29)
		// @EA: invokevirtual java.lang.StringBuilder.append(char)java.lang.StringBuilder
		// @ED: invokevirtual java.lang.StringBuilder.toString()java.lang.String
		// @F0: invokestatic game.C_100181_cf.func_105695_a(java.lang.Throwable, java.lang.String)game.C_100170_cm
		// @F3: athrow
		// @F4: return
	}
	
	static final void func_106011_d(int arg0)
	{
		// @00: iconst_1
		// @01: invokestatic game.C_100041_wf.func_104101_a(boolean)int
		// @04: istore_1
		// @05: iload_0
		// @06: bipush -3 (0xFD)
		// @08: if_icmpeq @16
		// @0B: aconst_null
		// @0C: checkcast java.lang.String
		// @0F: putstatic java.lang.String game.C_100215_ai.field_106013_g
		// @12: goto @16
		// @15: athrow
		// @16: bipush -58 (0xC6)
		// @18: invokestatic game.C_100231_oc.func_102189_f(byte)int
		// @1B: istore_2
		// @1C: getstatic game.C_100127_tl game.C_100309_lk.field_103263_T
		// @1F: getstatic int game.C_100215_ai.field_106019_l
		// @22: ineg
		// @23: getstatic int game.C_100138_bo.field_100401_f
		// @26: iadd
		// @27: getstatic int game.C_100055_ed.field_104240_g
		// @2A: ldc 2062348481 (0x7aecf0c1)
		// @2C: ishl
		// @2D: iload_2
		// @2E: iadd
		// @2F: getstatic int game.C_100055_ed.field_104240_g
		// @32: ineg
		// @33: getstatic int game.C_100336_im.field_102540_k
		// @36: iadd
		// @37: bipush 11 (0x0B)
		// @39: iload_1
		// @3A: getstatic int game.C_100215_ai.field_106019_l
		// @3D: ldc -94694143 (0xfa5b1501)
		// @3F: ishl
		// @40: iadd
		// @41: invokevirtual game.C_100127_tl.func_104944_a(int, int, int, int, int)void
		// @44: bipush -118 (0x8A)
		// @46: invokestatic game.C_100183_cd.func_103413_f(byte)void
		// @49: goto @6D
		// @4C: astore_1
		// @4D: aload_1
		// @4E: new java.lang.StringBuilder
		// @51: dup
		// @52: invokespecial java.lang.StringBuilder.<init>()void
		// @55: getstatic java.lang.String[] game.C_100215_ai.field_106024_z
		// @58: iconst_0
		// @59: aaload
		// @5A: invokevirtual java.lang.StringBuilder.append(java.lang.String)java.lang.StringBuilder
		// @5D: iload_0
		// @5E: invokevirtual java.lang.StringBuilder.append(int)java.lang.StringBuilder
		// @61: bipush 41 (0x29)
		// @63: invokevirtual java.lang.StringBuilder.append(char)java.lang.StringBuilder
		// @66: invokevirtual java.lang.StringBuilder.toString()java.lang.String
		// @69: invokestatic game.C_100181_cf.func_105695_a(java.lang.Throwable, java.lang.String)game.C_100170_cm
		// @6C: athrow
		// @6D: return
	}
	
	static final void func_106010_a(C_100290_jm arg0, int arg1)
	{
		// @00: aload_0
		// @01: putstatic game.C_100290_jm game.C_100038_wa.field_104069_e
		// @04: iload_1
		// @05: sipush 31322 (0x7A5A)
		// @08: if_icmpeq @12
		// @0B: aconst_null
		// @0C: checkcast java.lang.String[]
		// @0F: putstatic java.lang.String[] game.C_100215_ai.field_106016_b
		// @12: goto @51
		// @15: astore_2
		// @16: aload_2
		// @17: new java.lang.StringBuilder
		// @1A: dup
		// @1B: invokespecial java.lang.StringBuilder.<init>()void
		// @1E: getstatic java.lang.String[] game.C_100215_ai.field_106024_z
		// @21: bipush 7 (0x07)
		// @23: aaload
		// @24: invokevirtual java.lang.StringBuilder.append(java.lang.String)java.lang.StringBuilder
		// @27: aload_0
		// @28: ifnull @34
		// @2B: getstatic java.lang.String[] game.C_100215_ai.field_106024_z
		// @2E: iconst_3
		// @2F: aaload
		// @30: goto @39
		// @33: athrow
		// @34: getstatic java.lang.String[] game.C_100215_ai.field_106024_z
		// @37: iconst_4
		// @38: aaload
		// @39: invokevirtual java.lang.StringBuilder.append(java.lang.String)java.lang.StringBuilder
		// @3C: bipush 44 (0x2C)
		// @3E: invokevirtual java.lang.StringBuilder.append(char)java.lang.StringBuilder
		// @41: iload_1
		// @42: invokevirtual java.lang.StringBuilder.append(int)java.lang.StringBuilder
		// @45: bipush 41 (0x29)
		// @47: invokevirtual java.lang.StringBuilder.append(char)java.lang.StringBuilder
		// @4A: invokevirtual java.lang.StringBuilder.toString()java.lang.String
		// @4D: invokestatic game.C_100181_cf.func_105695_a(java.lang.Throwable, java.lang.String)game.C_100170_cm
		// @50: athrow
		// @51: return
	}
	
	static final void func_106006_a(int arg0)
	{
		// @00: iload_0
		// @01: getstatic int game.C_100216_aj.field_104467_z
		// @04: iconst_m1
		// @05: ixor
		// @06: if_icmpge @23
		// @09: getstatic int game.C_100216_aj.field_104467_z
		// @0C: bipush 32 (0x20)
		// @0E: irem
		// @0F: istore_1
		// @10: bipush 32 (0x20)
		// @12: getstatic int game.C_100216_aj.field_104467_z
		// @15: iadd
		// @16: iload_1
		// @17: isub
		// @18: bipush 94 (0x5E)
		// @1A: invokestatic game.C_100310_lj.func_100542_a(int, byte)void
		// @1D: getstatic int game.SteelSentinels.field_105275_O
		// @20: ifeq @2F
		// @23: sipush 256 (0x0100)
		// @26: bipush 80 (0x50)
		// @28: invokestatic game.C_100310_lj.func_100542_a(int, byte)void
		// @2B: goto @2F
		// @2E: athrow
		// @2F: goto @53
		// @32: astore_1
		// @33: aload_1
		// @34: new java.lang.StringBuilder
		// @37: dup
		// @38: invokespecial java.lang.StringBuilder.<init>()void
		// @3B: getstatic java.lang.String[] game.C_100215_ai.field_106024_z
		// @3E: iconst_1
		// @3F: aaload
		// @40: invokevirtual java.lang.StringBuilder.append(java.lang.String)java.lang.StringBuilder
		// @43: iload_0
		// @44: invokevirtual java.lang.StringBuilder.append(int)java.lang.StringBuilder
		// @47: bipush 41 (0x29)
		// @49: invokevirtual java.lang.StringBuilder.append(char)java.lang.StringBuilder
		// @4C: invokevirtual java.lang.StringBuilder.toString()java.lang.String
		// @4F: invokestatic game.C_100181_cf.func_105695_a(java.lang.Throwable, java.lang.String)game.C_100170_cm
		// @52: athrow
		// @53: return
	}
	
	static
	{
		// @000: bipush 10 (0x0A)
		// @002: anewarray java.lang.String
		// @005: dup
		// @006: iconst_0
		// @007: ldc "p0\u0003\u0005\u000c"
		// @009: invokestatic game.C_100215_ai.func_106009_z(java.lang.String)char[]
		// @00C: invokestatic game.C_100215_ai.func_106007_z(char[])java.lang.String
		// @00F: aastore
		// @010: dup
		// @011: iconst_1
		// @012: ldc "p0\u0003\u0002\u000c"
		// @014: invokestatic game.C_100215_ai.func_106009_z(java.lang.String)char[]
		// @017: invokestatic game.C_100215_ai.func_106007_z(char[])java.lang.String
		// @01A: aastore
		// @01B: dup
		// @01C: iconst_2
		// @01D: ldc "p0\u0003\u0007\u000c"
		// @01F: invokestatic game.C_100215_ai.func_106009_z(java.lang.String)char[]
		// @022: invokestatic game.C_100215_ai.func_106007_z(char[])java.lang.String
		// @025: aastore
		// @026: dup
		// @027: iconst_3
		// @028: ldc "jw\u0003nY"
		// @02A: invokestatic game.C_100215_ai.func_106009_z(java.lang.String)char[]
		// @02D: invokestatic game.C_100215_ai.func_106007_z(char[])java.lang.String
		// @030: aastore
		// @031: dup
		// @032: iconst_4
		// @033: ldc "\u007f,A,"
		// @035: invokestatic game.C_100215_ai.func_106009_z(java.lang.String)char[]
		// @038: invokestatic game.C_100215_ai.func_106007_z(char[])java.lang.String
		// @03B: aastore
		// @03C: dup
		// @03D: iconst_5
		// @03E: ldc "p0\u0003\u0004\u000c"
		// @040: invokestatic game.C_100215_ai.func_106009_z(java.lang.String)char[]
		// @043: invokestatic game.C_100215_ai.func_106007_z(char[])java.lang.String
		// @046: aastore
		// @047: dup
		// @048: bipush 6 (0x06)
		// @04A: ldc "p0\u0003\u0001\u000c"
		// @04C: invokestatic game.C_100215_ai.func_106009_z(java.lang.String)char[]
		// @04F: invokestatic game.C_100215_ai.func_106007_z(char[])java.lang.String
		// @052: aastore
		// @053: dup
		// @054: bipush 7 (0x07)
		// @056: ldc "p0\u0003\u0008\u000c"
		// @058: invokestatic game.C_100215_ai.func_106009_z(java.lang.String)char[]
		// @05B: invokestatic game.C_100215_ai.func_106007_z(char[])java.lang.String
		// @05E: aastore
		// @05F: dup
		// @060: bipush 8 (0x08)
		// @062: ldc "p0\u0003\u0003\u000c"
		// @064: invokestatic game.C_100215_ai.func_106009_z(java.lang.String)char[]
		// @067: invokestatic game.C_100215_ai.func_106007_z(char[])java.lang.String
		// @06A: aastore
		// @06B: dup
		// @06C: bipush 9 (0x09)
		// @06E: ldc "p0\u0003\u0006\u000c"
		// @070: invokestatic game.C_100215_ai.func_106009_z(java.lang.String)char[]
		// @073: invokestatic game.C_100215_ai.func_106007_z(char[])java.lang.String
		// @076: aastore
		// @077: putstatic java.lang.String[] game.C_100215_ai.field_106024_z
		// @07A: ldc "P:N%Tey\u0011e\u0014/yD.P~yY(MbyJ!It"
		// @07C: invokestatic game.C_100215_ai.func_106009_z(java.lang.String)char[]
		// @07F: invokestatic game.C_100215_ai.func_106007_z(char[])java.lang.String
		// @082: putstatic java.lang.String game.C_100215_ai.field_106023_i
		// @085: ldc "B<N5Vx-T"
		// @087: invokestatic game.C_100215_ai.func_106009_z(java.lang.String)char[]
		// @08A: invokestatic game.C_100215_ai.func_106007_z(char[])java.lang.String
		// @08D: putstatic java.lang.String game.C_100215_ai.field_106012_f
		// @090: bipush 39 (0x27)
		// @092: anewarray java.lang.String
		// @095: dup
		// @096: iconst_0
		// @097: ldc "D*H`V~:F%PbyY/\u0004y0Y`E1-L2Ct-\rq\u00141-D-AbyD.\u0004py_/S?y\u0005\u0012Ee<I`K\u007f5Ti"
		// @099: invokestatic game.C_100215_ai.func_106009_z(java.lang.String)char[]
		// @09C: invokestatic game.C_100215_ai.func_106007_z(char[])java.lang.String
		// @09F: aastore
		// @0A0: dup
		// @0A1: iconst_1
		// @0A2: ldc "Y0Y`A\u007f<@)AbyD.\u0004e1H`Ex+\r7Me1\rq\u001414D3Wx5H3\u0004u,_)JvyL`Cp4Hn\u00049\u000bL4AuyB.Hhp"
		// @0A4: invokestatic game.C_100215_ai.func_106009_z(java.lang.String)char[]
		// @0A7: invokestatic game.C_100215_ai.func_106007_z(char[])java.lang.String
		// @0AA: aastore
		// @0AB: dup
		// @0AC: iconst_2
		// @0AD: ldc "Y0Y`A\u007f<@)AbyD.\u0004e1H`Ex+\r7Me1\rq\u00141*E%H}*\r!JuvB2\u0004c6N+Ae*\r$Qc0C'\u0004pyJ!Itw\rhvp-H$\u0004~7A9\r"
		// @0AF: invokestatic game.C_100215_ai.func_106009_z(java.lang.String)char[]
		// @0B2: invokestatic game.C_100215_ai.func_106007_z(char[])java.lang.String
		// @0B5: aastore
		// @0B6: dup
		// @0B7: iconst_3
		// @0B8: ldc "R6A,Ar-\rq\u0014!y\n\rKb-\r\tJe<_#Aa-D/Jb~\r4Ev*\r)J1\u000bL4AuyJ!It*\u0003"
		// @0BA: invokestatic game.C_100215_ai.func_106009_z(java.lang.String)char[]
		// @0BD: invokestatic game.C_100215_ai.func_106007_z(char[])java.lang.String
		// @0C0: aastore
		// @0C1: dup
		// @0C2: iconst_4
		// @0C3: ldc "U<^4V~ \r!J1<C%Ihy^%Je0C%H1;T`M\u007f-H2Gt)Y)JvyL`Ix*^)HtyB2\u0004c6N+Aew\rhvp-H$\u0004~7A9\r"
		// @0C5: invokestatic game.C_100215_ai.func_106009_z(java.lang.String)char[]
		// @0C8: invokestatic game.C_100215_ai.func_106007_z(char[])java.lang.String
		// @0CB: aastore
		// @0CC: dup
		// @0CD: iconst_5
		// @0CE: ldc "U<^4V~ \r!J1<C%Ihy^%Je0C%H1.E)HtyD4\u0004x*\r)J1-E%\u0004p0_n\u00049\u000bL4AuyB.Hhp"
		// @0D0: invokestatic game.C_100215_ai.func_106009_z(java.lang.String)char[]
		// @0D3: invokestatic game.C_100215_ai.func_106007_z(char[])java.lang.String
		// @0D6: aastore
		// @0D7: dup
		// @0D8: bipush 6 (0x06)
		// @0DA: ldc "D7A/GzyY(A1\u0014D2Ev<\r$Ag0N%\u0004s \r#K|)A%Px7J`Py<\r-A|;H2W6yN!Ia8D'J?"
		// @0DC: invokestatic game.C_100215_ai.func_106009_z(java.lang.String)char[]
		// @0DF: invokestatic game.C_100215_ai.func_106007_z(char[])java.lang.String
		// @0E2: aastore
		// @0E3: dup
		// @0E4: bipush 7 (0x07)
		// @0E6: ldc "R6A,Ar-\rq\u0014!y\n\u0010Ac?H#P6yY!CbyD.\u0004C8Y%@1>L-Abw"
		// @0E8: invokestatic game.C_100215_ai.func_106009_z(java.lang.String)char[]
		// @0EB: invokestatic game.C_100215_ai.func_106007_z(char[])java.lang.String
		// @0EE: aastore
		// @0EF: dup
		// @0F0: bipush 8 (0x08)
		// @0F2: ldc "A<_3K\u007f8A,]1=H3Pc6T`Pf6\r/Ta6C%Je*\r7Me1D.\u0004$y^%G~7I3\n1q\u007f!Pt=\r/J} \u0004"
		// @0F4: invokestatic game.C_100215_ai.func_106009_z(java.lang.String)char[]
		// @0F7: invokestatic game.C_100215_ai.func_106007_z(char[])java.lang.String
		// @0FA: aastore
		// @0FB: dup
		// @0FC: bipush 9 (0x09)
		// @0FE: ldc "F0C`E1h\u001fmT}8T%V1>L-A1.D4L1-E%\u0004y0J(Ab-\r3G~+Hn\u00049\u000bL4AuyB.Hhp"
		// @100: invokestatic game.C_100215_ai.func_106009_z(java.lang.String)char[]
		// @103: invokestatic game.C_100215_ai.func_106007_z(char[])java.lang.String
		// @106: aastore
		// @107: dup
		// @108: bipush 10 (0x0A)
		// @10A: ldc "R6A,Ar-\rq\u0014!yB&\u0004t8N(\u0004~?\r4LtyK/H}6Z)JvyY!CbyD.\u0004C8Y%@1>L-Abc\rgi~*Y`ox5A3\u0003=y\n\rKb-\r\u0004E|8J%\u0003=y\n\u000bM}5D.C1\nY2Ap2^g\u0004p7I`\u0003W0_3P1\u0012D,Hb~\u0003"
		// @10C: invokestatic game.C_100215_ai.func_106009_z(java.lang.String)char[]
		// @10F: invokestatic game.C_100215_ai.func_106007_z(char[])java.lang.String
		// @112: aastore
		// @113: dup
		// @114: bipush 11 (0x0B)
		// @116: ldc "R6A,Ar-\rq\u0014!yB&\u0004t8N(\u0004~?\r4LtyK/H}6Z)JvyY!CbyD.\u0004C8Y%@1>L-Abc\rgi~*Y`cd7\r\u000bM}5^g\u00081~`/Weyn!J\u007f6C`ox5A3\u000318C$\u00046\u0014B3P1\u000bB#Ot-\r\u000bM}5^g\n"
		// @118: invokestatic game.C_100215_ai.func_106009_z(java.lang.String)char[]
		// @11B: invokestatic game.C_100215_ai.func_106007_z(char[])java.lang.String
		// @11E: aastore
		// @11F: dup
		// @120: bipush 12 (0x0C)
		// @122: ldc "R6A,Ar-\rq\u0014!yB&\u0004t8N(\u0004~?\r4LtyK/H}6Z)JvyY!CbyD.\u0004C8Y%@1>L-Abc\rgi~*Y`ft8@`ox5A3\u0003=y\n\rKb-\r\u0010Hp*@!\u0004Z0A,W6yL.@1~`/Wey\u007f!M}yf)H}*\nn"
		// @124: invokestatic game.C_100215_ai.func_106009_z(java.lang.String)char[]
		// @127: invokestatic game.C_100215_ai.func_106007_z(char[])java.lang.String
		// @12A: aastore
		// @12B: dup
		// @12C: bipush 13 (0x0D)
		// @12E: ldc "R6A,Ar-\rq\u0014!yY!CbyK/V1~`/Wey`%Ht<\r\u000bM}5^g\u0004x7\r\u0012Ee<I`Cp4H3\n"
		// @130: invokestatic game.C_100215_ai.func_106009_z(java.lang.String)char[]
		// @133: invokestatic game.C_100215_ai.func_106007_z(char[])java.lang.String
		// @136: aastore
		// @137: dup
		// @138: bipush 14 (0x0E)
		// @13A: ldc "R6A,Ar-\rq\u0014!yB&\u0004t8N(\u0004~?\r4LtyK/H}6Z)JvyY!CbyD.\u0004C8Y%@1>L-Abc\rgi~*Y`wy0]`a\u007f<_'Mb<^g\u00081~k)Vb-\r4K1\u001cC%Vv0^%\u000318C$\u00046\u0012D,Hx7J`a\u007f<_'Mb<I`a\u007f<@)Ab~\u0003"
		// @13C: invokestatic game.C_100215_ai.func_106009_z(java.lang.String)char[]
		// @13F: invokestatic game.C_100215_ai.func_106007_z(char[])java.lang.String
		// @142: aastore
		// @143: dup
		// @144: bipush 15 (0x0F)
		// @146: ldc "R6A,Ar-\rq\u0014!y\n\u0002Ab-\r\u0014Ap4\r\u0013G~+Hg\u0004e8J3\u0004x7\r\u0012Ee<I`Cp4H3\n"
		// @148: invokestatic game.C_100215_ai.func_106009_z(java.lang.String)char[]
		// @14B: invokestatic game.C_100215_ai.func_106007_z(char[])java.lang.String
		// @14E: aastore
		// @14F: dup
		// @150: bipush 16 (0x10)
		// @152: ldc "A<_3K\u007f8A,]1=H3Pc6T`B~,_`Ka)B.A\u007f-^`Sx-E)J1l\r3Ar6C$W?y\u0005\u0012Ee<I`K\u007f5Ti"
		// @154: invokestatic game.C_100215_ai.func_106009_z(java.lang.String)char[]
		// @157: invokestatic game.C_100215_ai.func_106007_z(char[])java.lang.String
		// @15A: aastore
		// @15B: dup
		// @15C: bipush 17 (0x11)
		// @15E: ldc "F0C`E1\u000bL4AuyJ!Itw"
		// @160: invokestatic game.C_100215_ai.func_106009_z(java.lang.String)char[]
		// @163: invokestatic game.C_100215_ai.func_106007_z(char[])java.lang.String
		// @166: aastore
		// @167: dup
		// @168: bipush 18 (0x12)
		// @16A: ldc "R6A,Ar-\ru\u0004~?\r/JtyY!C?"
		// @16C: invokestatic game.C_100215_ai.func_106009_z(java.lang.String)char[]
		// @16F: invokestatic game.C_100215_ai.func_106007_z(char[])java.lang.String
		// @172: aastore
		// @173: dup
		// @174: bipush 19 (0x13)
		// @176: ldc "F0C`\u0016$y\u007f!Pt=\r'E|<^`E\u007f=\r#K}5H#P1h\u001d`Pp>^`Bc6@`\u00111=D&Bt+H.P1:L4Av6_)Abw"
		// @178: invokestatic game.C_100215_ai.func_106009_z(java.lang.String)char[]
		// @17B: invokestatic game.C_100215_ai.func_106007_z(char[])java.lang.String
		// @17E: aastore
		// @17F: dup
		// @180: bipush 20 (0x14)
		// @182: ldc "F0C`\u0011!y\u007f!Pt=\r'E|<^`E\u007f=\r#K}5H#P1k\u001d`Pp>^`Bc6@`\u0015!yI)Bw<_%JeyN!Pt>B2Mt*\u0003"
		// @184: invokestatic game.C_100215_ai.func_106009_z(java.lang.String)char[]
		// @187: invokestatic game.C_100215_ai.func_106007_z(char[])java.lang.String
		// @18A: aastore
		// @18B: dup
		// @18C: bipush 21 (0x15)
		// @18E: ldc "F0C`\u0015!i\r\u0012Ee<I`Cp4H3\u0004p7I`G~5A%Gey\u001ep\u0004e8J3\u0004w+B-\u0004 l\r$Mw?H2A\u007f-\r#Ee<J/Vx<^n"
		// @190: invokestatic game.C_100215_ai.func_106009_z(java.lang.String)char[]
		// @193: invokestatic game.C_100215_ai.func_106007_z(char[])java.lang.String
		// @196: aastore
		// @197: dup
		// @198: bipush 22 (0x16)
		// @19A: ldc "F0C`\u0015$i\r\u0012Ee<I`Cp4H3\u0004p7I`G~5A%Gey\u0019p\u0004e8J3\u0004w+B-\u0004#i\r$Mw?H2A\u007f-\r#Ee<J/Vx<^n"
		// @19C: invokestatic game.C_100215_ai.func_106009_z(java.lang.String)char[]
		// @19F: invokestatic game.C_100215_ai.func_106007_z(char[])java.lang.String
		// @1A2: aastore
		// @1A3: dup
		// @1A4: bipush 23 (0x17)
		// @1A6: ldc "F0C`\u0016!i\r\u0012Ee<I`Cp4H3\u0004p7I`G~5A%Gey\u0018p\u0004e8J3\u0004w+B-\u0004#l\r$Mw?H2A\u007f-\r#Ee<J/Vx<^n"
		// @1A8: invokestatic game.C_100215_ai.func_106009_z(java.lang.String)char[]
		// @1AB: invokestatic game.C_100215_ai.func_106007_z(char[])java.lang.String
		// @1AE: aastore
		// @1AF: dup
		// @1B0: bipush 24 (0x18)
		// @1B2: ldc "F0C`E1>L-A1?_/I18\r,Kb0C'\u0004a6^)Px6C`EeyY(A1*Y!VeyB&\u0004b,I$A\u007fyI%Ee1\u0003`\u000cC8Y%@16C,]=y\u001fmT}8T%V8"
		// @1B4: invokestatic game.C_100215_ai.func_106009_z(java.lang.String)char[]
		// @1B7: invokestatic game.C_100215_ai.func_106007_z(char[])java.lang.String
		// @1BA: aastore
		// @1BB: dup
		// @1BC: bipush 25 (0x19)
		// @1BE: ldc "D7A/GzyY(A1\u001eB,A|tN,Eb*\r\u0004aP\re`Jd:A%EcyZ!Vy<L$\u0004s \r#K|)A%Px7J`Py<\r#K<6]`Cp4Hn"
		// @1C0: invokestatic game.C_100215_ai.func_106009_z(java.lang.String)char[]
		// @1C3: invokestatic game.C_100215_ai.func_106007_z(char[])java.lang.String
		// @1C6: aastore
		// @1C7: dup
		// @1C8: bipush 26 (0x1A)
		// @1CA: ldc "U<^4V~ \r4Lty^%Je0C%H1.E/\u0004}8^4\u0004u<K%Ee<I`]~,\r4LtyC%\\eyY)ItyT/Q14H%P?y\u0005\u0012Ee<I`K\u007f5Tl\u0004#t],Eh<_i"
		// @1CC: invokestatic game.C_100215_ai.func_106009_z(java.lang.String)char[]
		// @1CF: invokestatic game.C_100215_ai.func_106007_z(char[])java.lang.String
		// @1D2: aastore
		// @1D3: dup
		// @1D4: bipush 27 (0x1B)
		// @1D6: ldc "T8_.\u0004 i\u001dl\u0014!i\r0Kx7Y3\u0004x7\r4LtyN/\t~)\r'E|<\u0003"
		// @1D8: invokestatic game.C_100215_ai.func_106009_z(java.lang.String)char[]
		// @1DB: invokestatic game.C_100215_ai.func_106007_z(char[])java.lang.String
		// @1DE: aastore
		// @1DF: dup
		// @1E0: bipush 28 (0x1C)
		// @1E2: ldc "T8_.\u0004#l\u001dl\u0014!i\r0Kx7Y3\u0004x7\r4LtyN/\t~)\r'E|<\u0003"
		// @1E4: invokestatic game.C_100215_ai.func_106009_z(java.lang.String)char[]
		// @1E7: invokestatic game.C_100215_ai.func_106007_z(char[])java.lang.String
		// @1EA: aastore
		// @1EB: dup
		// @1EC: bipush 29 (0x1D)
		// @1EE: ldc "U<^4V~ \r4Lty^%Je0C%H1.E/\u0004{,^4\u0004u<^4V~ H$\u0004h6Xl\u0004f1D,A1-E%]18_%\u0004v5B!Px7Jn\u00049\u000bL4AuyB.Hhp"
		// @1F0: invokestatic game.C_100215_ai.func_106009_z(java.lang.String)char[]
		// @1F3: invokestatic game.C_100215_ai.func_106007_z(char[])java.lang.String
		// @1F6: aastore
		// @1F7: dup
		// @1F8: bipush 30 (0x1E)
		// @1FA: ldc "U<^4V~ \r!\u0004b<C4M\u007f<A`Py8Y`Lp*\r!\u0004e<N(\u0004g8A5A1?B5V1-D-AbyY(EeyB&\u0004h6X2\u0004~.Cn\u00049\u000bL4AuyB.Hhp"
		// @1FC: invokestatic game.C_100215_ai.func_106009_z(java.lang.String)char[]
		// @1FF: invokestatic game.C_100215_ai.func_106007_z(char[])java.lang.String
		// @202: aastore
		// @203: dup
		// @204: bipush 31 (0x1F)
		// @206: ldc "U<^4V~ \r%Rt+T/JtyD.\u0004pyJ!ItyZ)PyyL`Wx7J,A17X+A=yD.G},I)JvyT/Qc*H,B?w\u0003`\u000cC8Y%@16C,]*yL4\u0004}<L3P1?B5V1*H.Px7H,W8"
		// @208: invokestatic game.C_100215_ai.func_106009_z(java.lang.String)char[]
		// @20B: invokestatic game.C_100215_ai.func_106007_z(char[])java.lang.String
		// @20E: aastore
		// @20F: dup
		// @210: bipush 32 (0x20)
		// @212: ldc "R6@0Ht-H`Py<\r\tH~5D!J1\u0010C#Mu<C4\u0004r8@0Ex>Cn"
		// @214: invokestatic game.C_100215_ai.func_106009_z(java.lang.String)char[]
		// @217: invokestatic game.C_100215_ai.func_106007_z(char[])java.lang.String
		// @21A: aastore
		// @21B: dup
		// @21C: bipush 33 (0x21)
		// @21E: ldc "V<Y`\u00111*Y!VbyK/V1:L-Tp0J.\u0004|0^3M~7^n"
		// @220: invokestatic game.C_100215_ai.func_106009_z(java.lang.String)char[]
		// @223: invokestatic game.C_100215_ai.func_106007_z(char[])java.lang.String
		// @226: aastore
		// @227: dup
		// @228: bipush 34 (0x22)
		// @22A: ldc "V<Y`\u0015!yJ/Huy^4Ec*\r&KcyN!Ia8D'J14D3Wx6C3\n"
		// @22C: invokestatic game.C_100215_ai.func_106009_z(java.lang.String)char[]
		// @22F: invokestatic game.C_100215_ai.func_106007_z(char[])java.lang.String
		// @232: aastore
		// @233: dup
		// @234: bipush 35 (0x23)
		// @236: ldc "V<Y`\u0015$y^4Ec*\r&KcyN!Ia8D'J14D3Wx6C3\n"
		// @238: invokestatic game.C_100215_ai.func_106009_z(java.lang.String)char[]
		// @23B: invokestatic game.C_100215_ai.func_106007_z(char[])java.lang.String
		// @23E: aastore
		// @23F: dup
		// @240: bipush 36 (0x24)
		// @242: ldc "V<Y`\u0016!yJ/Huy^4Ec*\r&KcyN!Ia8D'J14D3Wx6C3\n"
		// @244: invokestatic game.C_100215_ai.func_106009_z(java.lang.String)char[]
		// @247: invokestatic game.C_100215_ai.func_106007_z(char[])java.lang.String
		// @24A: aastore
		// @24B: dup
		// @24C: bipush 37 (0x25)
		// @24E: ldc "U<^4V~ \r\u0002E68An"
		// @250: invokestatic game.C_100215_ai.func_106009_z(java.lang.String)char[]
		// @253: invokestatic game.C_100215_ai.func_106007_z(char[])java.lang.String
		// @256: aastore
		// @257: dup
		// @258: bipush 38 (0x26)
		// @25A: ldc "R6A,Ar-\rq\u00171-L'W1?B2\u00046\u0014B3P1;L4\u0004z0A,W6yD.\u0004C8Y%@1>L-AbyL4\u0004Y8A,Kf<\n%J?"
		// @25C: invokestatic game.C_100215_ai.func_106009_z(java.lang.String)char[]
		// @25F: invokestatic game.C_100215_ai.func_106007_z(char[])java.lang.String
		// @262: aastore
		// @263: putstatic java.lang.String[] game.C_100215_ai.field_106016_b
		// @266: ldc "T\u001di"
		// @268: invokestatic game.C_100215_ai.func_106009_z(java.lang.String)char[]
		// @26B: invokestatic game.C_100215_ai.func_106007_z(char[])java.lang.String
		// @26E: putstatic java.lang.String game.C_100215_ai.field_106015_e
		// @271: ldc "^)Y)K\u007f*"
		// @273: invokestatic game.C_100215_ai.func_106009_z(java.lang.String)char[]
		// @276: invokestatic game.C_100215_ai.func_106007_z(char[])java.lang.String
		// @279: putstatic java.lang.String game.C_100215_ai.field_106018_a
		// @27C: ldc "_\u0016\r\u0013h^\r"
		// @27E: invokestatic game.C_100215_ai.func_106009_z(java.lang.String)char[]
		// @281: invokestatic game.C_100215_ai.func_106007_z(char[])java.lang.String
		// @284: putstatic java.lang.String game.C_100215_ai.field_106020_j
		// @287: ldc "-|\u001d~\u0004y8^`H~*Y`G~7C%Ge0B.\n"
		// @289: invokestatic game.C_100215_ai.func_106009_z(java.lang.String)char[]
		// @28C: invokestatic game.C_100215_ai.func_106007_z(char[])java.lang.String
		// @28F: putstatic java.lang.String game.C_100215_ai.field_106013_g
		// @292: ldc "T\u001di"
		// @294: invokestatic game.C_100215_ai.func_106009_z(java.lang.String)char[]
		// @297: invokestatic game.C_100215_ai.func_106007_z(char[])java.lang.String
		// @29A: putstatic java.lang.String game.C_100215_ai.field_106014_d
		// @29D: iconst_1
		// @29E: putstatic int game.C_100215_ai.field_106021_k
		// @2A1: return
	}
	
	private static char[] func_106009_z(String arg0)
	{
		// @00: aload_0
		// @01: invokevirtual java.lang.String.toCharArray()char[]
		// @04: dup
		// @05: arraylength
		// @06: iconst_2
		// @07: if_icmpge @13
		// @0A: dup
		// @0B: iconst_0
		// @0C: dup2
		// @0D: caload
		// @0E: bipush 36 (0x24)
		// @10: ixor
		// @11: i2c
		// @12: castore
		// @13: areturn
	}
	
	private static String func_106007_z(char[] arg0)
	{
		// @00: aload_0
		// @01: dup
		// @02: arraylength
		// @03: swap
		// @04: iconst_0
		// @05: istore_1
		// @06: goto @4C
		// @09: dup
		// @0A: iload_1
		// @0B: dup2
		// @0C: caload
		// @0D: iload_1
		// @0E: iconst_5
		// @0F: irem
		// @10: tableswitch def: @44, for 0: @30, for 1: @35, for 2: @3A, for 3: @3F
		// @30: bipush 17 (0x11)
		// @32: goto @46
		// @35: bipush 89 (0x59)
		// @37: goto @46
		// @3A: bipush 45 (0x2D)
		// @3C: goto @46
		// @3F: bipush 64 (0x40)
		// @41: goto @46
		// @44: bipush 36 (0x24)
		// @46: ixor
		// @47: i2c
		// @48: castore
		// @49: iinc #1 +1
		// @4C: swap
		// @4D: dup_x1
		// @4E: iload_1
		// @4F: if_icmpgt @09
		// @52: new java.lang.String
		// @55: dup_x1
		// @56: swap
		// @57: invokespecial java.lang.String.<init>(char[])void
		// @5A: invokevirtual java.lang.String.intern()java.lang.String
		// @5D: areturn
	}
}
