package game;

final class C_100245_pf
{
	static String field_106385_g;
	static String field_106390_a;
	static String field_106391_j;
	static String field_106394_h;
	static int field_106389_c;
	static String field_106393_k;
	static C_100302_ka field_106388_b;
	static String field_106387_e;
	static String[] field_106384_f;
	static boolean[][] field_106386_d;
	static int field_106395_i;
	private static final String field_106392_z;
	
	public static void func_106381_a(int arg0)
	{
		// @00: aconst_null
		// @01: putstatic java.lang.String game.C_100245_pf.field_106393_k
		// @04: aconst_null
		// @05: putstatic java.lang.String game.C_100245_pf.field_106385_g
		// @08: aconst_null
		// @09: putstatic java.lang.String game.C_100245_pf.field_106394_h
		// @0C: aconst_null
		// @0D: putstatic java.lang.String game.C_100245_pf.field_106387_e
		// @10: aconst_null
		// @11: putstatic game.C_100302_ka game.C_100245_pf.field_106388_b
		// @14: aconst_null
		// @15: putstatic java.lang.String[] game.C_100245_pf.field_106384_f
		// @18: iload_0
		// @19: bipush 88 (0x58)
		// @1B: if_icmpgt @27
		// @1E: bipush 108 (0x6C)
		// @20: putstatic int game.C_100245_pf.field_106395_i
		// @23: goto @27
		// @26: athrow
		// @27: aconst_null
		// @28: putstatic java.lang.String game.C_100245_pf.field_106390_a
		// @2B: aconst_null
		// @2C: putstatic java.lang.String game.C_100245_pf.field_106391_j
		// @2F: aconst_null
		// @30: checkcast boolean[][]
		// @33: putstatic boolean[][] game.C_100245_pf.field_106386_d
		// @36: goto @58
		// @39: astore_1
		// @3A: aload_1
		// @3B: new java.lang.StringBuilder
		// @3E: dup
		// @3F: invokespecial java.lang.StringBuilder.<init>()void
		// @42: getstatic java.lang.String game.C_100245_pf.field_106392_z
		// @45: invokevirtual java.lang.StringBuilder.append(java.lang.String)java.lang.StringBuilder
		// @48: iload_0
		// @49: invokevirtual java.lang.StringBuilder.append(int)java.lang.StringBuilder
		// @4C: bipush 41 (0x29)
		// @4E: invokevirtual java.lang.StringBuilder.append(char)java.lang.StringBuilder
		// @51: invokevirtual java.lang.StringBuilder.toString()java.lang.String
		// @54: invokestatic game.C_100181_cf.func_105695_a(java.lang.Throwable, java.lang.String)game.C_100170_cm
		// @57: athrow
		// @58: return
	}
	
	static
	{
		// @000: ldc "\u0012m+0\\"
		// @002: invokestatic game.C_100245_pf.func_106383_z(java.lang.String)char[]
		// @005: invokestatic game.C_100245_pf.func_106382_z(char[])java.lang.String
		// @008: putstatic java.lang.String game.C_100245_pf.field_106392_z
		// @00B: ldc ";dp\u0003T\u0005jh\u0014"
		// @00D: invokestatic game.C_100245_pf.func_106383_z(java.lang.String)char[]
		// @010: invokestatic game.C_100245_pf.func_106382_z(char[])java.lang.String
		// @013: putstatic java.lang.String game.C_100245_pf.field_106385_g
		// @016: ldc "-{`\u001fT\u000be%\u0001\u001b\u0012~uQ\u0003\u000bea\u001e\u0003"
		// @018: invokestatic game.C_100245_pf.func_106383_z(java.lang.String)char[]
		// @01B: invokestatic game.C_100245_pf.func_106382_z(char[])java.lang.String
		// @01E: putstatic java.lang.String game.C_100245_pf.field_106394_h
		// @021: ldc "2yl\u0007\u0015\u0016n"
		// @023: invokestatic game.C_100245_pf.func_106383_z(java.lang.String)char[]
		// @026: invokestatic game.C_100245_pf.func_106382_z(char[])java.lang.String
		// @029: putstatic java.lang.String game.C_100245_pf.field_106393_k
		// @02C: ldc " jf\u001a"
		// @02E: invokestatic game.C_100245_pf.func_106383_z(java.lang.String)char[]
		// @031: invokestatic game.C_100245_pf.func_106382_z(char[])java.lang.String
		// @034: putstatic java.lang.String game.C_100245_pf.field_106390_a
		// @037: bipush 20 (0x14)
		// @039: anewarray java.lang.String
		// @03C: dup
		// @03D: iconst_0
		// @03E: ldc "!gj\u0002\u0011Bjv\u0002\u0015\u0017gqQ\u0013\u0017ev"
		// @040: invokestatic game.C_100245_pf.func_106383_z(java.lang.String)char[]
		// @043: invokestatic game.C_100245_pf.func_106382_z(char[])java.lang.String
		// @046: aastore
		// @047: dup
		// @048: iconst_1
		// @049: ldc "$gd\u001aT\u0001jk\u001f\u001b\u000cx"
		// @04B: invokestatic game.C_100245_pf.func_106383_z(java.lang.String)char[]
		// @04E: invokestatic game.C_100245_pf.func_106382_z(char[])java.lang.String
		// @051: aastore
		// @052: dup
		// @053: iconst_2
		// @054: ldc "'su\u001d\u001b\u0011bs\u0014T\u0001jk\u001f\u001b\u000cx"
		// @056: invokestatic game.C_100245_pf.func_106383_z(java.lang.String)char[]
		// @059: invokestatic game.C_100245_pf.func_106382_z(char[])java.lang.String
		// @05C: aastore
		// @05D: dup
		// @05E: iconst_3
		// @05F: ldc "0bc\u001d\u0011\u0006+f\u0010\u001a\u000cdk\u0002"
		// @061: invokestatic game.C_100245_pf.func_106383_z(java.lang.String)char[]
		// @064: invokestatic game.C_100245_pf.func_106382_z(char[])java.lang.String
		// @067: aastore
		// @068: dup
		// @069: iconst_4
		// @06A: ldc "#yq\u0018\u0018\u000enw\u0008"
		// @06C: invokestatic game.C_100245_pf.func_106383_z(java.lang.String)char[]
		// @06F: invokestatic game.C_100245_pf.func_106382_z(char[])java.lang.String
		// @072: aastore
		// @073: dup
		// @074: iconst_5
		// @075: ldc " dh\u0013\u0007"
		// @077: invokestatic game.C_100245_pf.func_106383_z(java.lang.String)char[]
		// @07A: invokestatic game.C_100245_pf.func_106382_z(char[])java.lang.String
		// @07D: aastore
		// @07E: dup
		// @07F: bipush 6 (0x06)
		// @081: ldc "'e`\u0003\u0013\u000bx`\u0015T\tbk\u0014\u0000\u000bh%\u0006\u0011\u0003{j\u001f\u0007"
		// @083: invokestatic game.C_100245_pf.func_106383_z(java.lang.String)char[]
		// @086: invokestatic game.C_100245_pf.func_106382_z(char[])java.lang.String
		// @089: aastore
		// @08A: dup
		// @08B: bipush 7 (0x07)
		// @08D: ldc ".jv\u0014\u0006B|`\u0010\u0004\rev"
		// @08F: invokestatic game.C_100245_pf.func_106383_z(java.lang.String)char[]
		// @092: invokestatic game.C_100245_pf.func_106382_z(char[])java.lang.String
		// @095: aastore
		// @096: dup
		// @097: bipush 8 (0x08)
		// @099: ldc "1~u\u0014\u0006Bgd\u0002\u0011\u0010+r\u0014\u0015\u0012dk\u0002"
		// @09B: invokestatic game.C_100245_pf.func_106383_z(java.lang.String)char[]
		// @09E: invokestatic game.C_100245_pf.func_106382_z(char[])java.lang.String
		// @0A1: aastore
		// @0A2: dup
		// @0A3: bipush 9 (0x09)
		// @0A5: ldc "2gd\u0002\u0019\u0003+r\u0014\u0015\u0012dk\u0002"
		// @0A7: invokestatic game.C_100245_pf.func_106383_z(java.lang.String)char[]
		// @0AA: invokestatic game.C_100245_pf.func_106382_z(char[])java.lang.String
		// @0AD: aastore
		// @0AE: dup
		// @0AF: bipush 10 (0x0A)
		// @0B1: ldc "'FUQ\u0003\u0007ju\u001e\u001a\u0011"
		// @0B3: invokestatic game.C_100245_pf.func_106383_z(java.lang.String)char[]
		// @0B6: invokestatic game.C_100245_pf.func_106382_z(char[])java.lang.String
		// @0B9: aastore
		// @0BA: dup
		// @0BB: bipush 11 (0x0B)
		// @0BD: ldc "0ju\u0018\u0011\u0010+h\u0018\u0007\u0011bi\u0014\u0007"
		// @0BF: invokestatic game.C_100245_pf.func_106383_z(java.lang.String)char[]
		// @0C2: invokestatic game.C_100245_pf.func_106382_z(char[])java.lang.String
		// @0C5: aastore
		// @0C6: dup
		// @0C7: bipush 12 (0x0C)
		// @0C9: ldc "#bwQ\u0010\u0007jq\u0019T\u000fbv\u0002\u001d\u000env"
		// @0CB: invokestatic game.C_100245_pf.func_106383_z(java.lang.String)char[]
		// @0CE: invokestatic game.C_100245_pf.func_106382_z(char[])java.lang.String
		// @0D1: aastore
		// @0D2: dup
		// @0D3: bipush 13 (0x0D)
		// @0D5: ldc "2b`\u0003\u0017\u0007y%\u0003\u001b\u0001``\u0005\u0007"
		// @0D7: invokestatic game.C_100245_pf.func_106383_z(java.lang.String)char[]
		// @0DA: invokestatic game.C_100245_pf.func_106382_z(char[])java.lang.String
		// @0DD: aastore
		// @0DE: dup
		// @0DF: bipush 14 (0x0E)
		// @0E1: ldc "'FUQ\u0006\rhn\u0014\u0000\u0011"
		// @0E3: invokestatic game.C_100245_pf.func_106383_z(java.lang.String)char[]
		// @0E6: invokestatic game.C_100245_pf.func_106382_z(char[])java.lang.String
		// @0E9: aastore
		// @0EA: dup
		// @0EB: bipush 15 (0x0F)
		// @0ED: ldc "#bw\u0013\u0001\u0010xqQ\u0006\rhn\u0014\u0000\u0011"
		// @0EF: invokestatic game.C_100245_pf.func_106383_z(java.lang.String)char[]
		// @0F2: invokestatic game.C_100245_pf.func_106382_z(char[])java.lang.String
		// @0F5: aastore
		// @0F6: dup
		// @0F7: bipush 16 (0x10)
		// @0F9: ldc "/~i\u0005\u001d\u0010df\u001a\u0011\u0016x"
		// @0FB: invokestatic game.C_100245_pf.func_106383_z(java.lang.String)char[]
		// @0FE: invokestatic game.C_100245_pf.func_106382_z(char[])java.lang.String
		// @101: aastore
		// @102: dup
		// @103: bipush 17 (0x11)
		// @105: ldc "*nd\u0007\rByj\u0012\u001f\u0007\u007fv"
		// @107: invokestatic game.C_100245_pf.func_106383_z(java.lang.String)char[]
		// @10A: invokestatic game.C_100245_pf.func_106382_z(char[])java.lang.String
		// @10D: aastore
		// @10E: dup
		// @10F: bipush 18 (0x12)
		// @111: ldc "&nv\u0005\u0006\u0017hq\u001e\u0006Byj\u0012\u001f\u0007\u007fv"
		// @113: invokestatic game.C_100245_pf.func_106383_z(java.lang.String)char[]
		// @116: invokestatic game.C_100245_pf.func_106382_z(char[])java.lang.String
		// @119: aastore
		// @11A: dup
		// @11B: bipush 19 (0x13)
		// @11D: ldc "#\u007fj\u001c\u001d\u0001x"
		// @11F: invokestatic game.C_100245_pf.func_106383_z(java.lang.String)char[]
		// @122: invokestatic game.C_100245_pf.func_106382_z(char[])java.lang.String
		// @125: aastore
		// @126: putstatic java.lang.String[] game.C_100245_pf.field_106384_f
		// @129: ldc "^.4OT\u0015jvQ\u0017\u0003~b\u0019\u0000BbkQHG;;V\u0007Bhj\u0003\u0011Bhj\u001f\u0000\u0003bk\u001c\u0011\u000c\u007f%\u0014\u000c\u0012gj\u0002\u001d\re"
		// @12B: invokestatic game.C_100245_pf.func_106383_z(java.lang.String)char[]
		// @12E: invokestatic game.C_100245_pf.func_106382_z(char[])java.lang.String
		// @131: putstatic java.lang.String game.C_100245_pf.field_106391_j
		// @134: return
	}
	
	private static char[] func_106383_z(String arg0)
	{
		// @00: aload_0
		// @01: invokevirtual java.lang.String.toCharArray()char[]
		// @04: dup
		// @05: arraylength
		// @06: iconst_2
		// @07: if_icmpge @13
		// @0A: dup
		// @0B: iconst_0
		// @0C: dup2
		// @0D: caload
		// @0E: bipush 116 (0x74)
		// @10: ixor
		// @11: i2c
		// @12: castore
		// @13: areturn
	}
	
	private static String func_106382_z(char[] arg0)
	{
		// @00: aload_0
		// @01: dup
		// @02: arraylength
		// @03: swap
		// @04: iconst_0
		// @05: istore_1
		// @06: goto @4B
		// @09: dup
		// @0A: iload_1
		// @0B: dup2
		// @0C: caload
		// @0D: iload_1
		// @0E: iconst_5
		// @0F: irem
		// @10: tableswitch def: @43, for 0: @30, for 1: @35, for 2: @3A, for 3: @3E
		// @30: bipush 98 (0x62)
		// @32: goto @45
		// @35: bipush 11 (0x0B)
		// @37: goto @45
		// @3A: iconst_5
		// @3B: goto @45
		// @3E: bipush 113 (0x71)
		// @40: goto @45
		// @43: bipush 116 (0x74)
		// @45: ixor
		// @46: i2c
		// @47: castore
		// @48: iinc #1 +1
		// @4B: swap
		// @4C: dup_x1
		// @4D: iload_1
		// @4E: if_icmpgt @09
		// @51: new java.lang.String
		// @54: dup_x1
		// @55: swap
		// @56: invokespecial java.lang.String.<init>(char[])void
		// @59: invokevirtual java.lang.String.intern()java.lang.String
		// @5C: areturn
	}
}
