package game;

final class C_100214_al extends C_100229_oe
{
	byte[] field_100885_l;
	int field_100887_k;
	int field_100883_n;
	int field_100884_o;
	boolean field_100886_m;
	
	C_100214_al(int arg0, byte[] arg1, int arg2, int arg3)
	{
		// @00: aload_0
		// @01: invokespecial game.C_100229_oe.<init>()void
		// @04: aload_0
		// @05: iload_1
		// @06: putfield int game.C_100214_al.field_100884_o
		// @09: aload_0
		// @0A: aload_2
		// @0B: putfield byte[] game.C_100214_al.field_100885_l
		// @0E: aload_0
		// @0F: iload_3
		// @10: putfield int game.C_100214_al.field_100887_k
		// @13: aload_0
		// @14: iload #4
		// @16: putfield int game.C_100214_al.field_100883_n
		// @19: return
	}
	
	C_100214_al(int arg0, byte[] arg1, int arg2, int arg3, boolean arg4)
	{
		// @00: aload_0
		// @01: invokespecial game.C_100229_oe.<init>()void
		// @04: aload_0
		// @05: iload_1
		// @06: putfield int game.C_100214_al.field_100884_o
		// @09: aload_0
		// @0A: aload_2
		// @0B: putfield byte[] game.C_100214_al.field_100885_l
		// @0E: aload_0
		// @0F: iload_3
		// @10: putfield int game.C_100214_al.field_100887_k
		// @13: aload_0
		// @14: iload #4
		// @16: putfield int game.C_100214_al.field_100883_n
		// @19: aload_0
		// @1A: iload #5
		// @1C: putfield boolean game.C_100214_al.field_100886_m
		// @1F: return
	}
}
