package game;

import java.lang.reflect.Constructor;

final class C_100250_pl
{
	static C_100013_fn field_106433_f;
	static long field_106434_d;
	static C_100302_ka field_106436_b;
	String[] field_106435_e;
	static Constructor field_106437_c;
	static C_100302_ka field_106438_a;
	private static final String[] field_106439_z;
	
	static final void func_106432_a(boolean arg0)
	{
		// @00: aconst_null
		// @01: getstatic game.C_100282_nh game.C_100027_hc.field_102598_S
		// @04: if_acmpne @0B
		// @07: goto @13
		// @0A: athrow
		// @0B: getstatic game.C_100282_nh game.C_100027_hc.field_102598_S
		// @0E: bipush -120 (0x88)
		// @10: invokevirtual game.C_100282_nh.func_102701_r(int)void
		// @13: new game.C_100128_ca
		// @16: dup
		// @17: invokespecial game.C_100128_ca.<init>()void
		// @1A: putstatic game.C_100128_ca game.C_100280_nf.field_101172_t
		// @1D: getstatic game.C_100209_qb game.C_100318_hj.field_107201_j
		// @20: getstatic game.C_100128_ca game.C_100280_nf.field_101172_t
		// @23: bipush 75 (0x4B)
		// @25: invokevirtual game.C_100209_qb.func_102660_a(game.C_100336_im, byte)void
		// @28: iload_0
		// @29: ifeq @35
		// @2C: bipush -61 (0xC3)
		// @2E: invokestatic game.C_100250_pl.func_106429_a(int)void
		// @31: goto @35
		// @34: athrow
		// @35: goto @59
		// @38: astore_1
		// @39: aload_1
		// @3A: new java.lang.StringBuilder
		// @3D: dup
		// @3E: invokespecial java.lang.StringBuilder.<init>()void
		// @41: getstatic java.lang.String[] game.C_100250_pl.field_106439_z
		// @44: iconst_1
		// @45: aaload
		// @46: invokevirtual java.lang.StringBuilder.append(java.lang.String)java.lang.StringBuilder
		// @49: iload_0
		// @4A: invokevirtual java.lang.StringBuilder.append(boolean)java.lang.StringBuilder
		// @4D: bipush 41 (0x29)
		// @4F: invokevirtual java.lang.StringBuilder.append(char)java.lang.StringBuilder
		// @52: invokevirtual java.lang.StringBuilder.toString()java.lang.String
		// @55: invokestatic game.C_100181_cf.func_105695_a(java.lang.Throwable, java.lang.String)game.C_100170_cm
		// @58: athrow
		// @59: return
	}
	
	public static void func_106429_a(int arg0)
	{
		// @00: aconst_null
		// @01: putstatic java.lang.reflect.Constructor game.C_100250_pl.field_106437_c
		// @04: aconst_null
		// @05: putstatic game.C_100013_fn game.C_100250_pl.field_106433_f
		// @08: iload_0
		// @09: iconst_2
		// @0A: if_icmpeq @18
		// @0D: aconst_null
		// @0E: checkcast game.C_100302_ka
		// @11: putstatic game.C_100302_ka game.C_100250_pl.field_106436_b
		// @14: goto @18
		// @17: athrow
		// @18: aconst_null
		// @19: putstatic game.C_100302_ka game.C_100250_pl.field_106436_b
		// @1C: aconst_null
		// @1D: putstatic game.C_100302_ka game.C_100250_pl.field_106438_a
		// @20: goto @44
		// @23: astore_1
		// @24: aload_1
		// @25: new java.lang.StringBuilder
		// @28: dup
		// @29: invokespecial java.lang.StringBuilder.<init>()void
		// @2C: getstatic java.lang.String[] game.C_100250_pl.field_106439_z
		// @2F: iconst_0
		// @30: aaload
		// @31: invokevirtual java.lang.StringBuilder.append(java.lang.String)java.lang.StringBuilder
		// @34: iload_0
		// @35: invokevirtual java.lang.StringBuilder.append(int)java.lang.StringBuilder
		// @38: bipush 41 (0x29)
		// @3A: invokevirtual java.lang.StringBuilder.append(char)java.lang.StringBuilder
		// @3D: invokevirtual java.lang.StringBuilder.toString()java.lang.String
		// @40: invokestatic game.C_100181_cf.func_105695_a(java.lang.Throwable, java.lang.String)game.C_100170_cm
		// @43: athrow
		// @44: return
	}
	
	private C_100250_pl() throws Throwable
	{
		// @00: aload_0
		// @01: invokespecial java.lang.Object.<init>()void
		// @04: new java.lang.Error
		// @07: dup
		// @08: invokespecial java.lang.Error.<init>()void
		// @0B: athrow
		// @0C: astore_1
		// @0D: aload_1
		// @0E: getstatic java.lang.String[] game.C_100250_pl.field_106439_z
		// @11: iconst_2
		// @12: aaload
		// @13: invokestatic game.C_100181_cf.func_105695_a(java.lang.Throwable, java.lang.String)game.C_100170_cm
		// @16: athrow
	}
	
	static
	{
		// @00: iconst_3
		// @01: anewarray java.lang.String
		// @04: dup
		// @05: iconst_0
		// @06: ldc "dRXlE"
		// @08: invokestatic game.C_100250_pl.func_106431_z(java.lang.String)char[]
		// @0B: invokestatic game.C_100250_pl.func_106430_z(char[])java.lang.String
		// @0E: aastore
		// @0F: dup
		// @10: iconst_1
		// @11: ldc "dRXoE"
		// @13: invokestatic game.C_100250_pl.func_106431_z(java.lang.String)char[]
		// @16: invokestatic game.C_100250_pl.func_106430_z(char[])java.lang.String
		// @19: aastore
		// @1A: dup
		// @1B: iconst_2
		// @1C: ldc "dRX\u0011\u0004zW\u0002\u0013E="
		// @1E: invokestatic game.C_100250_pl.func_106431_z(java.lang.String)char[]
		// @21: invokestatic game.C_100250_pl.func_106430_z(char[])java.lang.String
		// @24: aastore
		// @25: putstatic java.lang.String[] game.C_100250_pl.field_106439_z
		// @28: new game.C_100013_fn
		// @2B: dup
		// @2C: iconst_2
		// @2D: invokespecial game.C_100013_fn.<init>(int)void
		// @30: putstatic game.C_100013_fn game.C_100250_pl.field_106433_f
		// @33: return
	}
	
	private static char[] func_106431_z(String arg0)
	{
		// @00: aload_0
		// @01: invokevirtual java.lang.String.toCharArray()char[]
		// @04: dup
		// @05: arraylength
		// @06: iconst_2
		// @07: if_icmpge @13
		// @0A: dup
		// @0B: iconst_0
		// @0C: dup2
		// @0D: caload
		// @0E: bipush 109 (0x6D)
		// @10: ixor
		// @11: i2c
		// @12: castore
		// @13: areturn
	}
	
	private static String func_106430_z(char[] arg0)
	{
		// @00: aload_0
		// @01: dup
		// @02: arraylength
		// @03: swap
		// @04: iconst_0
		// @05: istore_1
		// @06: goto @4C
		// @09: dup
		// @0A: iload_1
		// @0B: dup2
		// @0C: caload
		// @0D: iload_1
		// @0E: iconst_5
		// @0F: irem
		// @10: tableswitch def: @44, for 0: @30, for 1: @35, for 2: @3A, for 3: @3F
		// @30: bipush 20 (0x14)
		// @32: goto @46
		// @35: bipush 62 (0x3E)
		// @37: goto @46
		// @3A: bipush 118 (0x76)
		// @3C: goto @46
		// @3F: bipush 45 (0x2D)
		// @41: goto @46
		// @44: bipush 109 (0x6D)
		// @46: ixor
		// @47: i2c
		// @48: castore
		// @49: iinc #1 +1
		// @4C: swap
		// @4D: dup_x1
		// @4E: iload_1
		// @4F: if_icmpgt @09
		// @52: new java.lang.String
		// @55: dup_x1
		// @56: swap
		// @57: invokespecial java.lang.String.<init>(char[])void
		// @5A: invokevirtual java.lang.String.intern()java.lang.String
		// @5D: areturn
	}
}
