package game;

final class C_100332_ii
{
	static String field_107320_h;
	static C_100037_wb[] field_107311_b;
	int field_107310_e;
	String field_107308_g;
	static String field_107314_n;
	static String field_107312_c;
	static String[] field_107315_o;
	String field_107318_j;
	static boolean field_107321_i;
	C_100098_h field_107316_l;
	static String field_107309_d;
	static int[][] field_107319_k;
	static String field_107307_f;
	static int[] field_107313_a;
	String field_107317_m;
	private static final String[] field_107322_z;
	
	static final void func_107300_a(int arg0, int arg1, int arg2, int arg3)
	{
		// @00: iload_0
		// @01: putstatic int game.C_100277_nc.field_106728_o
		// @04: iload_1
		// @05: bipush -2 (0xFE)
		// @07: if_icmpeq @15
		// @0A: aconst_null
		// @0B: checkcast java.lang.String
		// @0E: putstatic java.lang.String game.C_100332_ii.field_107309_d
		// @11: goto @15
		// @14: athrow
		// @15: iload_2
		// @16: putstatic int game.C_100137_bn.field_105037_a
		// @19: iload_3
		// @1A: putstatic int game.C_100050_vg.field_100636_r
		// @1D: goto @5E
		// @20: astore #4
		// @22: aload #4
		// @24: new java.lang.StringBuilder
		// @27: dup
		// @28: invokespecial java.lang.StringBuilder.<init>()void
		// @2B: getstatic java.lang.String[] game.C_100332_ii.field_107322_z
		// @2E: iconst_5
		// @2F: aaload
		// @30: invokevirtual java.lang.StringBuilder.append(java.lang.String)java.lang.StringBuilder
		// @33: iload_0
		// @34: invokevirtual java.lang.StringBuilder.append(int)java.lang.StringBuilder
		// @37: bipush 44 (0x2C)
		// @39: invokevirtual java.lang.StringBuilder.append(char)java.lang.StringBuilder
		// @3C: iload_1
		// @3D: invokevirtual java.lang.StringBuilder.append(int)java.lang.StringBuilder
		// @40: bipush 44 (0x2C)
		// @42: invokevirtual java.lang.StringBuilder.append(char)java.lang.StringBuilder
		// @45: iload_2
		// @46: invokevirtual java.lang.StringBuilder.append(int)java.lang.StringBuilder
		// @49: bipush 44 (0x2C)
		// @4B: invokevirtual java.lang.StringBuilder.append(char)java.lang.StringBuilder
		// @4E: iload_3
		// @4F: invokevirtual java.lang.StringBuilder.append(int)java.lang.StringBuilder
		// @52: bipush 41 (0x29)
		// @54: invokevirtual java.lang.StringBuilder.append(char)java.lang.StringBuilder
		// @57: invokevirtual java.lang.StringBuilder.toString()java.lang.String
		// @5A: invokestatic game.C_100181_cf.func_105695_a(java.lang.Throwable, java.lang.String)game.C_100170_cm
		// @5D: athrow
		// @5E: return
	}
	
	public static void func_107301_b(int arg0)
	{
		// @00: aconst_null
		// @01: putstatic java.lang.String game.C_100332_ii.field_107320_h
		// @04: aconst_null
		// @05: putstatic java.lang.String game.C_100332_ii.field_107314_n
		// @08: aconst_null
		// @09: checkcast int[][]
		// @0C: putstatic int[][] game.C_100332_ii.field_107319_k
		// @0F: iload_0
		// @10: bipush -3 (0xFD)
		// @12: if_icmple @16
		// @15: return
		// @16: aconst_null
		// @17: putstatic java.lang.String game.C_100332_ii.field_107312_c
		// @1A: aconst_null
		// @1B: putstatic game.C_100037_wb[] game.C_100332_ii.field_107311_b
		// @1E: aconst_null
		// @1F: putstatic java.lang.String game.C_100332_ii.field_107309_d
		// @22: aconst_null
		// @23: putstatic java.lang.String game.C_100332_ii.field_107307_f
		// @26: aconst_null
		// @27: putstatic int[] game.C_100332_ii.field_107313_a
		// @2A: aconst_null
		// @2B: putstatic java.lang.String[] game.C_100332_ii.field_107315_o
		// @2E: goto @53
		// @31: astore_1
		// @32: aload_1
		// @33: new java.lang.StringBuilder
		// @36: dup
		// @37: invokespecial java.lang.StringBuilder.<init>()void
		// @3A: getstatic java.lang.String[] game.C_100332_ii.field_107322_z
		// @3D: bipush 6 (0x06)
		// @3F: aaload
		// @40: invokevirtual java.lang.StringBuilder.append(java.lang.String)java.lang.StringBuilder
		// @43: iload_0
		// @44: invokevirtual java.lang.StringBuilder.append(int)java.lang.StringBuilder
		// @47: bipush 41 (0x29)
		// @49: invokevirtual java.lang.StringBuilder.append(char)java.lang.StringBuilder
		// @4C: invokevirtual java.lang.StringBuilder.toString()java.lang.String
		// @4F: invokestatic game.C_100181_cf.func_105695_a(java.lang.Throwable, java.lang.String)game.C_100170_cm
		// @52: athrow
		// @53: return
	}
	
	static final void func_107302_a(int arg0)
	{
		// @00: getstatic int game.SteelSentinels.field_105275_O
		// @03: istore #4
		// @05: new game.C_100037_wb
		// @08: dup
		// @09: sipush 540 (0x021C)
		// @0C: sipush 140 (0x008C)
		// @0F: invokespecial game.C_100037_wb.<init>(int, int)void
		// @12: astore_1
		// @13: aload_1
		// @14: iload_0
		// @15: sipush -259 (0xFEFD)
		// @18: iadd
		// @19: invokestatic game.C_100138_bo.func_100398_a(game.C_100037_wb, int)void
		// @1C: invokestatic game.C_100070_dn.func_104363_a()void
		// @1F: invokestatic game.C_100196_rb.func_105792_b()void
		// @22: iconst_0
		// @23: putstatic int game.C_100015_wh.field_103783_e
		// @26: bipush 55 (0x37)
		// @28: invokestatic game.C_100315_la.func_107172_a(byte)void
		// @2B: iload_0
		// @2C: sipush 255 (0x00FF)
		// @2F: if_icmpeq @33
		// @32: return
		// @33: aload_1
		// @34: invokevirtual game.C_100037_wb.func_102381_e()game.C_100037_wb
		// @37: astore_2
		// @38: iconst_0
		// @39: istore_3
		// @3A: bipush -16 (0xF0)
		// @3C: iload_3
		// @3D: iconst_m1
		// @3E: ixor
		// @3F: if_icmpge @6A
		// @42: aload_2
		// @43: bipush -2 (0xFE)
		// @45: bipush -2 (0xFE)
		// @47: ldc 16777215 (0xffffff)
		// @49: invokevirtual game.C_100037_wb.func_102366_b(int, int, int)void
		// @4C: iconst_4
		// @4D: iconst_4
		// @4E: iconst_0
		// @4F: iconst_0
		// @50: sipush 540 (0x021C)
		// @53: sipush 140 (0x008C)
		// @56: invokestatic game.C_100196_rb.func_105790_d(int, int, int, int, int, int)void
		// @59: iinc #3 +1
		// @5C: iload #4
		// @5E: ifne @7B
		// @61: iload #4
		// @63: ifeq @3A
		// @66: goto @6A
		// @69: athrow
		// @6A: getstatic game.C_100037_wb game.C_100083_c.field_103170_S
		// @6D: invokevirtual game.C_100037_wb.func_102379_d()void
		// @70: aload_1
		// @71: iconst_0
		// @72: iconst_0
		// @73: invokevirtual game.C_100037_wb.func_102360_g(int, int)void
		// @76: bipush -77 (0xB3)
		// @78: invokestatic game.C_100200_ba.func_105842_a(byte)void
		// @7B: goto @9F
		// @7E: astore_1
		// @7F: aload_1
		// @80: new java.lang.StringBuilder
		// @83: dup
		// @84: invokespecial java.lang.StringBuilder.<init>()void
		// @87: getstatic java.lang.String[] game.C_100332_ii.field_107322_z
		// @8A: iconst_3
		// @8B: aaload
		// @8C: invokevirtual java.lang.StringBuilder.append(java.lang.String)java.lang.StringBuilder
		// @8F: iload_0
		// @90: invokevirtual java.lang.StringBuilder.append(int)java.lang.StringBuilder
		// @93: bipush 41 (0x29)
		// @95: invokevirtual java.lang.StringBuilder.append(char)java.lang.StringBuilder
		// @98: invokevirtual java.lang.StringBuilder.toString()java.lang.String
		// @9B: invokestatic game.C_100181_cf.func_105695_a(java.lang.Throwable, java.lang.String)game.C_100170_cm
		// @9E: athrow
		// @9F: return
	}
	
	static final void func_107306_a(int arg0, C_100240_oj arg1)
	{
		// @000: getstatic int game.SteelSentinels.field_105275_O
		// @003: istore #5
		// @005: iconst_0
		// @006: istore_2
		// @007: iload_2
		// @008: iconst_3
		// @009: if_icmpge @023
		// @00C: getstatic int[] game.C_100332_ii.field_107313_a
		// @00F: iload_2
		// @010: iconst_0
		// @011: iastore
		// @012: iinc #2 +1
		// @015: iload #5
		// @017: ifne @025
		// @01A: iload #5
		// @01C: ifeq @007
		// @01F: goto @023
		// @022: athrow
		// @023: iconst_0
		// @024: istore_2
		// @025: getstatic int game.C_100188_rj.field_105737_e
		// @028: iload_2
		// @029: if_icmple @064
		// @02C: getstatic game.C_100240_oj[] game.C_100006_fj.field_103617_g
		// @02F: iload_2
		// @030: aaload
		// @031: getfield int game.C_100240_oj.field_106317_a
		// @034: aload_1
		// @035: getfield int game.C_100240_oj.field_106317_a
		// @038: iload #5
		// @03A: ifne @076
		// @03D: goto @041
		// @040: athrow
		// @041: if_icmpeq @04B
		// @044: goto @048
		// @047: athrow
		// @048: goto @05C
		// @04B: getstatic int[] game.C_100332_ii.field_107313_a
		// @04E: getstatic game.C_100240_oj[] game.C_100006_fj.field_103617_g
		// @051: iload_2
		// @052: aaload
		// @053: iconst_m1
		// @054: invokevirtual game.C_100240_oj.func_106309_a(int)int
		// @057: dup2
		// @058: iaload
		// @059: iconst_1
		// @05A: iadd
		// @05B: iastore
		// @05C: iinc #2 +1
		// @05F: iload #5
		// @061: ifeq @025
		// @064: getstatic int[] game.C_100332_ii.field_107313_a
		// @067: aload_1
		// @068: iconst_m1
		// @069: invokevirtual game.C_100240_oj.func_106309_a(int)int
		// @06C: dup2
		// @06D: iaload
		// @06E: iconst_1
		// @06F: iadd
		// @070: iastore
		// @071: iconst_0
		// @072: istore_2
		// @073: iload_0
		// @074: bipush 44 (0x2C)
		// @076: if_icmpgt @07A
		// @079: return
		// @07A: iconst_0
		// @07B: istore_3
		// @07C: iload_3
		// @07D: iconst_m1
		// @07E: ixor
		// @07F: getstatic int game.C_100188_rj.field_105737_e
		// @082: iconst_m1
		// @083: ixor
		// @084: if_icmple @0E6
		// @087: getstatic game.C_100240_oj[] game.C_100006_fj.field_103617_g
		// @08A: iload_3
		// @08B: aaload
		// @08C: getfield int game.C_100240_oj.field_106317_a
		// @08F: iload #5
		// @091: ifne @0E7
		// @094: aload_1
		// @095: getfield int game.C_100240_oj.field_106317_a
		// @098: if_icmpne @0CD
		// @09B: goto @09F
		// @09E: athrow
		// @09F: getstatic game.C_100240_oj[] game.C_100006_fj.field_103617_g
		// @0A2: iload_3
		// @0A3: aaload
		// @0A4: iconst_m1
		// @0A5: invokevirtual game.C_100240_oj.func_106309_a(int)int
		// @0A8: istore #4
		// @0AA: getstatic int[] game.C_100332_ii.field_107313_a
		// @0AD: iload #4
		// @0AF: iaload
		// @0B0: iconst_m1
		// @0B1: ixor
		// @0B2: getstatic int game.C_100271_mj.field_103432_U
		// @0B5: iconst_m1
		// @0B6: ixor
		// @0B7: if_icmplt @0BE
		// @0BA: goto @0CD
		// @0BD: athrow
		// @0BE: getstatic int[] game.C_100332_ii.field_107313_a
		// @0C1: iload #4
		// @0C3: dup2
		// @0C4: iaload
		// @0C5: iconst_1
		// @0C6: isub
		// @0C7: iastore
		// @0C8: iload #5
		// @0CA: ifeq @0DE
		// @0CD: getstatic game.C_100240_oj[] game.C_100006_fj.field_103617_g
		// @0D0: iload_2
		// @0D1: iinc #2 +1
		// @0D4: getstatic game.C_100240_oj[] game.C_100006_fj.field_103617_g
		// @0D7: iload_3
		// @0D8: aaload
		// @0D9: aastore
		// @0DA: goto @0DE
		// @0DD: athrow
		// @0DE: iinc #3 +1
		// @0E1: iload #5
		// @0E3: ifeq @07C
		// @0E6: iload_2
		// @0E7: putstatic int game.C_100188_rj.field_105737_e
		// @0EA: getstatic game.C_100240_oj[] game.C_100006_fj.field_103617_g
		// @0ED: getstatic int game.C_100188_rj.field_105737_e
		// @0F0: dup
		// @0F1: iconst_1
		// @0F2: iadd
		// @0F3: putstatic int game.C_100188_rj.field_105737_e
		// @0F6: aload_1
		// @0F7: aastore
		// @0F8: goto @136
		// @0FB: astore_2
		// @0FC: aload_2
		// @0FD: new java.lang.StringBuilder
		// @100: dup
		// @101: invokespecial java.lang.StringBuilder.<init>()void
		// @104: getstatic java.lang.String[] game.C_100332_ii.field_107322_z
		// @107: iconst_0
		// @108: aaload
		// @109: invokevirtual java.lang.StringBuilder.append(java.lang.String)java.lang.StringBuilder
		// @10C: iload_0
		// @10D: invokevirtual java.lang.StringBuilder.append(int)java.lang.StringBuilder
		// @110: bipush 44 (0x2C)
		// @112: invokevirtual java.lang.StringBuilder.append(char)java.lang.StringBuilder
		// @115: aload_1
		// @116: ifnull @122
		// @119: getstatic java.lang.String[] game.C_100332_ii.field_107322_z
		// @11C: iconst_2
		// @11D: aaload
		// @11E: goto @127
		// @121: athrow
		// @122: getstatic java.lang.String[] game.C_100332_ii.field_107322_z
		// @125: iconst_1
		// @126: aaload
		// @127: invokevirtual java.lang.StringBuilder.append(java.lang.String)java.lang.StringBuilder
		// @12A: bipush 41 (0x29)
		// @12C: invokevirtual java.lang.StringBuilder.append(char)java.lang.StringBuilder
		// @12F: invokevirtual java.lang.StringBuilder.toString()java.lang.String
		// @132: invokestatic game.C_100181_cf.func_105695_a(java.lang.Throwable, java.lang.String)game.C_100170_cm
		// @135: athrow
		// @136: return
	}
	
	static final int func_107305_a(boolean arg0)
	{
		// @00: iload_0
		// @01: ifeq @0F
		// @04: aconst_null
		// @05: checkcast java.lang.String
		// @08: putstatic java.lang.String game.C_100332_ii.field_107307_f
		// @0B: goto @0F
		// @0E: athrow
		// @0F: getstatic int game.C_100057_dd.field_104256_e
		// @12: ireturn
		// @13: astore_1
		// @14: aload_1
		// @15: new java.lang.StringBuilder
		// @18: dup
		// @19: invokespecial java.lang.StringBuilder.<init>()void
		// @1C: getstatic java.lang.String[] game.C_100332_ii.field_107322_z
		// @1F: bipush 7 (0x07)
		// @21: aaload
		// @22: invokevirtual java.lang.StringBuilder.append(java.lang.String)java.lang.StringBuilder
		// @25: iload_0
		// @26: invokevirtual java.lang.StringBuilder.append(boolean)java.lang.StringBuilder
		// @29: bipush 41 (0x29)
		// @2B: invokevirtual java.lang.StringBuilder.append(char)java.lang.StringBuilder
		// @2E: invokevirtual java.lang.StringBuilder.toString()java.lang.String
		// @31: invokestatic game.C_100181_cf.func_105695_a(java.lang.Throwable, java.lang.String)game.C_100170_cm
		// @34: athrow
	}
	
	private C_100332_ii() throws Throwable
	{
		// @00: aload_0
		// @01: invokespecial java.lang.Object.<init>()void
		// @04: new java.lang.Error
		// @07: dup
		// @08: invokespecial java.lang.Error.<init>()void
		// @0B: athrow
		// @0C: astore_1
		// @0D: aload_1
		// @0E: getstatic java.lang.String[] game.C_100332_ii.field_107322_z
		// @11: iconst_4
		// @12: aaload
		// @13: invokestatic game.C_100181_cf.func_105695_a(java.lang.Throwable, java.lang.String)game.C_100170_cm
		// @16: athrow
	}
	
	static
	{
		// @00: bipush 8 (0x08)
		// @02: anewarray java.lang.String
		// @05: dup
		// @06: iconst_0
		// @07: ldc ":\u0017}qa"
		// @09: invokestatic game.C_100332_ii.func_107304_z(java.lang.String)char[]
		// @0C: invokestatic game.C_100332_ii.func_107303_z(char[])java.lang.String
		// @0F: aastore
		// @10: dup
		// @11: iconst_1
		// @12: ldc "=\u000b?_"
		// @14: invokestatic game.C_100332_ii.func_107304_z(java.lang.String)char[]
		// @17: invokestatic game.C_100332_ii.func_107303_z(char[])java.lang.String
		// @1A: aastore
		// @1B: dup
		// @1C: iconst_2
		// @1D: ldc "(P}\u001d4"
		// @1F: invokestatic game.C_100332_ii.func_107304_z(java.lang.String)char[]
		// @22: invokestatic game.C_100332_ii.func_107303_z(char[])java.lang.String
		// @25: aastore
		// @26: dup
		// @27: iconst_3
		// @28: ldc ":\u0017}wa"
		// @2A: invokestatic game.C_100332_ii.func_107304_z(java.lang.String)char[]
		// @2D: invokestatic game.C_100332_ii.func_107303_z(char[])java.lang.String
		// @30: aastore
		// @31: dup
		// @32: iconst_4
		// @33: ldc ":\u0017}\u000f =\u0017'\raz"
		// @35: invokestatic game.C_100332_ii.func_107304_z(java.lang.String)char[]
		// @38: invokestatic game.C_100332_ii.func_107303_z(char[])java.lang.String
		// @3B: aastore
		// @3C: dup
		// @3D: iconst_5
		// @3E: ldc ":\u0017}ra"
		// @40: invokestatic game.C_100332_ii.func_107304_z(java.lang.String)char[]
		// @43: invokestatic game.C_100332_ii.func_107303_z(char[])java.lang.String
		// @46: aastore
		// @47: dup
		// @48: bipush 6 (0x06)
		// @4A: ldc ":\u0017}pa"
		// @4C: invokestatic game.C_100332_ii.func_107304_z(java.lang.String)char[]
		// @4F: invokestatic game.C_100332_ii.func_107303_z(char[])java.lang.String
		// @52: aastore
		// @53: dup
		// @54: bipush 7 (0x07)
		// @56: ldc ":\u0017}va"
		// @58: invokestatic game.C_100332_ii.func_107304_z(java.lang.String)char[]
		// @5B: invokestatic game.C_100332_ii.func_107303_z(char[])java.lang.String
		// @5E: aastore
		// @5F: putstatic java.lang.String[] game.C_100332_ii.field_107322_z
		// @62: ldc "C"
		// @64: putstatic java.lang.String game.C_100332_ii.field_107320_h
		// @67: sipush 255 (0x00FF)
		// @6A: anewarray java.lang.String
		// @6D: putstatic java.lang.String[] game.C_100332_ii.field_107315_o
		// @70: iconst_0
		// @71: putstatic boolean game.C_100332_ii.field_107321_i
		// @74: ldc "\u0003\u00122J,!\r"
		// @76: invokestatic game.C_100332_ii.func_107304_z(java.lang.String)char[]
		// @79: invokestatic game.C_100332_ii.func_107303_z(char[])java.lang.String
		// @7C: putstatic java.lang.String game.C_100332_ii.field_107312_c
		// @7F: ldc "\u007f^2]-s\u000e?F$>\u001b'V-s\u0012:X,s\u001fs@=2\u0012?V-s\u001c!Z*8"
		// @81: invokestatic game.C_100332_ii.func_107304_z(java.lang.String)char[]
		// @84: invokestatic game.C_100332_ii.func_107303_z(char[])java.lang.String
		// @87: putstatic java.lang.String game.C_100332_ii.field_107307_f
		// @8A: ldc "\u0000\u001b!E 0\u001bsF'2\u00082Z%2\u001c?V"
		// @8C: invokestatic game.C_100332_ii.func_107304_z(java.lang.String)char[]
		// @8F: invokestatic game.C_100332_ii.func_107303_z(char[])java.lang.String
		// @92: putstatic java.lang.String game.C_100332_ii.field_107314_n
		// @95: ldc "\u001d\u001f>V"
		// @97: invokestatic game.C_100332_ii.func_107304_z(java.lang.String)char[]
		// @9A: invokestatic game.C_100332_ii.func_107303_z(char[])java.lang.String
		// @9D: putstatic java.lang.String game.C_100332_ii.field_107309_d
		// @A0: return
	}
	
	private static char[] func_107304_z(String arg0)
	{
		// @00: aload_0
		// @01: invokevirtual java.lang.String.toCharArray()char[]
		// @04: dup
		// @05: arraylength
		// @06: iconst_2
		// @07: if_icmpge @13
		// @0A: dup
		// @0B: iconst_0
		// @0C: dup2
		// @0D: caload
		// @0E: bipush 73 (0x49)
		// @10: ixor
		// @11: i2c
		// @12: castore
		// @13: areturn
	}
	
	private static String func_107303_z(char[] arg0)
	{
		// @00: aload_0
		// @01: dup
		// @02: arraylength
		// @03: swap
		// @04: iconst_0
		// @05: istore_1
		// @06: goto @4C
		// @09: dup
		// @0A: iload_1
		// @0B: dup2
		// @0C: caload
		// @0D: iload_1
		// @0E: iconst_5
		// @0F: irem
		// @10: tableswitch def: @44, for 0: @30, for 1: @35, for 2: @3A, for 3: @3F
		// @30: bipush 83 (0x53)
		// @32: goto @46
		// @35: bipush 126 (0x7E)
		// @37: goto @46
		// @3A: bipush 83 (0x53)
		// @3C: goto @46
		// @3F: bipush 51 (0x33)
		// @41: goto @46
		// @44: bipush 73 (0x49)
		// @46: ixor
		// @47: i2c
		// @48: castore
		// @49: iinc #1 +1
		// @4C: swap
		// @4D: dup_x1
		// @4E: iload_1
		// @4F: if_icmpgt @09
		// @52: new java.lang.String
		// @55: dup_x1
		// @56: swap
		// @57: invokespecial java.lang.String.<init>(char[])void
		// @5A: invokevirtual java.lang.String.intern()java.lang.String
		// @5D: areturn
	}
}
