package game;

final class C_100248_pb
{
	static String[] field_106424_d;
	static String field_106426_c;
	static int field_106425_b;
	String[] field_106427_a;
	private static final String[] field_106428_z;
	
	static final void func_106422_a(String arg0, byte arg1, String[] arg2, int arg3)
	{
		// @00: getstatic int game.SteelSentinels.field_105275_O
		// @03: istore #5
		// @05: iload_1
		// @06: bipush -16 (0xF0)
		// @08: if_icmple @16
		// @0B: aconst_null
		// @0C: checkcast java.lang.String
		// @0F: putstatic java.lang.String game.C_100248_pb.field_106426_c
		// @12: goto @16
		// @15: athrow
		// @16: getstatic game.C_100068_vc game.C_100213_ak.field_105993_g
		// @19: putstatic game.C_100068_vc game.C_100222_aa.field_106086_a
		// @1C: sipush 255 (0x00FF)
		// @1F: iload_3
		// @20: if_icmpeq @5D
		// @23: iload_3
		// @24: bipush 100 (0x64)
		// @26: if_icmplt @39
		// @29: goto @2D
		// @2C: athrow
		// @2D: iload_3
		// @2E: iconst_m1
		// @2F: ixor
		// @30: bipush -106 (0x96)
		// @32: if_icmpge @4B
		// @35: goto @39
		// @38: athrow
		// @39: aload_0
		// @3A: iconst_0
		// @3B: iload_3
		// @3C: invokestatic game.C_100111_el.func_104855_a(java.lang.String, boolean, int)game.C_100096_un
		// @3F: putstatic game.C_100096_un game.C_100236_on.field_100900_k
		// @42: iload #5
		// @44: ifeq @79
		// @47: goto @4B
		// @4A: athrow
		// @4B: bipush -25 (0xE7)
		// @4D: aload_2
		// @4E: invokestatic game.C_100320_hh.func_102907_a(int, java.lang.String[])game.C_100096_un
		// @51: putstatic game.C_100096_un game.C_100236_on.field_100900_k
		// @54: iload #5
		// @56: ifeq @79
		// @59: goto @5D
		// @5C: athrow
		// @5D: bipush -105 (0x97)
		// @5F: getstatic int game.C_100089_fa.field_103728_c
		// @62: iconst_m1
		// @63: ixor
		// @64: bipush -14 (0xF2)
		// @66: if_icmple @72
		// @69: goto @6D
		// @6C: athrow
		// @6D: iconst_1
		// @6E: goto @73
		// @71: athrow
		// @72: iconst_0
		// @73: invokestatic game.C_100217_ao.func_106032_a(byte, boolean)game.C_100096_un
		// @76: putstatic game.C_100096_un game.C_100236_on.field_100900_k
		// @79: goto @DC
		// @7C: astore #4
		// @7E: aload #4
		// @80: new java.lang.StringBuilder
		// @83: dup
		// @84: invokespecial java.lang.StringBuilder.<init>()void
		// @87: getstatic java.lang.String[] game.C_100248_pb.field_106428_z
		// @8A: iconst_0
		// @8B: aaload
		// @8C: invokevirtual java.lang.StringBuilder.append(java.lang.String)java.lang.StringBuilder
		// @8F: aload_0
		// @90: ifnull @9C
		// @93: getstatic java.lang.String[] game.C_100248_pb.field_106428_z
		// @96: iconst_2
		// @97: aaload
		// @98: goto @A1
		// @9B: athrow
		// @9C: getstatic java.lang.String[] game.C_100248_pb.field_106428_z
		// @9F: iconst_1
		// @A0: aaload
		// @A1: invokevirtual java.lang.StringBuilder.append(java.lang.String)java.lang.StringBuilder
		// @A4: bipush 44 (0x2C)
		// @A6: invokevirtual java.lang.StringBuilder.append(char)java.lang.StringBuilder
		// @A9: iload_1
		// @AA: invokevirtual java.lang.StringBuilder.append(int)java.lang.StringBuilder
		// @AD: bipush 44 (0x2C)
		// @AF: invokevirtual java.lang.StringBuilder.append(char)java.lang.StringBuilder
		// @B2: aload_2
		// @B3: ifnull @BF
		// @B6: getstatic java.lang.String[] game.C_100248_pb.field_106428_z
		// @B9: iconst_2
		// @BA: aaload
		// @BB: goto @C4
		// @BE: athrow
		// @BF: getstatic java.lang.String[] game.C_100248_pb.field_106428_z
		// @C2: iconst_1
		// @C3: aaload
		// @C4: invokevirtual java.lang.StringBuilder.append(java.lang.String)java.lang.StringBuilder
		// @C7: bipush 44 (0x2C)
		// @C9: invokevirtual java.lang.StringBuilder.append(char)java.lang.StringBuilder
		// @CC: iload_3
		// @CD: invokevirtual java.lang.StringBuilder.append(int)java.lang.StringBuilder
		// @D0: bipush 41 (0x29)
		// @D2: invokevirtual java.lang.StringBuilder.append(char)java.lang.StringBuilder
		// @D5: invokevirtual java.lang.StringBuilder.toString()java.lang.String
		// @D8: invokestatic game.C_100181_cf.func_105695_a(java.lang.Throwable, java.lang.String)game.C_100170_cm
		// @DB: athrow
		// @DC: return
	}
	
	public static void func_106419_a(int arg0)
	{
		// @00: iload_0
		// @01: ifeq @17
		// @04: aconst_null
		// @05: checkcast java.lang.String
		// @08: bipush 105 (0x69)
		// @0A: aconst_null
		// @0B: checkcast java.lang.String[]
		// @0E: bipush 16 (0x10)
		// @10: invokestatic game.C_100248_pb.func_106422_a(java.lang.String, byte, java.lang.String[], int)void
		// @13: goto @17
		// @16: athrow
		// @17: aconst_null
		// @18: putstatic java.lang.String[] game.C_100248_pb.field_106424_d
		// @1B: aconst_null
		// @1C: putstatic java.lang.String game.C_100248_pb.field_106426_c
		// @1F: goto @43
		// @22: astore_1
		// @23: aload_1
		// @24: new java.lang.StringBuilder
		// @27: dup
		// @28: invokespecial java.lang.StringBuilder.<init>()void
		// @2B: getstatic java.lang.String[] game.C_100248_pb.field_106428_z
		// @2E: iconst_5
		// @2F: aaload
		// @30: invokevirtual java.lang.StringBuilder.append(java.lang.String)java.lang.StringBuilder
		// @33: iload_0
		// @34: invokevirtual java.lang.StringBuilder.append(int)java.lang.StringBuilder
		// @37: bipush 41 (0x29)
		// @39: invokevirtual java.lang.StringBuilder.append(char)java.lang.StringBuilder
		// @3C: invokevirtual java.lang.StringBuilder.toString()java.lang.String
		// @3F: invokestatic game.C_100181_cf.func_105695_a(java.lang.Throwable, java.lang.String)game.C_100170_cm
		// @42: athrow
		// @43: return
	}
	
	private C_100248_pb() throws Throwable
	{
		// @00: aload_0
		// @01: invokespecial java.lang.Object.<init>()void
		// @04: new java.lang.Error
		// @07: dup
		// @08: invokespecial java.lang.Error.<init>()void
		// @0B: athrow
		// @0C: astore_1
		// @0D: aload_1
		// @0E: getstatic java.lang.String[] game.C_100248_pb.field_106428_z
		// @11: iconst_4
		// @12: aaload
		// @13: invokestatic game.C_100181_cf.func_105695_a(java.lang.Throwable, java.lang.String)game.C_100170_cm
		// @16: athrow
	}
	
	static final String func_106423_a(int arg0, long arg1)
	{
		// @000: getstatic int game.SteelSentinels.field_105275_O
		// @003: istore #11
		// @005: ldc2_w -1
		// @008: lload_1
		// @009: ldc2_w -1
		// @00C: lxor
		// @00D: lcmp
		// @00E: ifle @021
		// @011: ldc2_w -6582952005840035282
		// @014: lload_1
		// @015: ldc2_w -1
		// @018: lxor
		// @019: lcmp
		// @01A: iflt @023
		// @01D: goto @021
		// @020: athrow
		// @021: aconst_null
		// @022: areturn
		// @023: lconst_0
		// @024: lload_1
		// @025: ldc2_w 37
		// @028: lrem
		// @029: lcmp
		// @02A: ifne @02F
		// @02D: aconst_null
		// @02E: areturn
		// @02F: iconst_0
		// @030: istore_3
		// @031: iload_0
		// @032: bipush -49 (0xCF)
		// @034: if_icmplt @04A
		// @037: aconst_null
		// @038: checkcast java.lang.String
		// @03B: bipush 116 (0x74)
		// @03D: aconst_null
		// @03E: checkcast java.lang.String[]
		// @041: bipush 9 (0x09)
		// @043: invokestatic game.C_100248_pb.func_106422_a(java.lang.String, byte, java.lang.String[], int)void
		// @046: goto @04A
		// @049: athrow
		// @04A: lload_1
		// @04B: lstore #4
		// @04D: lconst_0
		// @04E: lload #4
		// @050: lcmp
		// @051: ifeq @064
		// @054: iinc #3 +1
		// @057: lload #4
		// @059: ldc2_w 37
		// @05C: ldiv
		// @05D: lstore #4
		// @05F: iload #11
		// @061: ifeq @04D
		// @064: new java.lang.StringBuilder
		// @067: dup
		// @068: iload_3
		// @069: invokespecial java.lang.StringBuilder.<init>(int)void
		// @06C: astore #6
		// @06E: lload_1
		// @06F: ldc2_w -1
		// @072: lxor
		// @073: ldc2_w -1
		// @076: lcmp
		// @077: ifeq @0CF
		// @07A: lload_1
		// @07B: lstore #7
		// @07D: lload_1
		// @07E: ldc2_w 37
		// @081: ldiv
		// @082: lstore_1
		// @083: getstatic char[] game.C_100170_cm.field_105540_b
		// @086: lload_1
		// @087: ldc2_w 37
		// @08A: lmul
		// @08B: lneg
		// @08C: lload #7
		// @08E: ladd
		// @08F: l2i
		// @090: caload
		// @091: istore #9
		// @093: iload #11
		// @095: ifne @0E4
		// @098: iload #9
		// @09A: bipush 95 (0x5F)
		// @09C: if_icmpne @0C2
		// @09F: goto @0A3
		// @0A2: athrow
		// @0A3: iconst_m1
		// @0A4: aload #6
		// @0A6: invokevirtual java.lang.StringBuilder.length()int
		// @0A9: iadd
		// @0AA: istore #10
		// @0AC: aload #6
		// @0AE: iload #10
		// @0B0: aload #6
		// @0B2: iload #10
		// @0B4: invokevirtual java.lang.StringBuilder.charAt(int)char
		// @0B7: invokestatic java.lang.Character.toUpperCase(char)char
		// @0BA: invokevirtual java.lang.StringBuilder.setCharAt(int, char)void
		// @0BD: sipush 160 (0x00A0)
		// @0C0: istore #9
		// @0C2: aload #6
		// @0C4: iload #9
		// @0C6: invokevirtual java.lang.StringBuilder.append(char)java.lang.StringBuilder
		// @0C9: pop
		// @0CA: iload #11
		// @0CC: ifeq @06E
		// @0CF: aload #6
		// @0D1: invokevirtual java.lang.StringBuilder.reverse()java.lang.StringBuilder
		// @0D4: pop
		// @0D5: aload #6
		// @0D7: iconst_0
		// @0D8: aload #6
		// @0DA: iconst_0
		// @0DB: invokevirtual java.lang.StringBuilder.charAt(int)char
		// @0DE: invokestatic java.lang.Character.toUpperCase(char)char
		// @0E1: invokevirtual java.lang.StringBuilder.setCharAt(int, char)void
		// @0E4: aload #6
		// @0E6: invokevirtual java.lang.StringBuilder.toString()java.lang.String
		// @0E9: areturn
		// @0EA: astore_3
		// @0EB: aload_3
		// @0EC: new java.lang.StringBuilder
		// @0EF: dup
		// @0F0: invokespecial java.lang.StringBuilder.<init>()void
		// @0F3: getstatic java.lang.String[] game.C_100248_pb.field_106428_z
		// @0F6: iconst_3
		// @0F7: aaload
		// @0F8: invokevirtual java.lang.StringBuilder.append(java.lang.String)java.lang.StringBuilder
		// @0FB: iload_0
		// @0FC: invokevirtual java.lang.StringBuilder.append(int)java.lang.StringBuilder
		// @0FF: bipush 44 (0x2C)
		// @101: invokevirtual java.lang.StringBuilder.append(char)java.lang.StringBuilder
		// @104: lload_1
		// @105: invokevirtual java.lang.StringBuilder.append(long)java.lang.StringBuilder
		// @108: bipush 41 (0x29)
		// @10A: invokevirtual java.lang.StringBuilder.append(char)java.lang.StringBuilder
		// @10D: invokevirtual java.lang.StringBuilder.toString()java.lang.String
		// @110: invokestatic game.C_100181_cf.func_105695_a(java.lang.Throwable, java.lang.String)game.C_100170_cm
		// @113: athrow
	}
	
	static
	{
		// @00: bipush 6 (0x06)
		// @02: anewarray java.lang.String
		// @05: dup
		// @06: iconst_0
		// @07: ldc "\u00070E\u000c="
		// @09: invokestatic game.C_100248_pb.func_106421_z(java.lang.String)char[]
		// @0C: invokestatic game.C_100248_pb.func_106420_z(char[])java.lang.String
		// @0F: aastore
		// @10: dup
		// @11: iconst_1
		// @12: ldc "\u0019'\u0007!"
		// @14: invokestatic game.C_100248_pb.func_106421_z(java.lang.String)char[]
		// @17: invokestatic game.C_100248_pb.func_106420_z(char[])java.lang.String
		// @1A: aastore
		// @1B: dup
		// @1C: iconst_2
		// @1D: ldc "\u000c|Ech"
		// @1F: invokestatic game.C_100248_pb.func_106421_z(java.lang.String)char[]
		// @22: invokestatic game.C_100248_pb.func_106420_z(char[])java.lang.String
		// @25: aastore
		// @26: dup
		// @27: iconst_3
		// @28: ldc "\u00070E\u000e="
		// @2A: invokestatic game.C_100248_pb.func_106421_z(java.lang.String)char[]
		// @2D: invokestatic game.C_100248_pb.func_106420_z(char[])java.lang.String
		// @30: aastore
		// @31: dup
		// @32: iconst_4
		// @33: ldc "\u00070Eq|\u0019;\u001fs=^"
		// @35: invokestatic game.C_100248_pb.func_106421_z(java.lang.String)char[]
		// @38: invokestatic game.C_100248_pb.func_106420_z(char[])java.lang.String
		// @3B: aastore
		// @3C: dup
		// @3D: iconst_5
		// @3E: ldc "\u00070E\u000f="
		// @40: invokestatic game.C_100248_pb.func_106421_z(java.lang.String)char[]
		// @43: invokestatic game.C_100248_pb.func_106420_z(char[])java.lang.String
		// @46: aastore
		// @47: putstatic java.lang.String[] game.C_100248_pb.field_106428_z
		// @4A: iconst_3
		// @4B: anewarray java.lang.String
		// @4E: dup
		// @4F: iconst_0
		// @50: ldc "03\u0006(8\u0003;\u0006(5\u001a=\u000f("
		// @52: invokestatic game.C_100248_pb.func_106421_z(java.lang.String)char[]
		// @55: invokestatic game.C_100248_pb.func_106420_z(char[])java.lang.String
		// @58: aastore
		// @59: dup
		// @5A: iconst_1
		// @5B: ldc "#7\u0008%{\u0018>\u0004*lW>\u000e;p\u001b"
		// @5D: invokestatic game.C_100248_pb.func_106421_z(java.lang.String)char[]
		// @60: invokestatic game.C_100248_pb.func_106420_z(char[])java.lang.String
		// @63: aastore
		// @64: dup
		// @65: iconst_2
		// @66: ldc "03\u0006(5\u001a3\u001b"
		// @68: invokestatic game.C_100248_pb.func_106421_z(java.lang.String)char[]
		// @6B: invokestatic game.C_100248_pb.func_106420_z(char[])java.lang.String
		// @6E: aastore
		// @6F: putstatic java.lang.String[] game.C_100248_pb.field_106424_d
		// @72: ldc "Kw[s5\u001f3\u0018my\u00124\u001fma\u001f7K!z\u00150\u0012c"
		// @74: invokestatic game.C_100248_pb.func_106421_z(java.lang.String)char[]
		// @77: invokestatic game.C_100248_pb.func_106420_z(char[])java.lang.String
		// @7A: putstatic java.lang.String game.C_100248_pb.field_106426_c
		// @7D: return
	}
	
	private static char[] func_106421_z(String arg0)
	{
		// @00: aload_0
		// @01: invokevirtual java.lang.String.toCharArray()char[]
		// @04: dup
		// @05: arraylength
		// @06: iconst_2
		// @07: if_icmpge @13
		// @0A: dup
		// @0B: iconst_0
		// @0C: dup2
		// @0D: caload
		// @0E: bipush 21 (0x15)
		// @10: ixor
		// @11: i2c
		// @12: castore
		// @13: areturn
	}
	
	private static String func_106420_z(char[] arg0)
	{
		// @00: aload_0
		// @01: dup
		// @02: arraylength
		// @03: swap
		// @04: iconst_0
		// @05: istore_1
		// @06: goto @4C
		// @09: dup
		// @0A: iload_1
		// @0B: dup2
		// @0C: caload
		// @0D: iload_1
		// @0E: iconst_5
		// @0F: irem
		// @10: tableswitch def: @44, for 0: @30, for 1: @35, for 2: @3A, for 3: @3F
		// @30: bipush 119 (0x77)
		// @32: goto @46
		// @35: bipush 82 (0x52)
		// @37: goto @46
		// @3A: bipush 107 (0x6B)
		// @3C: goto @46
		// @3F: bipush 77 (0x4D)
		// @41: goto @46
		// @44: bipush 21 (0x15)
		// @46: ixor
		// @47: i2c
		// @48: castore
		// @49: iinc #1 +1
		// @4C: swap
		// @4D: dup_x1
		// @4E: iload_1
		// @4F: if_icmpgt @09
		// @52: new java.lang.String
		// @55: dup_x1
		// @56: swap
		// @57: invokespecial java.lang.String.<init>(char[])void
		// @5A: invokevirtual java.lang.String.intern()java.lang.String
		// @5D: areturn
	}
}
