package game;

final class C_100078_ul extends C_100309_lk implements C_100267_mf
{
	static C_100028_ha field_103281_jb;
	private C_100308_lh field_103287_mb;
	private int field_103282_ib;
	static C_100153_be[] field_103284_ob;
	static String field_103290_qb;
	static int field_103285_pb;
	static String field_103288_kb;
	static String field_103289_lb;
	static C_100100_i field_103283_nb;
	static int field_103291_rb;
	private static final String[] field_103286_sb;
	
	C_100078_ul(String arg0, C_100337_in arg1, int arg2)
	{
		// @0: aload_0
		// @1: aload_1
		// @2: aload_2
		// @3: iload_3
		// @4: invokespecial game.C_100309_lk.<init>(java.lang.String, game.C_100337_in, int)void
		// @7: return
	}
	
	public final C_100308_lh func_103100_a(boolean arg0)
	{
		// @00: iload_1
		// @01: iconst_1
		// @02: if_icmpeq @0D
		// @05: iconst_1
		// @06: invokestatic game.C_100078_ul.func_103276_f(boolean)void
		// @09: goto @0D
		// @0C: athrow
		// @0D: aload_0
		// @0E: getfield game.C_100308_lh game.C_100078_ul.field_103287_mb
		// @11: areturn
		// @12: astore_2
		// @13: aload_2
		// @14: new java.lang.StringBuilder
		// @17: dup
		// @18: invokespecial java.lang.StringBuilder.<init>()void
		// @1B: getstatic java.lang.String[] game.C_100078_ul.field_103286_sb
		// @1E: iconst_4
		// @1F: aaload
		// @20: invokevirtual java.lang.StringBuilder.append(java.lang.String)java.lang.StringBuilder
		// @23: iload_1
		// @24: invokevirtual java.lang.StringBuilder.append(boolean)java.lang.StringBuilder
		// @27: bipush 41 (0x29)
		// @29: invokevirtual java.lang.StringBuilder.append(char)java.lang.StringBuilder
		// @2C: invokevirtual java.lang.StringBuilder.toString()java.lang.String
		// @2F: invokestatic game.C_100181_cf.func_105695_a(java.lang.Throwable, java.lang.String)game.C_100170_cm
		// @32: athrow
	}
	
	final void func_103279_a(byte arg0, C_100308_lh arg1)
	{
		// @00: iload_1
		// @01: bipush -40 (0xD8)
		// @03: if_icmplt @10
		// @06: aload_0
		// @07: bipush 23 (0x17)
		// @09: invokevirtual game.C_100078_ul.func_103241_k(int)void
		// @0C: goto @10
		// @0F: athrow
		// @10: aload_0
		// @11: aload_2
		// @12: putfield game.C_100308_lh game.C_100078_ul.field_103287_mb
		// @15: goto @53
		// @18: astore_3
		// @19: aload_3
		// @1A: new java.lang.StringBuilder
		// @1D: dup
		// @1E: invokespecial java.lang.StringBuilder.<init>()void
		// @21: getstatic java.lang.String[] game.C_100078_ul.field_103286_sb
		// @24: iconst_1
		// @25: aaload
		// @26: invokevirtual java.lang.StringBuilder.append(java.lang.String)java.lang.StringBuilder
		// @29: iload_1
		// @2A: invokevirtual java.lang.StringBuilder.append(int)java.lang.StringBuilder
		// @2D: bipush 44 (0x2C)
		// @2F: invokevirtual java.lang.StringBuilder.append(char)java.lang.StringBuilder
		// @32: aload_2
		// @33: ifnull @3F
		// @36: getstatic java.lang.String[] game.C_100078_ul.field_103286_sb
		// @39: iconst_3
		// @3A: aaload
		// @3B: goto @44
		// @3E: athrow
		// @3F: getstatic java.lang.String[] game.C_100078_ul.field_103286_sb
		// @42: iconst_2
		// @43: aaload
		// @44: invokevirtual java.lang.StringBuilder.append(java.lang.String)java.lang.StringBuilder
		// @47: bipush 41 (0x29)
		// @49: invokevirtual java.lang.StringBuilder.append(char)java.lang.StringBuilder
		// @4C: invokevirtual java.lang.StringBuilder.toString()java.lang.String
		// @4F: invokestatic game.C_100181_cf.func_105695_a(java.lang.Throwable, java.lang.String)game.C_100170_cm
		// @52: athrow
		// @53: return
	}
	
	final String func_102525_c(byte arg0)
	{
		// @00: aload_0
		// @01: getfield boolean game.C_100078_ul.field_102539_j
		// @04: ifeq @12
		// @07: aload_0
		// @08: getfield java.lang.String game.C_100078_ul.field_102536_o
		// @0B: ifnonnull @14
		// @0E: goto @12
		// @11: athrow
		// @12: aconst_null
		// @13: areturn
		// @14: aload_0
		// @15: getfield int game.C_100078_ul.field_102537_l
		// @18: aload_0
		// @19: getfield int game.C_100078_ul.field_103282_ib
		// @1C: ineg
		// @1D: getstatic int game.C_100015_wh.field_103781_g
		// @20: iadd
		// @21: iadd
		// @22: getstatic int game.C_100338_jc.field_105370_l
		// @25: bipush 102 (0x66)
		// @27: invokestatic game.C_100323_hl.func_107246_a(int, int, int)void
		// @2A: iload_1
		// @2B: bipush 34 (0x22)
		// @2D: if_icmpge @38
		// @30: iconst_1
		// @31: invokestatic game.C_100078_ul.func_103276_f(boolean)void
		// @34: goto @38
		// @37: athrow
		// @38: aload_0
		// @39: getfield java.lang.String game.C_100078_ul.field_102536_o
		// @3C: areturn
		// @3D: astore_2
		// @3E: aload_2
		// @3F: new java.lang.StringBuilder
		// @42: dup
		// @43: invokespecial java.lang.StringBuilder.<init>()void
		// @46: getstatic java.lang.String[] game.C_100078_ul.field_103286_sb
		// @49: iconst_0
		// @4A: aaload
		// @4B: invokevirtual java.lang.StringBuilder.append(java.lang.String)java.lang.StringBuilder
		// @4E: iload_1
		// @4F: invokevirtual java.lang.StringBuilder.append(int)java.lang.StringBuilder
		// @52: bipush 41 (0x29)
		// @54: invokevirtual java.lang.StringBuilder.append(char)java.lang.StringBuilder
		// @57: invokevirtual java.lang.StringBuilder.toString()java.lang.String
		// @5A: invokestatic game.C_100181_cf.func_105695_a(java.lang.Throwable, java.lang.String)game.C_100170_cm
		// @5D: athrow
	}
	
	final void func_102513_a(C_100336_im arg0, int arg1, int arg2, int arg3)
	{
		// @00: aload_0
		// @01: aload_1
		// @02: iload_2
		// @03: iload_3
		// @04: iload #4
		// @06: invokespecial game.C_100309_lk.func_102513_a(game.C_100336_im, int, int, int)void
		// @09: aload_0
		// @0A: getstatic int game.C_100015_wh.field_103781_g
		// @0D: aload_0
		// @0E: getfield int game.C_100078_ul.field_102538_m
		// @11: ineg
		// @12: iload #4
		// @14: isub
		// @15: iadd
		// @16: putfield int game.C_100078_ul.field_103282_ib
		// @19: goto @6D
		// @1C: astore #5
		// @1E: aload #5
		// @20: new java.lang.StringBuilder
		// @23: dup
		// @24: invokespecial java.lang.StringBuilder.<init>()void
		// @27: getstatic java.lang.String[] game.C_100078_ul.field_103286_sb
		// @2A: bipush 6 (0x06)
		// @2C: aaload
		// @2D: invokevirtual java.lang.StringBuilder.append(java.lang.String)java.lang.StringBuilder
		// @30: aload_1
		// @31: ifnull @3D
		// @34: getstatic java.lang.String[] game.C_100078_ul.field_103286_sb
		// @37: iconst_3
		// @38: aaload
		// @39: goto @42
		// @3C: athrow
		// @3D: getstatic java.lang.String[] game.C_100078_ul.field_103286_sb
		// @40: iconst_2
		// @41: aaload
		// @42: invokevirtual java.lang.StringBuilder.append(java.lang.String)java.lang.StringBuilder
		// @45: bipush 44 (0x2C)
		// @47: invokevirtual java.lang.StringBuilder.append(char)java.lang.StringBuilder
		// @4A: iload_2
		// @4B: invokevirtual java.lang.StringBuilder.append(int)java.lang.StringBuilder
		// @4E: bipush 44 (0x2C)
		// @50: invokevirtual java.lang.StringBuilder.append(char)java.lang.StringBuilder
		// @53: iload_3
		// @54: invokevirtual java.lang.StringBuilder.append(int)java.lang.StringBuilder
		// @57: bipush 44 (0x2C)
		// @59: invokevirtual java.lang.StringBuilder.append(char)java.lang.StringBuilder
		// @5C: iload #4
		// @5E: invokevirtual java.lang.StringBuilder.append(int)java.lang.StringBuilder
		// @61: bipush 41 (0x29)
		// @63: invokevirtual java.lang.StringBuilder.append(char)java.lang.StringBuilder
		// @66: invokevirtual java.lang.StringBuilder.toString()java.lang.String
		// @69: invokestatic game.C_100181_cf.func_105695_a(java.lang.Throwable, java.lang.String)game.C_100170_cm
		// @6C: athrow
		// @6D: return
	}
	
	static final void func_103276_f(boolean arg0)
	{
		// @00: iconst_0
		// @01: putstatic int game.C_100113_ek.field_104880_b
		// @04: bipush 87 (0x57)
		// @06: invokestatic game.C_100240_oj.func_106302_b(int)void
		// @09: iload_0
		// @0A: ifeq @14
		// @0D: aconst_null
		// @0E: checkcast game.C_100153_be[]
		// @11: putstatic game.C_100153_be[] game.C_100078_ul.field_103284_ob
		// @14: goto @39
		// @17: astore_1
		// @18: aload_1
		// @19: new java.lang.StringBuilder
		// @1C: dup
		// @1D: invokespecial java.lang.StringBuilder.<init>()void
		// @20: getstatic java.lang.String[] game.C_100078_ul.field_103286_sb
		// @23: bipush 7 (0x07)
		// @25: aaload
		// @26: invokevirtual java.lang.StringBuilder.append(java.lang.String)java.lang.StringBuilder
		// @29: iload_0
		// @2A: invokevirtual java.lang.StringBuilder.append(boolean)java.lang.StringBuilder
		// @2D: bipush 41 (0x29)
		// @2F: invokevirtual java.lang.StringBuilder.append(char)java.lang.StringBuilder
		// @32: invokevirtual java.lang.StringBuilder.toString()java.lang.String
		// @35: invokestatic game.C_100181_cf.func_105695_a(java.lang.Throwable, java.lang.String)game.C_100170_cm
		// @38: athrow
		// @39: return
	}
	
	final void func_103241_k(int arg0)
	{
		// @00: aload_0
		// @01: iload_1
		// @02: invokespecial game.C_100309_lk.func_103241_k(int)void
		// @05: aconst_null
		// @06: aload_0
		// @07: getfield game.C_100308_lh game.C_100078_ul.field_103287_mb
		// @0A: if_acmpeq @1B
		// @0D: aload_0
		// @0E: getfield game.C_100308_lh game.C_100078_ul.field_103287_mb
		// @11: iload_1
		// @12: sipush 19191 (0x4AF7)
		// @15: iadd
		// @16: invokeinterface game.C_100308_lh.func_102951_b(int)void
		// @1B: goto @40
		// @1E: astore_2
		// @1F: aload_2
		// @20: new java.lang.StringBuilder
		// @23: dup
		// @24: invokespecial java.lang.StringBuilder.<init>()void
		// @27: getstatic java.lang.String[] game.C_100078_ul.field_103286_sb
		// @2A: bipush 8 (0x08)
		// @2C: aaload
		// @2D: invokevirtual java.lang.StringBuilder.append(java.lang.String)java.lang.StringBuilder
		// @30: iload_1
		// @31: invokevirtual java.lang.StringBuilder.append(int)java.lang.StringBuilder
		// @34: bipush 41 (0x29)
		// @36: invokevirtual java.lang.StringBuilder.append(char)java.lang.StringBuilder
		// @39: invokevirtual java.lang.StringBuilder.toString()java.lang.String
		// @3C: invokestatic game.C_100181_cf.func_105695_a(java.lang.Throwable, java.lang.String)game.C_100170_cm
		// @3F: athrow
		// @40: return
	}
	
	public static void func_103280_r(int arg0)
	{
		// @00: iload_0
		// @01: sipush -22295 (0xA8E9)
		// @04: if_icmpeq @08
		// @07: return
		// @08: aconst_null
		// @09: putstatic game.C_100153_be[] game.C_100078_ul.field_103284_ob
		// @0C: aconst_null
		// @0D: putstatic game.C_100028_ha game.C_100078_ul.field_103281_jb
		// @10: aconst_null
		// @11: putstatic java.lang.String game.C_100078_ul.field_103288_kb
		// @14: aconst_null
		// @15: putstatic java.lang.String game.C_100078_ul.field_103290_qb
		// @18: aconst_null
		// @19: putstatic java.lang.String game.C_100078_ul.field_103289_lb
		// @1C: aconst_null
		// @1D: putstatic game.C_100100_i game.C_100078_ul.field_103283_nb
		// @20: goto @44
		// @23: astore_1
		// @24: aload_1
		// @25: new java.lang.StringBuilder
		// @28: dup
		// @29: invokespecial java.lang.StringBuilder.<init>()void
		// @2C: getstatic java.lang.String[] game.C_100078_ul.field_103286_sb
		// @2F: iconst_5
		// @30: aaload
		// @31: invokevirtual java.lang.StringBuilder.append(java.lang.String)java.lang.StringBuilder
		// @34: iload_0
		// @35: invokevirtual java.lang.StringBuilder.append(int)java.lang.StringBuilder
		// @38: bipush 41 (0x29)
		// @3A: invokevirtual java.lang.StringBuilder.append(char)java.lang.StringBuilder
		// @3D: invokevirtual java.lang.StringBuilder.toString()java.lang.String
		// @40: invokestatic game.C_100181_cf.func_105695_a(java.lang.Throwable, java.lang.String)game.C_100170_cm
		// @43: athrow
		// @44: return
	}
	
	static
	{
		// @00: bipush 9 (0x09)
		// @02: anewarray java.lang.String
		// @05: dup
		// @06: iconst_0
		// @07: ldc "\u000cMcY}"
		// @09: invokestatic game.C_100078_ul.func_103278_z(java.lang.String)char[]
		// @0C: invokestatic game.C_100078_ul.func_103277_z(char[])java.lang.String
		// @0F: aastore
		// @10: dup
		// @11: iconst_1
		// @12: ldc "\u000cMcM\u0014Q"
		// @14: invokestatic game.C_100078_ul.func_103278_z(java.lang.String)char[]
		// @17: invokestatic game.C_100078_ul.func_103277_z(char[])java.lang.String
		// @1A: aastore
		// @1B: dup
		// @1C: iconst_2
		// @1D: ldc "\u0017T!s"
		// @1F: invokestatic game.C_100078_ul.func_103278_z(java.lang.String)char[]
		// @22: invokestatic game.C_100078_ul.func_103277_z(char[])java.lang.String
		// @25: aastore
		// @26: dup
		// @27: iconst_3
		// @28: ldc "\u0002\u000fc1("
		// @2A: invokestatic game.C_100078_ul.func_103278_z(java.lang.String)char[]
		// @2D: invokestatic game.C_100078_ul.func_103277_z(char[])java.lang.String
		// @30: aastore
		// @31: dup
		// @32: iconst_4
		// @33: ldc "\u000cMcK\u0014Q"
		// @35: invokestatic game.C_100078_ul.func_103278_z(java.lang.String)char[]
		// @38: invokestatic game.C_100078_ul.func_103277_z(char[])java.lang.String
		// @3B: aastore
		// @3C: dup
		// @3D: iconst_5
		// @3E: ldc "\u000cMcL\u0014Q"
		// @40: invokestatic game.C_100078_ul.func_103278_z(java.lang.String)char[]
		// @43: invokestatic game.C_100078_ul.func_103277_z(char[])java.lang.String
		// @46: aastore
		// @47: dup
		// @48: bipush 6 (0x06)
		// @4A: ldc "\u000cMcN}"
		// @4C: invokestatic game.C_100078_ul.func_103278_z(java.lang.String)char[]
		// @4F: invokestatic game.C_100078_ul.func_103277_z(char[])java.lang.String
		// @52: aastore
		// @53: dup
		// @54: bipush 7 (0x07)
		// @56: ldc "\u000cMcJ\u0014Q"
		// @58: invokestatic game.C_100078_ul.func_103278_z(java.lang.String)char[]
		// @5B: invokestatic game.C_100078_ul.func_103277_z(char[])java.lang.String
		// @5E: aastore
		// @5F: dup
		// @60: bipush 8 (0x08)
		// @62: ldc "\u000cMcV\u0014Q"
		// @64: invokestatic game.C_100078_ul.func_103278_z(java.lang.String)char[]
		// @67: invokestatic game.C_100078_ul.func_103277_z(char[])java.lang.String
		// @6A: aastore
		// @6B: putstatic java.lang.String[] game.C_100078_ul.field_103286_sb
		// @6E: ldc "*J$ou\u0014H>l<\u0016O"
		// @70: invokestatic game.C_100078_ul.func_103278_z(java.lang.String)char[]
		// @73: invokestatic game.C_100078_ul.func_103277_z(char[])java.lang.String
		// @76: putstatic java.lang.String game.C_100078_ul.field_103290_qb
		// @79: new game.C_100028_ha
		// @7C: dup
		// @7D: invokespecial game.C_100028_ha.<init>()void
		// @80: putstatic game.C_100028_ha game.C_100078_ul.field_103281_jb
		// @83: ldc "-I$lu\u001e@ zu\u0011@>?7\u001cD#? \tE,k0\u001d\u0000mO9\u001c@>zu\u000bD!p4\u001d\u00019w<\n\u0001=~2\u001c\u000f"
		// @85: invokestatic game.C_100078_ul.func_103278_z(java.lang.String)char[]
		// @88: invokestatic game.C_100078_ul.func_103277_z(char[])java.lang.String
		// @8B: putstatic java.lang.String game.C_100078_ul.field_103289_lb
		// @8E: ldc ",R(m;\u0018L(%u"
		// @90: invokestatic game.C_100078_ul.func_103278_z(java.lang.String)char[]
		// @93: invokestatic game.C_100078_ul.func_103277_z(char[])java.lang.String
		// @96: putstatic java.lang.String game.C_100078_ul.field_103288_kb
		// @99: return
	}
	
	private static char[] func_103278_z(String arg0)
	{
		// @00: aload_0
		// @01: invokevirtual java.lang.String.toCharArray()char[]
		// @04: dup
		// @05: arraylength
		// @06: iconst_2
		// @07: if_icmpge @13
		// @0A: dup
		// @0B: iconst_0
		// @0C: dup2
		// @0D: caload
		// @0E: bipush 85 (0x55)
		// @10: ixor
		// @11: i2c
		// @12: castore
		// @13: areturn
	}
	
	private static String func_103277_z(char[] arg0)
	{
		// @00: aload_0
		// @01: dup
		// @02: arraylength
		// @03: swap
		// @04: iconst_0
		// @05: istore_1
		// @06: goto @4C
		// @09: dup
		// @0A: iload_1
		// @0B: dup2
		// @0C: caload
		// @0D: iload_1
		// @0E: iconst_5
		// @0F: irem
		// @10: tableswitch def: @44, for 0: @30, for 1: @35, for 2: @3A, for 3: @3F
		// @30: bipush 121 (0x79)
		// @32: goto @46
		// @35: bipush 33 (0x21)
		// @37: goto @46
		// @3A: bipush 77 (0x4D)
		// @3C: goto @46
		// @3F: bipush 31 (0x1F)
		// @41: goto @46
		// @44: bipush 85 (0x55)
		// @46: ixor
		// @47: i2c
		// @48: castore
		// @49: iinc #1 +1
		// @4C: swap
		// @4D: dup_x1
		// @4E: iload_1
		// @4F: if_icmpgt @09
		// @52: new java.lang.String
		// @55: dup_x1
		// @56: swap
		// @57: invokespecial java.lang.String.<init>(char[])void
		// @5A: invokevirtual java.lang.String.intern()java.lang.String
		// @5D: areturn
	}
}
