package game;

final class C_100198_qn
{
	static boolean field_105833_d;
	static String field_105835_c;
	static boolean field_105834_b;
	static String field_105836_a;
	private static final String[] field_105837_z;
	
	public static void func_105831_a(boolean arg0)
	{
		// @00: aconst_null
		// @01: putstatic java.lang.String game.C_100198_qn.field_105835_c
		// @04: aconst_null
		// @05: putstatic java.lang.String game.C_100198_qn.field_105836_a
		// @08: iload_0
		// @09: ifeq @13
		// @0C: aconst_null
		// @0D: checkcast java.lang.String
		// @10: putstatic java.lang.String game.C_100198_qn.field_105835_c
		// @13: goto @37
		// @16: astore_1
		// @17: aload_1
		// @18: new java.lang.StringBuilder
		// @1B: dup
		// @1C: invokespecial java.lang.StringBuilder.<init>()void
		// @1F: getstatic java.lang.String[] game.C_100198_qn.field_105837_z
		// @22: iconst_2
		// @23: aaload
		// @24: invokevirtual java.lang.StringBuilder.append(java.lang.String)java.lang.StringBuilder
		// @27: iload_0
		// @28: invokevirtual java.lang.StringBuilder.append(boolean)java.lang.StringBuilder
		// @2B: bipush 41 (0x29)
		// @2D: invokevirtual java.lang.StringBuilder.append(char)java.lang.StringBuilder
		// @30: invokevirtual java.lang.StringBuilder.toString()java.lang.String
		// @33: invokestatic game.C_100181_cf.func_105695_a(java.lang.Throwable, java.lang.String)game.C_100170_cm
		// @36: athrow
		// @37: return
	}
	
	static final byte func_105832_a(boolean arg0, char arg1)
	{
		// @000: iload_0
		// @001: ifeq @007
		// @004: bipush -56 (0xC8)
		// @006: ireturn
		// @007: iload_1
		// @008: iconst_m1
		// @009: ixor
		// @00A: iconst_m1
		// @00B: if_icmpge @019
		// @00E: sipush 128 (0x0080)
		// @011: iload_1
		// @012: if_icmpgt @1F0
		// @015: goto @019
		// @018: athrow
		// @019: sipush 160 (0x00A0)
		// @01C: iload_1
		// @01D: if_icmpgt @031
		// @020: goto @024
		// @023: athrow
		// @024: sipush -256 (0xFF00)
		// @027: iload_1
		// @028: iconst_m1
		// @029: ixor
		// @02A: if_icmple @1F0
		// @02D: goto @031
		// @030: athrow
		// @031: sipush -8365 (0xDF53)
		// @034: iload_1
		// @035: iconst_m1
		// @036: ixor
		// @037: if_icmpne @044
		// @03A: goto @03E
		// @03D: athrow
		// @03E: bipush -128 (0x80)
		// @040: istore_2
		// @041: goto @1F3
		// @044: sipush -8219 (0xDFE5)
		// @047: iload_1
		// @048: iconst_m1
		// @049: ixor
		// @04A: if_icmpeq @1EA
		// @04D: sipush 402 (0x0192)
		// @050: iload_1
		// @051: if_icmpeq @1E4
		// @054: goto @058
		// @057: athrow
		// @058: sipush 8222 (0x201E)
		// @05B: iload_1
		// @05C: if_icmpeq @1DE
		// @05F: goto @063
		// @062: athrow
		// @063: iload_1
		// @064: sipush 8230 (0x2026)
		// @067: if_icmpeq @1D8
		// @06A: goto @06E
		// @06D: athrow
		// @06E: sipush -8225 (0xDFDF)
		// @071: iload_1
		// @072: iconst_m1
		// @073: ixor
		// @074: if_icmpeq @1D2
		// @077: goto @07B
		// @07A: athrow
		// @07B: iload_1
		// @07C: sipush 8225 (0x2021)
		// @07F: if_icmpeq @1CC
		// @082: goto @086
		// @085: athrow
		// @086: iload_1
		// @087: iconst_m1
		// @088: ixor
		// @089: sipush -711 (0xFD39)
		// @08C: if_icmpne @099
		// @08F: goto @093
		// @092: athrow
		// @093: bipush -120 (0x88)
		// @095: istore_2
		// @096: goto @1F3
		// @099: iload_1
		// @09A: sipush 8240 (0x2030)
		// @09D: if_icmpeq @1C6
		// @0A0: sipush 352 (0x0160)
		// @0A3: iload_1
		// @0A4: if_icmpeq @1C0
		// @0A7: goto @0AB
		// @0AA: athrow
		// @0AB: sipush 8249 (0x2039)
		// @0AE: iload_1
		// @0AF: if_icmpne @0BC
		// @0B2: goto @0B6
		// @0B5: athrow
		// @0B6: bipush -117 (0x8B)
		// @0B8: istore_2
		// @0B9: goto @1F3
		// @0BC: sipush 338 (0x0152)
		// @0BF: iload_1
		// @0C0: if_icmpne @0C9
		// @0C3: bipush -116 (0x8C)
		// @0C5: istore_2
		// @0C6: goto @1F3
		// @0C9: iload_1
		// @0CA: iconst_m1
		// @0CB: ixor
		// @0CC: sipush -382 (0xFE82)
		// @0CF: if_icmpeq @1BA
		// @0D2: sipush 8216 (0x2018)
		// @0D5: iload_1
		// @0D6: if_icmpeq @1B4
		// @0D9: goto @0DD
		// @0DC: athrow
		// @0DD: iload_1
		// @0DE: iconst_m1
		// @0DF: ixor
		// @0E0: sipush -8218 (0xDFE6)
		// @0E3: if_icmpeq @1AE
		// @0E6: goto @0EA
		// @0E9: athrow
		// @0EA: sipush -8221 (0xDFE3)
		// @0ED: iload_1
		// @0EE: iconst_m1
		// @0EF: ixor
		// @0F0: if_icmpne @0FD
		// @0F3: goto @0F7
		// @0F6: athrow
		// @0F7: bipush -109 (0x93)
		// @0F9: istore_2
		// @0FA: goto @1F3
		// @0FD: sipush -8222 (0xDFE2)
		// @100: iload_1
		// @101: iconst_m1
		// @102: ixor
		// @103: if_icmpeq @1A8
		// @106: iload_1
		// @107: sipush 8226 (0x2022)
		// @10A: if_icmpeq @1A2
		// @10D: goto @111
		// @110: athrow
		// @111: sipush 8211 (0x2013)
		// @114: iload_1
		// @115: if_icmpne @122
		// @118: goto @11C
		// @11B: athrow
		// @11C: bipush -106 (0x96)
		// @11E: istore_2
		// @11F: goto @1F3
		// @122: iload_1
		// @123: iconst_m1
		// @124: ixor
		// @125: sipush -8213 (0xDFEB)
		// @128: if_icmpeq @19C
		// @12B: sipush 732 (0x02DC)
		// @12E: iload_1
		// @12F: if_icmpne @13C
		// @132: goto @136
		// @135: athrow
		// @136: bipush -104 (0x98)
		// @138: istore_2
		// @139: goto @1F3
		// @13C: sipush -8483 (0xDEDD)
		// @13F: iload_1
		// @140: iconst_m1
		// @141: ixor
		// @142: if_icmpne @14B
		// @145: bipush -103 (0x99)
		// @147: istore_2
		// @148: goto @1F3
		// @14B: iload_1
		// @14C: sipush 353 (0x0161)
		// @14F: if_icmpne @158
		// @152: bipush -102 (0x9A)
		// @154: istore_2
		// @155: goto @1F3
		// @158: sipush 8250 (0x203A)
		// @15B: iload_1
		// @15C: if_icmpeq @196
		// @15F: sipush 339 (0x0153)
		// @162: iload_1
		// @163: if_icmpeq @190
		// @166: goto @16A
		// @169: athrow
		// @16A: iload_1
		// @16B: iconst_m1
		// @16C: ixor
		// @16D: sipush -383 (0xFE81)
		// @170: if_icmpne @17D
		// @173: goto @177
		// @176: athrow
		// @177: bipush -98 (0x9E)
		// @179: istore_2
		// @17A: goto @1F3
		// @17D: iload_1
		// @17E: sipush 376 (0x0178)
		// @181: if_icmpeq @18A
		// @184: bipush 63 (0x3F)
		// @186: istore_2
		// @187: goto @1F3
		// @18A: bipush -97 (0x9F)
		// @18C: istore_2
		// @18D: goto @1F3
		// @190: bipush -100 (0x9C)
		// @192: istore_2
		// @193: goto @1F3
		// @196: bipush -101 (0x9B)
		// @198: istore_2
		// @199: goto @1F3
		// @19C: bipush -105 (0x97)
		// @19E: istore_2
		// @19F: goto @1F3
		// @1A2: bipush -107 (0x95)
		// @1A4: istore_2
		// @1A5: goto @1F3
		// @1A8: bipush -108 (0x94)
		// @1AA: istore_2
		// @1AB: goto @1F3
		// @1AE: bipush -110 (0x92)
		// @1B0: istore_2
		// @1B1: goto @1F3
		// @1B4: bipush -111 (0x91)
		// @1B6: istore_2
		// @1B7: goto @1F3
		// @1BA: bipush -114 (0x8E)
		// @1BC: istore_2
		// @1BD: goto @1F3
		// @1C0: bipush -118 (0x8A)
		// @1C2: istore_2
		// @1C3: goto @1F3
		// @1C6: bipush -119 (0x89)
		// @1C8: istore_2
		// @1C9: goto @1F3
		// @1CC: bipush -121 (0x87)
		// @1CE: istore_2
		// @1CF: goto @1F3
		// @1D2: bipush -122 (0x86)
		// @1D4: istore_2
		// @1D5: goto @1F3
		// @1D8: bipush -123 (0x85)
		// @1DA: istore_2
		// @1DB: goto @1F3
		// @1DE: bipush -124 (0x84)
		// @1E0: istore_2
		// @1E1: goto @1F3
		// @1E4: bipush -125 (0x83)
		// @1E6: istore_2
		// @1E7: goto @1F3
		// @1EA: bipush -126 (0x82)
		// @1EC: istore_2
		// @1ED: goto @1F3
		// @1F0: iload_1
		// @1F1: i2b
		// @1F2: istore_2
		// @1F3: iload_2
		// @1F4: ireturn
		// @1F5: astore_2
		// @1F6: aload_2
		// @1F7: new java.lang.StringBuilder
		// @1FA: dup
		// @1FB: invokespecial java.lang.StringBuilder.<init>()void
		// @1FE: getstatic java.lang.String[] game.C_100198_qn.field_105837_z
		// @201: iconst_0
		// @202: aaload
		// @203: invokevirtual java.lang.StringBuilder.append(java.lang.String)java.lang.StringBuilder
		// @206: iload_0
		// @207: invokevirtual java.lang.StringBuilder.append(boolean)java.lang.StringBuilder
		// @20A: bipush 44 (0x2C)
		// @20C: invokevirtual java.lang.StringBuilder.append(char)java.lang.StringBuilder
		// @20F: iload_1
		// @210: invokevirtual java.lang.StringBuilder.append(char)java.lang.StringBuilder
		// @213: bipush 41 (0x29)
		// @215: invokevirtual java.lang.StringBuilder.append(char)java.lang.StringBuilder
		// @218: invokevirtual java.lang.StringBuilder.toString()java.lang.String
		// @21B: invokestatic game.C_100181_cf.func_105695_a(java.lang.Throwable, java.lang.String)game.C_100170_cm
		// @21E: athrow
	}
	
	static final synchronized long func_105828_a(byte arg0)
	{
		// @00: invokestatic java.lang.System.currentTimeMillis()long
		// @03: lstore_1
		// @04: bipush -16 (0xF0)
		// @06: bipush 11 (0x0B)
		// @08: iload_0
		// @09: isub
		// @0A: bipush 32 (0x20)
		// @0C: idiv
		// @0D: idiv
		// @0E: istore_3
		// @0F: getstatic long game.C_100062_dk.field_104283_b
		// @12: ldc2_w -1
		// @15: lxor
		// @16: lload_1
		// @17: ldc2_w -1
		// @1A: lxor
		// @1B: lcmp
		// @1C: iflt @23
		// @1F: goto @2F
		// @22: athrow
		// @23: getstatic long game.C_100087_n.field_100700_s
		// @26: getstatic long game.C_100062_dk.field_104283_b
		// @29: lload_1
		// @2A: lsub
		// @2B: ladd
		// @2C: putstatic long game.C_100087_n.field_100700_s
		// @2F: lload_1
		// @30: putstatic long game.C_100062_dk.field_104283_b
		// @33: lload_1
		// @34: getstatic long game.C_100087_n.field_100700_s
		// @37: lneg
		// @38: lsub
		// @39: lreturn
		// @3A: astore_1
		// @3B: aload_1
		// @3C: new java.lang.StringBuilder
		// @3F: dup
		// @40: invokespecial java.lang.StringBuilder.<init>()void
		// @43: getstatic java.lang.String[] game.C_100198_qn.field_105837_z
		// @46: iconst_1
		// @47: aaload
		// @48: invokevirtual java.lang.StringBuilder.append(java.lang.String)java.lang.StringBuilder
		// @4B: iload_0
		// @4C: invokevirtual java.lang.StringBuilder.append(int)java.lang.StringBuilder
		// @4F: bipush 41 (0x29)
		// @51: invokevirtual java.lang.StringBuilder.append(char)java.lang.StringBuilder
		// @54: invokevirtual java.lang.StringBuilder.toString()java.lang.String
		// @57: invokestatic game.C_100181_cf.func_105695_a(java.lang.Throwable, java.lang.String)game.C_100170_cm
		// @5A: athrow
	}
	
	static
	{
		// @00: iconst_3
		// @01: anewarray java.lang.String
		// @04: dup
		// @05: iconst_0
		// @06: ldc "e\u001bBA8"
		// @08: invokestatic game.C_100198_qn.func_105830_z(java.lang.String)char[]
		// @0B: invokestatic game.C_100198_qn.func_105829_z(char[])java.lang.String
		// @0E: aastore
		// @0F: dup
		// @10: iconst_1
		// @11: ldc "e\u001bB@8"
		// @13: invokestatic game.C_100198_qn.func_105830_z(java.lang.String)char[]
		// @16: invokestatic game.C_100198_qn.func_105829_z(char[])java.lang.String
		// @19: aastore
		// @1A: dup
		// @1B: iconst_2
		// @1C: ldc "e\u001bBB8"
		// @1E: invokestatic game.C_100198_qn.func_105830_z(java.lang.String)char[]
		// @21: invokestatic game.C_100198_qn.func_105829_z(char[])java.lang.String
		// @24: aastore
		// @25: putstatic java.lang.String[] game.C_100198_qn.field_105837_z
		// @28: iconst_0
		// @29: putstatic boolean game.C_100198_qn.field_105834_b
		// @2C: ldc "C\u0014\u001af*4II3."
		// @2E: invokestatic game.C_100198_qn.func_105830_z(java.lang.String)char[]
		// @31: invokestatic game.C_100198_qn.func_105829_z(char[])java.lang.String
		// @34: putstatic java.lang.String game.C_100198_qn.field_105835_c
		// @37: ldc "Y\u0010\u0001auf\u0006"
		// @39: invokestatic game.C_100198_qn.func_105830_z(java.lang.String)char[]
		// @3C: invokestatic game.C_100198_qn.func_105829_z(char[])java.lang.String
		// @3F: putstatic java.lang.String game.C_100198_qn.field_105836_a
		// @42: return
	}
	
	private static char[] func_105830_z(String arg0)
	{
		// @00: aload_0
		// @01: invokevirtual java.lang.String.toCharArray()char[]
		// @04: dup
		// @05: arraylength
		// @06: iconst_2
		// @07: if_icmpge @13
		// @0A: dup
		// @0B: iconst_0
		// @0C: dup2
		// @0D: caload
		// @0E: bipush 16 (0x10)
		// @10: ixor
		// @11: i2c
		// @12: castore
		// @13: areturn
	}
	
	private static String func_105829_z(char[] arg0)
	{
		// @00: aload_0
		// @01: dup
		// @02: arraylength
		// @03: swap
		// @04: iconst_0
		// @05: istore_1
		// @06: goto @4B
		// @09: dup
		// @0A: iload_1
		// @0B: dup2
		// @0C: caload
		// @0D: iload_1
		// @0E: iconst_5
		// @0F: irem
		// @10: tableswitch def: @43, for 0: @30, for 1: @35, for 2: @3A, for 3: @3F
		// @30: bipush 20 (0x14)
		// @32: goto @45
		// @35: bipush 117 (0x75)
		// @37: goto @45
		// @3A: bipush 108 (0x6C)
		// @3C: goto @45
		// @3F: iconst_3
		// @40: goto @45
		// @43: bipush 16 (0x10)
		// @45: ixor
		// @46: i2c
		// @47: castore
		// @48: iinc #1 +1
		// @4B: swap
		// @4C: dup_x1
		// @4D: iload_1
		// @4E: if_icmpgt @09
		// @51: new java.lang.String
		// @54: dup_x1
		// @55: swap
		// @56: invokespecial java.lang.String.<init>(char[])void
		// @59: invokevirtual java.lang.String.intern()java.lang.String
		// @5C: areturn
	}
}
