package game;

import java.util.Random;

final class C_100067_vd
{
	private int field_104320_m;
	private int field_104310_f;
	private C_100037_wb[] field_104329_s;
	private int field_104314_b;
	static Random field_104322_k;
	private int field_104331_q;
	private boolean field_104313_e;
	private C_100037_wb[] field_104318_o;
	private String field_104316_a;
	private int field_104312_d;
	private C_100112_r field_104328_t;
	private int field_104327_u;
	private C_100037_wb field_104326_v;
	C_100302_ka field_104319_l;
	private boolean field_104325_w;
	private int field_104330_r;
	static int[] field_104321_j;
	static int field_104324_i;
	static C_100292_jk field_104315_c;
	static int field_104332_p;
	static C_100302_ka[] field_104323_h;
	static String[] field_104311_g;
	static String field_104317_n;
	private static final String[] field_104333_z;
	
	private final void func_104303_a(int arg0)
	{
		// @00: aload_0
		// @01: aload_0
		// @02: getfield int game.C_100067_vd.field_104330_r
		// @05: iconst_2
		// @06: imul
		// @07: putfield int game.C_100067_vd.field_104331_q
		// @0A: aload_0
		// @0B: getfield game.C_100037_wb game.C_100067_vd.field_104326_v
		// @0E: ifnull @28
		// @11: aload_0
		// @12: dup
		// @13: getfield int game.C_100067_vd.field_104331_q
		// @16: aload_0
		// @17: getfield game.C_100037_wb game.C_100067_vd.field_104326_v
		// @1A: getfield int game.C_100037_wb.field_102337_u
		// @1D: bipush -2 (0xFE)
		// @1F: isub
		// @20: iadd
		// @21: putfield int game.C_100067_vd.field_104331_q
		// @24: goto @28
		// @27: athrow
		// @28: aconst_null
		// @29: aload_0
		// @2A: getfield java.lang.String game.C_100067_vd.field_104316_a
		// @2D: if_acmpne @34
		// @30: goto @55
		// @33: athrow
		// @34: aload_0
		// @35: dup
		// @36: getfield int game.C_100067_vd.field_104331_q
		// @39: aload_0
		// @3A: getfield game.C_100112_r game.C_100067_vd.field_104328_t
		// @3D: aload_0
		// @3E: getfield java.lang.String game.C_100067_vd.field_104316_a
		// @41: aload_0
		// @42: getfield int game.C_100067_vd.field_104312_d
		// @45: iconst_2
		// @46: imul
		// @47: ineg
		// @48: aload_0
		// @49: getfield int game.C_100067_vd.field_104314_b
		// @4C: iadd
		// @4D: iconst_0
		// @4E: invokevirtual game.C_100112_r.func_101734_a(java.lang.String, int, int)int
		// @51: iadd
		// @52: putfield int game.C_100067_vd.field_104331_q
		// @55: iload_1
		// @56: bipush 63 (0x3F)
		// @58: if_icmpgt @5C
		// @5B: return
		// @5C: aload_0
		// @5D: getfield boolean game.C_100067_vd.field_104325_w
		// @60: ifeq @6E
		// @63: aload_0
		// @64: dup
		// @65: getfield int game.C_100067_vd.field_104331_q
		// @68: bipush 40 (0x28)
		// @6A: iadd
		// @6B: putfield int game.C_100067_vd.field_104331_q
		// @6E: goto @93
		// @71: astore_2
		// @72: aload_2
		// @73: new java.lang.StringBuilder
		// @76: dup
		// @77: invokespecial java.lang.StringBuilder.<init>()void
		// @7A: getstatic java.lang.String[] game.C_100067_vd.field_104333_z
		// @7D: bipush 7 (0x07)
		// @7F: aaload
		// @80: invokevirtual java.lang.StringBuilder.append(java.lang.String)java.lang.StringBuilder
		// @83: iload_1
		// @84: invokevirtual java.lang.StringBuilder.append(int)java.lang.StringBuilder
		// @87: bipush 41 (0x29)
		// @89: invokevirtual java.lang.StringBuilder.append(char)java.lang.StringBuilder
		// @8C: invokevirtual java.lang.StringBuilder.toString()java.lang.String
		// @8F: invokestatic game.C_100181_cf.func_105695_a(java.lang.Throwable, java.lang.String)game.C_100170_cm
		// @92: athrow
		// @93: return
	}
	
	final boolean func_104300_a(byte arg0)
	{
		// @00: iconst_1
		// @01: putstatic boolean game.C_100034_gi.field_104029_d
		// @04: bipush 59 (0x3B)
		// @06: iload_1
		// @07: bipush -57 (0xC7)
		// @09: isub
		// @0A: bipush 44 (0x2C)
		// @0C: idiv
		// @0D: idiv
		// @0E: istore_2
		// @0F: iconst_1
		// @10: putstatic boolean game.C_100309_lk.field_103271_ab
		// @13: iconst_0
		// @14: ireturn
		// @15: astore_2
		// @16: aload_2
		// @17: new java.lang.StringBuilder
		// @1A: dup
		// @1B: invokespecial java.lang.StringBuilder.<init>()void
		// @1E: getstatic java.lang.String[] game.C_100067_vd.field_104333_z
		// @21: iconst_4
		// @22: aaload
		// @23: invokevirtual java.lang.StringBuilder.append(java.lang.String)java.lang.StringBuilder
		// @26: iload_1
		// @27: invokevirtual java.lang.StringBuilder.append(int)java.lang.StringBuilder
		// @2A: bipush 41 (0x29)
		// @2C: invokevirtual java.lang.StringBuilder.append(char)java.lang.StringBuilder
		// @2F: invokevirtual java.lang.StringBuilder.toString()java.lang.String
		// @32: invokestatic game.C_100181_cf.func_105695_a(java.lang.Throwable, java.lang.String)game.C_100170_cm
		// @35: athrow
	}
	
	private final C_100302_ka func_104306_d(byte arg0)
	{
		// @00: getstatic int game.SteelSentinels.field_105275_O
		// @03: istore_3
		// @04: iload_1
		// @05: iconst_2
		// @06: if_icmpge @13
		// @09: aload_0
		// @0A: bipush -49 (0xCF)
		// @0C: putfield int game.C_100067_vd.field_104331_q
		// @0F: goto @13
		// @12: athrow
		// @13: aload_0
		// @14: getfield int game.C_100067_vd.field_104310_f
		// @17: istore_2
		// @18: iconst_3
		// @19: iload_2
		// @1A: if_icmpne @25
		// @1D: iload_3
		// @1E: ifeq @58
		// @21: goto @25
		// @24: athrow
		// @25: iload_2
		// @26: iconst_5
		// @27: if_icmpne @36
		// @2A: goto @2E
		// @2D: athrow
		// @2E: iload_3
		// @2F: ifeq @5E
		// @32: goto @36
		// @35: athrow
		// @36: bipush -11 (0xF5)
		// @38: iload_2
		// @39: iconst_m1
		// @3A: ixor
		// @3B: if_icmpne @4A
		// @3E: goto @42
		// @41: athrow
		// @42: iload_3
		// @43: ifeq @64
		// @46: goto @4A
		// @49: athrow
		// @4A: iload_2
		// @4B: bipush 14 (0x0E)
		// @4D: if_icmpeq @6A
		// @50: goto @54
		// @53: athrow
		// @54: goto @70
		// @57: athrow
		// @58: getstatic game.C_100302_ka[] game.C_100136_th.field_102618_W
		// @5B: iconst_1
		// @5C: aaload
		// @5D: areturn
		// @5E: getstatic game.C_100302_ka[] game.C_100136_th.field_102618_W
		// @61: iconst_2
		// @62: aaload
		// @63: areturn
		// @64: getstatic game.C_100302_ka[] game.C_100136_th.field_102618_W
		// @67: iconst_3
		// @68: aaload
		// @69: areturn
		// @6A: getstatic game.C_100302_ka[] game.C_100136_th.field_102618_W
		// @6D: iconst_0
		// @6E: aaload
		// @6F: areturn
		// @70: aload_0
		// @71: getfield game.C_100302_ka game.C_100067_vd.field_104319_l
		// @74: areturn
		// @75: astore_2
		// @76: aload_2
		// @77: new java.lang.StringBuilder
		// @7A: dup
		// @7B: invokespecial java.lang.StringBuilder.<init>()void
		// @7E: getstatic java.lang.String[] game.C_100067_vd.field_104333_z
		// @81: bipush 10 (0x0A)
		// @83: aaload
		// @84: invokevirtual java.lang.StringBuilder.append(java.lang.String)java.lang.StringBuilder
		// @87: iload_1
		// @88: invokevirtual java.lang.StringBuilder.append(int)java.lang.StringBuilder
		// @8B: bipush 41 (0x29)
		// @8D: invokevirtual java.lang.StringBuilder.append(char)java.lang.StringBuilder
		// @90: invokevirtual java.lang.StringBuilder.toString()java.lang.String
		// @93: invokestatic game.C_100181_cf.func_105695_a(java.lang.Throwable, java.lang.String)game.C_100170_cm
		// @96: athrow
	}
	
	final boolean func_104302_a(int arg0, C_100333_ij arg1)
	{
		// @000: getstatic int game.SteelSentinels.field_105275_O
		// @003: istore #6
		// @005: iconst_1
		// @006: putstatic boolean game.C_100309_lk.field_103271_ab
		// @009: iconst_1
		// @00A: putstatic boolean game.C_100034_gi.field_104029_d
		// @00D: aload_0
		// @00E: getfield boolean game.C_100067_vd.field_104325_w
		// @011: ifeq @031
		// @014: aload_0
		// @015: getfield boolean game.C_100067_vd.field_104313_e
		// @018: ifeq @031
		// @01B: goto @01F
		// @01E: athrow
		// @01F: bipush 95 (0x5F)
		// @021: iload_1
		// @022: bipush 12 (0x0C)
		// @024: iadd
		// @025: invokestatic game.C_100278_nd.func_101196_k(int, int)void
		// @028: bipush 72 (0x48)
		// @02A: invokestatic game.C_100312_ld.func_107146_a(byte)void
		// @02D: goto @031
		// @030: athrow
		// @031: iload_1
		// @032: aload_2
		// @033: getfield int game.C_100333_ij.field_107347_b
		// @036: iconst_m1
		// @037: ixor
		// @038: if_icmpeq @03F
		// @03B: goto @04B
		// @03E: athrow
		// @03F: aload_0
		// @040: bipush 123 (0x7B)
		// @042: invokevirtual game.C_100067_vd.func_104307_c(byte)void
		// @045: iconst_m1
		// @046: putstatic int game.C_100068_vc.field_104343_e
		// @049: iconst_1
		// @04A: ireturn
		// @04B: getstatic game.C_100115_ej game.C_100017_wj.field_103823_k
		// @04E: astore_3
		// @04F: aload_3
		// @050: ifnull @072
		// @053: aload_3
		// @054: getfield game.C_100231_oc game.C_100115_ej.field_102038_Vb
		// @057: ifnull @072
		// @05A: goto @05E
		// @05D: athrow
		// @05E: aload_3
		// @05F: getfield game.C_100231_oc game.C_100115_ej.field_102038_Vb
		// @062: getfield boolean game.C_100231_oc.field_101839_db
		// @065: ifne @070
		// @068: goto @06C
		// @06B: athrow
		// @06C: goto @072
		// @06F: athrow
		// @070: iconst_1
		// @071: ireturn
		// @072: getstatic game.C_100115_ej game.C_100316_lc.field_102410_w
		// @075: astore_3
		// @076: aload_3
		// @077: ifnull @096
		// @07A: aconst_null
		// @07B: aload_3
		// @07C: getfield game.C_100231_oc game.C_100115_ej.field_102038_Vb
		// @07F: if_acmpeq @096
		// @082: goto @086
		// @085: athrow
		// @086: aload_3
		// @087: getfield game.C_100231_oc game.C_100115_ej.field_102038_Vb
		// @08A: getfield boolean game.C_100231_oc.field_101839_db
		// @08D: ifeq @096
		// @090: goto @094
		// @093: athrow
		// @094: iconst_1
		// @095: ireturn
		// @096: aload_0
		// @097: bipush 23 (0x17)
		// @099: invokespecial game.C_100067_vd.func_104306_d(byte)game.C_100302_ka
		// @09C: astore_3
		// @09D: aconst_null
		// @09E: aload_3
		// @09F: if_acmpeq @0B2
		// @0A2: aload_3
		// @0A3: getfield boolean game.C_100302_ka.field_101839_db
		// @0A6: ifeq @0B2
		// @0A9: goto @0AD
		// @0AC: athrow
		// @0AD: iconst_1
		// @0AE: goto @0B3
		// @0B1: athrow
		// @0B2: iconst_0
		// @0B3: istore #4
		// @0B5: aload_0
		// @0B6: getfield int game.C_100067_vd.field_104310_f
		// @0B9: istore #5
		// @0BB: iload #5
		// @0BD: iconst_m1
		// @0BE: ixor
		// @0BF: bipush -2 (0xFE)
		// @0C1: if_icmpeq @157
		// @0C4: iload #5
		// @0C6: iconst_m1
		// @0C7: ixor
		// @0C8: bipush -4 (0xFC)
		// @0CA: if_icmpne @0DA
		// @0CD: goto @0D1
		// @0D0: athrow
		// @0D1: iload #6
		// @0D3: ifeq @167
		// @0D6: goto @0DA
		// @0D9: athrow
		// @0DA: bipush -6 (0xFA)
		// @0DC: iload #5
		// @0DE: iconst_m1
		// @0DF: ixor
		// @0E0: if_icmpne @0F0
		// @0E3: goto @0E7
		// @0E6: athrow
		// @0E7: iload #6
		// @0E9: ifeq @177
		// @0EC: goto @0F0
		// @0EF: athrow
		// @0F0: iload #5
		// @0F2: iconst_m1
		// @0F3: ixor
		// @0F4: bipush -8 (0xF8)
		// @0F6: if_icmpne @106
		// @0F9: goto @0FD
		// @0FC: athrow
		// @0FD: iload #6
		// @0FF: ifeq @183
		// @102: goto @106
		// @105: athrow
		// @106: bipush 8 (0x08)
		// @108: iload #5
		// @10A: if_icmpne @11A
		// @10D: goto @111
		// @110: athrow
		// @111: iload #6
		// @113: ifeq @18F
		// @116: goto @11A
		// @119: athrow
		// @11A: bipush 10 (0x0A)
		// @11C: iload #5
		// @11E: if_icmpeq @197
		// @121: goto @125
		// @124: athrow
		// @125: bipush -13 (0xF3)
		// @127: iload #5
		// @129: iconst_m1
		// @12A: ixor
		// @12B: if_icmpne @13B
		// @12E: goto @132
		// @131: athrow
		// @132: iload #6
		// @134: ifeq @1A7
		// @137: goto @13B
		// @13A: athrow
		// @13B: bipush -15 (0xF1)
		// @13D: iload #5
		// @13F: iconst_m1
		// @140: ixor
		// @141: if_icmpeq @1B8
		// @144: goto @148
		// @147: athrow
		// @148: bipush 16 (0x10)
		// @14A: iload #5
		// @14C: if_icmpeq @1C4
		// @14F: goto @153
		// @152: athrow
		// @153: goto @1D3
		// @156: athrow
		// @157: iload #4
		// @159: ifne @160
		// @15C: goto @1D3
		// @15F: athrow
		// @160: bipush 72 (0x48)
		// @162: invokestatic game.C_100312_ld.func_107146_a(byte)void
		// @165: iconst_1
		// @166: ireturn
		// @167: iload #4
		// @169: ifne @170
		// @16C: goto @1D3
		// @16F: athrow
		// @170: bipush 72 (0x48)
		// @172: invokestatic game.C_100312_ld.func_107146_a(byte)void
		// @175: iconst_1
		// @176: ireturn
		// @177: iload #4
		// @179: ifeq @1D3
		// @17C: bipush 72 (0x48)
		// @17E: invokestatic game.C_100312_ld.func_107146_a(byte)void
		// @181: iconst_1
		// @182: ireturn
		// @183: iload #4
		// @185: ifeq @1D3
		// @188: bipush 72 (0x48)
		// @18A: invokestatic game.C_100312_ld.func_107146_a(byte)void
		// @18D: iconst_1
		// @18E: ireturn
		// @18F: getstatic game.C_100049_vf game.C_100013_fn.field_103742_c
		// @192: ifnull @1D3
		// @195: iconst_1
		// @196: ireturn
		// @197: iload #4
		// @199: ifne @1A0
		// @19C: goto @1D3
		// @19F: athrow
		// @1A0: bipush 72 (0x48)
		// @1A2: invokestatic game.C_100312_ld.func_107146_a(byte)void
		// @1A5: iconst_1
		// @1A6: ireturn
		// @1A7: getstatic boolean game.C_100064_ve.field_103011_A
		// @1AA: ifne @1B1
		// @1AD: goto @1D3
		// @1B0: athrow
		// @1B1: bipush 72 (0x48)
		// @1B3: invokestatic game.C_100312_ld.func_107146_a(byte)void
		// @1B6: iconst_1
		// @1B7: ireturn
		// @1B8: iload #4
		// @1BA: ifeq @1D3
		// @1BD: bipush 72 (0x48)
		// @1BF: invokestatic game.C_100312_ld.func_107146_a(byte)void
		// @1C2: iconst_1
		// @1C3: ireturn
		// @1C4: sipush 448 (0x01C0)
		// @1C7: getstatic int game.C_100338_jc.field_105370_l
		// @1CA: if_icmple @1D1
		// @1CD: goto @1D3
		// @1D0: athrow
		// @1D1: iconst_1
		// @1D2: ireturn
		// @1D3: iconst_0
		// @1D4: ireturn
		// @1D5: astore_3
		// @1D6: aload_3
		// @1D7: new java.lang.StringBuilder
		// @1DA: dup
		// @1DB: invokespecial java.lang.StringBuilder.<init>()void
		// @1DE: getstatic java.lang.String[] game.C_100067_vd.field_104333_z
		// @1E1: iconst_5
		// @1E2: aaload
		// @1E3: invokevirtual java.lang.StringBuilder.append(java.lang.String)java.lang.StringBuilder
		// @1E6: iload_1
		// @1E7: invokevirtual java.lang.StringBuilder.append(int)java.lang.StringBuilder
		// @1EA: bipush 44 (0x2C)
		// @1EC: invokevirtual java.lang.StringBuilder.append(char)java.lang.StringBuilder
		// @1EF: aload_2
		// @1F0: ifnull @1FC
		// @1F3: getstatic java.lang.String[] game.C_100067_vd.field_104333_z
		// @1F6: iconst_0
		// @1F7: aaload
		// @1F8: goto @201
		// @1FB: athrow
		// @1FC: getstatic java.lang.String[] game.C_100067_vd.field_104333_z
		// @1FF: iconst_2
		// @200: aaload
		// @201: invokevirtual java.lang.StringBuilder.append(java.lang.String)java.lang.StringBuilder
		// @204: bipush 41 (0x29)
		// @206: invokevirtual java.lang.StringBuilder.append(char)java.lang.StringBuilder
		// @209: invokevirtual java.lang.StringBuilder.toString()java.lang.String
		// @20C: invokestatic game.C_100181_cf.func_105695_a(java.lang.Throwable, java.lang.String)game.C_100170_cm
		// @20F: athrow
	}
	
	public static void func_104309_b(byte arg0)
	{
		// @00: aconst_null
		// @01: putstatic java.lang.String[] game.C_100067_vd.field_104311_g
		// @04: aconst_null
		// @05: putstatic game.C_100292_jk game.C_100067_vd.field_104315_c
		// @08: aconst_null
		// @09: putstatic int[] game.C_100067_vd.field_104321_j
		// @0C: aconst_null
		// @0D: putstatic java.util.Random game.C_100067_vd.field_104322_k
		// @10: iload_0
		// @11: bipush 13 (0x0D)
		// @13: if_icmpge @21
		// @16: aconst_null
		// @17: checkcast game.C_100292_jk
		// @1A: putstatic game.C_100292_jk game.C_100067_vd.field_104315_c
		// @1D: goto @21
		// @20: athrow
		// @21: aconst_null
		// @22: putstatic java.lang.String game.C_100067_vd.field_104317_n
		// @25: aconst_null
		// @26: putstatic game.C_100302_ka[] game.C_100067_vd.field_104323_h
		// @29: goto @4E
		// @2C: astore_1
		// @2D: aload_1
		// @2E: new java.lang.StringBuilder
		// @31: dup
		// @32: invokespecial java.lang.StringBuilder.<init>()void
		// @35: getstatic java.lang.String[] game.C_100067_vd.field_104333_z
		// @38: bipush 6 (0x06)
		// @3A: aaload
		// @3B: invokevirtual java.lang.StringBuilder.append(java.lang.String)java.lang.StringBuilder
		// @3E: iload_0
		// @3F: invokevirtual java.lang.StringBuilder.append(int)java.lang.StringBuilder
		// @42: bipush 41 (0x29)
		// @44: invokevirtual java.lang.StringBuilder.append(char)java.lang.StringBuilder
		// @47: invokevirtual java.lang.StringBuilder.toString()java.lang.String
		// @4A: invokestatic game.C_100181_cf.func_105695_a(java.lang.Throwable, java.lang.String)game.C_100170_cm
		// @4D: athrow
		// @4E: return
	}
	
	static final String func_104299_a(byte arg0, int arg1)
	{
		// @000: getstatic int game.SteelSentinels.field_105275_O
		// @003: istore #10
		// @005: iload_0
		// @006: bipush -94 (0xA2)
		// @008: if_icmpeq @010
		// @00B: aconst_null
		// @00C: checkcast java.lang.String
		// @00F: areturn
		// @010: iload_1
		// @011: bipush -72 (0xB8)
		// @013: invokestatic game.C_100209_qb.func_102686_b(int, byte)game.C_100327_ib
		// @016: astore_2
		// @017: aload_2
		// @018: getfield int game.C_100327_ib.field_102497_w
		// @01B: istore_3
		// @01C: bipush -3 (0xFD)
		// @01E: iload_3
		// @01F: iconst_m1
		// @020: ixor
		// @021: if_icmpne @02D
		// @024: iload #10
		// @026: ifeq @05D
		// @029: goto @02D
		// @02C: athrow
		// @02D: bipush -5 (0xFB)
		// @02F: iload_3
		// @030: iconst_m1
		// @031: ixor
		// @032: if_icmpeq @0CF
		// @035: goto @039
		// @038: athrow
		// @039: iload_3
		// @03A: iconst_m1
		// @03B: ixor
		// @03C: sipush -2049 (0xF7FF)
		// @03F: if_icmpne @04F
		// @042: goto @046
		// @045: athrow
		// @046: iload #10
		// @048: ifeq @0CF
		// @04B: goto @04F
		// @04E: athrow
		// @04F: bipush 8 (0x08)
		// @051: iload_3
		// @052: if_icmpeq @13F
		// @055: goto @059
		// @058: athrow
		// @059: goto @2CF
		// @05C: athrow
		// @05D: iconst_0
		// @05E: istore_3
		// @05F: iload_3
		// @060: iconst_m1
		// @061: ixor
		// @062: getstatic int[] game.C_100017_wj.field_103821_j
		// @065: arraylength
		// @066: iconst_m1
		// @067: ixor
		// @068: if_icmple @0CA
		// @06B: getstatic int[] game.C_100017_wj.field_103821_j
		// @06E: iload_3
		// @06F: iaload
		// @070: istore #4
		// @072: bipush 103 (0x67)
		// @074: iload #4
		// @076: invokestatic game.C_100042_we.func_104129_b(int, int)int[]
		// @079: astore #5
		// @07B: iload #10
		// @07D: ifne @2CF
		// @080: iconst_0
		// @081: istore #6
		// @083: iload #6
		// @085: iconst_m1
		// @086: ixor
		// @087: bipush -8 (0xF8)
		// @089: aload #5
		// @08B: arraylength
		// @08C: iadd
		// @08D: iconst_m1
		// @08E: ixor
		// @08F: if_icmple @0C2
		// @092: aload #5
		// @094: iload #6
		// @096: iaload
		// @097: iconst_m1
		// @098: ixor
		// @099: iload_1
		// @09A: iconst_m1
		// @09B: ixor
		// @09C: iload #10
		// @09E: ifne @068
		// @0A1: if_icmpne @0BA
		// @0A4: sipush -30945 (0x871F)
		// @0A7: iconst_1
		// @0A8: anewarray java.lang.String
		// @0AB: dup
		// @0AC: iconst_0
		// @0AD: getstatic java.lang.String[] game.C_100179_ch.field_100813_l
		// @0B0: iload_3
		// @0B1: aaload
		// @0B2: aastore
		// @0B3: getstatic java.lang.String game.C_100233_oa.field_106246_l
		// @0B6: invokestatic game.C_100132_td.func_104965_a(int, java.lang.String[], java.lang.String)java.lang.String
		// @0B9: areturn
		// @0BA: iinc #6 +1
		// @0BD: iload #10
		// @0BF: ifeq @083
		// @0C2: iinc #3 +1
		// @0C5: iload #10
		// @0C7: ifeq @05F
		// @0CA: iload #10
		// @0CC: ifeq @2CF
		// @0CF: iconst_0
		// @0D0: istore_3
		// @0D1: iload_3
		// @0D2: iconst_m1
		// @0D3: ixor
		// @0D4: getstatic int[] game.C_100017_wj.field_103821_j
		// @0D7: arraylength
		// @0D8: iconst_m1
		// @0D9: ixor
		// @0DA: if_icmple @13A
		// @0DD: getstatic int[] game.C_100017_wj.field_103821_j
		// @0E0: iload_3
		// @0E1: iaload
		// @0E2: istore #4
		// @0E4: iload_0
		// @0E5: sipush 157 (0x009D)
		// @0E8: iadd
		// @0E9: iload #4
		// @0EB: invokestatic game.C_100042_we.func_104129_b(int, int)int[]
		// @0EE: astore #5
		// @0F0: iload #10
		// @0F2: ifne @2CF
		// @0F5: iconst_0
		// @0F6: istore #6
		// @0F8: iload #6
		// @0FA: bipush -8 (0xF8)
		// @0FC: aload #5
		// @0FE: arraylength
		// @0FF: iadd
		// @100: if_icmpge @132
		// @103: aload #5
		// @105: iload #6
		// @107: iaload
		// @108: iload_1
		// @109: iload #10
		// @10B: ifne @0DA
		// @10E: if_icmpeq @114
		// @111: goto @12A
		// @114: sipush -30945 (0x871F)
		// @117: iconst_1
		// @118: anewarray java.lang.String
		// @11B: dup
		// @11C: iconst_0
		// @11D: getstatic java.lang.String[] game.C_100179_ch.field_100813_l
		// @120: iload_3
		// @121: aaload
		// @122: aastore
		// @123: getstatic java.lang.String game.C_100118_ub.field_102057_ac
		// @126: invokestatic game.C_100132_td.func_104965_a(int, java.lang.String[], java.lang.String)java.lang.String
		// @129: areturn
		// @12A: iinc #6 +1
		// @12D: iload #10
		// @12F: ifeq @0F8
		// @132: iinc #3 +1
		// @135: iload #10
		// @137: ifeq @0D1
		// @13A: iload #10
		// @13C: ifeq @2CF
		// @13F: iconst_0
		// @140: istore_3
		// @141: iconst_0
		// @142: istore #4
		// @144: iload #4
		// @146: iconst_m1
		// @147: ixor
		// @148: getstatic int[] game.C_100017_wj.field_103821_j
		// @14B: arraylength
		// @14C: iconst_m1
		// @14D: ixor
		// @14E: if_icmple @1A6
		// @151: getstatic int[] game.C_100017_wj.field_103821_j
		// @154: iload #4
		// @156: iaload
		// @157: istore #5
		// @159: bipush 117 (0x75)
		// @15B: iload #5
		// @15D: invokestatic game.C_100042_we.func_104129_b(int, int)int[]
		// @160: astore #6
		// @162: iload #10
		// @164: ifne @2CF
		// @167: iconst_0
		// @168: istore #7
		// @16A: iload #7
		// @16C: aload #6
		// @16E: arraylength
		// @16F: bipush 8 (0x08)
		// @171: isub
		// @172: if_icmpge @19E
		// @175: iload_1
		// @176: iconst_m1
		// @177: ixor
		// @178: aload #6
		// @17A: iload #7
		// @17C: iaload
		// @17D: iconst_m1
		// @17E: ixor
		// @17F: iload #10
		// @181: ifne @14E
		// @184: if_icmpeq @18A
		// @187: goto @192
		// @18A: iinc #3 +1
		// @18D: iload #10
		// @18F: ifeq @19E
		// @192: iinc #7 +1
		// @195: iload #10
		// @197: ifeq @16A
		// @19A: goto @19E
		// @19D: athrow
		// @19E: iinc #4 +1
		// @1A1: iload #10
		// @1A3: ifeq @144
		// @1A6: getstatic java.lang.String[] game.C_100260_mc.field_102223_dc
		// @1A9: iconst_0
		// @1AA: aaload
		// @1AB: astore #4
		// @1AD: iconst_0
		// @1AE: istore #5
		// @1B0: iconst_0
		// @1B1: istore #6
		// @1B3: getstatic int[] game.C_100017_wj.field_103821_j
		// @1B6: arraylength
		// @1B7: iconst_m1
		// @1B8: ixor
		// @1B9: iload #6
		// @1BB: iconst_m1
		// @1BC: ixor
		// @1BD: if_icmpge @2CC
		// @1C0: getstatic int[] game.C_100017_wj.field_103821_j
		// @1C3: iload #6
		// @1C5: iaload
		// @1C6: istore #7
		// @1C8: bipush -25 (0xE7)
		// @1CA: iload #7
		// @1CC: invokestatic game.C_100042_we.func_104129_b(int, int)int[]
		// @1CF: astore #8
		// @1D1: iload #10
		// @1D3: ifne @2CF
		// @1D6: iconst_0
		// @1D7: istore #9
		// @1D9: iload #9
		// @1DB: iconst_m1
		// @1DC: ixor
		// @1DD: aload #8
		// @1DF: arraylength
		// @1E0: bipush -8 (0xF8)
		// @1E2: iadd
		// @1E3: iconst_m1
		// @1E4: ixor
		// @1E5: if_icmple @2C4
		// @1E8: iload_1
		// @1E9: iconst_m1
		// @1EA: ixor
		// @1EB: aload #8
		// @1ED: iload #9
		// @1EF: iaload
		// @1F0: iconst_m1
		// @1F1: ixor
		// @1F2: iload #10
		// @1F4: ifne @1BD
		// @1F7: if_icmpeq @1FD
		// @1FA: goto @2B8
		// @1FD: iinc #5 +1
		// @200: iload #5
		// @202: iconst_m1
		// @203: ixor
		// @204: iconst_m1
		// @205: iload_3
		// @206: iadd
		// @207: iconst_m1
		// @208: ixor
		// @209: if_icmpgt @291
		// @20C: iload_3
		// @20D: iconst_1
		// @20E: isub
		// @20F: iconst_m1
		// @210: ixor
		// @211: iload #5
		// @213: iconst_m1
		// @214: ixor
		// @215: if_icmpeq @26A
		// @218: goto @21C
		// @21B: athrow
		// @21C: iload_3
		// @21D: iconst_m1
		// @21E: ixor
		// @21F: bipush -2 (0xFE)
		// @221: if_icmpge @249
		// @224: goto @228
		// @227: athrow
		// @228: new java.lang.StringBuilder
		// @22B: dup
		// @22C: invokespecial java.lang.StringBuilder.<init>()void
		// @22F: aload #4
		// @231: invokevirtual java.lang.StringBuilder.append(java.lang.String)java.lang.StringBuilder
		// @234: getstatic java.lang.String[] game.C_100179_ch.field_100813_l
		// @237: iload #6
		// @239: aaload
		// @23A: invokevirtual java.lang.StringBuilder.append(java.lang.String)java.lang.StringBuilder
		// @23D: getstatic java.lang.String[] game.C_100260_mc.field_102223_dc
		// @240: iconst_4
		// @241: aaload
		// @242: invokevirtual java.lang.StringBuilder.append(java.lang.String)java.lang.StringBuilder
		// @245: invokevirtual java.lang.StringBuilder.toString()java.lang.String
		// @248: areturn
		// @249: new java.lang.StringBuilder
		// @24C: dup
		// @24D: invokespecial java.lang.StringBuilder.<init>()void
		// @250: aload #4
		// @252: invokevirtual java.lang.StringBuilder.append(java.lang.String)java.lang.StringBuilder
		// @255: getstatic java.lang.String[] game.C_100179_ch.field_100813_l
		// @258: iload #6
		// @25A: aaload
		// @25B: invokevirtual java.lang.StringBuilder.append(java.lang.String)java.lang.StringBuilder
		// @25E: getstatic java.lang.String[] game.C_100260_mc.field_102223_dc
		// @261: iconst_3
		// @262: aaload
		// @263: invokevirtual java.lang.StringBuilder.append(java.lang.String)java.lang.StringBuilder
		// @266: invokevirtual java.lang.StringBuilder.toString()java.lang.String
		// @269: areturn
		// @26A: new java.lang.StringBuilder
		// @26D: dup
		// @26E: invokespecial java.lang.StringBuilder.<init>()void
		// @271: aload #4
		// @273: invokevirtual java.lang.StringBuilder.append(java.lang.String)java.lang.StringBuilder
		// @276: getstatic java.lang.String[] game.C_100179_ch.field_100813_l
		// @279: iload #6
		// @27B: aaload
		// @27C: invokevirtual java.lang.StringBuilder.append(java.lang.String)java.lang.StringBuilder
		// @27F: getstatic java.lang.String[] game.C_100260_mc.field_102223_dc
		// @282: iconst_2
		// @283: aaload
		// @284: invokevirtual java.lang.StringBuilder.append(java.lang.String)java.lang.StringBuilder
		// @287: invokevirtual java.lang.StringBuilder.toString()java.lang.String
		// @28A: astore #4
		// @28C: iload #10
		// @28E: ifeq @2C4
		// @291: new java.lang.StringBuilder
		// @294: dup
		// @295: invokespecial java.lang.StringBuilder.<init>()void
		// @298: aload #4
		// @29A: invokevirtual java.lang.StringBuilder.append(java.lang.String)java.lang.StringBuilder
		// @29D: getstatic java.lang.String[] game.C_100179_ch.field_100813_l
		// @2A0: iload #6
		// @2A2: aaload
		// @2A3: invokevirtual java.lang.StringBuilder.append(java.lang.String)java.lang.StringBuilder
		// @2A6: getstatic java.lang.String[] game.C_100260_mc.field_102223_dc
		// @2A9: iconst_1
		// @2AA: aaload
		// @2AB: invokevirtual java.lang.StringBuilder.append(java.lang.String)java.lang.StringBuilder
		// @2AE: invokevirtual java.lang.StringBuilder.toString()java.lang.String
		// @2B1: astore #4
		// @2B3: iload #10
		// @2B5: ifeq @2C4
		// @2B8: iinc #9 +1
		// @2BB: iload #10
		// @2BD: ifeq @1D9
		// @2C0: goto @2C4
		// @2C3: athrow
		// @2C4: iinc #6 +1
		// @2C7: iload #10
		// @2C9: ifeq @1B3
		// @2CC: goto @2CF
		// @2CF: aconst_null
		// @2D0: areturn
		// @2D1: astore_2
		// @2D2: aload_2
		// @2D3: new java.lang.StringBuilder
		// @2D6: dup
		// @2D7: invokespecial java.lang.StringBuilder.<init>()void
		// @2DA: getstatic java.lang.String[] game.C_100067_vd.field_104333_z
		// @2DD: bipush 9 (0x09)
		// @2DF: aaload
		// @2E0: invokevirtual java.lang.StringBuilder.append(java.lang.String)java.lang.StringBuilder
		// @2E3: iload_0
		// @2E4: invokevirtual java.lang.StringBuilder.append(int)java.lang.StringBuilder
		// @2E7: bipush 44 (0x2C)
		// @2E9: invokevirtual java.lang.StringBuilder.append(char)java.lang.StringBuilder
		// @2EC: iload_1
		// @2ED: invokevirtual java.lang.StringBuilder.append(int)java.lang.StringBuilder
		// @2F0: bipush 41 (0x29)
		// @2F2: invokevirtual java.lang.StringBuilder.append(char)java.lang.StringBuilder
		// @2F5: invokevirtual java.lang.StringBuilder.toString()java.lang.String
		// @2F8: invokestatic game.C_100181_cf.func_105695_a(java.lang.Throwable, java.lang.String)game.C_100170_cm
		// @2FB: athrow
	}
	
	final void func_104301_b(int arg0)
	{
		// @00: aload_0
		// @01: getfield java.lang.String game.C_100067_vd.field_104316_a
		// @04: aload_0
		// @05: getfield int game.C_100067_vd.field_104314_b
		// @08: ldc 1071146 (0x10582a)
		// @0A: aload_0
		// @0B: getfield boolean game.C_100067_vd.field_104325_w
		// @0E: ifne @16
		// @11: aconst_null
		// @12: goto @19
		// @15: athrow
		// @16: getstatic java.lang.String[] game.C_100136_th.field_102616_U
		// @19: aload_0
		// @1A: getfield int game.C_100067_vd.field_104320_m
		// @1D: aload_0
		// @1E: getfield game.C_100037_wb game.C_100067_vd.field_104326_v
		// @21: aload_0
		// @22: getfield int game.C_100067_vd.field_104331_q
		// @25: iconst_m1
		// @26: iconst_0
		// @27: aload_0
		// @28: getfield int game.C_100067_vd.field_104327_u
		// @2B: invokestatic game.C_100138_bo.func_100397_a(java.lang.String, int, int, java.lang.String[], int, game.C_100037_wb, int, int, boolean, int)int
		// @2E: istore_2
		// @2F: iload_2
		// @30: iconst_m1
		// @31: ixor
		// @32: iconst_m1
		// @33: if_icmpgt @57
		// @36: aload_0
		// @37: getfield boolean game.C_100067_vd.field_104313_e
		// @3A: ifeq @45
		// @3D: goto @41
		// @40: athrow
		// @41: goto @4C
		// @44: athrow
		// @45: bipush 97 (0x61)
		// @47: bipush 8 (0x08)
		// @49: invokestatic game.C_100278_nd.func_101196_k(int, int)void
		// @4C: aload_0
		// @4D: iconst_1
		// @4E: putfield boolean game.C_100067_vd.field_104313_e
		// @51: getstatic int game.SteelSentinels.field_105275_O
		// @54: ifeq @60
		// @57: aload_0
		// @58: iconst_0
		// @59: putfield boolean game.C_100067_vd.field_104313_e
		// @5C: goto @60
		// @5F: athrow
		// @60: aload_0
		// @61: bipush 119 (0x77)
		// @63: invokespecial game.C_100067_vd.func_104306_d(byte)game.C_100302_ka
		// @66: astore_3
		// @67: aconst_null
		// @68: aload_3
		// @69: if_acmpeq @9E
		// @6C: aload_0
		// @6D: getfield game.C_100037_wb[] game.C_100067_vd.field_104329_s
		// @70: ifnull @7B
		// @73: goto @77
		// @76: athrow
		// @77: goto @83
		// @7A: athrow
		// @7B: aload_0
		// @7C: aload_3
		// @7D: getfield game.C_100037_wb[] game.C_100302_ka.field_101862_T
		// @80: putfield game.C_100037_wb[] game.C_100067_vd.field_104329_s
		// @83: aload_3
		// @84: getstatic int game.C_100066_dl.field_101636_H
		// @87: bipush 32 (0x20)
		// @89: irem
		// @8A: bipush 16 (0x10)
		// @8C: if_icmplt @97
		// @8F: aload_0
		// @90: getfield game.C_100037_wb[] game.C_100067_vd.field_104318_o
		// @93: goto @9B
		// @96: athrow
		// @97: aload_0
		// @98: getfield game.C_100037_wb[] game.C_100067_vd.field_104329_s
		// @9B: putfield game.C_100037_wb[] game.C_100302_ka.field_101862_T
		// @9E: iload_1
		// @9F: bipush -105 (0x97)
		// @A1: if_icmplt @AD
		// @A4: bipush -7 (0xF9)
		// @A6: putstatic int game.C_100067_vd.field_104324_i
		// @A9: goto @AD
		// @AC: athrow
		// @AD: goto @D2
		// @B0: astore_2
		// @B1: aload_2
		// @B2: new java.lang.StringBuilder
		// @B5: dup
		// @B6: invokespecial java.lang.StringBuilder.<init>()void
		// @B9: getstatic java.lang.String[] game.C_100067_vd.field_104333_z
		// @BC: bipush 12 (0x0C)
		// @BE: aaload
		// @BF: invokevirtual java.lang.StringBuilder.append(java.lang.String)java.lang.StringBuilder
		// @C2: iload_1
		// @C3: invokevirtual java.lang.StringBuilder.append(int)java.lang.StringBuilder
		// @C6: bipush 41 (0x29)
		// @C8: invokevirtual java.lang.StringBuilder.append(char)java.lang.StringBuilder
		// @CB: invokevirtual java.lang.StringBuilder.toString()java.lang.String
		// @CE: invokestatic game.C_100181_cf.func_105695_a(java.lang.Throwable, java.lang.String)game.C_100170_cm
		// @D1: athrow
		// @D2: return
	}
	
	static final String func_104308_a(byte arg0, String arg1)
	{
		// @000: getstatic int game.SteelSentinels.field_105275_O
		// @003: istore #7
		// @005: aload_1
		// @006: ifnull @011
		// @009: aload_1
		// @00A: invokevirtual java.lang.String.length()int
		// @00D: goto @012
		// @010: athrow
		// @011: iconst_0
		// @012: istore_2
		// @013: iload_2
		// @014: ifeq @01B
		// @017: goto @01D
		// @01A: athrow
		// @01B: aload_1
		// @01C: areturn
		// @01D: iload_2
		// @01E: newarray char[]
		// @020: astore_3
		// @021: iload_0
		// @022: iconst_2
		// @023: if_icmpgt @031
		// @026: aconst_null
		// @027: checkcast game.C_100292_jk
		// @02A: putstatic game.C_100292_jk game.C_100067_vd.field_104315_c
		// @02D: goto @031
		// @030: athrow
		// @031: iconst_0
		// @032: istore #4
		// @034: iconst_0
		// @035: istore #5
		// @037: iconst_0
		// @038: istore #6
		// @03A: iload #6
		// @03C: iconst_m1
		// @03D: ixor
		// @03E: iload_2
		// @03F: iconst_m1
		// @040: ixor
		// @041: if_icmple @0C4
		// @044: aload_3
		// @045: iload #6
		// @047: aload_1
		// @048: iload #6
		// @04A: invokevirtual java.lang.String.charAt(int)char
		// @04D: castore
		// @04E: aload_3
		// @04F: iload #6
		// @051: caload
		// @052: iconst_m1
		// @053: ixor
		// @054: bipush -61 (0xC3)
		// @056: if_icmpeq @0B5
		// @059: bipush 62 (0x3E)
		// @05B: aload_3
		// @05C: iload #6
		// @05E: caload
		// @05F: if_icmpne @072
		// @062: goto @066
		// @065: athrow
		// @066: iconst_m1
		// @067: iload #4
		// @069: iconst_m1
		// @06A: ixor
		// @06B: if_icmpgt @0A9
		// @06E: goto @072
		// @071: athrow
		// @072: iload #4
		// @074: ifne @0BC
		// @077: goto @07B
		// @07A: athrow
		// @07B: iload #5
		// @07D: ifne @0BC
		// @080: goto @084
		// @083: athrow
		// @084: aload_3
		// @085: iload #6
		// @087: caload
		// @088: invokestatic java.lang.Character.isWhitespace(char)boolean
		// @08B: ifeq @096
		// @08E: goto @092
		// @091: athrow
		// @092: goto @0BC
		// @095: athrow
		// @096: aload_3
		// @097: iload #6
		// @099: aload_3
		// @09A: iload #6
		// @09C: caload
		// @09D: invokestatic java.lang.Character.toUpperCase(char)char
		// @0A0: castore
		// @0A1: iconst_1
		// @0A2: istore #5
		// @0A4: iload #7
		// @0A6: ifeq @0BC
		// @0A9: iinc #4 +255
		// @0AC: iload #7
		// @0AE: ifeq @0BC
		// @0B1: goto @0B5
		// @0B4: athrow
		// @0B5: iinc #4 +1
		// @0B8: goto @0BC
		// @0BB: athrow
		// @0BC: iinc #6 +1
		// @0BF: iload #7
		// @0C1: ifeq @03A
		// @0C4: new java.lang.String
		// @0C7: dup
		// @0C8: aload_3
		// @0C9: invokespecial java.lang.String.<init>(char[])void
		// @0CC: areturn
		// @0CD: astore_2
		// @0CE: aload_2
		// @0CF: new java.lang.StringBuilder
		// @0D2: dup
		// @0D3: invokespecial java.lang.StringBuilder.<init>()void
		// @0D6: getstatic java.lang.String[] game.C_100067_vd.field_104333_z
		// @0D9: bipush 8 (0x08)
		// @0DB: aaload
		// @0DC: invokevirtual java.lang.StringBuilder.append(java.lang.String)java.lang.StringBuilder
		// @0DF: iload_0
		// @0E0: invokevirtual java.lang.StringBuilder.append(int)java.lang.StringBuilder
		// @0E3: bipush 44 (0x2C)
		// @0E5: invokevirtual java.lang.StringBuilder.append(char)java.lang.StringBuilder
		// @0E8: aload_1
		// @0E9: ifnull @0F5
		// @0EC: getstatic java.lang.String[] game.C_100067_vd.field_104333_z
		// @0EF: iconst_0
		// @0F0: aaload
		// @0F1: goto @0FA
		// @0F4: athrow
		// @0F5: getstatic java.lang.String[] game.C_100067_vd.field_104333_z
		// @0F8: iconst_2
		// @0F9: aaload
		// @0FA: invokevirtual java.lang.StringBuilder.append(java.lang.String)java.lang.StringBuilder
		// @0FD: bipush 41 (0x29)
		// @0FF: invokevirtual java.lang.StringBuilder.append(char)java.lang.StringBuilder
		// @102: invokevirtual java.lang.StringBuilder.toString()java.lang.String
		// @105: invokestatic game.C_100181_cf.func_105695_a(java.lang.Throwable, java.lang.String)game.C_100170_cm
		// @108: athrow
	}
	
	C_100067_vd(int arg0, int arg1, int arg2, int arg3, int arg4, C_100037_wb arg5, boolean arg6)
	{
		// @00: aload_0
		// @01: getstatic java.lang.String[] game.C_100330_ig.field_107286_e
		// @04: iload_1
		// @05: aaload
		// @06: iload_2
		// @07: iload_3
		// @08: iload #4
		// @0A: iload #5
		// @0C: aload #6
		// @0E: iload #7
		// @10: invokespecial game.C_100067_vd.<init>(java.lang.String, int, int, int, int, game.C_100037_wb, boolean)void
		// @13: aload_0
		// @14: iload_1
		// @15: putfield int game.C_100067_vd.field_104310_f
		// @18: goto @89
		// @1B: astore #8
		// @1D: aload #8
		// @1F: new java.lang.StringBuilder
		// @22: dup
		// @23: invokespecial java.lang.StringBuilder.<init>()void
		// @26: getstatic java.lang.String[] game.C_100067_vd.field_104333_z
		// @29: iconst_1
		// @2A: aaload
		// @2B: invokevirtual java.lang.StringBuilder.append(java.lang.String)java.lang.StringBuilder
		// @2E: iload_1
		// @2F: invokevirtual java.lang.StringBuilder.append(int)java.lang.StringBuilder
		// @32: bipush 44 (0x2C)
		// @34: invokevirtual java.lang.StringBuilder.append(char)java.lang.StringBuilder
		// @37: iload_2
		// @38: invokevirtual java.lang.StringBuilder.append(int)java.lang.StringBuilder
		// @3B: bipush 44 (0x2C)
		// @3D: invokevirtual java.lang.StringBuilder.append(char)java.lang.StringBuilder
		// @40: iload_3
		// @41: invokevirtual java.lang.StringBuilder.append(int)java.lang.StringBuilder
		// @44: bipush 44 (0x2C)
		// @46: invokevirtual java.lang.StringBuilder.append(char)java.lang.StringBuilder
		// @49: iload #4
		// @4B: invokevirtual java.lang.StringBuilder.append(int)java.lang.StringBuilder
		// @4E: bipush 44 (0x2C)
		// @50: invokevirtual java.lang.StringBuilder.append(char)java.lang.StringBuilder
		// @53: iload #5
		// @55: invokevirtual java.lang.StringBuilder.append(int)java.lang.StringBuilder
		// @58: bipush 44 (0x2C)
		// @5A: invokevirtual java.lang.StringBuilder.append(char)java.lang.StringBuilder
		// @5D: aload #6
		// @5F: ifnull @6B
		// @62: getstatic java.lang.String[] game.C_100067_vd.field_104333_z
		// @65: iconst_0
		// @66: aaload
		// @67: goto @70
		// @6A: athrow
		// @6B: getstatic java.lang.String[] game.C_100067_vd.field_104333_z
		// @6E: iconst_2
		// @6F: aaload
		// @70: invokevirtual java.lang.StringBuilder.append(java.lang.String)java.lang.StringBuilder
		// @73: bipush 44 (0x2C)
		// @75: invokevirtual java.lang.StringBuilder.append(char)java.lang.StringBuilder
		// @78: iload #7
		// @7A: invokevirtual java.lang.StringBuilder.append(boolean)java.lang.StringBuilder
		// @7D: bipush 41 (0x29)
		// @7F: invokevirtual java.lang.StringBuilder.append(char)java.lang.StringBuilder
		// @82: invokevirtual java.lang.StringBuilder.toString()java.lang.String
		// @85: invokestatic game.C_100181_cf.func_105695_a(java.lang.Throwable, java.lang.String)game.C_100170_cm
		// @88: athrow
		// @89: return
	}
	
	final boolean func_104298_a(int arg0, int arg1)
	{
		// @00: getstatic int game.SteelSentinels.field_105275_O
		// @03: istore #4
		// @05: iload_2
		// @06: bipush -2 (0xFE)
		// @08: if_icmpeq @16
		// @0B: aconst_null
		// @0C: checkcast java.lang.String[]
		// @0F: putstatic java.lang.String[] game.C_100067_vd.field_104311_g
		// @12: goto @16
		// @15: athrow
		// @16: aload_0
		// @17: getfield int game.C_100067_vd.field_104310_f
		// @1A: istore_3
		// @1B: iconst_4
		// @1C: iload_3
		// @1D: if_icmpeq @4B
		// @20: iload_3
		// @21: bipush 6 (0x06)
		// @23: if_icmpeq @4B
		// @26: goto @2A
		// @29: athrow
		// @2A: bipush -12 (0xF4)
		// @2C: iload_3
		// @2D: iconst_m1
		// @2E: ixor
		// @2F: if_icmpeq @4B
		// @32: goto @36
		// @35: athrow
		// @36: bipush -16 (0xF0)
		// @38: iload_3
		// @39: iconst_m1
		// @3A: ixor
		// @3B: if_icmpne @78
		// @3E: goto @42
		// @41: athrow
		// @42: iload #4
		// @44: ifeq @5F
		// @47: goto @4B
		// @4A: athrow
		// @4B: aload_0
		// @4C: iconst_1
		// @4D: putfield boolean game.C_100067_vd.field_104325_w
		// @50: aload_0
		// @51: bipush 119 (0x77)
		// @53: invokespecial game.C_100067_vd.func_104303_a(int)void
		// @56: iload #4
		// @58: ifeq @78
		// @5B: goto @5F
		// @5E: athrow
		// @5F: getstatic boolean game.C_100064_ve.field_103011_A
		// @62: ifne @6D
		// @65: goto @69
		// @68: athrow
		// @69: goto @78
		// @6C: athrow
		// @6D: aload_0
		// @6E: iconst_1
		// @6F: putfield boolean game.C_100067_vd.field_104325_w
		// @72: aload_0
		// @73: bipush 96 (0x60)
		// @75: invokespecial game.C_100067_vd.func_104303_a(int)void
		// @78: iconst_1
		// @79: ireturn
		// @7A: astore_3
		// @7B: aload_3
		// @7C: new java.lang.StringBuilder
		// @7F: dup
		// @80: invokespecial java.lang.StringBuilder.<init>()void
		// @83: getstatic java.lang.String[] game.C_100067_vd.field_104333_z
		// @86: iconst_3
		// @87: aaload
		// @88: invokevirtual java.lang.StringBuilder.append(java.lang.String)java.lang.StringBuilder
		// @8B: iload_1
		// @8C: invokevirtual java.lang.StringBuilder.append(int)java.lang.StringBuilder
		// @8F: bipush 44 (0x2C)
		// @91: invokevirtual java.lang.StringBuilder.append(char)java.lang.StringBuilder
		// @94: iload_2
		// @95: invokevirtual java.lang.StringBuilder.append(int)java.lang.StringBuilder
		// @98: bipush 41 (0x29)
		// @9A: invokevirtual java.lang.StringBuilder.append(char)java.lang.StringBuilder
		// @9D: invokevirtual java.lang.StringBuilder.toString()java.lang.String
		// @A0: invokestatic game.C_100181_cf.func_105695_a(java.lang.Throwable, java.lang.String)game.C_100170_cm
		// @A3: athrow
	}
	
	private C_100067_vd(String arg0, int arg1, int arg2, int arg3, int arg4, C_100037_wb arg5, boolean arg6)
	{
		// @00: aload_0
		// @01: invokespecial java.lang.Object.<init>()void
		// @04: aload_0
		// @05: getstatic game.C_100037_wb[] game.C_100064_ve.field_103017_t
		// @08: putfield game.C_100037_wb[] game.C_100067_vd.field_104318_o
		// @0B: aload_0
		// @0C: bipush 8 (0x08)
		// @0E: putfield int game.C_100067_vd.field_104312_d
		// @11: aload_0
		// @12: getstatic game.C_100317_lb game.C_100318_hj.field_107197_e
		// @15: putfield game.C_100112_r game.C_100067_vd.field_104328_t
		// @18: aload_0
		// @19: iconst_m1
		// @1A: putfield int game.C_100067_vd.field_104310_f
		// @1D: aload_0
		// @1E: iconst_5
		// @1F: putfield int game.C_100067_vd.field_104330_r
		// @22: aload_0
		// @23: aload #6
		// @25: putfield game.C_100037_wb game.C_100067_vd.field_104326_v
		// @28: aload_0
		// @29: iload #7
		// @2B: putfield boolean game.C_100067_vd.field_104325_w
		// @2E: aload_0
		// @2F: iload #4
		// @31: putfield int game.C_100067_vd.field_104314_b
		// @34: aload_0
		// @35: iload_3
		// @36: putfield int game.C_100067_vd.field_104327_u
		// @39: aload_0
		// @3A: iload #5
		// @3C: putfield int game.C_100067_vd.field_104331_q
		// @3F: aload_0
		// @40: iload_2
		// @41: putfield int game.C_100067_vd.field_104320_m
		// @44: aload_0
		// @45: aload_1
		// @46: putfield java.lang.String game.C_100067_vd.field_104316_a
		// @49: aload_0
		// @4A: getfield int game.C_100067_vd.field_104331_q
		// @4D: ifne @56
		// @50: aload_0
		// @51: bipush 109 (0x6D)
		// @53: invokespecial game.C_100067_vd.func_104303_a(int)void
		// @56: goto @D8
		// @59: astore #8
		// @5B: aload #8
		// @5D: new java.lang.StringBuilder
		// @60: dup
		// @61: invokespecial java.lang.StringBuilder.<init>()void
		// @64: getstatic java.lang.String[] game.C_100067_vd.field_104333_z
		// @67: iconst_1
		// @68: aaload
		// @69: invokevirtual java.lang.StringBuilder.append(java.lang.String)java.lang.StringBuilder
		// @6C: aload_1
		// @6D: ifnull @79
		// @70: getstatic java.lang.String[] game.C_100067_vd.field_104333_z
		// @73: iconst_0
		// @74: aaload
		// @75: goto @7E
		// @78: athrow
		// @79: getstatic java.lang.String[] game.C_100067_vd.field_104333_z
		// @7C: iconst_2
		// @7D: aaload
		// @7E: invokevirtual java.lang.StringBuilder.append(java.lang.String)java.lang.StringBuilder
		// @81: bipush 44 (0x2C)
		// @83: invokevirtual java.lang.StringBuilder.append(char)java.lang.StringBuilder
		// @86: iload_2
		// @87: invokevirtual java.lang.StringBuilder.append(int)java.lang.StringBuilder
		// @8A: bipush 44 (0x2C)
		// @8C: invokevirtual java.lang.StringBuilder.append(char)java.lang.StringBuilder
		// @8F: iload_3
		// @90: invokevirtual java.lang.StringBuilder.append(int)java.lang.StringBuilder
		// @93: bipush 44 (0x2C)
		// @95: invokevirtual java.lang.StringBuilder.append(char)java.lang.StringBuilder
		// @98: iload #4
		// @9A: invokevirtual java.lang.StringBuilder.append(int)java.lang.StringBuilder
		// @9D: bipush 44 (0x2C)
		// @9F: invokevirtual java.lang.StringBuilder.append(char)java.lang.StringBuilder
		// @A2: iload #5
		// @A4: invokevirtual java.lang.StringBuilder.append(int)java.lang.StringBuilder
		// @A7: bipush 44 (0x2C)
		// @A9: invokevirtual java.lang.StringBuilder.append(char)java.lang.StringBuilder
		// @AC: aload #6
		// @AE: ifnull @BA
		// @B1: getstatic java.lang.String[] game.C_100067_vd.field_104333_z
		// @B4: iconst_0
		// @B5: aaload
		// @B6: goto @BF
		// @B9: athrow
		// @BA: getstatic java.lang.String[] game.C_100067_vd.field_104333_z
		// @BD: iconst_2
		// @BE: aaload
		// @BF: invokevirtual java.lang.StringBuilder.append(java.lang.String)java.lang.StringBuilder
		// @C2: bipush 44 (0x2C)
		// @C4: invokevirtual java.lang.StringBuilder.append(char)java.lang.StringBuilder
		// @C7: iload #7
		// @C9: invokevirtual java.lang.StringBuilder.append(boolean)java.lang.StringBuilder
		// @CC: bipush 41 (0x29)
		// @CE: invokevirtual java.lang.StringBuilder.append(char)java.lang.StringBuilder
		// @D1: invokevirtual java.lang.StringBuilder.toString()java.lang.String
		// @D4: invokestatic game.C_100181_cf.func_105695_a(java.lang.Throwable, java.lang.String)game.C_100170_cm
		// @D7: athrow
		// @D8: return
	}
	
	final void func_104307_c(byte arg0)
	{
		// @00: iconst_1
		// @01: putstatic boolean game.C_100309_lk.field_103271_ab
		// @04: iconst_1
		// @05: putstatic boolean game.C_100034_gi.field_104029_d
		// @08: aload_0
		// @09: bipush 35 (0x23)
		// @0B: invokespecial game.C_100067_vd.func_104306_d(byte)game.C_100302_ka
		// @0E: astore_2
		// @0F: aload_2
		// @10: ifnull @2A
		// @13: aload_0
		// @14: getfield game.C_100037_wb[] game.C_100067_vd.field_104329_s
		// @17: ifnonnull @22
		// @1A: goto @1E
		// @1D: athrow
		// @1E: goto @2A
		// @21: athrow
		// @22: aload_2
		// @23: aload_0
		// @24: getfield game.C_100037_wb[] game.C_100067_vd.field_104329_s
		// @27: putfield game.C_100037_wb[] game.C_100302_ka.field_101862_T
		// @2A: aload_0
		// @2B: aconst_null
		// @2C: putfield game.C_100037_wb[] game.C_100067_vd.field_104329_s
		// @2F: iload_1
		// @30: bipush 46 (0x2E)
		// @32: if_icmpgt @40
		// @35: aload_0
		// @36: bipush 125 (0x7D)
		// @38: invokevirtual game.C_100067_vd.func_104300_a(byte)boolean
		// @3B: pop
		// @3C: goto @40
		// @3F: athrow
		// @40: goto @65
		// @43: astore_2
		// @44: aload_2
		// @45: new java.lang.StringBuilder
		// @48: dup
		// @49: invokespecial java.lang.StringBuilder.<init>()void
		// @4C: getstatic java.lang.String[] game.C_100067_vd.field_104333_z
		// @4F: bipush 11 (0x0B)
		// @51: aaload
		// @52: invokevirtual java.lang.StringBuilder.append(java.lang.String)java.lang.StringBuilder
		// @55: iload_1
		// @56: invokevirtual java.lang.StringBuilder.append(int)java.lang.StringBuilder
		// @59: bipush 41 (0x29)
		// @5B: invokevirtual java.lang.StringBuilder.append(char)java.lang.StringBuilder
		// @5E: invokevirtual java.lang.StringBuilder.toString()java.lang.String
		// @61: invokestatic game.C_100181_cf.func_105695_a(java.lang.Throwable, java.lang.String)game.C_100170_cm
		// @64: athrow
		// @65: return
	}
	
	static
	{
		// @000: bipush 13 (0x0D)
		// @002: anewarray java.lang.String
		// @005: dup
		// @006: iconst_0
		// @007: ldc "Nw-\u0012\u001b"
		// @009: invokestatic game.C_100067_vd.func_104305_z(java.lang.String)char[]
		// @00C: invokestatic game.C_100067_vd.func_104304_z(char[])java.lang.String
		// @00F: aastore
		// @010: dup
		// @011: iconst_1
		// @012: ldc "C=-\u0000\u000f[0w\u0002N"
		// @014: invokestatic game.C_100067_vd.func_104305_z(java.lang.String)char[]
		// @017: invokestatic game.C_100067_vd.func_104304_z(char[])java.lang.String
		// @01A: aastore
		// @01B: dup
		// @01C: iconst_2
		// @01D: ldc "[,oP"
		// @01F: invokestatic game.C_100067_vd.func_104305_z(java.lang.String)char[]
		// @022: invokestatic game.C_100067_vd.func_104304_z(char[])java.lang.String
		// @025: aastore
		// @026: dup
		// @027: iconst_3
		// @028: ldc "C=-~N"
		// @02A: invokestatic game.C_100067_vd.func_104305_z(java.lang.String)char[]
		// @02D: invokestatic game.C_100067_vd.func_104304_z(char[])java.lang.String
		// @030: aastore
		// @031: dup
		// @032: iconst_4
		// @033: ldc "C=-\u007fN"
		// @035: invokestatic game.C_100067_vd.func_104305_z(java.lang.String)char[]
		// @038: invokestatic game.C_100067_vd.func_104304_z(char[])java.lang.String
		// @03B: aastore
		// @03C: dup
		// @03D: iconst_5
		// @03E: ldc "C=-uN"
		// @040: invokestatic game.C_100067_vd.func_104305_z(java.lang.String)char[]
		// @043: invokestatic game.C_100067_vd.func_104304_z(char[])java.lang.String
		// @046: aastore
		// @047: dup
		// @048: bipush 6 (0x06)
		// @04A: ldc "C=-{N"
		// @04C: invokestatic game.C_100067_vd.func_104305_z(java.lang.String)char[]
		// @04F: invokestatic game.C_100067_vd.func_104304_z(char[])java.lang.String
		// @052: aastore
		// @053: dup
		// @054: bipush 7 (0x07)
		// @056: ldc "C=-vN"
		// @058: invokestatic game.C_100067_vd.func_104305_z(java.lang.String)char[]
		// @05B: invokestatic game.C_100067_vd.func_104304_z(char[])java.lang.String
		// @05E: aastore
		// @05F: dup
		// @060: bipush 8 (0x08)
		// @062: ldc "C=-zN"
		// @064: invokestatic game.C_100067_vd.func_104305_z(java.lang.String)char[]
		// @067: invokestatic game.C_100067_vd.func_104304_z(char[])java.lang.String
		// @06A: aastore
		// @06B: dup
		// @06C: bipush 9 (0x09)
		// @06E: ldc "C=-}N"
		// @070: invokestatic game.C_100067_vd.func_104305_z(java.lang.String)char[]
		// @073: invokestatic game.C_100067_vd.func_104304_z(char[])java.lang.String
		// @076: aastore
		// @077: dup
		// @078: bipush 10 (0x0A)
		// @07A: ldc "C=-yN"
		// @07C: invokestatic game.C_100067_vd.func_104305_z(java.lang.String)char[]
		// @07F: invokestatic game.C_100067_vd.func_104304_z(char[])java.lang.String
		// @082: aastore
		// @083: dup
		// @084: bipush 11 (0x0B)
		// @086: ldc "C=-xN"
		// @088: invokestatic game.C_100067_vd.func_104305_z(java.lang.String)char[]
		// @08B: invokestatic game.C_100067_vd.func_104304_z(char[])java.lang.String
		// @08E: aastore
		// @08F: dup
		// @090: bipush 12 (0x0C)
		// @092: ldc "C=-tN"
		// @094: invokestatic game.C_100067_vd.func_104305_z(java.lang.String)char[]
		// @097: invokestatic game.C_100067_vd.func_104304_z(char[])java.lang.String
		// @09A: aastore
		// @09B: putstatic java.lang.String[] game.C_100067_vd.field_104333_z
		// @09E: new java.util.Random
		// @0A1: dup
		// @0A2: invokespecial java.util.Random.<init>()void
		// @0A5: putstatic java.util.Random game.C_100067_vd.field_104322_k
		// @0A8: iconst_2
		// @0A9: newarray int[]
		// @0AB: dup
		// @0AC: iconst_0
		// @0AD: bipush 100 (0x64)
		// @0AF: iastore
		// @0B0: dup
		// @0B1: iconst_1
		// @0B2: bipush 25 (0x19)
		// @0B4: iastore
		// @0B5: putstatic int[] game.C_100067_vd.field_104321_j
		// @0B8: bipush 46 (0x2E)
		// @0BA: anewarray java.lang.String
		// @0BD: dup
		// @0BE: iconst_0
		// @0BF: ldc "|7`N\u0003T*fOFL6vNFF<mH\u000f[<o\u001b\u0015\u0015)lK\u0003GydY\u0008P+bH\u000fZ7#Z\tGy?_\tYdeZ\u0000S?e\u0002U\u0005ypY\u0005Z7gOZ\u001a:lPX\u001b"
		// @0C1: invokestatic game.C_100067_vd.func_104305_z(java.lang.String)char[]
		// @0C4: invokestatic game.C_100067_vd.func_104304_z(char[])java.lang.String
		// @0C7: aastore
		// @0C8: dup
		// @0C9: iconst_1
		// @0CA: ldc "|7`N\u0003T*fOFL6vNFF<mH\u000f[<o\u001b\u0015\u0015)lK\u0003GydY\u0008P+bH\u000fZ7#Z\tGy?_\tYdeZ\u0000S?e\u0002U\u0005ypY\u0005Z7gOZ\u001a:lPX\u001b"
		// @0CC: invokestatic game.C_100067_vd.func_104305_z(java.lang.String)char[]
		// @0CF: invokestatic game.C_100067_vd.func_104304_z(char[])java.lang.String
		// @0D2: aastore
		// @0D3: dup
		// @0D4: iconst_2
		// @0D5: ldc "|7`N\u0003T*fOFL6vNFF<mH\u000f[<o\u001b\u0015\u0015)lK\u0003GydY\u0008P+bH\u000fZ7#Z\tGy?_\tYdeZ\u0000S?e\u0002U\u0005ypY\u0005Z7gOZ\u001a:lPX\u001b"
		// @0D7: invokestatic game.C_100067_vd.func_104305_z(java.lang.String)char[]
		// @0DA: invokestatic game.C_100067_vd.func_104304_z(char[])java.lang.String
		// @0DD: aastore
		// @0DE: dup
		// @0DF: iconst_3
		// @0E0: ldc "|7`N\u0003T*fOFL6vNFF<mH\u000f[<o\u001b\u0015\u0015)lK\u0003GydY\u0008P+bH\u000fZ7#Z\tGy?_\tYdeZ\u0000S?e\u0002U\u0005ypY\u0005Z7gOZ\u001a:lPX\u001b"
		// @0E2: invokestatic game.C_100067_vd.func_104305_z(java.lang.String)char[]
		// @0E5: invokestatic game.C_100067_vd.func_104304_z(char[])java.lang.String
		// @0E8: aastore
		// @0E9: dup
		// @0EA: iconst_4
		// @0EB: ldc "|7`N\u0003T*fOFL6vNFF<mH\u000f[<o\u001b\u0015\u0015)lK\u0003GydY\u0008P+bH\u000fZ7#Z\tGy?_\tYdeZ\u0000S?e\u0002U\u0005ypY\u0005Z7gOZ\u001a:lPX\u001b"
		// @0ED: invokestatic game.C_100067_vd.func_104305_z(java.lang.String)char[]
		// @0F0: invokestatic game.C_100067_vd.func_104304_z(char[])java.lang.String
		// @0F3: aastore
		// @0F4: dup
		// @0F5: iconst_5
		// @0F6: ldc "|7`N\u0003T*fOFL6vNFF<mH\u000f[<o\u001b\u0015\u0015<mY\u0014R #_\u0007E8`U\u0012LyeS\u0014\u0015e`S\n\u0008?eZ\u0000S?=\u000fV\u0015*f_\t[=p\u0000IV6o\u0002H"
		// @0F8: invokestatic game.C_100067_vd.func_104305_z(java.lang.String)char[]
		// @0FB: invokestatic game.C_100067_vd.func_104304_z(char[])java.lang.String
		// @0FE: aastore
		// @0FF: dup
		// @100: bipush 6 (0x06)
		// @102: ldc "|7`N\u0003T*fOFL6vNFF<mH\u000f[<o\u001b\u0015\u0015<mY\u0014R #_\u0007E8`U\u0012LyeS\u0014\u0015e`S\n\u0008?eZ\u0000S?=\u000fV\u0015*f_\t[=p\u0000IV6o\u0002H"
		// @104: invokestatic game.C_100067_vd.func_104305_z(java.lang.String)char[]
		// @107: invokestatic game.C_100067_vd.func_104304_z(char[])java.lang.String
		// @10A: aastore
		// @10B: dup
		// @10C: bipush 7 (0x07)
		// @10E: ldc "|7`N\u0003T*fOFL6vNFF<mH\u000f[<o\u001b\u0015\u0015<mY\u0014R #_\u0007E8`U\u0012LyeS\u0014\u0015e`S\n\u0008?eZ\u0000S?=\u000fV\u0015*f_\t[=p\u0000IV6o\u0002H"
		// @110: invokestatic game.C_100067_vd.func_104305_z(java.lang.String)char[]
		// @113: invokestatic game.C_100067_vd.func_104304_z(char[])java.lang.String
		// @116: aastore
		// @117: dup
		// @118: bipush 8 (0x08)
		// @11A: ldc "|7`N\u0003T*fOFL6vNFF<mH\u000f[<o\u001b\u0015\u0015<mY\u0014R #_\u0007E8`U\u0012LyeS\u0014\u0015e`S\n\u0008?eZ\u0000S?=\u000fV\u0015*f_\t[=p\u0000IV6o\u0002H"
		// @11C: invokestatic game.C_100067_vd.func_104305_z(java.lang.String)char[]
		// @11F: invokestatic game.C_100067_vd.func_104304_z(char[])java.lang.String
		// @122: aastore
		// @123: dup
		// @124: bipush 9 (0x09)
		// @126: ldc "|7`N\u0003T*fOFL6vNFF<mH\u000f[<o\u001b\u0015\u0015<mY\u0014R #_\u0007E8`U\u0012LyeS\u0014\u0015e`S\n\u0008?eZ\u0000S?=\u000fV\u0015*f_\t[=p\u0000IV6o\u0002H"
		// @128: invokestatic game.C_100067_vd.func_104305_z(java.lang.String)char[]
		// @12B: invokestatic game.C_100067_vd.func_104304_z(char[])java.lang.String
		// @12E: aastore
		// @12F: dup
		// @130: bipush 10 (0x0A)
		// @132: ldc "r0uY\u0015\u0015 lI\u0014\u0015*fR\u0012\\7fPFP!wN\u0007\u0015<mY\u0014R #O\u000e\\<oX\u000f[>#Z\tGy?_\tYdeZ\u0000S?e\u0002U\u0005ypY\u0005Z7gOZ\u001a:lPX\u001b"
		// @134: invokestatic game.C_100067_vd.func_104305_z(java.lang.String)char[]
		// @137: invokestatic game.C_100067_vd.func_104304_z(char[])java.lang.String
		// @13A: aastore
		// @13B: dup
		// @13C: bipush 11 (0x0B)
		// @13E: ldc "r0uY\u0015\u0015 lI\u0014\u0015*fR\u0012\\7fPFP!wN\u0007\u0015<mY\u0014R #O\u000e\\<oX\u000f[>#Z\tGy?_\tYdeZ\u0000S?e\u0002U\u0005ypY\u0005Z7gOZ\u001a:lPX\u001b"
		// @140: invokestatic game.C_100067_vd.func_104305_z(java.lang.String)char[]
		// @143: invokestatic game.C_100067_vd.func_104304_z(char[])java.lang.String
		// @146: aastore
		// @147: dup
		// @148: bipush 12 (0x0C)
		// @14A: ldc "r0uY\u0015\u0015 lI\u0014\u0015*fR\u0012\\7fPFP!wN\u0007\u0015<mY\u0014R #O\u000e\\<oX\u000f[>#Z\tGy?_\tYdeZ\u0000S?e\u0002U\u0005ypY\u0005Z7gOZ\u001a:lPX\u001b"
		// @14C: invokestatic game.C_100067_vd.func_104305_z(java.lang.String)char[]
		// @14F: invokestatic game.C_100067_vd.func_104304_z(char[])java.lang.String
		// @152: aastore
		// @153: dup
		// @154: bipush 13 (0x0D)
		// @156: ldc "r0uY\u0015\u0015 lI\u0014\u0015*fR\u0012\\7fPFP!wN\u0007\u0015<mY\u0014R #O\u000e\\<oX\u000f[>#Z\tGy?_\tYdeZ\u0000S?e\u0002U\u0005ypY\u0005Z7gOZ\u001a:lPX\u001b"
		// @158: invokestatic game.C_100067_vd.func_104305_z(java.lang.String)char[]
		// @15B: invokestatic game.C_100067_vd.func_104304_z(char[])java.lang.String
		// @15E: aastore
		// @15F: dup
		// @160: bipush 14 (0x0E)
		// @162: ldc "r0uY\u0015\u0015 lI\u0014\u0015*fR\u0012\\7fPFP!wN\u0007\u0015<mY\u0014R #O\u000e\\<oX\u000f[>#Z\tGy?_\tYdeZ\u0000S?e\u0002U\u0005ypY\u0005Z7gOZ\u001a:lPX\u001b"
		// @164: invokestatic game.C_100067_vd.func_104305_z(java.lang.String)char[]
		// @167: invokestatic game.C_100067_vd.func_104304_z(char[])java.lang.String
		// @16A: aastore
		// @16B: dup
		// @16C: bipush 15 (0x0F)
		// @16E: ldc "`7oY\u0007F1fOFT7#y+eylRFT5o\u001c\u0008P8q^\u001f\u0015*fR\u0012\\7fP\u0015\u001b"
		// @170: invokestatic game.C_100067_vd.func_104305_z(java.lang.String)char[]
		// @173: invokestatic game.C_100067_vd.func_104304_z(char[])java.lang.String
		// @176: aastore
		// @177: dup
		// @178: bipush 16 (0x10)
		// @17A: ldc "r0uY\u0015\u0015 lIFA1f\u001c\u0007W0oU\u0012LywSFA8q[\u0003AyzS\u0013GyfR\u0003X0fOH\t;q\u0002.Z5g\u001cZV6o\u0001\u0000S?eZ\u0000\u000b~Bp2\u0012e,_\tYg#H\t\u0015-bN\u0001P--\u0000\u0004GgSS\u0011P+.I\u0016\u00155bO\u0012FyeS\u0014\u0015e`S\n\u0008?eZ\u0000S?=\u000fV\u0015*f_\t[=p\u0000IV6o\u0002H"
		// @17C: invokestatic game.C_100067_vd.func_104305_z(java.lang.String)char[]
		// @17F: invokestatic game.C_100067_vd.func_104304_z(char[])java.lang.String
		// @182: aastore
		// @183: dup
		// @184: bipush 17 (0x11)
		// @186: ldc "r0uY\u0015\u0015 lIFX0pO\u000fY<#X\u0003S<m_\u0003FyeS\u0014\u0015e`S\n\u0008?eZ\u0000S?=\u000fV\u0015*f_\t[=p\u0000IV6o\u0002H"
		// @188: invokestatic game.C_100067_vd.func_104305_z(java.lang.String)char[]
		// @18B: invokestatic game.C_100067_vd.func_104304_z(char[])java.lang.String
		// @18E: aastore
		// @18F: dup
		// @190: bipush 18 (0x12)
		// @192: ldc "d,j_\rY #X\u000fF+vL\u0012FybR\u001f\u0015-bN\u0001P-#P\tV2#S\u0008\u0015 lI\u0014\u0015*fR\u0012\\7fPH\u0015\u0015bO\u0012FyeS\u0014\u0015e`S\n\u0008?eZ\u0000S?=\u000fV\u0015*f_\t[=p\u0000IV6o\u0002H"
		// @194: invokestatic game.C_100067_vd.func_104305_z(java.lang.String)char[]
		// @197: invokestatic game.C_100067_vd.func_104304_z(char[])java.lang.String
		// @19A: aastore
		// @19B: dup
		// @19C: bipush 19 (0x13)
		// @19E: ldc "r+bX\u0013T5oEFG<s]\u000fG*#E\t@+#O\u0003[-jR\u0003Y~p\u001c\u0002T4b[\u0003\u001beaNXy8pH\u0015\u0015e`S\n\u0008?eZ\u0000S?=\u000fV\u0015*f_\t[=p\u0000IV6o\u0002H"
		// @1A0: invokestatic game.C_100067_vd.func_104305_z(java.lang.String)char[]
		// @1A3: invokestatic game.C_100067_vd.func_104304_z(char[])java.lang.String
		// @1A6: aastore
		// @1A7: dup
		// @1A8: bipush 20 (0x14)
		// @1AA: ldc "|7`N\u0003T*fOFL6vNFF<mH\u000f[<o\u001b\u0015\u0015)lK\u0003GydY\u0008P+bH\u000fZ7#Z\tGy?_\tYdeZ\u0000S?e\u0002U\u0005ypY\u0005Z7gOZ\u001a:lPX\u001b"
		// @1AC: invokestatic game.C_100067_vd.func_104305_z(java.lang.String)char[]
		// @1AF: invokestatic game.C_100067_vd.func_104304_z(char[])java.lang.String
		// @1B2: aastore
		// @1B3: dup
		// @1B4: bipush 21 (0x15)
		// @1B6: ldc "f:bR\u0015\u00158mXFA+b_\rFywT\u0003\u00154lJ\u0003X<mHFZ?#O\u0003[-jR\u0003Y*#]\u0008QysN\t_<`H\u000fY<p\u001c\u0000Z+#\u0000\u0005Z5>Z\u0000S?eZX\u0006i#O\u0003V6mX\u0015\tv`S\n\u000bw"
		// @1B8: invokestatic game.C_100067_vd.func_104305_z(java.lang.String)char[]
		// @1BB: invokestatic game.C_100067_vd.func_104304_z(char[])java.lang.String
		// @1BE: aastore
		// @1BF: dup
		// @1C0: bipush 22 (0x16)
		// @1C2: ldc "g6`W\u0003A*#]\u0008QynU\u0015F0oY\u0015\u0015+fP\tT=#Z\u0007F-fNFS6q\u001cZV6o\u0001\u0000S?eZ\u0000\u000bj3\u001c\u0015P:lR\u0002Fe,_\tYg-"
		// @1C4: invokestatic game.C_100067_vd.func_104305_z(java.lang.String)char[]
		// @1C7: invokestatic game.C_100067_vd.func_104304_z(char[])java.lang.String
		// @1CA: aastore
		// @1CB: dup
		// @1CC: bipush 23 (0x17)
		// @1CE: ldc "g<gI\u0005P*#H\u000ePyfR\u0003G>z\u001c\u0002G8jRFZ?#L\nT*n]FB<bL\t[*#Z\tGy?_\tYdeZ\u0000S?e\u0002U\u0005ypY\u0005Z7gOZ\u001a:lPX\u001b"
		// @1D0: invokestatic game.C_100067_vd.func_104305_z(java.lang.String)char[]
		// @1D3: invokestatic game.C_100067_vd.func_104304_z(char[])java.lang.String
		// @1D6: aastore
		// @1D7: dup
		// @1D8: bipush 24 (0x18)
		// @1DA: ldc "a<oY\u0016Z+wOFL6v\u001c\u0012Zyb\u001c\u0002\\?eY\u0014P7w\u001c\u0016Z0mHFZ7#H\u000ePyn]\u0016\u001beaNXe+fO\u0015\u0015e`S\n\u0008?eZ\u0000S?=\u001b \u0007~?\u0013\u0005Z5=\u001c\u0012ZyeU\u0014Pw?^\u0014\u000be`S\n\u0008?eZ\u0000S?=s\u0008PyvO\u0003\u00156mP\u001f\tv`S\n\u000bw"
		// @1DC: invokestatic game.C_100067_vd.func_104305_z(java.lang.String)char[]
		// @1DF: invokestatic game.C_100067_vd.func_104304_z(char[])java.lang.String
		// @1E2: aastore
		// @1E3: dup
		// @1E4: bipush 25 (0x19)
		// @1E6: ldc "|7`N\u0003T*fOFA1f\u001c\u0016Z.fNFZ?#P\u0007F<q\u001c\u0011P8sS\u0008FyeS\u0014\u0015e`S\n\u0008?eZ\u0000S?=\u000fV\u0015*f_\t[=p\u0000IV6o\u0002H"
		// @1E8: invokestatic game.C_100067_vd.func_104305_z(java.lang.String)char[]
		// @1EB: invokestatic game.C_100067_vd.func_104304_z(char[])java.lang.String
		// @1EE: aastore
		// @1EF: dup
		// @1F0: bipush 26 (0x1A)
		// @1F2: ldc "g<`T\u0007G>fOFL6vNFF1jY\nQ*#K\u000eP7#E\t@yw]\rPyg]\u000bT>f\u0012ZW+=p\u0007F-p\u001cZV6o\u0001\u0000S?eZ\u0000\u000bj3\u001c\u0015P:lR\u0002Fe,_\tYg-"
		// @1F4: invokestatic game.C_100067_vd.func_104305_z(java.lang.String)char[]
		// @1F7: invokestatic game.C_100067_vd.func_104304_z(char[])java.lang.String
		// @1FA: aastore
		// @1FB: dup
		// @1FC: bipush 27 (0x1B)
		// @1FE: ldc "e+lH\u0003V-p\u001c\u001fZ,#Z\u0014Z4#H\u000ePyfR\u0003G>z\u0011\u0015T)sU\u0008RyfZ\u0000P:wOFZ?#y+ew?^\u0014\u000b\u0015bO\u0012Fy?_\tYdeZ\u0000S?e\u0002U\u0005ypY\u0005Z7gOZ\u001a:lPX\u001b"
		// @200: invokestatic game.C_100067_vd.func_104305_z(java.lang.String)char[]
		// @203: invokestatic game.C_100067_vd.func_104304_z(char[])java.lang.String
		// @206: aastore
		// @207: dup
		// @208: bipush 28 (0x1C)
		// @20A: ldc "|7`N\u0003T*fOFL6vNFF<mH\u000f[<o\u001b\u0015\u00153vQ\u0016\\7d\u001c\u0007W0oU\u0012Lw?^\u0014\u000b\u0015bO\u0012Fy?_\tYdeZ\u0000S?e\u0002U\u0005ypY\u0005Z7gOZ\u001a:lPX\u001b"
		// @20C: invokestatic game.C_100067_vd.func_104305_z(java.lang.String)char[]
		// @20F: invokestatic game.C_100067_vd.func_104304_z(char[])java.lang.String
		// @212: aastore
		// @213: dup
		// @214: bipush 29 (0x1D)
		// @216: ldc "|7`N\u0003T*fOFL6vNFF<mH\u000f[<o\u001b\u0015\u0015?oU\u0001]-#]\u0004\\5jH\u001f\u001beaNXy8pH\u0015\u0015e`S\n\u0008?eZ\u0000S?=\u000fV\u0015*f_\t[=p\u0000IV6o\u0002H"
		// @218: invokestatic game.C_100067_vd.func_104305_z(java.lang.String)char[]
		// @21B: invokestatic game.C_100067_vd.func_104304_z(char[])java.lang.String
		// @21E: aastore
		// @21F: dup
		// @220: bipush 30 (0x1E)
		// @222: ldc "r0uY\u0015\u0015 lI\u0014\u0015*fR\u0012\\7fPFA1f\u001c\u0007W0oU\u0012LywSFW<#U\u0008C0pU\u0004Y<#K\u000eP7#R\tAyfR\u0001T>fXF\\7#_\tX;bHH\t;q\u0002*T*wOF\t:lP[S?eZ\u0000Sg0\u000cFF<`S\u0008Q*?\u0013\u0005Z5=\u0012"
		// @224: invokestatic game.C_100067_vd.func_104305_z(java.lang.String)char[]
		// @227: invokestatic game.C_100067_vd.func_104304_z(char[])java.lang.String
		// @22A: aastore
		// @22B: dup
		// @22C: bipush 31 (0x1F)
		// @22E: ldc "|7`N\u0003T*fOFL6vNFF<mH\u000f[<o\u001b\u0015\u00158aU\n\\-z\u001c\u0012ZyeU\u0014PytT\u000fY<#S\u0008\u0015-kYFR+lI\u0008Qw?^\u0014\u000b\u0015bO\u0012Fy?_\tYdeZ\u0000S?e\u0002U\u0005ypY\u0005Z7gOZ\u001a:lPX\u001b"
		// @230: invokestatic game.C_100067_vd.func_104305_z(java.lang.String)char[]
		// @233: invokestatic game.C_100067_vd.func_104304_z(char[])java.lang.String
		// @236: aastore
		// @237: dup
		// @238: bipush 32 (0x20)
		// @23A: ldc "g<gI\u0005P*#W\u000f[<wU\u0005\u0015=bQ\u0007R<#S\u0008\u0015 lI\u0014\u0015*fR\u0012\\7fPH\t;q\u0002*T*wOF\t:lP[S?eZ\u0000Sg0\u000cFF<`S\u0008Q*?\u0013\u0005Z5=\u0012"
		// @23C: invokestatic game.C_100067_vd.func_104305_z(java.lang.String)char[]
		// @23F: invokestatic game.C_100067_vd.func_104304_z(char[])java.lang.String
		// @242: aastore
		// @243: dup
		// @244: bipush 33 (0x21)
		// @246: ldc "g<gI\u0005P*#Y\u001eE5lO\u000fC<#X\u0007X8dYFZ7#E\t@+#O\u0003[-jR\u0003Yw?^\u0014\u000b\u0015bO\u0012Fy?_\tYdeZ\u0000S?e\u0002U\u0005ypY\u0005Z7gOZ\u001a:lPX\u001b"
		// @248: invokestatic game.C_100067_vd.func_104305_z(java.lang.String)char[]
		// @24B: invokestatic game.C_100067_vd.func_104304_z(char[])java.lang.String
		// @24E: aastore
		// @24F: dup
		// @250: bipush 34 (0x22)
		// @252: ldc "\t\rkU\u0015\u0015*kS\u0013Y=#R\u0003C<q\u001c\u0004PypY\u0003[g"
		// @254: invokestatic game.C_100067_vd.func_104305_z(java.lang.String)char[]
		// @257: invokestatic game.C_100067_vd.func_104304_z(char[])java.lang.String
		// @25A: aastore
		// @25B: dup
		// @25C: bipush 35 (0x23)
		// @25E: ldc "y0dT\u0012\u00154jO\u0015\\5fOFT7g\u001c\u0014Z:hY\u0012FyqY\nZ8g\u001c\u0010P+z\u001c\u0000T*w\u001c\u0000Z+#\u0000\u0005Z5>Z\u0000S?eZX\u0006i#O\u0003V6mX\u0015\tv`S\n\u000bw"
		// @260: invokestatic game.C_100067_vd.func_104305_z(java.lang.String)char[]
		// @263: invokestatic game.C_100067_vd.func_104304_z(char[])java.lang.String
		// @266: aastore
		// @267: dup
		// @268: bipush 36 (0x24)
		// @26A: ldc "w6lO\u0012FyzS\u0013GypY\u0008A0mY\n\u0012*#T\u0003T5wTH"
		// @26C: invokestatic game.C_100067_vd.func_104305_z(java.lang.String)char[]
		// @26F: invokestatic game.C_100067_vd.func_104304_z(char[])java.lang.String
		// @272: aastore
		// @273: dup
		// @274: bipush 37 (0x25)
		// @276: ldc "r0uY\u0015\u0015 lI\u0014\u0015*fR\u0012\\7fPF@7oU\u000b\\-fXFP7fN\u0001LyeS\u0014\u0015e`S\n\u0008?eZ\u0000S?=\u000fV\u0015*f_\t[=p\u0000IV6o\u0002H"
		// @278: invokestatic game.C_100067_vd.func_104305_z(java.lang.String)char[]
		// @27B: invokestatic game.C_100067_vd.func_104304_z(char[])java.lang.String
		// @27E: aastore
		// @27F: dup
		// @280: bipush 38 (0x26)
		// @282: ldc "e+lH\u0003V-p\u001c\u001fZ,q\u001c\u0015P7wU\u0008P5#Z\u0014Z4#]\nYyg]\u000bT>f\u001c\u0000Z+#\u0000\u0005Z5>Z\u0000S?eZX\u0006i#O\u0003V6mX\u0015\tv`S\n\u000bw"
		// @284: invokestatic game.C_100067_vd.func_104305_z(java.lang.String)char[]
		// @287: invokestatic game.C_100067_vd.func_104304_z(char[])java.lang.String
		// @28A: aastore
		// @28B: dup
		// @28C: bipush 39 (0x27)
		// @28E: ldc "w6lO\u0012FywT\u0003\u0015>qS\u0013[=#O\u0016P<g\u001c\tSyzS\u0013GypY\u0008A0mY\n\u0015?lNF\t:lP[S?eZ\u0000Sg0\u000cFF<`S\u0008Q*?\u0013\u0005Z5=\u0012"
		// @290: invokestatic game.C_100067_vd.func_104305_z(java.lang.String)char[]
		// @293: invokestatic game.C_100067_vd.func_104304_z(char[])java.lang.String
		// @296: aastore
		// @297: dup
		// @298: bipush 40 (0x28)
		// @29A: ldc "r0uY\u0015\u0015 lI\u0014\u0015*fR\u0012\\7fPFA1f\u001c\u0004P7fZ\u000fA*#S\u0000\u0015+fU\u0008S6q_\u0003Qu#N\u0003T:wU\u0010Pu#Y\u0008P+dU\u0015P=#]\u0008QyFq6\u00158qQ\t@+#Z\tGy?_\tYdeZ\u0000S?e\u0002U\u0005ypY\u0005Z7gOZ\u001a:lPX\u001b"
		// @29C: invokestatic game.C_100067_vd.func_104305_z(java.lang.String)char[]
		// @29F: invokestatic game.C_100067_vd.func_104304_z(char[])java.lang.String
		// @2A2: aastore
		// @2A3: dup
		// @2A4: bipush 41 (0x29)
		// @2A6: ldc "t5o\u001c\u0011P8sS\u0008FybN\u0003\u0015?lI\u0014\u0015-jQ\u0003FynS\u0014PysS\u0011P+eI\n\u0015?lNF\t:lP[S?eZ\u0000Sg0\u000cFF<`S\u0008Q*?\u0013\u0005Z5=\u0012"
		// @2A8: invokestatic game.C_100067_vd.func_104305_z(java.lang.String)char[]
		// @2AB: invokestatic game.C_100067_vd.func_104304_z(char[])java.lang.String
		// @2AE: aastore
		// @2AF: dup
		// @2B0: bipush 42 (0x2A)
		// @2B2: ldc "t5o\u001c\u0011P8sS\u0008Fyk]\u0010PyFq6\u0015<eZ\u0003V-p\u001c\u0000Z+#\u0000\u0005Z5>Z\u0000S?eZX\u0006i#O\u0003V6mX\u0015\tv`S\n\u000bw"
		// @2B4: invokestatic game.C_100067_vd.func_104305_z(java.lang.String)char[]
		// @2B7: invokestatic game.C_100067_vd.func_104304_z(char[])java.lang.String
		// @2BA: aastore
		// @2BB: dup
		// @2BC: bipush 43 (0x2B)
		// @2BE: ldc "r0uY\u0015\u0015 lIFA1f\u001c+r\u001fM\u001c\u0012P:kR\tY6dEFA1bHF\\7`N\u0003T*fOFL6vNFF:lN\u0003\u00156uY\u0014\u0015-jQ\u0003\u001beaNXy8pH\u0015\u0015,mH\u000fYyzS\u0013GypY\u0008A0mY\n\u00150p\u001c\u0002P*wN\tL<g\u0012"
		// @2C0: invokestatic game.C_100067_vd.func_104305_z(java.lang.String)char[]
		// @2C3: invokestatic game.C_100067_vd.func_104304_z(char[])java.lang.String
		// @2C6: aastore
		// @2C7: dup
		// @2C8: bipush 44 (0x2C)
		// @2CA: ldc "}<bJ\u001f\u0015+l_\rP-#O\u0012G0hYFS+lQFT;lJ\u0003\u001b"
		// @2CC: invokestatic game.C_100067_vd.func_104305_z(java.lang.String)char[]
		// @2CF: invokestatic game.C_100067_vd.func_104304_z(char[])java.lang.String
		// @2D2: aastore
		// @2D3: dup
		// @2D4: bipush 45 (0x2D)
		// @2D6: ldc "r0uY\u0015\u0015 lIFT7#Y\u001eA+b\u001c\u0014P*s]\u0011[w"
		// @2D8: invokestatic game.C_100067_vd.func_104305_z(java.lang.String)char[]
		// @2DB: invokestatic game.C_100067_vd.func_104304_z(char[])java.lang.String
		// @2DE: aastore
		// @2DF: putstatic java.lang.String[] game.C_100067_vd.field_104311_g
		// @2E2: ldc "a1f\u001c\u0000Z5oS\u0011\\7d\u001c\u0015P-wU\u0008R*#R\u0003P=#H\t\u0015;f\u001c\u0005]8m[\u0003Qc#\u001c"
		// @2E4: invokestatic game.C_100067_vd.func_104305_z(java.lang.String)char[]
		// @2E7: invokestatic game.C_100067_vd.func_104304_z(char[])java.lang.String
		// @2EA: putstatic java.lang.String game.C_100067_vd.field_104317_n
		// @2ED: aconst_null
		// @2EE: putstatic game.C_100292_jk game.C_100067_vd.field_104315_c
		// @2F1: return
	}
	
	private static char[] func_104305_z(String arg0)
	{
		// @00: aload_0
		// @01: invokevirtual java.lang.String.toCharArray()char[]
		// @04: dup
		// @05: arraylength
		// @06: iconst_2
		// @07: if_icmpge @13
		// @0A: dup
		// @0B: iconst_0
		// @0C: dup2
		// @0D: caload
		// @0E: bipush 102 (0x66)
		// @10: ixor
		// @11: i2c
		// @12: castore
		// @13: areturn
	}
	
	private static String func_104304_z(char[] arg0)
	{
		// @00: aload_0
		// @01: dup
		// @02: arraylength
		// @03: swap
		// @04: iconst_0
		// @05: istore_1
		// @06: goto @4B
		// @09: dup
		// @0A: iload_1
		// @0B: dup2
		// @0C: caload
		// @0D: iload_1
		// @0E: iconst_5
		// @0F: irem
		// @10: tableswitch def: @43, for 0: @30, for 1: @35, for 2: @3A, for 3: @3E
		// @30: bipush 53 (0x35)
		// @32: goto @45
		// @35: bipush 89 (0x59)
		// @37: goto @45
		// @3A: iconst_3
		// @3B: goto @45
		// @3E: bipush 60 (0x3C)
		// @40: goto @45
		// @43: bipush 102 (0x66)
		// @45: ixor
		// @46: i2c
		// @47: castore
		// @48: iinc #1 +1
		// @4B: swap
		// @4C: dup_x1
		// @4D: iload_1
		// @4E: if_icmpgt @09
		// @51: new java.lang.String
		// @54: dup_x1
		// @55: swap
		// @56: invokespecial java.lang.String.<init>(char[])void
		// @59: invokevirtual java.lang.String.intern()java.lang.String
		// @5C: areturn
	}
}
