package game;

import java.util.Iterator;
import java.awt.Container;

final class C_100092_um implements Iterator
{
	private C_100158_da field_104529_g;
	private int field_104533_c;
	static C_100037_wb field_104532_b;
	static boolean[][] field_104536_j;
	static C_100153_be[] field_104534_a;
	static C_100112_r field_104531_e;
	static String field_104537_k;
	static int[][] field_104539_i;
	static String field_104528_f;
	private C_100266_me field_104530_d;
	private C_100158_da field_104538_h;
	static String field_104535_l;
	private static final String[] field_104540_z;
	
	static final boolean func_104523_a(String arg0, int arg1)
	{
		// @00: getstatic int game.SteelSentinels.field_105275_O
		// @03: istore #4
		// @05: iload_1
		// @06: sipush 27048 (0x69A8)
		// @09: if_icmpeq @0E
		// @0C: iconst_0
		// @0D: ireturn
		// @0E: aload_0
		// @0F: iconst_0
		// @10: invokevirtual java.lang.String.charAt(int)char
		// @13: istore_2
		// @14: iconst_1
		// @15: istore_3
		// @16: aload_0
		// @17: invokevirtual java.lang.String.length()int
		// @1A: iconst_m1
		// @1B: ixor
		// @1C: iload_3
		// @1D: iconst_m1
		// @1E: ixor
		// @1F: if_icmpge @46
		// @22: iload_2
		// @23: iconst_m1
		// @24: ixor
		// @25: iload #4
		// @27: ifne @47
		// @2A: aload_0
		// @2B: iload_3
		// @2C: invokevirtual java.lang.String.charAt(int)char
		// @2F: iconst_m1
		// @30: ixor
		// @31: if_icmpne @3C
		// @34: goto @38
		// @37: athrow
		// @38: goto @3E
		// @3B: athrow
		// @3C: iconst_0
		// @3D: ireturn
		// @3E: iinc #3 +1
		// @41: iload #4
		// @43: ifeq @16
		// @46: iconst_1
		// @47: ireturn
		// @48: astore_2
		// @49: aload_2
		// @4A: new java.lang.StringBuilder
		// @4D: dup
		// @4E: invokespecial java.lang.StringBuilder.<init>()void
		// @51: getstatic java.lang.String[] game.C_100092_um.field_104540_z
		// @54: bipush 8 (0x08)
		// @56: aaload
		// @57: invokevirtual java.lang.StringBuilder.append(java.lang.String)java.lang.StringBuilder
		// @5A: aload_0
		// @5B: ifnull @67
		// @5E: getstatic java.lang.String[] game.C_100092_um.field_104540_z
		// @61: iconst_1
		// @62: aaload
		// @63: goto @6C
		// @66: athrow
		// @67: getstatic java.lang.String[] game.C_100092_um.field_104540_z
		// @6A: iconst_0
		// @6B: aaload
		// @6C: invokevirtual java.lang.StringBuilder.append(java.lang.String)java.lang.StringBuilder
		// @6F: bipush 44 (0x2C)
		// @71: invokevirtual java.lang.StringBuilder.append(char)java.lang.StringBuilder
		// @74: iload_1
		// @75: invokevirtual java.lang.StringBuilder.append(int)java.lang.StringBuilder
		// @78: bipush 41 (0x29)
		// @7A: invokevirtual java.lang.StringBuilder.append(char)java.lang.StringBuilder
		// @7D: invokevirtual java.lang.StringBuilder.toString()java.lang.String
		// @80: invokestatic game.C_100181_cf.func_105695_a(java.lang.Throwable, java.lang.String)game.C_100170_cm
		// @83: athrow
	}
	
	static final int func_104527_a(int arg0, String arg1, String arg2, int arg3, boolean arg4, String arg5, int arg6)
	{
		// @00: iload_0
		// @01: sipush 26245 (0x6685)
		// @04: if_icmpeq @15
		// @07: aconst_null
		// @08: checkcast java.lang.String
		// @0B: bipush 13 (0x0D)
		// @0D: invokestatic game.C_100092_um.func_104523_a(java.lang.String, int)boolean
		// @10: pop
		// @11: goto @15
		// @14: athrow
		// @15: new game.C_100154_sl
		// @18: dup
		// @19: aload_2
		// @1A: invokespecial game.C_100154_sl.<init>(java.lang.String)void
		// @1D: astore #7
		// @1F: new game.C_100154_sl
		// @22: dup
		// @23: aload_1
		// @24: invokespecial game.C_100154_sl.<init>(java.lang.String)void
		// @27: astore #8
		// @29: aload #7
		// @2B: aload #5
		// @2D: iload #4
		// @2F: aload #8
		// @31: iload #6
		// @33: iload_3
		// @34: bipush 70 (0x46)
		// @36: invokestatic game.C_100295_kh.func_105279_a(game.C_100154_sl, java.lang.String, boolean, game.C_100154_sl, int, int, int)int
		// @39: ireturn
		// @3A: astore #7
		// @3C: aload #7
		// @3E: new java.lang.StringBuilder
		// @41: dup
		// @42: invokespecial java.lang.StringBuilder.<init>()void
		// @45: getstatic java.lang.String[] game.C_100092_um.field_104540_z
		// @48: iconst_4
		// @49: aaload
		// @4A: invokevirtual java.lang.StringBuilder.append(java.lang.String)java.lang.StringBuilder
		// @4D: iload_0
		// @4E: invokevirtual java.lang.StringBuilder.append(int)java.lang.StringBuilder
		// @51: bipush 44 (0x2C)
		// @53: invokevirtual java.lang.StringBuilder.append(char)java.lang.StringBuilder
		// @56: aload_1
		// @57: ifnull @63
		// @5A: getstatic java.lang.String[] game.C_100092_um.field_104540_z
		// @5D: iconst_1
		// @5E: aaload
		// @5F: goto @68
		// @62: athrow
		// @63: getstatic java.lang.String[] game.C_100092_um.field_104540_z
		// @66: iconst_0
		// @67: aaload
		// @68: invokevirtual java.lang.StringBuilder.append(java.lang.String)java.lang.StringBuilder
		// @6B: bipush 44 (0x2C)
		// @6D: invokevirtual java.lang.StringBuilder.append(char)java.lang.StringBuilder
		// @70: aload_2
		// @71: ifnull @7D
		// @74: getstatic java.lang.String[] game.C_100092_um.field_104540_z
		// @77: iconst_1
		// @78: aaload
		// @79: goto @82
		// @7C: athrow
		// @7D: getstatic java.lang.String[] game.C_100092_um.field_104540_z
		// @80: iconst_0
		// @81: aaload
		// @82: invokevirtual java.lang.StringBuilder.append(java.lang.String)java.lang.StringBuilder
		// @85: bipush 44 (0x2C)
		// @87: invokevirtual java.lang.StringBuilder.append(char)java.lang.StringBuilder
		// @8A: iload_3
		// @8B: invokevirtual java.lang.StringBuilder.append(int)java.lang.StringBuilder
		// @8E: bipush 44 (0x2C)
		// @90: invokevirtual java.lang.StringBuilder.append(char)java.lang.StringBuilder
		// @93: iload #4
		// @95: invokevirtual java.lang.StringBuilder.append(boolean)java.lang.StringBuilder
		// @98: bipush 44 (0x2C)
		// @9A: invokevirtual java.lang.StringBuilder.append(char)java.lang.StringBuilder
		// @9D: aload #5
		// @9F: ifnull @AB
		// @A2: getstatic java.lang.String[] game.C_100092_um.field_104540_z
		// @A5: iconst_1
		// @A6: aaload
		// @A7: goto @B0
		// @AA: athrow
		// @AB: getstatic java.lang.String[] game.C_100092_um.field_104540_z
		// @AE: iconst_0
		// @AF: aaload
		// @B0: invokevirtual java.lang.StringBuilder.append(java.lang.String)java.lang.StringBuilder
		// @B3: bipush 44 (0x2C)
		// @B5: invokevirtual java.lang.StringBuilder.append(char)java.lang.StringBuilder
		// @B8: iload #6
		// @BA: invokevirtual java.lang.StringBuilder.append(int)java.lang.StringBuilder
		// @BD: bipush 41 (0x29)
		// @BF: invokevirtual java.lang.StringBuilder.append(char)java.lang.StringBuilder
		// @C2: invokevirtual java.lang.StringBuilder.toString()java.lang.String
		// @C5: invokestatic game.C_100181_cf.func_105695_a(java.lang.Throwable, java.lang.String)game.C_100170_cm
		// @C8: athrow
	}
	
	static final void func_104521_a(boolean arg0, byte arg1)
	{
		// @00: iconst_0
		// @01: putstatic int game.C_100292_jk.field_101215_r
		// @04: iconst_0
		// @05: putstatic int game.C_100113_ek.field_104882_a
		// @08: getstatic int game.C_100338_jc.field_105367_b
		// @0B: putstatic int game.C_100042_we.field_104137_m
		// @0E: iconst_0
		// @0F: putstatic int game.C_100287_nm.field_106826_b
		// @12: new game.C_100333_ij
		// @15: dup
		// @16: iconst_2
		// @17: invokespecial game.C_100333_ij.<init>(int)void
		// @1A: putstatic game.C_100333_ij game.C_100220_ac.field_106064_h
		// @1D: getstatic game.C_100333_ij game.C_100220_ac.field_106064_h
		// @20: iload_1
		// @21: bipush 100 (0x64)
		// @23: iadd
		// @24: getstatic int game.C_100338_jc.field_105370_l
		// @27: bipush 7 (0x07)
		// @29: getstatic int game.C_100015_wh.field_103781_g
		// @2C: invokestatic game.C_100141_tc.func_105046_a(int, int, int)int
		// @2F: iconst_m1
		// @30: iload_0
		// @31: invokevirtual game.C_100333_ij.func_107340_a(int, int, int, boolean)void
		// @34: iload_1
		// @35: bipush -100 (0x9C)
		// @37: if_icmpeq @40
		// @3A: bipush 54 (0x36)
		// @3C: invokestatic game.C_100092_um.func_104520_b(int)java.awt.Container
		// @3F: pop
		// @40: goto @6E
		// @43: astore_2
		// @44: aload_2
		// @45: new java.lang.StringBuilder
		// @48: dup
		// @49: invokespecial java.lang.StringBuilder.<init>()void
		// @4C: getstatic java.lang.String[] game.C_100092_um.field_104540_z
		// @4F: bipush 6 (0x06)
		// @51: aaload
		// @52: invokevirtual java.lang.StringBuilder.append(java.lang.String)java.lang.StringBuilder
		// @55: iload_0
		// @56: invokevirtual java.lang.StringBuilder.append(boolean)java.lang.StringBuilder
		// @59: bipush 44 (0x2C)
		// @5B: invokevirtual java.lang.StringBuilder.append(char)java.lang.StringBuilder
		// @5E: iload_1
		// @5F: invokevirtual java.lang.StringBuilder.append(int)java.lang.StringBuilder
		// @62: bipush 41 (0x29)
		// @64: invokevirtual java.lang.StringBuilder.append(char)java.lang.StringBuilder
		// @67: invokevirtual java.lang.StringBuilder.toString()java.lang.String
		// @6A: invokestatic game.C_100181_cf.func_105695_a(java.lang.Throwable, java.lang.String)game.C_100170_cm
		// @6D: athrow
		// @6E: return
	}
	
	public final boolean hasNext()
	{
		// @00: getstatic int game.SteelSentinels.field_105275_O
		// @03: istore_2
		// @04: aload_0
		// @05: getfield game.C_100266_me game.C_100092_um.field_104530_d
		// @08: getfield game.C_100158_da[] game.C_100266_me.field_106658_i
		// @0B: aload_0
		// @0C: getfield int game.C_100092_um.field_104533_c
		// @0F: iconst_m1
		// @10: iadd
		// @11: aaload
		// @12: aload_0
		// @13: getfield game.C_100158_da game.C_100092_um.field_104538_h
		// @16: if_acmpeq @1B
		// @19: iconst_1
		// @1A: ireturn
		// @1B: aload_0
		// @1C: getfield int game.C_100092_um.field_104533_c
		// @1F: aload_0
		// @20: getfield game.C_100266_me game.C_100092_um.field_104530_d
		// @23: getfield int game.C_100266_me.field_106655_j
		// @26: if_icmpge @7D
		// @29: aload_0
		// @2A: getfield game.C_100266_me game.C_100092_um.field_104530_d
		// @2D: getfield game.C_100158_da[] game.C_100266_me.field_106658_i
		// @30: aload_0
		// @31: dup
		// @32: getfield int game.C_100092_um.field_104533_c
		// @35: dup_x1
		// @36: iconst_1
		// @37: iadd
		// @38: putfield int game.C_100092_um.field_104533_c
		// @3B: aaload
		// @3C: getfield game.C_100158_da game.C_100158_da.field_100590_f
		// @3F: aload_0
		// @40: getfield game.C_100266_me game.C_100092_um.field_104530_d
		// @43: getfield game.C_100158_da[] game.C_100266_me.field_106658_i
		// @46: iconst_m1
		// @47: aload_0
		// @48: getfield int game.C_100092_um.field_104533_c
		// @4B: iadd
		// @4C: aaload
		// @4D: if_acmpeq @67
		// @50: aload_0
		// @51: aload_0
		// @52: getfield game.C_100266_me game.C_100092_um.field_104530_d
		// @55: getfield game.C_100158_da[] game.C_100266_me.field_106658_i
		// @58: iconst_m1
		// @59: aload_0
		// @5A: getfield int game.C_100092_um.field_104533_c
		// @5D: iadd
		// @5E: aaload
		// @5F: getfield game.C_100158_da game.C_100158_da.field_100590_f
		// @62: putfield game.C_100158_da game.C_100092_um.field_104538_h
		// @65: iconst_1
		// @66: ireturn
		// @67: aload_0
		// @68: aload_0
		// @69: getfield game.C_100266_me game.C_100092_um.field_104530_d
		// @6C: getfield game.C_100158_da[] game.C_100266_me.field_106658_i
		// @6F: aload_0
		// @70: getfield int game.C_100092_um.field_104533_c
		// @73: iconst_m1
		// @74: iadd
		// @75: aaload
		// @76: putfield game.C_100158_da game.C_100092_um.field_104538_h
		// @79: iload_2
		// @7A: ifeq @1B
		// @7D: iconst_0
		// @7E: ireturn
		// @7F: astore_1
		// @80: aload_1
		// @81: getstatic java.lang.String[] game.C_100092_um.field_104540_z
		// @84: bipush 10 (0x0A)
		// @86: aaload
		// @87: invokestatic game.C_100181_cf.func_105695_a(java.lang.Throwable, java.lang.String)game.C_100170_cm
		// @8A: athrow
	}
	
	static final Container func_104520_b(int arg0)
	{
		// @00: iload_0
		// @01: sipush 26594 (0x67E2)
		// @04: if_icmpeq @15
		// @07: aconst_null
		// @08: checkcast java.lang.String
		// @0B: bipush -90 (0xA6)
		// @0D: invokestatic game.C_100092_um.func_104523_a(java.lang.String, int)boolean
		// @10: pop
		// @11: goto @15
		// @14: athrow
		// @15: aconst_null
		// @16: getstatic java.awt.Frame game.C_100227_af.field_106168_b
		// @19: if_acmpne @20
		// @1C: goto @24
		// @1F: athrow
		// @20: getstatic java.awt.Frame game.C_100227_af.field_106168_b
		// @23: areturn
		// @24: iconst_0
		// @25: invokestatic game.C_100206_qe.func_105938_b(boolean)java.applet.Applet
		// @28: areturn
		// @29: astore_1
		// @2A: aload_1
		// @2B: new java.lang.StringBuilder
		// @2E: dup
		// @2F: invokespecial java.lang.StringBuilder.<init>()void
		// @32: getstatic java.lang.String[] game.C_100092_um.field_104540_z
		// @35: bipush 9 (0x09)
		// @37: aaload
		// @38: invokevirtual java.lang.StringBuilder.append(java.lang.String)java.lang.StringBuilder
		// @3B: iload_0
		// @3C: invokevirtual java.lang.StringBuilder.append(int)java.lang.StringBuilder
		// @3F: bipush 41 (0x29)
		// @41: invokevirtual java.lang.StringBuilder.append(char)java.lang.StringBuilder
		// @44: invokevirtual java.lang.StringBuilder.toString()java.lang.String
		// @47: invokestatic game.C_100181_cf.func_105695_a(java.lang.Throwable, java.lang.String)game.C_100170_cm
		// @4A: athrow
	}
	
	public final void remove()
	{
		// @00: aload_0
		// @01: getfield game.C_100158_da game.C_100092_um.field_104529_g
		// @04: ifnonnull @10
		// @07: new java.lang.IllegalStateException
		// @0A: dup
		// @0B: invokespecial java.lang.IllegalStateException.<init>()void
		// @0E: athrow
		// @0F: athrow
		// @10: aload_0
		// @11: getfield game.C_100158_da game.C_100092_um.field_104529_g
		// @14: bipush 45 (0x2D)
		// @16: invokevirtual game.C_100158_da.func_100583_c(int)void
		// @19: aload_0
		// @1A: aconst_null
		// @1B: putfield game.C_100158_da game.C_100092_um.field_104529_g
		// @1E: goto @2C
		// @21: astore_1
		// @22: aload_1
		// @23: getstatic java.lang.String[] game.C_100092_um.field_104540_z
		// @26: iconst_3
		// @27: aaload
		// @28: invokestatic game.C_100181_cf.func_105695_a(java.lang.Throwable, java.lang.String)game.C_100170_cm
		// @2B: athrow
		// @2C: return
	}
	
	private final void func_104522_a(int arg0)
	{
		// @00: aload_0
		// @01: aload_0
		// @02: getfield game.C_100266_me game.C_100092_um.field_104530_d
		// @05: getfield game.C_100158_da[] game.C_100266_me.field_106658_i
		// @08: iconst_0
		// @09: aaload
		// @0A: getfield game.C_100158_da game.C_100158_da.field_100590_f
		// @0D: putfield game.C_100158_da game.C_100092_um.field_104538_h
		// @10: aload_0
		// @11: iload_1
		// @12: putfield int game.C_100092_um.field_104533_c
		// @15: aload_0
		// @16: aconst_null
		// @17: putfield game.C_100158_da game.C_100092_um.field_104529_g
		// @1A: goto @3F
		// @1D: astore_2
		// @1E: aload_2
		// @1F: new java.lang.StringBuilder
		// @22: dup
		// @23: invokespecial java.lang.StringBuilder.<init>()void
		// @26: getstatic java.lang.String[] game.C_100092_um.field_104540_z
		// @29: bipush 11 (0x0B)
		// @2B: aaload
		// @2C: invokevirtual java.lang.StringBuilder.append(java.lang.String)java.lang.StringBuilder
		// @2F: iload_1
		// @30: invokevirtual java.lang.StringBuilder.append(int)java.lang.StringBuilder
		// @33: bipush 41 (0x29)
		// @35: invokevirtual java.lang.StringBuilder.append(char)java.lang.StringBuilder
		// @38: invokevirtual java.lang.StringBuilder.toString()java.lang.String
		// @3B: invokestatic game.C_100181_cf.func_105695_a(java.lang.Throwable, java.lang.String)game.C_100170_cm
		// @3E: athrow
		// @3F: return
	}
	
	public static void func_104525_a(byte arg0)
	{
		// @00: aconst_null
		// @01: putstatic game.C_100037_wb game.C_100092_um.field_104532_b
		// @04: aconst_null
		// @05: putstatic java.lang.String game.C_100092_um.field_104535_l
		// @08: aconst_null
		// @09: putstatic game.C_100112_r game.C_100092_um.field_104531_e
		// @0C: aconst_null
		// @0D: checkcast boolean[][]
		// @10: putstatic boolean[][] game.C_100092_um.field_104536_j
		// @13: aconst_null
		// @14: putstatic game.C_100153_be[] game.C_100092_um.field_104534_a
		// @17: aconst_null
		// @18: checkcast int[][]
		// @1B: putstatic int[][] game.C_100092_um.field_104539_i
		// @1E: aconst_null
		// @1F: putstatic java.lang.String game.C_100092_um.field_104537_k
		// @22: iload_0
		// @23: bipush -93 (0xA3)
		// @25: if_icmple @29
		// @28: return
		// @29: aconst_null
		// @2A: putstatic java.lang.String game.C_100092_um.field_104528_f
		// @2D: goto @51
		// @30: astore_1
		// @31: aload_1
		// @32: new java.lang.StringBuilder
		// @35: dup
		// @36: invokespecial java.lang.StringBuilder.<init>()void
		// @39: getstatic java.lang.String[] game.C_100092_um.field_104540_z
		// @3C: iconst_5
		// @3D: aaload
		// @3E: invokevirtual java.lang.StringBuilder.append(java.lang.String)java.lang.StringBuilder
		// @41: iload_0
		// @42: invokevirtual java.lang.StringBuilder.append(int)java.lang.StringBuilder
		// @45: bipush 41 (0x29)
		// @47: invokevirtual java.lang.StringBuilder.append(char)java.lang.StringBuilder
		// @4A: invokevirtual java.lang.StringBuilder.toString()java.lang.String
		// @4D: invokestatic game.C_100181_cf.func_105695_a(java.lang.Throwable, java.lang.String)game.C_100170_cm
		// @50: athrow
		// @51: return
	}
	
	public final Object next()
	{
		// @00: getstatic int game.SteelSentinels.field_105275_O
		// @03: istore_2
		// @04: aload_0
		// @05: getfield game.C_100158_da game.C_100092_um.field_104538_h
		// @08: aload_0
		// @09: getfield game.C_100266_me game.C_100092_um.field_104530_d
		// @0C: getfield game.C_100158_da[] game.C_100266_me.field_106658_i
		// @0F: aload_0
		// @10: getfield int game.C_100092_um.field_104533_c
		// @13: iconst_1
		// @14: isub
		// @15: aaload
		// @16: if_acmpne @1D
		// @19: goto @31
		// @1C: athrow
		// @1D: aload_0
		// @1E: getfield game.C_100158_da game.C_100092_um.field_104538_h
		// @21: astore_1
		// @22: aload_0
		// @23: aload_1
		// @24: getfield game.C_100158_da game.C_100158_da.field_100590_f
		// @27: putfield game.C_100158_da game.C_100092_um.field_104538_h
		// @2A: aload_0
		// @2B: aload_1
		// @2C: putfield game.C_100158_da game.C_100092_um.field_104529_g
		// @2F: aload_1
		// @30: areturn
		// @31: aload_0
		// @32: getfield game.C_100266_me game.C_100092_um.field_104530_d
		// @35: getfield int game.C_100266_me.field_106655_j
		// @38: iconst_m1
		// @39: ixor
		// @3A: aload_0
		// @3B: getfield int game.C_100092_um.field_104533_c
		// @3E: iconst_m1
		// @3F: ixor
		// @40: if_icmpge @83
		// @43: aload_0
		// @44: getfield game.C_100266_me game.C_100092_um.field_104530_d
		// @47: getfield game.C_100158_da[] game.C_100266_me.field_106658_i
		// @4A: aload_0
		// @4B: dup
		// @4C: getfield int game.C_100092_um.field_104533_c
		// @4F: dup_x1
		// @50: iconst_1
		// @51: iadd
		// @52: putfield int game.C_100092_um.field_104533_c
		// @55: aaload
		// @56: getfield game.C_100158_da game.C_100158_da.field_100590_f
		// @59: astore_1
		// @5A: aload_1
		// @5B: aload_0
		// @5C: getfield game.C_100266_me game.C_100092_um.field_104530_d
		// @5F: getfield game.C_100158_da[] game.C_100266_me.field_106658_i
		// @62: aload_0
		// @63: getfield int game.C_100092_um.field_104533_c
		// @66: iconst_m1
		// @67: iadd
		// @68: aaload
		// @69: if_acmpne @70
		// @6C: goto @7F
		// @6F: athrow
		// @70: aload_0
		// @71: aload_1
		// @72: putfield game.C_100158_da game.C_100092_um.field_104529_g
		// @75: aload_0
		// @76: aload_1
		// @77: getfield game.C_100158_da game.C_100158_da.field_100590_f
		// @7A: putfield game.C_100158_da game.C_100092_um.field_104538_h
		// @7D: aload_1
		// @7E: areturn
		// @7F: iload_2
		// @80: ifeq @31
		// @83: aconst_null
		// @84: areturn
		// @85: astore_1
		// @86: aload_1
		// @87: getstatic java.lang.String[] game.C_100092_um.field_104540_z
		// @8A: bipush 7 (0x07)
		// @8C: aaload
		// @8D: invokestatic game.C_100181_cf.func_105695_a(java.lang.Throwable, java.lang.String)game.C_100170_cm
		// @90: athrow
	}
	
	C_100092_um(C_100266_me arg0)
	{
		// @00: aload_0
		// @01: invokespecial java.lang.Object.<init>()void
		// @04: aload_0
		// @05: aconst_null
		// @06: putfield game.C_100158_da game.C_100092_um.field_104529_g
		// @09: aload_0
		// @0A: aload_1
		// @0B: putfield game.C_100266_me game.C_100092_um.field_104530_d
		// @0E: aload_0
		// @0F: iconst_1
		// @10: invokespecial game.C_100092_um.func_104522_a(int)void
		// @13: goto @48
		// @16: astore_2
		// @17: aload_2
		// @18: new java.lang.StringBuilder
		// @1B: dup
		// @1C: invokespecial java.lang.StringBuilder.<init>()void
		// @1F: getstatic java.lang.String[] game.C_100092_um.field_104540_z
		// @22: iconst_2
		// @23: aaload
		// @24: invokevirtual java.lang.StringBuilder.append(java.lang.String)java.lang.StringBuilder
		// @27: aload_1
		// @28: ifnull @34
		// @2B: getstatic java.lang.String[] game.C_100092_um.field_104540_z
		// @2E: iconst_1
		// @2F: aaload
		// @30: goto @39
		// @33: athrow
		// @34: getstatic java.lang.String[] game.C_100092_um.field_104540_z
		// @37: iconst_0
		// @38: aaload
		// @39: invokevirtual java.lang.StringBuilder.append(java.lang.String)java.lang.StringBuilder
		// @3C: bipush 41 (0x29)
		// @3E: invokevirtual java.lang.StringBuilder.append(char)java.lang.StringBuilder
		// @41: invokevirtual java.lang.StringBuilder.toString()java.lang.String
		// @44: invokestatic game.C_100181_cf.func_105695_a(java.lang.Throwable, java.lang.String)game.C_100170_cm
		// @47: athrow
		// @48: return
	}
	
	static
	{
		// @00: bipush 12 (0x0C)
		// @02: anewarray java.lang.String
		// @05: dup
		// @06: iconst_0
		// @07: ldc "\u0016RFu"
		// @09: invokestatic game.C_100092_um.func_104526_z(java.lang.String)char[]
		// @0C: invokestatic game.C_100092_um.func_104524_z(char[])java.lang.String
		// @0F: aastore
		// @10: dup
		// @11: iconst_1
		// @12: ldc "\u0003\t\u00047K"
		// @14: invokestatic game.C_100092_um.func_104526_z(java.lang.String)char[]
		// @17: invokestatic game.C_100092_um.func_104524_z(char[])java.lang.String
		// @1A: aastore
		// @1B: dup
		// @1C: iconst_2
		// @1D: ldc "\rJ\u0004%_\u0016N^'\u001e"
		// @1F: invokestatic game.C_100092_um.func_104526_z(java.lang.String)char[]
		// @22: invokestatic game.C_100092_um.func_104524_z(char[])java.lang.String
		// @25: aastore
		// @26: dup
		// @27: iconst_3
		// @28: ldc "\rJ\u0004kS\u0015H\\|\u001eQ"
		// @2A: invokestatic game.C_100092_um.func_104526_z(java.lang.String)char[]
		// @2D: invokestatic game.C_100092_um.func_104524_z(char[])java.lang.String
		// @30: aastore
		// @31: dup
		// @32: iconst_4
		// @33: ldc "\rJ\u0004\\\u001e"
		// @35: invokestatic game.C_100092_um.func_104526_z(java.lang.String)char[]
		// @38: invokestatic game.C_100092_um.func_104524_z(char[])java.lang.String
		// @3B: aastore
		// @3C: dup
		// @3D: iconst_5
		// @3E: ldc "\rJ\u0004Z\u001e"
		// @40: invokestatic game.C_100092_um.func_104526_z(java.lang.String)char[]
		// @43: invokestatic game.C_100092_um.func_104524_z(char[])java.lang.String
		// @46: aastore
		// @47: dup
		// @48: bipush 6 (0x06)
		// @4A: ldc "\rJ\u0004[\u001e"
		// @4C: invokestatic game.C_100092_um.func_104526_z(java.lang.String)char[]
		// @4F: invokestatic game.C_100092_um.func_104524_z(char[])java.lang.String
		// @52: aastore
		// @53: dup
		// @54: bipush 7 (0x07)
		// @56: ldc "\rJ\u0004wS\u0000S\u00020"
		// @58: invokestatic game.C_100092_um.func_104526_z(java.lang.String)char[]
		// @5B: invokestatic game.C_100092_um.func_104524_z(char[])java.lang.String
		// @5E: aastore
		// @5F: dup
		// @60: bipush 8 (0x08)
		// @62: ldc "\rJ\u0004]\u001e"
		// @64: invokestatic game.C_100092_um.func_104526_z(java.lang.String)char[]
		// @67: invokestatic game.C_100092_um.func_104524_z(char[])java.lang.String
		// @6A: aastore
		// @6B: dup
		// @6C: bipush 9 (0x09)
		// @6E: ldc "\rJ\u0004_\u001e"
		// @70: invokestatic game.C_100092_um.func_104526_z(java.lang.String)char[]
		// @73: invokestatic game.C_100092_um.func_104524_z(char[])java.lang.String
		// @76: aastore
		// @77: dup
		// @78: bipush 10 (0x0A)
		// @7A: ldc "\rJ\u0004qW\u000biOaBP\u000e"
		// @7C: invokestatic game.C_100092_um.func_104526_z(java.lang.String)char[]
		// @7F: invokestatic game.C_100092_um.func_104524_z(char[])java.lang.String
		// @82: aastore
		// @83: dup
		// @84: bipush 11 (0x0B)
		// @86: ldc "\rJ\u0004X\u001e"
		// @88: invokestatic game.C_100092_um.func_104526_z(java.lang.String)char[]
		// @8B: invokestatic game.C_100092_um.func_104524_z(char[])java.lang.String
		// @8E: aastore
		// @8F: putstatic java.lang.String[] game.C_100092_um.field_104540_z
		// @92: ldc "?b~9r=akLz,\u0007y\\b"
		// @94: invokestatic game.C_100092_um.func_104526_z(java.lang.String)char[]
		// @97: invokestatic game.C_100092_um.func_104524_z(char[])java.lang.String
		// @9A: putstatic java.lang.String game.C_100092_um.field_104537_k
		// @9D: ldc "*BY|W\nDB9_\u0016SE9\n\u001bHF$\u0006HAL\u007fPFBD|D\u001f^\nj^\u0011BF}ED\u0008IvZF\u0007Cj\u0016\u0016BO}S\u001c\u0007H|P\u0017UO9B\u0010B\n%\u0013H\u0019\nzW\u0016\u0007H|\u0016\u001dIMpX\u001dBX|RV"
		// @9F: invokestatic game.C_100092_um.func_104526_z(java.lang.String)char[]
		// @A2: invokestatic game.C_100092_um.func_104524_z(char[])java.lang.String
		// @A5: putstatic java.lang.String game.C_100092_um.field_104528_f
		// @A8: iconst_3
		// @A9: anewarray boolean[]
		// @AC: dup
		// @AD: iconst_0
		// @AE: aconst_null
		// @AF: aastore
		// @B0: dup
		// @B1: iconst_1
		// @B2: iconst_3
		// @B3: newarray boolean[]
		// @B5: dup
		// @B6: iconst_0
		// @B7: iconst_0
		// @B8: bastore
		// @B9: dup
		// @BA: iconst_1
		// @BB: iconst_0
		// @BC: bastore
		// @BD: dup
		// @BE: iconst_2
		// @BF: iconst_0
		// @C0: bastore
		// @C1: aastore
		// @C2: dup
		// @C3: iconst_2
		// @C4: bipush 6 (0x06)
		// @C6: newarray boolean[]
		// @C8: dup
		// @C9: iconst_0
		// @CA: iconst_0
		// @CB: bastore
		// @CC: dup
		// @CD: iconst_1
		// @CE: iconst_0
		// @CF: bastore
		// @D0: dup
		// @D1: iconst_2
		// @D2: iconst_0
		// @D3: bastore
		// @D4: dup
		// @D5: iconst_3
		// @D6: iconst_0
		// @D7: bastore
		// @D8: dup
		// @D9: iconst_4
		// @DA: iconst_0
		// @DB: bastore
		// @DC: dup
		// @DD: iconst_5
		// @DE: iconst_1
		// @DF: bastore
		// @E0: aastore
		// @E1: putstatic boolean[][] game.C_100092_um.field_104536_j
		// @E4: return
	}
	
	private static char[] func_104526_z(String arg0)
	{
		// @00: aload_0
		// @01: invokevirtual java.lang.String.toCharArray()char[]
		// @04: dup
		// @05: arraylength
		// @06: iconst_2
		// @07: if_icmpge @13
		// @0A: dup
		// @0B: iconst_0
		// @0C: dup2
		// @0D: caload
		// @0E: bipush 54 (0x36)
		// @10: ixor
		// @11: i2c
		// @12: castore
		// @13: areturn
	}
	
	private static String func_104524_z(char[] arg0)
	{
		// @00: aload_0
		// @01: dup
		// @02: arraylength
		// @03: swap
		// @04: iconst_0
		// @05: istore_1
		// @06: goto @4C
		// @09: dup
		// @0A: iload_1
		// @0B: dup2
		// @0C: caload
		// @0D: iload_1
		// @0E: iconst_5
		// @0F: irem
		// @10: tableswitch def: @44, for 0: @30, for 1: @35, for 2: @3A, for 3: @3F
		// @30: bipush 120 (0x78)
		// @32: goto @46
		// @35: bipush 39 (0x27)
		// @37: goto @46
		// @3A: bipush 42 (0x2A)
		// @3C: goto @46
		// @3F: bipush 25 (0x19)
		// @41: goto @46
		// @44: bipush 54 (0x36)
		// @46: ixor
		// @47: i2c
		// @48: castore
		// @49: iinc #1 +1
		// @4C: swap
		// @4D: dup_x1
		// @4E: iload_1
		// @4F: if_icmpgt @09
		// @52: new java.lang.String
		// @55: dup_x1
		// @56: swap
		// @57: invokespecial java.lang.String.<init>(char[])void
		// @5A: invokevirtual java.lang.String.intern()java.lang.String
		// @5D: areturn
	}
}
