package game;

final class C_100240_oj
{
	static boolean field_106322_j;
	boolean field_106311_f;
	C_100302_ka field_106314_e;
	int field_106312_g;
	String field_106320_l;
	int[] field_106326_p;
	int field_106323_k;
	String field_106325_i;
	long field_106316_c;
	int field_106315_b;
	String field_106321_m;
	int field_106324_h;
	String field_106313_d;
	int field_106317_a;
	static C_100304_kl[] field_106319_o;
	static C_100098_h field_106318_n;
	private static final String[] field_106327_z;
	
	final int func_106309_a(int arg0)
	{
		// @00: aload_0
		// @01: getfield boolean game.C_100240_oj.field_106311_f
		// @04: ifne @21
		// @07: iconst_2
		// @08: aload_0
		// @09: getfield int game.C_100240_oj.field_106317_a
		// @0C: if_icmpne @23
		// @0F: goto @13
		// @12: athrow
		// @13: iconst_m1
		// @14: aload_0
		// @15: getfield int game.C_100240_oj.field_106315_b
		// @18: iconst_m1
		// @19: ixor
		// @1A: if_icmple @23
		// @1D: goto @21
		// @20: athrow
		// @21: iconst_2
		// @22: ireturn
		// @23: getstatic long game.C_100321_hi.field_107215_f
		// @26: aload_0
		// @27: getfield long game.C_100240_oj.field_106316_c
		// @2A: lcmp
		// @2B: ifeq @32
		// @2E: goto @34
		// @31: athrow
		// @32: iconst_1
		// @33: ireturn
		// @34: iload_1
		// @35: iconst_m1
		// @36: if_icmpeq @47
		// @39: aconst_null
		// @3A: checkcast java.lang.CharSequence
		// @3D: bipush 91 (0x5B)
		// @3F: invokestatic game.C_100240_oj.func_106310_a(java.lang.CharSequence, byte)boolean
		// @42: pop
		// @43: goto @47
		// @46: athrow
		// @47: iconst_2
		// @48: getstatic int game.C_100062_dk.field_104281_d
		// @4B: if_icmpne @64
		// @4E: aload_0
		// @4F: getfield java.lang.String game.C_100240_oj.field_106313_d
		// @52: bipush 120 (0x78)
		// @54: invokestatic game.C_100099_fb.func_103035_a(java.lang.String, byte)boolean
		// @57: ifne @62
		// @5A: goto @5E
		// @5D: athrow
		// @5E: goto @64
		// @61: athrow
		// @62: iconst_1
		// @63: ireturn
		// @64: iconst_0
		// @65: ireturn
		// @66: astore_2
		// @67: aload_2
		// @68: new java.lang.StringBuilder
		// @6B: dup
		// @6C: invokespecial java.lang.StringBuilder.<init>()void
		// @6F: getstatic java.lang.String[] game.C_100240_oj.field_106327_z
		// @72: iconst_5
		// @73: aaload
		// @74: invokevirtual java.lang.StringBuilder.append(java.lang.String)java.lang.StringBuilder
		// @77: iload_1
		// @78: invokevirtual java.lang.StringBuilder.append(int)java.lang.StringBuilder
		// @7B: bipush 41 (0x29)
		// @7D: invokevirtual java.lang.StringBuilder.append(char)java.lang.StringBuilder
		// @80: invokevirtual java.lang.StringBuilder.toString()java.lang.String
		// @83: invokestatic game.C_100181_cf.func_105695_a(java.lang.Throwable, java.lang.String)game.C_100170_cm
		// @86: athrow
	}
	
	public static void func_106308_a(boolean arg0)
	{
		// @00: iload_0
		// @01: iconst_1
		// @02: if_icmpeq @06
		// @05: return
		// @06: aconst_null
		// @07: putstatic game.C_100098_h game.C_100240_oj.field_106318_n
		// @0A: aconst_null
		// @0B: putstatic game.C_100304_kl[] game.C_100240_oj.field_106319_o
		// @0E: goto @32
		// @11: astore_1
		// @12: aload_1
		// @13: new java.lang.StringBuilder
		// @16: dup
		// @17: invokespecial java.lang.StringBuilder.<init>()void
		// @1A: getstatic java.lang.String[] game.C_100240_oj.field_106327_z
		// @1D: iconst_0
		// @1E: aaload
		// @1F: invokevirtual java.lang.StringBuilder.append(java.lang.String)java.lang.StringBuilder
		// @22: iload_0
		// @23: invokevirtual java.lang.StringBuilder.append(boolean)java.lang.StringBuilder
		// @26: bipush 41 (0x29)
		// @28: invokevirtual java.lang.StringBuilder.append(char)java.lang.StringBuilder
		// @2B: invokevirtual java.lang.StringBuilder.toString()java.lang.String
		// @2E: invokestatic game.C_100181_cf.func_105695_a(java.lang.Throwable, java.lang.String)game.C_100170_cm
		// @31: athrow
		// @32: return
	}
	
	static final String func_106303_a(int arg0, String arg1, int arg2)
	{
		// @000: iload_2
		// @001: sipush -1064 (0xFBD8)
		// @004: if_icmpeq @011
		// @007: bipush 118 (0x76)
		// @009: iconst_0
		// @00A: invokestatic game.C_100240_oj.func_106301_a(byte, boolean)void
		// @00D: goto @011
		// @010: athrow
		// @011: aload_1
		// @012: bipush 43 (0x2B)
		// @014: invokestatic game.C_100240_oj.func_106310_a(java.lang.CharSequence, byte)boolean
		// @017: ifeq @01E
		// @01A: goto @022
		// @01D: athrow
		// @01E: getstatic java.lang.String game.C_100315_la.field_107175_g
		// @021: areturn
		// @022: bipush -3 (0xFD)
		// @024: getstatic int game.C_100062_dk.field_104281_d
		// @027: iconst_m1
		// @028: ixor
		// @029: if_icmpeq @030
		// @02C: getstatic java.lang.String game.C_100346_ja.field_103490_v
		// @02F: areturn
		// @030: aload_1
		// @031: sipush -7290 (0xE386)
		// @034: invokestatic game.C_100050_vg.func_100621_a(java.lang.String, int)boolean
		// @037: ifeq @03E
		// @03A: getstatic java.lang.String game.C_100255_pj.field_105253_u
		// @03D: areturn
		// @03E: aload_1
		// @03F: bipush 120 (0x78)
		// @041: invokestatic game.C_100099_fb.func_103035_a(java.lang.String, byte)boolean
		// @044: ifne @04B
		// @047: goto @05D
		// @04A: athrow
		// @04B: sipush -30945 (0x871F)
		// @04E: iconst_1
		// @04F: anewarray java.lang.String
		// @052: dup
		// @053: iconst_0
		// @054: aload_1
		// @055: aastore
		// @056: getstatic java.lang.String game.C_100255_pj.field_105242_E
		// @059: invokestatic game.C_100132_td.func_104965_a(int, java.lang.String[], java.lang.String)java.lang.String
		// @05C: areturn
		// @05D: bipush -101 (0x9B)
		// @05F: getstatic int game.C_100291_jj.field_106878_a
		// @062: iconst_m1
		// @063: ixor
		// @064: if_icmplt @07C
		// @067: iconst_m1
		// @068: getstatic int game.C_100212_qc.field_105976_b
		// @06B: iconst_m1
		// @06C: ixor
		// @06D: if_icmple @078
		// @070: goto @074
		// @073: athrow
		// @074: goto @07C
		// @077: athrow
		// @078: getstatic java.lang.String game.C_100110_s.field_104843_f
		// @07B: areturn
		// @07C: sipush -201 (0xFF37)
		// @07F: getstatic int game.C_100291_jj.field_106878_a
		// @082: iconst_m1
		// @083: ixor
		// @084: if_icmplt @08B
		// @087: getstatic java.lang.String game.C_100110_s.field_104843_f
		// @08A: areturn
		// @08B: aload_1
		// @08C: bipush -45 (0xD3)
		// @08E: invokestatic game.C_100032_gk.func_103125_a(java.lang.String, byte)boolean
		// @091: ifne @098
		// @094: goto @0AA
		// @097: athrow
		// @098: sipush -30945 (0x871F)
		// @09B: iconst_1
		// @09C: anewarray java.lang.String
		// @09F: dup
		// @0A0: iconst_0
		// @0A1: aload_1
		// @0A2: aastore
		// @0A3: getstatic java.lang.String game.C_100116_ei.field_104124_a
		// @0A6: invokestatic game.C_100132_td.func_104965_a(int, java.lang.String[], java.lang.String)java.lang.String
		// @0A9: areturn
		// @0AA: getstatic game.C_100278_nd game.C_100115_ej.field_102043_Yb
		// @0AD: astore_3
		// @0AE: aload_3
		// @0AF: iload_0
		// @0B0: bipush 114 (0x72)
		// @0B2: invokevirtual game.C_100278_nd.func_101189_h(int, int)void
		// @0B5: aload_3
		// @0B6: dup
		// @0B7: getfield int game.C_100278_nd.field_101177_n
		// @0BA: iconst_1
		// @0BB: iadd
		// @0BC: putfield int game.C_100278_nd.field_101177_n
		// @0BF: aload_3
		// @0C0: getfield int game.C_100278_nd.field_101177_n
		// @0C3: istore #4
		// @0C5: aload_3
		// @0C6: sipush 7838 (0x1E9E)
		// @0C9: iconst_0
		// @0CA: invokevirtual game.C_100278_nd.func_101169_f(int, int)void
		// @0CD: aload_3
		// @0CE: iload_2
		// @0CF: sipush 27371 (0x6AEB)
		// @0D2: ixor
		// @0D3: aload_1
		// @0D4: invokevirtual game.C_100278_nd.func_101167_a(int, java.lang.String)void
		// @0D7: aload_3
		// @0D8: aload_3
		// @0D9: getfield int game.C_100278_nd.field_101177_n
		// @0DC: iload #4
		// @0DE: isub
		// @0DF: bipush -81 (0xAF)
		// @0E1: invokevirtual game.C_100278_nd.func_101139_c(int, byte)void
		// @0E4: aconst_null
		// @0E5: areturn
		// @0E6: astore_3
		// @0E7: aload_3
		// @0E8: new java.lang.StringBuilder
		// @0EB: dup
		// @0EC: invokespecial java.lang.StringBuilder.<init>()void
		// @0EF: getstatic java.lang.String[] game.C_100240_oj.field_106327_z
		// @0F2: bipush 7 (0x07)
		// @0F4: aaload
		// @0F5: invokevirtual java.lang.StringBuilder.append(java.lang.String)java.lang.StringBuilder
		// @0F8: iload_0
		// @0F9: invokevirtual java.lang.StringBuilder.append(int)java.lang.StringBuilder
		// @0FC: bipush 44 (0x2C)
		// @0FE: invokevirtual java.lang.StringBuilder.append(char)java.lang.StringBuilder
		// @101: aload_1
		// @102: ifnull @10E
		// @105: getstatic java.lang.String[] game.C_100240_oj.field_106327_z
		// @108: iconst_3
		// @109: aaload
		// @10A: goto @113
		// @10D: athrow
		// @10E: getstatic java.lang.String[] game.C_100240_oj.field_106327_z
		// @111: iconst_2
		// @112: aaload
		// @113: invokevirtual java.lang.StringBuilder.append(java.lang.String)java.lang.StringBuilder
		// @116: bipush 44 (0x2C)
		// @118: invokevirtual java.lang.StringBuilder.append(char)java.lang.StringBuilder
		// @11B: iload_2
		// @11C: invokevirtual java.lang.StringBuilder.append(int)java.lang.StringBuilder
		// @11F: bipush 41 (0x29)
		// @121: invokevirtual java.lang.StringBuilder.append(char)java.lang.StringBuilder
		// @124: invokevirtual java.lang.StringBuilder.toString()java.lang.String
		// @127: invokestatic game.C_100181_cf.func_105695_a(java.lang.Throwable, java.lang.String)game.C_100170_cm
		// @12A: athrow
	}
	
	static final void func_106302_b(int arg0)
	{
		// @00: bipush 119 (0x77)
		// @02: bipush -14 (0xF2)
		// @04: iload_0
		// @05: isub
		// @06: bipush 61 (0x3D)
		// @08: idiv
		// @09: irem
		// @0A: istore_1
		// @0B: sipush 23494 (0x5BC6)
		// @0E: getstatic game.C_100033_gj game.C_100336_im.field_102547_q
		// @11: invokestatic game.C_100107_u.func_104767_a(int, game.C_100033_gj)void
		// @14: goto @39
		// @17: astore_1
		// @18: aload_1
		// @19: new java.lang.StringBuilder
		// @1C: dup
		// @1D: invokespecial java.lang.StringBuilder.<init>()void
		// @20: getstatic java.lang.String[] game.C_100240_oj.field_106327_z
		// @23: bipush 9 (0x09)
		// @25: aaload
		// @26: invokevirtual java.lang.StringBuilder.append(java.lang.String)java.lang.StringBuilder
		// @29: iload_0
		// @2A: invokevirtual java.lang.StringBuilder.append(int)java.lang.StringBuilder
		// @2D: bipush 41 (0x29)
		// @2F: invokevirtual java.lang.StringBuilder.append(char)java.lang.StringBuilder
		// @32: invokevirtual java.lang.StringBuilder.toString()java.lang.String
		// @35: invokestatic game.C_100181_cf.func_105695_a(java.lang.Throwable, java.lang.String)game.C_100170_cm
		// @38: athrow
		// @39: return
	}
	
	static final void func_106307_b(byte arg0, boolean arg1)
	{
		// @00: iload_1
		// @01: iconst_1
		// @02: bipush -115 (0x8D)
		// @04: invokestatic game.C_100144_bm.func_102089_a(boolean, boolean, int)void
		// @07: iload_0
		// @08: bipush 102 (0x66)
		// @0A: if_icmpgt @11
		// @0D: iconst_0
		// @0E: putstatic boolean game.C_100240_oj.field_106322_j
		// @11: goto @3F
		// @14: astore_2
		// @15: aload_2
		// @16: new java.lang.StringBuilder
		// @19: dup
		// @1A: invokespecial java.lang.StringBuilder.<init>()void
		// @1D: getstatic java.lang.String[] game.C_100240_oj.field_106327_z
		// @20: bipush 6 (0x06)
		// @22: aaload
		// @23: invokevirtual java.lang.StringBuilder.append(java.lang.String)java.lang.StringBuilder
		// @26: iload_0
		// @27: invokevirtual java.lang.StringBuilder.append(int)java.lang.StringBuilder
		// @2A: bipush 44 (0x2C)
		// @2C: invokevirtual java.lang.StringBuilder.append(char)java.lang.StringBuilder
		// @2F: iload_1
		// @30: invokevirtual java.lang.StringBuilder.append(boolean)java.lang.StringBuilder
		// @33: bipush 41 (0x29)
		// @35: invokevirtual java.lang.StringBuilder.append(char)java.lang.StringBuilder
		// @38: invokevirtual java.lang.StringBuilder.toString()java.lang.String
		// @3B: invokestatic game.C_100181_cf.func_105695_a(java.lang.Throwable, java.lang.String)game.C_100170_cm
		// @3E: athrow
		// @3F: return
	}
	
	static final void func_106301_a(byte arg0, boolean arg1)
	{
		// @000: getstatic int game.SteelSentinels.field_105275_O
		// @003: istore_3
		// @004: bipush -42 (0xD6)
		// @006: iload_0
		// @007: bipush 19 (0x13)
		// @009: isub
		// @00A: bipush 37 (0x25)
		// @00C: idiv
		// @00D: irem
		// @00E: istore_2
		// @00F: iload_1
		// @010: ifne @021
		// @013: getstatic game.C_100211_qd game.C_100068_vc.field_104342_d
		// @016: ifnull @021
		// @019: goto @01D
		// @01C: athrow
		// @01D: goto @025
		// @020: athrow
		// @021: iconst_0
		// @022: putstatic boolean game.C_100003_ga.field_103535_w
		// @025: iload_1
		// @026: ifeq @07D
		// @029: getstatic int game.C_100015_wh.field_103782_d
		// @02C: iconst_m1
		// @02D: ixor
		// @02E: iconst_m1
		// @02F: if_icmpge @046
		// @032: goto @036
		// @035: athrow
		// @036: getstatic int game.C_100015_wh.field_103782_d
		// @039: iconst_1
		// @03A: isub
		// @03B: putstatic int game.C_100015_wh.field_103782_d
		// @03E: iload_3
		// @03F: ifeq @1D3
		// @042: goto @046
		// @045: athrow
		// @046: iconst_m1
		// @047: getstatic int game.C_100102_w.field_104635_b
		// @04A: iconst_m1
		// @04B: ixor
		// @04C: if_icmple @063
		// @04F: goto @053
		// @052: athrow
		// @053: getstatic int game.C_100102_w.field_104635_b
		// @056: iconst_1
		// @057: isub
		// @058: putstatic int game.C_100102_w.field_104635_b
		// @05B: iload_3
		// @05C: ifeq @1D3
		// @05F: goto @063
		// @062: athrow
		// @063: getstatic int game.C_100100_i.field_102014_hc
		// @066: ifgt @071
		// @069: goto @06D
		// @06C: athrow
		// @06D: goto @1D3
		// @070: athrow
		// @071: getstatic int game.C_100100_i.field_102014_hc
		// @074: iconst_1
		// @075: isub
		// @076: putstatic int game.C_100100_i.field_102014_hc
		// @079: iload_3
		// @07A: ifeq @1D3
		// @07D: aconst_null
		// @07E: getstatic game.C_100211_qd game.C_100068_vc.field_104342_d
		// @081: if_acmpeq @0F1
		// @084: goto @088
		// @087: athrow
		// @088: getstatic int game.C_100015_wh.field_103782_d
		// @08B: iconst_m1
		// @08C: ixor
		// @08D: iconst_m1
		// @08E: if_icmpge @0A5
		// @091: goto @095
		// @094: athrow
		// @095: getstatic int game.C_100015_wh.field_103782_d
		// @098: iconst_1
		// @099: isub
		// @09A: putstatic int game.C_100015_wh.field_103782_d
		// @09D: iload_3
		// @09E: ifeq @1D3
		// @0A1: goto @0A5
		// @0A4: athrow
		// @0A5: getstatic int game.C_100102_w.field_104635_b
		// @0A8: iconst_m1
		// @0A9: ixor
		// @0AA: iconst_m1
		// @0AB: if_icmpge @0C2
		// @0AE: goto @0B2
		// @0B1: athrow
		// @0B2: getstatic int game.C_100102_w.field_104635_b
		// @0B5: iconst_1
		// @0B6: isub
		// @0B7: putstatic int game.C_100102_w.field_104635_b
		// @0BA: iload_3
		// @0BB: ifeq @1D3
		// @0BE: goto @0C2
		// @0C1: athrow
		// @0C2: getstatic int game.C_100239_oi.field_102312_P
		// @0C5: getstatic int game.C_100100_i.field_102014_hc
		// @0C8: if_icmpgt @0D3
		// @0CB: goto @0CF
		// @0CE: athrow
		// @0CF: goto @1D3
		// @0D2: athrow
		// @0D3: iconst_0
		// @0D4: getstatic int game.C_100100_i.field_102014_hc
		// @0D7: if_icmpeq @0DE
		// @0DA: goto @0E5
		// @0DD: athrow
		// @0DE: sipush 743 (0x02E7)
		// @0E1: iconst_0
		// @0E2: invokestatic game.C_100080_b.func_104429_a(int, boolean)void
		// @0E5: getstatic int game.C_100100_i.field_102014_hc
		// @0E8: iconst_1
		// @0E9: iadd
		// @0EA: putstatic int game.C_100100_i.field_102014_hc
		// @0ED: iload_3
		// @0EE: ifeq @1D3
		// @0F1: getstatic game.C_100211_qd game.SteelSentinels.field_105274_N
		// @0F4: ifnull @166
		// @0F7: goto @0FB
		// @0FA: athrow
		// @0FB: iconst_0
		// @0FC: getstatic int game.C_100015_wh.field_103782_d
		// @0FF: if_icmplt @156
		// @102: goto @106
		// @105: athrow
		// @106: iconst_0
		// @107: getstatic int game.C_100100_i.field_102014_hc
		// @10A: if_icmplt @146
		// @10D: goto @111
		// @110: athrow
		// @111: getstatic int game.C_100239_oi.field_102312_P
		// @114: iconst_m1
		// @115: ixor
		// @116: getstatic int game.C_100102_w.field_104635_b
		// @119: iconst_m1
		// @11A: ixor
		// @11B: if_icmplt @126
		// @11E: goto @122
		// @121: athrow
		// @122: goto @1D3
		// @125: athrow
		// @126: iconst_m1
		// @127: getstatic int game.C_100102_w.field_104635_b
		// @12A: iconst_m1
		// @12B: ixor
		// @12C: if_icmpne @13A
		// @12F: sipush 743 (0x02E7)
		// @132: iconst_1
		// @133: invokestatic game.C_100080_b.func_104429_a(int, boolean)void
		// @136: goto @13A
		// @139: athrow
		// @13A: getstatic int game.C_100102_w.field_104635_b
		// @13D: iconst_1
		// @13E: iadd
		// @13F: putstatic int game.C_100102_w.field_104635_b
		// @142: iload_3
		// @143: ifeq @1D3
		// @146: getstatic int game.C_100100_i.field_102014_hc
		// @149: iconst_1
		// @14A: isub
		// @14B: putstatic int game.C_100100_i.field_102014_hc
		// @14E: iload_3
		// @14F: ifeq @1D3
		// @152: goto @156
		// @155: athrow
		// @156: getstatic int game.C_100015_wh.field_103782_d
		// @159: iconst_1
		// @15A: isub
		// @15B: putstatic int game.C_100015_wh.field_103782_d
		// @15E: iload_3
		// @15F: ifeq @1D3
		// @162: goto @166
		// @165: athrow
		// @166: iconst_0
		// @167: putstatic boolean game.C_100003_ga.field_103535_w
		// @16A: iconst_m1
		// @16B: getstatic int game.C_100102_w.field_104635_b
		// @16E: iconst_m1
		// @16F: ixor
		// @170: if_icmpgt @1C7
		// @173: goto @177
		// @176: athrow
		// @177: iconst_m1
		// @178: getstatic int game.C_100100_i.field_102014_hc
		// @17B: iconst_m1
		// @17C: ixor
		// @17D: if_icmpgt @1B7
		// @180: goto @184
		// @183: athrow
		// @184: getstatic int game.C_100239_oi.field_102312_P
		// @187: iconst_m1
		// @188: ixor
		// @189: getstatic int game.C_100015_wh.field_103782_d
		// @18C: iconst_m1
		// @18D: ixor
		// @18E: if_icmpge @1D3
		// @191: goto @195
		// @194: athrow
		// @195: iconst_m1
		// @196: getstatic int game.C_100015_wh.field_103782_d
		// @199: iconst_m1
		// @19A: ixor
		// @19B: if_icmpne @1AB
		// @19E: goto @1A2
		// @1A1: athrow
		// @1A2: bipush -111 (0x91)
		// @1A4: invokestatic game.C_100263_mb.func_106500_a(byte)void
		// @1A7: goto @1AB
		// @1AA: athrow
		// @1AB: getstatic int game.C_100015_wh.field_103782_d
		// @1AE: iconst_1
		// @1AF: iadd
		// @1B0: putstatic int game.C_100015_wh.field_103782_d
		// @1B3: iload_3
		// @1B4: ifeq @1D3
		// @1B7: getstatic int game.C_100100_i.field_102014_hc
		// @1BA: iconst_1
		// @1BB: isub
		// @1BC: putstatic int game.C_100100_i.field_102014_hc
		// @1BF: iload_3
		// @1C0: ifeq @1D3
		// @1C3: goto @1C7
		// @1C6: athrow
		// @1C7: getstatic int game.C_100102_w.field_104635_b
		// @1CA: iconst_1
		// @1CB: isub
		// @1CC: putstatic int game.C_100102_w.field_104635_b
		// @1CF: goto @1D3
		// @1D2: athrow
		// @1D3: goto @201
		// @1D6: astore_2
		// @1D7: aload_2
		// @1D8: new java.lang.StringBuilder
		// @1DB: dup
		// @1DC: invokespecial java.lang.StringBuilder.<init>()void
		// @1DF: getstatic java.lang.String[] game.C_100240_oj.field_106327_z
		// @1E2: bipush 8 (0x08)
		// @1E4: aaload
		// @1E5: invokevirtual java.lang.StringBuilder.append(java.lang.String)java.lang.StringBuilder
		// @1E8: iload_0
		// @1E9: invokevirtual java.lang.StringBuilder.append(int)java.lang.StringBuilder
		// @1EC: bipush 44 (0x2C)
		// @1EE: invokevirtual java.lang.StringBuilder.append(char)java.lang.StringBuilder
		// @1F1: iload_1
		// @1F2: invokevirtual java.lang.StringBuilder.append(boolean)java.lang.StringBuilder
		// @1F5: bipush 41 (0x29)
		// @1F7: invokevirtual java.lang.StringBuilder.append(char)java.lang.StringBuilder
		// @1FA: invokevirtual java.lang.StringBuilder.toString()java.lang.String
		// @1FD: invokestatic game.C_100181_cf.func_105695_a(java.lang.Throwable, java.lang.String)game.C_100170_cm
		// @200: athrow
		// @201: return
	}
	
	static final boolean func_106304_a(int arg0, byte arg1, int arg2, String arg3, int arg4, int arg5)
	{
		// @00: iload_1
		// @01: bipush -105 (0x97)
		// @03: if_icmplt @0F
		// @06: bipush -112 (0x90)
		// @08: invokestatic game.C_100240_oj.func_106302_b(int)void
		// @0B: goto @0F
		// @0E: athrow
		// @0F: getstatic int game.C_100015_wh.field_103781_g
		// @12: iconst_m1
		// @13: ixor
		// @14: iload #4
		// @16: iconst_m1
		// @17: ixor
		// @18: if_icmpgt @49
		// @1B: iload #4
		// @1D: iload_0
		// @1E: ineg
		// @1F: isub
		// @20: getstatic int game.C_100015_wh.field_103781_g
		// @23: if_icmple @49
		// @26: goto @2A
		// @29: athrow
		// @2A: iload #5
		// @2C: getstatic int game.C_100338_jc.field_105370_l
		// @2F: if_icmpgt @49
		// @32: goto @36
		// @35: athrow
		// @36: iload_2
		// @37: iload #5
		// @39: iadd
		// @3A: getstatic int game.C_100338_jc.field_105370_l
		// @3D: if_icmplt @49
		// @40: goto @44
		// @43: athrow
		// @44: iconst_1
		// @45: goto @4A
		// @48: athrow
		// @49: iconst_0
		// @4A: istore #6
		// @4C: iload #6
		// @4E: ifeq @57
		// @51: ldc 1044724 (0xff0f4)
		// @53: goto @59
		// @56: athrow
		// @57: ldc 1021128 (0xf94c8)
		// @59: istore #7
		// @5B: getstatic game.C_100037_wb[] game.C_100285_nk.field_106786_j
		// @5E: astore #8
		// @60: iload #4
		// @62: iload #5
		// @64: bipush -79 (0xB1)
		// @66: iload_0
		// @67: aload #8
		// @69: iload_2
		// @6A: invokestatic game.C_100157_db.func_103554_a(int, int, int, int, game.C_100037_wb[], int)void
		// @6D: aload_3
		// @6E: ifnonnull @75
		// @71: goto @99
		// @74: athrow
		// @75: getstatic game.C_100193_re game.C_100029_gn.field_103368_S
		// @78: aload_3
		// @79: iconst_0
		// @7A: invokestatic game.C_100096_un.func_104560_a(java.lang.String, boolean)java.lang.String
		// @7D: iload #4
		// @7F: iload_0
		// @80: iconst_2
		// @81: idiv
		// @82: ineg
		// @83: isub
		// @84: iload_2
		// @85: getstatic game.C_100193_re game.C_100029_gn.field_103368_S
		// @88: getfield int game.C_100193_re.field_101769_u
		// @8B: iadd
		// @8C: iconst_m1
		// @8D: isub
		// @8E: iconst_2
		// @8F: idiv
		// @90: iload #5
		// @92: iadd
		// @93: iload #7
		// @95: iconst_m1
		// @96: invokevirtual game.C_100193_re.func_101744_b(java.lang.String, int, int, int, int)void
		// @99: iload #6
		// @9B: ireturn
		// @9C: astore #6
		// @9E: aload #6
		// @A0: new java.lang.StringBuilder
		// @A3: dup
		// @A4: invokespecial java.lang.StringBuilder.<init>()void
		// @A7: getstatic java.lang.String[] game.C_100240_oj.field_106327_z
		// @AA: iconst_1
		// @AB: aaload
		// @AC: invokevirtual java.lang.StringBuilder.append(java.lang.String)java.lang.StringBuilder
		// @AF: iload_0
		// @B0: invokevirtual java.lang.StringBuilder.append(int)java.lang.StringBuilder
		// @B3: bipush 44 (0x2C)
		// @B5: invokevirtual java.lang.StringBuilder.append(char)java.lang.StringBuilder
		// @B8: iload_1
		// @B9: invokevirtual java.lang.StringBuilder.append(int)java.lang.StringBuilder
		// @BC: bipush 44 (0x2C)
		// @BE: invokevirtual java.lang.StringBuilder.append(char)java.lang.StringBuilder
		// @C1: iload_2
		// @C2: invokevirtual java.lang.StringBuilder.append(int)java.lang.StringBuilder
		// @C5: bipush 44 (0x2C)
		// @C7: invokevirtual java.lang.StringBuilder.append(char)java.lang.StringBuilder
		// @CA: aload_3
		// @CB: ifnull @D7
		// @CE: getstatic java.lang.String[] game.C_100240_oj.field_106327_z
		// @D1: iconst_3
		// @D2: aaload
		// @D3: goto @DC
		// @D6: athrow
		// @D7: getstatic java.lang.String[] game.C_100240_oj.field_106327_z
		// @DA: iconst_2
		// @DB: aaload
		// @DC: invokevirtual java.lang.StringBuilder.append(java.lang.String)java.lang.StringBuilder
		// @DF: bipush 44 (0x2C)
		// @E1: invokevirtual java.lang.StringBuilder.append(char)java.lang.StringBuilder
		// @E4: iload #4
		// @E6: invokevirtual java.lang.StringBuilder.append(int)java.lang.StringBuilder
		// @E9: bipush 44 (0x2C)
		// @EB: invokevirtual java.lang.StringBuilder.append(char)java.lang.StringBuilder
		// @EE: iload #5
		// @F0: invokevirtual java.lang.StringBuilder.append(int)java.lang.StringBuilder
		// @F3: bipush 41 (0x29)
		// @F5: invokevirtual java.lang.StringBuilder.append(char)java.lang.StringBuilder
		// @F8: invokevirtual java.lang.StringBuilder.toString()java.lang.String
		// @FB: invokestatic game.C_100181_cf.func_105695_a(java.lang.Throwable, java.lang.String)game.C_100170_cm
		// @FE: athrow
	}
	
	static final boolean func_106310_a(CharSequence arg0, byte arg1)
	{
		// @00: getstatic int game.SteelSentinels.field_105275_O
		// @03: istore_3
		// @04: iconst_1
		// @05: iconst_0
		// @06: aload_0
		// @07: invokestatic game.C_100270_mi.func_102256_a(boolean, int, java.lang.CharSequence)boolean
		// @0A: ifne @0F
		// @0D: iconst_0
		// @0E: ireturn
		// @0F: iconst_0
		// @10: istore_2
		// @11: iload_2
		// @12: aload_0
		// @13: invokeinterface java.lang.CharSequence.length()int
		// @18: if_icmpge @3B
		// @1B: aload_0
		// @1C: iload_2
		// @1D: invokeinterface java.lang.CharSequence.charAt(int)char
		// @22: bipush 105 (0x69)
		// @24: invokestatic game.C_100129_tg.func_102732_a(char, int)boolean
		// @27: iload_3
		// @28: ifne @47
		// @2B: ifne @34
		// @2E: goto @32
		// @31: athrow
		// @32: iconst_0
		// @33: ireturn
		// @34: iinc #2 +1
		// @37: iload_3
		// @38: ifeq @11
		// @3B: bipush -64 (0xC0)
		// @3D: iload_1
		// @3E: bipush -35 (0xDD)
		// @40: isub
		// @41: bipush 36 (0x24)
		// @43: idiv
		// @44: idiv
		// @45: istore_2
		// @46: iconst_1
		// @47: ireturn
		// @48: astore_2
		// @49: aload_2
		// @4A: new java.lang.StringBuilder
		// @4D: dup
		// @4E: invokespecial java.lang.StringBuilder.<init>()void
		// @51: getstatic java.lang.String[] game.C_100240_oj.field_106327_z
		// @54: bipush 10 (0x0A)
		// @56: aaload
		// @57: invokevirtual java.lang.StringBuilder.append(java.lang.String)java.lang.StringBuilder
		// @5A: aload_0
		// @5B: ifnull @67
		// @5E: getstatic java.lang.String[] game.C_100240_oj.field_106327_z
		// @61: iconst_3
		// @62: aaload
		// @63: goto @6C
		// @66: athrow
		// @67: getstatic java.lang.String[] game.C_100240_oj.field_106327_z
		// @6A: iconst_2
		// @6B: aaload
		// @6C: invokevirtual java.lang.StringBuilder.append(java.lang.String)java.lang.StringBuilder
		// @6F: bipush 44 (0x2C)
		// @71: invokevirtual java.lang.StringBuilder.append(char)java.lang.StringBuilder
		// @74: iload_1
		// @75: invokevirtual java.lang.StringBuilder.append(int)java.lang.StringBuilder
		// @78: bipush 41 (0x29)
		// @7A: invokevirtual java.lang.StringBuilder.append(char)java.lang.StringBuilder
		// @7D: invokevirtual java.lang.StringBuilder.toString()java.lang.String
		// @80: invokestatic game.C_100181_cf.func_105695_a(java.lang.Throwable, java.lang.String)game.C_100170_cm
		// @83: athrow
	}
	
	C_100240_oj(boolean arg0)
	{
		// @00: aload_0
		// @01: invokespecial java.lang.Object.<init>()void
		// @04: aload_0
		// @05: getstatic boolean game.C_100277_nc.field_106705_N
		// @08: putfield boolean game.C_100240_oj.field_106311_f
		// @0B: aload_0
		// @0C: getstatic int game.C_100003_ga.field_103544_y
		// @0F: putfield int game.C_100240_oj.field_106312_g
		// @12: aload_0
		// @13: getstatic java.lang.String game.C_100089_fa.field_103724_g
		// @16: putfield java.lang.String game.C_100240_oj.field_106325_i
		// @19: aload_0
		// @1A: getstatic int game.C_100269_ml.field_101124_o
		// @1D: putfield int game.C_100240_oj.field_106323_k
		// @20: aload_0
		// @21: getstatic int game.C_100071_va.field_101669_x
		// @24: putfield int game.C_100240_oj.field_106315_b
		// @27: aload_0
		// @28: getstatic java.lang.String game.C_100022_hf.field_103907_i
		// @2B: putfield java.lang.String game.C_100240_oj.field_106320_l
		// @2E: iload_1
		// @2F: ifeq @3F
		// @32: aload_0
		// @33: getstatic int[] game.C_100269_ml.field_101125_l
		// @36: putfield int[] game.C_100240_oj.field_106326_p
		// @39: getstatic int game.SteelSentinels.field_105275_O
		// @3C: ifeq @48
		// @3F: aload_0
		// @40: aconst_null
		// @41: putfield int[] game.C_100240_oj.field_106326_p
		// @44: goto @48
		// @47: athrow
		// @48: aload_0
		// @49: getstatic java.lang.String game.C_100231_oc.field_102205_kc
		// @4C: putfield java.lang.String game.C_100240_oj.field_106313_d
		// @4F: aload_0
		// @50: getstatic java.lang.String game.C_100085_a.field_102566_F
		// @53: putfield java.lang.String game.C_100240_oj.field_106321_m
		// @56: aload_0
		// @57: getstatic long game.C_100250_pl.field_106434_d
		// @5A: putfield long game.C_100240_oj.field_106316_c
		// @5D: aload_0
		// @5E: getstatic int game.C_100016_wi.field_103802_d
		// @61: putfield int game.C_100240_oj.field_106324_h
		// @64: aload_0
		// @65: getstatic int game.C_100183_cd.field_103415_U
		// @68: putfield int game.C_100240_oj.field_106317_a
		// @6B: goto @8F
		// @6E: astore_2
		// @6F: aload_2
		// @70: new java.lang.StringBuilder
		// @73: dup
		// @74: invokespecial java.lang.StringBuilder.<init>()void
		// @77: getstatic java.lang.String[] game.C_100240_oj.field_106327_z
		// @7A: iconst_4
		// @7B: aaload
		// @7C: invokevirtual java.lang.StringBuilder.append(java.lang.String)java.lang.StringBuilder
		// @7F: iload_1
		// @80: invokevirtual java.lang.StringBuilder.append(boolean)java.lang.StringBuilder
		// @83: bipush 41 (0x29)
		// @85: invokevirtual java.lang.StringBuilder.append(char)java.lang.StringBuilder
		// @88: invokevirtual java.lang.StringBuilder.toString()java.lang.String
		// @8B: invokestatic game.C_100181_cf.func_105695_a(java.lang.Throwable, java.lang.String)game.C_100170_cm
		// @8E: athrow
		// @8F: return
	}
	
	C_100240_oj(int arg0, String arg1, int arg2, String arg3, String arg4)
	{
		// @00: aload_0
		// @01: invokespecial java.lang.Object.<init>()void
		// @04: aload_0
		// @05: aload_2
		// @06: putfield java.lang.String game.C_100240_oj.field_106313_d
		// @09: aload_0
		// @0A: iconst_0
		// @0B: putfield int game.C_100240_oj.field_106312_g
		// @0E: aload_0
		// @0F: aconst_null
		// @10: putfield int[] game.C_100240_oj.field_106326_p
		// @13: aload_0
		// @14: iload_1
		// @15: putfield int game.C_100240_oj.field_106317_a
		// @18: aload_0
		// @19: iconst_1
		// @1A: putfield boolean game.C_100240_oj.field_106311_f
		// @1D: aload_0
		// @1E: iconst_0
		// @1F: putfield int game.C_100240_oj.field_106323_k
		// @22: aload_0
		// @23: aload_2
		// @24: putfield java.lang.String game.C_100240_oj.field_106321_m
		// @27: aload_0
		// @28: aload #4
		// @2A: putfield java.lang.String game.C_100240_oj.field_106325_i
		// @2D: aload_0
		// @2E: iload_3
		// @2F: putfield int game.C_100240_oj.field_106324_h
		// @32: aload_0
		// @33: aload #5
		// @35: putfield java.lang.String game.C_100240_oj.field_106320_l
		// @38: aload_0
		// @39: lconst_0
		// @3A: putfield long game.C_100240_oj.field_106316_c
		// @3D: aload_0
		// @3E: iconst_0
		// @3F: putfield int game.C_100240_oj.field_106315_b
		// @42: goto @C1
		// @45: astore #6
		// @47: aload #6
		// @49: new java.lang.StringBuilder
		// @4C: dup
		// @4D: invokespecial java.lang.StringBuilder.<init>()void
		// @50: getstatic java.lang.String[] game.C_100240_oj.field_106327_z
		// @53: iconst_4
		// @54: aaload
		// @55: invokevirtual java.lang.StringBuilder.append(java.lang.String)java.lang.StringBuilder
		// @58: iload_1
		// @59: invokevirtual java.lang.StringBuilder.append(int)java.lang.StringBuilder
		// @5C: bipush 44 (0x2C)
		// @5E: invokevirtual java.lang.StringBuilder.append(char)java.lang.StringBuilder
		// @61: aload_2
		// @62: ifnull @6E
		// @65: getstatic java.lang.String[] game.C_100240_oj.field_106327_z
		// @68: iconst_3
		// @69: aaload
		// @6A: goto @73
		// @6D: athrow
		// @6E: getstatic java.lang.String[] game.C_100240_oj.field_106327_z
		// @71: iconst_2
		// @72: aaload
		// @73: invokevirtual java.lang.StringBuilder.append(java.lang.String)java.lang.StringBuilder
		// @76: bipush 44 (0x2C)
		// @78: invokevirtual java.lang.StringBuilder.append(char)java.lang.StringBuilder
		// @7B: iload_3
		// @7C: invokevirtual java.lang.StringBuilder.append(int)java.lang.StringBuilder
		// @7F: bipush 44 (0x2C)
		// @81: invokevirtual java.lang.StringBuilder.append(char)java.lang.StringBuilder
		// @84: aload #4
		// @86: ifnull @92
		// @89: getstatic java.lang.String[] game.C_100240_oj.field_106327_z
		// @8C: iconst_3
		// @8D: aaload
		// @8E: goto @97
		// @91: athrow
		// @92: getstatic java.lang.String[] game.C_100240_oj.field_106327_z
		// @95: iconst_2
		// @96: aaload
		// @97: invokevirtual java.lang.StringBuilder.append(java.lang.String)java.lang.StringBuilder
		// @9A: bipush 44 (0x2C)
		// @9C: invokevirtual java.lang.StringBuilder.append(char)java.lang.StringBuilder
		// @9F: aload #5
		// @A1: ifnull @AD
		// @A4: getstatic java.lang.String[] game.C_100240_oj.field_106327_z
		// @A7: iconst_3
		// @A8: aaload
		// @A9: goto @B2
		// @AC: athrow
		// @AD: getstatic java.lang.String[] game.C_100240_oj.field_106327_z
		// @B0: iconst_2
		// @B1: aaload
		// @B2: invokevirtual java.lang.StringBuilder.append(java.lang.String)java.lang.StringBuilder
		// @B5: bipush 41 (0x29)
		// @B7: invokevirtual java.lang.StringBuilder.append(char)java.lang.StringBuilder
		// @BA: invokevirtual java.lang.StringBuilder.toString()java.lang.String
		// @BD: invokestatic game.C_100181_cf.func_105695_a(java.lang.Throwable, java.lang.String)game.C_100170_cm
		// @C0: athrow
		// @C1: return
	}
	
	static
	{
		// @00: bipush 11 (0x0B)
		// @02: anewarray java.lang.String
		// @05: dup
		// @06: iconst_0
		// @07: ldc "Nt\u0007|I"
		// @09: invokestatic game.C_100240_oj.func_106306_z(java.lang.String)char[]
		// @0C: invokestatic game.C_100240_oj.func_106305_z(char[])java.lang.String
		// @0F: aastore
		// @10: dup
		// @11: iconst_1
		// @12: ldc "Nt\u0007xI"
		// @14: invokestatic game.C_100240_oj.func_106306_z(java.lang.String)char[]
		// @17: invokestatic game.C_100240_oj.func_106305_z(char[])java.lang.String
		// @1A: aastore
		// @1B: dup
		// @1C: iconst_2
		// @1D: ldc "OkEV"
		// @1F: invokestatic game.C_100240_oj.func_106306_z(java.lang.String)char[]
		// @22: invokestatic game.C_100240_oj.func_106305_z(char[])java.lang.String
		// @25: aastore
		// @26: dup
		// @27: iconst_3
		// @28: ldc "Z0\u0007\u0014\u001c"
		// @2A: invokestatic game.C_100240_oj.func_106306_z(java.lang.String)char[]
		// @2D: invokestatic game.C_100240_oj.func_106305_z(char[])java.lang.String
		// @30: aastore
		// @31: dup
		// @32: iconst_4
		// @33: ldc "Nt\u0007\u0006\u0008Ow]\u0004I"
		// @35: invokestatic game.C_100240_oj.func_106306_z(java.lang.String)char[]
		// @38: invokestatic game.C_100240_oj.func_106305_z(char[])java.lang.String
		// @3B: aastore
		// @3C: dup
		// @3D: iconst_5
		// @3E: ldc "Nt\u0007~I"
		// @40: invokestatic game.C_100240_oj.func_106306_z(java.lang.String)char[]
		// @43: invokestatic game.C_100240_oj.func_106305_z(char[])java.lang.String
		// @46: aastore
		// @47: dup
		// @48: bipush 6 (0x06)
		// @4A: ldc "Nt\u0007rI"
		// @4C: invokestatic game.C_100240_oj.func_106306_z(java.lang.String)char[]
		// @4F: invokestatic game.C_100240_oj.func_106305_z(char[])java.lang.String
		// @52: aastore
		// @53: dup
		// @54: bipush 7 (0x07)
		// @56: ldc "Nt\u0007yI"
		// @58: invokestatic game.C_100240_oj.func_106306_z(java.lang.String)char[]
		// @5B: invokestatic game.C_100240_oj.func_106305_z(char[])java.lang.String
		// @5E: aastore
		// @5F: dup
		// @60: bipush 8 (0x08)
		// @62: ldc "Nt\u0007}I"
		// @64: invokestatic game.C_100240_oj.func_106306_z(java.lang.String)char[]
		// @67: invokestatic game.C_100240_oj.func_106305_z(char[])java.lang.String
		// @6A: aastore
		// @6B: dup
		// @6C: bipush 9 (0x09)
		// @6E: ldc "Nt\u0007{I"
		// @70: invokestatic game.C_100240_oj.func_106306_z(java.lang.String)char[]
		// @73: invokestatic game.C_100240_oj.func_106305_z(char[])java.lang.String
		// @76: aastore
		// @77: dup
		// @78: bipush 10 (0x0A)
		// @7A: ldc "Nt\u0007\u007fI"
		// @7C: invokestatic game.C_100240_oj.func_106306_z(java.lang.String)char[]
		// @7F: invokestatic game.C_100240_oj.func_106305_z(char[])java.lang.String
		// @82: aastore
		// @83: putstatic java.lang.String[] game.C_100240_oj.field_106327_z
		// @86: iconst_0
		// @87: putstatic boolean game.C_100240_oj.field_106322_j
		// @8A: sipush 255 (0x00FF)
		// @8D: anewarray game.C_100304_kl
		// @90: putstatic game.C_100304_kl[] game.C_100240_oj.field_106319_o
		// @93: iconst_0
		// @94: istore_0
		// @95: getstatic game.C_100304_kl[] game.C_100240_oj.field_106319_o
		// @98: arraylength
		// @99: iload_0
		// @9A: if_icmple @B0
		// @9D: getstatic game.C_100304_kl[] game.C_100240_oj.field_106319_o
		// @A0: iload_0
		// @A1: new game.C_100304_kl
		// @A4: dup
		// @A5: invokespecial game.C_100304_kl.<init>()void
		// @A8: aastore
		// @A9: iinc #0 +1
		// @AC: goto @95
		// @AF: athrow
		// @B0: return
	}
	
	private static char[] func_106306_z(String arg0)
	{
		// @00: aload_0
		// @01: invokevirtual java.lang.String.toCharArray()char[]
		// @04: dup
		// @05: arraylength
		// @06: iconst_2
		// @07: if_icmpge @13
		// @0A: dup
		// @0B: iconst_0
		// @0C: dup2
		// @0D: caload
		// @0E: bipush 97 (0x61)
		// @10: ixor
		// @11: i2c
		// @12: castore
		// @13: areturn
	}
	
	private static String func_106305_z(char[] arg0)
	{
		// @00: aload_0
		// @01: dup
		// @02: arraylength
		// @03: swap
		// @04: iconst_0
		// @05: istore_1
		// @06: goto @4C
		// @09: dup
		// @0A: iload_1
		// @0B: dup2
		// @0C: caload
		// @0D: iload_1
		// @0E: iconst_5
		// @0F: irem
		// @10: tableswitch def: @44, for 0: @30, for 1: @35, for 2: @3A, for 3: @3F
		// @30: bipush 33 (0x21)
		// @32: goto @46
		// @35: bipush 30 (0x1E)
		// @37: goto @46
		// @3A: bipush 41 (0x29)
		// @3C: goto @46
		// @3F: bipush 58 (0x3A)
		// @41: goto @46
		// @44: bipush 97 (0x61)
		// @46: ixor
		// @47: i2c
		// @48: castore
		// @49: iinc #1 +1
		// @4C: swap
		// @4D: dup_x1
		// @4E: iload_1
		// @4F: if_icmpgt @09
		// @52: new java.lang.String
		// @55: dup_x1
		// @56: swap
		// @57: invokespecial java.lang.String.<init>(char[])void
		// @5A: invokevirtual java.lang.String.intern()java.lang.String
		// @5D: areturn
	}
}
