package game;

import java.awt.Frame;

final class C_100110_s
{
	static String field_104843_f;
	static int[] field_104845_e;
	static int field_104848_a;
	static String field_104846_b;
	static String field_104847_c;
	static String field_104844_d;
	private static final String[] field_104849_z;
	
	static final void func_104842_a(C_100201_qj arg0, Frame arg1, int arg2)
	{
		// @00: getstatic int game.SteelSentinels.field_105275_O
		// @03: istore #4
		// @05: iload_2
		// @06: sipush 8192 (0x2000)
		// @09: if_icmpeq @0D
		// @0C: return
		// @0D: aload_0
		// @0E: aload_1
		// @0F: bipush 104 (0x68)
		// @11: invokevirtual game.C_100201_qj.func_105868_a(java.awt.Frame, byte)game.C_100331_ie
		// @14: astore_3
		// @15: iconst_0
		// @16: aload_3
		// @17: getfield int game.C_100331_ie.field_107293_f
		// @1A: if_icmpne @33
		// @1D: ldc2_w 10
		// @20: bipush -123 (0x85)
		// @22: invokestatic game.C_100138_bo.func_100396_a(long, int)void
		// @25: iload #4
		// @27: ifne @50
		// @2A: iload #4
		// @2C: ifeq @15
		// @2F: goto @33
		// @32: athrow
		// @33: aload_3
		// @34: getfield int game.C_100331_ie.field_107293_f
		// @37: iconst_1
		// @38: if_icmpne @44
		// @3B: iload #4
		// @3D: ifeq @55
		// @40: goto @44
		// @43: athrow
		// @44: ldc2_w 100
		// @47: bipush -124 (0x84)
		// @49: invokestatic game.C_100138_bo.func_100396_a(long, int)void
		// @4C: goto @50
		// @4F: athrow
		// @50: iload #4
		// @52: ifeq @0D
		// @55: aload_1
		// @56: iconst_0
		// @57: invokevirtual java.awt.Frame.setVisible(boolean)void
		// @5A: aload_1
		// @5B: invokevirtual java.awt.Frame.dispose()void
		// @5E: goto @B6
		// @61: astore_3
		// @62: aload_3
		// @63: new java.lang.StringBuilder
		// @66: dup
		// @67: invokespecial java.lang.StringBuilder.<init>()void
		// @6A: getstatic java.lang.String[] game.C_100110_s.field_104849_z
		// @6D: iconst_1
		// @6E: aaload
		// @6F: invokevirtual java.lang.StringBuilder.append(java.lang.String)java.lang.StringBuilder
		// @72: aload_0
		// @73: ifnull @7F
		// @76: getstatic java.lang.String[] game.C_100110_s.field_104849_z
		// @79: iconst_0
		// @7A: aaload
		// @7B: goto @84
		// @7E: athrow
		// @7F: getstatic java.lang.String[] game.C_100110_s.field_104849_z
		// @82: iconst_2
		// @83: aaload
		// @84: invokevirtual java.lang.StringBuilder.append(java.lang.String)java.lang.StringBuilder
		// @87: bipush 44 (0x2C)
		// @89: invokevirtual java.lang.StringBuilder.append(char)java.lang.StringBuilder
		// @8C: aload_1
		// @8D: ifnull @99
		// @90: getstatic java.lang.String[] game.C_100110_s.field_104849_z
		// @93: iconst_0
		// @94: aaload
		// @95: goto @9E
		// @98: athrow
		// @99: getstatic java.lang.String[] game.C_100110_s.field_104849_z
		// @9C: iconst_2
		// @9D: aaload
		// @9E: invokevirtual java.lang.StringBuilder.append(java.lang.String)java.lang.StringBuilder
		// @A1: bipush 44 (0x2C)
		// @A3: invokevirtual java.lang.StringBuilder.append(char)java.lang.StringBuilder
		// @A6: iload_2
		// @A7: invokevirtual java.lang.StringBuilder.append(int)java.lang.StringBuilder
		// @AA: bipush 41 (0x29)
		// @AC: invokevirtual java.lang.StringBuilder.append(char)java.lang.StringBuilder
		// @AF: invokevirtual java.lang.StringBuilder.toString()java.lang.String
		// @B2: invokestatic game.C_100181_cf.func_105695_a(java.lang.Throwable, java.lang.String)game.C_100170_cm
		// @B5: athrow
		// @B6: return
	}
	
	static final String func_104838_a(byte arg0, byte[] arg1)
	{
		// @00: bipush 85 (0x55)
		// @02: iload_0
		// @03: bipush -27 (0xE5)
		// @05: isub
		// @06: bipush 60 (0x3C)
		// @08: idiv
		// @09: idiv
		// @0A: istore_2
		// @0B: aload_1
		// @0C: sipush 5278 (0x149E)
		// @0F: iconst_0
		// @10: aload_1
		// @11: arraylength
		// @12: invokestatic game.C_100280_nf.func_101130_c(byte[], int, int, int)java.lang.String
		// @15: areturn
		// @16: astore_2
		// @17: aload_2
		// @18: new java.lang.StringBuilder
		// @1B: dup
		// @1C: invokespecial java.lang.StringBuilder.<init>()void
		// @1F: getstatic java.lang.String[] game.C_100110_s.field_104849_z
		// @22: iconst_3
		// @23: aaload
		// @24: invokevirtual java.lang.StringBuilder.append(java.lang.String)java.lang.StringBuilder
		// @27: iload_0
		// @28: invokevirtual java.lang.StringBuilder.append(int)java.lang.StringBuilder
		// @2B: bipush 44 (0x2C)
		// @2D: invokevirtual java.lang.StringBuilder.append(char)java.lang.StringBuilder
		// @30: aload_1
		// @31: ifnull @3D
		// @34: getstatic java.lang.String[] game.C_100110_s.field_104849_z
		// @37: iconst_0
		// @38: aaload
		// @39: goto @42
		// @3C: athrow
		// @3D: getstatic java.lang.String[] game.C_100110_s.field_104849_z
		// @40: iconst_2
		// @41: aaload
		// @42: invokevirtual java.lang.StringBuilder.append(java.lang.String)java.lang.StringBuilder
		// @45: bipush 41 (0x29)
		// @47: invokevirtual java.lang.StringBuilder.append(char)java.lang.StringBuilder
		// @4A: invokevirtual java.lang.StringBuilder.toString()java.lang.String
		// @4D: invokestatic game.C_100181_cf.func_105695_a(java.lang.Throwable, java.lang.String)game.C_100170_cm
		// @50: athrow
	}
	
	public static void func_104841_a(boolean arg0)
	{
		// @00: aconst_null
		// @01: putstatic java.lang.String game.C_100110_s.field_104843_f
		// @04: aconst_null
		// @05: putstatic java.lang.String game.C_100110_s.field_104847_c
		// @08: iload_0
		// @09: iconst_1
		// @0A: if_icmpeq @0E
		// @0D: return
		// @0E: aconst_null
		// @0F: putstatic java.lang.String game.C_100110_s.field_104844_d
		// @12: aconst_null
		// @13: putstatic java.lang.String game.C_100110_s.field_104846_b
		// @16: aconst_null
		// @17: putstatic int[] game.C_100110_s.field_104845_e
		// @1A: goto @3E
		// @1D: astore_1
		// @1E: aload_1
		// @1F: new java.lang.StringBuilder
		// @22: dup
		// @23: invokespecial java.lang.StringBuilder.<init>()void
		// @26: getstatic java.lang.String[] game.C_100110_s.field_104849_z
		// @29: iconst_4
		// @2A: aaload
		// @2B: invokevirtual java.lang.StringBuilder.append(java.lang.String)java.lang.StringBuilder
		// @2E: iload_0
		// @2F: invokevirtual java.lang.StringBuilder.append(boolean)java.lang.StringBuilder
		// @32: bipush 41 (0x29)
		// @34: invokevirtual java.lang.StringBuilder.append(char)java.lang.StringBuilder
		// @37: invokevirtual java.lang.StringBuilder.toString()java.lang.String
		// @3A: invokestatic game.C_100181_cf.func_105695_a(java.lang.Throwable, java.lang.String)game.C_100170_cm
		// @3D: athrow
		// @3E: return
	}
	
	static
	{
		// @00: iconst_5
		// @01: anewarray java.lang.String
		// @04: dup
		// @05: iconst_0
		// @06: ldc "\u00070b/0"
		// @08: invokestatic game.C_100110_s.func_104840_z(java.lang.String)char[]
		// @0B: invokestatic game.C_100110_s.func_104839_z(char[])java.lang.String
		// @0E: aastore
		// @0F: dup
		// @10: iconst_1
		// @11: ldc "\u000f0\u000e)"
		// @13: invokestatic game.C_100110_s.func_104840_z(java.lang.String)char[]
		// @16: invokestatic game.C_100110_s.func_104839_z(char[])java.lang.String
		// @19: aastore
		// @1A: dup
		// @1B: iconst_2
		// @1C: ldc "\u0012k m"
		// @1E: invokestatic game.C_100110_s.func_104840_z(java.lang.String)char[]
		// @21: invokestatic game.C_100110_s.func_104839_z(char[])java.lang.String
		// @24: aastore
		// @25: dup
		// @26: iconst_3
		// @27: ldc "\u000f0\u000f)"
		// @29: invokestatic game.C_100110_s.func_104840_z(java.lang.String)char[]
		// @2C: invokestatic game.C_100110_s.func_104839_z(char[])java.lang.String
		// @2F: aastore
		// @30: dup
		// @31: iconst_4
		// @32: ldc "\u000f0\r)"
		// @34: invokestatic game.C_100110_s.func_104840_z(java.lang.String)char[]
		// @37: invokestatic game.C_100110_s.func_104839_z(char[])java.lang.String
		// @3A: aastore
		// @3B: putstatic java.lang.String[] game.C_100110_s.field_104849_z
		// @3E: ldc "%q9sm\u001al%d#\u0018> h>\u0008>%rm\u001ak mc\\S-ym\u0013xl0}L>*n?\\x>d(\\k?d?\u000f2l`#\u0018>~1}\\x#sm\u0011{!c(\u000emb"
		// @40: invokestatic game.C_100110_s.func_104840_z(java.lang.String)char[]
		// @43: invokestatic game.C_100110_s.func_104839_z(char[])java.lang.String
		// @46: putstatic java.lang.String game.C_100110_s.field_104843_f
		// @49: sipush 8192 (0x2000)
		// @4C: newarray int[]
		// @4E: putstatic int[] game.C_100110_s.field_104845_e
		// @51: ldc "@;}?m\u000b\u007f?!.\u001dk+i9\\w\"!qY.r&>\\p9b!\u0019\u007f>!+\u0015l)c,\u0010r"
		// @53: invokestatic game.C_100110_s.func_104840_z(java.lang.String)char[]
		// @56: invokestatic game.C_100110_s.func_104839_z(char[])java.lang.String
		// @59: putstatic java.lang.String game.C_100110_s.field_104847_c
		// @5C: ldc "?v#n>\u0019>-!.\u0014\u007f?r$\u000f>*n?\\g#t?\\m)o9\u0015p)mm\u001fq\"g$\u001bk>`9\u0015q\"/m9\u007f/im\u001fv-r>\u0015mlh>\\{=t$\u000cn)em\u000bw8im\u001d>(d+\u001dk um\u000f{8!\"\u001a>;d,\u000cq\"rm\u001dp(! \u0013z9m(\u000f0"
		// @5E: invokestatic game.C_100110_s.func_104840_z(java.lang.String)char[]
		// @61: invokestatic game.C_100110_s.func_104839_z(char[])java.lang.String
		// @64: putstatic java.lang.String game.C_100110_s.field_104846_b
		// @67: ldc ".{*d?\u0019p/dm\u0011\u007f\"t,\u0010"
		// @69: invokestatic game.C_100110_s.func_104840_z(java.lang.String)char[]
		// @6C: invokestatic game.C_100110_s.func_104839_z(char[])java.lang.String
		// @6F: putstatic java.lang.String game.C_100110_s.field_104844_d
		// @72: return
	}
	
	private static char[] func_104840_z(String arg0)
	{
		// @00: aload_0
		// @01: invokevirtual java.lang.String.toCharArray()char[]
		// @04: dup
		// @05: arraylength
		// @06: iconst_2
		// @07: if_icmpge @13
		// @0A: dup
		// @0B: iconst_0
		// @0C: dup2
		// @0D: caload
		// @0E: bipush 77 (0x4D)
		// @10: ixor
		// @11: i2c
		// @12: castore
		// @13: areturn
	}
	
	private static String func_104839_z(char[] arg0)
	{
		// @00: aload_0
		// @01: dup
		// @02: arraylength
		// @03: swap
		// @04: iconst_0
		// @05: istore_1
		// @06: goto @4B
		// @09: dup
		// @0A: iload_1
		// @0B: dup2
		// @0C: caload
		// @0D: iload_1
		// @0E: iconst_5
		// @0F: irem
		// @10: tableswitch def: @43, for 0: @30, for 1: @35, for 2: @3A, for 3: @3F
		// @30: bipush 124 (0x7C)
		// @32: goto @45
		// @35: bipush 30 (0x1E)
		// @37: goto @45
		// @3A: bipush 76 (0x4C)
		// @3C: goto @45
		// @3F: iconst_1
		// @40: goto @45
		// @43: bipush 77 (0x4D)
		// @45: ixor
		// @46: i2c
		// @47: castore
		// @48: iinc #1 +1
		// @4B: swap
		// @4C: dup_x1
		// @4D: iload_1
		// @4E: if_icmpgt @09
		// @51: new java.lang.String
		// @54: dup_x1
		// @55: swap
		// @56: invokespecial java.lang.String.<init>(char[])void
		// @59: invokevirtual java.lang.String.intern()java.lang.String
		// @5C: areturn
	}
}
