package game;

final class C_100203_ql
{
	static C_100098_h field_105932_a;
	static int[][][] field_105931_c;
	static String field_105930_b;
	static String field_105929_e;
	static String field_105928_d;
	static C_100253_ph field_105927_f;
	private static final String[] field_105933_z;
	
	static final C_100277_nc func_105925_a(C_100278_nd arg0, int arg1)
	{
		// @000: getstatic int game.SteelSentinels.field_105275_O
		// @003: istore #8
		// @005: aload_0
		// @006: bipush 8 (0x08)
		// @008: sipush 15738 (0x3D7A)
		// @00B: invokevirtual game.C_100278_nd.func_101195_i(int, int)int
		// @00E: istore_2
		// @00F: iload_2
		// @010: iconst_m1
		// @011: ixor
		// @012: iconst_m1
		// @013: if_icmplt @01A
		// @016: goto @035
		// @019: athrow
		// @01A: new java.lang.IllegalStateException
		// @01D: dup
		// @01E: new java.lang.StringBuilder
		// @021: dup
		// @022: invokespecial java.lang.StringBuilder.<init>()void
		// @025: ldc ""
		// @027: invokevirtual java.lang.StringBuilder.append(java.lang.String)java.lang.StringBuilder
		// @02A: iload_2
		// @02B: invokevirtual java.lang.StringBuilder.append(int)java.lang.StringBuilder
		// @02E: invokevirtual java.lang.StringBuilder.toString()java.lang.String
		// @031: invokespecial java.lang.IllegalStateException.<init>(java.lang.String)void
		// @034: athrow
		// @035: aload_0
		// @036: bipush 81 (0x51)
		// @038: invokestatic game.C_100210_qa.func_101041_a(game.C_100278_nd, int)boolean
		// @03B: istore_3
		// @03C: aload_0
		// @03D: bipush 109 (0x6D)
		// @03F: invokestatic game.C_100210_qa.func_101041_a(game.C_100278_nd, int)boolean
		// @042: istore #4
		// @044: new game.C_100277_nc
		// @047: dup
		// @048: invokespecial game.C_100277_nc.<init>()void
		// @04B: astore #5
		// @04D: aload #5
		// @04F: aload_0
		// @050: bipush 16 (0x10)
		// @052: iload_1
		// @053: sipush 15722 (0x3D6A)
		// @056: ixor
		// @057: invokevirtual game.C_100278_nd.func_101195_i(int, int)int
		// @05A: i2s
		// @05B: putfield short game.C_100277_nc.field_106698_F
		// @05E: aload #5
		// @060: bipush 16 (0x10)
		// @062: iload_1
		// @063: bipush -84 (0xAC)
		// @065: ixor
		// @066: aload #5
		// @068: getfield short[] game.C_100277_nc.field_106711_U
		// @06B: aload_0
		// @06C: invokestatic game.C_100172_ck.func_102106_a(int, int, short[], game.C_100278_nd)short[]
		// @06F: putfield short[] game.C_100277_nc.field_106711_U
		// @072: aload #5
		// @074: bipush 16 (0x10)
		// @076: bipush -23 (0xE9)
		// @078: aload #5
		// @07A: getfield short[] game.C_100277_nc.field_106724_b
		// @07D: aload_0
		// @07E: invokestatic game.C_100172_ck.func_102106_a(int, int, short[], game.C_100278_nd)short[]
		// @081: putfield short[] game.C_100277_nc.field_106724_b
		// @084: aload #5
		// @086: bipush 16 (0x10)
		// @088: iload_1
		// @089: bipush -57 (0xC7)
		// @08B: iadd
		// @08C: aload #5
		// @08E: getfield short[] game.C_100277_nc.field_106714_V
		// @091: aload_0
		// @092: invokestatic game.C_100172_ck.func_102106_a(int, int, short[], game.C_100278_nd)short[]
		// @095: putfield short[] game.C_100277_nc.field_106714_V
		// @098: aload #5
		// @09A: aload_0
		// @09B: bipush 16 (0x10)
		// @09D: sipush 15738 (0x3D7A)
		// @0A0: invokevirtual game.C_100278_nd.func_101195_i(int, int)int
		// @0A3: i2s
		// @0A4: putfield short game.C_100277_nc.field_106721_g
		// @0A7: aload #5
		// @0A9: bipush 16 (0x10)
		// @0AB: bipush -104 (0x98)
		// @0AD: aload #5
		// @0AF: getfield short[] game.C_100277_nc.field_106733_h
		// @0B2: aload_0
		// @0B3: invokestatic game.C_100172_ck.func_102106_a(int, int, short[], game.C_100278_nd)short[]
		// @0B6: putfield short[] game.C_100277_nc.field_106733_h
		// @0B9: aload #5
		// @0BB: iload_1
		// @0BC: iload_1
		// @0BD: bipush -37 (0xDB)
		// @0BF: iadd
		// @0C0: aload #5
		// @0C2: getfield short[] game.C_100277_nc.field_106717_S
		// @0C5: aload_0
		// @0C6: invokestatic game.C_100172_ck.func_102106_a(int, int, short[], game.C_100278_nd)short[]
		// @0C9: putfield short[] game.C_100277_nc.field_106717_S
		// @0CC: aload #5
		// @0CE: bipush 16 (0x10)
		// @0D0: iload_1
		// @0D1: bipush 99 (0x63)
		// @0D3: ixor
		// @0D4: aload #5
		// @0D6: getfield short[] game.C_100277_nc.field_106743_z
		// @0D9: aload_0
		// @0DA: invokestatic game.C_100172_ck.func_102106_a(int, int, short[], game.C_100278_nd)short[]
		// @0DD: putfield short[] game.C_100277_nc.field_106743_z
		// @0E0: iload_3
		// @0E1: ifne @0E8
		// @0E4: goto @165
		// @0E7: athrow
		// @0E8: aload #5
		// @0EA: aload_0
		// @0EB: bipush 16 (0x10)
		// @0ED: sipush 15738 (0x3D7A)
		// @0F0: invokevirtual game.C_100278_nd.func_101195_i(int, int)int
		// @0F3: i2s
		// @0F4: putfield short game.C_100277_nc.field_106735_w
		// @0F7: aload #5
		// @0F9: bipush 16 (0x10)
		// @0FB: bipush 123 (0x7B)
		// @0FD: aload #5
		// @0FF: getfield short[] game.C_100277_nc.field_106697_E
		// @102: aload_0
		// @103: invokestatic game.C_100172_ck.func_102106_a(int, int, short[], game.C_100278_nd)short[]
		// @106: putfield short[] game.C_100277_nc.field_106697_E
		// @109: aload #5
		// @10B: bipush 16 (0x10)
		// @10D: bipush 118 (0x76)
		// @10F: aload #5
		// @111: getfield short[] game.C_100277_nc.field_106708_I
		// @114: aload_0
		// @115: invokestatic game.C_100172_ck.func_102106_a(int, int, short[], game.C_100278_nd)short[]
		// @118: putfield short[] game.C_100277_nc.field_106708_I
		// @11B: aload #5
		// @11D: bipush 16 (0x10)
		// @11F: bipush 123 (0x7B)
		// @121: aload #5
		// @123: getfield short[] game.C_100277_nc.field_106731_j
		// @126: aload_0
		// @127: invokestatic game.C_100172_ck.func_102106_a(int, int, short[], game.C_100278_nd)short[]
		// @12A: putfield short[] game.C_100277_nc.field_106731_j
		// @12D: aload #5
		// @12F: bipush 16 (0x10)
		// @131: iload_1
		// @132: bipush -78 (0xB2)
		// @134: iadd
		// @135: aload #5
		// @137: getfield short[] game.C_100277_nc.field_106738_t
		// @13A: aload_0
		// @13B: invokestatic game.C_100172_ck.func_102106_a(int, int, short[], game.C_100278_nd)short[]
		// @13E: putfield short[] game.C_100277_nc.field_106738_t
		// @141: aload #5
		// @143: bipush 16 (0x10)
		// @145: bipush -62 (0xC2)
		// @147: aload #5
		// @149: getfield short[] game.C_100277_nc.field_106723_e
		// @14C: aload_0
		// @14D: invokestatic game.C_100172_ck.func_102106_a(int, int, short[], game.C_100278_nd)short[]
		// @150: putfield short[] game.C_100277_nc.field_106723_e
		// @153: aload #5
		// @155: bipush 16 (0x10)
		// @157: bipush -114 (0x8E)
		// @159: aload #5
		// @15B: getfield short[] game.C_100277_nc.field_106710_K
		// @15E: aload_0
		// @15F: invokestatic game.C_100172_ck.func_102106_a(int, int, short[], game.C_100278_nd)short[]
		// @162: putfield short[] game.C_100277_nc.field_106710_K
		// @165: iload #4
		// @167: ifeq @1D8
		// @16A: aload_0
		// @16B: bipush 16 (0x10)
		// @16D: iload_1
		// @16E: sipush 15722 (0x3D6A)
		// @171: ixor
		// @172: invokevirtual game.C_100278_nd.func_101195_i(int, int)int
		// @175: pop
		// @176: aload #5
		// @178: bipush 16 (0x10)
		// @17A: bipush -71 (0xB9)
		// @17C: aload #5
		// @17E: getfield short[] game.C_100277_nc.field_106722_d
		// @181: aload_0
		// @182: invokestatic game.C_100172_ck.func_102106_a(int, int, short[], game.C_100278_nd)short[]
		// @185: putfield short[] game.C_100277_nc.field_106722_d
		// @188: aload #5
		// @18A: bipush 16 (0x10)
		// @18C: bipush 117 (0x75)
		// @18E: aload #5
		// @190: getfield short[] game.C_100277_nc.field_106707_H
		// @193: aload_0
		// @194: invokestatic game.C_100172_ck.func_102106_a(int, int, short[], game.C_100278_nd)short[]
		// @197: putfield short[] game.C_100277_nc.field_106707_H
		// @19A: aload #5
		// @19C: bipush 16 (0x10)
		// @19E: iload_1
		// @19F: bipush -120 (0x88)
		// @1A1: ixor
		// @1A2: aload #5
		// @1A4: getfield short[] game.C_100277_nc.field_106703_L
		// @1A7: aload_0
		// @1A8: invokestatic game.C_100172_ck.func_102106_a(int, int, short[], game.C_100278_nd)short[]
		// @1AB: putfield short[] game.C_100277_nc.field_106703_L
		// @1AE: aload #5
		// @1B0: bipush 16 (0x10)
		// @1B2: iload_1
		// @1B3: bipush -13 (0xF3)
		// @1B5: ixor
		// @1B6: aload #5
		// @1B8: getfield short[] game.C_100277_nc.field_106706_O
		// @1BB: aload_0
		// @1BC: invokestatic game.C_100172_ck.func_102106_a(int, int, short[], game.C_100278_nd)short[]
		// @1BF: putfield short[] game.C_100277_nc.field_106706_O
		// @1C2: aload #5
		// @1C4: bipush 16 (0x10)
		// @1C6: bipush -124 (0x84)
		// @1C8: aload #5
		// @1CA: getfield short[] game.C_100277_nc.field_106734_i
		// @1CD: aload_0
		// @1CE: invokestatic game.C_100172_ck.func_102106_a(int, int, short[], game.C_100278_nd)short[]
		// @1D1: putfield short[] game.C_100277_nc.field_106734_i
		// @1D4: goto @1D8
		// @1D7: athrow
		// @1D8: aload_0
		// @1D9: bipush 77 (0x4D)
		// @1DB: invokestatic game.C_100210_qa.func_101041_a(game.C_100278_nd, int)boolean
		// @1DE: ifne @1E5
		// @1E1: goto @1F9
		// @1E4: athrow
		// @1E5: aload #5
		// @1E7: bipush 16 (0x10)
		// @1E9: iload_1
		// @1EA: bipush 99 (0x63)
		// @1EC: ixor
		// @1ED: aload #5
		// @1EF: getfield short[] game.C_100277_nc.field_106730_m
		// @1F2: aload_0
		// @1F3: invokestatic game.C_100172_ck.func_102106_a(int, int, short[], game.C_100278_nd)short[]
		// @1F6: putfield short[] game.C_100277_nc.field_106730_m
		// @1F9: aload_0
		// @1FA: bipush 112 (0x70)
		// @1FC: invokestatic game.C_100210_qa.func_101041_a(game.C_100278_nd, int)boolean
		// @1FF: ifeq @27D
		// @202: aload #5
		// @204: aload #5
		// @206: getfield byte[] game.C_100277_nc.field_106718_R
		// @209: aload_0
		// @20A: iconst_0
		// @20B: bipush 16 (0x10)
		// @20D: invokestatic game.C_100061_dh.func_101973_a(byte[], game.C_100278_nd, boolean, int)byte[]
		// @210: putfield byte[] game.C_100277_nc.field_106718_R
		// @213: iconst_0
		// @214: istore #6
		// @216: iconst_0
		// @217: istore #7
		// @219: iload #7
		// @21B: aload #5
		// @21D: getfield byte[] game.C_100277_nc.field_106718_R
		// @220: arraylength
		// @221: if_icmpge @258
		// @224: iload #6
		// @226: iconst_m1
		// @227: ixor
		// @228: aload #5
		// @22A: getfield byte[] game.C_100277_nc.field_106718_R
		// @22D: iload #7
		// @22F: baload
		// @230: sipush 255 (0x00FF)
		// @233: iand
		// @234: iconst_m1
		// @235: ixor
		// @236: iload #8
		// @238: ifne @25D
		// @23B: if_icmple @250
		// @23E: goto @242
		// @241: athrow
		// @242: sipush 255 (0x00FF)
		// @245: aload #5
		// @247: getfield byte[] game.C_100277_nc.field_106718_R
		// @24A: iload #7
		// @24C: baload
		// @24D: iand
		// @24E: istore #6
		// @250: iinc #7 +1
		// @253: iload #8
		// @255: ifeq @219
		// @258: iconst_m1
		// @259: iload #6
		// @25B: iconst_m1
		// @25C: ixor
		// @25D: if_icmpne @26F
		// @260: aload #5
		// @262: aconst_null
		// @263: putfield byte[] game.C_100277_nc.field_106718_R
		// @266: iload #8
		// @268: ifeq @27D
		// @26B: goto @26F
		// @26E: athrow
		// @26F: aload #5
		// @271: iload #6
		// @273: iconst_1
		// @274: iadd
		// @275: i2b
		// @276: putfield byte game.C_100277_nc.field_106729_l
		// @279: goto @27D
		// @27C: athrow
		// @27D: aload #5
		// @27F: areturn
		// @280: astore_2
		// @281: aload_2
		// @282: new java.lang.StringBuilder
		// @285: dup
		// @286: invokespecial java.lang.StringBuilder.<init>()void
		// @289: getstatic java.lang.String[] game.C_100203_ql.field_105933_z
		// @28C: bipush 6 (0x06)
		// @28E: aaload
		// @28F: invokevirtual java.lang.StringBuilder.append(java.lang.String)java.lang.StringBuilder
		// @292: aload_0
		// @293: ifnull @29F
		// @296: getstatic java.lang.String[] game.C_100203_ql.field_105933_z
		// @299: iconst_4
		// @29A: aaload
		// @29B: goto @2A4
		// @29E: athrow
		// @29F: getstatic java.lang.String[] game.C_100203_ql.field_105933_z
		// @2A2: iconst_5
		// @2A3: aaload
		// @2A4: invokevirtual java.lang.StringBuilder.append(java.lang.String)java.lang.StringBuilder
		// @2A7: bipush 44 (0x2C)
		// @2A9: invokevirtual java.lang.StringBuilder.append(char)java.lang.StringBuilder
		// @2AC: iload_1
		// @2AD: invokevirtual java.lang.StringBuilder.append(int)java.lang.StringBuilder
		// @2B0: bipush 41 (0x29)
		// @2B2: invokevirtual java.lang.StringBuilder.append(char)java.lang.StringBuilder
		// @2B5: invokevirtual java.lang.StringBuilder.toString()java.lang.String
		// @2B8: invokestatic game.C_100181_cf.func_105695_a(java.lang.Throwable, java.lang.String)game.C_100170_cm
		// @2BB: athrow
	}
	
	static final void func_105921_a(int arg0)
	{
		// @00: getstatic int game.SteelSentinels.field_105275_O
		// @03: istore_2
		// @04: iconst_1
		// @05: putstatic boolean game.C_100034_gi.field_104029_d
		// @08: aconst_null
		// @09: putstatic game.C_100302_ka game.C_100226_ae.field_106147_g
		// @0C: aconst_null
		// @0D: putstatic game.C_100115_ej game.C_100316_lc.field_102410_w
		// @10: iconst_1
		// @11: putstatic boolean game.C_100309_lk.field_103271_ab
		// @14: aconst_null
		// @15: putstatic game.C_100302_ka game.C_100145_ta.field_100422_e
		// @18: aconst_null
		// @19: putstatic game.C_100302_ka game.C_100189_ri.field_105752_d
		// @1C: aconst_null
		// @1D: putstatic game.C_100115_ej game.C_100017_wj.field_103823_k
		// @20: aconst_null
		// @21: putstatic game.C_100302_ka game.C_100046_vk.field_102764_yb
		// @24: iload_0
		// @25: bipush -28 (0xE4)
		// @27: if_icmple @38
		// @2A: aconst_null
		// @2B: checkcast game.C_100278_nd
		// @2E: bipush -65 (0xBF)
		// @30: invokestatic game.C_100203_ql.func_105925_a(game.C_100278_nd, int)game.C_100277_nc
		// @33: pop
		// @34: goto @38
		// @37: athrow
		// @38: iconst_0
		// @39: istore_1
		// @3A: iload_1
		// @3B: getstatic game.C_100302_ka[] game.C_100103_eh.field_104669_j
		// @3E: arraylength
		// @3F: if_icmpge @57
		// @42: getstatic game.C_100302_ka[] game.C_100103_eh.field_104669_j
		// @45: iload_1
		// @46: aconst_null
		// @47: aastore
		// @48: iinc #1 +1
		// @4B: iload_2
		// @4C: ifne @59
		// @4F: iload_2
		// @50: ifeq @3A
		// @53: goto @57
		// @56: athrow
		// @57: iconst_0
		// @58: istore_1
		// @59: getstatic game.C_100302_ka[] game.C_100063_dj.field_104290_f
		// @5C: arraylength
		// @5D: iconst_m1
		// @5E: ixor
		// @5F: iload_1
		// @60: iconst_m1
		// @61: ixor
		// @62: if_icmpge @7E
		// @65: getstatic game.C_100302_ka[] game.C_100063_dj.field_104290_f
		// @68: iload_1
		// @69: aconst_null
		// @6A: aastore
		// @6B: iinc #1 +1
		// @6E: iload_2
		// @6F: ifne @A2
		// @72: goto @76
		// @75: athrow
		// @76: iload_2
		// @77: ifeq @59
		// @7A: goto @7E
		// @7D: athrow
		// @7E: goto @A2
		// @81: astore_1
		// @82: aload_1
		// @83: new java.lang.StringBuilder
		// @86: dup
		// @87: invokespecial java.lang.StringBuilder.<init>()void
		// @8A: getstatic java.lang.String[] game.C_100203_ql.field_105933_z
		// @8D: iconst_1
		// @8E: aaload
		// @8F: invokevirtual java.lang.StringBuilder.append(java.lang.String)java.lang.StringBuilder
		// @92: iload_0
		// @93: invokevirtual java.lang.StringBuilder.append(int)java.lang.StringBuilder
		// @96: bipush 41 (0x29)
		// @98: invokevirtual java.lang.StringBuilder.append(char)java.lang.StringBuilder
		// @9B: invokevirtual java.lang.StringBuilder.toString()java.lang.String
		// @9E: invokestatic game.C_100181_cf.func_105695_a(java.lang.Throwable, java.lang.String)game.C_100170_cm
		// @A1: athrow
		// @A2: return
	}
	
	public static void func_105920_b(int arg0)
	{
		// @00: aconst_null
		// @01: putstatic java.lang.String game.C_100203_ql.field_105930_b
		// @04: iload_0
		// @05: bipush 30 (0x1E)
		// @07: if_icmpeq @18
		// @0A: aconst_null
		// @0B: checkcast int[][][]
		// @0E: checkcast int[][][]
		// @11: putstatic int[][][] game.C_100203_ql.field_105931_c
		// @14: goto @18
		// @17: athrow
		// @18: aconst_null
		// @19: putstatic java.lang.String game.C_100203_ql.field_105928_d
		// @1C: aconst_null
		// @1D: checkcast int[][][]
		// @20: putstatic int[][][] game.C_100203_ql.field_105931_c
		// @23: aconst_null
		// @24: putstatic java.lang.String game.C_100203_ql.field_105929_e
		// @27: aconst_null
		// @28: putstatic game.C_100098_h game.C_100203_ql.field_105932_a
		// @2B: aconst_null
		// @2C: putstatic game.C_100253_ph game.C_100203_ql.field_105927_f
		// @2F: goto @53
		// @32: astore_1
		// @33: aload_1
		// @34: new java.lang.StringBuilder
		// @37: dup
		// @38: invokespecial java.lang.StringBuilder.<init>()void
		// @3B: getstatic java.lang.String[] game.C_100203_ql.field_105933_z
		// @3E: iconst_2
		// @3F: aaload
		// @40: invokevirtual java.lang.StringBuilder.append(java.lang.String)java.lang.StringBuilder
		// @43: iload_0
		// @44: invokevirtual java.lang.StringBuilder.append(int)java.lang.StringBuilder
		// @47: bipush 41 (0x29)
		// @49: invokevirtual java.lang.StringBuilder.append(char)java.lang.StringBuilder
		// @4C: invokevirtual java.lang.StringBuilder.toString()java.lang.String
		// @4F: invokestatic game.C_100181_cf.func_105695_a(java.lang.Throwable, java.lang.String)game.C_100170_cm
		// @52: athrow
		// @53: return
	}
	
	static final C_100211_qd func_105926_a(boolean arg0, int arg1)
	{
		// @00: iload_0
		// @01: iconst_1
		// @02: if_icmpeq @10
		// @05: iconst_1
		// @06: bipush -5 (0xFB)
		// @08: invokestatic game.C_100203_ql.func_105926_a(boolean, int)game.C_100211_qd
		// @0B: pop
		// @0C: goto @10
		// @0F: athrow
		// @10: aconst_null
		// @11: getstatic game.C_100105_eg game.C_100329_ih.field_107271_c
		// @14: if_acmpne @1C
		// @17: aconst_null
		// @18: goto @27
		// @1B: athrow
		// @1C: getstatic game.C_100105_eg game.C_100329_ih.field_107271_c
		// @1F: sipush -16397 (0xBFF3)
		// @22: iload_1
		// @23: i2l
		// @24: invokevirtual game.C_100105_eg.func_104724_a(int, long)game.C_100325_id
		// @27: checkcast game.C_100211_qd
		// @2A: checkcast game.C_100211_qd
		// @2D: areturn
		// @2E: astore_2
		// @2F: aload_2
		// @30: new java.lang.StringBuilder
		// @33: dup
		// @34: invokespecial java.lang.StringBuilder.<init>()void
		// @37: getstatic java.lang.String[] game.C_100203_ql.field_105933_z
		// @3A: iconst_0
		// @3B: aaload
		// @3C: invokevirtual java.lang.StringBuilder.append(java.lang.String)java.lang.StringBuilder
		// @3F: iload_0
		// @40: invokevirtual java.lang.StringBuilder.append(boolean)java.lang.StringBuilder
		// @43: bipush 44 (0x2C)
		// @45: invokevirtual java.lang.StringBuilder.append(char)java.lang.StringBuilder
		// @48: iload_1
		// @49: invokevirtual java.lang.StringBuilder.append(int)java.lang.StringBuilder
		// @4C: bipush 41 (0x29)
		// @4E: invokevirtual java.lang.StringBuilder.append(char)java.lang.StringBuilder
		// @51: invokevirtual java.lang.StringBuilder.toString()java.lang.String
		// @54: invokestatic game.C_100181_cf.func_105695_a(java.lang.Throwable, java.lang.String)game.C_100170_cm
		// @57: athrow
	}
	
	static final void func_105924_a(int arg0, int arg1, byte arg2, int arg3, C_100127_tl arg4, C_100127_tl arg5)
	{
		// @00: iload_1
		// @01: putstatic int game.C_100085_a.field_102575_J
		// @04: aload #4
		// @06: putstatic game.C_100127_tl game.C_100197_ra.field_100856_n
		// @09: aload #5
		// @0B: putstatic game.C_100127_tl game.C_100160_sm.field_105415_b
		// @0E: iload_3
		// @0F: putstatic int game.C_100314_lf.field_101381_bb
		// @12: iload_0
		// @13: putstatic int game.C_100057_dd.field_104253_f
		// @16: iload_2
		// @17: bipush 83 (0x53)
		// @19: if_icmpgt @23
		// @1C: aconst_null
		// @1D: checkcast java.lang.String
		// @20: putstatic java.lang.String game.C_100203_ql.field_105928_d
		// @23: goto @9A
		// @26: astore #6
		// @28: aload #6
		// @2A: new java.lang.StringBuilder
		// @2D: dup
		// @2E: invokespecial java.lang.StringBuilder.<init>()void
		// @31: getstatic java.lang.String[] game.C_100203_ql.field_105933_z
		// @34: iconst_3
		// @35: aaload
		// @36: invokevirtual java.lang.StringBuilder.append(java.lang.String)java.lang.StringBuilder
		// @39: iload_0
		// @3A: invokevirtual java.lang.StringBuilder.append(int)java.lang.StringBuilder
		// @3D: bipush 44 (0x2C)
		// @3F: invokevirtual java.lang.StringBuilder.append(char)java.lang.StringBuilder
		// @42: iload_1
		// @43: invokevirtual java.lang.StringBuilder.append(int)java.lang.StringBuilder
		// @46: bipush 44 (0x2C)
		// @48: invokevirtual java.lang.StringBuilder.append(char)java.lang.StringBuilder
		// @4B: iload_2
		// @4C: invokevirtual java.lang.StringBuilder.append(int)java.lang.StringBuilder
		// @4F: bipush 44 (0x2C)
		// @51: invokevirtual java.lang.StringBuilder.append(char)java.lang.StringBuilder
		// @54: iload_3
		// @55: invokevirtual java.lang.StringBuilder.append(int)java.lang.StringBuilder
		// @58: bipush 44 (0x2C)
		// @5A: invokevirtual java.lang.StringBuilder.append(char)java.lang.StringBuilder
		// @5D: aload #4
		// @5F: ifnull @6B
		// @62: getstatic java.lang.String[] game.C_100203_ql.field_105933_z
		// @65: iconst_4
		// @66: aaload
		// @67: goto @70
		// @6A: athrow
		// @6B: getstatic java.lang.String[] game.C_100203_ql.field_105933_z
		// @6E: iconst_5
		// @6F: aaload
		// @70: invokevirtual java.lang.StringBuilder.append(java.lang.String)java.lang.StringBuilder
		// @73: bipush 44 (0x2C)
		// @75: invokevirtual java.lang.StringBuilder.append(char)java.lang.StringBuilder
		// @78: aload #5
		// @7A: ifnull @86
		// @7D: getstatic java.lang.String[] game.C_100203_ql.field_105933_z
		// @80: iconst_4
		// @81: aaload
		// @82: goto @8B
		// @85: athrow
		// @86: getstatic java.lang.String[] game.C_100203_ql.field_105933_z
		// @89: iconst_5
		// @8A: aaload
		// @8B: invokevirtual java.lang.StringBuilder.append(java.lang.String)java.lang.StringBuilder
		// @8E: bipush 41 (0x29)
		// @90: invokevirtual java.lang.StringBuilder.append(char)java.lang.StringBuilder
		// @93: invokevirtual java.lang.StringBuilder.toString()java.lang.String
		// @96: invokestatic game.C_100181_cf.func_105695_a(java.lang.Throwable, java.lang.String)game.C_100170_cm
		// @99: athrow
		// @9A: return
	}
	
	static
	{
		// @000: bipush 7 (0x07)
		// @002: anewarray java.lang.String
		// @005: dup
		// @006: iconst_0
		// @007: ldc "T\u0014gpH"
		// @009: invokestatic game.C_100203_ql.func_105923_z(java.lang.String)char[]
		// @00C: invokestatic game.C_100203_ql.func_105922_z(char[])java.lang.String
		// @00F: aastore
		// @010: dup
		// @011: iconst_1
		// @012: ldc "T\u0014gtH"
		// @014: invokestatic game.C_100203_ql.func_105923_z(java.lang.String)char[]
		// @017: invokestatic game.C_100203_ql.func_105922_z(char[])java.lang.String
		// @01A: aastore
		// @01B: dup
		// @01C: iconst_2
		// @01D: ldc "T\u0014gsH"
		// @01F: invokestatic game.C_100203_ql.func_105923_z(java.lang.String)char[]
		// @022: invokestatic game.C_100203_ql.func_105922_z(char[])java.lang.String
		// @025: aastore
		// @026: dup
		// @027: iconst_3
		// @028: ldc "T\u0014guH"
		// @02A: invokestatic game.C_100203_ql.func_105923_z(java.lang.String)char[]
		// @02D: invokestatic game.C_100203_ql.func_105922_z(char[])java.lang.String
		// @030: aastore
		// @031: dup
		// @032: iconst_4
		// @033: ldc "^Vg\u001f\u001d"
		// @035: invokestatic game.C_100203_ql.func_105923_z(java.lang.String)char[]
		// @038: invokestatic game.C_100203_ql.func_105922_z(char[])java.lang.String
		// @03B: aastore
		// @03C: dup
		// @03D: iconst_5
		// @03E: ldc "K\r%]"
		// @040: invokestatic game.C_100203_ql.func_105923_z(java.lang.String)char[]
		// @043: invokestatic game.C_100203_ql.func_105922_z(char[])java.lang.String
		// @046: aastore
		// @047: dup
		// @048: bipush 6 (0x06)
		// @04A: ldc "T\u0014grH"
		// @04C: invokestatic game.C_100203_ql.func_105923_z(java.lang.String)char[]
		// @04F: invokestatic game.C_100203_ql.func_105922_z(char[])java.lang.String
		// @052: aastore
		// @053: putstatic java.lang.String[] game.C_100203_ql.field_105933_z
		// @056: ldc "f\n,P\u0014@X(\u0011\u0006W\u001d,\u0011!F\u001b&D\u000eQ"
		// @058: invokestatic game.C_100203_ql.func_105923_z(java.lang.String)char[]
		// @05B: invokestatic game.C_100203_ql.func_105922_z(char[])java.lang.String
		// @05E: putstatic java.lang.String game.C_100203_ql.field_105930_b
		// @061: iconst_2
		// @062: anewarray int[][]
		// @065: dup
		// @066: iconst_0
		// @067: iconst_3
		// @068: anewarray int[]
		// @06B: dup
		// @06C: iconst_0
		// @06D: bipush 8 (0x08)
		// @06F: newarray int[]
		// @071: dup
		// @072: iconst_0
		// @073: iconst_0
		// @074: iastore
		// @075: dup
		// @076: iconst_1
		// @077: iconst_1
		// @078: iastore
		// @079: dup
		// @07A: iconst_2
		// @07B: iconst_2
		// @07C: iastore
		// @07D: dup
		// @07E: iconst_3
		// @07F: iconst_4
		// @080: iastore
		// @081: dup
		// @082: iconst_4
		// @083: iconst_5
		// @084: iastore
		// @085: dup
		// @086: iconst_5
		// @087: bipush 8 (0x08)
		// @089: iastore
		// @08A: dup
		// @08B: bipush 6 (0x06)
		// @08D: bipush 16 (0x10)
		// @08F: iastore
		// @090: dup
		// @091: bipush 7 (0x07)
		// @093: bipush 9 (0x09)
		// @095: iastore
		// @096: aastore
		// @097: dup
		// @098: iconst_1
		// @099: bipush 8 (0x08)
		// @09B: newarray int[]
		// @09D: dup
		// @09E: iconst_0
		// @09F: bipush 24 (0x18)
		// @0A1: iastore
		// @0A2: dup
		// @0A3: iconst_1
		// @0A4: bipush 25 (0x19)
		// @0A6: iastore
		// @0A7: dup
		// @0A8: iconst_2
		// @0A9: bipush 26 (0x1A)
		// @0AB: iastore
		// @0AC: dup
		// @0AD: iconst_3
		// @0AE: bipush 27 (0x1B)
		// @0B0: iastore
		// @0B1: dup
		// @0B2: iconst_4
		// @0B3: bipush 28 (0x1C)
		// @0B5: iastore
		// @0B6: dup
		// @0B7: iconst_5
		// @0B8: bipush 29 (0x1D)
		// @0BA: iastore
		// @0BB: dup
		// @0BC: bipush 6 (0x06)
		// @0BE: bipush 30 (0x1E)
		// @0C0: iastore
		// @0C1: dup
		// @0C2: bipush 7 (0x07)
		// @0C4: bipush 31 (0x1F)
		// @0C6: iastore
		// @0C7: aastore
		// @0C8: dup
		// @0C9: iconst_2
		// @0CA: bipush 7 (0x07)
		// @0CC: newarray int[]
		// @0CE: dup
		// @0CF: iconst_0
		// @0D0: bipush 32 (0x20)
		// @0D2: iastore
		// @0D3: dup
		// @0D4: iconst_1
		// @0D5: bipush 6 (0x06)
		// @0D7: iastore
		// @0D8: dup
		// @0D9: iconst_2
		// @0DA: bipush 33 (0x21)
		// @0DC: iastore
		// @0DD: dup
		// @0DE: iconst_3
		// @0DF: bipush 34 (0x22)
		// @0E1: iastore
		// @0E2: dup
		// @0E3: iconst_4
		// @0E4: bipush 35 (0x23)
		// @0E6: iastore
		// @0E7: dup
		// @0E8: iconst_5
		// @0E9: bipush 36 (0x24)
		// @0EB: iastore
		// @0EC: dup
		// @0ED: bipush 6 (0x06)
		// @0EF: bipush 37 (0x25)
		// @0F1: iastore
		// @0F2: aastore
		// @0F3: aastore
		// @0F4: dup
		// @0F5: iconst_1
		// @0F6: iconst_3
		// @0F7: anewarray int[]
		// @0FA: dup
		// @0FB: iconst_0
		// @0FC: bipush 7 (0x07)
		// @0FE: newarray int[]
		// @100: dup
		// @101: iconst_0
		// @102: bipush 17 (0x11)
		// @104: iastore
		// @105: dup
		// @106: iconst_1
		// @107: bipush 18 (0x12)
		// @109: iastore
		// @10A: dup
		// @10B: iconst_2
		// @10C: bipush 19 (0x13)
		// @10E: iastore
		// @10F: dup
		// @110: iconst_3
		// @111: bipush 20 (0x14)
		// @113: iastore
		// @114: dup
		// @115: iconst_4
		// @116: bipush 21 (0x15)
		// @118: iastore
		// @119: dup
		// @11A: iconst_5
		// @11B: bipush 22 (0x16)
		// @11D: iastore
		// @11E: dup
		// @11F: bipush 6 (0x06)
		// @121: bipush 23 (0x17)
		// @123: iastore
		// @124: aastore
		// @125: dup
		// @126: iconst_1
		// @127: bipush 8 (0x08)
		// @129: newarray int[]
		// @12B: dup
		// @12C: iconst_0
		// @12D: iconst_3
		// @12E: iastore
		// @12F: dup
		// @130: iconst_1
		// @131: bipush 7 (0x07)
		// @133: iastore
		// @134: dup
		// @135: iconst_2
		// @136: bipush 10 (0x0A)
		// @138: iastore
		// @139: dup
		// @13A: iconst_3
		// @13B: bipush 11 (0x0B)
		// @13D: iastore
		// @13E: dup
		// @13F: iconst_4
		// @140: bipush 12 (0x0C)
		// @142: iastore
		// @143: dup
		// @144: iconst_5
		// @145: bipush 13 (0x0D)
		// @147: iastore
		// @148: dup
		// @149: bipush 6 (0x06)
		// @14B: bipush 15 (0x0F)
		// @14D: iastore
		// @14E: dup
		// @14F: bipush 7 (0x07)
		// @151: bipush 14 (0x0E)
		// @153: iastore
		// @154: aastore
		// @155: dup
		// @156: iconst_2
		// @157: iconst_1
		// @158: newarray int[]
		// @15A: dup
		// @15B: iconst_0
		// @15C: bipush 38 (0x26)
		// @15E: iastore
		// @15F: aastore
		// @160: aastore
		// @161: putstatic int[][][] game.C_100203_ql.field_105931_c
		// @164: ldc "\u0019]y\u000f@L\u000biP\u000cW\u001d(U\u0019\u0005\u0017'\u0011\u0019J\r;\u0011\tB\u0016&C\u0005\u0005\u0014 B\u0014\u000b"
		// @166: invokestatic game.C_100203_ql.func_105923_z(java.lang.String)char[]
		// @169: invokestatic game.C_100203_ql.func_105922_z(char[])java.lang.String
		// @16C: putstatic java.lang.String game.C_100203_ql.field_105928_d
		// @16F: ldc "l\u001eiH\u000fPX(C\u0005\u0005\u0016&EL\u0005\u0008%T\u0001V\u001diR\u0008D\u0016.T@\\\u0017<C@U\u0019:B\u0017J\n-\u0011\u0014JX:^\r@\u000c!X\u000eBX$^\u0012@X&S\u0013F\r;TA"
		// @171: invokestatic game.C_100203_ql.func_105923_z(java.lang.String)char[]
		// @174: invokestatic game.C_100203_ql.func_105922_z(char[])java.lang.String
		// @177: putstatic java.lang.String game.C_100203_ql.field_105929_e
		// @17A: return
	}
	
	private static char[] func_105923_z(String arg0)
	{
		// @00: aload_0
		// @01: invokevirtual java.lang.String.toCharArray()char[]
		// @04: dup
		// @05: arraylength
		// @06: iconst_2
		// @07: if_icmpge @13
		// @0A: dup
		// @0B: iconst_0
		// @0C: dup2
		// @0D: caload
		// @0E: bipush 96 (0x60)
		// @10: ixor
		// @11: i2c
		// @12: castore
		// @13: areturn
	}
	
	private static String func_105922_z(char[] arg0)
	{
		// @00: aload_0
		// @01: dup
		// @02: arraylength
		// @03: swap
		// @04: iconst_0
		// @05: istore_1
		// @06: goto @4C
		// @09: dup
		// @0A: iload_1
		// @0B: dup2
		// @0C: caload
		// @0D: iload_1
		// @0E: iconst_5
		// @0F: irem
		// @10: tableswitch def: @44, for 0: @30, for 1: @35, for 2: @3A, for 3: @3F
		// @30: bipush 37 (0x25)
		// @32: goto @46
		// @35: bipush 120 (0x78)
		// @37: goto @46
		// @3A: bipush 73 (0x49)
		// @3C: goto @46
		// @3F: bipush 49 (0x31)
		// @41: goto @46
		// @44: bipush 96 (0x60)
		// @46: ixor
		// @47: i2c
		// @48: castore
		// @49: iinc #1 +1
		// @4C: swap
		// @4D: dup_x1
		// @4E: iload_1
		// @4F: if_icmpgt @09
		// @52: new java.lang.String
		// @55: dup_x1
		// @56: swap
		// @57: invokespecial java.lang.String.<init>(char[])void
		// @5A: invokevirtual java.lang.String.intern()java.lang.String
		// @5D: areturn
	}
}
