package game;

import java.applet.Applet;

final class C_100206_qe
{
	static boolean field_105941_c;
	static String field_105942_a;
	static String field_105939_d;
	static String field_105940_b;
	private static final String[] field_105943_z;
	
	public static void func_105937_a(boolean arg0)
	{
		// @00: aconst_null
		// @01: putstatic java.lang.String game.C_100206_qe.field_105939_d
		// @04: aconst_null
		// @05: putstatic java.lang.String game.C_100206_qe.field_105940_b
		// @08: aconst_null
		// @09: putstatic java.lang.String game.C_100206_qe.field_105942_a
		// @0C: iload_0
		// @0D: iconst_1
		// @0E: if_icmpeq @15
		// @11: iconst_0
		// @12: putstatic boolean game.C_100206_qe.field_105941_c
		// @15: goto @39
		// @18: astore_1
		// @19: aload_1
		// @1A: new java.lang.StringBuilder
		// @1D: dup
		// @1E: invokespecial java.lang.StringBuilder.<init>()void
		// @21: getstatic java.lang.String[] game.C_100206_qe.field_105943_z
		// @24: iconst_0
		// @25: aaload
		// @26: invokevirtual java.lang.StringBuilder.append(java.lang.String)java.lang.StringBuilder
		// @29: iload_0
		// @2A: invokevirtual java.lang.StringBuilder.append(boolean)java.lang.StringBuilder
		// @2D: bipush 41 (0x29)
		// @2F: invokevirtual java.lang.StringBuilder.append(char)java.lang.StringBuilder
		// @32: invokevirtual java.lang.StringBuilder.toString()java.lang.String
		// @35: invokestatic game.C_100181_cf.func_105695_a(java.lang.Throwable, java.lang.String)game.C_100170_cm
		// @38: athrow
		// @39: return
	}
	
	static final Applet func_105938_b(boolean arg0)
	{
		// @00: iload_0
		// @01: ifeq @14
		// @04: aconst_null
		// @05: checkcast game.C_100098_h
		// @08: iconst_4
		// @09: aconst_null
		// @0A: checkcast game.C_100098_h
		// @0D: invokestatic game.C_100206_qe.func_105934_a(game.C_100098_h, int, game.C_100098_h)void
		// @10: goto @14
		// @13: athrow
		// @14: aconst_null
		// @15: getstatic java.applet.Applet game.C_100107_u.field_104771_d
		// @18: if_acmpne @1F
		// @1B: goto @23
		// @1E: athrow
		// @1F: getstatic java.applet.Applet game.C_100107_u.field_104771_d
		// @22: areturn
		// @23: getstatic game.C_100152_bd game.C_100272_mn.field_102428_L
		// @26: areturn
		// @27: astore_1
		// @28: aload_1
		// @29: new java.lang.StringBuilder
		// @2C: dup
		// @2D: invokespecial java.lang.StringBuilder.<init>()void
		// @30: getstatic java.lang.String[] game.C_100206_qe.field_105943_z
		// @33: bipush 28 (0x1C)
		// @35: aaload
		// @36: invokevirtual java.lang.StringBuilder.append(java.lang.String)java.lang.StringBuilder
		// @39: iload_0
		// @3A: invokevirtual java.lang.StringBuilder.append(boolean)java.lang.StringBuilder
		// @3D: bipush 41 (0x29)
		// @3F: invokevirtual java.lang.StringBuilder.append(char)java.lang.StringBuilder
		// @42: invokevirtual java.lang.StringBuilder.toString()java.lang.String
		// @45: invokestatic game.C_100181_cf.func_105695_a(java.lang.Throwable, java.lang.String)game.C_100170_cm
		// @48: athrow
	}
	
	static final void func_105934_a(C_100098_h arg0, int arg1, C_100098_h arg2)
	{
		// @000: iconst_m1
		// @001: invokestatic game.C_100209_qb.func_102680_r(int)java.awt.Canvas
		// @004: astore_3
		// @005: aload_3
		// @006: ifnonnull @011
		// @009: new java.awt.Canvas
		// @00C: dup
		// @00D: invokespecial java.awt.Canvas.<init>()void
		// @010: astore_3
		// @011: iconst_5
		// @012: anewarray game.C_100037_wb[]
		// @015: putstatic game.C_100037_wb[][] game.C_100058_dg.field_101564_G
		// @018: aconst_null
		// @019: aload_2
		// @01A: if_acmpne @021
		// @01D: goto @1E8
		// @020: athrow
		// @021: getstatic game.C_100037_wb[][] game.C_100058_dg.field_101564_G
		// @024: iconst_0
		// @025: bipush 7 (0x07)
		// @027: anewarray game.C_100037_wb
		// @02A: aastore
		// @02B: getstatic game.C_100037_wb[][] game.C_100058_dg.field_101564_G
		// @02E: iconst_0
		// @02F: aaload
		// @030: iconst_0
		// @031: new game.C_100251_pm
		// @034: dup
		// @035: aload_2
		// @036: getstatic java.lang.String[] game.C_100206_qe.field_105943_z
		// @039: bipush 15 (0x0F)
		// @03B: aaload
		// @03C: getstatic java.lang.String[] game.C_100206_qe.field_105943_z
		// @03F: bipush 21 (0x15)
		// @041: aaload
		// @042: bipush -44 (0xD4)
		// @044: invokevirtual game.C_100098_h.func_104608_a(java.lang.String, java.lang.String, int)byte[]
		// @047: aload_3
		// @048: invokespecial game.C_100251_pm.<init>(byte[], java.awt.Component)void
		// @04B: aastore
		// @04C: getstatic game.C_100037_wb[][] game.C_100058_dg.field_101564_G
		// @04F: iconst_0
		// @050: aaload
		// @051: iconst_1
		// @052: new game.C_100251_pm
		// @055: dup
		// @056: aload_2
		// @057: getstatic java.lang.String[] game.C_100206_qe.field_105943_z
		// @05A: bipush 25 (0x19)
		// @05C: aaload
		// @05D: getstatic java.lang.String[] game.C_100206_qe.field_105943_z
		// @060: bipush 21 (0x15)
		// @062: aaload
		// @063: iload_1
		// @064: bipush -48 (0xD0)
		// @066: invokestatic game.C_100089_fa.func_103722_a(int, int)int
		// @069: invokevirtual game.C_100098_h.func_104608_a(java.lang.String, java.lang.String, int)byte[]
		// @06C: aload_3
		// @06D: invokespecial game.C_100251_pm.<init>(byte[], java.awt.Component)void
		// @070: aastore
		// @071: getstatic game.C_100037_wb[][] game.C_100058_dg.field_101564_G
		// @074: iconst_0
		// @075: aaload
		// @076: iconst_2
		// @077: new game.C_100251_pm
		// @07A: dup
		// @07B: aload_2
		// @07C: getstatic java.lang.String[] game.C_100206_qe.field_105943_z
		// @07F: bipush 27 (0x1B)
		// @081: aaload
		// @082: getstatic java.lang.String[] game.C_100206_qe.field_105943_z
		// @085: bipush 21 (0x15)
		// @087: aaload
		// @088: bipush 127 (0x7F)
		// @08A: invokevirtual game.C_100098_h.func_104608_a(java.lang.String, java.lang.String, int)byte[]
		// @08D: aload_3
		// @08E: invokespecial game.C_100251_pm.<init>(byte[], java.awt.Component)void
		// @091: aastore
		// @092: getstatic game.C_100037_wb[][] game.C_100058_dg.field_101564_G
		// @095: iconst_0
		// @096: aaload
		// @097: iconst_3
		// @098: new game.C_100251_pm
		// @09B: dup
		// @09C: aload_2
		// @09D: getstatic java.lang.String[] game.C_100206_qe.field_105943_z
		// @0A0: bipush 22 (0x16)
		// @0A2: aaload
		// @0A3: getstatic java.lang.String[] game.C_100206_qe.field_105943_z
		// @0A6: bipush 21 (0x15)
		// @0A8: aaload
		// @0A9: bipush -85 (0xAB)
		// @0AB: invokevirtual game.C_100098_h.func_104608_a(java.lang.String, java.lang.String, int)byte[]
		// @0AE: aload_3
		// @0AF: invokespecial game.C_100251_pm.<init>(byte[], java.awt.Component)void
		// @0B2: aastore
		// @0B3: getstatic game.C_100037_wb[][] game.C_100058_dg.field_101564_G
		// @0B6: iconst_0
		// @0B7: aaload
		// @0B8: iconst_4
		// @0B9: new game.C_100251_pm
		// @0BC: dup
		// @0BD: aload_2
		// @0BE: getstatic java.lang.String[] game.C_100206_qe.field_105943_z
		// @0C1: bipush 20 (0x14)
		// @0C3: aaload
		// @0C4: getstatic java.lang.String[] game.C_100206_qe.field_105943_z
		// @0C7: bipush 21 (0x15)
		// @0C9: aaload
		// @0CA: bipush 118 (0x76)
		// @0CC: invokevirtual game.C_100098_h.func_104608_a(java.lang.String, java.lang.String, int)byte[]
		// @0CF: aload_3
		// @0D0: invokespecial game.C_100251_pm.<init>(byte[], java.awt.Component)void
		// @0D3: aastore
		// @0D4: getstatic game.C_100037_wb[][] game.C_100058_dg.field_101564_G
		// @0D7: iconst_0
		// @0D8: aaload
		// @0D9: iconst_5
		// @0DA: new game.C_100251_pm
		// @0DD: dup
		// @0DE: aload_2
		// @0DF: getstatic java.lang.String[] game.C_100206_qe.field_105943_z
		// @0E2: bipush 8 (0x08)
		// @0E4: aaload
		// @0E5: getstatic java.lang.String[] game.C_100206_qe.field_105943_z
		// @0E8: bipush 21 (0x15)
		// @0EA: aaload
		// @0EB: bipush 113 (0x71)
		// @0ED: invokevirtual game.C_100098_h.func_104608_a(java.lang.String, java.lang.String, int)byte[]
		// @0F0: aload_3
		// @0F1: invokespecial game.C_100251_pm.<init>(byte[], java.awt.Component)void
		// @0F4: aastore
		// @0F5: getstatic game.C_100037_wb[][] game.C_100058_dg.field_101564_G
		// @0F8: iconst_0
		// @0F9: aaload
		// @0FA: bipush 6 (0x06)
		// @0FC: new game.C_100251_pm
		// @0FF: dup
		// @100: aload_2
		// @101: getstatic java.lang.String[] game.C_100206_qe.field_105943_z
		// @104: bipush 11 (0x0B)
		// @106: aaload
		// @107: getstatic java.lang.String[] game.C_100206_qe.field_105943_z
		// @10A: bipush 21 (0x15)
		// @10C: aaload
		// @10D: bipush 116 (0x74)
		// @10F: invokevirtual game.C_100098_h.func_104608_a(java.lang.String, java.lang.String, int)byte[]
		// @112: aload_3
		// @113: invokespecial game.C_100251_pm.<init>(byte[], java.awt.Component)void
		// @116: aastore
		// @117: getstatic game.C_100037_wb[][] game.C_100058_dg.field_101564_G
		// @11A: iconst_1
		// @11B: bipush 6 (0x06)
		// @11D: anewarray game.C_100037_wb
		// @120: aastore
		// @121: getstatic game.C_100037_wb[][] game.C_100058_dg.field_101564_G
		// @124: iconst_1
		// @125: aaload
		// @126: iconst_0
		// @127: new game.C_100251_pm
		// @12A: dup
		// @12B: aload_2
		// @12C: getstatic java.lang.String[] game.C_100206_qe.field_105943_z
		// @12F: bipush 17 (0x11)
		// @131: aaload
		// @132: getstatic java.lang.String[] game.C_100206_qe.field_105943_z
		// @135: bipush 7 (0x07)
		// @137: aaload
		// @138: bipush -73 (0xB7)
		// @13A: invokevirtual game.C_100098_h.func_104608_a(java.lang.String, java.lang.String, int)byte[]
		// @13D: aload_3
		// @13E: invokespecial game.C_100251_pm.<init>(byte[], java.awt.Component)void
		// @141: aastore
		// @142: getstatic game.C_100037_wb[][] game.C_100058_dg.field_101564_G
		// @145: iconst_1
		// @146: aaload
		// @147: iconst_1
		// @148: new game.C_100251_pm
		// @14B: dup
		// @14C: aload_2
		// @14D: getstatic java.lang.String[] game.C_100206_qe.field_105943_z
		// @150: bipush 14 (0x0E)
		// @152: aaload
		// @153: getstatic java.lang.String[] game.C_100206_qe.field_105943_z
		// @156: bipush 7 (0x07)
		// @158: aaload
		// @159: bipush -114 (0x8E)
		// @15B: invokevirtual game.C_100098_h.func_104608_a(java.lang.String, java.lang.String, int)byte[]
		// @15E: aload_3
		// @15F: invokespecial game.C_100251_pm.<init>(byte[], java.awt.Component)void
		// @162: aastore
		// @163: getstatic game.C_100037_wb[][] game.C_100058_dg.field_101564_G
		// @166: iconst_1
		// @167: aaload
		// @168: iconst_2
		// @169: new game.C_100251_pm
		// @16C: dup
		// @16D: aload_2
		// @16E: getstatic java.lang.String[] game.C_100206_qe.field_105943_z
		// @171: bipush 23 (0x17)
		// @173: aaload
		// @174: getstatic java.lang.String[] game.C_100206_qe.field_105943_z
		// @177: bipush 7 (0x07)
		// @179: aaload
		// @17A: bipush -31 (0xE1)
		// @17C: invokevirtual game.C_100098_h.func_104608_a(java.lang.String, java.lang.String, int)byte[]
		// @17F: aload_3
		// @180: invokespecial game.C_100251_pm.<init>(byte[], java.awt.Component)void
		// @183: aastore
		// @184: getstatic game.C_100037_wb[][] game.C_100058_dg.field_101564_G
		// @187: iconst_1
		// @188: aaload
		// @189: iconst_3
		// @18A: new game.C_100251_pm
		// @18D: dup
		// @18E: aload_2
		// @18F: getstatic java.lang.String[] game.C_100206_qe.field_105943_z
		// @192: bipush 26 (0x1A)
		// @194: aaload
		// @195: getstatic java.lang.String[] game.C_100206_qe.field_105943_z
		// @198: bipush 7 (0x07)
		// @19A: aaload
		// @19B: iload_1
		// @19C: bipush 117 (0x75)
		// @19E: iadd
		// @19F: invokevirtual game.C_100098_h.func_104608_a(java.lang.String, java.lang.String, int)byte[]
		// @1A2: aload_3
		// @1A3: invokespecial game.C_100251_pm.<init>(byte[], java.awt.Component)void
		// @1A6: aastore
		// @1A7: getstatic game.C_100037_wb[][] game.C_100058_dg.field_101564_G
		// @1AA: iconst_1
		// @1AB: aaload
		// @1AC: iconst_4
		// @1AD: new game.C_100251_pm
		// @1B0: dup
		// @1B1: aload_2
		// @1B2: getstatic java.lang.String[] game.C_100206_qe.field_105943_z
		// @1B5: iconst_4
		// @1B6: aaload
		// @1B7: getstatic java.lang.String[] game.C_100206_qe.field_105943_z
		// @1BA: bipush 7 (0x07)
		// @1BC: aaload
		// @1BD: bipush -81 (0xAF)
		// @1BF: invokevirtual game.C_100098_h.func_104608_a(java.lang.String, java.lang.String, int)byte[]
		// @1C2: aload_3
		// @1C3: invokespecial game.C_100251_pm.<init>(byte[], java.awt.Component)void
		// @1C6: aastore
		// @1C7: getstatic game.C_100037_wb[][] game.C_100058_dg.field_101564_G
		// @1CA: iconst_1
		// @1CB: aaload
		// @1CC: iconst_5
		// @1CD: new game.C_100251_pm
		// @1D0: dup
		// @1D1: aload_2
		// @1D2: getstatic java.lang.String[] game.C_100206_qe.field_105943_z
		// @1D5: bipush 18 (0x12)
		// @1D7: aaload
		// @1D8: getstatic java.lang.String[] game.C_100206_qe.field_105943_z
		// @1DB: bipush 7 (0x07)
		// @1DD: aaload
		// @1DE: bipush 120 (0x78)
		// @1E0: invokevirtual game.C_100098_h.func_104608_a(java.lang.String, java.lang.String, int)byte[]
		// @1E3: aload_3
		// @1E4: invokespecial game.C_100251_pm.<init>(byte[], java.awt.Component)void
		// @1E7: aastore
		// @1E8: getstatic game.C_100037_wb[][] game.C_100058_dg.field_101564_G
		// @1EB: iconst_2
		// @1EC: bipush 6 (0x06)
		// @1EE: anewarray game.C_100037_wb
		// @1F1: aastore
		// @1F2: getstatic game.C_100037_wb[][] game.C_100058_dg.field_101564_G
		// @1F5: iconst_2
		// @1F6: aaload
		// @1F7: iconst_0
		// @1F8: bipush 101 (0x65)
		// @1FA: getstatic java.lang.String[] game.C_100206_qe.field_105943_z
		// @1FD: bipush 16 (0x10)
		// @1FF: aaload
		// @200: aload_0
		// @201: getstatic java.lang.String[] game.C_100206_qe.field_105943_z
		// @204: iconst_5
		// @205: aaload
		// @206: invokestatic game.C_100021_wn.func_103861_a(byte, java.lang.String, game.C_100098_h, java.lang.String)game.C_100037_wb
		// @209: aastore
		// @20A: getstatic game.C_100037_wb[][] game.C_100058_dg.field_101564_G
		// @20D: iconst_2
		// @20E: aaload
		// @20F: iconst_1
		// @210: bipush 112 (0x70)
		// @212: getstatic java.lang.String[] game.C_100206_qe.field_105943_z
		// @215: bipush 16 (0x10)
		// @217: aaload
		// @218: aload_0
		// @219: getstatic java.lang.String[] game.C_100206_qe.field_105943_z
		// @21C: bipush 10 (0x0A)
		// @21E: aaload
		// @21F: invokestatic game.C_100021_wn.func_103861_a(byte, java.lang.String, game.C_100098_h, java.lang.String)game.C_100037_wb
		// @222: aastore
		// @223: getstatic game.C_100037_wb[][] game.C_100058_dg.field_101564_G
		// @226: iconst_2
		// @227: aaload
		// @228: iconst_2
		// @229: bipush 84 (0x54)
		// @22B: getstatic java.lang.String[] game.C_100206_qe.field_105943_z
		// @22E: bipush 16 (0x10)
		// @230: aaload
		// @231: aload_0
		// @232: getstatic java.lang.String[] game.C_100206_qe.field_105943_z
		// @235: iconst_2
		// @236: aaload
		// @237: invokestatic game.C_100021_wn.func_103861_a(byte, java.lang.String, game.C_100098_h, java.lang.String)game.C_100037_wb
		// @23A: aastore
		// @23B: getstatic game.C_100037_wb[][] game.C_100058_dg.field_101564_G
		// @23E: iconst_2
		// @23F: aaload
		// @240: iconst_3
		// @241: bipush 98 (0x62)
		// @243: getstatic java.lang.String[] game.C_100206_qe.field_105943_z
		// @246: bipush 16 (0x10)
		// @248: aaload
		// @249: aload_0
		// @24A: getstatic java.lang.String[] game.C_100206_qe.field_105943_z
		// @24D: bipush 6 (0x06)
		// @24F: aaload
		// @250: invokestatic game.C_100021_wn.func_103861_a(byte, java.lang.String, game.C_100098_h, java.lang.String)game.C_100037_wb
		// @253: aastore
		// @254: getstatic game.C_100037_wb[][] game.C_100058_dg.field_101564_G
		// @257: iconst_2
		// @258: aaload
		// @259: iconst_4
		// @25A: bipush 89 (0x59)
		// @25C: getstatic java.lang.String[] game.C_100206_qe.field_105943_z
		// @25F: bipush 16 (0x10)
		// @261: aaload
		// @262: aload_0
		// @263: getstatic java.lang.String[] game.C_100206_qe.field_105943_z
		// @266: bipush 12 (0x0C)
		// @268: aaload
		// @269: invokestatic game.C_100021_wn.func_103861_a(byte, java.lang.String, game.C_100098_h, java.lang.String)game.C_100037_wb
		// @26C: aastore
		// @26D: getstatic game.C_100037_wb[][] game.C_100058_dg.field_101564_G
		// @270: iconst_2
		// @271: aaload
		// @272: iconst_5
		// @273: bipush 101 (0x65)
		// @275: getstatic java.lang.String[] game.C_100206_qe.field_105943_z
		// @278: bipush 16 (0x10)
		// @27A: aaload
		// @27B: aload_0
		// @27C: getstatic java.lang.String[] game.C_100206_qe.field_105943_z
		// @27F: bipush 9 (0x09)
		// @281: aaload
		// @282: invokestatic game.C_100021_wn.func_103861_a(byte, java.lang.String, game.C_100098_h, java.lang.String)game.C_100037_wb
		// @285: aastore
		// @286: getstatic game.C_100037_wb[][] game.C_100058_dg.field_101564_G
		// @289: iconst_4
		// @28A: iconst_2
		// @28B: anewarray game.C_100037_wb
		// @28E: aastore
		// @28F: getstatic game.C_100037_wb[][] game.C_100058_dg.field_101564_G
		// @292: iconst_4
		// @293: aaload
		// @294: iconst_0
		// @295: bipush 92 (0x5C)
		// @297: getstatic java.lang.String[] game.C_100206_qe.field_105943_z
		// @29A: bipush 16 (0x10)
		// @29C: aaload
		// @29D: aload_0
		// @29E: getstatic java.lang.String[] game.C_100206_qe.field_105943_z
		// @2A1: bipush 19 (0x13)
		// @2A3: aaload
		// @2A4: invokestatic game.C_100021_wn.func_103861_a(byte, java.lang.String, game.C_100098_h, java.lang.String)game.C_100037_wb
		// @2A7: aastore
		// @2A8: getstatic game.C_100037_wb[][] game.C_100058_dg.field_101564_G
		// @2AB: iconst_4
		// @2AC: aaload
		// @2AD: iload_1
		// @2AE: bipush 96 (0x60)
		// @2B0: getstatic java.lang.String[] game.C_100206_qe.field_105943_z
		// @2B3: bipush 16 (0x10)
		// @2B5: aaload
		// @2B6: aload_0
		// @2B7: getstatic java.lang.String[] game.C_100206_qe.field_105943_z
		// @2BA: iconst_3
		// @2BB: aaload
		// @2BC: invokestatic game.C_100021_wn.func_103861_a(byte, java.lang.String, game.C_100098_h, java.lang.String)game.C_100037_wb
		// @2BF: aastore
		// @2C0: goto @31B
		// @2C3: astore_3
		// @2C4: aload_3
		// @2C5: new java.lang.StringBuilder
		// @2C8: dup
		// @2C9: invokespecial java.lang.StringBuilder.<init>()void
		// @2CC: getstatic java.lang.String[] game.C_100206_qe.field_105943_z
		// @2CF: bipush 24 (0x18)
		// @2D1: aaload
		// @2D2: invokevirtual java.lang.StringBuilder.append(java.lang.String)java.lang.StringBuilder
		// @2D5: aload_0
		// @2D6: ifnull @2E2
		// @2D9: getstatic java.lang.String[] game.C_100206_qe.field_105943_z
		// @2DC: iconst_1
		// @2DD: aaload
		// @2DE: goto @2E8
		// @2E1: athrow
		// @2E2: getstatic java.lang.String[] game.C_100206_qe.field_105943_z
		// @2E5: bipush 13 (0x0D)
		// @2E7: aaload
		// @2E8: invokevirtual java.lang.StringBuilder.append(java.lang.String)java.lang.StringBuilder
		// @2EB: bipush 44 (0x2C)
		// @2ED: invokevirtual java.lang.StringBuilder.append(char)java.lang.StringBuilder
		// @2F0: iload_1
		// @2F1: invokevirtual java.lang.StringBuilder.append(int)java.lang.StringBuilder
		// @2F4: bipush 44 (0x2C)
		// @2F6: invokevirtual java.lang.StringBuilder.append(char)java.lang.StringBuilder
		// @2F9: aload_2
		// @2FA: ifnull @306
		// @2FD: getstatic java.lang.String[] game.C_100206_qe.field_105943_z
		// @300: iconst_1
		// @301: aaload
		// @302: goto @30C
		// @305: athrow
		// @306: getstatic java.lang.String[] game.C_100206_qe.field_105943_z
		// @309: bipush 13 (0x0D)
		// @30B: aaload
		// @30C: invokevirtual java.lang.StringBuilder.append(java.lang.String)java.lang.StringBuilder
		// @30F: bipush 41 (0x29)
		// @311: invokevirtual java.lang.StringBuilder.append(char)java.lang.StringBuilder
		// @314: invokevirtual java.lang.StringBuilder.toString()java.lang.String
		// @317: invokestatic game.C_100181_cf.func_105695_a(java.lang.Throwable, java.lang.String)game.C_100170_cm
		// @31A: athrow
		// @31B: return
	}
	
	static
	{
		// @000: bipush 29 (0x1D)
		// @002: anewarray java.lang.String
		// @005: dup
		// @006: iconst_0
		// @007: ldc "]\u001bzwQ"
		// @009: invokestatic game.C_100206_qe.func_105936_z(java.lang.String)char[]
		// @00C: invokestatic game.C_100206_qe.func_105935_z(char[])java.lang.String
		// @00F: aastore
		// @010: dup
		// @011: iconst_1
		// @012: ldc "WPz\u0018\u0004"
		// @014: invokestatic game.C_100206_qe.func_105936_z(java.lang.String)char[]
		// @017: invokestatic game.C_100206_qe.func_105935_z(char[])java.lang.String
		// @01A: aastore
		// @01B: dup
		// @01C: iconst_2
		// @01D: ldc "O\n\u000bP\u0016^\u001b3D\u0016Y\u00100iI\u001f"
		// @01F: invokestatic game.C_100206_qe.func_105936_z(java.lang.String)char[]
		// @022: invokestatic game.C_100206_qe.func_105935_z(char[])java.lang.String
		// @025: aastore
		// @026: dup
		// @027: iconst_3
		// @028: ldc "_\n5D\u001a^\u000b=E\u001c^! Y\t"
		// @02A: invokestatic game.C_100206_qe.func_105936_z(java.lang.String)char[]
		// @02D: invokestatic game.C_100206_qe.func_105935_z(char[])java.lang.String
		// @030: aastore
		// @031: dup
		// @032: iconst_4
		// @033: ldc "_\u001c\u000bP\u0016^\u001b3D\u0016Y\u00100iI\u0019P$X\u001e"
		// @035: invokestatic game.C_100206_qe.func_105936_z(java.lang.String)char[]
		// @038: invokestatic game.C_100206_qe.func_105935_z(char[])java.lang.String
		// @03B: aastore
		// @03C: dup
		// @03D: iconst_5
		// @03E: ldc "O\n\u000bP\u0016^\u001b3D\u0016Y\u00100iI\u001d"
		// @040: invokestatic game.C_100206_qe.func_105936_z(java.lang.String)char[]
		// @043: invokestatic game.C_100206_qe.func_105935_z(char[])java.lang.String
		// @046: aastore
		// @047: dup
		// @048: bipush 6 (0x06)
		// @04A: ldc "O\n\u000bP\u0016^\u001b3D\u0016Y\u00100iI\u0018"
		// @04C: invokestatic game.C_100206_qe.func_105936_z(java.lang.String)char[]
		// @04F: invokestatic game.C_100206_qe.func_105935_z(char[])java.lang.String
		// @052: aastore
		// @053: dup
		// @054: bipush 7 (0x07)
		// @056: ldc "J\u00121S\rN\u001f B\u0015IQ"
		// @058: invokestatic game.C_100206_qe.func_105936_z(java.lang.String)char[]
		// @05B: invokestatic game.C_100206_qe.func_105935_z(char[])java.lang.String
		// @05E: aastore
		// @05F: dup
		// @060: bipush 8 (0x08)
		// @062: ldc "[\u0004\u000bP\u0016^\u001b3D\u0016Y\u00100iI\u001aP$X\u001e"
		// @064: invokestatic game.C_100206_qe.func_105936_z(java.lang.String)char[]
		// @067: invokestatic game.C_100206_qe.func_105935_z(char[])java.lang.String
		// @06A: aastore
		// @06B: dup
		// @06C: bipush 9 (0x09)
		// @06E: ldc "O\n\u000bP\u0016^\u001b3D\u0016Y\u00100iI\u001a"
		// @070: invokestatic game.C_100206_qe.func_105936_z(java.lang.String)char[]
		// @073: invokestatic game.C_100206_qe.func_105935_z(char[])java.lang.String
		// @076: aastore
		// @077: dup
		// @078: bipush 10 (0x0A)
		// @07A: ldc "O\n\u000bP\u0016^\u001b3D\u0016Y\u00100iI\u001e"
		// @07C: invokestatic game.C_100206_qe.func_105936_z(java.lang.String)char[]
		// @07F: invokestatic game.C_100206_qe.func_105935_z(char[])java.lang.String
		// @082: aastore
		// @083: dup
		// @084: bipush 11 (0x0B)
		// @086: ldc "[\u0004\u000bP\u0016^\u001b3D\u0016Y\u00100iI\u001bP$X\u001e"
		// @088: invokestatic game.C_100206_qe.func_105936_z(java.lang.String)char[]
		// @08B: invokestatic game.C_100206_qe.func_105935_z(char[])java.lang.String
		// @08E: aastore
		// @08F: dup
		// @090: bipush 12 (0x0C)
		// @092: ldc "O\n\u000bP\u0016^\u001b3D\u0016Y\u00100iI\u0019"
		// @094: invokestatic game.C_100206_qe.func_105936_z(java.lang.String)char[]
		// @097: invokestatic game.C_100206_qe.func_105935_z(char[])java.lang.String
		// @09A: aastore
		// @09B: dup
		// @09C: bipush 13 (0x0D)
		// @09E: ldc "B\u000b8Z"
		// @0A0: invokestatic game.C_100206_qe.func_105936_z(java.lang.String)char[]
		// @0A3: invokestatic game.C_100206_qe.func_105935_z(char[])java.lang.String
		// @0A6: aastore
		// @0A7: dup
		// @0A8: bipush 14 (0x0E)
		// @0AA: ldc "_\u001c\u000bP\u0016^\u001b3D\u0016Y\u00100iI\u001eP$X\u001e"
		// @0AC: invokestatic game.C_100206_qe.func_105936_z(java.lang.String)char[]
		// @0AF: invokestatic game.C_100206_qe.func_105935_z(char[])java.lang.String
		// @0B2: aastore
		// @0B3: dup
		// @0B4: bipush 15 (0x0F)
		// @0B6: ldc "[\u0004\u000bP\u0016^\u001b3D\u0016Y\u00100iI\u001dP$X\u001e"
		// @0B8: invokestatic game.C_100206_qe.func_105936_z(java.lang.String)char[]
		// @0BB: invokestatic game.C_100206_qe.func_105935_z(char[])java.lang.String
		// @0BE: aastore
		// @0BF: dup
		// @0C0: bipush 16 (0x10)
		// @0C2: ldc "N\u001f'_\u001a"
		// @0C4: invokestatic game.C_100206_qe.func_105936_z(java.lang.String)char[]
		// @0C7: invokestatic game.C_100206_qe.func_105935_z(char[])java.lang.String
		// @0CA: aastore
		// @0CB: dup
		// @0CC: bipush 17 (0x11)
		// @0CE: ldc "_\u001c\u000bP\u0016^\u001b3D\u0016Y\u00100iI\u001dP$X\u001e"
		// @0D0: invokestatic game.C_100206_qe.func_105936_z(java.lang.String)char[]
		// @0D3: invokestatic game.C_100206_qe.func_105935_z(char[])java.lang.String
		// @0D6: aastore
		// @0D7: dup
		// @0D8: bipush 18 (0x12)
		// @0DA: ldc "_\u001c\u000bP\u0016^\u001b3D\u0016Y\u00100iI\u001aP$X\u001e"
		// @0DC: invokestatic game.C_100206_qe.func_105936_z(java.lang.String)char[]
		// @0DF: invokestatic game.C_100206_qe.func_105935_z(char[])java.lang.String
		// @0E2: aastore
		// @0E3: dup
		// @0E4: bipush 19 (0x13)
		// @0E6: ldc "_\n5D\u001a^\u000b=E\u001c^!6W\nI"
		// @0E8: invokestatic game.C_100206_qe.func_105936_z(java.lang.String)char[]
		// @0EB: invokestatic game.C_100206_qe.func_105935_z(char[])java.lang.String
		// @0EE: aastore
		// @0EF: dup
		// @0F0: bipush 20 (0x14)
		// @0F2: ldc "[\u0004\u000bP\u0016^\u001b3D\u0016Y\u00100iI\u0019P$X\u001e"
		// @0F4: invokestatic game.C_100206_qe.func_105936_z(java.lang.String)char[]
		// @0F7: invokestatic game.C_100206_qe.func_105935_z(char[])java.lang.String
		// @0FA: aastore
		// @0FB: dup
		// @0FC: bipush 21 (0x15)
		// @0FE: ldc "[\u001f&L\u0016B\u001b{"
		// @100: invokestatic game.C_100206_qe.func_105936_z(java.lang.String)char[]
		// @103: invokestatic game.C_100206_qe.func_105935_z(char[])java.lang.String
		// @106: aastore
		// @107: dup
		// @108: bipush 22 (0x16)
		// @10A: ldc "[\u0004\u000bP\u0016^\u001b3D\u0016Y\u00100iI\u0018P$X\u001e"
		// @10C: invokestatic game.C_100206_qe.func_105936_z(java.lang.String)char[]
		// @10F: invokestatic game.C_100206_qe.func_105935_z(char[])java.lang.String
		// @112: aastore
		// @113: dup
		// @114: bipush 23 (0x17)
		// @116: ldc "_\u001c\u000bP\u0016^\u001b3D\u0016Y\u00100iI\u001fP$X\u001e"
		// @118: invokestatic game.C_100206_qe.func_105936_z(java.lang.String)char[]
		// @11B: invokestatic game.C_100206_qe.func_105935_z(char[])java.lang.String
		// @11E: aastore
		// @11F: dup
		// @120: bipush 24 (0x18)
		// @122: ldc "]\u001bztQ"
		// @124: invokestatic game.C_100206_qe.func_105936_z(java.lang.String)char[]
		// @127: invokestatic game.C_100206_qe.func_105935_z(char[])java.lang.String
		// @12A: aastore
		// @12B: dup
		// @12C: bipush 25 (0x19)
		// @12E: ldc "[\u0004\u000bP\u0016^\u001b3D\u0016Y\u00100iI\u001eP$X\u001e"
		// @130: invokestatic game.C_100206_qe.func_105936_z(java.lang.String)char[]
		// @133: invokestatic game.C_100206_qe.func_105935_z(char[])java.lang.String
		// @136: aastore
		// @137: dup
		// @138: bipush 26 (0x1A)
		// @13A: ldc "_\u001c\u000bP\u0016^\u001b3D\u0016Y\u00100iI\u0018P$X\u001e"
		// @13C: invokestatic game.C_100206_qe.func_105936_z(java.lang.String)char[]
		// @13F: invokestatic game.C_100206_qe.func_105935_z(char[])java.lang.String
		// @142: aastore
		// @143: dup
		// @144: bipush 27 (0x1B)
		// @146: ldc "[\u0004\u000bP\u0016^\u001b3D\u0016Y\u00100iI\u001fP$X\u001e"
		// @148: invokestatic game.C_100206_qe.func_105936_z(java.lang.String)char[]
		// @14B: invokestatic game.C_100206_qe.func_105935_z(char[])java.lang.String
		// @14E: aastore
		// @14F: dup
		// @150: bipush 28 (0x1C)
		// @152: ldc "]\u001bzuQ"
		// @154: invokestatic game.C_100206_qe.func_105936_z(java.lang.String)char[]
		// @157: invokestatic game.C_100206_qe.func_105935_z(char[])java.lang.String
		// @15A: aastore
		// @15B: putstatic java.lang.String[] game.C_100206_qe.field_105943_z
		// @15E: ldc "y\u000e0W\rI\rtA\u0010@\u0012tE\u001cB\ntB\u0016\u000c\n<SYI\u00135_\u0015\u000c\u001f0R\u000bI\r'\u0016\u0000C\u000bs@\u001c\u000c\u0019=@\u001cB"
		// @160: invokestatic game.C_100206_qe.func_105936_z(java.lang.String)char[]
		// @163: invokestatic game.C_100206_qe.func_105935_z(char[])java.lang.String
		// @166: putstatic java.lang.String game.C_100206_qe.field_105939_d
		// @169: ldc "u\u0011!DY^\u001b%C\u001c_\ntB\u0016\u000c\u0014;_\u0017\u000c\u00165EYN\u001b1XYH\u001b7Z\u0010B\u001b0\u0018"
		// @16B: invokestatic game.C_100206_qe.func_105936_z(java.lang.String)char[]
		// @16E: invokestatic game.C_100206_qe.func_105935_z(char[])java.lang.String
		// @171: putstatic java.lang.String game.C_100206_qe.field_105940_b
		// @174: ldc "a\u001f7D\u0016E\u00103\u0016\u0016^^!E\u001c\u000c\u00112\u0016\u001bC\n'"
		// @176: invokestatic game.C_100206_qe.func_105936_z(java.lang.String)char[]
		// @179: invokestatic game.C_100206_qe.func_105935_z(char[])java.lang.String
		// @17C: putstatic java.lang.String game.C_100206_qe.field_105942_a
		// @17F: return
	}
	
	private static char[] func_105936_z(String arg0)
	{
		// @00: aload_0
		// @01: invokevirtual java.lang.String.toCharArray()char[]
		// @04: dup
		// @05: arraylength
		// @06: iconst_2
		// @07: if_icmpge @13
		// @0A: dup
		// @0B: iconst_0
		// @0C: dup2
		// @0D: caload
		// @0E: bipush 121 (0x79)
		// @10: ixor
		// @11: i2c
		// @12: castore
		// @13: areturn
	}
	
	private static String func_105935_z(char[] arg0)
	{
		// @00: aload_0
		// @01: dup
		// @02: arraylength
		// @03: swap
		// @04: iconst_0
		// @05: istore_1
		// @06: goto @4C
		// @09: dup
		// @0A: iload_1
		// @0B: dup2
		// @0C: caload
		// @0D: iload_1
		// @0E: iconst_5
		// @0F: irem
		// @10: tableswitch def: @44, for 0: @30, for 1: @35, for 2: @3A, for 3: @3F
		// @30: bipush 44 (0x2C)
		// @32: goto @46
		// @35: bipush 126 (0x7E)
		// @37: goto @46
		// @3A: bipush 84 (0x54)
		// @3C: goto @46
		// @3F: bipush 54 (0x36)
		// @41: goto @46
		// @44: bipush 121 (0x79)
		// @46: ixor
		// @47: i2c
		// @48: castore
		// @49: iinc #1 +1
		// @4C: swap
		// @4D: dup_x1
		// @4E: iload_1
		// @4F: if_icmpgt @09
		// @52: new java.lang.String
		// @55: dup_x1
		// @56: swap
		// @57: invokespecial java.lang.String.<init>(char[])void
		// @5A: invokevirtual java.lang.String.intern()java.lang.String
		// @5D: areturn
	}
}
