package game;

final class C_100121_ud extends C_100158_da
{
	int field_100720_H;
	int field_100723_o;
	int field_100718_B;
	int field_100733_r;
	C_100132_td field_100738_x;
	int field_100736_z;
	int field_100719_C;
	C_100117_p field_100730_u;
	int field_100735_p;
	int field_100729_v;
	static C_100113_ek field_100715_F;
	int field_100728_w;
	int field_100724_l;
	int field_100725_m;
	int field_100732_s;
	int field_100717_A;
	int field_100722_n;
	static String field_100734_q;
	int field_100727_k;
	int field_100713_D;
	C_100236_on field_100726_j;
	int field_100737_y;
	C_100214_al field_100731_t;
	static boolean field_100716_G;
	static String field_100714_E;
	private static final String[] field_100721_I;
	
	public static void func_100709_d(byte arg0)
	{
		// @00: aconst_null
		// @01: putstatic game.C_100113_ek game.C_100121_ud.field_100715_F
		// @04: aconst_null
		// @05: putstatic java.lang.String game.C_100121_ud.field_100734_q
		// @08: iload_0
		// @09: bipush -93 (0xA3)
		// @0B: if_icmpeq @1A
		// @0E: bipush -61 (0xC3)
		// @10: bipush -36 (0xDC)
		// @12: invokestatic game.C_100121_ud.func_100708_b(int, byte)game.C_100219_an
		// @15: pop
		// @16: goto @1A
		// @19: athrow
		// @1A: aconst_null
		// @1B: putstatic java.lang.String game.C_100121_ud.field_100714_E
		// @1E: goto @42
		// @21: astore_1
		// @22: aload_1
		// @23: new java.lang.StringBuilder
		// @26: dup
		// @27: invokespecial java.lang.StringBuilder.<init>()void
		// @2A: getstatic java.lang.String[] game.C_100121_ud.field_100721_I
		// @2D: iconst_1
		// @2E: aaload
		// @2F: invokevirtual java.lang.StringBuilder.append(java.lang.String)java.lang.StringBuilder
		// @32: iload_0
		// @33: invokevirtual java.lang.StringBuilder.append(int)java.lang.StringBuilder
		// @36: bipush 41 (0x29)
		// @38: invokevirtual java.lang.StringBuilder.append(char)java.lang.StringBuilder
		// @3B: invokevirtual java.lang.StringBuilder.toString()java.lang.String
		// @3E: invokestatic game.C_100181_cf.func_105695_a(java.lang.Throwable, java.lang.String)game.C_100170_cm
		// @41: athrow
		// @42: return
	}
	
	static final C_100219_an func_100708_b(int arg0, byte arg1)
	{
		// @00: new game.C_100219_an
		// @03: dup
		// @04: invokespecial game.C_100219_an.<init>()void
		// @07: astore_2
		// @08: iload_1
		// @09: bipush 22 (0x16)
		// @0B: if_icmpge @19
		// @0E: aconst_null
		// @0F: checkcast game.C_100113_ek
		// @12: putstatic game.C_100113_ek game.C_100121_ud.field_100715_F
		// @15: goto @19
		// @18: athrow
		// @19: getstatic game.C_100202_qi game.C_100249_pc.field_102342_x
		// @1C: bipush 123 (0x7B)
		// @1E: aload_2
		// @1F: invokevirtual game.C_100202_qi.func_105901_a(int, game.C_100158_da)void
		// @22: iload_0
		// @23: bipush -69 (0xBB)
		// @25: invokestatic game.C_100298_ke.func_103204_c(int, byte)void
		// @28: aload_2
		// @29: areturn
		// @2A: astore_2
		// @2B: aload_2
		// @2C: new java.lang.StringBuilder
		// @2F: dup
		// @30: invokespecial java.lang.StringBuilder.<init>()void
		// @33: getstatic java.lang.String[] game.C_100121_ud.field_100721_I
		// @36: iconst_3
		// @37: aaload
		// @38: invokevirtual java.lang.StringBuilder.append(java.lang.String)java.lang.StringBuilder
		// @3B: iload_0
		// @3C: invokevirtual java.lang.StringBuilder.append(int)java.lang.StringBuilder
		// @3F: bipush 44 (0x2C)
		// @41: invokevirtual java.lang.StringBuilder.append(char)java.lang.StringBuilder
		// @44: iload_1
		// @45: invokevirtual java.lang.StringBuilder.append(int)java.lang.StringBuilder
		// @48: bipush 41 (0x29)
		// @4A: invokevirtual java.lang.StringBuilder.append(char)java.lang.StringBuilder
		// @4D: invokevirtual java.lang.StringBuilder.toString()java.lang.String
		// @50: invokestatic game.C_100181_cf.func_105695_a(java.lang.Throwable, java.lang.String)game.C_100170_cm
		// @53: athrow
	}
	
	static final boolean func_100707_a(byte arg0)
	{
		// @00: iload_0
		// @01: bipush 60 (0x3C)
		// @03: if_icmpeq @10
		// @06: bipush -62 (0xC2)
		// @08: invokestatic game.C_100121_ud.func_100707_a(byte)boolean
		// @0B: pop
		// @0C: goto @10
		// @0F: athrow
		// @10: bipush 25 (0x19)
		// @12: bipush 31 (0x1F)
		// @14: getstatic int[] game.C_100066_dl.field_101632_G
		// @17: invokestatic game.C_100189_ri.func_105742_a(int, int, int[])boolean
		// @1A: ireturn
		// @1B: astore_1
		// @1C: aload_1
		// @1D: new java.lang.StringBuilder
		// @20: dup
		// @21: invokespecial java.lang.StringBuilder.<init>()void
		// @24: getstatic java.lang.String[] game.C_100121_ud.field_100721_I
		// @27: iconst_0
		// @28: aaload
		// @29: invokevirtual java.lang.StringBuilder.append(java.lang.String)java.lang.StringBuilder
		// @2C: iload_0
		// @2D: invokevirtual java.lang.StringBuilder.append(int)java.lang.StringBuilder
		// @30: bipush 41 (0x29)
		// @32: invokevirtual java.lang.StringBuilder.append(char)java.lang.StringBuilder
		// @35: invokevirtual java.lang.StringBuilder.toString()java.lang.String
		// @38: invokestatic game.C_100181_cf.func_105695_a(java.lang.Throwable, java.lang.String)game.C_100170_cm
		// @3B: athrow
	}
	
	final void func_100712_c(byte arg0)
	{
		// @00: aload_0
		// @01: aconst_null
		// @02: putfield game.C_100132_td game.C_100121_ud.field_100738_x
		// @05: aload_0
		// @06: aconst_null
		// @07: putfield game.C_100236_on game.C_100121_ud.field_100726_j
		// @0A: aload_0
		// @0B: aconst_null
		// @0C: putfield game.C_100117_p game.C_100121_ud.field_100730_u
		// @0F: aload_0
		// @10: aconst_null
		// @11: putfield game.C_100214_al game.C_100121_ud.field_100731_t
		// @14: iload_1
		// @15: ifeq @1D
		// @18: bipush 66 (0x42)
		// @1A: invokestatic game.C_100121_ud.func_100709_d(byte)void
		// @1D: goto @41
		// @20: astore_2
		// @21: aload_2
		// @22: new java.lang.StringBuilder
		// @25: dup
		// @26: invokespecial java.lang.StringBuilder.<init>()void
		// @29: getstatic java.lang.String[] game.C_100121_ud.field_100721_I
		// @2C: iconst_2
		// @2D: aaload
		// @2E: invokevirtual java.lang.StringBuilder.append(java.lang.String)java.lang.StringBuilder
		// @31: iload_1
		// @32: invokevirtual java.lang.StringBuilder.append(int)java.lang.StringBuilder
		// @35: bipush 41 (0x29)
		// @37: invokevirtual java.lang.StringBuilder.append(char)java.lang.StringBuilder
		// @3A: invokevirtual java.lang.StringBuilder.toString()java.lang.String
		// @3D: invokestatic game.C_100181_cf.func_105695_a(java.lang.Throwable, java.lang.String)game.C_100170_cm
		// @40: athrow
		// @41: return
	}
	
	static
	{
		// @00: iconst_4
		// @01: anewarray java.lang.String
		// @04: dup
		// @05: iconst_0
		// @06: ldc " \tY\u001c\u0017"
		// @08: invokestatic game.C_100121_ud.func_100711_z(java.lang.String)char[]
		// @0B: invokestatic game.C_100121_ud.func_100710_z(char[])java.lang.String
		// @0E: aastore
		// @0F: dup
		// @10: iconst_1
		// @11: ldc " \tY\u001d\u0017"
		// @13: invokestatic game.C_100121_ud.func_100711_z(java.lang.String)char[]
		// @16: invokestatic game.C_100121_ud.func_100710_z(char[])java.lang.String
		// @19: aastore
		// @1A: dup
		// @1B: iconst_2
		// @1C: ldc " \tY\u001a\u0017"
		// @1E: invokestatic game.C_100121_ud.func_100711_z(java.lang.String)char[]
		// @21: invokestatic game.C_100121_ud.func_100710_z(char[])java.lang.String
		// @24: aastore
		// @25: dup
		// @26: iconst_3
		// @27: ldc " \tY\u001f\u0017"
		// @29: invokestatic game.C_100121_ud.func_100711_z(java.lang.String)char[]
		// @2C: invokestatic game.C_100121_ud.func_100710_z(char[])java.lang.String
		// @2F: aastore
		// @30: putstatic java.lang.String[] game.C_100121_ud.field_100721_I
		// @33: ldc "\u0016\":\u000ep\u001b(9\nl"
		// @35: invokestatic game.C_100121_ud.func_100711_z(java.lang.String)char[]
		// @38: invokestatic game.C_100121_ud.func_100710_z(char[])java.lang.String
		// @3B: putstatic java.lang.String game.C_100121_ud.field_100734_q
		// @3E: new game.C_100113_ek
		// @41: dup
		// @42: ldc "0\u0000\u00167S"
		// @44: invokestatic game.C_100121_ud.func_100711_z(java.lang.String)char[]
		// @47: invokestatic game.C_100121_ud.func_100710_z(char[])java.lang.String
		// @4A: invokespecial game.C_100113_ek.<init>(java.lang.String)void
		// @4D: putstatic game.C_100113_ek game.C_100121_ud.field_100715_F
		// @50: iconst_1
		// @51: putstatic boolean game.C_100121_ud.field_100716_G
		// @54: ldc "\u001d\u0008\u0016:\u001f&\u0001\u0018*"
		// @56: invokestatic game.C_100121_ud.func_100711_z(java.lang.String)char[]
		// @59: invokestatic game.C_100121_ud.func_100710_z(char[])java.lang.String
		// @5C: putstatic java.lang.String game.C_100121_ud.field_100714_E
		// @5F: return
	}
	
	private static char[] func_100711_z(String arg0)
	{
		// @00: aload_0
		// @01: invokevirtual java.lang.String.toCharArray()char[]
		// @04: dup
		// @05: arraylength
		// @06: iconst_2
		// @07: if_icmpge @13
		// @0A: dup
		// @0B: iconst_0
		// @0C: dup2
		// @0D: caload
		// @0E: bipush 63 (0x3F)
		// @10: ixor
		// @11: i2c
		// @12: castore
		// @13: areturn
	}
	
	private static String func_100710_z(char[] arg0)
	{
		// @00: aload_0
		// @01: dup
		// @02: arraylength
		// @03: swap
		// @04: iconst_0
		// @05: istore_1
		// @06: goto @4C
		// @09: dup
		// @0A: iload_1
		// @0B: dup2
		// @0C: caload
		// @0D: iload_1
		// @0E: iconst_5
		// @0F: irem
		// @10: tableswitch def: @44, for 0: @30, for 1: @35, for 2: @3A, for 3: @3F
		// @30: bipush 85 (0x55)
		// @32: goto @46
		// @35: bipush 109 (0x6D)
		// @37: goto @46
		// @3A: bipush 119 (0x77)
		// @3C: goto @46
		// @3F: bipush 94 (0x5E)
		// @41: goto @46
		// @44: bipush 63 (0x3F)
		// @46: ixor
		// @47: i2c
		// @48: castore
		// @49: iinc #1 +1
		// @4C: swap
		// @4D: dup_x1
		// @4E: iload_1
		// @4F: if_icmpgt @09
		// @52: new java.lang.String
		// @55: dup_x1
		// @56: swap
		// @57: invokespecial java.lang.String.<init>(char[])void
		// @5A: invokevirtual java.lang.String.intern()java.lang.String
		// @5D: areturn
	}
}
