package game;

final class C_100045_vj extends C_100158_da
{
	int field_100606_n;
	static C_100153_be[] field_100608_l;
	int field_100613_u;
	int field_100618_p;
	static C_100112_r field_100609_m;
	int[] field_100617_q;
	static int field_100607_o;
	static String field_100612_v;
	int field_100615_s;
	int field_100610_j;
	static String field_100611_k;
	int field_100614_t;
	static String field_100616_r;
	private static final String[] field_100619_z;
	
	static final void func_100600_a(C_100302_ka arg0, C_100302_ka arg1, C_100302_ka arg2, byte arg3, C_100302_ka arg4)
	{
		// @000: getstatic int game.SteelSentinels.field_105275_O
		// @003: istore #7
		// @005: aconst_null
		// @006: getstatic game.C_100302_ka game.C_100266_me.field_106650_d
		// @009: if_acmpeq @00D
		// @00C: return
		// @00D: iconst_0
		// @00E: putstatic boolean game.C_100230_of.field_106216_k
		// @011: bipush 106 (0x6A)
		// @013: bipush -33 (0xDF)
		// @015: iload_3
		// @016: isub
		// @017: bipush 47 (0x2F)
		// @019: idiv
		// @01A: idiv
		// @01B: istore #6
		// @01D: getstatic boolean game.C_100272_mn.field_102435_K
		// @020: ifne @041
		// @023: getstatic boolean game.C_100164_se.field_105449_g
		// @026: ifne @037
		// @029: goto @02D
		// @02C: athrow
		// @02D: getstatic java.lang.String game.C_100071_va.field_101662_w
		// @030: astore #5
		// @032: iload #7
		// @034: ifeq @046
		// @037: getstatic java.lang.String game.C_100287_nm.field_106824_d
		// @03A: astore #5
		// @03C: iload #7
		// @03E: ifeq @046
		// @041: getstatic java.lang.String game.C_100108_ee.field_100391_h
		// @044: astore #5
		// @046: iconst_0
		// @047: aconst_null
		// @048: aload #5
		// @04A: getstatic int game.C_100273_mm.field_106679_f
		// @04D: iconst_1
		// @04E: invokestatic game.C_100068_vc.func_104339_a(int, java.lang.String, java.lang.String, int, boolean)void
		// @051: getstatic game.C_100302_ka game.C_100235_om.field_106296_j
		// @054: getstatic int game.C_100273_mm.field_106679_f
		// @057: ldc 8355711 (0x7f7f7f)
		// @059: getstatic int game.C_100273_mm.field_106679_f
		// @05C: ldc 2068179553 (0x7b45ea61)
		// @05E: ishr
		// @05F: iand
		// @060: isub
		// @061: getstatic game.C_100302_ka game.C_100114_q.field_100494_y
		// @064: getfield int game.C_100302_ka.field_101860_K
		// @067: ldc -2024736095 (0x8750faa1)
		// @069: ishr
		// @06A: ldc 8355711 (0x7f7f7f)
		// @06C: iand
		// @06D: iadd
		// @06E: putfield int game.C_100302_ka.field_101860_K
		// @071: getstatic game.C_100302_ka game.C_100235_om.field_106296_j
		// @074: putstatic game.C_100302_ka game.C_100266_me.field_106650_d
		// @077: getstatic game.C_100302_ka game.C_100127_tl.field_104946_d
		// @07A: putstatic game.C_100302_ka game.C_100152_bd.field_105207_m
		// @07D: getstatic game.C_100302_ka game.C_100235_om.field_106296_j
		// @080: ldc 8355711 (0x7f7f7f)
		// @082: getstatic int game.C_100273_mm.field_106679_f
		// @085: ldc 1063999137 (0x3f6b56a1)
		// @087: ishr
		// @088: iand
		// @089: ineg
		// @08A: getstatic int game.C_100273_mm.field_106679_f
		// @08D: getstatic game.C_100302_ka game.C_100114_q.field_100494_y
		// @090: getfield int game.C_100302_ka.field_101872_Nb
		// @093: ldc 16711423 (0xfefeff)
		// @095: iand
		// @096: ldc 144798625 (0x8a173a1)
		// @098: ishr
		// @099: ineg
		// @09A: isub
		// @09B: iadd
		// @09C: putfield int game.C_100302_ka.field_101872_Nb
		// @09F: getstatic game.C_100302_ka game.C_100235_om.field_106296_j
		// @0A2: ldc 16711423 (0xfefeff)
		// @0A4: getstatic game.C_100302_ka game.C_100114_q.field_100494_y
		// @0A7: getfield int game.C_100302_ka.field_101868_Ab
		// @0AA: iand
		// @0AB: ldc -1061585023 (0xc0b97f81)
		// @0AD: ishr
		// @0AE: getstatic int game.C_100273_mm.field_106679_f
		// @0B1: getstatic int game.C_100273_mm.field_106679_f
		// @0B4: ldc 1785851713 (0x6a71ef41)
		// @0B6: ishr
		// @0B7: ldc 8355711 (0x7f7f7f)
		// @0B9: iand
		// @0BA: ineg
		// @0BB: iadd
		// @0BC: iadd
		// @0BD: putfield int game.C_100302_ka.field_101868_Ab
		// @0C0: new game.C_100302_ka
		// @0C3: dup
		// @0C4: lconst_0
		// @0C5: aload_0
		// @0C6: invokespecial game.C_100302_ka.<init>(long, game.C_100302_ka)void
		// @0C9: putstatic game.C_100302_ka game.C_100154_sl.field_105332_e
		// @0CC: new game.C_100302_ka
		// @0CF: dup
		// @0D0: lconst_0
		// @0D1: aload_1
		// @0D2: invokespecial game.C_100302_ka.<init>(long, game.C_100302_ka)void
		// @0D5: putstatic game.C_100302_ka game.C_100146_bf.field_105127_a
		// @0D8: new game.C_100302_ka
		// @0DB: dup
		// @0DC: lconst_0
		// @0DD: aconst_null
		// @0DE: invokespecial game.C_100302_ka.<init>(long, game.C_100302_ka)void
		// @0E1: putstatic game.C_100302_ka game.C_100018_wk.field_101531_T
		// @0E4: new game.C_100302_ka
		// @0E7: dup
		// @0E8: lconst_0
		// @0E9: aload_2
		// @0EA: invokespecial game.C_100302_ka.<init>(long, game.C_100302_ka)void
		// @0ED: putstatic game.C_100302_ka game.C_100210_qa.field_101054_C
		// @0F0: new game.C_100302_ka
		// @0F3: dup
		// @0F4: lconst_0
		// @0F5: aload #4
		// @0F7: invokespecial game.C_100302_ka.<init>(long, game.C_100302_ka)void
		// @0FA: putstatic game.C_100302_ka game.C_100235_om.field_106296_j
		// @0FD: getstatic game.C_100302_ka game.C_100235_om.field_106296_j
		// @100: getstatic game.C_100112_r game.C_100053_vn.field_102827_cb
		// @103: putfield game.C_100112_r game.C_100302_ka.field_101845_sb
		// @106: getstatic game.C_100302_ka game.C_100210_qa.field_101054_C
		// @109: bipush -112 (0x90)
		// @10B: getstatic game.C_100302_ka game.C_100235_om.field_106296_j
		// @10E: invokevirtual game.C_100302_ka.func_101824_b(int, game.C_100302_ka)void
		// @111: new game.C_100302_ka
		// @114: dup
		// @115: lconst_0
		// @116: getstatic game.C_100302_ka game.C_100152_bd.field_105207_m
		// @119: invokespecial game.C_100302_ka.<init>(long, game.C_100302_ka)void
		// @11C: putstatic game.C_100302_ka game.C_100127_tl.field_104946_d
		// @11F: getstatic game.C_100302_ka game.C_100210_qa.field_101054_C
		// @122: bipush -76 (0xB4)
		// @124: getstatic game.C_100302_ka game.C_100127_tl.field_104946_d
		// @127: invokevirtual game.C_100302_ka.func_101824_b(int, game.C_100302_ka)void
		// @12A: new game.C_100302_ka
		// @12D: dup
		// @12E: lconst_0
		// @12F: getstatic game.C_100302_ka game.C_100114_q.field_100494_y
		// @132: getstatic java.lang.String game.C_100328_ia.field_107255_f
		// @135: invokespecial game.C_100302_ka.<init>(long, game.C_100302_ka, java.lang.String)void
		// @138: putstatic game.C_100302_ka game.C_100291_jj.field_106874_d
		// @13B: new game.C_100302_ka
		// @13E: dup
		// @13F: lconst_0
		// @140: getstatic game.C_100302_ka game.C_100114_q.field_100494_y
		// @143: invokespecial game.C_100302_ka.<init>(long, game.C_100302_ka)void
		// @146: putstatic game.C_100302_ka game.C_100032_gk.field_103140_X
		// @149: getstatic game.C_100302_ka game.C_100154_sl.field_105332_e
		// @14C: bipush -96 (0xA0)
		// @14E: getstatic game.C_100302_ka game.C_100146_bf.field_105127_a
		// @151: invokevirtual game.C_100302_ka.func_101824_b(int, game.C_100302_ka)void
		// @154: getstatic game.C_100302_ka game.C_100154_sl.field_105332_e
		// @157: bipush -85 (0xAB)
		// @159: getstatic game.C_100302_ka game.C_100018_wk.field_101531_T
		// @15C: invokevirtual game.C_100302_ka.func_101824_b(int, game.C_100302_ka)void
		// @15F: getstatic game.C_100302_ka game.C_100018_wk.field_101531_T
		// @162: bipush -105 (0x97)
		// @164: getstatic game.C_100302_ka game.C_100210_qa.field_101054_C
		// @167: invokevirtual game.C_100302_ka.func_101824_b(int, game.C_100302_ka)void
		// @16A: getstatic game.C_100302_ka game.C_100018_wk.field_101531_T
		// @16D: bipush -89 (0xA7)
		// @16F: getstatic game.C_100302_ka game.C_100291_jj.field_106874_d
		// @172: invokevirtual game.C_100302_ka.func_101824_b(int, game.C_100302_ka)void
		// @175: getstatic game.C_100302_ka game.C_100018_wk.field_101531_T
		// @178: bipush -118 (0x8A)
		// @17A: getstatic game.C_100302_ka game.C_100032_gk.field_103140_X
		// @17D: invokevirtual game.C_100302_ka.func_101824_b(int, game.C_100302_ka)void
		// @180: goto @20F
		// @183: astore #5
		// @185: aload #5
		// @187: new java.lang.StringBuilder
		// @18A: dup
		// @18B: invokespecial java.lang.StringBuilder.<init>()void
		// @18E: getstatic java.lang.String[] game.C_100045_vj.field_100619_z
		// @191: iconst_3
		// @192: aaload
		// @193: invokevirtual java.lang.StringBuilder.append(java.lang.String)java.lang.StringBuilder
		// @196: aload_0
		// @197: ifnull @1A3
		// @19A: getstatic java.lang.String[] game.C_100045_vj.field_100619_z
		// @19D: iconst_0
		// @19E: aaload
		// @19F: goto @1A8
		// @1A2: athrow
		// @1A3: getstatic java.lang.String[] game.C_100045_vj.field_100619_z
		// @1A6: iconst_1
		// @1A7: aaload
		// @1A8: invokevirtual java.lang.StringBuilder.append(java.lang.String)java.lang.StringBuilder
		// @1AB: bipush 44 (0x2C)
		// @1AD: invokevirtual java.lang.StringBuilder.append(char)java.lang.StringBuilder
		// @1B0: aload_1
		// @1B1: ifnull @1BD
		// @1B4: getstatic java.lang.String[] game.C_100045_vj.field_100619_z
		// @1B7: iconst_0
		// @1B8: aaload
		// @1B9: goto @1C2
		// @1BC: athrow
		// @1BD: getstatic java.lang.String[] game.C_100045_vj.field_100619_z
		// @1C0: iconst_1
		// @1C1: aaload
		// @1C2: invokevirtual java.lang.StringBuilder.append(java.lang.String)java.lang.StringBuilder
		// @1C5: bipush 44 (0x2C)
		// @1C7: invokevirtual java.lang.StringBuilder.append(char)java.lang.StringBuilder
		// @1CA: aload_2
		// @1CB: ifnull @1D7
		// @1CE: getstatic java.lang.String[] game.C_100045_vj.field_100619_z
		// @1D1: iconst_0
		// @1D2: aaload
		// @1D3: goto @1DC
		// @1D6: athrow
		// @1D7: getstatic java.lang.String[] game.C_100045_vj.field_100619_z
		// @1DA: iconst_1
		// @1DB: aaload
		// @1DC: invokevirtual java.lang.StringBuilder.append(java.lang.String)java.lang.StringBuilder
		// @1DF: bipush 44 (0x2C)
		// @1E1: invokevirtual java.lang.StringBuilder.append(char)java.lang.StringBuilder
		// @1E4: iload_3
		// @1E5: invokevirtual java.lang.StringBuilder.append(int)java.lang.StringBuilder
		// @1E8: bipush 44 (0x2C)
		// @1EA: invokevirtual java.lang.StringBuilder.append(char)java.lang.StringBuilder
		// @1ED: aload #4
		// @1EF: ifnull @1FB
		// @1F2: getstatic java.lang.String[] game.C_100045_vj.field_100619_z
		// @1F5: iconst_0
		// @1F6: aaload
		// @1F7: goto @200
		// @1FA: athrow
		// @1FB: getstatic java.lang.String[] game.C_100045_vj.field_100619_z
		// @1FE: iconst_1
		// @1FF: aaload
		// @200: invokevirtual java.lang.StringBuilder.append(java.lang.String)java.lang.StringBuilder
		// @203: bipush 41 (0x29)
		// @205: invokevirtual java.lang.StringBuilder.append(char)java.lang.StringBuilder
		// @208: invokevirtual java.lang.StringBuilder.toString()java.lang.String
		// @20B: invokestatic game.C_100181_cf.func_105695_a(java.lang.Throwable, java.lang.String)game.C_100170_cm
		// @20E: athrow
		// @20F: return
	}
	
	static final boolean func_100601_a(byte arg0)
	{
		// @00: iload_0
		// @01: bipush -124 (0x84)
		// @03: if_icmpeq @11
		// @06: aconst_null
		// @07: checkcast java.lang.String
		// @0A: putstatic java.lang.String game.C_100045_vj.field_100611_k
		// @0D: goto @11
		// @10: athrow
		// @11: getstatic int game.C_100283_ni.field_106760_c
		// @14: iconst_m1
		// @15: ixor
		// @16: bipush -21 (0xEB)
		// @18: if_icmpgt @40
		// @1B: iload_0
		// @1C: sipush 29844 (0x7494)
		// @1F: ixor
		// @20: invokestatic game.C_100023_hg.func_103909_c(int)boolean
		// @23: ifeq @40
		// @26: goto @2A
		// @29: athrow
		// @2A: getstatic int game.C_100300_kc.field_107071_c
		// @2D: ifle @45
		// @30: goto @34
		// @33: athrow
		// @34: bipush -112 (0x90)
		// @36: invokestatic game.C_100069_vb.func_104350_a(byte)boolean
		// @39: ifne @45
		// @3C: goto @40
		// @3F: athrow
		// @40: iconst_1
		// @41: goto @46
		// @44: athrow
		// @45: iconst_0
		// @46: ireturn
		// @47: astore_1
		// @48: aload_1
		// @49: new java.lang.StringBuilder
		// @4C: dup
		// @4D: invokespecial java.lang.StringBuilder.<init>()void
		// @50: getstatic java.lang.String[] game.C_100045_vj.field_100619_z
		// @53: iconst_5
		// @54: aaload
		// @55: invokevirtual java.lang.StringBuilder.append(java.lang.String)java.lang.StringBuilder
		// @58: iload_0
		// @59: invokevirtual java.lang.StringBuilder.append(int)java.lang.StringBuilder
		// @5C: bipush 41 (0x29)
		// @5E: invokevirtual java.lang.StringBuilder.append(char)java.lang.StringBuilder
		// @61: invokevirtual java.lang.StringBuilder.toString()java.lang.String
		// @64: invokestatic game.C_100181_cf.func_105695_a(java.lang.Throwable, java.lang.String)game.C_100170_cm
		// @67: athrow
	}
	
	public static void func_100605_e(int arg0)
	{
		// @00: aconst_null
		// @01: putstatic java.lang.String game.C_100045_vj.field_100611_k
		// @04: aconst_null
		// @05: putstatic java.lang.String game.C_100045_vj.field_100616_r
		// @08: aconst_null
		// @09: putstatic game.C_100153_be[] game.C_100045_vj.field_100608_l
		// @0C: aconst_null
		// @0D: putstatic game.C_100112_r game.C_100045_vj.field_100609_m
		// @10: bipush -106 (0x96)
		// @12: iload_0
		// @13: bipush 54 (0x36)
		// @15: isub
		// @16: bipush 56 (0x38)
		// @18: idiv
		// @19: idiv
		// @1A: istore_1
		// @1B: aconst_null
		// @1C: putstatic java.lang.String game.C_100045_vj.field_100612_v
		// @1F: goto @43
		// @22: astore_1
		// @23: aload_1
		// @24: new java.lang.StringBuilder
		// @27: dup
		// @28: invokespecial java.lang.StringBuilder.<init>()void
		// @2B: getstatic java.lang.String[] game.C_100045_vj.field_100619_z
		// @2E: iconst_4
		// @2F: aaload
		// @30: invokevirtual java.lang.StringBuilder.append(java.lang.String)java.lang.StringBuilder
		// @33: iload_0
		// @34: invokevirtual java.lang.StringBuilder.append(int)java.lang.StringBuilder
		// @37: bipush 41 (0x29)
		// @39: invokevirtual java.lang.StringBuilder.append(char)java.lang.StringBuilder
		// @3C: invokevirtual java.lang.StringBuilder.toString()java.lang.String
		// @3F: invokestatic game.C_100181_cf.func_105695_a(java.lang.Throwable, java.lang.String)game.C_100170_cm
		// @42: athrow
		// @43: return
	}
	
	final void func_100602_a(int arg0, int arg1, int arg2, boolean arg3, int[] arg4, int arg5, int arg6, int arg7)
	{
		// @00: aload_0
		// @01: iload_1
		// @02: putfield int game.C_100045_vj.field_100615_s
		// @05: aload_0
		// @06: iload #7
		// @08: putfield int game.C_100045_vj.field_100606_n
		// @0B: aload_0
		// @0C: iload #6
		// @0E: putfield int game.C_100045_vj.field_100613_u
		// @11: aload_0
		// @12: aload #5
		// @14: putfield int[] game.C_100045_vj.field_100617_q
		// @17: iload #4
		// @19: iconst_1
		// @1A: if_icmpeq @29
		// @1D: aload_0
		// @1E: aconst_null
		// @1F: checkcast int[]
		// @22: putfield int[] game.C_100045_vj.field_100617_q
		// @25: goto @29
		// @28: athrow
		// @29: aload_0
		// @2A: iload_2
		// @2B: putfield int game.C_100045_vj.field_100610_j
		// @2E: aload_0
		// @2F: iload_3
		// @30: putfield int game.C_100045_vj.field_100618_p
		// @33: aload_0
		// @34: iload #8
		// @36: putfield int game.C_100045_vj.field_100614_t
		// @39: goto @B4
		// @3C: astore #9
		// @3E: aload #9
		// @40: new java.lang.StringBuilder
		// @43: dup
		// @44: invokespecial java.lang.StringBuilder.<init>()void
		// @47: getstatic java.lang.String[] game.C_100045_vj.field_100619_z
		// @4A: iconst_2
		// @4B: aaload
		// @4C: invokevirtual java.lang.StringBuilder.append(java.lang.String)java.lang.StringBuilder
		// @4F: iload_1
		// @50: invokevirtual java.lang.StringBuilder.append(int)java.lang.StringBuilder
		// @53: bipush 44 (0x2C)
		// @55: invokevirtual java.lang.StringBuilder.append(char)java.lang.StringBuilder
		// @58: iload_2
		// @59: invokevirtual java.lang.StringBuilder.append(int)java.lang.StringBuilder
		// @5C: bipush 44 (0x2C)
		// @5E: invokevirtual java.lang.StringBuilder.append(char)java.lang.StringBuilder
		// @61: iload_3
		// @62: invokevirtual java.lang.StringBuilder.append(int)java.lang.StringBuilder
		// @65: bipush 44 (0x2C)
		// @67: invokevirtual java.lang.StringBuilder.append(char)java.lang.StringBuilder
		// @6A: iload #4
		// @6C: invokevirtual java.lang.StringBuilder.append(boolean)java.lang.StringBuilder
		// @6F: bipush 44 (0x2C)
		// @71: invokevirtual java.lang.StringBuilder.append(char)java.lang.StringBuilder
		// @74: aload #5
		// @76: ifnull @82
		// @79: getstatic java.lang.String[] game.C_100045_vj.field_100619_z
		// @7C: iconst_0
		// @7D: aaload
		// @7E: goto @87
		// @81: athrow
		// @82: getstatic java.lang.String[] game.C_100045_vj.field_100619_z
		// @85: iconst_1
		// @86: aaload
		// @87: invokevirtual java.lang.StringBuilder.append(java.lang.String)java.lang.StringBuilder
		// @8A: bipush 44 (0x2C)
		// @8C: invokevirtual java.lang.StringBuilder.append(char)java.lang.StringBuilder
		// @8F: iload #6
		// @91: invokevirtual java.lang.StringBuilder.append(int)java.lang.StringBuilder
		// @94: bipush 44 (0x2C)
		// @96: invokevirtual java.lang.StringBuilder.append(char)java.lang.StringBuilder
		// @99: iload #7
		// @9B: invokevirtual java.lang.StringBuilder.append(int)java.lang.StringBuilder
		// @9E: bipush 44 (0x2C)
		// @A0: invokevirtual java.lang.StringBuilder.append(char)java.lang.StringBuilder
		// @A3: iload #8
		// @A5: invokevirtual java.lang.StringBuilder.append(int)java.lang.StringBuilder
		// @A8: bipush 41 (0x29)
		// @AA: invokevirtual java.lang.StringBuilder.append(char)java.lang.StringBuilder
		// @AD: invokevirtual java.lang.StringBuilder.toString()java.lang.String
		// @B0: invokestatic game.C_100181_cf.func_105695_a(java.lang.Throwable, java.lang.String)game.C_100170_cm
		// @B3: athrow
		// @B4: return
	}
	
	static
	{
		// @00: bipush 6 (0x06)
		// @02: anewarray java.lang.String
		// @05: dup
		// @06: iconst_0
		// @07: ldc "Rw\u00136#"
		// @09: invokestatic game.C_100045_vj.func_100604_z(java.lang.String)char[]
		// @0C: invokestatic game.C_100045_vj.func_100603_z(char[])java.lang.String
		// @0F: aastore
		// @10: dup
		// @11: iconst_1
		// @12: ldc "G,Qt"
		// @14: invokestatic game.C_100045_vj.func_100604_z(java.lang.String)char[]
		// @17: invokestatic game.C_100045_vj.func_100603_z(char[])java.lang.String
		// @1A: aastore
		// @1B: dup
		// @1C: iconst_2
		// @1D: ldc "_3\u0013Yv"
		// @1F: invokestatic game.C_100045_vj.func_100604_z(java.lang.String)char[]
		// @22: invokestatic game.C_100045_vj.func_100603_z(char[])java.lang.String
		// @25: aastore
		// @26: dup
		// @27: iconst_3
		// @28: ldc "_3\u0013Zv"
		// @2A: invokestatic game.C_100045_vj.func_100604_z(java.lang.String)char[]
		// @2D: invokestatic game.C_100045_vj.func_100603_z(char[])java.lang.String
		// @30: aastore
		// @31: dup
		// @32: iconst_4
		// @33: ldc "_3\u0013[v"
		// @35: invokestatic game.C_100045_vj.func_100604_z(java.lang.String)char[]
		// @38: invokestatic game.C_100045_vj.func_100603_z(char[])java.lang.String
		// @3B: aastore
		// @3C: dup
		// @3D: iconst_5
		// @3E: ldc "_3\u0013\\v"
		// @40: invokestatic game.C_100045_vj.func_100604_z(java.lang.String)char[]
		// @43: invokestatic game.C_100045_vj.func_100603_z(char[])java.lang.String
		// @46: aastore
		// @47: putstatic java.lang.String[] game.C_100045_vj.field_100619_z
		// @4A: ldc "\u007f0Nq*\t-U}~h:^w+G-\u001dU?G8Z}3L7I8-L:Iq1GyRv~]1X83H0S8-@-X8*FyKq;^w"
		// @4C: invokestatic game.C_100045_vj.func_100604_z(java.lang.String)char[]
		// @4F: invokestatic game.C_100045_vj.func_100603_z(char[])java.lang.String
		// @52: putstatic java.lang.String game.C_100045_vj.field_100611_k
		// @55: ldc "|7[w,],Sy*L5D8*A<O}~^8N8?\t?R{+ZyMj1K5Xu~^1Tt;\t*Xl*@7Z88\\5Qk=[<Xv~D6Y}p\t\u0000Rm~J6Ht:\t-Oa~M0Ny<E0S\u007f~H7D83\\5Iq.E<\u001du1G0Iw,\t=Oq(L+N81[yJq0M6J8;G1\\v=L4Xv*Zu\u001dq8\t Rm~A8K}~H7D8;G8_t;Mu\u001dw,\t-Oa~HyYq8O<O}0]yO}-F5Hl7F7\u0013"
		// @57: invokestatic game.C_100045_vj.func_100604_z(java.lang.String)char[]
		// @5A: invokestatic game.C_100045_vj.func_100603_z(char[])java.lang.String
		// @5D: putstatic java.lang.String game.C_100045_vj.field_100612_v
		// @60: ldc "\u0001e\u0018(`\t)Qy'L+N8)H7I8*FyWw7Gp"
		// @62: invokestatic game.C_100045_vj.func_100604_z(java.lang.String)char[]
		// @65: invokestatic game.C_100045_vj.func_100603_z(char[])java.lang.String
		// @68: putstatic java.lang.String game.C_100045_vj.field_100616_r
		// @6B: return
	}
	
	private static char[] func_100604_z(String arg0)
	{
		// @00: aload_0
		// @01: invokevirtual java.lang.String.toCharArray()char[]
		// @04: dup
		// @05: arraylength
		// @06: iconst_2
		// @07: if_icmpge @13
		// @0A: dup
		// @0B: iconst_0
		// @0C: dup2
		// @0D: caload
		// @0E: bipush 94 (0x5E)
		// @10: ixor
		// @11: i2c
		// @12: castore
		// @13: areturn
	}
	
	private static String func_100603_z(char[] arg0)
	{
		// @00: aload_0
		// @01: dup
		// @02: arraylength
		// @03: swap
		// @04: iconst_0
		// @05: istore_1
		// @06: goto @4C
		// @09: dup
		// @0A: iload_1
		// @0B: dup2
		// @0C: caload
		// @0D: iload_1
		// @0E: iconst_5
		// @0F: irem
		// @10: tableswitch def: @44, for 0: @30, for 1: @35, for 2: @3A, for 3: @3F
		// @30: bipush 41 (0x29)
		// @32: goto @46
		// @35: bipush 89 (0x59)
		// @37: goto @46
		// @3A: bipush 61 (0x3D)
		// @3C: goto @46
		// @3F: bipush 24 (0x18)
		// @41: goto @46
		// @44: bipush 94 (0x5E)
		// @46: ixor
		// @47: i2c
		// @48: castore
		// @49: iinc #1 +1
		// @4C: swap
		// @4D: dup_x1
		// @4E: iload_1
		// @4F: if_icmpgt @09
		// @52: new java.lang.String
		// @55: dup_x1
		// @56: swap
		// @57: invokespecial java.lang.String.<init>(char[])void
		// @5A: invokevirtual java.lang.String.intern()java.lang.String
		// @5D: areturn
	}
}
