package game;

import java.applet.Applet;

abstract class C_100295_kh
{
	static String field_105295_n;
	int field_105303_s;
	int field_105298_m;
	static C_100302_ka field_105291_e;
	static String field_105306_p;
	int field_105300_k;
	int field_105297_l;
	int field_105301_h;
	static String field_105292_b;
	static String field_105294_a;
	int field_105304_r;
	static C_100034_gi[] field_105293_c;
	static C_100037_wb field_105302_i;
	static String field_105288_f;
	static long field_105305_q;
	static String field_105296_o;
	static int[] field_105290_d;
	static C_100115_ej field_105299_j;
	static String field_105289_g;
	private static final String[] field_105307_z;
	
	public static void func_105283_a(int arg0)
	{
		// @00: aconst_null
		// @01: putstatic int[] game.C_100295_kh.field_105290_d
		// @04: aconst_null
		// @05: putstatic java.lang.String game.C_100295_kh.field_105292_b
		// @08: aconst_null
		// @09: putstatic java.lang.String game.C_100295_kh.field_105306_p
		// @0C: aconst_null
		// @0D: putstatic java.lang.String game.C_100295_kh.field_105289_g
		// @10: aconst_null
		// @11: putstatic game.C_100115_ej game.C_100295_kh.field_105299_j
		// @14: aconst_null
		// @15: putstatic java.lang.String game.C_100295_kh.field_105294_a
		// @18: aconst_null
		// @19: putstatic game.C_100037_wb game.C_100295_kh.field_105302_i
		// @1C: iload_0
		// @1D: bipush -99 (0x9D)
		// @1F: if_icmple @2B
		// @22: bipush 114 (0x72)
		// @24: invokestatic game.C_100295_kh.func_105283_a(int)void
		// @27: goto @2B
		// @2A: athrow
		// @2B: aconst_null
		// @2C: putstatic game.C_100302_ka game.C_100295_kh.field_105291_e
		// @2F: aconst_null
		// @30: putstatic game.C_100034_gi[] game.C_100295_kh.field_105293_c
		// @33: aconst_null
		// @34: putstatic java.lang.String game.C_100295_kh.field_105288_f
		// @37: aconst_null
		// @38: putstatic java.lang.String game.C_100295_kh.field_105295_n
		// @3B: aconst_null
		// @3C: putstatic java.lang.String game.C_100295_kh.field_105296_o
		// @3F: goto @63
		// @42: astore_1
		// @43: aload_1
		// @44: new java.lang.StringBuilder
		// @47: dup
		// @48: invokespecial java.lang.StringBuilder.<init>()void
		// @4B: getstatic java.lang.String[] game.C_100295_kh.field_105307_z
		// @4E: iconst_0
		// @4F: aaload
		// @50: invokevirtual java.lang.StringBuilder.append(java.lang.String)java.lang.StringBuilder
		// @53: iload_0
		// @54: invokevirtual java.lang.StringBuilder.append(int)java.lang.StringBuilder
		// @57: bipush 41 (0x29)
		// @59: invokevirtual java.lang.StringBuilder.append(char)java.lang.StringBuilder
		// @5C: invokevirtual java.lang.StringBuilder.toString()java.lang.String
		// @5F: invokestatic game.C_100181_cf.func_105695_a(java.lang.Throwable, java.lang.String)game.C_100170_cm
		// @62: athrow
		// @63: return
	}
	
	abstract void func_105287_a(int arg0, int arg1, int arg2);
	
	static final void func_105282_a(int arg0, int arg1, byte arg2, int arg3, C_100112_r arg4, int arg5, int arg6, int arg7, int arg8, C_100037_wb[] arg9, int arg10, int arg11, C_100037_wb[] arg12, C_100037_wb[] arg13, int arg14)
	{
		// @000: iload_2
		// @001: bipush -111 (0x91)
		// @003: if_icmpeq @017
		// @006: bipush -116 (0x8C)
		// @008: aconst_null
		// @009: checkcast java.applet.Applet
		// @00C: aconst_null
		// @00D: checkcast java.lang.String
		// @010: invokestatic game.C_100295_kh.func_105280_a(byte, java.applet.Applet, java.lang.String)void
		// @013: goto @017
		// @016: athrow
		// @017: aload #4
		// @019: getfield int game.C_100112_r.field_101763_H
		// @01C: aload #4
		// @01E: getfield int game.C_100112_r.field_101769_u
		// @021: iadd
		// @022: istore #15
		// @024: aload #4
		// @026: getfield int game.C_100112_r.field_101769_u
		// @029: istore #16
		// @02B: aload #12
		// @02D: iload #5
		// @02F: iload #14
		// @031: aload #9
		// @033: iload #8
		// @035: iload #15
		// @037: iload #16
		// @039: bipush -128 (0x80)
		// @03B: iload #16
		// @03D: iload #11
		// @03F: aload #4
		// @041: iload #15
		// @043: iload #6
		// @045: iload #7
		// @047: iload_3
		// @048: iload_1
		// @049: iload_0
		// @04A: aload #4
		// @04C: iload #10
		// @04E: aload #13
		// @050: invokestatic game.C_100227_af.func_106159_a(game.C_100037_wb[], int, int, game.C_100037_wb[], int, int, int, byte, int, int, game.C_100112_r, int, int, int, int, int, int, game.C_100112_r, int, game.C_100037_wb[])void
		// @053: goto @146
		// @056: astore #15
		// @058: aload #15
		// @05A: new java.lang.StringBuilder
		// @05D: dup
		// @05E: invokespecial java.lang.StringBuilder.<init>()void
		// @061: getstatic java.lang.String[] game.C_100295_kh.field_105307_z
		// @064: iconst_1
		// @065: aaload
		// @066: invokevirtual java.lang.StringBuilder.append(java.lang.String)java.lang.StringBuilder
		// @069: iload_0
		// @06A: invokevirtual java.lang.StringBuilder.append(int)java.lang.StringBuilder
		// @06D: bipush 44 (0x2C)
		// @06F: invokevirtual java.lang.StringBuilder.append(char)java.lang.StringBuilder
		// @072: iload_1
		// @073: invokevirtual java.lang.StringBuilder.append(int)java.lang.StringBuilder
		// @076: bipush 44 (0x2C)
		// @078: invokevirtual java.lang.StringBuilder.append(char)java.lang.StringBuilder
		// @07B: iload_2
		// @07C: invokevirtual java.lang.StringBuilder.append(int)java.lang.StringBuilder
		// @07F: bipush 44 (0x2C)
		// @081: invokevirtual java.lang.StringBuilder.append(char)java.lang.StringBuilder
		// @084: iload_3
		// @085: invokevirtual java.lang.StringBuilder.append(int)java.lang.StringBuilder
		// @088: bipush 44 (0x2C)
		// @08A: invokevirtual java.lang.StringBuilder.append(char)java.lang.StringBuilder
		// @08D: aload #4
		// @08F: ifnull @09B
		// @092: getstatic java.lang.String[] game.C_100295_kh.field_105307_z
		// @095: iconst_3
		// @096: aaload
		// @097: goto @0A0
		// @09A: athrow
		// @09B: getstatic java.lang.String[] game.C_100295_kh.field_105307_z
		// @09E: iconst_2
		// @09F: aaload
		// @0A0: invokevirtual java.lang.StringBuilder.append(java.lang.String)java.lang.StringBuilder
		// @0A3: bipush 44 (0x2C)
		// @0A5: invokevirtual java.lang.StringBuilder.append(char)java.lang.StringBuilder
		// @0A8: iload #5
		// @0AA: invokevirtual java.lang.StringBuilder.append(int)java.lang.StringBuilder
		// @0AD: bipush 44 (0x2C)
		// @0AF: invokevirtual java.lang.StringBuilder.append(char)java.lang.StringBuilder
		// @0B2: iload #6
		// @0B4: invokevirtual java.lang.StringBuilder.append(int)java.lang.StringBuilder
		// @0B7: bipush 44 (0x2C)
		// @0B9: invokevirtual java.lang.StringBuilder.append(char)java.lang.StringBuilder
		// @0BC: iload #7
		// @0BE: invokevirtual java.lang.StringBuilder.append(int)java.lang.StringBuilder
		// @0C1: bipush 44 (0x2C)
		// @0C3: invokevirtual java.lang.StringBuilder.append(char)java.lang.StringBuilder
		// @0C6: iload #8
		// @0C8: invokevirtual java.lang.StringBuilder.append(int)java.lang.StringBuilder
		// @0CB: bipush 44 (0x2C)
		// @0CD: invokevirtual java.lang.StringBuilder.append(char)java.lang.StringBuilder
		// @0D0: aload #9
		// @0D2: ifnull @0DE
		// @0D5: getstatic java.lang.String[] game.C_100295_kh.field_105307_z
		// @0D8: iconst_3
		// @0D9: aaload
		// @0DA: goto @0E3
		// @0DD: athrow
		// @0DE: getstatic java.lang.String[] game.C_100295_kh.field_105307_z
		// @0E1: iconst_2
		// @0E2: aaload
		// @0E3: invokevirtual java.lang.StringBuilder.append(java.lang.String)java.lang.StringBuilder
		// @0E6: bipush 44 (0x2C)
		// @0E8: invokevirtual java.lang.StringBuilder.append(char)java.lang.StringBuilder
		// @0EB: iload #10
		// @0ED: invokevirtual java.lang.StringBuilder.append(int)java.lang.StringBuilder
		// @0F0: bipush 44 (0x2C)
		// @0F2: invokevirtual java.lang.StringBuilder.append(char)java.lang.StringBuilder
		// @0F5: iload #11
		// @0F7: invokevirtual java.lang.StringBuilder.append(int)java.lang.StringBuilder
		// @0FA: bipush 44 (0x2C)
		// @0FC: invokevirtual java.lang.StringBuilder.append(char)java.lang.StringBuilder
		// @0FF: aload #12
		// @101: ifnull @10D
		// @104: getstatic java.lang.String[] game.C_100295_kh.field_105307_z
		// @107: iconst_3
		// @108: aaload
		// @109: goto @112
		// @10C: athrow
		// @10D: getstatic java.lang.String[] game.C_100295_kh.field_105307_z
		// @110: iconst_2
		// @111: aaload
		// @112: invokevirtual java.lang.StringBuilder.append(java.lang.String)java.lang.StringBuilder
		// @115: bipush 44 (0x2C)
		// @117: invokevirtual java.lang.StringBuilder.append(char)java.lang.StringBuilder
		// @11A: aload #13
		// @11C: ifnull @128
		// @11F: getstatic java.lang.String[] game.C_100295_kh.field_105307_z
		// @122: iconst_3
		// @123: aaload
		// @124: goto @12D
		// @127: athrow
		// @128: getstatic java.lang.String[] game.C_100295_kh.field_105307_z
		// @12B: iconst_2
		// @12C: aaload
		// @12D: invokevirtual java.lang.StringBuilder.append(java.lang.String)java.lang.StringBuilder
		// @130: bipush 44 (0x2C)
		// @132: invokevirtual java.lang.StringBuilder.append(char)java.lang.StringBuilder
		// @135: iload #14
		// @137: invokevirtual java.lang.StringBuilder.append(int)java.lang.StringBuilder
		// @13A: bipush 41 (0x29)
		// @13C: invokevirtual java.lang.StringBuilder.append(char)java.lang.StringBuilder
		// @13F: invokevirtual java.lang.StringBuilder.toString()java.lang.String
		// @142: invokestatic game.C_100181_cf.func_105695_a(java.lang.Throwable, java.lang.String)game.C_100170_cm
		// @145: athrow
		// @146: return
	}
	
	static final void func_105280_a(byte arg0, Applet arg1, String arg2)
	{
		// @00: aload_2
		// @01: putstatic java.lang.String game.C_100314_lf.field_101303_Eb
		// @04: bipush 18 (0x12)
		// @06: iload_0
		// @07: bipush 30 (0x1E)
		// @09: isub
		// @0A: bipush 42 (0x2A)
		// @0C: idiv
		// @0D: irem
		// @0E: istore #4
		// @10: aload_1
		// @11: getstatic java.lang.String[] game.C_100295_kh.field_105307_z
		// @14: iconst_5
		// @15: aaload
		// @16: invokevirtual java.applet.Applet.getParameter(java.lang.String)java.lang.String
		// @19: astore_3
		// @1A: aload_1
		// @1B: getstatic java.lang.String[] game.C_100295_kh.field_105307_z
		// @1E: bipush 10 (0x0A)
		// @20: aaload
		// @21: invokevirtual java.applet.Applet.getParameter(java.lang.String)java.lang.String
		// @24: astore #5
		// @26: new java.lang.StringBuilder
		// @29: dup
		// @2A: invokespecial java.lang.StringBuilder.<init>()void
		// @2D: aload_3
		// @2E: invokevirtual java.lang.StringBuilder.append(java.lang.String)java.lang.StringBuilder
		// @31: getstatic java.lang.String[] game.C_100295_kh.field_105307_z
		// @34: bipush 8 (0x08)
		// @36: aaload
		// @37: invokevirtual java.lang.StringBuilder.append(java.lang.String)java.lang.StringBuilder
		// @3A: aload_2
		// @3B: invokevirtual java.lang.StringBuilder.append(java.lang.String)java.lang.StringBuilder
		// @3E: getstatic java.lang.String[] game.C_100295_kh.field_105307_z
		// @41: bipush 6 (0x06)
		// @43: aaload
		// @44: invokevirtual java.lang.StringBuilder.append(java.lang.String)java.lang.StringBuilder
		// @47: aload #5
		// @49: invokevirtual java.lang.StringBuilder.append(java.lang.String)java.lang.StringBuilder
		// @4C: invokevirtual java.lang.StringBuilder.toString()java.lang.String
		// @4F: astore #6
		// @51: iconst_m1
		// @52: aload_2
		// @53: invokevirtual java.lang.String.length()int
		// @56: iconst_m1
		// @57: ixor
		// @58: if_icmpne @75
		// @5B: new java.lang.StringBuilder
		// @5E: dup
		// @5F: invokespecial java.lang.StringBuilder.<init>()void
		// @62: aload #6
		// @64: invokevirtual java.lang.StringBuilder.append(java.lang.String)java.lang.StringBuilder
		// @67: getstatic java.lang.String[] game.C_100295_kh.field_105307_z
		// @6A: bipush 7 (0x07)
		// @6C: aaload
		// @6D: invokevirtual java.lang.StringBuilder.append(java.lang.String)java.lang.StringBuilder
		// @70: invokevirtual java.lang.StringBuilder.toString()java.lang.String
		// @73: astore #6
		// @75: new java.lang.StringBuilder
		// @78: dup
		// @79: invokespecial java.lang.StringBuilder.<init>()void
		// @7C: getstatic java.lang.String[] game.C_100295_kh.field_105307_z
		// @7F: iconst_4
		// @80: aaload
		// @81: invokevirtual java.lang.StringBuilder.append(java.lang.String)java.lang.StringBuilder
		// @84: aload #6
		// @86: invokevirtual java.lang.StringBuilder.append(java.lang.String)java.lang.StringBuilder
		// @89: ldc "\""
		// @8B: invokevirtual java.lang.StringBuilder.append(java.lang.String)java.lang.StringBuilder
		// @8E: invokevirtual java.lang.StringBuilder.toString()java.lang.String
		// @91: sipush -1492 (0xFA2C)
		// @94: aload_1
		// @95: invokestatic game.C_100175_cl.func_105615_a(java.lang.String, int, java.applet.Applet)void
		// @98: goto @9C
		// @9B: astore_3
		// @9C: iconst_0
		// @9D: aload_1
		// @9E: invokestatic game.C_100277_nc.func_106689_a(boolean, java.applet.Applet)void
		// @A1: goto @FA
		// @A4: astore_3
		// @A5: aload_3
		// @A6: new java.lang.StringBuilder
		// @A9: dup
		// @AA: invokespecial java.lang.StringBuilder.<init>()void
		// @AD: getstatic java.lang.String[] game.C_100295_kh.field_105307_z
		// @B0: bipush 9 (0x09)
		// @B2: aaload
		// @B3: invokevirtual java.lang.StringBuilder.append(java.lang.String)java.lang.StringBuilder
		// @B6: iload_0
		// @B7: invokevirtual java.lang.StringBuilder.append(int)java.lang.StringBuilder
		// @BA: bipush 44 (0x2C)
		// @BC: invokevirtual java.lang.StringBuilder.append(char)java.lang.StringBuilder
		// @BF: aload_1
		// @C0: ifnull @CC
		// @C3: getstatic java.lang.String[] game.C_100295_kh.field_105307_z
		// @C6: iconst_3
		// @C7: aaload
		// @C8: goto @D1
		// @CB: athrow
		// @CC: getstatic java.lang.String[] game.C_100295_kh.field_105307_z
		// @CF: iconst_2
		// @D0: aaload
		// @D1: invokevirtual java.lang.StringBuilder.append(java.lang.String)java.lang.StringBuilder
		// @D4: bipush 44 (0x2C)
		// @D6: invokevirtual java.lang.StringBuilder.append(char)java.lang.StringBuilder
		// @D9: aload_2
		// @DA: ifnull @E6
		// @DD: getstatic java.lang.String[] game.C_100295_kh.field_105307_z
		// @E0: iconst_3
		// @E1: aaload
		// @E2: goto @EB
		// @E5: athrow
		// @E6: getstatic java.lang.String[] game.C_100295_kh.field_105307_z
		// @E9: iconst_2
		// @EA: aaload
		// @EB: invokevirtual java.lang.StringBuilder.append(java.lang.String)java.lang.StringBuilder
		// @EE: bipush 41 (0x29)
		// @F0: invokevirtual java.lang.StringBuilder.append(char)java.lang.StringBuilder
		// @F3: invokevirtual java.lang.StringBuilder.toString()java.lang.String
		// @F6: invokestatic game.C_100181_cf.func_105695_a(java.lang.Throwable, java.lang.String)game.C_100170_cm
		// @F9: athrow
		// @FA: return
	}
	
	abstract void func_105286_a(int arg0, int arg1);
	
	static final boolean func_105281_a(boolean arg0)
	{
		// @00: iload_0
		// @01: iconst_1
		// @02: if_icmpeq @32
		// @05: bipush -58 (0xC6)
		// @07: bipush 36 (0x24)
		// @09: bipush -49 (0xCF)
		// @0B: bipush 115 (0x73)
		// @0D: aconst_null
		// @0E: checkcast game.C_100112_r
		// @11: bipush -3 (0xFD)
		// @13: bipush -12 (0xF4)
		// @15: bipush 16 (0x10)
		// @17: bipush 54 (0x36)
		// @19: aconst_null
		// @1A: checkcast game.C_100037_wb[]
		// @1D: bipush 33 (0x21)
		// @1F: bipush -54 (0xCA)
		// @21: aconst_null
		// @22: checkcast game.C_100037_wb[]
		// @25: aconst_null
		// @26: checkcast game.C_100037_wb[]
		// @29: bipush 89 (0x59)
		// @2B: invokestatic game.C_100295_kh.func_105282_a(int, int, byte, int, game.C_100112_r, int, int, int, int, game.C_100037_wb[], int, int, game.C_100037_wb[], game.C_100037_wb[], int)void
		// @2E: goto @32
		// @31: athrow
		// @32: getstatic game.C_100321_hi game.C_100106_ef.field_104753_e
		// @35: bipush -2 (0xFE)
		// @37: invokevirtual game.C_100321_hi.func_107211_b(int)boolean
		// @3A: ifne @42
		// @3D: iconst_1
		// @3E: goto @43
		// @41: athrow
		// @42: iconst_0
		// @43: ireturn
		// @44: astore_1
		// @45: aload_1
		// @46: new java.lang.StringBuilder
		// @49: dup
		// @4A: invokespecial java.lang.StringBuilder.<init>()void
		// @4D: getstatic java.lang.String[] game.C_100295_kh.field_105307_z
		// @50: bipush 11 (0x0B)
		// @52: aaload
		// @53: invokevirtual java.lang.StringBuilder.append(java.lang.String)java.lang.StringBuilder
		// @56: iload_0
		// @57: invokevirtual java.lang.StringBuilder.append(boolean)java.lang.StringBuilder
		// @5A: bipush 41 (0x29)
		// @5C: invokevirtual java.lang.StringBuilder.append(char)java.lang.StringBuilder
		// @5F: invokevirtual java.lang.StringBuilder.toString()java.lang.String
		// @62: invokestatic game.C_100181_cf.func_105695_a(java.lang.Throwable, java.lang.String)game.C_100170_cm
		// @65: athrow
	}
	
	static final void func_105278_a(int arg0, C_100280_nf arg1, int arg2, C_100201_qj arg3)
	{
		// @000: getstatic int game.SteelSentinels.field_105275_O
		// @003: istore #14
		// @005: new game.C_100167_sj
		// @008: dup
		// @009: invokespecial game.C_100167_sj.<init>()void
		// @00C: astore #4
		// @00E: aload #4
		// @010: aload_1
		// @011: iconst_0
		// @012: invokevirtual game.C_100280_nf.func_101156_c(boolean)int
		// @015: putfield int game.C_100167_sj.field_100800_y
		// @018: aload #4
		// @01A: aload_1
		// @01B: sipush -1543 (0xF9F9)
		// @01E: invokevirtual game.C_100280_nf.func_101171_e(int)int
		// @021: putfield int game.C_100167_sj.field_100792_v
		// @024: aload #4
		// @026: aload #4
		// @028: getfield int game.C_100167_sj.field_100800_y
		// @02B: newarray int[]
		// @02D: putfield int[] game.C_100167_sj.field_100790_k
		// @030: aload #4
		// @032: aload #4
		// @034: getfield int game.C_100167_sj.field_100800_y
		// @037: newarray int[]
		// @039: putfield int[] game.C_100167_sj.field_100789_j
		// @03C: aload #4
		// @03E: aload #4
		// @040: getfield int game.C_100167_sj.field_100800_y
		// @043: newarray int[]
		// @045: putfield int[] game.C_100167_sj.field_100787_l
		// @048: aload #4
		// @04A: aload #4
		// @04C: getfield int game.C_100167_sj.field_100800_y
		// @04F: anewarray game.C_100331_ie
		// @052: putfield game.C_100331_ie[] game.C_100167_sj.field_100798_p
		// @055: aload #4
		// @057: aload #4
		// @059: getfield int game.C_100167_sj.field_100800_y
		// @05C: anewarray game.C_100331_ie
		// @05F: putfield game.C_100331_ie[] game.C_100167_sj.field_100795_s
		// @062: aload #4
		// @064: aload #4
		// @066: getfield int game.C_100167_sj.field_100800_y
		// @069: anewarray byte[][]
		// @06C: putfield byte[][][] game.C_100167_sj.field_100785_n
		// @06F: iload_0
		// @070: bipush 60 (0x3C)
		// @072: if_icmpge @0A0
		// @075: bipush -66 (0xBE)
		// @077: bipush -106 (0x96)
		// @079: iconst_0
		// @07A: bipush -103 (0x99)
		// @07C: aconst_null
		// @07D: checkcast game.C_100112_r
		// @080: bipush -107 (0x95)
		// @082: bipush 76 (0x4C)
		// @084: bipush -63 (0xC1)
		// @086: bipush 108 (0x6C)
		// @088: aconst_null
		// @089: checkcast game.C_100037_wb[]
		// @08C: bipush -67 (0xBD)
		// @08E: bipush 86 (0x56)
		// @090: aconst_null
		// @091: checkcast game.C_100037_wb[]
		// @094: aconst_null
		// @095: checkcast game.C_100037_wb[]
		// @098: iconst_2
		// @099: invokestatic game.C_100295_kh.func_105282_a(int, int, byte, int, game.C_100112_r, int, int, int, int, game.C_100037_wb[], int, int, game.C_100037_wb[], game.C_100037_wb[], int)void
		// @09C: goto @0A0
		// @09F: athrow
		// @0A0: iconst_0
		// @0A1: istore #5
		// @0A3: aload #4
		// @0A5: getfield int game.C_100167_sj.field_100800_y
		// @0A8: iconst_m1
		// @0A9: ixor
		// @0AA: iload #5
		// @0AC: iconst_m1
		// @0AD: ixor
		// @0AE: if_icmpge @29D
		// @0B1: aload_1
		// @0B2: iconst_0
		// @0B3: invokevirtual game.C_100280_nf.func_101156_c(boolean)int
		// @0B6: istore #6
		// @0B8: iload #14
		// @0BA: ifne @2A7
		// @0BD: iconst_0
		// @0BE: iload #6
		// @0C0: if_icmpeq @1F8
		// @0C3: goto @0C7
		// @0C6: athrow
		// @0C7: iload #6
		// @0C9: iconst_1
		// @0CA: if_icmpeq @1F8
		// @0CD: goto @0D1
		// @0D0: athrow
		// @0D1: iload #6
		// @0D3: iconst_m1
		// @0D4: ixor
		// @0D5: bipush -3 (0xFD)
		// @0D7: if_icmpeq @1F8
		// @0DA: goto @0DE
		// @0DD: athrow
		// @0DE: iconst_3
		// @0DF: iload #6
		// @0E1: if_icmpeq @0F6
		// @0E4: goto @0E8
		// @0E7: athrow
		// @0E8: iconst_4
		// @0E9: iload #6
		// @0EB: if_icmpeq @0F6
		// @0EE: goto @0F2
		// @0F1: athrow
		// @0F2: goto @24B
		// @0F5: athrow
		// @0F6: aload_1
		// @0F7: sipush 9692 (0x25DC)
		// @0FA: invokevirtual game.C_100280_nf.func_101164_f(int)java.lang.String
		// @0FD: astore #7
		// @0FF: aload_1
		// @100: sipush 9692 (0x25DC)
		// @103: invokevirtual game.C_100280_nf.func_101164_f(int)java.lang.String
		// @106: astore #8
		// @108: aload_1
		// @109: iconst_0
		// @10A: invokevirtual game.C_100280_nf.func_101156_c(boolean)int
		// @10D: istore #9
		// @10F: iload #9
		// @111: anewarray java.lang.String
		// @114: astore #10
		// @116: iconst_0
		// @117: istore #11
		// @119: iload #11
		// @11B: iload #9
		// @11D: if_icmpge @13D
		// @120: aload #10
		// @122: iload #11
		// @124: aload_1
		// @125: sipush 9692 (0x25DC)
		// @128: invokevirtual game.C_100280_nf.func_101164_f(int)java.lang.String
		// @12B: aastore
		// @12C: iinc #11 +1
		// @12F: iload #14
		// @131: ifne @24B
		// @134: iload #14
		// @136: ifeq @119
		// @139: goto @13D
		// @13C: athrow
		// @13D: iload #9
		// @13F: anewarray byte[]
		// @142: astore #11
		// @144: iload #6
		// @146: iconst_m1
		// @147: ixor
		// @148: bipush -4 (0xFC)
		// @14A: if_icmpeq @151
		// @14D: goto @191
		// @150: athrow
		// @151: iconst_0
		// @152: istore #12
		// @154: iload #12
		// @156: iconst_m1
		// @157: ixor
		// @158: iload #9
		// @15A: iconst_m1
		// @15B: ixor
		// @15C: if_icmple @191
		// @15F: aload_1
		// @160: sipush -1543 (0xF9F9)
		// @163: invokevirtual game.C_100280_nf.func_101171_e(int)int
		// @166: istore #13
		// @168: aload #11
		// @16A: iload #12
		// @16C: iload #13
		// @16E: newarray byte[]
		// @170: aastore
		// @171: aload_1
		// @172: aload #11
		// @174: iload #12
		// @176: aaload
		// @177: iload #13
		// @179: iconst_0
		// @17A: sipush -7623 (0xE239)
		// @17D: invokevirtual game.C_100280_nf.func_101149_a(byte[], int, int, int)void
		// @180: iinc #12 +1
		// @183: iload #14
		// @185: ifne @19B
		// @188: iload #14
		// @18A: ifeq @154
		// @18D: goto @191
		// @190: athrow
		// @191: aload #4
		// @193: getfield int[] game.C_100167_sj.field_100789_j
		// @196: iload #5
		// @198: iload #6
		// @19A: iastore
		// @19B: iload #9
		// @19D: anewarray java.lang.Class
		// @1A0: astore #12
		// @1A2: iconst_0
		// @1A3: istore #13
		// @1A5: iload #13
		// @1A7: iconst_m1
		// @1A8: ixor
		// @1A9: iload #9
		// @1AB: iconst_m1
		// @1AC: ixor
		// @1AD: if_icmple @1D0
		// @1B0: aload #12
		// @1B2: iload #13
		// @1B4: bipush -115 (0x8D)
		// @1B6: aload #10
		// @1B8: iload #13
		// @1BA: aaload
		// @1BB: invokestatic game.C_100160_sm.func_105410_a(byte, java.lang.String)java.lang.Class
		// @1BE: aastore
		// @1BF: iinc #13 +1
		// @1C2: iload #14
		// @1C4: ifne @1F3
		// @1C7: iload #14
		// @1C9: ifeq @1A5
		// @1CC: goto @1D0
		// @1CF: athrow
		// @1D0: aload #4
		// @1D2: getfield game.C_100331_ie[] game.C_100167_sj.field_100795_s
		// @1D5: iload #5
		// @1D7: aload_3
		// @1D8: bipush -63 (0xC1)
		// @1DA: aload #7
		// @1DC: invokestatic game.C_100160_sm.func_105410_a(byte, java.lang.String)java.lang.Class
		// @1DF: bipush 27 (0x1B)
		// @1E1: aload #8
		// @1E3: aload #12
		// @1E5: invokevirtual game.C_100201_qj.func_105861_a(java.lang.Class, byte, java.lang.String, java.lang.Class[])game.C_100331_ie
		// @1E8: aastore
		// @1E9: aload #4
		// @1EB: getfield byte[][][] game.C_100167_sj.field_100785_n
		// @1EE: iload #5
		// @1F0: aload #11
		// @1F2: aastore
		// @1F3: iload #14
		// @1F5: ifeq @24B
		// @1F8: aload_1
		// @1F9: sipush 9692 (0x25DC)
		// @1FC: invokevirtual game.C_100280_nf.func_101164_f(int)java.lang.String
		// @1FF: astore #7
		// @201: aload_1
		// @202: sipush 9692 (0x25DC)
		// @205: invokevirtual game.C_100280_nf.func_101164_f(int)java.lang.String
		// @208: astore #8
		// @20A: iconst_0
		// @20B: istore #9
		// @20D: iconst_1
		// @20E: iload #6
		// @210: if_icmpeq @217
		// @213: goto @220
		// @216: athrow
		// @217: aload_1
		// @218: sipush -1543 (0xF9F9)
		// @21B: invokevirtual game.C_100280_nf.func_101171_e(int)int
		// @21E: istore #9
		// @220: aload #4
		// @222: getfield int[] game.C_100167_sj.field_100789_j
		// @225: iload #5
		// @227: iload #6
		// @229: iastore
		// @22A: aload #4
		// @22C: getfield int[] game.C_100167_sj.field_100787_l
		// @22F: iload #5
		// @231: iload #9
		// @233: iastore
		// @234: aload #4
		// @236: getfield game.C_100331_ie[] game.C_100167_sj.field_100798_p
		// @239: iload #5
		// @23B: aload_3
		// @23C: bipush -118 (0x8A)
		// @23E: aload #8
		// @240: bipush -116 (0x8C)
		// @242: aload #7
		// @244: invokestatic game.C_100160_sm.func_105410_a(byte, java.lang.String)java.lang.Class
		// @247: invokevirtual game.C_100201_qj.func_105864_a(byte, java.lang.String, java.lang.Class)game.C_100331_ie
		// @24A: aastore
		// @24B: goto @295
		// @24E: astore #6
		// @250: aload #4
		// @252: getfield int[] game.C_100167_sj.field_100790_k
		// @255: iload #5
		// @257: iconst_m1
		// @258: iastore
		// @259: goto @295
		// @25C: astore #6
		// @25E: aload #4
		// @260: getfield int[] game.C_100167_sj.field_100790_k
		// @263: iload #5
		// @265: bipush -2 (0xFE)
		// @267: iastore
		// @268: goto @295
		// @26B: astore #6
		// @26D: aload #4
		// @26F: getfield int[] game.C_100167_sj.field_100790_k
		// @272: iload #5
		// @274: bipush -3 (0xFD)
		// @276: iastore
		// @277: goto @295
		// @27A: astore #6
		// @27C: aload #4
		// @27E: getfield int[] game.C_100167_sj.field_100790_k
		// @281: iload #5
		// @283: bipush -4 (0xFC)
		// @285: iastore
		// @286: goto @295
		// @289: astore #6
		// @28B: aload #4
		// @28D: getfield int[] game.C_100167_sj.field_100790_k
		// @290: iload #5
		// @292: bipush -5 (0xFB)
		// @294: iastore
		// @295: iinc #5 +1
		// @298: iload #14
		// @29A: ifeq @0A3
		// @29D: getstatic game.C_100202_qi game.C_100132_td.field_104979_l
		// @2A0: bipush 124 (0x7C)
		// @2A2: aload #4
		// @2A4: invokevirtual game.C_100202_qi.func_105901_a(int, game.C_100158_da)void
		// @2A7: goto @30B
		// @2AA: astore #4
		// @2AC: aload #4
		// @2AE: new java.lang.StringBuilder
		// @2B1: dup
		// @2B2: invokespecial java.lang.StringBuilder.<init>()void
		// @2B5: getstatic java.lang.String[] game.C_100295_kh.field_105307_z
		// @2B8: bipush 13 (0x0D)
		// @2BA: aaload
		// @2BB: invokevirtual java.lang.StringBuilder.append(java.lang.String)java.lang.StringBuilder
		// @2BE: iload_0
		// @2BF: invokevirtual java.lang.StringBuilder.append(int)java.lang.StringBuilder
		// @2C2: bipush 44 (0x2C)
		// @2C4: invokevirtual java.lang.StringBuilder.append(char)java.lang.StringBuilder
		// @2C7: aload_1
		// @2C8: ifnull @2D4
		// @2CB: getstatic java.lang.String[] game.C_100295_kh.field_105307_z
		// @2CE: iconst_3
		// @2CF: aaload
		// @2D0: goto @2D9
		// @2D3: athrow
		// @2D4: getstatic java.lang.String[] game.C_100295_kh.field_105307_z
		// @2D7: iconst_2
		// @2D8: aaload
		// @2D9: invokevirtual java.lang.StringBuilder.append(java.lang.String)java.lang.StringBuilder
		// @2DC: bipush 44 (0x2C)
		// @2DE: invokevirtual java.lang.StringBuilder.append(char)java.lang.StringBuilder
		// @2E1: iload_2
		// @2E2: invokevirtual java.lang.StringBuilder.append(int)java.lang.StringBuilder
		// @2E5: bipush 44 (0x2C)
		// @2E7: invokevirtual java.lang.StringBuilder.append(char)java.lang.StringBuilder
		// @2EA: aload_3
		// @2EB: ifnull @2F7
		// @2EE: getstatic java.lang.String[] game.C_100295_kh.field_105307_z
		// @2F1: iconst_3
		// @2F2: aaload
		// @2F3: goto @2FC
		// @2F6: athrow
		// @2F7: getstatic java.lang.String[] game.C_100295_kh.field_105307_z
		// @2FA: iconst_2
		// @2FB: aaload
		// @2FC: invokevirtual java.lang.StringBuilder.append(java.lang.String)java.lang.StringBuilder
		// @2FF: bipush 41 (0x29)
		// @301: invokevirtual java.lang.StringBuilder.append(char)java.lang.StringBuilder
		// @304: invokevirtual java.lang.StringBuilder.toString()java.lang.String
		// @307: invokestatic game.C_100181_cf.func_105695_a(java.lang.Throwable, java.lang.String)game.C_100170_cm
		// @30A: athrow
		// @30B: return
	}
	
	static final int func_105279_a(C_100154_sl arg0, String arg1, boolean arg2, C_100154_sl arg3, int arg4, int arg5, int arg6)
	{
		// @000: getstatic int game.SteelSentinels.field_105275_O
		// @003: istore #13
		// @005: aload_0
		// @006: bipush -117 (0x8B)
		// @008: invokevirtual game.C_100154_sl.func_105321_c(int)java.lang.String
		// @00B: astore #7
		// @00D: aload_3
		// @00E: bipush -120 (0x88)
		// @010: invokevirtual game.C_100154_sl.func_105321_c(int)java.lang.String
		// @013: astore #8
		// @015: aconst_null
		// @016: getstatic game.C_100286_nl game.C_100318_hj.field_107194_f
		// @019: if_acmpne @02E
		// @01C: iconst_0
		// @01D: iconst_0
		// @01E: invokestatic game.C_100051_ea.func_103302_a(boolean, int)boolean
		// @021: istore #9
		// @023: iload #9
		// @025: ifeq @02C
		// @028: goto @02E
		// @02B: athrow
		// @02C: iconst_m1
		// @02D: ireturn
		// @02E: getstatic game.C_100268_mk game.C_100066_dl.field_101642_t
		// @031: getstatic game.C_100268_mk game.C_100293_kj.field_106891_a
		// @034: if_acmpne @1CE
		// @037: aconst_null
		// @038: putstatic java.lang.Boolean game.C_100285_nk.field_106783_b
		// @03B: getstatic game.C_100278_nd game.C_100115_ej.field_102043_Yb
		// @03E: iconst_0
		// @03F: putfield int game.C_100278_nd.field_101177_n
		// @042: aload_1
		// @043: ifnull @127
		// @046: goto @04A
		// @049: athrow
		// @04A: iconst_0
		// @04B: istore #9
		// @04D: iload_2
		// @04E: ifeq @057
		// @051: iload #9
		// @053: iconst_1
		// @054: ior
		// @055: istore #9
		// @057: getstatic game.C_100280_nf game.C_100127_tl.field_104945_f
		// @05A: iconst_0
		// @05B: putfield int game.C_100280_nf.field_101177_n
		// @05E: getstatic game.C_100280_nf game.C_100127_tl.field_104945_f
		// @061: getstatic java.util.Random game.C_100067_vd.field_104322_k
		// @064: invokevirtual java.util.Random.nextInt()int
		// @067: bipush 48 (0x30)
		// @069: invokevirtual game.C_100280_nf.func_101154_d(int, int)void
		// @06C: getstatic game.C_100280_nf game.C_100127_tl.field_104945_f
		// @06F: getstatic java.util.Random game.C_100067_vd.field_104322_k
		// @072: invokevirtual java.util.Random.nextInt()int
		// @075: bipush 54 (0x36)
		// @077: invokevirtual game.C_100280_nf.func_101154_d(int, int)void
		// @07A: getstatic game.C_100280_nf game.C_100127_tl.field_104945_f
		// @07D: aload #7
		// @07F: bipush -97 (0x9F)
		// @081: invokevirtual game.C_100280_nf.func_101155_a(java.lang.String, byte)void
		// @084: getstatic game.C_100280_nf game.C_100127_tl.field_104945_f
		// @087: aload #8
		// @089: bipush 111 (0x6F)
		// @08B: invokevirtual game.C_100280_nf.func_101155_a(java.lang.String, byte)void
		// @08E: getstatic game.C_100280_nf game.C_100127_tl.field_104945_f
		// @091: aload_1
		// @092: sipush 8192 (0x2000)
		// @095: invokestatic game.C_100327_ib.func_102456_a(java.lang.CharSequence, int)java.lang.String
		// @098: bipush -70 (0xBA)
		// @09A: invokevirtual game.C_100280_nf.func_101155_a(java.lang.String, byte)void
		// @09D: getstatic game.C_100280_nf game.C_100127_tl.field_104945_f
		// @0A0: iload #5
		// @0A2: bipush -114 (0x8E)
		// @0A4: invokevirtual game.C_100280_nf.func_101141_d(int, byte)void
		// @0A7: getstatic game.C_100280_nf game.C_100127_tl.field_104945_f
		// @0AA: sipush 7838 (0x1E9E)
		// @0AD: iload #4
		// @0AF: invokevirtual game.C_100280_nf.func_101169_f(int, int)void
		// @0B2: getstatic game.C_100280_nf game.C_100127_tl.field_104945_f
		// @0B5: sipush 7838 (0x1E9E)
		// @0B8: iload #9
		// @0BA: invokevirtual game.C_100280_nf.func_101169_f(int, int)void
		// @0BD: getstatic game.C_100278_nd game.C_100115_ej.field_102043_Yb
		// @0C0: sipush 7838 (0x1E9E)
		// @0C3: bipush 18 (0x12)
		// @0C5: invokevirtual game.C_100278_nd.func_101169_f(int, int)void
		// @0C8: getstatic game.C_100278_nd game.C_100115_ej.field_102043_Yb
		// @0CB: dup
		// @0CC: getfield int game.C_100278_nd.field_101177_n
		// @0CF: iconst_2
		// @0D0: iadd
		// @0D1: putfield int game.C_100278_nd.field_101177_n
		// @0D4: getstatic game.C_100278_nd game.C_100115_ej.field_102043_Yb
		// @0D7: getfield int game.C_100278_nd.field_101177_n
		// @0DA: istore #10
		// @0DC: iconst_0
		// @0DD: invokestatic game.C_100206_qe.func_105938_b(boolean)java.applet.Applet
		// @0E0: bipush 61 (0x3D)
		// @0E2: invokestatic game.C_100253_ph.func_101084_a(java.applet.Applet, int)java.lang.String
		// @0E5: astore #11
		// @0E7: aconst_null
		// @0E8: aload #11
		// @0EA: if_acmpeq @0F1
		// @0ED: goto @0F5
		// @0F0: athrow
		// @0F1: ldc ""
		// @0F3: astore #11
		// @0F5: getstatic game.C_100278_nd game.C_100115_ej.field_102043_Yb
		// @0F8: sipush -28365 (0x9133)
		// @0FB: aload #11
		// @0FD: invokevirtual game.C_100278_nd.func_101167_a(int, java.lang.String)void
		// @100: getstatic game.C_100280_nf game.C_100127_tl.field_104945_f
		// @103: getstatic java.math.BigInteger game.C_100287_nm.field_106831_k
		// @106: bipush 86 (0x56)
		// @108: getstatic java.math.BigInteger game.C_100084_ug.field_104488_h
		// @10B: getstatic game.C_100278_nd game.C_100115_ej.field_102043_Yb
		// @10E: invokestatic game.C_100255_pj.func_105219_a(game.C_100280_nf, java.math.BigInteger, int, java.math.BigInteger, game.C_100280_nf)void
		// @111: getstatic game.C_100278_nd game.C_100115_ej.field_102043_Yb
		// @114: iload #10
		// @116: ineg
		// @117: getstatic game.C_100278_nd game.C_100115_ej.field_102043_Yb
		// @11A: getfield int game.C_100278_nd.field_101177_n
		// @11D: iadd
		// @11E: iconst_0
		// @11F: invokevirtual game.C_100278_nd.func_101162_a(int, boolean)void
		// @122: iload #13
		// @124: ifeq @1C2
		// @127: getstatic game.C_100280_nf game.C_100127_tl.field_104945_f
		// @12A: iconst_0
		// @12B: putfield int game.C_100280_nf.field_101177_n
		// @12E: getstatic game.C_100280_nf game.C_100127_tl.field_104945_f
		// @131: getstatic java.util.Random game.C_100067_vd.field_104322_k
		// @134: invokevirtual java.util.Random.nextInt()int
		// @137: bipush -121 (0x87)
		// @139: invokevirtual game.C_100280_nf.func_101154_d(int, int)void
		// @13C: getstatic game.C_100280_nf game.C_100127_tl.field_104945_f
		// @13F: getstatic java.util.Random game.C_100067_vd.field_104322_k
		// @142: invokevirtual java.util.Random.nextInt()int
		// @145: bipush 62 (0x3E)
		// @147: invokevirtual game.C_100280_nf.func_101154_d(int, int)void
		// @14A: getstatic game.C_100280_nf game.C_100127_tl.field_104945_f
		// @14D: aload_0
		// @14E: bipush 78 (0x4E)
		// @150: invokevirtual game.C_100154_sl.func_105326_a(int)boolean
		// @153: ifeq @160
		// @156: goto @15A
		// @159: athrow
		// @15A: aload #7
		// @15C: goto @162
		// @15F: athrow
		// @160: ldc ""
		// @162: bipush -107 (0x95)
		// @164: invokevirtual game.C_100280_nf.func_101155_a(java.lang.String, byte)void
		// @167: getstatic game.C_100280_nf game.C_100127_tl.field_104945_f
		// @16A: aload_3
		// @16B: bipush 63 (0x3F)
		// @16D: invokevirtual game.C_100154_sl.func_105326_a(int)boolean
		// @170: ifeq @179
		// @173: aload #8
		// @175: goto @17B
		// @178: athrow
		// @179: ldc ""
		// @17B: bipush -57 (0xC7)
		// @17D: invokevirtual game.C_100280_nf.func_101155_a(java.lang.String, byte)void
		// @180: getstatic game.C_100278_nd game.C_100115_ej.field_102043_Yb
		// @183: sipush 7838 (0x1E9E)
		// @186: bipush 16 (0x10)
		// @188: invokevirtual game.C_100278_nd.func_101169_f(int, int)void
		// @18B: getstatic game.C_100278_nd game.C_100115_ej.field_102043_Yb
		// @18E: dup
		// @18F: getfield int game.C_100278_nd.field_101177_n
		// @192: iconst_1
		// @193: iadd
		// @194: putfield int game.C_100278_nd.field_101177_n
		// @197: getstatic game.C_100278_nd game.C_100115_ej.field_102043_Yb
		// @19A: getfield int game.C_100278_nd.field_101177_n
		// @19D: istore #9
		// @19F: getstatic game.C_100280_nf game.C_100127_tl.field_104945_f
		// @1A2: getstatic java.math.BigInteger game.C_100287_nm.field_106831_k
		// @1A5: bipush 106 (0x6A)
		// @1A7: getstatic java.math.BigInteger game.C_100084_ug.field_104488_h
		// @1AA: getstatic game.C_100278_nd game.C_100115_ej.field_102043_Yb
		// @1AD: invokestatic game.C_100255_pj.func_105219_a(game.C_100280_nf, java.math.BigInteger, int, java.math.BigInteger, game.C_100280_nf)void
		// @1B0: getstatic game.C_100278_nd game.C_100115_ej.field_102043_Yb
		// @1B3: getstatic game.C_100278_nd game.C_100115_ej.field_102043_Yb
		// @1B6: getfield int game.C_100278_nd.field_101177_n
		// @1B9: iload #9
		// @1BB: ineg
		// @1BC: iadd
		// @1BD: bipush -100 (0x9C)
		// @1BF: invokevirtual game.C_100278_nd.func_101139_c(int, byte)void
		// @1C2: iconst_m1
		// @1C3: bipush -84 (0xAC)
		// @1C5: invokestatic game.C_100306_kn.func_107128_a(int, byte)void
		// @1C8: getstatic game.C_100268_mk game.C_100156_sk.field_105392_n
		// @1CB: putstatic game.C_100268_mk game.C_100066_dl.field_101642_t
		// @1CE: getstatic game.C_100268_mk game.C_100066_dl.field_101642_t
		// @1D1: getstatic game.C_100268_mk game.C_100156_sk.field_105392_n
		// @1D4: if_acmpeq @1DB
		// @1D7: goto @29A
		// @1DA: athrow
		// @1DB: iconst_1
		// @1DC: bipush 51 (0x33)
		// @1DE: invokestatic game.C_100114_q.func_100483_a(int, byte)boolean
		// @1E1: ifne @1E8
		// @1E4: goto @29A
		// @1E7: athrow
		// @1E8: getstatic game.C_100278_nd game.C_100288_jn.field_106839_f
		// @1EB: iconst_0
		// @1EC: invokevirtual game.C_100278_nd.func_101156_c(boolean)int
		// @1EF: istore #9
		// @1F1: getstatic game.C_100278_nd game.C_100288_jn.field_106839_f
		// @1F4: iconst_0
		// @1F5: putfield int game.C_100278_nd.field_101177_n
		// @1F8: bipush -101 (0x9B)
		// @1FA: iload #9
		// @1FC: iconst_m1
		// @1FD: ixor
		// @1FE: if_icmplt @20E
		// @201: bipush -106 (0x96)
		// @203: iload #9
		// @205: iconst_m1
		// @206: ixor
		// @207: if_icmple @285
		// @20A: goto @20E
		// @20D: athrow
		// @20E: sipush 248 (0x00F8)
		// @211: iload #9
		// @213: if_icmpne @237
		// @216: goto @21A
		// @219: athrow
		// @21A: iconst_0
		// @21B: invokestatic game.C_100206_qe.func_105938_b(boolean)java.applet.Applet
		// @21E: sipush 198 (0x00C6)
		// @221: invokestatic game.C_100015_wh.func_103773_a(java.applet.Applet, int)void
		// @224: getstatic java.lang.String game.C_100074_g.field_104409_d
		// @227: putstatic java.lang.String game.C_100167_sj.field_100791_w
		// @22A: sipush 13313 (0x3401)
		// @22D: invokestatic game.C_100095_fe.func_103371_l(int)void
		// @230: iconst_0
		// @231: putstatic boolean game.C_100208_qg.field_105957_e
		// @234: iload #9
		// @236: ireturn
		// @237: iload #9
		// @239: iconst_m1
		// @23A: ixor
		// @23B: bipush -100 (0x9C)
		// @23D: if_icmpeq @258
		// @240: getstatic game.C_100268_mk game.C_100131_te.field_100762_m
		// @243: putstatic game.C_100268_mk game.C_100066_dl.field_101642_t
		// @246: iload #9
		// @248: putstatic int game.C_100299_kd.field_107051_z
		// @24B: iconst_m1
		// @24C: putstatic int game.C_100056_de.field_103194_Y
		// @24F: iload #13
		// @251: ifeq @29A
		// @254: goto @258
		// @257: athrow
		// @258: iconst_m1
		// @259: invokestatic game.C_100047_vh.func_104148_b(int)int
		// @25C: bipush 51 (0x33)
		// @25E: invokestatic game.C_100114_q.func_100483_a(int, byte)boolean
		// @261: pop
		// @262: new java.lang.Boolean
		// @265: dup
		// @266: sipush -22292 (0xA8EC)
		// @269: getstatic game.C_100278_nd game.C_100288_jn.field_106839_f
		// @26C: invokestatic game.C_100293_kj.func_106886_a(int, game.C_100280_nf)boolean
		// @26F: invokespecial java.lang.Boolean.<init>(boolean)void
		// @272: putstatic java.lang.Boolean game.C_100285_nk.field_106783_b
		// @275: getstatic game.C_100278_nd game.C_100288_jn.field_106839_f
		// @278: iconst_0
		// @279: putfield int game.C_100278_nd.field_101177_n
		// @27C: iload #13
		// @27E: ifeq @29A
		// @281: goto @285
		// @284: athrow
		// @285: getstatic game.C_100268_mk game.C_100309_lk.field_103259_eb
		// @288: putstatic game.C_100268_mk game.C_100066_dl.field_101642_t
		// @28B: iload #9
		// @28D: bipush -100 (0x9C)
		// @28F: iadd
		// @290: anewarray java.lang.String
		// @293: putstatic java.lang.String[] game.C_100124_tn.field_104935_b
		// @296: goto @29A
		// @299: athrow
		// @29A: getstatic game.C_100268_mk game.C_100066_dl.field_101642_t
		// @29D: getstatic game.C_100268_mk game.C_100309_lk.field_103259_eb
		// @2A0: if_acmpne @312
		// @2A3: iconst_2
		// @2A4: istore #9
		// @2A6: iload #9
		// @2A8: bipush 51 (0x33)
		// @2AA: invokestatic game.C_100114_q.func_100483_a(int, byte)boolean
		// @2AD: ifeq @312
		// @2B0: getstatic game.C_100278_nd game.C_100288_jn.field_106839_f
		// @2B3: bipush -2 (0xFE)
		// @2B5: invokevirtual game.C_100278_nd.func_101143_l(int)int
		// @2B8: istore #10
		// @2BA: getstatic game.C_100278_nd game.C_100288_jn.field_106839_f
		// @2BD: iconst_0
		// @2BE: putfield int game.C_100278_nd.field_101177_n
		// @2C1: iload #10
		// @2C3: bipush 51 (0x33)
		// @2C5: invokestatic game.C_100114_q.func_100483_a(int, byte)boolean
		// @2C8: ifne @2CF
		// @2CB: goto @312
		// @2CE: athrow
		// @2CF: getstatic java.lang.String[] game.C_100124_tn.field_104935_b
		// @2D2: arraylength
		// @2D3: istore #11
		// @2D5: iconst_0
		// @2D6: istore #12
		// @2D8: iload #11
		// @2DA: iconst_m1
		// @2DB: ixor
		// @2DC: iload #12
		// @2DE: iconst_m1
		// @2DF: ixor
		// @2E0: if_icmpge @301
		// @2E3: getstatic java.lang.String[] game.C_100124_tn.field_104935_b
		// @2E6: iload #12
		// @2E8: getstatic game.C_100278_nd game.C_100288_jn.field_106839_f
		// @2EB: iconst_m1
		// @2EC: invokevirtual game.C_100278_nd.func_101144_g(int)java.lang.String
		// @2EF: aastore
		// @2F0: iinc #12 +1
		// @2F3: iload #13
		// @2F5: ifne @30B
		// @2F8: iload #13
		// @2FA: ifeq @2D8
		// @2FD: goto @301
		// @300: athrow
		// @301: sipush 13313 (0x3401)
		// @304: invokestatic game.C_100095_fe.func_103371_l(int)void
		// @307: iconst_0
		// @308: putstatic boolean game.C_100208_qg.field_105957_e
		// @30B: bipush 100 (0x64)
		// @30D: iload #11
		// @30F: ineg
		// @310: isub
		// @311: ireturn
		// @312: getstatic game.C_100268_mk game.C_100066_dl.field_101642_t
		// @315: getstatic game.C_100268_mk game.C_100131_te.field_100762_m
		// @318: if_acmpeq @31F
		// @31B: goto @375
		// @31E: athrow
		// @31F: iconst_0
		// @320: invokestatic game.C_100149_bi.func_105150_b(int)boolean
		// @323: ifeq @375
		// @326: sipush 255 (0x00FF)
		// @329: getstatic int game.C_100299_kd.field_107051_z
		// @32C: if_icmpeq @348
		// @32F: goto @333
		// @332: athrow
		// @333: getstatic game.C_100278_nd game.C_100288_jn.field_106839_f
		// @336: sipush 9692 (0x25DC)
		// @339: invokevirtual game.C_100278_nd.func_101164_f(int)java.lang.String
		// @33C: putstatic java.lang.String game.C_100167_sj.field_100791_w
		// @33F: iload #13
		// @341: ifeq @367
		// @344: goto @348
		// @347: athrow
		// @348: getstatic game.C_100278_nd game.C_100288_jn.field_106839_f
		// @34B: bipush 6 (0x06)
		// @34D: invokevirtual game.C_100278_nd.func_101163_j(int)java.lang.String
		// @350: astore #9
		// @352: aconst_null
		// @353: aload #9
		// @355: if_acmpeq @367
		// @358: bipush -51 (0xCD)
		// @35A: aload #9
		// @35C: iconst_0
		// @35D: invokestatic game.C_100206_qe.func_105938_b(boolean)java.applet.Applet
		// @360: invokestatic game.C_100298_ke.func_103206_a(int, java.lang.String, java.applet.Applet)void
		// @363: goto @367
		// @366: athrow
		// @367: sipush 13313 (0x3401)
		// @36A: invokestatic game.C_100095_fe.func_103371_l(int)void
		// @36D: iconst_0
		// @36E: putstatic boolean game.C_100208_qg.field_105957_e
		// @371: getstatic int game.C_100299_kd.field_107051_z
		// @374: ireturn
		// @375: iload #6
		// @377: bipush 31 (0x1F)
		// @379: if_icmpge @387
		// @37C: aconst_null
		// @37D: checkcast java.lang.String
		// @380: putstatic java.lang.String game.C_100295_kh.field_105296_o
		// @383: goto @387
		// @386: athrow
		// @387: getstatic game.C_100286_nl game.C_100318_hj.field_107194_f
		// @38A: ifnonnull @3E5
		// @38D: getstatic boolean game.C_100208_qg.field_105957_e
		// @390: ifne @3B0
		// @393: goto @397
		// @396: athrow
		// @397: getstatic int game.C_100180_ce.field_104810_s
		// @39A: istore #9
		// @39C: getstatic int game.C_100163_sf.field_105434_f
		// @39F: putstatic int game.C_100180_ce.field_104810_s
		// @3A2: iconst_1
		// @3A3: putstatic boolean game.C_100208_qg.field_105957_e
		// @3A6: iload #9
		// @3A8: putstatic int game.C_100163_sf.field_105434_f
		// @3AB: iload #13
		// @3AD: ifeq @3E5
		// @3B0: ldc2_w -30001
		// @3B3: bipush 37 (0x25)
		// @3B5: invokestatic game.C_100133_tk.func_104988_c(int)long
		// @3B8: ldc2_w -1
		// @3BB: lxor
		// @3BC: lcmp
		// @3BD: ifgt @3D3
		// @3C0: goto @3C4
		// @3C3: athrow
		// @3C4: getstatic java.lang.String game.C_100155_dc.field_105350_e
		// @3C7: putstatic java.lang.String game.C_100167_sj.field_100791_w
		// @3CA: iload #13
		// @3CC: ifeq @3DD
		// @3CF: goto @3D3
		// @3D2: athrow
		// @3D3: getstatic java.lang.String game.C_100321_hi.field_107227_k
		// @3D6: putstatic java.lang.String game.C_100167_sj.field_100791_w
		// @3D9: goto @3DD
		// @3DC: athrow
		// @3DD: iconst_0
		// @3DE: putstatic boolean game.C_100208_qg.field_105957_e
		// @3E1: sipush 249 (0x00F9)
		// @3E4: ireturn
		// @3E5: iconst_m1
		// @3E6: ireturn
		// @3E7: astore #7
		// @3E9: aload #7
		// @3EB: new java.lang.StringBuilder
		// @3EE: dup
		// @3EF: invokespecial java.lang.StringBuilder.<init>()void
		// @3F2: getstatic java.lang.String[] game.C_100295_kh.field_105307_z
		// @3F5: bipush 12 (0x0C)
		// @3F7: aaload
		// @3F8: invokevirtual java.lang.StringBuilder.append(java.lang.String)java.lang.StringBuilder
		// @3FB: aload_0
		// @3FC: ifnull @408
		// @3FF: getstatic java.lang.String[] game.C_100295_kh.field_105307_z
		// @402: iconst_3
		// @403: aaload
		// @404: goto @40D
		// @407: athrow
		// @408: getstatic java.lang.String[] game.C_100295_kh.field_105307_z
		// @40B: iconst_2
		// @40C: aaload
		// @40D: invokevirtual java.lang.StringBuilder.append(java.lang.String)java.lang.StringBuilder
		// @410: bipush 44 (0x2C)
		// @412: invokevirtual java.lang.StringBuilder.append(char)java.lang.StringBuilder
		// @415: aload_1
		// @416: ifnull @422
		// @419: getstatic java.lang.String[] game.C_100295_kh.field_105307_z
		// @41C: iconst_3
		// @41D: aaload
		// @41E: goto @427
		// @421: athrow
		// @422: getstatic java.lang.String[] game.C_100295_kh.field_105307_z
		// @425: iconst_2
		// @426: aaload
		// @427: invokevirtual java.lang.StringBuilder.append(java.lang.String)java.lang.StringBuilder
		// @42A: bipush 44 (0x2C)
		// @42C: invokevirtual java.lang.StringBuilder.append(char)java.lang.StringBuilder
		// @42F: iload_2
		// @430: invokevirtual java.lang.StringBuilder.append(boolean)java.lang.StringBuilder
		// @433: bipush 44 (0x2C)
		// @435: invokevirtual java.lang.StringBuilder.append(char)java.lang.StringBuilder
		// @438: aload_3
		// @439: ifnull @445
		// @43C: getstatic java.lang.String[] game.C_100295_kh.field_105307_z
		// @43F: iconst_3
		// @440: aaload
		// @441: goto @44A
		// @444: athrow
		// @445: getstatic java.lang.String[] game.C_100295_kh.field_105307_z
		// @448: iconst_2
		// @449: aaload
		// @44A: invokevirtual java.lang.StringBuilder.append(java.lang.String)java.lang.StringBuilder
		// @44D: bipush 44 (0x2C)
		// @44F: invokevirtual java.lang.StringBuilder.append(char)java.lang.StringBuilder
		// @452: iload #4
		// @454: invokevirtual java.lang.StringBuilder.append(int)java.lang.StringBuilder
		// @457: bipush 44 (0x2C)
		// @459: invokevirtual java.lang.StringBuilder.append(char)java.lang.StringBuilder
		// @45C: iload #5
		// @45E: invokevirtual java.lang.StringBuilder.append(int)java.lang.StringBuilder
		// @461: bipush 44 (0x2C)
		// @463: invokevirtual java.lang.StringBuilder.append(char)java.lang.StringBuilder
		// @466: iload #6
		// @468: invokevirtual java.lang.StringBuilder.append(int)java.lang.StringBuilder
		// @46B: bipush 41 (0x29)
		// @46D: invokevirtual java.lang.StringBuilder.append(char)java.lang.StringBuilder
		// @470: invokevirtual java.lang.StringBuilder.toString()java.lang.String
		// @473: invokestatic game.C_100181_cf.func_105695_a(java.lang.Throwable, java.lang.String)game.C_100170_cm
		// @476: athrow
	}
	
	static
	{
		// @000: bipush 14 (0x0E)
		// @002: anewarray java.lang.String
		// @005: dup
		// @006: iconst_0
		// @007: ldc "&w\u000ej_"
		// @009: invokestatic game.C_100295_kh.func_105285_z(java.lang.String)char[]
		// @00C: invokestatic game.C_100295_kh.func_105284_z(char[])java.lang.String
		// @00F: aastore
		// @010: dup
		// @011: iconst_1
		// @012: ldc "&w\u000eh_"
		// @014: invokestatic game.C_100295_kh.func_105285_z(java.lang.String)char[]
		// @017: invokestatic game.C_100295_kh.func_105284_z(char[])java.lang.String
		// @01A: aastore
		// @01B: dup
		// @01C: iconst_2
		// @01D: ldc "#jLV"
		// @01F: invokestatic game.C_100295_kh.func_105285_z(java.lang.String)char[]
		// @022: invokestatic game.C_100295_kh.func_105284_z(char[])java.lang.String
		// @025: aastore
		// @026: dup
		// @027: iconst_3
		// @028: ldc "61\u000e\u0014\n"
		// @02A: invokestatic game.C_100295_kh.func_105285_z(java.lang.String)char[]
		// @02D: invokestatic game.C_100295_kh.func_105284_z(char[])java.lang.String
		// @030: aastore
		// @031: dup
		// @032: iconst_4
		// @033: ldc ")pCO\u001a(qT\u0014\u0014\"pKS\u0012p="
		// @035: invokestatic game.C_100295_kh.func_105285_z(java.lang.String)char[]
		// @038: invokestatic game.C_100295_kh.func_105284_z(char[])java.lang.String
		// @03B: aastore
		// @03C: dup
		// @03D: iconst_5
		// @03E: ldc ".pOQ\u001e(oR_\u0011$g"
		// @040: invokestatic game.C_100295_kh.func_105285_z(java.lang.String)char[]
		// @043: invokestatic game.C_100295_kh.func_105284_z(char[])java.lang.String
		// @046: aastore
		// @047: dup
		// @048: bipush 6 (0x06)
		// @04A: ldc "v?V_\u0005>vOTJ|$\u0000J\u00169w\u001d\u0015Lm{OW\u0016$q\u001d"
		// @04C: invokestatic game.C_100295_kh.func_105285_z(java.lang.String)char[]
		// @04F: invokestatic game.C_100295_kh.func_105284_z(char[])java.lang.String
		// @052: aastore
		// @053: dup
		// @054: bipush 7 (0x07)
		// @056: ldc "v?eB\u0007$mEIJ\u0019wU\u0016W}.\rp\u0016#2\u0011\u0003@}?\u0010\nM}/\u001a\nGmXmnLmRABZ\u000cxE\u0007G"
		// @058: invokestatic game.C_100295_kh.func_105285_z(java.lang.String)char[]
		// @05B: invokestatic game.C_100295_kh.func_105284_z(char[])java.lang.String
		// @05E: aastore
		// @05F: dup
		// @060: bipush 8 (0x08)
		// @062: ldc ">zSI\u001e\"q\u001d"
		// @064: invokestatic game.C_100295_kh.func_105285_z(java.lang.String)char[]
		// @067: invokestatic game.C_100295_kh.func_105284_z(char[])java.lang.String
		// @06A: aastore
		// @06B: dup
		// @06C: bipush 9 (0x09)
		// @06E: ldc "&w\u000eu_"
		// @070: invokestatic game.C_100295_kh.func_105285_z(java.lang.String)char[]
		// @073: invokestatic game.C_100295_kh.func_105284_z(char[])java.lang.String
		// @076: aastore
		// @077: dup
		// @078: bipush 10 (0x0A)
		// @07A: ldc ".pOQ\u001e(wOI\u0003"
		// @07C: invokestatic game.C_100295_kh.func_105285_z(java.lang.String)char[]
		// @07F: invokestatic game.C_100295_kh.func_105284_z(char[])java.lang.String
		// @082: aastore
		// @083: dup
		// @084: bipush 11 (0x0B)
		// @086: ldc "&w\u000ei_"
		// @088: invokestatic game.C_100295_kh.func_105285_z(java.lang.String)char[]
		// @08B: invokestatic game.C_100295_kh.func_105284_z(char[])java.lang.String
		// @08E: aastore
		// @08F: dup
		// @090: bipush 12 (0x0C)
		// @092: ldc "&w\u000et_"
		// @094: invokestatic game.C_100295_kh.func_105285_z(java.lang.String)char[]
		// @097: invokestatic game.C_100295_kh.func_105284_z(char[])java.lang.String
		// @09A: aastore
		// @09B: dup
		// @09C: bipush 13 (0x0D)
		// @09E: ldc "&w\u000ek_"
		// @0A0: invokestatic game.C_100295_kh.func_105285_z(java.lang.String)char[]
		// @0A3: invokestatic game.C_100295_kh.func_105284_z(char[])java.lang.String
		// @0A6: aastore
		// @0A7: putstatic java.lang.String[] game.C_100295_kh.field_105307_z
		// @0AA: ldc "\u000b^vu\"\u001fVt\u007f$"
		// @0AC: invokestatic game.C_100295_kh.func_105285_z(java.lang.String)char[]
		// @0AF: invokestatic game.C_100295_kh.func_105284_z(char[])java.lang.String
		// @0B2: putstatic java.lang.String game.C_100295_kh.field_105295_n
		// @0B5: ldc "\u000e^mj6\u0004Xn\u001a#\u0004Re\u0000W"
		// @0B7: invokestatic game.C_100295_kh.func_105285_z(java.lang.String)char[]
		// @0BA: invokestatic game.C_100295_kh.func_105284_z(char[])java.lang.String
		// @0BD: putstatic java.lang.String game.C_100295_kh.field_105306_p
		// @0C0: ldc "\u001eKah#mRii$\u0004Pn"
		// @0C2: invokestatic game.C_100295_kh.func_105285_z(java.lang.String)char[]
		// @0C5: invokestatic game.C_100295_kh.func_105284_z(char[])java.lang.String
		// @0C8: putstatic java.lang.String game.C_100295_kh.field_105292_b
		// @0CB: ldc "\t~T[W>zRL\u0012??FO\u001b!?OHW9pO\u001a\u001a,qY\u001a\u0014\"qN_\u00149vOT\u0004myRU\u001amfOO\u0005m~D^\u0005(lS\u0014W\u001dsE[\u0004(?TH\u000em~G[\u001e#?ITW,?F_\u0000mrIT\u00029zS\u0014"
		// @0CD: invokestatic game.C_100295_kh.func_105285_z(java.lang.String)char[]
		// @0D0: invokestatic game.C_100295_kh.func_105284_z(char[])java.lang.String
		// @0D3: putstatic java.lang.String game.C_100295_kh.field_105294_a
		// @0D6: ldc "\u0003zXN"
		// @0D8: invokestatic game.C_100295_kh.func_105285_z(java.lang.String)char[]
		// @0DB: invokestatic game.C_100295_kh.func_105284_z(char[])java.lang.String
		// @0DE: putstatic java.lang.String game.C_100295_kh.field_105288_f
		// @0E1: ldc "9p\u0000U\u0001(m\u0000\u0006R}!\u0000]\u0005(~T\u001a\u0010,rEI"
		// @0E3: invokestatic game.C_100295_kh.func_105285_z(java.lang.String)char[]
		// @0E6: invokestatic game.C_100295_kh.func_105284_z(char[])java.lang.String
		// @0E9: putstatic java.lang.String game.C_100295_kh.field_105296_o
		// @0EC: bipush 23 (0x17)
		// @0EE: anewarray game.C_100034_gi
		// @0F1: putstatic game.C_100034_gi[] game.C_100295_kh.field_105293_c
		// @0F4: bipush 12 (0x0C)
		// @0F6: newarray int[]
		// @0F8: dup
		// @0F9: iconst_0
		// @0FA: bipush 31 (0x1F)
		// @0FC: iastore
		// @0FD: dup
		// @0FE: iconst_1
		// @0FF: bipush 28 (0x1C)
		// @101: iastore
		// @102: dup
		// @103: iconst_2
		// @104: bipush 31 (0x1F)
		// @106: iastore
		// @107: dup
		// @108: iconst_3
		// @109: bipush 30 (0x1E)
		// @10B: iastore
		// @10C: dup
		// @10D: iconst_4
		// @10E: bipush 31 (0x1F)
		// @110: iastore
		// @111: dup
		// @112: iconst_5
		// @113: bipush 30 (0x1E)
		// @115: iastore
		// @116: dup
		// @117: bipush 6 (0x06)
		// @119: bipush 31 (0x1F)
		// @11B: iastore
		// @11C: dup
		// @11D: bipush 7 (0x07)
		// @11F: bipush 31 (0x1F)
		// @121: iastore
		// @122: dup
		// @123: bipush 8 (0x08)
		// @125: bipush 30 (0x1E)
		// @127: iastore
		// @128: dup
		// @129: bipush 9 (0x09)
		// @12B: bipush 31 (0x1F)
		// @12D: iastore
		// @12E: dup
		// @12F: bipush 10 (0x0A)
		// @131: bipush 30 (0x1E)
		// @133: iastore
		// @134: dup
		// @135: bipush 11 (0x0B)
		// @137: bipush 31 (0x1F)
		// @139: iastore
		// @13A: putstatic int[] game.C_100295_kh.field_105290_d
		// @13D: ldc "\u000bJlvW\u000c\\c\u007f$\u001e"
		// @13F: invokestatic game.C_100295_kh.func_105285_z(java.lang.String)char[]
		// @142: invokestatic game.C_100295_kh.func_105284_z(char[])java.lang.String
		// @145: putstatic java.lang.String game.C_100295_kh.field_105289_g
		// @148: return
	}
	
	private static char[] func_105285_z(String arg0)
	{
		// @00: aload_0
		// @01: invokevirtual java.lang.String.toCharArray()char[]
		// @04: dup
		// @05: arraylength
		// @06: iconst_2
		// @07: if_icmpge @13
		// @0A: dup
		// @0B: iconst_0
		// @0C: dup2
		// @0D: caload
		// @0E: bipush 119 (0x77)
		// @10: ixor
		// @11: i2c
		// @12: castore
		// @13: areturn
	}
	
	private static String func_105284_z(char[] arg0)
	{
		// @00: aload_0
		// @01: dup
		// @02: arraylength
		// @03: swap
		// @04: iconst_0
		// @05: istore_1
		// @06: goto @4C
		// @09: dup
		// @0A: iload_1
		// @0B: dup2
		// @0C: caload
		// @0D: iload_1
		// @0E: iconst_5
		// @0F: irem
		// @10: tableswitch def: @44, for 0: @30, for 1: @35, for 2: @3A, for 3: @3F
		// @30: bipush 77 (0x4D)
		// @32: goto @46
		// @35: bipush 31 (0x1F)
		// @37: goto @46
		// @3A: bipush 32 (0x20)
		// @3C: goto @46
		// @3F: bipush 58 (0x3A)
		// @41: goto @46
		// @44: bipush 119 (0x77)
		// @46: ixor
		// @47: i2c
		// @48: castore
		// @49: iinc #1 +1
		// @4C: swap
		// @4D: dup_x1
		// @4E: iload_1
		// @4F: if_icmpgt @09
		// @52: new java.lang.String
		// @55: dup_x1
		// @56: swap
		// @57: invokespecial java.lang.String.<init>(char[])void
		// @5A: invokevirtual java.lang.String.intern()java.lang.String
		// @5D: areturn
	}
}
