package game;

import java.applet.Applet;

final class C_100270_mi extends C_100302_ka
{
	private C_100037_wb[] field_102265_Xb;
	private int field_102264_Zb;
	static long[] field_102262_dc;
	static boolean field_102276_Vb;
	private int[] field_102274_Ub;
	static String field_102281_bc;
	private C_100302_ka field_102277_nc;
	static int field_102282_cc;
	private C_100302_ka field_102269_fc;
	private C_100144_bm[] field_102275_mc;
	private int field_102267_Yb;
	static C_100037_wb field_102271_Wb;
	static String field_102279_ac;
	private int field_102272_ic;
	static String field_102268_ec;
	private int field_102266_hc;
	private int field_102278_kc;
	static int field_102270_jc;
	private int field_102263_gc;
	private int field_102280_lc;
	private static final String[] field_102273_oc;
	
	static final String func_102260_a(byte arg0, CharSequence[] arg1)
	{
		// @00: iload_0
		// @01: bipush 52 (0x34)
		// @03: if_icmpgt @10
		// @06: bipush 6 (0x06)
		// @08: iconst_1
		// @09: invokestatic game.C_100270_mi.func_102255_b(int, boolean)void
		// @0C: goto @10
		// @0F: athrow
		// @10: bipush -58 (0xC6)
		// @12: aload_1
		// @13: arraylength
		// @14: aload_1
		// @15: iconst_0
		// @16: invokestatic game.C_100162_sc.func_102849_a(byte, int, java.lang.CharSequence[], int)java.lang.String
		// @19: areturn
		// @1A: astore_2
		// @1B: aload_2
		// @1C: new java.lang.StringBuilder
		// @1F: dup
		// @20: invokespecial java.lang.StringBuilder.<init>()void
		// @23: getstatic java.lang.String[] game.C_100270_mi.field_102273_oc
		// @26: iconst_3
		// @27: aaload
		// @28: invokevirtual java.lang.StringBuilder.append(java.lang.String)java.lang.StringBuilder
		// @2B: iload_0
		// @2C: invokevirtual java.lang.StringBuilder.append(int)java.lang.StringBuilder
		// @2F: bipush 44 (0x2C)
		// @31: invokevirtual java.lang.StringBuilder.append(char)java.lang.StringBuilder
		// @34: aload_1
		// @35: ifnull @41
		// @38: getstatic java.lang.String[] game.C_100270_mi.field_102273_oc
		// @3B: iconst_2
		// @3C: aaload
		// @3D: goto @46
		// @40: athrow
		// @41: getstatic java.lang.String[] game.C_100270_mi.field_102273_oc
		// @44: iconst_1
		// @45: aaload
		// @46: invokevirtual java.lang.StringBuilder.append(java.lang.String)java.lang.StringBuilder
		// @49: bipush 41 (0x29)
		// @4B: invokevirtual java.lang.StringBuilder.append(char)java.lang.StringBuilder
		// @4E: invokevirtual java.lang.StringBuilder.toString()java.lang.String
		// @51: invokestatic game.C_100181_cf.func_105695_a(java.lang.Throwable, java.lang.String)game.C_100170_cm
		// @54: athrow
	}
	
	static final boolean func_102256_a(boolean arg0, int arg1, CharSequence arg2)
	{
		// @000: getstatic int game.SteelSentinels.field_105275_O
		// @003: istore #8
		// @005: aload_2
		// @006: ifnull @00D
		// @009: goto @00F
		// @00C: athrow
		// @00D: iconst_0
		// @00E: ireturn
		// @00F: aload_2
		// @010: invokeinterface java.lang.CharSequence.length()int
		// @015: istore_3
		// @016: bipush -2 (0xFE)
		// @018: iload_3
		// @019: iconst_m1
		// @01A: ixor
		// @01B: if_icmplt @02A
		// @01E: iload_3
		// @01F: iconst_m1
		// @020: ixor
		// @021: bipush -13 (0xF3)
		// @023: if_icmpge @02C
		// @026: goto @02A
		// @029: athrow
		// @02A: iconst_0
		// @02B: ireturn
		// @02C: bipush 75 (0x4B)
		// @02E: aload_2
		// @02F: invokestatic game.C_100106_ef.func_104742_a(byte, java.lang.CharSequence)java.lang.String
		// @032: astore #4
		// @034: aload #4
		// @036: ifnull @04D
		// @039: bipush -2 (0xFE)
		// @03B: aload #4
		// @03D: invokevirtual java.lang.String.length()int
		// @040: iconst_m1
		// @041: ixor
		// @042: if_icmplt @04D
		// @045: goto @049
		// @048: athrow
		// @049: goto @04F
		// @04C: athrow
		// @04D: iconst_0
		// @04E: ireturn
		// @04F: bipush -96 (0xA0)
		// @051: aload #4
		// @053: iload_1
		// @054: invokevirtual java.lang.String.charAt(int)char
		// @057: invokestatic game.C_100053_vn.func_102812_a(int, char)boolean
		// @05A: ifne @07B
		// @05D: iload_1
		// @05E: bipush -96 (0xA0)
		// @060: iadd
		// @061: aload #4
		// @063: iconst_m1
		// @064: aload #4
		// @066: invokevirtual java.lang.String.length()int
		// @069: iadd
		// @06A: invokevirtual java.lang.String.charAt(int)char
		// @06D: invokestatic game.C_100053_vn.func_102812_a(int, char)boolean
		// @070: ifne @07B
		// @073: goto @077
		// @076: athrow
		// @077: goto @07D
		// @07A: athrow
		// @07B: iconst_0
		// @07C: ireturn
		// @07D: iconst_0
		// @07E: istore #5
		// @080: iconst_0
		// @081: istore #6
		// @083: aload_2
		// @084: invokeinterface java.lang.CharSequence.length()int
		// @089: iload #6
		// @08B: if_icmple @0D8
		// @08E: aload_2
		// @08F: iload #6
		// @091: invokeinterface java.lang.CharSequence.charAt(int)char
		// @096: istore #7
		// @098: iload_1
		// @099: bipush -96 (0xA0)
		// @09B: iadd
		// @09C: iload #7
		// @09E: invokestatic game.C_100053_vn.func_102812_a(int, char)boolean
		// @0A1: iload #8
		// @0A3: ifne @0DA
		// @0A6: ifne @0B5
		// @0A9: goto @0AD
		// @0AC: athrow
		// @0AD: iconst_0
		// @0AE: istore #5
		// @0B0: iload #8
		// @0B2: ifeq @0BC
		// @0B5: iinc #5 +1
		// @0B8: goto @0BC
		// @0BB: athrow
		// @0BC: iload #5
		// @0BE: iconst_2
		// @0BF: if_icmplt @0D0
		// @0C2: iload_0
		// @0C3: ifeq @0CE
		// @0C6: goto @0CA
		// @0C9: athrow
		// @0CA: goto @0D0
		// @0CD: athrow
		// @0CE: iconst_0
		// @0CF: ireturn
		// @0D0: iinc #6 +1
		// @0D3: iload #8
		// @0D5: ifeq @083
		// @0D8: iload #5
		// @0DA: ifle @0DF
		// @0DD: iconst_0
		// @0DE: ireturn
		// @0DF: iconst_1
		// @0E0: ireturn
		// @0E1: astore_3
		// @0E2: aload_3
		// @0E3: new java.lang.StringBuilder
		// @0E6: dup
		// @0E7: invokespecial java.lang.StringBuilder.<init>()void
		// @0EA: getstatic java.lang.String[] game.C_100270_mi.field_102273_oc
		// @0ED: bipush 10 (0x0A)
		// @0EF: aaload
		// @0F0: invokevirtual java.lang.StringBuilder.append(java.lang.String)java.lang.StringBuilder
		// @0F3: iload_0
		// @0F4: invokevirtual java.lang.StringBuilder.append(boolean)java.lang.StringBuilder
		// @0F7: bipush 44 (0x2C)
		// @0F9: invokevirtual java.lang.StringBuilder.append(char)java.lang.StringBuilder
		// @0FC: iload_1
		// @0FD: invokevirtual java.lang.StringBuilder.append(int)java.lang.StringBuilder
		// @100: bipush 44 (0x2C)
		// @102: invokevirtual java.lang.StringBuilder.append(char)java.lang.StringBuilder
		// @105: aload_2
		// @106: ifnull @112
		// @109: getstatic java.lang.String[] game.C_100270_mi.field_102273_oc
		// @10C: iconst_2
		// @10D: aaload
		// @10E: goto @117
		// @111: athrow
		// @112: getstatic java.lang.String[] game.C_100270_mi.field_102273_oc
		// @115: iconst_1
		// @116: aaload
		// @117: invokevirtual java.lang.StringBuilder.append(java.lang.String)java.lang.StringBuilder
		// @11A: bipush 41 (0x29)
		// @11C: invokevirtual java.lang.StringBuilder.append(char)java.lang.StringBuilder
		// @11F: invokevirtual java.lang.StringBuilder.toString()java.lang.String
		// @122: invokestatic game.C_100181_cf.func_105695_a(java.lang.Throwable, java.lang.String)game.C_100170_cm
		// @125: athrow
	}
	
	final void func_102250_a(int arg0, int arg1, String arg2)
	{
		// @00: aload_0
		// @01: getfield game.C_100144_bm[] game.C_100270_mi.field_102275_mc
		// @04: aload_0
		// @05: getfield int game.C_100270_mi.field_102280_lc
		// @08: new game.C_100144_bm
		// @0B: dup
		// @0C: lconst_0
		// @0D: aconst_null
		// @0E: aconst_null
		// @0F: aload_0
		// @10: getfield game.C_100302_ka game.C_100270_mi.field_102269_fc
		// @13: aconst_null
		// @14: aload_3
		// @15: invokespecial game.C_100144_bm.<init>(long, game.C_100302_ka, game.C_100302_ka, game.C_100302_ka, game.C_100037_wb, java.lang.String)void
		// @18: aastore
		// @19: aload_0
		// @1A: getfield game.C_100144_bm[] game.C_100270_mi.field_102275_mc
		// @1D: aload_0
		// @1E: getfield int game.C_100270_mi.field_102280_lc
		// @21: aaload
		// @22: aload_0
		// @23: getfield game.C_100037_wb[] game.C_100270_mi.field_102265_Xb
		// @26: putfield game.C_100037_wb[] game.C_100144_bm.field_101883_qb
		// @29: iload_1
		// @2A: bipush 52 (0x34)
		// @2C: if_icmpgt @38
		// @2F: bipush 31 (0x1F)
		// @31: invokestatic game.C_100270_mi.func_102249_l(int)void
		// @34: goto @38
		// @37: athrow
		// @38: aload_0
		// @39: getfield game.C_100144_bm[] game.C_100270_mi.field_102275_mc
		// @3C: aload_0
		// @3D: getfield int game.C_100270_mi.field_102280_lc
		// @40: aaload
		// @41: iconst_1
		// @42: putfield boolean game.C_100144_bm.field_101881_yb
		// @45: aload_0
		// @46: getfield game.C_100144_bm[] game.C_100270_mi.field_102275_mc
		// @49: aload_0
		// @4A: getfield int game.C_100270_mi.field_102280_lc
		// @4D: aaload
		// @4E: iconst_1
		// @4F: putfield int game.C_100144_bm.field_101858_J
		// @52: aload_0
		// @53: bipush -102 (0x9A)
		// @55: aload_0
		// @56: getfield game.C_100144_bm[] game.C_100270_mi.field_102275_mc
		// @59: aload_0
		// @5A: getfield int game.C_100270_mi.field_102280_lc
		// @5D: aaload
		// @5E: invokevirtual game.C_100270_mi.func_101824_b(int, game.C_100302_ka)void
		// @61: aload_0
		// @62: getfield int[] game.C_100270_mi.field_102274_Ub
		// @65: aload_0
		// @66: getfield int game.C_100270_mi.field_102280_lc
		// @69: iload_2
		// @6A: iastore
		// @6B: aload_0
		// @6C: dup
		// @6D: getfield int game.C_100270_mi.field_102280_lc
		// @70: iconst_1
		// @71: iadd
		// @72: putfield int game.C_100270_mi.field_102280_lc
		// @75: goto @BE
		// @78: astore #4
		// @7A: aload #4
		// @7C: new java.lang.StringBuilder
		// @7F: dup
		// @80: invokespecial java.lang.StringBuilder.<init>()void
		// @83: getstatic java.lang.String[] game.C_100270_mi.field_102273_oc
		// @86: iconst_4
		// @87: aaload
		// @88: invokevirtual java.lang.StringBuilder.append(java.lang.String)java.lang.StringBuilder
		// @8B: iload_1
		// @8C: invokevirtual java.lang.StringBuilder.append(int)java.lang.StringBuilder
		// @8F: bipush 44 (0x2C)
		// @91: invokevirtual java.lang.StringBuilder.append(char)java.lang.StringBuilder
		// @94: iload_2
		// @95: invokevirtual java.lang.StringBuilder.append(int)java.lang.StringBuilder
		// @98: bipush 44 (0x2C)
		// @9A: invokevirtual java.lang.StringBuilder.append(char)java.lang.StringBuilder
		// @9D: aload_3
		// @9E: ifnull @AA
		// @A1: getstatic java.lang.String[] game.C_100270_mi.field_102273_oc
		// @A4: iconst_2
		// @A5: aaload
		// @A6: goto @AF
		// @A9: athrow
		// @AA: getstatic java.lang.String[] game.C_100270_mi.field_102273_oc
		// @AD: iconst_1
		// @AE: aaload
		// @AF: invokevirtual java.lang.StringBuilder.append(java.lang.String)java.lang.StringBuilder
		// @B2: bipush 41 (0x29)
		// @B4: invokevirtual java.lang.StringBuilder.append(char)java.lang.StringBuilder
		// @B7: invokevirtual java.lang.StringBuilder.toString()java.lang.String
		// @BA: invokestatic game.C_100181_cf.func_105695_a(java.lang.Throwable, java.lang.String)game.C_100170_cm
		// @BD: athrow
		// @BE: return
	}
	
	C_100270_mi(C_100302_ka arg0, C_100037_wb[] arg1, C_100302_ka arg2, C_100302_ka arg3, int arg4, int arg5, int arg6, int arg7, int arg8)
	{
		// @000: aload_0
		// @001: lconst_0
		// @002: aload_1
		// @003: invokespecial game.C_100302_ka.<init>(long, game.C_100302_ka)void
		// @006: aload_0
		// @007: sipush 256 (0x0100)
		// @00A: newarray int[]
		// @00C: putfield int[] game.C_100270_mi.field_102274_Ub
		// @00F: aload_0
		// @010: sipush 256 (0x0100)
		// @013: anewarray game.C_100144_bm
		// @016: putfield game.C_100144_bm[] game.C_100270_mi.field_102275_mc
		// @019: aload_0
		// @01A: bipush -2 (0xFE)
		// @01C: putfield int game.C_100270_mi.field_102272_ic
		// @01F: aload_0
		// @020: iload #7
		// @022: putfield int game.C_100270_mi.field_102267_Yb
		// @025: aload_0
		// @026: iload #6
		// @028: putfield int game.C_100270_mi.field_102263_gc
		// @02B: aload_0
		// @02C: iload #8
		// @02E: putfield int game.C_100270_mi.field_102264_Zb
		// @031: aload_0
		// @032: iload #5
		// @034: putfield int game.C_100270_mi.field_102278_kc
		// @037: aload_0
		// @038: aload #4
		// @03A: putfield game.C_100302_ka game.C_100270_mi.field_102269_fc
		// @03D: aload_0
		// @03E: aload_3
		// @03F: putfield game.C_100302_ka game.C_100270_mi.field_102277_nc
		// @042: aload_0
		// @043: iload #9
		// @045: putfield int game.C_100270_mi.field_102266_hc
		// @048: aload_0
		// @049: aload_2
		// @04A: putfield game.C_100037_wb[] game.C_100270_mi.field_102265_Xb
		// @04D: goto @106
		// @050: astore #10
		// @052: aload #10
		// @054: new java.lang.StringBuilder
		// @057: dup
		// @058: invokespecial java.lang.StringBuilder.<init>()void
		// @05B: getstatic java.lang.String[] game.C_100270_mi.field_102273_oc
		// @05E: bipush 9 (0x09)
		// @060: aaload
		// @061: invokevirtual java.lang.StringBuilder.append(java.lang.String)java.lang.StringBuilder
		// @064: aload_1
		// @065: ifnull @071
		// @068: getstatic java.lang.String[] game.C_100270_mi.field_102273_oc
		// @06B: iconst_2
		// @06C: aaload
		// @06D: goto @076
		// @070: athrow
		// @071: getstatic java.lang.String[] game.C_100270_mi.field_102273_oc
		// @074: iconst_1
		// @075: aaload
		// @076: invokevirtual java.lang.StringBuilder.append(java.lang.String)java.lang.StringBuilder
		// @079: bipush 44 (0x2C)
		// @07B: invokevirtual java.lang.StringBuilder.append(char)java.lang.StringBuilder
		// @07E: aload_2
		// @07F: ifnull @08B
		// @082: getstatic java.lang.String[] game.C_100270_mi.field_102273_oc
		// @085: iconst_2
		// @086: aaload
		// @087: goto @090
		// @08A: athrow
		// @08B: getstatic java.lang.String[] game.C_100270_mi.field_102273_oc
		// @08E: iconst_1
		// @08F: aaload
		// @090: invokevirtual java.lang.StringBuilder.append(java.lang.String)java.lang.StringBuilder
		// @093: bipush 44 (0x2C)
		// @095: invokevirtual java.lang.StringBuilder.append(char)java.lang.StringBuilder
		// @098: aload_3
		// @099: ifnull @0A5
		// @09C: getstatic java.lang.String[] game.C_100270_mi.field_102273_oc
		// @09F: iconst_2
		// @0A0: aaload
		// @0A1: goto @0AA
		// @0A4: athrow
		// @0A5: getstatic java.lang.String[] game.C_100270_mi.field_102273_oc
		// @0A8: iconst_1
		// @0A9: aaload
		// @0AA: invokevirtual java.lang.StringBuilder.append(java.lang.String)java.lang.StringBuilder
		// @0AD: bipush 44 (0x2C)
		// @0AF: invokevirtual java.lang.StringBuilder.append(char)java.lang.StringBuilder
		// @0B2: aload #4
		// @0B4: ifnull @0C0
		// @0B7: getstatic java.lang.String[] game.C_100270_mi.field_102273_oc
		// @0BA: iconst_2
		// @0BB: aaload
		// @0BC: goto @0C5
		// @0BF: athrow
		// @0C0: getstatic java.lang.String[] game.C_100270_mi.field_102273_oc
		// @0C3: iconst_1
		// @0C4: aaload
		// @0C5: invokevirtual java.lang.StringBuilder.append(java.lang.String)java.lang.StringBuilder
		// @0C8: bipush 44 (0x2C)
		// @0CA: invokevirtual java.lang.StringBuilder.append(char)java.lang.StringBuilder
		// @0CD: iload #5
		// @0CF: invokevirtual java.lang.StringBuilder.append(int)java.lang.StringBuilder
		// @0D2: bipush 44 (0x2C)
		// @0D4: invokevirtual java.lang.StringBuilder.append(char)java.lang.StringBuilder
		// @0D7: iload #6
		// @0D9: invokevirtual java.lang.StringBuilder.append(int)java.lang.StringBuilder
		// @0DC: bipush 44 (0x2C)
		// @0DE: invokevirtual java.lang.StringBuilder.append(char)java.lang.StringBuilder
		// @0E1: iload #7
		// @0E3: invokevirtual java.lang.StringBuilder.append(int)java.lang.StringBuilder
		// @0E6: bipush 44 (0x2C)
		// @0E8: invokevirtual java.lang.StringBuilder.append(char)java.lang.StringBuilder
		// @0EB: iload #8
		// @0ED: invokevirtual java.lang.StringBuilder.append(int)java.lang.StringBuilder
		// @0F0: bipush 44 (0x2C)
		// @0F2: invokevirtual java.lang.StringBuilder.append(char)java.lang.StringBuilder
		// @0F5: iload #9
		// @0F7: invokevirtual java.lang.StringBuilder.append(int)java.lang.StringBuilder
		// @0FA: bipush 41 (0x29)
		// @0FC: invokevirtual java.lang.StringBuilder.append(char)java.lang.StringBuilder
		// @0FF: invokevirtual java.lang.StringBuilder.toString()java.lang.String
		// @102: invokestatic game.C_100181_cf.func_105695_a(java.lang.Throwable, java.lang.String)game.C_100170_cm
		// @105: athrow
		// @106: return
	}
	
	final void func_102261_b(int arg0, int arg1, int arg2, int arg3, int arg4)
	{
		// @000: getstatic int game.SteelSentinels.field_105275_O
		// @003: istore #11
		// @005: iconst_m1
		// @006: aload_0
		// @007: getfield int game.C_100270_mi.field_102280_lc
		// @00A: iconst_m1
		// @00B: ixor
		// @00C: if_icmpeq @013
		// @00F: goto @05E
		// @012: athrow
		// @013: aload_0
		// @014: getfield game.C_100144_bm[] game.C_100270_mi.field_102275_mc
		// @017: aload_0
		// @018: getfield int game.C_100270_mi.field_102280_lc
		// @01B: new game.C_100144_bm
		// @01E: dup
		// @01F: lconst_0
		// @020: aconst_null
		// @021: aconst_null
		// @022: aload_0
		// @023: getfield game.C_100302_ka game.C_100270_mi.field_102277_nc
		// @026: aconst_null
		// @027: getstatic java.lang.String game.C_100119_ua.field_104904_a
		// @02A: invokespecial game.C_100144_bm.<init>(long, game.C_100302_ka, game.C_100302_ka, game.C_100302_ka, game.C_100037_wb, java.lang.String)void
		// @02D: aastore
		// @02E: aload_0
		// @02F: getfield game.C_100144_bm[] game.C_100270_mi.field_102275_mc
		// @032: aload_0
		// @033: getfield int game.C_100270_mi.field_102280_lc
		// @036: aaload
		// @037: iconst_1
		// @038: putfield int game.C_100144_bm.field_101858_J
		// @03B: aload_0
		// @03C: bipush -98 (0x9E)
		// @03E: aload_0
		// @03F: getfield game.C_100144_bm[] game.C_100270_mi.field_102275_mc
		// @042: aload_0
		// @043: getfield int game.C_100270_mi.field_102280_lc
		// @046: aaload
		// @047: invokevirtual game.C_100270_mi.func_101824_b(int, game.C_100302_ka)void
		// @04A: aload_0
		// @04B: getfield int[] game.C_100270_mi.field_102274_Ub
		// @04E: aload_0
		// @04F: getfield int game.C_100270_mi.field_102280_lc
		// @052: iconst_m1
		// @053: iastore
		// @054: aload_0
		// @055: dup
		// @056: getfield int game.C_100270_mi.field_102280_lc
		// @059: iconst_1
		// @05A: iadd
		// @05B: putfield int game.C_100270_mi.field_102280_lc
		// @05E: iconst_0
		// @05F: istore #6
		// @061: iconst_0
		// @062: istore #7
		// @064: aload_0
		// @065: getfield int game.C_100270_mi.field_102280_lc
		// @068: iconst_m1
		// @069: ixor
		// @06A: iload #7
		// @06C: iconst_m1
		// @06D: ixor
		// @06E: if_icmpge @0A7
		// @071: aload_0
		// @072: getfield game.C_100144_bm[] game.C_100270_mi.field_102275_mc
		// @075: iload #7
		// @077: aaload
		// @078: aload_0
		// @079: getfield int game.C_100270_mi.field_102263_gc
		// @07C: sipush 23958 (0x5D96)
		// @07F: aload_0
		// @080: getfield int game.C_100270_mi.field_102267_Yb
		// @083: invokevirtual game.C_100144_bm.func_102084_a(int, int, int)int
		// @086: istore #8
		// @088: iload #6
		// @08A: iload #8
		// @08C: iload #11
		// @08E: ifne @0D6
		// @091: if_icmplt @09B
		// @094: goto @098
		// @097: athrow
		// @098: goto @09F
		// @09B: iload #8
		// @09D: istore #6
		// @09F: iinc #7 +1
		// @0A2: iload #11
		// @0A4: ifeq @064
		// @0A7: iload #6
		// @0A9: aload_0
		// @0AA: getfield int game.C_100270_mi.field_102278_kc
		// @0AD: iconst_2
		// @0AE: imul
		// @0AF: iadd
		// @0B0: istore #6
		// @0B2: aload_0
		// @0B3: getfield int game.C_100270_mi.field_102264_Zb
		// @0B6: aload_0
		// @0B7: getfield int game.C_100270_mi.field_102280_lc
		// @0BA: aload_0
		// @0BB: getfield int game.C_100270_mi.field_102266_hc
		// @0BE: imul
		// @0BF: ineg
		// @0C0: isub
		// @0C1: aload_0
		// @0C2: getfield int game.C_100270_mi.field_102264_Zb
		// @0C5: iadd
		// @0C6: istore #7
		// @0C8: iload #5
		// @0CA: iload_1
		// @0CB: iload #6
		// @0CD: iconst_m1
		// @0CE: invokestatic game.C_100211_qd.func_102123_a(int, int, int, int)int
		// @0D1: istore #8
		// @0D3: iload_3
		// @0D4: iload #7
		// @0D6: sipush -19295 (0xB4A1)
		// @0D9: iload_2
		// @0DA: invokestatic game.C_100257_ln.func_106471_a(int, int, int, int)int
		// @0DD: istore #9
		// @0DF: aload_0
		// @0E0: iload #8
		// @0E2: iload #7
		// @0E4: iconst_m1
		// @0E5: iload #9
		// @0E7: iload #6
		// @0E9: invokevirtual game.C_100270_mi.func_101825_a(int, int, int, int, int)void
		// @0EC: iconst_0
		// @0ED: istore #10
		// @0EF: iload #4
		// @0F1: bipush 41 (0x29)
		// @0F3: if_icmpge @102
		// @0F6: aload_0
		// @0F7: aconst_null
		// @0F8: checkcast game.C_100302_ka
		// @0FB: putfield game.C_100302_ka game.C_100270_mi.field_102269_fc
		// @0FE: goto @102
		// @101: athrow
		// @102: iload #10
		// @104: iconst_m1
		// @105: ixor
		// @106: aload_0
		// @107: getfield int game.C_100270_mi.field_102280_lc
		// @10A: iconst_m1
		// @10B: ixor
		// @10C: if_icmple @153
		// @10F: aload_0
		// @110: getfield game.C_100144_bm[] game.C_100270_mi.field_102275_mc
		// @113: iload #10
		// @115: aaload
		// @116: aload_0
		// @117: getfield int game.C_100270_mi.field_102278_kc
		// @11A: aload_0
		// @11B: getfield int game.C_100270_mi.field_102263_gc
		// @11E: aload_0
		// @11F: getfield int game.C_100270_mi.field_102266_hc
		// @122: aload_0
		// @123: getfield int game.C_100270_mi.field_102267_Yb
		// @126: sipush 2532 (0x09E4)
		// @129: iconst_2
		// @12A: aload_0
		// @12B: getfield int game.C_100270_mi.field_102278_kc
		// @12E: imul
		// @12F: ineg
		// @130: iload #6
		// @132: iadd
		// @133: aload_0
		// @134: getfield int game.C_100270_mi.field_102264_Zb
		// @137: aload_0
		// @138: getfield int game.C_100270_mi.field_102266_hc
		// @13B: iload #10
		// @13D: imul
		// @13E: iadd
		// @13F: invokevirtual game.C_100144_bm.func_102086_a(int, int, int, int, int, int, int)void
		// @142: iinc #10 +1
		// @145: iload #11
		// @147: ifne @1A0
		// @14A: iload #11
		// @14C: ifeq @102
		// @14F: goto @153
		// @152: athrow
		// @153: goto @1A0
		// @156: astore #6
		// @158: aload #6
		// @15A: new java.lang.StringBuilder
		// @15D: dup
		// @15E: invokespecial java.lang.StringBuilder.<init>()void
		// @161: getstatic java.lang.String[] game.C_100270_mi.field_102273_oc
		// @164: bipush 12 (0x0C)
		// @166: aaload
		// @167: invokevirtual java.lang.StringBuilder.append(java.lang.String)java.lang.StringBuilder
		// @16A: iload_1
		// @16B: invokevirtual java.lang.StringBuilder.append(int)java.lang.StringBuilder
		// @16E: bipush 44 (0x2C)
		// @170: invokevirtual java.lang.StringBuilder.append(char)java.lang.StringBuilder
		// @173: iload_2
		// @174: invokevirtual java.lang.StringBuilder.append(int)java.lang.StringBuilder
		// @177: bipush 44 (0x2C)
		// @179: invokevirtual java.lang.StringBuilder.append(char)java.lang.StringBuilder
		// @17C: iload_3
		// @17D: invokevirtual java.lang.StringBuilder.append(int)java.lang.StringBuilder
		// @180: bipush 44 (0x2C)
		// @182: invokevirtual java.lang.StringBuilder.append(char)java.lang.StringBuilder
		// @185: iload #4
		// @187: invokevirtual java.lang.StringBuilder.append(int)java.lang.StringBuilder
		// @18A: bipush 44 (0x2C)
		// @18C: invokevirtual java.lang.StringBuilder.append(char)java.lang.StringBuilder
		// @18F: iload #5
		// @191: invokevirtual java.lang.StringBuilder.append(int)java.lang.StringBuilder
		// @194: bipush 41 (0x29)
		// @196: invokevirtual java.lang.StringBuilder.append(char)java.lang.StringBuilder
		// @199: invokevirtual java.lang.StringBuilder.toString()java.lang.String
		// @19C: invokestatic game.C_100181_cf.func_105695_a(java.lang.Throwable, java.lang.String)game.C_100170_cm
		// @19F: athrow
		// @1A0: return
	}
	
	final int func_102248_a(int arg0, boolean arg1)
	{
		// @00: getstatic int game.SteelSentinels.field_105275_O
		// @03: istore #4
		// @05: aload_0
		// @06: iload_2
		// @07: bipush 30 (0x1E)
		// @09: invokevirtual game.C_100270_mi.func_101819_a(boolean, byte)void
		// @0C: iload_2
		// @0D: ifne @13
		// @10: bipush -2 (0xFE)
		// @12: ireturn
		// @13: iconst_0
		// @14: istore_3
		// @15: iload_1
		// @16: sipush -26142 (0x99E2)
		// @19: if_icmpeq @26
		// @1C: aload_0
		// @1D: bipush -64 (0xC0)
		// @1F: putfield int game.C_100270_mi.field_102267_Yb
		// @22: goto @26
		// @25: athrow
		// @26: iload_3
		// @27: aload_0
		// @28: getfield int game.C_100270_mi.field_102280_lc
		// @2B: if_icmpge @55
		// @2E: aload_0
		// @2F: getfield game.C_100144_bm[] game.C_100270_mi.field_102275_mc
		// @32: iload_3
		// @33: aaload
		// @34: getfield int game.C_100144_bm.field_101854_N
		// @37: iconst_m1
		// @38: ixor
		// @39: iconst_m1
		// @3A: iload #4
		// @3C: ifne @5B
		// @3F: if_icmpeq @4D
		// @42: goto @46
		// @45: athrow
		// @46: aload_0
		// @47: getfield int[] game.C_100270_mi.field_102274_Ub
		// @4A: iload_3
		// @4B: iaload
		// @4C: ireturn
		// @4D: iinc #3 +1
		// @50: iload #4
		// @52: ifeq @26
		// @55: iconst_m1
		// @56: getstatic int game.C_100102_w.field_104636_c
		// @59: iconst_m1
		// @5A: ixor
		// @5B: if_icmpeq @60
		// @5E: iconst_m1
		// @5F: ireturn
		// @60: aload_0
		// @61: getfield int game.C_100270_mi.field_102272_ic
		// @64: ireturn
		// @65: astore_3
		// @66: aload_3
		// @67: new java.lang.StringBuilder
		// @6A: dup
		// @6B: invokespecial java.lang.StringBuilder.<init>()void
		// @6E: getstatic java.lang.String[] game.C_100270_mi.field_102273_oc
		// @71: bipush 11 (0x0B)
		// @73: aaload
		// @74: invokevirtual java.lang.StringBuilder.append(java.lang.String)java.lang.StringBuilder
		// @77: iload_1
		// @78: invokevirtual java.lang.StringBuilder.append(int)java.lang.StringBuilder
		// @7B: bipush 44 (0x2C)
		// @7D: invokevirtual java.lang.StringBuilder.append(char)java.lang.StringBuilder
		// @80: iload_2
		// @81: invokevirtual java.lang.StringBuilder.append(boolean)java.lang.StringBuilder
		// @84: bipush 41 (0x29)
		// @86: invokevirtual java.lang.StringBuilder.append(char)java.lang.StringBuilder
		// @89: invokevirtual java.lang.StringBuilder.toString()java.lang.String
		// @8C: invokestatic game.C_100181_cf.func_105695_a(java.lang.Throwable, java.lang.String)game.C_100170_cm
		// @8F: athrow
	}
	
	final void func_102257_a(C_100037_wb arg0, int arg1, int arg2, String arg3)
	{
		// @00: iload_2
		// @01: bipush -43 (0xD5)
		// @03: if_icmplt @07
		// @06: return
		// @07: aload_0
		// @08: getfield game.C_100144_bm[] game.C_100270_mi.field_102275_mc
		// @0B: aload_0
		// @0C: getfield int game.C_100270_mi.field_102280_lc
		// @0F: new game.C_100144_bm
		// @12: dup
		// @13: lconst_0
		// @14: aconst_null
		// @15: aconst_null
		// @16: aload_0
		// @17: getfield game.C_100302_ka game.C_100270_mi.field_102269_fc
		// @1A: aload_1
		// @1B: aload #4
		// @1D: invokespecial game.C_100144_bm.<init>(long, game.C_100302_ka, game.C_100302_ka, game.C_100302_ka, game.C_100037_wb, java.lang.String)void
		// @20: aastore
		// @21: aload_0
		// @22: getfield game.C_100144_bm[] game.C_100270_mi.field_102275_mc
		// @25: aload_0
		// @26: getfield int game.C_100270_mi.field_102280_lc
		// @29: aaload
		// @2A: aload_0
		// @2B: getfield game.C_100037_wb[] game.C_100270_mi.field_102265_Xb
		// @2E: putfield game.C_100037_wb[] game.C_100144_bm.field_101883_qb
		// @31: aload_0
		// @32: getfield game.C_100144_bm[] game.C_100270_mi.field_102275_mc
		// @35: aload_0
		// @36: getfield int game.C_100270_mi.field_102280_lc
		// @39: aaload
		// @3A: iconst_1
		// @3B: putfield boolean game.C_100144_bm.field_101881_yb
		// @3E: aload_0
		// @3F: getfield game.C_100144_bm[] game.C_100270_mi.field_102275_mc
		// @42: aload_0
		// @43: getfield int game.C_100270_mi.field_102280_lc
		// @46: aaload
		// @47: iconst_1
		// @48: putfield int game.C_100144_bm.field_101858_J
		// @4B: aload_0
		// @4C: bipush -72 (0xB8)
		// @4E: aload_0
		// @4F: getfield game.C_100144_bm[] game.C_100270_mi.field_102275_mc
		// @52: aload_0
		// @53: getfield int game.C_100270_mi.field_102280_lc
		// @56: aaload
		// @57: invokevirtual game.C_100270_mi.func_101824_b(int, game.C_100302_ka)void
		// @5A: aload_0
		// @5B: getfield int[] game.C_100270_mi.field_102274_Ub
		// @5E: aload_0
		// @5F: getfield int game.C_100270_mi.field_102280_lc
		// @62: iload_3
		// @63: iastore
		// @64: aload_0
		// @65: dup
		// @66: getfield int game.C_100270_mi.field_102280_lc
		// @69: iconst_1
		// @6A: iadd
		// @6B: putfield int game.C_100270_mi.field_102280_lc
		// @6E: goto @D3
		// @71: astore #5
		// @73: aload #5
		// @75: new java.lang.StringBuilder
		// @78: dup
		// @79: invokespecial java.lang.StringBuilder.<init>()void
		// @7C: getstatic java.lang.String[] game.C_100270_mi.field_102273_oc
		// @7F: bipush 13 (0x0D)
		// @81: aaload
		// @82: invokevirtual java.lang.StringBuilder.append(java.lang.String)java.lang.StringBuilder
		// @85: aload_1
		// @86: ifnull @92
		// @89: getstatic java.lang.String[] game.C_100270_mi.field_102273_oc
		// @8C: iconst_2
		// @8D: aaload
		// @8E: goto @97
		// @91: athrow
		// @92: getstatic java.lang.String[] game.C_100270_mi.field_102273_oc
		// @95: iconst_1
		// @96: aaload
		// @97: invokevirtual java.lang.StringBuilder.append(java.lang.String)java.lang.StringBuilder
		// @9A: bipush 44 (0x2C)
		// @9C: invokevirtual java.lang.StringBuilder.append(char)java.lang.StringBuilder
		// @9F: iload_2
		// @A0: invokevirtual java.lang.StringBuilder.append(int)java.lang.StringBuilder
		// @A3: bipush 44 (0x2C)
		// @A5: invokevirtual java.lang.StringBuilder.append(char)java.lang.StringBuilder
		// @A8: iload_3
		// @A9: invokevirtual java.lang.StringBuilder.append(int)java.lang.StringBuilder
		// @AC: bipush 44 (0x2C)
		// @AE: invokevirtual java.lang.StringBuilder.append(char)java.lang.StringBuilder
		// @B1: aload #4
		// @B3: ifnull @BF
		// @B6: getstatic java.lang.String[] game.C_100270_mi.field_102273_oc
		// @B9: iconst_2
		// @BA: aaload
		// @BB: goto @C4
		// @BE: athrow
		// @BF: getstatic java.lang.String[] game.C_100270_mi.field_102273_oc
		// @C2: iconst_1
		// @C3: aaload
		// @C4: invokevirtual java.lang.StringBuilder.append(java.lang.String)java.lang.StringBuilder
		// @C7: bipush 41 (0x29)
		// @C9: invokevirtual java.lang.StringBuilder.append(char)java.lang.StringBuilder
		// @CC: invokevirtual java.lang.StringBuilder.toString()java.lang.String
		// @CF: invokestatic game.C_100181_cf.func_105695_a(java.lang.Throwable, java.lang.String)game.C_100170_cm
		// @D2: athrow
		// @D3: return
	}
	
	static final void func_102259_a(int arg0, int arg1)
	{
		// @00: getstatic game.C_100278_nd game.C_100115_ej.field_102043_Yb
		// @03: astore_2
		// @04: aload_2
		// @05: iload_1
		// @06: iload_0
		// @07: bipush 108 (0x6C)
		// @09: iadd
		// @0A: invokevirtual game.C_100278_nd.func_101189_h(int, int)void
		// @0D: aload_2
		// @0E: dup
		// @0F: getfield int game.C_100278_nd.field_101177_n
		// @12: iconst_1
		// @13: iadd
		// @14: putfield int game.C_100278_nd.field_101177_n
		// @17: aload_2
		// @18: getfield int game.C_100278_nd.field_101177_n
		// @1B: istore_3
		// @1C: aload_2
		// @1D: sipush 7838 (0x1E9E)
		// @20: iload_0
		// @21: invokevirtual game.C_100278_nd.func_101169_f(int, int)void
		// @24: aload_2
		// @25: getstatic byte[] game.C_100217_ao.field_106037_b
		// @28: iconst_0
		// @29: getstatic byte[] game.C_100217_ao.field_106037_b
		// @2C: arraylength
		// @2D: bipush -54 (0xCA)
		// @2F: invokevirtual game.C_100278_nd.func_101165_b(byte[], int, int, int)void
		// @32: aload_2
		// @33: sipush 7838 (0x1E9E)
		// @36: getstatic int game.C_100271_mj.field_103437_P
		// @39: invokevirtual game.C_100278_nd.func_101169_f(int, int)void
		// @3C: aload_2
		// @3D: sipush 7838 (0x1E9E)
		// @40: getstatic int game.C_100029_gn.field_103366_Q
		// @43: invokevirtual game.C_100278_nd.func_101169_f(int, int)void
		// @46: aload_2
		// @47: getstatic byte[] game.C_100132_td.field_104970_f
		// @4A: iconst_0
		// @4B: getstatic byte[] game.C_100132_td.field_104970_f
		// @4E: arraylength
		// @4F: bipush -27 (0xE5)
		// @51: invokevirtual game.C_100278_nd.func_101165_b(byte[], int, int, int)void
		// @54: aload_2
		// @55: iload_3
		// @56: ineg
		// @57: aload_2
		// @58: getfield int game.C_100278_nd.field_101177_n
		// @5B: iadd
		// @5C: bipush -107 (0x95)
		// @5E: invokevirtual game.C_100278_nd.func_101139_c(int, byte)void
		// @61: goto @8F
		// @64: astore_2
		// @65: aload_2
		// @66: new java.lang.StringBuilder
		// @69: dup
		// @6A: invokespecial java.lang.StringBuilder.<init>()void
		// @6D: getstatic java.lang.String[] game.C_100270_mi.field_102273_oc
		// @70: bipush 8 (0x08)
		// @72: aaload
		// @73: invokevirtual java.lang.StringBuilder.append(java.lang.String)java.lang.StringBuilder
		// @76: iload_0
		// @77: invokevirtual java.lang.StringBuilder.append(int)java.lang.StringBuilder
		// @7A: bipush 44 (0x2C)
		// @7C: invokevirtual java.lang.StringBuilder.append(char)java.lang.StringBuilder
		// @7F: iload_1
		// @80: invokevirtual java.lang.StringBuilder.append(int)java.lang.StringBuilder
		// @83: bipush 41 (0x29)
		// @85: invokevirtual java.lang.StringBuilder.append(char)java.lang.StringBuilder
		// @88: invokevirtual java.lang.StringBuilder.toString()java.lang.String
		// @8B: invokestatic game.C_100181_cf.func_105695_a(java.lang.Throwable, java.lang.String)game.C_100170_cm
		// @8E: athrow
		// @8F: return
	}
	
	public static void func_102249_l(int arg0)
	{
		// @00: aconst_null
		// @01: putstatic java.lang.String game.C_100270_mi.field_102268_ec
		// @04: aconst_null
		// @05: putstatic game.C_100037_wb game.C_100270_mi.field_102271_Wb
		// @08: aconst_null
		// @09: putstatic long[] game.C_100270_mi.field_102262_dc
		// @0C: aconst_null
		// @0D: putstatic java.lang.String game.C_100270_mi.field_102281_bc
		// @10: iload_0
		// @11: sipush 29378 (0x72C2)
		// @14: if_icmpeq @18
		// @17: return
		// @18: aconst_null
		// @19: putstatic java.lang.String game.C_100270_mi.field_102279_ac
		// @1C: goto @41
		// @1F: astore_1
		// @20: aload_1
		// @21: new java.lang.StringBuilder
		// @24: dup
		// @25: invokespecial java.lang.StringBuilder.<init>()void
		// @28: getstatic java.lang.String[] game.C_100270_mi.field_102273_oc
		// @2B: bipush 14 (0x0E)
		// @2D: aaload
		// @2E: invokevirtual java.lang.StringBuilder.append(java.lang.String)java.lang.StringBuilder
		// @31: iload_0
		// @32: invokevirtual java.lang.StringBuilder.append(int)java.lang.StringBuilder
		// @35: bipush 41 (0x29)
		// @37: invokevirtual java.lang.StringBuilder.append(char)java.lang.StringBuilder
		// @3A: invokevirtual java.lang.StringBuilder.toString()java.lang.String
		// @3D: invokestatic game.C_100181_cf.func_105695_a(java.lang.Throwable, java.lang.String)game.C_100170_cm
		// @40: athrow
		// @41: return
	}
	
	static final void func_102255_b(int arg0, boolean arg1)
	{
		// @00: bipush -12 (0xF4)
		// @02: bipush 15 (0x0F)
		// @04: iload_0
		// @05: isub
		// @06: bipush 41 (0x29)
		// @08: idiv
		// @09: idiv
		// @0A: istore_2
		// @0B: getstatic game.C_100043_vl game.C_100343_jf.field_104825_l
		// @0E: ifnonnull @15
		// @11: goto @2A
		// @14: athrow
		// @15: getstatic game.C_100043_vl game.C_100343_jf.field_104825_l
		// @18: sipush -8031 (0xE0A1)
		// @1B: iload_1
		// @1C: invokevirtual game.C_100043_vl.func_101933_a(int, boolean)boolean
		// @1F: ifne @26
		// @22: goto @2A
		// @25: athrow
		// @26: aconst_null
		// @27: putstatic game.C_100043_vl game.C_100343_jf.field_104825_l
		// @2A: goto @58
		// @2D: astore_2
		// @2E: aload_2
		// @2F: new java.lang.StringBuilder
		// @32: dup
		// @33: invokespecial java.lang.StringBuilder.<init>()void
		// @36: getstatic java.lang.String[] game.C_100270_mi.field_102273_oc
		// @39: bipush 16 (0x10)
		// @3B: aaload
		// @3C: invokevirtual java.lang.StringBuilder.append(java.lang.String)java.lang.StringBuilder
		// @3F: iload_0
		// @40: invokevirtual java.lang.StringBuilder.append(int)java.lang.StringBuilder
		// @43: bipush 44 (0x2C)
		// @45: invokevirtual java.lang.StringBuilder.append(char)java.lang.StringBuilder
		// @48: iload_1
		// @49: invokevirtual java.lang.StringBuilder.append(boolean)java.lang.StringBuilder
		// @4C: bipush 41 (0x29)
		// @4E: invokevirtual java.lang.StringBuilder.append(char)java.lang.StringBuilder
		// @51: invokevirtual java.lang.StringBuilder.toString()java.lang.String
		// @54: invokestatic game.C_100181_cf.func_105695_a(java.lang.Throwable, java.lang.String)game.C_100170_cm
		// @57: athrow
		// @58: return
	}
	
	C_100270_mi(C_100270_mi arg0)
	{
		// @00: aload_0
		// @01: aload_1
		// @02: aload_1
		// @03: getfield game.C_100037_wb[] game.C_100270_mi.field_102265_Xb
		// @06: aload_1
		// @07: getfield game.C_100302_ka game.C_100270_mi.field_102277_nc
		// @0A: aload_1
		// @0B: getfield game.C_100302_ka game.C_100270_mi.field_102269_fc
		// @0E: aload_1
		// @0F: getfield int game.C_100270_mi.field_102278_kc
		// @12: aload_1
		// @13: getfield int game.C_100270_mi.field_102263_gc
		// @16: aload_1
		// @17: getfield int game.C_100270_mi.field_102267_Yb
		// @1A: aload_1
		// @1B: getfield int game.C_100270_mi.field_102264_Zb
		// @1E: aload_1
		// @1F: getfield int game.C_100270_mi.field_102266_hc
		// @22: invokespecial game.C_100270_mi.<init>(game.C_100302_ka, game.C_100037_wb[], game.C_100302_ka, game.C_100302_ka, int, int, int, int, int)void
		// @25: return
	}
	
	static final boolean func_102251_a(Applet arg0, int arg1)
	{
		// @00: getstatic int game.SteelSentinels.field_105275_O
		// @03: istore #7
		// @05: getstatic boolean game.C_100004_gb.field_103578_i
		// @08: ifeq @0D
		// @0B: iconst_1
		// @0C: ireturn
		// @0D: getstatic java.lang.String[] game.C_100270_mi.field_102273_oc
		// @10: iconst_5
		// @11: aaload
		// @12: astore_2
		// @13: sipush 17228 (0x434C)
		// @16: getstatic java.lang.String[] game.C_100270_mi.field_102273_oc
		// @19: bipush 7 (0x07)
		// @1B: aaload
		// @1C: aload_0
		// @1D: invokestatic game.C_100175_cl.func_105614_a(int, java.lang.String, java.applet.Applet)java.lang.Object
		// @20: checkcast java.lang.String
		// @23: astore_3
		// @24: iload_1
		// @25: sipush 1134 (0x046E)
		// @28: if_icmpeq @36
		// @2B: aconst_null
		// @2C: checkcast java.lang.String
		// @2F: putstatic java.lang.String game.C_100270_mi.field_102279_ac
		// @32: goto @36
		// @35: athrow
		// @36: bipush 101 (0x65)
		// @38: aload_3
		// @39: bipush 59 (0x3B)
		// @3B: invokestatic game.C_100087_n.func_100679_a(int, java.lang.String, char)java.lang.String[]
		// @3E: astore #4
		// @40: iconst_0
		// @41: istore #5
		// @43: iload #5
		// @45: iconst_m1
		// @46: ixor
		// @47: aload #4
		// @49: arraylength
		// @4A: iconst_m1
		// @4B: ixor
		// @4C: if_icmple @93
		// @4F: aload #4
		// @51: iload #5
		// @53: aaload
		// @54: bipush 61 (0x3D)
		// @56: invokevirtual java.lang.String.indexOf(int)int
		// @59: istore #6
		// @5B: iload #6
		// @5D: iconst_m1
		// @5E: ixor
		// @5F: iload #7
		// @61: ifne @AA
		// @64: iconst_m1
		// @65: if_icmpgt @8B
		// @68: goto @6C
		// @6B: athrow
		// @6C: aload #4
		// @6E: iload #5
		// @70: aaload
		// @71: iconst_0
		// @72: iload #6
		// @74: invokevirtual java.lang.String.substring(int, int)java.lang.String
		// @77: invokevirtual java.lang.String.trim()java.lang.String
		// @7A: aload_2
		// @7B: invokevirtual java.lang.String.equals(java.lang.Object)boolean
		// @7E: ifne @89
		// @81: goto @85
		// @84: athrow
		// @85: goto @8B
		// @88: athrow
		// @89: iconst_1
		// @8A: ireturn
		// @8B: iinc #5 +1
		// @8E: iload #7
		// @90: ifeq @43
		// @93: goto @97
		// @96: astore_2
		// @97: aconst_null
		// @98: aload_0
		// @99: getstatic java.lang.String[] game.C_100270_mi.field_102273_oc
		// @9C: iconst_5
		// @9D: aaload
		// @9E: invokevirtual java.applet.Applet.getParameter(java.lang.String)java.lang.String
		// @A1: if_acmpeq @A9
		// @A4: iconst_1
		// @A5: goto @AA
		// @A8: athrow
		// @A9: iconst_0
		// @AA: ireturn
		// @AB: astore_2
		// @AC: aload_2
		// @AD: new java.lang.StringBuilder
		// @B0: dup
		// @B1: invokespecial java.lang.StringBuilder.<init>()void
		// @B4: getstatic java.lang.String[] game.C_100270_mi.field_102273_oc
		// @B7: bipush 6 (0x06)
		// @B9: aaload
		// @BA: invokevirtual java.lang.StringBuilder.append(java.lang.String)java.lang.StringBuilder
		// @BD: aload_0
		// @BE: ifnull @CA
		// @C1: getstatic java.lang.String[] game.C_100270_mi.field_102273_oc
		// @C4: iconst_2
		// @C5: aaload
		// @C6: goto @CF
		// @C9: athrow
		// @CA: getstatic java.lang.String[] game.C_100270_mi.field_102273_oc
		// @CD: iconst_1
		// @CE: aaload
		// @CF: invokevirtual java.lang.StringBuilder.append(java.lang.String)java.lang.StringBuilder
		// @D2: bipush 44 (0x2C)
		// @D4: invokevirtual java.lang.StringBuilder.append(char)java.lang.StringBuilder
		// @D7: iload_1
		// @D8: invokevirtual java.lang.StringBuilder.append(int)java.lang.StringBuilder
		// @DB: bipush 41 (0x29)
		// @DD: invokevirtual java.lang.StringBuilder.append(char)java.lang.StringBuilder
		// @E0: invokevirtual java.lang.StringBuilder.toString()java.lang.String
		// @E3: invokestatic game.C_100181_cf.func_105695_a(java.lang.Throwable, java.lang.String)game.C_100170_cm
		// @E6: athrow
	}
	
	final boolean func_102258_m(int arg0)
	{
		// @00: aload_0
		// @01: getfield int game.C_100270_mi.field_102272_ic
		// @04: bipush -2 (0xFE)
		// @06: if_icmpeq @0B
		// @09: iconst_0
		// @0A: ireturn
		// @0B: iload_1
		// @0C: ifeq @11
		// @0F: iconst_0
		// @10: ireturn
		// @11: getstatic int game.C_100293_kj.field_106890_c
		// @14: iconst_m1
		// @15: ixor
		// @16: bipush -14 (0xF2)
		// @18: if_icmpeq @1F
		// @1B: goto @24
		// @1E: athrow
		// @1F: aload_0
		// @20: iconst_m1
		// @21: putfield int game.C_100270_mi.field_102272_ic
		// @24: iconst_1
		// @25: ireturn
		// @26: astore_2
		// @27: aload_2
		// @28: new java.lang.StringBuilder
		// @2B: dup
		// @2C: invokespecial java.lang.StringBuilder.<init>()void
		// @2F: getstatic java.lang.String[] game.C_100270_mi.field_102273_oc
		// @32: iconst_0
		// @33: aaload
		// @34: invokevirtual java.lang.StringBuilder.append(java.lang.String)java.lang.StringBuilder
		// @37: iload_1
		// @38: invokevirtual java.lang.StringBuilder.append(int)java.lang.StringBuilder
		// @3B: bipush 41 (0x29)
		// @3D: invokevirtual java.lang.StringBuilder.append(char)java.lang.StringBuilder
		// @40: invokevirtual java.lang.StringBuilder.toString()java.lang.String
		// @43: invokestatic game.C_100181_cf.func_105695_a(java.lang.Throwable, java.lang.String)game.C_100170_cm
		// @46: athrow
	}
	
	static final void func_102254_a(String arg0, float arg1, int arg2)
	{
		// @00: iload_2
		// @01: sipush 256 (0x0100)
		// @04: if_icmpeq @15
		// @07: aconst_null
		// @08: checkcast java.applet.Applet
		// @0B: bipush -20 (0xEC)
		// @0D: invokestatic game.C_100270_mi.func_102251_a(java.applet.Applet, int)boolean
		// @10: pop
		// @11: goto @15
		// @14: athrow
		// @15: aload_0
		// @16: putstatic java.lang.String game.C_100122_em.field_102079_Vb
		// @19: fload_1
		// @1A: putstatic float game.C_100100_i.field_102011_gc
		// @1D: goto @65
		// @20: astore_3
		// @21: aload_3
		// @22: new java.lang.StringBuilder
		// @25: dup
		// @26: invokespecial java.lang.StringBuilder.<init>()void
		// @29: getstatic java.lang.String[] game.C_100270_mi.field_102273_oc
		// @2C: bipush 15 (0x0F)
		// @2E: aaload
		// @2F: invokevirtual java.lang.StringBuilder.append(java.lang.String)java.lang.StringBuilder
		// @32: aload_0
		// @33: ifnull @3F
		// @36: getstatic java.lang.String[] game.C_100270_mi.field_102273_oc
		// @39: iconst_2
		// @3A: aaload
		// @3B: goto @44
		// @3E: athrow
		// @3F: getstatic java.lang.String[] game.C_100270_mi.field_102273_oc
		// @42: iconst_1
		// @43: aaload
		// @44: invokevirtual java.lang.StringBuilder.append(java.lang.String)java.lang.StringBuilder
		// @47: bipush 44 (0x2C)
		// @49: invokevirtual java.lang.StringBuilder.append(char)java.lang.StringBuilder
		// @4C: fload_1
		// @4D: invokevirtual java.lang.StringBuilder.append(float)java.lang.StringBuilder
		// @50: bipush 44 (0x2C)
		// @52: invokevirtual java.lang.StringBuilder.append(char)java.lang.StringBuilder
		// @55: iload_2
		// @56: invokevirtual java.lang.StringBuilder.append(int)java.lang.StringBuilder
		// @59: bipush 41 (0x29)
		// @5B: invokevirtual java.lang.StringBuilder.append(char)java.lang.StringBuilder
		// @5E: invokevirtual java.lang.StringBuilder.toString()java.lang.String
		// @61: invokestatic game.C_100181_cf.func_105695_a(java.lang.Throwable, java.lang.String)game.C_100170_cm
		// @64: athrow
		// @65: return
	}
	
	static
	{
		// @000: bipush 17 (0x11)
		// @002: anewarray java.lang.String
		// @005: dup
		// @006: iconst_0
		// @007: ldc "\r7\u0003\u0004\u0011"
		// @009: invokestatic game.C_100270_mi.func_102253_z(java.lang.String)char[]
		// @00C: invokestatic game.C_100270_mi.func_102252_z(char[])java.lang.String
		// @00F: aastore
		// @010: dup
		// @011: iconst_1
		// @012: ldc "\u000e+A9"
		// @014: invokestatic game.C_100270_mi.func_102253_z(java.lang.String)char[]
		// @017: invokestatic game.C_100270_mi.func_102252_z(char[])java.lang.String
		// @01A: aastore
		// @01B: dup
		// @01C: iconst_2
		// @01D: ldc "\u001bp\u0003{D"
		// @01F: invokestatic game.C_100270_mi.func_102253_z(java.lang.String)char[]
		// @022: invokestatic game.C_100270_mi.func_102252_z(char[])java.lang.String
		// @025: aastore
		// @026: dup
		// @027: iconst_3
		// @028: ldc "\r7\u0003\u001d\u0011"
		// @02A: invokestatic game.C_100270_mi.func_102253_z(java.lang.String)char[]
		// @02D: invokestatic game.C_100270_mi.func_102252_z(char[])java.lang.String
		// @030: aastore
		// @031: dup
		// @032: iconst_4
		// @033: ldc "\r7\u0003\u0010\u0011"
		// @035: invokestatic game.C_100270_mi.func_102253_z(java.lang.String)char[]
		// @038: invokestatic game.C_100270_mi.func_102252_z(char[])java.lang.String
		// @03B: aastore
		// @03C: dup
		// @03D: iconst_5
		// @03E: ldc "\u0014+E&M\u0001*O M"
		// @040: invokestatic game.C_100270_mi.func_102253_z(java.lang.String)char[]
		// @043: invokestatic game.C_100270_mi.func_102252_z(char[])java.lang.String
		// @046: aastore
		// @047: dup
		// @048: bipush 6 (0x06)
		// @04A: ldc "\r7\u0003\u0007\u0011"
		// @04C: invokestatic game.C_100270_mi.func_102253_z(java.lang.String)char[]
		// @04F: invokestatic game.C_100270_mi.func_102252_z(char[])java.lang.String
		// @052: aastore
		// @053: dup
		// @054: bipush 7 (0x07)
		// @056: ldc "\u0007;Y6V\u000f5D0J"
		// @058: invokestatic game.C_100270_mi.func_102253_z(java.lang.String)char[]
		// @05B: invokestatic game.C_100270_mi.func_102252_z(char[])java.lang.String
		// @05E: aastore
		// @05F: dup
		// @060: bipush 8 (0x08)
		// @062: ldc "\r7\u0003\u0013\u0011"
		// @064: invokestatic game.C_100270_mi.func_102253_z(java.lang.String)char[]
		// @067: invokestatic game.C_100270_mi.func_102252_z(char[])java.lang.String
		// @06A: aastore
		// @06B: dup
		// @06C: bipush 9 (0x09)
		// @06E: ldc "\r7\u0003iP\u000e7Yk\u0011"
		// @070: invokestatic game.C_100270_mi.func_102253_z(java.lang.String)char[]
		// @073: invokestatic game.C_100270_mi.func_102252_z(char[])java.lang.String
		// @076: aastore
		// @077: dup
		// @078: bipush 10 (0x0A)
		// @07A: ldc "\r7\u0003\u0016\u0011"
		// @07C: invokestatic game.C_100270_mi.func_102253_z(java.lang.String)char[]
		// @07F: invokestatic game.C_100270_mi.func_102252_z(char[])java.lang.String
		// @082: aastore
		// @083: dup
		// @084: bipush 11 (0x0B)
		// @086: ldc "\r7\u0003\u0012\u0011"
		// @088: invokestatic game.C_100270_mi.func_102253_z(java.lang.String)char[]
		// @08B: invokestatic game.C_100270_mi.func_102252_z(char[])java.lang.String
		// @08E: aastore
		// @08F: dup
		// @090: bipush 12 (0x0C)
		// @092: ldc "\r7\u0003\u0017\u0011"
		// @094: invokestatic game.C_100270_mi.func_102253_z(java.lang.String)char[]
		// @097: invokestatic game.C_100270_mi.func_102252_z(char[])java.lang.String
		// @09A: aastore
		// @09B: dup
		// @09C: bipush 13 (0x0D)
		// @09E: ldc "\r7\u0003\u0006\u0011"
		// @0A0: invokestatic game.C_100270_mi.func_102253_z(java.lang.String)char[]
		// @0A3: invokestatic game.C_100270_mi.func_102252_z(char[])java.lang.String
		// @0A6: aastore
		// @0A7: dup
		// @0A8: bipush 14 (0x0E)
		// @0AA: ldc "\r7\u0003\u0011\u0011"
		// @0AC: invokestatic game.C_100270_mi.func_102253_z(java.lang.String)char[]
		// @0AF: invokestatic game.C_100270_mi.func_102252_z(char[])java.lang.String
		// @0B2: aastore
		// @0B3: dup
		// @0B4: bipush 15 (0x0F)
		// @0B6: ldc "\r7\u0003\u001c\u0011"
		// @0B8: invokestatic game.C_100270_mi.func_102253_z(java.lang.String)char[]
		// @0BB: invokestatic game.C_100270_mi.func_102252_z(char[])java.lang.String
		// @0BE: aastore
		// @0BF: dup
		// @0C0: bipush 16 (0x10)
		// @0C2: ldc "\r7\u0003\u0014\u0011"
		// @0C4: invokestatic game.C_100270_mi.func_102253_z(java.lang.String)char[]
		// @0C7: invokestatic game.C_100270_mi.func_102252_z(char[])java.lang.String
		// @0CA: aastore
		// @0CB: putstatic java.lang.String[] game.C_100270_mi.field_102273_oc
		// @0CE: bipush 32 (0x20)
		// @0D0: newarray long[]
		// @0D2: putstatic long[] game.C_100270_mi.field_102262_dc
		// @0D5: ldc "9;^"
		// @0D7: invokestatic game.C_100270_mi.func_102253_z(java.lang.String)char[]
		// @0DA: invokestatic game.C_100270_mi.func_102252_z(char[])java.lang.String
		// @0DD: putstatic java.lang.String game.C_100270_mi.field_102268_ec
		// @0E0: ldc "#2D6R@1_uI\u0012;^&\u0019&o\u001duM\u000f~B%\\\u000e~| P\u00035\r\u0016Q\u0001*"
		// @0E2: invokestatic game.C_100270_mi.func_102253_z(java.lang.String)char[]
		// @0E5: invokestatic game.C_100270_mi.func_102252_z(char[])java.lang.String
		// @0E8: putstatic java.lang.String game.C_100270_mi.field_102279_ac
		// @0EB: iconst_0
		// @0EC: putstatic boolean game.C_100270_mi.field_102276_Vb
		// @0EF: ldc "50_4M\u0005:\r2X\r;"
		// @0F1: invokestatic game.C_100270_mi.func_102253_z(java.lang.String)char[]
		// @0F4: invokestatic game.C_100270_mi.func_102252_z(char[])java.lang.String
		// @0F7: putstatic java.lang.String game.C_100270_mi.field_102281_bc
		// @0FA: sipush 4096 (0x1000)
		// @0FD: putstatic int game.C_100270_mi.field_102270_jc
		// @100: return
	}
	
	private static char[] func_102253_z(String arg0)
	{
		// @00: aload_0
		// @01: invokevirtual java.lang.String.toCharArray()char[]
		// @04: dup
		// @05: arraylength
		// @06: iconst_2
		// @07: if_icmpge @13
		// @0A: dup
		// @0B: iconst_0
		// @0C: dup2
		// @0D: caload
		// @0E: bipush 57 (0x39)
		// @10: ixor
		// @11: i2c
		// @12: castore
		// @13: areturn
	}
	
	private static String func_102252_z(char[] arg0)
	{
		// @00: aload_0
		// @01: dup
		// @02: arraylength
		// @03: swap
		// @04: iconst_0
		// @05: istore_1
		// @06: goto @4C
		// @09: dup
		// @0A: iload_1
		// @0B: dup2
		// @0C: caload
		// @0D: iload_1
		// @0E: iconst_5
		// @0F: irem
		// @10: tableswitch def: @44, for 0: @30, for 1: @35, for 2: @3A, for 3: @3F
		// @30: bipush 96 (0x60)
		// @32: goto @46
		// @35: bipush 94 (0x5E)
		// @37: goto @46
		// @3A: bipush 45 (0x2D)
		// @3C: goto @46
		// @3F: bipush 85 (0x55)
		// @41: goto @46
		// @44: bipush 57 (0x39)
		// @46: ixor
		// @47: i2c
		// @48: castore
		// @49: iinc #1 +1
		// @4C: swap
		// @4D: dup_x1
		// @4E: iload_1
		// @4F: if_icmpgt @09
		// @52: new java.lang.String
		// @55: dup_x1
		// @56: swap
		// @57: invokespecial java.lang.String.<init>(char[])void
		// @5A: invokevirtual java.lang.String.intern()java.lang.String
		// @5D: areturn
	}
}
