package game;

final class C_100057_dd
{
	static String field_104254_g;
	static int field_104257_b;
	static C_100327_ib[] field_104262_i;
	static long field_104261_h;
	static String[] field_104255_d;
	static boolean field_104259_a;
	static int field_104258_c;
	static volatile int field_104256_e;
	static int field_104253_f;
	private static final String[] field_104260_z;
	
	public static void func_104248_b(int arg0)
	{
		// @00: aconst_null
		// @01: putstatic game.C_100327_ib[] game.C_100057_dd.field_104262_i
		// @04: aconst_null
		// @05: putstatic java.lang.String game.C_100057_dd.field_104254_g
		// @08: iload_0
		// @09: bipush -17 (0xEF)
		// @0B: if_icmplt @1E
		// @0E: bipush 37 (0x25)
		// @10: aconst_null
		// @11: checkcast java.lang.String
		// @14: bipush -24 (0xE8)
		// @16: invokestatic game.C_100057_dd.func_104249_a(int, java.lang.String, int)java.lang.String
		// @19: pop
		// @1A: goto @1E
		// @1D: athrow
		// @1E: aconst_null
		// @1F: putstatic java.lang.String[] game.C_100057_dd.field_104255_d
		// @22: goto @46
		// @25: astore_1
		// @26: aload_1
		// @27: new java.lang.StringBuilder
		// @2A: dup
		// @2B: invokespecial java.lang.StringBuilder.<init>()void
		// @2E: getstatic java.lang.String[] game.C_100057_dd.field_104260_z
		// @31: iconst_1
		// @32: aaload
		// @33: invokevirtual java.lang.StringBuilder.append(java.lang.String)java.lang.StringBuilder
		// @36: iload_0
		// @37: invokevirtual java.lang.StringBuilder.append(int)java.lang.StringBuilder
		// @3A: bipush 41 (0x29)
		// @3C: invokevirtual java.lang.StringBuilder.append(char)java.lang.StringBuilder
		// @3F: invokevirtual java.lang.StringBuilder.toString()java.lang.String
		// @42: invokestatic game.C_100181_cf.func_105695_a(java.lang.Throwable, java.lang.String)game.C_100170_cm
		// @45: athrow
		// @46: return
	}
	
	static final void func_104247_a(byte[] arg0, C_100098_h arg1, byte arg2, int arg3, int[] arg4, int arg5, String[] arg6, int[] arg7, byte[] arg8, C_100098_h arg9, C_100098_h arg10, C_100037_wb[][] arg11, String[][] arg12, C_100037_wb[][] arg13, boolean arg14, int arg15, C_100153_be[] arg16, String[][] arg17, String[] arg18)
	{
		// @000: aload_1
		// @001: iload #15
		// @003: sipush -24373 (0xA0CB)
		// @006: aload #6
		// @008: aload #9
		// @00A: aload #16
		// @00C: aconst_null
		// @00D: aload #12
		// @00F: aload #11
		// @011: aload #13
		// @013: aload #7
		// @015: iconst_1
		// @016: aload #17
		// @018: iload #14
		// @01A: aload #18
		// @01C: aload #10
		// @01E: aload #4
		// @020: aload #8
		// @022: iload_3
		// @023: aload_0
		// @024: invokestatic game.C_100281_ng.func_103444_a(game.C_100098_h, int, int, java.lang.String[], game.C_100098_h, game.C_100153_be[], java.lang.String[], java.lang.String[][], game.C_100037_wb[][], game.C_100037_wb[][], int[], int, java.lang.String[][], boolean, java.lang.String[], game.C_100098_h, int[], byte[], int, byte[])void
		// @027: iload_2
		// @028: bipush 53 (0x35)
		// @02A: if_icmpgt @033
		// @02D: bipush -55 (0xC9)
		// @02F: invokestatic game.C_100057_dd.func_104252_a(int)boolean
		// @032: pop
		// @033: goto @1F8
		// @036: astore #19
		// @038: aload #19
		// @03A: new java.lang.StringBuilder
		// @03D: dup
		// @03E: invokespecial java.lang.StringBuilder.<init>()void
		// @041: getstatic java.lang.String[] game.C_100057_dd.field_104260_z
		// @044: iconst_3
		// @045: aaload
		// @046: invokevirtual java.lang.StringBuilder.append(java.lang.String)java.lang.StringBuilder
		// @049: aload_0
		// @04A: ifnull @056
		// @04D: getstatic java.lang.String[] game.C_100057_dd.field_104260_z
		// @050: iconst_4
		// @051: aaload
		// @052: goto @05B
		// @055: athrow
		// @056: getstatic java.lang.String[] game.C_100057_dd.field_104260_z
		// @059: iconst_2
		// @05A: aaload
		// @05B: invokevirtual java.lang.StringBuilder.append(java.lang.String)java.lang.StringBuilder
		// @05E: bipush 44 (0x2C)
		// @060: invokevirtual java.lang.StringBuilder.append(char)java.lang.StringBuilder
		// @063: aload_1
		// @064: ifnull @070
		// @067: getstatic java.lang.String[] game.C_100057_dd.field_104260_z
		// @06A: iconst_4
		// @06B: aaload
		// @06C: goto @075
		// @06F: athrow
		// @070: getstatic java.lang.String[] game.C_100057_dd.field_104260_z
		// @073: iconst_2
		// @074: aaload
		// @075: invokevirtual java.lang.StringBuilder.append(java.lang.String)java.lang.StringBuilder
		// @078: bipush 44 (0x2C)
		// @07A: invokevirtual java.lang.StringBuilder.append(char)java.lang.StringBuilder
		// @07D: iload_2
		// @07E: invokevirtual java.lang.StringBuilder.append(int)java.lang.StringBuilder
		// @081: bipush 44 (0x2C)
		// @083: invokevirtual java.lang.StringBuilder.append(char)java.lang.StringBuilder
		// @086: iload_3
		// @087: invokevirtual java.lang.StringBuilder.append(int)java.lang.StringBuilder
		// @08A: bipush 44 (0x2C)
		// @08C: invokevirtual java.lang.StringBuilder.append(char)java.lang.StringBuilder
		// @08F: aload #4
		// @091: ifnull @09D
		// @094: getstatic java.lang.String[] game.C_100057_dd.field_104260_z
		// @097: iconst_4
		// @098: aaload
		// @099: goto @0A2
		// @09C: athrow
		// @09D: getstatic java.lang.String[] game.C_100057_dd.field_104260_z
		// @0A0: iconst_2
		// @0A1: aaload
		// @0A2: invokevirtual java.lang.StringBuilder.append(java.lang.String)java.lang.StringBuilder
		// @0A5: bipush 44 (0x2C)
		// @0A7: invokevirtual java.lang.StringBuilder.append(char)java.lang.StringBuilder
		// @0AA: iload #5
		// @0AC: invokevirtual java.lang.StringBuilder.append(int)java.lang.StringBuilder
		// @0AF: bipush 44 (0x2C)
		// @0B1: invokevirtual java.lang.StringBuilder.append(char)java.lang.StringBuilder
		// @0B4: aload #6
		// @0B6: ifnull @0C2
		// @0B9: getstatic java.lang.String[] game.C_100057_dd.field_104260_z
		// @0BC: iconst_4
		// @0BD: aaload
		// @0BE: goto @0C7
		// @0C1: athrow
		// @0C2: getstatic java.lang.String[] game.C_100057_dd.field_104260_z
		// @0C5: iconst_2
		// @0C6: aaload
		// @0C7: invokevirtual java.lang.StringBuilder.append(java.lang.String)java.lang.StringBuilder
		// @0CA: bipush 44 (0x2C)
		// @0CC: invokevirtual java.lang.StringBuilder.append(char)java.lang.StringBuilder
		// @0CF: aload #7
		// @0D1: ifnull @0DD
		// @0D4: getstatic java.lang.String[] game.C_100057_dd.field_104260_z
		// @0D7: iconst_4
		// @0D8: aaload
		// @0D9: goto @0E2
		// @0DC: athrow
		// @0DD: getstatic java.lang.String[] game.C_100057_dd.field_104260_z
		// @0E0: iconst_2
		// @0E1: aaload
		// @0E2: invokevirtual java.lang.StringBuilder.append(java.lang.String)java.lang.StringBuilder
		// @0E5: bipush 44 (0x2C)
		// @0E7: invokevirtual java.lang.StringBuilder.append(char)java.lang.StringBuilder
		// @0EA: aload #8
		// @0EC: ifnull @0F8
		// @0EF: getstatic java.lang.String[] game.C_100057_dd.field_104260_z
		// @0F2: iconst_4
		// @0F3: aaload
		// @0F4: goto @0FD
		// @0F7: athrow
		// @0F8: getstatic java.lang.String[] game.C_100057_dd.field_104260_z
		// @0FB: iconst_2
		// @0FC: aaload
		// @0FD: invokevirtual java.lang.StringBuilder.append(java.lang.String)java.lang.StringBuilder
		// @100: bipush 44 (0x2C)
		// @102: invokevirtual java.lang.StringBuilder.append(char)java.lang.StringBuilder
		// @105: aload #9
		// @107: ifnull @113
		// @10A: getstatic java.lang.String[] game.C_100057_dd.field_104260_z
		// @10D: iconst_4
		// @10E: aaload
		// @10F: goto @118
		// @112: athrow
		// @113: getstatic java.lang.String[] game.C_100057_dd.field_104260_z
		// @116: iconst_2
		// @117: aaload
		// @118: invokevirtual java.lang.StringBuilder.append(java.lang.String)java.lang.StringBuilder
		// @11B: bipush 44 (0x2C)
		// @11D: invokevirtual java.lang.StringBuilder.append(char)java.lang.StringBuilder
		// @120: aload #10
		// @122: ifnull @12E
		// @125: getstatic java.lang.String[] game.C_100057_dd.field_104260_z
		// @128: iconst_4
		// @129: aaload
		// @12A: goto @133
		// @12D: athrow
		// @12E: getstatic java.lang.String[] game.C_100057_dd.field_104260_z
		// @131: iconst_2
		// @132: aaload
		// @133: invokevirtual java.lang.StringBuilder.append(java.lang.String)java.lang.StringBuilder
		// @136: bipush 44 (0x2C)
		// @138: invokevirtual java.lang.StringBuilder.append(char)java.lang.StringBuilder
		// @13B: aload #11
		// @13D: ifnull @149
		// @140: getstatic java.lang.String[] game.C_100057_dd.field_104260_z
		// @143: iconst_4
		// @144: aaload
		// @145: goto @14E
		// @148: athrow
		// @149: getstatic java.lang.String[] game.C_100057_dd.field_104260_z
		// @14C: iconst_2
		// @14D: aaload
		// @14E: invokevirtual java.lang.StringBuilder.append(java.lang.String)java.lang.StringBuilder
		// @151: bipush 44 (0x2C)
		// @153: invokevirtual java.lang.StringBuilder.append(char)java.lang.StringBuilder
		// @156: aload #12
		// @158: ifnull @164
		// @15B: getstatic java.lang.String[] game.C_100057_dd.field_104260_z
		// @15E: iconst_4
		// @15F: aaload
		// @160: goto @169
		// @163: athrow
		// @164: getstatic java.lang.String[] game.C_100057_dd.field_104260_z
		// @167: iconst_2
		// @168: aaload
		// @169: invokevirtual java.lang.StringBuilder.append(java.lang.String)java.lang.StringBuilder
		// @16C: bipush 44 (0x2C)
		// @16E: invokevirtual java.lang.StringBuilder.append(char)java.lang.StringBuilder
		// @171: aload #13
		// @173: ifnull @17F
		// @176: getstatic java.lang.String[] game.C_100057_dd.field_104260_z
		// @179: iconst_4
		// @17A: aaload
		// @17B: goto @184
		// @17E: athrow
		// @17F: getstatic java.lang.String[] game.C_100057_dd.field_104260_z
		// @182: iconst_2
		// @183: aaload
		// @184: invokevirtual java.lang.StringBuilder.append(java.lang.String)java.lang.StringBuilder
		// @187: bipush 44 (0x2C)
		// @189: invokevirtual java.lang.StringBuilder.append(char)java.lang.StringBuilder
		// @18C: iload #14
		// @18E: invokevirtual java.lang.StringBuilder.append(boolean)java.lang.StringBuilder
		// @191: bipush 44 (0x2C)
		// @193: invokevirtual java.lang.StringBuilder.append(char)java.lang.StringBuilder
		// @196: iload #15
		// @198: invokevirtual java.lang.StringBuilder.append(int)java.lang.StringBuilder
		// @19B: bipush 44 (0x2C)
		// @19D: invokevirtual java.lang.StringBuilder.append(char)java.lang.StringBuilder
		// @1A0: aload #16
		// @1A2: ifnull @1AE
		// @1A5: getstatic java.lang.String[] game.C_100057_dd.field_104260_z
		// @1A8: iconst_4
		// @1A9: aaload
		// @1AA: goto @1B3
		// @1AD: athrow
		// @1AE: getstatic java.lang.String[] game.C_100057_dd.field_104260_z
		// @1B1: iconst_2
		// @1B2: aaload
		// @1B3: invokevirtual java.lang.StringBuilder.append(java.lang.String)java.lang.StringBuilder
		// @1B6: bipush 44 (0x2C)
		// @1B8: invokevirtual java.lang.StringBuilder.append(char)java.lang.StringBuilder
		// @1BB: aload #17
		// @1BD: ifnull @1C9
		// @1C0: getstatic java.lang.String[] game.C_100057_dd.field_104260_z
		// @1C3: iconst_4
		// @1C4: aaload
		// @1C5: goto @1CE
		// @1C8: athrow
		// @1C9: getstatic java.lang.String[] game.C_100057_dd.field_104260_z
		// @1CC: iconst_2
		// @1CD: aaload
		// @1CE: invokevirtual java.lang.StringBuilder.append(java.lang.String)java.lang.StringBuilder
		// @1D1: bipush 44 (0x2C)
		// @1D3: invokevirtual java.lang.StringBuilder.append(char)java.lang.StringBuilder
		// @1D6: aload #18
		// @1D8: ifnull @1E4
		// @1DB: getstatic java.lang.String[] game.C_100057_dd.field_104260_z
		// @1DE: iconst_4
		// @1DF: aaload
		// @1E0: goto @1E9
		// @1E3: athrow
		// @1E4: getstatic java.lang.String[] game.C_100057_dd.field_104260_z
		// @1E7: iconst_2
		// @1E8: aaload
		// @1E9: invokevirtual java.lang.StringBuilder.append(java.lang.String)java.lang.StringBuilder
		// @1EC: bipush 41 (0x29)
		// @1EE: invokevirtual java.lang.StringBuilder.append(char)java.lang.StringBuilder
		// @1F1: invokevirtual java.lang.StringBuilder.toString()java.lang.String
		// @1F4: invokestatic game.C_100181_cf.func_105695_a(java.lang.Throwable, java.lang.String)game.C_100170_cm
		// @1F7: athrow
		// @1F8: return
	}
	
	static final String func_104249_a(int arg0, String arg1, int arg2)
	{
		// @00: bipush -4 (0xFC)
		// @02: iload_2
		// @03: iconst_m1
		// @04: ixor
		// @05: if_icmpne @0C
		// @08: getstatic java.lang.String game.C_100299_kd.field_107027_K
		// @0B: areturn
		// @0C: bipush -7 (0xF9)
		// @0E: iload_2
		// @0F: iconst_m1
		// @10: ixor
		// @11: if_icmpne @18
		// @14: getstatic java.lang.String game.C_100343_jf.field_104826_m
		// @17: areturn
		// @18: bipush -8 (0xF8)
		// @1A: iload_2
		// @1B: iconst_m1
		// @1C: ixor
		// @1D: if_icmpeq @24
		// @20: goto @28
		// @23: athrow
		// @24: getstatic java.lang.String game.C_100165_sh.field_100773_n
		// @27: areturn
		// @28: iload_0
		// @29: sipush 27448 (0x6B38)
		// @2C: if_icmpeq @34
		// @2F: aconst_null
		// @30: checkcast java.lang.String
		// @33: areturn
		// @34: bipush -9 (0xF7)
		// @36: iload_2
		// @37: iconst_m1
		// @38: ixor
		// @39: if_icmpne @40
		// @3C: getstatic java.lang.String game.C_100059_df.field_101616_z
		// @3F: areturn
		// @40: bipush -10 (0xF6)
		// @42: iload_2
		// @43: iconst_m1
		// @44: ixor
		// @45: if_icmpeq @4C
		// @48: goto @50
		// @4B: athrow
		// @4C: getstatic java.lang.String game.C_100263_mb.field_106509_b
		// @4F: areturn
		// @50: bipush -11 (0xF5)
		// @52: iload_2
		// @53: iconst_m1
		// @54: ixor
		// @55: if_icmpeq @5C
		// @58: goto @60
		// @5B: athrow
		// @5C: getstatic java.lang.String game.C_100206_qe.field_105940_b
		// @5F: areturn
		// @60: iload_2
		// @61: bipush 11 (0x0B)
		// @63: if_icmpne @6A
		// @66: getstatic java.lang.String game.C_100340_je.field_102986_i
		// @69: areturn
		// @6A: iload_2
		// @6B: iconst_m1
		// @6C: ixor
		// @6D: bipush -15 (0xF1)
		// @6F: if_icmpeq @76
		// @72: goto @88
		// @75: athrow
		// @76: sipush -30945 (0x871F)
		// @79: iconst_1
		// @7A: anewarray java.lang.String
		// @7D: dup
		// @7E: iconst_0
		// @7F: aload_1
		// @80: aastore
		// @81: getstatic java.lang.String game.C_100180_ce.field_104803_A
		// @84: invokestatic game.C_100132_td.func_104965_a(int, java.lang.String[], java.lang.String)java.lang.String
		// @87: areturn
		// @88: aconst_null
		// @89: areturn
		// @8A: astore_3
		// @8B: aload_3
		// @8C: new java.lang.StringBuilder
		// @8F: dup
		// @90: invokespecial java.lang.StringBuilder.<init>()void
		// @93: getstatic java.lang.String[] game.C_100057_dd.field_104260_z
		// @96: iconst_5
		// @97: aaload
		// @98: invokevirtual java.lang.StringBuilder.append(java.lang.String)java.lang.StringBuilder
		// @9B: iload_0
		// @9C: invokevirtual java.lang.StringBuilder.append(int)java.lang.StringBuilder
		// @9F: bipush 44 (0x2C)
		// @A1: invokevirtual java.lang.StringBuilder.append(char)java.lang.StringBuilder
		// @A4: aload_1
		// @A5: ifnull @B1
		// @A8: getstatic java.lang.String[] game.C_100057_dd.field_104260_z
		// @AB: iconst_4
		// @AC: aaload
		// @AD: goto @B6
		// @B0: athrow
		// @B1: getstatic java.lang.String[] game.C_100057_dd.field_104260_z
		// @B4: iconst_2
		// @B5: aaload
		// @B6: invokevirtual java.lang.StringBuilder.append(java.lang.String)java.lang.StringBuilder
		// @B9: bipush 44 (0x2C)
		// @BB: invokevirtual java.lang.StringBuilder.append(char)java.lang.StringBuilder
		// @BE: iload_2
		// @BF: invokevirtual java.lang.StringBuilder.append(int)java.lang.StringBuilder
		// @C2: bipush 41 (0x29)
		// @C4: invokevirtual java.lang.StringBuilder.append(char)java.lang.StringBuilder
		// @C7: invokevirtual java.lang.StringBuilder.toString()java.lang.String
		// @CA: invokestatic game.C_100181_cf.func_105695_a(java.lang.Throwable, java.lang.String)game.C_100170_cm
		// @CD: athrow
	}
	
	static final boolean func_104252_a(int arg0)
	{
		// @00: iload_0
		// @01: bipush -15 (0xF1)
		// @03: if_icmpeq @08
		// @06: iconst_1
		// @07: ireturn
		// @08: bipush -11 (0xF5)
		// @0A: getstatic int game.C_100087_n.field_100697_v
		// @0D: iconst_m1
		// @0E: ixor
		// @0F: if_icmplt @2D
		// @12: getstatic boolean game.C_100010_ff.field_103697_l
		// @15: ifne @2D
		// @18: goto @1C
		// @1B: athrow
		// @1C: bipush -79 (0xB1)
		// @1E: invokestatic game.C_100238_ol.func_101684_e(byte)boolean
		// @21: ifne @2D
		// @24: goto @28
		// @27: athrow
		// @28: iconst_1
		// @29: goto @2E
		// @2C: athrow
		// @2D: iconst_0
		// @2E: ireturn
		// @2F: astore_1
		// @30: aload_1
		// @31: new java.lang.StringBuilder
		// @34: dup
		// @35: invokespecial java.lang.StringBuilder.<init>()void
		// @38: getstatic java.lang.String[] game.C_100057_dd.field_104260_z
		// @3B: iconst_0
		// @3C: aaload
		// @3D: invokevirtual java.lang.StringBuilder.append(java.lang.String)java.lang.StringBuilder
		// @40: iload_0
		// @41: invokevirtual java.lang.StringBuilder.append(int)java.lang.StringBuilder
		// @44: bipush 41 (0x29)
		// @46: invokevirtual java.lang.StringBuilder.append(char)java.lang.StringBuilder
		// @49: invokevirtual java.lang.StringBuilder.toString()java.lang.String
		// @4C: invokestatic game.C_100181_cf.func_105695_a(java.lang.Throwable, java.lang.String)game.C_100170_cm
		// @4F: athrow
	}
	
	static
	{
		// @00: bipush 6 (0x06)
		// @02: anewarray java.lang.String
		// @05: dup
		// @06: iconst_0
		// @07: ldc ",E\u0008(]"
		// @09: invokestatic game.C_100057_dd.func_104251_z(java.lang.String)char[]
		// @0C: invokestatic game.C_100057_dd.func_104250_z(char[])java.lang.String
		// @0F: aastore
		// @10: dup
		// @11: iconst_1
		// @12: ldc ",E\u0008)]"
		// @14: invokestatic game.C_100057_dd.func_104251_z(java.lang.String)char[]
		// @17: invokestatic game.C_100057_dd.func_104250_z(char[])java.lang.String
		// @1A: aastore
		// @1B: dup
		// @1C: iconst_2
		// @1D: ldc "&TJ\u0006"
		// @1F: invokestatic game.C_100057_dd.func_104251_z(java.lang.String)char[]
		// @22: invokestatic game.C_100057_dd.func_104250_z(char[])java.lang.String
		// @25: aastore
		// @26: dup
		// @27: iconst_3
		// @28: ldc ",E\u0008.]"
		// @2A: invokestatic game.C_100057_dd.func_104251_z(java.lang.String)char[]
		// @2D: invokestatic game.C_100057_dd.func_104250_z(char[])java.lang.String
		// @30: aastore
		// @31: dup
		// @32: iconst_4
		// @33: ldc "3\u000f\u0008D\u0008"
		// @35: invokestatic game.C_100057_dd.func_104251_z(java.lang.String)char[]
		// @38: invokestatic game.C_100057_dd.func_104250_z(char[])java.lang.String
		// @3B: aastore
		// @3C: dup
		// @3D: iconst_5
		// @3E: ldc ",E\u0008+]"
		// @40: invokestatic game.C_100057_dd.func_104251_z(java.lang.String)char[]
		// @43: invokestatic game.C_100057_dd.func_104250_z(char[])java.lang.String
		// @46: aastore
		// @47: putstatic java.lang.String[] game.C_100057_dd.field_104260_z
		// @4A: ldc "\u0018TD\u0006\u001c+\u0001E\u0002\u0014<\u0001O\u0019U=OG\u001c\u0014!MG\u0008\u0019-\u0001Q\u0002\u001c$D\u0006\u0019\u0010<UO\u0004\u0012hTVJ\u0014hSG\u001e\u0010,\u0001A\u000b\u0018-\u000f"
		// @4C: invokestatic game.C_100057_dd.func_104251_z(java.lang.String)char[]
		// @4F: invokestatic game.C_100057_dd.func_104250_z(char[])java.lang.String
		// @52: putstatic java.lang.String game.C_100057_dd.field_104254_g
		// @55: bipush 13 (0x0D)
		// @57: anewarray java.lang.String
		// @5A: dup
		// @5B: iconst_0
		// @5C: ldc "\u00eb\u0012\u0008XE"
		// @5E: invokestatic game.C_100057_dd.func_104251_z(java.lang.String)char[]
		// @61: invokestatic game.C_100057_dd.func_104250_z(char[])java.lang.String
		// @64: aastore
		// @65: dup
		// @66: iconst_1
		// @67: ldc "\u20e4\u0015\u0008X@"
		// @69: invokestatic game.C_100057_dd.func_104251_z(java.lang.String)char[]
		// @6C: invokestatic game.C_100057_dd.func_104250_z(char[])java.lang.String
		// @6F: aastore
		// @70: dup
		// @71: iconst_2
		// @72: ldc "\u001dr\u0002J@f\u0011\u0016"
		// @74: invokestatic game.C_100057_dd.func_104251_z(java.lang.String)char[]
		// @77: invokestatic game.C_100057_dd.func_104250_z(char[])java.lang.String
		// @7A: aastore
		// @7B: dup
		// @7C: iconst_3
		// @7D: ldc "\u000b@HNU|\u000f\u001f_"
		// @7F: invokestatic game.C_100057_dd.func_104251_z(java.lang.String)char[]
		// @82: invokestatic game.C_100057_dd.func_104250_z(char[])java.lang.String
		// @85: aastore
		// @86: dup
		// @87: iconst_4
		// @88: ldc "\tTUNU~\u000f\u0013Z"
		// @8A: invokestatic game.C_100057_dd.func_104251_z(java.lang.String)char[]
		// @8D: invokestatic game.C_100057_dd.func_104250_z(char[])java.lang.String
		// @90: aastore
		// @91: dup
		// @92: iconst_5
		// @93: ldc "\u0003SHJGq\u000f\u001f_"
		// @95: invokestatic game.C_100057_dd.func_104251_z(java.lang.String)char[]
		// @98: invokestatic game.C_100057_dd.func_104250_z(char[])java.lang.String
		// @9B: aastore
		// @9C: dup
		// @9D: bipush 6 (0x06)
		// @9F: ldc ""
		// @A1: aastore
		// @A2: dup
		// @A3: bipush 7 (0x07)
		// @A5: ldc "\u001aQ\u0006[Cx"
		// @A7: invokestatic game.C_100057_dd.func_104251_z(java.lang.String)char[]
		// @AA: invokestatic game.C_100057_dd.func_104250_z(char[])java.lang.String
		// @AD: aastore
		// @AE: dup
		// @AF: bipush 8 (0x08)
		// @B1: ldc "\u001aOAJD\u007f\u000f\u001f_"
		// @B3: invokestatic game.C_100057_dd.func_104251_z(java.lang.String)char[]
		// @B6: invokestatic game.C_100057_dd.func_104250_z(char[])java.lang.String
		// @B9: aastore
		// @BA: dup
		// @BB: bipush 9 (0x09)
		// @BD: ldc "\u0006{\u0002JBf\u0018\u0013"
		// @BF: invokestatic game.C_100057_dd.func_104251_z(java.lang.String)char[]
		// @C2: invokestatic game.C_100057_dd.func_104250_z(char[])java.lang.String
		// @C5: aastore
		// @C6: dup
		// @C7: bipush 10 (0x0A)
		// @C9: ldc "\u001bf\u0002JCf\u0018\u0013"
		// @CB: invokestatic game.C_100057_dd.func_104251_z(java.lang.String)char[]
		// @CE: invokestatic game.C_100057_dd.func_104250_z(char[])java.lang.String
		// @D1: aastore
		// @D2: dup
		// @D3: bipush 11 (0x0B)
		// @D5: ldc "\u0003SHJA|\u000f\u001f_"
		// @D7: invokestatic game.C_100057_dd.func_104251_z(java.lang.String)char[]
		// @DA: invokestatic game.C_100057_dd.func_104250_z(char[])java.lang.String
		// @DD: aastore
		// @DE: dup
		// @DF: bipush 12 (0x0C)
		// @E1: ldc "\u001a\u0005\u0006]Yx\u0011"
		// @E3: invokestatic game.C_100057_dd.func_104251_z(java.lang.String)char[]
		// @E6: invokestatic game.C_100057_dd.func_104250_z(char[])java.lang.String
		// @E9: aastore
		// @EA: putstatic java.lang.String[] game.C_100057_dd.field_104255_d
		// @ED: iconst_0
		// @EE: putstatic int game.C_100057_dd.field_104256_e
		// @F1: return
	}
	
	private static char[] func_104251_z(String arg0)
	{
		// @00: aload_0
		// @01: invokevirtual java.lang.String.toCharArray()char[]
		// @04: dup
		// @05: arraylength
		// @06: iconst_2
		// @07: if_icmpge @13
		// @0A: dup
		// @0B: iconst_0
		// @0C: dup2
		// @0D: caload
		// @0E: bipush 117 (0x75)
		// @10: ixor
		// @11: i2c
		// @12: castore
		// @13: areturn
	}
	
	private static String func_104250_z(char[] arg0)
	{
		// @00: aload_0
		// @01: dup
		// @02: arraylength
		// @03: swap
		// @04: iconst_0
		// @05: istore_1
		// @06: goto @4C
		// @09: dup
		// @0A: iload_1
		// @0B: dup2
		// @0C: caload
		// @0D: iload_1
		// @0E: iconst_5
		// @0F: irem
		// @10: tableswitch def: @44, for 0: @30, for 1: @35, for 2: @3A, for 3: @3F
		// @30: bipush 72 (0x48)
		// @32: goto @46
		// @35: bipush 33 (0x21)
		// @37: goto @46
		// @3A: bipush 38 (0x26)
		// @3C: goto @46
		// @3F: bipush 106 (0x6A)
		// @41: goto @46
		// @44: bipush 117 (0x75)
		// @46: ixor
		// @47: i2c
		// @48: castore
		// @49: iinc #1 +1
		// @4C: swap
		// @4D: dup_x1
		// @4E: iload_1
		// @4F: if_icmpgt @09
		// @52: new java.lang.String
		// @55: dup_x1
		// @56: swap
		// @57: invokespecial java.lang.String.<init>(char[])void
		// @5A: invokevirtual java.lang.String.intern()java.lang.String
		// @5D: areturn
	}
}
