package game;

final class C_100343_jf extends C_100107_u
{
	private String field_104832_r;
	private String field_104830_t;
	static C_100268_mk field_104828_k;
	static String field_104833_q;
	static String field_104824_o;
	static String[] field_104831_s;
	static int field_104829_i;
	static C_100327_ib field_104834_p;
	static C_100098_h field_104823_n;
	static String field_104826_m;
	static String field_104827_j;
	static C_100043_vl field_104825_l;
	private static final String[] field_104835_z;
	
	final void func_104763_a(C_100280_nf arg0, int arg1)
	{
		// @00: bipush -6 (0xFA)
		// @02: iload_2
		// @03: bipush 65 (0x41)
		// @05: isub
		// @06: bipush 48 (0x30)
		// @08: idiv
		// @09: idiv
		// @0A: istore_3
		// @0B: aload_1
		// @0C: aload_0
		// @0D: getfield java.lang.String game.C_100343_jf.field_104832_r
		// @10: bipush -85 (0xAB)
		// @12: invokevirtual game.C_100280_nf.func_101155_a(java.lang.String, byte)void
		// @15: aload_1
		// @16: aload_0
		// @17: getfield java.lang.String game.C_100343_jf.field_104830_t
		// @1A: bipush 38 (0x26)
		// @1C: invokevirtual game.C_100280_nf.func_101148_a(java.lang.String, int)void
		// @1F: goto @5D
		// @22: astore_3
		// @23: aload_3
		// @24: new java.lang.StringBuilder
		// @27: dup
		// @28: invokespecial java.lang.StringBuilder.<init>()void
		// @2B: getstatic java.lang.String[] game.C_100343_jf.field_104835_z
		// @2E: iconst_4
		// @2F: aaload
		// @30: invokevirtual java.lang.StringBuilder.append(java.lang.String)java.lang.StringBuilder
		// @33: aload_1
		// @34: ifnull @40
		// @37: getstatic java.lang.String[] game.C_100343_jf.field_104835_z
		// @3A: iconst_1
		// @3B: aaload
		// @3C: goto @45
		// @3F: athrow
		// @40: getstatic java.lang.String[] game.C_100343_jf.field_104835_z
		// @43: iconst_2
		// @44: aaload
		// @45: invokevirtual java.lang.StringBuilder.append(java.lang.String)java.lang.StringBuilder
		// @48: bipush 44 (0x2C)
		// @4A: invokevirtual java.lang.StringBuilder.append(char)java.lang.StringBuilder
		// @4D: iload_2
		// @4E: invokevirtual java.lang.StringBuilder.append(int)java.lang.StringBuilder
		// @51: bipush 41 (0x29)
		// @53: invokevirtual java.lang.StringBuilder.append(char)java.lang.StringBuilder
		// @56: invokevirtual java.lang.StringBuilder.toString()java.lang.String
		// @59: invokestatic game.C_100181_cf.func_105695_a(java.lang.Throwable, java.lang.String)game.C_100170_cm
		// @5C: athrow
		// @5D: return
	}
	
	static final int func_104820_a(int arg0, byte arg1, CharSequence arg2)
	{
		// @00: iload_1
		// @01: bipush -10 (0xF6)
		// @03: if_icmpeq @08
		// @06: iconst_0
		// @07: ireturn
		// @08: bipush -93 (0xA3)
		// @0A: aload_2
		// @0B: iload_0
		// @0C: iconst_1
		// @0D: invokestatic game.C_100008_fl.func_103636_a(byte, java.lang.CharSequence, int, boolean)int
		// @10: ireturn
		// @11: astore_3
		// @12: aload_3
		// @13: new java.lang.StringBuilder
		// @16: dup
		// @17: invokespecial java.lang.StringBuilder.<init>()void
		// @1A: getstatic java.lang.String[] game.C_100343_jf.field_104835_z
		// @1D: bipush 6 (0x06)
		// @1F: aaload
		// @20: invokevirtual java.lang.StringBuilder.append(java.lang.String)java.lang.StringBuilder
		// @23: iload_0
		// @24: invokevirtual java.lang.StringBuilder.append(int)java.lang.StringBuilder
		// @27: bipush 44 (0x2C)
		// @29: invokevirtual java.lang.StringBuilder.append(char)java.lang.StringBuilder
		// @2C: iload_1
		// @2D: invokevirtual java.lang.StringBuilder.append(int)java.lang.StringBuilder
		// @30: bipush 44 (0x2C)
		// @32: invokevirtual java.lang.StringBuilder.append(char)java.lang.StringBuilder
		// @35: aload_2
		// @36: ifnull @42
		// @39: getstatic java.lang.String[] game.C_100343_jf.field_104835_z
		// @3C: iconst_1
		// @3D: aaload
		// @3E: goto @47
		// @41: athrow
		// @42: getstatic java.lang.String[] game.C_100343_jf.field_104835_z
		// @45: iconst_2
		// @46: aaload
		// @47: invokevirtual java.lang.StringBuilder.append(java.lang.String)java.lang.StringBuilder
		// @4A: bipush 41 (0x29)
		// @4C: invokevirtual java.lang.StringBuilder.append(char)java.lang.StringBuilder
		// @4F: invokevirtual java.lang.StringBuilder.toString()java.lang.String
		// @52: invokestatic game.C_100181_cf.func_105695_a(java.lang.Throwable, java.lang.String)game.C_100170_cm
		// @55: athrow
	}
	
	static final void func_104821_a(int arg0, int arg1, C_100277_nc arg2, int arg3, int arg4, int arg5, int arg6, int arg7)
	{
		// @000: getstatic int game.SteelSentinels.field_105275_O
		// @003: istore #40
		// @005: iload_0
		// @006: ldc -1224802049 (0xb6ff00ff)
		// @008: if_icmpeq @00C
		// @00B: return
		// @00C: aload_2
		// @00D: astore #8
		// @00F: aload #8
		// @011: getfield byte[] game.C_100277_nc.field_106718_R
		// @014: ifnull @03B
		// @017: aload #8
		// @019: getfield byte game.C_100277_nc.field_106729_l
		// @01C: iconst_1
		// @01D: if_icmple @03B
		// @020: goto @024
		// @023: athrow
		// @024: aload #8
		// @026: getfield byte[] game.C_100277_nc.field_106718_R
		// @029: astore #9
		// @02B: iconst_0
		// @02C: iconst_0
		// @02D: aload #9
		// @02F: getstatic int[] game.C_100226_ae.field_106151_c
		// @032: iconst_0
		// @033: invokestatic game.C_100300_kc.func_107064_a(int, int, byte[], int[], boolean)void
		// @036: iload #40
		// @038: ifeq @043
		// @03B: iconst_1
		// @03C: invokestatic game.C_100325_id.func_101473_a(boolean)void
		// @03F: goto @043
		// @042: athrow
		// @043: aload_2
		// @044: getfield short game.C_100277_nc.field_106735_w
		// @047: newarray int[]
		// @049: astore #8
		// @04B: aload_2
		// @04C: getfield short game.C_100277_nc.field_106735_w
		// @04F: newarray int[]
		// @051: astore #9
		// @053: getstatic int[] game.C_100124_tn.field_104931_f
		// @056: astore #10
		// @058: getstatic int[] game.C_100133_tk.field_105001_a
		// @05B: astore #11
		// @05D: getstatic int[] game.C_100116_ei.field_104120_d
		// @060: astore #12
		// @062: iconst_0
		// @063: istore #13
		// @065: iload #13
		// @067: aload_2
		// @068: getfield short game.C_100277_nc.field_106735_w
		// @06B: if_icmpge @128
		// @06E: aload #12
		// @070: iload #13
		// @072: iaload
		// @073: iload #6
		// @075: imul
		// @076: aload #11
		// @078: iload #13
		// @07A: iaload
		// @07B: iload_1
		// @07C: imul
		// @07D: iload #7
		// @07F: aload #10
		// @081: iload #13
		// @083: iaload
		// @084: imul
		// @085: iadd
		// @086: iadd
		// @087: ldc 518519912 (0x1ee7fc68)
		// @089: ishr
		// @08A: istore #14
		// @08C: iconst_0
		// @08D: iload #14
		// @08F: iload #40
		// @091: ifne @130
		// @094: if_icmpgt @09E
		// @097: goto @09B
		// @09A: athrow
		// @09B: goto @0A3
		// @09E: iload #14
		// @0A0: ineg
		// @0A1: istore #14
		// @0A3: iload #14
		// @0A5: iconst_m1
		// @0A6: ixor
		// @0A7: iconst_m1
		// @0A8: if_icmpgt @0C9
		// @0AB: sipush -129 (0xFF7F)
		// @0AE: iload #14
		// @0B0: iconst_m1
		// @0B1: ixor
		// @0B2: if_icmplt @0C0
		// @0B5: goto @0B9
		// @0B8: athrow
		// @0B9: sipush 256 (0x0100)
		// @0BC: goto @0CC
		// @0BF: athrow
		// @0C0: iload #14
		// @0C2: sipush 128 (0x0080)
		// @0C5: iadd
		// @0C6: goto @0CC
		// @0C9: sipush 128 (0x0080)
		// @0CC: istore #14
		// @0CE: aload #11
		// @0D0: iload #13
		// @0D2: iaload
		// @0D3: iload_3
		// @0D4: imul
		// @0D5: aload #10
		// @0D7: iload #13
		// @0D9: iaload
		// @0DA: iload #5
		// @0DC: imul
		// @0DD: iadd
		// @0DE: aload #12
		// @0E0: iload #13
		// @0E2: iaload
		// @0E3: iload #4
		// @0E5: imul
		// @0E6: ineg
		// @0E7: isub
		// @0E8: ldc -772107416 (0xd1fa9368)
		// @0EA: ishr
		// @0EB: istore #15
		// @0ED: getstatic int[] game.C_100158_da.field_100591_g
		// @0F0: iconst_m1
		// @0F1: iload #15
		// @0F3: iconst_m1
		// @0F4: ixor
		// @0F5: if_icmplt @0FE
		// @0F8: iload #15
		// @0FA: goto @101
		// @0FD: athrow
		// @0FE: iload #15
		// @100: ineg
		// @101: iaload
		// @102: istore #15
		// @104: iload #14
		// @106: sipush 256 (0x0100)
		// @109: iload #15
		// @10B: isub
		// @10C: imul
		// @10D: ldc 86391144 (0x5263968)
		// @10F: iushr
		// @110: istore #14
		// @112: aload #8
		// @114: iload #13
		// @116: iload #14
		// @118: iastore
		// @119: aload #9
		// @11B: iload #13
		// @11D: iload #15
		// @11F: iastore
		// @120: iinc #13 +1
		// @123: iload #40
		// @125: ifeq @065
		// @128: iconst_0
		// @129: istore #13
		// @12B: iload #13
		// @12D: getstatic int game.C_100122_em.field_102080_ac
		// @130: if_icmpge @3C7
		// @133: getstatic int[] game.C_100093_fd.field_102781_W
		// @136: iload #13
		// @138: iaload
		// @139: istore #14
		// @13B: aload_2
		// @13C: getfield short[] game.C_100277_nc.field_106733_h
		// @13F: iload #14
		// @141: saload
		// @142: istore #15
		// @144: aload_2
		// @145: getfield short[] game.C_100277_nc.field_106717_S
		// @148: iload #14
		// @14A: saload
		// @14B: istore #16
		// @14D: aload_2
		// @14E: getfield short[] game.C_100277_nc.field_106743_z
		// @151: iload #14
		// @153: saload
		// @154: istore #17
		// @156: iload #40
		// @158: ifne @441
		// @15B: getstatic int[] game.C_100124_tn.field_104931_f
		// @15E: arraylength
		// @15F: aload_2
		// @160: getfield short[] game.C_100277_nc.field_106738_t
		// @163: iload #14
		// @165: saload
		// @166: if_icmple @178
		// @169: goto @16D
		// @16C: athrow
		// @16D: aload_2
		// @16E: getfield short[] game.C_100277_nc.field_106738_t
		// @171: iload #14
		// @173: saload
		// @174: goto @179
		// @177: athrow
		// @178: iconst_m1
		// @179: istore #18
		// @17B: getstatic int[] game.C_100124_tn.field_104931_f
		// @17E: arraylength
		// @17F: iconst_m1
		// @180: ixor
		// @181: aload_2
		// @182: getfield short[] game.C_100277_nc.field_106723_e
		// @185: iload #14
		// @187: saload
		// @188: iconst_m1
		// @189: ixor
		// @18A: if_icmplt @192
		// @18D: iconst_m1
		// @18E: goto @199
		// @191: athrow
		// @192: aload_2
		// @193: getfield short[] game.C_100277_nc.field_106723_e
		// @196: iload #14
		// @198: saload
		// @199: istore #19
		// @19B: aload_2
		// @19C: getfield short[] game.C_100277_nc.field_106710_K
		// @19F: iload #14
		// @1A1: saload
		// @1A2: getstatic int[] game.C_100124_tn.field_104931_f
		// @1A5: arraylength
		// @1A6: if_icmpge @1B4
		// @1A9: aload_2
		// @1AA: getfield short[] game.C_100277_nc.field_106710_K
		// @1AD: iload #14
		// @1AF: saload
		// @1B0: goto @1B5
		// @1B3: athrow
		// @1B4: iconst_m1
		// @1B5: istore #20
		// @1B7: aconst_null
		// @1B8: getstatic game.C_100243_pd[] game.C_100152_bd.field_105199_d
		// @1BB: if_acmpeq @209
		// @1BE: aload_2
		// @1BF: getfield short[] game.C_100277_nc.field_106730_m
		// @1C2: ifnull @209
		// @1C5: goto @1C9
		// @1C8: athrow
		// @1C9: aload_2
		// @1CA: getfield short[] game.C_100277_nc.field_106730_m
		// @1CD: arraylength
		// @1CE: iload #14
		// @1D0: if_icmple @209
		// @1D3: goto @1D7
		// @1D6: athrow
		// @1D7: iconst_0
		// @1D8: aload_2
		// @1D9: getfield short[] game.C_100277_nc.field_106730_m
		// @1DC: iload #14
		// @1DE: saload
		// @1DF: iconst_m1
		// @1E0: ixor
		// @1E1: if_icmpeq @209
		// @1E4: goto @1E8
		// @1E7: athrow
		// @1E8: aload_2
		// @1E9: getfield short[] game.C_100277_nc.field_106730_m
		// @1EC: iload #14
		// @1EE: saload
		// @1EF: getstatic game.C_100243_pd[] game.C_100152_bd.field_105199_d
		// @1F2: arraylength
		// @1F3: if_icmpge @209
		// @1F6: goto @1FA
		// @1F9: athrow
		// @1FA: getstatic game.C_100243_pd[] game.C_100152_bd.field_105199_d
		// @1FD: aload_2
		// @1FE: getfield short[] game.C_100277_nc.field_106730_m
		// @201: iload #14
		// @203: saload
		// @204: aaload
		// @205: goto @20A
		// @208: athrow
		// @209: aconst_null
		// @20A: astore #21
		// @20C: getstatic int[] game.C_100017_wj.field_103824_h
		// @20F: iload #15
		// @211: iaload
		// @212: istore #22
		// @214: getstatic int[] game.C_100110_s.field_104845_e
		// @217: iload #15
		// @219: iaload
		// @21A: istore #23
		// @21C: getstatic int[] game.C_100017_wj.field_103824_h
		// @21F: iload #16
		// @221: iaload
		// @222: istore #24
		// @224: getstatic int[] game.C_100110_s.field_104845_e
		// @227: iload #16
		// @229: iaload
		// @22A: istore #25
		// @22C: getstatic int[] game.C_100017_wj.field_103824_h
		// @22F: iload #17
		// @231: iaload
		// @232: istore #26
		// @234: getstatic int[] game.C_100110_s.field_104845_e
		// @237: iload #17
		// @239: iaload
		// @23A: istore #27
		// @23C: iload #18
		// @23E: iconst_m1
		// @23F: ixor
		// @240: iload #19
		// @242: iconst_m1
		// @243: ixor
		// @244: if_icmpne @2C1
		// @247: iload #20
		// @249: iload #19
		// @24B: if_icmpne @2C1
		// @24E: goto @252
		// @251: athrow
		// @252: aload #8
		// @254: iload #18
		// @256: iaload
		// @257: istore #28
		// @259: aload #9
		// @25B: iload #18
		// @25D: iaload
		// @25E: istore #29
		// @260: aload #21
		// @262: ifnonnull @26B
		// @265: ldc 8355711 (0x7f7f7f)
		// @267: goto @270
		// @26A: athrow
		// @26B: aload #21
		// @26D: getfield int game.C_100243_pd.field_106361_a
		// @270: istore #30
		// @272: iload #30
		// @274: ldc 16711935 (0xff00ff)
		// @276: iand
		// @277: istore #31
		// @279: iload #30
		// @27B: ldc 65280 (0xff00)
		// @27D: iand
		// @27E: istore #32
		// @280: iload #28
		// @282: iload #32
		// @284: imul
		// @285: ldc 16711928 (0xff00f8)
		// @287: iand
		// @288: ldc 1229538600 (0x49494528)
		// @28A: iushr
		// @28B: ldc -1224802049 (0xb6ff00ff)
		// @28D: iload #28
		// @28F: iload #31
		// @291: imul
		// @292: ldc -221504408 (0xf2cc1c68)
		// @294: iushr
		// @295: iand
		// @296: ior
		// @297: istore #33
		// @299: iload #33
		// @29B: ldc 65793 (0x10101)
		// @29D: iload #29
		// @29F: imul
		// @2A0: iadd
		// @2A1: istore #33
		// @2A3: iload #26
		// @2A5: iload #22
		// @2A7: iload #25
		// @2A9: bipush -100 (0x9C)
		// @2AB: iload #23
		// @2AD: iload #24
		// @2AF: iload #33
		// @2B1: ldc 16711422 (0xfefefe)
		// @2B3: iand
		// @2B4: ldc 240975297 (0xe5cfdc1)
		// @2B6: ishr
		// @2B7: iload #27
		// @2B9: invokestatic game.C_100136_th.func_102611_a(int, int, int, int, int, int, int, int)void
		// @2BC: iload #40
		// @2BE: ifeq @3BF
		// @2C1: aload #8
		// @2C3: iload #18
		// @2C5: iaload
		// @2C6: istore #28
		// @2C8: aload #8
		// @2CA: iload #19
		// @2CC: iaload
		// @2CD: istore #29
		// @2CF: aload #8
		// @2D1: iload #20
		// @2D3: iaload
		// @2D4: istore #30
		// @2D6: aload #9
		// @2D8: iload #18
		// @2DA: iaload
		// @2DB: istore #31
		// @2DD: aload #9
		// @2DF: iload #19
		// @2E1: iaload
		// @2E2: istore #32
		// @2E4: aload #9
		// @2E6: iload #20
		// @2E8: iaload
		// @2E9: istore #33
		// @2EB: aload #21
		// @2ED: ifnull @2F9
		// @2F0: aload #21
		// @2F2: getfield int game.C_100243_pd.field_106361_a
		// @2F5: goto @2FB
		// @2F8: athrow
		// @2F9: ldc 8355711 (0x7f7f7f)
		// @2FB: istore #34
		// @2FD: iload #34
		// @2FF: ldc 16711935 (0xff00ff)
		// @301: iand
		// @302: istore #35
		// @304: iload #34
		// @306: ldc 65280 (0xff00)
		// @308: iand
		// @309: istore #36
		// @30B: ldc -2113994497 (0x81ff00ff)
		// @30D: iload #35
		// @30F: iload #28
		// @311: imul
		// @312: ldc -1121177144 (0xbd2c31c8)
		// @314: iushr
		// @315: iand
		// @316: ldc 1258356480 (0x4b00ff00)
		// @318: iload #28
		// @31A: iload #36
		// @31C: imul
		// @31D: ldc 604865640 (0x240d8468)
		// @31F: iushr
		// @320: iand
		// @321: ior
		// @322: istore #37
		// @324: iload #36
		// @326: iload #29
		// @328: imul
		// @329: ldc 16711728 (0xff0030)
		// @32B: iand
		// @32C: ldc -168514104 (0xf5f4adc8)
		// @32E: iushr
		// @32F: iload #35
		// @331: iload #29
		// @333: imul
		// @334: ldc 1930282184 (0x730dc4c8)
		// @336: iushr
		// @337: ldc -1526791937 (0xa4ff00ff)
		// @339: iand
		// @33A: ior
		// @33B: istore #38
		// @33D: iload #38
		// @33F: iload #32
		// @341: ldc 65793 (0x10101)
		// @343: imul
		// @344: iadd
		// @345: istore #38
		// @347: ldc -1057029889 (0xc0ff00ff)
		// @349: iload #30
		// @34B: iload #35
		// @34D: imul
		// @34E: ldc -728754488 (0xd49016c8)
		// @350: iushr
		// @351: iand
		// @352: ldc 16711812 (0xff0084)
		// @354: iload #30
		// @356: iload #36
		// @358: imul
		// @359: iand
		// @35A: ldc 2052068264 (0x7a5013a8)
		// @35C: iushr
		// @35D: ior
		// @35E: istore #39
		// @360: iload #37
		// @362: iload #31
		// @364: ldc 65793 (0x10101)
		// @366: imul
		// @367: iadd
		// @368: istore #37
		// @36A: iload #39
		// @36C: ldc 65793 (0x10101)
		// @36E: iload #33
		// @370: imul
		// @371: iadd
		// @372: istore #39
		// @374: iload #25
		// @376: iload #22
		// @378: iload #39
		// @37A: ldc 65402 (0xff7a)
		// @37C: iand
		// @37D: ldc 1434439752 (0x557fd048)
		// @37F: ishr
		// @380: iload #37
		// @382: sipush 255 (0x00FF)
		// @385: iand
		// @386: bipush -5 (0xFB)
		// @388: iload #24
		// @38A: iload #27
		// @38C: iload #37
		// @38E: ldc -1558498200 (0xa31b3468)
		// @390: ishr
		// @391: sipush 255 (0x00FF)
		// @394: iand
		// @395: iload #37
		// @397: ldc -2071962832 (0x84805b30)
		// @399: ishr
		// @39A: sipush 255 (0x00FF)
		// @39D: iload #39
		// @39F: iand
		// @3A0: iload #23
		// @3A2: iload #38
		// @3A4: ldc -1371603344 (0xae3efe70)
		// @3A6: ishr
		// @3A7: iload #39
		// @3A9: ldc -313613168 (0xed4ea490)
		// @3AB: ishr
		// @3AC: iload #26
		// @3AE: ldc 65400 (0xff78)
		// @3B0: iload #38
		// @3B2: iand
		// @3B3: ldc 809666056 (0x30428608)
		// @3B5: ishr
		// @3B6: sipush 255 (0x00FF)
		// @3B9: iload #38
		// @3BB: iand
		// @3BC: invokestatic game.C_100282_nh.func_102703_a(int, int, int, int, int, int, int, int, int, int, int, int, int, int, int, int)void
		// @3BF: iinc #13 +1
		// @3C2: iload #40
		// @3C4: ifeq @12B
		// @3C7: goto @441
		// @3CA: astore #8
		// @3CC: aload #8
		// @3CE: new java.lang.StringBuilder
		// @3D1: dup
		// @3D2: invokespecial java.lang.StringBuilder.<init>()void
		// @3D5: getstatic java.lang.String[] game.C_100343_jf.field_104835_z
		// @3D8: iconst_0
		// @3D9: aaload
		// @3DA: invokevirtual java.lang.StringBuilder.append(java.lang.String)java.lang.StringBuilder
		// @3DD: iload_0
		// @3DE: invokevirtual java.lang.StringBuilder.append(int)java.lang.StringBuilder
		// @3E1: bipush 44 (0x2C)
		// @3E3: invokevirtual java.lang.StringBuilder.append(char)java.lang.StringBuilder
		// @3E6: iload_1
		// @3E7: invokevirtual java.lang.StringBuilder.append(int)java.lang.StringBuilder
		// @3EA: bipush 44 (0x2C)
		// @3EC: invokevirtual java.lang.StringBuilder.append(char)java.lang.StringBuilder
		// @3EF: aload_2
		// @3F0: ifnull @3FC
		// @3F3: getstatic java.lang.String[] game.C_100343_jf.field_104835_z
		// @3F6: iconst_1
		// @3F7: aaload
		// @3F8: goto @401
		// @3FB: athrow
		// @3FC: getstatic java.lang.String[] game.C_100343_jf.field_104835_z
		// @3FF: iconst_2
		// @400: aaload
		// @401: invokevirtual java.lang.StringBuilder.append(java.lang.String)java.lang.StringBuilder
		// @404: bipush 44 (0x2C)
		// @406: invokevirtual java.lang.StringBuilder.append(char)java.lang.StringBuilder
		// @409: iload_3
		// @40A: invokevirtual java.lang.StringBuilder.append(int)java.lang.StringBuilder
		// @40D: bipush 44 (0x2C)
		// @40F: invokevirtual java.lang.StringBuilder.append(char)java.lang.StringBuilder
		// @412: iload #4
		// @414: invokevirtual java.lang.StringBuilder.append(int)java.lang.StringBuilder
		// @417: bipush 44 (0x2C)
		// @419: invokevirtual java.lang.StringBuilder.append(char)java.lang.StringBuilder
		// @41C: iload #5
		// @41E: invokevirtual java.lang.StringBuilder.append(int)java.lang.StringBuilder
		// @421: bipush 44 (0x2C)
		// @423: invokevirtual java.lang.StringBuilder.append(char)java.lang.StringBuilder
		// @426: iload #6
		// @428: invokevirtual java.lang.StringBuilder.append(int)java.lang.StringBuilder
		// @42B: bipush 44 (0x2C)
		// @42D: invokevirtual java.lang.StringBuilder.append(char)java.lang.StringBuilder
		// @430: iload #7
		// @432: invokevirtual java.lang.StringBuilder.append(int)java.lang.StringBuilder
		// @435: bipush 41 (0x29)
		// @437: invokevirtual java.lang.StringBuilder.append(char)java.lang.StringBuilder
		// @43A: invokevirtual java.lang.StringBuilder.toString()java.lang.String
		// @43D: invokestatic game.C_100181_cf.func_105695_a(java.lang.Throwable, java.lang.String)game.C_100170_cm
		// @440: athrow
		// @441: return
	}
	
	final C_100013_fn func_104766_b(int arg0)
	{
		// @00: iload_1
		// @01: ifeq @1D
		// @04: bipush 86 (0x56)
		// @06: bipush -78 (0xB2)
		// @08: aconst_null
		// @09: checkcast game.C_100277_nc
		// @0C: bipush 39 (0x27)
		// @0E: bipush -126 (0x82)
		// @10: bipush -116 (0x8C)
		// @12: bipush 28 (0x1C)
		// @14: bipush -64 (0xC0)
		// @16: invokestatic game.C_100343_jf.func_104821_a(int, int, game.C_100277_nc, int, int, int, int, int)void
		// @19: goto @1D
		// @1C: athrow
		// @1D: getstatic game.C_100013_fn game.C_100060_di.field_104273_a
		// @20: areturn
		// @21: astore_2
		// @22: aload_2
		// @23: new java.lang.StringBuilder
		// @26: dup
		// @27: invokespecial java.lang.StringBuilder.<init>()void
		// @2A: getstatic java.lang.String[] game.C_100343_jf.field_104835_z
		// @2D: bipush 7 (0x07)
		// @2F: aaload
		// @30: invokevirtual java.lang.StringBuilder.append(java.lang.String)java.lang.StringBuilder
		// @33: iload_1
		// @34: invokevirtual java.lang.StringBuilder.append(int)java.lang.StringBuilder
		// @37: bipush 41 (0x29)
		// @39: invokevirtual java.lang.StringBuilder.append(char)java.lang.StringBuilder
		// @3C: invokevirtual java.lang.StringBuilder.toString()java.lang.String
		// @3F: invokestatic game.C_100181_cf.func_105695_a(java.lang.Throwable, java.lang.String)game.C_100170_cm
		// @42: athrow
	}
	
	public static void func_104816_c(int arg0)
	{
		// @00: aconst_null
		// @01: putstatic java.lang.String game.C_100343_jf.field_104826_m
		// @04: aconst_null
		// @05: putstatic java.lang.String game.C_100343_jf.field_104833_q
		// @08: aconst_null
		// @09: putstatic game.C_100098_h game.C_100343_jf.field_104823_n
		// @0C: aconst_null
		// @0D: putstatic game.C_100327_ib game.C_100343_jf.field_104834_p
		// @10: iload_0
		// @11: bipush -104 (0x98)
		// @13: if_icmple @17
		// @16: return
		// @17: aconst_null
		// @18: putstatic game.C_100043_vl game.C_100343_jf.field_104825_l
		// @1B: aconst_null
		// @1C: putstatic java.lang.String game.C_100343_jf.field_104827_j
		// @1F: aconst_null
		// @20: putstatic game.C_100268_mk game.C_100343_jf.field_104828_k
		// @23: aconst_null
		// @24: putstatic java.lang.String[] game.C_100343_jf.field_104831_s
		// @27: aconst_null
		// @28: putstatic java.lang.String game.C_100343_jf.field_104824_o
		// @2B: goto @4F
		// @2E: astore_1
		// @2F: aload_1
		// @30: new java.lang.StringBuilder
		// @33: dup
		// @34: invokespecial java.lang.StringBuilder.<init>()void
		// @37: getstatic java.lang.String[] game.C_100343_jf.field_104835_z
		// @3A: iconst_3
		// @3B: aaload
		// @3C: invokevirtual java.lang.StringBuilder.append(java.lang.String)java.lang.StringBuilder
		// @3F: iload_0
		// @40: invokevirtual java.lang.StringBuilder.append(int)java.lang.StringBuilder
		// @43: bipush 41 (0x29)
		// @45: invokevirtual java.lang.StringBuilder.append(char)java.lang.StringBuilder
		// @48: invokevirtual java.lang.StringBuilder.toString()java.lang.String
		// @4B: invokestatic game.C_100181_cf.func_105695_a(java.lang.Throwable, java.lang.String)game.C_100170_cm
		// @4E: athrow
		// @4F: return
	}
	
	C_100343_jf(String arg0, String arg1)
	{
		// @00: aload_0
		// @01: invokespecial game.C_100107_u.<init>()void
		// @04: aload_0
		// @05: aload_1
		// @06: putfield java.lang.String game.C_100343_jf.field_104832_r
		// @09: aload_0
		// @0A: aload_2
		// @0B: putfield java.lang.String game.C_100343_jf.field_104830_t
		// @0E: goto @5E
		// @11: astore_3
		// @12: aload_3
		// @13: new java.lang.StringBuilder
		// @16: dup
		// @17: invokespecial java.lang.StringBuilder.<init>()void
		// @1A: getstatic java.lang.String[] game.C_100343_jf.field_104835_z
		// @1D: bipush 10 (0x0A)
		// @1F: aaload
		// @20: invokevirtual java.lang.StringBuilder.append(java.lang.String)java.lang.StringBuilder
		// @23: aload_1
		// @24: ifnull @30
		// @27: getstatic java.lang.String[] game.C_100343_jf.field_104835_z
		// @2A: iconst_1
		// @2B: aaload
		// @2C: goto @35
		// @2F: athrow
		// @30: getstatic java.lang.String[] game.C_100343_jf.field_104835_z
		// @33: iconst_2
		// @34: aaload
		// @35: invokevirtual java.lang.StringBuilder.append(java.lang.String)java.lang.StringBuilder
		// @38: bipush 44 (0x2C)
		// @3A: invokevirtual java.lang.StringBuilder.append(char)java.lang.StringBuilder
		// @3D: aload_2
		// @3E: ifnull @4A
		// @41: getstatic java.lang.String[] game.C_100343_jf.field_104835_z
		// @44: iconst_1
		// @45: aaload
		// @46: goto @4F
		// @49: athrow
		// @4A: getstatic java.lang.String[] game.C_100343_jf.field_104835_z
		// @4D: iconst_2
		// @4E: aaload
		// @4F: invokevirtual java.lang.StringBuilder.append(java.lang.String)java.lang.StringBuilder
		// @52: bipush 41 (0x29)
		// @54: invokevirtual java.lang.StringBuilder.append(char)java.lang.StringBuilder
		// @57: invokevirtual java.lang.StringBuilder.toString()java.lang.String
		// @5A: invokestatic game.C_100181_cf.func_105695_a(java.lang.Throwable, java.lang.String)game.C_100170_cm
		// @5D: athrow
		// @5E: return
	}
	
	static final void func_104822_d(int arg0)
	{
		// @000: getstatic int game.SteelSentinels.field_105275_O
		// @003: istore #9
		// @005: getstatic game.C_100278_nd game.C_100288_jn.field_106839_f
		// @008: astore_1
		// @009: aload_1
		// @00A: iconst_0
		// @00B: invokevirtual game.C_100278_nd.func_101156_c(boolean)int
		// @00E: istore_2
		// @00F: iconst_0
		// @010: iload_2
		// @011: if_icmpne @102
		// @014: getstatic game.C_100105_eg game.C_100003_ga.field_103533_h
		// @017: ifnull @022
		// @01A: goto @01E
		// @01D: athrow
		// @01E: goto @033
		// @021: athrow
		// @022: new game.C_100105_eg
		// @025: dup
		// @026: sipush 128 (0x0080)
		// @029: invokespecial game.C_100105_eg.<init>(int)void
		// @02C: putstatic game.C_100105_eg game.C_100003_ga.field_103533_h
		// @02F: iconst_0
		// @030: putstatic int game.C_100316_lc.field_102407_A
		// @033: bipush -2 (0xFE)
		// @035: aload_1
		// @036: iconst_0
		// @037: invokevirtual game.C_100278_nd.func_101156_c(boolean)int
		// @03A: iconst_m1
		// @03B: ixor
		// @03C: if_icmpne @044
		// @03F: iconst_1
		// @040: goto @045
		// @043: athrow
		// @044: iconst_0
		// @045: istore_3
		// @046: aload_1
		// @047: sipush 9692 (0x25DC)
		// @04A: invokevirtual game.C_100278_nd.func_101164_f(int)java.lang.String
		// @04D: astore #4
		// @04F: iload_3
		// @050: ifne @05C
		// @053: aload #4
		// @055: astore #5
		// @057: iload #9
		// @059: ifeq @066
		// @05C: aload_1
		// @05D: iload_0
		// @05E: ldc 313622860 (0x12b1814c)
		// @060: iadd
		// @061: invokevirtual game.C_100278_nd.func_101164_f(int)java.lang.String
		// @064: astore #5
		// @066: aload #4
		// @068: bipush 93 (0x5D)
		// @06A: invokestatic game.C_100075_uj.func_100640_a(java.lang.String, int)game.C_100061_dh
		// @06D: astore #6
		// @06F: aload_1
		// @070: sipush 9692 (0x25DC)
		// @073: invokevirtual game.C_100278_nd.func_101164_f(int)java.lang.String
		// @076: astore #7
		// @078: bipush 105 (0x69)
		// @07A: aload #4
		// @07C: invokestatic game.C_100106_ef.func_104742_a(byte, java.lang.CharSequence)java.lang.String
		// @07F: astore #8
		// @081: aload #8
		// @083: ifnonnull @08A
		// @086: aload #4
		// @088: astore #8
		// @08A: aconst_null
		// @08B: aload #6
		// @08D: if_acmpne @0B5
		// @090: aload #7
		// @092: bipush -112 (0x90)
		// @094: invokestatic game.C_100075_uj.func_100640_a(java.lang.String, int)game.C_100061_dh
		// @097: astore #6
		// @099: aconst_null
		// @09A: aload #6
		// @09C: if_acmpne @0A3
		// @09F: goto @0B5
		// @0A2: athrow
		// @0A3: getstatic game.C_100105_eg game.C_100003_ga.field_103533_h
		// @0A6: aload #6
		// @0A8: iload_0
		// @0A9: ldc 313613167 (0x12b15b6f)
		// @0AB: ixor
		// @0AC: aload #8
		// @0AE: invokevirtual java.lang.String.hashCode()int
		// @0B1: i2l
		// @0B2: invokevirtual game.C_100105_eg.func_104725_a(game.C_100325_id, int, long)void
		// @0B5: aload #6
		// @0B7: ifnonnull @0EC
		// @0BA: new game.C_100061_dh
		// @0BD: dup
		// @0BE: invokespecial game.C_100061_dh.<init>()void
		// @0C1: astore #6
		// @0C3: getstatic game.C_100105_eg game.C_100003_ga.field_103533_h
		// @0C6: aload #6
		// @0C8: iconst_m1
		// @0C9: aload #8
		// @0CB: invokevirtual java.lang.String.hashCode()int
		// @0CE: i2l
		// @0CF: invokevirtual game.C_100105_eg.func_104725_a(game.C_100325_id, int, long)void
		// @0D2: aload #6
		// @0D4: getstatic int game.C_100316_lc.field_102407_A
		// @0D7: dup
		// @0D8: iconst_1
		// @0D9: iadd
		// @0DA: putstatic int game.C_100316_lc.field_102407_A
		// @0DD: putfield int game.C_100061_dh.field_101984_hc
		// @0E0: getstatic game.C_100202_qi game.C_100312_ld.field_107155_b
		// @0E3: iload_0
		// @0E4: ldc 313613292 (0x12b15bec)
		// @0E6: iadd
		// @0E7: aload #6
		// @0E9: invokevirtual game.C_100202_qi.func_105901_a(int, game.C_100158_da)void
		// @0EC: aload #6
		// @0EE: aload #4
		// @0F0: putfield java.lang.String game.C_100061_dh.field_101993_nc
		// @0F3: aload #6
		// @0F5: aload #5
		// @0F7: putfield java.lang.String game.C_100061_dh.field_101990_oc
		// @0FA: aload #6
		// @0FC: aload #7
		// @0FE: putfield java.lang.String game.C_100061_dh.field_101997_ac
		// @101: return
		// @102: iload_2
		// @103: iconst_m1
		// @104: ixor
		// @105: bipush -2 (0xFE)
		// @107: if_icmpne @25E
		// @10A: getstatic game.C_100105_eg game.C_100170_cm.field_105536_f
		// @10D: ifnull @118
		// @110: goto @114
		// @113: athrow
		// @114: goto @129
		// @117: athrow
		// @118: new game.C_100105_eg
		// @11B: dup
		// @11C: sipush 128 (0x0080)
		// @11F: invokespecial game.C_100105_eg.<init>(int)void
		// @122: putstatic game.C_100105_eg game.C_100170_cm.field_105536_f
		// @125: iconst_0
		// @126: putstatic int game.C_100291_jj.field_106878_a
		// @129: aload_1
		// @12A: sipush 9692 (0x25DC)
		// @12D: invokevirtual game.C_100278_nd.func_101164_f(int)java.lang.String
		// @130: astore_3
		// @131: aload_3
		// @132: ldc ""
		// @134: invokevirtual java.lang.String.equals(java.lang.Object)boolean
		// @137: ifne @13E
		// @13A: goto @140
		// @13D: athrow
		// @13E: aconst_null
		// @13F: astore_3
		// @140: aload_1
		// @141: sipush 9692 (0x25DC)
		// @144: invokevirtual game.C_100278_nd.func_101164_f(int)java.lang.String
		// @147: astore #4
		// @149: aload_1
		// @14A: iload_0
		// @14B: ldc 313622860 (0x12b1814c)
		// @14D: iadd
		// @14E: invokevirtual game.C_100278_nd.func_101164_f(int)java.lang.String
		// @151: astore #5
		// @153: aload #4
		// @155: iload_0
		// @156: ldc 313613228 (0x12b15bac)
		// @158: iadd
		// @159: invokestatic game.C_100278_nd.func_101197_b(java.lang.String, int)game.C_100061_dh
		// @15C: astore #6
		// @15E: aconst_null
		// @15F: aload #6
		// @161: if_acmpeq @168
		// @164: goto @194
		// @167: athrow
		// @168: aload #5
		// @16A: iload_0
		// @16B: ldc -313613140 (0xed4ea4ac)
		// @16D: ixor
		// @16E: invokestatic game.C_100278_nd.func_101197_b(java.lang.String, int)game.C_100061_dh
		// @171: astore #6
		// @173: aconst_null
		// @174: aload #6
		// @176: if_acmpeq @194
		// @179: getstatic game.C_100105_eg game.C_100170_cm.field_105536_f
		// @17C: aload #6
		// @17E: iload_0
		// @17F: ldc 313613167 (0x12b15b6f)
		// @181: ixor
		// @182: bipush -119 (0x89)
		// @184: aload #4
		// @186: invokestatic game.C_100106_ef.func_104742_a(byte, java.lang.CharSequence)java.lang.String
		// @189: invokevirtual java.lang.String.hashCode()int
		// @18C: i2l
		// @18D: invokevirtual game.C_100105_eg.func_104725_a(game.C_100325_id, int, long)void
		// @190: goto @194
		// @193: athrow
		// @194: aconst_null
		// @195: aload #6
		// @197: if_acmpeq @19E
		// @19A: goto @1D3
		// @19D: athrow
		// @19E: new game.C_100061_dh
		// @1A1: dup
		// @1A2: invokespecial game.C_100061_dh.<init>()void
		// @1A5: astore #6
		// @1A7: getstatic game.C_100105_eg game.C_100170_cm.field_105536_f
		// @1AA: aload #6
		// @1AC: iconst_m1
		// @1AD: bipush -96 (0xA0)
		// @1AF: aload #4
		// @1B1: invokestatic game.C_100106_ef.func_104742_a(byte, java.lang.CharSequence)java.lang.String
		// @1B4: invokevirtual java.lang.String.hashCode()int
		// @1B7: i2l
		// @1B8: invokevirtual game.C_100105_eg.func_104725_a(game.C_100325_id, int, long)void
		// @1BB: aload #6
		// @1BD: getstatic int game.C_100291_jj.field_106878_a
		// @1C0: dup
		// @1C1: iconst_1
		// @1C2: iadd
		// @1C3: putstatic int game.C_100291_jj.field_106878_a
		// @1C6: putfield int game.C_100061_dh.field_101984_hc
		// @1C9: getstatic game.C_100202_qi game.C_100085_a.field_102569_L
		// @1CC: bipush 126 (0x7E)
		// @1CE: aload #6
		// @1D0: invokevirtual game.C_100202_qi.func_105901_a(int, game.C_100158_da)void
		// @1D3: aconst_null
		// @1D4: aload_3
		// @1D5: if_acmpne @1DC
		// @1D8: goto @1E1
		// @1DB: athrow
		// @1DC: aload_3
		// @1DD: invokevirtual java.lang.String.intern()java.lang.String
		// @1E0: astore_3
		// @1E1: aload #6
		// @1E3: aload #5
		// @1E5: putfield java.lang.String game.C_100061_dh.field_101997_ac
		// @1E8: aload #6
		// @1EA: aload_3
		// @1EB: putfield java.lang.String game.C_100061_dh.field_101996_kc
		// @1EE: aload #6
		// @1F0: aload #4
		// @1F2: putfield java.lang.String game.C_100061_dh.field_101993_nc
		// @1F5: aload #6
		// @1F7: iload_0
		// @1F8: ldc 313613213 (0x12b15b9d)
		// @1FA: iadd
		// @1FB: invokevirtual game.C_100061_dh.func_100583_c(int)void
		// @1FE: getstatic game.C_100202_qi game.C_100085_a.field_102569_L
		// @201: bipush 85 (0x55)
		// @203: invokevirtual game.C_100202_qi.func_105899_c(int)game.C_100158_da
		// @206: checkcast game.C_100061_dh
		// @209: astore #7
		// @20B: aconst_null
		// @20C: aload #7
		// @20E: if_acmpeq @238
		// @211: bipush 66 (0x42)
		// @213: aload #7
		// @215: aload #6
		// @217: invokestatic game.C_100327_ib.func_102449_a(byte, game.C_100061_dh, game.C_100061_dh)boolean
		// @21A: iload #9
		// @21C: ifne @243
		// @21F: ifeq @238
		// @222: goto @226
		// @225: athrow
		// @226: getstatic game.C_100202_qi game.C_100085_a.field_102569_L
		// @229: bipush 93 (0x5D)
		// @22B: invokevirtual game.C_100202_qi.func_105907_c(byte)game.C_100158_da
		// @22E: checkcast game.C_100061_dh
		// @231: astore #7
		// @233: iload #9
		// @235: ifeq @20B
		// @238: aload #7
		// @23A: ifnull @24F
		// @23D: bipush 72 (0x48)
		// @23F: goto @243
		// @242: athrow
		// @243: aload #6
		// @245: aload #7
		// @247: invokestatic game.C_100042_we.func_104130_a(int, game.C_100158_da, game.C_100158_da)void
		// @24A: iload #9
		// @24C: ifeq @25D
		// @24F: getstatic game.C_100202_qi game.C_100085_a.field_102569_L
		// @252: bipush 123 (0x7B)
		// @254: aload #6
		// @256: invokevirtual game.C_100202_qi.func_105901_a(int, game.C_100158_da)void
		// @259: goto @25D
		// @25C: athrow
		// @25D: return
		// @25E: bipush -3 (0xFD)
		// @260: iload_2
		// @261: iconst_m1
		// @262: ixor
		// @263: if_icmpne @27D
		// @266: bipush -2 (0xFE)
		// @268: getstatic int game.C_100062_dk.field_104281_d
		// @26B: iconst_m1
		// @26C: ixor
		// @26D: if_icmpeq @278
		// @270: goto @274
		// @273: athrow
		// @274: goto @27C
		// @277: athrow
		// @278: iconst_2
		// @279: putstatic int game.C_100062_dk.field_104281_d
		// @27C: return
		// @27D: iload_2
		// @27E: iconst_m1
		// @27F: ixor
		// @280: bipush -4 (0xFC)
		// @282: if_icmpne @299
		// @285: iconst_2
		// @286: getstatic int game.C_100062_dk.field_104281_d
		// @289: if_icmpne @298
		// @28C: goto @290
		// @28F: athrow
		// @290: iconst_1
		// @291: putstatic int game.C_100062_dk.field_104281_d
		// @294: goto @298
		// @297: athrow
		// @298: return
		// @299: bipush -5 (0xFB)
		// @29B: iload_2
		// @29C: iconst_m1
		// @29D: ixor
		// @29E: if_icmpeq @2A5
		// @2A1: goto @2C7
		// @2A4: athrow
		// @2A5: iconst_1
		// @2A6: putstatic int game.C_100062_dk.field_104281_d
		// @2A9: aload_1
		// @2AA: sipush 9692 (0x25DC)
		// @2AD: invokevirtual game.C_100278_nd.func_101164_f(int)java.lang.String
		// @2B0: astore_3
		// @2B1: aload_3
		// @2B2: invokevirtual java.lang.String.intern()java.lang.String
		// @2B5: putstatic java.lang.String game.C_100119_ua.field_104909_i
		// @2B8: aload_1
		// @2B9: iconst_0
		// @2BA: invokevirtual game.C_100278_nd.func_101156_c(boolean)int
		// @2BD: istore #4
		// @2BF: iload #4
		// @2C1: bipush 118 (0x76)
		// @2C3: invokestatic game.C_100278_nd.func_101199_j(int, int)void
		// @2C6: return
		// @2C7: iload_0
		// @2C8: ldc -313613167 (0xed4ea491)
		// @2CA: ixor
		// @2CB: new java.lang.StringBuilder
		// @2CE: dup
		// @2CF: invokespecial java.lang.StringBuilder.<init>()void
		// @2D2: getstatic java.lang.String[] game.C_100343_jf.field_104835_z
		// @2D5: bipush 9 (0x09)
		// @2D7: aaload
		// @2D8: invokevirtual java.lang.StringBuilder.append(java.lang.String)java.lang.StringBuilder
		// @2DB: bipush 104 (0x68)
		// @2DD: invokestatic game.C_100316_lc.func_102399_d(byte)java.lang.String
		// @2E0: invokevirtual java.lang.StringBuilder.append(java.lang.String)java.lang.StringBuilder
		// @2E3: invokevirtual java.lang.StringBuilder.toString()java.lang.String
		// @2E6: aconst_null
		// @2E7: invokestatic game.C_100036_gg.func_103142_a(int, java.lang.String, java.lang.Throwable)void
		// @2EA: iload_0
		// @2EB: ldc -313613168 (0xed4ea490)
		// @2ED: if_icmpeq @2FB
		// @2F0: aconst_null
		// @2F1: checkcast java.lang.String
		// @2F4: putstatic java.lang.String game.C_100343_jf.field_104826_m
		// @2F7: goto @2FB
		// @2FA: athrow
		// @2FB: sipush 13313 (0x3401)
		// @2FE: invokestatic game.C_100095_fe.func_103371_l(int)void
		// @301: goto @326
		// @304: astore_1
		// @305: aload_1
		// @306: new java.lang.StringBuilder
		// @309: dup
		// @30A: invokespecial java.lang.StringBuilder.<init>()void
		// @30D: getstatic java.lang.String[] game.C_100343_jf.field_104835_z
		// @310: bipush 8 (0x08)
		// @312: aaload
		// @313: invokevirtual java.lang.StringBuilder.append(java.lang.String)java.lang.StringBuilder
		// @316: iload_0
		// @317: invokevirtual java.lang.StringBuilder.append(int)java.lang.StringBuilder
		// @31A: bipush 41 (0x29)
		// @31C: invokevirtual java.lang.StringBuilder.append(char)java.lang.StringBuilder
		// @31F: invokevirtual java.lang.StringBuilder.toString()java.lang.String
		// @322: invokestatic game.C_100181_cf.func_105695_a(java.lang.Throwable, java.lang.String)game.C_100170_cm
		// @325: athrow
		// @326: return
	}
	
	static final void func_104818_a(byte arg0)
	{
		// @00: getstatic game.C_100177_cj game.C_100313_lg.field_107164_d
		// @03: ifnonnull @0A
		// @06: goto @10
		// @09: athrow
		// @0A: getstatic game.C_100177_cj game.C_100313_lg.field_107164_d
		// @0D: invokevirtual game.C_100177_cj.func_105638_e()void
		// @10: iload_0
		// @11: bipush -19 (0xED)
		// @13: if_icmpeq @17
		// @16: return
		// @17: getstatic game.C_100177_cj game.C_100341_jd.field_102643_gb
		// @1A: ifnull @23
		// @1D: getstatic game.C_100177_cj game.C_100341_jd.field_102643_gb
		// @20: invokevirtual game.C_100177_cj.func_105638_e()void
		// @23: goto @47
		// @26: astore_1
		// @27: aload_1
		// @28: new java.lang.StringBuilder
		// @2B: dup
		// @2C: invokespecial java.lang.StringBuilder.<init>()void
		// @2F: getstatic java.lang.String[] game.C_100343_jf.field_104835_z
		// @32: iconst_5
		// @33: aaload
		// @34: invokevirtual java.lang.StringBuilder.append(java.lang.String)java.lang.StringBuilder
		// @37: iload_0
		// @38: invokevirtual java.lang.StringBuilder.append(int)java.lang.StringBuilder
		// @3B: bipush 41 (0x29)
		// @3D: invokevirtual java.lang.StringBuilder.append(char)java.lang.StringBuilder
		// @40: invokevirtual java.lang.StringBuilder.toString()java.lang.String
		// @43: invokestatic game.C_100181_cf.func_105695_a(java.lang.Throwable, java.lang.String)game.C_100170_cm
		// @46: athrow
		// @47: return
	}
	
	static
	{
		// @00: bipush 11 (0x0B)
		// @02: anewarray java.lang.String
		// @05: dup
		// @06: iconst_0
		// @07: ldc "5$\u0010\u000e\u007f"
		// @09: invokestatic game.C_100343_jf.func_104819_z(java.lang.String)char[]
		// @0C: invokestatic game.C_100343_jf.func_104817_z(char[])java.lang.String
		// @0F: aastore
		// @10: dup
		// @11: iconst_1
		// @12: ldc "$l\u0010k*"
		// @14: invokestatic game.C_100343_jf.func_104819_z(java.lang.String)char[]
		// @17: invokestatic game.C_100343_jf.func_104817_z(char[])java.lang.String
		// @1A: aastore
		// @1B: dup
		// @1C: iconst_2
		// @1D: ldc "17R)"
		// @1F: invokestatic game.C_100343_jf.func_104819_z(java.lang.String)char[]
		// @22: invokestatic game.C_100343_jf.func_104817_z(char[])java.lang.String
		// @25: aastore
		// @26: dup
		// @27: iconst_3
		// @28: ldc "5$\u0010\t\u007f"
		// @2A: invokestatic game.C_100343_jf.func_104819_z(java.lang.String)char[]
		// @2D: invokestatic game.C_100343_jf.func_104817_z(char[])java.lang.String
		// @30: aastore
		// @31: dup
		// @32: iconst_4
		// @33: ldc "5$\u0010\u0000\u007f"
		// @35: invokestatic game.C_100343_jf.func_104819_z(java.lang.String)char[]
		// @38: invokestatic game.C_100343_jf.func_104817_z(char[])java.lang.String
		// @3B: aastore
		// @3C: dup
		// @3D: iconst_5
		// @3E: ldc "5$\u0010\u000c\u007f"
		// @40: invokestatic game.C_100343_jf.func_104819_z(java.lang.String)char[]
		// @43: invokestatic game.C_100343_jf.func_104817_z(char[])java.lang.String
		// @46: aastore
		// @47: dup
		// @48: bipush 6 (0x06)
		// @4A: ldc "5$\u0010\u000f\u007f"
		// @4C: invokestatic game.C_100343_jf.func_104819_z(java.lang.String)char[]
		// @4F: invokestatic game.C_100343_jf.func_104817_z(char[])java.lang.String
		// @52: aastore
		// @53: dup
		// @54: bipush 7 (0x07)
		// @56: ldc "5$\u0010\u0002\u007f"
		// @58: invokestatic game.C_100343_jf.func_104819_z(java.lang.String)char[]
		// @5B: invokestatic game.C_100343_jf.func_104817_z(char[])java.lang.String
		// @5E: aastore
		// @5F: dup
		// @60: bipush 8 (0x08)
		// @62: ldc "5$\u0010\r\u007f"
		// @64: invokestatic game.C_100343_jf.func_104819_z(java.lang.String)char[]
		// @67: invokestatic game.C_100343_jf.func_104817_z(char[])java.lang.String
		// @6A: aastore
		// @6B: dup
		// @6C: bipush 9 (0x09)
		// @6E: ldc "\u0019s\u0004e"
		// @70: invokestatic game.C_100343_jf.func_104819_z(java.lang.String)char[]
		// @73: invokestatic game.C_100343_jf.func_104817_z(char[])java.lang.String
		// @76: aastore
		// @77: dup
		// @78: bipush 10 (0x0A)
		// @7A: ldc "5$\u0010y>1+J{\u007f"
		// @7C: invokestatic game.C_100343_jf.func_104819_z(java.lang.String)char[]
		// @7F: invokestatic game.C_100343_jf.func_104817_z(char[])java.lang.String
		// @82: aastore
		// @83: putstatic java.lang.String[] game.C_100343_jf.field_104835_z
		// @86: new game.C_100268_mk
		// @89: dup
		// @8A: invokespecial game.C_100268_mk.<init>()void
		// @8D: putstatic game.C_100268_mk game.C_100343_jf.field_104828_k
		// @90: ldc "D"
		// @92: putstatic java.lang.String game.C_100343_jf.field_104833_q
		// @95: iconst_2
		// @96: anewarray java.lang.String
		// @99: dup
		// @9A: iconst_0
		// @9B: ldc "\u001d;\u001e76++P\""
		// @9D: invokestatic game.C_100343_jf.func_104819_z(java.lang.String)char[]
		// @A0: invokestatic game.C_100343_jf.func_104817_z(char[])java.lang.String
		// @A3: aastore
		// @A4: dup
		// @A5: iconst_1
		// @A6: ldc "\u001d;\u001e2>1bN %<'P168'"
		// @A8: invokestatic game.C_100343_jf.func_104819_z(java.lang.String)char[]
		// @AB: invokestatic game.C_100343_jf.func_104817_z(char[])java.lang.String
		// @AE: aastore
		// @AF: putstatic java.lang.String[] game.C_100343_jf.field_104831_s
		// @B2: ldc "\u000b*W6w8#S w61\u001e#\"3.\u0010"
		// @B4: invokestatic game.C_100343_jf.func_104819_z(java.lang.String)char[]
		// @B7: invokestatic game.C_100343_jf.func_104817_z(char[])java.lang.String
		// @BA: putstatic java.lang.String game.C_100343_jf.field_104826_m
		// @BD: ldc "cg\u000e{w61\u001e+8+bQ+w&-K7w90W 9;bR,$+l"
		// @BF: invokestatic game.C_100343_jf.func_104819_z(java.lang.String)char[]
		// @C2: invokestatic game.C_100343_jf.func_104817_z(char[])java.lang.String
		// @C5: putstatic java.lang.String game.C_100343_jf.field_104824_o
		// @C8: ldc "\u000f#K62\u007f\u000f[+\""
		// @CA: invokestatic game.C_100343_jf.func_104819_z(java.lang.String)char[]
		// @CD: invokestatic game.C_100343_jf.func_104817_z(char[])java.lang.String
		// @D0: putstatic java.lang.String game.C_100343_jf.field_104827_j
		// @D3: return
	}
	
	private static char[] func_104819_z(String arg0)
	{
		// @00: aload_0
		// @01: invokevirtual java.lang.String.toCharArray()char[]
		// @04: dup
		// @05: arraylength
		// @06: iconst_2
		// @07: if_icmpge @13
		// @0A: dup
		// @0B: iconst_0
		// @0C: dup2
		// @0D: caload
		// @0E: bipush 87 (0x57)
		// @10: ixor
		// @11: i2c
		// @12: castore
		// @13: areturn
	}
	
	private static String func_104817_z(char[] arg0)
	{
		// @00: aload_0
		// @01: dup
		// @02: arraylength
		// @03: swap
		// @04: iconst_0
		// @05: istore_1
		// @06: goto @4C
		// @09: dup
		// @0A: iload_1
		// @0B: dup2
		// @0C: caload
		// @0D: iload_1
		// @0E: iconst_5
		// @0F: irem
		// @10: tableswitch def: @44, for 0: @30, for 1: @35, for 2: @3A, for 3: @3F
		// @30: bipush 95 (0x5F)
		// @32: goto @46
		// @35: bipush 66 (0x42)
		// @37: goto @46
		// @3A: bipush 62 (0x3E)
		// @3C: goto @46
		// @3F: bipush 69 (0x45)
		// @41: goto @46
		// @44: bipush 87 (0x57)
		// @46: ixor
		// @47: i2c
		// @48: castore
		// @49: iinc #1 +1
		// @4C: swap
		// @4D: dup_x1
		// @4E: iload_1
		// @4F: if_icmpgt @09
		// @52: new java.lang.String
		// @55: dup_x1
		// @56: swap
		// @57: invokespecial java.lang.String.<init>(char[])void
		// @5A: invokevirtual java.lang.String.intern()java.lang.String
		// @5D: areturn
	}
}
