package game;

final class C_100180_ce extends C_100303_kk
{
	static C_100037_wb field_104804_B;
	static C_100302_ka field_104814_y;
	static String field_104808_u;
	static String[] field_104812_q;
	static String field_104809_t;
	static int field_104811_r;
	static int field_104805_C;
	static String field_104815_x;
	static int field_104810_s;
	static String field_104803_A;
	static String field_104807_v;
	static int[] field_104806_w;
	static int field_104813_z;
	private static final String[] field_104802_D;
	
	C_100180_ce(long arg0, String arg1)
	{
		// @0: aload_0
		// @1: lload_1
		// @2: aload_3
		// @3: invokespecial game.C_100303_kk.<init>(long, java.lang.String)void
		// @6: return
	}
	
	final C_100013_fn func_104766_b(int arg0)
	{
		// @00: iload_1
		// @01: ifeq @0D
		// @04: bipush 6 (0x06)
		// @06: invokestatic game.C_100180_ce.func_104796_c(int)void
		// @09: goto @0D
		// @0C: athrow
		// @0D: getstatic game.C_100013_fn game.C_100043_vl.field_101944_bc
		// @10: areturn
		// @11: astore_2
		// @12: aload_2
		// @13: new java.lang.StringBuilder
		// @16: dup
		// @17: invokespecial java.lang.StringBuilder.<init>()void
		// @1A: getstatic java.lang.String[] game.C_100180_ce.field_104802_D
		// @1D: iconst_5
		// @1E: aaload
		// @1F: invokevirtual java.lang.StringBuilder.append(java.lang.String)java.lang.StringBuilder
		// @22: iload_1
		// @23: invokevirtual java.lang.StringBuilder.append(int)java.lang.StringBuilder
		// @26: bipush 41 (0x29)
		// @28: invokevirtual java.lang.StringBuilder.append(char)java.lang.StringBuilder
		// @2B: invokevirtual java.lang.StringBuilder.toString()java.lang.String
		// @2E: invokestatic game.C_100181_cf.func_105695_a(java.lang.Throwable, java.lang.String)game.C_100170_cm
		// @31: athrow
	}
	
	static final int func_104799_a(boolean arg0)
	{
		// @00: getstatic game.C_100208_qg game.C_100271_mj.field_103440_O
		// @03: bipush 8 (0x08)
		// @05: invokevirtual game.C_100208_qg.func_105948_a(int)void
		// @08: iload_0
		// @09: iconst_1
		// @0A: if_icmpeq @10
		// @0D: bipush 18 (0x12)
		// @0F: ireturn
		// @10: getstatic game.C_100104_v game.C_100311_le.field_104714_w
		// @13: bipush 106 (0x6A)
		// @15: invokevirtual game.C_100104_v.func_104676_a(byte)boolean
		// @18: ifne @20
		// @1B: iconst_1
		// @1C: invokestatic game.C_100210_qa.func_101027_h(int)int
		// @1F: ireturn
		// @20: iconst_0
		// @21: ireturn
		// @22: astore_1
		// @23: aload_1
		// @24: new java.lang.StringBuilder
		// @27: dup
		// @28: invokespecial java.lang.StringBuilder.<init>()void
		// @2B: getstatic java.lang.String[] game.C_100180_ce.field_104802_D
		// @2E: iconst_0
		// @2F: aaload
		// @30: invokevirtual java.lang.StringBuilder.append(java.lang.String)java.lang.StringBuilder
		// @33: iload_0
		// @34: invokevirtual java.lang.StringBuilder.append(boolean)java.lang.StringBuilder
		// @37: bipush 41 (0x29)
		// @39: invokevirtual java.lang.StringBuilder.append(char)java.lang.StringBuilder
		// @3C: invokevirtual java.lang.StringBuilder.toString()java.lang.String
		// @3F: invokestatic game.C_100181_cf.func_105695_a(java.lang.Throwable, java.lang.String)game.C_100170_cm
		// @42: athrow
	}
	
	public static void func_104796_c(int arg0)
	{
		// @00: aconst_null
		// @01: putstatic java.lang.String game.C_100180_ce.field_104807_v
		// @04: aconst_null
		// @05: putstatic int[] game.C_100180_ce.field_104806_w
		// @08: aconst_null
		// @09: putstatic java.lang.String game.C_100180_ce.field_104809_t
		// @0C: aconst_null
		// @0D: putstatic java.lang.String game.C_100180_ce.field_104803_A
		// @10: iload_0
		// @11: iconst_5
		// @12: if_icmpeq @16
		// @15: return
		// @16: aconst_null
		// @17: putstatic java.lang.String game.C_100180_ce.field_104815_x
		// @1A: aconst_null
		// @1B: putstatic java.lang.String game.C_100180_ce.field_104808_u
		// @1E: aconst_null
		// @1F: putstatic game.C_100302_ka game.C_100180_ce.field_104814_y
		// @22: aconst_null
		// @23: putstatic java.lang.String[] game.C_100180_ce.field_104812_q
		// @26: aconst_null
		// @27: putstatic game.C_100037_wb game.C_100180_ce.field_104804_B
		// @2A: goto @4F
		// @2D: astore_1
		// @2E: aload_1
		// @2F: new java.lang.StringBuilder
		// @32: dup
		// @33: invokespecial java.lang.StringBuilder.<init>()void
		// @36: getstatic java.lang.String[] game.C_100180_ce.field_104802_D
		// @39: bipush 7 (0x07)
		// @3B: aaload
		// @3C: invokevirtual java.lang.StringBuilder.append(java.lang.String)java.lang.StringBuilder
		// @3F: iload_0
		// @40: invokevirtual java.lang.StringBuilder.append(int)java.lang.StringBuilder
		// @43: bipush 41 (0x29)
		// @45: invokevirtual java.lang.StringBuilder.append(char)java.lang.StringBuilder
		// @48: invokevirtual java.lang.StringBuilder.toString()java.lang.String
		// @4B: invokestatic game.C_100181_cf.func_105695_a(java.lang.Throwable, java.lang.String)game.C_100170_cm
		// @4E: athrow
		// @4F: return
	}
	
	static final C_100179_ch func_104800_a(int arg0, C_100214_al arg1, int arg2)
	{
		// @00: iload_2
		// @01: ifeq @0E
		// @04: bipush 46 (0x2E)
		// @06: invokestatic game.C_100180_ce.func_104801_c(byte)java.lang.String
		// @09: pop
		// @0A: goto @0E
		// @0D: athrow
		// @0E: aload_1
		// @0F: bipush 100 (0x64)
		// @11: iload_0
		// @12: invokestatic game.C_100117_p.func_100959_a(game.C_100214_al, int, int)game.C_100117_p
		// @15: bipush 103 (0x67)
		// @17: invokestatic game.C_100130_tf.func_104952_a(game.C_100117_p, byte)game.C_100179_ch
		// @1A: areturn
		// @1B: astore_3
		// @1C: aload_3
		// @1D: new java.lang.StringBuilder
		// @20: dup
		// @21: invokespecial java.lang.StringBuilder.<init>()void
		// @24: getstatic java.lang.String[] game.C_100180_ce.field_104802_D
		// @27: iconst_4
		// @28: aaload
		// @29: invokevirtual java.lang.StringBuilder.append(java.lang.String)java.lang.StringBuilder
		// @2C: iload_0
		// @2D: invokevirtual java.lang.StringBuilder.append(int)java.lang.StringBuilder
		// @30: bipush 44 (0x2C)
		// @32: invokevirtual java.lang.StringBuilder.append(char)java.lang.StringBuilder
		// @35: aload_1
		// @36: ifnull @42
		// @39: getstatic java.lang.String[] game.C_100180_ce.field_104802_D
		// @3C: iconst_2
		// @3D: aaload
		// @3E: goto @47
		// @41: athrow
		// @42: getstatic java.lang.String[] game.C_100180_ce.field_104802_D
		// @45: iconst_3
		// @46: aaload
		// @47: invokevirtual java.lang.StringBuilder.append(java.lang.String)java.lang.StringBuilder
		// @4A: bipush 44 (0x2C)
		// @4C: invokevirtual java.lang.StringBuilder.append(char)java.lang.StringBuilder
		// @4F: iload_2
		// @50: invokevirtual java.lang.StringBuilder.append(int)java.lang.StringBuilder
		// @53: bipush 41 (0x29)
		// @55: invokevirtual java.lang.StringBuilder.append(char)java.lang.StringBuilder
		// @58: invokevirtual java.lang.StringBuilder.toString()java.lang.String
		// @5B: invokestatic game.C_100181_cf.func_105695_a(java.lang.Throwable, java.lang.String)game.C_100170_cm
		// @5E: athrow
	}
	
	static final int func_104795_a(int arg0, C_100240_oj arg1)
	{
		// @00: getstatic int game.SteelSentinels.field_105275_O
		// @03: istore #4
		// @05: getstatic int game.C_100273_mm.field_106679_f
		// @08: istore_2
		// @09: bipush -3 (0xFD)
		// @0B: aload_1
		// @0C: getfield int game.C_100240_oj.field_106317_a
		// @0F: iconst_m1
		// @10: ixor
		// @11: if_icmpne @60
		// @14: aload_1
		// @15: getfield boolean game.C_100240_oj.field_106311_f
		// @18: ifeq @28
		// @1B: goto @1F
		// @1E: athrow
		// @1F: getstatic int game.C_100273_mm.field_106679_f
		// @22: istore_2
		// @23: iload #4
		// @25: ifeq @A0
		// @28: iconst_m1
		// @29: aload_1
		// @2A: getfield int game.C_100240_oj.field_106312_g
		// @2D: iconst_m1
		// @2E: ixor
		// @2F: if_icmpne @44
		// @32: goto @36
		// @35: athrow
		// @36: aload_1
		// @37: getfield int game.C_100240_oj.field_106323_k
		// @3A: iconst_m1
		// @3B: ixor
		// @3C: iconst_m1
		// @3D: if_icmpeq @52
		// @40: goto @44
		// @43: athrow
		// @44: getstatic int[] game.C_100140_bj.field_102968_c
		// @47: aload_1
		// @48: getfield int game.C_100240_oj.field_106317_a
		// @4B: iaload
		// @4C: istore_2
		// @4D: iload #4
		// @4F: ifeq @A0
		// @52: getstatic int[] game.C_100269_ml.field_101123_n
		// @55: aload_1
		// @56: getfield int game.C_100240_oj.field_106317_a
		// @59: iaload
		// @5A: istore_2
		// @5B: iload #4
		// @5D: ifeq @A0
		// @60: aload_1
		// @61: getfield int game.C_100240_oj.field_106317_a
		// @64: iconst_4
		// @65: if_icmpeq @97
		// @68: goto @6C
		// @6B: athrow
		// @6C: getstatic long game.C_100321_hi.field_107215_f
		// @6F: aload_1
		// @70: getfield long game.C_100240_oj.field_106316_c
		// @73: lcmp
		// @74: ifeq @89
		// @77: goto @7B
		// @7A: athrow
		// @7B: getstatic int[] game.C_100140_bj.field_102968_c
		// @7E: aload_1
		// @7F: getfield int game.C_100240_oj.field_106317_a
		// @82: iaload
		// @83: istore_2
		// @84: iload #4
		// @86: ifeq @A0
		// @89: getstatic int[] game.C_100269_ml.field_101123_n
		// @8C: aload_1
		// @8D: getfield int game.C_100240_oj.field_106317_a
		// @90: iaload
		// @91: istore_2
		// @92: iload #4
		// @94: ifeq @A0
		// @97: getstatic int[] game.C_100140_bj.field_102968_c
		// @9A: aload_1
		// @9B: getfield int game.C_100240_oj.field_106317_a
		// @9E: iaload
		// @9F: istore_2
		// @A0: bipush -79 (0xB1)
		// @A2: bipush 56 (0x38)
		// @A4: iload_0
		// @A5: isub
		// @A6: bipush 55 (0x37)
		// @A8: idiv
		// @A9: irem
		// @AA: istore_3
		// @AB: iload_2
		// @AC: ireturn
		// @AD: astore_2
		// @AE: aload_2
		// @AF: new java.lang.StringBuilder
		// @B2: dup
		// @B3: invokespecial java.lang.StringBuilder.<init>()void
		// @B6: getstatic java.lang.String[] game.C_100180_ce.field_104802_D
		// @B9: iconst_1
		// @BA: aaload
		// @BB: invokevirtual java.lang.StringBuilder.append(java.lang.String)java.lang.StringBuilder
		// @BE: iload_0
		// @BF: invokevirtual java.lang.StringBuilder.append(int)java.lang.StringBuilder
		// @C2: bipush 44 (0x2C)
		// @C4: invokevirtual java.lang.StringBuilder.append(char)java.lang.StringBuilder
		// @C7: aload_1
		// @C8: ifnull @D4
		// @CB: getstatic java.lang.String[] game.C_100180_ce.field_104802_D
		// @CE: iconst_2
		// @CF: aaload
		// @D0: goto @D9
		// @D3: athrow
		// @D4: getstatic java.lang.String[] game.C_100180_ce.field_104802_D
		// @D7: iconst_3
		// @D8: aaload
		// @D9: invokevirtual java.lang.StringBuilder.append(java.lang.String)java.lang.StringBuilder
		// @DC: bipush 41 (0x29)
		// @DE: invokevirtual java.lang.StringBuilder.append(char)java.lang.StringBuilder
		// @E1: invokevirtual java.lang.StringBuilder.toString()java.lang.String
		// @E4: invokestatic game.C_100181_cf.func_105695_a(java.lang.Throwable, java.lang.String)game.C_100170_cm
		// @E7: athrow
	}
	
	static final String func_104801_c(byte arg0)
	{
		// @00: iload_0
		// @01: bipush -95 (0xA1)
		// @03: if_icmpeq @14
		// @06: bipush -8 (0xF8)
		// @08: aconst_null
		// @09: checkcast game.C_100240_oj
		// @0C: invokestatic game.C_100180_ce.func_104795_a(int, game.C_100240_oj)int
		// @0F: pop
		// @10: goto @14
		// @13: athrow
		// @14: ldc ""
		// @16: astore_1
		// @17: aconst_null
		// @18: getstatic game.C_100151_bc game.C_100099_fb.field_103039_E
		// @1B: if_acmpeq @27
		// @1E: getstatic game.C_100151_bc game.C_100099_fb.field_103039_E
		// @21: bipush -69 (0xBB)
		// @23: invokevirtual game.C_100151_bc.func_102926_g(byte)java.lang.String
		// @26: astore_1
		// @27: aload_1
		// @28: invokevirtual java.lang.String.length()int
		// @2B: ifne @37
		// @2E: iload_0
		// @2F: sipush -463 (0xFE31)
		// @32: ixor
		// @33: invokestatic game.C_100012_fh.func_100497_f(int)java.lang.String
		// @36: astore_1
		// @37: aload_1
		// @38: invokevirtual java.lang.String.length()int
		// @3B: ifeq @42
		// @3E: goto @46
		// @41: athrow
		// @42: getstatic java.lang.String game.C_100043_vl.field_101940_ac
		// @45: astore_1
		// @46: aload_1
		// @47: areturn
		// @48: astore_1
		// @49: aload_1
		// @4A: new java.lang.StringBuilder
		// @4D: dup
		// @4E: invokespecial java.lang.StringBuilder.<init>()void
		// @51: getstatic java.lang.String[] game.C_100180_ce.field_104802_D
		// @54: bipush 6 (0x06)
		// @56: aaload
		// @57: invokevirtual java.lang.StringBuilder.append(java.lang.String)java.lang.StringBuilder
		// @5A: iload_0
		// @5B: invokevirtual java.lang.StringBuilder.append(int)java.lang.StringBuilder
		// @5E: bipush 41 (0x29)
		// @60: invokevirtual java.lang.StringBuilder.append(char)java.lang.StringBuilder
		// @63: invokevirtual java.lang.StringBuilder.toString()java.lang.String
		// @66: invokestatic game.C_100181_cf.func_105695_a(java.lang.Throwable, java.lang.String)game.C_100170_cm
		// @69: athrow
	}
	
	static
	{
		// @000: bipush 8 (0x08)
		// @002: anewarray java.lang.String
		// @005: dup
		// @006: iconst_0
		// @007: ldc "9$|\u007fF"
		// @009: invokestatic game.C_100180_ce.func_104798_z(java.lang.String)char[]
		// @00C: invokestatic game.C_100180_ce.func_104797_z(char[])java.lang.String
		// @00F: aastore
		// @010: dup
		// @011: iconst_1
		// @012: ldc "9$|`F"
		// @014: invokestatic game.C_100180_ce.func_104798_z(java.lang.String)char[]
		// @017: invokestatic game.C_100180_ce.func_104797_z(char[])java.lang.String
		// @01A: aastore
		// @01B: dup
		// @01C: iconst_2
		// @01D: ldc "!o|\u0000\u0013"
		// @01F: invokestatic game.C_100180_ce.func_104798_z(java.lang.String)char[]
		// @022: invokestatic game.C_100180_ce.func_104797_z(char[])java.lang.String
		// @025: aastore
		// @026: dup
		// @027: iconst_3
		// @028: ldc "44>B"
		// @02A: invokestatic game.C_100180_ce.func_104798_z(java.lang.String)char[]
		// @02D: invokestatic game.C_100180_ce.func_104797_z(char[])java.lang.String
		// @030: aastore
		// @031: dup
		// @032: iconst_4
		// @033: ldc "9$|~F"
		// @035: invokestatic game.C_100180_ce.func_104798_z(java.lang.String)char[]
		// @038: invokestatic game.C_100180_ce.func_104797_z(char[])java.lang.String
		// @03B: aastore
		// @03C: dup
		// @03D: iconst_5
		// @03E: ldc "9$|iF"
		// @040: invokestatic game.C_100180_ce.func_104798_z(java.lang.String)char[]
		// @043: invokestatic game.C_100180_ce.func_104797_z(char[])java.lang.String
		// @046: aastore
		// @047: dup
		// @048: bipush 6 (0x06)
		// @04A: ldc "9$||F"
		// @04C: invokestatic game.C_100180_ce.func_104798_z(java.lang.String)char[]
		// @04F: invokestatic game.C_100180_ce.func_104797_z(char[])java.lang.String
		// @052: aastore
		// @053: dup
		// @054: bipush 7 (0x07)
		// @056: ldc "9$|aF"
		// @058: invokestatic game.C_100180_ce.func_104798_z(java.lang.String)char[]
		// @05B: invokestatic game.C_100180_ce.func_104797_z(char[])java.lang.String
		// @05E: aastore
		// @05F: putstatic java.lang.String[] game.C_100180_ce.field_104802_D
		// @062: ldc "\u001b->\u000e\u001e6 +K\u001c)a:O\u0018?a>K\u0008.an\u000b^df!\u000e\t;,7\u0000"
		// @064: invokestatic game.C_100180_ce.func_104798_z(java.lang.String)char[]
		// @067: invokestatic game.C_100180_ce.func_104797_z(char[])java.lang.String
		// @06A: putstatic java.lang.String game.C_100180_ce.field_104803_A
		// @06D: iconst_0
		// @06E: putstatic int game.C_100180_ce.field_104805_C
		// @071: bipush 12 (0x0C)
		// @073: anewarray java.lang.String
		// @076: dup
		// @077: iconst_0
		// @078: ldc "f\"=BS<'b\u001e^j\u007f\u0006F\u0007)a!K\u0000.(<K\u0002z)3]N4.rY\u000b;1=@\u001dt}}M\u00016\u007f"
		// @07A: invokestatic game.C_100180_ce.func_104798_z(java.lang.String)char[]
		// @07D: invokestatic game.C_100180_ce.func_104797_z(char[])java.lang.String
		// @080: aastore
		// @081: dup
		// @082: iconst_1
		// @083: ldc "\u0012 $G\u0000=a?[\u0002.(\"B\u000bz}w\u001ePz,=J\u001b6$!\u000e\u0007)a K\n//6O\u0000.o"
		// @085: invokestatic game.C_100180_ce.func_104798_z(java.lang.String)char[]
		// @088: invokestatic game.C_100180_ce.func_104797_z(char[])java.lang.String
		// @08B: aastore
		// @08C: dup
		// @08D: iconst_2
		// @08E: ldc "\u000e)7\u000e\u000b4$ I\u0007)$6\u000e\u000f(,=[\u001cz.<B\u0017z6=\\\u0005)a;@N9.?L\u00074 &G\u00014a%G\u001a2a7@\u000b(&+\u000e\u001d2(7B\n)o"
		// @090: invokestatic game.C_100180_ce.func_104798_z(java.lang.String)char[]
		// @093: invokestatic game.C_100180_ce.func_104797_z(char[])java.lang.String
		// @096: aastore
		// @097: dup
		// @098: iconst_3
		// @099: ldc "\u000e)7\u000e\t( $G\u001a#a\"A\n)a3\\\u000bz.4\u000e\u00005a']\u000bz.<\u000e\u000fz27@\u001a3/7BN.)3ZN9 <@\u0001.a8[\u0003*o"
		// @09B: invokestatic game.C_100180_ce.func_104798_z(java.lang.String)char[]
		// @09E: invokestatic game.C_100180_ce.func_104797_z(char[])java.lang.String
		// @0A1: aastore
		// @0A2: dup
		// @0A3: iconst_4
		// @0A4: ldc "\u000e)7\u000e\u000f33r]\u001a;#;B\u0007)$ ]N;37\u000e\u0001<a<AN/27\u000e\u00014a3\u000e\u001d?/&G\u0000?-rZ\u0006;5rM\u000f4/=ZN.) [\u001d.o"
		// @0A6: invokestatic game.C_100180_ce.func_104798_z(java.lang.String)char[]
		// @0A9: invokestatic game.C_100180_ce.func_104797_z(char[])java.lang.String
		// @0AC: aastore
		// @0AD: dup
		// @0AE: iconst_5
		// @0AF: ldc "\u000e);]N)$<Z\u00074$>\u000e\u0006;2r@\u0001z67O\u001e5/!\u000e\r5,\"O\u001a3#>KN-(&FN\u001b\u000c\u0013|*\to"
		// @0B1: invokestatic game.C_100180_ce.func_104798_z(java.lang.String)char[]
		// @0B4: invokestatic game.C_100180_ce.func_104797_z(char[])java.lang.String
		// @0B7: aastore
		// @0B8: dup
		// @0B9: bipush 6 (0x06)
		// @0BB: ldc "\u000e);]N)$<Z\u00074$>\u000e\u0006;2r@\u0001z67O\u001e5/!\u000e\r5,\"O\u001a3#>KN-(&FN35!\u000e\u001a;35K\u001a3/5\u000e\u001d#2&K\u0003t"
		// @0BD: invokestatic game.C_100180_ce.func_104798_z(java.lang.String)char[]
		// @0C0: invokestatic game.C_100180_ce.func_104797_z(char[])java.lang.String
		// @0C3: aastore
		// @0C4: dup
		// @0C5: bipush 7 (0x07)
		// @0C7: ldc "\u000e)7\u000e\u001d*$7JC6.3J\u000b(a=@\u0002#a%A\u001c12rY\u0007.)r\\\u00019*7Z\u001dz. \u000e\u000332!G\u0002?2|"
		// @0C9: invokestatic game.C_100180_ce.func_104798_z(java.lang.String)char[]
		// @0CC: invokestatic game.C_100180_ce.func_104797_z(char[])java.lang.String
		// @0CF: aastore
		// @0D0: dup
		// @0D1: bipush 8 (0x08)
		// @0D3: ldc "\u000e)7\u000e\r5.>O\u0000.a3\\\u001c;8rA\u000068rY\u0001(*!\u000e\u001935:\u000e\u001e6 !C\u000fz67O\u001e5/!\u0000"
		// @0D5: invokestatic game.C_100180_ce.func_104798_z(java.lang.String)char[]
		// @0D8: invokestatic game.C_100180_ce.func_104797_z(char[])java.lang.String
		// @0DB: aastore
		// @0DC: dup
		// @0DD: bipush 9 (0x09)
		// @0DF: ldc "\u000e)7\u000e\u00063&:\u0003\u000b4$ I\u0017z ?^\u00023';K\u001cz.<B\u0017z6=\\\u0005)a%G\u001a2a>O\u001d?3rY\u000b;1=@\u001dt"
		// @0E1: invokestatic game.C_100180_ce.func_104798_z(java.lang.String)char[]
		// @0E4: invokestatic game.C_100180_ce.func_104797_z(char[])java.lang.String
		// @0E7: aastore
		// @0E8: dup
		// @0E9: bipush 10 (0x0A)
		// @0EB: ldc "\u000e)7\u000e\u000b7$ I\u000b4\"+\u000e\n32\"B\u000f9$?K\u0000.a6K\u001e6.+C\u000b45r\\\u000b+4;\\\u000b)ag\u0012\u000082\"\u0010:\u0010a=HN?/7\\\t#a1O\u001e;\";Z\u0017t"
		// @0ED: invokestatic game.C_100180_ce.func_104798_z(java.lang.String)char[]
		// @0F0: invokestatic game.C_100180_ce.func_104797_z(char[])java.lang.String
		// @0F3: aastore
		// @0F4: dup
		// @0F5: bipush 11 (0x0B)
		// @0F7: ldc "\u000e)7\u000e\u0008/2;A\u0000z#>O\n?a1B\u0001)$\u007fM\u00017#3ZN;5&O\r1a K\u001f/( K\u001dzpb\u0012\u000082\"\u0010:\u0010a=HN?/7\\\t#a1O\u001e;\";Z\u0017t"
		// @0F9: invokestatic game.C_100180_ce.func_104798_z(java.lang.String)char[]
		// @0FC: invokestatic game.C_100180_ce.func_104797_z(char[])java.lang.String
		// @0FF: aastore
		// @100: putstatic java.lang.String[] game.C_100180_ce.field_104812_q
		// @103: ldc "\u0008$\"A\u001c.an\u000b^da4A\u001cz 0[\u001d?"
		// @105: invokestatic game.C_100180_ce.func_104798_z(java.lang.String)char[]
		// @108: invokestatic game.C_100180_ce.func_104797_z(char[])java.lang.String
		// @10B: putstatic java.lang.String game.C_100180_ce.field_104815_x
		// @10E: ldc "\u0019-=]\u000b"
		// @110: invokestatic game.C_100180_ce.func_104798_z(java.lang.String)char[]
		// @113: invokestatic game.C_100180_ce.func_104797_z(char[])java.lang.String
		// @116: putstatic java.lang.String game.C_100180_ce.field_104807_v
		// @119: ldc "\u0003.'\u000e\r;/<A\u001az\":O\u001az5=\u000eR\u007fql\u000e\u000c?\"3[\u001d?an\u000b^da;]N4.&\u000e\u00074a+A\u001b(a4\\\u0007?/6\u000e\u000232&\u0000"
		// @11B: invokestatic game.C_100180_ce.func_104798_z(java.lang.String)char[]
		// @11E: invokestatic game.C_100180_ce.func_104797_z(char[])java.lang.String
		// @121: putstatic java.lang.String game.C_100180_ce.field_104809_t
		// @124: bipush 8 (0x08)
		// @126: newarray int[]
		// @128: dup
		// @129: iconst_0
		// @12A: iconst_2
		// @12B: iastore
		// @12C: dup
		// @12D: iconst_1
		// @12E: bipush 20 (0x14)
		// @130: iastore
		// @131: dup
		// @132: iconst_2
		// @133: bipush 21 (0x15)
		// @135: iastore
		// @136: dup
		// @137: iconst_3
		// @138: bipush 6 (0x06)
		// @13A: iastore
		// @13B: dup
		// @13C: iconst_4
		// @13D: bipush 37 (0x25)
		// @13F: iastore
		// @140: dup
		// @141: iconst_5
		// @142: bipush 45 (0x2D)
		// @144: iastore
		// @145: dup
		// @146: bipush 6 (0x06)
		// @148: iconst_5
		// @149: iastore
		// @14A: dup
		// @14B: bipush 7 (0x07)
		// @14D: bipush 9 (0x09)
		// @14F: iastore
		// @150: putstatic int[] game.C_100180_ce.field_104806_w
		// @153: ldc "\u0016.3J\u00074&r\u0012Kj\u007fw"
		// @155: invokestatic game.C_100180_ce.func_104798_z(java.lang.String)char[]
		// @158: invokestatic game.C_100180_ce.func_104797_z(char[])java.lang.String
		// @15B: putstatic java.lang.String game.C_100180_ce.field_104808_u
		// @15E: return
	}
	
	private static char[] func_104798_z(String arg0)
	{
		// @00: aload_0
		// @01: invokevirtual java.lang.String.toCharArray()char[]
		// @04: dup
		// @05: arraylength
		// @06: iconst_2
		// @07: if_icmpge @13
		// @0A: dup
		// @0B: iconst_0
		// @0C: dup2
		// @0D: caload
		// @0E: bipush 110 (0x6E)
		// @10: ixor
		// @11: i2c
		// @12: castore
		// @13: areturn
	}
	
	private static String func_104797_z(char[] arg0)
	{
		// @00: aload_0
		// @01: dup
		// @02: arraylength
		// @03: swap
		// @04: iconst_0
		// @05: istore_1
		// @06: goto @4C
		// @09: dup
		// @0A: iload_1
		// @0B: dup2
		// @0C: caload
		// @0D: iload_1
		// @0E: iconst_5
		// @0F: irem
		// @10: tableswitch def: @44, for 0: @30, for 1: @35, for 2: @3A, for 3: @3F
		// @30: bipush 90 (0x5A)
		// @32: goto @46
		// @35: bipush 65 (0x41)
		// @37: goto @46
		// @3A: bipush 82 (0x52)
		// @3C: goto @46
		// @3F: bipush 46 (0x2E)
		// @41: goto @46
		// @44: bipush 110 (0x6E)
		// @46: ixor
		// @47: i2c
		// @48: castore
		// @49: iinc #1 +1
		// @4C: swap
		// @4D: dup_x1
		// @4E: iload_1
		// @4F: if_icmpgt @09
		// @52: new java.lang.String
		// @55: dup_x1
		// @56: swap
		// @57: invokespecial java.lang.String.<init>(char[])void
		// @5A: invokevirtual java.lang.String.intern()java.lang.String
		// @5D: areturn
	}
}
