package game;

import java.util.Hashtable;

abstract class C_100030_gm extends C_100336_im implements C_100259_ll
{
	static int field_103344_G;
	static C_100037_wb field_103342_E;
	static String field_103350_I;
	C_100336_im field_103351_J;
	static C_100193_re field_103343_F;
	static String[][] field_103347_N;
	static String field_103352_K;
	static String field_103346_M;
	static String field_103345_L;
	static C_100317_lb field_103349_H;
	static C_100302_ka field_103341_D;
	private static final String[] field_103348_O;
	
	private final boolean func_103331_a(C_100336_im arg0, byte arg1)
	{
		// @00: iload_2
		// @01: bipush 10 (0x0A)
		// @03: if_icmpge @11
		// @06: aconst_null
		// @07: checkcast game.C_100302_ka
		// @0A: putstatic game.C_100302_ka game.C_100030_gm.field_103341_D
		// @0D: goto @11
		// @10: athrow
		// @11: aload_0
		// @12: getfield game.C_100336_im game.C_100030_gm.field_103351_J
		// @15: ifnull @3D
		// @18: aload_0
		// @19: getfield game.C_100336_im game.C_100030_gm.field_103351_J
		// @1C: bipush 67 (0x43)
		// @1E: invokevirtual game.C_100336_im.func_102515_d(byte)boolean
		// @21: ifne @3D
		// @24: goto @28
		// @27: athrow
		// @28: aload_0
		// @29: getfield game.C_100336_im game.C_100030_gm.field_103351_J
		// @2C: iconst_1
		// @2D: aload_1
		// @2E: invokevirtual game.C_100336_im.func_102522_a(int, game.C_100336_im)boolean
		// @31: ifeq @3D
		// @34: goto @38
		// @37: athrow
		// @38: iconst_1
		// @39: goto @3E
		// @3C: athrow
		// @3D: iconst_0
		// @3E: ireturn
		// @3F: astore_3
		// @40: aload_3
		// @41: new java.lang.StringBuilder
		// @44: dup
		// @45: invokespecial java.lang.StringBuilder.<init>()void
		// @48: getstatic java.lang.String[] game.C_100030_gm.field_103348_O
		// @4B: bipush 8 (0x08)
		// @4D: aaload
		// @4E: invokevirtual java.lang.StringBuilder.append(java.lang.String)java.lang.StringBuilder
		// @51: aload_1
		// @52: ifnull @5E
		// @55: getstatic java.lang.String[] game.C_100030_gm.field_103348_O
		// @58: iconst_3
		// @59: aaload
		// @5A: goto @63
		// @5D: athrow
		// @5E: getstatic java.lang.String[] game.C_100030_gm.field_103348_O
		// @61: iconst_1
		// @62: aaload
		// @63: invokevirtual java.lang.StringBuilder.append(java.lang.String)java.lang.StringBuilder
		// @66: bipush 44 (0x2C)
		// @68: invokevirtual java.lang.StringBuilder.append(char)java.lang.StringBuilder
		// @6B: iload_2
		// @6C: invokevirtual java.lang.StringBuilder.append(int)java.lang.StringBuilder
		// @6F: bipush 41 (0x29)
		// @71: invokevirtual java.lang.StringBuilder.append(char)java.lang.StringBuilder
		// @74: invokevirtual java.lang.StringBuilder.toString()java.lang.String
		// @77: invokestatic game.C_100181_cf.func_105695_a(java.lang.Throwable, java.lang.String)game.C_100170_cm
		// @7A: athrow
	}
	
	void func_102528_a(int arg0, int arg1, int arg2, byte arg3)
	{
		// @00: iload #4
		// @02: bipush -126 (0x82)
		// @04: if_icmple @12
		// @07: aconst_null
		// @08: checkcast game.C_100037_wb
		// @0B: putstatic game.C_100037_wb game.C_100030_gm.field_103342_E
		// @0E: goto @12
		// @11: athrow
		// @12: iconst_0
		// @13: iload_1
		// @14: if_icmpne @37
		// @17: aconst_null
		// @18: aload_0
		// @19: getfield game.C_100326_ic game.C_100030_gm.field_102533_B
		// @1C: if_acmpeq @37
		// @1F: goto @23
		// @22: athrow
		// @23: aload_0
		// @24: getfield game.C_100326_ic game.C_100030_gm.field_102533_B
		// @27: iconst_1
		// @28: sipush -26568 (0x9838)
		// @2B: iload_3
		// @2C: iload_2
		// @2D: aload_0
		// @2E: invokeinterface game.C_100326_ic.func_100362_a(boolean, int, int, int, game.C_100336_im)void
		// @33: goto @37
		// @36: athrow
		// @37: aconst_null
		// @38: aload_0
		// @39: getfield game.C_100336_im game.C_100030_gm.field_103351_J
		// @3C: if_acmpeq @5A
		// @3F: aload_0
		// @40: getfield game.C_100336_im game.C_100030_gm.field_103351_J
		// @43: iload_1
		// @44: iload_2
		// @45: aload_0
		// @46: getfield int game.C_100030_gm.field_102541_w
		// @49: ineg
		// @4A: isub
		// @4B: aload_0
		// @4C: getfield int game.C_100030_gm.field_102538_m
		// @4F: iload_3
		// @50: iadd
		// @51: bipush -128 (0x80)
		// @53: invokevirtual game.C_100336_im.func_102528_a(int, int, int, byte)void
		// @56: goto @5A
		// @59: athrow
		// @5A: goto @9D
		// @5D: astore #5
		// @5F: aload #5
		// @61: new java.lang.StringBuilder
		// @64: dup
		// @65: invokespecial java.lang.StringBuilder.<init>()void
		// @68: getstatic java.lang.String[] game.C_100030_gm.field_103348_O
		// @6B: bipush 6 (0x06)
		// @6D: aaload
		// @6E: invokevirtual java.lang.StringBuilder.append(java.lang.String)java.lang.StringBuilder
		// @71: iload_1
		// @72: invokevirtual java.lang.StringBuilder.append(int)java.lang.StringBuilder
		// @75: bipush 44 (0x2C)
		// @77: invokevirtual java.lang.StringBuilder.append(char)java.lang.StringBuilder
		// @7A: iload_2
		// @7B: invokevirtual java.lang.StringBuilder.append(int)java.lang.StringBuilder
		// @7E: bipush 44 (0x2C)
		// @80: invokevirtual java.lang.StringBuilder.append(char)java.lang.StringBuilder
		// @83: iload_3
		// @84: invokevirtual java.lang.StringBuilder.append(int)java.lang.StringBuilder
		// @87: bipush 44 (0x2C)
		// @89: invokevirtual java.lang.StringBuilder.append(char)java.lang.StringBuilder
		// @8C: iload #4
		// @8E: invokevirtual java.lang.StringBuilder.append(int)java.lang.StringBuilder
		// @91: bipush 41 (0x29)
		// @93: invokevirtual java.lang.StringBuilder.append(char)java.lang.StringBuilder
		// @96: invokevirtual java.lang.StringBuilder.toString()java.lang.String
		// @99: invokestatic game.C_100181_cf.func_105695_a(java.lang.Throwable, java.lang.String)game.C_100170_cm
		// @9C: athrow
		// @9D: return
	}
	
	final boolean func_102512_b(int arg0, C_100336_im arg1, int arg2, int arg3, int arg4, int arg5, int arg6)
	{
		// @00: iload #4
		// @02: bipush -20 (0xEC)
		// @04: if_icmplt @09
		// @07: iconst_1
		// @08: ireturn
		// @09: aload_0
		// @0A: getfield game.C_100336_im game.C_100030_gm.field_103351_J
		// @0D: ifnull @3E
		// @10: aload_0
		// @11: getfield game.C_100336_im game.C_100030_gm.field_103351_J
		// @14: bipush 71 (0x47)
		// @16: invokevirtual game.C_100336_im.func_102515_d(byte)boolean
		// @19: ifeq @3E
		// @1C: goto @20
		// @1F: athrow
		// @20: aload_0
		// @21: getfield game.C_100336_im game.C_100030_gm.field_103351_J
		// @24: iload_1
		// @25: aload_2
		// @26: iload_3
		// @27: bipush -76 (0xB4)
		// @29: iload #5
		// @2B: iload #6
		// @2D: iload #7
		// @2F: invokevirtual game.C_100336_im.func_102512_b(int, game.C_100336_im, int, int, int, int, int)boolean
		// @32: ifeq @3E
		// @35: goto @39
		// @38: athrow
		// @39: iconst_1
		// @3A: goto @3F
		// @3D: athrow
		// @3E: iconst_0
		// @3F: ireturn
		// @40: astore #8
		// @42: aload #8
		// @44: new java.lang.StringBuilder
		// @47: dup
		// @48: invokespecial java.lang.StringBuilder.<init>()void
		// @4B: getstatic java.lang.String[] game.C_100030_gm.field_103348_O
		// @4E: bipush 15 (0x0F)
		// @50: aaload
		// @51: invokevirtual java.lang.StringBuilder.append(java.lang.String)java.lang.StringBuilder
		// @54: iload_1
		// @55: invokevirtual java.lang.StringBuilder.append(int)java.lang.StringBuilder
		// @58: bipush 44 (0x2C)
		// @5A: invokevirtual java.lang.StringBuilder.append(char)java.lang.StringBuilder
		// @5D: aload_2
		// @5E: ifnull @6A
		// @61: getstatic java.lang.String[] game.C_100030_gm.field_103348_O
		// @64: iconst_3
		// @65: aaload
		// @66: goto @6F
		// @69: athrow
		// @6A: getstatic java.lang.String[] game.C_100030_gm.field_103348_O
		// @6D: iconst_1
		// @6E: aaload
		// @6F: invokevirtual java.lang.StringBuilder.append(java.lang.String)java.lang.StringBuilder
		// @72: bipush 44 (0x2C)
		// @74: invokevirtual java.lang.StringBuilder.append(char)java.lang.StringBuilder
		// @77: iload_3
		// @78: invokevirtual java.lang.StringBuilder.append(int)java.lang.StringBuilder
		// @7B: bipush 44 (0x2C)
		// @7D: invokevirtual java.lang.StringBuilder.append(char)java.lang.StringBuilder
		// @80: iload #4
		// @82: invokevirtual java.lang.StringBuilder.append(int)java.lang.StringBuilder
		// @85: bipush 44 (0x2C)
		// @87: invokevirtual java.lang.StringBuilder.append(char)java.lang.StringBuilder
		// @8A: iload #5
		// @8C: invokevirtual java.lang.StringBuilder.append(int)java.lang.StringBuilder
		// @8F: bipush 44 (0x2C)
		// @91: invokevirtual java.lang.StringBuilder.append(char)java.lang.StringBuilder
		// @94: iload #6
		// @96: invokevirtual java.lang.StringBuilder.append(int)java.lang.StringBuilder
		// @99: bipush 44 (0x2C)
		// @9B: invokevirtual java.lang.StringBuilder.append(char)java.lang.StringBuilder
		// @9E: iload #7
		// @A0: invokevirtual java.lang.StringBuilder.append(int)java.lang.StringBuilder
		// @A3: bipush 41 (0x29)
		// @A5: invokevirtual java.lang.StringBuilder.append(char)java.lang.StringBuilder
		// @A8: invokevirtual java.lang.StringBuilder.toString()java.lang.String
		// @AB: invokestatic game.C_100181_cf.func_105695_a(java.lang.Throwable, java.lang.String)game.C_100170_cm
		// @AE: athrow
	}
	
	final void func_102526_b(boolean arg0)
	{
		// @00: aload_0
		// @01: getfield game.C_100336_im game.C_100030_gm.field_103351_J
		// @04: ifnonnull @0B
		// @07: goto @13
		// @0A: athrow
		// @0B: aload_0
		// @0C: getfield game.C_100336_im game.C_100030_gm.field_103351_J
		// @0F: iconst_0
		// @10: invokevirtual game.C_100336_im.func_102526_b(boolean)void
		// @13: iload_1
		// @14: ifeq @20
		// @17: bipush 120 (0x78)
		// @19: invokestatic game.C_100030_gm.func_103338_i(int)void
		// @1C: goto @20
		// @1F: athrow
		// @20: goto @45
		// @23: astore_2
		// @24: aload_2
		// @25: new java.lang.StringBuilder
		// @28: dup
		// @29: invokespecial java.lang.StringBuilder.<init>()void
		// @2C: getstatic java.lang.String[] game.C_100030_gm.field_103348_O
		// @2F: bipush 21 (0x15)
		// @31: aaload
		// @32: invokevirtual java.lang.StringBuilder.append(java.lang.String)java.lang.StringBuilder
		// @35: iload_1
		// @36: invokevirtual java.lang.StringBuilder.append(boolean)java.lang.StringBuilder
		// @39: bipush 41 (0x29)
		// @3B: invokevirtual java.lang.StringBuilder.append(char)java.lang.StringBuilder
		// @3E: invokevirtual java.lang.StringBuilder.toString()java.lang.String
		// @41: invokestatic game.C_100181_cf.func_105695_a(java.lang.Throwable, java.lang.String)game.C_100170_cm
		// @44: athrow
		// @45: return
	}
	
	final int func_102527_g(int arg0)
	{
		// @00: iload_1
		// @01: sipush -21742 (0xAB12)
		// @04: if_icmpeq @0A
		// @07: bipush -97 (0x9F)
		// @09: ireturn
		// @0A: aload_0
		// @0B: getfield game.C_100336_im game.C_100030_gm.field_103351_J
		// @0E: ifnull @1F
		// @11: aload_0
		// @12: getfield game.C_100336_im game.C_100030_gm.field_103351_J
		// @15: iload_1
		// @16: iconst_0
		// @17: ixor
		// @18: invokevirtual game.C_100336_im.func_102527_g(int)int
		// @1B: goto @20
		// @1E: athrow
		// @1F: iconst_0
		// @20: ireturn
		// @21: astore_2
		// @22: aload_2
		// @23: new java.lang.StringBuilder
		// @26: dup
		// @27: invokespecial java.lang.StringBuilder.<init>()void
		// @2A: getstatic java.lang.String[] game.C_100030_gm.field_103348_O
		// @2D: bipush 7 (0x07)
		// @2F: aaload
		// @30: invokevirtual java.lang.StringBuilder.append(java.lang.String)java.lang.StringBuilder
		// @33: iload_1
		// @34: invokevirtual java.lang.StringBuilder.append(int)java.lang.StringBuilder
		// @37: bipush 41 (0x29)
		// @39: invokevirtual java.lang.StringBuilder.append(char)java.lang.StringBuilder
		// @3C: invokevirtual java.lang.StringBuilder.toString()java.lang.String
		// @3F: invokestatic game.C_100181_cf.func_105695_a(java.lang.Throwable, java.lang.String)game.C_100170_cm
		// @42: athrow
	}
	
	C_100336_im func_103339_j(int arg0)
	{
		// @00: iload_1
		// @01: sipush -22255 (0xA911)
		// @04: if_icmpeq @0C
		// @07: aconst_null
		// @08: checkcast game.C_100336_im
		// @0B: areturn
		// @0C: aload_0
		// @0D: getfield game.C_100336_im game.C_100030_gm.field_103351_J
		// @10: astore_2
		// @11: aconst_null
		// @12: aload_2
		// @13: if_acmpeq @25
		// @16: aload_2
		// @17: bipush 17 (0x11)
		// @19: invokevirtual game.C_100336_im.func_102515_d(byte)boolean
		// @1C: ifeq @25
		// @1F: goto @23
		// @22: athrow
		// @23: aload_2
		// @24: areturn
		// @25: aconst_null
		// @26: areturn
		// @27: astore_2
		// @28: aload_2
		// @29: new java.lang.StringBuilder
		// @2C: dup
		// @2D: invokespecial java.lang.StringBuilder.<init>()void
		// @30: getstatic java.lang.String[] game.C_100030_gm.field_103348_O
		// @33: iconst_0
		// @34: aaload
		// @35: invokevirtual java.lang.StringBuilder.append(java.lang.String)java.lang.StringBuilder
		// @38: iload_1
		// @39: invokevirtual java.lang.StringBuilder.append(int)java.lang.StringBuilder
		// @3C: bipush 41 (0x29)
		// @3E: invokevirtual java.lang.StringBuilder.append(char)java.lang.StringBuilder
		// @41: invokevirtual java.lang.StringBuilder.toString()java.lang.String
		// @44: invokestatic game.C_100181_cf.func_105695_a(java.lang.Throwable, java.lang.String)game.C_100170_cm
		// @47: athrow
	}
	
	void func_103340_h(int arg0)
	{
		// @00: aload_0
		// @01: getfield game.C_100336_im game.C_100030_gm.field_103351_J
		// @04: ifnonnull @0B
		// @07: goto @17
		// @0A: athrow
		// @0B: aload_0
		// @0C: getfield game.C_100336_im game.C_100030_gm.field_103351_J
		// @0F: iload_1
		// @10: sipush -16871 (0xBE19)
		// @13: iadd
		// @14: invokevirtual game.C_100336_im.func_102530_f(int)void
		// @17: iload_1
		// @18: sipush 27816 (0x6CA8)
		// @1B: if_icmpeq @2C
		// @1E: aconst_null
		// @1F: checkcast java.lang.String[][]
		// @22: checkcast java.lang.String[][]
		// @25: putstatic java.lang.String[][] game.C_100030_gm.field_103347_N
		// @28: goto @2C
		// @2B: athrow
		// @2C: goto @51
		// @2F: astore_2
		// @30: aload_2
		// @31: new java.lang.StringBuilder
		// @34: dup
		// @35: invokespecial java.lang.StringBuilder.<init>()void
		// @38: getstatic java.lang.String[] game.C_100030_gm.field_103348_O
		// @3B: bipush 14 (0x0E)
		// @3D: aaload
		// @3E: invokevirtual java.lang.StringBuilder.append(java.lang.String)java.lang.StringBuilder
		// @41: iload_1
		// @42: invokevirtual java.lang.StringBuilder.append(int)java.lang.StringBuilder
		// @45: bipush 41 (0x29)
		// @47: invokevirtual java.lang.StringBuilder.append(char)java.lang.StringBuilder
		// @4A: invokevirtual java.lang.StringBuilder.toString()java.lang.String
		// @4D: invokestatic game.C_100181_cf.func_105695_a(java.lang.Throwable, java.lang.String)game.C_100170_cm
		// @50: athrow
		// @51: return
	}
	
	final boolean func_102515_d(byte arg0)
	{
		// @00: iload_1
		// @01: bipush 10 (0x0A)
		// @03: if_icmpge @08
		// @06: iconst_0
		// @07: ireturn
		// @08: aconst_null
		// @09: aload_0
		// @0A: sipush -22255 (0xA911)
		// @0D: invokevirtual game.C_100030_gm.func_103339_j(int)game.C_100336_im
		// @10: if_acmpeq @18
		// @13: iconst_1
		// @14: goto @19
		// @17: athrow
		// @18: iconst_0
		// @19: ireturn
		// @1A: astore_2
		// @1B: aload_2
		// @1C: new java.lang.StringBuilder
		// @1F: dup
		// @20: invokespecial java.lang.StringBuilder.<init>()void
		// @23: getstatic java.lang.String[] game.C_100030_gm.field_103348_O
		// @26: bipush 11 (0x0B)
		// @28: aaload
		// @29: invokevirtual java.lang.StringBuilder.append(java.lang.String)java.lang.StringBuilder
		// @2C: iload_1
		// @2D: invokevirtual java.lang.StringBuilder.append(int)java.lang.StringBuilder
		// @30: bipush 41 (0x29)
		// @32: invokevirtual java.lang.StringBuilder.append(char)java.lang.StringBuilder
		// @35: invokevirtual java.lang.StringBuilder.toString()java.lang.String
		// @38: invokestatic game.C_100181_cf.func_105695_a(java.lang.Throwable, java.lang.String)game.C_100170_cm
		// @3B: athrow
	}
	
	public static void func_103335_e(byte arg0)
	{
		// @00: aconst_null
		// @01: putstatic game.C_100037_wb game.C_100030_gm.field_103342_E
		// @04: aconst_null
		// @05: putstatic java.lang.String game.C_100030_gm.field_103346_M
		// @08: aconst_null
		// @09: putstatic game.C_100302_ka game.C_100030_gm.field_103341_D
		// @0C: iload_0
		// @0D: iflt @11
		// @10: return
		// @11: aconst_null
		// @12: putstatic java.lang.String game.C_100030_gm.field_103352_K
		// @15: aconst_null
		// @16: checkcast java.lang.String[][]
		// @19: putstatic java.lang.String[][] game.C_100030_gm.field_103347_N
		// @1C: aconst_null
		// @1D: putstatic game.C_100193_re game.C_100030_gm.field_103343_F
		// @20: aconst_null
		// @21: putstatic game.C_100317_lb game.C_100030_gm.field_103349_H
		// @24: aconst_null
		// @25: putstatic java.lang.String game.C_100030_gm.field_103350_I
		// @28: aconst_null
		// @29: putstatic java.lang.String game.C_100030_gm.field_103345_L
		// @2C: goto @50
		// @2F: astore_1
		// @30: aload_1
		// @31: new java.lang.StringBuilder
		// @34: dup
		// @35: invokespecial java.lang.StringBuilder.<init>()void
		// @38: getstatic java.lang.String[] game.C_100030_gm.field_103348_O
		// @3B: iconst_4
		// @3C: aaload
		// @3D: invokevirtual java.lang.StringBuilder.append(java.lang.String)java.lang.StringBuilder
		// @40: iload_0
		// @41: invokevirtual java.lang.StringBuilder.append(int)java.lang.StringBuilder
		// @44: bipush 41 (0x29)
		// @46: invokevirtual java.lang.StringBuilder.append(char)java.lang.StringBuilder
		// @49: invokevirtual java.lang.StringBuilder.toString()java.lang.String
		// @4C: invokestatic game.C_100181_cf.func_105695_a(java.lang.Throwable, java.lang.String)game.C_100170_cm
		// @4F: athrow
		// @50: return
	}
	
	static final void func_103334_a(int arg0, int arg1)
	{
		// @00: getstatic game.C_100117_p game.C_100146_bf.field_105124_e
		// @03: ifnonnull @0A
		// @06: goto @1C
		// @09: athrow
		// @0A: getstatic game.C_100117_p game.C_100146_bf.field_105124_e
		// @0D: bipush 36 (0x24)
		// @0F: invokestatic game.C_100019_wl.func_103829_a(game.C_100117_p, int)void
		// @12: bipush 109 (0x6D)
		// @14: getstatic int game.C_100346_ja.field_103498_y
		// @17: iconst_2
		// @18: imul
		// @19: invokestatic game.C_100266_me.func_106646_a(int, int)void
		// @1C: iload_1
		// @1D: iconst_2
		// @1E: if_icmpeq @22
		// @21: return
		// @22: iload_0
		// @23: iconst_m1
		// @24: if_icmpeq @5A
		// @27: getstatic game.C_100214_al[] game.C_100330_ig.field_107287_b
		// @2A: iload_0
		// @2B: aaload
		// @2C: ifnull @5A
		// @2F: goto @33
		// @32: athrow
		// @33: getstatic game.C_100214_al[] game.C_100330_ig.field_107287_b
		// @36: iload_0
		// @37: aaload
		// @38: bipush 100 (0x64)
		// @3A: getstatic int game.C_100346_ja.field_103498_y
		// @3D: invokestatic game.C_100117_p.func_100959_a(game.C_100214_al, int, int)game.C_100117_p
		// @40: putstatic game.C_100117_p game.C_100146_bf.field_105124_e
		// @43: bipush 111 (0x6F)
		// @45: getstatic int game.C_100346_ja.field_103498_y
		// @48: iconst_2
		// @49: idiv
		// @4A: invokestatic game.C_100266_me.func_106646_a(int, int)void
		// @4D: getstatic game.C_100117_p game.C_100146_bf.field_105124_e
		// @50: bipush -58 (0xC6)
		// @52: invokestatic game.C_100130_tf.func_104952_a(game.C_100117_p, byte)game.C_100179_ch
		// @55: pop
		// @56: goto @5A
		// @59: athrow
		// @5A: goto @88
		// @5D: astore_2
		// @5E: aload_2
		// @5F: new java.lang.StringBuilder
		// @62: dup
		// @63: invokespecial java.lang.StringBuilder.<init>()void
		// @66: getstatic java.lang.String[] game.C_100030_gm.field_103348_O
		// @69: bipush 10 (0x0A)
		// @6B: aaload
		// @6C: invokevirtual java.lang.StringBuilder.append(java.lang.String)java.lang.StringBuilder
		// @6F: iload_0
		// @70: invokevirtual java.lang.StringBuilder.append(int)java.lang.StringBuilder
		// @73: bipush 44 (0x2C)
		// @75: invokevirtual java.lang.StringBuilder.append(char)java.lang.StringBuilder
		// @78: iload_1
		// @79: invokevirtual java.lang.StringBuilder.append(int)java.lang.StringBuilder
		// @7C: bipush 41 (0x29)
		// @7E: invokevirtual java.lang.StringBuilder.append(char)java.lang.StringBuilder
		// @81: invokevirtual java.lang.StringBuilder.toString()java.lang.String
		// @84: invokestatic game.C_100181_cf.func_105695_a(java.lang.Throwable, java.lang.String)game.C_100170_cm
		// @87: athrow
		// @88: return
	}
	
	C_100030_gm(int arg0, int arg1, int arg2, int arg3, C_100326_ic arg4, C_100337_in arg5)
	{
		// @0: aload_0
		// @1: iload_1
		// @2: iload_2
		// @3: iload_3
		// @4: iload #4
		// @6: aload #5
		// @8: aload #6
		// @A: invokespecial game.C_100336_im.<init>(int, int, int, int, game.C_100326_ic, game.C_100337_in)void
		// @D: return
	}
	
	boolean func_102520_a(int arg0, C_100336_im arg1, int arg2, int arg3, int arg4, int arg5, int arg6)
	{
		// @00: bipush -45 (0xD3)
		// @02: iload_3
		// @03: bipush 32 (0x20)
		// @05: isub
		// @06: bipush 52 (0x34)
		// @08: idiv
		// @09: idiv
		// @0A: istore #8
		// @0C: aconst_null
		// @0D: aload_0
		// @0E: getfield game.C_100336_im game.C_100030_gm.field_103351_J
		// @11: if_acmpeq @3D
		// @14: aload_0
		// @15: getfield game.C_100336_im game.C_100030_gm.field_103351_J
		// @18: iload_1
		// @19: aload_2
		// @1A: bipush 86 (0x56)
		// @1C: iload #4
		// @1E: aload_0
		// @1F: getfield int game.C_100030_gm.field_102541_w
		// @22: iload #5
		// @24: iadd
		// @25: iload #6
		// @27: aload_0
		// @28: getfield int game.C_100030_gm.field_102538_m
		// @2B: iadd
		// @2C: iload #7
		// @2E: invokevirtual game.C_100336_im.func_102520_a(int, game.C_100336_im, int, int, int, int, int)boolean
		// @31: ifeq @3D
		// @34: goto @38
		// @37: athrow
		// @38: iconst_1
		// @39: goto @3E
		// @3C: athrow
		// @3D: iconst_0
		// @3E: ireturn
		// @3F: astore #8
		// @41: aload #8
		// @43: new java.lang.StringBuilder
		// @46: dup
		// @47: invokespecial java.lang.StringBuilder.<init>()void
		// @4A: getstatic java.lang.String[] game.C_100030_gm.field_103348_O
		// @4D: bipush 22 (0x16)
		// @4F: aaload
		// @50: invokevirtual java.lang.StringBuilder.append(java.lang.String)java.lang.StringBuilder
		// @53: iload_1
		// @54: invokevirtual java.lang.StringBuilder.append(int)java.lang.StringBuilder
		// @57: bipush 44 (0x2C)
		// @59: invokevirtual java.lang.StringBuilder.append(char)java.lang.StringBuilder
		// @5C: aload_2
		// @5D: ifnull @69
		// @60: getstatic java.lang.String[] game.C_100030_gm.field_103348_O
		// @63: iconst_3
		// @64: aaload
		// @65: goto @6E
		// @68: athrow
		// @69: getstatic java.lang.String[] game.C_100030_gm.field_103348_O
		// @6C: iconst_1
		// @6D: aaload
		// @6E: invokevirtual java.lang.StringBuilder.append(java.lang.String)java.lang.StringBuilder
		// @71: bipush 44 (0x2C)
		// @73: invokevirtual java.lang.StringBuilder.append(char)java.lang.StringBuilder
		// @76: iload_3
		// @77: invokevirtual java.lang.StringBuilder.append(int)java.lang.StringBuilder
		// @7A: bipush 44 (0x2C)
		// @7C: invokevirtual java.lang.StringBuilder.append(char)java.lang.StringBuilder
		// @7F: iload #4
		// @81: invokevirtual java.lang.StringBuilder.append(int)java.lang.StringBuilder
		// @84: bipush 44 (0x2C)
		// @86: invokevirtual java.lang.StringBuilder.append(char)java.lang.StringBuilder
		// @89: iload #5
		// @8B: invokevirtual java.lang.StringBuilder.append(int)java.lang.StringBuilder
		// @8E: bipush 44 (0x2C)
		// @90: invokevirtual java.lang.StringBuilder.append(char)java.lang.StringBuilder
		// @93: iload #6
		// @95: invokevirtual java.lang.StringBuilder.append(int)java.lang.StringBuilder
		// @98: bipush 44 (0x2C)
		// @9A: invokevirtual java.lang.StringBuilder.append(char)java.lang.StringBuilder
		// @9D: iload #7
		// @9F: invokevirtual java.lang.StringBuilder.append(int)java.lang.StringBuilder
		// @A2: bipush 41 (0x29)
		// @A4: invokevirtual java.lang.StringBuilder.append(char)java.lang.StringBuilder
		// @A7: invokevirtual java.lang.StringBuilder.toString()java.lang.String
		// @AA: invokestatic game.C_100181_cf.func_105695_a(java.lang.Throwable, java.lang.String)game.C_100170_cm
		// @AD: athrow
	}
	
	final boolean func_102522_a(int arg0, C_100336_im arg1)
	{
		// @00: iload_1
		// @01: iconst_1
		// @02: if_icmpeq @07
		// @05: iconst_0
		// @06: ireturn
		// @07: aconst_null
		// @08: aload_0
		// @09: getfield game.C_100336_im game.C_100030_gm.field_103351_J
		// @0C: if_acmpeq @26
		// @0F: aload_0
		// @10: getfield game.C_100336_im game.C_100030_gm.field_103351_J
		// @13: iload_1
		// @14: iconst_0
		// @15: ixor
		// @16: aload_2
		// @17: invokevirtual game.C_100336_im.func_102522_a(int, game.C_100336_im)boolean
		// @1A: ifeq @26
		// @1D: goto @21
		// @20: athrow
		// @21: iconst_1
		// @22: goto @27
		// @25: athrow
		// @26: iconst_0
		// @27: ireturn
		// @28: astore_3
		// @29: aload_3
		// @2A: new java.lang.StringBuilder
		// @2D: dup
		// @2E: invokespecial java.lang.StringBuilder.<init>()void
		// @31: getstatic java.lang.String[] game.C_100030_gm.field_103348_O
		// @34: bipush 13 (0x0D)
		// @36: aaload
		// @37: invokevirtual java.lang.StringBuilder.append(java.lang.String)java.lang.StringBuilder
		// @3A: iload_1
		// @3B: invokevirtual java.lang.StringBuilder.append(int)java.lang.StringBuilder
		// @3E: bipush 44 (0x2C)
		// @40: invokevirtual java.lang.StringBuilder.append(char)java.lang.StringBuilder
		// @43: aload_2
		// @44: ifnull @50
		// @47: getstatic java.lang.String[] game.C_100030_gm.field_103348_O
		// @4A: iconst_3
		// @4B: aaload
		// @4C: goto @55
		// @4F: athrow
		// @50: getstatic java.lang.String[] game.C_100030_gm.field_103348_O
		// @53: iconst_1
		// @54: aaload
		// @55: invokevirtual java.lang.StringBuilder.append(java.lang.String)java.lang.StringBuilder
		// @58: bipush 41 (0x29)
		// @5A: invokevirtual java.lang.StringBuilder.append(char)java.lang.StringBuilder
		// @5D: invokevirtual java.lang.StringBuilder.toString()java.lang.String
		// @60: invokestatic game.C_100181_cf.func_105695_a(java.lang.Throwable, java.lang.String)game.C_100170_cm
		// @63: athrow
	}
	
	String func_102525_c(byte arg0)
	{
		// @00: iload_1
		// @01: bipush 34 (0x22)
		// @03: if_icmpge @1F
		// @06: aload_0
		// @07: bipush -71 (0xB9)
		// @09: aconst_null
		// @0A: checkcast game.C_100336_im
		// @0D: bipush 53 (0x35)
		// @0F: bipush 63 (0x3F)
		// @11: bipush -10 (0xF6)
		// @13: bipush 114 (0x72)
		// @15: bipush -32 (0xE0)
		// @17: invokevirtual game.C_100030_gm.func_102520_a(int, game.C_100336_im, int, int, int, int, int)boolean
		// @1A: pop
		// @1B: goto @1F
		// @1E: athrow
		// @1F: aload_0
		// @20: bipush 66 (0x42)
		// @22: invokespecial game.C_100336_im.func_102525_c(byte)java.lang.String
		// @25: astore_2
		// @26: aload_0
		// @27: getfield game.C_100336_im game.C_100030_gm.field_103351_J
		// @2A: ifnonnull @31
		// @2D: goto @41
		// @30: athrow
		// @31: aload_0
		// @32: getfield game.C_100336_im game.C_100030_gm.field_103351_J
		// @35: bipush 68 (0x44)
		// @37: invokevirtual game.C_100336_im.func_102525_c(byte)java.lang.String
		// @3A: astore_3
		// @3B: aload_3
		// @3C: ifnull @41
		// @3F: aload_3
		// @40: areturn
		// @41: aload_2
		// @42: areturn
		// @43: astore_2
		// @44: aload_2
		// @45: new java.lang.StringBuilder
		// @48: dup
		// @49: invokespecial java.lang.StringBuilder.<init>()void
		// @4C: getstatic java.lang.String[] game.C_100030_gm.field_103348_O
		// @4F: bipush 12 (0x0C)
		// @51: aaload
		// @52: invokevirtual java.lang.StringBuilder.append(java.lang.String)java.lang.StringBuilder
		// @55: iload_1
		// @56: invokevirtual java.lang.StringBuilder.append(int)java.lang.StringBuilder
		// @59: bipush 41 (0x29)
		// @5B: invokevirtual java.lang.StringBuilder.append(char)java.lang.StringBuilder
		// @5E: invokevirtual java.lang.StringBuilder.toString()java.lang.String
		// @61: invokestatic game.C_100181_cf.func_105695_a(java.lang.Throwable, java.lang.String)game.C_100170_cm
		// @64: athrow
	}
	
	void func_102519_a(byte arg0, int arg1, int arg2, int arg3, C_100336_im arg4, int arg5)
	{
		// @00: aload_0
		// @01: getfield game.C_100336_im game.C_100030_gm.field_103351_J
		// @04: ifnonnull @0B
		// @07: goto @26
		// @0A: athrow
		// @0B: aload_0
		// @0C: getfield game.C_100336_im game.C_100030_gm.field_103351_J
		// @0F: bipush 122 (0x7A)
		// @11: iload_2
		// @12: aload_0
		// @13: getfield int game.C_100030_gm.field_102538_m
		// @16: iadd
		// @17: iload_3
		// @18: iload #4
		// @1A: aload #5
		// @1C: iload #6
		// @1E: aload_0
		// @1F: getfield int game.C_100030_gm.field_102541_w
		// @22: iadd
		// @23: invokevirtual game.C_100336_im.func_102519_a(byte, int, int, int, game.C_100336_im, int)void
		// @26: iload_1
		// @27: bipush 122 (0x7A)
		// @29: if_icmpeq @3A
		// @2C: aconst_null
		// @2D: checkcast java.lang.String[][]
		// @30: checkcast java.lang.String[][]
		// @33: putstatic java.lang.String[][] game.C_100030_gm.field_103347_N
		// @36: goto @3A
		// @39: athrow
		// @3A: goto @A2
		// @3D: astore #7
		// @3F: aload #7
		// @41: new java.lang.StringBuilder
		// @44: dup
		// @45: invokespecial java.lang.StringBuilder.<init>()void
		// @48: getstatic java.lang.String[] game.C_100030_gm.field_103348_O
		// @4B: bipush 19 (0x13)
		// @4D: aaload
		// @4E: invokevirtual java.lang.StringBuilder.append(java.lang.String)java.lang.StringBuilder
		// @51: iload_1
		// @52: invokevirtual java.lang.StringBuilder.append(int)java.lang.StringBuilder
		// @55: bipush 44 (0x2C)
		// @57: invokevirtual java.lang.StringBuilder.append(char)java.lang.StringBuilder
		// @5A: iload_2
		// @5B: invokevirtual java.lang.StringBuilder.append(int)java.lang.StringBuilder
		// @5E: bipush 44 (0x2C)
		// @60: invokevirtual java.lang.StringBuilder.append(char)java.lang.StringBuilder
		// @63: iload_3
		// @64: invokevirtual java.lang.StringBuilder.append(int)java.lang.StringBuilder
		// @67: bipush 44 (0x2C)
		// @69: invokevirtual java.lang.StringBuilder.append(char)java.lang.StringBuilder
		// @6C: iload #4
		// @6E: invokevirtual java.lang.StringBuilder.append(int)java.lang.StringBuilder
		// @71: bipush 44 (0x2C)
		// @73: invokevirtual java.lang.StringBuilder.append(char)java.lang.StringBuilder
		// @76: aload #5
		// @78: ifnull @84
		// @7B: getstatic java.lang.String[] game.C_100030_gm.field_103348_O
		// @7E: iconst_3
		// @7F: aaload
		// @80: goto @89
		// @83: athrow
		// @84: getstatic java.lang.String[] game.C_100030_gm.field_103348_O
		// @87: iconst_1
		// @88: aaload
		// @89: invokevirtual java.lang.StringBuilder.append(java.lang.String)java.lang.StringBuilder
		// @8C: bipush 44 (0x2C)
		// @8E: invokevirtual java.lang.StringBuilder.append(char)java.lang.StringBuilder
		// @91: iload #6
		// @93: invokevirtual java.lang.StringBuilder.append(int)java.lang.StringBuilder
		// @96: bipush 41 (0x29)
		// @98: invokevirtual java.lang.StringBuilder.append(char)java.lang.StringBuilder
		// @9B: invokevirtual java.lang.StringBuilder.toString()java.lang.String
		// @9E: invokestatic game.C_100181_cf.func_105695_a(java.lang.Throwable, java.lang.String)game.C_100170_cm
		// @A1: athrow
		// @A2: return
	}
	
	static final void func_103338_i(int arg0)
	{
		// @00: getstatic game.C_100047_vh game.C_100111_el.field_104859_g
		// @03: dup
		// @04: astore_1
		// @05: monitorenter
		// @06: getstatic int game.C_100012_fh.field_100514_J
		// @09: iconst_1
		// @0A: iadd
		// @0B: putstatic int game.C_100012_fh.field_100514_J
		// @0E: iload_0
		// @0F: sipush -687 (0xFD51)
		// @12: if_icmpeq @1F
		// @15: aconst_null
		// @16: checkcast java.lang.String[][]
		// @19: checkcast java.lang.String[][]
		// @1C: putstatic java.lang.String[][] game.C_100030_gm.field_103347_N
		// @1F: getstatic int game.C_100083_c.field_103172_O
		// @22: putstatic int game.C_100083_c.field_103171_R
		// @25: getstatic int game.C_100231_oc.field_102198_ec
		// @28: putstatic int game.C_100015_wh.field_103781_g
		// @2B: getstatic int game.C_100113_ek.field_104884_h
		// @2E: putstatic int game.C_100338_jc.field_105370_l
		// @31: getstatic boolean game.C_100246_pg.field_106404_b
		// @34: putstatic boolean game.C_100240_oj.field_106322_j
		// @37: iconst_0
		// @38: putstatic boolean game.C_100246_pg.field_106404_b
		// @3B: getstatic int game.C_100130_tf.field_104958_f
		// @3E: putstatic int game.C_100102_w.field_104636_c
		// @41: getstatic int game.C_100012_fh.field_100520_R
		// @44: putstatic int game.C_100340_je.field_102981_m
		// @47: getstatic int game.C_100001_ge.field_100563_e
		// @4A: putstatic int game.C_100125_tm.field_100745_p
		// @4D: iconst_0
		// @4E: putstatic int game.C_100130_tf.field_104958_f
		// @51: getstatic int game.C_100062_dk.field_104279_f
		// @54: putstatic int game.C_100151_bc.field_102931_db
		// @57: aload_1
		// @58: monitorexit
		// @59: goto @61
		// @5C: astore_2
		// @5D: aload_1
		// @5E: monitorexit
		// @5F: aload_2
		// @60: athrow
		// @61: goto @86
		// @64: astore_1
		// @65: aload_1
		// @66: new java.lang.StringBuilder
		// @69: dup
		// @6A: invokespecial java.lang.StringBuilder.<init>()void
		// @6D: getstatic java.lang.String[] game.C_100030_gm.field_103348_O
		// @70: bipush 17 (0x11)
		// @72: aaload
		// @73: invokevirtual java.lang.StringBuilder.append(java.lang.String)java.lang.StringBuilder
		// @76: iload_0
		// @77: invokevirtual java.lang.StringBuilder.append(int)java.lang.StringBuilder
		// @7A: bipush 41 (0x29)
		// @7C: invokevirtual java.lang.StringBuilder.append(char)java.lang.StringBuilder
		// @7F: invokevirtual java.lang.StringBuilder.toString()java.lang.String
		// @82: invokestatic game.C_100181_cf.func_105695_a(java.lang.Throwable, java.lang.String)game.C_100170_cm
		// @85: athrow
		// @86: return
	}
	
	static final void func_103336_a(byte arg0)
	{
		// @00: bipush 57 (0x39)
		// @02: iload_0
		// @03: bipush -22 (0xEA)
		// @05: isub
		// @06: bipush 49 (0x31)
		// @08: idiv
		// @09: irem
		// @0A: istore_1
		// @0B: aconst_null
		// @0C: putstatic int[] game.C_100312_ld.field_107156_c
		// @0F: aconst_null
		// @10: putstatic int[] game.C_100085_a.field_102573_H
		// @13: aconst_null
		// @14: putstatic int[] game.C_100213_ak.field_105994_d
		// @17: aconst_null
		// @18: checkcast byte[][]
		// @1B: putstatic byte[][] game.C_100107_u.field_104774_c
		// @1E: aconst_null
		// @1F: putstatic int[] game.C_100068_vc.field_104340_f
		// @22: aconst_null
		// @23: putstatic int[] game.C_100012_fh.field_100509_M
		// @26: goto @4B
		// @29: astore_1
		// @2A: aload_1
		// @2B: new java.lang.StringBuilder
		// @2E: dup
		// @2F: invokespecial java.lang.StringBuilder.<init>()void
		// @32: getstatic java.lang.String[] game.C_100030_gm.field_103348_O
		// @35: bipush 20 (0x14)
		// @37: aaload
		// @38: invokevirtual java.lang.StringBuilder.append(java.lang.String)java.lang.StringBuilder
		// @3B: iload_0
		// @3C: invokevirtual java.lang.StringBuilder.append(int)java.lang.StringBuilder
		// @3F: bipush 41 (0x29)
		// @41: invokevirtual java.lang.StringBuilder.append(char)java.lang.StringBuilder
		// @44: invokevirtual java.lang.StringBuilder.toString()java.lang.String
		// @47: invokestatic game.C_100181_cf.func_105695_a(java.lang.Throwable, java.lang.String)game.C_100170_cm
		// @4A: athrow
		// @4B: return
	}
	
	final void func_102524_a(int arg0, int arg1, int arg2, int arg3, byte arg4)
	{
		// @00: bipush -113 (0x8F)
		// @02: iload #5
		// @04: bipush -11 (0xF5)
		// @06: isub
		// @07: bipush 48 (0x30)
		// @09: idiv
		// @0A: irem
		// @0B: istore #6
		// @0D: aload_0
		// @0E: iload_1
		// @0F: iload_2
		// @10: iload_3
		// @11: iload #4
		// @13: bipush 42 (0x2A)
		// @15: invokespecial game.C_100336_im.func_102524_a(int, int, int, int, byte)void
		// @18: aload_0
		// @19: sipush 27816 (0x6CA8)
		// @1C: invokevirtual game.C_100030_gm.func_103340_h(int)void
		// @1F: goto @6C
		// @22: astore #6
		// @24: aload #6
		// @26: new java.lang.StringBuilder
		// @29: dup
		// @2A: invokespecial java.lang.StringBuilder.<init>()void
		// @2D: getstatic java.lang.String[] game.C_100030_gm.field_103348_O
		// @30: bipush 24 (0x18)
		// @32: aaload
		// @33: invokevirtual java.lang.StringBuilder.append(java.lang.String)java.lang.StringBuilder
		// @36: iload_1
		// @37: invokevirtual java.lang.StringBuilder.append(int)java.lang.StringBuilder
		// @3A: bipush 44 (0x2C)
		// @3C: invokevirtual java.lang.StringBuilder.append(char)java.lang.StringBuilder
		// @3F: iload_2
		// @40: invokevirtual java.lang.StringBuilder.append(int)java.lang.StringBuilder
		// @43: bipush 44 (0x2C)
		// @45: invokevirtual java.lang.StringBuilder.append(char)java.lang.StringBuilder
		// @48: iload_3
		// @49: invokevirtual java.lang.StringBuilder.append(int)java.lang.StringBuilder
		// @4C: bipush 44 (0x2C)
		// @4E: invokevirtual java.lang.StringBuilder.append(char)java.lang.StringBuilder
		// @51: iload #4
		// @53: invokevirtual java.lang.StringBuilder.append(int)java.lang.StringBuilder
		// @56: bipush 44 (0x2C)
		// @58: invokevirtual java.lang.StringBuilder.append(char)java.lang.StringBuilder
		// @5B: iload #5
		// @5D: invokevirtual java.lang.StringBuilder.append(int)java.lang.StringBuilder
		// @60: bipush 41 (0x29)
		// @62: invokevirtual java.lang.StringBuilder.append(char)java.lang.StringBuilder
		// @65: invokevirtual java.lang.StringBuilder.toString()java.lang.String
		// @68: invokestatic game.C_100181_cf.func_105695_a(java.lang.Throwable, java.lang.String)game.C_100170_cm
		// @6B: athrow
		// @6C: return
	}
	
	void func_102513_a(C_100336_im arg0, int arg1, int arg2, int arg3)
	{
		// @00: aload_0
		// @01: aload_1
		// @02: iload_2
		// @03: iload_3
		// @04: iload #4
		// @06: invokespecial game.C_100336_im.func_102513_a(game.C_100336_im, int, int, int)void
		// @09: aload_0
		// @0A: getfield game.C_100336_im game.C_100030_gm.field_103351_J
		// @0D: ifnull @28
		// @10: aload_0
		// @11: getfield game.C_100336_im game.C_100030_gm.field_103351_J
		// @14: aload_1
		// @15: iload_2
		// @16: aload_0
		// @17: getfield int game.C_100030_gm.field_102541_w
		// @1A: ineg
		// @1B: isub
		// @1C: iconst_2
		// @1D: iload #4
		// @1F: aload_0
		// @20: getfield int game.C_100030_gm.field_102538_m
		// @23: ineg
		// @24: isub
		// @25: invokevirtual game.C_100336_im.func_102513_a(game.C_100336_im, int, int, int)void
		// @28: goto @7C
		// @2B: astore #5
		// @2D: aload #5
		// @2F: new java.lang.StringBuilder
		// @32: dup
		// @33: invokespecial java.lang.StringBuilder.<init>()void
		// @36: getstatic java.lang.String[] game.C_100030_gm.field_103348_O
		// @39: bipush 9 (0x09)
		// @3B: aaload
		// @3C: invokevirtual java.lang.StringBuilder.append(java.lang.String)java.lang.StringBuilder
		// @3F: aload_1
		// @40: ifnull @4C
		// @43: getstatic java.lang.String[] game.C_100030_gm.field_103348_O
		// @46: iconst_3
		// @47: aaload
		// @48: goto @51
		// @4B: athrow
		// @4C: getstatic java.lang.String[] game.C_100030_gm.field_103348_O
		// @4F: iconst_1
		// @50: aaload
		// @51: invokevirtual java.lang.StringBuilder.append(java.lang.String)java.lang.StringBuilder
		// @54: bipush 44 (0x2C)
		// @56: invokevirtual java.lang.StringBuilder.append(char)java.lang.StringBuilder
		// @59: iload_2
		// @5A: invokevirtual java.lang.StringBuilder.append(int)java.lang.StringBuilder
		// @5D: bipush 44 (0x2C)
		// @5F: invokevirtual java.lang.StringBuilder.append(char)java.lang.StringBuilder
		// @62: iload_3
		// @63: invokevirtual java.lang.StringBuilder.append(int)java.lang.StringBuilder
		// @66: bipush 44 (0x2C)
		// @68: invokevirtual java.lang.StringBuilder.append(char)java.lang.StringBuilder
		// @6B: iload #4
		// @6D: invokevirtual java.lang.StringBuilder.append(int)java.lang.StringBuilder
		// @70: bipush 41 (0x29)
		// @72: invokevirtual java.lang.StringBuilder.append(char)java.lang.StringBuilder
		// @75: invokevirtual java.lang.StringBuilder.toString()java.lang.String
		// @78: invokestatic game.C_100181_cf.func_105695_a(java.lang.Throwable, java.lang.String)game.C_100170_cm
		// @7B: athrow
		// @7C: return
	}
	
	StringBuilder func_102510_a(int arg0, byte arg1, StringBuilder arg2, Hashtable arg3)
	{
		// @00: bipush 14 (0x0E)
		// @02: iload_2
		// @03: bipush -42 (0xD6)
		// @05: isub
		// @06: bipush 63 (0x3F)
		// @08: idiv
		// @09: idiv
		// @0A: istore #5
		// @0C: aload_0
		// @0D: aload #4
		// @0F: iload_1
		// @10: aload_3
		// @11: bipush -76 (0xB4)
		// @13: invokevirtual game.C_100030_gm.func_102516_a(java.util.Hashtable, int, java.lang.StringBuilder, byte)boolean
		// @16: ifne @1D
		// @19: goto @30
		// @1C: athrow
		// @1D: aload_0
		// @1E: bipush -127 (0x81)
		// @20: aload_3
		// @21: iload_1
		// @22: aload #4
		// @24: invokevirtual game.C_100030_gm.func_102518_a(byte, java.lang.StringBuilder, int, java.util.Hashtable)void
		// @27: aload_0
		// @28: aload #4
		// @2A: iconst_1
		// @2B: iload_1
		// @2C: aload_3
		// @2D: invokevirtual game.C_100030_gm.func_103333_a(java.util.Hashtable, int, int, java.lang.StringBuilder)void
		// @30: aload_3
		// @31: areturn
		// @32: astore #5
		// @34: aload #5
		// @36: new java.lang.StringBuilder
		// @39: dup
		// @3A: invokespecial java.lang.StringBuilder.<init>()void
		// @3D: getstatic java.lang.String[] game.C_100030_gm.field_103348_O
		// @40: bipush 18 (0x12)
		// @42: aaload
		// @43: invokevirtual java.lang.StringBuilder.append(java.lang.String)java.lang.StringBuilder
		// @46: iload_1
		// @47: invokevirtual java.lang.StringBuilder.append(int)java.lang.StringBuilder
		// @4A: bipush 44 (0x2C)
		// @4C: invokevirtual java.lang.StringBuilder.append(char)java.lang.StringBuilder
		// @4F: iload_2
		// @50: invokevirtual java.lang.StringBuilder.append(int)java.lang.StringBuilder
		// @53: bipush 44 (0x2C)
		// @55: invokevirtual java.lang.StringBuilder.append(char)java.lang.StringBuilder
		// @58: aload_3
		// @59: ifnull @65
		// @5C: getstatic java.lang.String[] game.C_100030_gm.field_103348_O
		// @5F: iconst_3
		// @60: aaload
		// @61: goto @6A
		// @64: athrow
		// @65: getstatic java.lang.String[] game.C_100030_gm.field_103348_O
		// @68: iconst_1
		// @69: aaload
		// @6A: invokevirtual java.lang.StringBuilder.append(java.lang.String)java.lang.StringBuilder
		// @6D: bipush 44 (0x2C)
		// @6F: invokevirtual java.lang.StringBuilder.append(char)java.lang.StringBuilder
		// @72: aload #4
		// @74: ifnull @80
		// @77: getstatic java.lang.String[] game.C_100030_gm.field_103348_O
		// @7A: iconst_3
		// @7B: aaload
		// @7C: goto @85
		// @7F: athrow
		// @80: getstatic java.lang.String[] game.C_100030_gm.field_103348_O
		// @83: iconst_1
		// @84: aaload
		// @85: invokevirtual java.lang.StringBuilder.append(java.lang.String)java.lang.StringBuilder
		// @88: bipush 41 (0x29)
		// @8A: invokevirtual java.lang.StringBuilder.append(char)java.lang.StringBuilder
		// @8D: invokevirtual java.lang.StringBuilder.toString()java.lang.String
		// @90: invokestatic game.C_100181_cf.func_105695_a(java.lang.Throwable, java.lang.String)game.C_100170_cm
		// @93: athrow
	}
	
	static final void func_103329_a(byte[] arg0, int arg1)
	{
		// @000: getstatic int game.SteelSentinels.field_105275_O
		// @003: istore #10
		// @005: aconst_null
		// @006: aload_0
		// @007: if_acmpeq @010
		// @00A: iconst_0
		// @00B: aload_0
		// @00C: arraylength
		// @00D: if_icmpne @011
		// @010: return
		// @011: iconst_0
		// @012: istore_2
		// @013: aload_0
		// @014: iload_2
		// @015: iinc #2 +1
		// @018: baload
		// @019: istore_3
		// @01A: bipush -3 (0xFD)
		// @01C: iload_3
		// @01D: iconst_m1
		// @01E: ixor
		// @01F: if_icmplt @16B
		// @022: iload_2
		// @023: iconst_m1
		// @024: ixor
		// @025: aload_0
		// @026: arraylength
		// @027: iconst_m1
		// @028: ixor
		// @029: if_icmpgt @034
		// @02C: goto @030
		// @02F: athrow
		// @030: goto @16B
		// @033: athrow
		// @034: aload_0
		// @035: iload_2
		// @036: iinc #2 +1
		// @039: baload
		// @03A: istore #4
		// @03C: getstatic boolean game.C_100216_aj.field_104462_t
		// @03F: istore #5
		// @041: iconst_m1
		// @042: iload #4
		// @044: iconst_1
		// @045: iand
		// @046: iconst_m1
		// @047: ixor
		// @048: if_icmpeq @050
		// @04B: iconst_1
		// @04C: goto @051
		// @04F: athrow
		// @050: iconst_0
		// @051: putstatic boolean game.C_100034_gi.field_104036_j
		// @054: iconst_0
		// @055: iload #4
		// @057: iconst_2
		// @058: iand
		// @059: if_icmpeq @061
		// @05C: iconst_1
		// @05D: goto @062
		// @060: athrow
		// @061: iconst_0
		// @062: putstatic boolean game.C_100050_vg.field_100637_q
		// @065: iconst_m1
		// @066: bipush 16 (0x10)
		// @068: iload #4
		// @06A: iand
		// @06B: iconst_m1
		// @06C: ixor
		// @06D: if_icmpeq @075
		// @070: iconst_1
		// @071: goto @076
		// @074: athrow
		// @075: iconst_0
		// @076: putstatic boolean game.C_100102_w.field_104632_g
		// @079: iconst_m1
		// @07A: bipush 8 (0x08)
		// @07C: iload #4
		// @07E: iand
		// @07F: iconst_m1
		// @080: ixor
		// @081: if_icmpeq @089
		// @084: iconst_1
		// @085: goto @08A
		// @088: athrow
		// @089: iconst_0
		// @08A: putstatic boolean game.C_100094_j.field_104552_j
		// @08D: iconst_m1
		// @08E: iload #4
		// @090: iconst_4
		// @091: iand
		// @092: iconst_m1
		// @093: ixor
		// @094: if_icmpeq @09C
		// @097: iconst_1
		// @098: goto @09D
		// @09B: athrow
		// @09C: iconst_0
		// @09D: putstatic boolean game.C_100216_aj.field_104462_t
		// @0A0: getstatic boolean game.C_100247_pa.field_106414_d
		// @0A3: istore #6
		// @0A5: getstatic java.lang.String[] game.C_100268_mk.field_106669_b
		// @0A8: bipush 41 (0x29)
		// @0AA: getstatic boolean game.C_100034_gi.field_104036_j
		// @0AD: ifeq @0B7
		// @0B0: getstatic java.lang.String game.C_100027_hc.field_102597_P
		// @0B3: goto @0BA
		// @0B6: athrow
		// @0B7: getstatic java.lang.String game.C_100116_ei.field_104122_b
		// @0BA: aastore
		// @0BB: iload #4
		// @0BD: bipush 32 (0x20)
		// @0BF: iand
		// @0C0: iconst_m1
		// @0C1: ixor
		// @0C2: iconst_m1
		// @0C3: if_icmpeq @0CB
		// @0C6: iconst_1
		// @0C7: goto @0CC
		// @0CA: athrow
		// @0CB: iconst_0
		// @0CC: putstatic boolean game.C_100247_pa.field_106414_d
		// @0CF: getstatic java.lang.String[] game.C_100268_mk.field_106669_b
		// @0D2: bipush 44 (0x2C)
		// @0D4: getstatic boolean game.C_100102_w.field_104632_g
		// @0D7: ifne @0E1
		// @0DA: getstatic java.lang.String game.C_100059_df.field_101606_K
		// @0DD: goto @0E4
		// @0E0: athrow
		// @0E1: getstatic java.lang.String game.C_100041_wf.field_104105_e
		// @0E4: aastore
		// @0E5: getstatic java.lang.String[] game.C_100268_mk.field_106669_b
		// @0E8: bipush 37 (0x25)
		// @0EA: getstatic boolean game.C_100050_vg.field_100637_q
		// @0ED: ifne @0F7
		// @0F0: getstatic java.lang.String game.C_100081_ue.field_100675_m
		// @0F3: goto @0FA
		// @0F6: athrow
		// @0F7: getstatic java.lang.String game.C_100316_lc.field_102413_t
		// @0FA: aastore
		// @0FB: getstatic java.lang.String[] game.C_100268_mk.field_106669_b
		// @0FE: bipush 42 (0x2A)
		// @100: getstatic boolean game.C_100216_aj.field_104462_t
		// @103: ifne @10D
		// @106: getstatic java.lang.String game.C_100138_bo.field_100413_h
		// @109: goto @110
		// @10C: athrow
		// @10D: getstatic java.lang.String game.C_100164_se.field_105453_c
		// @110: aastore
		// @111: getstatic java.lang.String[] game.C_100268_mk.field_106669_b
		// @114: bipush 43 (0x2B)
		// @116: getstatic boolean game.C_100094_j.field_104552_j
		// @119: ifne @123
		// @11C: getstatic java.lang.String game.C_100141_tc.field_105057_f
		// @11F: goto @126
		// @122: athrow
		// @123: getstatic java.lang.String game.C_100151_bc.field_102941_P
		// @126: aastore
		// @127: iload #5
		// @129: getstatic boolean game.C_100216_aj.field_104462_t
		// @12C: ifne @134
		// @12F: iconst_1
		// @130: goto @135
		// @133: athrow
		// @134: iconst_0
		// @135: if_icmpeq @14D
		// @138: iload #6
		// @13A: getstatic boolean game.C_100247_pa.field_106414_d
		// @13D: ifne @149
		// @140: goto @144
		// @143: athrow
		// @144: iconst_1
		// @145: goto @14A
		// @148: athrow
		// @149: iconst_0
		// @14A: if_icmpne @155
		// @14D: aconst_null
		// @14E: putstatic game.C_100302_ka game.C_100145_ta.field_100429_j
		// @151: goto @155
		// @154: athrow
		// @155: getstatic java.lang.String[] game.C_100268_mk.field_106669_b
		// @158: bipush 47 (0x2F)
		// @15A: getstatic boolean game.C_100247_pa.field_106414_d
		// @15D: ifeq @167
		// @160: getstatic java.lang.String game.C_100033_gj.field_101922_mc
		// @163: goto @16A
		// @166: athrow
		// @167: getstatic java.lang.String game.C_100220_ac.field_106063_k
		// @16A: aastore
		// @16B: iconst_1
		// @16C: iload_3
		// @16D: if_icmpgt @187
		// @170: aload_0
		// @171: arraylength
		// @172: iload_2
		// @173: if_icmple @187
		// @176: goto @17A
		// @179: athrow
		// @17A: aload_0
		// @17B: iload_2
		// @17C: iinc #2 +1
		// @17F: baload
		// @180: putstatic int game.C_100249_pc.field_102333_I
		// @183: goto @187
		// @186: athrow
		// @187: iload_3
		// @188: ifge @18F
		// @18B: goto @2F5
		// @18E: athrow
		// @18F: aload_0
		// @190: arraylength
		// @191: iconst_m1
		// @192: ixor
		// @193: iload_2
		// @194: iconst_m1
		// @195: ixor
		// @196: if_icmpeq @19D
		// @199: goto @19E
		// @19C: athrow
		// @19D: return
		// @19E: sipush 255 (0x00FF)
		// @1A1: aload_0
		// @1A2: iload_2
		// @1A3: iinc #2 +1
		// @1A6: baload
		// @1A7: iand
		// @1A8: istore #4
		// @1AA: aload_0
		// @1AB: arraylength
		// @1AC: iconst_m1
		// @1AD: ixor
		// @1AE: iload #4
		// @1B0: iload_2
		// @1B1: ineg
		// @1B2: isub
		// @1B3: iconst_m1
		// @1B4: ixor
		// @1B5: if_icmpgt @1BC
		// @1B8: goto @1BD
		// @1BB: athrow
		// @1BC: return
		// @1BD: iload #4
		// @1BF: newarray int[]
		// @1C1: putstatic int[] game.C_100280_nf.field_101178_o
		// @1C4: iconst_0
		// @1C5: istore #5
		// @1C7: iload #5
		// @1C9: iconst_m1
		// @1CA: ixor
		// @1CB: iload #4
		// @1CD: iconst_m1
		// @1CE: ixor
		// @1CF: if_icmple @20C
		// @1D2: getstatic int[] game.C_100280_nf.field_101178_o
		// @1D5: iload #5
		// @1D7: sipush 255 (0x00FF)
		// @1DA: aload_0
		// @1DB: iload_2
		// @1DC: iinc #2 +1
		// @1DF: baload
		// @1E0: invokestatic game.C_100256_pk.func_100449_a(int, int)int
		// @1E3: iastore
		// @1E4: sipush 255 (0x00FF)
		// @1E7: getstatic int[] game.C_100280_nf.field_101178_o
		// @1EA: iload #5
		// @1EC: iaload
		// @1ED: iload #10
		// @1EF: ifne @2F9
		// @1F2: if_icmpne @204
		// @1F5: goto @1F9
		// @1F8: athrow
		// @1F9: getstatic int[] game.C_100280_nf.field_101178_o
		// @1FC: iload #5
		// @1FE: iconst_m1
		// @1FF: iastore
		// @200: goto @204
		// @203: athrow
		// @204: iinc #5 +1
		// @207: iload #10
		// @209: ifeq @1C7
		// @20C: bipush 8 (0x08)
		// @20E: newarray int[]
		// @210: astore #5
		// @212: aconst_null
		// @213: getstatic int[] game.C_100280_nf.field_101178_o
		// @216: bipush -61 (0xC3)
		// @218: aload #5
		// @21A: invokestatic game.C_100157_db.func_103546_a(int[], byte, int[])game.C_100327_ib
		// @21D: if_acmpne @23C
		// @220: getstatic int[] game.C_100005_fk.field_103605_u
		// @223: arraylength
		// @224: newarray int[]
		// @226: putstatic int[] game.C_100280_nf.field_101178_o
		// @229: getstatic int[] game.C_100005_fk.field_103605_u
		// @22C: iconst_0
		// @22D: getstatic int[] game.C_100280_nf.field_101178_o
		// @230: iconst_0
		// @231: getstatic int[] game.C_100280_nf.field_101178_o
		// @234: arraylength
		// @235: invokestatic game.C_100120_en.func_104913_a(int[], int, int[], int, int)void
		// @238: goto @23C
		// @23B: athrow
		// @23C: bipush -25 (0xE7)
		// @23E: invokestatic game.C_100234_ob.func_106268_c(byte)boolean
		// @241: ifne @24F
		// @244: iconst_0
		// @245: getstatic int game.C_100212_qc.field_105976_b
		// @248: if_icmplt @2F5
		// @24B: goto @24F
		// @24E: athrow
		// @24F: getstatic int[] game.C_100280_nf.field_101178_o
		// @252: iconst_0
		// @253: iaload
		// @254: istore #6
		// @256: bipush -102 (0x9A)
		// @258: iload #6
		// @25A: invokestatic game.C_100042_we.func_104129_b(int, int)int[]
		// @25D: astore #7
		// @25F: iconst_0
		// @260: istore #8
		// @262: aconst_null
		// @263: aload #7
		// @265: if_acmpeq @2CF
		// @268: iconst_0
		// @269: sipush -11145 (0xD477)
		// @26C: iload #6
		// @26E: invokestatic game.C_100080_b.func_104421_a(boolean, int, int)boolean
		// @271: ifne @2CF
		// @274: goto @278
		// @277: athrow
		// @278: iconst_0
		// @279: istore #9
		// @27B: iload #9
		// @27D: iconst_m1
		// @27E: ixor
		// @27F: getstatic int[] game.C_100280_nf.field_101178_o
		// @282: arraylength
		// @283: iconst_m1
		// @284: ixor
		// @285: if_icmple @2CA
		// @288: bipush -8 (0xF8)
		// @28A: getstatic int[] game.C_100280_nf.field_101178_o
		// @28D: arraylength
		// @28E: iadd
		// @28F: iload #9
		// @291: iload #10
		// @293: ifne @2F9
		// @296: if_icmpgt @2A2
		// @299: goto @29D
		// @29C: athrow
		// @29D: iconst_1
		// @29E: goto @2A3
		// @2A1: athrow
		// @2A2: iconst_0
		// @2A3: sipush -11145 (0xD477)
		// @2A6: getstatic int[] game.C_100280_nf.field_101178_o
		// @2A9: iload #9
		// @2AB: iaload
		// @2AC: invokestatic game.C_100080_b.func_104421_a(boolean, int, int)boolean
		// @2AF: ifne @2B6
		// @2B2: goto @2BE
		// @2B5: athrow
		// @2B6: iconst_1
		// @2B7: istore #8
		// @2B9: iload #10
		// @2BB: ifeq @2CA
		// @2BE: iinc #9 +1
		// @2C1: iload #10
		// @2C3: ifeq @27B
		// @2C6: goto @2CA
		// @2C9: athrow
		// @2CA: iload #10
		// @2CC: ifeq @2D7
		// @2CF: iconst_1
		// @2D0: istore #8
		// @2D2: getstatic int[] game.C_100005_fk.field_103605_u
		// @2D5: astore #7
		// @2D7: iload #8
		// @2D9: ifeq @2F5
		// @2DC: aload #7
		// @2DE: arraylength
		// @2DF: newarray int[]
		// @2E1: putstatic int[] game.C_100280_nf.field_101178_o
		// @2E4: aload #7
		// @2E6: iconst_0
		// @2E7: getstatic int[] game.C_100280_nf.field_101178_o
		// @2EA: iconst_0
		// @2EB: aload #7
		// @2ED: arraylength
		// @2EE: invokestatic game.C_100120_en.func_104913_a(int[], int, int[], int, int)void
		// @2F1: goto @2F5
		// @2F4: athrow
		// @2F5: iload_1
		// @2F6: sipush 9837 (0x266D)
		// @2F9: if_icmpeq @305
		// @2FC: bipush -46 (0xD2)
		// @2FE: invokestatic game.C_100030_gm.func_103335_e(byte)void
		// @301: goto @305
		// @304: athrow
		// @305: iload_3
		// @306: iconst_3
		// @307: if_icmplt @3DE
		// @30A: getstatic int[][] game.C_100122_em.field_102073_Xb
		// @30D: astore #4
		// @30F: iconst_0
		// @310: istore #5
		// @312: aload #4
		// @314: arraylength
		// @315: iload #5
		// @317: if_icmple @3DE
		// @31A: iload #10
		// @31C: ifne @41D
		// @31F: iload_2
		// @320: aload_0
		// @321: arraylength
		// @322: if_icmpge @32D
		// @325: goto @329
		// @328: athrow
		// @329: goto @32E
		// @32C: athrow
		// @32D: return
		// @32E: sipush 255 (0x00FF)
		// @331: aload_0
		// @332: iload_2
		// @333: iinc #2 +1
		// @336: baload
		// @337: iand
		// @338: istore #6
		// @33A: iload #6
		// @33C: ifne @34E
		// @33F: aload #4
		// @341: iload #5
		// @343: aconst_null
		// @344: aastore
		// @345: iload #10
		// @347: ifeq @3CD
		// @34A: goto @34E
		// @34D: athrow
		// @34E: aload_0
		// @34F: arraylength
		// @350: iload_2
		// @351: iload #6
		// @353: iadd
		// @354: if_icmpge @35C
		// @357: goto @35B
		// @35A: athrow
		// @35B: return
		// @35C: aconst_null
		// @35D: aload #4
		// @35F: iload #5
		// @361: aaload
		// @362: if_acmpeq @378
		// @365: iload #6
		// @367: iconst_m1
		// @368: ixor
		// @369: aload #4
		// @36B: iload #5
		// @36D: aaload
		// @36E: arraylength
		// @36F: iconst_m1
		// @370: ixor
		// @371: if_icmpeq @385
		// @374: goto @378
		// @377: athrow
		// @378: aload #4
		// @37A: iload #5
		// @37C: iload #6
		// @37E: newarray int[]
		// @380: aastore
		// @381: goto @385
		// @384: athrow
		// @385: iconst_0
		// @386: istore #7
		// @388: iload #6
		// @38A: iload #7
		// @38C: if_icmple @3CD
		// @38F: aload #4
		// @391: iload #5
		// @393: aaload
		// @394: iload #7
		// @396: sipush 255 (0x00FF)
		// @399: aload_0
		// @39A: iload_2
		// @39B: iinc #2 +1
		// @39E: baload
		// @39F: invokestatic game.C_100256_pk.func_100449_a(int, int)int
		// @3A2: iastore
		// @3A3: aload #4
		// @3A5: iload #5
		// @3A7: aaload
		// @3A8: iload #7
		// @3AA: iaload
		// @3AB: iconst_m1
		// @3AC: ixor
		// @3AD: sipush -256 (0xFF00)
		// @3B0: iload #10
		// @3B2: ifne @317
		// @3B5: if_icmpne @3C5
		// @3B8: aload #4
		// @3BA: iload #5
		// @3BC: aaload
		// @3BD: iload #7
		// @3BF: iconst_m1
		// @3C0: iastore
		// @3C1: goto @3C5
		// @3C4: athrow
		// @3C5: iinc #7 +1
		// @3C8: iload #10
		// @3CA: ifeq @388
		// @3CD: sipush 1000 (0x03E8)
		// @3D0: aconst_null
		// @3D1: iload #5
		// @3D3: invokestatic game.C_100013_fn.func_103736_a(int, game.C_100327_ib, int)void
		// @3D6: iinc #5 +1
		// @3D9: iload #10
		// @3DB: ifeq @312
		// @3DE: goto @41D
		// @3E1: astore_2
		// @3E2: aload_2
		// @3E3: new java.lang.StringBuilder
		// @3E6: dup
		// @3E7: invokespecial java.lang.StringBuilder.<init>()void
		// @3EA: getstatic java.lang.String[] game.C_100030_gm.field_103348_O
		// @3ED: bipush 16 (0x10)
		// @3EF: aaload
		// @3F0: invokevirtual java.lang.StringBuilder.append(java.lang.String)java.lang.StringBuilder
		// @3F3: aload_0
		// @3F4: ifnull @400
		// @3F7: getstatic java.lang.String[] game.C_100030_gm.field_103348_O
		// @3FA: iconst_3
		// @3FB: aaload
		// @3FC: goto @405
		// @3FF: athrow
		// @400: getstatic java.lang.String[] game.C_100030_gm.field_103348_O
		// @403: iconst_1
		// @404: aaload
		// @405: invokevirtual java.lang.StringBuilder.append(java.lang.String)java.lang.StringBuilder
		// @408: bipush 44 (0x2C)
		// @40A: invokevirtual java.lang.StringBuilder.append(char)java.lang.StringBuilder
		// @40D: iload_1
		// @40E: invokevirtual java.lang.StringBuilder.append(int)java.lang.StringBuilder
		// @411: bipush 41 (0x29)
		// @413: invokevirtual java.lang.StringBuilder.append(char)java.lang.StringBuilder
		// @416: invokevirtual java.lang.StringBuilder.toString()java.lang.String
		// @419: invokestatic game.C_100181_cf.func_105695_a(java.lang.Throwable, java.lang.String)game.C_100170_cm
		// @41C: athrow
		// @41D: return
	}
	
	private final boolean func_103332_a(C_100336_im arg0, boolean arg1)
	{
		// @00: iload_2
		// @01: iconst_1
		// @02: if_icmpeq @10
		// @05: aconst_null
		// @06: checkcast game.C_100302_ka
		// @09: putstatic game.C_100302_ka game.C_100030_gm.field_103341_D
		// @0C: goto @10
		// @0F: athrow
		// @10: aconst_null
		// @11: aload_0
		// @12: getfield game.C_100336_im game.C_100030_gm.field_103351_J
		// @15: if_acmpeq @3D
		// @18: aload_0
		// @19: getfield game.C_100336_im game.C_100030_gm.field_103351_J
		// @1C: bipush 97 (0x61)
		// @1E: invokevirtual game.C_100336_im.func_102515_d(byte)boolean
		// @21: ifne @3D
		// @24: goto @28
		// @27: athrow
		// @28: aload_0
		// @29: getfield game.C_100336_im game.C_100030_gm.field_103351_J
		// @2C: iconst_1
		// @2D: aload_1
		// @2E: invokevirtual game.C_100336_im.func_102522_a(int, game.C_100336_im)boolean
		// @31: ifeq @3D
		// @34: goto @38
		// @37: athrow
		// @38: iconst_1
		// @39: goto @3E
		// @3C: athrow
		// @3D: iconst_0
		// @3E: ireturn
		// @3F: astore_3
		// @40: aload_3
		// @41: new java.lang.StringBuilder
		// @44: dup
		// @45: invokespecial java.lang.StringBuilder.<init>()void
		// @48: getstatic java.lang.String[] game.C_100030_gm.field_103348_O
		// @4B: iconst_5
		// @4C: aaload
		// @4D: invokevirtual java.lang.StringBuilder.append(java.lang.String)java.lang.StringBuilder
		// @50: aload_1
		// @51: ifnull @5D
		// @54: getstatic java.lang.String[] game.C_100030_gm.field_103348_O
		// @57: iconst_3
		// @58: aaload
		// @59: goto @62
		// @5C: athrow
		// @5D: getstatic java.lang.String[] game.C_100030_gm.field_103348_O
		// @60: iconst_1
		// @61: aaload
		// @62: invokevirtual java.lang.StringBuilder.append(java.lang.String)java.lang.StringBuilder
		// @65: bipush 44 (0x2C)
		// @67: invokevirtual java.lang.StringBuilder.append(char)java.lang.StringBuilder
		// @6A: iload_2
		// @6B: invokevirtual java.lang.StringBuilder.append(boolean)java.lang.StringBuilder
		// @6E: bipush 41 (0x29)
		// @70: invokevirtual java.lang.StringBuilder.append(char)java.lang.StringBuilder
		// @73: invokevirtual java.lang.StringBuilder.toString()java.lang.String
		// @76: invokestatic game.C_100181_cf.func_105695_a(java.lang.Throwable, java.lang.String)game.C_100170_cm
		// @79: athrow
	}
	
	final boolean func_102506_a(char arg0, int arg1, int arg2, C_100336_im arg3)
	{
		// @00: aconst_null
		// @01: aload_0
		// @02: getfield game.C_100336_im game.C_100030_gm.field_103351_J
		// @05: if_acmpeq @2F
		// @08: aload_0
		// @09: getfield game.C_100336_im game.C_100030_gm.field_103351_J
		// @0C: bipush 58 (0x3A)
		// @0E: invokevirtual game.C_100336_im.func_102515_d(byte)boolean
		// @11: ifeq @2F
		// @14: goto @18
		// @17: athrow
		// @18: aload_0
		// @19: getfield game.C_100336_im game.C_100030_gm.field_103351_J
		// @1C: iload_1
		// @1D: iload_2
		// @1E: sipush 22545 (0x5811)
		// @21: aload #4
		// @23: invokevirtual game.C_100336_im.func_102506_a(char, int, int, game.C_100336_im)boolean
		// @26: ifeq @2F
		// @29: goto @2D
		// @2C: athrow
		// @2D: iconst_1
		// @2E: ireturn
		// @2F: iload_2
		// @30: istore #5
		// @32: iload #5
		// @34: bipush 80 (0x50)
		// @36: if_icmpeq @3D
		// @39: goto @5A
		// @3C: athrow
		// @3D: getstatic boolean[] game.C_100309_lk.field_103258_hb
		// @40: bipush 81 (0x51)
		// @42: baload
		// @43: ifne @51
		// @46: aload_0
		// @47: aload #4
		// @49: iconst_1
		// @4A: invokespecial game.C_100030_gm.func_103332_a(game.C_100336_im, boolean)boolean
		// @4D: goto @59
		// @50: athrow
		// @51: aload_0
		// @52: aload #4
		// @54: bipush 64 (0x40)
		// @56: invokespecial game.C_100030_gm.func_103331_a(game.C_100336_im, byte)boolean
		// @59: ireturn
		// @5A: iload_3
		// @5B: sipush 22545 (0x5811)
		// @5E: if_icmpeq @6C
		// @61: aload_0
		// @62: bipush -42 (0xD6)
		// @64: invokevirtual game.C_100030_gm.func_103339_j(int)game.C_100336_im
		// @67: pop
		// @68: goto @6C
		// @6B: athrow
		// @6C: iconst_0
		// @6D: ireturn
		// @6E: astore #5
		// @70: aload #5
		// @72: new java.lang.StringBuilder
		// @75: dup
		// @76: invokespecial java.lang.StringBuilder.<init>()void
		// @79: getstatic java.lang.String[] game.C_100030_gm.field_103348_O
		// @7C: iconst_2
		// @7D: aaload
		// @7E: invokevirtual java.lang.StringBuilder.append(java.lang.String)java.lang.StringBuilder
		// @81: iload_1
		// @82: invokevirtual java.lang.StringBuilder.append(char)java.lang.StringBuilder
		// @85: bipush 44 (0x2C)
		// @87: invokevirtual java.lang.StringBuilder.append(char)java.lang.StringBuilder
		// @8A: iload_2
		// @8B: invokevirtual java.lang.StringBuilder.append(int)java.lang.StringBuilder
		// @8E: bipush 44 (0x2C)
		// @90: invokevirtual java.lang.StringBuilder.append(char)java.lang.StringBuilder
		// @93: iload_3
		// @94: invokevirtual java.lang.StringBuilder.append(int)java.lang.StringBuilder
		// @97: bipush 44 (0x2C)
		// @99: invokevirtual java.lang.StringBuilder.append(char)java.lang.StringBuilder
		// @9C: aload #4
		// @9E: ifnull @AA
		// @A1: getstatic java.lang.String[] game.C_100030_gm.field_103348_O
		// @A4: iconst_3
		// @A5: aaload
		// @A6: goto @AF
		// @A9: athrow
		// @AA: getstatic java.lang.String[] game.C_100030_gm.field_103348_O
		// @AD: iconst_1
		// @AE: aaload
		// @AF: invokevirtual java.lang.StringBuilder.append(java.lang.String)java.lang.StringBuilder
		// @B2: bipush 41 (0x29)
		// @B4: invokevirtual java.lang.StringBuilder.append(char)java.lang.StringBuilder
		// @B7: invokevirtual java.lang.StringBuilder.toString()java.lang.String
		// @BA: invokestatic game.C_100181_cf.func_105695_a(java.lang.Throwable, java.lang.String)game.C_100170_cm
		// @BD: athrow
	}
	
	final void func_103333_a(Hashtable arg0, int arg1, int arg2, StringBuilder arg3)
	{
		// @00: getstatic int game.SteelSentinels.field_105275_O
		// @03: istore #6
		// @05: aload #4
		// @07: bipush 10 (0x0A)
		// @09: invokevirtual java.lang.StringBuilder.append(char)java.lang.StringBuilder
		// @0C: pop
		// @0D: iconst_0
		// @0E: istore #5
		// @10: iload_3
		// @11: iconst_m1
		// @12: ixor
		// @13: iload #5
		// @15: iconst_m1
		// @16: ixor
		// @17: if_icmpgt @33
		// @1A: aload #4
		// @1C: bipush 32 (0x20)
		// @1E: invokevirtual java.lang.StringBuilder.append(char)java.lang.StringBuilder
		// @21: pop
		// @22: iinc #5 +1
		// @25: iload #6
		// @27: ifne @4E
		// @2A: iload #6
		// @2C: ifeq @10
		// @2F: goto @33
		// @32: athrow
		// @33: aload_0
		// @34: getfield game.C_100336_im game.C_100030_gm.field_103351_J
		// @37: ifnonnull @4E
		// @3A: aload #4
		// @3C: getstatic java.lang.String[] game.C_100030_gm.field_103348_O
		// @3F: iconst_1
		// @40: aaload
		// @41: invokevirtual java.lang.StringBuilder.append(java.lang.String)java.lang.StringBuilder
		// @44: pop
		// @45: iload #6
		// @47: ifeq @5E
		// @4A: goto @4E
		// @4D: athrow
		// @4E: aload_0
		// @4F: getfield game.C_100336_im game.C_100030_gm.field_103351_J
		// @52: iload_3
		// @53: iconst_1
		// @54: iadd
		// @55: bipush 27 (0x1B)
		// @57: aload #4
		// @59: aload_1
		// @5A: invokevirtual game.C_100336_im.func_102510_a(int, byte, java.lang.StringBuilder, java.util.Hashtable)java.lang.StringBuilder
		// @5D: pop
		// @5E: iload_2
		// @5F: iconst_1
		// @60: if_icmpeq @71
		// @63: aconst_null
		// @64: checkcast java.lang.String[][]
		// @67: checkcast java.lang.String[][]
		// @6A: putstatic java.lang.String[][] game.C_100030_gm.field_103347_N
		// @6D: goto @71
		// @70: athrow
		// @71: goto @D6
		// @74: astore #5
		// @76: aload #5
		// @78: new java.lang.StringBuilder
		// @7B: dup
		// @7C: invokespecial java.lang.StringBuilder.<init>()void
		// @7F: getstatic java.lang.String[] game.C_100030_gm.field_103348_O
		// @82: bipush 23 (0x17)
		// @84: aaload
		// @85: invokevirtual java.lang.StringBuilder.append(java.lang.String)java.lang.StringBuilder
		// @88: aload_1
		// @89: ifnull @95
		// @8C: getstatic java.lang.String[] game.C_100030_gm.field_103348_O
		// @8F: iconst_3
		// @90: aaload
		// @91: goto @9A
		// @94: athrow
		// @95: getstatic java.lang.String[] game.C_100030_gm.field_103348_O
		// @98: iconst_1
		// @99: aaload
		// @9A: invokevirtual java.lang.StringBuilder.append(java.lang.String)java.lang.StringBuilder
		// @9D: bipush 44 (0x2C)
		// @9F: invokevirtual java.lang.StringBuilder.append(char)java.lang.StringBuilder
		// @A2: iload_2
		// @A3: invokevirtual java.lang.StringBuilder.append(int)java.lang.StringBuilder
		// @A6: bipush 44 (0x2C)
		// @A8: invokevirtual java.lang.StringBuilder.append(char)java.lang.StringBuilder
		// @AB: iload_3
		// @AC: invokevirtual java.lang.StringBuilder.append(int)java.lang.StringBuilder
		// @AF: bipush 44 (0x2C)
		// @B1: invokevirtual java.lang.StringBuilder.append(char)java.lang.StringBuilder
		// @B4: aload #4
		// @B6: ifnull @C2
		// @B9: getstatic java.lang.String[] game.C_100030_gm.field_103348_O
		// @BC: iconst_3
		// @BD: aaload
		// @BE: goto @C7
		// @C1: athrow
		// @C2: getstatic java.lang.String[] game.C_100030_gm.field_103348_O
		// @C5: iconst_1
		// @C6: aaload
		// @C7: invokevirtual java.lang.StringBuilder.append(java.lang.String)java.lang.StringBuilder
		// @CA: bipush 41 (0x29)
		// @CC: invokevirtual java.lang.StringBuilder.append(char)java.lang.StringBuilder
		// @CF: invokevirtual java.lang.StringBuilder.toString()java.lang.String
		// @D2: invokestatic game.C_100181_cf.func_105695_a(java.lang.Throwable, java.lang.String)game.C_100170_cm
		// @D5: athrow
		// @D6: return
	}
	
	static
	{
		// @000: bipush 25 (0x19)
		// @002: anewarray java.lang.String
		// @005: dup
		// @006: iconst_0
		// @007: ldc ">hK\u0019nq"
		// @009: invokestatic game.C_100030_gm.func_103337_z(java.lang.String)char[]
		// @00C: invokestatic game.C_100030_gm.func_103330_z(char[])java.lang.String
		// @00F: aastore
		// @010: dup
		// @011: iconst_1
		// @012: ldc "7p\t;"
		// @014: invokestatic game.C_100030_gm.func_103337_z(java.lang.String)char[]
		// @017: invokestatic game.C_100030_gm.func_103330_z(char[])java.lang.String
		// @01A: aastore
		// @01B: dup
		// @01C: iconst_2
		// @01D: ldc ">hK\u0011nq"
		// @01F: invokestatic game.C_100030_gm.func_103337_z(java.lang.String)char[]
		// @022: invokestatic game.C_100030_gm.func_103330_z(char[])java.lang.String
		// @025: aastore
		// @026: dup
		// @027: iconst_3
		// @028: ldc "\"+KyR"
		// @02A: invokestatic game.C_100030_gm.func_103337_z(java.lang.String)char[]
		// @02D: invokestatic game.C_100030_gm.func_103330_z(char[])java.lang.String
		// @030: aastore
		// @031: dup
		// @032: iconst_4
		// @033: ldc ">hK\u001anq"
		// @035: invokestatic game.C_100030_gm.func_103337_z(java.lang.String)char[]
		// @038: invokestatic game.C_100030_gm.func_103330_z(char[])java.lang.String
		// @03B: aastore
		// @03C: dup
		// @03D: iconst_5
		// @03E: ldc ">hK\u0001\u0007"
		// @040: invokestatic game.C_100030_gm.func_103337_z(java.lang.String)char[]
		// @043: invokestatic game.C_100030_gm.func_103330_z(char[])java.lang.String
		// @046: aastore
		// @047: dup
		// @048: bipush 6 (0x06)
		// @04A: ldc ">hK\u0014\u0007"
		// @04C: invokestatic game.C_100030_gm.func_103337_z(java.lang.String)char[]
		// @04F: invokestatic game.C_100030_gm.func_103330_z(char[])java.lang.String
		// @052: aastore
		// @053: dup
		// @054: bipush 7 (0x07)
		// @056: ldc ">hK\u0013nq"
		// @058: invokestatic game.C_100030_gm.func_103337_z(java.lang.String)char[]
		// @05B: invokestatic game.C_100030_gm.func_103330_z(char[])java.lang.String
		// @05E: aastore
		// @05F: dup
		// @060: bipush 8 (0x08)
		// @062: ldc ">hK\u0005\u0007"
		// @064: invokestatic game.C_100030_gm.func_103337_z(java.lang.String)char[]
		// @067: invokestatic game.C_100030_gm.func_103330_z(char[])java.lang.String
		// @06A: aastore
		// @06B: dup
		// @06C: bipush 9 (0x09)
		// @06E: ldc ">hK\u0006\u0007"
		// @070: invokestatic game.C_100030_gm.func_103337_z(java.lang.String)char[]
		// @073: invokestatic game.C_100030_gm.func_103330_z(char[])java.lang.String
		// @076: aastore
		// @077: dup
		// @078: bipush 10 (0x0A)
		// @07A: ldc ">hK\u001enq"
		// @07C: invokestatic game.C_100030_gm.func_103337_z(java.lang.String)char[]
		// @07F: invokestatic game.C_100030_gm.func_103330_z(char[])java.lang.String
		// @082: aastore
		// @083: dup
		// @084: bipush 11 (0x0B)
		// @086: ldc ">hK\u0012nq"
		// @088: invokestatic game.C_100030_gm.func_103337_z(java.lang.String)char[]
		// @08B: invokestatic game.C_100030_gm.func_103330_z(char[])java.lang.String
		// @08E: aastore
		// @08F: dup
		// @090: bipush 12 (0x0C)
		// @092: ldc ">hK\u0011\u0007"
		// @094: invokestatic game.C_100030_gm.func_103337_z(java.lang.String)char[]
		// @097: invokestatic game.C_100030_gm.func_103330_z(char[])java.lang.String
		// @09A: aastore
		// @09B: dup
		// @09C: bipush 13 (0x0D)
		// @09E: ldc ">hK\u0004\u0007"
		// @0A0: invokestatic game.C_100030_gm.func_103337_z(java.lang.String)char[]
		// @0A3: invokestatic game.C_100030_gm.func_103330_z(char[])java.lang.String
		// @0A6: aastore
		// @0A7: dup
		// @0A8: bipush 14 (0x0E)
		// @0AA: ldc ">hK\u001cnq"
		// @0AC: invokestatic game.C_100030_gm.func_103337_z(java.lang.String)char[]
		// @0AF: invokestatic game.C_100030_gm.func_103330_z(char[])java.lang.String
		// @0B2: aastore
		// @0B3: dup
		// @0B4: bipush 15 (0x0F)
		// @0B6: ldc ">hK\u0014nq"
		// @0B8: invokestatic game.C_100030_gm.func_103337_z(java.lang.String)char[]
		// @0BB: invokestatic game.C_100030_gm.func_103330_z(char[])java.lang.String
		// @0BE: aastore
		// @0BF: dup
		// @0C0: bipush 16 (0x10)
		// @0C2: ldc ">hK\u0010nq"
		// @0C4: invokestatic game.C_100030_gm.func_103337_z(java.lang.String)char[]
		// @0C7: invokestatic game.C_100030_gm.func_103330_z(char[])java.lang.String
		// @0CA: aastore
		// @0CB: dup
		// @0CC: bipush 17 (0x11)
		// @0CE: ldc ">hK\u001dnq"
		// @0D0: invokestatic game.C_100030_gm.func_103337_z(java.lang.String)char[]
		// @0D3: invokestatic game.C_100030_gm.func_103330_z(char[])java.lang.String
		// @0D6: aastore
		// @0D7: dup
		// @0D8: bipush 18 (0x12)
		// @0DA: ldc ">hK\u0016nq"
		// @0DC: invokestatic game.C_100030_gm.func_103337_z(java.lang.String)char[]
		// @0DF: invokestatic game.C_100030_gm.func_103330_z(char[])java.lang.String
		// @0E2: aastore
		// @0E3: dup
		// @0E4: bipush 19 (0x13)
		// @0E6: ldc ">hK\u0003\u0007"
		// @0E8: invokestatic game.C_100030_gm.func_103337_z(java.lang.String)char[]
		// @0EB: invokestatic game.C_100030_gm.func_103330_z(char[])java.lang.String
		// @0EE: aastore
		// @0EF: dup
		// @0F0: bipush 20 (0x14)
		// @0F2: ldc ">hK\u001fnq"
		// @0F4: invokestatic game.C_100030_gm.func_103337_z(java.lang.String)char[]
		// @0F7: invokestatic game.C_100030_gm.func_103330_z(char[])java.lang.String
		// @0FA: aastore
		// @0FB: dup
		// @0FC: bipush 21 (0x15)
		// @0FE: ldc ">hK\u0000\u0007"
		// @100: invokestatic game.C_100030_gm.func_103337_z(java.lang.String)char[]
		// @103: invokestatic game.C_100030_gm.func_103330_z(char[])java.lang.String
		// @106: aastore
		// @107: dup
		// @108: bipush 22 (0x16)
		// @10A: ldc ">hK\u0002\u0007"
		// @10C: invokestatic game.C_100030_gm.func_103337_z(java.lang.String)char[]
		// @10F: invokestatic game.C_100030_gm.func_103330_z(char[])java.lang.String
		// @112: aastore
		// @113: dup
		// @114: bipush 23 (0x17)
		// @116: ldc ">hK\u0015nq"
		// @118: invokestatic game.C_100030_gm.func_103337_z(java.lang.String)char[]
		// @11B: invokestatic game.C_100030_gm.func_103330_z(char[])java.lang.String
		// @11E: aastore
		// @11F: dup
		// @120: bipush 24 (0x18)
		// @122: ldc ">hK\u001bnq"
		// @124: invokestatic game.C_100030_gm.func_103337_z(java.lang.String)char[]
		// @127: invokestatic game.C_100030_gm.func_103330_z(char[])java.lang.String
		// @12A: aastore
		// @12B: putstatic java.lang.String[] game.C_100030_gm.field_103348_O
		// @12E: ldc "\u0000j\u0010wK6%\u000b8[ym\u0004!JydE$Z0q\u00045C<%\u000b\"B;`\u0017w@?%\u0015;N `\u0017$\u000f?j\u0017w[1`E4Z+w\u00009[yj\u0015#F6k\u0016y"
		// @130: invokestatic game.C_100030_gm.func_103337_z(java.lang.String)char[]
		// @133: invokestatic game.C_100030_gm.func_103330_z(char[])java.lang.String
		// @136: putstatic java.lang.String game.C_100030_gm.field_103352_K
		// @139: bipush 10 (0x0A)
		// @13B: anewarray java.lang.String[]
		// @13E: dup
		// @13F: iconst_0
		// @140: bipush 24 (0x18)
		// @142: anewarray java.lang.String
		// @145: dup
		// @146: iconst_0
		// @147: aconst_null
		// @148: aastore
		// @149: dup
		// @14A: iconst_1
		// @14B: aconst_null
		// @14C: aastore
		// @14D: dup
		// @14E: iconst_2
		// @14F: ldc "\rd\u0015w[1`Epu~%\u000e2Vyq\nw[<i\twV6p\u0017w\\<k\u0011>A<iE#@yv\u00116]-%\u00088Y0k\u0002wC<c\u0011y"
		// @151: invokestatic game.C_100030_gm.func_103337_z(java.lang.String)char[]
		// @154: invokestatic game.C_100030_gm.func_103330_z(char[])java.lang.String
		// @157: aastore
		// @158: dup
		// @159: iconst_3
		// @15A: ldc "\tw\u0000$\\y\"?p\u000f6k\u00062\u000f-jE$[8w\u0011wB6s\u000c9Hyi\u00001[w"
		// @15C: invokestatic game.C_100030_gm.func_103337_z(java.lang.String)char[]
		// @15F: invokestatic game.C_100030_gm.func_103330_z(char[])java.lang.String
		// @162: aastore
		// @163: dup
		// @164: iconst_4
		// @165: ldc "\nl\u000b4Jy|\n\"\u000f8w\u0000w]<h\n#J5|E'F5j\u0011>A>%\u001c8Z+%\u00162A-l\u000b2Cu%\u0011?J+`E>\\ydE$G6w\u0011wK<i\u0004.\u000f;`\u0011 J<kE G<kE.@,%\u000c$\\,`E6Ayj\u00173J+%\u00049Kyr\r2Ayq\r2\u000f*`\u000b#F7`\tw]<f\u0000>Y<vE6A=%\u00044[*%\u0010'@7%\u000c#\u0001y9\u0007%\u0011\rd\u0015w[1`Epl~%\u000e2Vyq\nwF7v\u0011%Z:qE.@,wE$J7q\u000c9J5%\u00118\u000f*q\u0004%[yh\n!F7bE%F>m\u0011y"
		// @167: invokestatic game.C_100030_gm.func_103337_z(java.lang.String)char[]
		// @16A: invokestatic game.C_100030_gm.func_103330_z(char[])java.lang.String
		// @16D: aastore
		// @16E: dup
		// @16F: iconst_5
		// @170: ldc "\tw\u0000$\\y\"&p\u000f6k\u00062\u000f-jE$[8w\u0011wB6s\u000c9Hyw\u000c0G-+"
		// @172: invokestatic game.C_100030_gm.func_103337_z(java.lang.String)char[]
		// @175: invokestatic game.C_100030_gm.func_103330_z(char[])java.lang.String
		// @178: aastore
		// @179: dup
		// @17A: bipush 6 (0x06)
		// @17C: ldc "\u0010kE#G<%\u00045\\<k\u00062\u000f6cE8[1`\u0017w@+a\u0000%\\u%\u001c8Z+%\u00162A-l\u000b2Cyr\u000c;Cyf\u0004%] %\n9\u000f.d\t<F7bKw\u007f+`\u0016$\u000f~]Bw[6%\u00112C5%\u000c#\u000f-jE?N5qK"
		// @17E: invokestatic game.C_100030_gm.func_103337_z(java.lang.String)char[]
		// @181: invokestatic game.C_100030_gm.func_103330_z(char[])java.lang.String
		// @184: aastore
		// @185: dup
		// @186: bipush 7 (0x07)
		// @188: ldc "\tw\u0000$\\y\"=p\u000f-jE$[6uE:@/l\u000b0\u0001"
		// @18A: invokestatic game.C_100030_gm.func_103337_z(java.lang.String)char[]
		// @18D: invokestatic game.C_100030_gm.func_103330_z(char[])java.lang.String
		// @190: aastore
		// @191: dup
		// @192: bipush 8 (0x08)
		// @194: ldc "\u0018qE#G<%\u00078[-j\u0008w@?%\u001c8Z+%\u00164]<`\u000bwF*%\u0011?Jyh\u000c9F4d\u0015y\u000f\rm\u000c$\u000f*m\n \\yq\r2\u000f5j\u00066[0j\u000b$\u000f6cE$J7q\u000c9J5vE8Ayq\r2\u000f;d\u0011#C<c\u000c2C=+E\u0003G<%\u0007;Z<%\u0006>]:i\u0000wF*%\u001c8Z+%\u00162A-l\u000b2Cu%\u00049Kyq\r2\u000f?i\u0004$G0k\u0002w]<aE4F+f\t2\u000f0vE6\u000f-w\u0004>A0k\u0002wK+j\u000b2\u0001yR\u0004;Dy|\n\"]yv\u00009[0k\u0000;\u000f-jE#G<%\u0011%N0k\u000c9Hya\u00178A<%\u00049Kyv\u00118_yd\u0016wL5j\u00162\u000f-jE>[yd\u0016w_6v\u0016>M5`K"
		// @196: invokestatic game.C_100030_gm.func_103337_z(java.lang.String)char[]
		// @199: invokestatic game.C_100030_gm.func_103330_z(char[])java.lang.String
		// @19C: aastore
		// @19D: dup
		// @19E: bipush 9 (0x09)
		// @1A0: ldc "\u000cv\u0000w\u0008\u0003\"Iw\u0008\u0001\"Iw\u0008\u001a\"E#@yu\n$F-l\n9\u000f j\u0010%\u000f*`\u000b#F7`\twN-%\u0011?Jyq\u00176F7l\u000b0\u000f=w\n9Jw"
		// @1A2: invokestatic game.C_100030_gm.func_103337_z(java.lang.String)char[]
		// @1A5: invokestatic game.C_100030_gm.func_103330_z(char[])java.lang.String
		// @1A8: aastore
		// @1A9: dup
		// @1AA: bipush 10 (0x0A)
		// @1AC: ldc "\u0000j\u0010wL8kE:@/`E#G<%\u00066B<w\u0004wX0q\rw[1`Epx~)B\u0016\u0008u\"6p\u000f8k\u0001w\u0008\u001d\"E<J vKw{1`E5Z-q\n9\u000f6kE#G<%\u0017>H1qE8I?`\u0017$\u000f*j\u00082\u000f6u\u0011>@7vE1@+%\u0006?N7b\u000c9Hyq\r2\u000f:j\u000b#]6i\u0016y\u0013;w[\u0003] %\u0011?J4%\n\"[yd\u000b3\u000f:m\n8\\<%\u0011?Jyj\u000b2\u000f j\u0010w_+`\u00032]w"
		// @1AE: invokestatic game.C_100030_gm.func_103337_z(java.lang.String)char[]
		// @1B1: invokestatic game.C_100030_gm.func_103330_z(char[])java.lang.String
		// @1B4: aastore
		// @1B5: dup
		// @1B6: bipush 11 (0x0B)
		// @1B8: aconst_null
		// @1B9: aastore
		// @1BA: dup
		// @1BB: bipush 12 (0x0C)
		// @1BD: ldc "\rm\u0000w|5d\u00132\u000f8i\u00168\u000f1d\u0016w[1`E6M0i\u000c#Vyq\nwE,h\u0015y\u000f\rjE>A*q\u0017\"L-%\u001c8Z+%\u00162A-l\u000b2Cyq\nwE,h\u0015{\u000f1j\t3\u000f~V-\u001ei\r\"E6A=%\t2I-(\u0006;F:nE6M6s\u0000wV6p\u0017w\\<k\u0011>A<iK"
		// @1BF: invokestatic game.C_100030_gm.func_103337_z(java.lang.String)char[]
		// @1C2: invokestatic game.C_100030_gm.func_103330_z(char[])java.lang.String
		// @1C5: aastore
		// @1C6: dup
		// @1C7: bipush 13 (0x0D)
		// @1C9: ldc "\u000cv\u0000w\u0008\nM,\u0011{~%\u00049Kyi\u00001[tf\t>L2%\u00118\u000f3p\u0008'\u0001"
		// @1CB: invokestatic game.C_100030_gm.func_103337_z(java.lang.String)char[]
		// @1CE: invokestatic game.C_100030_gm.func_103330_z(char[])java.lang.String
		// @1D1: aastore
		// @1D2: dup
		// @1D3: bipush 14 (0x0E)
		// @1D5: ldc "\u000em\u000c;Jy|\n\"\u000f1j\t3\u000f~V-\u001ei\r\"Iw[1`E']6o\u00004[<aE'N-mE8Iy|\n\"]yo\u0010:_yl\u0016wK0v\u0015;N `\u0001w@7%\u001c8Z+%\u00164]<`\u000by\u000f\rm\u000c$\u000f8i\t8X*%\u001c8Zyq\nwN0hE.@,wE=Z4uE']<f\u000c$J5|E5Vyh\n!F7bE#G<%\u00088Z*`KkM+;1?J+`E6]<%\u000b8Xyq\r%J<%\u0001%@7`\u0016wF7%\u0000;J/d\u00112Kyu\n$F-l\n9\\yj\u000bw[1`E5N-q\t2I0`\t3\u0001yW\u00006L1%\u0011?J4%\u0004;Cyg\u001cwE,h\u0015>A>+"
		// @1D7: invokestatic game.C_100030_gm.func_103337_z(java.lang.String)char[]
		// @1DA: invokestatic game.C_100030_gm.func_103330_z(char[])java.lang.String
		// @1DD: aastore
		// @1DE: dup
		// @1DF: bipush 15 (0x0F)
		// @1E1: ldc "\u0011j\t3\u000f~V-\u001ei\r\"E6A=%\u00088Y<%\u0011?Jyh\n\"\\<%\u00118\u000f)i\u00049\u000f-m\u0000w[+d\u000f2L-j\u0017.\u000f6cE.@,wE=Z4uKkM+;72N:mE6C5%\u0011?Jya\u00178A<vE5Vyo\u0010:_0k\u0002y"
		// @1E3: invokestatic game.C_100030_gm.func_103337_z(java.lang.String)char[]
		// @1E6: invokestatic game.C_100030_gm.func_103330_z(char[])java.lang.String
		// @1E9: aastore
		// @1EA: dup
		// @1EB: bipush 16 (0x10)
		// @1ED: aconst_null
		// @1EE: aastore
		// @1EF: dup
		// @1F0: bipush 17 (0x11)
		// @1F2: aconst_null
		// @1F3: aastore
		// @1F4: dup
		// @1F5: bipush 18 (0x12)
		// @1F7: aconst_null
		// @1F8: aastore
		// @1F9: dup
		// @1FA: bipush 19 (0x13)
		// @1FC: aconst_null
		// @1FD: aastore
		// @1FE: dup
		// @1FF: bipush 20 (0x14)
		// @201: ldc "\nj\u00082\u000f4j\u0007>C<%\u0001%@7`\u0016wG8s\u0000wM<`\u000bw_5d\u00062Kyj\u000bw[1`E#]8l\u000b>A>%\u0003>J5aKwk<v\u0011%@ %\u0011?J4%\u0004;Cw%.2J)%\u000c9\u000f4l\u000b3\u000f-m\u0004#\u000f j\u0010%\u000f>p\u000b$\u000f1d\u00132\u000f8%\t>B0q\u00003\u000f+d\u000b0Jyd\u000b3\u000f8%\u00172\\-w\u000c4[<aE1F+l\u000b0\u000f8w\u0006y\u0013;w[\u0005J4`\u00085J+)E.@,%\u00066Ayh\n!Jy|\n\"]yv\u00009[0k\u0000;\u000f-jE6\u000f;`\u0011#J+%\u00158\\0q\u000c8Ayp\u0016>A>%\u0011?Jyh\n!Jyn\u0000.\\y-B\r\u0008u%B\u000f\u0008u%B\u0014\u0008p%\n%\u000f;|E=Z4u\u000c9Hy-B\u0004g\u0010C1p\u000f8k\u0001wL5l\u0006<\u0006w"
		// @203: invokestatic game.C_100030_gm.func_103337_z(java.lang.String)char[]
		// @206: invokestatic game.C_100030_gm.func_103330_z(char[])java.lang.String
		// @209: aastore
		// @20A: dup
		// @20B: bipush 21 (0x15)
		// @20D: aconst_null
		// @20E: aastore
		// @20F: dup
		// @210: bipush 22 (0x16)
		// @212: aconst_null
		// @213: aastore
		// @214: dup
		// @215: bipush 23 (0x17)
		// @217: aconst_null
		// @218: aastore
		// @219: aastore
		// @21A: dup
		// @21B: iconst_1
		// @21C: bipush 30 (0x1E)
		// @21E: anewarray java.lang.String
		// @221: dup
		// @222: iconst_0
		// @223: aconst_null
		// @224: aastore
		// @225: dup
		// @226: iconst_1
		// @227: aconst_null
		// @228: aastore
		// @229: dup
		// @22A: iconst_2
		// @22B: aconst_null
		// @22C: aastore
		// @22D: dup
		// @22E: iconst_3
		// @22F: aconst_null
		// @230: aastore
		// @231: dup
		// @232: iconst_4
		// @233: aconst_null
		// @234: aastore
		// @235: dup
		// @236: iconst_5
		// @237: aconst_null
		// @238: aastore
		// @239: dup
		// @23A: bipush 6 (0x06)
		// @23C: aconst_null
		// @23D: aastore
		// @23E: dup
		// @23F: bipush 7 (0x07)
		// @241: aconst_null
		// @242: aastore
		// @243: dup
		// @244: bipush 8 (0x08)
		// @246: aconst_null
		// @247: aastore
		// @248: dup
		// @249: bipush 9 (0x09)
		// @24B: aconst_null
		// @24C: aastore
		// @24D: dup
		// @24E: bipush 10 (0x0A)
		// @250: ldc "\rm\u0000%Jyl\u0016w@7`E:@+`E3]6k\u0000{\u000f6kE#G<%\t2I-%\r6A=%\u0016>K<%\n1\u000f-m\u0000wM8q\u0011;J?l\u0000;Kw%64]6i\twC<c\u0011w\u0007;|E']<v\u0016>A>%B\u0016\u0008p%\u00118\u000f?l\u000b3\u000f0qK"
		// @252: invokestatic game.C_100030_gm.func_103337_z(java.lang.String)char[]
		// @255: invokestatic game.C_100030_gm.func_103330_z(char[])java.lang.String
		// @258: aastore
		// @259: dup
		// @25A: bipush 11 (0x0B)
		// @25C: ldc "\tw\u0000$\\y\"$p\u000f-jE:@/`E#G<%\u00066B<w\u0004wC<c\u0011y"
		// @25E: invokestatic game.C_100030_gm.func_103337_z(java.lang.String)char[]
		// @261: invokestatic game.C_100030_gm.func_103330_z(char[])java.lang.String
		// @264: aastore
		// @265: dup
		// @266: bipush 12 (0x0C)
		// @268: ldc "\u000em\u00009\u000f j\u0010%\u000f*`\u000b#F7`\twF*%\n1Itv\u0006%J<kIw[1`E>A*`\u0011wK0v\u0015;N %\u0004'_<d\u0017$\u000f8qE#G<%\u00164]<`\u000bwJ=b\u0000wL5j\u00162\\-%\u00118\u000f j\u0010%\u000f*`\u000b#F7`\t{\u000f-jE%J4l\u000b3\u000f j\u0010wX1`\u00172\u000f j\u0010%\u000f*`\u000b#F7`\twF*+E\u0002\\<%B\u0000\u0008u\"$p\u0003~VB{\u0008\u001d\"E#@yh\n!Jyq\r2\u000f:d\u00082]8%\u0004%@,k\u0001{\u000f8k\u0001w[1`E?F>m\t>H1q\u00003\u000f;j\u001dw@7%\u001c8Z+%\u0008>A0h\u0004'\u000f*m\n \\yr\r6[yu\u0004%[yj\u0003w[1`E5N-q\t2I0`\t3\u000f j\u0010wN+`E4Z+w\u00009[5|E!F<r\u000c9Hw"
		// @26A: invokestatic game.C_100030_gm.func_103337_z(java.lang.String)char[]
		// @26D: invokestatic game.C_100030_gm.func_103330_z(char[])java.lang.String
		// @270: aastore
		// @271: dup
		// @272: bipush 13 (0x0D)
		// @274: ldc "\u000cv\u0000w\u0008\u000e\"Ipn~)B\u0004\u0008u\"!p\u000f-jE:@/`E#G<%\u00066B<w\u0004wN+j\u00109Kw"
		// @276: invokestatic game.C_100030_gm.func_103337_z(java.lang.String)char[]
		// @279: invokestatic game.C_100030_gm.func_103330_z(char[])java.lang.String
		// @27C: aastore
		// @27D: dup
		// @27E: bipush 14 (0x0E)
		// @280: aconst_null
		// @281: aastore
		// @282: dup
		// @283: bipush 15 (0x0F)
		// @285: aconst_null
		// @286: aastore
		// @287: dup
		// @288: bipush 16 (0x10)
		// @28A: aconst_null
		// @28B: aastore
		// @28C: dup
		// @28D: bipush 17 (0x11)
		// @28F: aconst_null
		// @290: aastore
		// @291: dup
		// @292: bipush 18 (0x12)
		// @294: aconst_null
		// @295: aastore
		// @296: dup
		// @297: bipush 19 (0x13)
		// @299: aconst_null
		// @29A: aastore
		// @29B: dup
		// @29C: bipush 20 (0x14)
		// @29E: aconst_null
		// @29F: aastore
		// @2A0: dup
		// @2A1: bipush 21 (0x15)
		// @2A3: aconst_null
		// @2A4: aastore
		// @2A5: dup
		// @2A6: bipush 22 (0x16)
		// @2A8: aconst_null
		// @2A9: aastore
		// @2AA: dup
		// @2AB: bipush 23 (0x17)
		// @2AD: aconst_null
		// @2AE: aastore
		// @2AF: dup
		// @2B0: bipush 24 (0x18)
		// @2B2: aconst_null
		// @2B3: aastore
		// @2B4: dup
		// @2B5: bipush 25 (0x19)
		// @2B7: aconst_null
		// @2B8: aastore
		// @2B9: dup
		// @2BA: bipush 26 (0x1A)
		// @2BC: aconst_null
		// @2BD: aastore
		// @2BE: dup
		// @2BF: bipush 27 (0x1B)
		// @2C1: aconst_null
		// @2C2: aastore
		// @2C3: dup
		// @2C4: bipush 28 (0x1C)
		// @2C6: aconst_null
		// @2C7: aastore
		// @2C8: dup
		// @2C9: bipush 29 (0x1D)
		// @2CB: aconst_null
		// @2CC: aastore
		// @2CD: aastore
		// @2CE: dup
		// @2CF: iconst_2
		// @2D0: aconst_null
		// @2D1: aastore
		// @2D2: dup
		// @2D3: iconst_3
		// @2D4: bipush 14 (0x0E)
		// @2D6: anewarray java.lang.String
		// @2D9: dup
		// @2DA: iconst_0
		// @2DB: aconst_null
		// @2DC: aastore
		// @2DD: dup
		// @2DE: iconst_1
		// @2DF: aconst_null
		// @2E0: aastore
		// @2E1: dup
		// @2E2: iconst_2
		// @2E3: ldc "\rjE#G+p\u0016#\u0003yp\u00162\u000f~V-\u001ei\r\"E6A=%\u0011?Jyh\n\"\\<%\u00118\u000f)`\u00171@+hE6\u000f3p\u0008'\u0001yQ\r2Au%\u0012?F5`E>Ayq\r2\u000f8l\u0017{\u000f1j\t3\u000f~V-\u001ei\r\"E6A=%\u000f\"B)%\u00040N0kK"
		// @2E5: invokestatic game.C_100030_gm.func_103337_z(java.lang.String)char[]
		// @2E8: invokestatic game.C_100030_gm.func_103330_z(char[])java.lang.String
		// @2EB: aastore
		// @2EC: dup
		// @2ED: iconst_3
		// @2EE: ldc "\u000cv\u0000w\u0008\nM,\u0011{~%\u00049Kyq\r2\u000f5`\u0003#\u000f4j\u0010$Jyg\u0010#[6kE G0i\u0000wF7%\u0011?Jyd\u000c%\u000f-jE#G+p\u0016#\u0001"
		// @2F0: invokestatic game.C_100030_gm.func_103337_z(java.lang.String)char[]
		// @2F3: invokestatic game.C_100030_gm.func_103330_z(char[])java.lang.String
		// @2F6: aastore
		// @2F7: dup
		// @2F8: iconst_4
		// @2F9: ldc "\u0017j\u0012{\u000f;|E#G+p\u0016#F7bE:Z5q\u000c'C<%\u0011>B<vIw[+|E6A=%\u0016#N %\u000c9\u000f-m\u0000wN0wE1@+%\u0004$\u000f5j\u000b0\u000f8vE'@*v\u000c5C<+"
		// @2FB: invokestatic game.C_100030_gm.func_103337_z(java.lang.String)char[]
		// @2FE: invokestatic game.C_100030_gm.func_103330_z(char[])java.lang.String
		// @301: aastore
		// @302: dup
		// @303: iconst_5
		// @304: ldc "\u000cv\u0000w\u0008\nM,\u0011{~%\u00049Kyq\r2\u000f5`\u0003#\u000f4j\u0010$Jyg\u0010#[6kE G0i\u0000wF7%\u0011?Jyd\u000c%\u000f-jE#G+p\u0016#\u0001"
		// @306: invokestatic game.C_100030_gm.func_103337_z(java.lang.String)char[]
		// @309: invokestatic game.C_100030_gm.func_103330_z(char[])java.lang.String
		// @30C: aastore
		// @30D: dup
		// @30E: bipush 6 (0x06)
		// @310: aconst_null
		// @311: aastore
		// @312: dup
		// @313: bipush 7 (0x07)
		// @315: aconst_null
		// @316: aastore
		// @317: dup
		// @318: bipush 8 (0x08)
		// @31A: aconst_null
		// @31B: aastore
		// @31C: dup
		// @31D: bipush 9 (0x09)
		// @31F: aconst_null
		// @320: aastore
		// @321: dup
		// @322: bipush 10 (0x0A)
		// @324: aconst_null
		// @325: aastore
		// @326: dup
		// @327: bipush 11 (0x0B)
		// @329: aconst_null
		// @32A: aastore
		// @32B: dup
		// @32C: bipush 12 (0x0C)
		// @32E: aconst_null
		// @32F: aastore
		// @330: dup
		// @331: bipush 13 (0x0D)
		// @333: aconst_null
		// @334: aastore
		// @335: aastore
		// @336: dup
		// @337: iconst_4
		// @338: aconst_null
		// @339: aastore
		// @33A: dup
		// @33B: iconst_5
		// @33C: aconst_null
		// @33D: aastore
		// @33E: dup
		// @33F: bipush 6 (0x06)
		// @341: aconst_null
		// @342: aastore
		// @343: dup
		// @344: bipush 7 (0x07)
		// @346: aconst_null
		// @347: aastore
		// @348: dup
		// @349: bipush 8 (0x08)
		// @34B: aconst_null
		// @34C: aastore
		// @34D: dup
		// @34E: bipush 9 (0x09)
		// @350: aconst_null
		// @351: aastore
		// @352: putstatic java.lang.String[][] game.C_100030_gm.field_103347_N
		// @355: ldc "\ti\u0004.\u000f?w\u00002\u000f/`\u0017$F6k"
		// @357: invokestatic game.C_100030_gm.func_103337_z(java.lang.String)char[]
		// @35A: invokestatic game.C_100030_gm.func_103330_z(char[])java.lang.String
		// @35D: putstatic java.lang.String game.C_100030_gm.field_103350_I
		// @360: ldc "\u0000j\u0010wB,v\u0011w_5d\u001cw\u0013|4[wB6w\u0000w]8q\u00003\u000f>d\u00082\\yg\u00001@+`E'C8|\u000c9Hyr\u000c#Gyq\r2\u000f:p\u0017%J7qE8_-l\n9\\w"
		// @362: invokestatic game.C_100030_gm.func_103337_z(java.lang.String)char[]
		// @365: invokestatic game.C_100030_gm.func_103330_z(char[])java.lang.String
		// @368: putstatic java.lang.String game.C_100030_gm.field_103345_L
		// @36B: ldc "\u001ck\u00112]ydE'N*v\u00128]=%\u00038]yq\r>\\yd\u00064@,k\u0011y\u000f\rw\u001cw[6%\u0015>L2%\u0004w\\-w\n9Hyu\u0004$\\.j\u00173\u000f-m\u0004#\u000f:d\u000bp[y`\u0004$F5|E5Jyb\u00102\\*`\u0001y"
		// @36D: invokestatic game.C_100030_gm.func_103337_z(java.lang.String)char[]
		// @370: invokestatic game.C_100030_gm.func_103330_z(char[])java.lang.String
		// @373: putstatic java.lang.String game.C_100030_gm.field_103346_M
		// @376: return
	}
	
	private static char[] func_103337_z(String arg0)
	{
		// @00: aload_0
		// @01: invokevirtual java.lang.String.toCharArray()char[]
		// @04: dup
		// @05: arraylength
		// @06: iconst_2
		// @07: if_icmpge @13
		// @0A: dup
		// @0B: iconst_0
		// @0C: dup2
		// @0D: caload
		// @0E: bipush 47 (0x2F)
		// @10: ixor
		// @11: i2c
		// @12: castore
		// @13: areturn
	}
	
	private static String func_103330_z(char[] arg0)
	{
		// @00: aload_0
		// @01: dup
		// @02: arraylength
		// @03: swap
		// @04: iconst_0
		// @05: istore_1
		// @06: goto @4B
		// @09: dup
		// @0A: iload_1
		// @0B: dup2
		// @0C: caload
		// @0D: iload_1
		// @0E: iconst_5
		// @0F: irem
		// @10: tableswitch def: @43, for 0: @30, for 1: @35, for 2: @39, for 3: @3E
		// @30: bipush 89 (0x59)
		// @32: goto @45
		// @35: iconst_5
		// @36: goto @45
		// @39: bipush 101 (0x65)
		// @3B: goto @45
		// @3E: bipush 87 (0x57)
		// @40: goto @45
		// @43: bipush 47 (0x2F)
		// @45: ixor
		// @46: i2c
		// @47: castore
		// @48: iinc #1 +1
		// @4B: swap
		// @4C: dup_x1
		// @4D: iload_1
		// @4E: if_icmpgt @09
		// @51: new java.lang.String
		// @54: dup_x1
		// @55: swap
		// @56: invokespecial java.lang.String.<init>(char[])void
		// @59: invokevirtual java.lang.String.intern()java.lang.String
		// @5C: areturn
	}
}
