package game;

final class C_100102_w
{
	static String field_104637_a;
	static C_100333_ij field_104631_f;
	static int field_104636_c;
	static int field_104648_u;
	static int field_104635_b;
	static String field_104651_r;
	static String field_104647_v;
	private int field_104641_m;
	private int field_104633_d;
	private int field_104642_j;
	private int field_104650_s;
	static C_100037_wb[] field_104655_y;
	private int field_104644_h;
	static C_100037_wb field_104639_o;
	static int field_104646_w;
	private C_100314_lf field_104653_p;
	private int field_104640_l;
	private int field_104656_x;
	private int field_104634_e;
	private int field_104643_k;
	static boolean field_104632_g;
	static C_100037_wb field_104638_n;
	private int field_104645_i;
	private int field_104652_q;
	private int field_104649_t;
	private static final String[] field_104654_z;
	
	static final void func_104623_a(int[] arg0, boolean arg1, int arg2)
	{
		// @00: getstatic int[][] game.C_100012_fh.field_100515_K
		// @03: iload_2
		// @04: aload_0
		// @05: aastore
		// @06: getstatic game.C_100034_gi[] game.C_100295_kh.field_105293_c
		// @09: iload_2
		// @0A: new game.C_100034_gi
		// @0D: dup
		// @0E: iload_2
		// @0F: invokespecial game.C_100034_gi.<init>(int)void
		// @12: aastore
		// @13: iload_1
		// @14: iconst_1
		// @15: if_icmpeq @1C
		// @18: iconst_1
		// @19: invokestatic game.C_100102_w.func_104628_a(boolean)void
		// @1C: goto @66
		// @1F: astore_3
		// @20: aload_3
		// @21: new java.lang.StringBuilder
		// @24: dup
		// @25: invokespecial java.lang.StringBuilder.<init>()void
		// @28: getstatic java.lang.String[] game.C_100102_w.field_104654_z
		// @2B: bipush 11 (0x0B)
		// @2D: aaload
		// @2E: invokevirtual java.lang.StringBuilder.append(java.lang.String)java.lang.StringBuilder
		// @31: aload_0
		// @32: ifnull @3F
		// @35: getstatic java.lang.String[] game.C_100102_w.field_104654_z
		// @38: bipush 9 (0x09)
		// @3A: aaload
		// @3B: goto @45
		// @3E: athrow
		// @3F: getstatic java.lang.String[] game.C_100102_w.field_104654_z
		// @42: bipush 10 (0x0A)
		// @44: aaload
		// @45: invokevirtual java.lang.StringBuilder.append(java.lang.String)java.lang.StringBuilder
		// @48: bipush 44 (0x2C)
		// @4A: invokevirtual java.lang.StringBuilder.append(char)java.lang.StringBuilder
		// @4D: iload_1
		// @4E: invokevirtual java.lang.StringBuilder.append(boolean)java.lang.StringBuilder
		// @51: bipush 44 (0x2C)
		// @53: invokevirtual java.lang.StringBuilder.append(char)java.lang.StringBuilder
		// @56: iload_2
		// @57: invokevirtual java.lang.StringBuilder.append(int)java.lang.StringBuilder
		// @5A: bipush 41 (0x29)
		// @5C: invokevirtual java.lang.StringBuilder.append(char)java.lang.StringBuilder
		// @5F: invokevirtual java.lang.StringBuilder.toString()java.lang.String
		// @62: invokestatic game.C_100181_cf.func_105695_a(java.lang.Throwable, java.lang.String)game.C_100170_cm
		// @65: athrow
		// @66: return
	}
	
	public static void func_104628_a(boolean arg0)
	{
		// @00: aconst_null
		// @01: putstatic game.C_100037_wb game.C_100102_w.field_104639_o
		// @04: aconst_null
		// @05: putstatic game.C_100037_wb game.C_100102_w.field_104638_n
		// @08: aconst_null
		// @09: putstatic java.lang.String game.C_100102_w.field_104647_v
		// @0C: iload_0
		// @0D: ifeq @19
		// @10: bipush 81 (0x51)
		// @12: invokestatic game.C_100102_w.func_104626_a(byte)void
		// @15: goto @19
		// @18: athrow
		// @19: aconst_null
		// @1A: putstatic java.lang.String game.C_100102_w.field_104651_r
		// @1D: aconst_null
		// @1E: putstatic game.C_100333_ij game.C_100102_w.field_104631_f
		// @21: aconst_null
		// @22: putstatic java.lang.String game.C_100102_w.field_104637_a
		// @25: aconst_null
		// @26: putstatic game.C_100037_wb[] game.C_100102_w.field_104655_y
		// @29: goto @4D
		// @2C: astore_1
		// @2D: aload_1
		// @2E: new java.lang.StringBuilder
		// @31: dup
		// @32: invokespecial java.lang.StringBuilder.<init>()void
		// @35: getstatic java.lang.String[] game.C_100102_w.field_104654_z
		// @38: iconst_1
		// @39: aaload
		// @3A: invokevirtual java.lang.StringBuilder.append(java.lang.String)java.lang.StringBuilder
		// @3D: iload_0
		// @3E: invokevirtual java.lang.StringBuilder.append(boolean)java.lang.StringBuilder
		// @41: bipush 41 (0x29)
		// @43: invokevirtual java.lang.StringBuilder.append(char)java.lang.StringBuilder
		// @46: invokevirtual java.lang.StringBuilder.toString()java.lang.String
		// @49: invokestatic game.C_100181_cf.func_105695_a(java.lang.Throwable, java.lang.String)game.C_100170_cm
		// @4C: athrow
		// @4D: return
	}
	
	final void func_104622_b(int arg0)
	{
		// @000: getstatic int game.SteelSentinels.field_105275_O
		// @003: istore_3
		// @004: iload_1
		// @005: bipush 17 (0x11)
		// @007: if_icmpeq @012
		// @00A: iconst_0
		// @00B: invokestatic game.C_100102_w.func_104628_a(boolean)void
		// @00E: goto @012
		// @011: athrow
		// @012: aload_0
		// @013: getfield int game.C_100102_w.field_104644_h
		// @016: iconst_m1
		// @017: ixor
		// @018: getstatic int game.C_100238_ol.field_101702_J
		// @01B: iconst_m1
		// @01C: ixor
		// @01D: if_icmpne @040
		// @020: aload_0
		// @021: getfield game.C_100314_lf game.C_100102_w.field_104653_p
		// @024: iconst_0
		// @025: putfield int game.C_100314_lf.field_101309_wb
		// @028: aload_0
		// @029: getfield game.C_100314_lf game.C_100102_w.field_104653_p
		// @02C: iconst_0
		// @02D: putfield int game.C_100314_lf.field_101295_gb
		// @030: aload_0
		// @031: getfield game.C_100314_lf game.C_100102_w.field_104653_p
		// @034: iconst_0
		// @035: putfield boolean game.C_100314_lf.field_101307_pb
		// @038: iload_3
		// @039: ifeq @2AB
		// @03C: goto @040
		// @03F: athrow
		// @040: aload_0
		// @041: getfield int game.C_100102_w.field_104644_h
		// @044: iconst_m1
		// @045: ixor
		// @046: getstatic int game.C_100151_bc.field_102940_Q
		// @049: iconst_m1
		// @04A: ixor
		// @04B: if_icmpeq @1DB
		// @04E: goto @052
		// @051: athrow
		// @052: getstatic int game.C_100001_ge.field_100574_i
		// @055: aload_0
		// @056: getfield int game.C_100102_w.field_104644_h
		// @059: if_icmpeq @19C
		// @05C: goto @060
		// @05F: athrow
		// @060: aload_0
		// @061: getfield int game.C_100102_w.field_104644_h
		// @064: iconst_m1
		// @065: ixor
		// @066: getstatic int game.C_100048_vi.field_104186_q
		// @069: iconst_m1
		// @06A: ixor
		// @06B: if_icmpeq @15C
		// @06E: goto @072
		// @071: athrow
		// @072: getstatic int game.C_100202_qi.field_105918_a
		// @075: iconst_m1
		// @076: ixor
		// @077: aload_0
		// @078: getfield int game.C_100102_w.field_104644_h
		// @07B: iconst_m1
		// @07C: ixor
		// @07D: if_icmpeq @088
		// @080: goto @084
		// @083: athrow
		// @084: goto @2AB
		// @087: athrow
		// @088: aload_0
		// @089: getfield game.C_100314_lf game.C_100102_w.field_104653_p
		// @08C: iconst_0
		// @08D: putfield int game.C_100314_lf.field_101295_gb
		// @090: aload_0
		// @091: getfield game.C_100314_lf game.C_100102_w.field_104653_p
		// @094: bipush 25 (0x19)
		// @096: putfield int game.C_100314_lf.field_101396_rb
		// @099: aload_0
		// @09A: getfield game.C_100314_lf game.C_100102_w.field_104653_p
		// @09D: iconst_0
		// @09E: putfield boolean game.C_100314_lf.field_101307_pb
		// @0A1: aload_0
		// @0A2: getfield game.C_100314_lf game.C_100102_w.field_104653_p
		// @0A5: iconst_1
		// @0A6: putfield int game.C_100314_lf.field_101309_wb
		// @0A9: aload_0
		// @0AA: getfield int game.C_100102_w.field_104643_k
		// @0AD: getstatic int game.C_100180_ce.field_104805_C
		// @0B0: if_icmpeq @14F
		// @0B3: aload_0
		// @0B4: getfield int game.C_100102_w.field_104643_k
		// @0B7: iconst_m1
		// @0B8: ixor
		// @0B9: getstatic int game.C_100309_lk.field_103267_Q
		// @0BC: iconst_m1
		// @0BD: ixor
		// @0BE: if_icmpne @0DA
		// @0C1: goto @0C5
		// @0C4: athrow
		// @0C5: aload_0
		// @0C6: iconst_0
		// @0C7: putfield int game.C_100102_w.field_104642_j
		// @0CA: aload_0
		// @0CB: getfield game.C_100314_lf game.C_100102_w.field_104653_p
		// @0CE: iconst_0
		// @0CF: putfield int game.C_100314_lf.field_101388_sb
		// @0D2: iload_3
		// @0D3: ifeq @2AB
		// @0D6: goto @0DA
		// @0D9: athrow
		// @0DA: aload_0
		// @0DB: dup
		// @0DC: getfield int game.C_100102_w.field_104649_t
		// @0DF: iconst_1
		// @0E0: iadd
		// @0E1: putfield int game.C_100102_w.field_104649_t
		// @0E4: aload_0
		// @0E5: getfield int game.C_100102_w.field_104649_t
		// @0E8: iconst_m1
		// @0E9: ixor
		// @0EA: sipush -201 (0xFF37)
		// @0ED: if_icmplt @0F8
		// @0F0: goto @0F4
		// @0F3: athrow
		// @0F4: goto @104
		// @0F7: athrow
		// @0F8: aload_0
		// @0F9: dup
		// @0FA: getfield int game.C_100102_w.field_104649_t
		// @0FD: sipush 400 (0x0190)
		// @100: isub
		// @101: putfield int game.C_100102_w.field_104649_t
		// @104: aload_0
		// @105: aload_0
		// @106: getfield int game.C_100102_w.field_104649_t
		// @109: getstatic int[][][] game.C_100165_sh.field_100774_o
		// @10C: aload_0
		// @10D: getfield int game.C_100102_w.field_104633_d
		// @110: bipush 59 (0x3B)
		// @112: invokestatic game.C_100183_cd.func_103414_b(int, byte)int
		// @115: aaload
		// @116: bipush 25 (0x19)
		// @118: aaload
		// @119: iconst_5
		// @11A: iaload
		// @11B: imul
		// @11C: aload_0
		// @11D: getfield int game.C_100102_w.field_104645_i
		// @120: imul
		// @121: bipush 10 (0x0A)
		// @123: getstatic int[][][] game.C_100165_sh.field_100774_o
		// @126: aload_0
		// @127: getfield int game.C_100102_w.field_104633_d
		// @12A: bipush 59 (0x3B)
		// @12C: invokestatic game.C_100183_cd.func_103414_b(int, byte)int
		// @12F: aaload
		// @130: bipush 25 (0x19)
		// @132: aaload
		// @133: bipush 6 (0x06)
		// @135: iaload
		// @136: imul
		// @137: idiv
		// @138: putfield int game.C_100102_w.field_104642_j
		// @13B: aload_0
		// @13C: aload_0
		// @13D: getfield int game.C_100102_w.field_104642_j
		// @140: sipush 511 (0x01FF)
		// @143: iand
		// @144: sipush -256 (0xFF00)
		// @147: iadd
		// @148: putfield int game.C_100102_w.field_104642_j
		// @14B: iload_3
		// @14C: ifeq @2AB
		// @14F: aload_0
		// @150: iconst_0
		// @151: putfield int game.C_100102_w.field_104642_j
		// @154: iload_3
		// @155: ifeq @2AB
		// @158: goto @15C
		// @15B: athrow
		// @15C: aload_0
		// @15D: getfield game.C_100314_lf game.C_100102_w.field_104653_p
		// @160: dup
		// @161: getfield int game.C_100314_lf.field_101294_gc
		// @164: iconst_1
		// @165: iadd
		// @166: putfield int game.C_100314_lf.field_101294_gc
		// @169: aload_0
		// @16A: getfield game.C_100314_lf game.C_100102_w.field_104653_p
		// @16D: iconst_1
		// @16E: putfield boolean game.C_100314_lf.field_101307_pb
		// @171: aload_0
		// @172: getfield game.C_100314_lf game.C_100102_w.field_104653_p
		// @175: iconst_0
		// @176: putfield int game.C_100314_lf.field_101295_gb
		// @179: aload_0
		// @17A: getfield game.C_100314_lf game.C_100102_w.field_104653_p
		// @17D: getfield int game.C_100314_lf.field_101294_gc
		// @180: iconst_m1
		// @181: ixor
		// @182: bipush -51 (0xCD)
		// @184: if_icmplt @18F
		// @187: goto @18B
		// @18A: athrow
		// @18B: goto @2AB
		// @18E: athrow
		// @18F: aload_0
		// @190: getfield game.C_100314_lf game.C_100102_w.field_104653_p
		// @193: bipush -50 (0xCE)
		// @195: putfield int game.C_100314_lf.field_101294_gc
		// @198: iload_3
		// @199: ifeq @2AB
		// @19C: aload_0
		// @19D: getfield game.C_100314_lf game.C_100102_w.field_104653_p
		// @1A0: dup
		// @1A1: getfield int game.C_100314_lf.field_101295_gb
		// @1A4: dup_x1
		// @1A5: iconst_1
		// @1A6: iadd
		// @1A7: putfield int game.C_100314_lf.field_101295_gb
		// @1AA: getstatic int[][][] game.C_100165_sh.field_100774_o
		// @1AD: aload_0
		// @1AE: getfield int game.C_100102_w.field_104633_d
		// @1B1: bipush 59 (0x3B)
		// @1B3: invokestatic game.C_100183_cd.func_103414_b(int, byte)int
		// @1B6: aaload
		// @1B7: bipush 25 (0x19)
		// @1B9: aaload
		// @1BA: iconst_2
		// @1BB: iaload
		// @1BC: if_icmpge @1C7
		// @1BF: goto @1C3
		// @1C2: athrow
		// @1C3: goto @1CF
		// @1C6: athrow
		// @1C7: aload_0
		// @1C8: getfield game.C_100314_lf game.C_100102_w.field_104653_p
		// @1CB: iconst_0
		// @1CC: putfield int game.C_100314_lf.field_101295_gb
		// @1CF: aload_0
		// @1D0: getfield game.C_100314_lf game.C_100102_w.field_104653_p
		// @1D3: iconst_0
		// @1D4: putfield boolean game.C_100314_lf.field_101307_pb
		// @1D7: iload_3
		// @1D8: ifeq @2AB
		// @1DB: aload_0
		// @1DC: getfield game.C_100314_lf game.C_100102_w.field_104653_p
		// @1DF: iconst_0
		// @1E0: putfield boolean game.C_100314_lf.field_101307_pb
		// @1E3: aload_0
		// @1E4: getfield game.C_100314_lf game.C_100102_w.field_104653_p
		// @1E7: iconst_1
		// @1E8: putfield int game.C_100314_lf.field_101309_wb
		// @1EB: aload_0
		// @1EC: getfield game.C_100314_lf game.C_100102_w.field_104653_p
		// @1EF: iconst_0
		// @1F0: putfield int game.C_100314_lf.field_101396_rb
		// @1F3: aload_0
		// @1F4: getfield game.C_100314_lf game.C_100102_w.field_104653_p
		// @1F7: iconst_0
		// @1F8: putfield int game.C_100314_lf.field_101295_gb
		// @1FB: aload_0
		// @1FC: getfield int game.C_100102_w.field_104643_k
		// @1FF: iconst_m1
		// @200: ixor
		// @201: getstatic int game.C_100180_ce.field_104805_C
		// @204: iconst_m1
		// @205: ixor
		// @206: if_icmpeq @2A2
		// @209: goto @20D
		// @20C: athrow
		// @20D: aload_0
		// @20E: getfield int game.C_100102_w.field_104643_k
		// @211: getstatic int game.C_100309_lk.field_103267_Q
		// @214: if_icmpeq @28D
		// @217: goto @21B
		// @21A: athrow
		// @21B: aload_0
		// @21C: dup
		// @21D: getfield int game.C_100102_w.field_104649_t
		// @220: iconst_1
		// @221: iadd
		// @222: putfield int game.C_100102_w.field_104649_t
		// @225: sipush 200 (0x00C8)
		// @228: aload_0
		// @229: getfield int game.C_100102_w.field_104649_t
		// @22C: if_icmpge @243
		// @22F: goto @233
		// @232: athrow
		// @233: aload_0
		// @234: dup
		// @235: getfield int game.C_100102_w.field_104649_t
		// @238: sipush 400 (0x0190)
		// @23B: isub
		// @23C: putfield int game.C_100102_w.field_104649_t
		// @23F: goto @243
		// @242: athrow
		// @243: aload_0
		// @244: aload_0
		// @245: getfield int game.C_100102_w.field_104649_t
		// @248: getstatic int[][][] game.C_100165_sh.field_100774_o
		// @24B: aload_0
		// @24C: getfield int game.C_100102_w.field_104633_d
		// @24F: bipush 59 (0x3B)
		// @251: invokestatic game.C_100183_cd.func_103414_b(int, byte)int
		// @254: aaload
		// @255: bipush 25 (0x19)
		// @257: aaload
		// @258: iconst_0
		// @259: iaload
		// @25A: imul
		// @25B: aload_0
		// @25C: getfield int game.C_100102_w.field_104645_i
		// @25F: imul
		// @260: getstatic int[][][] game.C_100165_sh.field_100774_o
		// @263: aload_0
		// @264: getfield int game.C_100102_w.field_104633_d
		// @267: bipush 59 (0x3B)
		// @269: invokestatic game.C_100183_cd.func_103414_b(int, byte)int
		// @26C: aaload
		// @26D: bipush 25 (0x19)
		// @26F: aaload
		// @270: iconst_1
		// @271: iaload
		// @272: bipush 10 (0x0A)
		// @274: imul
		// @275: idiv
		// @276: putfield int game.C_100102_w.field_104642_j
		// @279: aload_0
		// @27A: sipush -256 (0xFF00)
		// @27D: aload_0
		// @27E: getfield int game.C_100102_w.field_104642_j
		// @281: sipush 511 (0x01FF)
		// @284: iand
		// @285: iadd
		// @286: putfield int game.C_100102_w.field_104642_j
		// @289: iload_3
		// @28A: ifeq @2AB
		// @28D: aload_0
		// @28E: iconst_0
		// @28F: putfield int game.C_100102_w.field_104642_j
		// @292: aload_0
		// @293: getfield game.C_100314_lf game.C_100102_w.field_104653_p
		// @296: iconst_0
		// @297: putfield int game.C_100314_lf.field_101388_sb
		// @29A: iload_3
		// @29B: ifeq @2AB
		// @29E: goto @2A2
		// @2A1: athrow
		// @2A2: aload_0
		// @2A3: iconst_0
		// @2A4: putfield int game.C_100102_w.field_104642_j
		// @2A7: goto @2AB
		// @2AA: athrow
		// @2AB: aload_0
		// @2AC: getfield game.C_100314_lf game.C_100102_w.field_104653_p
		// @2AF: aload_0
		// @2B0: getfield int game.C_100102_w.field_104633_d
		// @2B3: bipush 116 (0x74)
		// @2B5: invokevirtual game.C_100314_lf.func_101291_b(int, byte)void
		// @2B8: bipush -2 (0xFE)
		// @2BA: getstatic int game.C_100083_c.field_103171_R
		// @2BD: iconst_m1
		// @2BE: ixor
		// @2BF: if_icmpne @36D
		// @2C2: iconst_m1
		// @2C3: aload_0
		// @2C4: getfield int game.C_100102_w.field_104634_e
		// @2C7: if_icmpeq @36D
		// @2CA: goto @2CE
		// @2CD: athrow
		// @2CE: aload_0
		// @2CF: getfield int game.C_100102_w.field_104634_e
		// @2D2: iconst_m1
		// @2D3: ixor
		// @2D4: aload_0
		// @2D5: getfield int game.C_100102_w.field_104640_l
		// @2D8: iconst_m1
		// @2D9: ixor
		// @2DA: if_icmpeq @308
		// @2DD: goto @2E1
		// @2E0: athrow
		// @2E1: aload_0
		// @2E2: aload_0
		// @2E3: getfield int game.C_100102_w.field_104634_e
		// @2E6: putfield int game.C_100102_w.field_104640_l
		// @2E9: aload_0
		// @2EA: getstatic int[][][] game.C_100165_sh.field_100774_o
		// @2ED: aload_0
		// @2EE: getfield int game.C_100102_w.field_104633_d
		// @2F1: bipush 59 (0x3B)
		// @2F3: invokestatic game.C_100183_cd.func_103414_b(int, byte)int
		// @2F6: aaload
		// @2F7: aload_0
		// @2F8: getfield int game.C_100102_w.field_104656_x
		// @2FB: aaload
		// @2FC: aload_0
		// @2FD: getfield int game.C_100102_w.field_104634_e
		// @300: iaload
		// @301: putfield int game.C_100102_w.field_104650_s
		// @304: goto @308
		// @307: athrow
		// @308: getstatic int[][][] game.C_100165_sh.field_100774_o
		// @30B: aload_0
		// @30C: getfield int game.C_100102_w.field_104633_d
		// @30F: bipush 59 (0x3B)
		// @311: invokestatic game.C_100183_cd.func_103414_b(int, byte)int
		// @314: aaload
		// @315: aload_0
		// @316: getfield int game.C_100102_w.field_104656_x
		// @319: aaload
		// @31A: aload_0
		// @31B: getfield int game.C_100102_w.field_104634_e
		// @31E: aload_0
		// @31F: getfield int game.C_100102_w.field_104641_m
		// @322: iastore
		// @323: getstatic game.C_100037_wb[] game.C_100254_pi.field_106468_p
		// @326: aload_0
		// @327: getfield int game.C_100102_w.field_104656_x
		// @32A: aaload
		// @32B: invokevirtual game.C_100037_wb.func_102379_d()void
		// @32E: invokestatic game.C_100196_rb.func_105792_b()void
		// @331: aload_0
		// @332: getfield game.C_100314_lf game.C_100102_w.field_104653_p
		// @335: aload_0
		// @336: getfield int game.C_100102_w.field_104656_x
		// @339: putfield int game.C_100314_lf.field_101408_qb
		// @33C: aload_0
		// @33D: getfield game.C_100314_lf game.C_100102_w.field_104653_p
		// @340: aload_0
		// @341: getfield int game.C_100102_w.field_104656_x
		// @344: putfield int game.C_100314_lf.field_101315_F
		// @347: aload_0
		// @348: getfield game.C_100314_lf game.C_100102_w.field_104653_p
		// @34B: aload_0
		// @34C: getfield int game.C_100102_w.field_104633_d
		// @34F: iconst_2
		// @350: invokevirtual game.C_100314_lf.func_101272_k(int, int)int[]
		// @353: pop
		// @354: aload_0
		// @355: getfield game.C_100314_lf game.C_100102_w.field_104653_p
		// @358: bipush -128 (0x80)
		// @35A: getstatic int game.C_100116_ei.field_104121_e
		// @35D: sipush 128 (0x0080)
		// @360: bipush 64 (0x40)
		// @362: invokevirtual game.C_100314_lf.func_101245_b(int, int, int, int)void
		// @365: getstatic game.C_100185_rm game.C_100049_vf.field_104206_l
		// @368: bipush 113 (0x71)
		// @36A: invokevirtual game.C_100185_rm.func_105476_a(byte)void
		// @36D: goto @392
		// @370: astore_2
		// @371: aload_2
		// @372: new java.lang.StringBuilder
		// @375: dup
		// @376: invokespecial java.lang.StringBuilder.<init>()void
		// @379: getstatic java.lang.String[] game.C_100102_w.field_104654_z
		// @37C: bipush 12 (0x0C)
		// @37E: aaload
		// @37F: invokevirtual java.lang.StringBuilder.append(java.lang.String)java.lang.StringBuilder
		// @382: iload_1
		// @383: invokevirtual java.lang.StringBuilder.append(int)java.lang.StringBuilder
		// @386: bipush 41 (0x29)
		// @388: invokevirtual java.lang.StringBuilder.append(char)java.lang.StringBuilder
		// @38B: invokevirtual java.lang.StringBuilder.toString()java.lang.String
		// @38E: invokestatic game.C_100181_cf.func_105695_a(java.lang.Throwable, java.lang.String)game.C_100170_cm
		// @391: athrow
		// @392: return
	}
	
	static final void func_104626_a(byte arg0)
	{
		// @00: iload_0
		// @01: bipush 23 (0x17)
		// @03: if_icmpgt @0B
		// @06: bipush 46 (0x2E)
		// @08: putstatic int game.C_100102_w.field_104635_b
		// @0B: goto @30
		// @0E: astore_1
		// @0F: aload_1
		// @10: new java.lang.StringBuilder
		// @13: dup
		// @14: invokespecial java.lang.StringBuilder.<init>()void
		// @17: getstatic java.lang.String[] game.C_100102_w.field_104654_z
		// @1A: bipush 34 (0x22)
		// @1C: aaload
		// @1D: invokevirtual java.lang.StringBuilder.append(java.lang.String)java.lang.StringBuilder
		// @20: iload_0
		// @21: invokevirtual java.lang.StringBuilder.append(int)java.lang.StringBuilder
		// @24: bipush 41 (0x29)
		// @26: invokevirtual java.lang.StringBuilder.append(char)java.lang.StringBuilder
		// @29: invokevirtual java.lang.StringBuilder.toString()java.lang.String
		// @2C: invokestatic game.C_100181_cf.func_105695_a(java.lang.Throwable, java.lang.String)game.C_100170_cm
		// @2F: athrow
		// @30: return
	}
	
	static final boolean func_104629_c(byte arg0)
	{
		// @00: iload_0
		// @01: bipush -90 (0xA6)
		// @03: if_icmpeq @0F
		// @06: bipush 10 (0x0A)
		// @08: putstatic int game.C_100102_w.field_104648_u
		// @0B: goto @0F
		// @0E: athrow
		// @0F: bipush -68 (0xBC)
		// @11: invokestatic game.C_100031_gl.func_103958_a(byte)void
		// @14: getstatic java.lang.reflect.Method game.C_100019_wl.field_103846_a
		// @17: ifnull @1F
		// @1A: iconst_1
		// @1B: goto @20
		// @1E: athrow
		// @1F: iconst_0
		// @20: ireturn
		// @21: astore_1
		// @22: aload_1
		// @23: new java.lang.StringBuilder
		// @26: dup
		// @27: invokespecial java.lang.StringBuilder.<init>()void
		// @2A: getstatic java.lang.String[] game.C_100102_w.field_104654_z
		// @2D: iconst_0
		// @2E: aaload
		// @2F: invokevirtual java.lang.StringBuilder.append(java.lang.String)java.lang.StringBuilder
		// @32: iload_0
		// @33: invokevirtual java.lang.StringBuilder.append(int)java.lang.StringBuilder
		// @36: bipush 41 (0x29)
		// @38: invokevirtual java.lang.StringBuilder.append(char)java.lang.StringBuilder
		// @3B: invokevirtual java.lang.StringBuilder.toString()java.lang.String
		// @3E: invokestatic game.C_100181_cf.func_105695_a(java.lang.Throwable, java.lang.String)game.C_100170_cm
		// @41: athrow
	}
	
	final void func_104630_b(byte arg0)
	{
		// @0000: getstatic int game.SteelSentinels.field_105275_O
		// @0003: istore #11
		// @0005: getstatic int[][][] game.C_100165_sh.field_100774_o
		// @0008: aload_0
		// @0009: getfield int game.C_100102_w.field_104633_d
		// @000C: bipush 59 (0x3B)
		// @000E: invokestatic game.C_100183_cd.func_103414_b(int, byte)int
		// @0011: aaload
		// @0012: ifnull @0029
		// @0015: aconst_null
		// @0016: getstatic int[][][] game.C_100165_sh.field_100774_o
		// @0019: aload_0
		// @001A: getfield int game.C_100102_w.field_104633_d
		// @001D: bipush 59 (0x3B)
		// @001F: invokestatic game.C_100183_cd.func_103414_b(int, byte)int
		// @0022: aaload
		// @0023: bipush 25 (0x19)
		// @0025: aaload
		// @0026: if_acmpne @002A
		// @0029: return
		// @002A: iconst_0
		// @002B: iconst_0
		// @002C: sipush 640 (0x0280)
		// @002F: sipush 380 (0x017C)
		// @0032: iconst_0
		// @0033: invokestatic game.C_100196_rb.func_105782_i(int, int, int, int, int)void
		// @0036: iconst_0
		// @0037: iconst_0
		// @0038: sipush 640 (0x0280)
		// @003B: sipush 396 (0x018C)
		// @003E: invokestatic game.C_100196_rb.func_105815_h(int, int, int, int)void
		// @0041: aload_0
		// @0042: getfield int game.C_100102_w.field_104634_e
		// @0045: istore #4
		// @0047: aload_0
		// @0048: iconst_m1
		// @0049: putfield int game.C_100102_w.field_104634_e
		// @004C: iconst_0
		// @004D: aload_0
		// @004E: getfield game.C_100314_lf game.C_100102_w.field_104653_p
		// @0051: getfield game.C_100327_ib[] game.C_100314_lf.field_101314_E
		// @0054: arraylength
		// @0055: if_icmplt @005C
		// @0058: goto @043F
		// @005B: athrow
		// @005C: sipush 320 (0x0140)
		// @005F: istore_2
		// @0060: bipush 32 (0x20)
		// @0062: istore_3
		// @0063: getstatic int[][][] game.C_100165_sh.field_100774_o
		// @0066: aload_0
		// @0067: getfield int game.C_100102_w.field_104633_d
		// @006A: bipush 59 (0x3B)
		// @006C: invokestatic game.C_100183_cd.func_103414_b(int, byte)int
		// @006F: aaload
		// @0070: aload_0
		// @0071: getfield int game.C_100102_w.field_104656_x
		// @0074: aaload
		// @0075: astore #5
		// @0077: aload #5
		// @0079: ifnull @0080
		// @007C: goto @00A1
		// @007F: athrow
		// @0080: getstatic int[][][] game.C_100165_sh.field_100774_o
		// @0083: aload_0
		// @0084: getfield int game.C_100102_w.field_104633_d
		// @0087: bipush 59 (0x3B)
		// @0089: invokestatic game.C_100183_cd.func_103414_b(int, byte)int
		// @008C: aaload
		// @008D: aload_0
		// @008E: getfield int game.C_100102_w.field_104656_x
		// @0091: aload_0
		// @0092: getfield game.C_100314_lf game.C_100102_w.field_104653_p
		// @0095: getfield game.C_100327_ib[] game.C_100314_lf.field_101314_E
		// @0098: arraylength
		// @0099: iconst_2
		// @009A: iadd
		// @009B: newarray int[]
		// @009D: dup_x2
		// @009E: aastore
		// @009F: astore #5
		// @00A1: aload #5
		// @00A3: arraylength
		// @00A4: istore #6
		// @00A6: aconst_null
		// @00A7: aload #5
		// @00A9: if_acmpeq @00C3
		// @00AC: iconst_2
		// @00AD: aload_0
		// @00AE: getfield game.C_100314_lf game.C_100102_w.field_104653_p
		// @00B1: getfield game.C_100327_ib[] game.C_100314_lf.field_101314_E
		// @00B4: arraylength
		// @00B5: iadd
		// @00B6: iconst_m1
		// @00B7: ixor
		// @00B8: iload #6
		// @00BA: iconst_m1
		// @00BB: ixor
		// @00BC: if_icmpeq @0137
		// @00BF: goto @00C3
		// @00C2: athrow
		// @00C3: iconst_2
		// @00C4: aload_0
		// @00C5: getfield game.C_100314_lf game.C_100102_w.field_104653_p
		// @00C8: getfield game.C_100327_ib[] game.C_100314_lf.field_101314_E
		// @00CB: arraylength
		// @00CC: iadd
		// @00CD: newarray int[]
		// @00CF: astore #5
		// @00D1: iconst_0
		// @00D2: istore #8
		// @00D4: aload #5
		// @00D6: arraylength
		// @00D7: iload #8
		// @00D9: if_icmple @0123
		// @00DC: iload #8
		// @00DE: getstatic int[][][] game.C_100165_sh.field_100774_o
		// @00E1: aload_0
		// @00E2: getfield int game.C_100102_w.field_104633_d
		// @00E5: bipush 59 (0x3B)
		// @00E7: invokestatic game.C_100183_cd.func_103414_b(int, byte)int
		// @00EA: aaload
		// @00EB: aload_0
		// @00EC: getfield int game.C_100102_w.field_104656_x
		// @00EF: aaload
		// @00F0: arraylength
		// @00F1: iload #11
		// @00F3: ifne @044E
		// @00F6: if_icmpge @011B
		// @00F9: goto @00FD
		// @00FC: athrow
		// @00FD: aload #5
		// @00FF: iload #8
		// @0101: getstatic int[][][] game.C_100165_sh.field_100774_o
		// @0104: aload_0
		// @0105: getfield int game.C_100102_w.field_104633_d
		// @0108: bipush 59 (0x3B)
		// @010A: invokestatic game.C_100183_cd.func_103414_b(int, byte)int
		// @010D: aaload
		// @010E: aload_0
		// @010F: getfield int game.C_100102_w.field_104656_x
		// @0112: aaload
		// @0113: iload #8
		// @0115: iaload
		// @0116: iastore
		// @0117: goto @011B
		// @011A: athrow
		// @011B: iinc #8 +1
		// @011E: iload #11
		// @0120: ifeq @00D4
		// @0123: getstatic int[][][] game.C_100165_sh.field_100774_o
		// @0126: aload_0
		// @0127: getfield int game.C_100102_w.field_104633_d
		// @012A: bipush 59 (0x3B)
		// @012C: invokestatic game.C_100183_cd.func_103414_b(int, byte)int
		// @012F: aaload
		// @0130: aload_0
		// @0131: getfield int game.C_100102_w.field_104656_x
		// @0134: aload #5
		// @0136: aastore
		// @0137: bipush 48 (0x30)
		// @0139: istore #7
		// @013B: iconst_0
		// @013C: istore #8
		// @013E: iload #6
		// @0140: iload #8
		// @0142: if_icmple @043F
		// @0145: iload #8
		// @0147: iconst_m1
		// @0148: ixor
		// @0149: aload_0
		// @014A: getfield game.C_100314_lf game.C_100102_w.field_104653_p
		// @014D: getfield game.C_100327_ib[] game.C_100314_lf.field_101314_E
		// @0150: arraylength
		// @0151: iconst_m1
		// @0152: ixor
		// @0153: iload #11
		// @0155: ifne @044E
		// @0158: if_icmpgt @0325
		// @015B: goto @015F
		// @015E: athrow
		// @015F: iload #6
		// @0161: iconst_2
		// @0162: isub
		// @0163: iconst_m1
		// @0164: ixor
		// @0165: iload #8
		// @0167: iconst_m1
		// @0168: ixor
		// @0169: if_icmpne @0243
		// @016C: goto @0170
		// @016F: athrow
		// @0170: iload_2
		// @0171: iload_3
		// @0172: iconst_2
		// @0173: iload #7
		// @0175: imul
		// @0176: ldc 16777215 (0xffffff)
		// @0178: invokestatic game.C_100196_rb.func_105778_a(int, int, int, int)void
		// @017B: bipush -3 (0xFD)
		// @017D: iload_2
		// @017E: iadd
		// @017F: iload #7
		// @0181: iload_3
		// @0182: iadd
		// @0183: bipush 7 (0x07)
		// @0185: ldc 16746496 (0xff8800)
		// @0187: invokestatic game.C_100196_rb.func_105807_g(int, int, int, int)void
		// @018A: iload_3
		// @018B: iload #7
		// @018D: aload #5
		// @018F: iload #8
		// @0191: iaload
		// @0192: iload #7
		// @0194: imul
		// @0195: sipush 2500 (0x09C4)
		// @0198: idiv
		// @0199: iadd
		// @019A: iadd
		// @019B: istore #9
		// @019D: iload_2
		// @019E: iload #9
		// @01A0: iconst_5
		// @01A1: ldc 16746496 (0xff8800)
		// @01A3: invokestatic game.C_100196_rb.func_105776_b(int, int, int, int)void
		// @01A6: getstatic int game.C_100083_c.field_103171_R
		// @01A9: ifeq @01BB
		// @01AC: iload #8
		// @01AE: iconst_m1
		// @01AF: ixor
		// @01B0: iload #4
		// @01B2: iconst_m1
		// @01B3: ixor
		// @01B4: if_icmpne @023E
		// @01B7: goto @01BB
		// @01BA: athrow
		// @01BB: getstatic int game.C_100015_wh.field_103781_g
		// @01BE: iconst_m1
		// @01BF: ixor
		// @01C0: iload_2
		// @01C1: iconst_5
		// @01C2: isub
		// @01C3: iconst_m1
		// @01C4: ixor
		// @01C5: if_icmpgt @023E
		// @01C8: goto @01CC
		// @01CB: athrow
		// @01CC: getstatic int game.C_100015_wh.field_103781_g
		// @01CF: iconst_5
		// @01D0: iload_2
		// @01D1: iadd
		// @01D2: if_icmpgt @023E
		// @01D5: goto @01D9
		// @01D8: athrow
		// @01D9: getstatic int game.C_100338_jc.field_105370_l
		// @01DC: iconst_m1
		// @01DD: ixor
		// @01DE: iload_3
		// @01DF: iconst_m1
		// @01E0: ixor
		// @01E1: if_icmpgt @023E
		// @01E4: goto @01E8
		// @01E7: athrow
		// @01E8: getstatic int game.C_100338_jc.field_105370_l
		// @01EB: iconst_2
		// @01EC: iload #7
		// @01EE: imul
		// @01EF: iload_3
		// @01F0: iadd
		// @01F1: if_icmpgt @023E
		// @01F4: goto @01F8
		// @01F7: athrow
		// @01F8: aload_0
		// @01F9: iload_3
		// @01FA: ineg
		// @01FB: getstatic int game.C_100338_jc.field_105370_l
		// @01FE: iadd
		// @01FF: iload #7
		// @0201: ineg
		// @0202: iadd
		// @0203: sipush 2500 (0x09C4)
		// @0206: imul
		// @0207: iload #7
		// @0209: idiv
		// @020A: putfield int game.C_100102_w.field_104641_m
		// @020D: aload_0
		// @020E: iload #8
		// @0210: putfield int game.C_100102_w.field_104634_e
		// @0213: iload #7
		// @0215: ineg
		// @0216: iload_3
		// @0217: ineg
		// @0218: getstatic int game.C_100338_jc.field_105370_l
		// @021B: iadd
		// @021C: iadd
		// @021D: invokestatic java.lang.Math.abs(int)int
		// @0220: iconst_m1
		// @0221: ixor
		// @0222: bipush -2 (0xFE)
		// @0224: if_icmplt @0234
		// @0227: goto @022B
		// @022A: athrow
		// @022B: aload_0
		// @022C: iconst_0
		// @022D: putfield int game.C_100102_w.field_104641_m
		// @0230: goto @0234
		// @0233: athrow
		// @0234: iload_2
		// @0235: iload #9
		// @0237: bipush 6 (0x06)
		// @0239: ldc 16746496 (0xff8800)
		// @023B: invokestatic game.C_100196_rb.func_105776_b(int, int, int, int)void
		// @023E: iload #11
		// @0240: ifeq @0434
		// @0243: iload #8
		// @0245: iconst_m1
		// @0246: ixor
		// @0247: iconst_m1
		// @0248: iload #6
		// @024A: iadd
		// @024B: iconst_m1
		// @024C: ixor
		// @024D: if_icmpne @0434
		// @0250: goto @0254
		// @0253: athrow
		// @0254: iload_2
		// @0255: iload_3
		// @0256: iload #7
		// @0258: iconst_2
		// @0259: imul
		// @025A: ldc 16777215 (0xffffff)
		// @025C: invokestatic game.C_100196_rb.func_105807_g(int, int, int, int)void
		// @025F: iload_2
		// @0260: iload #7
		// @0262: ineg
		// @0263: isub
		// @0264: iload_3
		// @0265: iconst_3
		// @0266: isub
		// @0267: bipush 7 (0x07)
		// @0269: ldc 16746496 (0xff8800)
		// @026B: invokestatic game.C_100196_rb.func_105778_a(int, int, int, int)void
		// @026E: aload #5
		// @0270: iload #8
		// @0272: iaload
		// @0273: iload #7
		// @0275: imul
		// @0276: sipush 2500 (0x09C4)
		// @0279: idiv
		// @027A: iload_2
		// @027B: iadd
		// @027C: iload #7
		// @027E: iadd
		// @027F: istore #9
		// @0281: iload #9
		// @0283: iload_3
		// @0284: iconst_5
		// @0285: ldc 16746496 (0xff8800)
		// @0287: invokestatic game.C_100196_rb.func_105776_b(int, int, int, int)void
		// @028A: iconst_m1
		// @028B: getstatic int game.C_100083_c.field_103171_R
		// @028E: iconst_m1
		// @028F: ixor
		// @0290: if_icmpeq @029E
		// @0293: iload #8
		// @0295: iload #4
		// @0297: if_icmpne @0320
		// @029A: goto @029E
		// @029D: athrow
		// @029E: getstatic int game.C_100015_wh.field_103781_g
		// @02A1: iload_2
		// @02A2: if_icmplt @0320
		// @02A5: goto @02A9
		// @02A8: athrow
		// @02A9: iconst_2
		// @02AA: iload #7
		// @02AC: imul
		// @02AD: iload_2
		// @02AE: iadd
		// @02AF: getstatic int game.C_100015_wh.field_103781_g
		// @02B2: if_icmplt @0320
		// @02B5: goto @02B9
		// @02B8: athrow
		// @02B9: iload_3
		// @02BA: iconst_5
		// @02BB: isub
		// @02BC: iconst_m1
		// @02BD: ixor
		// @02BE: getstatic int game.C_100338_jc.field_105370_l
		// @02C1: iconst_m1
		// @02C2: ixor
		// @02C3: if_icmplt @0320
		// @02C6: goto @02CA
		// @02C9: athrow
		// @02CA: iconst_5
		// @02CB: iload_3
		// @02CC: iadd
		// @02CD: iconst_m1
		// @02CE: ixor
		// @02CF: getstatic int game.C_100338_jc.field_105370_l
		// @02D2: iconst_m1
		// @02D3: ixor
		// @02D4: if_icmple @02DF
		// @02D7: goto @02DB
		// @02DA: athrow
		// @02DB: goto @0320
		// @02DE: athrow
		// @02DF: aload_0
		// @02E0: iload #8
		// @02E2: putfield int game.C_100102_w.field_104634_e
		// @02E5: aload_0
		// @02E6: iload #7
		// @02E8: ineg
		// @02E9: getstatic int game.C_100015_wh.field_103781_g
		// @02EC: iload_2
		// @02ED: isub
		// @02EE: iadd
		// @02EF: sipush 2500 (0x09C4)
		// @02F2: imul
		// @02F3: iload #7
		// @02F5: idiv
		// @02F6: putfield int game.C_100102_w.field_104641_m
		// @02F9: iload #7
		// @02FB: ineg
		// @02FC: getstatic int game.C_100015_wh.field_103781_g
		// @02FF: iadd
		// @0300: iload_2
		// @0301: ineg
		// @0302: iadd
		// @0303: invokestatic java.lang.Math.abs(int)int
		// @0306: iconst_m1
		// @0307: ixor
		// @0308: bipush -2 (0xFE)
		// @030A: if_icmpge @0311
		// @030D: goto @0316
		// @0310: athrow
		// @0311: aload_0
		// @0312: iconst_0
		// @0313: putfield int game.C_100102_w.field_104641_m
		// @0316: iload #9
		// @0318: iload_3
		// @0319: bipush 6 (0x06)
		// @031B: ldc 16746496 (0xff8800)
		// @031D: invokestatic game.C_100196_rb.func_105776_b(int, int, int, int)void
		// @0320: iload #11
		// @0322: ifeq @0434
		// @0325: iload_2
		// @0326: iload_3
		// @0327: iload #7
		// @0329: iconst_2
		// @032A: imul
		// @032B: ldc 16777215 (0xffffff)
		// @032D: invokestatic game.C_100196_rb.func_105778_a(int, int, int, int)void
		// @0330: bipush -3 (0xFD)
		// @0332: iload_2
		// @0333: iadd
		// @0334: iload_3
		// @0335: iload #7
		// @0337: ineg
		// @0338: isub
		// @0339: bipush 7 (0x07)
		// @033B: ldc 16777215 (0xffffff)
		// @033D: invokestatic game.C_100196_rb.func_105807_g(int, int, int, int)void
		// @0340: iload_3
		// @0341: iload #7
		// @0343: ineg
		// @0344: isub
		// @0345: aload #5
		// @0347: iload #8
		// @0349: iaload
		// @034A: iload #7
		// @034C: imul
		// @034D: sipush 17763 (0x4563)
		// @0350: idiv
		// @0351: iadd
		// @0352: istore #9
		// @0354: ldc 16777215 (0xffffff)
		// @0356: istore #10
		// @0358: iconst_0
		// @0359: aload #5
		// @035B: iload #8
		// @035D: iaload
		// @035E: if_icmpne @0366
		// @0361: sipush 26248 (0x6688)
		// @0364: istore #10
		// @0366: iload_2
		// @0367: iload #9
		// @0369: iconst_5
		// @036A: iload #10
		// @036C: invokestatic game.C_100196_rb.func_105776_b(int, int, int, int)void
		// @036F: getstatic int game.C_100083_c.field_103171_R
		// @0372: iconst_m1
		// @0373: ixor
		// @0374: iconst_m1
		// @0375: if_icmpeq @0383
		// @0378: iload #8
		// @037A: iload #4
		// @037C: if_icmpne @0434
		// @037F: goto @0383
		// @0382: athrow
		// @0383: bipush -5 (0xFB)
		// @0385: iload_2
		// @0386: iadd
		// @0387: getstatic int game.C_100015_wh.field_103781_g
		// @038A: if_icmpgt @0434
		// @038D: goto @0391
		// @0390: athrow
		// @0391: getstatic int game.C_100015_wh.field_103781_g
		// @0394: iload_2
		// @0395: iconst_5
		// @0396: iadd
		// @0397: if_icmpgt @0434
		// @039A: goto @039E
		// @039D: athrow
		// @039E: getstatic int game.C_100338_jc.field_105370_l
		// @03A1: iconst_m1
		// @03A2: ixor
		// @03A3: iload_3
		// @03A4: iconst_m1
		// @03A5: ixor
		// @03A6: if_icmpgt @0434
		// @03A9: goto @03AD
		// @03AC: athrow
		// @03AD: getstatic int game.C_100338_jc.field_105370_l
		// @03B0: iconst_m1
		// @03B1: ixor
		// @03B2: iload_3
		// @03B3: iload #7
		// @03B5: iconst_2
		// @03B6: imul
		// @03B7: ineg
		// @03B8: isub
		// @03B9: iconst_m1
		// @03BA: ixor
		// @03BB: if_icmplt @0434
		// @03BE: goto @03C2
		// @03C1: athrow
		// @03C2: aload_0
		// @03C3: iload #8
		// @03C5: putfield int game.C_100102_w.field_104634_e
		// @03C8: aload_0
		// @03C9: iload_3
		// @03CA: ineg
		// @03CB: getstatic int game.C_100338_jc.field_105370_l
		// @03CE: iadd
		// @03CF: iload #7
		// @03D1: ineg
		// @03D2: iadd
		// @03D3: sipush 17763 (0x4563)
		// @03D6: imul
		// @03D7: iload #7
		// @03D9: idiv
		// @03DA: putfield int game.C_100102_w.field_104641_m
		// @03DD: getstatic boolean[] game.C_100309_lk.field_103258_hb
		// @03E0: bipush 81 (0x51)
		// @03E2: baload
		// @03E3: ifeq @0402
		// @03E6: goto @03EA
		// @03E9: athrow
		// @03EA: aload_0
		// @03EB: ldc 35526 (0x8ac6)
		// @03ED: iload #7
		// @03EF: ineg
		// @03F0: iload_3
		// @03F1: ineg
		// @03F2: getstatic int game.C_100338_jc.field_105370_l
		// @03F5: iadd
		// @03F6: iadd
		// @03F7: imul
		// @03F8: iload #7
		// @03FA: idiv
		// @03FB: putfield int game.C_100102_w.field_104641_m
		// @03FE: goto @0402
		// @0401: athrow
		// @0402: getstatic int game.C_100338_jc.field_105370_l
		// @0405: iload_3
		// @0406: iload #7
		// @0408: iadd
		// @0409: isub
		// @040A: invokestatic java.lang.Math.abs(int)int
		// @040D: iconst_1
		// @040E: if_icmpgt @041A
		// @0411: aload_0
		// @0412: iconst_0
		// @0413: putfield int game.C_100102_w.field_104641_m
		// @0416: goto @041A
		// @0419: athrow
		// @041A: aload_0
		// @041B: getfield int game.C_100102_w.field_104641_m
		// @041E: ifeq @0425
		// @0421: goto @042A
		// @0424: athrow
		// @0425: sipush 26248 (0x6688)
		// @0428: istore #10
		// @042A: iload_2
		// @042B: iload #9
		// @042D: bipush 6 (0x06)
		// @042F: iload #10
		// @0431: invokestatic game.C_100196_rb.func_105776_b(int, int, int, int)void
		// @0434: iinc #2 +16
		// @0437: iinc #8 +1
		// @043A: iload #11
		// @043C: ifeq @013E
		// @043F: sipush 380 (0x017C)
		// @0442: istore_3
		// @0443: sipush 160 (0x00A0)
		// @0446: istore_2
		// @0447: getstatic int game.C_100202_qi.field_105918_a
		// @044A: aload_0
		// @044B: getfield int game.C_100102_w.field_104644_h
		// @044E: if_icmpne @049D
		// @0451: iconst_0
		// @0452: istore #5
		// @0454: iload #5
		// @0456: bipush 64 (0x40)
		// @0458: if_icmpge @0498
		// @045B: iload #5
		// @045D: iconst_1
		// @045E: iand
		// @045F: iload_2
		// @0460: iadd
		// @0461: bipush 64 (0x40)
		// @0463: isub
		// @0464: iload #5
		// @0466: iconst_2
		// @0467: idiv
		// @0468: bipush 64 (0x40)
		// @046A: iload_3
		// @046B: iadd
		// @046C: iadd
		// @046D: sipush 128 (0x0080)
		// @0470: iload_2
		// @0471: iconst_1
		// @0472: iload #5
		// @0474: iand
		// @0475: ineg
		// @0476: isub
		// @0477: iadd
		// @0478: bipush -128 (0x80)
		// @047A: iload_3
		// @047B: iload #5
		// @047D: iconst_2
		// @047E: idiv
		// @047F: ineg
		// @0480: isub
		// @0481: iadd
		// @0482: ldc 3351057 (0x332211)
		// @0484: invokestatic game.C_100196_rb.func_105802_e(int, int, int, int, int)void
		// @0487: iinc #5 +1
		// @048A: iload #11
		// @048C: ifne @04C4
		// @048F: iload #11
		// @0491: ifeq @0454
		// @0494: goto @0498
		// @0497: athrow
		// @0498: iload #11
		// @049A: ifeq @04B0
		// @049D: bipush -128 (0x80)
		// @049F: iload_2
		// @04A0: iadd
		// @04A1: iload_3
		// @04A2: sipush 257 (0x0101)
		// @04A5: bipush 64 (0x40)
		// @04A7: ldc 3351057 (0x332211)
		// @04A9: invokestatic game.C_100196_rb.func_105782_i(int, int, int, int, int)void
		// @04AC: goto @04B0
		// @04AF: athrow
		// @04B0: getstatic int[][][] game.C_100165_sh.field_100774_o
		// @04B3: aload_0
		// @04B4: getfield int game.C_100102_w.field_104633_d
		// @04B7: bipush 59 (0x3B)
		// @04B9: invokestatic game.C_100183_cd.func_103414_b(int, byte)int
		// @04BC: aaload
		// @04BD: bipush 25 (0x19)
		// @04BF: aaload
		// @04C0: iconst_0
		// @04C1: iaload
		// @04C2: istore #5
		// @04C4: getstatic int[][][] game.C_100165_sh.field_100774_o
		// @04C7: aload_0
		// @04C8: getfield int game.C_100102_w.field_104633_d
		// @04CB: bipush 59 (0x3B)
		// @04CD: invokestatic game.C_100183_cd.func_103414_b(int, byte)int
		// @04D0: aaload
		// @04D1: bipush 25 (0x19)
		// @04D3: aaload
		// @04D4: iconst_1
		// @04D5: iaload
		// @04D6: istore #6
		// @04D8: aload_0
		// @04D9: getfield game.C_100314_lf game.C_100102_w.field_104653_p
		// @04DC: getfield int game.C_100314_lf.field_101396_rb
		// @04DF: iconst_m1
		// @04E0: ixor
		// @04E1: iconst_m1
		// @04E2: if_icmplt @04E9
		// @04E5: goto @0512
		// @04E8: athrow
		// @04E9: getstatic int[][][] game.C_100165_sh.field_100774_o
		// @04EC: aload_0
		// @04ED: getfield int game.C_100102_w.field_104633_d
		// @04F0: bipush 59 (0x3B)
		// @04F2: invokestatic game.C_100183_cd.func_103414_b(int, byte)int
		// @04F5: aaload
		// @04F6: bipush 25 (0x19)
		// @04F8: aaload
		// @04F9: iconst_5
		// @04FA: iaload
		// @04FB: istore #5
		// @04FD: getstatic int[][][] game.C_100165_sh.field_100774_o
		// @0500: aload_0
		// @0501: getfield int game.C_100102_w.field_104633_d
		// @0504: bipush 59 (0x3B)
		// @0506: invokestatic game.C_100183_cd.func_103414_b(int, byte)int
		// @0509: aaload
		// @050A: bipush 25 (0x19)
		// @050C: aaload
		// @050D: bipush 6 (0x06)
		// @050F: iaload
		// @0510: istore #6
		// @0512: aload_0
		// @0513: getfield int game.C_100102_w.field_104644_h
		// @0516: getstatic int game.C_100151_bc.field_102940_Q
		// @0519: if_icmpne @063E
		// @051C: iload_2
		// @051D: sipush -192 (0xFF40)
		// @0520: iload_3
		// @0521: iadd
		// @0522: sipush 192 (0x00C0)
		// @0525: ldc 16777215 (0xffffff)
		// @0527: bipush 64 (0x40)
		// @0529: invokestatic game.C_100196_rb.func_105805_b(int, int, int, int, int)void
		// @052C: iload_2
		// @052D: bipush 64 (0x40)
		// @052F: isub
		// @0530: iload_3
		// @0531: sipush -192 (0xFF40)
		// @0534: iadd
		// @0535: sipush 192 (0x00C0)
		// @0538: ldc 16777215 (0xffffff)
		// @053A: bipush 64 (0x40)
		// @053C: invokestatic game.C_100196_rb.func_105805_b(int, int, int, int, int)void
		// @053F: iload_2
		// @0540: bipush -64 (0xC0)
		// @0542: isub
		// @0543: sipush -192 (0xFF40)
		// @0546: iload_3
		// @0547: iadd
		// @0548: sipush 192 (0x00C0)
		// @054B: ldc 16777215 (0xffffff)
		// @054D: bipush 64 (0x40)
		// @054F: invokestatic game.C_100196_rb.func_105805_b(int, int, int, int, int)void
		// @0552: getstatic int[][][] game.C_100165_sh.field_100774_o
		// @0555: aload_0
		// @0556: getfield int game.C_100102_w.field_104633_d
		// @0559: bipush 59 (0x3B)
		// @055B: invokestatic game.C_100183_cd.func_103414_b(int, byte)int
		// @055E: aaload
		// @055F: bipush 25 (0x19)
		// @0561: aaload
		// @0562: iconst_3
		// @0563: iaload
		// @0564: istore #7
		// @0566: iload_2
		// @0567: aload_0
		// @0568: getfield int game.C_100102_w.field_104645_i
		// @056B: iconst_m1
		// @056C: aload_0
		// @056D: getfield int game.C_100102_w.field_104656_x
		// @0570: iadd
		// @0571: iload #5
		// @0573: imul
		// @0574: imul
		// @0575: iload #6
		// @0577: idiv
		// @0578: isub
		// @0579: iload_3
		// @057A: bipush 7 (0x07)
		// @057C: iadd
		// @057D: bipush 7 (0x07)
		// @057F: ldc 16777215 (0xffffff)
		// @0581: sipush 255 (0x00FF)
		// @0584: sipush 256 (0x0100)
		// @0587: iconst_m1
		// @0588: aload_0
		// @0589: getfield int game.C_100102_w.field_104656_x
		// @058C: iadd
		// @058D: imul
		// @058E: iload #7
		// @0590: idiv
		// @0591: ineg
		// @0592: iadd
		// @0593: invokestatic game.C_100196_rb.func_105796_c(int, int, int, int, int)void
		// @0596: aload_0
		// @0597: getfield int game.C_100102_w.field_104645_i
		// @059A: iload #7
		// @059C: iload #5
		// @059E: imul
		// @059F: imul
		// @05A0: iload #6
		// @05A2: iconst_2
		// @05A3: imul
		// @05A4: idiv
		// @05A5: ineg
		// @05A6: iload #5
		// @05A8: iconst_m1
		// @05A9: aload_0
		// @05AA: getfield int game.C_100102_w.field_104656_x
		// @05AD: iadd
		// @05AE: aload_0
		// @05AF: getfield int game.C_100102_w.field_104645_i
		// @05B2: imul
		// @05B3: imul
		// @05B4: iload #6
		// @05B6: idiv
		// @05B7: ineg
		// @05B8: iload_2
		// @05B9: iadd
		// @05BA: iadd
		// @05BB: iload_3
		// @05BC: bipush 7 (0x07)
		// @05BE: iadd
		// @05BF: bipush 7 (0x07)
		// @05C1: ldc 16711680 (0xff0000)
		// @05C3: sipush 128 (0x0080)
		// @05C6: invokestatic game.C_100196_rb.func_105796_c(int, int, int, int, int)void
		// @05C9: iload #5
		// @05CB: iload #7
		// @05CD: ineg
		// @05CE: aload_0
		// @05CF: getfield int game.C_100102_w.field_104656_x
		// @05D2: iadd
		// @05D3: iconst_m1
		// @05D4: iadd
		// @05D5: imul
		// @05D6: aload_0
		// @05D7: getfield int game.C_100102_w.field_104645_i
		// @05DA: imul
		// @05DB: iload #6
		// @05DD: idiv
		// @05DE: ineg
		// @05DF: iload_2
		// @05E0: iadd
		// @05E1: bipush 7 (0x07)
		// @05E3: iload_3
		// @05E4: iadd
		// @05E5: bipush 7 (0x07)
		// @05E7: ldc 16777215 (0xffffff)
		// @05E9: sipush 255 (0x00FF)
		// @05EC: aload_0
		// @05ED: getfield int game.C_100102_w.field_104656_x
		// @05F0: iload #7
		// @05F2: isub
		// @05F3: sipush 256 (0x0100)
		// @05F6: imul
		// @05F7: sipush 256 (0x0100)
		// @05FA: isub
		// @05FB: iload #7
		// @05FD: idiv
		// @05FE: ineg
		// @05FF: isub
		// @0600: invokestatic game.C_100196_rb.func_105796_c(int, int, int, int, int)void
		// @0603: iload #7
		// @0605: iload #5
		// @0607: imul
		// @0608: aload_0
		// @0609: getfield int game.C_100102_w.field_104645_i
		// @060C: imul
		// @060D: iconst_2
		// @060E: iload #6
		// @0610: imul
		// @0611: idiv
		// @0612: ineg
		// @0613: aload_0
		// @0614: getfield int game.C_100102_w.field_104645_i
		// @0617: aload_0
		// @0618: getfield int game.C_100102_w.field_104656_x
		// @061B: iload #7
		// @061D: isub
		// @061E: iconst_m1
		// @061F: iadd
		// @0620: iload #5
		// @0622: imul
		// @0623: imul
		// @0624: iload #6
		// @0626: idiv
		// @0627: ineg
		// @0628: iload_2
		// @0629: iadd
		// @062A: iadd
		// @062B: iload_3
		// @062C: bipush 7 (0x07)
		// @062E: iadd
		// @062F: bipush 7 (0x07)
		// @0631: ldc 16711680 (0xff0000)
		// @0633: sipush 128 (0x0080)
		// @0636: invokestatic game.C_100196_rb.func_105796_c(int, int, int, int, int)void
		// @0639: iload #11
		// @063B: ifeq @07A2
		// @063E: aload_0
		// @063F: getfield int game.C_100102_w.field_104644_h
		// @0642: getstatic int game.C_100202_qi.field_105918_a
		// @0645: if_icmpne @0792
		// @0648: goto @064C
		// @064B: athrow
		// @064C: iload_2
		// @064D: iload_3
		// @064E: sipush -192 (0xFF40)
		// @0651: iadd
		// @0652: sipush 192 (0x00C0)
		// @0655: ldc 16777215 (0xffffff)
		// @0657: bipush 64 (0x40)
		// @0659: invokestatic game.C_100196_rb.func_105805_b(int, int, int, int, int)void
		// @065C: iload_2
		// @065D: bipush 64 (0x40)
		// @065F: isub
		// @0660: iload_3
		// @0661: sipush 192 (0x00C0)
		// @0664: isub
		// @0665: sipush 192 (0x00C0)
		// @0668: ldc 16777215 (0xffffff)
		// @066A: bipush 64 (0x40)
		// @066C: invokestatic game.C_100196_rb.func_105805_b(int, int, int, int, int)void
		// @066F: iload_2
		// @0670: bipush -64 (0xC0)
		// @0672: isub
		// @0673: sipush -192 (0xFF40)
		// @0676: iload_3
		// @0677: iadd
		// @0678: sipush 192 (0x00C0)
		// @067B: ldc 16777215 (0xffffff)
		// @067D: bipush 64 (0x40)
		// @067F: invokestatic game.C_100196_rb.func_105805_b(int, int, int, int, int)void
		// @0682: getstatic int[][][] game.C_100165_sh.field_100774_o
		// @0685: aload_0
		// @0686: getfield int game.C_100102_w.field_104633_d
		// @0689: bipush 59 (0x3B)
		// @068B: invokestatic game.C_100183_cd.func_103414_b(int, byte)int
		// @068E: aaload
		// @068F: bipush 25 (0x19)
		// @0691: aaload
		// @0692: bipush 7 (0x07)
		// @0694: iaload
		// @0695: istore #7
		// @0697: iload #5
		// @0699: aload_0
		// @069A: getfield int game.C_100102_w.field_104656_x
		// @069D: bipush -17 (0xEF)
		// @069F: iadd
		// @06A0: imul
		// @06A1: aload_0
		// @06A2: getfield int game.C_100102_w.field_104645_i
		// @06A5: imul
		// @06A6: iload #6
		// @06A8: idiv
		// @06A9: istore #8
		// @06AB: iload_2
		// @06AC: iload #8
		// @06AE: ineg
		// @06AF: iadd
		// @06B0: bipush 7 (0x07)
		// @06B2: iload_3
		// @06B3: iadd
		// @06B4: iload #8
		// @06B6: iadd
		// @06B7: bipush 7 (0x07)
		// @06B9: ldc 16777215 (0xffffff)
		// @06BB: sipush 256 (0x0100)
		// @06BE: aload_0
		// @06BF: getfield int game.C_100102_w.field_104656_x
		// @06C2: bipush -17 (0xEF)
		// @06C4: iadd
		// @06C5: imul
		// @06C6: iload #7
		// @06C8: idiv
		// @06C9: ineg
		// @06CA: sipush 255 (0x00FF)
		// @06CD: iadd
		// @06CE: invokestatic game.C_100196_rb.func_105796_c(int, int, int, int, int)void
		// @06D1: aload_0
		// @06D2: getfield int game.C_100102_w.field_104645_i
		// @06D5: bipush -17 (0xEF)
		// @06D7: aload_0
		// @06D8: getfield int game.C_100102_w.field_104656_x
		// @06DB: iadd
		// @06DC: imul
		// @06DD: iload #5
		// @06DF: imul
		// @06E0: iload #6
		// @06E2: idiv
		// @06E3: iload #7
		// @06E5: iload #5
		// @06E7: aload_0
		// @06E8: getfield int game.C_100102_w.field_104645_i
		// @06EB: imul
		// @06EC: imul
		// @06ED: iconst_2
		// @06EE: iload #6
		// @06F0: imul
		// @06F1: idiv
		// @06F2: ineg
		// @06F3: iadd
		// @06F4: istore #8
		// @06F6: iload #8
		// @06F8: ineg
		// @06F9: iload_2
		// @06FA: iadd
		// @06FB: bipush 7 (0x07)
		// @06FD: iload_3
		// @06FE: iadd
		// @06FF: iload #8
		// @0701: iadd
		// @0702: bipush 7 (0x07)
		// @0704: ldc 16711680 (0xff0000)
		// @0706: sipush 128 (0x0080)
		// @0709: invokestatic game.C_100196_rb.func_105796_c(int, int, int, int, int)void
		// @070C: aload_0
		// @070D: getfield int game.C_100102_w.field_104645_i
		// @0710: iload #5
		// @0712: aload_0
		// @0713: getfield int game.C_100102_w.field_104656_x
		// @0716: iload #7
		// @0718: ineg
		// @0719: iadd
		// @071A: bipush -17 (0xEF)
		// @071C: iadd
		// @071D: imul
		// @071E: imul
		// @071F: iload #6
		// @0721: idiv
		// @0722: istore #8
		// @0724: iload #8
		// @0726: ineg
		// @0727: iload_2
		// @0728: iadd
		// @0729: bipush 7 (0x07)
		// @072B: iload_3
		// @072C: iload #8
		// @072E: ineg
		// @072F: isub
		// @0730: iadd
		// @0731: bipush 7 (0x07)
		// @0733: ldc 16777215 (0xffffff)
		// @0735: sipush 256 (0x0100)
		// @0738: bipush -17 (0xEF)
		// @073A: aload_0
		// @073B: getfield int game.C_100102_w.field_104656_x
		// @073E: iload #7
		// @0740: ineg
		// @0741: iadd
		// @0742: iadd
		// @0743: imul
		// @0744: iload #7
		// @0746: idiv
		// @0747: sipush 255 (0x00FF)
		// @074A: iadd
		// @074B: invokestatic game.C_100196_rb.func_105796_c(int, int, int, int, int)void
		// @074E: iload #7
		// @0750: iload #5
		// @0752: aload_0
		// @0753: getfield int game.C_100102_w.field_104645_i
		// @0756: imul
		// @0757: imul
		// @0758: iconst_2
		// @0759: iload #6
		// @075B: imul
		// @075C: idiv
		// @075D: ineg
		// @075E: aload_0
		// @075F: getfield int game.C_100102_w.field_104656_x
		// @0762: iload #7
		// @0764: ineg
		// @0765: iadd
		// @0766: bipush -17 (0xEF)
		// @0768: iadd
		// @0769: iload #5
		// @076B: imul
		// @076C: aload_0
		// @076D: getfield int game.C_100102_w.field_104645_i
		// @0770: imul
		// @0771: iload #6
		// @0773: idiv
		// @0774: iadd
		// @0775: istore #8
		// @0777: iload #8
		// @0779: ineg
		// @077A: iload_2
		// @077B: iadd
		// @077C: iload #8
		// @077E: iload_3
		// @077F: iadd
		// @0780: bipush -7 (0xF9)
		// @0782: isub
		// @0783: bipush 7 (0x07)
		// @0785: ldc 16711680 (0xff0000)
		// @0787: sipush 128 (0x0080)
		// @078A: invokestatic game.C_100196_rb.func_105796_c(int, int, int, int, int)void
		// @078D: iload #11
		// @078F: ifeq @07A2
		// @0792: iload_2
		// @0793: iload_3
		// @0794: bipush -7 (0xF9)
		// @0796: isub
		// @0797: bipush 7 (0x07)
		// @0799: ldc 16777215 (0xffffff)
		// @079B: invokestatic game.C_100196_rb.func_105795_d(int, int, int, int)void
		// @079E: goto @07A2
		// @07A1: athrow
		// @07A2: getstatic game.C_100037_wb[] game.C_100254_pi.field_106468_p
		// @07A5: aload_0
		// @07A6: getfield int game.C_100102_w.field_104656_x
		// @07A9: aaload
		// @07AA: bipush -128 (0x80)
		// @07AC: iload_2
		// @07AD: iadd
		// @07AE: iload_3
		// @07AF: sipush -256 (0xFF00)
		// @07B2: iadd
		// @07B3: sipush 256 (0x0100)
		// @07B6: sipush 256 (0x0100)
		// @07B9: invokevirtual game.C_100037_wb.func_102364_d(int, int, int, int)void
		// @07BC: wide (iinc) #2 +320
		// @07C2: iload_1
		// @07C3: bipush -29 (0xE3)
		// @07C5: if_icmple @07D1
		// @07C8: bipush 48 (0x30)
		// @07CA: putstatic int game.C_100102_w.field_104648_u
		// @07CD: goto @07D1
		// @07D0: athrow
		// @07D1: aload_0
		// @07D2: getfield int game.C_100102_w.field_104644_h
		// @07D5: iconst_m1
		// @07D6: ixor
		// @07D7: getstatic int game.C_100202_qi.field_105918_a
		// @07DA: iconst_m1
		// @07DB: ixor
		// @07DC: if_icmpeq @07F7
		// @07DF: bipush -128 (0x80)
		// @07E1: iload_2
		// @07E2: iadd
		// @07E3: iload_3
		// @07E4: sipush 257 (0x0101)
		// @07E7: bipush 64 (0x40)
		// @07E9: ldc 3351057 (0x332211)
		// @07EB: invokestatic game.C_100196_rb.func_105782_i(int, int, int, int, int)void
		// @07EE: iload #11
		// @07F0: ifeq @083F
		// @07F3: goto @07F7
		// @07F6: athrow
		// @07F7: iconst_0
		// @07F8: istore #7
		// @07FA: bipush -65 (0xBF)
		// @07FC: iload #7
		// @07FE: iconst_m1
		// @07FF: ixor
		// @0800: if_icmpge @083F
		// @0803: iload #7
		// @0805: iconst_1
		// @0806: iand
		// @0807: iload_2
		// @0808: iadd
		// @0809: bipush -64 (0xC0)
		// @080B: iadd
		// @080C: iload #7
		// @080E: iconst_2
		// @080F: idiv
		// @0810: iload_3
		// @0811: iadd
		// @0812: bipush 64 (0x40)
		// @0814: iadd
		// @0815: sipush 128 (0x0080)
		// @0818: iload_2
		// @0819: iconst_1
		// @081A: iload #7
		// @081C: iand
		// @081D: iadd
		// @081E: iadd
		// @081F: iload #7
		// @0821: iconst_2
		// @0822: idiv
		// @0823: iload_3
		// @0824: iadd
		// @0825: sipush 128 (0x0080)
		// @0828: isub
		// @0829: ldc 3351057 (0x332211)
		// @082B: invokestatic game.C_100196_rb.func_105802_e(int, int, int, int, int)void
		// @082E: iinc #7 +1
		// @0831: iload #11
		// @0833: ifne @0842
		// @0836: iload #11
		// @0838: ifeq @07FA
		// @083B: goto @083F
		// @083E: athrow
		// @083F: invokestatic game.C_100196_rb.func_105781_a()void
		// @0842: aload_0
		// @0843: getfield int game.C_100102_w.field_104644_h
		// @0846: iconst_m1
		// @0847: ixor
		// @0848: getstatic int game.C_100151_bc.field_102940_Q
		// @084B: iconst_m1
		// @084C: ixor
		// @084D: if_icmpeq @0A7F
		// @0850: aload_0
		// @0851: getfield int game.C_100102_w.field_104644_h
		// @0854: iconst_m1
		// @0855: ixor
		// @0856: getstatic int game.C_100202_qi.field_105918_a
		// @0859: iconst_m1
		// @085A: ixor
		// @085B: if_icmpne @0A57
		// @085E: goto @0862
		// @0861: athrow
		// @0862: bipush -128 (0x80)
		// @0864: iload_2
		// @0865: iadd
		// @0866: sipush 130 (0x0082)
		// @0869: sipush 128 (0x0080)
		// @086C: iload_2
		// @086D: iadd
		// @086E: iload_3
		// @086F: invokestatic game.C_100196_rb.func_105815_h(int, int, int, int)void
		// @0872: iconst_m1
		// @0873: aload_0
		// @0874: getfield int game.C_100102_w.field_104634_e
		// @0877: iconst_m1
		// @0878: ixor
		// @0879: if_icmplt @0893
		// @087C: goto @0880
		// @087F: athrow
		// @0880: aload_0
		// @0881: getfield int game.C_100102_w.field_104634_e
		// @0884: aload_0
		// @0885: getfield game.C_100314_lf game.C_100102_w.field_104653_p
		// @0888: getfield game.C_100327_ib[] game.C_100314_lf.field_101314_E
		// @088B: arraylength
		// @088C: if_icmplt @08AA
		// @088F: goto @0893
		// @0892: athrow
		// @0893: aload_0
		// @0894: getfield game.C_100314_lf game.C_100102_w.field_104653_p
		// @0897: bipush -122 (0x86)
		// @0899: getstatic int game.C_100192_rf.field_101681_I
		// @089C: iload_3
		// @089D: aload_0
		// @089E: getfield int game.C_100102_w.field_104642_j
		// @08A1: iload_2
		// @08A2: iadd
		// @08A3: invokevirtual game.C_100314_lf.func_101245_b(int, int, int, int)void
		// @08A6: goto @08AA
		// @08A9: athrow
		// @08AA: aload_0
		// @08AB: getfield int game.C_100102_w.field_104643_k
		// @08AE: getstatic int game.C_100180_ce.field_104805_C
		// @08B1: if_icmpeq @08B8
		// @08B4: goto @0A4F
		// @08B7: athrow
		// @08B8: getstatic int[][][] game.C_100165_sh.field_100774_o
		// @08BB: aload_0
		// @08BC: getfield int game.C_100102_w.field_104633_d
		// @08BF: bipush 59 (0x3B)
		// @08C1: invokestatic game.C_100183_cd.func_103414_b(int, byte)int
		// @08C4: aaload
		// @08C5: bipush 25 (0x19)
		// @08C7: aaload
		// @08C8: bipush 7 (0x07)
		// @08CA: iaload
		// @08CB: istore #7
		// @08CD: iload_2
		// @08CE: iload_3
		// @08CF: sipush 192 (0x00C0)
		// @08D2: isub
		// @08D3: sipush 192 (0x00C0)
		// @08D6: ldc 16777215 (0xffffff)
		// @08D8: bipush 64 (0x40)
		// @08DA: invokestatic game.C_100196_rb.func_105805_b(int, int, int, int, int)void
		// @08DD: iload_2
		// @08DE: bipush 64 (0x40)
		// @08E0: isub
		// @08E1: sipush -192 (0xFF40)
		// @08E4: iload_3
		// @08E5: iadd
		// @08E6: sipush 192 (0x00C0)
		// @08E9: ldc 16777215 (0xffffff)
		// @08EB: bipush 64 (0x40)
		// @08ED: invokestatic game.C_100196_rb.func_105805_b(int, int, int, int, int)void
		// @08F0: iload_2
		// @08F1: bipush 64 (0x40)
		// @08F3: iadd
		// @08F4: iload_3
		// @08F5: sipush 192 (0x00C0)
		// @08F8: isub
		// @08F9: sipush 192 (0x00C0)
		// @08FC: ldc 16777215 (0xffffff)
		// @08FE: bipush 64 (0x40)
		// @0900: invokestatic game.C_100196_rb.func_105805_b(int, int, int, int, int)void
		// @0903: bipush -128 (0x80)
		// @0905: iload_2
		// @0906: iadd
		// @0907: iconst_0
		// @0908: iload_2
		// @0909: bipush -128 (0x80)
		// @090B: isub
		// @090C: sipush 480 (0x01E0)
		// @090F: invokestatic game.C_100196_rb.func_105815_h(int, int, int, int)void
		// @0912: iload_3
		// @0913: bipush -50 (0xCE)
		// @0915: aload_0
		// @0916: getfield game.C_100314_lf game.C_100102_w.field_104653_p
		// @0919: getfield int game.C_100314_lf.field_101388_sb
		// @091C: iadd
		// @091D: iload #5
		// @091F: imul
		// @0920: aload_0
		// @0921: getfield int game.C_100102_w.field_104645_i
		// @0924: imul
		// @0925: iload #6
		// @0927: bipush 50 (0x32)
		// @0929: imul
		// @092A: idiv
		// @092B: iadd
		// @092C: istore_3
		// @092D: iload_2
		// @092E: iload #5
		// @0930: bipush -50 (0xCE)
		// @0932: aload_0
		// @0933: getfield game.C_100314_lf game.C_100102_w.field_104653_p
		// @0936: getfield int game.C_100314_lf.field_101388_sb
		// @0939: iadd
		// @093A: aload_0
		// @093B: getfield int game.C_100102_w.field_104645_i
		// @093E: imul
		// @093F: imul
		// @0940: bipush 50 (0x32)
		// @0942: iload #6
		// @0944: imul
		// @0945: idiv
		// @0946: isub
		// @0947: istore_2
		// @0948: aload_0
		// @0949: getfield game.C_100314_lf game.C_100102_w.field_104653_p
		// @094C: getfield int game.C_100314_lf.field_101315_F
		// @094F: bipush -17 (0xEF)
		// @0951: iadd
		// @0952: iload #5
		// @0954: aload_0
		// @0955: getfield int game.C_100102_w.field_104645_i
		// @0958: imul
		// @0959: imul
		// @095A: iload #6
		// @095C: idiv
		// @095D: istore #8
		// @095F: iload #8
		// @0961: ineg
		// @0962: iload_2
		// @0963: iadd
		// @0964: bipush 7 (0x07)
		// @0966: iload_3
		// @0967: iload #8
		// @0969: ineg
		// @096A: isub
		// @096B: iadd
		// @096C: bipush 7 (0x07)
		// @096E: ldc 16777215 (0xffffff)
		// @0970: sipush 255 (0x00FF)
		// @0973: sipush 256 (0x0100)
		// @0976: bipush -17 (0xEF)
		// @0978: aload_0
		// @0979: getfield game.C_100314_lf game.C_100102_w.field_104653_p
		// @097C: getfield int game.C_100314_lf.field_101315_F
		// @097F: iadd
		// @0980: imul
		// @0981: iload #7
		// @0983: idiv
		// @0984: isub
		// @0985: invokestatic game.C_100196_rb.func_105796_c(int, int, int, int, int)void
		// @0988: bipush -17 (0xEF)
		// @098A: aload_0
		// @098B: getfield game.C_100314_lf game.C_100102_w.field_104653_p
		// @098E: getfield int game.C_100314_lf.field_101315_F
		// @0991: iadd
		// @0992: iload #5
		// @0994: imul
		// @0995: aload_0
		// @0996: getfield int game.C_100102_w.field_104645_i
		// @0999: imul
		// @099A: iload #6
		// @099C: idiv
		// @099D: iload #7
		// @099F: iload #5
		// @09A1: aload_0
		// @09A2: getfield int game.C_100102_w.field_104645_i
		// @09A5: imul
		// @09A6: imul
		// @09A7: iload #6
		// @09A9: iconst_2
		// @09AA: imul
		// @09AB: idiv
		// @09AC: isub
		// @09AD: istore #8
		// @09AF: iload #8
		// @09B1: ineg
		// @09B2: iload_2
		// @09B3: iadd
		// @09B4: iload #8
		// @09B6: bipush 7 (0x07)
		// @09B8: iadd
		// @09B9: iload_3
		// @09BA: iadd
		// @09BB: bipush 7 (0x07)
		// @09BD: ldc 16711680 (0xff0000)
		// @09BF: sipush 128 (0x0080)
		// @09C2: invokestatic game.C_100196_rb.func_105796_c(int, int, int, int, int)void
		// @09C5: bipush -17 (0xEF)
		// @09C7: aload_0
		// @09C8: getfield game.C_100314_lf game.C_100102_w.field_104653_p
		// @09CB: getfield int game.C_100314_lf.field_101315_F
		// @09CE: iload #7
		// @09D0: isub
		// @09D1: iadd
		// @09D2: iload #5
		// @09D4: aload_0
		// @09D5: getfield int game.C_100102_w.field_104645_i
		// @09D8: imul
		// @09D9: imul
		// @09DA: iload #6
		// @09DC: idiv
		// @09DD: istore #8
		// @09DF: iload #8
		// @09E1: ineg
		// @09E2: iload_2
		// @09E3: iadd
		// @09E4: iload #8
		// @09E6: iload_3
		// @09E7: iadd
		// @09E8: bipush -7 (0xF9)
		// @09EA: isub
		// @09EB: bipush 7 (0x07)
		// @09ED: ldc 16777215 (0xffffff)
		// @09EF: sipush 256 (0x0100)
		// @09F2: iload #7
		// @09F4: ineg
		// @09F5: aload_0
		// @09F6: getfield game.C_100314_lf game.C_100102_w.field_104653_p
		// @09F9: getfield int game.C_100314_lf.field_101315_F
		// @09FC: bipush -17 (0xEF)
		// @09FE: iadd
		// @09FF: iadd
		// @0A00: imul
		// @0A01: iload #7
		// @0A03: idiv
		// @0A04: sipush 255 (0x00FF)
		// @0A07: iadd
		// @0A08: invokestatic game.C_100196_rb.func_105796_c(int, int, int, int, int)void
		// @0A0B: iload #5
		// @0A0D: iload #7
		// @0A0F: aload_0
		// @0A10: getfield int game.C_100102_w.field_104645_i
		// @0A13: imul
		// @0A14: imul
		// @0A15: iload #6
		// @0A17: iconst_2
		// @0A18: imul
		// @0A19: idiv
		// @0A1A: ineg
		// @0A1B: aload_0
		// @0A1C: getfield game.C_100314_lf game.C_100102_w.field_104653_p
		// @0A1F: getfield int game.C_100314_lf.field_101315_F
		// @0A22: iload #7
		// @0A24: bipush -17 (0xEF)
		// @0A26: isub
		// @0A27: isub
		// @0A28: iload #5
		// @0A2A: imul
		// @0A2B: aload_0
		// @0A2C: getfield int game.C_100102_w.field_104645_i
		// @0A2F: imul
		// @0A30: iload #6
		// @0A32: idiv
		// @0A33: iadd
		// @0A34: istore #8
		// @0A36: iload_2
		// @0A37: iload #8
		// @0A39: ineg
		// @0A3A: iadd
		// @0A3B: iload #8
		// @0A3D: iload_3
		// @0A3E: bipush -7 (0xF9)
		// @0A40: isub
		// @0A41: iadd
		// @0A42: bipush 7 (0x07)
		// @0A44: ldc 16711680 (0xff0000)
		// @0A46: sipush 128 (0x0080)
		// @0A49: invokestatic game.C_100196_rb.func_105796_c(int, int, int, int, int)void
		// @0A4C: invokestatic game.C_100196_rb.func_105781_a()void
		// @0A4F: invokestatic game.C_100196_rb.func_105781_a()void
		// @0A52: iload #11
		// @0A54: ifeq @0C33
		// @0A57: bipush -128 (0x80)
		// @0A59: iload_2
		// @0A5A: iadd
		// @0A5B: sipush 130 (0x0082)
		// @0A5E: iload_2
		// @0A5F: sipush 128 (0x0080)
		// @0A62: iadd
		// @0A63: iload_3
		// @0A64: invokestatic game.C_100196_rb.func_105815_h(int, int, int, int)void
		// @0A67: invokestatic game.C_100196_rb.func_105781_a()void
		// @0A6A: iload_2
		// @0A6B: bipush 7 (0x07)
		// @0A6D: iload_3
		// @0A6E: iadd
		// @0A6F: bipush 7 (0x07)
		// @0A71: ldc 16777215 (0xffffff)
		// @0A73: invokestatic game.C_100196_rb.func_105795_d(int, int, int, int)void
		// @0A76: iload #11
		// @0A78: ifeq @0C33
		// @0A7B: goto @0A7F
		// @0A7E: athrow
		// @0A7F: iload_2
		// @0A80: bipush -128 (0x80)
		// @0A82: iadd
		// @0A83: sipush 130 (0x0082)
		// @0A86: iload_2
		// @0A87: bipush -128 (0x80)
		// @0A89: isub
		// @0A8A: iload_3
		// @0A8B: invokestatic game.C_100196_rb.func_105815_h(int, int, int, int)void
		// @0A8E: aload_0
		// @0A8F: getfield int game.C_100102_w.field_104634_e
		// @0A92: iconst_m1
		// @0A93: ixor
		// @0A94: iconst_m1
		// @0A95: if_icmpgt @0AB3
		// @0A98: goto @0A9C
		// @0A9B: athrow
		// @0A9C: aload_0
		// @0A9D: getfield game.C_100314_lf game.C_100102_w.field_104653_p
		// @0AA0: getfield game.C_100327_ib[] game.C_100314_lf.field_101314_E
		// @0AA3: arraylength
		// @0AA4: iconst_m1
		// @0AA5: ixor
		// @0AA6: aload_0
		// @0AA7: getfield int game.C_100102_w.field_104634_e
		// @0AAA: iconst_m1
		// @0AAB: ixor
		// @0AAC: if_icmplt @0ACA
		// @0AAF: goto @0AB3
		// @0AB2: athrow
		// @0AB3: aload_0
		// @0AB4: getfield game.C_100314_lf game.C_100102_w.field_104653_p
		// @0AB7: bipush -121 (0x87)
		// @0AB9: getstatic int game.C_100192_rf.field_101681_I
		// @0ABC: iload_3
		// @0ABD: iload_2
		// @0ABE: aload_0
		// @0ABF: getfield int game.C_100102_w.field_104642_j
		// @0AC2: iadd
		// @0AC3: invokevirtual game.C_100314_lf.func_101245_b(int, int, int, int)void
		// @0AC6: goto @0ACA
		// @0AC9: athrow
		// @0ACA: getstatic int game.C_100180_ce.field_104805_C
		// @0ACD: aload_0
		// @0ACE: getfield int game.C_100102_w.field_104643_k
		// @0AD1: if_icmpne @0C30
		// @0AD4: getstatic int[][][] game.C_100165_sh.field_100774_o
		// @0AD7: aload_0
		// @0AD8: getfield int game.C_100102_w.field_104633_d
		// @0ADB: bipush 59 (0x3B)
		// @0ADD: invokestatic game.C_100183_cd.func_103414_b(int, byte)int
		// @0AE0: aaload
		// @0AE1: bipush 25 (0x19)
		// @0AE3: aaload
		// @0AE4: iconst_3
		// @0AE5: iaload
		// @0AE6: istore #7
		// @0AE8: iload_2
		// @0AE9: sipush -192 (0xFF40)
		// @0AEC: iload_3
		// @0AED: iadd
		// @0AEE: sipush 192 (0x00C0)
		// @0AF1: ldc 16777215 (0xffffff)
		// @0AF3: bipush 64 (0x40)
		// @0AF5: invokestatic game.C_100196_rb.func_105805_b(int, int, int, int, int)void
		// @0AF8: bipush -64 (0xC0)
		// @0AFA: iload_2
		// @0AFB: iadd
		// @0AFC: sipush -192 (0xFF40)
		// @0AFF: iload_3
		// @0B00: iadd
		// @0B01: sipush 192 (0x00C0)
		// @0B04: ldc 16777215 (0xffffff)
		// @0B06: bipush 64 (0x40)
		// @0B08: invokestatic game.C_100196_rb.func_105805_b(int, int, int, int, int)void
		// @0B0B: iload_2
		// @0B0C: bipush 64 (0x40)
		// @0B0E: iadd
		// @0B0F: iload_3
		// @0B10: sipush 192 (0x00C0)
		// @0B13: isub
		// @0B14: sipush 192 (0x00C0)
		// @0B17: ldc 16777215 (0xffffff)
		// @0B19: bipush 64 (0x40)
		// @0B1B: invokestatic game.C_100196_rb.func_105805_b(int, int, int, int, int)void
		// @0B1E: bipush -128 (0x80)
		// @0B20: iload_2
		// @0B21: iadd
		// @0B22: iconst_0
		// @0B23: sipush 128 (0x0080)
		// @0B26: iload_2
		// @0B27: iadd
		// @0B28: sipush 480 (0x01E0)
		// @0B2B: invokestatic game.C_100196_rb.func_105815_h(int, int, int, int)void
		// @0B2E: iload_2
		// @0B2F: bipush -50 (0xCE)
		// @0B31: aload_0
		// @0B32: getfield game.C_100314_lf game.C_100102_w.field_104653_p
		// @0B35: getfield int game.C_100314_lf.field_101388_sb
		// @0B38: iadd
		// @0B39: iload #5
		// @0B3B: imul
		// @0B3C: aload_0
		// @0B3D: getfield int game.C_100102_w.field_104645_i
		// @0B40: imul
		// @0B41: bipush 50 (0x32)
		// @0B43: iload #6
		// @0B45: imul
		// @0B46: idiv
		// @0B47: isub
		// @0B48: istore_2
		// @0B49: iload_2
		// @0B4A: aload_0
		// @0B4B: getfield int game.C_100102_w.field_104645_i
		// @0B4E: iload #5
		// @0B50: aload_0
		// @0B51: getfield game.C_100314_lf game.C_100102_w.field_104653_p
		// @0B54: getfield int game.C_100314_lf.field_101315_F
		// @0B57: iconst_1
		// @0B58: isub
		// @0B59: imul
		// @0B5A: imul
		// @0B5B: iload #6
		// @0B5D: idiv
		// @0B5E: ineg
		// @0B5F: iadd
		// @0B60: iload_3
		// @0B61: bipush -7 (0xF9)
		// @0B63: isub
		// @0B64: bipush 7 (0x07)
		// @0B66: ldc 16777215 (0xffffff)
		// @0B68: sipush -256 (0xFF00)
		// @0B6B: sipush 256 (0x0100)
		// @0B6E: aload_0
		// @0B6F: getfield game.C_100314_lf game.C_100102_w.field_104653_p
		// @0B72: getfield int game.C_100314_lf.field_101315_F
		// @0B75: imul
		// @0B76: iadd
		// @0B77: iload #7
		// @0B79: idiv
		// @0B7A: ineg
		// @0B7B: sipush 255 (0x00FF)
		// @0B7E: iadd
		// @0B7F: invokestatic game.C_100196_rb.func_105796_c(int, int, int, int, int)void
		// @0B82: iload #5
		// @0B84: iconst_m1
		// @0B85: aload_0
		// @0B86: getfield game.C_100314_lf game.C_100102_w.field_104653_p
		// @0B89: getfield int game.C_100314_lf.field_101315_F
		// @0B8C: iadd
		// @0B8D: aload_0
		// @0B8E: getfield int game.C_100102_w.field_104645_i
		// @0B91: imul
		// @0B92: imul
		// @0B93: iload #6
		// @0B95: idiv
		// @0B96: ineg
		// @0B97: iload_2
		// @0B98: iload #7
		// @0B9A: iload #5
		// @0B9C: imul
		// @0B9D: aload_0
		// @0B9E: getfield int game.C_100102_w.field_104645_i
		// @0BA1: imul
		// @0BA2: iconst_2
		// @0BA3: iload #6
		// @0BA5: imul
		// @0BA6: idiv
		// @0BA7: isub
		// @0BA8: iadd
		// @0BA9: bipush 7 (0x07)
		// @0BAB: iload_3
		// @0BAC: iadd
		// @0BAD: bipush 7 (0x07)
		// @0BAF: ldc 16711680 (0xff0000)
		// @0BB1: sipush 128 (0x0080)
		// @0BB4: invokestatic game.C_100196_rb.func_105796_c(int, int, int, int, int)void
		// @0BB7: iload_2
		// @0BB8: aload_0
		// @0BB9: getfield int game.C_100102_w.field_104645_i
		// @0BBC: iload #7
		// @0BBE: ineg
		// @0BBF: aload_0
		// @0BC0: getfield game.C_100314_lf game.C_100102_w.field_104653_p
		// @0BC3: getfield int game.C_100314_lf.field_101315_F
		// @0BC6: iconst_m1
		// @0BC7: iadd
		// @0BC8: iadd
		// @0BC9: iload #5
		// @0BCB: imul
		// @0BCC: imul
		// @0BCD: iload #6
		// @0BCF: idiv
		// @0BD0: isub
		// @0BD1: bipush 7 (0x07)
		// @0BD3: iload_3
		// @0BD4: iadd
		// @0BD5: bipush 7 (0x07)
		// @0BD7: ldc 16777215 (0xffffff)
		// @0BD9: iconst_m1
		// @0BDA: aload_0
		// @0BDB: getfield game.C_100314_lf game.C_100102_w.field_104653_p
		// @0BDE: getfield int game.C_100314_lf.field_101315_F
		// @0BE1: iadd
		// @0BE2: iload #7
		// @0BE4: ineg
		// @0BE5: iadd
		// @0BE6: sipush 256 (0x0100)
		// @0BE9: imul
		// @0BEA: iload #7
		// @0BEC: idiv
		// @0BED: sipush 255 (0x00FF)
		// @0BF0: iadd
		// @0BF1: invokestatic game.C_100196_rb.func_105796_c(int, int, int, int, int)void
		// @0BF4: aload_0
		// @0BF5: getfield int game.C_100102_w.field_104645_i
		// @0BF8: iconst_m1
		// @0BF9: iload #7
		// @0BFB: ineg
		// @0BFC: aload_0
		// @0BFD: getfield game.C_100314_lf game.C_100102_w.field_104653_p
		// @0C00: getfield int game.C_100314_lf.field_101315_F
		// @0C03: iadd
		// @0C04: iadd
		// @0C05: imul
		// @0C06: iload #5
		// @0C08: imul
		// @0C09: iload #6
		// @0C0B: idiv
		// @0C0C: ineg
		// @0C0D: iload_2
		// @0C0E: aload_0
		// @0C0F: getfield int game.C_100102_w.field_104645_i
		// @0C12: iload #5
		// @0C14: iload #7
		// @0C16: imul
		// @0C17: imul
		// @0C18: iconst_2
		// @0C19: iload #6
		// @0C1B: imul
		// @0C1C: idiv
		// @0C1D: isub
		// @0C1E: iadd
		// @0C1F: bipush 7 (0x07)
		// @0C21: iload_3
		// @0C22: iadd
		// @0C23: bipush 7 (0x07)
		// @0C25: ldc 16711680 (0xff0000)
		// @0C27: sipush 128 (0x0080)
		// @0C2A: invokestatic game.C_100196_rb.func_105796_c(int, int, int, int, int)void
		// @0C2D: invokestatic game.C_100196_rb.func_105781_a()void
		// @0C30: invokestatic game.C_100196_rb.func_105781_a()void
		// @0C33: ldc ""
		// @0C35: astore #7
		// @0C37: new java.lang.StringBuilder
		// @0C3A: dup
		// @0C3B: invokespecial java.lang.StringBuilder.<init>()void
		// @0C3E: aload #7
		// @0C40: invokevirtual java.lang.StringBuilder.append(java.lang.String)java.lang.StringBuilder
		// @0C43: getstatic java.lang.String[] game.C_100102_w.field_104654_z
		// @0C46: bipush 19 (0x13)
		// @0C48: aaload
		// @0C49: invokevirtual java.lang.StringBuilder.append(java.lang.String)java.lang.StringBuilder
		// @0C4C: invokevirtual java.lang.StringBuilder.toString()java.lang.String
		// @0C4F: astore #7
		// @0C51: getstatic int game.C_100238_ol.field_101702_J
		// @0C54: iconst_m1
		// @0C55: ixor
		// @0C56: aload_0
		// @0C57: getfield int game.C_100102_w.field_104644_h
		// @0C5A: iconst_m1
		// @0C5B: ixor
		// @0C5C: if_icmpeq @0C63
		// @0C5F: goto @0C7D
		// @0C62: athrow
		// @0C63: new java.lang.StringBuilder
		// @0C66: dup
		// @0C67: invokespecial java.lang.StringBuilder.<init>()void
		// @0C6A: aload #7
		// @0C6C: invokevirtual java.lang.StringBuilder.append(java.lang.String)java.lang.StringBuilder
		// @0C6F: getstatic java.lang.String[] game.C_100102_w.field_104654_z
		// @0C72: bipush 26 (0x1A)
		// @0C74: aaload
		// @0C75: invokevirtual java.lang.StringBuilder.append(java.lang.String)java.lang.StringBuilder
		// @0C78: invokevirtual java.lang.StringBuilder.toString()java.lang.String
		// @0C7B: astore #7
		// @0C7D: new java.lang.StringBuilder
		// @0C80: dup
		// @0C81: invokespecial java.lang.StringBuilder.<init>()void
		// @0C84: aload #7
		// @0C86: invokevirtual java.lang.StringBuilder.append(java.lang.String)java.lang.StringBuilder
		// @0C89: getstatic java.lang.String[] game.C_100102_w.field_104654_z
		// @0C8C: bipush 15 (0x0F)
		// @0C8E: aaload
		// @0C8F: invokevirtual java.lang.StringBuilder.append(java.lang.String)java.lang.StringBuilder
		// @0C92: invokevirtual java.lang.StringBuilder.toString()java.lang.String
		// @0C95: astore #7
		// @0C97: aload_0
		// @0C98: getfield int game.C_100102_w.field_104644_h
		// @0C9B: iconst_m1
		// @0C9C: ixor
		// @0C9D: getstatic int game.C_100151_bc.field_102940_Q
		// @0CA0: iconst_m1
		// @0CA1: ixor
		// @0CA2: if_icmpne @0CBF
		// @0CA5: new java.lang.StringBuilder
		// @0CA8: dup
		// @0CA9: invokespecial java.lang.StringBuilder.<init>()void
		// @0CAC: aload #7
		// @0CAE: invokevirtual java.lang.StringBuilder.append(java.lang.String)java.lang.StringBuilder
		// @0CB1: getstatic java.lang.String[] game.C_100102_w.field_104654_z
		// @0CB4: bipush 26 (0x1A)
		// @0CB6: aaload
		// @0CB7: invokevirtual java.lang.StringBuilder.append(java.lang.String)java.lang.StringBuilder
		// @0CBA: invokevirtual java.lang.StringBuilder.toString()java.lang.String
		// @0CBD: astore #7
		// @0CBF: new java.lang.StringBuilder
		// @0CC2: dup
		// @0CC3: invokespecial java.lang.StringBuilder.<init>()void
		// @0CC6: aload #7
		// @0CC8: invokevirtual java.lang.StringBuilder.append(java.lang.String)java.lang.StringBuilder
		// @0CCB: getstatic java.lang.String[] game.C_100102_w.field_104654_z
		// @0CCE: bipush 16 (0x10)
		// @0CD0: aaload
		// @0CD1: invokevirtual java.lang.StringBuilder.append(java.lang.String)java.lang.StringBuilder
		// @0CD4: invokevirtual java.lang.StringBuilder.toString()java.lang.String
		// @0CD7: astore #7
		// @0CD9: getstatic int game.C_100001_ge.field_100574_i
		// @0CDC: iconst_m1
		// @0CDD: ixor
		// @0CDE: aload_0
		// @0CDF: getfield int game.C_100102_w.field_104644_h
		// @0CE2: iconst_m1
		// @0CE3: ixor
		// @0CE4: if_icmpne @0D01
		// @0CE7: new java.lang.StringBuilder
		// @0CEA: dup
		// @0CEB: invokespecial java.lang.StringBuilder.<init>()void
		// @0CEE: aload #7
		// @0CF0: invokevirtual java.lang.StringBuilder.append(java.lang.String)java.lang.StringBuilder
		// @0CF3: getstatic java.lang.String[] game.C_100102_w.field_104654_z
		// @0CF6: bipush 26 (0x1A)
		// @0CF8: aaload
		// @0CF9: invokevirtual java.lang.StringBuilder.append(java.lang.String)java.lang.StringBuilder
		// @0CFC: invokevirtual java.lang.StringBuilder.toString()java.lang.String
		// @0CFF: astore #7
		// @0D01: new java.lang.StringBuilder
		// @0D04: dup
		// @0D05: invokespecial java.lang.StringBuilder.<init>()void
		// @0D08: aload #7
		// @0D0A: invokevirtual java.lang.StringBuilder.append(java.lang.String)java.lang.StringBuilder
		// @0D0D: getstatic java.lang.String[] game.C_100102_w.field_104654_z
		// @0D10: bipush 18 (0x12)
		// @0D12: aaload
		// @0D13: invokevirtual java.lang.StringBuilder.append(java.lang.String)java.lang.StringBuilder
		// @0D16: invokevirtual java.lang.StringBuilder.toString()java.lang.String
		// @0D19: astore #7
		// @0D1B: getstatic int game.C_100048_vi.field_104186_q
		// @0D1E: aload_0
		// @0D1F: getfield int game.C_100102_w.field_104644_h
		// @0D22: if_icmpeq @0D29
		// @0D25: goto @0D43
		// @0D28: athrow
		// @0D29: new java.lang.StringBuilder
		// @0D2C: dup
		// @0D2D: invokespecial java.lang.StringBuilder.<init>()void
		// @0D30: aload #7
		// @0D32: invokevirtual java.lang.StringBuilder.append(java.lang.String)java.lang.StringBuilder
		// @0D35: getstatic java.lang.String[] game.C_100102_w.field_104654_z
		// @0D38: bipush 26 (0x1A)
		// @0D3A: aaload
		// @0D3B: invokevirtual java.lang.StringBuilder.append(java.lang.String)java.lang.StringBuilder
		// @0D3E: invokevirtual java.lang.StringBuilder.toString()java.lang.String
		// @0D41: astore #7
		// @0D43: new java.lang.StringBuilder
		// @0D46: dup
		// @0D47: invokespecial java.lang.StringBuilder.<init>()void
		// @0D4A: aload #7
		// @0D4C: invokevirtual java.lang.StringBuilder.append(java.lang.String)java.lang.StringBuilder
		// @0D4F: getstatic java.lang.String[] game.C_100102_w.field_104654_z
		// @0D52: bipush 29 (0x1D)
		// @0D54: aaload
		// @0D55: invokevirtual java.lang.StringBuilder.append(java.lang.String)java.lang.StringBuilder
		// @0D58: invokevirtual java.lang.StringBuilder.toString()java.lang.String
		// @0D5B: astore #7
		// @0D5D: aload_0
		// @0D5E: getfield int game.C_100102_w.field_104644_h
		// @0D61: getstatic int game.C_100202_qi.field_105918_a
		// @0D64: if_icmpeq @0D6B
		// @0D67: goto @0D85
		// @0D6A: athrow
		// @0D6B: new java.lang.StringBuilder
		// @0D6E: dup
		// @0D6F: invokespecial java.lang.StringBuilder.<init>()void
		// @0D72: aload #7
		// @0D74: invokevirtual java.lang.StringBuilder.append(java.lang.String)java.lang.StringBuilder
		// @0D77: getstatic java.lang.String[] game.C_100102_w.field_104654_z
		// @0D7A: bipush 26 (0x1A)
		// @0D7C: aaload
		// @0D7D: invokevirtual java.lang.StringBuilder.append(java.lang.String)java.lang.StringBuilder
		// @0D80: invokevirtual java.lang.StringBuilder.toString()java.lang.String
		// @0D83: astore #7
		// @0D85: new java.lang.StringBuilder
		// @0D88: dup
		// @0D89: invokespecial java.lang.StringBuilder.<init>()void
		// @0D8C: aload #7
		// @0D8E: invokevirtual java.lang.StringBuilder.append(java.lang.String)java.lang.StringBuilder
		// @0D91: getstatic java.lang.String[] game.C_100102_w.field_104654_z
		// @0D94: bipush 25 (0x19)
		// @0D96: aaload
		// @0D97: invokevirtual java.lang.StringBuilder.append(java.lang.String)java.lang.StringBuilder
		// @0D9A: invokevirtual java.lang.StringBuilder.toString()java.lang.String
		// @0D9D: astore #7
		// @0D9F: new java.lang.StringBuilder
		// @0DA2: dup
		// @0DA3: invokespecial java.lang.StringBuilder.<init>()void
		// @0DA6: aload #7
		// @0DA8: invokevirtual java.lang.StringBuilder.append(java.lang.String)java.lang.StringBuilder
		// @0DAB: getstatic java.lang.String[] game.C_100102_w.field_104654_z
		// @0DAE: bipush 33 (0x21)
		// @0DB0: aaload
		// @0DB1: invokevirtual java.lang.StringBuilder.append(java.lang.String)java.lang.StringBuilder
		// @0DB4: invokevirtual java.lang.StringBuilder.toString()java.lang.String
		// @0DB7: astore #7
		// @0DB9: aload_0
		// @0DBA: getfield int game.C_100102_w.field_104644_h
		// @0DBD: iconst_m1
		// @0DBE: ixor
		// @0DBF: getstatic int game.C_100151_bc.field_102940_Q
		// @0DC2: iconst_m1
		// @0DC3: ixor
		// @0DC4: if_icmpeq @0DCB
		// @0DC7: goto @0E91
		// @0DCA: athrow
		// @0DCB: new java.lang.StringBuilder
		// @0DCE: dup
		// @0DCF: invokespecial java.lang.StringBuilder.<init>()void
		// @0DD2: aload #7
		// @0DD4: invokevirtual java.lang.StringBuilder.append(java.lang.String)java.lang.StringBuilder
		// @0DD7: getstatic java.lang.String[] game.C_100102_w.field_104654_z
		// @0DDA: bipush 24 (0x18)
		// @0DDC: aaload
		// @0DDD: invokevirtual java.lang.StringBuilder.append(java.lang.String)java.lang.StringBuilder
		// @0DE0: invokevirtual java.lang.StringBuilder.toString()java.lang.String
		// @0DE3: astore #7
		// @0DE5: new java.lang.StringBuilder
		// @0DE8: dup
		// @0DE9: invokespecial java.lang.StringBuilder.<init>()void
		// @0DEC: aload #7
		// @0DEE: invokevirtual java.lang.StringBuilder.append(java.lang.String)java.lang.StringBuilder
		// @0DF1: getstatic java.lang.String[] game.C_100102_w.field_104654_z
		// @0DF4: bipush 28 (0x1C)
		// @0DF6: aaload
		// @0DF7: invokevirtual java.lang.StringBuilder.append(java.lang.String)java.lang.StringBuilder
		// @0DFA: iload #5
		// @0DFC: invokevirtual java.lang.StringBuilder.append(int)java.lang.StringBuilder
		// @0DFF: getstatic java.lang.String[] game.C_100102_w.field_104654_z
		// @0E02: bipush 21 (0x15)
		// @0E04: aaload
		// @0E05: invokevirtual java.lang.StringBuilder.append(java.lang.String)java.lang.StringBuilder
		// @0E08: invokevirtual java.lang.StringBuilder.toString()java.lang.String
		// @0E0B: astore #7
		// @0E0D: new java.lang.StringBuilder
		// @0E10: dup
		// @0E11: invokespecial java.lang.StringBuilder.<init>()void
		// @0E14: aload #7
		// @0E16: invokevirtual java.lang.StringBuilder.append(java.lang.String)java.lang.StringBuilder
		// @0E19: getstatic java.lang.String[] game.C_100102_w.field_104654_z
		// @0E1C: bipush 17 (0x11)
		// @0E1E: aaload
		// @0E1F: invokevirtual java.lang.StringBuilder.append(java.lang.String)java.lang.StringBuilder
		// @0E22: iconst_m1
		// @0E23: aload_0
		// @0E24: getfield int game.C_100102_w.field_104656_x
		// @0E27: iadd
		// @0E28: iconst_1
		// @0E29: iadd
		// @0E2A: invokevirtual java.lang.StringBuilder.append(int)java.lang.StringBuilder
		// @0E2D: getstatic java.lang.String[] game.C_100102_w.field_104654_z
		// @0E30: bipush 23 (0x17)
		// @0E32: aaload
		// @0E33: invokevirtual java.lang.StringBuilder.append(java.lang.String)java.lang.StringBuilder
		// @0E36: getstatic int[][][] game.C_100165_sh.field_100774_o
		// @0E39: aload_0
		// @0E3A: getfield int game.C_100102_w.field_104633_d
		// @0E3D: bipush 59 (0x3B)
		// @0E3F: invokestatic game.C_100183_cd.func_103414_b(int, byte)int
		// @0E42: aaload
		// @0E43: bipush 25 (0x19)
		// @0E45: aaload
		// @0E46: iconst_3
		// @0E47: iaload
		// @0E48: invokevirtual java.lang.StringBuilder.append(int)java.lang.StringBuilder
		// @0E4B: getstatic java.lang.String[] game.C_100102_w.field_104654_z
		// @0E4E: bipush 32 (0x20)
		// @0E50: aaload
		// @0E51: invokevirtual java.lang.StringBuilder.append(java.lang.String)java.lang.StringBuilder
		// @0E54: invokevirtual java.lang.StringBuilder.toString()java.lang.String
		// @0E57: astore #7
		// @0E59: new java.lang.StringBuilder
		// @0E5C: dup
		// @0E5D: invokespecial java.lang.StringBuilder.<init>()void
		// @0E60: aload #7
		// @0E62: invokevirtual java.lang.StringBuilder.append(java.lang.String)java.lang.StringBuilder
		// @0E65: getstatic java.lang.String[] game.C_100102_w.field_104654_z
		// @0E68: bipush 22 (0x16)
		// @0E6A: aaload
		// @0E6B: invokevirtual java.lang.StringBuilder.append(java.lang.String)java.lang.StringBuilder
		// @0E6E: getstatic int[][][] game.C_100165_sh.field_100774_o
		// @0E71: aload_0
		// @0E72: getfield int game.C_100102_w.field_104633_d
		// @0E75: bipush 59 (0x3B)
		// @0E77: invokestatic game.C_100183_cd.func_103414_b(int, byte)int
		// @0E7A: aaload
		// @0E7B: bipush 25 (0x19)
		// @0E7D: aaload
		// @0E7E: iconst_1
		// @0E7F: iaload
		// @0E80: invokevirtual java.lang.StringBuilder.append(int)java.lang.StringBuilder
		// @0E83: getstatic java.lang.String[] game.C_100102_w.field_104654_z
		// @0E86: bipush 31 (0x1F)
		// @0E88: aaload
		// @0E89: invokevirtual java.lang.StringBuilder.append(java.lang.String)java.lang.StringBuilder
		// @0E8C: invokevirtual java.lang.StringBuilder.toString()java.lang.String
		// @0E8F: astore #7
		// @0E91: getstatic int game.C_100001_ge.field_100574_i
		// @0E94: iconst_m1
		// @0E95: ixor
		// @0E96: aload_0
		// @0E97: getfield int game.C_100102_w.field_104644_h
		// @0E9A: iconst_m1
		// @0E9B: ixor
		// @0E9C: if_icmpne @0F7A
		// @0E9F: new java.lang.StringBuilder
		// @0EA2: dup
		// @0EA3: invokespecial java.lang.StringBuilder.<init>()void
		// @0EA6: aload #7
		// @0EA8: invokevirtual java.lang.StringBuilder.append(java.lang.String)java.lang.StringBuilder
		// @0EAB: getstatic java.lang.String[] game.C_100102_w.field_104654_z
		// @0EAE: bipush 20 (0x14)
		// @0EB0: aaload
		// @0EB1: invokevirtual java.lang.StringBuilder.append(java.lang.String)java.lang.StringBuilder
		// @0EB4: invokevirtual java.lang.StringBuilder.toString()java.lang.String
		// @0EB7: astore #7
		// @0EB9: new java.lang.StringBuilder
		// @0EBC: dup
		// @0EBD: invokespecial java.lang.StringBuilder.<init>()void
		// @0EC0: aload #7
		// @0EC2: invokevirtual java.lang.StringBuilder.append(java.lang.String)java.lang.StringBuilder
		// @0EC5: getstatic java.lang.String[] game.C_100102_w.field_104654_z
		// @0EC8: bipush 17 (0x11)
		// @0ECA: aaload
		// @0ECB: invokevirtual java.lang.StringBuilder.append(java.lang.String)java.lang.StringBuilder
		// @0ECE: iconst_1
		// @0ECF: aload_0
		// @0ED0: getfield int game.C_100102_w.field_104656_x
		// @0ED3: iadd
		// @0ED4: bipush -9 (0xF7)
		// @0ED6: iadd
		// @0ED7: invokevirtual java.lang.StringBuilder.append(int)java.lang.StringBuilder
		// @0EDA: getstatic java.lang.String[] game.C_100102_w.field_104654_z
		// @0EDD: bipush 23 (0x17)
		// @0EDF: aaload
		// @0EE0: invokevirtual java.lang.StringBuilder.append(java.lang.String)java.lang.StringBuilder
		// @0EE3: getstatic int[][][] game.C_100165_sh.field_100774_o
		// @0EE6: aload_0
		// @0EE7: getfield int game.C_100102_w.field_104633_d
		// @0EEA: bipush 59 (0x3B)
		// @0EEC: invokestatic game.C_100183_cd.func_103414_b(int, byte)int
		// @0EEF: aaload
		// @0EF0: bipush 25 (0x19)
		// @0EF2: aaload
		// @0EF3: iconst_4
		// @0EF4: iaload
		// @0EF5: invokevirtual java.lang.StringBuilder.append(int)java.lang.StringBuilder
		// @0EF8: getstatic java.lang.String[] game.C_100102_w.field_104654_z
		// @0EFB: bipush 32 (0x20)
		// @0EFD: aaload
		// @0EFE: invokevirtual java.lang.StringBuilder.append(java.lang.String)java.lang.StringBuilder
		// @0F01: invokevirtual java.lang.StringBuilder.toString()java.lang.String
		// @0F04: astore #7
		// @0F06: new java.lang.StringBuilder
		// @0F09: dup
		// @0F0A: invokespecial java.lang.StringBuilder.<init>()void
		// @0F0D: aload #7
		// @0F0F: invokevirtual java.lang.StringBuilder.append(java.lang.String)java.lang.StringBuilder
		// @0F12: getstatic java.lang.String[] game.C_100102_w.field_104654_z
		// @0F15: bipush 27 (0x1B)
		// @0F17: aaload
		// @0F18: invokevirtual java.lang.StringBuilder.append(java.lang.String)java.lang.StringBuilder
		// @0F1B: getstatic int[][][] game.C_100165_sh.field_100774_o
		// @0F1E: aload_0
		// @0F1F: getfield int game.C_100102_w.field_104633_d
		// @0F22: bipush 59 (0x3B)
		// @0F24: invokestatic game.C_100183_cd.func_103414_b(int, byte)int
		// @0F27: aaload
		// @0F28: bipush 25 (0x19)
		// @0F2A: aaload
		// @0F2B: iconst_2
		// @0F2C: iaload
		// @0F2D: bipush 50 (0x32)
		// @0F2F: idiv
		// @0F30: invokevirtual java.lang.StringBuilder.append(int)java.lang.StringBuilder
		// @0F33: ldc "."
		// @0F35: invokevirtual java.lang.StringBuilder.append(java.lang.String)java.lang.StringBuilder
		// @0F38: getstatic int[][][] game.C_100165_sh.field_100774_o
		// @0F3B: aload_0
		// @0F3C: getfield int game.C_100102_w.field_104633_d
		// @0F3F: bipush 59 (0x3B)
		// @0F41: invokestatic game.C_100183_cd.func_103414_b(int, byte)int
		// @0F44: aaload
		// @0F45: bipush 25 (0x19)
		// @0F47: aaload
		// @0F48: iconst_2
		// @0F49: iaload
		// @0F4A: iconst_5
		// @0F4B: idiv
		// @0F4C: bipush 10 (0x0A)
		// @0F4E: irem
		// @0F4F: invokevirtual java.lang.StringBuilder.append(int)java.lang.StringBuilder
		// @0F52: getstatic int[][][] game.C_100165_sh.field_100774_o
		// @0F55: aload_0
		// @0F56: getfield int game.C_100102_w.field_104633_d
		// @0F59: bipush 59 (0x3B)
		// @0F5B: invokestatic game.C_100183_cd.func_103414_b(int, byte)int
		// @0F5E: aaload
		// @0F5F: bipush 25 (0x19)
		// @0F61: aaload
		// @0F62: iconst_2
		// @0F63: iaload
		// @0F64: iconst_2
		// @0F65: imul
		// @0F66: bipush 10 (0x0A)
		// @0F68: irem
		// @0F69: invokevirtual java.lang.StringBuilder.append(int)java.lang.StringBuilder
		// @0F6C: getstatic java.lang.String[] game.C_100102_w.field_104654_z
		// @0F6F: bipush 30 (0x1E)
		// @0F71: aaload
		// @0F72: invokevirtual java.lang.StringBuilder.append(java.lang.String)java.lang.StringBuilder
		// @0F75: invokevirtual java.lang.StringBuilder.toString()java.lang.String
		// @0F78: astore #7
		// @0F7A: getstatic int game.C_100202_qi.field_105918_a
		// @0F7D: aload_0
		// @0F7E: getfield int game.C_100102_w.field_104644_h
		// @0F81: if_icmpeq @0F88
		// @0F84: goto @1051
		// @0F87: athrow
		// @0F88: new java.lang.StringBuilder
		// @0F8B: dup
		// @0F8C: invokespecial java.lang.StringBuilder.<init>()void
		// @0F8F: aload #7
		// @0F91: invokevirtual java.lang.StringBuilder.append(java.lang.String)java.lang.StringBuilder
		// @0F94: getstatic java.lang.String[] game.C_100102_w.field_104654_z
		// @0F97: bipush 24 (0x18)
		// @0F99: aaload
		// @0F9A: invokevirtual java.lang.StringBuilder.append(java.lang.String)java.lang.StringBuilder
		// @0F9D: invokevirtual java.lang.StringBuilder.toString()java.lang.String
		// @0FA0: astore #7
		// @0FA2: new java.lang.StringBuilder
		// @0FA5: dup
		// @0FA6: invokespecial java.lang.StringBuilder.<init>()void
		// @0FA9: aload #7
		// @0FAB: invokevirtual java.lang.StringBuilder.append(java.lang.String)java.lang.StringBuilder
		// @0FAE: getstatic java.lang.String[] game.C_100102_w.field_104654_z
		// @0FB1: bipush 28 (0x1C)
		// @0FB3: aaload
		// @0FB4: invokevirtual java.lang.StringBuilder.append(java.lang.String)java.lang.StringBuilder
		// @0FB7: iload #5
		// @0FB9: invokevirtual java.lang.StringBuilder.append(int)java.lang.StringBuilder
		// @0FBC: getstatic java.lang.String[] game.C_100102_w.field_104654_z
		// @0FBF: bipush 21 (0x15)
		// @0FC1: aaload
		// @0FC2: invokevirtual java.lang.StringBuilder.append(java.lang.String)java.lang.StringBuilder
		// @0FC5: invokevirtual java.lang.StringBuilder.toString()java.lang.String
		// @0FC8: astore #7
		// @0FCA: new java.lang.StringBuilder
		// @0FCD: dup
		// @0FCE: invokespecial java.lang.StringBuilder.<init>()void
		// @0FD1: aload #7
		// @0FD3: invokevirtual java.lang.StringBuilder.append(java.lang.String)java.lang.StringBuilder
		// @0FD6: getstatic java.lang.String[] game.C_100102_w.field_104654_z
		// @0FD9: bipush 17 (0x11)
		// @0FDB: aaload
		// @0FDC: invokevirtual java.lang.StringBuilder.append(java.lang.String)java.lang.StringBuilder
		// @0FDF: iconst_1
		// @0FE0: aload_0
		// @0FE1: getfield int game.C_100102_w.field_104656_x
		// @0FE4: bipush 17 (0x11)
		// @0FE6: isub
		// @0FE7: iadd
		// @0FE8: invokevirtual java.lang.StringBuilder.append(int)java.lang.StringBuilder
		// @0FEB: getstatic java.lang.String[] game.C_100102_w.field_104654_z
		// @0FEE: bipush 23 (0x17)
		// @0FF0: aaload
		// @0FF1: invokevirtual java.lang.StringBuilder.append(java.lang.String)java.lang.StringBuilder
		// @0FF4: getstatic int[][][] game.C_100165_sh.field_100774_o
		// @0FF7: aload_0
		// @0FF8: getfield int game.C_100102_w.field_104633_d
		// @0FFB: bipush 59 (0x3B)
		// @0FFD: invokestatic game.C_100183_cd.func_103414_b(int, byte)int
		// @1000: aaload
		// @1001: bipush 25 (0x19)
		// @1003: aaload
		// @1004: bipush 7 (0x07)
		// @1006: iaload
		// @1007: invokevirtual java.lang.StringBuilder.append(int)java.lang.StringBuilder
		// @100A: getstatic java.lang.String[] game.C_100102_w.field_104654_z
		// @100D: bipush 32 (0x20)
		// @100F: aaload
		// @1010: invokevirtual java.lang.StringBuilder.append(java.lang.String)java.lang.StringBuilder
		// @1013: invokevirtual java.lang.StringBuilder.toString()java.lang.String
		// @1016: astore #7
		// @1018: new java.lang.StringBuilder
		// @101B: dup
		// @101C: invokespecial java.lang.StringBuilder.<init>()void
		// @101F: aload #7
		// @1021: invokevirtual java.lang.StringBuilder.append(java.lang.String)java.lang.StringBuilder
		// @1024: getstatic java.lang.String[] game.C_100102_w.field_104654_z
		// @1027: bipush 22 (0x16)
		// @1029: aaload
		// @102A: invokevirtual java.lang.StringBuilder.append(java.lang.String)java.lang.StringBuilder
		// @102D: getstatic int[][][] game.C_100165_sh.field_100774_o
		// @1030: aload_0
		// @1031: getfield int game.C_100102_w.field_104633_d
		// @1034: bipush 59 (0x3B)
		// @1036: invokestatic game.C_100183_cd.func_103414_b(int, byte)int
		// @1039: aaload
		// @103A: bipush 25 (0x19)
		// @103C: aaload
		// @103D: bipush 6 (0x06)
		// @103F: iaload
		// @1040: invokevirtual java.lang.StringBuilder.append(int)java.lang.StringBuilder
		// @1043: getstatic java.lang.String[] game.C_100102_w.field_104654_z
		// @1046: bipush 31 (0x1F)
		// @1048: aaload
		// @1049: invokevirtual java.lang.StringBuilder.append(java.lang.String)java.lang.StringBuilder
		// @104C: invokevirtual java.lang.StringBuilder.toString()java.lang.String
		// @104F: astore #7
		// @1051: getstatic game.C_100317_lb game.C_100321_hi.field_107217_d
		// @1054: aload #7
		// @1056: bipush 8 (0x08)
		// @1058: bipush 8 (0x08)
		// @105A: sipush 624 (0x0270)
		// @105D: bipush 100 (0x64)
		// @105F: ldc 43724 (0xaacc)
		// @1061: iconst_0
		// @1062: iconst_0
		// @1063: iconst_0
		// @1064: bipush 12 (0x0C)
		// @1066: invokevirtual game.C_100317_lb.func_101729_a(java.lang.String, int, int, int, int, int, int, int, int, int)int
		// @1069: pop
		// @106A: goto @108F
		// @106D: astore_2
		// @106E: aload_2
		// @106F: new java.lang.StringBuilder
		// @1072: dup
		// @1073: invokespecial java.lang.StringBuilder.<init>()void
		// @1076: getstatic java.lang.String[] game.C_100102_w.field_104654_z
		// @1079: bipush 14 (0x0E)
		// @107B: aaload
		// @107C: invokevirtual java.lang.StringBuilder.append(java.lang.String)java.lang.StringBuilder
		// @107F: iload_1
		// @1080: invokevirtual java.lang.StringBuilder.append(int)java.lang.StringBuilder
		// @1083: bipush 41 (0x29)
		// @1085: invokevirtual java.lang.StringBuilder.append(char)java.lang.StringBuilder
		// @1088: invokevirtual java.lang.StringBuilder.toString()java.lang.String
		// @108B: invokestatic game.C_100181_cf.func_105695_a(java.lang.Throwable, java.lang.String)game.C_100170_cm
		// @108E: athrow
		// @108F: return
	}
	
	final void func_104624_a(int arg0)
	{
		// @000: getstatic int game.SteelSentinels.field_105275_O
		// @003: istore #5
		// @005: getstatic int game.C_100293_kj.field_106890_c
		// @008: bipush 16 (0x10)
		// @00A: if_icmpeq @011
		// @00D: goto @022
		// @010: athrow
		// @011: aload_0
		// @012: iconst_m1
		// @013: putfield int game.C_100102_w.field_104640_l
		// @016: aload_0
		// @017: iconst_0
		// @018: putfield int game.C_100102_w.field_104656_x
		// @01B: aload_0
		// @01C: getstatic int game.C_100238_ol.field_101702_J
		// @01F: putfield int game.C_100102_w.field_104644_h
		// @022: bipush 17 (0x11)
		// @024: getstatic int game.C_100293_kj.field_106890_c
		// @027: if_icmpne @03F
		// @02A: aload_0
		// @02B: iconst_1
		// @02C: putfield int game.C_100102_w.field_104656_x
		// @02F: aload_0
		// @030: iconst_m1
		// @031: putfield int game.C_100102_w.field_104640_l
		// @034: aload_0
		// @035: getstatic int game.C_100151_bc.field_102940_Q
		// @038: putfield int game.C_100102_w.field_104644_h
		// @03B: goto @03F
		// @03E: athrow
		// @03F: bipush 18 (0x12)
		// @041: getstatic int game.C_100293_kj.field_106890_c
		// @044: if_icmpne @05D
		// @047: aload_0
		// @048: getstatic int game.C_100001_ge.field_100574_i
		// @04B: putfield int game.C_100102_w.field_104644_h
		// @04E: aload_0
		// @04F: bipush 9 (0x09)
		// @051: putfield int game.C_100102_w.field_104656_x
		// @054: aload_0
		// @055: iconst_m1
		// @056: putfield int game.C_100102_w.field_104640_l
		// @059: goto @05D
		// @05C: athrow
		// @05D: bipush -20 (0xEC)
		// @05F: getstatic int game.C_100293_kj.field_106890_c
		// @062: iconst_m1
		// @063: ixor
		// @064: if_icmpne @07D
		// @067: aload_0
		// @068: bipush 14 (0x0E)
		// @06A: putfield int game.C_100102_w.field_104656_x
		// @06D: aload_0
		// @06E: iconst_m1
		// @06F: putfield int game.C_100102_w.field_104640_l
		// @072: aload_0
		// @073: getstatic int game.C_100048_vi.field_104186_q
		// @076: putfield int game.C_100102_w.field_104644_h
		// @079: goto @07D
		// @07C: athrow
		// @07D: getstatic int game.C_100293_kj.field_106890_c
		// @080: bipush 20 (0x14)
		// @082: if_icmpne @09B
		// @085: aload_0
		// @086: getstatic int game.C_100202_qi.field_105918_a
		// @089: putfield int game.C_100102_w.field_104644_h
		// @08C: aload_0
		// @08D: iconst_m1
		// @08E: putfield int game.C_100102_w.field_104640_l
		// @091: aload_0
		// @092: bipush 17 (0x11)
		// @094: putfield int game.C_100102_w.field_104656_x
		// @097: goto @09B
		// @09A: athrow
		// @09B: bipush 66 (0x42)
		// @09D: getstatic int game.C_100293_kj.field_106890_c
		// @0A0: if_icmpne @0AF
		// @0A3: aload_0
		// @0A4: aload_0
		// @0A5: getfield int game.C_100102_w.field_104656_x
		// @0A8: putfield int game.C_100102_w.field_104652_q
		// @0AB: goto @0AF
		// @0AE: athrow
		// @0AF: bipush -42 (0xD6)
		// @0B1: getstatic int game.C_100293_kj.field_106890_c
		// @0B4: iconst_m1
		// @0B5: ixor
		// @0B6: if_icmpne @175
		// @0B9: getstatic boolean[] game.C_100309_lk.field_103258_hb
		// @0BC: bipush 82 (0x52)
		// @0BE: baload
		// @0BF: ifeq @175
		// @0C2: goto @0C6
		// @0C5: athrow
		// @0C6: iconst_0
		// @0C7: aload_0
		// @0C8: getfield int game.C_100102_w.field_104652_q
		// @0CB: iconst_m1
		// @0CC: ixor
		// @0CD: if_icmpeq @175
		// @0D0: goto @0D4
		// @0D3: athrow
		// @0D4: iconst_0
		// @0D5: istore_2
		// @0D6: iload_2
		// @0D7: getstatic int[][][] game.C_100165_sh.field_100774_o
		// @0DA: aload_0
		// @0DB: getfield int game.C_100102_w.field_104633_d
		// @0DE: bipush 59 (0x3B)
		// @0E0: invokestatic game.C_100183_cd.func_103414_b(int, byte)int
		// @0E3: aaload
		// @0E4: aload_0
		// @0E5: getfield int game.C_100102_w.field_104656_x
		// @0E8: aaload
		// @0E9: arraylength
		// @0EA: if_icmpge @126
		// @0ED: getstatic int[][][] game.C_100165_sh.field_100774_o
		// @0F0: aload_0
		// @0F1: getfield int game.C_100102_w.field_104633_d
		// @0F4: bipush 59 (0x3B)
		// @0F6: invokestatic game.C_100183_cd.func_103414_b(int, byte)int
		// @0F9: aaload
		// @0FA: aload_0
		// @0FB: getfield int game.C_100102_w.field_104656_x
		// @0FE: aaload
		// @0FF: iload_2
		// @100: getstatic int[][][] game.C_100165_sh.field_100774_o
		// @103: aload_0
		// @104: getfield int game.C_100102_w.field_104633_d
		// @107: bipush 59 (0x3B)
		// @109: invokestatic game.C_100183_cd.func_103414_b(int, byte)int
		// @10C: aaload
		// @10D: aload_0
		// @10E: getfield int game.C_100102_w.field_104652_q
		// @111: aaload
		// @112: iload_2
		// @113: iaload
		// @114: iastore
		// @115: iinc #2 +1
		// @118: iload #5
		// @11A: ifne @16D
		// @11D: iload #5
		// @11F: ifeq @0D6
		// @122: goto @126
		// @125: athrow
		// @126: aload_0
		// @127: iconst_m1
		// @128: putfield int game.C_100102_w.field_104652_q
		// @12B: getstatic game.C_100037_wb[] game.C_100254_pi.field_106468_p
		// @12E: aload_0
		// @12F: getfield int game.C_100102_w.field_104656_x
		// @132: aaload
		// @133: invokevirtual game.C_100037_wb.func_102379_d()void
		// @136: invokestatic game.C_100196_rb.func_105792_b()void
		// @139: aload_0
		// @13A: getfield game.C_100314_lf game.C_100102_w.field_104653_p
		// @13D: aload_0
		// @13E: getfield int game.C_100102_w.field_104656_x
		// @141: putfield int game.C_100314_lf.field_101408_qb
		// @144: aload_0
		// @145: getfield game.C_100314_lf game.C_100102_w.field_104653_p
		// @148: aload_0
		// @149: getfield int game.C_100102_w.field_104656_x
		// @14C: putfield int game.C_100314_lf.field_101315_F
		// @14F: aload_0
		// @150: getfield game.C_100314_lf game.C_100102_w.field_104653_p
		// @153: aload_0
		// @154: getfield int game.C_100102_w.field_104633_d
		// @157: iconst_2
		// @158: invokevirtual game.C_100314_lf.func_101272_k(int, int)int[]
		// @15B: pop
		// @15C: aload_0
		// @15D: getfield game.C_100314_lf game.C_100102_w.field_104653_p
		// @160: bipush -123 (0x85)
		// @162: getstatic int game.C_100116_ei.field_104121_e
		// @165: sipush 128 (0x0080)
		// @168: bipush 64 (0x40)
		// @16A: invokevirtual game.C_100314_lf.func_101245_b(int, int, int, int)void
		// @16D: getstatic game.C_100185_rm game.C_100049_vf.field_104206_l
		// @170: bipush 126 (0x7E)
		// @172: invokevirtual game.C_100185_rm.func_105476_a(byte)void
		// @175: getstatic int game.C_100293_kj.field_106890_c
		// @178: bipush 65 (0x41)
		// @17A: if_icmpne @1F4
		// @17D: iconst_0
		// @17E: aload_0
		// @17F: getfield int game.C_100102_w.field_104640_l
		// @182: iconst_m1
		// @183: ixor
		// @184: if_icmpeq @1F4
		// @187: goto @18B
		// @18A: athrow
		// @18B: getstatic int[][][] game.C_100165_sh.field_100774_o
		// @18E: aload_0
		// @18F: getfield int game.C_100102_w.field_104633_d
		// @192: bipush 59 (0x3B)
		// @194: invokestatic game.C_100183_cd.func_103414_b(int, byte)int
		// @197: aaload
		// @198: aload_0
		// @199: getfield int game.C_100102_w.field_104656_x
		// @19C: aaload
		// @19D: aload_0
		// @19E: getfield int game.C_100102_w.field_104640_l
		// @1A1: aload_0
		// @1A2: getfield int game.C_100102_w.field_104650_s
		// @1A5: iastore
		// @1A6: getstatic game.C_100037_wb[] game.C_100254_pi.field_106468_p
		// @1A9: aload_0
		// @1AA: getfield int game.C_100102_w.field_104656_x
		// @1AD: aaload
		// @1AE: invokevirtual game.C_100037_wb.func_102379_d()void
		// @1B1: invokestatic game.C_100196_rb.func_105792_b()void
		// @1B4: aload_0
		// @1B5: getfield game.C_100314_lf game.C_100102_w.field_104653_p
		// @1B8: aload_0
		// @1B9: getfield int game.C_100102_w.field_104656_x
		// @1BC: putfield int game.C_100314_lf.field_101315_F
		// @1BF: aload_0
		// @1C0: getfield game.C_100314_lf game.C_100102_w.field_104653_p
		// @1C3: aload_0
		// @1C4: getfield int game.C_100102_w.field_104656_x
		// @1C7: putfield int game.C_100314_lf.field_101408_qb
		// @1CA: aload_0
		// @1CB: getfield game.C_100314_lf game.C_100102_w.field_104653_p
		// @1CE: aload_0
		// @1CF: getfield int game.C_100102_w.field_104633_d
		// @1D2: iconst_2
		// @1D3: invokevirtual game.C_100314_lf.func_101272_k(int, int)int[]
		// @1D6: pop
		// @1D7: aload_0
		// @1D8: getfield game.C_100314_lf game.C_100102_w.field_104653_p
		// @1DB: bipush -126 (0x82)
		// @1DD: getstatic int game.C_100116_ei.field_104121_e
		// @1E0: sipush 128 (0x0080)
		// @1E3: bipush 64 (0x40)
		// @1E5: invokevirtual game.C_100314_lf.func_101245_b(int, int, int, int)void
		// @1E8: getstatic game.C_100185_rm game.C_100049_vf.field_104206_l
		// @1EB: bipush 126 (0x7E)
		// @1ED: invokevirtual game.C_100185_rm.func_105476_a(byte)void
		// @1F0: goto @1F4
		// @1F3: athrow
		// @1F4: bipush -50 (0xCE)
		// @1F6: getstatic int game.C_100293_kj.field_106890_c
		// @1F9: iconst_m1
		// @1FA: ixor
		// @1FB: if_icmpeq @202
		// @1FE: goto @209
		// @201: athrow
		// @202: aload_0
		// @203: getstatic int game.C_100180_ce.field_104805_C
		// @206: putfield int game.C_100102_w.field_104643_k
		// @209: getstatic int game.C_100293_kj.field_106890_c
		// @20C: iconst_m1
		// @20D: ixor
		// @20E: bipush -71 (0xB9)
		// @210: if_icmpne @21E
		// @213: aload_0
		// @214: getstatic int game.C_100119_ua.field_104905_j
		// @217: putfield int game.C_100102_w.field_104643_k
		// @21A: goto @21E
		// @21D: athrow
		// @21E: getstatic int game.C_100293_kj.field_106890_c
		// @221: bipush 51 (0x33)
		// @223: if_icmpne @231
		// @226: aload_0
		// @227: getstatic int game.C_100309_lk.field_103267_Q
		// @22A: putfield int game.C_100102_w.field_104643_k
		// @22D: goto @231
		// @230: athrow
		// @231: iload_1
		// @232: sipush 320 (0x0140)
		// @235: if_icmpeq @246
		// @238: aconst_null
		// @239: checkcast int[]
		// @23C: iconst_1
		// @23D: bipush 69 (0x45)
		// @23F: invokestatic game.C_100102_w.func_104623_a(int[], boolean, int)void
		// @242: goto @246
		// @245: athrow
		// @246: bipush -42 (0xD6)
		// @248: getstatic int game.C_100293_kj.field_106890_c
		// @24B: iconst_m1
		// @24C: ixor
		// @24D: if_icmpne @313
		// @250: aload_0
		// @251: getfield int game.C_100102_w.field_104633_d
		// @254: bipush 59 (0x3B)
		// @256: invokestatic game.C_100183_cd.func_103414_b(int, byte)int
		// @259: istore_2
		// @25A: getstatic java.io.PrintStream java.lang.System.out
		// @25D: getstatic java.lang.String[] game.C_100102_w.field_104654_z
		// @260: iconst_5
		// @261: aaload
		// @262: invokevirtual java.io.PrintStream.println(java.lang.String)void
		// @265: getstatic java.io.PrintStream java.lang.System.out
		// @268: new java.lang.StringBuilder
		// @26B: dup
		// @26C: invokespecial java.lang.StringBuilder.<init>()void
		// @26F: getstatic java.lang.String[] game.C_100102_w.field_104654_z
		// @272: iconst_4
		// @273: aaload
		// @274: invokevirtual java.lang.StringBuilder.append(java.lang.String)java.lang.StringBuilder
		// @277: iload_2
		// @278: invokevirtual java.lang.StringBuilder.append(int)java.lang.StringBuilder
		// @27B: getstatic java.lang.String[] game.C_100102_w.field_104654_z
		// @27E: bipush 7 (0x07)
		// @280: aaload
		// @281: invokevirtual java.lang.StringBuilder.append(java.lang.String)java.lang.StringBuilder
		// @284: invokevirtual java.lang.StringBuilder.toString()java.lang.String
		// @287: invokevirtual java.io.PrintStream.println(java.lang.String)void
		// @28A: iconst_0
		// @28B: istore_3
		// @28C: bipush 26 (0x1A)
		// @28E: iload_3
		// @28F: if_icmple @313
		// @292: getstatic java.io.PrintStream java.lang.System.out
		// @295: new java.lang.StringBuilder
		// @298: dup
		// @299: invokespecial java.lang.StringBuilder.<init>()void
		// @29C: getstatic java.lang.String[] game.C_100102_w.field_104654_z
		// @29F: iconst_2
		// @2A0: aaload
		// @2A1: invokevirtual java.lang.StringBuilder.append(java.lang.String)java.lang.StringBuilder
		// @2A4: iload_3
		// @2A5: invokevirtual java.lang.StringBuilder.append(int)java.lang.StringBuilder
		// @2A8: getstatic java.lang.String[] game.C_100102_w.field_104654_z
		// @2AB: iconst_3
		// @2AC: aaload
		// @2AD: invokevirtual java.lang.StringBuilder.append(java.lang.String)java.lang.StringBuilder
		// @2B0: invokevirtual java.lang.StringBuilder.toString()java.lang.String
		// @2B3: invokevirtual java.io.PrintStream.print(java.lang.String)void
		// @2B6: iconst_0
		// @2B7: iload #5
		// @2B9: ifne @318
		// @2BC: istore #4
		// @2BE: iload #4
		// @2C0: iconst_m1
		// @2C1: ixor
		// @2C2: getstatic int[][][] game.C_100165_sh.field_100774_o
		// @2C5: iload_2
		// @2C6: aaload
		// @2C7: iload_3
		// @2C8: aaload
		// @2C9: arraylength
		// @2CA: iconst_m1
		// @2CB: ixor
		// @2CC: if_icmple @2FF
		// @2CF: iconst_m1
		// @2D0: iload #4
		// @2D2: iconst_m1
		// @2D3: ixor
		// @2D4: iload #5
		// @2D6: ifne @28F
		// @2D9: if_icmpgt @2DF
		// @2DC: goto @2E7
		// @2DF: getstatic java.io.PrintStream java.lang.System.out
		// @2E2: ldc ","
		// @2E4: invokevirtual java.io.PrintStream.print(java.lang.String)void
		// @2E7: getstatic java.io.PrintStream java.lang.System.out
		// @2EA: getstatic int[][][] game.C_100165_sh.field_100774_o
		// @2ED: iload_2
		// @2EE: aaload
		// @2EF: iload_3
		// @2F0: aaload
		// @2F1: iload #4
		// @2F3: iaload
		// @2F4: invokevirtual java.io.PrintStream.print(int)void
		// @2F7: iinc #4 +1
		// @2FA: iload #5
		// @2FC: ifeq @2BE
		// @2FF: getstatic java.io.PrintStream java.lang.System.out
		// @302: getstatic java.lang.String[] game.C_100102_w.field_104654_z
		// @305: bipush 8 (0x08)
		// @307: aaload
		// @308: invokevirtual java.io.PrintStream.println(java.lang.String)void
		// @30B: iinc #3 +1
		// @30E: iload #5
		// @310: ifeq @28C
		// @313: getstatic int game.C_100293_kj.field_106890_c
		// @316: iconst_m1
		// @317: ixor
		// @318: bipush -97 (0x9F)
		// @31A: if_icmpne @3F9
		// @31D: aload_0
		// @31E: iconst_m1
		// @31F: putfield int game.C_100102_w.field_104640_l
		// @322: aload_0
		// @323: dup
		// @324: getfield int game.C_100102_w.field_104656_x
		// @327: iconst_1
		// @328: isub
		// @329: putfield int game.C_100102_w.field_104656_x
		// @32C: getstatic int game.C_100238_ol.field_101702_J
		// @32F: aload_0
		// @330: getfield int game.C_100102_w.field_104644_h
		// @333: if_icmpeq @33E
		// @336: goto @33A
		// @339: athrow
		// @33A: goto @343
		// @33D: athrow
		// @33E: aload_0
		// @33F: iconst_0
		// @340: putfield int game.C_100102_w.field_104656_x
		// @343: getstatic int game.C_100151_bc.field_102940_Q
		// @346: iconst_m1
		// @347: ixor
		// @348: aload_0
		// @349: getfield int game.C_100102_w.field_104644_h
		// @34C: iconst_m1
		// @34D: ixor
		// @34E: if_icmpne @37C
		// @351: aload_0
		// @352: getfield int game.C_100102_w.field_104656_x
		// @355: iconst_1
		// @356: if_icmpge @37C
		// @359: goto @35D
		// @35C: athrow
		// @35D: aload_0
		// @35E: dup
		// @35F: getfield int game.C_100102_w.field_104656_x
		// @362: getstatic int[][][] game.C_100165_sh.field_100774_o
		// @365: aload_0
		// @366: getfield int game.C_100102_w.field_104633_d
		// @369: bipush 59 (0x3B)
		// @36B: invokestatic game.C_100183_cd.func_103414_b(int, byte)int
		// @36E: aaload
		// @36F: bipush 25 (0x19)
		// @371: aaload
		// @372: iconst_3
		// @373: iaload
		// @374: iadd
		// @375: putfield int game.C_100102_w.field_104656_x
		// @378: goto @37C
		// @37B: athrow
		// @37C: aload_0
		// @37D: getfield int game.C_100102_w.field_104644_h
		// @380: getstatic int game.C_100001_ge.field_100574_i
		// @383: if_icmpne @39D
		// @386: bipush 9 (0x09)
		// @388: aload_0
		// @389: getfield int game.C_100102_w.field_104656_x
		// @38C: if_icmpgt @397
		// @38F: goto @393
		// @392: athrow
		// @393: goto @39D
		// @396: athrow
		// @397: aload_0
		// @398: bipush 9 (0x09)
		// @39A: putfield int game.C_100102_w.field_104656_x
		// @39D: getstatic int game.C_100048_vi.field_104186_q
		// @3A0: iconst_m1
		// @3A1: ixor
		// @3A2: aload_0
		// @3A3: getfield int game.C_100102_w.field_104644_h
		// @3A6: iconst_m1
		// @3A7: ixor
		// @3A8: if_icmpne @3C2
		// @3AB: bipush 14 (0x0E)
		// @3AD: aload_0
		// @3AE: getfield int game.C_100102_w.field_104656_x
		// @3B1: if_icmple @3C2
		// @3B4: goto @3B8
		// @3B7: athrow
		// @3B8: aload_0
		// @3B9: bipush 14 (0x0E)
		// @3BB: putfield int game.C_100102_w.field_104656_x
		// @3BE: goto @3C2
		// @3C1: athrow
		// @3C2: getstatic int game.C_100202_qi.field_105918_a
		// @3C5: aload_0
		// @3C6: getfield int game.C_100102_w.field_104644_h
		// @3C9: if_icmpne @3F9
		// @3CC: bipush 17 (0x11)
		// @3CE: aload_0
		// @3CF: getfield int game.C_100102_w.field_104656_x
		// @3D2: if_icmple @3F9
		// @3D5: goto @3D9
		// @3D8: athrow
		// @3D9: aload_0
		// @3DA: dup
		// @3DB: getfield int game.C_100102_w.field_104656_x
		// @3DE: getstatic int[][][] game.C_100165_sh.field_100774_o
		// @3E1: aload_0
		// @3E2: getfield int game.C_100102_w.field_104633_d
		// @3E5: bipush 59 (0x3B)
		// @3E7: invokestatic game.C_100183_cd.func_103414_b(int, byte)int
		// @3EA: aaload
		// @3EB: bipush 25 (0x19)
		// @3ED: aaload
		// @3EE: bipush 7 (0x07)
		// @3F0: iaload
		// @3F1: iadd
		// @3F2: putfield int game.C_100102_w.field_104656_x
		// @3F5: goto @3F9
		// @3F8: athrow
		// @3F9: getstatic int game.C_100293_kj.field_106890_c
		// @3FC: iconst_m1
		// @3FD: ixor
		// @3FE: bipush -98 (0x9E)
		// @400: if_icmpne @53E
		// @403: aload_0
		// @404: dup
		// @405: getfield int game.C_100102_w.field_104656_x
		// @408: iconst_1
		// @409: iadd
		// @40A: putfield int game.C_100102_w.field_104656_x
		// @40D: aload_0
		// @40E: iconst_m1
		// @40F: putfield int game.C_100102_w.field_104640_l
		// @412: aload_0
		// @413: getfield int game.C_100102_w.field_104644_h
		// @416: iconst_m1
		// @417: ixor
		// @418: getstatic int game.C_100238_ol.field_101702_J
		// @41B: iconst_m1
		// @41C: ixor
		// @41D: if_icmpne @42D
		// @420: goto @424
		// @423: athrow
		// @424: aload_0
		// @425: iconst_0
		// @426: putfield int game.C_100102_w.field_104656_x
		// @429: goto @42D
		// @42C: athrow
		// @42D: getstatic int game.C_100151_bc.field_102940_Q
		// @430: aload_0
		// @431: getfield int game.C_100102_w.field_104644_h
		// @434: if_icmpne @479
		// @437: aload_0
		// @438: getfield int game.C_100102_w.field_104656_x
		// @43B: iconst_m1
		// @43C: ixor
		// @43D: iconst_1
		// @43E: getstatic int[][][] game.C_100165_sh.field_100774_o
		// @441: aload_0
		// @442: getfield int game.C_100102_w.field_104633_d
		// @445: bipush 59 (0x3B)
		// @447: invokestatic game.C_100183_cd.func_103414_b(int, byte)int
		// @44A: aaload
		// @44B: bipush 25 (0x19)
		// @44D: aaload
		// @44E: iconst_3
		// @44F: iaload
		// @450: iadd
		// @451: iconst_m1
		// @452: ixor
		// @453: if_icmpgt @479
		// @456: goto @45A
		// @459: athrow
		// @45A: aload_0
		// @45B: dup
		// @45C: getfield int game.C_100102_w.field_104656_x
		// @45F: getstatic int[][][] game.C_100165_sh.field_100774_o
		// @462: aload_0
		// @463: getfield int game.C_100102_w.field_104633_d
		// @466: bipush 59 (0x3B)
		// @468: invokestatic game.C_100183_cd.func_103414_b(int, byte)int
		// @46B: aaload
		// @46C: bipush 25 (0x19)
		// @46E: aaload
		// @46F: iconst_3
		// @470: iaload
		// @471: isub
		// @472: putfield int game.C_100102_w.field_104656_x
		// @475: goto @479
		// @478: athrow
		// @479: getstatic int game.C_100001_ge.field_100574_i
		// @47C: iconst_m1
		// @47D: ixor
		// @47E: aload_0
		// @47F: getfield int game.C_100102_w.field_104644_h
		// @482: iconst_m1
		// @483: ixor
		// @484: if_icmpne @4CA
		// @487: aload_0
		// @488: getfield int game.C_100102_w.field_104656_x
		// @48B: iconst_m1
		// @48C: ixor
		// @48D: getstatic int[][][] game.C_100165_sh.field_100774_o
		// @490: aload_0
		// @491: getfield int game.C_100102_w.field_104633_d
		// @494: bipush 59 (0x3B)
		// @496: invokestatic game.C_100183_cd.func_103414_b(int, byte)int
		// @499: aaload
		// @49A: bipush 25 (0x19)
		// @49C: aaload
		// @49D: iconst_4
		// @49E: iaload
		// @49F: bipush 9 (0x09)
		// @4A1: iadd
		// @4A2: iconst_m1
		// @4A3: ixor
		// @4A4: if_icmpgt @4CA
		// @4A7: goto @4AB
		// @4AA: athrow
		// @4AB: aload_0
		// @4AC: iconst_m1
		// @4AD: getstatic int[][][] game.C_100165_sh.field_100774_o
		// @4B0: aload_0
		// @4B1: getfield int game.C_100102_w.field_104633_d
		// @4B4: bipush 59 (0x3B)
		// @4B6: invokestatic game.C_100183_cd.func_103414_b(int, byte)int
		// @4B9: aaload
		// @4BA: bipush 25 (0x19)
		// @4BC: aaload
		// @4BD: iconst_4
		// @4BE: iaload
		// @4BF: iadd
		// @4C0: bipush 9 (0x09)
		// @4C2: iadd
		// @4C3: putfield int game.C_100102_w.field_104656_x
		// @4C6: goto @4CA
		// @4C9: athrow
		// @4CA: aload_0
		// @4CB: getfield int game.C_100102_w.field_104644_h
		// @4CE: iconst_m1
		// @4CF: ixor
		// @4D0: getstatic int game.C_100048_vi.field_104186_q
		// @4D3: iconst_m1
		// @4D4: ixor
		// @4D5: if_icmpne @4EF
		// @4D8: bipush 16 (0x10)
		// @4DA: aload_0
		// @4DB: getfield int game.C_100102_w.field_104656_x
		// @4DE: if_icmpge @4EF
		// @4E1: goto @4E5
		// @4E4: athrow
		// @4E5: aload_0
		// @4E6: bipush 16 (0x10)
		// @4E8: putfield int game.C_100102_w.field_104656_x
		// @4EB: goto @4EF
		// @4EE: athrow
		// @4EF: aload_0
		// @4F0: getfield int game.C_100102_w.field_104644_h
		// @4F3: iconst_m1
		// @4F4: ixor
		// @4F5: getstatic int game.C_100202_qi.field_105918_a
		// @4F8: iconst_m1
		// @4F9: ixor
		// @4FA: if_icmpne @53E
		// @4FD: aload_0
		// @4FE: getfield int game.C_100102_w.field_104656_x
		// @501: getstatic int[][][] game.C_100165_sh.field_100774_o
		// @504: aload_0
		// @505: getfield int game.C_100102_w.field_104633_d
		// @508: bipush 59 (0x3B)
		// @50A: invokestatic game.C_100183_cd.func_103414_b(int, byte)int
		// @50D: aaload
		// @50E: bipush 25 (0x19)
		// @510: aaload
		// @511: bipush 7 (0x07)
		// @513: iaload
		// @514: bipush 17 (0x11)
		// @516: iadd
		// @517: if_icmpge @522
		// @51A: goto @51E
		// @51D: athrow
		// @51E: goto @53E
		// @521: athrow
		// @522: aload_0
		// @523: dup
		// @524: getfield int game.C_100102_w.field_104656_x
		// @527: getstatic int[][][] game.C_100165_sh.field_100774_o
		// @52A: aload_0
		// @52B: getfield int game.C_100102_w.field_104633_d
		// @52E: bipush 59 (0x3B)
		// @530: invokestatic game.C_100183_cd.func_103414_b(int, byte)int
		// @533: aaload
		// @534: bipush 25 (0x19)
		// @536: aaload
		// @537: bipush 7 (0x07)
		// @539: iaload
		// @53A: isub
		// @53B: putfield int game.C_100102_w.field_104656_x
		// @53E: bipush 26 (0x1A)
		// @540: getstatic int game.C_100293_kj.field_106890_c
		// @543: if_icmpne @61F
		// @546: getstatic int game.C_100151_bc.field_102940_Q
		// @549: aload_0
		// @54A: getfield int game.C_100102_w.field_104644_h
		// @54D: if_icmpne @58D
		// @550: goto @554
		// @553: athrow
		// @554: getstatic int[][][] game.C_100165_sh.field_100774_o
		// @557: aload_0
		// @558: getfield int game.C_100102_w.field_104633_d
		// @55B: bipush 59 (0x3B)
		// @55D: invokestatic game.C_100183_cd.func_103414_b(int, byte)int
		// @560: aaload
		// @561: bipush 25 (0x19)
		// @563: aaload
		// @564: iconst_3
		// @565: iaload
		// @566: iconst_3
		// @567: if_icmpgt @572
		// @56A: goto @56E
		// @56D: athrow
		// @56E: goto @61F
		// @571: athrow
		// @572: getstatic int[][][] game.C_100165_sh.field_100774_o
		// @575: aload_0
		// @576: getfield int game.C_100102_w.field_104633_d
		// @579: bipush 59 (0x3B)
		// @57B: invokestatic game.C_100183_cd.func_103414_b(int, byte)int
		// @57E: aaload
		// @57F: bipush 25 (0x19)
		// @581: aaload
		// @582: iconst_3
		// @583: dup2
		// @584: iaload
		// @585: iconst_1
		// @586: isub
		// @587: iastore
		// @588: iload #5
		// @58A: ifeq @61F
		// @58D: aload_0
		// @58E: getfield int game.C_100102_w.field_104644_h
		// @591: getstatic int game.C_100001_ge.field_100574_i
		// @594: if_icmpeq @5E8
		// @597: goto @59B
		// @59A: athrow
		// @59B: aload_0
		// @59C: getfield int game.C_100102_w.field_104644_h
		// @59F: iconst_m1
		// @5A0: ixor
		// @5A1: getstatic int game.C_100202_qi.field_105918_a
		// @5A4: iconst_m1
		// @5A5: ixor
		// @5A6: if_icmpne @61F
		// @5A9: goto @5AD
		// @5AC: athrow
		// @5AD: iconst_3
		// @5AE: getstatic int[][][] game.C_100165_sh.field_100774_o
		// @5B1: aload_0
		// @5B2: getfield int game.C_100102_w.field_104633_d
		// @5B5: bipush 59 (0x3B)
		// @5B7: invokestatic game.C_100183_cd.func_103414_b(int, byte)int
		// @5BA: aaload
		// @5BB: bipush 25 (0x19)
		// @5BD: aaload
		// @5BE: bipush 7 (0x07)
		// @5C0: iaload
		// @5C1: if_icmpge @61F
		// @5C4: goto @5C8
		// @5C7: athrow
		// @5C8: getstatic int[][][] game.C_100165_sh.field_100774_o
		// @5CB: aload_0
		// @5CC: getfield int game.C_100102_w.field_104633_d
		// @5CF: bipush 59 (0x3B)
		// @5D1: invokestatic game.C_100183_cd.func_103414_b(int, byte)int
		// @5D4: aaload
		// @5D5: bipush 25 (0x19)
		// @5D7: aaload
		// @5D8: bipush 7 (0x07)
		// @5DA: dup2
		// @5DB: iaload
		// @5DC: iconst_1
		// @5DD: isub
		// @5DE: iastore
		// @5DF: iload #5
		// @5E1: ifeq @61F
		// @5E4: goto @5E8
		// @5E7: athrow
		// @5E8: bipush -2 (0xFE)
		// @5EA: getstatic int[][][] game.C_100165_sh.field_100774_o
		// @5ED: aload_0
		// @5EE: getfield int game.C_100102_w.field_104633_d
		// @5F1: bipush 59 (0x3B)
		// @5F3: invokestatic game.C_100183_cd.func_103414_b(int, byte)int
		// @5F6: aaload
		// @5F7: bipush 25 (0x19)
		// @5F9: aaload
		// @5FA: iconst_4
		// @5FB: iaload
		// @5FC: iconst_m1
		// @5FD: ixor
		// @5FE: if_icmple @61F
		// @601: goto @605
		// @604: athrow
		// @605: getstatic int[][][] game.C_100165_sh.field_100774_o
		// @608: aload_0
		// @609: getfield int game.C_100102_w.field_104633_d
		// @60C: bipush 59 (0x3B)
		// @60E: invokestatic game.C_100183_cd.func_103414_b(int, byte)int
		// @611: aaload
		// @612: bipush 25 (0x19)
		// @614: aaload
		// @615: iconst_4
		// @616: dup2
		// @617: iaload
		// @618: iconst_1
		// @619: isub
		// @61A: iastore
		// @61B: goto @61F
		// @61E: athrow
		// @61F: bipush -28 (0xE4)
		// @621: getstatic int game.C_100293_kj.field_106890_c
		// @624: iconst_m1
		// @625: ixor
		// @626: if_icmpeq @62D
		// @629: goto @706
		// @62C: athrow
		// @62D: getstatic int game.C_100151_bc.field_102940_Q
		// @630: aload_0
		// @631: getfield int game.C_100102_w.field_104644_h
		// @634: if_icmpne @671
		// @637: bipush 8 (0x08)
		// @639: getstatic int[][][] game.C_100165_sh.field_100774_o
		// @63C: aload_0
		// @63D: getfield int game.C_100102_w.field_104633_d
		// @640: bipush 59 (0x3B)
		// @642: invokestatic game.C_100183_cd.func_103414_b(int, byte)int
		// @645: aaload
		// @646: bipush 25 (0x19)
		// @648: aaload
		// @649: iconst_3
		// @64A: iaload
		// @64B: if_icmple @706
		// @64E: goto @652
		// @651: athrow
		// @652: getstatic int[][][] game.C_100165_sh.field_100774_o
		// @655: aload_0
		// @656: getfield int game.C_100102_w.field_104633_d
		// @659: bipush 59 (0x3B)
		// @65B: invokestatic game.C_100183_cd.func_103414_b(int, byte)int
		// @65E: aaload
		// @65F: bipush 25 (0x19)
		// @661: aaload
		// @662: iconst_3
		// @663: dup2
		// @664: iaload
		// @665: iconst_1
		// @666: iadd
		// @667: iastore
		// @668: iload #5
		// @66A: ifeq @706
		// @66D: goto @671
		// @670: athrow
		// @671: getstatic int game.C_100001_ge.field_100574_i
		// @674: aload_0
		// @675: getfield int game.C_100102_w.field_104644_h
		// @678: if_icmpeq @6CF
		// @67B: goto @67F
		// @67E: athrow
		// @67F: aload_0
		// @680: getfield int game.C_100102_w.field_104644_h
		// @683: iconst_m1
		// @684: ixor
		// @685: getstatic int game.C_100202_qi.field_105918_a
		// @688: iconst_m1
		// @689: ixor
		// @68A: if_icmpeq @695
		// @68D: goto @691
		// @690: athrow
		// @691: goto @706
		// @694: athrow
		// @695: getstatic int[][][] game.C_100165_sh.field_100774_o
		// @698: aload_0
		// @699: getfield int game.C_100102_w.field_104633_d
		// @69C: bipush 59 (0x3B)
		// @69E: invokestatic game.C_100183_cd.func_103414_b(int, byte)int
		// @6A1: aaload
		// @6A2: bipush 25 (0x19)
		// @6A4: aaload
		// @6A5: bipush 7 (0x07)
		// @6A7: iaload
		// @6A8: iconst_m1
		// @6A9: ixor
		// @6AA: bipush -9 (0xF7)
		// @6AC: if_icmpgt @6B3
		// @6AF: goto @706
		// @6B2: athrow
		// @6B3: getstatic int[][][] game.C_100165_sh.field_100774_o
		// @6B6: aload_0
		// @6B7: getfield int game.C_100102_w.field_104633_d
		// @6BA: bipush 59 (0x3B)
		// @6BC: invokestatic game.C_100183_cd.func_103414_b(int, byte)int
		// @6BF: aaload
		// @6C0: bipush 25 (0x19)
		// @6C2: aaload
		// @6C3: bipush 7 (0x07)
		// @6C5: dup2
		// @6C6: iaload
		// @6C7: iconst_1
		// @6C8: iadd
		// @6C9: iastore
		// @6CA: iload #5
		// @6CC: ifeq @706
		// @6CF: bipush -6 (0xFA)
		// @6D1: getstatic int[][][] game.C_100165_sh.field_100774_o
		// @6D4: aload_0
		// @6D5: getfield int game.C_100102_w.field_104633_d
		// @6D8: bipush 59 (0x3B)
		// @6DA: invokestatic game.C_100183_cd.func_103414_b(int, byte)int
		// @6DD: aaload
		// @6DE: bipush 25 (0x19)
		// @6E0: aaload
		// @6E1: iconst_4
		// @6E2: iaload
		// @6E3: iconst_m1
		// @6E4: ixor
		// @6E5: if_icmpge @706
		// @6E8: goto @6EC
		// @6EB: athrow
		// @6EC: getstatic int[][][] game.C_100165_sh.field_100774_o
		// @6EF: aload_0
		// @6F0: getfield int game.C_100102_w.field_104633_d
		// @6F3: bipush 59 (0x3B)
		// @6F5: invokestatic game.C_100183_cd.func_103414_b(int, byte)int
		// @6F8: aaload
		// @6F9: bipush 25 (0x19)
		// @6FB: aaload
		// @6FC: iconst_4
		// @6FD: dup2
		// @6FE: iaload
		// @6FF: iconst_1
		// @700: iadd
		// @701: iastore
		// @702: goto @706
		// @705: athrow
		// @706: bipush -72 (0xB8)
		// @708: getstatic int game.C_100293_kj.field_106890_c
		// @70B: iconst_m1
		// @70C: ixor
		// @70D: if_icmpeq @714
		// @710: goto @871
		// @713: athrow
		// @714: getstatic int game.C_100151_bc.field_102940_Q
		// @717: aload_0
		// @718: getfield int game.C_100102_w.field_104644_h
		// @71B: if_icmpeq @7F7
		// @71E: getstatic int game.C_100001_ge.field_100574_i
		// @721: aload_0
		// @722: getfield int game.C_100102_w.field_104644_h
		// @725: if_icmpne @765
		// @728: goto @72C
		// @72B: athrow
		// @72C: iconst_1
		// @72D: getstatic int[][][] game.C_100165_sh.field_100774_o
		// @730: aload_0
		// @731: getfield int game.C_100102_w.field_104633_d
		// @734: bipush 59 (0x3B)
		// @736: invokestatic game.C_100183_cd.func_103414_b(int, byte)int
		// @739: aaload
		// @73A: bipush 25 (0x19)
		// @73C: aaload
		// @73D: iconst_2
		// @73E: iaload
		// @73F: if_icmplt @74A
		// @742: goto @746
		// @745: athrow
		// @746: goto @871
		// @749: athrow
		// @74A: getstatic int[][][] game.C_100165_sh.field_100774_o
		// @74D: aload_0
		// @74E: getfield int game.C_100102_w.field_104633_d
		// @751: bipush 59 (0x3B)
		// @753: invokestatic game.C_100183_cd.func_103414_b(int, byte)int
		// @756: aaload
		// @757: bipush 25 (0x19)
		// @759: aaload
		// @75A: iconst_2
		// @75B: dup2
		// @75C: iaload
		// @75D: iconst_1
		// @75E: isub
		// @75F: iastore
		// @760: iload #5
		// @762: ifeq @871
		// @765: getstatic int game.C_100202_qi.field_105918_a
		// @768: aload_0
		// @769: getfield int game.C_100102_w.field_104644_h
		// @76C: if_icmpne @871
		// @76F: goto @773
		// @772: athrow
		// @773: getstatic boolean[] game.C_100309_lk.field_103258_hb
		// @776: bipush 81 (0x51)
		// @778: baload
		// @779: ifne @7BC
		// @77C: goto @780
		// @77F: athrow
		// @780: getstatic int[][][] game.C_100165_sh.field_100774_o
		// @783: aload_0
		// @784: getfield int game.C_100102_w.field_104633_d
		// @787: bipush 59 (0x3B)
		// @789: invokestatic game.C_100183_cd.func_103414_b(int, byte)int
		// @78C: aaload
		// @78D: bipush 25 (0x19)
		// @78F: aaload
		// @790: iconst_5
		// @791: iaload
		// @792: iconst_m1
		// @793: ixor
		// @794: bipush -2 (0xFE)
		// @796: if_icmpge @871
		// @799: goto @79D
		// @79C: athrow
		// @79D: getstatic int[][][] game.C_100165_sh.field_100774_o
		// @7A0: aload_0
		// @7A1: getfield int game.C_100102_w.field_104633_d
		// @7A4: bipush 59 (0x3B)
		// @7A6: invokestatic game.C_100183_cd.func_103414_b(int, byte)int
		// @7A9: aaload
		// @7AA: bipush 25 (0x19)
		// @7AC: aaload
		// @7AD: iconst_5
		// @7AE: dup2
		// @7AF: iaload
		// @7B0: iconst_1
		// @7B1: isub
		// @7B2: iastore
		// @7B3: iload #5
		// @7B5: ifeq @871
		// @7B8: goto @7BC
		// @7BB: athrow
		// @7BC: getstatic int[][][] game.C_100165_sh.field_100774_o
		// @7BF: aload_0
		// @7C0: getfield int game.C_100102_w.field_104633_d
		// @7C3: bipush 59 (0x3B)
		// @7C5: invokestatic game.C_100183_cd.func_103414_b(int, byte)int
		// @7C8: aaload
		// @7C9: bipush 25 (0x19)
		// @7CB: aaload
		// @7CC: bipush 6 (0x06)
		// @7CE: iaload
		// @7CF: iconst_1
		// @7D0: if_icmpgt @7DB
		// @7D3: goto @7D7
		// @7D6: athrow
		// @7D7: goto @871
		// @7DA: athrow
		// @7DB: getstatic int[][][] game.C_100165_sh.field_100774_o
		// @7DE: aload_0
		// @7DF: getfield int game.C_100102_w.field_104633_d
		// @7E2: bipush 59 (0x3B)
		// @7E4: invokestatic game.C_100183_cd.func_103414_b(int, byte)int
		// @7E7: aaload
		// @7E8: bipush 25 (0x19)
		// @7EA: aaload
		// @7EB: bipush 6 (0x06)
		// @7ED: dup2
		// @7EE: iaload
		// @7EF: iconst_1
		// @7F0: isub
		// @7F1: iastore
		// @7F2: iload #5
		// @7F4: ifeq @871
		// @7F7: getstatic boolean[] game.C_100309_lk.field_103258_hb
		// @7FA: bipush 81 (0x51)
		// @7FC: baload
		// @7FD: ifeq @83D
		// @800: goto @804
		// @803: athrow
		// @804: iconst_1
		// @805: getstatic int[][][] game.C_100165_sh.field_100774_o
		// @808: aload_0
		// @809: getfield int game.C_100102_w.field_104633_d
		// @80C: bipush 59 (0x3B)
		// @80E: invokestatic game.C_100183_cd.func_103414_b(int, byte)int
		// @811: aaload
		// @812: bipush 25 (0x19)
		// @814: aaload
		// @815: iconst_1
		// @816: iaload
		// @817: if_icmpge @871
		// @81A: goto @81E
		// @81D: athrow
		// @81E: getstatic int[][][] game.C_100165_sh.field_100774_o
		// @821: aload_0
		// @822: getfield int game.C_100102_w.field_104633_d
		// @825: bipush 59 (0x3B)
		// @827: invokestatic game.C_100183_cd.func_103414_b(int, byte)int
		// @82A: aaload
		// @82B: bipush 25 (0x19)
		// @82D: aaload
		// @82E: iconst_1
		// @82F: dup2
		// @830: iaload
		// @831: iconst_1
		// @832: isub
		// @833: iastore
		// @834: iload #5
		// @836: ifeq @871
		// @839: goto @83D
		// @83C: athrow
		// @83D: getstatic int[][][] game.C_100165_sh.field_100774_o
		// @840: aload_0
		// @841: getfield int game.C_100102_w.field_104633_d
		// @844: bipush 59 (0x3B)
		// @846: invokestatic game.C_100183_cd.func_103414_b(int, byte)int
		// @849: aaload
		// @84A: bipush 25 (0x19)
		// @84C: aaload
		// @84D: iconst_0
		// @84E: iaload
		// @84F: iconst_1
		// @850: if_icmple @871
		// @853: goto @857
		// @856: athrow
		// @857: getstatic int[][][] game.C_100165_sh.field_100774_o
		// @85A: aload_0
		// @85B: getfield int game.C_100102_w.field_104633_d
		// @85E: bipush 59 (0x3B)
		// @860: invokestatic game.C_100183_cd.func_103414_b(int, byte)int
		// @863: aaload
		// @864: bipush 25 (0x19)
		// @866: aaload
		// @867: iconst_0
		// @868: dup2
		// @869: iaload
		// @86A: iconst_1
		// @86B: isub
		// @86C: iastore
		// @86D: goto @871
		// @870: athrow
		// @871: getstatic int game.C_100293_kj.field_106890_c
		// @874: bipush 72 (0x48)
		// @876: if_icmpeq @87D
		// @879: goto @9EA
		// @87C: athrow
		// @87D: getstatic int game.C_100151_bc.field_102940_Q
		// @880: aload_0
		// @881: getfield int game.C_100102_w.field_104644_h
		// @884: if_icmpeq @96B
		// @887: getstatic int game.C_100001_ge.field_100574_i
		// @88A: aload_0
		// @88B: getfield int game.C_100102_w.field_104644_h
		// @88E: if_icmpne @8D1
		// @891: goto @895
		// @894: athrow
		// @895: bipush -101 (0x9B)
		// @897: getstatic int[][][] game.C_100165_sh.field_100774_o
		// @89A: aload_0
		// @89B: getfield int game.C_100102_w.field_104633_d
		// @89E: bipush 59 (0x3B)
		// @8A0: invokestatic game.C_100183_cd.func_103414_b(int, byte)int
		// @8A3: aaload
		// @8A4: bipush 25 (0x19)
		// @8A6: aaload
		// @8A7: iconst_2
		// @8A8: iaload
		// @8A9: iconst_m1
		// @8AA: ixor
		// @8AB: if_icmpge @9EA
		// @8AE: goto @8B2
		// @8B1: athrow
		// @8B2: getstatic int[][][] game.C_100165_sh.field_100774_o
		// @8B5: aload_0
		// @8B6: getfield int game.C_100102_w.field_104633_d
		// @8B9: bipush 59 (0x3B)
		// @8BB: invokestatic game.C_100183_cd.func_103414_b(int, byte)int
		// @8BE: aaload
		// @8BF: bipush 25 (0x19)
		// @8C1: aaload
		// @8C2: iconst_2
		// @8C3: dup2
		// @8C4: iaload
		// @8C5: iconst_1
		// @8C6: iadd
		// @8C7: iastore
		// @8C8: iload #5
		// @8CA: ifeq @9EA
		// @8CD: goto @8D1
		// @8D0: athrow
		// @8D1: getstatic int game.C_100202_qi.field_105918_a
		// @8D4: iconst_m1
		// @8D5: ixor
		// @8D6: aload_0
		// @8D7: getfield int game.C_100102_w.field_104644_h
		// @8DA: iconst_m1
		// @8DB: ixor
		// @8DC: if_icmpeq @8E7
		// @8DF: goto @8E3
		// @8E2: athrow
		// @8E3: goto @9EA
		// @8E6: athrow
		// @8E7: getstatic boolean[] game.C_100309_lk.field_103258_hb
		// @8EA: bipush 81 (0x51)
		// @8EC: baload
		// @8ED: ifeq @92E
		// @8F0: bipush -26 (0xE6)
		// @8F2: getstatic int[][][] game.C_100165_sh.field_100774_o
		// @8F5: aload_0
		// @8F6: getfield int game.C_100102_w.field_104633_d
		// @8F9: bipush 59 (0x3B)
		// @8FB: invokestatic game.C_100183_cd.func_103414_b(int, byte)int
		// @8FE: aaload
		// @8FF: bipush 25 (0x19)
		// @901: aaload
		// @902: bipush 6 (0x06)
		// @904: iaload
		// @905: iconst_m1
		// @906: ixor
		// @907: if_icmpge @9EA
		// @90A: goto @90E
		// @90D: athrow
		// @90E: getstatic int[][][] game.C_100165_sh.field_100774_o
		// @911: aload_0
		// @912: getfield int game.C_100102_w.field_104633_d
		// @915: bipush 59 (0x3B)
		// @917: invokestatic game.C_100183_cd.func_103414_b(int, byte)int
		// @91A: aaload
		// @91B: bipush 25 (0x19)
		// @91D: aaload
		// @91E: bipush 6 (0x06)
		// @920: dup2
		// @921: iaload
		// @922: iconst_1
		// @923: iadd
		// @924: iastore
		// @925: iload #5
		// @927: ifeq @9EA
		// @92A: goto @92E
		// @92D: athrow
		// @92E: sipush -257 (0xFEFF)
		// @931: getstatic int[][][] game.C_100165_sh.field_100774_o
		// @934: aload_0
		// @935: getfield int game.C_100102_w.field_104633_d
		// @938: bipush 59 (0x3B)
		// @93A: invokestatic game.C_100183_cd.func_103414_b(int, byte)int
		// @93D: aaload
		// @93E: bipush 25 (0x19)
		// @940: aaload
		// @941: iconst_5
		// @942: iaload
		// @943: iconst_m1
		// @944: ixor
		// @945: if_icmplt @950
		// @948: goto @94C
		// @94B: athrow
		// @94C: goto @9EA
		// @94F: athrow
		// @950: getstatic int[][][] game.C_100165_sh.field_100774_o
		// @953: aload_0
		// @954: getfield int game.C_100102_w.field_104633_d
		// @957: bipush 59 (0x3B)
		// @959: invokestatic game.C_100183_cd.func_103414_b(int, byte)int
		// @95C: aaload
		// @95D: bipush 25 (0x19)
		// @95F: aaload
		// @960: iconst_5
		// @961: dup2
		// @962: iaload
		// @963: iconst_1
		// @964: iadd
		// @965: iastore
		// @966: iload #5
		// @968: ifeq @9EA
		// @96B: getstatic boolean[] game.C_100309_lk.field_103258_hb
		// @96E: bipush 81 (0x51)
		// @970: baload
		// @971: ifne @9B3
		// @974: goto @978
		// @977: athrow
		// @978: getstatic int[][][] game.C_100165_sh.field_100774_o
		// @97B: aload_0
		// @97C: getfield int game.C_100102_w.field_104633_d
		// @97F: bipush 59 (0x3B)
		// @981: invokestatic game.C_100183_cd.func_103414_b(int, byte)int
		// @984: aaload
		// @985: bipush 25 (0x19)
		// @987: aaload
		// @988: iconst_0
		// @989: iaload
		// @98A: sipush 256 (0x0100)
		// @98D: if_icmpge @9EA
		// @990: goto @994
		// @993: athrow
		// @994: getstatic int[][][] game.C_100165_sh.field_100774_o
		// @997: aload_0
		// @998: getfield int game.C_100102_w.field_104633_d
		// @99B: bipush 59 (0x3B)
		// @99D: invokestatic game.C_100183_cd.func_103414_b(int, byte)int
		// @9A0: aaload
		// @9A1: bipush 25 (0x19)
		// @9A3: aaload
		// @9A4: iconst_0
		// @9A5: dup2
		// @9A6: iaload
		// @9A7: iconst_1
		// @9A8: iadd
		// @9A9: iastore
		// @9AA: iload #5
		// @9AC: ifeq @9EA
		// @9AF: goto @9B3
		// @9B2: athrow
		// @9B3: getstatic int[][][] game.C_100165_sh.field_100774_o
		// @9B6: aload_0
		// @9B7: getfield int game.C_100102_w.field_104633_d
		// @9BA: bipush 59 (0x3B)
		// @9BC: invokestatic game.C_100183_cd.func_103414_b(int, byte)int
		// @9BF: aaload
		// @9C0: bipush 25 (0x19)
		// @9C2: aaload
		// @9C3: iconst_1
		// @9C4: iaload
		// @9C5: iconst_m1
		// @9C6: ixor
		// @9C7: bipush -26 (0xE6)
		// @9C9: if_icmple @9EA
		// @9CC: goto @9D0
		// @9CF: athrow
		// @9D0: getstatic int[][][] game.C_100165_sh.field_100774_o
		// @9D3: aload_0
		// @9D4: getfield int game.C_100102_w.field_104633_d
		// @9D7: bipush 59 (0x3B)
		// @9D9: invokestatic game.C_100183_cd.func_103414_b(int, byte)int
		// @9DC: aaload
		// @9DD: bipush 25 (0x19)
		// @9DF: aaload
		// @9E0: iconst_1
		// @9E1: dup2
		// @9E2: iaload
		// @9E3: iconst_1
		// @9E4: iadd
		// @9E5: iastore
		// @9E6: goto @9EA
		// @9E9: athrow
		// @9EA: goto @A0F
		// @9ED: astore_2
		// @9EE: aload_2
		// @9EF: new java.lang.StringBuilder
		// @9F2: dup
		// @9F3: invokespecial java.lang.StringBuilder.<init>()void
		// @9F6: getstatic java.lang.String[] game.C_100102_w.field_104654_z
		// @9F9: bipush 6 (0x06)
		// @9FB: aaload
		// @9FC: invokevirtual java.lang.StringBuilder.append(java.lang.String)java.lang.StringBuilder
		// @9FF: iload_1
		// @A00: invokevirtual java.lang.StringBuilder.append(int)java.lang.StringBuilder
		// @A03: bipush 41 (0x29)
		// @A05: invokevirtual java.lang.StringBuilder.append(char)java.lang.StringBuilder
		// @A08: invokevirtual java.lang.StringBuilder.toString()java.lang.String
		// @A0B: invokestatic game.C_100181_cf.func_105695_a(java.lang.Throwable, java.lang.String)game.C_100170_cm
		// @A0E: athrow
		// @A0F: return
	}
	
	private C_100102_w() throws Throwable
	{
		// @00: aload_0
		// @01: invokespecial java.lang.Object.<init>()void
		// @04: new java.lang.Error
		// @07: dup
		// @08: invokespecial java.lang.Error.<init>()void
		// @0B: athrow
		// @0C: astore_1
		// @0D: aload_1
		// @0E: getstatic java.lang.String[] game.C_100102_w.field_104654_z
		// @11: bipush 13 (0x0D)
		// @13: aaload
		// @14: invokestatic game.C_100181_cf.func_105695_a(java.lang.Throwable, java.lang.String)game.C_100170_cm
		// @17: athrow
	}
	
	static
	{
		// @000: bipush 35 (0x23)
		// @002: anewarray java.lang.String
		// @005: dup
		// @006: iconst_0
		// @007: ldc "`3<\u0002"
		// @009: invokestatic game.C_100102_w.func_104627_z(java.lang.String)char[]
		// @00C: invokestatic game.C_100102_w.func_104625_z(char[])java.lang.String
		// @00F: aastore
		// @010: dup
		// @011: iconst_1
		// @012: ldc "`3;\u0002"
		// @014: invokestatic game.C_100102_w.func_104627_z(java.lang.String)char[]
		// @017: invokestatic game.C_100102_w.func_104625_z(char[])java.lang.String
		// @01A: aastore
		// @01B: dup
		// @01C: iconst_2
		// @01D: ldc "vs\u0010GHct\u0016Dr"
		// @01F: invokestatic game.C_100102_w.func_104627_z(java.lang.String)char[]
		// @022: invokestatic game.C_100102_w.func_104625_z(char[])java.lang.String
		// @025: aastore
		// @026: dup
		// @027: iconst_3
		// @028: ldc "J=D\nGrjYCGcF$Q"
		// @02A: invokestatic game.C_100102_w.func_104627_z(java.lang.String)char[]
		// @02D: invokestatic game.C_100102_w.func_104625_z(char[])java.lang.String
		// @030: aastore
		// @031: dup
		// @032: iconst_4
		// @033: ldc "~s\rqtL@YKG~p\u0018^@xsY\u0017\tdx\u0017^@yx\u0015KG~p\u0018^@xs\nq"
		// @035: invokestatic game.C_100102_w.func_104627_z(java.lang.String)char[]
		// @038: invokestatic game.C_100102_w.func_104625_z(char[])java.lang.String
		// @03B: aastore
		// @03C: dup
		// @03D: iconst_5
		// @03E: ldc "Gq\u001cKZr=\nOGs=\rBL7{\u0016FExj\u0010DN7y\u0018^H7i\u0016\n}sOYYF7u\u001c\nJvsYCGdx\u000b^\t~iYCGcrY^Ar=\u001eKDr<"
		// @040: invokestatic game.C_100102_w.func_104627_z(java.lang.String)char[]
		// @043: invokestatic game.C_100102_w.func_104625_z(char[])java.lang.String
		// @046: aastore
		// @047: dup
		// @048: bipush 6 (0x06)
		// @04A: ldc "`3=\u0002"
		// @04C: invokestatic game.C_100102_w.func_104627_z(java.lang.String)char[]
		// @04F: invokestatic game.C_100102_w.func_104625_z(char[])java.lang.String
		// @052: aastore
		// @053: dup
		// @054: bipush 7 (0x07)
		// @056: ldc "J&"
		// @058: invokestatic game.C_100102_w.func_104627_z(java.lang.String)char[]
		// @05B: invokestatic game.C_100102_w.func_104625_z(char[])java.lang.String
		// @05E: aastore
		// @05F: dup
		// @060: bipush 8 (0x08)
		// @062: ldc "j&"
		// @064: invokestatic game.C_100102_w.func_104627_z(java.lang.String)char[]
		// @067: invokestatic game.C_100102_w.func_104625_z(char[])java.lang.String
		// @06A: aastore
		// @06B: dup
		// @06C: bipush 9 (0x09)
		// @06E: ldc "l3W\u0004T"
		// @070: invokestatic game.C_100102_w.func_104627_z(java.lang.String)char[]
		// @073: invokestatic game.C_100102_w.func_104625_z(char[])java.lang.String
		// @076: aastore
		// @077: dup
		// @078: bipush 10 (0x0A)
		// @07A: ldc "yh\u0015F"
		// @07C: invokestatic game.C_100102_w.func_104627_z(java.lang.String)char[]
		// @07F: invokestatic game.C_100102_w.func_104625_z(char[])java.lang.String
		// @082: aastore
		// @083: dup
		// @084: bipush 11 (0x0B)
		// @086: ldc "`3:\u0002"
		// @088: invokestatic game.C_100102_w.func_104627_z(java.lang.String)char[]
		// @08B: invokestatic game.C_100102_w.func_104625_z(char[])java.lang.String
		// @08E: aastore
		// @08F: dup
		// @090: bipush 12 (0x0C)
		// @092: ldc "`3?\u0002"
		// @094: invokestatic game.C_100102_w.func_104627_z(java.lang.String)char[]
		// @097: invokestatic game.C_100102_w.func_104625_z(char[])java.lang.String
		// @09A: aastore
		// @09B: dup
		// @09C: bipush 13 (0x0D)
		// @09E: ldc "`3ECG~iG\u0002\u0000"
		// @0A0: invokestatic game.C_100102_w.func_104627_z(java.lang.String)char[]
		// @0A3: invokestatic game.C_100102_w.func_104625_z(char[])java.lang.String
		// @0A6: aastore
		// @0A7: dup
		// @0A8: bipush 14 (0x0E)
		// @0AA: ldc "`38\u0002"
		// @0AC: invokestatic game.C_100102_w.func_104627_z(java.lang.String)char[]
		// @0AF: invokestatic game.C_100102_w.func_104625_z(char[])java.lang.String
		// @0B2: aastore
		// @0B3: dup
		// @0B4: bipush 15 (0x0F)
		// @0B6: ldc "&=T\nlst\r\n@sq\u001c\nHyt\u0014\u0016\u0006tr\u0015\u0014\u0015uoG"
		// @0B8: invokestatic game.C_100102_w.func_104627_z(java.lang.String)char[]
		// @0BB: invokestatic game.C_100102_w.func_104625_z(char[])java.lang.String
		// @0BE: aastore
		// @0BF: dup
		// @0C0: bipush 16 (0x10)
		// @0C2: ldc "%=T\nlst\r\n^vq\u0012\nHyt\u0014\u0016\u0006tr\u0015\u0014\u0015uoG"
		// @0C4: invokestatic game.C_100102_w.func_104627_z(java.lang.String)char[]
		// @0C7: invokestatic game.C_100102_w.func_104625_z(char[])java.lang.String
		// @0CA: aastore
		// @0CB: dup
		// @0CC: bipush 17 (0x11)
		// @0CE: ldc "Qo\u0018GL7 Y"
		// @0D0: invokestatic game.C_100102_w.func_104627_z(java.lang.String)char[]
		// @0D3: invokestatic game.C_100102_w.func_104625_z(char[])java.lang.String
		// @0D6: aastore
		// @0D7: dup
		// @0D8: bipush 18 (0x12)
		// @0DA: ldc "$=T\nlst\r\nCbp\t\nHyt\u0014\u0016\u0006tr\u0015\u0014\u0015uoG"
		// @0DC: invokestatic game.C_100102_w.func_104627_z(java.lang.String)char[]
		// @0DF: invokestatic game.C_100102_w.func_104625_z(char[])java.lang.String
		// @0E2: aastore
		// @0E3: dup
		// @0E4: bipush 19 (0x13)
		// @0E6: ldc "Vs\u0010GHct\u0016D\tRy\u0010^Fe!\u001bX\u0017G=T\nyet\u0017^\ts|\rK\tcrYIFyn\u0016FL+\u007f\u000b\u0014"
		// @0E8: invokestatic game.C_100102_w.func_104627_z(java.lang.String)char[]
		// @0EB: invokestatic game.C_100102_w.func_104625_z(char[])java.lang.String
		// @0EE: aastore
		// @0EF: dup
		// @0F0: bipush 20 (0x14)
		// @0F2: ldc "D=T\nZ\u007fr\u000e\n]ex\u0018ND~q\u0015\nHyt\u0014K]~r\u0017\u0016Ke#4\n\u00047n\u0011E^7p\u0016\\@yzYKG~p\u0018^@xsEH[)"
		// @0F4: invokestatic game.C_100102_w.func_104627_z(java.lang.String)char[]
		// @0F7: invokestatic game.C_100102_w.func_104625_z(char[])java.lang.String
		// @0FA: aastore
		// @0FB: dup
		// @0FC: bipush 21 (0x15)
		// @0FE: ldc "75EF])=\u0018DM7!\u001e^\u00177i\u0016\nJ\u007f|\u0017ML>!\u001bX\u0017"
		// @100: invokestatic game.C_100102_w.func_104627_z(java.lang.String)char[]
		// @103: invokestatic game.C_100102_w.func_104625_z(char[])java.lang.String
		// @106: aastore
		// @107: dup
		// @108: bipush 22 (0x16)
		// @10A: ldc "QM*\n\u00147"
		// @10C: invokestatic game.C_100102_w.func_104627_z(java.lang.String)char[]
		// @10F: invokestatic game.C_100102_w.func_104625_z(char[])java.lang.String
		// @112: aastore
		// @113: dup
		// @114: bipush 23 (0x17)
		// @116: ldc "7r\u001f\n"
		// @118: invokestatic game.C_100102_w.func_104627_z(java.lang.String)char[]
		// @11B: invokestatic game.C_100102_w.func_104625_z(char[])java.lang.String
		// @11E: aastore
		// @11F: dup
		// @120: bipush 24 (0x18)
		// @122: ldc "D=T\nZ\u007fr\u000e\n]ex\u0018ND~q\u0015\nHyt\u0014K]~r\u0017\u0016Ke#4\n\u00047n\u0011E^7p\u0016\\@yzYKG~p\u0018^@xsEH[)[Y\u0007\tdu\u0016]\tdi\u0010FE7{\u000bKDr!\u001bX\u0017"
		// @124: invokestatic game.C_100102_w.func_104627_z(java.lang.String)char[]
		// @127: invokestatic game.C_100102_w.func_104625_z(char[])java.lang.String
		// @12A: aastore
		// @12B: dup
		// @12C: bipush 25 (0x19)
		// @12E: ldc "\"=T\nlst\r\nJ{t\u0014H\tvs\u0010G\u00158~\u0016F\u0017+\u007f\u000b\u0014"
		// @130: invokestatic game.C_100102_w.func_104627_z(java.lang.String)char[]
		// @133: invokestatic game.C_100102_w.func_104625_z(char[])java.lang.String
		// @136: aastore
		// @137: dup
		// @138: bipush 26 (0x1A)
		// @13A: ldc "+~\u0016F\u0014q{\u001fLOq#"
		// @13C: invokestatic game.C_100102_w.func_104627_z(java.lang.String)char[]
		// @13F: invokestatic game.C_100102_w.func_104625_z(char[])java.lang.String
		// @142: aastore
		// @143: dup
		// @144: bipush 27 (0x1B)
		// @146: ldc "]h\u0014Z\tVs\u0010GHct\u0016D\tCt\u0014O\t*="
		// @148: invokestatic game.C_100102_w.func_104627_z(java.lang.String)char[]
		// @14B: invokestatic game.C_100102_w.func_104625_z(char[])java.lang.String
		// @14E: aastore
		// @14F: dup
		// @150: bipush 28 (0x1C)
		// @152: ldc "Dm\u001cOM7 Y"
		// @154: invokestatic game.C_100102_w.func_104627_z(java.lang.String)char[]
		// @157: invokestatic game.C_100102_w.func_104625_z(char[])java.lang.String
		// @15A: aastore
		// @15B: dup
		// @15C: bipush 29 (0x1D)
		// @15E: ldc "#=T\nlst\r\nH~oYKG~pE\u0005JxqG\u0016Ke#"
		// @160: invokestatic game.C_100102_w.func_104627_z(java.lang.String)char[]
		// @163: invokestatic game.C_100102_w.func_104625_z(char[])java.lang.String
		// @166: aastore
		// @167: dup
		// @168: bipush 30 (0x1E)
		// @16A: ldc "7n\u001cIZ75EF])=\u0018DM7!\u001e^\u00177i\u0016\nJ\u007f|\u0017ML>!\u001bX\u0017"
		// @16C: invokestatic game.C_100102_w.func_104627_z(java.lang.String)char[]
		// @16F: invokestatic game.C_100102_w.func_104625_z(char[])java.lang.String
		// @172: aastore
		// @173: dup
		// @174: bipush 31 (0x1F)
		// @176: ldc "75*b`QIY\u0001\t+q\r\u0014\tvs\u001d\n\u0015piG\n]x=\u001aBHyz\u001c\u0003\u0015uoG"
		// @178: invokestatic game.C_100102_w.func_104627_z(java.lang.String)char[]
		// @17B: invokestatic game.C_100102_w.func_104625_z(char[])java.lang.String
		// @17E: aastore
		// @17F: dup
		// @180: bipush 32 (0x20)
		// @182: ldc "75\u0018X[xjYALnnY^F7~\u0011KGpxU\n\u00027|\u0017N\t:=\rE\ttu\u0018DNr=\u0014KQ7{\u000bKDr=\u0017E\u0000+\u007f\u000b\u0014"
		// @184: invokestatic game.C_100102_w.func_104627_z(java.lang.String)char[]
		// @187: invokestatic game.C_100102_w.func_104625_z(char[])java.lang.String
		// @18A: aastore
		// @18B: dup
		// @18C: bipush 33 (0x21)
		// @18E: ldc "+\u007f\u000b\u0014er{\r\nHyyYx@pu\r\nJ\u007f|\u0017ML7{\u000bKDr!\u001bX\u0017Bn\u001c\n]\u007fxYYE~y\u001cXZ7i\u0016\nJ\u007f|\u0017ML7|\u0017MErnYKGs=\tEZ~i\u0010EGd3EH[)^Y\u0007\tdx\u0015OJc=\u0018\nOe|\u0014O\tcrYIFgdU\njCO5\u0001y70YZHdi\u001cY\tv=\u001fXHzxEH[)"
		// @190: invokestatic game.C_100102_w.func_104627_z(java.lang.String)char[]
		// @193: invokestatic game.C_100102_w.func_104625_z(char[])java.lang.String
		// @196: aastore
		// @197: dup
		// @198: bipush 34 (0x22)
		// @19A: ldc "`3>\u0002"
		// @19C: invokestatic game.C_100102_w.func_104627_z(java.lang.String)char[]
		// @19F: invokestatic game.C_100102_w.func_104625_z(char[])java.lang.String
		// @1A2: aastore
		// @1A3: putstatic java.lang.String[] game.C_100102_w.field_104654_z
		// @1A6: ldc "@|\u0010^@yzYLFe=\u001eXHgu\u0010IZ"
		// @1A8: invokestatic game.C_100102_w.func_104627_z(java.lang.String)char[]
		// @1AB: invokestatic game.C_100102_w.func_104625_z(char[])java.lang.String
		// @1AE: putstatic java.lang.String game.C_100102_w.field_104637_a
		// @1B1: ldc "Dx\r\n\\g=\u0017O^7h\u0017XHcx\u001d\nNvp\u001c"
		// @1B3: invokestatic game.C_100102_w.func_104627_z(java.lang.String)char[]
		// @1B6: invokestatic game.C_100102_w.func_104625_z(char[])java.lang.String
		// @1B9: putstatic java.lang.String game.C_100102_w.field_104651_r
		// @1BC: bipush 100 (0x64)
		// @1BE: putstatic int game.C_100102_w.field_104648_u
		// @1C1: ldc "w"
		// @1C3: putstatic java.lang.String game.C_100102_w.field_104647_v
		// @1C6: iconst_0
		// @1C7: putstatic int game.C_100102_w.field_104646_w
		// @1CA: iconst_0
		// @1CB: putstatic int game.C_100102_w.field_104636_c
		// @1CE: iconst_0
		// @1CF: putstatic boolean game.C_100102_w.field_104632_g
		// @1D2: new game.C_100333_ij
		// @1D5: dup
		// @1D6: iconst_1
		// @1D7: invokespecial game.C_100333_ij.<init>(int)void
		// @1DA: putstatic game.C_100333_ij game.C_100102_w.field_104631_f
		// @1DD: return
	}
	
	private static char[] func_104627_z(String arg0)
	{
		// @00: aload_0
		// @01: invokevirtual java.lang.String.toCharArray()char[]
		// @04: dup
		// @05: arraylength
		// @06: iconst_2
		// @07: if_icmpge @13
		// @0A: dup
		// @0B: iconst_0
		// @0C: dup2
		// @0D: caload
		// @0E: bipush 41 (0x29)
		// @10: ixor
		// @11: i2c
		// @12: castore
		// @13: areturn
	}
	
	private static String func_104625_z(char[] arg0)
	{
		// @00: aload_0
		// @01: dup
		// @02: arraylength
		// @03: swap
		// @04: iconst_0
		// @05: istore_1
		// @06: goto @4C
		// @09: dup
		// @0A: iload_1
		// @0B: dup2
		// @0C: caload
		// @0D: iload_1
		// @0E: iconst_5
		// @0F: irem
		// @10: tableswitch def: @44, for 0: @30, for 1: @35, for 2: @3A, for 3: @3F
		// @30: bipush 23 (0x17)
		// @32: goto @46
		// @35: bipush 29 (0x1D)
		// @37: goto @46
		// @3A: bipush 121 (0x79)
		// @3C: goto @46
		// @3F: bipush 42 (0x2A)
		// @41: goto @46
		// @44: bipush 41 (0x29)
		// @46: ixor
		// @47: i2c
		// @48: castore
		// @49: iinc #1 +1
		// @4C: swap
		// @4D: dup_x1
		// @4E: iload_1
		// @4F: if_icmpgt @09
		// @52: new java.lang.String
		// @55: dup_x1
		// @56: swap
		// @57: invokespecial java.lang.String.<init>(char[])void
		// @5A: invokevirtual java.lang.String.intern()java.lang.String
		// @5D: areturn
	}
}
