package game;

final class C_100120_en
{
	static final void func_104911_a(byte[] arg0, int arg1, byte[] arg2, int arg3, int arg4)
	{
		// @000: aload_0
		// @001: aload_2
		// @002: if_acmpne @0B0
		// @005: iload_1
		// @006: iload_3
		// @007: if_icmpne @00B
		// @00A: return
		// @00B: iload_3
		// @00C: iload_1
		// @00D: if_icmple @0B0
		// @010: iload_3
		// @011: iload_1
		// @012: iload #4
		// @014: iadd
		// @015: if_icmpge @0B0
		// @018: iinc #4 +255
		// @01B: iload_1
		// @01C: iload #4
		// @01E: iadd
		// @01F: istore_1
		// @020: iload_3
		// @021: iload #4
		// @023: iadd
		// @024: istore_3
		// @025: iload_1
		// @026: iload #4
		// @028: isub
		// @029: istore #4
		// @02B: iinc #4 +7
		// @02E: iload_1
		// @02F: iload #4
		// @031: if_icmplt @097
		// @034: aload_2
		// @035: iload_3
		// @036: iinc #3 +255
		// @039: aload_0
		// @03A: iload_1
		// @03B: iinc #1 +255
		// @03E: baload
		// @03F: bastore
		// @040: aload_2
		// @041: iload_3
		// @042: iinc #3 +255
		// @045: aload_0
		// @046: iload_1
		// @047: iinc #1 +255
		// @04A: baload
		// @04B: bastore
		// @04C: aload_2
		// @04D: iload_3
		// @04E: iinc #3 +255
		// @051: aload_0
		// @052: iload_1
		// @053: iinc #1 +255
		// @056: baload
		// @057: bastore
		// @058: aload_2
		// @059: iload_3
		// @05A: iinc #3 +255
		// @05D: aload_0
		// @05E: iload_1
		// @05F: iinc #1 +255
		// @062: baload
		// @063: bastore
		// @064: aload_2
		// @065: iload_3
		// @066: iinc #3 +255
		// @069: aload_0
		// @06A: iload_1
		// @06B: iinc #1 +255
		// @06E: baload
		// @06F: bastore
		// @070: aload_2
		// @071: iload_3
		// @072: iinc #3 +255
		// @075: aload_0
		// @076: iload_1
		// @077: iinc #1 +255
		// @07A: baload
		// @07B: bastore
		// @07C: aload_2
		// @07D: iload_3
		// @07E: iinc #3 +255
		// @081: aload_0
		// @082: iload_1
		// @083: iinc #1 +255
		// @086: baload
		// @087: bastore
		// @088: aload_2
		// @089: iload_3
		// @08A: iinc #3 +255
		// @08D: aload_0
		// @08E: iload_1
		// @08F: iinc #1 +255
		// @092: baload
		// @093: bastore
		// @094: goto @02E
		// @097: iinc #4 +249
		// @09A: iload_1
		// @09B: iload #4
		// @09D: if_icmplt @0AF
		// @0A0: aload_2
		// @0A1: iload_3
		// @0A2: iinc #3 +255
		// @0A5: aload_0
		// @0A6: iload_1
		// @0A7: iinc #1 +255
		// @0AA: baload
		// @0AB: bastore
		// @0AC: goto @09A
		// @0AF: return
		// @0B0: iload #4
		// @0B2: iload_1
		// @0B3: iadd
		// @0B4: istore #4
		// @0B6: iinc #4 +249
		// @0B9: iload_1
		// @0BA: iload #4
		// @0BC: if_icmpge @122
		// @0BF: aload_2
		// @0C0: iload_3
		// @0C1: iinc #3 +1
		// @0C4: aload_0
		// @0C5: iload_1
		// @0C6: iinc #1 +1
		// @0C9: baload
		// @0CA: bastore
		// @0CB: aload_2
		// @0CC: iload_3
		// @0CD: iinc #3 +1
		// @0D0: aload_0
		// @0D1: iload_1
		// @0D2: iinc #1 +1
		// @0D5: baload
		// @0D6: bastore
		// @0D7: aload_2
		// @0D8: iload_3
		// @0D9: iinc #3 +1
		// @0DC: aload_0
		// @0DD: iload_1
		// @0DE: iinc #1 +1
		// @0E1: baload
		// @0E2: bastore
		// @0E3: aload_2
		// @0E4: iload_3
		// @0E5: iinc #3 +1
		// @0E8: aload_0
		// @0E9: iload_1
		// @0EA: iinc #1 +1
		// @0ED: baload
		// @0EE: bastore
		// @0EF: aload_2
		// @0F0: iload_3
		// @0F1: iinc #3 +1
		// @0F4: aload_0
		// @0F5: iload_1
		// @0F6: iinc #1 +1
		// @0F9: baload
		// @0FA: bastore
		// @0FB: aload_2
		// @0FC: iload_3
		// @0FD: iinc #3 +1
		// @100: aload_0
		// @101: iload_1
		// @102: iinc #1 +1
		// @105: baload
		// @106: bastore
		// @107: aload_2
		// @108: iload_3
		// @109: iinc #3 +1
		// @10C: aload_0
		// @10D: iload_1
		// @10E: iinc #1 +1
		// @111: baload
		// @112: bastore
		// @113: aload_2
		// @114: iload_3
		// @115: iinc #3 +1
		// @118: aload_0
		// @119: iload_1
		// @11A: iinc #1 +1
		// @11D: baload
		// @11E: bastore
		// @11F: goto @0B9
		// @122: iinc #4 +7
		// @125: iload_1
		// @126: iload #4
		// @128: if_icmpge @13A
		// @12B: aload_2
		// @12C: iload_3
		// @12D: iinc #3 +1
		// @130: aload_0
		// @131: iload_1
		// @132: iinc #1 +1
		// @135: baload
		// @136: bastore
		// @137: goto @125
		// @13A: return
	}
	
	static final void func_104912_a(Object[] arg0, int arg1, Object[] arg2, int arg3, int arg4)
	{
		// @000: aload_0
		// @001: aload_2
		// @002: if_acmpne @0B0
		// @005: iload_1
		// @006: iload_3
		// @007: if_icmpne @00B
		// @00A: return
		// @00B: iload_3
		// @00C: iload_1
		// @00D: if_icmple @0B0
		// @010: iload_3
		// @011: iload_1
		// @012: iload #4
		// @014: iadd
		// @015: if_icmpge @0B0
		// @018: iinc #4 +255
		// @01B: iload_1
		// @01C: iload #4
		// @01E: iadd
		// @01F: istore_1
		// @020: iload_3
		// @021: iload #4
		// @023: iadd
		// @024: istore_3
		// @025: iload_1
		// @026: iload #4
		// @028: isub
		// @029: istore #4
		// @02B: iinc #4 +7
		// @02E: iload_1
		// @02F: iload #4
		// @031: if_icmplt @097
		// @034: aload_2
		// @035: iload_3
		// @036: iinc #3 +255
		// @039: aload_0
		// @03A: iload_1
		// @03B: iinc #1 +255
		// @03E: aaload
		// @03F: aastore
		// @040: aload_2
		// @041: iload_3
		// @042: iinc #3 +255
		// @045: aload_0
		// @046: iload_1
		// @047: iinc #1 +255
		// @04A: aaload
		// @04B: aastore
		// @04C: aload_2
		// @04D: iload_3
		// @04E: iinc #3 +255
		// @051: aload_0
		// @052: iload_1
		// @053: iinc #1 +255
		// @056: aaload
		// @057: aastore
		// @058: aload_2
		// @059: iload_3
		// @05A: iinc #3 +255
		// @05D: aload_0
		// @05E: iload_1
		// @05F: iinc #1 +255
		// @062: aaload
		// @063: aastore
		// @064: aload_2
		// @065: iload_3
		// @066: iinc #3 +255
		// @069: aload_0
		// @06A: iload_1
		// @06B: iinc #1 +255
		// @06E: aaload
		// @06F: aastore
		// @070: aload_2
		// @071: iload_3
		// @072: iinc #3 +255
		// @075: aload_0
		// @076: iload_1
		// @077: iinc #1 +255
		// @07A: aaload
		// @07B: aastore
		// @07C: aload_2
		// @07D: iload_3
		// @07E: iinc #3 +255
		// @081: aload_0
		// @082: iload_1
		// @083: iinc #1 +255
		// @086: aaload
		// @087: aastore
		// @088: aload_2
		// @089: iload_3
		// @08A: iinc #3 +255
		// @08D: aload_0
		// @08E: iload_1
		// @08F: iinc #1 +255
		// @092: aaload
		// @093: aastore
		// @094: goto @02E
		// @097: iinc #4 +249
		// @09A: iload_1
		// @09B: iload #4
		// @09D: if_icmplt @0AF
		// @0A0: aload_2
		// @0A1: iload_3
		// @0A2: iinc #3 +255
		// @0A5: aload_0
		// @0A6: iload_1
		// @0A7: iinc #1 +255
		// @0AA: aaload
		// @0AB: aastore
		// @0AC: goto @09A
		// @0AF: return
		// @0B0: iload #4
		// @0B2: iload_1
		// @0B3: iadd
		// @0B4: istore #4
		// @0B6: iinc #4 +249
		// @0B9: iload_1
		// @0BA: iload #4
		// @0BC: if_icmpge @122
		// @0BF: aload_2
		// @0C0: iload_3
		// @0C1: iinc #3 +1
		// @0C4: aload_0
		// @0C5: iload_1
		// @0C6: iinc #1 +1
		// @0C9: aaload
		// @0CA: aastore
		// @0CB: aload_2
		// @0CC: iload_3
		// @0CD: iinc #3 +1
		// @0D0: aload_0
		// @0D1: iload_1
		// @0D2: iinc #1 +1
		// @0D5: aaload
		// @0D6: aastore
		// @0D7: aload_2
		// @0D8: iload_3
		// @0D9: iinc #3 +1
		// @0DC: aload_0
		// @0DD: iload_1
		// @0DE: iinc #1 +1
		// @0E1: aaload
		// @0E2: aastore
		// @0E3: aload_2
		// @0E4: iload_3
		// @0E5: iinc #3 +1
		// @0E8: aload_0
		// @0E9: iload_1
		// @0EA: iinc #1 +1
		// @0ED: aaload
		// @0EE: aastore
		// @0EF: aload_2
		// @0F0: iload_3
		// @0F1: iinc #3 +1
		// @0F4: aload_0
		// @0F5: iload_1
		// @0F6: iinc #1 +1
		// @0F9: aaload
		// @0FA: aastore
		// @0FB: aload_2
		// @0FC: iload_3
		// @0FD: iinc #3 +1
		// @100: aload_0
		// @101: iload_1
		// @102: iinc #1 +1
		// @105: aaload
		// @106: aastore
		// @107: aload_2
		// @108: iload_3
		// @109: iinc #3 +1
		// @10C: aload_0
		// @10D: iload_1
		// @10E: iinc #1 +1
		// @111: aaload
		// @112: aastore
		// @113: aload_2
		// @114: iload_3
		// @115: iinc #3 +1
		// @118: aload_0
		// @119: iload_1
		// @11A: iinc #1 +1
		// @11D: aaload
		// @11E: aastore
		// @11F: goto @0B9
		// @122: iinc #4 +7
		// @125: iload_1
		// @126: iload #4
		// @128: if_icmpge @13A
		// @12B: aload_2
		// @12C: iload_3
		// @12D: iinc #3 +1
		// @130: aload_0
		// @131: iload_1
		// @132: iinc #1 +1
		// @135: aaload
		// @136: aastore
		// @137: goto @125
		// @13A: return
	}
	
	static final void func_104913_a(int[] arg0, int arg1, int[] arg2, int arg3, int arg4)
	{
		// @000: aload_0
		// @001: aload_2
		// @002: if_acmpne @0B0
		// @005: iload_1
		// @006: iload_3
		// @007: if_icmpne @00B
		// @00A: return
		// @00B: iload_3
		// @00C: iload_1
		// @00D: if_icmple @0B0
		// @010: iload_3
		// @011: iload_1
		// @012: iload #4
		// @014: iadd
		// @015: if_icmpge @0B0
		// @018: iinc #4 +255
		// @01B: iload_1
		// @01C: iload #4
		// @01E: iadd
		// @01F: istore_1
		// @020: iload_3
		// @021: iload #4
		// @023: iadd
		// @024: istore_3
		// @025: iload_1
		// @026: iload #4
		// @028: isub
		// @029: istore #4
		// @02B: iinc #4 +7
		// @02E: iload_1
		// @02F: iload #4
		// @031: if_icmplt @097
		// @034: aload_2
		// @035: iload_3
		// @036: iinc #3 +255
		// @039: aload_0
		// @03A: iload_1
		// @03B: iinc #1 +255
		// @03E: iaload
		// @03F: iastore
		// @040: aload_2
		// @041: iload_3
		// @042: iinc #3 +255
		// @045: aload_0
		// @046: iload_1
		// @047: iinc #1 +255
		// @04A: iaload
		// @04B: iastore
		// @04C: aload_2
		// @04D: iload_3
		// @04E: iinc #3 +255
		// @051: aload_0
		// @052: iload_1
		// @053: iinc #1 +255
		// @056: iaload
		// @057: iastore
		// @058: aload_2
		// @059: iload_3
		// @05A: iinc #3 +255
		// @05D: aload_0
		// @05E: iload_1
		// @05F: iinc #1 +255
		// @062: iaload
		// @063: iastore
		// @064: aload_2
		// @065: iload_3
		// @066: iinc #3 +255
		// @069: aload_0
		// @06A: iload_1
		// @06B: iinc #1 +255
		// @06E: iaload
		// @06F: iastore
		// @070: aload_2
		// @071: iload_3
		// @072: iinc #3 +255
		// @075: aload_0
		// @076: iload_1
		// @077: iinc #1 +255
		// @07A: iaload
		// @07B: iastore
		// @07C: aload_2
		// @07D: iload_3
		// @07E: iinc #3 +255
		// @081: aload_0
		// @082: iload_1
		// @083: iinc #1 +255
		// @086: iaload
		// @087: iastore
		// @088: aload_2
		// @089: iload_3
		// @08A: iinc #3 +255
		// @08D: aload_0
		// @08E: iload_1
		// @08F: iinc #1 +255
		// @092: iaload
		// @093: iastore
		// @094: goto @02E
		// @097: iinc #4 +249
		// @09A: iload_1
		// @09B: iload #4
		// @09D: if_icmplt @0AF
		// @0A0: aload_2
		// @0A1: iload_3
		// @0A2: iinc #3 +255
		// @0A5: aload_0
		// @0A6: iload_1
		// @0A7: iinc #1 +255
		// @0AA: iaload
		// @0AB: iastore
		// @0AC: goto @09A
		// @0AF: return
		// @0B0: iload #4
		// @0B2: iload_1
		// @0B3: iadd
		// @0B4: istore #4
		// @0B6: iinc #4 +249
		// @0B9: iload_1
		// @0BA: iload #4
		// @0BC: if_icmpge @122
		// @0BF: aload_2
		// @0C0: iload_3
		// @0C1: iinc #3 +1
		// @0C4: aload_0
		// @0C5: iload_1
		// @0C6: iinc #1 +1
		// @0C9: iaload
		// @0CA: iastore
		// @0CB: aload_2
		// @0CC: iload_3
		// @0CD: iinc #3 +1
		// @0D0: aload_0
		// @0D1: iload_1
		// @0D2: iinc #1 +1
		// @0D5: iaload
		// @0D6: iastore
		// @0D7: aload_2
		// @0D8: iload_3
		// @0D9: iinc #3 +1
		// @0DC: aload_0
		// @0DD: iload_1
		// @0DE: iinc #1 +1
		// @0E1: iaload
		// @0E2: iastore
		// @0E3: aload_2
		// @0E4: iload_3
		// @0E5: iinc #3 +1
		// @0E8: aload_0
		// @0E9: iload_1
		// @0EA: iinc #1 +1
		// @0ED: iaload
		// @0EE: iastore
		// @0EF: aload_2
		// @0F0: iload_3
		// @0F1: iinc #3 +1
		// @0F4: aload_0
		// @0F5: iload_1
		// @0F6: iinc #1 +1
		// @0F9: iaload
		// @0FA: iastore
		// @0FB: aload_2
		// @0FC: iload_3
		// @0FD: iinc #3 +1
		// @100: aload_0
		// @101: iload_1
		// @102: iinc #1 +1
		// @105: iaload
		// @106: iastore
		// @107: aload_2
		// @108: iload_3
		// @109: iinc #3 +1
		// @10C: aload_0
		// @10D: iload_1
		// @10E: iinc #1 +1
		// @111: iaload
		// @112: iastore
		// @113: aload_2
		// @114: iload_3
		// @115: iinc #3 +1
		// @118: aload_0
		// @119: iload_1
		// @11A: iinc #1 +1
		// @11D: iaload
		// @11E: iastore
		// @11F: goto @0B9
		// @122: iinc #4 +7
		// @125: iload_1
		// @126: iload #4
		// @128: if_icmpge @13A
		// @12B: aload_2
		// @12C: iload_3
		// @12D: iinc #3 +1
		// @130: aload_0
		// @131: iload_1
		// @132: iinc #1 +1
		// @135: iaload
		// @136: iastore
		// @137: goto @125
		// @13A: return
	}
	
	static final void func_104910_a(int[] arg0, int arg1, int arg2)
	{
		// @00: iload_1
		// @01: iload_2
		// @02: iadd
		// @03: bipush 7 (0x07)
		// @05: isub
		// @06: istore_2
		// @07: iload_1
		// @08: iload_2
		// @09: if_icmpge @47
		// @0C: aload_0
		// @0D: iload_1
		// @0E: iinc #1 +1
		// @11: iconst_0
		// @12: iastore
		// @13: aload_0
		// @14: iload_1
		// @15: iinc #1 +1
		// @18: iconst_0
		// @19: iastore
		// @1A: aload_0
		// @1B: iload_1
		// @1C: iinc #1 +1
		// @1F: iconst_0
		// @20: iastore
		// @21: aload_0
		// @22: iload_1
		// @23: iinc #1 +1
		// @26: iconst_0
		// @27: iastore
		// @28: aload_0
		// @29: iload_1
		// @2A: iinc #1 +1
		// @2D: iconst_0
		// @2E: iastore
		// @2F: aload_0
		// @30: iload_1
		// @31: iinc #1 +1
		// @34: iconst_0
		// @35: iastore
		// @36: aload_0
		// @37: iload_1
		// @38: iinc #1 +1
		// @3B: iconst_0
		// @3C: iastore
		// @3D: aload_0
		// @3E: iload_1
		// @3F: iinc #1 +1
		// @42: iconst_0
		// @43: iastore
		// @44: goto @07
		// @47: iinc #2 +7
		// @4A: iload_1
		// @4B: iload_2
		// @4C: if_icmpge @59
		// @4F: aload_0
		// @50: iload_1
		// @51: iinc #1 +1
		// @54: iconst_0
		// @55: iastore
		// @56: goto @4A
		// @59: return
	}
}
