package game;

import java.awt.Component;

final class C_100264_mg
{
	static String field_106522_b;
	static C_100323_hl field_106528_i;
	static boolean field_106524_a;
	static int field_106520_d;
	static String[] field_106527_h;
	static String field_106521_e;
	static String[] field_106519_g;
	static C_100219_an field_106518_f;
	static boolean field_106523_c;
	static int field_106525_j;
	private static final String[] field_106526_z;
	
	static final C_100185_rm func_106516_a(Component arg0, int arg1, int arg2, int arg3)
	{
		// @00: getstatic java.lang.String[] game.C_100264_mg.field_106526_z
		// @03: iconst_4
		// @04: aaload
		// @05: invokestatic java.lang.Class.forName(java.lang.String)java.lang.Class
		// @08: astore #4
		// @0A: iload_1
		// @0B: iconst_2
		// @0C: if_icmpeq @1A
		// @0F: aconst_null
		// @10: checkcast java.lang.String
		// @13: putstatic java.lang.String game.C_100264_mg.field_106522_b
		// @16: goto @1A
		// @19: athrow
		// @1A: aload #4
		// @1C: invokevirtual java.lang.Class.newInstance()java.lang.Object
		// @1F: checkcast game.C_100185_rm
		// @22: astore #5
		// @24: aload #5
		// @26: iload_2
		// @27: iload_3
		// @28: aload_0
		// @29: bipush 15 (0x0F)
		// @2B: invokevirtual game.C_100185_rm.func_105478_a(int, int, java.awt.Component, byte)void
		// @2E: aload #5
		// @30: areturn
		// @31: astore #4
		// @33: new game.C_100252_pn
		// @36: dup
		// @37: invokespecial game.C_100252_pn.<init>()void
		// @3A: astore #5
		// @3C: aload #5
		// @3E: iload_2
		// @3F: iload_3
		// @40: aload_0
		// @41: bipush 15 (0x0F)
		// @43: invokevirtual game.C_100185_rm.func_105478_a(int, int, java.awt.Component, byte)void
		// @46: aload #5
		// @48: areturn
		// @49: astore #4
		// @4B: aload #4
		// @4D: new java.lang.StringBuilder
		// @50: dup
		// @51: invokespecial java.lang.StringBuilder.<init>()void
		// @54: getstatic java.lang.String[] game.C_100264_mg.field_106526_z
		// @57: iconst_1
		// @58: aaload
		// @59: invokevirtual java.lang.StringBuilder.append(java.lang.String)java.lang.StringBuilder
		// @5C: aload_0
		// @5D: ifnull @69
		// @60: getstatic java.lang.String[] game.C_100264_mg.field_106526_z
		// @63: iconst_2
		// @64: aaload
		// @65: goto @6E
		// @68: athrow
		// @69: getstatic java.lang.String[] game.C_100264_mg.field_106526_z
		// @6C: iconst_3
		// @6D: aaload
		// @6E: invokevirtual java.lang.StringBuilder.append(java.lang.String)java.lang.StringBuilder
		// @71: bipush 44 (0x2C)
		// @73: invokevirtual java.lang.StringBuilder.append(char)java.lang.StringBuilder
		// @76: iload_1
		// @77: invokevirtual java.lang.StringBuilder.append(int)java.lang.StringBuilder
		// @7A: bipush 44 (0x2C)
		// @7C: invokevirtual java.lang.StringBuilder.append(char)java.lang.StringBuilder
		// @7F: iload_2
		// @80: invokevirtual java.lang.StringBuilder.append(int)java.lang.StringBuilder
		// @83: bipush 44 (0x2C)
		// @85: invokevirtual java.lang.StringBuilder.append(char)java.lang.StringBuilder
		// @88: iload_3
		// @89: invokevirtual java.lang.StringBuilder.append(int)java.lang.StringBuilder
		// @8C: bipush 41 (0x29)
		// @8E: invokevirtual java.lang.StringBuilder.append(char)java.lang.StringBuilder
		// @91: invokevirtual java.lang.StringBuilder.toString()java.lang.String
		// @94: invokestatic game.C_100181_cf.func_105695_a(java.lang.Throwable, java.lang.String)game.C_100170_cm
		// @97: athrow
	}
	
	static final C_100302_ka func_106517_a(int arg0)
	{
		// @00: bipush -90 (0xA6)
		// @02: bipush 63 (0x3F)
		// @04: iload_0
		// @05: isub
		// @06: bipush 63 (0x3F)
		// @08: idiv
		// @09: irem
		// @0A: istore_1
		// @0B: bipush -21 (0xEB)
		// @0D: invokestatic game.C_100223_ab.func_106095_b(byte)game.C_100302_ka
		// @10: areturn
		// @11: astore_1
		// @12: aload_1
		// @13: new java.lang.StringBuilder
		// @16: dup
		// @17: invokespecial java.lang.StringBuilder.<init>()void
		// @1A: getstatic java.lang.String[] game.C_100264_mg.field_106526_z
		// @1D: iconst_5
		// @1E: aaload
		// @1F: invokevirtual java.lang.StringBuilder.append(java.lang.String)java.lang.StringBuilder
		// @22: iload_0
		// @23: invokevirtual java.lang.StringBuilder.append(int)java.lang.StringBuilder
		// @26: bipush 41 (0x29)
		// @28: invokevirtual java.lang.StringBuilder.append(char)java.lang.StringBuilder
		// @2B: invokevirtual java.lang.StringBuilder.toString()java.lang.String
		// @2E: invokestatic game.C_100181_cf.func_105695_a(java.lang.Throwable, java.lang.String)game.C_100170_cm
		// @31: athrow
	}
	
	public static void func_106514_a(byte arg0)
	{
		// @00: aconst_null
		// @01: putstatic game.C_100219_an game.C_100264_mg.field_106518_f
		// @04: aconst_null
		// @05: putstatic game.C_100323_hl game.C_100264_mg.field_106528_i
		// @08: aconst_null
		// @09: putstatic java.lang.String[] game.C_100264_mg.field_106519_g
		// @0C: bipush 59 (0x3B)
		// @0E: bipush -4 (0xFC)
		// @10: iload_0
		// @11: isub
		// @12: bipush 54 (0x36)
		// @14: idiv
		// @15: idiv
		// @16: istore_1
		// @17: aconst_null
		// @18: putstatic java.lang.String game.C_100264_mg.field_106522_b
		// @1B: aconst_null
		// @1C: putstatic java.lang.String game.C_100264_mg.field_106521_e
		// @1F: aconst_null
		// @20: putstatic java.lang.String[] game.C_100264_mg.field_106527_h
		// @23: goto @47
		// @26: astore_1
		// @27: aload_1
		// @28: new java.lang.StringBuilder
		// @2B: dup
		// @2C: invokespecial java.lang.StringBuilder.<init>()void
		// @2F: getstatic java.lang.String[] game.C_100264_mg.field_106526_z
		// @32: iconst_0
		// @33: aaload
		// @34: invokevirtual java.lang.StringBuilder.append(java.lang.String)java.lang.StringBuilder
		// @37: iload_0
		// @38: invokevirtual java.lang.StringBuilder.append(int)java.lang.StringBuilder
		// @3B: bipush 41 (0x29)
		// @3D: invokevirtual java.lang.StringBuilder.append(char)java.lang.StringBuilder
		// @40: invokevirtual java.lang.StringBuilder.toString()java.lang.String
		// @43: invokestatic game.C_100181_cf.func_105695_a(java.lang.Throwable, java.lang.String)game.C_100170_cm
		// @46: athrow
		// @47: return
	}
	
	static
	{
		// @00: bipush 6 (0x06)
		// @02: anewarray java.lang.String
		// @05: dup
		// @06: iconst_0
		// @07: ldc "\tn=l|"
		// @09: invokestatic game.C_100264_mg.func_106515_z(java.lang.String)char[]
		// @0C: invokestatic game.C_100264_mg.func_106513_z(char[])java.lang.String
		// @0F: aastore
		// @10: dup
		// @11: iconst_1
		// @12: ldc "\tn=n|"
		// @14: invokestatic game.C_100264_mg.func_106515_z(java.lang.String)char[]
		// @17: invokestatic game.C_100264_mg.func_106513_z(char[])java.lang.String
		// @1A: aastore
		// @1B: dup
		// @1C: iconst_2
		// @1D: ldc "\u001f'=\u0001)"
		// @1F: invokestatic game.C_100264_mg.func_106515_z(java.lang.String)char[]
		// @22: invokestatic game.C_100264_mg.func_106513_z(char[])java.lang.String
		// @25: aastore
		// @26: dup
		// @27: iconst_3
		// @28: ldc "\n|\u007fC"
		// @2A: invokestatic game.C_100264_mg.func_106515_z(java.lang.String)char[]
		// @2D: invokestatic game.C_100264_mg.func_106513_z(char[])java.lang.String
		// @30: aastore
		// @31: dup
		// @32: iconst_4
		// @33: ldc "\u0017`"
		// @35: invokestatic game.C_100264_mg.func_106515_z(java.lang.String)char[]
		// @38: invokestatic game.C_100264_mg.func_106513_z(char[])java.lang.String
		// @3B: aastore
		// @3C: dup
		// @3D: iconst_5
		// @3E: ldc "\tn=m|"
		// @40: invokestatic game.C_100264_mg.func_106515_z(java.lang.String)char[]
		// @43: invokestatic game.C_100264_mg.func_106513_z(char[])java.lang.String
		// @46: aastore
		// @47: putstatic java.lang.String[] game.C_100264_mg.field_106526_z
		// @4A: ldc "!GV}\u0013="
		// @4C: invokestatic game.C_100264_mg.func_106515_z(java.lang.String)char[]
		// @4F: invokestatic game.C_100264_mg.func_106513_z(char[])java.lang.String
		// @52: putstatic java.lang.String game.C_100264_mg.field_106522_b
		// @55: iconst_0
		// @56: putstatic boolean game.C_100264_mg.field_106524_a
		// @59: iconst_2
		// @5A: putstatic int game.C_100264_mg.field_106520_d
		// @5D: new game.C_100323_hl
		// @60: dup
		// @61: invokespecial game.C_100323_hl.<init>()void
		// @64: putstatic game.C_100323_hl game.C_100264_mg.field_106528_i
		// @67: ldc "%meJ&\u0010``F:\u0003)dJ6\u0017`gJ'"
		// @69: invokestatic game.C_100264_mg.func_106515_z(java.lang.String)char[]
		// @6C: invokestatic game.C_100264_mg.func_106513_z(char[])java.lang.String
		// @6F: putstatic java.lang.String game.C_100264_mg.field_106521_e
		// @72: return
	}
	
	private static char[] func_106515_z(String arg0)
	{
		// @00: aload_0
		// @01: invokevirtual java.lang.String.toCharArray()char[]
		// @04: dup
		// @05: arraylength
		// @06: iconst_2
		// @07: if_icmpge @13
		// @0A: dup
		// @0B: iconst_0
		// @0C: dup2
		// @0D: caload
		// @0E: bipush 84 (0x54)
		// @10: ixor
		// @11: i2c
		// @12: castore
		// @13: areturn
	}
	
	private static String func_106513_z(char[] arg0)
	{
		// @00: aload_0
		// @01: dup
		// @02: arraylength
		// @03: swap
		// @04: iconst_0
		// @05: istore_1
		// @06: goto @4C
		// @09: dup
		// @0A: iload_1
		// @0B: dup2
		// @0C: caload
		// @0D: iload_1
		// @0E: iconst_5
		// @0F: irem
		// @10: tableswitch def: @44, for 0: @30, for 1: @35, for 2: @3A, for 3: @3F
		// @30: bipush 100 (0x64)
		// @32: goto @46
		// @35: bipush 9 (0x09)
		// @37: goto @46
		// @3A: bipush 19 (0x13)
		// @3C: goto @46
		// @3F: bipush 47 (0x2F)
		// @41: goto @46
		// @44: bipush 84 (0x54)
		// @46: ixor
		// @47: i2c
		// @48: castore
		// @49: iinc #1 +1
		// @4C: swap
		// @4D: dup_x1
		// @4E: iload_1
		// @4F: if_icmpgt @09
		// @52: new java.lang.String
		// @55: dup_x1
		// @56: swap
		// @57: invokespecial java.lang.String.<init>(char[])void
		// @5A: invokevirtual java.lang.String.intern()java.lang.String
		// @5D: areturn
	}
}
