package game;

final class C_100197_ra extends C_100158_da
{
	static int field_100867_r;
	byte[] field_100868_q;
	static int[] field_100859_m;
	static String field_100871_x;
	static String field_100865_t;
	static String field_100857_o;
	static C_100327_ib field_100861_k;
	static boolean field_100862_w;
	static byte[] field_100864_u;
	static String field_100869_p;
	static String[] field_100858_l;
	boolean field_100863_v;
	static C_100127_tl field_100856_n;
	static int[] field_100860_j;
	static int field_100866_s;
	private static final String[] field_100870_z;
	
	public static void func_100852_a(byte arg0)
	{
		// @00: aconst_null
		// @01: putstatic game.C_100327_ib game.C_100197_ra.field_100861_k
		// @04: aconst_null
		// @05: putstatic java.lang.String[] game.C_100197_ra.field_100858_l
		// @08: aconst_null
		// @09: putstatic java.lang.String game.C_100197_ra.field_100871_x
		// @0C: aconst_null
		// @0D: putstatic java.lang.String game.C_100197_ra.field_100857_o
		// @10: aconst_null
		// @11: putstatic int[] game.C_100197_ra.field_100859_m
		// @14: aconst_null
		// @15: putstatic int[] game.C_100197_ra.field_100860_j
		// @18: aconst_null
		// @19: putstatic java.lang.String game.C_100197_ra.field_100869_p
		// @1C: bipush 63 (0x3F)
		// @1E: bipush 35 (0x23)
		// @20: iload_0
		// @21: isub
		// @22: bipush 39 (0x27)
		// @24: idiv
		// @25: irem
		// @26: istore_1
		// @27: aconst_null
		// @28: putstatic byte[] game.C_100197_ra.field_100864_u
		// @2B: aconst_null
		// @2C: putstatic java.lang.String game.C_100197_ra.field_100865_t
		// @2F: aconst_null
		// @30: putstatic game.C_100127_tl game.C_100197_ra.field_100856_n
		// @33: goto @57
		// @36: astore_1
		// @37: aload_1
		// @38: new java.lang.StringBuilder
		// @3B: dup
		// @3C: invokespecial java.lang.StringBuilder.<init>()void
		// @3F: getstatic java.lang.String[] game.C_100197_ra.field_100870_z
		// @42: iconst_3
		// @43: aaload
		// @44: invokevirtual java.lang.StringBuilder.append(java.lang.String)java.lang.StringBuilder
		// @47: iload_0
		// @48: invokevirtual java.lang.StringBuilder.append(int)java.lang.StringBuilder
		// @4B: bipush 41 (0x29)
		// @4D: invokevirtual java.lang.StringBuilder.append(char)java.lang.StringBuilder
		// @50: invokevirtual java.lang.StringBuilder.toString()java.lang.String
		// @53: invokestatic game.C_100181_cf.func_105695_a(java.lang.Throwable, java.lang.String)game.C_100170_cm
		// @56: athrow
		// @57: return
	}
	
	static final void func_100855_a(byte arg0, C_100240_oj arg1)
	{
		// @00: getstatic int game.SteelSentinels.field_105275_O
		// @03: istore #4
		// @05: aload_1
		// @06: getfield java.lang.String game.C_100240_oj.field_106320_l
		// @09: ifnull @0F
		// @0C: goto @10
		// @0F: return
		// @10: aload_1
		// @11: getfield int game.C_100240_oj.field_106312_g
		// @14: iconst_m1
		// @15: ixor
		// @16: iconst_m1
		// @17: if_icmpne @28
		// @1A: aload_1
		// @1B: getfield int game.C_100240_oj.field_106323_k
		// @1E: iconst_m1
		// @1F: ixor
		// @20: iconst_m1
		// @21: if_icmpeq @76
		// @24: goto @28
		// @27: athrow
		// @28: iconst_0
		// @29: istore_2
		// @2A: getstatic int game.C_100188_rj.field_105737_e
		// @2D: iload_2
		// @2E: if_icmple @76
		// @31: getstatic game.C_100240_oj[] game.C_100006_fj.field_103617_g
		// @34: iload_2
		// @35: aaload
		// @36: astore_3
		// @37: bipush -3 (0xFD)
		// @39: aload_3
		// @3A: getfield int game.C_100240_oj.field_106317_a
		// @3D: iconst_m1
		// @3E: ixor
		// @3F: iload #4
		// @41: ifne @A6
		// @44: if_icmpne @6E
		// @47: goto @4B
		// @4A: athrow
		// @4B: aload_1
		// @4C: getfield int game.C_100240_oj.field_106312_g
		// @4F: aload_3
		// @50: getfield int game.C_100240_oj.field_106312_g
		// @53: if_icmpne @6E
		// @56: goto @5A
		// @59: athrow
		// @5A: aload_3
		// @5B: getfield int game.C_100240_oj.field_106323_k
		// @5E: iconst_m1
		// @5F: ixor
		// @60: aload_1
		// @61: getfield int game.C_100240_oj.field_106323_k
		// @64: iconst_m1
		// @65: ixor
		// @66: if_icmpne @6E
		// @69: goto @6D
		// @6C: athrow
		// @6D: return
		// @6E: iinc #2 +1
		// @71: iload #4
		// @73: ifeq @2A
		// @76: aload_1
		// @77: getfield int[] game.C_100240_oj.field_106326_p
		// @7A: ifnonnull @81
		// @7D: goto @9D
		// @80: athrow
		// @81: aload_1
		// @82: getfield int[] game.C_100240_oj.field_106326_p
		// @85: putstatic int[] game.C_100315_la.field_107178_b
		// @88: aload_1
		// @89: getfield long game.C_100240_oj.field_106316_c
		// @8C: putstatic long game.C_100050_vg.field_100633_u
		// @8F: aload_1
		// @90: getfield java.lang.String game.C_100240_oj.field_106313_d
		// @93: putstatic java.lang.String game.C_100215_ai.field_106022_h
		// @96: aload_1
		// @97: getfield int game.C_100240_oj.field_106317_a
		// @9A: putstatic int game.C_100149_bi.field_105154_d
		// @9D: bipush 50 (0x32)
		// @9F: aload_1
		// @A0: invokestatic game.C_100332_ii.func_107306_a(int, game.C_100240_oj)void
		// @A3: iload_0
		// @A4: bipush 17 (0x11)
		// @A6: if_icmpeq @B2
		// @A9: bipush 102 (0x66)
		// @AB: invokestatic game.C_100197_ra.func_100852_a(byte)void
		// @AE: goto @B2
		// @B1: athrow
		// @B2: goto @F0
		// @B5: astore_2
		// @B6: aload_2
		// @B7: new java.lang.StringBuilder
		// @BA: dup
		// @BB: invokespecial java.lang.StringBuilder.<init>()void
		// @BE: getstatic java.lang.String[] game.C_100197_ra.field_100870_z
		// @C1: iconst_2
		// @C2: aaload
		// @C3: invokevirtual java.lang.StringBuilder.append(java.lang.String)java.lang.StringBuilder
		// @C6: iload_0
		// @C7: invokevirtual java.lang.StringBuilder.append(int)java.lang.StringBuilder
		// @CA: bipush 44 (0x2C)
		// @CC: invokevirtual java.lang.StringBuilder.append(char)java.lang.StringBuilder
		// @CF: aload_1
		// @D0: ifnull @DC
		// @D3: getstatic java.lang.String[] game.C_100197_ra.field_100870_z
		// @D6: iconst_0
		// @D7: aaload
		// @D8: goto @E1
		// @DB: athrow
		// @DC: getstatic java.lang.String[] game.C_100197_ra.field_100870_z
		// @DF: iconst_1
		// @E0: aaload
		// @E1: invokevirtual java.lang.StringBuilder.append(java.lang.String)java.lang.StringBuilder
		// @E4: bipush 41 (0x29)
		// @E6: invokevirtual java.lang.StringBuilder.append(char)java.lang.StringBuilder
		// @E9: invokevirtual java.lang.StringBuilder.toString()java.lang.String
		// @EC: invokestatic game.C_100181_cf.func_105695_a(java.lang.Throwable, java.lang.String)game.C_100170_cm
		// @EF: athrow
		// @F0: return
	}
	
	static final void func_100854_a(boolean arg0, int arg1)
	{
		// @00: bipush 119 (0x77)
		// @02: iload_1
		// @03: bipush 63 (0x3F)
		// @05: isub
		// @06: bipush 54 (0x36)
		// @08: idiv
		// @09: idiv
		// @0A: istore_2
		// @0B: bipush 64 (0x40)
		// @0D: invokestatic game.C_100087_n.func_100688_e(int)boolean
		// @10: ifeq @15
		// @13: iconst_0
		// @14: istore_0
		// @15: bipush -97 (0x9F)
		// @17: iload_0
		// @18: invokestatic game.C_100226_ae.func_106143_b(int, boolean)void
		// @1B: getstatic boolean game.C_100069_vb.field_104355_g
		// @1E: ifne @25
		// @21: goto @58
		// @24: athrow
		// @25: getstatic game.C_100220_ac game.C_100091_m.field_104516_c
		// @28: getfield game.C_100172_ck game.C_100220_ac.field_106059_a
		// @2B: getfield int game.C_100172_ck.field_101841_Pb
		// @2E: getstatic game.C_100220_ac game.C_100091_m.field_104516_c
		// @31: getfield game.C_100172_ck game.C_100220_ac.field_106059_a
		// @34: getfield int game.C_100172_ck.field_101880_Gb
		// @37: getstatic game.C_100220_ac game.C_100091_m.field_104516_c
		// @3A: getfield game.C_100172_ck game.C_100220_ac.field_106059_a
		// @3D: getfield int game.C_100172_ck.field_101886_Kb
		// @40: getstatic game.C_100220_ac game.C_100091_m.field_104516_c
		// @43: getfield game.C_100172_ck game.C_100220_ac.field_106059_a
		// @46: getfield int game.C_100172_ck.field_101848_lb
		// @49: invokestatic game.C_100196_rb.func_105809_f(int, int, int, int)void
		// @4C: getstatic game.C_100220_ac game.C_100091_m.field_104516_c
		// @4F: getfield game.C_100172_ck game.C_100220_ac.field_106059_a
		// @52: bipush -127 (0x81)
		// @54: iload_0
		// @55: invokevirtual game.C_100172_ck.func_101809_a(byte, boolean)void
		// @58: bipush 127 (0x7F)
		// @5A: iload_0
		// @5B: invokestatic game.C_100136_th.func_102605_a(byte, boolean)void
		// @5E: goto @8B
		// @61: astore_2
		// @62: aload_2
		// @63: new java.lang.StringBuilder
		// @66: dup
		// @67: invokespecial java.lang.StringBuilder.<init>()void
		// @6A: getstatic java.lang.String[] game.C_100197_ra.field_100870_z
		// @6D: iconst_4
		// @6E: aaload
		// @6F: invokevirtual java.lang.StringBuilder.append(java.lang.String)java.lang.StringBuilder
		// @72: iload_0
		// @73: invokevirtual java.lang.StringBuilder.append(boolean)java.lang.StringBuilder
		// @76: bipush 44 (0x2C)
		// @78: invokevirtual java.lang.StringBuilder.append(char)java.lang.StringBuilder
		// @7B: iload_1
		// @7C: invokevirtual java.lang.StringBuilder.append(int)java.lang.StringBuilder
		// @7F: bipush 41 (0x29)
		// @81: invokevirtual java.lang.StringBuilder.append(char)java.lang.StringBuilder
		// @84: invokevirtual java.lang.StringBuilder.toString()java.lang.String
		// @87: invokestatic game.C_100181_cf.func_105695_a(java.lang.Throwable, java.lang.String)game.C_100170_cm
		// @8A: athrow
		// @8B: return
	}
	
	static
	{
		// @00: iconst_5
		// @01: anewarray java.lang.String
		// @04: dup
		// @05: iconst_0
		// @06: ldc "KL5\u000b\u0001"
		// @08: invokestatic game.C_100197_ra.func_100853_z(java.lang.String)char[]
		// @0B: invokestatic game.C_100197_ra.func_100851_z(char[])java.lang.String
		// @0E: aastore
		// @0F: dup
		// @10: iconst_1
		// @11: ldc "^\u0017wI"
		// @13: invokestatic game.C_100197_ra.func_100853_z(java.lang.String)char[]
		// @16: invokestatic game.C_100197_ra.func_100851_z(char[])java.lang.String
		// @19: aastore
		// @1A: dup
		// @1B: iconst_2
		// @1C: ldc "B\u00035fT"
		// @1E: invokestatic game.C_100197_ra.func_100853_z(java.lang.String)char[]
		// @21: invokestatic game.C_100197_ra.func_100851_z(char[])java.lang.String
		// @24: aastore
		// @25: dup
		// @26: iconst_3
		// @27: ldc "B\u00035gT"
		// @29: invokestatic game.C_100197_ra.func_100853_z(java.lang.String)char[]
		// @2C: invokestatic game.C_100197_ra.func_100851_z(char[])java.lang.String
		// @2F: aastore
		// @30: dup
		// @31: iconst_4
		// @32: ldc "B\u00035dT"
		// @34: invokestatic game.C_100197_ra.func_100853_z(java.lang.String)char[]
		// @37: invokestatic game.C_100197_ra.func_100851_z(char[])java.lang.String
		// @3A: aastore
		// @3B: putstatic java.lang.String[] game.C_100197_ra.field_100870_z
		// @3E: ldc "`\u0003hV\u000b_\u0010\u007fV\\S\u0003u\u0005\u0013^\u000eb\u0005\u001f_\u000coD\u0015^Bw@\u0008D\u0007iV\\Q\u000c\u007f\u0005\u0012E\u000fy@\u000eC"
		// @40: invokestatic game.C_100197_ra.func_100853_z(java.lang.String)char[]
		// @43: invokestatic game.C_100197_ra.func_100851_z(char[])java.lang.String
		// @46: putstatic java.lang.String game.C_100197_ra.field_100871_x
		// @49: iconst_0
		// @4A: putstatic int game.C_100197_ra.field_100867_r
		// @4D: bipush 12 (0x0C)
		// @4F: newarray int[]
		// @51: dup
		// @52: iconst_0
		// @53: bipush 108 (0x6C)
		// @55: iastore
		// @56: dup
		// @57: iconst_1
		// @58: bipush 71 (0x47)
		// @5A: iastore
		// @5B: dup
		// @5C: iconst_2
		// @5D: bipush 33 (0x21)
		// @5F: iastore
		// @60: dup
		// @61: iconst_3
		// @62: bipush 28 (0x1C)
		// @64: iastore
		// @65: dup
		// @66: iconst_4
		// @67: iconst_4
		// @68: iastore
		// @69: dup
		// @6A: iconst_5
		// @6B: bipush 9 (0x09)
		// @6D: iastore
		// @6E: dup
		// @6F: bipush 6 (0x06)
		// @71: bipush 14 (0x0E)
		// @73: iastore
		// @74: dup
		// @75: bipush 7 (0x07)
		// @77: bipush 17 (0x11)
		// @79: iastore
		// @7A: dup
		// @7B: bipush 8 (0x08)
		// @7D: iconst_m1
		// @7E: iastore
		// @7F: dup
		// @80: bipush 9 (0x09)
		// @82: iconst_m1
		// @83: iastore
		// @84: dup
		// @85: bipush 10 (0x0A)
		// @87: iconst_m1
		// @88: iastore
		// @89: dup
		// @8A: bipush 11 (0x0B)
		// @8C: iconst_m1
		// @8D: iastore
		// @8E: putstatic int[] game.C_100197_ra.field_100859_m
		// @91: ldc "c\u0016zW\u0008\u0010%zH\u0019"
		// @93: invokestatic game.C_100197_ra.func_100853_z(java.lang.String)char[]
		// @96: invokestatic game.C_100197_ra.func_100851_z(char[])java.lang.String
		// @99: putstatic java.lang.String game.C_100197_ra.field_100857_o
		// @9C: ldc "|\r|\u0005\u0015^"
		// @9E: invokestatic game.C_100197_ra.func_100853_z(java.lang.String)char[]
		// @A1: invokestatic game.C_100197_ra.func_100851_z(char[])java.lang.String
		// @A4: putstatic java.lang.String game.C_100197_ra.field_100865_t
		// @A7: sipush 520 (0x0208)
		// @AA: newarray byte[]
		// @AC: putstatic byte[] game.C_100197_ra.field_100864_u
		// @AF: iconst_3
		// @B0: anewarray java.lang.String
		// @B3: dup
		// @B4: iconst_0
		// @B5: ldc "v\u0017hL\u0013^^uG\u000f@\\i@\u001dF\u0007i"
		// @B7: invokestatic game.C_100197_ra.func_100853_z(java.lang.String)char[]
		// @BA: invokestatic game.C_100197_ra.func_100851_z(char[])java.lang.String
		// @BD: aastore
		// @BE: dup
		// @BF: iconst_1
		// @C0: ldc "u/K\u0019\u0012R\u0011k\u001b\u0010Q\u0001~W\u001dD\u000btK"
		// @C2: invokestatic game.C_100197_ra.func_100853_z(java.lang.String)char[]
		// @C5: invokestatic game.C_100197_ra.func_100851_z(char[])java.lang.String
		// @C8: aastore
		// @C9: dup
		// @CA: iconst_2
		// @CB: ldc "x\u0003vH\u0019B^uG\u000f@\\hQ\u000eY\t~"
		// @CD: invokestatic game.C_100197_ra.func_100853_z(java.lang.String)char[]
		// @D0: invokestatic game.C_100197_ra.func_100851_z(char[])java.lang.String
		// @D3: aastore
		// @D4: putstatic java.lang.String[] game.C_100197_ra.field_100858_l
		// @D7: ldc "\u000cG+\u001b\\X\u0003h\u0005\u0018B\rkU\u0019TBtP\u0008\u001e"
		// @D9: invokestatic game.C_100197_ra.func_100853_z(java.lang.String)char[]
		// @DC: invokestatic game.C_100197_ra.func_100851_z(char[])java.lang.String
		// @DF: putstatic java.lang.String game.C_100197_ra.field_100869_p
		// @E2: return
	}
	
	private static char[] func_100853_z(String arg0)
	{
		// @00: aload_0
		// @01: invokevirtual java.lang.String.toCharArray()char[]
		// @04: dup
		// @05: arraylength
		// @06: iconst_2
		// @07: if_icmpge @13
		// @0A: dup
		// @0B: iconst_0
		// @0C: dup2
		// @0D: caload
		// @0E: bipush 124 (0x7C)
		// @10: ixor
		// @11: i2c
		// @12: castore
		// @13: areturn
	}
	
	private static String func_100851_z(char[] arg0)
	{
		// @00: aload_0
		// @01: dup
		// @02: arraylength
		// @03: swap
		// @04: iconst_0
		// @05: istore_1
		// @06: goto @4C
		// @09: dup
		// @0A: iload_1
		// @0B: dup2
		// @0C: caload
		// @0D: iload_1
		// @0E: iconst_5
		// @0F: irem
		// @10: tableswitch def: @44, for 0: @30, for 1: @35, for 2: @3A, for 3: @3F
		// @30: bipush 48 (0x30)
		// @32: goto @46
		// @35: bipush 98 (0x62)
		// @37: goto @46
		// @3A: bipush 27 (0x1B)
		// @3C: goto @46
		// @3F: bipush 37 (0x25)
		// @41: goto @46
		// @44: bipush 124 (0x7C)
		// @46: ixor
		// @47: i2c
		// @48: castore
		// @49: iinc #1 +1
		// @4C: swap
		// @4D: dup_x1
		// @4E: iload_1
		// @4F: if_icmpgt @09
		// @52: new java.lang.String
		// @55: dup_x1
		// @56: swap
		// @57: invokespecial java.lang.String.<init>(char[])void
		// @5A: invokevirtual java.lang.String.intern()java.lang.String
		// @5D: areturn
	}
}
