package game;

final class C_100272_mn extends C_100316_lc
{
	static C_100105_eg field_102425_G;
	static String field_102429_M;
	static String field_102427_P;
	static C_100144_bm[][] field_102434_J;
	static boolean field_102435_K;
	static String field_102430_N;
	static int field_102431_O;
	static C_100152_bd field_102428_L;
	static C_100037_wb field_102433_I;
	private Object field_102424_F;
	static String field_102432_H;
	private static final String[] field_102426_Q;
	
	static final int func_102423_a(int arg0, int arg1)
	{
		// @00: getstatic int game.SteelSentinels.field_105275_O
		// @03: istore_3
		// @04: iload_1
		// @05: sipush -23881 (0xA2B7)
		// @08: if_icmpeq @14
		// @0B: bipush -29 (0xE3)
		// @0D: invokestatic game.C_100272_mn.func_102421_f(byte)void
		// @10: goto @14
		// @13: athrow
		// @14: iload_0
		// @15: istore_2
		// @16: bipush 55 (0x37)
		// @18: iload_2
		// @19: if_icmpeq @8E
		// @1C: iload_2
		// @1D: ifeq @90
		// @20: goto @24
		// @23: athrow
		// @24: bipush -58 (0xC6)
		// @26: iload_2
		// @27: iconst_m1
		// @28: ixor
		// @29: if_icmpeq @93
		// @2C: goto @30
		// @2F: athrow
		// @30: bipush 62 (0x3E)
		// @32: iload_2
		// @33: if_icmpne @42
		// @36: goto @3A
		// @39: athrow
		// @3A: iload_3
		// @3B: ifeq @95
		// @3E: goto @42
		// @41: athrow
		// @42: bipush -66 (0xBE)
		// @44: iload_2
		// @45: iconst_m1
		// @46: ixor
		// @47: if_icmpne @56
		// @4A: goto @4E
		// @4D: athrow
		// @4E: iload_3
		// @4F: ifeq @98
		// @52: goto @56
		// @55: athrow
		// @56: iload_2
		// @57: iconst_m1
		// @58: ixor
		// @59: bipush -70 (0xBA)
		// @5B: if_icmpne @6A
		// @5E: goto @62
		// @61: athrow
		// @62: iload_3
		// @63: ifeq @9B
		// @66: goto @6A
		// @69: athrow
		// @6A: bipush 72 (0x48)
		// @6C: iload_2
		// @6D: if_icmpeq @9E
		// @70: goto @74
		// @73: athrow
		// @74: bipush -76 (0xB4)
		// @76: iload_2
		// @77: iconst_m1
		// @78: ixor
		// @79: if_icmpeq @A1
		// @7C: goto @80
		// @7F: athrow
		// @80: iload_2
		// @81: bipush 79 (0x4F)
		// @83: if_icmpeq @A4
		// @86: goto @8A
		// @89: athrow
		// @8A: goto @A7
		// @8D: athrow
		// @8E: iconst_2
		// @8F: ireturn
		// @90: bipush 9 (0x09)
		// @92: ireturn
		// @93: iconst_5
		// @94: ireturn
		// @95: bipush 13 (0x0D)
		// @97: ireturn
		// @98: bipush 16 (0x10)
		// @9A: ireturn
		// @9B: bipush 19 (0x13)
		// @9D: ireturn
		// @9E: bipush 23 (0x17)
		// @A0: ireturn
		// @A1: bipush 26 (0x1A)
		// @A3: ireturn
		// @A4: bipush 28 (0x1C)
		// @A6: ireturn
		// @A7: iconst_m1
		// @A8: ireturn
		// @A9: astore_2
		// @AA: aload_2
		// @AB: new java.lang.StringBuilder
		// @AE: dup
		// @AF: invokespecial java.lang.StringBuilder.<init>()void
		// @B2: getstatic java.lang.String[] game.C_100272_mn.field_102426_Q
		// @B5: iconst_4
		// @B6: aaload
		// @B7: invokevirtual java.lang.StringBuilder.append(java.lang.String)java.lang.StringBuilder
		// @BA: iload_0
		// @BB: invokevirtual java.lang.StringBuilder.append(int)java.lang.StringBuilder
		// @BE: bipush 44 (0x2C)
		// @C0: invokevirtual java.lang.StringBuilder.append(char)java.lang.StringBuilder
		// @C3: iload_1
		// @C4: invokevirtual java.lang.StringBuilder.append(int)java.lang.StringBuilder
		// @C7: bipush 41 (0x29)
		// @C9: invokevirtual java.lang.StringBuilder.append(char)java.lang.StringBuilder
		// @CC: invokevirtual java.lang.StringBuilder.toString()java.lang.String
		// @CF: invokestatic game.C_100181_cf.func_105695_a(java.lang.Throwable, java.lang.String)game.C_100170_cm
		// @D2: athrow
	}
	
	public static void func_102421_f(byte arg0)
	{
		// @00: aconst_null
		// @01: putstatic java.lang.String game.C_100272_mn.field_102429_M
		// @04: aconst_null
		// @05: putstatic java.lang.String game.C_100272_mn.field_102432_H
		// @08: aconst_null
		// @09: putstatic java.lang.String game.C_100272_mn.field_102427_P
		// @0C: aconst_null
		// @0D: putstatic java.lang.String game.C_100272_mn.field_102430_N
		// @10: aconst_null
		// @11: putstatic game.C_100105_eg game.C_100272_mn.field_102425_G
		// @14: iload_0
		// @15: bipush 91 (0x5B)
		// @17: if_icmpge @23
		// @1A: bipush 112 (0x70)
		// @1C: invokestatic game.C_100272_mn.func_102421_f(byte)void
		// @1F: goto @23
		// @22: athrow
		// @23: aconst_null
		// @24: putstatic game.C_100037_wb game.C_100272_mn.field_102433_I
		// @27: aconst_null
		// @28: checkcast game.C_100144_bm[][]
		// @2B: putstatic game.C_100144_bm[][] game.C_100272_mn.field_102434_J
		// @2E: goto @53
		// @31: astore_1
		// @32: aload_1
		// @33: new java.lang.StringBuilder
		// @36: dup
		// @37: invokespecial java.lang.StringBuilder.<init>()void
		// @3A: getstatic java.lang.String[] game.C_100272_mn.field_102426_Q
		// @3D: bipush 8 (0x08)
		// @3F: aaload
		// @40: invokevirtual java.lang.StringBuilder.append(java.lang.String)java.lang.StringBuilder
		// @43: iload_0
		// @44: invokevirtual java.lang.StringBuilder.append(int)java.lang.StringBuilder
		// @47: bipush 41 (0x29)
		// @49: invokevirtual java.lang.StringBuilder.append(char)java.lang.StringBuilder
		// @4C: invokevirtual java.lang.StringBuilder.toString()java.lang.String
		// @4F: invokestatic game.C_100181_cf.func_105695_a(java.lang.Throwable, java.lang.String)game.C_100170_cm
		// @52: athrow
		// @53: return
	}
	
	static final void func_102420_k(int arg0)
	{
		// @00: iconst_1
		// @01: iconst_4
		// @02: invokestatic game.C_100152_bd.func_105184_a(boolean, int)void
		// @05: iload_0
		// @06: sipush 11152 (0x2B90)
		// @09: if_icmpeq @14
		// @0C: bipush 125 (0x7D)
		// @0E: bipush 96 (0x60)
		// @10: invokestatic game.C_100272_mn.func_102423_a(int, int)int
		// @13: pop
		// @14: goto @38
		// @17: astore_1
		// @18: aload_1
		// @19: new java.lang.StringBuilder
		// @1C: dup
		// @1D: invokespecial java.lang.StringBuilder.<init>()void
		// @20: getstatic java.lang.String[] game.C_100272_mn.field_102426_Q
		// @23: iconst_5
		// @24: aaload
		// @25: invokevirtual java.lang.StringBuilder.append(java.lang.String)java.lang.StringBuilder
		// @28: iload_0
		// @29: invokevirtual java.lang.StringBuilder.append(int)java.lang.StringBuilder
		// @2C: bipush 41 (0x29)
		// @2E: invokevirtual java.lang.StringBuilder.append(char)java.lang.StringBuilder
		// @31: invokevirtual java.lang.StringBuilder.toString()java.lang.String
		// @34: invokestatic game.C_100181_cf.func_105695_a(java.lang.Throwable, java.lang.String)game.C_100170_cm
		// @37: athrow
		// @38: return
	}
	
	static final void func_102422_a(int arg0, C_100278_nd arg1)
	{
		// @000: getstatic int game.SteelSentinels.field_105275_O
		// @003: istore #12
		// @005: getstatic game.C_100202_qi game.C_100132_td.field_104979_l
		// @008: bipush 55 (0x37)
		// @00A: invokevirtual game.C_100202_qi.func_105899_c(int)game.C_100158_da
		// @00D: checkcast game.C_100167_sj
		// @010: astore_2
		// @011: aload_2
		// @012: ifnonnull @016
		// @015: return
		// @016: iconst_0
		// @017: istore_3
		// @018: iconst_0
		// @019: istore #4
		// @01B: iload #4
		// @01D: iconst_m1
		// @01E: ixor
		// @01F: aload_2
		// @020: getfield int game.C_100167_sj.field_100800_y
		// @023: iconst_m1
		// @024: ixor
		// @025: if_icmple @0B5
		// @028: iload #12
		// @02A: ifne @0C0
		// @02D: aconst_null
		// @02E: aload_2
		// @02F: getfield game.C_100331_ie[] game.C_100167_sj.field_100798_p
		// @032: iload #4
		// @034: aaload
		// @035: if_acmpeq @06D
		// @038: goto @03C
		// @03B: athrow
		// @03C: iconst_2
		// @03D: aload_2
		// @03E: getfield game.C_100331_ie[] game.C_100167_sj.field_100798_p
		// @041: iload #4
		// @043: aaload
		// @044: getfield int game.C_100331_ie.field_107293_f
		// @047: if_icmpne @05B
		// @04A: goto @04E
		// @04D: athrow
		// @04E: aload_2
		// @04F: getfield int[] game.C_100167_sj.field_100790_k
		// @052: iload #4
		// @054: bipush -5 (0xFB)
		// @056: iastore
		// @057: goto @05B
		// @05A: athrow
		// @05B: aload_2
		// @05C: getfield game.C_100331_ie[] game.C_100167_sj.field_100798_p
		// @05F: iload #4
		// @061: aaload
		// @062: getfield int game.C_100331_ie.field_107293_f
		// @065: iconst_m1
		// @066: ixor
		// @067: iconst_m1
		// @068: if_icmpne @06D
		// @06B: iconst_1
		// @06C: istore_3
		// @06D: aload_2
		// @06E: getfield game.C_100331_ie[] game.C_100167_sj.field_100795_s
		// @071: iload #4
		// @073: aaload
		// @074: ifnonnull @07B
		// @077: goto @0AD
		// @07A: athrow
		// @07B: bipush -3 (0xFD)
		// @07D: aload_2
		// @07E: getfield game.C_100331_ie[] game.C_100167_sj.field_100795_s
		// @081: iload #4
		// @083: aaload
		// @084: getfield int game.C_100331_ie.field_107293_f
		// @087: iconst_m1
		// @088: ixor
		// @089: if_icmpne @099
		// @08C: aload_2
		// @08D: getfield int[] game.C_100167_sj.field_100790_k
		// @090: iload #4
		// @092: bipush -6 (0xFA)
		// @094: iastore
		// @095: goto @099
		// @098: athrow
		// @099: iconst_0
		// @09A: aload_2
		// @09B: getfield game.C_100331_ie[] game.C_100167_sj.field_100795_s
		// @09E: iload #4
		// @0A0: aaload
		// @0A1: getfield int game.C_100331_ie.field_107293_f
		// @0A4: if_icmpeq @0AB
		// @0A7: goto @0AD
		// @0AA: athrow
		// @0AB: iconst_1
		// @0AC: istore_3
		// @0AD: iinc #4 +1
		// @0B0: iload #12
		// @0B2: ifeq @01B
		// @0B5: iload_3
		// @0B6: ifeq @0BA
		// @0B9: return
		// @0BA: aload_1
		// @0BB: getfield int game.C_100278_nd.field_101177_n
		// @0BE: istore #4
		// @0C0: iload_0
		// @0C1: sipush 30781 (0x783D)
		// @0C4: if_icmpeq @0D0
		// @0C7: bipush 42 (0x2A)
		// @0C9: invokestatic game.C_100272_mn.func_102421_f(byte)void
		// @0CC: goto @0D0
		// @0CF: athrow
		// @0D0: aload_1
		// @0D1: aload_2
		// @0D2: getfield int game.C_100167_sj.field_100792_v
		// @0D5: bipush 18 (0x12)
		// @0D7: invokevirtual game.C_100278_nd.func_101154_d(int, int)void
		// @0DA: iconst_0
		// @0DB: istore #5
		// @0DD: iload #5
		// @0DF: iconst_m1
		// @0E0: ixor
		// @0E1: aload_2
		// @0E2: getfield int game.C_100167_sj.field_100800_y
		// @0E5: iconst_m1
		// @0E6: ixor
		// @0E7: if_icmple @399
		// @0EA: aload_2
		// @0EB: getfield int[] game.C_100167_sj.field_100790_k
		// @0EE: iload #5
		// @0F0: iaload
		// @0F1: iconst_m1
		// @0F2: ixor
		// @0F3: iload #12
		// @0F5: ifne @3A4
		// @0F8: iconst_m1
		// @0F9: if_icmpne @104
		// @0FC: goto @100
		// @0FF: athrow
		// @100: goto @117
		// @103: athrow
		// @104: aload_1
		// @105: sipush 7838 (0x1E9E)
		// @108: aload_2
		// @109: getfield int[] game.C_100167_sj.field_100790_k
		// @10C: iload #5
		// @10E: iaload
		// @10F: invokevirtual game.C_100278_nd.func_101169_f(int, int)void
		// @112: iload #12
		// @114: ifeq @391
		// @117: aload_2
		// @118: getfield int[] game.C_100167_sj.field_100789_j
		// @11B: iload #5
		// @11D: iaload
		// @11E: istore #6
		// @120: iload #6
		// @122: iconst_m1
		// @123: ixor
		// @124: iconst_m1
		// @125: if_icmpne @154
		// @128: aload_2
		// @129: getfield game.C_100331_ie[] game.C_100167_sj.field_100798_p
		// @12C: iload #5
		// @12E: aaload
		// @12F: getfield java.lang.Object game.C_100331_ie.field_107294_g
		// @132: checkcast java.lang.reflect.Field
		// @135: astore #7
		// @137: aload #7
		// @139: aconst_null
		// @13A: invokevirtual java.lang.reflect.Field.getInt(java.lang.Object)int
		// @13D: istore #8
		// @13F: aload_1
		// @140: sipush 7838 (0x1E9E)
		// @143: iconst_0
		// @144: invokevirtual game.C_100278_nd.func_101169_f(int, int)void
		// @147: aload_1
		// @148: iload #8
		// @14A: bipush 103 (0x67)
		// @14C: invokevirtual game.C_100278_nd.func_101154_d(int, int)void
		// @14F: iload #12
		// @151: ifeq @1BE
		// @154: bipush -2 (0xFE)
		// @156: iload #6
		// @158: iconst_m1
		// @159: ixor
		// @15A: if_icmpne @18C
		// @15D: goto @161
		// @160: athrow
		// @161: aload_2
		// @162: getfield game.C_100331_ie[] game.C_100167_sj.field_100798_p
		// @165: iload #5
		// @167: aaload
		// @168: getfield java.lang.Object game.C_100331_ie.field_107294_g
		// @16B: checkcast java.lang.reflect.Field
		// @16E: astore #7
		// @170: aload #7
		// @172: aconst_null
		// @173: aload_2
		// @174: getfield int[] game.C_100167_sj.field_100787_l
		// @177: iload #5
		// @179: iaload
		// @17A: invokevirtual java.lang.reflect.Field.setInt(java.lang.Object, int)void
		// @17D: aload_1
		// @17E: iload_0
		// @17F: sipush -22943 (0xA661)
		// @182: iadd
		// @183: iconst_0
		// @184: invokevirtual game.C_100278_nd.func_101169_f(int, int)void
		// @187: iload #12
		// @189: ifeq @1BE
		// @18C: iload #6
		// @18E: iconst_2
		// @18F: if_icmpne @1BE
		// @192: goto @196
		// @195: athrow
		// @196: aload_2
		// @197: getfield game.C_100331_ie[] game.C_100167_sj.field_100798_p
		// @19A: iload #5
		// @19C: aaload
		// @19D: getfield java.lang.Object game.C_100331_ie.field_107294_g
		// @1A0: checkcast java.lang.reflect.Field
		// @1A3: astore #7
		// @1A5: aload #7
		// @1A7: invokevirtual java.lang.reflect.Field.getModifiers()int
		// @1AA: istore #8
		// @1AC: aload_1
		// @1AD: iload_0
		// @1AE: sipush -22943 (0xA661)
		// @1B1: iadd
		// @1B2: iconst_0
		// @1B3: invokevirtual game.C_100278_nd.func_101169_f(int, int)void
		// @1B6: aload_1
		// @1B7: iload #8
		// @1B9: bipush 122 (0x7A)
		// @1BB: invokevirtual game.C_100278_nd.func_101154_d(int, int)void
		// @1BE: bipush -4 (0xFC)
		// @1C0: iload #6
		// @1C2: iconst_m1
		// @1C3: ixor
		// @1C4: if_icmpne @2B0
		// @1C7: aload_2
		// @1C8: getfield game.C_100331_ie[] game.C_100167_sj.field_100795_s
		// @1CB: iload #5
		// @1CD: aaload
		// @1CE: getfield java.lang.Object game.C_100331_ie.field_107294_g
		// @1D1: checkcast java.lang.reflect.Method
		// @1D4: astore #7
		// @1D6: aload_2
		// @1D7: getfield byte[][][] game.C_100167_sj.field_100785_n
		// @1DA: iload #5
		// @1DC: aaload
		// @1DD: astore #8
		// @1DF: aload #8
		// @1E1: arraylength
		// @1E2: anewarray java.lang.Object
		// @1E5: astore #9
		// @1E7: iconst_0
		// @1E8: istore #10
		// @1EA: aload #8
		// @1EC: arraylength
		// @1ED: iconst_m1
		// @1EE: ixor
		// @1EF: iload #10
		// @1F1: iconst_m1
		// @1F2: ixor
		// @1F3: if_icmpge @226
		// @1F6: new java.io.ObjectInputStream
		// @1F9: dup
		// @1FA: new java.io.ByteArrayInputStream
		// @1FD: dup
		// @1FE: aload #8
		// @200: iload #10
		// @202: aaload
		// @203: invokespecial java.io.ByteArrayInputStream.<init>(byte[])void
		// @206: invokespecial java.io.ObjectInputStream.<init>(java.io.InputStream)void
		// @209: astore #11
		// @20B: aload #9
		// @20D: iload #10
		// @20F: aload #11
		// @211: invokevirtual java.io.ObjectInputStream.readObject()java.lang.Object
		// @214: aastore
		// @215: iinc #10 +1
		// @218: iload #12
		// @21A: ifne @2E3
		// @21D: iload #12
		// @21F: ifeq @1EA
		// @222: goto @226
		// @225: athrow
		// @226: aload #7
		// @228: aconst_null
		// @229: aload #9
		// @22B: invokevirtual java.lang.reflect.Method.invoke(java.lang.Object, java.lang.Object[])java.lang.Object
		// @22E: astore #10
		// @230: aload #10
		// @232: ifnonnull @246
		// @235: aload_1
		// @236: sipush 7838 (0x1E9E)
		// @239: iconst_0
		// @23A: invokevirtual game.C_100278_nd.func_101169_f(int, int)void
		// @23D: iload #12
		// @23F: ifeq @2AB
		// @242: goto @246
		// @245: athrow
		// @246: aload #10
		// @248: instanceof java.lang.Number
		// @24B: ifeq @274
		// @24E: goto @252
		// @251: athrow
		// @252: aload_1
		// @253: sipush 7838 (0x1E9E)
		// @256: iconst_1
		// @257: invokevirtual game.C_100278_nd.func_101169_f(int, int)void
		// @25A: aload_1
		// @25B: iload_0
		// @25C: sipush -30781 (0x87C3)
		// @25F: iadd
		// @260: aload #10
		// @262: checkcast java.lang.Number
		// @265: invokevirtual java.lang.Number.longValue()long
		// @268: invokevirtual game.C_100278_nd.func_101131_a(int, long)void
		// @26B: iload #12
		// @26D: ifeq @2AB
		// @270: goto @274
		// @273: athrow
		// @274: aload #10
		// @276: instanceof java.lang.String
		// @279: ifeq @29F
		// @27C: goto @280
		// @27F: athrow
		// @280: aload_1
		// @281: sipush 7838 (0x1E9E)
		// @284: iconst_2
		// @285: invokevirtual game.C_100278_nd.func_101169_f(int, int)void
		// @288: aload_1
		// @289: iload_0
		// @28A: sipush -5874 (0xE90E)
		// @28D: ixor
		// @28E: aload #10
		// @290: checkcast java.lang.String
		// @293: invokevirtual game.C_100278_nd.func_101167_a(int, java.lang.String)void
		// @296: iload #12
		// @298: ifeq @2AB
		// @29B: goto @29F
		// @29E: athrow
		// @29F: aload_1
		// @2A0: sipush 7838 (0x1E9E)
		// @2A3: iconst_4
		// @2A4: invokevirtual game.C_100278_nd.func_101169_f(int, int)void
		// @2A7: goto @2AB
		// @2AA: athrow
		// @2AB: iload #12
		// @2AD: ifeq @2E3
		// @2B0: iload #6
		// @2B2: iconst_m1
		// @2B3: ixor
		// @2B4: bipush -5 (0xFB)
		// @2B6: if_icmpne @2E3
		// @2B9: goto @2BD
		// @2BC: athrow
		// @2BD: aload_2
		// @2BE: getfield game.C_100331_ie[] game.C_100167_sj.field_100795_s
		// @2C1: iload #5
		// @2C3: aaload
		// @2C4: getfield java.lang.Object game.C_100331_ie.field_107294_g
		// @2C7: checkcast java.lang.reflect.Method
		// @2CA: astore #7
		// @2CC: aload #7
		// @2CE: invokevirtual java.lang.reflect.Method.getModifiers()int
		// @2D1: istore #8
		// @2D3: aload_1
		// @2D4: sipush 7838 (0x1E9E)
		// @2D7: iconst_0
		// @2D8: invokevirtual game.C_100278_nd.func_101169_f(int, int)void
		// @2DB: aload_1
		// @2DC: iload #8
		// @2DE: bipush 9 (0x09)
		// @2E0: invokevirtual game.C_100278_nd.func_101154_d(int, int)void
		// @2E3: goto @391
		// @2E6: astore #6
		// @2E8: aload_1
		// @2E9: sipush 7838 (0x1E9E)
		// @2EC: bipush -10 (0xF6)
		// @2EE: invokevirtual game.C_100278_nd.func_101169_f(int, int)void
		// @2F1: goto @391
		// @2F4: astore #6
		// @2F6: aload_1
		// @2F7: sipush 7838 (0x1E9E)
		// @2FA: bipush -11 (0xF5)
		// @2FC: invokevirtual game.C_100278_nd.func_101169_f(int, int)void
		// @2FF: goto @391
		// @302: astore #6
		// @304: aload_1
		// @305: sipush 7838 (0x1E9E)
		// @308: bipush -12 (0xF4)
		// @30A: invokevirtual game.C_100278_nd.func_101169_f(int, int)void
		// @30D: goto @391
		// @310: astore #6
		// @312: aload_1
		// @313: iload_0
		// @314: sipush -22943 (0xA661)
		// @317: iadd
		// @318: bipush -13 (0xF3)
		// @31A: invokevirtual game.C_100278_nd.func_101169_f(int, int)void
		// @31D: goto @391
		// @320: astore #6
		// @322: aload_1
		// @323: iload_0
		// @324: sipush 26275 (0x66A3)
		// @327: ixor
		// @328: bipush -14 (0xF2)
		// @32A: invokevirtual game.C_100278_nd.func_101169_f(int, int)void
		// @32D: goto @391
		// @330: astore #6
		// @332: aload_1
		// @333: sipush 7838 (0x1E9E)
		// @336: bipush -15 (0xF1)
		// @338: invokevirtual game.C_100278_nd.func_101169_f(int, int)void
		// @33B: goto @391
		// @33E: astore #6
		// @340: aload_1
		// @341: sipush 7838 (0x1E9E)
		// @344: bipush -16 (0xF0)
		// @346: invokevirtual game.C_100278_nd.func_101169_f(int, int)void
		// @349: goto @391
		// @34C: astore #6
		// @34E: aload_1
		// @34F: sipush 7838 (0x1E9E)
		// @352: bipush -17 (0xEF)
		// @354: invokevirtual game.C_100278_nd.func_101169_f(int, int)void
		// @357: goto @391
		// @35A: astore #6
		// @35C: aload_1
		// @35D: iload_0
		// @35E: sipush 26275 (0x66A3)
		// @361: ixor
		// @362: bipush -18 (0xEE)
		// @364: invokevirtual game.C_100278_nd.func_101169_f(int, int)void
		// @367: goto @391
		// @36A: astore #6
		// @36C: aload_1
		// @36D: sipush 7838 (0x1E9E)
		// @370: bipush -19 (0xED)
		// @372: invokevirtual game.C_100278_nd.func_101169_f(int, int)void
		// @375: goto @391
		// @378: astore #6
		// @37A: aload_1
		// @37B: sipush 7838 (0x1E9E)
		// @37E: bipush -20 (0xEC)
		// @380: invokevirtual game.C_100278_nd.func_101169_f(int, int)void
		// @383: goto @391
		// @386: astore #6
		// @388: aload_1
		// @389: sipush 7838 (0x1E9E)
		// @38C: bipush -21 (0xEB)
		// @38E: invokevirtual game.C_100278_nd.func_101169_f(int, int)void
		// @391: iinc #5 +1
		// @394: iload #12
		// @396: ifeq @0DD
		// @399: aload_1
		// @39A: iload #4
		// @39C: iload_0
		// @39D: sipush -18371 (0xB83D)
		// @3A0: ixor
		// @3A1: invokevirtual game.C_100278_nd.func_101157_b(int, int)int
		// @3A4: pop
		// @3A5: aload_2
		// @3A6: iload_0
		// @3A7: sipush -30736 (0x87F0)
		// @3AA: iadd
		// @3AB: invokevirtual game.C_100167_sj.func_100583_c(int)void
		// @3AE: return
		// @3AF: astore_2
		// @3B0: aload_2
		// @3B1: new java.lang.StringBuilder
		// @3B4: dup
		// @3B5: invokespecial java.lang.StringBuilder.<init>()void
		// @3B8: getstatic java.lang.String[] game.C_100272_mn.field_102426_Q
		// @3BB: iconst_0
		// @3BC: aaload
		// @3BD: invokevirtual java.lang.StringBuilder.append(java.lang.String)java.lang.StringBuilder
		// @3C0: iload_0
		// @3C1: invokevirtual java.lang.StringBuilder.append(int)java.lang.StringBuilder
		// @3C4: bipush 44 (0x2C)
		// @3C6: invokevirtual java.lang.StringBuilder.append(char)java.lang.StringBuilder
		// @3C9: aload_1
		// @3CA: ifnull @3D6
		// @3CD: getstatic java.lang.String[] game.C_100272_mn.field_102426_Q
		// @3D0: iconst_2
		// @3D1: aaload
		// @3D2: goto @3DB
		// @3D5: athrow
		// @3D6: getstatic java.lang.String[] game.C_100272_mn.field_102426_Q
		// @3D9: iconst_1
		// @3DA: aaload
		// @3DB: invokevirtual java.lang.StringBuilder.append(java.lang.String)java.lang.StringBuilder
		// @3DE: bipush 41 (0x29)
		// @3E0: invokevirtual java.lang.StringBuilder.append(char)java.lang.StringBuilder
		// @3E3: invokevirtual java.lang.StringBuilder.toString()java.lang.String
		// @3E6: invokestatic game.C_100181_cf.func_105695_a(java.lang.Throwable, java.lang.String)game.C_100170_cm
		// @3E9: athrow
	}
	
	C_100272_mn(Object arg0, int arg1)
	{
		// @00: aload_0
		// @01: iload_2
		// @02: invokespecial game.C_100316_lc.<init>(int)void
		// @05: aload_0
		// @06: aload_1
		// @07: putfield java.lang.Object game.C_100272_mn.field_102424_F
		// @0A: goto @49
		// @0D: astore_3
		// @0E: aload_3
		// @0F: new java.lang.StringBuilder
		// @12: dup
		// @13: invokespecial java.lang.StringBuilder.<init>()void
		// @16: getstatic java.lang.String[] game.C_100272_mn.field_102426_Q
		// @19: bipush 6 (0x06)
		// @1B: aaload
		// @1C: invokevirtual java.lang.StringBuilder.append(java.lang.String)java.lang.StringBuilder
		// @1F: aload_1
		// @20: ifnull @2C
		// @23: getstatic java.lang.String[] game.C_100272_mn.field_102426_Q
		// @26: iconst_2
		// @27: aaload
		// @28: goto @31
		// @2B: athrow
		// @2C: getstatic java.lang.String[] game.C_100272_mn.field_102426_Q
		// @2F: iconst_1
		// @30: aaload
		// @31: invokevirtual java.lang.StringBuilder.append(java.lang.String)java.lang.StringBuilder
		// @34: bipush 44 (0x2C)
		// @36: invokevirtual java.lang.StringBuilder.append(char)java.lang.StringBuilder
		// @39: iload_2
		// @3A: invokevirtual java.lang.StringBuilder.append(int)java.lang.StringBuilder
		// @3D: bipush 41 (0x29)
		// @3F: invokevirtual java.lang.StringBuilder.append(char)java.lang.StringBuilder
		// @42: invokevirtual java.lang.StringBuilder.toString()java.lang.String
		// @45: invokestatic game.C_100181_cf.func_105695_a(java.lang.Throwable, java.lang.String)game.C_100170_cm
		// @48: athrow
		// @49: return
	}
	
	final Object func_102398_j(int arg0)
	{
		// @00: iload_1
		// @01: sipush 255 (0x00FF)
		// @04: if_icmpeq @0C
		// @07: aconst_null
		// @08: checkcast java.lang.Object
		// @0B: areturn
		// @0C: aload_0
		// @0D: getfield java.lang.Object game.C_100272_mn.field_102424_F
		// @10: areturn
		// @11: astore_2
		// @12: aload_2
		// @13: new java.lang.StringBuilder
		// @16: dup
		// @17: invokespecial java.lang.StringBuilder.<init>()void
		// @1A: getstatic java.lang.String[] game.C_100272_mn.field_102426_Q
		// @1D: bipush 7 (0x07)
		// @1F: aaload
		// @20: invokevirtual java.lang.StringBuilder.append(java.lang.String)java.lang.StringBuilder
		// @23: iload_1
		// @24: invokevirtual java.lang.StringBuilder.append(int)java.lang.StringBuilder
		// @27: bipush 41 (0x29)
		// @29: invokevirtual java.lang.StringBuilder.append(char)java.lang.StringBuilder
		// @2C: invokevirtual java.lang.StringBuilder.toString()java.lang.String
		// @2F: invokestatic game.C_100181_cf.func_105695_a(java.lang.Throwable, java.lang.String)game.C_100170_cm
		// @32: athrow
	}
	
	final boolean func_102402_i(int arg0)
	{
		// @00: iload_1
		// @01: sipush -20116 (0xB16C)
		// @04: if_icmpeq @12
		// @07: aconst_null
		// @08: checkcast java.lang.String
		// @0B: putstatic java.lang.String game.C_100272_mn.field_102432_H
		// @0E: goto @12
		// @11: athrow
		// @12: iconst_0
		// @13: ireturn
		// @14: astore_2
		// @15: aload_2
		// @16: new java.lang.StringBuilder
		// @19: dup
		// @1A: invokespecial java.lang.StringBuilder.<init>()void
		// @1D: getstatic java.lang.String[] game.C_100272_mn.field_102426_Q
		// @20: iconst_3
		// @21: aaload
		// @22: invokevirtual java.lang.StringBuilder.append(java.lang.String)java.lang.StringBuilder
		// @25: iload_1
		// @26: invokevirtual java.lang.StringBuilder.append(int)java.lang.StringBuilder
		// @29: bipush 41 (0x29)
		// @2B: invokevirtual java.lang.StringBuilder.append(char)java.lang.StringBuilder
		// @2E: invokevirtual java.lang.StringBuilder.toString()java.lang.String
		// @31: invokestatic game.C_100181_cf.func_105695_a(java.lang.Throwable, java.lang.String)game.C_100170_cm
		// @34: athrow
	}
	
	static
	{
		// @00: bipush 9 (0x09)
		// @02: anewarray java.lang.String
		// @05: dup
		// @06: iconst_0
		// @07: ldc "h\u0008)\u0004U"
		// @09: invokestatic game.C_100272_mn.func_102419_z(java.lang.String)char[]
		// @0C: invokestatic game.C_100272_mn.func_102418_z(char[])java.lang.String
		// @0F: aastore
		// @10: dup
		// @11: iconst_1
		// @12: ldc "k\u0013k-"
		// @14: invokestatic game.C_100272_mn.func_102419_z(java.lang.String)char[]
		// @17: invokestatic game.C_100272_mn.func_102418_z(char[])java.lang.String
		// @1A: aastore
		// @1B: dup
		// @1C: iconst_2
		// @1D: ldc "~H)o\u0000"
		// @1F: invokestatic game.C_100272_mn.func_102419_z(java.lang.String)char[]
		// @22: invokestatic game.C_100272_mn.func_102418_z(char[])java.lang.String
		// @25: aastore
		// @26: dup
		// @27: iconst_3
		// @28: ldc "h\u0008)\u0000U"
		// @2A: invokestatic game.C_100272_mn.func_102419_z(java.lang.String)char[]
		// @2D: invokestatic game.C_100272_mn.func_102418_z(char[])java.lang.String
		// @30: aastore
		// @31: dup
		// @32: iconst_4
		// @33: ldc "h\u0008)\u0003U"
		// @35: invokestatic game.C_100272_mn.func_102419_z(java.lang.String)char[]
		// @38: invokestatic game.C_100272_mn.func_102418_z(char[])java.lang.String
		// @3B: aastore
		// @3C: dup
		// @3D: iconst_5
		// @3E: ldc "h\u0008)\u0007U"
		// @40: invokestatic game.C_100272_mn.func_102419_z(java.lang.String)char[]
		// @43: invokestatic game.C_100272_mn.func_102418_z(char[])java.lang.String
		// @46: aastore
		// @47: dup
		// @48: bipush 6 (0x06)
		// @4A: ldc "h\u0008)}\u0014k\u000fs\u007fU"
		// @4C: invokestatic game.C_100272_mn.func_102419_z(java.lang.String)char[]
		// @4F: invokestatic game.C_100272_mn.func_102418_z(char[])java.lang.String
		// @52: aastore
		// @53: dup
		// @54: bipush 7 (0x07)
		// @56: ldc "h\u0008)\u0002U"
		// @58: invokestatic game.C_100272_mn.func_102419_z(java.lang.String)char[]
		// @5B: invokestatic game.C_100272_mn.func_102418_z(char[])java.lang.String
		// @5E: aastore
		// @5F: dup
		// @60: bipush 8 (0x08)
		// @62: ldc "h\u0008)\u0005U"
		// @64: invokestatic game.C_100272_mn.func_102419_z(java.lang.String)char[]
		// @67: invokestatic game.C_100272_mn.func_102418_z(char[])java.lang.String
		// @6A: aastore
		// @6B: putstatic java.lang.String[] game.C_100272_mn.field_102426_Q
		// @6E: ldc "V\u0003i5\u0014k\u0003k2]@\u001ew \u0013v\u000fh/"
		// @70: invokestatic game.C_100272_mn.func_102419_z(java.lang.String)char[]
		// @73: invokestatic game.C_100272_mn.func_102418_z(char[])java.lang.String
		// @76: putstatic java.lang.String game.C_100272_mn.field_102427_P
		// @79: iconst_1
		// @7A: putstatic boolean game.C_100272_mn.field_102435_K
		// @7D: aconst_null
		// @7E: putstatic game.C_100152_bd game.C_100272_mn.field_102428_L
		// @81: ldc "I\te#\u0004"
		// @83: invokestatic game.C_100272_mn.func_102419_z(java.lang.String)char[]
		// @86: invokestatic game.C_100272_mn.func_102418_z(char[])java.lang.String
		// @89: putstatic java.lang.String game.C_100272_mn.field_102432_H
		// @8C: ldc "F\ti5\u0014k\u0013b"
		// @8E: invokestatic game.C_100272_mn.func_102419_z(java.lang.String)char[]
		// @91: invokestatic game.C_100272_mn.func_102418_z(char[])java.lang.String
		// @94: putstatic java.lang.String game.C_100272_mn.field_102429_M
		// @97: ldc "M\u000f`)\u000ef\tu$\u000e"
		// @99: invokestatic game.C_100272_mn.func_102419_z(java.lang.String)char[]
		// @9C: invokestatic game.C_100272_mn.func_102418_z(char[])java.lang.String
		// @9F: putstatic java.lang.String game.C_100272_mn.field_102430_N
		// @A2: bipush 64 (0x40)
		// @A4: putstatic int game.C_100272_mn.field_102431_O
		// @A7: return
	}
	
	private static char[] func_102419_z(String arg0)
	{
		// @00: aload_0
		// @01: invokevirtual java.lang.String.toCharArray()char[]
		// @04: dup
		// @05: arraylength
		// @06: iconst_2
		// @07: if_icmpge @13
		// @0A: dup
		// @0B: iconst_0
		// @0C: dup2
		// @0D: caload
		// @0E: bipush 125 (0x7D)
		// @10: ixor
		// @11: i2c
		// @12: castore
		// @13: areturn
	}
	
	private static String func_102418_z(char[] arg0)
	{
		// @00: aload_0
		// @01: dup
		// @02: arraylength
		// @03: swap
		// @04: iconst_0
		// @05: istore_1
		// @06: goto @4B
		// @09: dup
		// @0A: iload_1
		// @0B: dup2
		// @0C: caload
		// @0D: iload_1
		// @0E: iconst_5
		// @0F: irem
		// @10: tableswitch def: @43, for 0: @30, for 1: @34, for 2: @39, for 3: @3E
		// @30: iconst_5
		// @31: goto @45
		// @34: bipush 102 (0x66)
		// @36: goto @45
		// @39: bipush 7 (0x07)
		// @3B: goto @45
		// @3E: bipush 65 (0x41)
		// @40: goto @45
		// @43: bipush 125 (0x7D)
		// @45: ixor
		// @46: i2c
		// @47: castore
		// @48: iinc #1 +1
		// @4B: swap
		// @4C: dup_x1
		// @4D: iload_1
		// @4E: if_icmpgt @09
		// @51: new java.lang.String
		// @54: dup_x1
		// @55: swap
		// @56: invokespecial java.lang.String.<init>(char[])void
		// @59: invokevirtual java.lang.String.intern()java.lang.String
		// @5C: areturn
	}
}
