package game;

final class C_100014_wg
{
	private C_100280_nf field_103764_f;
	private static byte[] field_103770_a;
	int[] field_103768_b;
	private int[] field_103767_e;
	private int field_103766_d;
	private long field_103772_i;
	private int[] field_103769_c;
	private int[] field_103771_h;
	int field_103765_g;
	
	final void func_103752_a(byte[] arg0)
	{
		// @00: aload_0
		// @01: getfield game.C_100280_nf game.C_100014_wg.field_103764_f
		// @04: aload_1
		// @05: putfield byte[] game.C_100280_nf.field_101179_l
		// @08: aload_0
		// @09: getfield game.C_100280_nf game.C_100014_wg.field_103764_f
		// @0C: bipush 10 (0x0A)
		// @0E: putfield int game.C_100280_nf.field_101177_n
		// @11: aload_0
		// @12: getfield game.C_100280_nf game.C_100014_wg.field_103764_f
		// @15: bipush -2 (0xFE)
		// @17: invokevirtual game.C_100280_nf.func_101143_l(int)int
		// @1A: istore_2
		// @1B: aload_0
		// @1C: aload_0
		// @1D: getfield game.C_100280_nf game.C_100014_wg.field_103764_f
		// @20: bipush -2 (0xFE)
		// @22: invokevirtual game.C_100280_nf.func_101143_l(int)int
		// @25: putfield int game.C_100014_wg.field_103765_g
		// @28: aload_0
		// @29: ldc 500000 (0x7a120)
		// @2B: putfield int game.C_100014_wg.field_103766_d
		// @2E: aload_0
		// @2F: iload_2
		// @30: newarray int[]
		// @32: putfield int[] game.C_100014_wg.field_103769_c
		// @35: iconst_0
		// @36: istore_3
		// @37: iload_3
		// @38: iload_2
		// @39: if_icmpge @7C
		// @3C: aload_0
		// @3D: getfield game.C_100280_nf game.C_100014_wg.field_103764_f
		// @40: sipush -1543 (0xF9F9)
		// @43: invokevirtual game.C_100280_nf.func_101171_e(int)int
		// @46: istore #4
		// @48: aload_0
		// @49: getfield game.C_100280_nf game.C_100014_wg.field_103764_f
		// @4C: sipush -1543 (0xF9F9)
		// @4F: invokevirtual game.C_100280_nf.func_101171_e(int)int
		// @52: istore #5
		// @54: iload #4
		// @56: ldc 1297379947 (0x4d54726b)
		// @58: if_icmpne @6B
		// @5B: aload_0
		// @5C: getfield int[] game.C_100014_wg.field_103769_c
		// @5F: iload_3
		// @60: aload_0
		// @61: getfield game.C_100280_nf game.C_100014_wg.field_103764_f
		// @64: getfield int game.C_100280_nf.field_101177_n
		// @67: iastore
		// @68: iinc #3 +1
		// @6B: aload_0
		// @6C: getfield game.C_100280_nf game.C_100014_wg.field_103764_f
		// @6F: dup
		// @70: getfield int game.C_100280_nf.field_101177_n
		// @73: iload #5
		// @75: iadd
		// @76: putfield int game.C_100280_nf.field_101177_n
		// @79: goto @37
		// @7C: aload_0
		// @7D: lconst_0
		// @7E: putfield long game.C_100014_wg.field_103772_i
		// @81: aload_0
		// @82: iload_2
		// @83: newarray int[]
		// @85: putfield int[] game.C_100014_wg.field_103767_e
		// @88: iconst_0
		// @89: istore_3
		// @8A: iload_3
		// @8B: iload_2
		// @8C: if_icmpge @A1
		// @8F: aload_0
		// @90: getfield int[] game.C_100014_wg.field_103767_e
		// @93: iload_3
		// @94: aload_0
		// @95: getfield int[] game.C_100014_wg.field_103769_c
		// @98: iload_3
		// @99: iaload
		// @9A: iastore
		// @9B: iinc #3 +1
		// @9E: goto @8A
		// @A1: aload_0
		// @A2: iload_2
		// @A3: newarray int[]
		// @A5: putfield int[] game.C_100014_wg.field_103768_b
		// @A8: aload_0
		// @A9: iload_2
		// @AA: newarray int[]
		// @AC: putfield int[] game.C_100014_wg.field_103771_h
		// @AF: return
	}
	
	final void func_103762_c()
	{
		// @00: aload_0
		// @01: getfield game.C_100280_nf game.C_100014_wg.field_103764_f
		// @04: aconst_null
		// @05: putfield byte[] game.C_100280_nf.field_101179_l
		// @08: aload_0
		// @09: aconst_null
		// @0A: putfield int[] game.C_100014_wg.field_103769_c
		// @0D: aload_0
		// @0E: aconst_null
		// @0F: putfield int[] game.C_100014_wg.field_103767_e
		// @12: aload_0
		// @13: aconst_null
		// @14: putfield int[] game.C_100014_wg.field_103768_b
		// @17: aload_0
		// @18: aconst_null
		// @19: putfield int[] game.C_100014_wg.field_103771_h
		// @1C: return
	}
	
	final boolean func_103753_g()
	{
		// @00: aload_0
		// @01: getfield int[] game.C_100014_wg.field_103767_e
		// @04: arraylength
		// @05: istore_1
		// @06: iconst_0
		// @07: istore_2
		// @08: iload_2
		// @09: iload_1
		// @0A: if_icmpge @1E
		// @0D: aload_0
		// @0E: getfield int[] game.C_100014_wg.field_103767_e
		// @11: iload_2
		// @12: iaload
		// @13: iflt @18
		// @16: iconst_0
		// @17: ireturn
		// @18: iinc #2 +1
		// @1B: goto @08
		// @1E: iconst_1
		// @1F: ireturn
	}
	
	final boolean func_103757_d()
	{
		// @00: aload_0
		// @01: getfield game.C_100280_nf game.C_100014_wg.field_103764_f
		// @04: getfield byte[] game.C_100280_nf.field_101179_l
		// @07: ifnull @0E
		// @0A: iconst_1
		// @0B: goto @0F
		// @0E: iconst_0
		// @0F: ireturn
	}
	
	private final int func_103763_e(int arg0)
	{
		// @00: aload_0
		// @01: getfield game.C_100280_nf game.C_100014_wg.field_103764_f
		// @04: getfield byte[] game.C_100280_nf.field_101179_l
		// @07: aload_0
		// @08: getfield game.C_100280_nf game.C_100014_wg.field_103764_f
		// @0B: getfield int game.C_100280_nf.field_101177_n
		// @0E: baload
		// @0F: istore_2
		// @10: iload_2
		// @11: ifge @31
		// @14: iload_2
		// @15: sipush 255 (0x00FF)
		// @18: iand
		// @19: istore_2
		// @1A: aload_0
		// @1B: getfield int[] game.C_100014_wg.field_103771_h
		// @1E: iload_1
		// @1F: iload_2
		// @20: iastore
		// @21: aload_0
		// @22: getfield game.C_100280_nf game.C_100014_wg.field_103764_f
		// @25: dup
		// @26: getfield int game.C_100280_nf.field_101177_n
		// @29: iconst_1
		// @2A: iadd
		// @2B: putfield int game.C_100280_nf.field_101177_n
		// @2E: goto @38
		// @31: aload_0
		// @32: getfield int[] game.C_100014_wg.field_103771_h
		// @35: iload_1
		// @36: iaload
		// @37: istore_2
		// @38: iload_2
		// @39: sipush 240 (0x00F0)
		// @3C: if_icmpeq @46
		// @3F: iload_2
		// @40: sipush 247 (0x00F7)
		// @43: if_icmpne @D4
		// @46: aload_0
		// @47: getfield game.C_100280_nf game.C_100014_wg.field_103764_f
		// @4A: bipush -110 (0x92)
		// @4C: invokevirtual game.C_100280_nf.func_101158_h(int)int
		// @4F: istore_3
		// @50: iload_2
		// @51: sipush 247 (0x00F7)
		// @54: if_icmpne @C5
		// @57: iload_3
		// @58: ifle @C5
		// @5B: aload_0
		// @5C: getfield game.C_100280_nf game.C_100014_wg.field_103764_f
		// @5F: getfield byte[] game.C_100280_nf.field_101179_l
		// @62: aload_0
		// @63: getfield game.C_100280_nf game.C_100014_wg.field_103764_f
		// @66: getfield int game.C_100280_nf.field_101177_n
		// @69: baload
		// @6A: sipush 255 (0x00FF)
		// @6D: iand
		// @6E: istore #4
		// @70: iload #4
		// @72: sipush 241 (0x00F1)
		// @75: if_icmplt @80
		// @78: iload #4
		// @7A: sipush 243 (0x00F3)
		// @7D: if_icmple @A8
		// @80: iload #4
		// @82: sipush 246 (0x00F6)
		// @85: if_icmpeq @A8
		// @88: iload #4
		// @8A: sipush 248 (0x00F8)
		// @8D: if_icmpeq @A8
		// @90: iload #4
		// @92: sipush 250 (0x00FA)
		// @95: if_icmplt @A0
		// @98: iload #4
		// @9A: sipush 252 (0x00FC)
		// @9D: if_icmple @A8
		// @A0: iload #4
		// @A2: sipush 254 (0x00FE)
		// @A5: if_icmpne @C5
		// @A8: aload_0
		// @A9: getfield game.C_100280_nf game.C_100014_wg.field_103764_f
		// @AC: dup
		// @AD: getfield int game.C_100280_nf.field_101177_n
		// @B0: iconst_1
		// @B1: iadd
		// @B2: putfield int game.C_100280_nf.field_101177_n
		// @B5: aload_0
		// @B6: getfield int[] game.C_100014_wg.field_103771_h
		// @B9: iload_1
		// @BA: iload #4
		// @BC: iastore
		// @BD: aload_0
		// @BE: iload_1
		// @BF: iload #4
		// @C1: invokespecial game.C_100014_wg.func_103754_a(int, int)int
		// @C4: ireturn
		// @C5: aload_0
		// @C6: getfield game.C_100280_nf game.C_100014_wg.field_103764_f
		// @C9: dup
		// @CA: getfield int game.C_100280_nf.field_101177_n
		// @CD: iload_3
		// @CE: iadd
		// @CF: putfield int game.C_100280_nf.field_101177_n
		// @D2: iconst_0
		// @D3: ireturn
		// @D4: aload_0
		// @D5: iload_1
		// @D6: iload_2
		// @D7: invokespecial game.C_100014_wg.func_103754_a(int, int)int
		// @DA: ireturn
	}
	
	final long func_103750_f(int arg0)
	{
		// @0: aload_0
		// @1: getfield long game.C_100014_wg.field_103772_i
		// @4: iload_1
		// @5: i2l
		// @6: aload_0
		// @7: getfield int game.C_100014_wg.field_103766_d
		// @A: i2l
		// @B: lmul
		// @C: ladd
		// @D: lreturn
	}
	
	public static void func_103755_f()
	{
		// @0: aconst_null
		// @1: putstatic byte[] game.C_100014_wg.field_103770_a
		// @4: return
	}
	
	final int func_103760_d(int arg0)
	{
		// @0: aload_0
		// @1: iload_1
		// @2: invokespecial game.C_100014_wg.func_103763_e(int)int
		// @5: istore_2
		// @6: iload_2
		// @7: ireturn
	}
	
	final void func_103756_c(int arg0)
	{
		// @0: aload_0
		// @1: getfield game.C_100280_nf game.C_100014_wg.field_103764_f
		// @4: aload_0
		// @5: getfield int[] game.C_100014_wg.field_103767_e
		// @8: iload_1
		// @9: iaload
		// @A: putfield int game.C_100280_nf.field_101177_n
		// @D: return
	}
	
	final void func_103748_b(int arg0)
	{
		// @0: aload_0
		// @1: getfield int[] game.C_100014_wg.field_103767_e
		// @4: iload_1
		// @5: aload_0
		// @6: getfield game.C_100280_nf game.C_100014_wg.field_103764_f
		// @9: getfield int game.C_100280_nf.field_101177_n
		// @C: iastore
		// @D: return
	}
	
	final void func_103751_a(int arg0)
	{
		// @00: aload_0
		// @01: getfield game.C_100280_nf game.C_100014_wg.field_103764_f
		// @04: bipush -127 (0x81)
		// @06: invokevirtual game.C_100280_nf.func_101158_h(int)int
		// @09: istore_2
		// @0A: aload_0
		// @0B: getfield int[] game.C_100014_wg.field_103768_b
		// @0E: iload_1
		// @0F: dup2
		// @10: iaload
		// @11: iload_2
		// @12: iadd
		// @13: iastore
		// @14: return
	}
	
	final void func_103761_a(long arg0)
	{
		// @00: aload_0
		// @01: lload_1
		// @02: putfield long game.C_100014_wg.field_103772_i
		// @05: aload_0
		// @06: getfield int[] game.C_100014_wg.field_103767_e
		// @09: arraylength
		// @0A: istore_3
		// @0B: iconst_0
		// @0C: istore #4
		// @0E: iload #4
		// @10: iload_3
		// @11: if_icmpge @4C
		// @14: aload_0
		// @15: getfield int[] game.C_100014_wg.field_103768_b
		// @18: iload #4
		// @1A: iconst_0
		// @1B: iastore
		// @1C: aload_0
		// @1D: getfield int[] game.C_100014_wg.field_103771_h
		// @20: iload #4
		// @22: iconst_0
		// @23: iastore
		// @24: aload_0
		// @25: getfield game.C_100280_nf game.C_100014_wg.field_103764_f
		// @28: aload_0
		// @29: getfield int[] game.C_100014_wg.field_103769_c
		// @2C: iload #4
		// @2E: iaload
		// @2F: putfield int game.C_100280_nf.field_101177_n
		// @32: aload_0
		// @33: iload #4
		// @35: invokevirtual game.C_100014_wg.func_103751_a(int)void
		// @38: aload_0
		// @39: getfield int[] game.C_100014_wg.field_103767_e
		// @3C: iload #4
		// @3E: aload_0
		// @3F: getfield game.C_100280_nf game.C_100014_wg.field_103764_f
		// @42: getfield int game.C_100280_nf.field_101177_n
		// @45: iastore
		// @46: iinc #4 +1
		// @49: goto @0E
		// @4C: return
	}
	
	private final int func_103754_a(int arg0, int arg1)
	{
		// @00: iload_2
		// @01: sipush 255 (0x00FF)
		// @04: if_icmpne @88
		// @07: aload_0
		// @08: getfield game.C_100280_nf game.C_100014_wg.field_103764_f
		// @0B: iconst_0
		// @0C: invokevirtual game.C_100280_nf.func_101156_c(boolean)int
		// @0F: istore_3
		// @10: aload_0
		// @11: getfield game.C_100280_nf game.C_100014_wg.field_103764_f
		// @14: bipush 106 (0x6A)
		// @16: invokevirtual game.C_100280_nf.func_101158_h(int)int
		// @19: istore #4
		// @1B: iload_3
		// @1C: bipush 47 (0x2F)
		// @1E: if_icmpne @31
		// @21: aload_0
		// @22: getfield game.C_100280_nf game.C_100014_wg.field_103764_f
		// @25: dup
		// @26: getfield int game.C_100280_nf.field_101177_n
		// @29: iload #4
		// @2B: iadd
		// @2C: putfield int game.C_100280_nf.field_101177_n
		// @2F: iconst_1
		// @30: ireturn
		// @31: iload_3
		// @32: bipush 81 (0x51)
		// @34: if_icmpne @78
		// @37: aload_0
		// @38: getfield game.C_100280_nf game.C_100014_wg.field_103764_f
		// @3B: bipush 119 (0x77)
		// @3D: invokevirtual game.C_100280_nf.func_101145_d(byte)int
		// @40: istore #5
		// @42: iinc #4 +253
		// @45: aload_0
		// @46: getfield int[] game.C_100014_wg.field_103768_b
		// @49: iload_1
		// @4A: iaload
		// @4B: istore #6
		// @4D: aload_0
		// @4E: dup
		// @4F: getfield long game.C_100014_wg.field_103772_i
		// @52: iload #6
		// @54: i2l
		// @55: aload_0
		// @56: getfield int game.C_100014_wg.field_103766_d
		// @59: iload #5
		// @5B: isub
		// @5C: i2l
		// @5D: lmul
		// @5E: ladd
		// @5F: putfield long game.C_100014_wg.field_103772_i
		// @62: aload_0
		// @63: iload #5
		// @65: putfield int game.C_100014_wg.field_103766_d
		// @68: aload_0
		// @69: getfield game.C_100280_nf game.C_100014_wg.field_103764_f
		// @6C: dup
		// @6D: getfield int game.C_100280_nf.field_101177_n
		// @70: iload #4
		// @72: iadd
		// @73: putfield int game.C_100280_nf.field_101177_n
		// @76: iconst_2
		// @77: ireturn
		// @78: aload_0
		// @79: getfield game.C_100280_nf game.C_100014_wg.field_103764_f
		// @7C: dup
		// @7D: getfield int game.C_100280_nf.field_101177_n
		// @80: iload #4
		// @82: iadd
		// @83: putfield int game.C_100280_nf.field_101177_n
		// @86: iconst_3
		// @87: ireturn
		// @88: getstatic byte[] game.C_100014_wg.field_103770_a
		// @8B: iload_2
		// @8C: sipush 128 (0x0080)
		// @8F: isub
		// @90: baload
		// @91: istore_3
		// @92: iload_2
		// @93: istore #4
		// @95: iload_3
		// @96: iconst_1
		// @97: if_icmplt @AA
		// @9A: iload #4
		// @9C: aload_0
		// @9D: getfield game.C_100280_nf game.C_100014_wg.field_103764_f
		// @A0: iconst_0
		// @A1: invokevirtual game.C_100280_nf.func_101156_c(boolean)int
		// @A4: bipush 8 (0x08)
		// @A6: ishl
		// @A7: ior
		// @A8: istore #4
		// @AA: iload_3
		// @AB: iconst_2
		// @AC: if_icmplt @BF
		// @AF: iload #4
		// @B1: aload_0
		// @B2: getfield game.C_100280_nf game.C_100014_wg.field_103764_f
		// @B5: iconst_0
		// @B6: invokevirtual game.C_100280_nf.func_101156_c(boolean)int
		// @B9: bipush 16 (0x10)
		// @BB: ishl
		// @BC: ior
		// @BD: istore #4
		// @BF: iload #4
		// @C1: ireturn
	}
	
	final int func_103758_a()
	{
		// @00: aload_0
		// @01: getfield int[] game.C_100014_wg.field_103767_e
		// @04: arraylength
		// @05: istore_1
		// @06: iconst_m1
		// @07: istore_2
		// @08: ldc 2147483647 (0x7fffffff)
		// @0A: istore_3
		// @0B: iconst_0
		// @0C: istore #4
		// @0E: iload #4
		// @10: iload_1
		// @11: if_icmpge @3D
		// @14: aload_0
		// @15: getfield int[] game.C_100014_wg.field_103767_e
		// @18: iload #4
		// @1A: iaload
		// @1B: ifge @21
		// @1E: goto @37
		// @21: aload_0
		// @22: getfield int[] game.C_100014_wg.field_103768_b
		// @25: iload #4
		// @27: iaload
		// @28: iload_3
		// @29: if_icmpge @37
		// @2C: iload #4
		// @2E: istore_2
		// @2F: aload_0
		// @30: getfield int[] game.C_100014_wg.field_103768_b
		// @33: iload #4
		// @35: iaload
		// @36: istore_3
		// @37: iinc #4 +1
		// @3A: goto @0E
		// @3D: iload_2
		// @3E: ireturn
	}
	
	final int func_103749_e()
	{
		// @0: aload_0
		// @1: getfield int[] game.C_100014_wg.field_103767_e
		// @4: arraylength
		// @5: ireturn
	}
	
	final void func_103759_b()
	{
		// @0: aload_0
		// @1: getfield game.C_100280_nf game.C_100014_wg.field_103764_f
		// @4: iconst_m1
		// @5: putfield int game.C_100280_nf.field_101177_n
		// @8: return
	}
	
	C_100014_wg()
	{
		// @00: aload_0
		// @01: invokespecial java.lang.Object.<init>()void
		// @04: aload_0
		// @05: new game.C_100280_nf
		// @08: dup
		// @09: aconst_null
		// @0A: invokespecial game.C_100280_nf.<init>(byte[])void
		// @0D: putfield game.C_100280_nf game.C_100014_wg.field_103764_f
		// @10: return
	}
	
	C_100014_wg(byte[] arg0)
	{
		// @00: aload_0
		// @01: invokespecial java.lang.Object.<init>()void
		// @04: aload_0
		// @05: new game.C_100280_nf
		// @08: dup
		// @09: aconst_null
		// @0A: invokespecial game.C_100280_nf.<init>(byte[])void
		// @0D: putfield game.C_100280_nf game.C_100014_wg.field_103764_f
		// @10: aload_0
		// @11: aload_1
		// @12: invokevirtual game.C_100014_wg.func_103752_a(byte[])void
		// @15: return
	}
	
	static
	{
		// @000: sipush 128 (0x0080)
		// @003: newarray byte[]
		// @005: dup
		// @006: iconst_0
		// @007: iconst_2
		// @008: bastore
		// @009: dup
		// @00A: iconst_1
		// @00B: iconst_2
		// @00C: bastore
		// @00D: dup
		// @00E: iconst_2
		// @00F: iconst_2
		// @010: bastore
		// @011: dup
		// @012: iconst_3
		// @013: iconst_2
		// @014: bastore
		// @015: dup
		// @016: iconst_4
		// @017: iconst_2
		// @018: bastore
		// @019: dup
		// @01A: iconst_5
		// @01B: iconst_2
		// @01C: bastore
		// @01D: dup
		// @01E: bipush 6 (0x06)
		// @020: iconst_2
		// @021: bastore
		// @022: dup
		// @023: bipush 7 (0x07)
		// @025: iconst_2
		// @026: bastore
		// @027: dup
		// @028: bipush 8 (0x08)
		// @02A: iconst_2
		// @02B: bastore
		// @02C: dup
		// @02D: bipush 9 (0x09)
		// @02F: iconst_2
		// @030: bastore
		// @031: dup
		// @032: bipush 10 (0x0A)
		// @034: iconst_2
		// @035: bastore
		// @036: dup
		// @037: bipush 11 (0x0B)
		// @039: iconst_2
		// @03A: bastore
		// @03B: dup
		// @03C: bipush 12 (0x0C)
		// @03E: iconst_2
		// @03F: bastore
		// @040: dup
		// @041: bipush 13 (0x0D)
		// @043: iconst_2
		// @044: bastore
		// @045: dup
		// @046: bipush 14 (0x0E)
		// @048: iconst_2
		// @049: bastore
		// @04A: dup
		// @04B: bipush 15 (0x0F)
		// @04D: iconst_2
		// @04E: bastore
		// @04F: dup
		// @050: bipush 16 (0x10)
		// @052: iconst_2
		// @053: bastore
		// @054: dup
		// @055: bipush 17 (0x11)
		// @057: iconst_2
		// @058: bastore
		// @059: dup
		// @05A: bipush 18 (0x12)
		// @05C: iconst_2
		// @05D: bastore
		// @05E: dup
		// @05F: bipush 19 (0x13)
		// @061: iconst_2
		// @062: bastore
		// @063: dup
		// @064: bipush 20 (0x14)
		// @066: iconst_2
		// @067: bastore
		// @068: dup
		// @069: bipush 21 (0x15)
		// @06B: iconst_2
		// @06C: bastore
		// @06D: dup
		// @06E: bipush 22 (0x16)
		// @070: iconst_2
		// @071: bastore
		// @072: dup
		// @073: bipush 23 (0x17)
		// @075: iconst_2
		// @076: bastore
		// @077: dup
		// @078: bipush 24 (0x18)
		// @07A: iconst_2
		// @07B: bastore
		// @07C: dup
		// @07D: bipush 25 (0x19)
		// @07F: iconst_2
		// @080: bastore
		// @081: dup
		// @082: bipush 26 (0x1A)
		// @084: iconst_2
		// @085: bastore
		// @086: dup
		// @087: bipush 27 (0x1B)
		// @089: iconst_2
		// @08A: bastore
		// @08B: dup
		// @08C: bipush 28 (0x1C)
		// @08E: iconst_2
		// @08F: bastore
		// @090: dup
		// @091: bipush 29 (0x1D)
		// @093: iconst_2
		// @094: bastore
		// @095: dup
		// @096: bipush 30 (0x1E)
		// @098: iconst_2
		// @099: bastore
		// @09A: dup
		// @09B: bipush 31 (0x1F)
		// @09D: iconst_2
		// @09E: bastore
		// @09F: dup
		// @0A0: bipush 32 (0x20)
		// @0A2: iconst_2
		// @0A3: bastore
		// @0A4: dup
		// @0A5: bipush 33 (0x21)
		// @0A7: iconst_2
		// @0A8: bastore
		// @0A9: dup
		// @0AA: bipush 34 (0x22)
		// @0AC: iconst_2
		// @0AD: bastore
		// @0AE: dup
		// @0AF: bipush 35 (0x23)
		// @0B1: iconst_2
		// @0B2: bastore
		// @0B3: dup
		// @0B4: bipush 36 (0x24)
		// @0B6: iconst_2
		// @0B7: bastore
		// @0B8: dup
		// @0B9: bipush 37 (0x25)
		// @0BB: iconst_2
		// @0BC: bastore
		// @0BD: dup
		// @0BE: bipush 38 (0x26)
		// @0C0: iconst_2
		// @0C1: bastore
		// @0C2: dup
		// @0C3: bipush 39 (0x27)
		// @0C5: iconst_2
		// @0C6: bastore
		// @0C7: dup
		// @0C8: bipush 40 (0x28)
		// @0CA: iconst_2
		// @0CB: bastore
		// @0CC: dup
		// @0CD: bipush 41 (0x29)
		// @0CF: iconst_2
		// @0D0: bastore
		// @0D1: dup
		// @0D2: bipush 42 (0x2A)
		// @0D4: iconst_2
		// @0D5: bastore
		// @0D6: dup
		// @0D7: bipush 43 (0x2B)
		// @0D9: iconst_2
		// @0DA: bastore
		// @0DB: dup
		// @0DC: bipush 44 (0x2C)
		// @0DE: iconst_2
		// @0DF: bastore
		// @0E0: dup
		// @0E1: bipush 45 (0x2D)
		// @0E3: iconst_2
		// @0E4: bastore
		// @0E5: dup
		// @0E6: bipush 46 (0x2E)
		// @0E8: iconst_2
		// @0E9: bastore
		// @0EA: dup
		// @0EB: bipush 47 (0x2F)
		// @0ED: iconst_2
		// @0EE: bastore
		// @0EF: dup
		// @0F0: bipush 48 (0x30)
		// @0F2: iconst_2
		// @0F3: bastore
		// @0F4: dup
		// @0F5: bipush 49 (0x31)
		// @0F7: iconst_2
		// @0F8: bastore
		// @0F9: dup
		// @0FA: bipush 50 (0x32)
		// @0FC: iconst_2
		// @0FD: bastore
		// @0FE: dup
		// @0FF: bipush 51 (0x33)
		// @101: iconst_2
		// @102: bastore
		// @103: dup
		// @104: bipush 52 (0x34)
		// @106: iconst_2
		// @107: bastore
		// @108: dup
		// @109: bipush 53 (0x35)
		// @10B: iconst_2
		// @10C: bastore
		// @10D: dup
		// @10E: bipush 54 (0x36)
		// @110: iconst_2
		// @111: bastore
		// @112: dup
		// @113: bipush 55 (0x37)
		// @115: iconst_2
		// @116: bastore
		// @117: dup
		// @118: bipush 56 (0x38)
		// @11A: iconst_2
		// @11B: bastore
		// @11C: dup
		// @11D: bipush 57 (0x39)
		// @11F: iconst_2
		// @120: bastore
		// @121: dup
		// @122: bipush 58 (0x3A)
		// @124: iconst_2
		// @125: bastore
		// @126: dup
		// @127: bipush 59 (0x3B)
		// @129: iconst_2
		// @12A: bastore
		// @12B: dup
		// @12C: bipush 60 (0x3C)
		// @12E: iconst_2
		// @12F: bastore
		// @130: dup
		// @131: bipush 61 (0x3D)
		// @133: iconst_2
		// @134: bastore
		// @135: dup
		// @136: bipush 62 (0x3E)
		// @138: iconst_2
		// @139: bastore
		// @13A: dup
		// @13B: bipush 63 (0x3F)
		// @13D: iconst_2
		// @13E: bastore
		// @13F: dup
		// @140: bipush 64 (0x40)
		// @142: iconst_1
		// @143: bastore
		// @144: dup
		// @145: bipush 65 (0x41)
		// @147: iconst_1
		// @148: bastore
		// @149: dup
		// @14A: bipush 66 (0x42)
		// @14C: iconst_1
		// @14D: bastore
		// @14E: dup
		// @14F: bipush 67 (0x43)
		// @151: iconst_1
		// @152: bastore
		// @153: dup
		// @154: bipush 68 (0x44)
		// @156: iconst_1
		// @157: bastore
		// @158: dup
		// @159: bipush 69 (0x45)
		// @15B: iconst_1
		// @15C: bastore
		// @15D: dup
		// @15E: bipush 70 (0x46)
		// @160: iconst_1
		// @161: bastore
		// @162: dup
		// @163: bipush 71 (0x47)
		// @165: iconst_1
		// @166: bastore
		// @167: dup
		// @168: bipush 72 (0x48)
		// @16A: iconst_1
		// @16B: bastore
		// @16C: dup
		// @16D: bipush 73 (0x49)
		// @16F: iconst_1
		// @170: bastore
		// @171: dup
		// @172: bipush 74 (0x4A)
		// @174: iconst_1
		// @175: bastore
		// @176: dup
		// @177: bipush 75 (0x4B)
		// @179: iconst_1
		// @17A: bastore
		// @17B: dup
		// @17C: bipush 76 (0x4C)
		// @17E: iconst_1
		// @17F: bastore
		// @180: dup
		// @181: bipush 77 (0x4D)
		// @183: iconst_1
		// @184: bastore
		// @185: dup
		// @186: bipush 78 (0x4E)
		// @188: iconst_1
		// @189: bastore
		// @18A: dup
		// @18B: bipush 79 (0x4F)
		// @18D: iconst_1
		// @18E: bastore
		// @18F: dup
		// @190: bipush 80 (0x50)
		// @192: iconst_1
		// @193: bastore
		// @194: dup
		// @195: bipush 81 (0x51)
		// @197: iconst_1
		// @198: bastore
		// @199: dup
		// @19A: bipush 82 (0x52)
		// @19C: iconst_1
		// @19D: bastore
		// @19E: dup
		// @19F: bipush 83 (0x53)
		// @1A1: iconst_1
		// @1A2: bastore
		// @1A3: dup
		// @1A4: bipush 84 (0x54)
		// @1A6: iconst_1
		// @1A7: bastore
		// @1A8: dup
		// @1A9: bipush 85 (0x55)
		// @1AB: iconst_1
		// @1AC: bastore
		// @1AD: dup
		// @1AE: bipush 86 (0x56)
		// @1B0: iconst_1
		// @1B1: bastore
		// @1B2: dup
		// @1B3: bipush 87 (0x57)
		// @1B5: iconst_1
		// @1B6: bastore
		// @1B7: dup
		// @1B8: bipush 88 (0x58)
		// @1BA: iconst_1
		// @1BB: bastore
		// @1BC: dup
		// @1BD: bipush 89 (0x59)
		// @1BF: iconst_1
		// @1C0: bastore
		// @1C1: dup
		// @1C2: bipush 90 (0x5A)
		// @1C4: iconst_1
		// @1C5: bastore
		// @1C6: dup
		// @1C7: bipush 91 (0x5B)
		// @1C9: iconst_1
		// @1CA: bastore
		// @1CB: dup
		// @1CC: bipush 92 (0x5C)
		// @1CE: iconst_1
		// @1CF: bastore
		// @1D0: dup
		// @1D1: bipush 93 (0x5D)
		// @1D3: iconst_1
		// @1D4: bastore
		// @1D5: dup
		// @1D6: bipush 94 (0x5E)
		// @1D8: iconst_1
		// @1D9: bastore
		// @1DA: dup
		// @1DB: bipush 95 (0x5F)
		// @1DD: iconst_1
		// @1DE: bastore
		// @1DF: dup
		// @1E0: bipush 96 (0x60)
		// @1E2: iconst_2
		// @1E3: bastore
		// @1E4: dup
		// @1E5: bipush 97 (0x61)
		// @1E7: iconst_2
		// @1E8: bastore
		// @1E9: dup
		// @1EA: bipush 98 (0x62)
		// @1EC: iconst_2
		// @1ED: bastore
		// @1EE: dup
		// @1EF: bipush 99 (0x63)
		// @1F1: iconst_2
		// @1F2: bastore
		// @1F3: dup
		// @1F4: bipush 100 (0x64)
		// @1F6: iconst_2
		// @1F7: bastore
		// @1F8: dup
		// @1F9: bipush 101 (0x65)
		// @1FB: iconst_2
		// @1FC: bastore
		// @1FD: dup
		// @1FE: bipush 102 (0x66)
		// @200: iconst_2
		// @201: bastore
		// @202: dup
		// @203: bipush 103 (0x67)
		// @205: iconst_2
		// @206: bastore
		// @207: dup
		// @208: bipush 104 (0x68)
		// @20A: iconst_2
		// @20B: bastore
		// @20C: dup
		// @20D: bipush 105 (0x69)
		// @20F: iconst_2
		// @210: bastore
		// @211: dup
		// @212: bipush 106 (0x6A)
		// @214: iconst_2
		// @215: bastore
		// @216: dup
		// @217: bipush 107 (0x6B)
		// @219: iconst_2
		// @21A: bastore
		// @21B: dup
		// @21C: bipush 108 (0x6C)
		// @21E: iconst_2
		// @21F: bastore
		// @220: dup
		// @221: bipush 109 (0x6D)
		// @223: iconst_2
		// @224: bastore
		// @225: dup
		// @226: bipush 110 (0x6E)
		// @228: iconst_2
		// @229: bastore
		// @22A: dup
		// @22B: bipush 111 (0x6F)
		// @22D: iconst_2
		// @22E: bastore
		// @22F: dup
		// @230: bipush 112 (0x70)
		// @232: iconst_0
		// @233: bastore
		// @234: dup
		// @235: bipush 113 (0x71)
		// @237: iconst_1
		// @238: bastore
		// @239: dup
		// @23A: bipush 114 (0x72)
		// @23C: iconst_2
		// @23D: bastore
		// @23E: dup
		// @23F: bipush 115 (0x73)
		// @241: iconst_1
		// @242: bastore
		// @243: dup
		// @244: bipush 116 (0x74)
		// @246: iconst_0
		// @247: bastore
		// @248: dup
		// @249: bipush 117 (0x75)
		// @24B: iconst_0
		// @24C: bastore
		// @24D: dup
		// @24E: bipush 118 (0x76)
		// @250: iconst_0
		// @251: bastore
		// @252: dup
		// @253: bipush 119 (0x77)
		// @255: iconst_0
		// @256: bastore
		// @257: dup
		// @258: bipush 120 (0x78)
		// @25A: iconst_0
		// @25B: bastore
		// @25C: dup
		// @25D: bipush 121 (0x79)
		// @25F: iconst_0
		// @260: bastore
		// @261: dup
		// @262: bipush 122 (0x7A)
		// @264: iconst_0
		// @265: bastore
		// @266: dup
		// @267: bipush 123 (0x7B)
		// @269: iconst_0
		// @26A: bastore
		// @26B: dup
		// @26C: bipush 124 (0x7C)
		// @26E: iconst_0
		// @26F: bastore
		// @270: dup
		// @271: bipush 125 (0x7D)
		// @273: iconst_0
		// @274: bastore
		// @275: dup
		// @276: bipush 126 (0x7E)
		// @278: iconst_0
		// @279: bastore
		// @27A: dup
		// @27B: bipush 127 (0x7F)
		// @27D: iconst_0
		// @27E: bastore
		// @27F: putstatic byte[] game.C_100014_wg.field_103770_a
		// @282: return
	}
}
