package game;

import java.awt.Canvas;

final class C_100238_ol extends C_100071_va
{
	byte[] field_101703_K;
	int field_101695_P;
	static C_100133_tk field_101696_R;
	static boolean field_101692_F;
	static boolean field_101697_L;
	static int[] field_101693_G;
	C_100091_m field_101699_N;
	static String field_101700_H;
	static String field_101694_Q;
	static int field_101691_E;
	static int field_101702_J;
	static String field_101701_I;
	private static final String[] field_101698_M;
	
	final int func_101651_b(boolean arg0)
	{
		// @00: aload_0
		// @01: getfield boolean game.C_100238_ol.field_101661_C
		// @04: ifeq @09
		// @07: iconst_0
		// @08: ireturn
		// @09: iload_1
		// @0A: ifeq @17
		// @0D: bipush 123 (0x7B)
		// @0F: invokestatic game.C_100238_ol.func_101686_d(byte)java.lang.String
		// @12: pop
		// @13: goto @17
		// @16: athrow
		// @17: bipush 100 (0x64)
		// @19: ireturn
		// @1A: astore_2
		// @1B: aload_2
		// @1C: new java.lang.StringBuilder
		// @1F: dup
		// @20: invokespecial java.lang.StringBuilder.<init>()void
		// @23: getstatic java.lang.String[] game.C_100238_ol.field_101698_M
		// @26: bipush 8 (0x08)
		// @28: aaload
		// @29: invokevirtual java.lang.StringBuilder.append(java.lang.String)java.lang.StringBuilder
		// @2C: iload_1
		// @2D: invokevirtual java.lang.StringBuilder.append(boolean)java.lang.StringBuilder
		// @30: bipush 41 (0x29)
		// @32: invokevirtual java.lang.StringBuilder.append(char)java.lang.StringBuilder
		// @35: invokevirtual java.lang.StringBuilder.toString()java.lang.String
		// @38: invokestatic game.C_100181_cf.func_105695_a(java.lang.Throwable, java.lang.String)game.C_100170_cm
		// @3B: athrow
	}
	
	final byte[] func_101649_j(int arg0)
	{
		// @00: aload_0
		// @01: getfield boolean game.C_100238_ol.field_101661_C
		// @04: ifne @0B
		// @07: goto @13
		// @0A: athrow
		// @0B: new java.lang.RuntimeException
		// @0E: dup
		// @0F: invokespecial java.lang.RuntimeException.<init>()void
		// @12: athrow
		// @13: iload_1
		// @14: sipush -20679 (0xAF39)
		// @17: if_icmpeq @22
		// @1A: iconst_1
		// @1B: putstatic boolean game.C_100238_ol.field_101697_L
		// @1E: goto @22
		// @21: athrow
		// @22: aload_0
		// @23: getfield byte[] game.C_100238_ol.field_101703_K
		// @26: areturn
		// @27: astore_2
		// @28: aload_2
		// @29: new java.lang.StringBuilder
		// @2C: dup
		// @2D: invokespecial java.lang.StringBuilder.<init>()void
		// @30: getstatic java.lang.String[] game.C_100238_ol.field_101698_M
		// @33: bipush 14 (0x0E)
		// @35: aaload
		// @36: invokevirtual java.lang.StringBuilder.append(java.lang.String)java.lang.StringBuilder
		// @39: iload_1
		// @3A: invokevirtual java.lang.StringBuilder.append(int)java.lang.StringBuilder
		// @3D: bipush 41 (0x29)
		// @3F: invokevirtual java.lang.StringBuilder.append(char)java.lang.StringBuilder
		// @42: invokevirtual java.lang.StringBuilder.toString()java.lang.String
		// @45: invokestatic game.C_100181_cf.func_105695_a(java.lang.Throwable, java.lang.String)game.C_100170_cm
		// @48: athrow
	}
	
	static final boolean func_101684_e(byte arg0)
	{
		// @00: iload_0
		// @01: bipush -54 (0xCA)
		// @03: if_icmplt @08
		// @06: iconst_0
		// @07: ireturn
		// @08: aconst_null
		// @09: getstatic game.C_100286_nl game.C_100318_hj.field_107194_f
		// @0C: if_acmpeq @21
		// @0F: getstatic game.C_100268_mk game.C_100066_dl.field_101642_t
		// @12: getstatic game.C_100268_mk game.C_100046_vk.field_102763_sb
		// @15: if_acmpne @21
		// @18: goto @1C
		// @1B: athrow
		// @1C: iconst_1
		// @1D: goto @22
		// @20: athrow
		// @21: iconst_0
		// @22: ireturn
		// @23: astore_1
		// @24: aload_1
		// @25: new java.lang.StringBuilder
		// @28: dup
		// @29: invokespecial java.lang.StringBuilder.<init>()void
		// @2C: getstatic java.lang.String[] game.C_100238_ol.field_101698_M
		// @2F: bipush 9 (0x09)
		// @31: aaload
		// @32: invokevirtual java.lang.StringBuilder.append(java.lang.String)java.lang.StringBuilder
		// @35: iload_0
		// @36: invokevirtual java.lang.StringBuilder.append(int)java.lang.StringBuilder
		// @39: bipush 41 (0x29)
		// @3B: invokevirtual java.lang.StringBuilder.append(char)java.lang.StringBuilder
		// @3E: invokevirtual java.lang.StringBuilder.toString()java.lang.String
		// @41: invokestatic game.C_100181_cf.func_105695_a(java.lang.Throwable, java.lang.String)game.C_100170_cm
		// @44: athrow
	}
	
	static final int func_101690_a(int[] arg0, C_100327_ib arg1, byte arg2)
	{
		// @00: getstatic int game.SteelSentinels.field_105275_O
		// @03: istore #6
		// @05: aload_1
		// @06: bipush 59 (0x3B)
		// @08: invokevirtual game.C_100327_ib.func_102471_o(int)int
		// @0B: istore_3
		// @0C: aload_1
		// @0D: sipush -3099 (0xF3E5)
		// @10: invokevirtual game.C_100327_ib.func_102460_q(int)int
		// @13: istore #4
		// @15: iload_2
		// @16: bipush 63 (0x3F)
		// @18: if_icmpge @2B
		// @1B: iconst_5
		// @1C: bipush 53 (0x35)
		// @1E: bipush -103 (0x99)
		// @20: aconst_null
		// @21: checkcast java.awt.Canvas
		// @24: invokestatic game.C_100238_ol.func_101689_a(int, int, int, java.awt.Canvas)void
		// @27: goto @2B
		// @2A: athrow
		// @2B: iconst_0
		// @2C: istore #5
		// @2E: iload #5
		// @30: iconst_m1
		// @31: ixor
		// @32: iload #4
		// @34: iconst_m1
		// @35: ixor
		// @36: if_icmple @83
		// @39: bipush 34 (0x22)
		// @3B: iload #6
		// @3D: ifne @84
		// @40: aload_0
		// @41: iload #5
		// @43: iaload
		// @44: if_icmpeq @4F
		// @47: goto @4B
		// @4A: athrow
		// @4B: goto @53
		// @4E: athrow
		// @4F: sipush 6100 (0x17D4)
		// @52: ireturn
		// @53: aload_0
		// @54: iload #5
		// @56: iaload
		// @57: iconst_m1
		// @58: ixor
		// @59: iconst_m1
		// @5A: if_icmpgt @7B
		// @5D: aload_0
		// @5E: iload #5
		// @60: iaload
		// @61: getstatic int[] game.C_100021_wn.field_103870_e
		// @64: arraylength
		// @65: if_icmplt @70
		// @68: goto @6C
		// @6B: athrow
		// @6C: goto @7B
		// @6F: athrow
		// @70: iload_3
		// @71: getstatic int[] game.C_100021_wn.field_103870_e
		// @74: aload_0
		// @75: iload #5
		// @77: iaload
		// @78: iaload
		// @79: iadd
		// @7A: istore_3
		// @7B: iinc #5 +1
		// @7E: iload #6
		// @80: ifeq @2E
		// @83: iload_3
		// @84: ireturn
		// @85: astore_3
		// @86: aload_3
		// @87: new java.lang.StringBuilder
		// @8A: dup
		// @8B: invokespecial java.lang.StringBuilder.<init>()void
		// @8E: getstatic java.lang.String[] game.C_100238_ol.field_101698_M
		// @91: bipush 12 (0x0C)
		// @93: aaload
		// @94: invokevirtual java.lang.StringBuilder.append(java.lang.String)java.lang.StringBuilder
		// @97: aload_0
		// @98: ifnull @A5
		// @9B: getstatic java.lang.String[] game.C_100238_ol.field_101698_M
		// @9E: bipush 11 (0x0B)
		// @A0: aaload
		// @A1: goto @AB
		// @A4: athrow
		// @A5: getstatic java.lang.String[] game.C_100238_ol.field_101698_M
		// @A8: bipush 10 (0x0A)
		// @AA: aaload
		// @AB: invokevirtual java.lang.StringBuilder.append(java.lang.String)java.lang.StringBuilder
		// @AE: bipush 44 (0x2C)
		// @B0: invokevirtual java.lang.StringBuilder.append(char)java.lang.StringBuilder
		// @B3: aload_1
		// @B4: ifnull @C1
		// @B7: getstatic java.lang.String[] game.C_100238_ol.field_101698_M
		// @BA: bipush 11 (0x0B)
		// @BC: aaload
		// @BD: goto @C7
		// @C0: athrow
		// @C1: getstatic java.lang.String[] game.C_100238_ol.field_101698_M
		// @C4: bipush 10 (0x0A)
		// @C6: aaload
		// @C7: invokevirtual java.lang.StringBuilder.append(java.lang.String)java.lang.StringBuilder
		// @CA: bipush 44 (0x2C)
		// @CC: invokevirtual java.lang.StringBuilder.append(char)java.lang.StringBuilder
		// @CF: iload_2
		// @D0: invokevirtual java.lang.StringBuilder.append(int)java.lang.StringBuilder
		// @D3: bipush 41 (0x29)
		// @D5: invokevirtual java.lang.StringBuilder.append(char)java.lang.StringBuilder
		// @D8: invokevirtual java.lang.StringBuilder.toString()java.lang.String
		// @DB: invokestatic game.C_100181_cf.func_105695_a(java.lang.Throwable, java.lang.String)game.C_100170_cm
		// @DE: athrow
	}
	
	public static void func_101685_l(int arg0)
	{
		// @00: aconst_null
		// @01: putstatic game.C_100133_tk game.C_100238_ol.field_101696_R
		// @04: aconst_null
		// @05: putstatic int[] game.C_100238_ol.field_101693_G
		// @08: iload_0
		// @09: sipush 4050 (0x0FD2)
		// @0C: if_icmpeq @20
		// @0F: bipush 114 (0x72)
		// @11: bipush 35 (0x23)
		// @13: bipush 20 (0x14)
		// @15: aconst_null
		// @16: checkcast java.awt.Canvas
		// @19: invokestatic game.C_100238_ol.func_101689_a(int, int, int, java.awt.Canvas)void
		// @1C: goto @20
		// @1F: athrow
		// @20: aconst_null
		// @21: putstatic java.lang.String game.C_100238_ol.field_101701_I
		// @24: aconst_null
		// @25: putstatic java.lang.String game.C_100238_ol.field_101700_H
		// @28: aconst_null
		// @29: putstatic java.lang.String game.C_100238_ol.field_101694_Q
		// @2C: goto @51
		// @2F: astore_1
		// @30: aload_1
		// @31: new java.lang.StringBuilder
		// @34: dup
		// @35: invokespecial java.lang.StringBuilder.<init>()void
		// @38: getstatic java.lang.String[] game.C_100238_ol.field_101698_M
		// @3B: bipush 7 (0x07)
		// @3D: aaload
		// @3E: invokevirtual java.lang.StringBuilder.append(java.lang.String)java.lang.StringBuilder
		// @41: iload_0
		// @42: invokevirtual java.lang.StringBuilder.append(int)java.lang.StringBuilder
		// @45: bipush 41 (0x29)
		// @47: invokevirtual java.lang.StringBuilder.append(char)java.lang.StringBuilder
		// @4A: invokevirtual java.lang.StringBuilder.toString()java.lang.String
		// @4D: invokestatic game.C_100181_cf.func_105695_a(java.lang.Throwable, java.lang.String)game.C_100170_cm
		// @50: athrow
		// @51: return
	}
	
	static final String func_101686_d(byte arg0)
	{
		// @000: getstatic int game.SteelSentinels.field_105275_O
		// @003: istore #10
		// @005: aconst_null
		// @006: astore_1
		// @007: iload_0
		// @008: bipush 59 (0x3B)
		// @00A: if_icmpge @01F
		// @00D: aconst_null
		// @00E: checkcast int[]
		// @011: aconst_null
		// @012: checkcast game.C_100327_ib
		// @015: bipush -80 (0xB0)
		// @017: invokestatic game.C_100238_ol.func_101690_a(int[], game.C_100327_ib, byte)int
		// @01A: pop
		// @01B: goto @01F
		// @01E: athrow
		// @01F: aconst_null
		// @020: astore_2
		// @021: getstatic int game.C_100113_ek.field_104880_b
		// @024: ifne @03A
		// @027: aconst_null
		// @028: getstatic game.C_100211_qd game.SteelSentinels.field_105274_N
		// @02B: if_acmpne @036
		// @02E: goto @032
		// @031: athrow
		// @032: goto @03A
		// @035: athrow
		// @036: getstatic java.lang.String game.C_100057_dd.field_104254_g
		// @039: astore_2
		// @03A: iconst_2
		// @03B: getstatic int game.C_100113_ek.field_104880_b
		// @03E: if_icmpne @0A3
		// @041: bipush -42 (0xD6)
		// @043: invokestatic game.C_100286_nl.func_106795_b(byte)boolean
		// @046: ifeq @051
		// @049: goto @04D
		// @04C: athrow
		// @04D: goto @0A3
		// @050: athrow
		// @051: getstatic java.lang.String game.C_100243_pd.field_106355_f
		// @054: bipush 120 (0x78)
		// @056: invokestatic game.C_100099_fb.func_103035_a(java.lang.String, byte)boolean
		// @059: ifne @075
		// @05C: sipush -30945 (0x871F)
		// @05F: iconst_1
		// @060: anewarray java.lang.String
		// @063: dup
		// @064: iconst_0
		// @065: getstatic java.lang.String game.C_100050_vg.field_100630_m
		// @068: aastore
		// @069: getstatic java.lang.String game.C_100180_ce.field_104809_t
		// @06C: invokestatic game.C_100132_td.func_104965_a(int, java.lang.String[], java.lang.String)java.lang.String
		// @06F: astore_2
		// @070: iload #10
		// @072: ifeq @089
		// @075: sipush -30945 (0x871F)
		// @078: iconst_1
		// @079: anewarray java.lang.String
		// @07C: dup
		// @07D: iconst_0
		// @07E: getstatic java.lang.String game.C_100050_vg.field_100630_m
		// @081: aastore
		// @082: getstatic java.lang.String game.C_100235_om.field_106298_h
		// @085: invokestatic game.C_100132_td.func_104965_a(int, java.lang.String[], java.lang.String)java.lang.String
		// @088: astore_2
		// @089: getstatic boolean game.C_100021_wn.field_103871_b
		// @08C: ifne @093
		// @08F: goto @0A3
		// @092: athrow
		// @093: aconst_null
		// @094: ldc -1221466785 (0xb731e55f)
		// @096: iconst_0
		// @097: iconst_2
		// @098: aconst_null
		// @099: aload_2
		// @09A: invokestatic game.C_100019_wl.func_103834_a(java.lang.String, int, int, int, java.lang.String, java.lang.String)void
		// @09D: sipush -24528 (0xA030)
		// @0A0: invokestatic game.C_100285_nk.func_106775_c(int)void
		// @0A3: aload_2
		// @0A4: ifnonnull @0C4
		// @0A7: getstatic boolean game.C_100149_bi.field_105158_a
		// @0AA: ifne @0C4
		// @0AD: goto @0B1
		// @0B0: athrow
		// @0B1: aconst_null
		// @0B2: getstatic game.C_100302_ka game.C_100154_sl.field_105332_e
		// @0B5: if_acmpeq @0C0
		// @0B8: goto @0BC
		// @0BB: athrow
		// @0BC: goto @0C4
		// @0BF: athrow
		// @0C0: getstatic java.lang.String game.C_100100_i.field_102010_dc
		// @0C3: astore_2
		// @0C4: aconst_null
		// @0C5: aload_2
		// @0C6: if_acmpeq @0DC
		// @0C9: iconst_0
		// @0CA: aconst_null
		// @0CB: aload_2
		// @0CC: getstatic int game.C_100273_mm.field_106679_f
		// @0CF: iconst_1
		// @0D0: invokestatic game.C_100068_vc.func_104339_a(int, java.lang.String, java.lang.String, int, boolean)void
		// @0D3: iload #10
		// @0D5: ifeq @393
		// @0D8: goto @0DC
		// @0DB: athrow
		// @0DC: getstatic java.lang.String game.C_100339_jb.field_107391_h
		// @0DF: astore_3
		// @0E0: aload_3
		// @0E1: bipush -128 (0x80)
		// @0E3: invokestatic game.C_100161_sd.func_105419_a(java.lang.String, int)java.lang.String
		// @0E6: astore_3
		// @0E7: ldc ""
		// @0E9: astore #4
		// @0EB: ldc "|"
		// @0ED: astore #5
		// @0EF: getstatic int game.C_100113_ek.field_104880_b
		// @0F2: istore #6
		// @0F4: iconst_0
		// @0F5: istore #7
		// @0F7: bipush -3 (0xFD)
		// @0F9: iload #6
		// @0FB: iconst_m1
		// @0FC: ixor
		// @0FD: if_icmpne @15F
		// @100: sipush -30945 (0x871F)
		// @103: iconst_1
		// @104: anewarray java.lang.String
		// @107: dup
		// @108: iconst_0
		// @109: getstatic java.lang.String game.C_100050_vg.field_100630_m
		// @10C: aastore
		// @10D: getstatic java.lang.String game.C_100249_pc.field_102331_C
		// @110: invokestatic game.C_100132_td.func_104965_a(int, java.lang.String[], java.lang.String)java.lang.String
		// @113: astore #4
		// @115: sipush -30945 (0x871F)
		// @118: iconst_1
		// @119: anewarray java.lang.String
		// @11C: dup
		// @11D: iconst_0
		// @11E: aload_3
		// @11F: aastore
		// @120: getstatic java.lang.String game.C_100278_nd.field_101205_y
		// @123: invokestatic game.C_100132_td.func_104965_a(int, java.lang.String[], java.lang.String)java.lang.String
		// @126: astore #8
		// @128: getstatic game.C_100302_ka game.C_100127_tl.field_104946_d
		// @12B: getfield int game.C_100302_ka.field_101886_Kb
		// @12E: getstatic game.C_100302_ka game.C_100235_om.field_106296_j
		// @131: getfield int game.C_100302_ka.field_101886_Kb
		// @134: iadd
		// @135: sipush -485 (0xFE1B)
		// @138: iadd
		// @139: getstatic game.C_100112_r game.C_100053_vn.field_102827_cb
		// @13C: aload #8
		// @13E: invokevirtual game.C_100112_r.func_101739_b(java.lang.String)int
		// @141: ineg
		// @142: getstatic game.C_100112_r game.C_100053_vn.field_102827_cb
		// @145: aload #4
		// @147: invokevirtual game.C_100112_r.func_101739_b(java.lang.String)int
		// @14A: ineg
		// @14B: isub
		// @14C: isub
		// @14D: istore #7
		// @14F: iload #7
		// @151: iconst_m1
		// @152: ixor
		// @153: iconst_m1
		// @154: if_icmple @15A
		// @157: iconst_0
		// @158: istore #7
		// @15A: iload #10
		// @15C: ifeq @334
		// @15F: iconst_0
		// @160: iload #6
		// @162: if_icmpne @215
		// @165: goto @169
		// @168: athrow
		// @169: aconst_null
		// @16A: getstatic game.C_100211_qd game.C_100068_vc.field_104342_d
		// @16D: if_acmpne @1A1
		// @170: goto @174
		// @173: athrow
		// @174: getstatic boolean game.C_100024_hd.field_103002_x
		// @177: ifne @182
		// @17A: goto @17E
		// @17D: athrow
		// @17E: goto @1A1
		// @181: athrow
		// @182: new java.lang.StringBuilder
		// @185: dup
		// @186: invokespecial java.lang.StringBuilder.<init>()void
		// @189: ldc "["
		// @18B: invokevirtual java.lang.StringBuilder.append(java.lang.String)java.lang.StringBuilder
		// @18E: getstatic java.lang.String game.C_100272_mn.field_102432_H
		// @191: invokevirtual java.lang.StringBuilder.append(java.lang.String)java.lang.StringBuilder
		// @194: getstatic java.lang.String[] game.C_100238_ol.field_101698_M
		// @197: iconst_0
		// @198: aaload
		// @199: invokevirtual java.lang.StringBuilder.append(java.lang.String)java.lang.StringBuilder
		// @19C: invokevirtual java.lang.StringBuilder.toString()java.lang.String
		// @19F: astore #4
		// @1A1: getstatic game.C_100211_qd game.C_100068_vc.field_104342_d
		// @1A4: ifnull @215
		// @1A7: getstatic boolean game.C_100069_vb.field_104356_d
		// @1AA: ifeq @1E0
		// @1AD: goto @1B1
		// @1B0: athrow
		// @1B1: aconst_null
		// @1B2: getstatic java.lang.String game.C_100281_ng.field_103461_O
		// @1B5: if_acmpeq @1E0
		// @1B8: goto @1BC
		// @1BB: athrow
		// @1BC: new java.lang.StringBuilder
		// @1BF: dup
		// @1C0: invokespecial java.lang.StringBuilder.<init>()void
		// @1C3: ldc "["
		// @1C5: invokevirtual java.lang.StringBuilder.append(java.lang.String)java.lang.StringBuilder
		// @1C8: getstatic java.lang.String game.C_100281_ng.field_103461_O
		// @1CB: invokevirtual java.lang.StringBuilder.append(java.lang.String)java.lang.StringBuilder
		// @1CE: getstatic java.lang.String[] game.C_100238_ol.field_101698_M
		// @1D1: iconst_0
		// @1D2: aaload
		// @1D3: invokevirtual java.lang.StringBuilder.append(java.lang.String)java.lang.StringBuilder
		// @1D6: invokevirtual java.lang.StringBuilder.toString()java.lang.String
		// @1D9: astore #4
		// @1DB: iload #10
		// @1DD: ifeq @212
		// @1E0: new java.lang.StringBuilder
		// @1E3: dup
		// @1E4: invokespecial java.lang.StringBuilder.<init>()void
		// @1E7: ldc "["
		// @1E9: invokevirtual java.lang.StringBuilder.append(java.lang.String)java.lang.StringBuilder
		// @1EC: sipush -30945 (0x871F)
		// @1EF: iconst_1
		// @1F0: anewarray java.lang.String
		// @1F3: dup
		// @1F4: iconst_0
		// @1F5: getstatic game.C_100211_qd game.C_100068_vc.field_104342_d
		// @1F8: getfield java.lang.String game.C_100211_qd.field_102155_dc
		// @1FB: aastore
		// @1FC: getstatic java.lang.String game.C_100287_nm.field_106823_g
		// @1FF: invokestatic game.C_100132_td.func_104965_a(int, java.lang.String[], java.lang.String)java.lang.String
		// @202: invokevirtual java.lang.StringBuilder.append(java.lang.String)java.lang.StringBuilder
		// @205: getstatic java.lang.String[] game.C_100238_ol.field_101698_M
		// @208: iconst_0
		// @209: aaload
		// @20A: invokevirtual java.lang.StringBuilder.append(java.lang.String)java.lang.StringBuilder
		// @20D: invokevirtual java.lang.StringBuilder.toString()java.lang.String
		// @210: astore #4
		// @212: iconst_1
		// @213: istore #6
		// @215: iconst_0
		// @216: invokestatic game.C_100252_pn.func_105499_a(boolean)boolean
		// @219: ifne @225
		// @21C: getstatic java.lang.String[] game.C_100238_ol.field_101698_M
		// @21F: iconst_3
		// @220: aaload
		// @221: goto @22A
		// @224: athrow
		// @225: getstatic java.lang.String[] game.C_100238_ol.field_101698_M
		// @228: iconst_2
		// @229: aaload
		// @22A: astore #8
		// @22C: new java.lang.StringBuilder
		// @22F: dup
		// @230: invokespecial java.lang.StringBuilder.<init>()void
		// @233: aload #4
		// @235: invokevirtual java.lang.StringBuilder.append(java.lang.String)java.lang.StringBuilder
		// @238: aload_3
		// @239: invokevirtual java.lang.StringBuilder.append(java.lang.String)java.lang.StringBuilder
		// @23C: aload #8
		// @23E: invokevirtual java.lang.StringBuilder.append(java.lang.String)java.lang.StringBuilder
		// @241: invokevirtual java.lang.StringBuilder.toString()java.lang.String
		// @244: astore #4
		// @246: getstatic boolean game.C_100272_mn.field_102435_K
		// @249: ifeq @27C
		// @24C: ldc ""
		// @24E: astore #5
		// @250: new java.lang.StringBuilder
		// @253: dup
		// @254: invokespecial java.lang.StringBuilder.<init>()void
		// @257: getstatic java.lang.String[] game.C_100238_ol.field_101698_M
		// @25A: iconst_5
		// @25B: aaload
		// @25C: invokevirtual java.lang.StringBuilder.append(java.lang.String)java.lang.StringBuilder
		// @25F: aload #4
		// @261: invokevirtual java.lang.StringBuilder.append(java.lang.String)java.lang.StringBuilder
		// @264: getstatic java.lang.String game.C_100108_ee.field_100391_h
		// @267: invokevirtual java.lang.StringBuilder.append(java.lang.String)java.lang.StringBuilder
		// @26A: getstatic java.lang.String[] game.C_100238_ol.field_101698_M
		// @26D: iconst_4
		// @26E: aaload
		// @26F: invokevirtual java.lang.StringBuilder.append(java.lang.String)java.lang.StringBuilder
		// @272: invokevirtual java.lang.StringBuilder.toString()java.lang.String
		// @275: astore #4
		// @277: iload #10
		// @279: ifeq @2B5
		// @27C: getstatic boolean game.C_100164_se.field_105449_g
		// @27F: ifne @28A
		// @282: goto @286
		// @285: athrow
		// @286: goto @2B5
		// @289: athrow
		// @28A: ldc ""
		// @28C: astore #5
		// @28E: new java.lang.StringBuilder
		// @291: dup
		// @292: invokespecial java.lang.StringBuilder.<init>()void
		// @295: getstatic java.lang.String[] game.C_100238_ol.field_101698_M
		// @298: iconst_5
		// @299: aaload
		// @29A: invokevirtual java.lang.StringBuilder.append(java.lang.String)java.lang.StringBuilder
		// @29D: aload #4
		// @29F: invokevirtual java.lang.StringBuilder.append(java.lang.String)java.lang.StringBuilder
		// @2A2: getstatic java.lang.String game.C_100270_mi.field_102279_ac
		// @2A5: invokevirtual java.lang.StringBuilder.append(java.lang.String)java.lang.StringBuilder
		// @2A8: getstatic java.lang.String[] game.C_100238_ol.field_101698_M
		// @2AB: iconst_4
		// @2AC: aaload
		// @2AD: invokevirtual java.lang.StringBuilder.append(java.lang.String)java.lang.StringBuilder
		// @2B0: invokevirtual java.lang.StringBuilder.toString()java.lang.String
		// @2B3: astore #4
		// @2B5: getstatic game.C_100112_r game.C_100053_vn.field_102827_cb
		// @2B8: aload #4
		// @2BA: invokevirtual game.C_100112_r.func_101739_b(java.lang.String)int
		// @2BD: istore #9
		// @2BF: iconst_0
		// @2C0: invokestatic game.C_100252_pn.func_105499_a(boolean)boolean
		// @2C3: ifeq @2CA
		// @2C6: goto @334
		// @2C9: athrow
		// @2CA: getstatic game.C_100302_ka game.C_100235_om.field_106296_j
		// @2CD: getfield boolean game.C_100302_ka.field_101839_db
		// @2D0: ifeq @303
		// @2D3: iload #9
		// @2D5: iconst_m1
		// @2D6: ixor
		// @2D7: getstatic game.C_100302_ka game.C_100235_om.field_106296_j
		// @2DA: getfield int game.C_100302_ka.field_101840_Eb
		// @2DD: ineg
		// @2DE: getstatic int game.C_100015_wh.field_103781_g
		// @2E1: iadd
		// @2E2: iconst_m1
		// @2E3: ixor
		// @2E4: if_icmpge @303
		// @2E7: goto @2EB
		// @2EA: athrow
		// @2EB: getstatic boolean game.C_100272_mn.field_102435_K
		// @2EE: ifeq @2FF
		// @2F1: goto @2F5
		// @2F4: athrow
		// @2F5: getstatic java.lang.String[] game.C_100238_ol.field_101698_M
		// @2F8: bipush 6 (0x06)
		// @2FA: aaload
		// @2FB: astore_1
		// @2FC: goto @303
		// @2FF: getstatic java.lang.String game.C_100270_mi.field_102279_ac
		// @302: astore_1
		// @303: getstatic game.C_100302_ka game.C_100235_om.field_106296_j
		// @306: getfield int game.C_100302_ka.field_101854_N
		// @309: iconst_m1
		// @30A: ixor
		// @30B: iconst_m1
		// @30C: if_icmpeq @334
		// @30F: getstatic game.C_100302_ka game.C_100235_om.field_106296_j
		// @312: getfield int game.C_100302_ka.field_101842_hb
		// @315: iconst_m1
		// @316: ixor
		// @317: iload #9
		// @319: iconst_m1
		// @31A: ixor
		// @31B: if_icmple @334
		// @31E: goto @322
		// @321: athrow
		// @322: getstatic boolean game.C_100272_mn.field_102435_K
		// @325: ifeq @330
		// @328: goto @32C
		// @32B: athrow
		// @32C: goto @334
		// @32F: athrow
		// @330: iconst_0
		// @331: invokestatic game.C_100078_ul.func_103276_f(boolean)void
		// @334: iload #7
		// @336: aload #5
		// @338: new java.lang.StringBuilder
		// @33B: dup
		// @33C: invokespecial java.lang.StringBuilder.<init>()void
		// @33F: aload #4
		// @341: invokevirtual java.lang.StringBuilder.append(java.lang.String)java.lang.StringBuilder
		// @344: getstatic java.lang.StringBuilder game.C_100183_cd.field_103422_O
		// @347: invokevirtual java.lang.StringBuilder.toString()java.lang.String
		// @34A: invokestatic game.C_100112_r.func_101750_c(java.lang.String)java.lang.String
		// @34D: invokevirtual java.lang.StringBuilder.append(java.lang.String)java.lang.StringBuilder
		// @350: invokevirtual java.lang.StringBuilder.toString()java.lang.String
		// @353: getstatic int[] game.C_100269_ml.field_101123_n
		// @356: iload #6
		// @358: iaload
		// @359: iconst_1
		// @35A: invokestatic game.C_100068_vc.func_104339_a(int, java.lang.String, java.lang.String, int, boolean)void
		// @35D: getstatic boolean game.C_100230_of.field_106216_k
		// @360: ifeq @367
		// @363: goto @36E
		// @366: athrow
		// @367: getstatic game.C_100302_ka game.C_100127_tl.field_104946_d
		// @36A: iconst_0
		// @36B: putfield boolean game.C_100302_ka.field_101839_db
		// @36E: getstatic game.C_100302_ka game.C_100127_tl.field_104946_d
		// @371: getfield boolean game.C_100302_ka.field_101839_db
		// @374: ifne @37B
		// @377: goto @393
		// @37A: athrow
		// @37B: sipush -30945 (0x871F)
		// @37E: iconst_2
		// @37F: anewarray java.lang.String
		// @382: dup
		// @383: iconst_0
		// @384: aload_3
		// @385: aastore
		// @386: dup
		// @387: iconst_1
		// @388: getstatic java.lang.String game.C_100050_vg.field_100630_m
		// @38B: aastore
		// @38C: getstatic java.lang.String game.C_100321_hi.field_107223_o
		// @38F: invokestatic game.C_100132_td.func_104965_a(int, java.lang.String[], java.lang.String)java.lang.String
		// @392: astore_1
		// @393: aload_1
		// @394: areturn
		// @395: astore_1
		// @396: aload_1
		// @397: new java.lang.StringBuilder
		// @39A: dup
		// @39B: invokespecial java.lang.StringBuilder.<init>()void
		// @39E: getstatic java.lang.String[] game.C_100238_ol.field_101698_M
		// @3A1: iconst_1
		// @3A2: aaload
		// @3A3: invokevirtual java.lang.StringBuilder.append(java.lang.String)java.lang.StringBuilder
		// @3A6: iload_0
		// @3A7: invokevirtual java.lang.StringBuilder.append(int)java.lang.StringBuilder
		// @3AA: bipush 41 (0x29)
		// @3AC: invokevirtual java.lang.StringBuilder.append(char)java.lang.StringBuilder
		// @3AF: invokevirtual java.lang.StringBuilder.toString()java.lang.String
		// @3B2: invokestatic game.C_100181_cf.func_105695_a(java.lang.Throwable, java.lang.String)game.C_100170_cm
		// @3B5: athrow
	}
	
	static final void func_101689_a(int arg0, int arg1, int arg2, Canvas arg3)
	{
		// @00: aload_3
		// @01: invokevirtual java.awt.Canvas.getGraphics()java.awt.Graphics
		// @04: astore #4
		// @06: getstatic game.C_100185_rm game.C_100049_vf.field_104206_l
		// @09: iload_1
		// @0A: sipush -26019 (0x9A5D)
		// @0D: ixor
		// @0E: iload_2
		// @0F: aload #4
		// @11: iload_0
		// @12: invokevirtual game.C_100185_rm.func_105474_a(int, int, java.awt.Graphics, int)void
		// @15: aload #4
		// @17: invokevirtual java.awt.Graphics.dispose()void
		// @1A: iload_1
		// @1B: sipush -25993 (0x9A77)
		// @1E: if_icmpeq @2A
		// @21: bipush -45 (0xD3)
		// @23: invokestatic game.C_100238_ol.func_101685_l(int)void
		// @26: goto @2A
		// @29: athrow
		// @2A: goto @33
		// @2D: astore #4
		// @2F: aload_3
		// @30: invokevirtual java.awt.Canvas.repaint()void
		// @33: goto @88
		// @36: astore #4
		// @38: aload #4
		// @3A: new java.lang.StringBuilder
		// @3D: dup
		// @3E: invokespecial java.lang.StringBuilder.<init>()void
		// @41: getstatic java.lang.String[] game.C_100238_ol.field_101698_M
		// @44: bipush 13 (0x0D)
		// @46: aaload
		// @47: invokevirtual java.lang.StringBuilder.append(java.lang.String)java.lang.StringBuilder
		// @4A: iload_0
		// @4B: invokevirtual java.lang.StringBuilder.append(int)java.lang.StringBuilder
		// @4E: bipush 44 (0x2C)
		// @50: invokevirtual java.lang.StringBuilder.append(char)java.lang.StringBuilder
		// @53: iload_1
		// @54: invokevirtual java.lang.StringBuilder.append(int)java.lang.StringBuilder
		// @57: bipush 44 (0x2C)
		// @59: invokevirtual java.lang.StringBuilder.append(char)java.lang.StringBuilder
		// @5C: iload_2
		// @5D: invokevirtual java.lang.StringBuilder.append(int)java.lang.StringBuilder
		// @60: bipush 44 (0x2C)
		// @62: invokevirtual java.lang.StringBuilder.append(char)java.lang.StringBuilder
		// @65: aload_3
		// @66: ifnull @73
		// @69: getstatic java.lang.String[] game.C_100238_ol.field_101698_M
		// @6C: bipush 11 (0x0B)
		// @6E: aaload
		// @6F: goto @79
		// @72: athrow
		// @73: getstatic java.lang.String[] game.C_100238_ol.field_101698_M
		// @76: bipush 10 (0x0A)
		// @78: aaload
		// @79: invokevirtual java.lang.StringBuilder.append(java.lang.String)java.lang.StringBuilder
		// @7C: bipush 41 (0x29)
		// @7E: invokevirtual java.lang.StringBuilder.append(char)java.lang.StringBuilder
		// @81: invokevirtual java.lang.StringBuilder.toString()java.lang.String
		// @84: invokestatic game.C_100181_cf.func_105695_a(java.lang.Throwable, java.lang.String)game.C_100170_cm
		// @87: athrow
		// @88: return
	}
	
	static
	{
		// @00: bipush 15 (0x0F)
		// @02: anewarray java.lang.String
		// @05: dup
		// @06: iconst_0
		// @07: ldc "E@"
		// @09: invokestatic game.C_100238_ol.func_101688_z(java.lang.String)char[]
		// @0C: invokestatic game.C_100238_ol.func_101687_z(char[])java.lang.String
		// @0F: aastore
		// @10: dup
		// @11: iconst_1
		// @12: ldc "w\u000c\u0005\u0006v"
		// @14: invokestatic game.C_100238_ol.func_101688_z(java.lang.String)char[]
		// @17: invokestatic game.C_100238_ol.func_101687_z(char[])java.lang.String
		// @1A: aastore
		// @1B: dup
		// @1C: iconst_2
		// @1D: ldc "\"@"
		// @1F: invokestatic game.C_100238_ol.func_101688_z(java.lang.String)char[]
		// @22: invokestatic game.C_100238_ol.func_101687_z(char[])java.lang.String
		// @25: aastore
		// @26: dup
		// @27: iconst_3
		// @28: ldc "$\tF0c+^\u0011w"
		// @2A: invokestatic game.C_100238_ol.func_101688_z(java.lang.String)char[]
		// @2D: invokestatic game.C_100238_ol.func_101687_z(char[])java.lang.String
		// @30: aastore
		// @31: dup
		// @32: iconst_4
		// @33: ldc "$OH82&"
		// @35: invokestatic game.C_100238_ol.func_101688_z(java.lang.String)char[]
		// @38: invokestatic game.C_100238_ol.func_101687_z(char[])java.lang.String
		// @3B: aastore
		// @3C: dup
		// @3D: iconst_5
		// @3E: ldc "$\u0003D;c!Y\u0012ng!^"
		// @40: invokestatic game.C_100238_ol.func_101688_z(java.lang.String)char[]
		// @43: invokestatic game.C_100238_ol.func_101687_z(char[])java.lang.String
		// @46: aastore
		// @47: dup
		// @48: bipush 6 (0x06)
		// @4A: ldc "Z\u0012D<;vA"
		// @4C: invokestatic game.C_100238_ol.func_101688_z(java.lang.String)char[]
		// @4F: invokestatic game.C_100238_ol.func_101687_z(char[])java.lang.String
		// @52: aastore
		// @53: dup
		// @54: bipush 7 (0x07)
		// @56: ldc "w\u000c\u0005\u0003v"
		// @58: invokestatic game.C_100238_ol.func_101688_z(java.lang.String)char[]
		// @5B: invokestatic game.C_100238_ol.func_101687_z(char[])java.lang.String
		// @5E: aastore
		// @5F: dup
		// @60: bipush 8 (0x08)
		// @62: ldc "w\u000c\u0005\u0011v"
		// @64: invokestatic game.C_100238_ol.func_101688_z(java.lang.String)char[]
		// @67: invokestatic game.C_100238_ol.func_101687_z(char[])java.lang.String
		// @6A: aastore
		// @6B: dup
		// @6C: bipush 9 (0x09)
		// @6E: ldc "w\u000c\u0005\u0005v"
		// @70: invokestatic game.C_100238_ol.func_101688_z(java.lang.String)char[]
		// @73: invokestatic game.C_100238_ol.func_101687_z(char[])java.lang.String
		// @76: aastore
		// @77: dup
		// @78: bipush 10 (0x0A)
		// @7A: ldc "v\u0015G;"
		// @7C: invokestatic game.C_100238_ol.func_101688_z(java.lang.String)char[]
		// @7F: invokestatic game.C_100238_ol.func_101687_z(char[])java.lang.String
		// @82: aastore
		// @83: dup
		// @84: bipush 11 (0x0B)
		// @86: ldc "cN\u0005y#"
		// @88: invokestatic game.C_100238_ol.func_101688_z(java.lang.String)char[]
		// @8B: invokestatic game.C_100238_ol.func_101687_z(char[])java.lang.String
		// @8E: aastore
		// @8F: dup
		// @90: bipush 12 (0x0C)
		// @92: ldc "w\u000c\u0005\u001ev"
		// @94: invokestatic game.C_100238_ol.func_101688_z(java.lang.String)char[]
		// @97: invokestatic game.C_100238_ol.func_101687_z(char[])java.lang.String
		// @9A: aastore
		// @9B: dup
		// @9C: bipush 13 (0x0D)
		// @9E: ldc "w\u000c\u0005\u0004v"
		// @A0: invokestatic game.C_100238_ol.func_101688_z(java.lang.String)char[]
		// @A3: invokestatic game.C_100238_ol.func_101687_z(char[])java.lang.String
		// @A6: aastore
		// @A7: dup
		// @A8: bipush 14 (0x0E)
		// @AA: ldc "w\u000c\u0005\u0014v"
		// @AC: invokestatic game.C_100238_ol.func_101688_z(java.lang.String)char[]
		// @AF: invokestatic game.C_100238_ol.func_101687_z(char[])java.lang.String
		// @B2: aastore
		// @B3: putstatic java.lang.String[] game.C_100238_ol.field_101698_M
		// @B6: new game.C_100133_tk
		// @B9: dup
		// @BA: invokespecial game.C_100133_tk.<init>()void
		// @BD: putstatic game.C_100133_tk game.C_100238_ol.field_101696_R
		// @C0: iconst_0
		// @C1: putstatic boolean game.C_100238_ol.field_101697_L
		// @C4: ldc "A\u000f^w3m\u0013_w<}@Jw3}\rI2,8\u0014Dw.t\u0001Rw)q\u0014Cw*p\u0005\u000b4+j\u0012N9*8\u000f[#7w\u000eXy"
		// @C6: invokestatic game.C_100238_ol.func_101688_z(java.lang.String)char[]
		// @C9: invokestatic game.C_100238_ol.func_101687_z(char[])java.lang.String
		// @CC: putstatic java.lang.String game.C_100238_ol.field_101694_Q
		// @CF: ldc "V/\u007fw\u001bV'b\u0019\u001b]2n\u0013"
		// @D1: invokestatic game.C_100238_ol.func_101688_z(java.lang.String)char[]
		// @D4: invokestatic game.C_100238_ol.func_101687_z(char[])java.lang.String
		// @D7: putstatic java.lang.String game.C_100238_ol.field_101700_H
		// @DA: sipush 128 (0x0080)
		// @DD: newarray int[]
		// @DF: putstatic int[] game.C_100238_ol.field_101693_G
		// @E2: ldc "W\u0012Iw.w\tE#-\"@"
		// @E4: invokestatic game.C_100238_ol.func_101688_z(java.lang.String)char[]
		// @E7: invokestatic game.C_100238_ol.func_101687_z(char[])java.lang.String
		// @EA: putstatic java.lang.String game.C_100238_ol.field_101701_I
		// @ED: iconst_0
		// @EE: putstatic int game.C_100238_ol.field_101702_J
		// @F1: iconst_m1
		// @F2: putstatic int game.C_100238_ol.field_101691_E
		// @F5: return
	}
	
	private static char[] func_101688_z(String arg0)
	{
		// @00: aload_0
		// @01: invokevirtual java.lang.String.toCharArray()char[]
		// @04: dup
		// @05: arraylength
		// @06: iconst_2
		// @07: if_icmpge @13
		// @0A: dup
		// @0B: iconst_0
		// @0C: dup2
		// @0D: caload
		// @0E: bipush 94 (0x5E)
		// @10: ixor
		// @11: i2c
		// @12: castore
		// @13: areturn
	}
	
	private static String func_101687_z(char[] arg0)
	{
		// @00: aload_0
		// @01: dup
		// @02: arraylength
		// @03: swap
		// @04: iconst_0
		// @05: istore_1
		// @06: goto @4C
		// @09: dup
		// @0A: iload_1
		// @0B: dup2
		// @0C: caload
		// @0D: iload_1
		// @0E: iconst_5
		// @0F: irem
		// @10: tableswitch def: @44, for 0: @30, for 1: @35, for 2: @3A, for 3: @3F
		// @30: bipush 24 (0x18)
		// @32: goto @46
		// @35: bipush 96 (0x60)
		// @37: goto @46
		// @3A: bipush 43 (0x2B)
		// @3C: goto @46
		// @3F: bipush 87 (0x57)
		// @41: goto @46
		// @44: bipush 94 (0x5E)
		// @46: ixor
		// @47: i2c
		// @48: castore
		// @49: iinc #1 +1
		// @4C: swap
		// @4D: dup_x1
		// @4E: iload_1
		// @4F: if_icmpgt @09
		// @52: new java.lang.String
		// @55: dup_x1
		// @56: swap
		// @57: invokespecial java.lang.String.<init>(char[])void
		// @5A: invokevirtual java.lang.String.intern()java.lang.String
		// @5D: areturn
	}
}
