package game;

import java.awt.Component;
import java.applet.Applet;

abstract class C_100107_u
{
	static String field_104777_h;
	static String field_104773_b;
	static int field_104770_g;
	static Applet field_104771_d;
	static int field_104772_e;
	static String field_104769_f;
	static byte[][] field_104774_c;
	static C_100037_wb field_104775_a;
	private static final String[] field_104776_z;
	
	static final C_100054_ec func_104768_a(int arg0, long arg1)
	{
		// @00: iload_0
		// @01: ifeq @09
		// @04: aconst_null
		// @05: checkcast game.C_100054_ec
		// @08: areturn
		// @09: getstatic game.C_100105_eg game.C_100053_vn.field_102832_U
		// @0C: sipush -16397 (0xBFF3)
		// @0F: lload_1
		// @10: invokevirtual game.C_100105_eg.func_104724_a(int, long)game.C_100325_id
		// @13: checkcast game.C_100054_ec
		// @16: areturn
		// @17: astore_3
		// @18: aload_3
		// @19: new java.lang.StringBuilder
		// @1C: dup
		// @1D: invokespecial java.lang.StringBuilder.<init>()void
		// @20: getstatic java.lang.String[] game.C_100107_u.field_104776_z
		// @23: iconst_5
		// @24: aaload
		// @25: invokevirtual java.lang.StringBuilder.append(java.lang.String)java.lang.StringBuilder
		// @28: iload_0
		// @29: invokevirtual java.lang.StringBuilder.append(int)java.lang.StringBuilder
		// @2C: bipush 44 (0x2C)
		// @2E: invokevirtual java.lang.StringBuilder.append(char)java.lang.StringBuilder
		// @31: lload_1
		// @32: invokevirtual java.lang.StringBuilder.append(long)java.lang.StringBuilder
		// @35: bipush 41 (0x29)
		// @37: invokevirtual java.lang.StringBuilder.append(char)java.lang.StringBuilder
		// @3A: invokevirtual java.lang.StringBuilder.toString()java.lang.String
		// @3D: invokestatic game.C_100181_cf.func_105695_a(java.lang.Throwable, java.lang.String)game.C_100170_cm
		// @40: athrow
	}
	
	static final void func_104760_a(boolean arg0, C_100302_ka arg1)
	{
		// @00: getstatic int game.SteelSentinels.field_105275_O
		// @03: istore_3
		// @04: aload_1
		// @05: getfield game.C_100202_qi game.C_100302_ka.field_101891_Ob
		// @08: bipush 23 (0x17)
		// @0A: invokevirtual game.C_100202_qi.func_105899_c(int)game.C_100158_da
		// @0D: checkcast game.C_100302_ka
		// @10: astore_2
		// @11: aconst_null
		// @12: aload_2
		// @13: if_acmpeq @43
		// @16: aload_2
		// @17: iconst_0
		// @18: putfield int game.C_100302_ka.field_101880_Gb
		// @1B: aload_2
		// @1C: iconst_0
		// @1D: putfield int game.C_100302_ka.field_101843_Tb
		// @20: aload_2
		// @21: iconst_0
		// @22: putfield int game.C_100302_ka.field_101848_lb
		// @25: aload_2
		// @26: iconst_0
		// @27: putfield int game.C_100302_ka.field_101832_tb
		// @2A: aload_1
		// @2B: getfield game.C_100202_qi game.C_100302_ka.field_101891_Ob
		// @2E: bipush 118 (0x76)
		// @30: invokevirtual game.C_100202_qi.func_105907_c(byte)game.C_100158_da
		// @33: checkcast game.C_100302_ka
		// @36: astore_2
		// @37: iload_3
		// @38: ifne @68
		// @3B: iload_3
		// @3C: ifeq @11
		// @3F: goto @43
		// @42: athrow
		// @43: iload_0
		// @44: iconst_1
		// @45: if_icmpeq @54
		// @48: iconst_1
		// @49: aconst_null
		// @4A: checkcast game.C_100302_ka
		// @4D: invokestatic game.C_100107_u.func_104760_a(boolean, game.C_100302_ka)void
		// @50: goto @54
		// @53: athrow
		// @54: aload_1
		// @55: iconst_0
		// @56: putfield int game.C_100302_ka.field_101880_Gb
		// @59: aload_1
		// @5A: iconst_0
		// @5B: putfield int game.C_100302_ka.field_101848_lb
		// @5E: aload_1
		// @5F: iconst_0
		// @60: putfield int game.C_100302_ka.field_101832_tb
		// @63: aload_1
		// @64: iconst_0
		// @65: putfield int game.C_100302_ka.field_101843_Tb
		// @68: goto @A6
		// @6B: astore_2
		// @6C: aload_2
		// @6D: new java.lang.StringBuilder
		// @70: dup
		// @71: invokespecial java.lang.StringBuilder.<init>()void
		// @74: getstatic java.lang.String[] game.C_100107_u.field_104776_z
		// @77: iconst_2
		// @78: aaload
		// @79: invokevirtual java.lang.StringBuilder.append(java.lang.String)java.lang.StringBuilder
		// @7C: iload_0
		// @7D: invokevirtual java.lang.StringBuilder.append(boolean)java.lang.StringBuilder
		// @80: bipush 44 (0x2C)
		// @82: invokevirtual java.lang.StringBuilder.append(char)java.lang.StringBuilder
		// @85: aload_1
		// @86: ifnull @92
		// @89: getstatic java.lang.String[] game.C_100107_u.field_104776_z
		// @8C: iconst_0
		// @8D: aaload
		// @8E: goto @97
		// @91: athrow
		// @92: getstatic java.lang.String[] game.C_100107_u.field_104776_z
		// @95: iconst_1
		// @96: aaload
		// @97: invokevirtual java.lang.StringBuilder.append(java.lang.String)java.lang.StringBuilder
		// @9A: bipush 41 (0x29)
		// @9C: invokevirtual java.lang.StringBuilder.append(char)java.lang.StringBuilder
		// @9F: invokevirtual java.lang.StringBuilder.toString()java.lang.String
		// @A2: invokestatic game.C_100181_cf.func_105695_a(java.lang.Throwable, java.lang.String)game.C_100170_cm
		// @A5: athrow
		// @A6: return
	}
	
	abstract void func_104763_a(C_100280_nf arg0, int arg1);
	
	public static void func_104762_a(int arg0)
	{
		// @00: aconst_null
		// @01: putstatic java.applet.Applet game.C_100107_u.field_104771_d
		// @04: aconst_null
		// @05: putstatic java.lang.String game.C_100107_u.field_104769_f
		// @08: aconst_null
		// @09: putstatic java.lang.String game.C_100107_u.field_104773_b
		// @0C: aconst_null
		// @0D: checkcast byte[][]
		// @10: putstatic byte[][] game.C_100107_u.field_104774_c
		// @13: aconst_null
		// @14: putstatic java.lang.String game.C_100107_u.field_104777_h
		// @17: aconst_null
		// @18: putstatic game.C_100037_wb game.C_100107_u.field_104775_a
		// @1B: iload_0
		// @1C: bipush 109 (0x6D)
		// @1E: if_icmpgt @2A
		// @21: bipush -83 (0xAD)
		// @23: aconst_null
		// @24: checkcast game.C_100033_gj
		// @27: invokestatic game.C_100107_u.func_104767_a(int, game.C_100033_gj)void
		// @2A: goto @4E
		// @2D: astore_1
		// @2E: aload_1
		// @2F: new java.lang.StringBuilder
		// @32: dup
		// @33: invokespecial java.lang.StringBuilder.<init>()void
		// @36: getstatic java.lang.String[] game.C_100107_u.field_104776_z
		// @39: iconst_3
		// @3A: aaload
		// @3B: invokevirtual java.lang.StringBuilder.append(java.lang.String)java.lang.StringBuilder
		// @3E: iload_0
		// @3F: invokevirtual java.lang.StringBuilder.append(int)java.lang.StringBuilder
		// @42: bipush 41 (0x29)
		// @44: invokevirtual java.lang.StringBuilder.append(char)java.lang.StringBuilder
		// @47: invokevirtual java.lang.StringBuilder.toString()java.lang.String
		// @4A: invokestatic game.C_100181_cf.func_105695_a(java.lang.Throwable, java.lang.String)game.C_100170_cm
		// @4D: athrow
		// @4E: return
	}
	
	static final void func_104761_a(Component arg0, byte arg1)
	{
		// @00: aload_0
		// @01: getstatic game.C_100047_vh game.C_100111_el.field_104859_g
		// @04: invokevirtual java.awt.Component.addMouseListener(java.awt.event.MouseListener)void
		// @07: iload_1
		// @08: bipush 20 (0x14)
		// @0A: if_icmpgt @16
		// @0D: bipush 15 (0x0F)
		// @0F: invokestatic game.C_100107_u.func_104762_a(int)void
		// @12: goto @16
		// @15: athrow
		// @16: aload_0
		// @17: getstatic game.C_100047_vh game.C_100111_el.field_104859_g
		// @1A: invokevirtual java.awt.Component.addMouseMotionListener(java.awt.event.MouseMotionListener)void
		// @1D: aload_0
		// @1E: getstatic game.C_100047_vh game.C_100111_el.field_104859_g
		// @21: invokevirtual java.awt.Component.addFocusListener(java.awt.event.FocusListener)void
		// @24: goto @63
		// @27: astore_2
		// @28: aload_2
		// @29: new java.lang.StringBuilder
		// @2C: dup
		// @2D: invokespecial java.lang.StringBuilder.<init>()void
		// @30: getstatic java.lang.String[] game.C_100107_u.field_104776_z
		// @33: bipush 6 (0x06)
		// @35: aaload
		// @36: invokevirtual java.lang.StringBuilder.append(java.lang.String)java.lang.StringBuilder
		// @39: aload_0
		// @3A: ifnull @46
		// @3D: getstatic java.lang.String[] game.C_100107_u.field_104776_z
		// @40: iconst_0
		// @41: aaload
		// @42: goto @4B
		// @45: athrow
		// @46: getstatic java.lang.String[] game.C_100107_u.field_104776_z
		// @49: iconst_1
		// @4A: aaload
		// @4B: invokevirtual java.lang.StringBuilder.append(java.lang.String)java.lang.StringBuilder
		// @4E: bipush 44 (0x2C)
		// @50: invokevirtual java.lang.StringBuilder.append(char)java.lang.StringBuilder
		// @53: iload_1
		// @54: invokevirtual java.lang.StringBuilder.append(int)java.lang.StringBuilder
		// @57: bipush 41 (0x29)
		// @59: invokevirtual java.lang.StringBuilder.append(char)java.lang.StringBuilder
		// @5C: invokevirtual java.lang.StringBuilder.toString()java.lang.String
		// @5F: invokestatic game.C_100181_cf.func_105695_a(java.lang.Throwable, java.lang.String)game.C_100170_cm
		// @62: athrow
		// @63: return
	}
	
	abstract C_100013_fn func_104766_b(int arg0);
	
	static final void func_104767_a(int arg0, C_100033_gj arg1)
	{
		// @00: aconst_null
		// @01: aload_1
		// @02: if_acmpeq @08
		// @05: goto @09
		// @08: return
		// @09: aload_1
		// @0A: putstatic game.C_100033_gj game.C_100159_sn.field_105401_e
		// @0D: getstatic game.C_100302_ka game.C_100245_pf.field_106388_b
		// @10: getfield game.C_100202_qi game.C_100302_ka.field_101891_Ob
		// @13: bipush -127 (0x81)
		// @15: invokevirtual game.C_100202_qi.func_105905_b(byte)void
		// @18: getstatic game.C_100302_ka game.C_100245_pf.field_106388_b
		// @1B: bipush -107 (0x95)
		// @1D: getstatic game.C_100033_gj game.C_100159_sn.field_105401_e
		// @20: invokevirtual game.C_100302_ka.func_101824_b(int, game.C_100302_ka)void
		// @23: iconst_1
		// @24: putstatic boolean game.C_100021_wn.field_103871_b
		// @27: iload_0
		// @28: sipush 23494 (0x5BC6)
		// @2B: if_icmpeq @37
		// @2E: bipush -107 (0x95)
		// @30: aconst_null
		// @31: checkcast game.C_100033_gj
		// @34: invokestatic game.C_100107_u.func_104767_a(int, game.C_100033_gj)void
		// @37: goto @75
		// @3A: astore_2
		// @3B: aload_2
		// @3C: new java.lang.StringBuilder
		// @3F: dup
		// @40: invokespecial java.lang.StringBuilder.<init>()void
		// @43: getstatic java.lang.String[] game.C_100107_u.field_104776_z
		// @46: iconst_4
		// @47: aaload
		// @48: invokevirtual java.lang.StringBuilder.append(java.lang.String)java.lang.StringBuilder
		// @4B: iload_0
		// @4C: invokevirtual java.lang.StringBuilder.append(int)java.lang.StringBuilder
		// @4F: bipush 44 (0x2C)
		// @51: invokevirtual java.lang.StringBuilder.append(char)java.lang.StringBuilder
		// @54: aload_1
		// @55: ifnull @61
		// @58: getstatic java.lang.String[] game.C_100107_u.field_104776_z
		// @5B: iconst_0
		// @5C: aaload
		// @5D: goto @66
		// @60: athrow
		// @61: getstatic java.lang.String[] game.C_100107_u.field_104776_z
		// @64: iconst_1
		// @65: aaload
		// @66: invokevirtual java.lang.StringBuilder.append(java.lang.String)java.lang.StringBuilder
		// @69: bipush 41 (0x29)
		// @6B: invokevirtual java.lang.StringBuilder.append(char)java.lang.StringBuilder
		// @6E: invokevirtual java.lang.StringBuilder.toString()java.lang.String
		// @71: invokestatic game.C_100181_cf.func_105695_a(java.lang.Throwable, java.lang.String)game.C_100170_cm
		// @74: athrow
		// @75: return
	}
	
	static
	{
		// @00: bipush 7 (0x07)
		// @02: anewarray java.lang.String
		// @05: dup
		// @06: iconst_0
		// @07: ldc "\u0000Y+Wr"
		// @09: invokestatic game.C_100107_u.func_104765_z(java.lang.String)char[]
		// @0C: invokestatic game.C_100107_u.func_104764_z(char[])java.lang.String
		// @0F: aastore
		// @10: dup
		// @11: iconst_1
		// @12: ldc "\u0015\u0002i\u0015"
		// @14: invokestatic game.C_100107_u.func_104765_z(java.lang.String)char[]
		// @17: invokestatic game.C_100107_u.func_104764_z(char[])java.lang.String
		// @1A: aastore
		// @1B: dup
		// @1C: iconst_2
		// @1D: ldc "\u000eYFQ"
		// @1F: invokestatic game.C_100107_u.func_104765_z(java.lang.String)char[]
		// @22: invokestatic game.C_100107_u.func_104764_z(char[])java.lang.String
		// @25: aastore
		// @26: dup
		// @27: iconst_3
		// @28: ldc "\u000eYCQ"
		// @2A: invokestatic game.C_100107_u.func_104765_z(java.lang.String)char[]
		// @2D: invokestatic game.C_100107_u.func_104764_z(char[])java.lang.String
		// @30: aastore
		// @31: dup
		// @32: iconst_4
		// @33: ldc "\u000eYGQ"
		// @35: invokestatic game.C_100107_u.func_104765_z(java.lang.String)char[]
		// @38: invokestatic game.C_100107_u.func_104764_z(char[])java.lang.String
		// @3B: aastore
		// @3C: dup
		// @3D: iconst_5
		// @3E: ldc "\u000eYDQ"
		// @40: invokestatic game.C_100107_u.func_104765_z(java.lang.String)char[]
		// @43: invokestatic game.C_100107_u.func_104764_z(char[])java.lang.String
		// @46: aastore
		// @47: dup
		// @48: bipush 6 (0x06)
		// @4A: ldc "\u000eYAQ"
		// @4C: invokestatic game.C_100107_u.func_104765_z(java.lang.String)char[]
		// @4F: invokestatic game.C_100107_u.func_104764_z(char[])java.lang.String
		// @52: aastore
		// @53: putstatic java.lang.String[] game.C_100107_u.field_104776_z
		// @56: ldc "3\u0012w\u001c/\u0002\u0018pYl\u001a\u0019%\nj\u000fWp\t/\u001aWw\u0018{\u001e\u0013%\u001en\u0016\u0012+YF\u001dW|\u0016z[\u0000l\u0017#[\u000ej\u000c}[\u0005d\rf\u0015\u0010%\u000ef\u0017\u001b%\u001e`[\u0002uW/2\u00119\u0017m\u0008\u0007;\u0000`\u000eWi\u0016|\u001e[%\u0010{[\u0000l\u0015c[\u0010jYk\u0014\u0000kX3\u0019\u0005;Em\tIU\u0015j\u001a\u0004`Y|\u000b\u0012f\u0010i\u0002W|\u0016z\tWu\u000bj\u001d\u0012w\u001ca\u0018\u0012vYn\u0015\u0013%\u001ac\u0012\u0014nY(GR5G(UWJ\u000c}[\u0004|\n{\u001e\u001a%\u000ef\u0017\u001b%\rg\u001e\u0019%\u0018{\u000f\u0012h\t{[\u0003jYi\u0012\u0019aY|\u000e\u001eq\u0018m\u0017\u0012%\u0016\u007f\u000b\u0018k\u001ca\u000f\u0004%\u0010a[\u0002k\u001dj\tWdYb\u0012\u0019p\rjWWa\u001c\u007f\u001e\u0019a\u0010a\u001cWj\u0017/\u0013\u0018rYm\u000e\u0004|Y{\u0013\u0012%\u0015`\u0019\u0015|Ea\u0019\u0004uGf\u0008Y9\u001b}EKg\u000b1/\u001fl\n/\u0012\u0004%\u0018a[\u0012}\u001aj\u0017\u001b`\u0017{[\u0000d\u0000/\u000f\u0018%\u001ej\u000fWq\u0016/\u0010\u0019j\u000e/\u0015\u0012rY\u007f\u001e\u0018u\u0015jZ"
		// @58: invokestatic game.C_100107_u.func_104765_z(java.lang.String)char[]
		// @5B: invokestatic game.C_100107_u.func_104764_z(char[])java.lang.String
		// @5E: putstatic java.lang.String game.C_100107_u.field_104777_h
		// @61: ldc "(\u0012w\u0010`\u000e\u0004i\u0000/\u0014\u0011c\u001ca\u0008\u001es\u001c/\u0017\u0016k\u001ez\u001a\u0010`"
		// @63: invokestatic game.C_100107_u.func_104765_z(java.lang.String)char[]
		// @66: invokestatic game.C_100107_u.func_104764_z(char[])java.lang.String
		// @69: putstatic java.lang.String game.C_100107_u.field_104773_b
		// @6C: ldc ")\u0018f\u0012j\u000f\u0004%\u0018a\u001fWh\u0010|\u0008\u001ei\u001c|[\u0005`\u0015`\u001a\u0013%\u001fn\u0008\u0003`\u000b!"
		// @6E: invokestatic game.C_100107_u.func_104765_z(java.lang.String)char[]
		// @71: invokestatic game.C_100107_u.func_104764_z(char[])java.lang.String
		// @74: putstatic java.lang.String game.C_100107_u.field_104769_f
		// @77: return
	}
	
	private static char[] func_104765_z(String arg0)
	{
		// @00: aload_0
		// @01: invokevirtual java.lang.String.toCharArray()char[]
		// @04: dup
		// @05: arraylength
		// @06: iconst_2
		// @07: if_icmpge @13
		// @0A: dup
		// @0B: iconst_0
		// @0C: dup2
		// @0D: caload
		// @0E: bipush 15 (0x0F)
		// @10: ixor
		// @11: i2c
		// @12: castore
		// @13: areturn
	}
	
	private static String func_104764_z(char[] arg0)
	{
		// @00: aload_0
		// @01: dup
		// @02: arraylength
		// @03: swap
		// @04: iconst_0
		// @05: istore_1
		// @06: goto @4B
		// @09: dup
		// @0A: iload_1
		// @0B: dup2
		// @0C: caload
		// @0D: iload_1
		// @0E: iconst_5
		// @0F: irem
		// @10: tableswitch def: @43, for 0: @30, for 1: @35, for 2: @3A, for 3: @3E
		// @30: bipush 123 (0x7B)
		// @32: goto @45
		// @35: bipush 119 (0x77)
		// @37: goto @45
		// @3A: iconst_5
		// @3B: goto @45
		// @3E: bipush 121 (0x79)
		// @40: goto @45
		// @43: bipush 15 (0x0F)
		// @45: ixor
		// @46: i2c
		// @47: castore
		// @48: iinc #1 +1
		// @4B: swap
		// @4C: dup_x1
		// @4D: iload_1
		// @4E: if_icmpgt @09
		// @51: new java.lang.String
		// @54: dup_x1
		// @55: swap
		// @56: invokespecial java.lang.String.<init>(char[])void
		// @59: invokevirtual java.lang.String.intern()java.lang.String
		// @5C: areturn
	}
}
