package game;

final class C_100333_ij
{
	private int field_107355_h;
	static String[] field_107349_a;
	private int field_107353_j;
	static int field_107350_n;
	static int[] field_107345_d;
	static String field_107348_c;
	int field_107347_b;
	private boolean field_107352_m;
	boolean field_107356_i;
	static int field_107346_e;
	static String[] field_107354_k;
	int field_107344_g;
	private int field_107343_f;
	private int field_107351_l;
	private static final String[] field_107357_z;
	
	static final boolean func_107341_a(int arg0, boolean arg1, C_100098_h arg2, int arg3)
	{
		// @00: iload_1
		// @01: iconst_1
		// @02: if_icmpeq @07
		// @05: iconst_0
		// @06: ireturn
		// @07: aload_2
		// @08: iload_3
		// @09: iconst_0
		// @0A: iload_0
		// @0B: invokevirtual game.C_100098_h.func_104610_b(int, int, int)byte[]
		// @0E: astore #4
		// @10: aconst_null
		// @11: aload #4
		// @13: if_acmpeq @1A
		// @16: goto @1C
		// @19: athrow
		// @1A: iconst_0
		// @1B: ireturn
		// @1C: aload #4
		// @1E: sipush 200 (0x00C8)
		// @21: invokestatic game.C_100328_ia.func_107250_a(byte[], int)void
		// @24: iconst_1
		// @25: ireturn
		// @26: astore #4
		// @28: aload #4
		// @2A: new java.lang.StringBuilder
		// @2D: dup
		// @2E: invokespecial java.lang.StringBuilder.<init>()void
		// @31: getstatic java.lang.String[] game.C_100333_ij.field_107357_z
		// @34: bipush 12 (0x0C)
		// @36: aaload
		// @37: invokevirtual java.lang.StringBuilder.append(java.lang.String)java.lang.StringBuilder
		// @3A: iload_0
		// @3B: invokevirtual java.lang.StringBuilder.append(int)java.lang.StringBuilder
		// @3E: bipush 44 (0x2C)
		// @40: invokevirtual java.lang.StringBuilder.append(char)java.lang.StringBuilder
		// @43: iload_1
		// @44: invokevirtual java.lang.StringBuilder.append(boolean)java.lang.StringBuilder
		// @47: bipush 44 (0x2C)
		// @49: invokevirtual java.lang.StringBuilder.append(char)java.lang.StringBuilder
		// @4C: aload_2
		// @4D: ifnull @5A
		// @50: getstatic java.lang.String[] game.C_100333_ij.field_107357_z
		// @53: bipush 13 (0x0D)
		// @55: aaload
		// @56: goto @60
		// @59: athrow
		// @5A: getstatic java.lang.String[] game.C_100333_ij.field_107357_z
		// @5D: bipush 11 (0x0B)
		// @5F: aaload
		// @60: invokevirtual java.lang.StringBuilder.append(java.lang.String)java.lang.StringBuilder
		// @63: bipush 44 (0x2C)
		// @65: invokevirtual java.lang.StringBuilder.append(char)java.lang.StringBuilder
		// @68: iload_3
		// @69: invokevirtual java.lang.StringBuilder.append(int)java.lang.StringBuilder
		// @6C: bipush 41 (0x29)
		// @6E: invokevirtual java.lang.StringBuilder.append(char)java.lang.StringBuilder
		// @71: invokevirtual java.lang.StringBuilder.toString()java.lang.String
		// @74: invokestatic game.C_100181_cf.func_105695_a(java.lang.Throwable, java.lang.String)game.C_100170_cm
		// @77: athrow
	}
	
	final boolean func_107336_c(int arg0)
	{
		// @00: iload_1
		// @01: sipush -27943 (0x92D9)
		// @04: if_icmpeq @09
		// @07: iconst_0
		// @08: ireturn
		// @09: bipush -97 (0x9F)
		// @0B: aload_0
		// @0C: getfield int game.C_100333_ij.field_107353_j
		// @0F: iconst_m1
		// @10: ixor
		// @11: if_icmpne @19
		// @14: iconst_1
		// @15: goto @1A
		// @18: athrow
		// @19: iconst_0
		// @1A: ireturn
		// @1B: astore_2
		// @1C: aload_2
		// @1D: new java.lang.StringBuilder
		// @20: dup
		// @21: invokespecial java.lang.StringBuilder.<init>()void
		// @24: getstatic java.lang.String[] game.C_100333_ij.field_107357_z
		// @27: bipush 14 (0x0E)
		// @29: aaload
		// @2A: invokevirtual java.lang.StringBuilder.append(java.lang.String)java.lang.StringBuilder
		// @2D: iload_1
		// @2E: invokevirtual java.lang.StringBuilder.append(int)java.lang.StringBuilder
		// @31: bipush 41 (0x29)
		// @33: invokevirtual java.lang.StringBuilder.append(char)java.lang.StringBuilder
		// @36: invokevirtual java.lang.StringBuilder.toString()java.lang.String
		// @39: invokestatic game.C_100181_cf.func_105695_a(java.lang.Throwable, java.lang.String)game.C_100170_cm
		// @3C: athrow
	}
	
	final boolean func_107338_f(int arg0)
	{
		// @00: iload_1
		// @01: ifeq @0F
		// @04: aload_0
		// @05: bipush 16 (0x10)
		// @07: invokevirtual game.C_100333_ij.func_107324_a(byte)boolean
		// @0A: pop
		// @0B: goto @0F
		// @0E: athrow
		// @0F: aload_0
		// @10: getfield int game.C_100333_ij.field_107355_h
		// @13: ifeq @1B
		// @16: iconst_1
		// @17: goto @1C
		// @1A: athrow
		// @1B: iconst_0
		// @1C: ireturn
		// @1D: astore_2
		// @1E: aload_2
		// @1F: new java.lang.StringBuilder
		// @22: dup
		// @23: invokespecial java.lang.StringBuilder.<init>()void
		// @26: getstatic java.lang.String[] game.C_100333_ij.field_107357_z
		// @29: bipush 22 (0x16)
		// @2B: aaload
		// @2C: invokevirtual java.lang.StringBuilder.append(java.lang.String)java.lang.StringBuilder
		// @2F: iload_1
		// @30: invokevirtual java.lang.StringBuilder.append(int)java.lang.StringBuilder
		// @33: bipush 41 (0x29)
		// @35: invokevirtual java.lang.StringBuilder.append(char)java.lang.StringBuilder
		// @38: invokevirtual java.lang.StringBuilder.toString()java.lang.String
		// @3B: invokestatic game.C_100181_cf.func_105695_a(java.lang.Throwable, java.lang.String)game.C_100170_cm
		// @3E: athrow
	}
	
	final void func_107328_a(int arg0)
	{
		// @00: aload_0
		// @01: iconst_0
		// @02: putfield boolean game.C_100333_ij.field_107356_i
		// @05: iload_1
		// @06: bipush -18 (0xEE)
		// @08: if_icmplt @19
		// @0B: aload_0
		// @0C: bipush -103 (0x99)
		// @0E: bipush 23 (0x17)
		// @10: bipush 101 (0x65)
		// @12: invokevirtual game.C_100333_ij.func_107335_a(int, int, int)void
		// @15: goto @19
		// @18: athrow
		// @19: aload_0
		// @1A: iconst_0
		// @1B: putfield int game.C_100333_ij.field_107343_f
		// @1E: aload_0
		// @1F: iconst_0
		// @20: putfield int game.C_100333_ij.field_107353_j
		// @23: aload_0
		// @24: getfield int game.C_100333_ij.field_107355_h
		// @27: ifne @35
		// @2A: aload_0
		// @2B: getstatic int game.C_100293_kj.field_106890_c
		// @2E: putfield int game.C_100333_ij.field_107353_j
		// @31: goto @35
		// @34: athrow
		// @35: iconst_0
		// @36: aload_0
		// @37: getfield int game.C_100333_ij.field_107355_h
		// @3A: if_icmpne @74
		// @3D: bipush 98 (0x62)
		// @3F: getstatic int game.C_100293_kj.field_106890_c
		// @42: if_icmpeq @4D
		// @45: goto @49
		// @48: athrow
		// @49: goto @74
		// @4C: athrow
		// @4D: aload_0
		// @4E: getfield int game.C_100333_ij.field_107347_b
		// @51: ifle @58
		// @54: goto @60
		// @57: athrow
		// @58: aload_0
		// @59: aload_0
		// @5A: getfield int game.C_100333_ij.field_107344_g
		// @5D: putfield int game.C_100333_ij.field_107347_b
		// @60: aload_0
		// @61: dup
		// @62: getfield int game.C_100333_ij.field_107347_b
		// @65: iconst_1
		// @66: isub
		// @67: putfield int game.C_100333_ij.field_107347_b
		// @6A: aload_0
		// @6B: iconst_1
		// @6C: putfield boolean game.C_100333_ij.field_107356_i
		// @6F: aload_0
		// @70: iconst_0
		// @71: putfield boolean game.C_100333_ij.field_107352_m
		// @74: aload_0
		// @75: getfield int game.C_100333_ij.field_107355_h
		// @78: iconst_m1
		// @79: ixor
		// @7A: iconst_m1
		// @7B: if_icmpne @BA
		// @7E: getstatic int game.C_100293_kj.field_106890_c
		// @81: bipush 99 (0x63)
		// @83: if_icmpeq @8E
		// @86: goto @8A
		// @89: athrow
		// @8A: goto @BA
		// @8D: athrow
		// @8E: aload_0
		// @8F: dup
		// @90: getfield int game.C_100333_ij.field_107347_b
		// @93: iconst_1
		// @94: iadd
		// @95: putfield int game.C_100333_ij.field_107347_b
		// @98: aload_0
		// @99: iconst_0
		// @9A: putfield boolean game.C_100333_ij.field_107352_m
		// @9D: aload_0
		// @9E: getfield int game.C_100333_ij.field_107347_b
		// @A1: iconst_m1
		// @A2: ixor
		// @A3: aload_0
		// @A4: getfield int game.C_100333_ij.field_107344_g
		// @A7: iconst_m1
		// @A8: ixor
		// @A9: if_icmple @B0
		// @AC: goto @B5
		// @AF: athrow
		// @B0: aload_0
		// @B1: iconst_0
		// @B2: putfield int game.C_100333_ij.field_107347_b
		// @B5: aload_0
		// @B6: iconst_1
		// @B7: putfield boolean game.C_100333_ij.field_107356_i
		// @BA: goto @DF
		// @BD: astore_2
		// @BE: aload_2
		// @BF: new java.lang.StringBuilder
		// @C2: dup
		// @C3: invokespecial java.lang.StringBuilder.<init>()void
		// @C6: getstatic java.lang.String[] game.C_100333_ij.field_107357_z
		// @C9: bipush 20 (0x14)
		// @CB: aaload
		// @CC: invokevirtual java.lang.StringBuilder.append(java.lang.String)java.lang.StringBuilder
		// @CF: iload_1
		// @D0: invokevirtual java.lang.StringBuilder.append(int)java.lang.StringBuilder
		// @D3: bipush 41 (0x29)
		// @D5: invokevirtual java.lang.StringBuilder.append(char)java.lang.StringBuilder
		// @D8: invokevirtual java.lang.StringBuilder.toString()java.lang.String
		// @DB: invokestatic game.C_100181_cf.func_105695_a(java.lang.Throwable, java.lang.String)game.C_100170_cm
		// @DE: athrow
		// @DF: return
	}
	
	final void func_107334_b(byte arg0)
	{
		// @00: aload_0
		// @01: iconst_0
		// @02: putfield int game.C_100333_ij.field_107343_f
		// @05: bipush -7 (0xF9)
		// @07: iload_1
		// @08: bipush -11 (0xF5)
		// @0A: isub
		// @0B: bipush 43 (0x2B)
		// @0D: idiv
		// @0E: idiv
		// @0F: istore_2
		// @10: aload_0
		// @11: iconst_0
		// @12: putfield boolean game.C_100333_ij.field_107356_i
		// @15: aload_0
		// @16: iconst_0
		// @17: putfield int game.C_100333_ij.field_107353_j
		// @1A: aload_0
		// @1B: getfield int game.C_100333_ij.field_107355_h
		// @1E: iconst_m1
		// @1F: ixor
		// @20: iconst_m1
		// @21: if_icmpeq @28
		// @24: goto @2F
		// @27: athrow
		// @28: aload_0
		// @29: getstatic int game.C_100293_kj.field_106890_c
		// @2C: putfield int game.C_100333_ij.field_107353_j
		// @2F: goto @54
		// @32: astore_2
		// @33: aload_2
		// @34: new java.lang.StringBuilder
		// @37: dup
		// @38: invokespecial java.lang.StringBuilder.<init>()void
		// @3B: getstatic java.lang.String[] game.C_100333_ij.field_107357_z
		// @3E: bipush 8 (0x08)
		// @40: aaload
		// @41: invokevirtual java.lang.StringBuilder.append(java.lang.String)java.lang.StringBuilder
		// @44: iload_1
		// @45: invokevirtual java.lang.StringBuilder.append(int)java.lang.StringBuilder
		// @48: bipush 41 (0x29)
		// @4A: invokevirtual java.lang.StringBuilder.append(char)java.lang.StringBuilder
		// @4D: invokevirtual java.lang.StringBuilder.toString()java.lang.String
		// @50: invokestatic game.C_100181_cf.func_105695_a(java.lang.Throwable, java.lang.String)game.C_100170_cm
		// @53: athrow
		// @54: return
	}
	
	final boolean func_107324_a(byte arg0)
	{
		// @00: iload_1
		// @01: bipush -35 (0xDD)
		// @03: if_icmplt @14
		// @06: aload_0
		// @07: bipush -4 (0xFC)
		// @09: bipush 119 (0x77)
		// @0B: bipush 95 (0x5F)
		// @0D: invokevirtual game.C_100333_ij.func_107335_a(int, int, int)void
		// @10: goto @14
		// @13: athrow
		// @14: aload_0
		// @15: getfield int game.C_100333_ij.field_107353_j
		// @18: iconst_m1
		// @19: ixor
		// @1A: bipush -103 (0x99)
		// @1C: if_icmpne @24
		// @1F: iconst_1
		// @20: goto @25
		// @23: athrow
		// @24: iconst_0
		// @25: ireturn
		// @26: astore_2
		// @27: aload_2
		// @28: new java.lang.StringBuilder
		// @2B: dup
		// @2C: invokespecial java.lang.StringBuilder.<init>()void
		// @2F: getstatic java.lang.String[] game.C_100333_ij.field_107357_z
		// @32: iconst_0
		// @33: aaload
		// @34: invokevirtual java.lang.StringBuilder.append(java.lang.String)java.lang.StringBuilder
		// @37: iload_1
		// @38: invokevirtual java.lang.StringBuilder.append(int)java.lang.StringBuilder
		// @3B: bipush 41 (0x29)
		// @3D: invokevirtual java.lang.StringBuilder.append(char)java.lang.StringBuilder
		// @40: invokevirtual java.lang.StringBuilder.toString()java.lang.String
		// @43: invokestatic game.C_100181_cf.func_105695_a(java.lang.Throwable, java.lang.String)game.C_100170_cm
		// @46: athrow
	}
	
	final boolean func_107339_b(boolean arg0)
	{
		// @00: iload_1
		// @01: iconst_1
		// @02: if_icmpeq @10
		// @05: aload_0
		// @06: bipush -41 (0xD7)
		// @08: invokevirtual game.C_100333_ij.func_107333_d(int)boolean
		// @0B: pop
		// @0C: goto @10
		// @0F: athrow
		// @10: aload_0
		// @11: getfield int game.C_100333_ij.field_107343_f
		// @14: iconst_m1
		// @15: ixor
		// @16: iconst_m1
		// @17: if_icmpne @36
		// @1A: aload_0
		// @1B: getfield int game.C_100333_ij.field_107353_j
		// @1E: bipush 84 (0x54)
		// @20: if_icmpeq @36
		// @23: goto @27
		// @26: athrow
		// @27: aload_0
		// @28: getfield int game.C_100333_ij.field_107353_j
		// @2B: iconst_m1
		// @2C: ixor
		// @2D: bipush -84 (0xAC)
		// @2F: if_icmpne @3B
		// @32: goto @36
		// @35: athrow
		// @36: iconst_1
		// @37: goto @3C
		// @3A: athrow
		// @3B: iconst_0
		// @3C: ireturn
		// @3D: astore_2
		// @3E: aload_2
		// @3F: new java.lang.StringBuilder
		// @42: dup
		// @43: invokespecial java.lang.StringBuilder.<init>()void
		// @46: getstatic java.lang.String[] game.C_100333_ij.field_107357_z
		// @49: bipush 10 (0x0A)
		// @4B: aaload
		// @4C: invokevirtual java.lang.StringBuilder.append(java.lang.String)java.lang.StringBuilder
		// @4F: iload_1
		// @50: invokevirtual java.lang.StringBuilder.append(boolean)java.lang.StringBuilder
		// @53: bipush 41 (0x29)
		// @55: invokevirtual java.lang.StringBuilder.append(char)java.lang.StringBuilder
		// @58: invokevirtual java.lang.StringBuilder.toString()java.lang.String
		// @5B: invokestatic game.C_100181_cf.func_105695_a(java.lang.Throwable, java.lang.String)game.C_100170_cm
		// @5E: athrow
	}
	
	final void func_107340_a(int arg0, int arg1, int arg2, boolean arg3)
	{
		// @00: aload_0
		// @01: iload #4
		// @03: putfield boolean game.C_100333_ij.field_107352_m
		// @06: aload_0
		// @07: iload_1
		// @08: putfield int game.C_100333_ij.field_107355_h
		// @0B: aload_0
		// @0C: getfield boolean game.C_100333_ij.field_107352_m
		// @0F: ifeq @21
		// @12: aload_0
		// @13: iload_2
		// @14: putfield int game.C_100333_ij.field_107347_b
		// @17: getstatic int game.SteelSentinels.field_105275_O
		// @1A: ifeq @2A
		// @1D: goto @21
		// @20: athrow
		// @21: aload_0
		// @22: iload_3
		// @23: putfield int game.C_100333_ij.field_107347_b
		// @26: goto @2A
		// @29: athrow
		// @2A: goto @6C
		// @2D: astore #5
		// @2F: aload #5
		// @31: new java.lang.StringBuilder
		// @34: dup
		// @35: invokespecial java.lang.StringBuilder.<init>()void
		// @38: getstatic java.lang.String[] game.C_100333_ij.field_107357_z
		// @3B: iconst_1
		// @3C: aaload
		// @3D: invokevirtual java.lang.StringBuilder.append(java.lang.String)java.lang.StringBuilder
		// @40: iload_1
		// @41: invokevirtual java.lang.StringBuilder.append(int)java.lang.StringBuilder
		// @44: bipush 44 (0x2C)
		// @46: invokevirtual java.lang.StringBuilder.append(char)java.lang.StringBuilder
		// @49: iload_2
		// @4A: invokevirtual java.lang.StringBuilder.append(int)java.lang.StringBuilder
		// @4D: bipush 44 (0x2C)
		// @4F: invokevirtual java.lang.StringBuilder.append(char)java.lang.StringBuilder
		// @52: iload_3
		// @53: invokevirtual java.lang.StringBuilder.append(int)java.lang.StringBuilder
		// @56: bipush 44 (0x2C)
		// @58: invokevirtual java.lang.StringBuilder.append(char)java.lang.StringBuilder
		// @5B: iload #4
		// @5D: invokevirtual java.lang.StringBuilder.append(boolean)java.lang.StringBuilder
		// @60: bipush 41 (0x29)
		// @62: invokevirtual java.lang.StringBuilder.append(char)java.lang.StringBuilder
		// @65: invokevirtual java.lang.StringBuilder.toString()java.lang.String
		// @68: invokestatic game.C_100181_cf.func_105695_a(java.lang.Throwable, java.lang.String)game.C_100170_cm
		// @6B: athrow
		// @6C: return
	}
	
	static final String func_107326_e(int arg0)
	{
		// @000: iconst_2
		// @001: getstatic int game.C_100283_ni.field_106760_c
		// @004: if_icmple @00B
		// @007: getstatic java.lang.String game.C_100123_uc.field_104919_f
		// @00A: areturn
		// @00B: getstatic game.C_100098_h game.C_100162_sc.field_102863_R
		// @00E: ifnull @02B
		// @011: getstatic game.C_100098_h game.C_100162_sc.field_102863_R
		// @014: iconst_0
		// @015: invokevirtual game.C_100098_h.func_104597_a(boolean)boolean
		// @018: ifeq @023
		// @01B: goto @01F
		// @01E: athrow
		// @01F: goto @027
		// @022: athrow
		// @023: getstatic java.lang.String game.C_100219_an.field_100877_l
		// @026: areturn
		// @027: getstatic java.lang.String game.C_100077_d.field_103321_V
		// @02A: areturn
		// @02B: bipush 41 (0x29)
		// @02D: iload_0
		// @02E: bipush 42 (0x2A)
		// @030: isub
		// @031: bipush 38 (0x26)
		// @033: idiv
		// @034: idiv
		// @035: istore_1
		// @036: getstatic game.C_100098_h game.C_100064_ve.field_103021_y
		// @039: iconst_0
		// @03A: invokevirtual game.C_100098_h.func_104597_a(boolean)boolean
		// @03D: ifeq @044
		// @040: goto @048
		// @043: athrow
		// @044: getstatic java.lang.String game.C_100102_w.field_104637_a
		// @047: areturn
		// @048: getstatic game.C_100098_h game.C_100064_ve.field_103021_y
		// @04B: getstatic java.lang.String[] game.C_100333_ij.field_107357_z
		// @04E: iconst_4
		// @04F: aaload
		// @050: iconst_0
		// @051: invokevirtual game.C_100098_h.func_104593_a(java.lang.String, boolean)boolean
		// @054: ifeq @05B
		// @057: goto @089
		// @05A: athrow
		// @05B: new java.lang.StringBuilder
		// @05E: dup
		// @05F: invokespecial java.lang.StringBuilder.<init>()void
		// @062: getstatic java.lang.String game.C_100049_vf.field_104205_o
		// @065: invokevirtual java.lang.StringBuilder.append(java.lang.String)java.lang.StringBuilder
		// @068: getstatic java.lang.String[] game.C_100333_ij.field_107357_z
		// @06B: iconst_5
		// @06C: aaload
		// @06D: invokevirtual java.lang.StringBuilder.append(java.lang.String)java.lang.StringBuilder
		// @070: getstatic game.C_100098_h game.C_100064_ve.field_103021_y
		// @073: bipush 110 (0x6E)
		// @075: getstatic java.lang.String[] game.C_100333_ij.field_107357_z
		// @078: iconst_4
		// @079: aaload
		// @07A: invokevirtual game.C_100098_h.func_104602_a(byte, java.lang.String)int
		// @07D: invokevirtual java.lang.StringBuilder.append(int)java.lang.StringBuilder
		// @080: ldc "%"
		// @082: invokevirtual java.lang.StringBuilder.append(java.lang.String)java.lang.StringBuilder
		// @085: invokevirtual java.lang.StringBuilder.toString()java.lang.String
		// @088: areturn
		// @089: getstatic game.C_100098_h game.C_100144_bm.field_102095_Zb
		// @08C: iconst_0
		// @08D: invokevirtual game.C_100098_h.func_104597_a(boolean)boolean
		// @090: ifeq @097
		// @093: goto @09B
		// @096: athrow
		// @097: getstatic java.lang.String game.C_100346_ja.field_103481_B
		// @09A: areturn
		// @09B: getstatic game.C_100098_h game.C_100144_bm.field_102095_Zb
		// @09E: getstatic java.lang.String[] game.C_100333_ij.field_107357_z
		// @0A1: iconst_4
		// @0A2: aaload
		// @0A3: iconst_0
		// @0A4: invokevirtual game.C_100098_h.func_104593_a(java.lang.String, boolean)boolean
		// @0A7: ifeq @0AE
		// @0AA: goto @0DC
		// @0AD: athrow
		// @0AE: new java.lang.StringBuilder
		// @0B1: dup
		// @0B2: invokespecial java.lang.StringBuilder.<init>()void
		// @0B5: getstatic java.lang.String game.C_100164_se.field_105452_b
		// @0B8: invokevirtual java.lang.StringBuilder.append(java.lang.String)java.lang.StringBuilder
		// @0BB: getstatic java.lang.String[] game.C_100333_ij.field_107357_z
		// @0BE: iconst_5
		// @0BF: aaload
		// @0C0: invokevirtual java.lang.StringBuilder.append(java.lang.String)java.lang.StringBuilder
		// @0C3: getstatic game.C_100098_h game.C_100144_bm.field_102095_Zb
		// @0C6: bipush -37 (0xDB)
		// @0C8: getstatic java.lang.String[] game.C_100333_ij.field_107357_z
		// @0CB: iconst_4
		// @0CC: aaload
		// @0CD: invokevirtual game.C_100098_h.func_104602_a(byte, java.lang.String)int
		// @0D0: invokevirtual java.lang.StringBuilder.append(int)java.lang.StringBuilder
		// @0D3: ldc "%"
		// @0D5: invokevirtual java.lang.StringBuilder.append(java.lang.String)java.lang.StringBuilder
		// @0D8: invokevirtual java.lang.StringBuilder.toString()java.lang.String
		// @0DB: areturn
		// @0DC: getstatic game.C_100098_h game.C_100325_id.field_101482_p
		// @0DF: iconst_0
		// @0E0: invokevirtual game.C_100098_h.func_104597_a(boolean)boolean
		// @0E3: ifeq @0EA
		// @0E6: goto @0EE
		// @0E9: athrow
		// @0EA: getstatic java.lang.String game.C_100170_cm.field_105550_i
		// @0ED: areturn
		// @0EE: getstatic game.C_100098_h game.C_100325_id.field_101482_p
		// @0F1: iconst_0
		// @0F2: invokevirtual game.C_100098_h.func_104598_a(int)boolean
		// @0F5: ifne @120
		// @0F8: new java.lang.StringBuilder
		// @0FB: dup
		// @0FC: invokespecial java.lang.StringBuilder.<init>()void
		// @0FF: getstatic java.lang.String game.C_100346_ja.field_103496_p
		// @102: invokevirtual java.lang.StringBuilder.append(java.lang.String)java.lang.StringBuilder
		// @105: getstatic java.lang.String[] game.C_100333_ij.field_107357_z
		// @108: iconst_5
		// @109: aaload
		// @10A: invokevirtual java.lang.StringBuilder.append(java.lang.String)java.lang.StringBuilder
		// @10D: getstatic game.C_100098_h game.C_100325_id.field_101482_p
		// @110: iconst_0
		// @111: invokevirtual game.C_100098_h.func_104590_b(boolean)int
		// @114: invokevirtual java.lang.StringBuilder.append(int)java.lang.StringBuilder
		// @117: ldc "%"
		// @119: invokevirtual java.lang.StringBuilder.append(java.lang.String)java.lang.StringBuilder
		// @11C: invokevirtual java.lang.StringBuilder.toString()java.lang.String
		// @11F: areturn
		// @120: getstatic java.lang.String game.C_100306_kn.field_107139_j
		// @123: areturn
		// @124: astore_1
		// @125: aload_1
		// @126: new java.lang.StringBuilder
		// @129: dup
		// @12A: invokespecial java.lang.StringBuilder.<init>()void
		// @12D: getstatic java.lang.String[] game.C_100333_ij.field_107357_z
		// @130: iconst_3
		// @131: aaload
		// @132: invokevirtual java.lang.StringBuilder.append(java.lang.String)java.lang.StringBuilder
		// @135: iload_0
		// @136: invokevirtual java.lang.StringBuilder.append(int)java.lang.StringBuilder
		// @139: bipush 41 (0x29)
		// @13B: invokevirtual java.lang.StringBuilder.append(char)java.lang.StringBuilder
		// @13E: invokevirtual java.lang.StringBuilder.toString()java.lang.String
		// @141: invokestatic game.C_100181_cf.func_105695_a(java.lang.Throwable, java.lang.String)game.C_100170_cm
		// @144: athrow
	}
	
	final void func_107342_a(int arg0, int arg1)
	{
		// @00: aload_0
		// @01: getfield int game.C_100333_ij.field_107355_h
		// @04: ifne @1A
		// @07: aload_0
		// @08: iconst_0
		// @09: putfield boolean game.C_100333_ij.field_107352_m
		// @0C: aload_0
		// @0D: iload_1
		// @0E: putfield int game.C_100333_ij.field_107347_b
		// @11: aload_0
		// @12: iconst_1
		// @13: putfield boolean game.C_100333_ij.field_107356_i
		// @16: goto @1A
		// @19: athrow
		// @1A: iload_2
		// @1B: bipush -31 (0xE1)
		// @1D: if_icmple @2D
		// @20: bipush 110 (0x6E)
		// @22: bipush -9 (0xF7)
		// @24: bipush 61 (0x3D)
		// @26: invokestatic game.C_100333_ij.func_107325_a(byte, int, int)void
		// @29: goto @2D
		// @2C: athrow
		// @2D: goto @5B
		// @30: astore_3
		// @31: aload_3
		// @32: new java.lang.StringBuilder
		// @35: dup
		// @36: invokespecial java.lang.StringBuilder.<init>()void
		// @39: getstatic java.lang.String[] game.C_100333_ij.field_107357_z
		// @3C: bipush 9 (0x09)
		// @3E: aaload
		// @3F: invokevirtual java.lang.StringBuilder.append(java.lang.String)java.lang.StringBuilder
		// @42: iload_1
		// @43: invokevirtual java.lang.StringBuilder.append(int)java.lang.StringBuilder
		// @46: bipush 44 (0x2C)
		// @48: invokevirtual java.lang.StringBuilder.append(char)java.lang.StringBuilder
		// @4B: iload_2
		// @4C: invokevirtual java.lang.StringBuilder.append(int)java.lang.StringBuilder
		// @4F: bipush 41 (0x29)
		// @51: invokevirtual java.lang.StringBuilder.append(char)java.lang.StringBuilder
		// @54: invokevirtual java.lang.StringBuilder.toString()java.lang.String
		// @57: invokestatic game.C_100181_cf.func_105695_a(java.lang.Throwable, java.lang.String)game.C_100170_cm
		// @5A: athrow
		// @5B: return
	}
	
	final boolean func_107333_d(int arg0)
	{
		// @00: iload_1
		// @01: ifeq @0F
		// @04: aconst_null
		// @05: checkcast java.lang.String
		// @08: putstatic java.lang.String game.C_100333_ij.field_107348_c
		// @0B: goto @0F
		// @0E: athrow
		// @0F: bipush -98 (0x9E)
		// @11: aload_0
		// @12: getfield int game.C_100333_ij.field_107353_j
		// @15: iconst_m1
		// @16: ixor
		// @17: if_icmpne @1F
		// @1A: iconst_1
		// @1B: goto @20
		// @1E: athrow
		// @1F: iconst_0
		// @20: ireturn
		// @21: astore_2
		// @22: aload_2
		// @23: new java.lang.StringBuilder
		// @26: dup
		// @27: invokespecial java.lang.StringBuilder.<init>()void
		// @2A: getstatic java.lang.String[] game.C_100333_ij.field_107357_z
		// @2D: bipush 23 (0x17)
		// @2F: aaload
		// @30: invokevirtual java.lang.StringBuilder.append(java.lang.String)java.lang.StringBuilder
		// @33: iload_1
		// @34: invokevirtual java.lang.StringBuilder.append(int)java.lang.StringBuilder
		// @37: bipush 41 (0x29)
		// @39: invokevirtual java.lang.StringBuilder.append(char)java.lang.StringBuilder
		// @3C: invokevirtual java.lang.StringBuilder.toString()java.lang.String
		// @3F: invokestatic game.C_100181_cf.func_105695_a(java.lang.Throwable, java.lang.String)game.C_100170_cm
		// @42: athrow
	}
	
	public static void func_107327_b(int arg0)
	{
		// @00: aconst_null
		// @01: putstatic java.lang.String[] game.C_100333_ij.field_107349_a
		// @04: iload_0
		// @05: sipush -22698 (0xA756)
		// @08: if_icmpeq @16
		// @0B: aconst_null
		// @0C: checkcast java.lang.String[]
		// @0F: putstatic java.lang.String[] game.C_100333_ij.field_107349_a
		// @12: goto @16
		// @15: athrow
		// @16: aconst_null
		// @17: putstatic java.lang.String[] game.C_100333_ij.field_107354_k
		// @1A: aconst_null
		// @1B: putstatic java.lang.String game.C_100333_ij.field_107348_c
		// @1E: aconst_null
		// @1F: putstatic int[] game.C_100333_ij.field_107345_d
		// @22: goto @47
		// @25: astore_1
		// @26: aload_1
		// @27: new java.lang.StringBuilder
		// @2A: dup
		// @2B: invokespecial java.lang.StringBuilder.<init>()void
		// @2E: getstatic java.lang.String[] game.C_100333_ij.field_107357_z
		// @31: bipush 7 (0x07)
		// @33: aaload
		// @34: invokevirtual java.lang.StringBuilder.append(java.lang.String)java.lang.StringBuilder
		// @37: iload_0
		// @38: invokevirtual java.lang.StringBuilder.append(int)java.lang.StringBuilder
		// @3B: bipush 41 (0x29)
		// @3D: invokevirtual java.lang.StringBuilder.append(char)java.lang.StringBuilder
		// @40: invokevirtual java.lang.StringBuilder.toString()java.lang.String
		// @43: invokestatic game.C_100181_cf.func_105695_a(java.lang.Throwable, java.lang.String)game.C_100170_cm
		// @46: athrow
		// @47: return
	}
	
	final void func_107335_a(int arg0, int arg1, int arg2)
	{
		// @000: aload_0
		// @001: getfield int game.C_100333_ij.field_107344_g
		// @004: iload_3
		// @005: if_icmple @00C
		// @008: goto @014
		// @00B: athrow
		// @00C: new java.lang.IllegalArgumentException
		// @00F: dup
		// @010: invokespecial java.lang.IllegalArgumentException.<init>()void
		// @013: athrow
		// @014: iload_2
		// @015: aload_0
		// @016: getfield int game.C_100333_ij.field_107344_g
		// @019: if_icmpge @020
		// @01C: goto @028
		// @01F: athrow
		// @020: new java.lang.IllegalArgumentException
		// @023: dup
		// @024: invokespecial java.lang.IllegalArgumentException.<init>()void
		// @027: athrow
		// @028: aload_0
		// @029: iconst_0
		// @02A: putfield int game.C_100333_ij.field_107353_j
		// @02D: aload_0
		// @02E: iconst_0
		// @02F: putfield boolean game.C_100333_ij.field_107356_i
		// @032: aload_0
		// @033: iconst_0
		// @034: putfield int game.C_100333_ij.field_107343_f
		// @037: iconst_0
		// @038: getstatic int game.C_100102_w.field_104636_c
		// @03B: if_icmpeq @061
		// @03E: aload_0
		// @03F: getstatic int game.C_100102_w.field_104636_c
		// @042: putfield int game.C_100333_ij.field_107355_h
		// @045: aload_0
		// @046: getstatic int game.C_100187_rk.field_100828_m
		// @049: putfield int game.C_100333_ij.field_107351_l
		// @04C: aload_0
		// @04D: iconst_1
		// @04E: putfield boolean game.C_100333_ij.field_107352_m
		// @051: aload_0
		// @052: iload_2
		// @053: putfield int game.C_100333_ij.field_107347_b
		// @056: aload_0
		// @057: getstatic int game.C_100102_w.field_104636_c
		// @05A: putfield int game.C_100333_ij.field_107343_f
		// @05D: goto @061
		// @060: athrow
		// @061: iconst_0
		// @062: aload_0
		// @063: getfield int game.C_100333_ij.field_107355_h
		// @066: if_icmpeq @096
		// @069: getstatic int game.C_100083_c.field_103171_R
		// @06C: ifeq @096
		// @06F: goto @073
		// @072: athrow
		// @073: iconst_m1
		// @074: aload_0
		// @075: getfield int game.C_100333_ij.field_107351_l
		// @078: iconst_m1
		// @079: ixor
		// @07A: if_icmpgt @08C
		// @07D: goto @081
		// @080: athrow
		// @081: aload_0
		// @082: getstatic int game.C_100233_oa.field_106247_m
		// @085: putfield int game.C_100333_ij.field_107351_l
		// @088: goto @08C
		// @08B: athrow
		// @08C: aload_0
		// @08D: dup
		// @08E: getfield int game.C_100333_ij.field_107351_l
		// @091: iconst_1
		// @092: isub
		// @093: putfield int game.C_100333_ij.field_107351_l
		// @096: iconst_0
		// @097: getstatic int game.C_100102_w.field_104636_c
		// @09A: if_icmpne @0B1
		// @09D: iconst_0
		// @09E: getstatic int game.C_100083_c.field_103171_R
		// @0A1: if_icmpeq @0AC
		// @0A4: goto @0A8
		// @0A7: athrow
		// @0A8: goto @0B1
		// @0AB: athrow
		// @0AC: aload_0
		// @0AD: iconst_0
		// @0AE: putfield int game.C_100333_ij.field_107355_h
		// @0B1: iload_1
		// @0B2: ifge @0B6
		// @0B5: return
		// @0B6: iconst_m1
		// @0B7: aload_0
		// @0B8: getfield int game.C_100333_ij.field_107355_h
		// @0BB: iconst_m1
		// @0BC: ixor
		// @0BD: if_icmpne @11D
		// @0C0: aload_0
		// @0C1: getfield boolean game.C_100333_ij.field_107352_m
		// @0C4: ifne @0D5
		// @0C7: goto @0CB
		// @0CA: athrow
		// @0CB: getstatic boolean game.C_100240_oj.field_106322_j
		// @0CE: ifeq @11D
		// @0D1: goto @0D5
		// @0D4: athrow
		// @0D5: iconst_m1
		// @0D6: iload_3
		// @0D7: iconst_m1
		// @0D8: ixor
		// @0D9: if_icmpge @0FA
		// @0DC: goto @0E0
		// @0DF: athrow
		// @0E0: aload_0
		// @0E1: getfield boolean game.C_100333_ij.field_107352_m
		// @0E4: ifeq @11D
		// @0E7: goto @0EB
		// @0EA: athrow
		// @0EB: aload_0
		// @0EC: iconst_m1
		// @0ED: putfield int game.C_100333_ij.field_107347_b
		// @0F0: getstatic int game.SteelSentinels.field_105275_O
		// @0F3: ifeq @11D
		// @0F6: goto @0FA
		// @0F9: athrow
		// @0FA: aload_0
		// @0FB: getfield int game.C_100333_ij.field_107347_b
		// @0FE: iconst_m1
		// @0FF: ixor
		// @100: iload_3
		// @101: iconst_m1
		// @102: ixor
		// @103: if_icmpeq @113
		// @106: goto @10A
		// @109: athrow
		// @10A: aload_0
		// @10B: iconst_1
		// @10C: putfield boolean game.C_100333_ij.field_107356_i
		// @10F: goto @113
		// @112: athrow
		// @113: aload_0
		// @114: iload_3
		// @115: putfield int game.C_100333_ij.field_107347_b
		// @118: aload_0
		// @119: iconst_1
		// @11A: putfield boolean game.C_100333_ij.field_107352_m
		// @11D: goto @156
		// @120: astore #4
		// @122: aload #4
		// @124: new java.lang.StringBuilder
		// @127: dup
		// @128: invokespecial java.lang.StringBuilder.<init>()void
		// @12B: getstatic java.lang.String[] game.C_100333_ij.field_107357_z
		// @12E: bipush 19 (0x13)
		// @130: aaload
		// @131: invokevirtual java.lang.StringBuilder.append(java.lang.String)java.lang.StringBuilder
		// @134: iload_1
		// @135: invokevirtual java.lang.StringBuilder.append(int)java.lang.StringBuilder
		// @138: bipush 44 (0x2C)
		// @13A: invokevirtual java.lang.StringBuilder.append(char)java.lang.StringBuilder
		// @13D: iload_2
		// @13E: invokevirtual java.lang.StringBuilder.append(int)java.lang.StringBuilder
		// @141: bipush 44 (0x2C)
		// @143: invokevirtual java.lang.StringBuilder.append(char)java.lang.StringBuilder
		// @146: iload_3
		// @147: invokevirtual java.lang.StringBuilder.append(int)java.lang.StringBuilder
		// @14A: bipush 41 (0x29)
		// @14C: invokevirtual java.lang.StringBuilder.append(char)java.lang.StringBuilder
		// @14F: invokevirtual java.lang.StringBuilder.toString()java.lang.String
		// @152: invokestatic game.C_100181_cf.func_105695_a(java.lang.Throwable, java.lang.String)game.C_100170_cm
		// @155: athrow
		// @156: return
	}
	
	final boolean func_107337_a(boolean arg0)
	{
		// @00: iload_1
		// @01: ifeq @0E
		// @04: aload_0
		// @05: bipush -50 (0xCE)
		// @07: invokevirtual game.C_100333_ij.func_107334_b(byte)void
		// @0A: goto @0E
		// @0D: athrow
		// @0E: aload_0
		// @0F: getfield int game.C_100333_ij.field_107353_j
		// @12: bipush 103 (0x67)
		// @14: if_icmpne @1C
		// @17: iconst_1
		// @18: goto @1D
		// @1B: athrow
		// @1C: iconst_0
		// @1D: ireturn
		// @1E: astore_2
		// @1F: aload_2
		// @20: new java.lang.StringBuilder
		// @23: dup
		// @24: invokespecial java.lang.StringBuilder.<init>()void
		// @27: getstatic java.lang.String[] game.C_100333_ij.field_107357_z
		// @2A: bipush 16 (0x10)
		// @2C: aaload
		// @2D: invokevirtual java.lang.StringBuilder.append(java.lang.String)java.lang.StringBuilder
		// @30: iload_1
		// @31: invokevirtual java.lang.StringBuilder.append(boolean)java.lang.StringBuilder
		// @34: bipush 41 (0x29)
		// @36: invokevirtual java.lang.StringBuilder.append(char)java.lang.StringBuilder
		// @39: invokevirtual java.lang.StringBuilder.toString()java.lang.String
		// @3C: invokestatic game.C_100181_cf.func_105695_a(java.lang.Throwable, java.lang.String)game.C_100170_cm
		// @3F: athrow
	}
	
	static final void func_107323_a(byte arg0, C_100201_qj arg1, Object arg2)
	{
		// @00: getstatic int game.SteelSentinels.field_105275_O
		// @03: istore #4
		// @05: aconst_null
		// @06: aload_1
		// @07: getfield java.awt.EventQueue game.C_100201_qj.field_105871_g
		// @0A: if_acmpne @0E
		// @0D: return
		// @0E: iconst_0
		// @0F: istore_3
		// @10: iload_3
		// @11: bipush 50 (0x32)
		// @13: if_icmpge @3E
		// @16: aconst_null
		// @17: iload #4
		// @19: ifne @69
		// @1C: aload_1
		// @1D: getfield java.awt.EventQueue game.C_100201_qj.field_105871_g
		// @20: invokevirtual java.awt.EventQueue.peekEvent()java.awt.AWTEvent
		// @23: if_acmpeq @3E
		// @26: goto @2A
		// @29: athrow
		// @2A: lconst_1
		// @2B: iload_0
		// @2C: bipush 20 (0x14)
		// @2E: ixor
		// @2F: invokestatic game.C_100138_bo.func_100396_a(long, int)void
		// @32: iinc #3 +1
		// @35: iload #4
		// @37: ifeq @10
		// @3A: goto @3E
		// @3D: athrow
		// @3E: aload_2
		// @3F: ifnull @5E
		// @42: aload_1
		// @43: getfield java.awt.EventQueue game.C_100201_qj.field_105871_g
		// @46: new java.awt.event.ActionEvent
		// @49: dup
		// @4A: aload_2
		// @4B: sipush 1001 (0x03E9)
		// @4E: getstatic java.lang.String[] game.C_100333_ij.field_107357_z
		// @51: bipush 18 (0x12)
		// @53: aaload
		// @54: invokespecial java.awt.event.ActionEvent.<init>(java.lang.Object, int, java.lang.String)void
		// @57: invokevirtual java.awt.EventQueue.postEvent(java.awt.AWTEvent)void
		// @5A: goto @5E
		// @5D: athrow
		// @5E: iload_0
		// @5F: bipush -108 (0x94)
		// @61: if_icmpeq @6F
		// @64: aconst_null
		// @65: goto @69
		// @68: athrow
		// @69: checkcast int[]
		// @6C: putstatic int[] game.C_100333_ij.field_107345_d
		// @6F: goto @73
		// @72: astore_3
		// @73: goto @D0
		// @76: astore_3
		// @77: aload_3
		// @78: new java.lang.StringBuilder
		// @7B: dup
		// @7C: invokespecial java.lang.StringBuilder.<init>()void
		// @7F: getstatic java.lang.String[] game.C_100333_ij.field_107357_z
		// @82: bipush 17 (0x11)
		// @84: aaload
		// @85: invokevirtual java.lang.StringBuilder.append(java.lang.String)java.lang.StringBuilder
		// @88: iload_0
		// @89: invokevirtual java.lang.StringBuilder.append(int)java.lang.StringBuilder
		// @8C: bipush 44 (0x2C)
		// @8E: invokevirtual java.lang.StringBuilder.append(char)java.lang.StringBuilder
		// @91: aload_1
		// @92: ifnull @9F
		// @95: getstatic java.lang.String[] game.C_100333_ij.field_107357_z
		// @98: bipush 13 (0x0D)
		// @9A: aaload
		// @9B: goto @A5
		// @9E: athrow
		// @9F: getstatic java.lang.String[] game.C_100333_ij.field_107357_z
		// @A2: bipush 11 (0x0B)
		// @A4: aaload
		// @A5: invokevirtual java.lang.StringBuilder.append(java.lang.String)java.lang.StringBuilder
		// @A8: bipush 44 (0x2C)
		// @AA: invokevirtual java.lang.StringBuilder.append(char)java.lang.StringBuilder
		// @AD: aload_2
		// @AE: ifnull @BB
		// @B1: getstatic java.lang.String[] game.C_100333_ij.field_107357_z
		// @B4: bipush 13 (0x0D)
		// @B6: aaload
		// @B7: goto @C1
		// @BA: athrow
		// @BB: getstatic java.lang.String[] game.C_100333_ij.field_107357_z
		// @BE: bipush 11 (0x0B)
		// @C0: aaload
		// @C1: invokevirtual java.lang.StringBuilder.append(java.lang.String)java.lang.StringBuilder
		// @C4: bipush 41 (0x29)
		// @C6: invokevirtual java.lang.StringBuilder.append(char)java.lang.StringBuilder
		// @C9: invokevirtual java.lang.StringBuilder.toString()java.lang.String
		// @CC: invokestatic game.C_100181_cf.func_105695_a(java.lang.Throwable, java.lang.String)game.C_100170_cm
		// @CF: athrow
		// @D0: return
	}
	
	static final void func_107325_a(byte arg0, int arg1, int arg2)
	{
		// @000: getstatic int game.SteelSentinels.field_105275_O
		// @003: istore #8
		// @005: iconst_m1
		// @006: getstatic int game.C_100015_wh.field_103783_e
		// @009: iconst_m1
		// @00A: ixor
		// @00B: if_icmpge @00F
		// @00E: return
		// @00F: sipush -135 (0xFF79)
		// @012: iload_1
		// @013: iadd
		// @014: istore_3
		// @015: iload_2
		// @016: bipush -35 (0xDD)
		// @018: iadd
		// @019: istore #4
		// @01B: sipush 256 (0x0100)
		// @01E: istore #5
		// @020: getstatic int game.C_100015_wh.field_103783_e
		// @023: bipush 75 (0x4B)
		// @025: if_icmpge @033
		// @028: getstatic int game.C_100015_wh.field_103783_e
		// @02B: ldc -2074591768 (0x84583de8)
		// @02D: ishl
		// @02E: bipush 75 (0x4B)
		// @030: idiv
		// @031: istore #5
		// @033: getstatic int game.C_100015_wh.field_103783_e
		// @036: sipush 200 (0x00C8)
		// @039: if_icmple @04C
		// @03C: getstatic int game.C_100015_wh.field_103783_e
		// @03F: ineg
		// @040: sipush 250 (0x00FA)
		// @043: iadd
		// @044: ldc -95011480 (0xfa563d68)
		// @046: ishl
		// @047: bipush 50 (0x32)
		// @049: idiv
		// @04A: istore #5
		// @04C: getstatic game.C_100037_wb game.C_100298_ke.field_103220_X
		// @04F: bipush -4 (0xFC)
		// @051: invokestatic game.C_100138_bo.func_100398_a(game.C_100037_wb, int)void
		// @054: invokestatic game.C_100070_dn.func_104363_a()void
		// @057: invokestatic game.C_100196_rb.func_105792_b()void
		// @05A: bipush 112 (0x70)
		// @05C: invokestatic game.C_100315_la.func_107172_a(byte)void
		// @05F: sipush -257 (0xFEFF)
		// @062: iload #5
		// @064: iconst_m1
		// @065: ixor
		// @066: if_icmplt @06D
		// @069: goto @080
		// @06C: athrow
		// @06D: iconst_0
		// @06E: iconst_0
		// @06F: getstatic int game.C_100196_rb.field_105819_e
		// @072: getstatic int game.C_100196_rb.field_105821_c
		// @075: iconst_0
		// @076: sipush 256 (0x0100)
		// @079: iload #5
		// @07B: ineg
		// @07C: iadd
		// @07D: invokestatic game.C_100196_rb.func_105804_g(int, int, int, int, int, int)void
		// @080: bipush -77 (0xB3)
		// @082: invokestatic game.C_100200_ba.func_105842_a(byte)void
		// @085: getstatic int game.C_100015_wh.field_103783_e
		// @088: iconst_m1
		// @089: ixor
		// @08A: sipush -151 (0xFF69)
		// @08D: if_icmpgt @0AA
		// @090: getstatic game.C_100037_wb game.C_100149_bi.field_105156_b
		// @093: iload_3
		// @094: bipush -15 (0xF1)
		// @096: isub
		// @097: bipush 10 (0x0A)
		// @099: iload #4
		// @09B: iadd
		// @09C: iload #5
		// @09E: invokevirtual game.C_100037_wb.func_102376_d(int, int, int)void
		// @0A1: iload #8
		// @0A3: ifeq @0B7
		// @0A6: goto @0AA
		// @0A9: athrow
		// @0AA: getstatic game.C_100037_wb game.C_100298_ke.field_103220_X
		// @0AD: iload_3
		// @0AE: iload #4
		// @0B0: invokevirtual game.C_100037_wb.func_102360_g(int, int)void
		// @0B3: goto @0B7
		// @0B6: athrow
		// @0B7: iload_0
		// @0B8: bipush 125 (0x7D)
		// @0BA: if_icmpeq @0C8
		// @0BD: aconst_null
		// @0BE: checkcast java.lang.String
		// @0C1: putstatic java.lang.String game.C_100333_ij.field_107348_c
		// @0C4: goto @0C8
		// @0C7: athrow
		// @0C8: getstatic int game.C_100015_wh.field_103783_e
		// @0CB: bipush -125 (0x83)
		// @0CD: iadd
		// @0CE: istore #6
		// @0D0: iload #6
		// @0D2: ifle @144
		// @0D5: bipush -51 (0xCD)
		// @0D7: iload #6
		// @0D9: iconst_m1
		// @0DA: ixor
		// @0DB: if_icmpge @144
		// @0DE: goto @0E2
		// @0E1: athrow
		// @0E2: iload #6
		// @0E4: iconst_m1
		// @0E5: ixor
		// @0E6: bipush -21 (0xEB)
		// @0E8: if_icmple @10A
		// @0EB: goto @0EF
		// @0EE: athrow
		// @0EF: iload #6
		// @0F1: sipush 256 (0x0100)
		// @0F4: imul
		// @0F5: bipush 20 (0x14)
		// @0F7: idiv
		// @0F8: istore #7
		// @0FA: getstatic game.C_100037_wb game.C_100083_c.field_103170_S
		// @0FD: iload_3
		// @0FE: iload #4
		// @100: iload #7
		// @102: invokevirtual game.C_100037_wb.func_102367_c(int, int, int)void
		// @105: iload #8
		// @107: ifeq @144
		// @10A: bipush 30 (0x1E)
		// @10C: iload #6
		// @10E: if_icmpgt @134
		// @111: goto @115
		// @114: athrow
		// @115: sipush 256 (0x0100)
		// @118: iload #6
		// @11A: ineg
		// @11B: bipush 50 (0x32)
		// @11D: iadd
		// @11E: imul
		// @11F: bipush 20 (0x14)
		// @121: idiv
		// @122: istore #7
		// @124: getstatic game.C_100037_wb game.C_100083_c.field_103170_S
		// @127: iload_3
		// @128: iload #4
		// @12A: iload #7
		// @12C: invokevirtual game.C_100037_wb.func_102367_c(int, int, int)void
		// @12F: iload #8
		// @131: ifeq @144
		// @134: getstatic game.C_100037_wb game.C_100083_c.field_103170_S
		// @137: iload_3
		// @138: iload #4
		// @13A: sipush 256 (0x0100)
		// @13D: invokevirtual game.C_100037_wb.func_102367_c(int, int, int)void
		// @140: goto @144
		// @143: athrow
		// @144: sipush -140 (0xFF74)
		// @147: getstatic int game.C_100015_wh.field_103783_e
		// @14A: iadd
		// @14B: istore #6
		// @14D: iconst_m1
		// @14E: iload #6
		// @150: iconst_m1
		// @151: ixor
		// @152: if_icmpgt @159
		// @155: goto @18D
		// @158: athrow
		// @159: sipush 256 (0x0100)
		// @15C: istore #7
		// @15E: iload #6
		// @160: iconst_m1
		// @161: ixor
		// @162: bipush -21 (0xEB)
		// @164: if_icmpgt @16B
		// @167: goto @176
		// @16A: athrow
		// @16B: sipush 256 (0x0100)
		// @16E: iload #6
		// @170: imul
		// @171: bipush 20 (0x14)
		// @173: idiv
		// @174: istore #7
		// @176: getstatic game.C_100037_wb game.C_100217_ao.field_106036_e
		// @179: iload_3
		// @17A: bipush -15 (0xF1)
		// @17C: isub
		// @17D: bipush 10 (0x0A)
		// @17F: iload #4
		// @181: iadd
		// @182: iload #7
		// @184: iload #5
		// @186: imul
		// @187: ldc 43327656 (0x29520a8)
		// @189: ishr
		// @18A: invokevirtual game.C_100037_wb.func_102376_d(int, int, int)void
		// @18D: goto @1C4
		// @190: astore_3
		// @191: aload_3
		// @192: new java.lang.StringBuilder
		// @195: dup
		// @196: invokespecial java.lang.StringBuilder.<init>()void
		// @199: getstatic java.lang.String[] game.C_100333_ij.field_107357_z
		// @19C: bipush 6 (0x06)
		// @19E: aaload
		// @19F: invokevirtual java.lang.StringBuilder.append(java.lang.String)java.lang.StringBuilder
		// @1A2: iload_0
		// @1A3: invokevirtual java.lang.StringBuilder.append(int)java.lang.StringBuilder
		// @1A6: bipush 44 (0x2C)
		// @1A8: invokevirtual java.lang.StringBuilder.append(char)java.lang.StringBuilder
		// @1AB: iload_1
		// @1AC: invokevirtual java.lang.StringBuilder.append(int)java.lang.StringBuilder
		// @1AF: bipush 44 (0x2C)
		// @1B1: invokevirtual java.lang.StringBuilder.append(char)java.lang.StringBuilder
		// @1B4: iload_2
		// @1B5: invokevirtual java.lang.StringBuilder.append(int)java.lang.StringBuilder
		// @1B8: bipush 41 (0x29)
		// @1BA: invokevirtual java.lang.StringBuilder.append(char)java.lang.StringBuilder
		// @1BD: invokevirtual java.lang.StringBuilder.toString()java.lang.String
		// @1C0: invokestatic game.C_100181_cf.func_105695_a(java.lang.Throwable, java.lang.String)game.C_100170_cm
		// @1C3: athrow
		// @1C4: return
	}
	
	final void func_107332_a(byte arg0, int arg1)
	{
		// @000: aload_0
		// @001: iconst_0
		// @002: putfield int game.C_100333_ij.field_107353_j
		// @005: bipush 105 (0x69)
		// @007: iload_1
		// @008: bipush -49 (0xCF)
		// @00A: isub
		// @00B: bipush 40 (0x28)
		// @00D: idiv
		// @00E: irem
		// @00F: istore_3
		// @010: aload_0
		// @011: iconst_0
		// @012: putfield int game.C_100333_ij.field_107343_f
		// @015: aload_0
		// @016: iconst_0
		// @017: putfield boolean game.C_100333_ij.field_107356_i
		// @01A: aload_0
		// @01B: getfield int game.C_100333_ij.field_107355_h
		// @01E: ifne @05A
		// @021: bipush -97 (0x9F)
		// @023: getstatic int game.C_100293_kj.field_106890_c
		// @026: iconst_m1
		// @027: ixor
		// @028: if_icmpeq @033
		// @02B: goto @02F
		// @02E: athrow
		// @02F: goto @05A
		// @032: athrow
		// @033: aload_0
		// @034: getfield int game.C_100333_ij.field_107347_b
		// @037: ifgt @046
		// @03A: aload_0
		// @03B: aload_0
		// @03C: getfield int game.C_100333_ij.field_107344_g
		// @03F: putfield int game.C_100333_ij.field_107347_b
		// @042: goto @046
		// @045: athrow
		// @046: aload_0
		// @047: dup
		// @048: getfield int game.C_100333_ij.field_107347_b
		// @04B: iconst_1
		// @04C: isub
		// @04D: putfield int game.C_100333_ij.field_107347_b
		// @050: aload_0
		// @051: iconst_1
		// @052: putfield boolean game.C_100333_ij.field_107356_i
		// @055: aload_0
		// @056: iconst_0
		// @057: putfield boolean game.C_100333_ij.field_107352_m
		// @05A: iconst_m1
		// @05B: aload_0
		// @05C: getfield int game.C_100333_ij.field_107355_h
		// @05F: iconst_m1
		// @060: ixor
		// @061: if_icmpne @06F
		// @064: aload_0
		// @065: getstatic int game.C_100293_kj.field_106890_c
		// @068: putfield int game.C_100333_ij.field_107353_j
		// @06B: goto @06F
		// @06E: athrow
		// @06F: aload_0
		// @070: getfield int game.C_100333_ij.field_107355_h
		// @073: iconst_m1
		// @074: ixor
		// @075: iconst_m1
		// @076: if_icmpne @0B7
		// @079: bipush -98 (0x9E)
		// @07B: getstatic int game.C_100293_kj.field_106890_c
		// @07E: iconst_m1
		// @07F: ixor
		// @080: if_icmpne @0B7
		// @083: goto @087
		// @086: athrow
		// @087: aload_0
		// @088: dup
		// @089: getfield int game.C_100333_ij.field_107347_b
		// @08C: iconst_1
		// @08D: iadd
		// @08E: putfield int game.C_100333_ij.field_107347_b
		// @091: aload_0
		// @092: getfield int game.C_100333_ij.field_107344_g
		// @095: iconst_m1
		// @096: ixor
		// @097: aload_0
		// @098: getfield int game.C_100333_ij.field_107347_b
		// @09B: iconst_m1
		// @09C: ixor
		// @09D: if_icmplt @0AD
		// @0A0: goto @0A4
		// @0A3: athrow
		// @0A4: aload_0
		// @0A5: iconst_0
		// @0A6: putfield int game.C_100333_ij.field_107347_b
		// @0A9: goto @0AD
		// @0AC: athrow
		// @0AD: aload_0
		// @0AE: iconst_1
		// @0AF: putfield boolean game.C_100333_ij.field_107356_i
		// @0B2: aload_0
		// @0B3: iconst_0
		// @0B4: putfield boolean game.C_100333_ij.field_107352_m
		// @0B7: iconst_m1
		// @0B8: aload_0
		// @0B9: getfield int game.C_100333_ij.field_107355_h
		// @0BC: iconst_m1
		// @0BD: ixor
		// @0BE: if_icmpne @0F7
		// @0C1: getstatic int game.C_100293_kj.field_106890_c
		// @0C4: bipush 98 (0x62)
		// @0C6: if_icmpeq @0DD
		// @0C9: goto @0CD
		// @0CC: athrow
		// @0CD: getstatic int game.C_100293_kj.field_106890_c
		// @0D0: bipush 99 (0x63)
		// @0D2: if_icmpeq @0DD
		// @0D5: goto @0D9
		// @0D8: athrow
		// @0D9: goto @0F7
		// @0DC: athrow
		// @0DD: aload_0
		// @0DE: iconst_1
		// @0DF: putfield boolean game.C_100333_ij.field_107356_i
		// @0E2: aload_0
		// @0E3: iconst_0
		// @0E4: putfield boolean game.C_100333_ij.field_107352_m
		// @0E7: aload_0
		// @0E8: getfield int game.C_100333_ij.field_107347_b
		// @0EB: iflt @0F2
		// @0EE: goto @0F7
		// @0F1: athrow
		// @0F2: aload_0
		// @0F3: iload_2
		// @0F4: putfield int game.C_100333_ij.field_107347_b
		// @0F7: goto @125
		// @0FA: astore_3
		// @0FB: aload_3
		// @0FC: new java.lang.StringBuilder
		// @0FF: dup
		// @100: invokespecial java.lang.StringBuilder.<init>()void
		// @103: getstatic java.lang.String[] game.C_100333_ij.field_107357_z
		// @106: bipush 15 (0x0F)
		// @108: aaload
		// @109: invokevirtual java.lang.StringBuilder.append(java.lang.String)java.lang.StringBuilder
		// @10C: iload_1
		// @10D: invokevirtual java.lang.StringBuilder.append(int)java.lang.StringBuilder
		// @110: bipush 44 (0x2C)
		// @112: invokevirtual java.lang.StringBuilder.append(char)java.lang.StringBuilder
		// @115: iload_2
		// @116: invokevirtual java.lang.StringBuilder.append(int)java.lang.StringBuilder
		// @119: bipush 41 (0x29)
		// @11B: invokevirtual java.lang.StringBuilder.append(char)java.lang.StringBuilder
		// @11E: invokevirtual java.lang.StringBuilder.toString()java.lang.String
		// @121: invokestatic game.C_100181_cf.func_105695_a(java.lang.Throwable, java.lang.String)game.C_100170_cm
		// @124: athrow
		// @125: return
	}
	
	static final C_100037_wb[] func_107331_b(int arg0, int arg1, int arg2)
	{
		// @00: iload_2
		// @01: iconst_m1
		// @02: if_icmpeq @0A
		// @05: aconst_null
		// @06: checkcast game.C_100037_wb[]
		// @09: areturn
		// @0A: iconst_1
		// @0B: iload_2
		// @0C: iconst_0
		// @0D: ixor
		// @0E: iload_0
		// @0F: iload_1
		// @10: invokestatic game.C_100024_hd.func_102990_a(int, int, int, int)game.C_100037_wb[]
		// @13: areturn
		// @14: astore_3
		// @15: aload_3
		// @16: new java.lang.StringBuilder
		// @19: dup
		// @1A: invokespecial java.lang.StringBuilder.<init>()void
		// @1D: getstatic java.lang.String[] game.C_100333_ij.field_107357_z
		// @20: bipush 21 (0x15)
		// @22: aaload
		// @23: invokevirtual java.lang.StringBuilder.append(java.lang.String)java.lang.StringBuilder
		// @26: iload_0
		// @27: invokevirtual java.lang.StringBuilder.append(int)java.lang.StringBuilder
		// @2A: bipush 44 (0x2C)
		// @2C: invokevirtual java.lang.StringBuilder.append(char)java.lang.StringBuilder
		// @2F: iload_1
		// @30: invokevirtual java.lang.StringBuilder.append(int)java.lang.StringBuilder
		// @33: bipush 44 (0x2C)
		// @35: invokevirtual java.lang.StringBuilder.append(char)java.lang.StringBuilder
		// @38: iload_2
		// @39: invokevirtual java.lang.StringBuilder.append(int)java.lang.StringBuilder
		// @3C: bipush 41 (0x29)
		// @3E: invokevirtual java.lang.StringBuilder.append(char)java.lang.StringBuilder
		// @41: invokevirtual java.lang.StringBuilder.toString()java.lang.String
		// @44: invokestatic game.C_100181_cf.func_105695_a(java.lang.Throwable, java.lang.String)game.C_100170_cm
		// @47: athrow
	}
	
	C_100333_ij(int arg0)
	{
		// @00: aload_0
		// @01: invokespecial java.lang.Object.<init>()void
		// @04: aload_0
		// @05: iconst_0
		// @06: putfield boolean game.C_100333_ij.field_107352_m
		// @09: aload_0
		// @0A: iconst_0
		// @0B: putfield int game.C_100333_ij.field_107347_b
		// @0E: aload_0
		// @0F: iload_1
		// @10: putfield int game.C_100333_ij.field_107344_g
		// @13: goto @37
		// @16: astore_2
		// @17: aload_2
		// @18: new java.lang.StringBuilder
		// @1B: dup
		// @1C: invokespecial java.lang.StringBuilder.<init>()void
		// @1F: getstatic java.lang.String[] game.C_100333_ij.field_107357_z
		// @22: iconst_2
		// @23: aaload
		// @24: invokevirtual java.lang.StringBuilder.append(java.lang.String)java.lang.StringBuilder
		// @27: iload_1
		// @28: invokevirtual java.lang.StringBuilder.append(int)java.lang.StringBuilder
		// @2B: bipush 41 (0x29)
		// @2D: invokevirtual java.lang.StringBuilder.append(char)java.lang.StringBuilder
		// @30: invokevirtual java.lang.StringBuilder.toString()java.lang.String
		// @33: invokestatic game.C_100181_cf.func_105695_a(java.lang.Throwable, java.lang.String)game.C_100170_cm
		// @36: athrow
		// @37: return
	}
	
	static
	{
		// @000: bipush 24 (0x18)
		// @002: anewarray java.lang.String
		// @005: dup
		// @006: iconst_0
		// @007: ldc "l\u0012\u0012~~"
		// @009: invokestatic game.C_100333_ij.func_107330_z(java.lang.String)char[]
		// @00C: invokestatic game.C_100333_ij.func_107329_z(char[])java.lang.String
		// @00F: aastore
		// @010: dup
		// @011: iconst_1
		// @012: ldc "l\u0012\u0012}~"
		// @014: invokestatic game.C_100333_ij.func_107330_z(java.lang.String)char[]
		// @017: invokestatic game.C_100333_ij.func_107329_z(char[])java.lang.String
		// @01A: aastore
		// @01B: dup
		// @01C: iconst_2
		// @01D: ldc "l\u0012\u0012\u0007?k\u0011H\u0005~"
		// @01F: invokestatic game.C_100333_ij.func_107330_z(java.lang.String)char[]
		// @022: invokestatic game.C_100333_ij.func_107329_z(char[])java.lang.String
		// @025: aastore
		// @026: dup
		// @027: iconst_3
		// @028: ldc "l\u0012\u0012x~"
		// @02A: invokestatic game.C_100333_ij.func_107330_z(java.lang.String)char[]
		// @02D: invokestatic game.C_100333_ij.func_107329_z(char[])java.lang.String
		// @030: aastore
		// @031: dup
		// @032: iconst_4
		// @033: ldc "f\u0017QV9k\rU"
		// @035: invokestatic game.C_100333_ij.func_107330_z(java.lang.String)char[]
		// @038: invokestatic game.C_100333_ij.func_107329_z(char[])java.lang.String
		// @03B: aastore
		// @03C: dup
		// @03D: iconst_5
		// @03E: ldc "%U\u001c"
		// @040: invokestatic game.C_100333_ij.func_107330_z(java.lang.String)char[]
		// @043: invokestatic game.C_100333_ij.func_107329_z(char[])java.lang.String
		// @046: aastore
		// @047: dup
		// @048: bipush 6 (0x06)
		// @04A: ldc "l\u0012\u0012|~"
		// @04C: invokestatic game.C_100333_ij.func_107330_z(java.lang.String)char[]
		// @04F: invokestatic game.C_100333_ij.func_107329_z(char[])java.lang.String
		// @052: aastore
		// @053: dup
		// @054: bipush 7 (0x07)
		// @056: ldc "l\u0012\u0012y~"
		// @058: invokestatic game.C_100333_ij.func_107330_z(java.lang.String)char[]
		// @05B: invokestatic game.C_100333_ij.func_107329_z(char[])java.lang.String
		// @05E: aastore
		// @05F: dup
		// @060: bipush 8 (0x08)
		// @062: ldc "l\u0012\u0012u~"
		// @064: invokestatic game.C_100333_ij.func_107330_z(java.lang.String)char[]
		// @067: invokestatic game.C_100333_ij.func_107329_z(char[])java.lang.String
		// @06A: aastore
		// @06B: dup
		// @06C: bipush 9 (0x09)
		// @06E: ldc "l\u0012\u0012k~"
		// @070: invokestatic game.C_100333_ij.func_107330_z(java.lang.String)char[]
		// @073: invokestatic game.C_100333_ij.func_107329_z(char[])java.lang.String
		// @076: aastore
		// @077: dup
		// @078: bipush 10 (0x0A)
		// @07A: ldc "l\u0012\u0012s~"
		// @07C: invokestatic game.C_100333_ij.func_107330_z(java.lang.String)char[]
		// @07F: invokestatic game.C_100333_ij.func_107329_z(char[])java.lang.String
		// @082: aastore
		// @083: dup
		// @084: bipush 11 (0x0B)
		// @086: ldc "k\rPW"
		// @088: invokestatic game.C_100333_ij.func_107330_z(java.lang.String)char[]
		// @08B: invokestatic game.C_100333_ij.func_107329_z(char[])java.lang.String
		// @08E: aastore
		// @08F: dup
		// @090: bipush 12 (0x0C)
		// @092: ldc "l\u0012\u0012r~"
		// @094: invokestatic game.C_100333_ij.func_107330_z(java.lang.String)char[]
		// @097: invokestatic game.C_100333_ij.func_107329_z(char[])java.lang.String
		// @09A: aastore
		// @09B: dup
		// @09C: bipush 13 (0x0D)
		// @09E: ldc "~V\u0012\u0015+"
		// @0A0: invokestatic game.C_100333_ij.func_107330_z(java.lang.String)char[]
		// @0A3: invokestatic game.C_100333_ij.func_107329_z(char[])java.lang.String
		// @0A6: aastore
		// @0A7: dup
		// @0A8: bipush 14 (0x0E)
		// @0AA: ldc "l\u0012\u0012i~"
		// @0AC: invokestatic game.C_100333_ij.func_107330_z(java.lang.String)char[]
		// @0AF: invokestatic game.C_100333_ij.func_107329_z(char[])java.lang.String
		// @0B2: aastore
		// @0B3: dup
		// @0B4: bipush 15 (0x0F)
		// @0B6: ldc "l\u0012\u0012v~"
		// @0B8: invokestatic game.C_100333_ij.func_107330_z(java.lang.String)char[]
		// @0BB: invokestatic game.C_100333_ij.func_107329_z(char[])java.lang.String
		// @0BE: aastore
		// @0BF: dup
		// @0C0: bipush 16 (0x10)
		// @0C2: ldc "l\u0012\u0012z~"
		// @0C4: invokestatic game.C_100333_ij.func_107330_z(java.lang.String)char[]
		// @0C7: invokestatic game.C_100333_ij.func_107329_z(char[])java.lang.String
		// @0CA: aastore
		// @0CB: dup
		// @0CC: bipush 17 (0x11)
		// @0CE: ldc "l\u0012\u0012j~"
		// @0D0: invokestatic game.C_100333_ij.func_107330_z(java.lang.String)char[]
		// @0D3: invokestatic game.C_100333_ij.func_107329_z(char[])java.lang.String
		// @0D6: aastore
		// @0D7: dup
		// @0D8: bipush 18 (0x12)
		// @0DA: ldc "a\rQV/"
		// @0DC: invokestatic game.C_100333_ij.func_107330_z(java.lang.String)char[]
		// @0DF: invokestatic game.C_100333_ij.func_107329_z(char[])java.lang.String
		// @0E2: aastore
		// @0E3: dup
		// @0E4: bipush 19 (0x13)
		// @0E6: ldc "l\u0012\u0012\u007f~"
		// @0E8: invokestatic game.C_100333_ij.func_107330_z(java.lang.String)char[]
		// @0EB: invokestatic game.C_100333_ij.func_107329_z(char[])java.lang.String
		// @0EE: aastore
		// @0EF: dup
		// @0F0: bipush 20 (0x14)
		// @0F2: ldc "l\u0012\u0012p~"
		// @0F4: invokestatic game.C_100333_ij.func_107330_z(java.lang.String)char[]
		// @0F7: invokestatic game.C_100333_ij.func_107329_z(char[])java.lang.String
		// @0FA: aastore
		// @0FB: dup
		// @0FC: bipush 21 (0x15)
		// @0FE: ldc "l\u0012\u0012q~"
		// @100: invokestatic game.C_100333_ij.func_107330_z(java.lang.String)char[]
		// @103: invokestatic game.C_100333_ij.func_107329_z(char[])java.lang.String
		// @106: aastore
		// @107: dup
		// @108: bipush 22 (0x16)
		// @10A: ldc "l\u0012\u0012t~"
		// @10C: invokestatic game.C_100333_ij.func_107330_z(java.lang.String)char[]
		// @10F: invokestatic game.C_100333_ij.func_107329_z(char[])java.lang.String
		// @112: aastore
		// @113: dup
		// @114: bipush 23 (0x17)
		// @116: ldc "l\u0012\u0012w~"
		// @118: invokestatic game.C_100333_ij.func_107330_z(java.lang.String)char[]
		// @11B: invokestatic game.C_100333_ij.func_107329_z(char[])java.lang.String
		// @11E: aastore
		// @11F: putstatic java.lang.String[] game.C_100333_ij.field_107357_z
		// @122: iconst_3
		// @123: anewarray java.lang.String
		// @126: dup
		// @127: iconst_0
		// @128: ldc "Q*}r\u0018L6{"
		// @12A: invokestatic game.C_100333_ij.func_107330_z(java.lang.String)char[]
		// @12D: invokestatic game.C_100333_ij.func_107329_z(char[])java.lang.String
		// @130: aastore
		// @131: dup
		// @132: iconst_1
		// @133: ldc "L4sw\u001fD6\u001cr\u0018F1x~\u0018Q"
		// @135: invokestatic game.C_100333_ij.func_107330_z(java.lang.String)char[]
		// @138: invokestatic game.C_100333_ij.func_107329_z(char[])java.lang.String
		// @13B: aastore
		// @13C: dup
		// @13D: iconst_2
		// @13E: ldc "V7pz\u0004L,y\u001b\u0001D*"
		// @140: invokestatic game.C_100333_ij.func_107330_z(java.lang.String)char[]
		// @143: invokestatic game.C_100333_ij.func_107329_z(char[])java.lang.String
		// @146: aastore
		// @147: putstatic java.lang.String[] game.C_100333_ij.field_107349_a
		// @14A: ldc "V\u001dRO?k\u001dP\u001b5j\u0016ZR1p\n]O?j\u0016\u001cR%%\u0016SLvp\u0016PT5n\u001dX\u0015jg\n\u0002|9%\u000cS\u001b\"m\u001d\u001c\u001cjf\u0017P\u0006f5\u001eZ]0;;SU0l\u001fII7q\u0011SUj*\u001bSWh\"XOX$`\u001dR\u001b\"jX_S9j\u000bY\u001b/j\rN\u001b%`\u0016HR8`\u0014\u0012"
		// @14C: invokestatic game.C_100333_ij.func_107330_z(java.lang.String)char[]
		// @14F: invokestatic game.C_100333_ij.func_107329_z(char[])java.lang.String
		// @152: putstatic java.lang.String game.C_100333_ij.field_107348_c
		// @155: bipush 34 (0x22)
		// @157: newarray int[]
		// @159: dup
		// @15A: iconst_0
		// @15B: bipush 38 (0x26)
		// @15D: iastore
		// @15E: dup
		// @15F: iconst_1
		// @160: bipush 38 (0x26)
		// @162: iastore
		// @163: dup
		// @164: iconst_2
		// @165: bipush 38 (0x26)
		// @167: iastore
		// @168: dup
		// @169: iconst_3
		// @16A: bipush 38 (0x26)
		// @16C: iastore
		// @16D: dup
		// @16E: iconst_4
		// @16F: bipush 38 (0x26)
		// @171: iastore
		// @172: dup
		// @173: iconst_5
		// @174: bipush 38 (0x26)
		// @176: iastore
		// @177: dup
		// @178: bipush 6 (0x06)
		// @17A: bipush 38 (0x26)
		// @17C: iastore
		// @17D: dup
		// @17E: bipush 7 (0x07)
		// @180: bipush 38 (0x26)
		// @182: iastore
		// @183: dup
		// @184: bipush 8 (0x08)
		// @186: bipush 38 (0x26)
		// @188: iastore
		// @189: dup
		// @18A: bipush 9 (0x09)
		// @18C: bipush 38 (0x26)
		// @18E: iastore
		// @18F: dup
		// @190: bipush 10 (0x0A)
		// @192: bipush 38 (0x26)
		// @194: iastore
		// @195: dup
		// @196: bipush 11 (0x0B)
		// @198: bipush 38 (0x26)
		// @19A: iastore
		// @19B: dup
		// @19C: bipush 12 (0x0C)
		// @19E: bipush 38 (0x26)
		// @1A0: iastore
		// @1A1: dup
		// @1A2: bipush 13 (0x0D)
		// @1A4: bipush 38 (0x26)
		// @1A6: iastore
		// @1A7: dup
		// @1A8: bipush 14 (0x0E)
		// @1AA: bipush 38 (0x26)
		// @1AC: iastore
		// @1AD: dup
		// @1AE: bipush 15 (0x0F)
		// @1B0: bipush 38 (0x26)
		// @1B2: iastore
		// @1B3: dup
		// @1B4: bipush 16 (0x10)
		// @1B6: bipush 38 (0x26)
		// @1B8: iastore
		// @1B9: dup
		// @1BA: bipush 17 (0x11)
		// @1BC: bipush 38 (0x26)
		// @1BE: iastore
		// @1BF: dup
		// @1C0: bipush 18 (0x12)
		// @1C2: bipush 38 (0x26)
		// @1C4: iastore
		// @1C5: dup
		// @1C6: bipush 19 (0x13)
		// @1C8: bipush 38 (0x26)
		// @1CA: iastore
		// @1CB: dup
		// @1CC: bipush 20 (0x14)
		// @1CE: bipush 38 (0x26)
		// @1D0: iastore
		// @1D1: dup
		// @1D2: bipush 21 (0x15)
		// @1D4: bipush 38 (0x26)
		// @1D6: iastore
		// @1D7: dup
		// @1D8: bipush 22 (0x16)
		// @1DA: bipush 38 (0x26)
		// @1DC: iastore
		// @1DD: dup
		// @1DE: bipush 23 (0x17)
		// @1E0: bipush 38 (0x26)
		// @1E2: iastore
		// @1E3: dup
		// @1E4: bipush 24 (0x18)
		// @1E6: bipush 38 (0x26)
		// @1E8: iastore
		// @1E9: dup
		// @1EA: bipush 25 (0x19)
		// @1EC: bipush 38 (0x26)
		// @1EE: iastore
		// @1EF: dup
		// @1F0: bipush 26 (0x1A)
		// @1F2: bipush 38 (0x26)
		// @1F4: iastore
		// @1F5: dup
		// @1F6: bipush 27 (0x1B)
		// @1F8: bipush 38 (0x26)
		// @1FA: iastore
		// @1FB: dup
		// @1FC: bipush 28 (0x1C)
		// @1FE: bipush 38 (0x26)
		// @200: iastore
		// @201: dup
		// @202: bipush 29 (0x1D)
		// @204: bipush 38 (0x26)
		// @206: iastore
		// @207: dup
		// @208: bipush 30 (0x1E)
		// @20A: iconst_m1
		// @20B: iastore
		// @20C: dup
		// @20D: bipush 31 (0x1F)
		// @20F: iconst_m1
		// @210: iastore
		// @211: dup
		// @212: bipush 32 (0x20)
		// @214: iconst_m1
		// @215: iastore
		// @216: dup
		// @217: bipush 33 (0x21)
		// @219: bipush 7 (0x07)
		// @21B: iastore
		// @21C: putstatic int[] game.C_100333_ij.field_107345_d
		// @21F: iconst_4
		// @220: anewarray java.lang.String
		// @223: dup
		// @224: iconst_0
		// @225: ldc "9\u001bSWk5H]\t0cFyU1l\u0016Y^$`\u001c\u001c\u0007?h\u001f\u0001\te;D\u0013X9iF"
		// @227: invokestatic game.C_100333_ij.func_107330_z(java.lang.String)char[]
		// @22A: invokestatic game.C_100333_ij.func_107329_z(char[])java.lang.String
		// @22D: aastore
		// @22E: dup
		// @22F: iconst_1
		// @230: ldc "9\u001bSWk5HX\u000bf5F\u007fT%qXHTv`\u0016[R8`\u001dN\u0001v9\u0011Q\\k7I\u0002\u0007s5F\u0000\u00145j\u0014\u0002"
		// @232: invokestatic game.C_100333_ij.func_107330_z(java.lang.String)char[]
		// @235: invokestatic game.C_100333_ij.func_107329_z(char[])java.lang.String
		// @238: aastore
		// @239: dup
		// @23A: iconst_2
		// @23B: ldc "9\u001bSWkaK\u000e\rd3F\u007fT%qXHTv`\u0016[R8`\u001dN\u0001v9\u0011Q\\k7J\u0002\u0007s5F\u0000\u00145j\u0014\u0002"
		// @23D: invokestatic game.C_100333_ij.func_107330_z(java.lang.String)char[]
		// @240: invokestatic game.C_100333_ij.func_107329_z(char[])java.lang.String
		// @243: aastore
		// @244: dup
		// @245: iconst_3
		// @246: ldc "9\u001bSWkaK\u000e\rd3FhT9%\u0019XM7k\u001bY_vq\u0017\u001c^8b\u0011R^3wD\u0013X9iF"
		// @248: invokestatic game.C_100333_ij.func_107330_z(java.lang.String)char[]
		// @24B: invokestatic game.C_100333_ij.func_107329_z(char[])java.lang.String
		// @24E: aastore
		// @24F: putstatic java.lang.String[] game.C_100333_ij.field_107354_k
		// @252: return
	}
	
	private static char[] func_107330_z(String arg0)
	{
		// @00: aload_0
		// @01: invokevirtual java.lang.String.toCharArray()char[]
		// @04: dup
		// @05: arraylength
		// @06: iconst_2
		// @07: if_icmpge @13
		// @0A: dup
		// @0B: iconst_0
		// @0C: dup2
		// @0D: caload
		// @0E: bipush 86 (0x56)
		// @10: ixor
		// @11: i2c
		// @12: castore
		// @13: areturn
	}
	
	private static String func_107329_z(char[] arg0)
	{
		// @00: aload_0
		// @01: dup
		// @02: arraylength
		// @03: swap
		// @04: iconst_0
		// @05: istore_1
		// @06: goto @4B
		// @09: dup
		// @0A: iload_1
		// @0B: dup2
		// @0C: caload
		// @0D: iload_1
		// @0E: iconst_5
		// @0F: irem
		// @10: tableswitch def: @43, for 0: @30, for 1: @34, for 2: @39, for 3: @3E
		// @30: iconst_5
		// @31: goto @45
		// @34: bipush 120 (0x78)
		// @36: goto @45
		// @39: bipush 60 (0x3C)
		// @3B: goto @45
		// @3E: bipush 59 (0x3B)
		// @40: goto @45
		// @43: bipush 86 (0x56)
		// @45: ixor
		// @46: i2c
		// @47: castore
		// @48: iinc #1 +1
		// @4B: swap
		// @4C: dup_x1
		// @4D: iload_1
		// @4E: if_icmpgt @09
		// @51: new java.lang.String
		// @54: dup_x1
		// @55: swap
		// @56: invokespecial java.lang.String.<init>(char[])void
		// @59: invokevirtual java.lang.String.intern()java.lang.String
		// @5C: areturn
	}
}
