package game;

final class C_100166_sg
{
	static String field_105468_a;
	static int field_105471_i;
	static C_100256_pk field_105463_g;
	static String field_105464_d;
	static int[] field_105470_h;
	static C_100153_be[] field_105466_b;
	static String[] field_105467_c;
	static C_100153_be[] field_105465_e;
	static String field_105462_f;
	private static final String[] field_105469_z;
	
	public static void func_105458_a(byte arg0)
	{
		// @00: aconst_null
		// @01: putstatic java.lang.String game.C_100166_sg.field_105464_d
		// @04: aconst_null
		// @05: putstatic game.C_100153_be[] game.C_100166_sg.field_105466_b
		// @08: aconst_null
		// @09: putstatic java.lang.String game.C_100166_sg.field_105468_a
		// @0C: aconst_null
		// @0D: putstatic game.C_100256_pk game.C_100166_sg.field_105463_g
		// @10: aconst_null
		// @11: putstatic java.lang.String[] game.C_100166_sg.field_105467_c
		// @14: aconst_null
		// @15: putstatic java.lang.String game.C_100166_sg.field_105462_f
		// @18: bipush 38 (0x26)
		// @1A: bipush -85 (0xAB)
		// @1C: iload_0
		// @1D: isub
		// @1E: bipush 33 (0x21)
		// @20: idiv
		// @21: idiv
		// @22: istore_1
		// @23: aconst_null
		// @24: putstatic int[] game.C_100166_sg.field_105470_h
		// @27: aconst_null
		// @28: putstatic game.C_100153_be[] game.C_100166_sg.field_105465_e
		// @2B: goto @4F
		// @2E: astore_1
		// @2F: aload_1
		// @30: new java.lang.StringBuilder
		// @33: dup
		// @34: invokespecial java.lang.StringBuilder.<init>()void
		// @37: getstatic java.lang.String[] game.C_100166_sg.field_105469_z
		// @3A: iconst_0
		// @3B: aaload
		// @3C: invokevirtual java.lang.StringBuilder.append(java.lang.String)java.lang.StringBuilder
		// @3F: iload_0
		// @40: invokevirtual java.lang.StringBuilder.append(int)java.lang.StringBuilder
		// @43: bipush 41 (0x29)
		// @45: invokevirtual java.lang.StringBuilder.append(char)java.lang.StringBuilder
		// @48: invokevirtual java.lang.StringBuilder.toString()java.lang.String
		// @4B: invokestatic game.C_100181_cf.func_105695_a(java.lang.Throwable, java.lang.String)game.C_100170_cm
		// @4E: athrow
		// @4F: return
	}
	
	static final int func_105460_a(boolean arg0, int arg1)
	{
		// @00: iload_0
		// @01: ifeq @07
		// @04: bipush -75 (0xB5)
		// @06: ireturn
		// @07: getstatic int[] game.C_100070_dn.field_104370_b
		// @0A: sipush 2047 (0x07FF)
		// @0D: iload_1
		// @0E: iand
		// @0F: iaload
		// @10: ireturn
		// @11: astore_2
		// @12: aload_2
		// @13: new java.lang.StringBuilder
		// @16: dup
		// @17: invokespecial java.lang.StringBuilder.<init>()void
		// @1A: getstatic java.lang.String[] game.C_100166_sg.field_105469_z
		// @1D: iconst_4
		// @1E: aaload
		// @1F: invokevirtual java.lang.StringBuilder.append(java.lang.String)java.lang.StringBuilder
		// @22: iload_0
		// @23: invokevirtual java.lang.StringBuilder.append(boolean)java.lang.StringBuilder
		// @26: bipush 44 (0x2C)
		// @28: invokevirtual java.lang.StringBuilder.append(char)java.lang.StringBuilder
		// @2B: iload_1
		// @2C: invokevirtual java.lang.StringBuilder.append(int)java.lang.StringBuilder
		// @2F: bipush 41 (0x29)
		// @31: invokevirtual java.lang.StringBuilder.append(char)java.lang.StringBuilder
		// @34: invokevirtual java.lang.StringBuilder.toString()java.lang.String
		// @37: invokestatic game.C_100181_cf.func_105695_a(java.lang.Throwable, java.lang.String)game.C_100170_cm
		// @3A: athrow
	}
	
	static final C_100130_tf func_105461_a(int arg0, String arg1)
	{
		// @000: getstatic int game.SteelSentinels.field_105275_O
		// @003: istore #6
		// @005: aload_1
		// @006: invokevirtual java.lang.String.length()int
		// @009: istore_2
		// @00A: iconst_0
		// @00B: iload_2
		// @00C: if_icmpne @013
		// @00F: getstatic game.C_100130_tf game.C_100082_uf.field_100374_a
		// @012: areturn
		// @013: iload_0
		// @014: sipush 5244 (0x147C)
		// @017: if_icmpeq @025
		// @01A: aconst_null
		// @01B: checkcast java.lang.String
		// @01E: putstatic java.lang.String game.C_100166_sg.field_105468_a
		// @021: goto @025
		// @024: athrow
		// @025: iload_2
		// @026: iconst_m1
		// @027: ixor
		// @028: bipush -65 (0xBF)
		// @02A: if_icmpge @031
		// @02D: getstatic game.C_100130_tf game.C_100115_ej.field_102039_ac
		// @030: areturn
		// @031: bipush -35 (0xDD)
		// @033: aload_1
		// @034: iconst_0
		// @035: invokevirtual java.lang.String.charAt(int)char
		// @038: iconst_m1
		// @039: ixor
		// @03A: if_icmpeq @041
		// @03D: goto @0A8
		// @040: athrow
		// @041: bipush 34 (0x22)
		// @043: aload_1
		// @044: iload_2
		// @045: iconst_1
		// @046: isub
		// @047: invokevirtual java.lang.String.charAt(int)char
		// @04A: if_icmpne @051
		// @04D: goto @055
		// @050: athrow
		// @051: getstatic game.C_100130_tf game.C_100132_td.field_104975_c
		// @054: areturn
		// @055: iconst_0
		// @056: istore_3
		// @057: iconst_1
		// @058: istore #4
		// @05A: iload #4
		// @05C: iconst_m1
		// @05D: iload_2
		// @05E: iadd
		// @05F: if_icmpge @0A6
		// @062: aload_1
		// @063: iload #4
		// @065: invokevirtual java.lang.String.charAt(int)char
		// @068: istore #5
		// @06A: bipush 92 (0x5C)
		// @06C: iload #5
		// @06E: if_icmpne @085
		// @071: iload_3
		// @072: ifne @07E
		// @075: goto @079
		// @078: athrow
		// @079: iconst_1
		// @07A: goto @07F
		// @07D: athrow
		// @07E: iconst_0
		// @07F: istore_3
		// @080: iload #6
		// @082: ifeq @09E
		// @085: iload #5
		// @087: bipush 34 (0x22)
		// @089: if_icmpne @09C
		// @08C: goto @090
		// @08F: athrow
		// @090: iload_3
		// @091: ifne @09C
		// @094: goto @098
		// @097: athrow
		// @098: getstatic game.C_100130_tf game.C_100132_td.field_104975_c
		// @09B: areturn
		// @09C: iconst_0
		// @09D: istore_3
		// @09E: iinc #4 +1
		// @0A1: iload #6
		// @0A3: ifeq @05A
		// @0A6: aconst_null
		// @0A7: areturn
		// @0A8: iconst_0
		// @0A9: istore_3
		// @0AA: iconst_0
		// @0AB: istore #4
		// @0AD: iload_2
		// @0AE: iload #4
		// @0B0: if_icmple @111
		// @0B3: aload_1
		// @0B4: iload #4
		// @0B6: invokevirtual java.lang.String.charAt(int)char
		// @0B9: istore #5
		// @0BB: bipush -47 (0xD1)
		// @0BD: iload #5
		// @0BF: iconst_m1
		// @0C0: ixor
		// @0C1: if_icmpeq @0C8
		// @0C4: goto @0F1
		// @0C7: athrow
		// @0C8: iconst_0
		// @0C9: iload #4
		// @0CB: if_icmpeq @0E6
		// @0CE: iload #4
		// @0D0: iconst_m1
		// @0D1: iload_2
		// @0D2: iadd
		// @0D3: if_icmpeq @0E6
		// @0D6: goto @0DA
		// @0D9: athrow
		// @0DA: iload_3
		// @0DB: ifne @0E6
		// @0DE: goto @0E2
		// @0E1: athrow
		// @0E2: goto @0EA
		// @0E5: athrow
		// @0E6: getstatic game.C_100130_tf game.C_100132_td.field_104975_c
		// @0E9: areturn
		// @0EA: iconst_1
		// @0EB: istore_3
		// @0EC: iload #6
		// @0EE: ifeq @109
		// @0F1: iconst_0
		// @0F2: getstatic java.lang.String game.C_100171_cn.field_105568_b
		// @0F5: iload #5
		// @0F7: invokevirtual java.lang.String.indexOf(int)int
		// @0FA: iconst_m1
		// @0FB: ixor
		// @0FC: if_icmpne @107
		// @0FF: goto @103
		// @102: athrow
		// @103: getstatic game.C_100130_tf game.C_100132_td.field_104975_c
		// @106: areturn
		// @107: iconst_0
		// @108: istore_3
		// @109: iinc #4 +1
		// @10C: iload #6
		// @10E: ifeq @0AD
		// @111: aconst_null
		// @112: areturn
		// @113: astore_2
		// @114: aload_2
		// @115: new java.lang.StringBuilder
		// @118: dup
		// @119: invokespecial java.lang.StringBuilder.<init>()void
		// @11C: getstatic java.lang.String[] game.C_100166_sg.field_105469_z
		// @11F: iconst_3
		// @120: aaload
		// @121: invokevirtual java.lang.StringBuilder.append(java.lang.String)java.lang.StringBuilder
		// @124: iload_0
		// @125: invokevirtual java.lang.StringBuilder.append(int)java.lang.StringBuilder
		// @128: bipush 44 (0x2C)
		// @12A: invokevirtual java.lang.StringBuilder.append(char)java.lang.StringBuilder
		// @12D: aload_1
		// @12E: ifnull @13A
		// @131: getstatic java.lang.String[] game.C_100166_sg.field_105469_z
		// @134: iconst_2
		// @135: aaload
		// @136: goto @13F
		// @139: athrow
		// @13A: getstatic java.lang.String[] game.C_100166_sg.field_105469_z
		// @13D: iconst_1
		// @13E: aaload
		// @13F: invokevirtual java.lang.StringBuilder.append(java.lang.String)java.lang.StringBuilder
		// @142: bipush 41 (0x29)
		// @144: invokevirtual java.lang.StringBuilder.append(char)java.lang.StringBuilder
		// @147: invokevirtual java.lang.StringBuilder.toString()java.lang.String
		// @14A: invokestatic game.C_100181_cf.func_105695_a(java.lang.Throwable, java.lang.String)game.C_100170_cm
		// @14D: athrow
	}
	
	static
	{
		// @000: iconst_5
		// @001: anewarray java.lang.String
		// @004: dup
		// @005: iconst_0
		// @006: ldc "\u0001\u000e`v\u0018"
		// @008: invokestatic game.C_100166_sg.func_105459_z(java.lang.String)char[]
		// @00B: invokestatic game.C_100166_sg.func_105457_z(char[])java.lang.String
		// @00E: aastore
		// @00F: dup
		// @010: iconst_1
		// @011: ldc "\u001c\u001c\"Y"
		// @013: invokestatic game.C_100166_sg.func_105459_z(java.lang.String)char[]
		// @016: invokestatic game.C_100166_sg.func_105457_z(char[])java.lang.String
		// @019: aastore
		// @01A: dup
		// @01B: iconst_2
		// @01C: ldc "\tG`\u001bM"
		// @01E: invokestatic game.C_100166_sg.func_105459_z(java.lang.String)char[]
		// @021: invokestatic game.C_100166_sg.func_105457_z(char[])java.lang.String
		// @024: aastore
		// @025: dup
		// @026: iconst_3
		// @027: ldc "\u0001\u000e`w\u0018"
		// @029: invokestatic game.C_100166_sg.func_105459_z(java.lang.String)char[]
		// @02C: invokestatic game.C_100166_sg.func_105457_z(char[])java.lang.String
		// @02F: aastore
		// @030: dup
		// @031: iconst_4
		// @032: ldc "\u0001\u000e`t\u0018"
		// @034: invokestatic game.C_100166_sg.func_105459_z(java.lang.String)char[]
		// @037: invokestatic game.C_100166_sg.func_105457_z(char[])java.lang.String
		// @03A: aastore
		// @03B: putstatic java.lang.String[] game.C_100166_sg.field_105469_z
		// @03E: ldc " ,\u001d|w<,\n"
		// @040: invokestatic game.C_100166_sg.func_105459_z(java.lang.String)char[]
		// @043: invokestatic game.C_100166_sg.func_105457_z(char[])java.lang.String
		// @046: putstatic java.lang.String game.C_100166_sg.field_105468_a
		// @049: bipush 64 (0x40)
		// @04B: putstatic int game.C_100166_sg.field_105471_i
		// @04E: ldc "1\u0006 V\\\u0007\r+Q"
		// @050: invokestatic game.C_100166_sg.func_105459_z(java.lang.String)char[]
		// @053: invokestatic game.C_100166_sg.func_105457_z(char[])java.lang.String
		// @056: putstatic java.lang.String game.C_100166_sg.field_105464_d
		// @059: bipush 36 (0x24)
		// @05B: newarray int[]
		// @05D: dup
		// @05E: iconst_0
		// @05F: iconst_0
		// @060: iastore
		// @061: dup
		// @062: iconst_1
		// @063: iconst_5
		// @064: iastore
		// @065: dup
		// @066: iconst_2
		// @067: bipush 10 (0x0A)
		// @069: iastore
		// @06A: dup
		// @06B: iconst_3
		// @06C: iconst_1
		// @06D: iastore
		// @06E: dup
		// @06F: iconst_4
		// @070: bipush 6 (0x06)
		// @072: iastore
		// @073: dup
		// @074: iconst_5
		// @075: bipush 11 (0x0B)
		// @077: iastore
		// @078: dup
		// @079: bipush 6 (0x06)
		// @07B: iconst_2
		// @07C: iastore
		// @07D: dup
		// @07E: bipush 7 (0x07)
		// @080: bipush 7 (0x07)
		// @082: iastore
		// @083: dup
		// @084: bipush 8 (0x08)
		// @086: bipush 12 (0x0C)
		// @088: iastore
		// @089: dup
		// @08A: bipush 9 (0x09)
		// @08C: bipush 33 (0x21)
		// @08E: iastore
		// @08F: dup
		// @090: bipush 10 (0x0A)
		// @092: bipush 32 (0x20)
		// @094: iastore
		// @095: dup
		// @096: bipush 11 (0x0B)
		// @098: bipush 26 (0x1A)
		// @09A: iastore
		// @09B: dup
		// @09C: bipush 12 (0x0C)
		// @09E: bipush 18 (0x12)
		// @0A0: iastore
		// @0A1: dup
		// @0A2: bipush 13 (0x0D)
		// @0A4: bipush 21 (0x15)
		// @0A6: iastore
		// @0A7: dup
		// @0A8: bipush 14 (0x0E)
		// @0AA: bipush 28 (0x1C)
		// @0AC: iastore
		// @0AD: dup
		// @0AE: bipush 15 (0x0F)
		// @0B0: bipush 29 (0x1D)
		// @0B2: iastore
		// @0B3: dup
		// @0B4: bipush 16 (0x10)
		// @0B6: bipush 36 (0x24)
		// @0B8: iastore
		// @0B9: dup
		// @0BA: bipush 17 (0x11)
		// @0BC: bipush 27 (0x1B)
		// @0BE: iastore
		// @0BF: dup
		// @0C0: bipush 18 (0x12)
		// @0C2: bipush 24 (0x18)
		// @0C4: iastore
		// @0C5: dup
		// @0C6: bipush 19 (0x13)
		// @0C8: iconst_3
		// @0C9: iastore
		// @0CA: dup
		// @0CB: bipush 20 (0x14)
		// @0CD: bipush 8 (0x08)
		// @0CF: iastore
		// @0D0: dup
		// @0D1: bipush 21 (0x15)
		// @0D3: bipush 13 (0x0D)
		// @0D5: iastore
		// @0D6: dup
		// @0D7: bipush 22 (0x16)
		// @0D9: bipush 9 (0x09)
		// @0DB: iastore
		// @0DC: dup
		// @0DD: bipush 23 (0x17)
		// @0DF: iconst_4
		// @0E0: iastore
		// @0E1: dup
		// @0E2: bipush 24 (0x18)
		// @0E4: bipush 14 (0x0E)
		// @0E6: iastore
		// @0E7: dup
		// @0E8: bipush 25 (0x19)
		// @0EA: bipush 42 (0x2A)
		// @0EC: iastore
		// @0ED: dup
		// @0EE: bipush 26 (0x1A)
		// @0F0: bipush 15 (0x0F)
		// @0F2: iastore
		// @0F3: dup
		// @0F4: bipush 27 (0x1B)
		// @0F6: bipush 39 (0x27)
		// @0F8: iastore
		// @0F9: dup
		// @0FA: bipush 28 (0x1C)
		// @0FC: bipush 40 (0x28)
		// @0FE: iastore
		// @0FF: dup
		// @100: bipush 29 (0x1D)
		// @102: bipush 20 (0x14)
		// @104: iastore
		// @105: dup
		// @106: bipush 30 (0x1E)
		// @108: bipush 30 (0x1E)
		// @10A: iastore
		// @10B: dup
		// @10C: bipush 31 (0x1F)
		// @10E: bipush 35 (0x23)
		// @110: iastore
		// @111: dup
		// @112: bipush 32 (0x20)
		// @114: bipush 38 (0x26)
		// @116: iastore
		// @117: dup
		// @118: bipush 33 (0x21)
		// @11A: bipush 37 (0x25)
		// @11C: iastore
		// @11D: dup
		// @11E: bipush 34 (0x22)
		// @120: bipush 44 (0x2C)
		// @122: iastore
		// @123: dup
		// @124: bipush 35 (0x23)
		// @126: bipush 41 (0x29)
		// @128: iastore
		// @129: putstatic int[] game.C_100166_sg.field_105470_h
		// @12C: ldc "4\u001b'P^\u0016\u001anVQ\u001cI,P\u0010\u0013\r*PTR\u0000 \u0015D\u001a\u000cnXE\u001e\u001d'E\\\u0013\u0010+G\u000c\u001c\u000b=E\u000e\u001e\u0006,WI"
		// @12E: invokestatic game.C_100166_sg.func_105459_z(java.lang.String)char[]
		// @131: invokestatic game.C_100166_sg.func_105457_z(char[])java.lang.String
		// @134: putstatic java.lang.String game.C_100166_sg.field_105462_f
		// @137: return
	}
	
	private static char[] func_105459_z(String arg0)
	{
		// @00: aload_0
		// @01: invokevirtual java.lang.String.toCharArray()char[]
		// @04: dup
		// @05: arraylength
		// @06: iconst_2
		// @07: if_icmpge @13
		// @0A: dup
		// @0B: iconst_0
		// @0C: dup2
		// @0D: caload
		// @0E: bipush 48 (0x30)
		// @10: ixor
		// @11: i2c
		// @12: castore
		// @13: areturn
	}
	
	private static String func_105457_z(char[] arg0)
	{
		// @00: aload_0
		// @01: dup
		// @02: arraylength
		// @03: swap
		// @04: iconst_0
		// @05: istore_1
		// @06: goto @4C
		// @09: dup
		// @0A: iload_1
		// @0B: dup2
		// @0C: caload
		// @0D: iload_1
		// @0E: iconst_5
		// @0F: irem
		// @10: tableswitch def: @44, for 0: @30, for 1: @35, for 2: @3A, for 3: @3F
		// @30: bipush 114 (0x72)
		// @32: goto @46
		// @35: bipush 105 (0x69)
		// @37: goto @46
		// @3A: bipush 78 (0x4E)
		// @3C: goto @46
		// @3F: bipush 53 (0x35)
		// @41: goto @46
		// @44: bipush 48 (0x30)
		// @46: ixor
		// @47: i2c
		// @48: castore
		// @49: iinc #1 +1
		// @4C: swap
		// @4D: dup_x1
		// @4E: iload_1
		// @4F: if_icmpgt @09
		// @52: new java.lang.String
		// @55: dup_x1
		// @56: swap
		// @57: invokespecial java.lang.String.<init>(char[])void
		// @5A: invokevirtual java.lang.String.intern()java.lang.String
		// @5D: areturn
	}
}
