package game;

import java.util.Iterator;
import java.applet.Applet;

final class C_100266_me implements Iterable
{
	int field_106655_j;
	private C_100158_da field_106648_f;
	static C_100302_ka field_106650_d;
	static C_100302_ka field_106649_g;
	static int[] field_106653_c;
	static String[][] field_106654_a;
	static C_100037_wb[] field_106651_e;
	static String field_106652_b;
	static C_100301_kb field_106657_h;
	C_100158_da[] field_106658_i;
	private static final String[] field_106656_z;
	
	public final Iterator iterator()
	{
		// @00: new game.C_100092_um
		// @03: dup
		// @04: aload_0
		// @05: invokespecial game.C_100092_um.<init>(game.C_100266_me)void
		// @08: areturn
		// @09: astore_1
		// @0A: aload_1
		// @0B: getstatic java.lang.String[] game.C_100266_me.field_106656_z
		// @0E: iconst_3
		// @0F: aaload
		// @10: invokestatic game.C_100181_cf.func_105695_a(java.lang.Throwable, java.lang.String)game.C_100170_cm
		// @13: athrow
	}
	
	public static void func_106641_a(int arg0)
	{
		// @00: aconst_null
		// @01: checkcast java.lang.String[][]
		// @04: putstatic java.lang.String[][] game.C_100266_me.field_106654_a
		// @07: aconst_null
		// @08: putstatic game.C_100301_kb game.C_100266_me.field_106657_h
		// @0B: aconst_null
		// @0C: putstatic java.lang.String game.C_100266_me.field_106652_b
		// @0F: bipush -108 (0x94)
		// @11: iload_0
		// @12: bipush -39 (0xD9)
		// @14: isub
		// @15: bipush 48 (0x30)
		// @17: idiv
		// @18: irem
		// @19: istore_1
		// @1A: aconst_null
		// @1B: putstatic int[] game.C_100266_me.field_106653_c
		// @1E: aconst_null
		// @1F: putstatic game.C_100302_ka game.C_100266_me.field_106650_d
		// @22: aconst_null
		// @23: putstatic game.C_100037_wb[] game.C_100266_me.field_106651_e
		// @26: aconst_null
		// @27: putstatic game.C_100302_ka game.C_100266_me.field_106649_g
		// @2A: goto @4F
		// @2D: astore_1
		// @2E: aload_1
		// @2F: new java.lang.StringBuilder
		// @32: dup
		// @33: invokespecial java.lang.StringBuilder.<init>()void
		// @36: getstatic java.lang.String[] game.C_100266_me.field_106656_z
		// @39: bipush 11 (0x0B)
		// @3B: aaload
		// @3C: invokevirtual java.lang.StringBuilder.append(java.lang.String)java.lang.StringBuilder
		// @3F: iload_0
		// @40: invokevirtual java.lang.StringBuilder.append(int)java.lang.StringBuilder
		// @43: bipush 41 (0x29)
		// @45: invokevirtual java.lang.StringBuilder.append(char)java.lang.StringBuilder
		// @48: invokevirtual java.lang.StringBuilder.toString()java.lang.String
		// @4B: invokestatic game.C_100181_cf.func_105695_a(java.lang.Throwable, java.lang.String)game.C_100170_cm
		// @4E: athrow
		// @4F: return
	}
	
	final C_100158_da func_106644_a(byte arg0, long arg1)
	{
		// @00: getstatic int game.SteelSentinels.field_105275_O
		// @03: istore #6
		// @05: aload_0
		// @06: getfield game.C_100158_da[] game.C_100266_me.field_106658_i
		// @09: lload_2
		// @0A: iconst_m1
		// @0B: aload_0
		// @0C: getfield int game.C_100266_me.field_106655_j
		// @0F: iadd
		// @10: i2l
		// @11: land
		// @12: l2i
		// @13: aaload
		// @14: astore #4
		// @16: aload_0
		// @17: aload #4
		// @19: getfield game.C_100158_da game.C_100158_da.field_100590_f
		// @1C: putfield game.C_100158_da game.C_100266_me.field_106648_f
		// @1F: iload_1
		// @20: bipush 59 (0x3B)
		// @22: if_icmpge @31
		// @25: aload_0
		// @26: aconst_null
		// @27: checkcast game.C_100158_da
		// @2A: putfield game.C_100158_da game.C_100266_me.field_106648_f
		// @2D: goto @31
		// @30: athrow
		// @31: aload_0
		// @32: getfield game.C_100158_da game.C_100266_me.field_106648_f
		// @35: aload #4
		// @37: if_acmpeq @77
		// @3A: aload_0
		// @3B: iload #6
		// @3D: ifne @78
		// @40: getfield game.C_100158_da game.C_100266_me.field_106648_f
		// @43: getfield long game.C_100158_da.field_100595_c
		// @46: lload_2
		// @47: lcmp
		// @48: ifeq @53
		// @4B: goto @4F
		// @4E: athrow
		// @4F: goto @67
		// @52: athrow
		// @53: aload_0
		// @54: getfield game.C_100158_da game.C_100266_me.field_106648_f
		// @57: astore #5
		// @59: aload_0
		// @5A: aload_0
		// @5B: getfield game.C_100158_da game.C_100266_me.field_106648_f
		// @5E: getfield game.C_100158_da game.C_100158_da.field_100590_f
		// @61: putfield game.C_100158_da game.C_100266_me.field_106648_f
		// @64: aload #5
		// @66: areturn
		// @67: aload_0
		// @68: aload_0
		// @69: getfield game.C_100158_da game.C_100266_me.field_106648_f
		// @6C: getfield game.C_100158_da game.C_100158_da.field_100590_f
		// @6F: putfield game.C_100158_da game.C_100266_me.field_106648_f
		// @72: iload #6
		// @74: ifeq @31
		// @77: aload_0
		// @78: aconst_null
		// @79: putfield game.C_100158_da game.C_100266_me.field_106648_f
		// @7C: aconst_null
		// @7D: areturn
		// @7E: astore #4
		// @80: aload #4
		// @82: new java.lang.StringBuilder
		// @85: dup
		// @86: invokespecial java.lang.StringBuilder.<init>()void
		// @89: getstatic java.lang.String[] game.C_100266_me.field_106656_z
		// @8C: iconst_4
		// @8D: aaload
		// @8E: invokevirtual java.lang.StringBuilder.append(java.lang.String)java.lang.StringBuilder
		// @91: iload_1
		// @92: invokevirtual java.lang.StringBuilder.append(int)java.lang.StringBuilder
		// @95: bipush 44 (0x2C)
		// @97: invokevirtual java.lang.StringBuilder.append(char)java.lang.StringBuilder
		// @9A: lload_2
		// @9B: invokevirtual java.lang.StringBuilder.append(long)java.lang.StringBuilder
		// @9E: bipush 41 (0x29)
		// @A0: invokevirtual java.lang.StringBuilder.append(char)java.lang.StringBuilder
		// @A3: invokevirtual java.lang.StringBuilder.toString()java.lang.String
		// @A6: invokestatic game.C_100181_cf.func_105695_a(java.lang.Throwable, java.lang.String)game.C_100170_cm
		// @A9: athrow
	}
	
	final void func_106639_a(C_100158_da arg0, long arg1, byte arg2)
	{
		// @00: aconst_null
		// @01: aload_1
		// @02: getfield game.C_100158_da game.C_100158_da.field_100599_i
		// @05: if_acmpne @0C
		// @08: goto @12
		// @0B: athrow
		// @0C: aload_1
		// @0D: bipush 45 (0x2D)
		// @0F: invokevirtual game.C_100158_da.func_100583_c(int)void
		// @12: aload_0
		// @13: getfield game.C_100158_da[] game.C_100266_me.field_106658_i
		// @16: lload_2
		// @17: aload_0
		// @18: getfield int game.C_100266_me.field_106655_j
		// @1B: iconst_m1
		// @1C: iadd
		// @1D: i2l
		// @1E: land
		// @1F: l2i
		// @20: aaload
		// @21: astore #5
		// @23: aload_1
		// @24: aload #5
		// @26: getfield game.C_100158_da game.C_100158_da.field_100599_i
		// @29: putfield game.C_100158_da game.C_100158_da.field_100599_i
		// @2C: aload_1
		// @2D: aload #5
		// @2F: putfield game.C_100158_da game.C_100158_da.field_100590_f
		// @32: aload_1
		// @33: getfield game.C_100158_da game.C_100158_da.field_100599_i
		// @36: aload_1
		// @37: putfield game.C_100158_da game.C_100158_da.field_100590_f
		// @3A: aload_1
		// @3B: lload_2
		// @3C: putfield long game.C_100158_da.field_100595_c
		// @3F: iload #4
		// @41: bipush 88 (0x58)
		// @43: if_icmpgt @4F
		// @46: bipush 50 (0x32)
		// @48: invokestatic game.C_100266_me.func_106641_a(int)void
		// @4B: goto @4F
		// @4E: athrow
		// @4F: aload_1
		// @50: getfield game.C_100158_da game.C_100158_da.field_100590_f
		// @53: aload_1
		// @54: putfield game.C_100158_da game.C_100158_da.field_100599_i
		// @57: goto @A1
		// @5A: astore #5
		// @5C: aload #5
		// @5E: new java.lang.StringBuilder
		// @61: dup
		// @62: invokespecial java.lang.StringBuilder.<init>()void
		// @65: getstatic java.lang.String[] game.C_100266_me.field_106656_z
		// @68: iconst_0
		// @69: aaload
		// @6A: invokevirtual java.lang.StringBuilder.append(java.lang.String)java.lang.StringBuilder
		// @6D: aload_1
		// @6E: ifnull @7A
		// @71: getstatic java.lang.String[] game.C_100266_me.field_106656_z
		// @74: iconst_1
		// @75: aaload
		// @76: goto @7F
		// @79: athrow
		// @7A: getstatic java.lang.String[] game.C_100266_me.field_106656_z
		// @7D: iconst_2
		// @7E: aaload
		// @7F: invokevirtual java.lang.StringBuilder.append(java.lang.String)java.lang.StringBuilder
		// @82: bipush 44 (0x2C)
		// @84: invokevirtual java.lang.StringBuilder.append(char)java.lang.StringBuilder
		// @87: lload_2
		// @88: invokevirtual java.lang.StringBuilder.append(long)java.lang.StringBuilder
		// @8B: bipush 44 (0x2C)
		// @8D: invokevirtual java.lang.StringBuilder.append(char)java.lang.StringBuilder
		// @90: iload #4
		// @92: invokevirtual java.lang.StringBuilder.append(int)java.lang.StringBuilder
		// @95: bipush 41 (0x29)
		// @97: invokevirtual java.lang.StringBuilder.append(char)java.lang.StringBuilder
		// @9A: invokevirtual java.lang.StringBuilder.toString()java.lang.String
		// @9D: invokestatic game.C_100181_cf.func_105695_a(java.lang.Throwable, java.lang.String)game.C_100170_cm
		// @A0: athrow
		// @A1: return
	}
	
	static final void func_106645_a(int arg0, int arg1, int arg2, int arg3, int arg4)
	{
		// @00: getstatic game.C_100037_wb[] game.C_100102_w.field_104655_y
		// @03: astore #5
		// @05: iload_3
		// @06: iload_2
		// @07: bipush -126 (0x82)
		// @09: iload_1
		// @0A: aload #5
		// @0C: iload #4
		// @0E: invokestatic game.C_100157_db.func_103554_a(int, int, int, int, game.C_100037_wb[], int)void
		// @11: iload_0
		// @12: ldc 33563 (0x831b)
		// @14: if_icmpeq @22
		// @17: aconst_null
		// @18: checkcast int[]
		// @1B: putstatic int[] game.C_100266_me.field_106653_c
		// @1E: goto @22
		// @21: athrow
		// @22: goto @6E
		// @25: astore #5
		// @27: aload #5
		// @29: new java.lang.StringBuilder
		// @2C: dup
		// @2D: invokespecial java.lang.StringBuilder.<init>()void
		// @30: getstatic java.lang.String[] game.C_100266_me.field_106656_z
		// @33: bipush 9 (0x09)
		// @35: aaload
		// @36: invokevirtual java.lang.StringBuilder.append(java.lang.String)java.lang.StringBuilder
		// @39: iload_0
		// @3A: invokevirtual java.lang.StringBuilder.append(int)java.lang.StringBuilder
		// @3D: bipush 44 (0x2C)
		// @3F: invokevirtual java.lang.StringBuilder.append(char)java.lang.StringBuilder
		// @42: iload_1
		// @43: invokevirtual java.lang.StringBuilder.append(int)java.lang.StringBuilder
		// @46: bipush 44 (0x2C)
		// @48: invokevirtual java.lang.StringBuilder.append(char)java.lang.StringBuilder
		// @4B: iload_2
		// @4C: invokevirtual java.lang.StringBuilder.append(int)java.lang.StringBuilder
		// @4F: bipush 44 (0x2C)
		// @51: invokevirtual java.lang.StringBuilder.append(char)java.lang.StringBuilder
		// @54: iload_3
		// @55: invokevirtual java.lang.StringBuilder.append(int)java.lang.StringBuilder
		// @58: bipush 44 (0x2C)
		// @5A: invokevirtual java.lang.StringBuilder.append(char)java.lang.StringBuilder
		// @5D: iload #4
		// @5F: invokevirtual java.lang.StringBuilder.append(int)java.lang.StringBuilder
		// @62: bipush 41 (0x29)
		// @64: invokevirtual java.lang.StringBuilder.append(char)java.lang.StringBuilder
		// @67: invokevirtual java.lang.StringBuilder.toString()java.lang.String
		// @6A: invokestatic game.C_100181_cf.func_105695_a(java.lang.Throwable, java.lang.String)game.C_100170_cm
		// @6D: athrow
		// @6E: return
	}
	
	static final void func_106646_a(int arg0, int arg1)
	{
		// @00: iload_1
		// @01: putstatic int game.C_100346_ja.field_103498_y
		// @04: getstatic game.C_100210_qa game.C_100004_gb.field_103576_k
		// @07: ifnonnull @0E
		// @0A: goto @17
		// @0D: athrow
		// @0E: getstatic game.C_100210_qa game.C_100004_gb.field_103576_k
		// @11: bipush -108 (0x94)
		// @13: iload_1
		// @14: invokevirtual game.C_100210_qa.func_101039_b(int, int)void
		// @17: iload_0
		// @18: bipush 106 (0x6A)
		// @1A: if_icmpge @28
		// @1D: aconst_null
		// @1E: checkcast java.lang.String
		// @21: putstatic java.lang.String game.C_100266_me.field_106652_b
		// @24: goto @28
		// @27: athrow
		// @28: aconst_null
		// @29: getstatic game.C_100253_ph game.C_100203_ql.field_105927_f
		// @2C: if_acmpeq @3C
		// @2F: getstatic game.C_100253_ph game.C_100203_ql.field_105927_f
		// @32: iload_1
		// @33: bipush -112 (0x90)
		// @35: invokevirtual game.C_100253_ph.func_101089_b(int, int)void
		// @38: goto @3C
		// @3B: athrow
		// @3C: goto @6A
		// @3F: astore_2
		// @40: aload_2
		// @41: new java.lang.StringBuilder
		// @44: dup
		// @45: invokespecial java.lang.StringBuilder.<init>()void
		// @48: getstatic java.lang.String[] game.C_100266_me.field_106656_z
		// @4B: bipush 12 (0x0C)
		// @4D: aaload
		// @4E: invokevirtual java.lang.StringBuilder.append(java.lang.String)java.lang.StringBuilder
		// @51: iload_0
		// @52: invokevirtual java.lang.StringBuilder.append(int)java.lang.StringBuilder
		// @55: bipush 44 (0x2C)
		// @57: invokevirtual java.lang.StringBuilder.append(char)java.lang.StringBuilder
		// @5A: iload_1
		// @5B: invokevirtual java.lang.StringBuilder.append(int)java.lang.StringBuilder
		// @5E: bipush 41 (0x29)
		// @60: invokevirtual java.lang.StringBuilder.append(char)java.lang.StringBuilder
		// @63: invokevirtual java.lang.StringBuilder.toString()java.lang.String
		// @66: invokestatic game.C_100181_cf.func_105695_a(java.lang.Throwable, java.lang.String)game.C_100170_cm
		// @69: athrow
		// @6A: return
	}
	
	static final byte[] func_106647_a(byte[] arg0, int arg1)
	{
		// @000: bipush -87 (0xA9)
		// @002: bipush -17 (0xEF)
		// @004: iload_1
		// @005: isub
		// @006: bipush 32 (0x20)
		// @008: idiv
		// @009: idiv
		// @00A: istore_3
		// @00B: new game.C_100280_nf
		// @00E: dup
		// @00F: aload_0
		// @010: invokespecial game.C_100280_nf.<init>(byte[])void
		// @013: astore_2
		// @014: aload_2
		// @015: iconst_0
		// @016: invokevirtual game.C_100280_nf.func_101156_c(boolean)int
		// @019: istore #4
		// @01B: aload_2
		// @01C: sipush -1543 (0xF9F9)
		// @01F: invokevirtual game.C_100280_nf.func_101171_e(int)int
		// @022: istore #5
		// @024: iconst_0
		// @025: iload #5
		// @027: if_icmpgt @043
		// @02A: getstatic int game.C_100059_df.field_101611_w
		// @02D: iconst_m1
		// @02E: ixor
		// @02F: iconst_m1
		// @030: if_icmpeq @04C
		// @033: goto @037
		// @036: athrow
		// @037: iload #5
		// @039: getstatic int game.C_100059_df.field_101611_w
		// @03C: if_icmple @04C
		// @03F: goto @043
		// @042: athrow
		// @043: new java.lang.RuntimeException
		// @046: dup
		// @047: invokespecial java.lang.RuntimeException.<init>()void
		// @04A: athrow
		// @04B: athrow
		// @04C: iconst_0
		// @04D: iload #4
		// @04F: if_icmpeq @0C4
		// @052: aload_2
		// @053: sipush -1543 (0xF9F9)
		// @056: invokevirtual game.C_100280_nf.func_101171_e(int)int
		// @059: istore #6
		// @05B: iload #6
		// @05D: iflt @079
		// @060: iconst_m1
		// @061: getstatic int game.C_100059_df.field_101611_w
		// @064: iconst_m1
		// @065: ixor
		// @066: if_icmpeq @082
		// @069: goto @06D
		// @06C: athrow
		// @06D: getstatic int game.C_100059_df.field_101611_w
		// @070: iload #6
		// @072: if_icmpge @082
		// @075: goto @079
		// @078: athrow
		// @079: new java.lang.RuntimeException
		// @07C: dup
		// @07D: invokespecial java.lang.RuntimeException.<init>()void
		// @080: athrow
		// @081: athrow
		// @082: iload #6
		// @084: newarray byte[]
		// @086: astore #7
		// @088: iload #4
		// @08A: iconst_m1
		// @08B: ixor
		// @08C: bipush -2 (0xFE)
		// @08E: if_icmpeq @0B4
		// @091: getstatic game.C_100028_ha game.C_100078_ul.field_103281_jb
		// @094: dup
		// @095: astore #8
		// @097: monitorenter
		// @098: getstatic game.C_100028_ha game.C_100078_ul.field_103281_jb
		// @09B: aload #7
		// @09D: aload_2
		// @09E: bipush 39 (0x27)
		// @0A0: invokevirtual game.C_100028_ha.func_103939_a(byte[], game.C_100280_nf, byte)void
		// @0A3: aload #8
		// @0A5: monitorexit
		// @0A6: goto @0B1
		// @0A9: astore #9
		// @0AB: aload #8
		// @0AD: monitorexit
		// @0AE: aload #9
		// @0B0: athrow
		// @0B1: goto @0C1
		// @0B4: aload #7
		// @0B6: iload #6
		// @0B8: aload_0
		// @0B9: iload #5
		// @0BB: bipush 9 (0x09)
		// @0BD: invokestatic game.C_100135_ti.func_105019_a(byte[], int, byte[], int, int)int
		// @0C0: pop
		// @0C1: aload #7
		// @0C3: areturn
		// @0C4: iload #5
		// @0C6: newarray byte[]
		// @0C8: astore #6
		// @0CA: aload_2
		// @0CB: aload #6
		// @0CD: iload #5
		// @0CF: iconst_0
		// @0D0: sipush -7623 (0xE239)
		// @0D3: invokevirtual game.C_100280_nf.func_101149_a(byte[], int, int, int)void
		// @0D6: aload #6
		// @0D8: areturn
		// @0D9: astore_2
		// @0DA: aload_2
		// @0DB: new java.lang.StringBuilder
		// @0DE: dup
		// @0DF: invokespecial java.lang.StringBuilder.<init>()void
		// @0E2: getstatic java.lang.String[] game.C_100266_me.field_106656_z
		// @0E5: bipush 8 (0x08)
		// @0E7: aaload
		// @0E8: invokevirtual java.lang.StringBuilder.append(java.lang.String)java.lang.StringBuilder
		// @0EB: aload_0
		// @0EC: ifnull @0F8
		// @0EF: getstatic java.lang.String[] game.C_100266_me.field_106656_z
		// @0F2: iconst_1
		// @0F3: aaload
		// @0F4: goto @0FD
		// @0F7: athrow
		// @0F8: getstatic java.lang.String[] game.C_100266_me.field_106656_z
		// @0FB: iconst_2
		// @0FC: aaload
		// @0FD: invokevirtual java.lang.StringBuilder.append(java.lang.String)java.lang.StringBuilder
		// @100: bipush 44 (0x2C)
		// @102: invokevirtual java.lang.StringBuilder.append(char)java.lang.StringBuilder
		// @105: iload_1
		// @106: invokevirtual java.lang.StringBuilder.append(int)java.lang.StringBuilder
		// @109: bipush 41 (0x29)
		// @10B: invokevirtual java.lang.StringBuilder.append(char)java.lang.StringBuilder
		// @10E: invokevirtual java.lang.StringBuilder.toString()java.lang.String
		// @111: invokestatic game.C_100181_cf.func_105695_a(java.lang.Throwable, java.lang.String)game.C_100170_cm
		// @114: athrow
	}
	
	static final void func_106640_a(int arg0, Applet arg1)
	{
		// @00: bipush -96 (0xA0)
		// @02: iload_0
		// @03: bipush -53 (0xCB)
		// @05: isub
		// @06: bipush 46 (0x2E)
		// @08: idiv
		// @09: idiv
		// @0A: istore_2
		// @0B: new java.net.URL
		// @0E: dup
		// @0F: aload_1
		// @10: invokevirtual java.applet.Applet.getCodeBase()java.net.URL
		// @13: getstatic java.lang.String[] game.C_100266_me.field_106656_z
		// @16: bipush 7 (0x07)
		// @18: aaload
		// @19: invokespecial java.net.URL.<init>(java.net.URL, java.lang.String)void
		// @1C: astore_3
		// @1D: aload_1
		// @1E: invokevirtual java.applet.Applet.getAppletContext()java.applet.AppletContext
		// @21: iconst_m1
		// @22: aload_3
		// @23: aload_1
		// @24: invokestatic game.C_100244_pe.func_106368_a(int, java.net.URL, java.applet.Applet)java.net.URL
		// @27: getstatic java.lang.String[] game.C_100266_me.field_106656_z
		// @2A: iconst_5
		// @2B: aaload
		// @2C: invokeinterface java.applet.AppletContext.showDocument(java.net.URL, java.lang.String)void
		// @31: goto @39
		// @34: astore_3
		// @35: aload_3
		// @36: invokevirtual java.lang.Exception.printStackTrace()void
		// @39: goto @78
		// @3C: astore_2
		// @3D: aload_2
		// @3E: new java.lang.StringBuilder
		// @41: dup
		// @42: invokespecial java.lang.StringBuilder.<init>()void
		// @45: getstatic java.lang.String[] game.C_100266_me.field_106656_z
		// @48: bipush 6 (0x06)
		// @4A: aaload
		// @4B: invokevirtual java.lang.StringBuilder.append(java.lang.String)java.lang.StringBuilder
		// @4E: iload_0
		// @4F: invokevirtual java.lang.StringBuilder.append(int)java.lang.StringBuilder
		// @52: bipush 44 (0x2C)
		// @54: invokevirtual java.lang.StringBuilder.append(char)java.lang.StringBuilder
		// @57: aload_1
		// @58: ifnull @64
		// @5B: getstatic java.lang.String[] game.C_100266_me.field_106656_z
		// @5E: iconst_1
		// @5F: aaload
		// @60: goto @69
		// @63: athrow
		// @64: getstatic java.lang.String[] game.C_100266_me.field_106656_z
		// @67: iconst_2
		// @68: aaload
		// @69: invokevirtual java.lang.StringBuilder.append(java.lang.String)java.lang.StringBuilder
		// @6C: bipush 41 (0x29)
		// @6E: invokevirtual java.lang.StringBuilder.append(char)java.lang.StringBuilder
		// @71: invokevirtual java.lang.StringBuilder.toString()java.lang.String
		// @74: invokestatic game.C_100181_cf.func_105695_a(java.lang.Throwable, java.lang.String)game.C_100170_cm
		// @77: athrow
		// @78: return
	}
	
	C_100266_me(int arg0)
	{
		// @00: getstatic int game.SteelSentinels.field_105275_O
		// @03: istore #4
		// @05: aload_0
		// @06: invokespecial java.lang.Object.<init>()void
		// @09: aload_0
		// @0A: iload_1
		// @0B: anewarray game.C_100158_da
		// @0E: putfield game.C_100158_da[] game.C_100266_me.field_106658_i
		// @11: aload_0
		// @12: iload_1
		// @13: putfield int game.C_100266_me.field_106655_j
		// @16: iconst_0
		// @17: istore_2
		// @18: iload_1
		// @19: iload_2
		// @1A: if_icmple @47
		// @1D: aload_0
		// @1E: getfield game.C_100158_da[] game.C_100266_me.field_106658_i
		// @21: iload_2
		// @22: new game.C_100158_da
		// @25: dup
		// @26: invokespecial game.C_100158_da.<init>()void
		// @29: dup_x2
		// @2A: aastore
		// @2B: astore_3
		// @2C: aload_3
		// @2D: aload_3
		// @2E: putfield game.C_100158_da game.C_100158_da.field_100599_i
		// @31: aload_3
		// @32: aload_3
		// @33: putfield game.C_100158_da game.C_100158_da.field_100590_f
		// @36: iinc #2 +1
		// @39: iload #4
		// @3B: ifne @6C
		// @3E: iload #4
		// @40: ifeq @18
		// @43: goto @47
		// @46: athrow
		// @47: goto @6C
		// @4A: astore_2
		// @4B: aload_2
		// @4C: new java.lang.StringBuilder
		// @4F: dup
		// @50: invokespecial java.lang.StringBuilder.<init>()void
		// @53: getstatic java.lang.String[] game.C_100266_me.field_106656_z
		// @56: bipush 10 (0x0A)
		// @58: aaload
		// @59: invokevirtual java.lang.StringBuilder.append(java.lang.String)java.lang.StringBuilder
		// @5C: iload_1
		// @5D: invokevirtual java.lang.StringBuilder.append(int)java.lang.StringBuilder
		// @60: bipush 41 (0x29)
		// @62: invokevirtual java.lang.StringBuilder.append(char)java.lang.StringBuilder
		// @65: invokevirtual java.lang.StringBuilder.toString()java.lang.String
		// @68: invokestatic game.C_100181_cf.func_105695_a(java.lang.Throwable, java.lang.String)game.C_100170_cm
		// @6B: athrow
		// @6C: return
	}
	
	static
	{
		// @0000: bipush 13 (0x0D)
		// @0002: anewarray java.lang.String
		// @0005: dup
		// @0006: iconst_0
		// @0007: ldc "M}_\u0004E"
		// @0009: invokestatic game.C_100266_me.func_106643_z(java.lang.String)char[]
		// @000C: invokestatic game.C_100266_me.func_106642_z(char[])java.lang.String
		// @000F: aastore
		// @0010: dup
		// @0011: iconst_1
		// @0012: ldc "[6_m\u0010"
		// @0014: invokestatic game.C_100266_me.func_106643_z(java.lang.String)char[]
		// @0017: invokestatic game.C_100266_me.func_106642_z(char[])java.lang.String
		// @001A: aastore
		// @001B: dup
		// @001C: iconst_2
		// @001D: ldc "Nm\u001d/"
		// @001F: invokestatic game.C_100266_me.func_106643_z(java.lang.String)char[]
		// @0022: invokestatic game.C_100266_me.func_106642_z(char[])java.lang.String
		// @0025: aastore
		// @0026: dup
		// @0027: iconst_3
		// @0028: ldc "M}_*\u0019Ej\u00107\u0002R0X"
		// @002A: invokestatic game.C_100266_me.func_106643_z(java.lang.String)char[]
		// @002D: invokestatic game.C_100266_me.func_106642_z(char[])java.lang.String
		// @0030: aastore
		// @0031: dup
		// @0032: iconst_4
		// @0033: ldc "M}_\u0007E"
		// @0035: invokestatic game.C_100266_me.func_106643_z(java.lang.String)char[]
		// @0038: invokestatic game.C_100266_me.func_106642_z(char[])java.lang.String
		// @003B: aastore
		// @003C: dup
		// @003D: iconst_5
		// @003E: ldc "\u007fl\u001e3"
		// @0040: invokestatic game.C_100266_me.func_106643_z(java.lang.String)char[]
		// @0043: invokestatic game.C_100266_me.func_106642_z(char[])java.lang.String
		// @0046: aastore
		// @0047: dup
		// @0048: bipush 6 (0x06)
		// @004A: ldc "M}_\u0006E"
		// @004C: invokestatic game.C_100266_me.func_106643_z(java.lang.String)char[]
		// @004F: invokestatic game.C_100266_me.func_106642_z(char[])java.lang.String
		// @0052: aastore
		// @0053: dup
		// @0054: bipush 7 (0x07)
		// @0056: ldc "Qm\u00187CWk"
		// @0058: invokestatic game.C_100266_me.func_106643_z(java.lang.String)char[]
		// @005B: invokestatic game.C_100266_me.func_106642_z(char[])java.lang.String
		// @005E: aastore
		// @005F: dup
		// @0060: bipush 8 (0x08)
		// @0062: ldc "M}_\u0005E"
		// @0064: invokestatic game.C_100266_me.func_106643_z(java.lang.String)char[]
		// @0067: invokestatic game.C_100266_me.func_106642_z(char[])java.lang.String
		// @006A: aastore
		// @006B: dup
		// @006C: bipush 9 (0x09)
		// @006E: ldc "M}_\u0001E"
		// @0070: invokestatic game.C_100266_me.func_106643_z(java.lang.String)char[]
		// @0073: invokestatic game.C_100266_me.func_106642_z(char[])java.lang.String
		// @0076: aastore
		// @0077: dup
		// @0078: bipush 10 (0x0A)
		// @007A: ldc "M}_\u007f\u0004Nq\u0005}E"
		// @007C: invokestatic game.C_100266_me.func_106643_z(java.lang.String)char[]
		// @007F: invokestatic game.C_100266_me.func_106642_z(char[])java.lang.String
		// @0082: aastore
		// @0083: dup
		// @0084: bipush 11 (0x0B)
		// @0086: ldc "M}_\u0000E"
		// @0088: invokestatic game.C_100266_me.func_106643_z(java.lang.String)char[]
		// @008B: invokestatic game.C_100266_me.func_106642_z(char[])java.lang.String
		// @008E: aastore
		// @008F: dup
		// @0090: bipush 12 (0x0C)
		// @0092: ldc "M}_\u0002E"
		// @0094: invokestatic game.C_100266_me.func_106643_z(java.lang.String)char[]
		// @0097: invokestatic game.C_100266_me.func_106642_z(char[])java.lang.String
		// @009A: aastore
		// @009B: putstatic java.lang.String[] game.C_100266_me.field_106656_z
		// @009E: sipush 2049 (0x0801)
		// @00A1: newarray int[]
		// @00A3: dup
		// @00A4: iconst_0
		// @00A5: iconst_0
		// @00A6: iastore
		// @00A7: dup
		// @00A8: iconst_1
		// @00A9: bipush 50 (0x32)
		// @00AB: iastore
		// @00AC: dup
		// @00AD: iconst_2
		// @00AE: bipush 101 (0x65)
		// @00B0: iastore
		// @00B1: dup
		// @00B2: iconst_3
		// @00B3: sipush 151 (0x0097)
		// @00B6: iastore
		// @00B7: dup
		// @00B8: iconst_4
		// @00B9: sipush 201 (0x00C9)
		// @00BC: iastore
		// @00BD: dup
		// @00BE: iconst_5
		// @00BF: sipush 251 (0x00FB)
		// @00C2: iastore
		// @00C3: dup
		// @00C4: bipush 6 (0x06)
		// @00C6: sipush 302 (0x012E)
		// @00C9: iastore
		// @00CA: dup
		// @00CB: bipush 7 (0x07)
		// @00CD: sipush 352 (0x0160)
		// @00D0: iastore
		// @00D1: dup
		// @00D2: bipush 8 (0x08)
		// @00D4: sipush 402 (0x0192)
		// @00D7: iastore
		// @00D8: dup
		// @00D9: bipush 9 (0x09)
		// @00DB: sipush 452 (0x01C4)
		// @00DE: iastore
		// @00DF: dup
		// @00E0: bipush 10 (0x0A)
		// @00E2: sipush 503 (0x01F7)
		// @00E5: iastore
		// @00E6: dup
		// @00E7: bipush 11 (0x0B)
		// @00E9: sipush 553 (0x0229)
		// @00EC: iastore
		// @00ED: dup
		// @00EE: bipush 12 (0x0C)
		// @00F0: sipush 603 (0x025B)
		// @00F3: iastore
		// @00F4: dup
		// @00F5: bipush 13 (0x0D)
		// @00F7: sipush 653 (0x028D)
		// @00FA: iastore
		// @00FB: dup
		// @00FC: bipush 14 (0x0E)
		// @00FE: sipush 704 (0x02C0)
		// @0101: iastore
		// @0102: dup
		// @0103: bipush 15 (0x0F)
		// @0105: sipush 754 (0x02F2)
		// @0108: iastore
		// @0109: dup
		// @010A: bipush 16 (0x10)
		// @010C: sipush 804 (0x0324)
		// @010F: iastore
		// @0110: dup
		// @0111: bipush 17 (0x11)
		// @0113: sipush 854 (0x0356)
		// @0116: iastore
		// @0117: dup
		// @0118: bipush 18 (0x12)
		// @011A: sipush 905 (0x0389)
		// @011D: iastore
		// @011E: dup
		// @011F: bipush 19 (0x13)
		// @0121: sipush 955 (0x03BB)
		// @0124: iastore
		// @0125: dup
		// @0126: bipush 20 (0x14)
		// @0128: sipush 1005 (0x03ED)
		// @012B: iastore
		// @012C: dup
		// @012D: bipush 21 (0x15)
		// @012F: sipush 1056 (0x0420)
		// @0132: iastore
		// @0133: dup
		// @0134: bipush 22 (0x16)
		// @0136: sipush 1106 (0x0452)
		// @0139: iastore
		// @013A: dup
		// @013B: bipush 23 (0x17)
		// @013D: sipush 1156 (0x0484)
		// @0140: iastore
		// @0141: dup
		// @0142: bipush 24 (0x18)
		// @0144: sipush 1206 (0x04B6)
		// @0147: iastore
		// @0148: dup
		// @0149: bipush 25 (0x19)
		// @014B: sipush 1257 (0x04E9)
		// @014E: iastore
		// @014F: dup
		// @0150: bipush 26 (0x1A)
		// @0152: sipush 1307 (0x051B)
		// @0155: iastore
		// @0156: dup
		// @0157: bipush 27 (0x1B)
		// @0159: sipush 1357 (0x054D)
		// @015C: iastore
		// @015D: dup
		// @015E: bipush 28 (0x1C)
		// @0160: sipush 1407 (0x057F)
		// @0163: iastore
		// @0164: dup
		// @0165: bipush 29 (0x1D)
		// @0167: sipush 1458 (0x05B2)
		// @016A: iastore
		// @016B: dup
		// @016C: bipush 30 (0x1E)
		// @016E: sipush 1508 (0x05E4)
		// @0171: iastore
		// @0172: dup
		// @0173: bipush 31 (0x1F)
		// @0175: sipush 1558 (0x0616)
		// @0178: iastore
		// @0179: dup
		// @017A: bipush 32 (0x20)
		// @017C: sipush 1608 (0x0648)
		// @017F: iastore
		// @0180: dup
		// @0181: bipush 33 (0x21)
		// @0183: sipush 1659 (0x067B)
		// @0186: iastore
		// @0187: dup
		// @0188: bipush 34 (0x22)
		// @018A: sipush 1709 (0x06AD)
		// @018D: iastore
		// @018E: dup
		// @018F: bipush 35 (0x23)
		// @0191: sipush 1759 (0x06DF)
		// @0194: iastore
		// @0195: dup
		// @0196: bipush 36 (0x24)
		// @0198: sipush 1809 (0x0711)
		// @019B: iastore
		// @019C: dup
		// @019D: bipush 37 (0x25)
		// @019F: sipush 1860 (0x0744)
		// @01A2: iastore
		// @01A3: dup
		// @01A4: bipush 38 (0x26)
		// @01A6: sipush 1910 (0x0776)
		// @01A9: iastore
		// @01AA: dup
		// @01AB: bipush 39 (0x27)
		// @01AD: sipush 1960 (0x07A8)
		// @01B0: iastore
		// @01B1: dup
		// @01B2: bipush 40 (0x28)
		// @01B4: sipush 2010 (0x07DA)
		// @01B7: iastore
		// @01B8: dup
		// @01B9: bipush 41 (0x29)
		// @01BB: sipush 2061 (0x080D)
		// @01BE: iastore
		// @01BF: dup
		// @01C0: bipush 42 (0x2A)
		// @01C2: sipush 2111 (0x083F)
		// @01C5: iastore
		// @01C6: dup
		// @01C7: bipush 43 (0x2B)
		// @01C9: sipush 2161 (0x0871)
		// @01CC: iastore
		// @01CD: dup
		// @01CE: bipush 44 (0x2C)
		// @01D0: sipush 2211 (0x08A3)
		// @01D3: iastore
		// @01D4: dup
		// @01D5: bipush 45 (0x2D)
		// @01D7: sipush 2261 (0x08D5)
		// @01DA: iastore
		// @01DB: dup
		// @01DC: bipush 46 (0x2E)
		// @01DE: sipush 2312 (0x0908)
		// @01E1: iastore
		// @01E2: dup
		// @01E3: bipush 47 (0x2F)
		// @01E5: sipush 2362 (0x093A)
		// @01E8: iastore
		// @01E9: dup
		// @01EA: bipush 48 (0x30)
		// @01EC: sipush 2412 (0x096C)
		// @01EF: iastore
		// @01F0: dup
		// @01F1: bipush 49 (0x31)
		// @01F3: sipush 2462 (0x099E)
		// @01F6: iastore
		// @01F7: dup
		// @01F8: bipush 50 (0x32)
		// @01FA: sipush 2513 (0x09D1)
		// @01FD: iastore
		// @01FE: dup
		// @01FF: bipush 51 (0x33)
		// @0201: sipush 2563 (0x0A03)
		// @0204: iastore
		// @0205: dup
		// @0206: bipush 52 (0x34)
		// @0208: sipush 2613 (0x0A35)
		// @020B: iastore
		// @020C: dup
		// @020D: bipush 53 (0x35)
		// @020F: sipush 2663 (0x0A67)
		// @0212: iastore
		// @0213: dup
		// @0214: bipush 54 (0x36)
		// @0216: sipush 2714 (0x0A9A)
		// @0219: iastore
		// @021A: dup
		// @021B: bipush 55 (0x37)
		// @021D: sipush 2764 (0x0ACC)
		// @0220: iastore
		// @0221: dup
		// @0222: bipush 56 (0x38)
		// @0224: sipush 2814 (0x0AFE)
		// @0227: iastore
		// @0228: dup
		// @0229: bipush 57 (0x39)
		// @022B: sipush 2864 (0x0B30)
		// @022E: iastore
		// @022F: dup
		// @0230: bipush 58 (0x3A)
		// @0232: sipush 2914 (0x0B62)
		// @0235: iastore
		// @0236: dup
		// @0237: bipush 59 (0x3B)
		// @0239: sipush 2965 (0x0B95)
		// @023C: iastore
		// @023D: dup
		// @023E: bipush 60 (0x3C)
		// @0240: sipush 3015 (0x0BC7)
		// @0243: iastore
		// @0244: dup
		// @0245: bipush 61 (0x3D)
		// @0247: sipush 3065 (0x0BF9)
		// @024A: iastore
		// @024B: dup
		// @024C: bipush 62 (0x3E)
		// @024E: sipush 3115 (0x0C2B)
		// @0251: iastore
		// @0252: dup
		// @0253: bipush 63 (0x3F)
		// @0255: sipush 3165 (0x0C5D)
		// @0258: iastore
		// @0259: dup
		// @025A: bipush 64 (0x40)
		// @025C: sipush 3216 (0x0C90)
		// @025F: iastore
		// @0260: dup
		// @0261: bipush 65 (0x41)
		// @0263: sipush 3266 (0x0CC2)
		// @0266: iastore
		// @0267: dup
		// @0268: bipush 66 (0x42)
		// @026A: sipush 3316 (0x0CF4)
		// @026D: iastore
		// @026E: dup
		// @026F: bipush 67 (0x43)
		// @0271: sipush 3366 (0x0D26)
		// @0274: iastore
		// @0275: dup
		// @0276: bipush 68 (0x44)
		// @0278: sipush 3417 (0x0D59)
		// @027B: iastore
		// @027C: dup
		// @027D: bipush 69 (0x45)
		// @027F: sipush 3467 (0x0D8B)
		// @0282: iastore
		// @0283: dup
		// @0284: bipush 70 (0x46)
		// @0286: sipush 3517 (0x0DBD)
		// @0289: iastore
		// @028A: dup
		// @028B: bipush 71 (0x47)
		// @028D: sipush 3567 (0x0DEF)
		// @0290: iastore
		// @0291: dup
		// @0292: bipush 72 (0x48)
		// @0294: sipush 3617 (0x0E21)
		// @0297: iastore
		// @0298: dup
		// @0299: bipush 73 (0x49)
		// @029B: sipush 3667 (0x0E53)
		// @029E: iastore
		// @029F: dup
		// @02A0: bipush 74 (0x4A)
		// @02A2: sipush 3718 (0x0E86)
		// @02A5: iastore
		// @02A6: dup
		// @02A7: bipush 75 (0x4B)
		// @02A9: sipush 3768 (0x0EB8)
		// @02AC: iastore
		// @02AD: dup
		// @02AE: bipush 76 (0x4C)
		// @02B0: sipush 3818 (0x0EEA)
		// @02B3: iastore
		// @02B4: dup
		// @02B5: bipush 77 (0x4D)
		// @02B7: sipush 3868 (0x0F1C)
		// @02BA: iastore
		// @02BB: dup
		// @02BC: bipush 78 (0x4E)
		// @02BE: sipush 3918 (0x0F4E)
		// @02C1: iastore
		// @02C2: dup
		// @02C3: bipush 79 (0x4F)
		// @02C5: sipush 3969 (0x0F81)
		// @02C8: iastore
		// @02C9: dup
		// @02CA: bipush 80 (0x50)
		// @02CC: sipush 4019 (0x0FB3)
		// @02CF: iastore
		// @02D0: dup
		// @02D1: bipush 81 (0x51)
		// @02D3: sipush 4069 (0x0FE5)
		// @02D6: iastore
		// @02D7: dup
		// @02D8: bipush 82 (0x52)
		// @02DA: sipush 4119 (0x1017)
		// @02DD: iastore
		// @02DE: dup
		// @02DF: bipush 83 (0x53)
		// @02E1: sipush 4169 (0x1049)
		// @02E4: iastore
		// @02E5: dup
		// @02E6: bipush 84 (0x54)
		// @02E8: sipush 4219 (0x107B)
		// @02EB: iastore
		// @02EC: dup
		// @02ED: bipush 85 (0x55)
		// @02EF: sipush 4270 (0x10AE)
		// @02F2: iastore
		// @02F3: dup
		// @02F4: bipush 86 (0x56)
		// @02F6: sipush 4320 (0x10E0)
		// @02F9: iastore
		// @02FA: dup
		// @02FB: bipush 87 (0x57)
		// @02FD: sipush 4370 (0x1112)
		// @0300: iastore
		// @0301: dup
		// @0302: bipush 88 (0x58)
		// @0304: sipush 4420 (0x1144)
		// @0307: iastore
		// @0308: dup
		// @0309: bipush 89 (0x59)
		// @030B: sipush 4470 (0x1176)
		// @030E: iastore
		// @030F: dup
		// @0310: bipush 90 (0x5A)
		// @0312: sipush 4520 (0x11A8)
		// @0315: iastore
		// @0316: dup
		// @0317: bipush 91 (0x5B)
		// @0319: sipush 4570 (0x11DA)
		// @031C: iastore
		// @031D: dup
		// @031E: bipush 92 (0x5C)
		// @0320: sipush 4621 (0x120D)
		// @0323: iastore
		// @0324: dup
		// @0325: bipush 93 (0x5D)
		// @0327: sipush 4671 (0x123F)
		// @032A: iastore
		// @032B: dup
		// @032C: bipush 94 (0x5E)
		// @032E: sipush 4721 (0x1271)
		// @0331: iastore
		// @0332: dup
		// @0333: bipush 95 (0x5F)
		// @0335: sipush 4771 (0x12A3)
		// @0338: iastore
		// @0339: dup
		// @033A: bipush 96 (0x60)
		// @033C: sipush 4821 (0x12D5)
		// @033F: iastore
		// @0340: dup
		// @0341: bipush 97 (0x61)
		// @0343: sipush 4871 (0x1307)
		// @0346: iastore
		// @0347: dup
		// @0348: bipush 98 (0x62)
		// @034A: sipush 4921 (0x1339)
		// @034D: iastore
		// @034E: dup
		// @034F: bipush 99 (0x63)
		// @0351: sipush 4972 (0x136C)
		// @0354: iastore
		// @0355: dup
		// @0356: bipush 100 (0x64)
		// @0358: sipush 5022 (0x139E)
		// @035B: iastore
		// @035C: dup
		// @035D: bipush 101 (0x65)
		// @035F: sipush 5072 (0x13D0)
		// @0362: iastore
		// @0363: dup
		// @0364: bipush 102 (0x66)
		// @0366: sipush 5122 (0x1402)
		// @0369: iastore
		// @036A: dup
		// @036B: bipush 103 (0x67)
		// @036D: sipush 5172 (0x1434)
		// @0370: iastore
		// @0371: dup
		// @0372: bipush 104 (0x68)
		// @0374: sipush 5222 (0x1466)
		// @0377: iastore
		// @0378: dup
		// @0379: bipush 105 (0x69)
		// @037B: sipush 5272 (0x1498)
		// @037E: iastore
		// @037F: dup
		// @0380: bipush 106 (0x6A)
		// @0382: sipush 5322 (0x14CA)
		// @0385: iastore
		// @0386: dup
		// @0387: bipush 107 (0x6B)
		// @0389: sipush 5372 (0x14FC)
		// @038C: iastore
		// @038D: dup
		// @038E: bipush 108 (0x6C)
		// @0390: sipush 5422 (0x152E)
		// @0393: iastore
		// @0394: dup
		// @0395: bipush 109 (0x6D)
		// @0397: sipush 5473 (0x1561)
		// @039A: iastore
		// @039B: dup
		// @039C: bipush 110 (0x6E)
		// @039E: sipush 5523 (0x1593)
		// @03A1: iastore
		// @03A2: dup
		// @03A3: bipush 111 (0x6F)
		// @03A5: sipush 5573 (0x15C5)
		// @03A8: iastore
		// @03A9: dup
		// @03AA: bipush 112 (0x70)
		// @03AC: sipush 5623 (0x15F7)
		// @03AF: iastore
		// @03B0: dup
		// @03B1: bipush 113 (0x71)
		// @03B3: sipush 5673 (0x1629)
		// @03B6: iastore
		// @03B7: dup
		// @03B8: bipush 114 (0x72)
		// @03BA: sipush 5723 (0x165B)
		// @03BD: iastore
		// @03BE: dup
		// @03BF: bipush 115 (0x73)
		// @03C1: sipush 5773 (0x168D)
		// @03C4: iastore
		// @03C5: dup
		// @03C6: bipush 116 (0x74)
		// @03C8: sipush 5823 (0x16BF)
		// @03CB: iastore
		// @03CC: dup
		// @03CD: bipush 117 (0x75)
		// @03CF: sipush 5873 (0x16F1)
		// @03D2: iastore
		// @03D3: dup
		// @03D4: bipush 118 (0x76)
		// @03D6: sipush 5923 (0x1723)
		// @03D9: iastore
		// @03DA: dup
		// @03DB: bipush 119 (0x77)
		// @03DD: sipush 5973 (0x1755)
		// @03E0: iastore
		// @03E1: dup
		// @03E2: bipush 120 (0x78)
		// @03E4: sipush 6023 (0x1787)
		// @03E7: iastore
		// @03E8: dup
		// @03E9: bipush 121 (0x79)
		// @03EB: sipush 6073 (0x17B9)
		// @03EE: iastore
		// @03EF: dup
		// @03F0: bipush 122 (0x7A)
		// @03F2: sipush 6123 (0x17EB)
		// @03F5: iastore
		// @03F6: dup
		// @03F7: bipush 123 (0x7B)
		// @03F9: sipush 6173 (0x181D)
		// @03FC: iastore
		// @03FD: dup
		// @03FE: bipush 124 (0x7C)
		// @0400: sipush 6224 (0x1850)
		// @0403: iastore
		// @0404: dup
		// @0405: bipush 125 (0x7D)
		// @0407: sipush 6274 (0x1882)
		// @040A: iastore
		// @040B: dup
		// @040C: bipush 126 (0x7E)
		// @040E: sipush 6324 (0x18B4)
		// @0411: iastore
		// @0412: dup
		// @0413: bipush 127 (0x7F)
		// @0415: sipush 6374 (0x18E6)
		// @0418: iastore
		// @0419: dup
		// @041A: sipush 128 (0x0080)
		// @041D: sipush 6424 (0x1918)
		// @0420: iastore
		// @0421: dup
		// @0422: sipush 129 (0x0081)
		// @0425: sipush 6474 (0x194A)
		// @0428: iastore
		// @0429: dup
		// @042A: sipush 130 (0x0082)
		// @042D: sipush 6524 (0x197C)
		// @0430: iastore
		// @0431: dup
		// @0432: sipush 131 (0x0083)
		// @0435: sipush 6574 (0x19AE)
		// @0438: iastore
		// @0439: dup
		// @043A: sipush 132 (0x0084)
		// @043D: sipush 6624 (0x19E0)
		// @0440: iastore
		// @0441: dup
		// @0442: sipush 133 (0x0085)
		// @0445: sipush 6674 (0x1A12)
		// @0448: iastore
		// @0449: dup
		// @044A: sipush 134 (0x0086)
		// @044D: sipush 6724 (0x1A44)
		// @0450: iastore
		// @0451: dup
		// @0452: sipush 135 (0x0087)
		// @0455: sipush 6774 (0x1A76)
		// @0458: iastore
		// @0459: dup
		// @045A: sipush 136 (0x0088)
		// @045D: sipush 6824 (0x1AA8)
		// @0460: iastore
		// @0461: dup
		// @0462: sipush 137 (0x0089)
		// @0465: sipush 6874 (0x1ADA)
		// @0468: iastore
		// @0469: dup
		// @046A: sipush 138 (0x008A)
		// @046D: sipush 6924 (0x1B0C)
		// @0470: iastore
		// @0471: dup
		// @0472: sipush 139 (0x008B)
		// @0475: sipush 6974 (0x1B3E)
		// @0478: iastore
		// @0479: dup
		// @047A: sipush 140 (0x008C)
		// @047D: sipush 7024 (0x1B70)
		// @0480: iastore
		// @0481: dup
		// @0482: sipush 141 (0x008D)
		// @0485: sipush 7074 (0x1BA2)
		// @0488: iastore
		// @0489: dup
		// @048A: sipush 142 (0x008E)
		// @048D: sipush 7124 (0x1BD4)
		// @0490: iastore
		// @0491: dup
		// @0492: sipush 143 (0x008F)
		// @0495: sipush 7174 (0x1C06)
		// @0498: iastore
		// @0499: dup
		// @049A: sipush 144 (0x0090)
		// @049D: sipush 7224 (0x1C38)
		// @04A0: iastore
		// @04A1: dup
		// @04A2: sipush 145 (0x0091)
		// @04A5: sipush 7273 (0x1C69)
		// @04A8: iastore
		// @04A9: dup
		// @04AA: sipush 146 (0x0092)
		// @04AD: sipush 7323 (0x1C9B)
		// @04B0: iastore
		// @04B1: dup
		// @04B2: sipush 147 (0x0093)
		// @04B5: sipush 7373 (0x1CCD)
		// @04B8: iastore
		// @04B9: dup
		// @04BA: sipush 148 (0x0094)
		// @04BD: sipush 7423 (0x1CFF)
		// @04C0: iastore
		// @04C1: dup
		// @04C2: sipush 149 (0x0095)
		// @04C5: sipush 7473 (0x1D31)
		// @04C8: iastore
		// @04C9: dup
		// @04CA: sipush 150 (0x0096)
		// @04CD: sipush 7523 (0x1D63)
		// @04D0: iastore
		// @04D1: dup
		// @04D2: sipush 151 (0x0097)
		// @04D5: sipush 7573 (0x1D95)
		// @04D8: iastore
		// @04D9: dup
		// @04DA: sipush 152 (0x0098)
		// @04DD: sipush 7623 (0x1DC7)
		// @04E0: iastore
		// @04E1: dup
		// @04E2: sipush 153 (0x0099)
		// @04E5: sipush 7673 (0x1DF9)
		// @04E8: iastore
		// @04E9: dup
		// @04EA: sipush 154 (0x009A)
		// @04ED: sipush 7723 (0x1E2B)
		// @04F0: iastore
		// @04F1: dup
		// @04F2: sipush 155 (0x009B)
		// @04F5: sipush 7773 (0x1E5D)
		// @04F8: iastore
		// @04F9: dup
		// @04FA: sipush 156 (0x009C)
		// @04FD: sipush 7823 (0x1E8F)
		// @0500: iastore
		// @0501: dup
		// @0502: sipush 157 (0x009D)
		// @0505: sipush 7873 (0x1EC1)
		// @0508: iastore
		// @0509: dup
		// @050A: sipush 158 (0x009E)
		// @050D: sipush 7923 (0x1EF3)
		// @0510: iastore
		// @0511: dup
		// @0512: sipush 159 (0x009F)
		// @0515: sipush 7972 (0x1F24)
		// @0518: iastore
		// @0519: dup
		// @051A: sipush 160 (0x00A0)
		// @051D: sipush 8022 (0x1F56)
		// @0520: iastore
		// @0521: dup
		// @0522: sipush 161 (0x00A1)
		// @0525: sipush 8072 (0x1F88)
		// @0528: iastore
		// @0529: dup
		// @052A: sipush 162 (0x00A2)
		// @052D: sipush 8122 (0x1FBA)
		// @0530: iastore
		// @0531: dup
		// @0532: sipush 163 (0x00A3)
		// @0535: sipush 8172 (0x1FEC)
		// @0538: iastore
		// @0539: dup
		// @053A: sipush 164 (0x00A4)
		// @053D: sipush 8222 (0x201E)
		// @0540: iastore
		// @0541: dup
		// @0542: sipush 165 (0x00A5)
		// @0545: sipush 8272 (0x2050)
		// @0548: iastore
		// @0549: dup
		// @054A: sipush 166 (0x00A6)
		// @054D: sipush 8322 (0x2082)
		// @0550: iastore
		// @0551: dup
		// @0552: sipush 167 (0x00A7)
		// @0555: sipush 8371 (0x20B3)
		// @0558: iastore
		// @0559: dup
		// @055A: sipush 168 (0x00A8)
		// @055D: sipush 8421 (0x20E5)
		// @0560: iastore
		// @0561: dup
		// @0562: sipush 169 (0x00A9)
		// @0565: sipush 8471 (0x2117)
		// @0568: iastore
		// @0569: dup
		// @056A: sipush 170 (0x00AA)
		// @056D: sipush 8521 (0x2149)
		// @0570: iastore
		// @0571: dup
		// @0572: sipush 171 (0x00AB)
		// @0575: sipush 8571 (0x217B)
		// @0578: iastore
		// @0579: dup
		// @057A: sipush 172 (0x00AC)
		// @057D: sipush 8621 (0x21AD)
		// @0580: iastore
		// @0581: dup
		// @0582: sipush 173 (0x00AD)
		// @0585: sipush 8670 (0x21DE)
		// @0588: iastore
		// @0589: dup
		// @058A: sipush 174 (0x00AE)
		// @058D: sipush 8720 (0x2210)
		// @0590: iastore
		// @0591: dup
		// @0592: sipush 175 (0x00AF)
		// @0595: sipush 8770 (0x2242)
		// @0598: iastore
		// @0599: dup
		// @059A: sipush 176 (0x00B0)
		// @059D: sipush 8820 (0x2274)
		// @05A0: iastore
		// @05A1: dup
		// @05A2: sipush 177 (0x00B1)
		// @05A5: sipush 8870 (0x22A6)
		// @05A8: iastore
		// @05A9: dup
		// @05AA: sipush 178 (0x00B2)
		// @05AD: sipush 8919 (0x22D7)
		// @05B0: iastore
		// @05B1: dup
		// @05B2: sipush 179 (0x00B3)
		// @05B5: sipush 8969 (0x2309)
		// @05B8: iastore
		// @05B9: dup
		// @05BA: sipush 180 (0x00B4)
		// @05BD: sipush 9019 (0x233B)
		// @05C0: iastore
		// @05C1: dup
		// @05C2: sipush 181 (0x00B5)
		// @05C5: sipush 9069 (0x236D)
		// @05C8: iastore
		// @05C9: dup
		// @05CA: sipush 182 (0x00B6)
		// @05CD: sipush 9119 (0x239F)
		// @05D0: iastore
		// @05D1: dup
		// @05D2: sipush 183 (0x00B7)
		// @05D5: sipush 9168 (0x23D0)
		// @05D8: iastore
		// @05D9: dup
		// @05DA: sipush 184 (0x00B8)
		// @05DD: sipush 9218 (0x2402)
		// @05E0: iastore
		// @05E1: dup
		// @05E2: sipush 185 (0x00B9)
		// @05E5: sipush 9268 (0x2434)
		// @05E8: iastore
		// @05E9: dup
		// @05EA: sipush 186 (0x00BA)
		// @05ED: sipush 9318 (0x2466)
		// @05F0: iastore
		// @05F1: dup
		// @05F2: sipush 187 (0x00BB)
		// @05F5: sipush 9367 (0x2497)
		// @05F8: iastore
		// @05F9: dup
		// @05FA: sipush 188 (0x00BC)
		// @05FD: sipush 9417 (0x24C9)
		// @0600: iastore
		// @0601: dup
		// @0602: sipush 189 (0x00BD)
		// @0605: sipush 9467 (0x24FB)
		// @0608: iastore
		// @0609: dup
		// @060A: sipush 190 (0x00BE)
		// @060D: sipush 9517 (0x252D)
		// @0610: iastore
		// @0611: dup
		// @0612: sipush 191 (0x00BF)
		// @0615: sipush 9566 (0x255E)
		// @0618: iastore
		// @0619: dup
		// @061A: sipush 192 (0x00C0)
		// @061D: sipush 9616 (0x2590)
		// @0620: iastore
		// @0621: dup
		// @0622: sipush 193 (0x00C1)
		// @0625: sipush 9666 (0x25C2)
		// @0628: iastore
		// @0629: dup
		// @062A: sipush 194 (0x00C2)
		// @062D: sipush 9716 (0x25F4)
		// @0630: iastore
		// @0631: dup
		// @0632: sipush 195 (0x00C3)
		// @0635: sipush 9765 (0x2625)
		// @0638: iastore
		// @0639: dup
		// @063A: sipush 196 (0x00C4)
		// @063D: sipush 9815 (0x2657)
		// @0640: iastore
		// @0641: dup
		// @0642: sipush 197 (0x00C5)
		// @0645: sipush 9865 (0x2689)
		// @0648: iastore
		// @0649: dup
		// @064A: sipush 198 (0x00C6)
		// @064D: sipush 9914 (0x26BA)
		// @0650: iastore
		// @0651: dup
		// @0652: sipush 199 (0x00C7)
		// @0655: sipush 9964 (0x26EC)
		// @0658: iastore
		// @0659: dup
		// @065A: sipush 200 (0x00C8)
		// @065D: sipush 10014 (0x271E)
		// @0660: iastore
		// @0661: dup
		// @0662: sipush 201 (0x00C9)
		// @0665: sipush 10063 (0x274F)
		// @0668: iastore
		// @0669: dup
		// @066A: sipush 202 (0x00CA)
		// @066D: sipush 10113 (0x2781)
		// @0670: iastore
		// @0671: dup
		// @0672: sipush 203 (0x00CB)
		// @0675: sipush 10163 (0x27B3)
		// @0678: iastore
		// @0679: dup
		// @067A: sipush 204 (0x00CC)
		// @067D: sipush 10212 (0x27E4)
		// @0680: iastore
		// @0681: dup
		// @0682: sipush 205 (0x00CD)
		// @0685: sipush 10262 (0x2816)
		// @0688: iastore
		// @0689: dup
		// @068A: sipush 206 (0x00CE)
		// @068D: sipush 10312 (0x2848)
		// @0690: iastore
		// @0691: dup
		// @0692: sipush 207 (0x00CF)
		// @0695: sipush 10361 (0x2879)
		// @0698: iastore
		// @0699: dup
		// @069A: sipush 208 (0x00D0)
		// @069D: sipush 10411 (0x28AB)
		// @06A0: iastore
		// @06A1: dup
		// @06A2: sipush 209 (0x00D1)
		// @06A5: sipush 10461 (0x28DD)
		// @06A8: iastore
		// @06A9: dup
		// @06AA: sipush 210 (0x00D2)
		// @06AD: sipush 10510 (0x290E)
		// @06B0: iastore
		// @06B1: dup
		// @06B2: sipush 211 (0x00D3)
		// @06B5: sipush 10560 (0x2940)
		// @06B8: iastore
		// @06B9: dup
		// @06BA: sipush 212 (0x00D4)
		// @06BD: sipush 10609 (0x2971)
		// @06C0: iastore
		// @06C1: dup
		// @06C2: sipush 213 (0x00D5)
		// @06C5: sipush 10659 (0x29A3)
		// @06C8: iastore
		// @06C9: dup
		// @06CA: sipush 214 (0x00D6)
		// @06CD: sipush 10709 (0x29D5)
		// @06D0: iastore
		// @06D1: dup
		// @06D2: sipush 215 (0x00D7)
		// @06D5: sipush 10758 (0x2A06)
		// @06D8: iastore
		// @06D9: dup
		// @06DA: sipush 216 (0x00D8)
		// @06DD: sipush 10808 (0x2A38)
		// @06E0: iastore
		// @06E1: dup
		// @06E2: sipush 217 (0x00D9)
		// @06E5: sipush 10857 (0x2A69)
		// @06E8: iastore
		// @06E9: dup
		// @06EA: sipush 218 (0x00DA)
		// @06ED: sipush 10907 (0x2A9B)
		// @06F0: iastore
		// @06F1: dup
		// @06F2: sipush 219 (0x00DB)
		// @06F5: sipush 10956 (0x2ACC)
		// @06F8: iastore
		// @06F9: dup
		// @06FA: sipush 220 (0x00DC)
		// @06FD: sipush 11006 (0x2AFE)
		// @0700: iastore
		// @0701: dup
		// @0702: sipush 221 (0x00DD)
		// @0705: sipush 11056 (0x2B30)
		// @0708: iastore
		// @0709: dup
		// @070A: sipush 222 (0x00DE)
		// @070D: sipush 11105 (0x2B61)
		// @0710: iastore
		// @0711: dup
		// @0712: sipush 223 (0x00DF)
		// @0715: sipush 11155 (0x2B93)
		// @0718: iastore
		// @0719: dup
		// @071A: sipush 224 (0x00E0)
		// @071D: sipush 11204 (0x2BC4)
		// @0720: iastore
		// @0721: dup
		// @0722: sipush 225 (0x00E1)
		// @0725: sipush 11254 (0x2BF6)
		// @0728: iastore
		// @0729: dup
		// @072A: sipush 226 (0x00E2)
		// @072D: sipush 11303 (0x2C27)
		// @0730: iastore
		// @0731: dup
		// @0732: sipush 227 (0x00E3)
		// @0735: sipush 11353 (0x2C59)
		// @0738: iastore
		// @0739: dup
		// @073A: sipush 228 (0x00E4)
		// @073D: sipush 11402 (0x2C8A)
		// @0740: iastore
		// @0741: dup
		// @0742: sipush 229 (0x00E5)
		// @0745: sipush 11452 (0x2CBC)
		// @0748: iastore
		// @0749: dup
		// @074A: sipush 230 (0x00E6)
		// @074D: sipush 11501 (0x2CED)
		// @0750: iastore
		// @0751: dup
		// @0752: sipush 231 (0x00E7)
		// @0755: sipush 11551 (0x2D1F)
		// @0758: iastore
		// @0759: dup
		// @075A: sipush 232 (0x00E8)
		// @075D: sipush 11600 (0x2D50)
		// @0760: iastore
		// @0761: dup
		// @0762: sipush 233 (0x00E9)
		// @0765: sipush 11650 (0x2D82)
		// @0768: iastore
		// @0769: dup
		// @076A: sipush 234 (0x00EA)
		// @076D: sipush 11699 (0x2DB3)
		// @0770: iastore
		// @0771: dup
		// @0772: sipush 235 (0x00EB)
		// @0775: sipush 11749 (0x2DE5)
		// @0778: iastore
		// @0779: dup
		// @077A: sipush 236 (0x00EC)
		// @077D: sipush 11798 (0x2E16)
		// @0780: iastore
		// @0781: dup
		// @0782: sipush 237 (0x00ED)
		// @0785: sipush 11847 (0x2E47)
		// @0788: iastore
		// @0789: dup
		// @078A: sipush 238 (0x00EE)
		// @078D: sipush 11897 (0x2E79)
		// @0790: iastore
		// @0791: dup
		// @0792: sipush 239 (0x00EF)
		// @0795: sipush 11946 (0x2EAA)
		// @0798: iastore
		// @0799: dup
		// @079A: sipush 240 (0x00F0)
		// @079D: sipush 11996 (0x2EDC)
		// @07A0: iastore
		// @07A1: dup
		// @07A2: sipush 241 (0x00F1)
		// @07A5: sipush 12045 (0x2F0D)
		// @07A8: iastore
		// @07A9: dup
		// @07AA: sipush 242 (0x00F2)
		// @07AD: sipush 12095 (0x2F3F)
		// @07B0: iastore
		// @07B1: dup
		// @07B2: sipush 243 (0x00F3)
		// @07B5: sipush 12144 (0x2F70)
		// @07B8: iastore
		// @07B9: dup
		// @07BA: sipush 244 (0x00F4)
		// @07BD: sipush 12193 (0x2FA1)
		// @07C0: iastore
		// @07C1: dup
		// @07C2: sipush 245 (0x00F5)
		// @07C5: sipush 12243 (0x2FD3)
		// @07C8: iastore
		// @07C9: dup
		// @07CA: sipush 246 (0x00F6)
		// @07CD: sipush 12292 (0x3004)
		// @07D0: iastore
		// @07D1: dup
		// @07D2: sipush 247 (0x00F7)
		// @07D5: sipush 12341 (0x3035)
		// @07D8: iastore
		// @07D9: dup
		// @07DA: sipush 248 (0x00F8)
		// @07DD: sipush 12391 (0x3067)
		// @07E0: iastore
		// @07E1: dup
		// @07E2: sipush 249 (0x00F9)
		// @07E5: sipush 12440 (0x3098)
		// @07E8: iastore
		// @07E9: dup
		// @07EA: sipush 250 (0x00FA)
		// @07ED: sipush 12490 (0x30CA)
		// @07F0: iastore
		// @07F1: dup
		// @07F2: sipush 251 (0x00FB)
		// @07F5: sipush 12539 (0x30FB)
		// @07F8: iastore
		// @07F9: dup
		// @07FA: sipush 252 (0x00FC)
		// @07FD: sipush 12588 (0x312C)
		// @0800: iastore
		// @0801: dup
		// @0802: sipush 253 (0x00FD)
		// @0805: sipush 12638 (0x315E)
		// @0808: iastore
		// @0809: dup
		// @080A: sipush 254 (0x00FE)
		// @080D: sipush 12687 (0x318F)
		// @0810: iastore
		// @0811: dup
		// @0812: sipush 255 (0x00FF)
		// @0815: sipush 12736 (0x31C0)
		// @0818: iastore
		// @0819: dup
		// @081A: sipush 256 (0x0100)
		// @081D: sipush 12785 (0x31F1)
		// @0820: iastore
		// @0821: dup
		// @0822: sipush 257 (0x0101)
		// @0825: sipush 12835 (0x3223)
		// @0828: iastore
		// @0829: dup
		// @082A: sipush 258 (0x0102)
		// @082D: sipush 12884 (0x3254)
		// @0830: iastore
		// @0831: dup
		// @0832: sipush 259 (0x0103)
		// @0835: sipush 12933 (0x3285)
		// @0838: iastore
		// @0839: dup
		// @083A: sipush 260 (0x0104)
		// @083D: sipush 12983 (0x32B7)
		// @0840: iastore
		// @0841: dup
		// @0842: sipush 261 (0x0105)
		// @0845: sipush 13032 (0x32E8)
		// @0848: iastore
		// @0849: dup
		// @084A: sipush 262 (0x0106)
		// @084D: sipush 13081 (0x3319)
		// @0850: iastore
		// @0851: dup
		// @0852: sipush 263 (0x0107)
		// @0855: sipush 13130 (0x334A)
		// @0858: iastore
		// @0859: dup
		// @085A: sipush 264 (0x0108)
		// @085D: sipush 13180 (0x337C)
		// @0860: iastore
		// @0861: dup
		// @0862: sipush 265 (0x0109)
		// @0865: sipush 13229 (0x33AD)
		// @0868: iastore
		// @0869: dup
		// @086A: sipush 266 (0x010A)
		// @086D: sipush 13278 (0x33DE)
		// @0870: iastore
		// @0871: dup
		// @0872: sipush 267 (0x010B)
		// @0875: sipush 13327 (0x340F)
		// @0878: iastore
		// @0879: dup
		// @087A: sipush 268 (0x010C)
		// @087D: sipush 13376 (0x3440)
		// @0880: iastore
		// @0881: dup
		// @0882: sipush 269 (0x010D)
		// @0885: sipush 13426 (0x3472)
		// @0888: iastore
		// @0889: dup
		// @088A: sipush 270 (0x010E)
		// @088D: sipush 13475 (0x34A3)
		// @0890: iastore
		// @0891: dup
		// @0892: sipush 271 (0x010F)
		// @0895: sipush 13524 (0x34D4)
		// @0898: iastore
		// @0899: dup
		// @089A: sipush 272 (0x0110)
		// @089D: sipush 13573 (0x3505)
		// @08A0: iastore
		// @08A1: dup
		// @08A2: sipush 273 (0x0111)
		// @08A5: sipush 13622 (0x3536)
		// @08A8: iastore
		// @08A9: dup
		// @08AA: sipush 274 (0x0112)
		// @08AD: sipush 13672 (0x3568)
		// @08B0: iastore
		// @08B1: dup
		// @08B2: sipush 275 (0x0113)
		// @08B5: sipush 13721 (0x3599)
		// @08B8: iastore
		// @08B9: dup
		// @08BA: sipush 276 (0x0114)
		// @08BD: sipush 13770 (0x35CA)
		// @08C0: iastore
		// @08C1: dup
		// @08C2: sipush 277 (0x0115)
		// @08C5: sipush 13819 (0x35FB)
		// @08C8: iastore
		// @08C9: dup
		// @08CA: sipush 278 (0x0116)
		// @08CD: sipush 13868 (0x362C)
		// @08D0: iastore
		// @08D1: dup
		// @08D2: sipush 279 (0x0117)
		// @08D5: sipush 13917 (0x365D)
		// @08D8: iastore
		// @08D9: dup
		// @08DA: sipush 280 (0x0118)
		// @08DD: sipush 13966 (0x368E)
		// @08E0: iastore
		// @08E1: dup
		// @08E2: sipush 281 (0x0119)
		// @08E5: sipush 14016 (0x36C0)
		// @08E8: iastore
		// @08E9: dup
		// @08EA: sipush 282 (0x011A)
		// @08ED: sipush 14065 (0x36F1)
		// @08F0: iastore
		// @08F1: dup
		// @08F2: sipush 283 (0x011B)
		// @08F5: sipush 14114 (0x3722)
		// @08F8: iastore
		// @08F9: dup
		// @08FA: sipush 284 (0x011C)
		// @08FD: sipush 14163 (0x3753)
		// @0900: iastore
		// @0901: dup
		// @0902: sipush 285 (0x011D)
		// @0905: sipush 14212 (0x3784)
		// @0908: iastore
		// @0909: dup
		// @090A: sipush 286 (0x011E)
		// @090D: sipush 14261 (0x37B5)
		// @0910: iastore
		// @0911: dup
		// @0912: sipush 287 (0x011F)
		// @0915: sipush 14310 (0x37E6)
		// @0918: iastore
		// @0919: dup
		// @091A: sipush 288 (0x0120)
		// @091D: sipush 14359 (0x3817)
		// @0920: iastore
		// @0921: dup
		// @0922: sipush 289 (0x0121)
		// @0925: sipush 14408 (0x3848)
		// @0928: iastore
		// @0929: dup
		// @092A: sipush 290 (0x0122)
		// @092D: sipush 14457 (0x3879)
		// @0930: iastore
		// @0931: dup
		// @0932: sipush 291 (0x0123)
		// @0935: sipush 14506 (0x38AA)
		// @0938: iastore
		// @0939: dup
		// @093A: sipush 292 (0x0124)
		// @093D: sipush 14555 (0x38DB)
		// @0940: iastore
		// @0941: dup
		// @0942: sipush 293 (0x0125)
		// @0945: sipush 14604 (0x390C)
		// @0948: iastore
		// @0949: dup
		// @094A: sipush 294 (0x0126)
		// @094D: sipush 14653 (0x393D)
		// @0950: iastore
		// @0951: dup
		// @0952: sipush 295 (0x0127)
		// @0955: sipush 14702 (0x396E)
		// @0958: iastore
		// @0959: dup
		// @095A: sipush 296 (0x0128)
		// @095D: sipush 14751 (0x399F)
		// @0960: iastore
		// @0961: dup
		// @0962: sipush 297 (0x0129)
		// @0965: sipush 14800 (0x39D0)
		// @0968: iastore
		// @0969: dup
		// @096A: sipush 298 (0x012A)
		// @096D: sipush 14849 (0x3A01)
		// @0970: iastore
		// @0971: dup
		// @0972: sipush 299 (0x012B)
		// @0975: sipush 14898 (0x3A32)
		// @0978: iastore
		// @0979: dup
		// @097A: sipush 300 (0x012C)
		// @097D: sipush 14947 (0x3A63)
		// @0980: iastore
		// @0981: dup
		// @0982: sipush 301 (0x012D)
		// @0985: sipush 14996 (0x3A94)
		// @0988: iastore
		// @0989: dup
		// @098A: sipush 302 (0x012E)
		// @098D: sipush 15045 (0x3AC5)
		// @0990: iastore
		// @0991: dup
		// @0992: sipush 303 (0x012F)
		// @0995: sipush 15094 (0x3AF6)
		// @0998: iastore
		// @0999: dup
		// @099A: sipush 304 (0x0130)
		// @099D: sipush 15143 (0x3B27)
		// @09A0: iastore
		// @09A1: dup
		// @09A2: sipush 305 (0x0131)
		// @09A5: sipush 15192 (0x3B58)
		// @09A8: iastore
		// @09A9: dup
		// @09AA: sipush 306 (0x0132)
		// @09AD: sipush 15240 (0x3B88)
		// @09B0: iastore
		// @09B1: dup
		// @09B2: sipush 307 (0x0133)
		// @09B5: sipush 15289 (0x3BB9)
		// @09B8: iastore
		// @09B9: dup
		// @09BA: sipush 308 (0x0134)
		// @09BD: sipush 15338 (0x3BEA)
		// @09C0: iastore
		// @09C1: dup
		// @09C2: sipush 309 (0x0135)
		// @09C5: sipush 15387 (0x3C1B)
		// @09C8: iastore
		// @09C9: dup
		// @09CA: sipush 310 (0x0136)
		// @09CD: sipush 15436 (0x3C4C)
		// @09D0: iastore
		// @09D1: dup
		// @09D2: sipush 311 (0x0137)
		// @09D5: sipush 15485 (0x3C7D)
		// @09D8: iastore
		// @09D9: dup
		// @09DA: sipush 312 (0x0138)
		// @09DD: sipush 15534 (0x3CAE)
		// @09E0: iastore
		// @09E1: dup
		// @09E2: sipush 313 (0x0139)
		// @09E5: sipush 15582 (0x3CDE)
		// @09E8: iastore
		// @09E9: dup
		// @09EA: sipush 314 (0x013A)
		// @09ED: sipush 15631 (0x3D0F)
		// @09F0: iastore
		// @09F1: dup
		// @09F2: sipush 315 (0x013B)
		// @09F5: sipush 15680 (0x3D40)
		// @09F8: iastore
		// @09F9: dup
		// @09FA: sipush 316 (0x013C)
		// @09FD: sipush 15729 (0x3D71)
		// @0A00: iastore
		// @0A01: dup
		// @0A02: sipush 317 (0x013D)
		// @0A05: sipush 15778 (0x3DA2)
		// @0A08: iastore
		// @0A09: dup
		// @0A0A: sipush 318 (0x013E)
		// @0A0D: sipush 15826 (0x3DD2)
		// @0A10: iastore
		// @0A11: dup
		// @0A12: sipush 319 (0x013F)
		// @0A15: sipush 15875 (0x3E03)
		// @0A18: iastore
		// @0A19: dup
		// @0A1A: sipush 320 (0x0140)
		// @0A1D: sipush 15924 (0x3E34)
		// @0A20: iastore
		// @0A21: dup
		// @0A22: sipush 321 (0x0141)
		// @0A25: sipush 15973 (0x3E65)
		// @0A28: iastore
		// @0A29: dup
		// @0A2A: sipush 322 (0x0142)
		// @0A2D: sipush 16021 (0x3E95)
		// @0A30: iastore
		// @0A31: dup
		// @0A32: sipush 323 (0x0143)
		// @0A35: sipush 16070 (0x3EC6)
		// @0A38: iastore
		// @0A39: dup
		// @0A3A: sipush 324 (0x0144)
		// @0A3D: sipush 16119 (0x3EF7)
		// @0A40: iastore
		// @0A41: dup
		// @0A42: sipush 325 (0x0145)
		// @0A45: sipush 16168 (0x3F28)
		// @0A48: iastore
		// @0A49: dup
		// @0A4A: sipush 326 (0x0146)
		// @0A4D: sipush 16216 (0x3F58)
		// @0A50: iastore
		// @0A51: dup
		// @0A52: sipush 327 (0x0147)
		// @0A55: sipush 16265 (0x3F89)
		// @0A58: iastore
		// @0A59: dup
		// @0A5A: sipush 328 (0x0148)
		// @0A5D: sipush 16314 (0x3FBA)
		// @0A60: iastore
		// @0A61: dup
		// @0A62: sipush 329 (0x0149)
		// @0A65: sipush 16362 (0x3FEA)
		// @0A68: iastore
		// @0A69: dup
		// @0A6A: sipush 330 (0x014A)
		// @0A6D: sipush 16411 (0x401B)
		// @0A70: iastore
		// @0A71: dup
		// @0A72: sipush 331 (0x014B)
		// @0A75: sipush 16460 (0x404C)
		// @0A78: iastore
		// @0A79: dup
		// @0A7A: sipush 332 (0x014C)
		// @0A7D: sipush 16508 (0x407C)
		// @0A80: iastore
		// @0A81: dup
		// @0A82: sipush 333 (0x014D)
		// @0A85: sipush 16557 (0x40AD)
		// @0A88: iastore
		// @0A89: dup
		// @0A8A: sipush 334 (0x014E)
		// @0A8D: sipush 16606 (0x40DE)
		// @0A90: iastore
		// @0A91: dup
		// @0A92: sipush 335 (0x014F)
		// @0A95: sipush 16654 (0x410E)
		// @0A98: iastore
		// @0A99: dup
		// @0A9A: sipush 336 (0x0150)
		// @0A9D: sipush 16703 (0x413F)
		// @0AA0: iastore
		// @0AA1: dup
		// @0AA2: sipush 337 (0x0151)
		// @0AA5: sipush 16751 (0x416F)
		// @0AA8: iastore
		// @0AA9: dup
		// @0AAA: sipush 338 (0x0152)
		// @0AAD: sipush 16800 (0x41A0)
		// @0AB0: iastore
		// @0AB1: dup
		// @0AB2: sipush 339 (0x0153)
		// @0AB5: sipush 16849 (0x41D1)
		// @0AB8: iastore
		// @0AB9: dup
		// @0ABA: sipush 340 (0x0154)
		// @0ABD: sipush 16897 (0x4201)
		// @0AC0: iastore
		// @0AC1: dup
		// @0AC2: sipush 341 (0x0155)
		// @0AC5: sipush 16946 (0x4232)
		// @0AC8: iastore
		// @0AC9: dup
		// @0ACA: sipush 342 (0x0156)
		// @0ACD: sipush 16994 (0x4262)
		// @0AD0: iastore
		// @0AD1: dup
		// @0AD2: sipush 343 (0x0157)
		// @0AD5: sipush 17043 (0x4293)
		// @0AD8: iastore
		// @0AD9: dup
		// @0ADA: sipush 344 (0x0158)
		// @0ADD: sipush 17091 (0x42C3)
		// @0AE0: iastore
		// @0AE1: dup
		// @0AE2: sipush 345 (0x0159)
		// @0AE5: sipush 17140 (0x42F4)
		// @0AE8: iastore
		// @0AE9: dup
		// @0AEA: sipush 346 (0x015A)
		// @0AED: sipush 17188 (0x4324)
		// @0AF0: iastore
		// @0AF1: dup
		// @0AF2: sipush 347 (0x015B)
		// @0AF5: sipush 17237 (0x4355)
		// @0AF8: iastore
		// @0AF9: dup
		// @0AFA: sipush 348 (0x015C)
		// @0AFD: sipush 17285 (0x4385)
		// @0B00: iastore
		// @0B01: dup
		// @0B02: sipush 349 (0x015D)
		// @0B05: sipush 17334 (0x43B6)
		// @0B08: iastore
		// @0B09: dup
		// @0B0A: sipush 350 (0x015E)
		// @0B0D: sipush 17382 (0x43E6)
		// @0B10: iastore
		// @0B11: dup
		// @0B12: sipush 351 (0x015F)
		// @0B15: sipush 17431 (0x4417)
		// @0B18: iastore
		// @0B19: dup
		// @0B1A: sipush 352 (0x0160)
		// @0B1D: sipush 17479 (0x4447)
		// @0B20: iastore
		// @0B21: dup
		// @0B22: sipush 353 (0x0161)
		// @0B25: sipush 17528 (0x4478)
		// @0B28: iastore
		// @0B29: dup
		// @0B2A: sipush 354 (0x0162)
		// @0B2D: sipush 17576 (0x44A8)
		// @0B30: iastore
		// @0B31: dup
		// @0B32: sipush 355 (0x0163)
		// @0B35: sipush 17625 (0x44D9)
		// @0B38: iastore
		// @0B39: dup
		// @0B3A: sipush 356 (0x0164)
		// @0B3D: sipush 17673 (0x4509)
		// @0B40: iastore
		// @0B41: dup
		// @0B42: sipush 357 (0x0165)
		// @0B45: sipush 17721 (0x4539)
		// @0B48: iastore
		// @0B49: dup
		// @0B4A: sipush 358 (0x0166)
		// @0B4D: sipush 17770 (0x456A)
		// @0B50: iastore
		// @0B51: dup
		// @0B52: sipush 359 (0x0167)
		// @0B55: sipush 17818 (0x459A)
		// @0B58: iastore
		// @0B59: dup
		// @0B5A: sipush 360 (0x0168)
		// @0B5D: sipush 17867 (0x45CB)
		// @0B60: iastore
		// @0B61: dup
		// @0B62: sipush 361 (0x0169)
		// @0B65: sipush 17915 (0x45FB)
		// @0B68: iastore
		// @0B69: dup
		// @0B6A: sipush 362 (0x016A)
		// @0B6D: sipush 17963 (0x462B)
		// @0B70: iastore
		// @0B71: dup
		// @0B72: sipush 363 (0x016B)
		// @0B75: sipush 18012 (0x465C)
		// @0B78: iastore
		// @0B79: dup
		// @0B7A: sipush 364 (0x016C)
		// @0B7D: sipush 18060 (0x468C)
		// @0B80: iastore
		// @0B81: dup
		// @0B82: sipush 365 (0x016D)
		// @0B85: sipush 18108 (0x46BC)
		// @0B88: iastore
		// @0B89: dup
		// @0B8A: sipush 366 (0x016E)
		// @0B8D: sipush 18156 (0x46EC)
		// @0B90: iastore
		// @0B91: dup
		// @0B92: sipush 367 (0x016F)
		// @0B95: sipush 18205 (0x471D)
		// @0B98: iastore
		// @0B99: dup
		// @0B9A: sipush 368 (0x0170)
		// @0B9D: sipush 18253 (0x474D)
		// @0BA0: iastore
		// @0BA1: dup
		// @0BA2: sipush 369 (0x0171)
		// @0BA5: sipush 18301 (0x477D)
		// @0BA8: iastore
		// @0BA9: dup
		// @0BAA: sipush 370 (0x0172)
		// @0BAD: sipush 18350 (0x47AE)
		// @0BB0: iastore
		// @0BB1: dup
		// @0BB2: sipush 371 (0x0173)
		// @0BB5: sipush 18398 (0x47DE)
		// @0BB8: iastore
		// @0BB9: dup
		// @0BBA: sipush 372 (0x0174)
		// @0BBD: sipush 18446 (0x480E)
		// @0BC0: iastore
		// @0BC1: dup
		// @0BC2: sipush 373 (0x0175)
		// @0BC5: sipush 18494 (0x483E)
		// @0BC8: iastore
		// @0BC9: dup
		// @0BCA: sipush 374 (0x0176)
		// @0BCD: sipush 18543 (0x486F)
		// @0BD0: iastore
		// @0BD1: dup
		// @0BD2: sipush 375 (0x0177)
		// @0BD5: sipush 18591 (0x489F)
		// @0BD8: iastore
		// @0BD9: dup
		// @0BDA: sipush 376 (0x0178)
		// @0BDD: sipush 18639 (0x48CF)
		// @0BE0: iastore
		// @0BE1: dup
		// @0BE2: sipush 377 (0x0179)
		// @0BE5: sipush 18687 (0x48FF)
		// @0BE8: iastore
		// @0BE9: dup
		// @0BEA: sipush 378 (0x017A)
		// @0BED: sipush 18735 (0x492F)
		// @0BF0: iastore
		// @0BF1: dup
		// @0BF2: sipush 379 (0x017B)
		// @0BF5: sipush 18783 (0x495F)
		// @0BF8: iastore
		// @0BF9: dup
		// @0BFA: sipush 380 (0x017C)
		// @0BFD: sipush 18832 (0x4990)
		// @0C00: iastore
		// @0C01: dup
		// @0C02: sipush 381 (0x017D)
		// @0C05: sipush 18880 (0x49C0)
		// @0C08: iastore
		// @0C09: dup
		// @0C0A: sipush 382 (0x017E)
		// @0C0D: sipush 18928 (0x49F0)
		// @0C10: iastore
		// @0C11: dup
		// @0C12: sipush 383 (0x017F)
		// @0C15: sipush 18976 (0x4A20)
		// @0C18: iastore
		// @0C19: dup
		// @0C1A: sipush 384 (0x0180)
		// @0C1D: sipush 19024 (0x4A50)
		// @0C20: iastore
		// @0C21: dup
		// @0C22: sipush 385 (0x0181)
		// @0C25: sipush 19072 (0x4A80)
		// @0C28: iastore
		// @0C29: dup
		// @0C2A: sipush 386 (0x0182)
		// @0C2D: sipush 19120 (0x4AB0)
		// @0C30: iastore
		// @0C31: dup
		// @0C32: sipush 387 (0x0183)
		// @0C35: sipush 19168 (0x4AE0)
		// @0C38: iastore
		// @0C39: dup
		// @0C3A: sipush 388 (0x0184)
		// @0C3D: sipush 19216 (0x4B10)
		// @0C40: iastore
		// @0C41: dup
		// @0C42: sipush 389 (0x0185)
		// @0C45: sipush 19264 (0x4B40)
		// @0C48: iastore
		// @0C49: dup
		// @0C4A: sipush 390 (0x0186)
		// @0C4D: sipush 19313 (0x4B71)
		// @0C50: iastore
		// @0C51: dup
		// @0C52: sipush 391 (0x0187)
		// @0C55: sipush 19361 (0x4BA1)
		// @0C58: iastore
		// @0C59: dup
		// @0C5A: sipush 392 (0x0188)
		// @0C5D: sipush 19409 (0x4BD1)
		// @0C60: iastore
		// @0C61: dup
		// @0C62: sipush 393 (0x0189)
		// @0C65: sipush 19457 (0x4C01)
		// @0C68: iastore
		// @0C69: dup
		// @0C6A: sipush 394 (0x018A)
		// @0C6D: sipush 19505 (0x4C31)
		// @0C70: iastore
		// @0C71: dup
		// @0C72: sipush 395 (0x018B)
		// @0C75: sipush 19553 (0x4C61)
		// @0C78: iastore
		// @0C79: dup
		// @0C7A: sipush 396 (0x018C)
		// @0C7D: sipush 19600 (0x4C90)
		// @0C80: iastore
		// @0C81: dup
		// @0C82: sipush 397 (0x018D)
		// @0C85: sipush 19648 (0x4CC0)
		// @0C88: iastore
		// @0C89: dup
		// @0C8A: sipush 398 (0x018E)
		// @0C8D: sipush 19696 (0x4CF0)
		// @0C90: iastore
		// @0C91: dup
		// @0C92: sipush 399 (0x018F)
		// @0C95: sipush 19744 (0x4D20)
		// @0C98: iastore
		// @0C99: dup
		// @0C9A: sipush 400 (0x0190)
		// @0C9D: sipush 19792 (0x4D50)
		// @0CA0: iastore
		// @0CA1: dup
		// @0CA2: sipush 401 (0x0191)
		// @0CA5: sipush 19840 (0x4D80)
		// @0CA8: iastore
		// @0CA9: dup
		// @0CAA: sipush 402 (0x0192)
		// @0CAD: sipush 19888 (0x4DB0)
		// @0CB0: iastore
		// @0CB1: dup
		// @0CB2: sipush 403 (0x0193)
		// @0CB5: sipush 19936 (0x4DE0)
		// @0CB8: iastore
		// @0CB9: dup
		// @0CBA: sipush 404 (0x0194)
		// @0CBD: sipush 19984 (0x4E10)
		// @0CC0: iastore
		// @0CC1: dup
		// @0CC2: sipush 405 (0x0195)
		// @0CC5: sipush 20032 (0x4E40)
		// @0CC8: iastore
		// @0CC9: dup
		// @0CCA: sipush 406 (0x0196)
		// @0CCD: sipush 20080 (0x4E70)
		// @0CD0: iastore
		// @0CD1: dup
		// @0CD2: sipush 407 (0x0197)
		// @0CD5: sipush 20127 (0x4E9F)
		// @0CD8: iastore
		// @0CD9: dup
		// @0CDA: sipush 408 (0x0198)
		// @0CDD: sipush 20175 (0x4ECF)
		// @0CE0: iastore
		// @0CE1: dup
		// @0CE2: sipush 409 (0x0199)
		// @0CE5: sipush 20223 (0x4EFF)
		// @0CE8: iastore
		// @0CE9: dup
		// @0CEA: sipush 410 (0x019A)
		// @0CED: sipush 20271 (0x4F2F)
		// @0CF0: iastore
		// @0CF1: dup
		// @0CF2: sipush 411 (0x019B)
		// @0CF5: sipush 20319 (0x4F5F)
		// @0CF8: iastore
		// @0CF9: dup
		// @0CFA: sipush 412 (0x019C)
		// @0CFD: sipush 20366 (0x4F8E)
		// @0D00: iastore
		// @0D01: dup
		// @0D02: sipush 413 (0x019D)
		// @0D05: sipush 20414 (0x4FBE)
		// @0D08: iastore
		// @0D09: dup
		// @0D0A: sipush 414 (0x019E)
		// @0D0D: sipush 20462 (0x4FEE)
		// @0D10: iastore
		// @0D11: dup
		// @0D12: sipush 415 (0x019F)
		// @0D15: sipush 20510 (0x501E)
		// @0D18: iastore
		// @0D19: dup
		// @0D1A: sipush 416 (0x01A0)
		// @0D1D: sipush 20557 (0x504D)
		// @0D20: iastore
		// @0D21: dup
		// @0D22: sipush 417 (0x01A1)
		// @0D25: sipush 20605 (0x507D)
		// @0D28: iastore
		// @0D29: dup
		// @0D2A: sipush 418 (0x01A2)
		// @0D2D: sipush 20653 (0x50AD)
		// @0D30: iastore
		// @0D31: dup
		// @0D32: sipush 419 (0x01A3)
		// @0D35: sipush 20701 (0x50DD)
		// @0D38: iastore
		// @0D39: dup
		// @0D3A: sipush 420 (0x01A4)
		// @0D3D: sipush 20748 (0x510C)
		// @0D40: iastore
		// @0D41: dup
		// @0D42: sipush 421 (0x01A5)
		// @0D45: sipush 20796 (0x513C)
		// @0D48: iastore
		// @0D49: dup
		// @0D4A: sipush 422 (0x01A6)
		// @0D4D: sipush 20844 (0x516C)
		// @0D50: iastore
		// @0D51: dup
		// @0D52: sipush 423 (0x01A7)
		// @0D55: sipush 20891 (0x519B)
		// @0D58: iastore
		// @0D59: dup
		// @0D5A: sipush 424 (0x01A8)
		// @0D5D: sipush 20939 (0x51CB)
		// @0D60: iastore
		// @0D61: dup
		// @0D62: sipush 425 (0x01A9)
		// @0D65: sipush 20987 (0x51FB)
		// @0D68: iastore
		// @0D69: dup
		// @0D6A: sipush 426 (0x01AA)
		// @0D6D: sipush 21034 (0x522A)
		// @0D70: iastore
		// @0D71: dup
		// @0D72: sipush 427 (0x01AB)
		// @0D75: sipush 21082 (0x525A)
		// @0D78: iastore
		// @0D79: dup
		// @0D7A: sipush 428 (0x01AC)
		// @0D7D: sipush 21129 (0x5289)
		// @0D80: iastore
		// @0D81: dup
		// @0D82: sipush 429 (0x01AD)
		// @0D85: sipush 21177 (0x52B9)
		// @0D88: iastore
		// @0D89: dup
		// @0D8A: sipush 430 (0x01AE)
		// @0D8D: sipush 21224 (0x52E8)
		// @0D90: iastore
		// @0D91: dup
		// @0D92: sipush 431 (0x01AF)
		// @0D95: sipush 21272 (0x5318)
		// @0D98: iastore
		// @0D99: dup
		// @0D9A: sipush 432 (0x01B0)
		// @0D9D: sipush 21320 (0x5348)
		// @0DA0: iastore
		// @0DA1: dup
		// @0DA2: sipush 433 (0x01B1)
		// @0DA5: sipush 21367 (0x5377)
		// @0DA8: iastore
		// @0DA9: dup
		// @0DAA: sipush 434 (0x01B2)
		// @0DAD: sipush 21415 (0x53A7)
		// @0DB0: iastore
		// @0DB1: dup
		// @0DB2: sipush 435 (0x01B3)
		// @0DB5: sipush 21462 (0x53D6)
		// @0DB8: iastore
		// @0DB9: dup
		// @0DBA: sipush 436 (0x01B4)
		// @0DBD: sipush 21510 (0x5406)
		// @0DC0: iastore
		// @0DC1: dup
		// @0DC2: sipush 437 (0x01B5)
		// @0DC5: sipush 21557 (0x5435)
		// @0DC8: iastore
		// @0DC9: dup
		// @0DCA: sipush 438 (0x01B6)
		// @0DCD: sipush 21604 (0x5464)
		// @0DD0: iastore
		// @0DD1: dup
		// @0DD2: sipush 439 (0x01B7)
		// @0DD5: sipush 21652 (0x5494)
		// @0DD8: iastore
		// @0DD9: dup
		// @0DDA: sipush 440 (0x01B8)
		// @0DDD: sipush 21699 (0x54C3)
		// @0DE0: iastore
		// @0DE1: dup
		// @0DE2: sipush 441 (0x01B9)
		// @0DE5: sipush 21747 (0x54F3)
		// @0DE8: iastore
		// @0DE9: dup
		// @0DEA: sipush 442 (0x01BA)
		// @0DED: sipush 21794 (0x5522)
		// @0DF0: iastore
		// @0DF1: dup
		// @0DF2: sipush 443 (0x01BB)
		// @0DF5: sipush 21842 (0x5552)
		// @0DF8: iastore
		// @0DF9: dup
		// @0DFA: sipush 444 (0x01BC)
		// @0DFD: sipush 21889 (0x5581)
		// @0E00: iastore
		// @0E01: dup
		// @0E02: sipush 445 (0x01BD)
		// @0E05: sipush 21936 (0x55B0)
		// @0E08: iastore
		// @0E09: dup
		// @0E0A: sipush 446 (0x01BE)
		// @0E0D: sipush 21984 (0x55E0)
		// @0E10: iastore
		// @0E11: dup
		// @0E12: sipush 447 (0x01BF)
		// @0E15: sipush 22031 (0x560F)
		// @0E18: iastore
		// @0E19: dup
		// @0E1A: sipush 448 (0x01C0)
		// @0E1D: sipush 22078 (0x563E)
		// @0E20: iastore
		// @0E21: dup
		// @0E22: sipush 449 (0x01C1)
		// @0E25: sipush 22126 (0x566E)
		// @0E28: iastore
		// @0E29: dup
		// @0E2A: sipush 450 (0x01C2)
		// @0E2D: sipush 22173 (0x569D)
		// @0E30: iastore
		// @0E31: dup
		// @0E32: sipush 451 (0x01C3)
		// @0E35: sipush 22220 (0x56CC)
		// @0E38: iastore
		// @0E39: dup
		// @0E3A: sipush 452 (0x01C4)
		// @0E3D: sipush 22268 (0x56FC)
		// @0E40: iastore
		// @0E41: dup
		// @0E42: sipush 453 (0x01C5)
		// @0E45: sipush 22315 (0x572B)
		// @0E48: iastore
		// @0E49: dup
		// @0E4A: sipush 454 (0x01C6)
		// @0E4D: sipush 22362 (0x575A)
		// @0E50: iastore
		// @0E51: dup
		// @0E52: sipush 455 (0x01C7)
		// @0E55: sipush 22409 (0x5789)
		// @0E58: iastore
		// @0E59: dup
		// @0E5A: sipush 456 (0x01C8)
		// @0E5D: sipush 22457 (0x57B9)
		// @0E60: iastore
		// @0E61: dup
		// @0E62: sipush 457 (0x01C9)
		// @0E65: sipush 22504 (0x57E8)
		// @0E68: iastore
		// @0E69: dup
		// @0E6A: sipush 458 (0x01CA)
		// @0E6D: sipush 22551 (0x5817)
		// @0E70: iastore
		// @0E71: dup
		// @0E72: sipush 459 (0x01CB)
		// @0E75: sipush 22598 (0x5846)
		// @0E78: iastore
		// @0E79: dup
		// @0E7A: sipush 460 (0x01CC)
		// @0E7D: sipush 22645 (0x5875)
		// @0E80: iastore
		// @0E81: dup
		// @0E82: sipush 461 (0x01CD)
		// @0E85: sipush 22693 (0x58A5)
		// @0E88: iastore
		// @0E89: dup
		// @0E8A: sipush 462 (0x01CE)
		// @0E8D: sipush 22740 (0x58D4)
		// @0E90: iastore
		// @0E91: dup
		// @0E92: sipush 463 (0x01CF)
		// @0E95: sipush 22787 (0x5903)
		// @0E98: iastore
		// @0E99: dup
		// @0E9A: sipush 464 (0x01D0)
		// @0E9D: sipush 22834 (0x5932)
		// @0EA0: iastore
		// @0EA1: dup
		// @0EA2: sipush 465 (0x01D1)
		// @0EA5: sipush 22881 (0x5961)
		// @0EA8: iastore
		// @0EA9: dup
		// @0EAA: sipush 466 (0x01D2)
		// @0EAD: sipush 22928 (0x5990)
		// @0EB0: iastore
		// @0EB1: dup
		// @0EB2: sipush 467 (0x01D3)
		// @0EB5: sipush 22975 (0x59BF)
		// @0EB8: iastore
		// @0EB9: dup
		// @0EBA: sipush 468 (0x01D4)
		// @0EBD: sipush 23022 (0x59EE)
		// @0EC0: iastore
		// @0EC1: dup
		// @0EC2: sipush 469 (0x01D5)
		// @0EC5: sipush 23069 (0x5A1D)
		// @0EC8: iastore
		// @0EC9: dup
		// @0ECA: sipush 470 (0x01D6)
		// @0ECD: sipush 23116 (0x5A4C)
		// @0ED0: iastore
		// @0ED1: dup
		// @0ED2: sipush 471 (0x01D7)
		// @0ED5: sipush 23163 (0x5A7B)
		// @0ED8: iastore
		// @0ED9: dup
		// @0EDA: sipush 472 (0x01D8)
		// @0EDD: sipush 23210 (0x5AAA)
		// @0EE0: iastore
		// @0EE1: dup
		// @0EE2: sipush 473 (0x01D9)
		// @0EE5: sipush 23257 (0x5AD9)
		// @0EE8: iastore
		// @0EE9: dup
		// @0EEA: sipush 474 (0x01DA)
		// @0EED: sipush 23304 (0x5B08)
		// @0EF0: iastore
		// @0EF1: dup
		// @0EF2: sipush 475 (0x01DB)
		// @0EF5: sipush 23351 (0x5B37)
		// @0EF8: iastore
		// @0EF9: dup
		// @0EFA: sipush 476 (0x01DC)
		// @0EFD: sipush 23398 (0x5B66)
		// @0F00: iastore
		// @0F01: dup
		// @0F02: sipush 477 (0x01DD)
		// @0F05: sipush 23445 (0x5B95)
		// @0F08: iastore
		// @0F09: dup
		// @0F0A: sipush 478 (0x01DE)
		// @0F0D: sipush 23492 (0x5BC4)
		// @0F10: iastore
		// @0F11: dup
		// @0F12: sipush 479 (0x01DF)
		// @0F15: sipush 23539 (0x5BF3)
		// @0F18: iastore
		// @0F19: dup
		// @0F1A: sipush 480 (0x01E0)
		// @0F1D: sipush 23586 (0x5C22)
		// @0F20: iastore
		// @0F21: dup
		// @0F22: sipush 481 (0x01E1)
		// @0F25: sipush 23633 (0x5C51)
		// @0F28: iastore
		// @0F29: dup
		// @0F2A: sipush 482 (0x01E2)
		// @0F2D: sipush 23680 (0x5C80)
		// @0F30: iastore
		// @0F31: dup
		// @0F32: sipush 483 (0x01E3)
		// @0F35: sipush 23727 (0x5CAF)
		// @0F38: iastore
		// @0F39: dup
		// @0F3A: sipush 484 (0x01E4)
		// @0F3D: sipush 23774 (0x5CDE)
		// @0F40: iastore
		// @0F41: dup
		// @0F42: sipush 485 (0x01E5)
		// @0F45: sipush 23820 (0x5D0C)
		// @0F48: iastore
		// @0F49: dup
		// @0F4A: sipush 486 (0x01E6)
		// @0F4D: sipush 23867 (0x5D3B)
		// @0F50: iastore
		// @0F51: dup
		// @0F52: sipush 487 (0x01E7)
		// @0F55: sipush 23914 (0x5D6A)
		// @0F58: iastore
		// @0F59: dup
		// @0F5A: sipush 488 (0x01E8)
		// @0F5D: sipush 23961 (0x5D99)
		// @0F60: iastore
		// @0F61: dup
		// @0F62: sipush 489 (0x01E9)
		// @0F65: sipush 24008 (0x5DC8)
		// @0F68: iastore
		// @0F69: dup
		// @0F6A: sipush 490 (0x01EA)
		// @0F6D: sipush 24054 (0x5DF6)
		// @0F70: iastore
		// @0F71: dup
		// @0F72: sipush 491 (0x01EB)
		// @0F75: sipush 24101 (0x5E25)
		// @0F78: iastore
		// @0F79: dup
		// @0F7A: sipush 492 (0x01EC)
		// @0F7D: sipush 24148 (0x5E54)
		// @0F80: iastore
		// @0F81: dup
		// @0F82: sipush 493 (0x01ED)
		// @0F85: sipush 24195 (0x5E83)
		// @0F88: iastore
		// @0F89: dup
		// @0F8A: sipush 494 (0x01EE)
		// @0F8D: sipush 24241 (0x5EB1)
		// @0F90: iastore
		// @0F91: dup
		// @0F92: sipush 495 (0x01EF)
		// @0F95: sipush 24288 (0x5EE0)
		// @0F98: iastore
		// @0F99: dup
		// @0F9A: sipush 496 (0x01F0)
		// @0F9D: sipush 24335 (0x5F0F)
		// @0FA0: iastore
		// @0FA1: dup
		// @0FA2: sipush 497 (0x01F1)
		// @0FA5: sipush 24381 (0x5F3D)
		// @0FA8: iastore
		// @0FA9: dup
		// @0FAA: sipush 498 (0x01F2)
		// @0FAD: sipush 24428 (0x5F6C)
		// @0FB0: iastore
		// @0FB1: dup
		// @0FB2: sipush 499 (0x01F3)
		// @0FB5: sipush 24475 (0x5F9B)
		// @0FB8: iastore
		// @0FB9: dup
		// @0FBA: sipush 500 (0x01F4)
		// @0FBD: sipush 24521 (0x5FC9)
		// @0FC0: iastore
		// @0FC1: dup
		// @0FC2: sipush 501 (0x01F5)
		// @0FC5: sipush 24568 (0x5FF8)
		// @0FC8: iastore
		// @0FC9: dup
		// @0FCA: sipush 502 (0x01F6)
		// @0FCD: sipush 24614 (0x6026)
		// @0FD0: iastore
		// @0FD1: dup
		// @0FD2: sipush 503 (0x01F7)
		// @0FD5: sipush 24661 (0x6055)
		// @0FD8: iastore
		// @0FD9: dup
		// @0FDA: sipush 504 (0x01F8)
		// @0FDD: sipush 24708 (0x6084)
		// @0FE0: iastore
		// @0FE1: dup
		// @0FE2: sipush 505 (0x01F9)
		// @0FE5: sipush 24754 (0x60B2)
		// @0FE8: iastore
		// @0FE9: dup
		// @0FEA: sipush 506 (0x01FA)
		// @0FED: sipush 24801 (0x60E1)
		// @0FF0: iastore
		// @0FF1: dup
		// @0FF2: sipush 507 (0x01FB)
		// @0FF5: sipush 24847 (0x610F)
		// @0FF8: iastore
		// @0FF9: dup
		// @0FFA: sipush 508 (0x01FC)
		// @0FFD: sipush 24894 (0x613E)
		// @1000: iastore
		// @1001: dup
		// @1002: sipush 509 (0x01FD)
		// @1005: sipush 24940 (0x616C)
		// @1008: iastore
		// @1009: dup
		// @100A: sipush 510 (0x01FE)
		// @100D: sipush 24987 (0x619B)
		// @1010: iastore
		// @1011: dup
		// @1012: sipush 511 (0x01FF)
		// @1015: sipush 25033 (0x61C9)
		// @1018: iastore
		// @1019: dup
		// @101A: sipush 512 (0x0200)
		// @101D: sipush 25080 (0x61F8)
		// @1020: iastore
		// @1021: dup
		// @1022: sipush 513 (0x0201)
		// @1025: sipush 25126 (0x6226)
		// @1028: iastore
		// @1029: dup
		// @102A: sipush 514 (0x0202)
		// @102D: sipush 25172 (0x6254)
		// @1030: iastore
		// @1031: dup
		// @1032: sipush 515 (0x0203)
		// @1035: sipush 25219 (0x6283)
		// @1038: iastore
		// @1039: dup
		// @103A: sipush 516 (0x0204)
		// @103D: sipush 25265 (0x62B1)
		// @1040: iastore
		// @1041: dup
		// @1042: sipush 517 (0x0205)
		// @1045: sipush 25312 (0x62E0)
		// @1048: iastore
		// @1049: dup
		// @104A: sipush 518 (0x0206)
		// @104D: sipush 25358 (0x630E)
		// @1050: iastore
		// @1051: dup
		// @1052: sipush 519 (0x0207)
		// @1055: sipush 25404 (0x633C)
		// @1058: iastore
		// @1059: dup
		// @105A: sipush 520 (0x0208)
		// @105D: sipush 25451 (0x636B)
		// @1060: iastore
		// @1061: dup
		// @1062: sipush 521 (0x0209)
		// @1065: sipush 25497 (0x6399)
		// @1068: iastore
		// @1069: dup
		// @106A: sipush 522 (0x020A)
		// @106D: sipush 25543 (0x63C7)
		// @1070: iastore
		// @1071: dup
		// @1072: sipush 523 (0x020B)
		// @1075: sipush 25589 (0x63F5)
		// @1078: iastore
		// @1079: dup
		// @107A: sipush 524 (0x020C)
		// @107D: sipush 25636 (0x6424)
		// @1080: iastore
		// @1081: dup
		// @1082: sipush 525 (0x020D)
		// @1085: sipush 25682 (0x6452)
		// @1088: iastore
		// @1089: dup
		// @108A: sipush 526 (0x020E)
		// @108D: sipush 25728 (0x6480)
		// @1090: iastore
		// @1091: dup
		// @1092: sipush 527 (0x020F)
		// @1095: sipush 25774 (0x64AE)
		// @1098: iastore
		// @1099: dup
		// @109A: sipush 528 (0x0210)
		// @109D: sipush 25821 (0x64DD)
		// @10A0: iastore
		// @10A1: dup
		// @10A2: sipush 529 (0x0211)
		// @10A5: sipush 25867 (0x650B)
		// @10A8: iastore
		// @10A9: dup
		// @10AA: sipush 530 (0x0212)
		// @10AD: sipush 25913 (0x6539)
		// @10B0: iastore
		// @10B1: dup
		// @10B2: sipush 531 (0x0213)
		// @10B5: sipush 25959 (0x6567)
		// @10B8: iastore
		// @10B9: dup
		// @10BA: sipush 532 (0x0214)
		// @10BD: sipush 26005 (0x6595)
		// @10C0: iastore
		// @10C1: dup
		// @10C2: sipush 533 (0x0215)
		// @10C5: sipush 26051 (0x65C3)
		// @10C8: iastore
		// @10C9: dup
		// @10CA: sipush 534 (0x0216)
		// @10CD: sipush 26098 (0x65F2)
		// @10D0: iastore
		// @10D1: dup
		// @10D2: sipush 535 (0x0217)
		// @10D5: sipush 26144 (0x6620)
		// @10D8: iastore
		// @10D9: dup
		// @10DA: sipush 536 (0x0218)
		// @10DD: sipush 26190 (0x664E)
		// @10E0: iastore
		// @10E1: dup
		// @10E2: sipush 537 (0x0219)
		// @10E5: sipush 26236 (0x667C)
		// @10E8: iastore
		// @10E9: dup
		// @10EA: sipush 538 (0x021A)
		// @10ED: sipush 26282 (0x66AA)
		// @10F0: iastore
		// @10F1: dup
		// @10F2: sipush 539 (0x021B)
		// @10F5: sipush 26328 (0x66D8)
		// @10F8: iastore
		// @10F9: dup
		// @10FA: sipush 540 (0x021C)
		// @10FD: sipush 26374 (0x6706)
		// @1100: iastore
		// @1101: dup
		// @1102: sipush 541 (0x021D)
		// @1105: sipush 26420 (0x6734)
		// @1108: iastore
		// @1109: dup
		// @110A: sipush 542 (0x021E)
		// @110D: sipush 26466 (0x6762)
		// @1110: iastore
		// @1111: dup
		// @1112: sipush 543 (0x021F)
		// @1115: sipush 26512 (0x6790)
		// @1118: iastore
		// @1119: dup
		// @111A: sipush 544 (0x0220)
		// @111D: sipush 26558 (0x67BE)
		// @1120: iastore
		// @1121: dup
		// @1122: sipush 545 (0x0221)
		// @1125: sipush 26604 (0x67EC)
		// @1128: iastore
		// @1129: dup
		// @112A: sipush 546 (0x0222)
		// @112D: sipush 26650 (0x681A)
		// @1130: iastore
		// @1131: dup
		// @1132: sipush 547 (0x0223)
		// @1135: sipush 26696 (0x6848)
		// @1138: iastore
		// @1139: dup
		// @113A: sipush 548 (0x0224)
		// @113D: sipush 26742 (0x6876)
		// @1140: iastore
		// @1141: dup
		// @1142: sipush 549 (0x0225)
		// @1145: sipush 26787 (0x68A3)
		// @1148: iastore
		// @1149: dup
		// @114A: sipush 550 (0x0226)
		// @114D: sipush 26833 (0x68D1)
		// @1150: iastore
		// @1151: dup
		// @1152: sipush 551 (0x0227)
		// @1155: sipush 26879 (0x68FF)
		// @1158: iastore
		// @1159: dup
		// @115A: sipush 552 (0x0228)
		// @115D: sipush 26925 (0x692D)
		// @1160: iastore
		// @1161: dup
		// @1162: sipush 553 (0x0229)
		// @1165: sipush 26971 (0x695B)
		// @1168: iastore
		// @1169: dup
		// @116A: sipush 554 (0x022A)
		// @116D: sipush 27017 (0x6989)
		// @1170: iastore
		// @1171: dup
		// @1172: sipush 555 (0x022B)
		// @1175: sipush 27062 (0x69B6)
		// @1178: iastore
		// @1179: dup
		// @117A: sipush 556 (0x022C)
		// @117D: sipush 27108 (0x69E4)
		// @1180: iastore
		// @1181: dup
		// @1182: sipush 557 (0x022D)
		// @1185: sipush 27154 (0x6A12)
		// @1188: iastore
		// @1189: dup
		// @118A: sipush 558 (0x022E)
		// @118D: sipush 27200 (0x6A40)
		// @1190: iastore
		// @1191: dup
		// @1192: sipush 559 (0x022F)
		// @1195: sipush 27245 (0x6A6D)
		// @1198: iastore
		// @1199: dup
		// @119A: sipush 560 (0x0230)
		// @119D: sipush 27291 (0x6A9B)
		// @11A0: iastore
		// @11A1: dup
		// @11A2: sipush 561 (0x0231)
		// @11A5: sipush 27337 (0x6AC9)
		// @11A8: iastore
		// @11A9: dup
		// @11AA: sipush 562 (0x0232)
		// @11AD: sipush 27382 (0x6AF6)
		// @11B0: iastore
		// @11B1: dup
		// @11B2: sipush 563 (0x0233)
		// @11B5: sipush 27428 (0x6B24)
		// @11B8: iastore
		// @11B9: dup
		// @11BA: sipush 564 (0x0234)
		// @11BD: sipush 27474 (0x6B52)
		// @11C0: iastore
		// @11C1: dup
		// @11C2: sipush 565 (0x0235)
		// @11C5: sipush 27519 (0x6B7F)
		// @11C8: iastore
		// @11C9: dup
		// @11CA: sipush 566 (0x0236)
		// @11CD: sipush 27565 (0x6BAD)
		// @11D0: iastore
		// @11D1: dup
		// @11D2: sipush 567 (0x0237)
		// @11D5: sipush 27611 (0x6BDB)
		// @11D8: iastore
		// @11D9: dup
		// @11DA: sipush 568 (0x0238)
		// @11DD: sipush 27656 (0x6C08)
		// @11E0: iastore
		// @11E1: dup
		// @11E2: sipush 569 (0x0239)
		// @11E5: sipush 27702 (0x6C36)
		// @11E8: iastore
		// @11E9: dup
		// @11EA: sipush 570 (0x023A)
		// @11ED: sipush 27747 (0x6C63)
		// @11F0: iastore
		// @11F1: dup
		// @11F2: sipush 571 (0x023B)
		// @11F5: sipush 27793 (0x6C91)
		// @11F8: iastore
		// @11F9: dup
		// @11FA: sipush 572 (0x023C)
		// @11FD: sipush 27838 (0x6CBE)
		// @1200: iastore
		// @1201: dup
		// @1202: sipush 573 (0x023D)
		// @1205: sipush 27884 (0x6CEC)
		// @1208: iastore
		// @1209: dup
		// @120A: sipush 574 (0x023E)
		// @120D: sipush 27929 (0x6D19)
		// @1210: iastore
		// @1211: dup
		// @1212: sipush 575 (0x023F)
		// @1215: sipush 27975 (0x6D47)
		// @1218: iastore
		// @1219: dup
		// @121A: sipush 576 (0x0240)
		// @121D: sipush 28020 (0x6D74)
		// @1220: iastore
		// @1221: dup
		// @1222: sipush 577 (0x0241)
		// @1225: sipush 28066 (0x6DA2)
		// @1228: iastore
		// @1229: dup
		// @122A: sipush 578 (0x0242)
		// @122D: sipush 28111 (0x6DCF)
		// @1230: iastore
		// @1231: dup
		// @1232: sipush 579 (0x0243)
		// @1235: sipush 28156 (0x6DFC)
		// @1238: iastore
		// @1239: dup
		// @123A: sipush 580 (0x0244)
		// @123D: sipush 28202 (0x6E2A)
		// @1240: iastore
		// @1241: dup
		// @1242: sipush 581 (0x0245)
		// @1245: sipush 28247 (0x6E57)
		// @1248: iastore
		// @1249: dup
		// @124A: sipush 582 (0x0246)
		// @124D: sipush 28293 (0x6E85)
		// @1250: iastore
		// @1251: dup
		// @1252: sipush 583 (0x0247)
		// @1255: sipush 28338 (0x6EB2)
		// @1258: iastore
		// @1259: dup
		// @125A: sipush 584 (0x0248)
		// @125D: sipush 28383 (0x6EDF)
		// @1260: iastore
		// @1261: dup
		// @1262: sipush 585 (0x0249)
		// @1265: sipush 28429 (0x6F0D)
		// @1268: iastore
		// @1269: dup
		// @126A: sipush 586 (0x024A)
		// @126D: sipush 28474 (0x6F3A)
		// @1270: iastore
		// @1271: dup
		// @1272: sipush 587 (0x024B)
		// @1275: sipush 28519 (0x6F67)
		// @1278: iastore
		// @1279: dup
		// @127A: sipush 588 (0x024C)
		// @127D: sipush 28564 (0x6F94)
		// @1280: iastore
		// @1281: dup
		// @1282: sipush 589 (0x024D)
		// @1285: sipush 28610 (0x6FC2)
		// @1288: iastore
		// @1289: dup
		// @128A: sipush 590 (0x024E)
		// @128D: sipush 28655 (0x6FEF)
		// @1290: iastore
		// @1291: dup
		// @1292: sipush 591 (0x024F)
		// @1295: sipush 28700 (0x701C)
		// @1298: iastore
		// @1299: dup
		// @129A: sipush 592 (0x0250)
		// @129D: sipush 28745 (0x7049)
		// @12A0: iastore
		// @12A1: dup
		// @12A2: sipush 593 (0x0251)
		// @12A5: sipush 28790 (0x7076)
		// @12A8: iastore
		// @12A9: dup
		// @12AA: sipush 594 (0x0252)
		// @12AD: sipush 28835 (0x70A3)
		// @12B0: iastore
		// @12B1: dup
		// @12B2: sipush 595 (0x0253)
		// @12B5: sipush 28881 (0x70D1)
		// @12B8: iastore
		// @12B9: dup
		// @12BA: sipush 596 (0x0254)
		// @12BD: sipush 28926 (0x70FE)
		// @12C0: iastore
		// @12C1: dup
		// @12C2: sipush 597 (0x0255)
		// @12C5: sipush 28971 (0x712B)
		// @12C8: iastore
		// @12C9: dup
		// @12CA: sipush 598 (0x0256)
		// @12CD: sipush 29016 (0x7158)
		// @12D0: iastore
		// @12D1: dup
		// @12D2: sipush 599 (0x0257)
		// @12D5: sipush 29061 (0x7185)
		// @12D8: iastore
		// @12D9: dup
		// @12DA: sipush 600 (0x0258)
		// @12DD: sipush 29106 (0x71B2)
		// @12E0: iastore
		// @12E1: dup
		// @12E2: sipush 601 (0x0259)
		// @12E5: sipush 29151 (0x71DF)
		// @12E8: iastore
		// @12E9: dup
		// @12EA: sipush 602 (0x025A)
		// @12ED: sipush 29196 (0x720C)
		// @12F0: iastore
		// @12F1: dup
		// @12F2: sipush 603 (0x025B)
		// @12F5: sipush 29241 (0x7239)
		// @12F8: iastore
		// @12F9: dup
		// @12FA: sipush 604 (0x025C)
		// @12FD: sipush 29286 (0x7266)
		// @1300: iastore
		// @1301: dup
		// @1302: sipush 605 (0x025D)
		// @1305: sipush 29331 (0x7293)
		// @1308: iastore
		// @1309: dup
		// @130A: sipush 606 (0x025E)
		// @130D: sipush 29376 (0x72C0)
		// @1310: iastore
		// @1311: dup
		// @1312: sipush 607 (0x025F)
		// @1315: sipush 29421 (0x72ED)
		// @1318: iastore
		// @1319: dup
		// @131A: sipush 608 (0x0260)
		// @131D: sipush 29466 (0x731A)
		// @1320: iastore
		// @1321: dup
		// @1322: sipush 609 (0x0261)
		// @1325: sipush 29511 (0x7347)
		// @1328: iastore
		// @1329: dup
		// @132A: sipush 610 (0x0262)
		// @132D: sipush 29555 (0x7373)
		// @1330: iastore
		// @1331: dup
		// @1332: sipush 611 (0x0263)
		// @1335: sipush 29600 (0x73A0)
		// @1338: iastore
		// @1339: dup
		// @133A: sipush 612 (0x0264)
		// @133D: sipush 29645 (0x73CD)
		// @1340: iastore
		// @1341: dup
		// @1342: sipush 613 (0x0265)
		// @1345: sipush 29690 (0x73FA)
		// @1348: iastore
		// @1349: dup
		// @134A: sipush 614 (0x0266)
		// @134D: sipush 29735 (0x7427)
		// @1350: iastore
		// @1351: dup
		// @1352: sipush 615 (0x0267)
		// @1355: sipush 29780 (0x7454)
		// @1358: iastore
		// @1359: dup
		// @135A: sipush 616 (0x0268)
		// @135D: sipush 29824 (0x7480)
		// @1360: iastore
		// @1361: dup
		// @1362: sipush 617 (0x0269)
		// @1365: sipush 29869 (0x74AD)
		// @1368: iastore
		// @1369: dup
		// @136A: sipush 618 (0x026A)
		// @136D: sipush 29914 (0x74DA)
		// @1370: iastore
		// @1371: dup
		// @1372: sipush 619 (0x026B)
		// @1375: sipush 29959 (0x7507)
		// @1378: iastore
		// @1379: dup
		// @137A: sipush 620 (0x026C)
		// @137D: sipush 30003 (0x7533)
		// @1380: iastore
		// @1381: dup
		// @1382: sipush 621 (0x026D)
		// @1385: sipush 30048 (0x7560)
		// @1388: iastore
		// @1389: dup
		// @138A: sipush 622 (0x026E)
		// @138D: sipush 30093 (0x758D)
		// @1390: iastore
		// @1391: dup
		// @1392: sipush 623 (0x026F)
		// @1395: sipush 30137 (0x75B9)
		// @1398: iastore
		// @1399: dup
		// @139A: sipush 624 (0x0270)
		// @139D: sipush 30182 (0x75E6)
		// @13A0: iastore
		// @13A1: dup
		// @13A2: sipush 625 (0x0271)
		// @13A5: sipush 30226 (0x7612)
		// @13A8: iastore
		// @13A9: dup
		// @13AA: sipush 626 (0x0272)
		// @13AD: sipush 30271 (0x763F)
		// @13B0: iastore
		// @13B1: dup
		// @13B2: sipush 627 (0x0273)
		// @13B5: sipush 30316 (0x766C)
		// @13B8: iastore
		// @13B9: dup
		// @13BA: sipush 628 (0x0274)
		// @13BD: sipush 30360 (0x7698)
		// @13C0: iastore
		// @13C1: dup
		// @13C2: sipush 629 (0x0275)
		// @13C5: sipush 30405 (0x76C5)
		// @13C8: iastore
		// @13C9: dup
		// @13CA: sipush 630 (0x0276)
		// @13CD: sipush 30449 (0x76F1)
		// @13D0: iastore
		// @13D1: dup
		// @13D2: sipush 631 (0x0277)
		// @13D5: sipush 30494 (0x771E)
		// @13D8: iastore
		// @13D9: dup
		// @13DA: sipush 632 (0x0278)
		// @13DD: sipush 30538 (0x774A)
		// @13E0: iastore
		// @13E1: dup
		// @13E2: sipush 633 (0x0279)
		// @13E5: sipush 30583 (0x7777)
		// @13E8: iastore
		// @13E9: dup
		// @13EA: sipush 634 (0x027A)
		// @13ED: sipush 30627 (0x77A3)
		// @13F0: iastore
		// @13F1: dup
		// @13F2: sipush 635 (0x027B)
		// @13F5: sipush 30672 (0x77D0)
		// @13F8: iastore
		// @13F9: dup
		// @13FA: sipush 636 (0x027C)
		// @13FD: sipush 30716 (0x77FC)
		// @1400: iastore
		// @1401: dup
		// @1402: sipush 637 (0x027D)
		// @1405: sipush 30760 (0x7828)
		// @1408: iastore
		// @1409: dup
		// @140A: sipush 638 (0x027E)
		// @140D: sipush 30805 (0x7855)
		// @1410: iastore
		// @1411: dup
		// @1412: sipush 639 (0x027F)
		// @1415: sipush 30849 (0x7881)
		// @1418: iastore
		// @1419: dup
		// @141A: sipush 640 (0x0280)
		// @141D: sipush 30893 (0x78AD)
		// @1420: iastore
		// @1421: dup
		// @1422: sipush 641 (0x0281)
		// @1425: sipush 30938 (0x78DA)
		// @1428: iastore
		// @1429: dup
		// @142A: sipush 642 (0x0282)
		// @142D: sipush 30982 (0x7906)
		// @1430: iastore
		// @1431: dup
		// @1432: sipush 643 (0x0283)
		// @1435: sipush 31026 (0x7932)
		// @1438: iastore
		// @1439: dup
		// @143A: sipush 644 (0x0284)
		// @143D: sipush 31071 (0x795F)
		// @1440: iastore
		// @1441: dup
		// @1442: sipush 645 (0x0285)
		// @1445: sipush 31115 (0x798B)
		// @1448: iastore
		// @1449: dup
		// @144A: sipush 646 (0x0286)
		// @144D: sipush 31159 (0x79B7)
		// @1450: iastore
		// @1451: dup
		// @1452: sipush 647 (0x0287)
		// @1455: sipush 31203 (0x79E3)
		// @1458: iastore
		// @1459: dup
		// @145A: sipush 648 (0x0288)
		// @145D: sipush 31248 (0x7A10)
		// @1460: iastore
		// @1461: dup
		// @1462: sipush 649 (0x0289)
		// @1465: sipush 31292 (0x7A3C)
		// @1468: iastore
		// @1469: dup
		// @146A: sipush 650 (0x028A)
		// @146D: sipush 31336 (0x7A68)
		// @1470: iastore
		// @1471: dup
		// @1472: sipush 651 (0x028B)
		// @1475: sipush 31380 (0x7A94)
		// @1478: iastore
		// @1479: dup
		// @147A: sipush 652 (0x028C)
		// @147D: sipush 31424 (0x7AC0)
		// @1480: iastore
		// @1481: dup
		// @1482: sipush 653 (0x028D)
		// @1485: sipush 31468 (0x7AEC)
		// @1488: iastore
		// @1489: dup
		// @148A: sipush 654 (0x028E)
		// @148D: sipush 31512 (0x7B18)
		// @1490: iastore
		// @1491: dup
		// @1492: sipush 655 (0x028F)
		// @1495: sipush 31556 (0x7B44)
		// @1498: iastore
		// @1499: dup
		// @149A: sipush 656 (0x0290)
		// @149D: sipush 31600 (0x7B70)
		// @14A0: iastore
		// @14A1: dup
		// @14A2: sipush 657 (0x0291)
		// @14A5: sipush 31644 (0x7B9C)
		// @14A8: iastore
		// @14A9: dup
		// @14AA: sipush 658 (0x0292)
		// @14AD: sipush 31688 (0x7BC8)
		// @14B0: iastore
		// @14B1: dup
		// @14B2: sipush 659 (0x0293)
		// @14B5: sipush 31732 (0x7BF4)
		// @14B8: iastore
		// @14B9: dup
		// @14BA: sipush 660 (0x0294)
		// @14BD: sipush 31776 (0x7C20)
		// @14C0: iastore
		// @14C1: dup
		// @14C2: sipush 661 (0x0295)
		// @14C5: sipush 31820 (0x7C4C)
		// @14C8: iastore
		// @14C9: dup
		// @14CA: sipush 662 (0x0296)
		// @14CD: sipush 31864 (0x7C78)
		// @14D0: iastore
		// @14D1: dup
		// @14D2: sipush 663 (0x0297)
		// @14D5: sipush 31908 (0x7CA4)
		// @14D8: iastore
		// @14D9: dup
		// @14DA: sipush 664 (0x0298)
		// @14DD: sipush 31952 (0x7CD0)
		// @14E0: iastore
		// @14E1: dup
		// @14E2: sipush 665 (0x0299)
		// @14E5: sipush 31996 (0x7CFC)
		// @14E8: iastore
		// @14E9: dup
		// @14EA: sipush 666 (0x029A)
		// @14ED: sipush 32040 (0x7D28)
		// @14F0: iastore
		// @14F1: dup
		// @14F2: sipush 667 (0x029B)
		// @14F5: sipush 32084 (0x7D54)
		// @14F8: iastore
		// @14F9: dup
		// @14FA: sipush 668 (0x029C)
		// @14FD: sipush 32127 (0x7D7F)
		// @1500: iastore
		// @1501: dup
		// @1502: sipush 669 (0x029D)
		// @1505: sipush 32171 (0x7DAB)
		// @1508: iastore
		// @1509: dup
		// @150A: sipush 670 (0x029E)
		// @150D: sipush 32215 (0x7DD7)
		// @1510: iastore
		// @1511: dup
		// @1512: sipush 671 (0x029F)
		// @1515: sipush 32259 (0x7E03)
		// @1518: iastore
		// @1519: dup
		// @151A: sipush 672 (0x02A0)
		// @151D: sipush 32303 (0x7E2F)
		// @1520: iastore
		// @1521: dup
		// @1522: sipush 673 (0x02A1)
		// @1525: sipush 32346 (0x7E5A)
		// @1528: iastore
		// @1529: dup
		// @152A: sipush 674 (0x02A2)
		// @152D: sipush 32390 (0x7E86)
		// @1530: iastore
		// @1531: dup
		// @1532: sipush 675 (0x02A3)
		// @1535: sipush 32434 (0x7EB2)
		// @1538: iastore
		// @1539: dup
		// @153A: sipush 676 (0x02A4)
		// @153D: sipush 32477 (0x7EDD)
		// @1540: iastore
		// @1541: dup
		// @1542: sipush 677 (0x02A5)
		// @1545: sipush 32521 (0x7F09)
		// @1548: iastore
		// @1549: dup
		// @154A: sipush 678 (0x02A6)
		// @154D: sipush 32565 (0x7F35)
		// @1550: iastore
		// @1551: dup
		// @1552: sipush 679 (0x02A7)
		// @1555: sipush 32608 (0x7F60)
		// @1558: iastore
		// @1559: dup
		// @155A: sipush 680 (0x02A8)
		// @155D: sipush 32652 (0x7F8C)
		// @1560: iastore
		// @1561: dup
		// @1562: sipush 681 (0x02A9)
		// @1565: sipush 32695 (0x7FB7)
		// @1568: iastore
		// @1569: dup
		// @156A: sipush 682 (0x02AA)
		// @156D: sipush 32739 (0x7FE3)
		// @1570: iastore
		// @1571: dup
		// @1572: sipush 683 (0x02AB)
		// @1575: ldc 32783 (0x800f)
		// @1577: iastore
		// @1578: dup
		// @1579: sipush 684 (0x02AC)
		// @157C: ldc 32826 (0x803a)
		// @157E: iastore
		// @157F: dup
		// @1580: sipush 685 (0x02AD)
		// @1583: ldc 32870 (0x8066)
		// @1585: iastore
		// @1586: dup
		// @1587: sipush 686 (0x02AE)
		// @158A: ldc 32913 (0x8091)
		// @158C: iastore
		// @158D: dup
		// @158E: sipush 687 (0x02AF)
		// @1591: ldc 32956 (0x80bc)
		// @1593: iastore
		// @1594: dup
		// @1595: sipush 688 (0x02B0)
		// @1598: ldc 33000 (0x80e8)
		// @159A: iastore
		// @159B: dup
		// @159C: sipush 689 (0x02B1)
		// @159F: ldc 33043 (0x8113)
		// @15A1: iastore
		// @15A2: dup
		// @15A3: sipush 690 (0x02B2)
		// @15A6: ldc 33087 (0x813f)
		// @15A8: iastore
		// @15A9: dup
		// @15AA: sipush 691 (0x02B3)
		// @15AD: ldc 33130 (0x816a)
		// @15AF: iastore
		// @15B0: dup
		// @15B1: sipush 692 (0x02B4)
		// @15B4: ldc 33173 (0x8195)
		// @15B6: iastore
		// @15B7: dup
		// @15B8: sipush 693 (0x02B5)
		// @15BB: ldc 33217 (0x81c1)
		// @15BD: iastore
		// @15BE: dup
		// @15BF: sipush 694 (0x02B6)
		// @15C2: ldc 33260 (0x81ec)
		// @15C4: iastore
		// @15C5: dup
		// @15C6: sipush 695 (0x02B7)
		// @15C9: ldc 33303 (0x8217)
		// @15CB: iastore
		// @15CC: dup
		// @15CD: sipush 696 (0x02B8)
		// @15D0: ldc 33347 (0x8243)
		// @15D2: iastore
		// @15D3: dup
		// @15D4: sipush 697 (0x02B9)
		// @15D7: ldc 33390 (0x826e)
		// @15D9: iastore
		// @15DA: dup
		// @15DB: sipush 698 (0x02BA)
		// @15DE: ldc 33433 (0x8299)
		// @15E0: iastore
		// @15E1: dup
		// @15E2: sipush 699 (0x02BB)
		// @15E5: ldc 33476 (0x82c4)
		// @15E7: iastore
		// @15E8: dup
		// @15E9: sipush 700 (0x02BC)
		// @15EC: ldc 33520 (0x82f0)
		// @15EE: iastore
		// @15EF: dup
		// @15F0: sipush 701 (0x02BD)
		// @15F3: ldc 33563 (0x831b)
		// @15F5: iastore
		// @15F6: dup
		// @15F7: sipush 702 (0x02BE)
		// @15FA: ldc 33606 (0x8346)
		// @15FC: iastore
		// @15FD: dup
		// @15FE: sipush 703 (0x02BF)
		// @1601: ldc 33649 (0x8371)
		// @1603: iastore
		// @1604: dup
		// @1605: sipush 704 (0x02C0)
		// @1608: ldc 33692 (0x839c)
		// @160A: iastore
		// @160B: dup
		// @160C: sipush 705 (0x02C1)
		// @160F: ldc 33735 (0x83c7)
		// @1611: iastore
		// @1612: dup
		// @1613: sipush 706 (0x02C2)
		// @1616: ldc 33778 (0x83f2)
		// @1618: iastore
		// @1619: dup
		// @161A: sipush 707 (0x02C3)
		// @161D: ldc 33821 (0x841d)
		// @161F: iastore
		// @1620: dup
		// @1621: sipush 708 (0x02C4)
		// @1624: ldc 33865 (0x8449)
		// @1626: iastore
		// @1627: dup
		// @1628: sipush 709 (0x02C5)
		// @162B: ldc 33908 (0x8474)
		// @162D: iastore
		// @162E: dup
		// @162F: sipush 710 (0x02C6)
		// @1632: ldc 33951 (0x849f)
		// @1634: iastore
		// @1635: dup
		// @1636: sipush 711 (0x02C7)
		// @1639: ldc 33994 (0x84ca)
		// @163B: iastore
		// @163C: dup
		// @163D: sipush 712 (0x02C8)
		// @1640: ldc 34037 (0x84f5)
		// @1642: iastore
		// @1643: dup
		// @1644: sipush 713 (0x02C9)
		// @1647: ldc 34079 (0x851f)
		// @1649: iastore
		// @164A: dup
		// @164B: sipush 714 (0x02CA)
		// @164E: ldc 34122 (0x854a)
		// @1650: iastore
		// @1651: dup
		// @1652: sipush 715 (0x02CB)
		// @1655: ldc 34165 (0x8575)
		// @1657: iastore
		// @1658: dup
		// @1659: sipush 716 (0x02CC)
		// @165C: ldc 34208 (0x85a0)
		// @165E: iastore
		// @165F: dup
		// @1660: sipush 717 (0x02CD)
		// @1663: ldc 34251 (0x85cb)
		// @1665: iastore
		// @1666: dup
		// @1667: sipush 718 (0x02CE)
		// @166A: ldc 34294 (0x85f6)
		// @166C: iastore
		// @166D: dup
		// @166E: sipush 719 (0x02CF)
		// @1671: ldc 34337 (0x8621)
		// @1673: iastore
		// @1674: dup
		// @1675: sipush 720 (0x02D0)
		// @1678: ldc 34380 (0x864c)
		// @167A: iastore
		// @167B: dup
		// @167C: sipush 721 (0x02D1)
		// @167F: ldc 34422 (0x8676)
		// @1681: iastore
		// @1682: dup
		// @1683: sipush 722 (0x02D2)
		// @1686: ldc 34465 (0x86a1)
		// @1688: iastore
		// @1689: dup
		// @168A: sipush 723 (0x02D3)
		// @168D: ldc 34508 (0x86cc)
		// @168F: iastore
		// @1690: dup
		// @1691: sipush 724 (0x02D4)
		// @1694: ldc 34551 (0x86f7)
		// @1696: iastore
		// @1697: dup
		// @1698: sipush 725 (0x02D5)
		// @169B: ldc 34593 (0x8721)
		// @169D: iastore
		// @169E: dup
		// @169F: sipush 726 (0x02D6)
		// @16A2: ldc 34636 (0x874c)
		// @16A4: iastore
		// @16A5: dup
		// @16A6: sipush 727 (0x02D7)
		// @16A9: ldc 34679 (0x8777)
		// @16AB: iastore
		// @16AC: dup
		// @16AD: sipush 728 (0x02D8)
		// @16B0: ldc 34721 (0x87a1)
		// @16B2: iastore
		// @16B3: dup
		// @16B4: sipush 729 (0x02D9)
		// @16B7: ldc 34764 (0x87cc)
		// @16B9: iastore
		// @16BA: dup
		// @16BB: sipush 730 (0x02DA)
		// @16BE: ldc 34806 (0x87f6)
		// @16C0: iastore
		// @16C1: dup
		// @16C2: sipush 731 (0x02DB)
		// @16C5: ldc 34849 (0x8821)
		// @16C7: iastore
		// @16C8: dup
		// @16C9: sipush 732 (0x02DC)
		// @16CC: ldc 34892 (0x884c)
		// @16CE: iastore
		// @16CF: dup
		// @16D0: sipush 733 (0x02DD)
		// @16D3: ldc 34934 (0x8876)
		// @16D5: iastore
		// @16D6: dup
		// @16D7: sipush 734 (0x02DE)
		// @16DA: ldc 34977 (0x88a1)
		// @16DC: iastore
		// @16DD: dup
		// @16DE: sipush 735 (0x02DF)
		// @16E1: ldc 35019 (0x88cb)
		// @16E3: iastore
		// @16E4: dup
		// @16E5: sipush 736 (0x02E0)
		// @16E8: ldc 35062 (0x88f6)
		// @16EA: iastore
		// @16EB: dup
		// @16EC: sipush 737 (0x02E1)
		// @16EF: ldc 35104 (0x8920)
		// @16F1: iastore
		// @16F2: dup
		// @16F3: sipush 738 (0x02E2)
		// @16F6: ldc 35146 (0x894a)
		// @16F8: iastore
		// @16F9: dup
		// @16FA: sipush 739 (0x02E3)
		// @16FD: ldc 35189 (0x8975)
		// @16FF: iastore
		// @1700: dup
		// @1701: sipush 740 (0x02E4)
		// @1704: ldc 35231 (0x899f)
		// @1706: iastore
		// @1707: dup
		// @1708: sipush 741 (0x02E5)
		// @170B: ldc 35274 (0x89ca)
		// @170D: iastore
		// @170E: dup
		// @170F: sipush 742 (0x02E6)
		// @1712: ldc 35316 (0x89f4)
		// @1714: iastore
		// @1715: dup
		// @1716: sipush 743 (0x02E7)
		// @1719: ldc 35358 (0x8a1e)
		// @171B: iastore
		// @171C: dup
		// @171D: sipush 744 (0x02E8)
		// @1720: ldc 35401 (0x8a49)
		// @1722: iastore
		// @1723: dup
		// @1724: sipush 745 (0x02E9)
		// @1727: ldc 35443 (0x8a73)
		// @1729: iastore
		// @172A: dup
		// @172B: sipush 746 (0x02EA)
		// @172E: ldc 35485 (0x8a9d)
		// @1730: iastore
		// @1731: dup
		// @1732: sipush 747 (0x02EB)
		// @1735: ldc 35527 (0x8ac7)
		// @1737: iastore
		// @1738: dup
		// @1739: sipush 748 (0x02EC)
		// @173C: ldc 35570 (0x8af2)
		// @173E: iastore
		// @173F: dup
		// @1740: sipush 749 (0x02ED)
		// @1743: ldc 35612 (0x8b1c)
		// @1745: iastore
		// @1746: dup
		// @1747: sipush 750 (0x02EE)
		// @174A: ldc 35654 (0x8b46)
		// @174C: iastore
		// @174D: dup
		// @174E: sipush 751 (0x02EF)
		// @1751: ldc 35696 (0x8b70)
		// @1753: iastore
		// @1754: dup
		// @1755: sipush 752 (0x02F0)
		// @1758: ldc 35738 (0x8b9a)
		// @175A: iastore
		// @175B: dup
		// @175C: sipush 753 (0x02F1)
		// @175F: ldc 35781 (0x8bc5)
		// @1761: iastore
		// @1762: dup
		// @1763: sipush 754 (0x02F2)
		// @1766: ldc 35823 (0x8bef)
		// @1768: iastore
		// @1769: dup
		// @176A: sipush 755 (0x02F3)
		// @176D: ldc 35865 (0x8c19)
		// @176F: iastore
		// @1770: dup
		// @1771: sipush 756 (0x02F4)
		// @1774: ldc 35907 (0x8c43)
		// @1776: iastore
		// @1777: dup
		// @1778: sipush 757 (0x02F5)
		// @177B: ldc 35949 (0x8c6d)
		// @177D: iastore
		// @177E: dup
		// @177F: sipush 758 (0x02F6)
		// @1782: ldc 35991 (0x8c97)
		// @1784: iastore
		// @1785: dup
		// @1786: sipush 759 (0x02F7)
		// @1789: ldc 36033 (0x8cc1)
		// @178B: iastore
		// @178C: dup
		// @178D: sipush 760 (0x02F8)
		// @1790: ldc 36075 (0x8ceb)
		// @1792: iastore
		// @1793: dup
		// @1794: sipush 761 (0x02F9)
		// @1797: ldc 36117 (0x8d15)
		// @1799: iastore
		// @179A: dup
		// @179B: sipush 762 (0x02FA)
		// @179E: ldc 36159 (0x8d3f)
		// @17A0: iastore
		// @17A1: dup
		// @17A2: sipush 763 (0x02FB)
		// @17A5: ldc 36201 (0x8d69)
		// @17A7: iastore
		// @17A8: dup
		// @17A9: sipush 764 (0x02FC)
		// @17AC: ldc 36243 (0x8d93)
		// @17AE: iastore
		// @17AF: dup
		// @17B0: sipush 765 (0x02FD)
		// @17B3: ldc 36284 (0x8dbc)
		// @17B5: iastore
		// @17B6: dup
		// @17B7: sipush 766 (0x02FE)
		// @17BA: ldc 36326 (0x8de6)
		// @17BC: iastore
		// @17BD: dup
		// @17BE: sipush 767 (0x02FF)
		// @17C1: ldc 36368 (0x8e10)
		// @17C3: iastore
		// @17C4: dup
		// @17C5: sipush 768 (0x0300)
		// @17C8: ldc 36410 (0x8e3a)
		// @17CA: iastore
		// @17CB: dup
		// @17CC: sipush 769 (0x0301)
		// @17CF: ldc 36452 (0x8e64)
		// @17D1: iastore
		// @17D2: dup
		// @17D3: sipush 770 (0x0302)
		// @17D6: ldc 36493 (0x8e8d)
		// @17D8: iastore
		// @17D9: dup
		// @17DA: sipush 771 (0x0303)
		// @17DD: ldc 36535 (0x8eb7)
		// @17DF: iastore
		// @17E0: dup
		// @17E1: sipush 772 (0x0304)
		// @17E4: ldc 36577 (0x8ee1)
		// @17E6: iastore
		// @17E7: dup
		// @17E8: sipush 773 (0x0305)
		// @17EB: ldc 36619 (0x8f0b)
		// @17ED: iastore
		// @17EE: dup
		// @17EF: sipush 774 (0x0306)
		// @17F2: ldc 36660 (0x8f34)
		// @17F4: iastore
		// @17F5: dup
		// @17F6: sipush 775 (0x0307)
		// @17F9: ldc 36702 (0x8f5e)
		// @17FB: iastore
		// @17FC: dup
		// @17FD: sipush 776 (0x0308)
		// @1800: ldc 36744 (0x8f88)
		// @1802: iastore
		// @1803: dup
		// @1804: sipush 777 (0x0309)
		// @1807: ldc 36785 (0x8fb1)
		// @1809: iastore
		// @180A: dup
		// @180B: sipush 778 (0x030A)
		// @180E: ldc 36827 (0x8fdb)
		// @1810: iastore
		// @1811: dup
		// @1812: sipush 779 (0x030B)
		// @1815: ldc 36868 (0x9004)
		// @1817: iastore
		// @1818: dup
		// @1819: sipush 780 (0x030C)
		// @181C: ldc 36910 (0x902e)
		// @181E: iastore
		// @181F: dup
		// @1820: sipush 781 (0x030D)
		// @1823: ldc 36951 (0x9057)
		// @1825: iastore
		// @1826: dup
		// @1827: sipush 782 (0x030E)
		// @182A: ldc 36993 (0x9081)
		// @182C: iastore
		// @182D: dup
		// @182E: sipush 783 (0x030F)
		// @1831: ldc 37034 (0x90aa)
		// @1833: iastore
		// @1834: dup
		// @1835: sipush 784 (0x0310)
		// @1838: ldc 37076 (0x90d4)
		// @183A: iastore
		// @183B: dup
		// @183C: sipush 785 (0x0311)
		// @183F: ldc 37117 (0x90fd)
		// @1841: iastore
		// @1842: dup
		// @1843: sipush 786 (0x0312)
		// @1846: ldc 37159 (0x9127)
		// @1848: iastore
		// @1849: dup
		// @184A: sipush 787 (0x0313)
		// @184D: ldc 37200 (0x9150)
		// @184F: iastore
		// @1850: dup
		// @1851: sipush 788 (0x0314)
		// @1854: ldc 37241 (0x9179)
		// @1856: iastore
		// @1857: dup
		// @1858: sipush 789 (0x0315)
		// @185B: ldc 37283 (0x91a3)
		// @185D: iastore
		// @185E: dup
		// @185F: sipush 790 (0x0316)
		// @1862: ldc 37324 (0x91cc)
		// @1864: iastore
		// @1865: dup
		// @1866: sipush 791 (0x0317)
		// @1869: ldc 37365 (0x91f5)
		// @186B: iastore
		// @186C: dup
		// @186D: sipush 792 (0x0318)
		// @1870: ldc 37407 (0x921f)
		// @1872: iastore
		// @1873: dup
		// @1874: sipush 793 (0x0319)
		// @1877: ldc 37448 (0x9248)
		// @1879: iastore
		// @187A: dup
		// @187B: sipush 794 (0x031A)
		// @187E: ldc 37489 (0x9271)
		// @1880: iastore
		// @1881: dup
		// @1882: sipush 795 (0x031B)
		// @1885: ldc 37530 (0x929a)
		// @1887: iastore
		// @1888: dup
		// @1889: sipush 796 (0x031C)
		// @188C: ldc 37572 (0x92c4)
		// @188E: iastore
		// @188F: dup
		// @1890: sipush 797 (0x031D)
		// @1893: ldc 37613 (0x92ed)
		// @1895: iastore
		// @1896: dup
		// @1897: sipush 798 (0x031E)
		// @189A: ldc 37654 (0x9316)
		// @189C: iastore
		// @189D: dup
		// @189E: sipush 799 (0x031F)
		// @18A1: ldc 37695 (0x933f)
		// @18A3: iastore
		// @18A4: dup
		// @18A5: sipush 800 (0x0320)
		// @18A8: ldc 37736 (0x9368)
		// @18AA: iastore
		// @18AB: dup
		// @18AC: sipush 801 (0x0321)
		// @18AF: ldc 37777 (0x9391)
		// @18B1: iastore
		// @18B2: dup
		// @18B3: sipush 802 (0x0322)
		// @18B6: ldc 37818 (0x93ba)
		// @18B8: iastore
		// @18B9: dup
		// @18BA: sipush 803 (0x0323)
		// @18BD: ldc 37859 (0x93e3)
		// @18BF: iastore
		// @18C0: dup
		// @18C1: sipush 804 (0x0324)
		// @18C4: ldc 37900 (0x940c)
		// @18C6: iastore
		// @18C7: dup
		// @18C8: sipush 805 (0x0325)
		// @18CB: ldc 37941 (0x9435)
		// @18CD: iastore
		// @18CE: dup
		// @18CF: sipush 806 (0x0326)
		// @18D2: ldc 37982 (0x945e)
		// @18D4: iastore
		// @18D5: dup
		// @18D6: sipush 807 (0x0327)
		// @18D9: ldc 38023 (0x9487)
		// @18DB: iastore
		// @18DC: dup
		// @18DD: sipush 808 (0x0328)
		// @18E0: ldc 38064 (0x94b0)
		// @18E2: iastore
		// @18E3: dup
		// @18E4: sipush 809 (0x0329)
		// @18E7: ldc 38105 (0x94d9)
		// @18E9: iastore
		// @18EA: dup
		// @18EB: sipush 810 (0x032A)
		// @18EE: ldc 38146 (0x9502)
		// @18F0: iastore
		// @18F1: dup
		// @18F2: sipush 811 (0x032B)
		// @18F5: ldc 38187 (0x952b)
		// @18F7: iastore
		// @18F8: dup
		// @18F9: sipush 812 (0x032C)
		// @18FC: ldc 38228 (0x9554)
		// @18FE: iastore
		// @18FF: dup
		// @1900: sipush 813 (0x032D)
		// @1903: ldc 38269 (0x957d)
		// @1905: iastore
		// @1906: dup
		// @1907: sipush 814 (0x032E)
		// @190A: ldc 38309 (0x95a5)
		// @190C: iastore
		// @190D: dup
		// @190E: sipush 815 (0x032F)
		// @1911: ldc 38350 (0x95ce)
		// @1913: iastore
		// @1914: dup
		// @1915: sipush 816 (0x0330)
		// @1918: ldc 38391 (0x95f7)
		// @191A: iastore
		// @191B: dup
		// @191C: sipush 817 (0x0331)
		// @191F: ldc 38432 (0x9620)
		// @1921: iastore
		// @1922: dup
		// @1923: sipush 818 (0x0332)
		// @1926: ldc 38472 (0x9648)
		// @1928: iastore
		// @1929: dup
		// @192A: sipush 819 (0x0333)
		// @192D: ldc 38513 (0x9671)
		// @192F: iastore
		// @1930: dup
		// @1931: sipush 820 (0x0334)
		// @1934: ldc 38554 (0x969a)
		// @1936: iastore
		// @1937: dup
		// @1938: sipush 821 (0x0335)
		// @193B: ldc 38594 (0x96c2)
		// @193D: iastore
		// @193E: dup
		// @193F: sipush 822 (0x0336)
		// @1942: ldc 38635 (0x96eb)
		// @1944: iastore
		// @1945: dup
		// @1946: sipush 823 (0x0337)
		// @1949: ldc 38675 (0x9713)
		// @194B: iastore
		// @194C: dup
		// @194D: sipush 824 (0x0338)
		// @1950: ldc 38716 (0x973c)
		// @1952: iastore
		// @1953: dup
		// @1954: sipush 825 (0x0339)
		// @1957: ldc 38757 (0x9765)
		// @1959: iastore
		// @195A: dup
		// @195B: sipush 826 (0x033A)
		// @195E: ldc 38797 (0x978d)
		// @1960: iastore
		// @1961: dup
		// @1962: sipush 827 (0x033B)
		// @1965: ldc 38838 (0x97b6)
		// @1967: iastore
		// @1968: dup
		// @1969: sipush 828 (0x033C)
		// @196C: ldc 38878 (0x97de)
		// @196E: iastore
		// @196F: dup
		// @1970: sipush 829 (0x033D)
		// @1973: ldc 38919 (0x9807)
		// @1975: iastore
		// @1976: dup
		// @1977: sipush 830 (0x033E)
		// @197A: ldc 38959 (0x982f)
		// @197C: iastore
		// @197D: dup
		// @197E: sipush 831 (0x033F)
		// @1981: ldc 38999 (0x9857)
		// @1983: iastore
		// @1984: dup
		// @1985: sipush 832 (0x0340)
		// @1988: ldc 39040 (0x9880)
		// @198A: iastore
		// @198B: dup
		// @198C: sipush 833 (0x0341)
		// @198F: ldc 39080 (0x98a8)
		// @1991: iastore
		// @1992: dup
		// @1993: sipush 834 (0x0342)
		// @1996: ldc 39120 (0x98d0)
		// @1998: iastore
		// @1999: dup
		// @199A: sipush 835 (0x0343)
		// @199D: ldc 39161 (0x98f9)
		// @199F: iastore
		// @19A0: dup
		// @19A1: sipush 836 (0x0344)
		// @19A4: ldc 39201 (0x9921)
		// @19A6: iastore
		// @19A7: dup
		// @19A8: sipush 837 (0x0345)
		// @19AB: ldc 39241 (0x9949)
		// @19AD: iastore
		// @19AE: dup
		// @19AF: sipush 838 (0x0346)
		// @19B2: ldc 39282 (0x9972)
		// @19B4: iastore
		// @19B5: dup
		// @19B6: sipush 839 (0x0347)
		// @19B9: ldc 39322 (0x999a)
		// @19BB: iastore
		// @19BC: dup
		// @19BD: sipush 840 (0x0348)
		// @19C0: ldc 39362 (0x99c2)
		// @19C2: iastore
		// @19C3: dup
		// @19C4: sipush 841 (0x0349)
		// @19C7: ldc 39402 (0x99ea)
		// @19C9: iastore
		// @19CA: dup
		// @19CB: sipush 842 (0x034A)
		// @19CE: ldc 39442 (0x9a12)
		// @19D0: iastore
		// @19D1: dup
		// @19D2: sipush 843 (0x034B)
		// @19D5: ldc 39482 (0x9a3a)
		// @19D7: iastore
		// @19D8: dup
		// @19D9: sipush 844 (0x034C)
		// @19DC: ldc 39523 (0x9a63)
		// @19DE: iastore
		// @19DF: dup
		// @19E0: sipush 845 (0x034D)
		// @19E3: ldc 39563 (0x9a8b)
		// @19E5: iastore
		// @19E6: dup
		// @19E7: sipush 846 (0x034E)
		// @19EA: ldc 39603 (0x9ab3)
		// @19EC: iastore
		// @19ED: dup
		// @19EE: sipush 847 (0x034F)
		// @19F1: ldc 39643 (0x9adb)
		// @19F3: iastore
		// @19F4: dup
		// @19F5: sipush 848 (0x0350)
		// @19F8: ldc 39683 (0x9b03)
		// @19FA: iastore
		// @19FB: dup
		// @19FC: sipush 849 (0x0351)
		// @19FF: ldc 39723 (0x9b2b)
		// @1A01: iastore
		// @1A02: dup
		// @1A03: sipush 850 (0x0352)
		// @1A06: ldc 39763 (0x9b53)
		// @1A08: iastore
		// @1A09: dup
		// @1A0A: sipush 851 (0x0353)
		// @1A0D: ldc 39803 (0x9b7b)
		// @1A0F: iastore
		// @1A10: dup
		// @1A11: sipush 852 (0x0354)
		// @1A14: ldc 39843 (0x9ba3)
		// @1A16: iastore
		// @1A17: dup
		// @1A18: sipush 853 (0x0355)
		// @1A1B: ldc 39882 (0x9bca)
		// @1A1D: iastore
		// @1A1E: dup
		// @1A1F: sipush 854 (0x0356)
		// @1A22: ldc 39922 (0x9bf2)
		// @1A24: iastore
		// @1A25: dup
		// @1A26: sipush 855 (0x0357)
		// @1A29: ldc 39962 (0x9c1a)
		// @1A2B: iastore
		// @1A2C: dup
		// @1A2D: sipush 856 (0x0358)
		// @1A30: ldc 40002 (0x9c42)
		// @1A32: iastore
		// @1A33: dup
		// @1A34: sipush 857 (0x0359)
		// @1A37: ldc 40042 (0x9c6a)
		// @1A39: iastore
		// @1A3A: dup
		// @1A3B: sipush 858 (0x035A)
		// @1A3E: ldc 40082 (0x9c92)
		// @1A40: iastore
		// @1A41: dup
		// @1A42: sipush 859 (0x035B)
		// @1A45: ldc 40121 (0x9cb9)
		// @1A47: iastore
		// @1A48: dup
		// @1A49: sipush 860 (0x035C)
		// @1A4C: ldc 40161 (0x9ce1)
		// @1A4E: iastore
		// @1A4F: dup
		// @1A50: sipush 861 (0x035D)
		// @1A53: ldc 40201 (0x9d09)
		// @1A55: iastore
		// @1A56: dup
		// @1A57: sipush 862 (0x035E)
		// @1A5A: ldc 40241 (0x9d31)
		// @1A5C: iastore
		// @1A5D: dup
		// @1A5E: sipush 863 (0x035F)
		// @1A61: ldc 40280 (0x9d58)
		// @1A63: iastore
		// @1A64: dup
		// @1A65: sipush 864 (0x0360)
		// @1A68: ldc 40320 (0x9d80)
		// @1A6A: iastore
		// @1A6B: dup
		// @1A6C: sipush 865 (0x0361)
		// @1A6F: ldc 40359 (0x9da7)
		// @1A71: iastore
		// @1A72: dup
		// @1A73: sipush 866 (0x0362)
		// @1A76: ldc 40399 (0x9dcf)
		// @1A78: iastore
		// @1A79: dup
		// @1A7A: sipush 867 (0x0363)
		// @1A7D: ldc 40439 (0x9df7)
		// @1A7F: iastore
		// @1A80: dup
		// @1A81: sipush 868 (0x0364)
		// @1A84: ldc_w 40478 (0x9e1e)
		// @1A87: iastore
		// @1A88: dup
		// @1A89: sipush 869 (0x0365)
		// @1A8C: ldc_w 40518 (0x9e46)
		// @1A8F: iastore
		// @1A90: dup
		// @1A91: sipush 870 (0x0366)
		// @1A94: ldc_w 40557 (0x9e6d)
		// @1A97: iastore
		// @1A98: dup
		// @1A99: sipush 871 (0x0367)
		// @1A9C: ldc_w 40597 (0x9e95)
		// @1A9F: iastore
		// @1AA0: dup
		// @1AA1: sipush 872 (0x0368)
		// @1AA4: ldc_w 40636 (0x9ebc)
		// @1AA7: iastore
		// @1AA8: dup
		// @1AA9: sipush 873 (0x0369)
		// @1AAC: ldc_w 40675 (0x9ee3)
		// @1AAF: iastore
		// @1AB0: dup
		// @1AB1: sipush 874 (0x036A)
		// @1AB4: ldc_w 40715 (0x9f0b)
		// @1AB7: iastore
		// @1AB8: dup
		// @1AB9: sipush 875 (0x036B)
		// @1ABC: ldc_w 40754 (0x9f32)
		// @1ABF: iastore
		// @1AC0: dup
		// @1AC1: sipush 876 (0x036C)
		// @1AC4: ldc_w 40794 (0x9f5a)
		// @1AC7: iastore
		// @1AC8: dup
		// @1AC9: sipush 877 (0x036D)
		// @1ACC: ldc_w 40833 (0x9f81)
		// @1ACF: iastore
		// @1AD0: dup
		// @1AD1: sipush 878 (0x036E)
		// @1AD4: ldc_w 40872 (0x9fa8)
		// @1AD7: iastore
		// @1AD8: dup
		// @1AD9: sipush 879 (0x036F)
		// @1ADC: ldc_w 40912 (0x9fd0)
		// @1ADF: iastore
		// @1AE0: dup
		// @1AE1: sipush 880 (0x0370)
		// @1AE4: ldc_w 40951 (0x9ff7)
		// @1AE7: iastore
		// @1AE8: dup
		// @1AE9: sipush 881 (0x0371)
		// @1AEC: ldc_w 40990 (0xa01e)
		// @1AEF: iastore
		// @1AF0: dup
		// @1AF1: sipush 882 (0x0372)
		// @1AF4: ldc_w 41029 (0xa045)
		// @1AF7: iastore
		// @1AF8: dup
		// @1AF9: sipush 883 (0x0373)
		// @1AFC: ldc_w 41068 (0xa06c)
		// @1AFF: iastore
		// @1B00: dup
		// @1B01: sipush 884 (0x0374)
		// @1B04: ldc_w 41108 (0xa094)
		// @1B07: iastore
		// @1B08: dup
		// @1B09: sipush 885 (0x0375)
		// @1B0C: ldc_w 41147 (0xa0bb)
		// @1B0F: iastore
		// @1B10: dup
		// @1B11: sipush 886 (0x0376)
		// @1B14: ldc_w 41186 (0xa0e2)
		// @1B17: iastore
		// @1B18: dup
		// @1B19: sipush 887 (0x0377)
		// @1B1C: ldc_w 41225 (0xa109)
		// @1B1F: iastore
		// @1B20: dup
		// @1B21: sipush 888 (0x0378)
		// @1B24: ldc_w 41264 (0xa130)
		// @1B27: iastore
		// @1B28: dup
		// @1B29: sipush 889 (0x0379)
		// @1B2C: ldc_w 41303 (0xa157)
		// @1B2F: iastore
		// @1B30: dup
		// @1B31: sipush 890 (0x037A)
		// @1B34: ldc_w 41342 (0xa17e)
		// @1B37: iastore
		// @1B38: dup
		// @1B39: sipush 891 (0x037B)
		// @1B3C: ldc_w 41381 (0xa1a5)
		// @1B3F: iastore
		// @1B40: dup
		// @1B41: sipush 892 (0x037C)
		// @1B44: ldc_w 41420 (0xa1cc)
		// @1B47: iastore
		// @1B48: dup
		// @1B49: sipush 893 (0x037D)
		// @1B4C: ldc_w 41459 (0xa1f3)
		// @1B4F: iastore
		// @1B50: dup
		// @1B51: sipush 894 (0x037E)
		// @1B54: ldc_w 41498 (0xa21a)
		// @1B57: iastore
		// @1B58: dup
		// @1B59: sipush 895 (0x037F)
		// @1B5C: ldc_w 41537 (0xa241)
		// @1B5F: iastore
		// @1B60: dup
		// @1B61: sipush 896 (0x0380)
		// @1B64: ldc_w 41576 (0xa268)
		// @1B67: iastore
		// @1B68: dup
		// @1B69: sipush 897 (0x0381)
		// @1B6C: ldc_w 41614 (0xa28e)
		// @1B6F: iastore
		// @1B70: dup
		// @1B71: sipush 898 (0x0382)
		// @1B74: ldc_w 41653 (0xa2b5)
		// @1B77: iastore
		// @1B78: dup
		// @1B79: sipush 899 (0x0383)
		// @1B7C: ldc_w 41692 (0xa2dc)
		// @1B7F: iastore
		// @1B80: dup
		// @1B81: sipush 900 (0x0384)
		// @1B84: ldc_w 41731 (0xa303)
		// @1B87: iastore
		// @1B88: dup
		// @1B89: sipush 901 (0x0385)
		// @1B8C: ldc_w 41770 (0xa32a)
		// @1B8F: iastore
		// @1B90: dup
		// @1B91: sipush 902 (0x0386)
		// @1B94: ldc_w 41808 (0xa350)
		// @1B97: iastore
		// @1B98: dup
		// @1B99: sipush 903 (0x0387)
		// @1B9C: ldc_w 41847 (0xa377)
		// @1B9F: iastore
		// @1BA0: dup
		// @1BA1: sipush 904 (0x0388)
		// @1BA4: ldc_w 41886 (0xa39e)
		// @1BA7: iastore
		// @1BA8: dup
		// @1BA9: sipush 905 (0x0389)
		// @1BAC: ldc_w 41924 (0xa3c4)
		// @1BAF: iastore
		// @1BB0: dup
		// @1BB1: sipush 906 (0x038A)
		// @1BB4: ldc_w 41963 (0xa3eb)
		// @1BB7: iastore
		// @1BB8: dup
		// @1BB9: sipush 907 (0x038B)
		// @1BBC: ldc_w 42002 (0xa412)
		// @1BBF: iastore
		// @1BC0: dup
		// @1BC1: sipush 908 (0x038C)
		// @1BC4: ldc_w 42040 (0xa438)
		// @1BC7: iastore
		// @1BC8: dup
		// @1BC9: sipush 909 (0x038D)
		// @1BCC: ldc_w 42079 (0xa45f)
		// @1BCF: iastore
		// @1BD0: dup
		// @1BD1: sipush 910 (0x038E)
		// @1BD4: ldc_w 42117 (0xa485)
		// @1BD7: iastore
		// @1BD8: dup
		// @1BD9: sipush 911 (0x038F)
		// @1BDC: ldc_w 42156 (0xa4ac)
		// @1BDF: iastore
		// @1BE0: dup
		// @1BE1: sipush 912 (0x0390)
		// @1BE4: ldc_w 42194 (0xa4d2)
		// @1BE7: iastore
		// @1BE8: dup
		// @1BE9: sipush 913 (0x0391)
		// @1BEC: ldc_w 42233 (0xa4f9)
		// @1BEF: iastore
		// @1BF0: dup
		// @1BF1: sipush 914 (0x0392)
		// @1BF4: ldc_w 42271 (0xa51f)
		// @1BF7: iastore
		// @1BF8: dup
		// @1BF9: sipush 915 (0x0393)
		// @1BFC: ldc_w 42309 (0xa545)
		// @1BFF: iastore
		// @1C00: dup
		// @1C01: sipush 916 (0x0394)
		// @1C04: ldc_w 42348 (0xa56c)
		// @1C07: iastore
		// @1C08: dup
		// @1C09: sipush 917 (0x0395)
		// @1C0C: ldc_w 42386 (0xa592)
		// @1C0F: iastore
		// @1C10: dup
		// @1C11: sipush 918 (0x0396)
		// @1C14: ldc_w 42424 (0xa5b8)
		// @1C17: iastore
		// @1C18: dup
		// @1C19: sipush 919 (0x0397)
		// @1C1C: ldc_w 42463 (0xa5df)
		// @1C1F: iastore
		// @1C20: dup
		// @1C21: sipush 920 (0x0398)
		// @1C24: ldc_w 42501 (0xa605)
		// @1C27: iastore
		// @1C28: dup
		// @1C29: sipush 921 (0x0399)
		// @1C2C: ldc_w 42539 (0xa62b)
		// @1C2F: iastore
		// @1C30: dup
		// @1C31: sipush 922 (0x039A)
		// @1C34: ldc_w 42578 (0xa652)
		// @1C37: iastore
		// @1C38: dup
		// @1C39: sipush 923 (0x039B)
		// @1C3C: ldc_w 42616 (0xa678)
		// @1C3F: iastore
		// @1C40: dup
		// @1C41: sipush 924 (0x039C)
		// @1C44: ldc_w 42654 (0xa69e)
		// @1C47: iastore
		// @1C48: dup
		// @1C49: sipush 925 (0x039D)
		// @1C4C: ldc_w 42692 (0xa6c4)
		// @1C4F: iastore
		// @1C50: dup
		// @1C51: sipush 926 (0x039E)
		// @1C54: ldc_w 42730 (0xa6ea)
		// @1C57: iastore
		// @1C58: dup
		// @1C59: sipush 927 (0x039F)
		// @1C5C: ldc_w 42768 (0xa710)
		// @1C5F: iastore
		// @1C60: dup
		// @1C61: sipush 928 (0x03A0)
		// @1C64: ldc_w 42806 (0xa736)
		// @1C67: iastore
		// @1C68: dup
		// @1C69: sipush 929 (0x03A1)
		// @1C6C: ldc_w 42844 (0xa75c)
		// @1C6F: iastore
		// @1C70: dup
		// @1C71: sipush 930 (0x03A2)
		// @1C74: ldc_w 42882 (0xa782)
		// @1C77: iastore
		// @1C78: dup
		// @1C79: sipush 931 (0x03A3)
		// @1C7C: ldc_w 42920 (0xa7a8)
		// @1C7F: iastore
		// @1C80: dup
		// @1C81: sipush 932 (0x03A4)
		// @1C84: ldc_w 42958 (0xa7ce)
		// @1C87: iastore
		// @1C88: dup
		// @1C89: sipush 933 (0x03A5)
		// @1C8C: ldc_w 42996 (0xa7f4)
		// @1C8F: iastore
		// @1C90: dup
		// @1C91: sipush 934 (0x03A6)
		// @1C94: ldc_w 43034 (0xa81a)
		// @1C97: iastore
		// @1C98: dup
		// @1C99: sipush 935 (0x03A7)
		// @1C9C: ldc_w 43072 (0xa840)
		// @1C9F: iastore
		// @1CA0: dup
		// @1CA1: sipush 936 (0x03A8)
		// @1CA4: ldc_w 43110 (0xa866)
		// @1CA7: iastore
		// @1CA8: dup
		// @1CA9: sipush 937 (0x03A9)
		// @1CAC: ldc_w 43148 (0xa88c)
		// @1CAF: iastore
		// @1CB0: dup
		// @1CB1: sipush 938 (0x03AA)
		// @1CB4: ldc_w 43186 (0xa8b2)
		// @1CB7: iastore
		// @1CB8: dup
		// @1CB9: sipush 939 (0x03AB)
		// @1CBC: ldc_w 43223 (0xa8d7)
		// @1CBF: iastore
		// @1CC0: dup
		// @1CC1: sipush 940 (0x03AC)
		// @1CC4: ldc_w 43261 (0xa8fd)
		// @1CC7: iastore
		// @1CC8: dup
		// @1CC9: sipush 941 (0x03AD)
		// @1CCC: ldc_w 43299 (0xa923)
		// @1CCF: iastore
		// @1CD0: dup
		// @1CD1: sipush 942 (0x03AE)
		// @1CD4: ldc_w 43337 (0xa949)
		// @1CD7: iastore
		// @1CD8: dup
		// @1CD9: sipush 943 (0x03AF)
		// @1CDC: ldc_w 43374 (0xa96e)
		// @1CDF: iastore
		// @1CE0: dup
		// @1CE1: sipush 944 (0x03B0)
		// @1CE4: ldc_w 43412 (0xa994)
		// @1CE7: iastore
		// @1CE8: dup
		// @1CE9: sipush 945 (0x03B1)
		// @1CEC: ldc_w 43450 (0xa9ba)
		// @1CEF: iastore
		// @1CF0: dup
		// @1CF1: sipush 946 (0x03B2)
		// @1CF4: ldc_w 43487 (0xa9df)
		// @1CF7: iastore
		// @1CF8: dup
		// @1CF9: sipush 947 (0x03B3)
		// @1CFC: ldc_w 43525 (0xaa05)
		// @1CFF: iastore
		// @1D00: dup
		// @1D01: sipush 948 (0x03B4)
		// @1D04: ldc_w 43562 (0xaa2a)
		// @1D07: iastore
		// @1D08: dup
		// @1D09: sipush 949 (0x03B5)
		// @1D0C: ldc_w 43600 (0xaa50)
		// @1D0F: iastore
		// @1D10: dup
		// @1D11: sipush 950 (0x03B6)
		// @1D14: ldc_w 43638 (0xaa76)
		// @1D17: iastore
		// @1D18: dup
		// @1D19: sipush 951 (0x03B7)
		// @1D1C: ldc_w 43675 (0xaa9b)
		// @1D1F: iastore
		// @1D20: dup
		// @1D21: sipush 952 (0x03B8)
		// @1D24: ldc_w 43713 (0xaac1)
		// @1D27: iastore
		// @1D28: dup
		// @1D29: sipush 953 (0x03B9)
		// @1D2C: ldc_w 43750 (0xaae6)
		// @1D2F: iastore
		// @1D30: dup
		// @1D31: sipush 954 (0x03BA)
		// @1D34: ldc_w 43787 (0xab0b)
		// @1D37: iastore
		// @1D38: dup
		// @1D39: sipush 955 (0x03BB)
		// @1D3C: ldc_w 43825 (0xab31)
		// @1D3F: iastore
		// @1D40: dup
		// @1D41: sipush 956 (0x03BC)
		// @1D44: ldc_w 43862 (0xab56)
		// @1D47: iastore
		// @1D48: dup
		// @1D49: sipush 957 (0x03BD)
		// @1D4C: ldc_w 43899 (0xab7b)
		// @1D4F: iastore
		// @1D50: dup
		// @1D51: sipush 958 (0x03BE)
		// @1D54: ldc_w 43937 (0xaba1)
		// @1D57: iastore
		// @1D58: dup
		// @1D59: sipush 959 (0x03BF)
		// @1D5C: ldc_w 43974 (0xabc6)
		// @1D5F: iastore
		// @1D60: dup
		// @1D61: sipush 960 (0x03C0)
		// @1D64: ldc_w 44011 (0xabeb)
		// @1D67: iastore
		// @1D68: dup
		// @1D69: sipush 961 (0x03C1)
		// @1D6C: ldc_w 44049 (0xac11)
		// @1D6F: iastore
		// @1D70: dup
		// @1D71: sipush 962 (0x03C2)
		// @1D74: ldc_w 44086 (0xac36)
		// @1D77: iastore
		// @1D78: dup
		// @1D79: sipush 963 (0x03C3)
		// @1D7C: ldc_w 44123 (0xac5b)
		// @1D7F: iastore
		// @1D80: dup
		// @1D81: sipush 964 (0x03C4)
		// @1D84: ldc_w 44160 (0xac80)
		// @1D87: iastore
		// @1D88: dup
		// @1D89: sipush 965 (0x03C5)
		// @1D8C: ldc_w 44197 (0xaca5)
		// @1D8F: iastore
		// @1D90: dup
		// @1D91: sipush 966 (0x03C6)
		// @1D94: ldc_w 44234 (0xacca)
		// @1D97: iastore
		// @1D98: dup
		// @1D99: sipush 967 (0x03C7)
		// @1D9C: ldc_w 44271 (0xacef)
		// @1D9F: iastore
		// @1DA0: dup
		// @1DA1: sipush 968 (0x03C8)
		// @1DA4: ldc_w 44308 (0xad14)
		// @1DA7: iastore
		// @1DA8: dup
		// @1DA9: sipush 969 (0x03C9)
		// @1DAC: ldc_w 44345 (0xad39)
		// @1DAF: iastore
		// @1DB0: dup
		// @1DB1: sipush 970 (0x03CA)
		// @1DB4: ldc_w 44382 (0xad5e)
		// @1DB7: iastore
		// @1DB8: dup
		// @1DB9: sipush 971 (0x03CB)
		// @1DBC: ldc_w 44419 (0xad83)
		// @1DBF: iastore
		// @1DC0: dup
		// @1DC1: sipush 972 (0x03CC)
		// @1DC4: ldc_w 44456 (0xada8)
		// @1DC7: iastore
		// @1DC8: dup
		// @1DC9: sipush 973 (0x03CD)
		// @1DCC: ldc_w 44493 (0xadcd)
		// @1DCF: iastore
		// @1DD0: dup
		// @1DD1: sipush 974 (0x03CE)
		// @1DD4: ldc_w 44530 (0xadf2)
		// @1DD7: iastore
		// @1DD8: dup
		// @1DD9: sipush 975 (0x03CF)
		// @1DDC: ldc_w 44567 (0xae17)
		// @1DDF: iastore
		// @1DE0: dup
		// @1DE1: sipush 976 (0x03D0)
		// @1DE4: ldc_w 44604 (0xae3c)
		// @1DE7: iastore
		// @1DE8: dup
		// @1DE9: sipush 977 (0x03D1)
		// @1DEC: ldc_w 44641 (0xae61)
		// @1DEF: iastore
		// @1DF0: dup
		// @1DF1: sipush 978 (0x03D2)
		// @1DF4: ldc_w 44677 (0xae85)
		// @1DF7: iastore
		// @1DF8: dup
		// @1DF9: sipush 979 (0x03D3)
		// @1DFC: ldc_w 44714 (0xaeaa)
		// @1DFF: iastore
		// @1E00: dup
		// @1E01: sipush 980 (0x03D4)
		// @1E04: ldc_w 44751 (0xaecf)
		// @1E07: iastore
		// @1E08: dup
		// @1E09: sipush 981 (0x03D5)
		// @1E0C: ldc_w 44788 (0xaef4)
		// @1E0F: iastore
		// @1E10: dup
		// @1E11: sipush 982 (0x03D6)
		// @1E14: ldc_w 44824 (0xaf18)
		// @1E17: iastore
		// @1E18: dup
		// @1E19: sipush 983 (0x03D7)
		// @1E1C: ldc_w 44861 (0xaf3d)
		// @1E1F: iastore
		// @1E20: dup
		// @1E21: sipush 984 (0x03D8)
		// @1E24: ldc_w 44898 (0xaf62)
		// @1E27: iastore
		// @1E28: dup
		// @1E29: sipush 985 (0x03D9)
		// @1E2C: ldc_w 44934 (0xaf86)
		// @1E2F: iastore
		// @1E30: dup
		// @1E31: sipush 986 (0x03DA)
		// @1E34: ldc_w 44971 (0xafab)
		// @1E37: iastore
		// @1E38: dup
		// @1E39: sipush 987 (0x03DB)
		// @1E3C: ldc_w 45007 (0xafcf)
		// @1E3F: iastore
		// @1E40: dup
		// @1E41: sipush 988 (0x03DC)
		// @1E44: ldc_w 45044 (0xaff4)
		// @1E47: iastore
		// @1E48: dup
		// @1E49: sipush 989 (0x03DD)
		// @1E4C: ldc_w 45080 (0xb018)
		// @1E4F: iastore
		// @1E50: dup
		// @1E51: sipush 990 (0x03DE)
		// @1E54: ldc_w 45117 (0xb03d)
		// @1E57: iastore
		// @1E58: dup
		// @1E59: sipush 991 (0x03DF)
		// @1E5C: ldc_w 45153 (0xb061)
		// @1E5F: iastore
		// @1E60: dup
		// @1E61: sipush 992 (0x03E0)
		// @1E64: ldc_w 45190 (0xb086)
		// @1E67: iastore
		// @1E68: dup
		// @1E69: sipush 993 (0x03E1)
		// @1E6C: ldc_w 45226 (0xb0aa)
		// @1E6F: iastore
		// @1E70: dup
		// @1E71: sipush 994 (0x03E2)
		// @1E74: ldc_w 45262 (0xb0ce)
		// @1E77: iastore
		// @1E78: dup
		// @1E79: sipush 995 (0x03E3)
		// @1E7C: ldc_w 45299 (0xb0f3)
		// @1E7F: iastore
		// @1E80: dup
		// @1E81: sipush 996 (0x03E4)
		// @1E84: ldc_w 45335 (0xb117)
		// @1E87: iastore
		// @1E88: dup
		// @1E89: sipush 997 (0x03E5)
		// @1E8C: ldc_w 45371 (0xb13b)
		// @1E8F: iastore
		// @1E90: dup
		// @1E91: sipush 998 (0x03E6)
		// @1E94: ldc_w 45408 (0xb160)
		// @1E97: iastore
		// @1E98: dup
		// @1E99: sipush 999 (0x03E7)
		// @1E9C: ldc_w 45444 (0xb184)
		// @1E9F: iastore
		// @1EA0: dup
		// @1EA1: sipush 1000 (0x03E8)
		// @1EA4: ldc_w 45480 (0xb1a8)
		// @1EA7: iastore
		// @1EA8: dup
		// @1EA9: sipush 1001 (0x03E9)
		// @1EAC: ldc_w 45516 (0xb1cc)
		// @1EAF: iastore
		// @1EB0: dup
		// @1EB1: sipush 1002 (0x03EA)
		// @1EB4: ldc_w 45552 (0xb1f0)
		// @1EB7: iastore
		// @1EB8: dup
		// @1EB9: sipush 1003 (0x03EB)
		// @1EBC: ldc_w 45589 (0xb215)
		// @1EBF: iastore
		// @1EC0: dup
		// @1EC1: sipush 1004 (0x03EC)
		// @1EC4: ldc_w 45625 (0xb239)
		// @1EC7: iastore
		// @1EC8: dup
		// @1EC9: sipush 1005 (0x03ED)
		// @1ECC: ldc_w 45661 (0xb25d)
		// @1ECF: iastore
		// @1ED0: dup
		// @1ED1: sipush 1006 (0x03EE)
		// @1ED4: ldc_w 45697 (0xb281)
		// @1ED7: iastore
		// @1ED8: dup
		// @1ED9: sipush 1007 (0x03EF)
		// @1EDC: ldc_w 45733 (0xb2a5)
		// @1EDF: iastore
		// @1EE0: dup
		// @1EE1: sipush 1008 (0x03F0)
		// @1EE4: ldc_w 45769 (0xb2c9)
		// @1EE7: iastore
		// @1EE8: dup
		// @1EE9: sipush 1009 (0x03F1)
		// @1EEC: ldc_w 45805 (0xb2ed)
		// @1EEF: iastore
		// @1EF0: dup
		// @1EF1: sipush 1010 (0x03F2)
		// @1EF4: ldc_w 45841 (0xb311)
		// @1EF7: iastore
		// @1EF8: dup
		// @1EF9: sipush 1011 (0x03F3)
		// @1EFC: ldc_w 45877 (0xb335)
		// @1EFF: iastore
		// @1F00: dup
		// @1F01: sipush 1012 (0x03F4)
		// @1F04: ldc_w 45912 (0xb358)
		// @1F07: iastore
		// @1F08: dup
		// @1F09: sipush 1013 (0x03F5)
		// @1F0C: ldc_w 45948 (0xb37c)
		// @1F0F: iastore
		// @1F10: dup
		// @1F11: sipush 1014 (0x03F6)
		// @1F14: ldc_w 45984 (0xb3a0)
		// @1F17: iastore
		// @1F18: dup
		// @1F19: sipush 1015 (0x03F7)
		// @1F1C: ldc_w 46020 (0xb3c4)
		// @1F1F: iastore
		// @1F20: dup
		// @1F21: sipush 1016 (0x03F8)
		// @1F24: ldc_w 46056 (0xb3e8)
		// @1F27: iastore
		// @1F28: dup
		// @1F29: sipush 1017 (0x03F9)
		// @1F2C: ldc_w 46091 (0xb40b)
		// @1F2F: iastore
		// @1F30: dup
		// @1F31: sipush 1018 (0x03FA)
		// @1F34: ldc_w 46127 (0xb42f)
		// @1F37: iastore
		// @1F38: dup
		// @1F39: sipush 1019 (0x03FB)
		// @1F3C: ldc_w 46163 (0xb453)
		// @1F3F: iastore
		// @1F40: dup
		// @1F41: sipush 1020 (0x03FC)
		// @1F44: ldc_w 46199 (0xb477)
		// @1F47: iastore
		// @1F48: dup
		// @1F49: sipush 1021 (0x03FD)
		// @1F4C: ldc_w 46234 (0xb49a)
		// @1F4F: iastore
		// @1F50: dup
		// @1F51: sipush 1022 (0x03FE)
		// @1F54: ldc_w 46270 (0xb4be)
		// @1F57: iastore
		// @1F58: dup
		// @1F59: sipush 1023 (0x03FF)
		// @1F5C: ldc_w 46305 (0xb4e1)
		// @1F5F: iastore
		// @1F60: dup
		// @1F61: sipush 1024 (0x0400)
		// @1F64: ldc_w 46341 (0xb505)
		// @1F67: iastore
		// @1F68: dup
		// @1F69: sipush 1025 (0x0401)
		// @1F6C: ldc_w 46376 (0xb528)
		// @1F6F: iastore
		// @1F70: dup
		// @1F71: sipush 1026 (0x0402)
		// @1F74: ldc_w 46412 (0xb54c)
		// @1F77: iastore
		// @1F78: dup
		// @1F79: sipush 1027 (0x0403)
		// @1F7C: ldc_w 46447 (0xb56f)
		// @1F7F: iastore
		// @1F80: dup
		// @1F81: sipush 1028 (0x0404)
		// @1F84: ldc_w 46483 (0xb593)
		// @1F87: iastore
		// @1F88: dup
		// @1F89: sipush 1029 (0x0405)
		// @1F8C: ldc_w 46518 (0xb5b6)
		// @1F8F: iastore
		// @1F90: dup
		// @1F91: sipush 1030 (0x0406)
		// @1F94: ldc_w 46554 (0xb5da)
		// @1F97: iastore
		// @1F98: dup
		// @1F99: sipush 1031 (0x0407)
		// @1F9C: ldc_w 46589 (0xb5fd)
		// @1F9F: iastore
		// @1FA0: dup
		// @1FA1: sipush 1032 (0x0408)
		// @1FA4: ldc_w 46624 (0xb620)
		// @1FA7: iastore
		// @1FA8: dup
		// @1FA9: sipush 1033 (0x0409)
		// @1FAC: ldc_w 46660 (0xb644)
		// @1FAF: iastore
		// @1FB0: dup
		// @1FB1: sipush 1034 (0x040A)
		// @1FB4: ldc_w 46695 (0xb667)
		// @1FB7: iastore
		// @1FB8: dup
		// @1FB9: sipush 1035 (0x040B)
		// @1FBC: ldc_w 46730 (0xb68a)
		// @1FBF: iastore
		// @1FC0: dup
		// @1FC1: sipush 1036 (0x040C)
		// @1FC4: ldc_w 46765 (0xb6ad)
		// @1FC7: iastore
		// @1FC8: dup
		// @1FC9: sipush 1037 (0x040D)
		// @1FCC: ldc_w 46801 (0xb6d1)
		// @1FCF: iastore
		// @1FD0: dup
		// @1FD1: sipush 1038 (0x040E)
		// @1FD4: ldc_w 46836 (0xb6f4)
		// @1FD7: iastore
		// @1FD8: dup
		// @1FD9: sipush 1039 (0x040F)
		// @1FDC: ldc_w 46871 (0xb717)
		// @1FDF: iastore
		// @1FE0: dup
		// @1FE1: sipush 1040 (0x0410)
		// @1FE4: ldc_w 46906 (0xb73a)
		// @1FE7: iastore
		// @1FE8: dup
		// @1FE9: sipush 1041 (0x0411)
		// @1FEC: ldc_w 46941 (0xb75d)
		// @1FEF: iastore
		// @1FF0: dup
		// @1FF1: sipush 1042 (0x0412)
		// @1FF4: ldc_w 46976 (0xb780)
		// @1FF7: iastore
		// @1FF8: dup
		// @1FF9: sipush 1043 (0x0413)
		// @1FFC: ldc_w 47011 (0xb7a3)
		// @1FFF: iastore
		// @2000: dup
		// @2001: sipush 1044 (0x0414)
		// @2004: ldc_w 47046 (0xb7c6)
		// @2007: iastore
		// @2008: dup
		// @2009: sipush 1045 (0x0415)
		// @200C: ldc_w 47081 (0xb7e9)
		// @200F: iastore
		// @2010: dup
		// @2011: sipush 1046 (0x0416)
		// @2014: ldc_w 47116 (0xb80c)
		// @2017: iastore
		// @2018: dup
		// @2019: sipush 1047 (0x0417)
		// @201C: ldc_w 47151 (0xb82f)
		// @201F: iastore
		// @2020: dup
		// @2021: sipush 1048 (0x0418)
		// @2024: ldc_w 47186 (0xb852)
		// @2027: iastore
		// @2028: dup
		// @2029: sipush 1049 (0x0419)
		// @202C: ldc_w 47221 (0xb875)
		// @202F: iastore
		// @2030: dup
		// @2031: sipush 1050 (0x041A)
		// @2034: ldc_w 47256 (0xb898)
		// @2037: iastore
		// @2038: dup
		// @2039: sipush 1051 (0x041B)
		// @203C: ldc_w 47291 (0xb8bb)
		// @203F: iastore
		// @2040: dup
		// @2041: sipush 1052 (0x041C)
		// @2044: ldc_w 47325 (0xb8dd)
		// @2047: iastore
		// @2048: dup
		// @2049: sipush 1053 (0x041D)
		// @204C: ldc_w 47360 (0xb900)
		// @204F: iastore
		// @2050: dup
		// @2051: sipush 1054 (0x041E)
		// @2054: ldc_w 47395 (0xb923)
		// @2057: iastore
		// @2058: dup
		// @2059: sipush 1055 (0x041F)
		// @205C: ldc_w 47430 (0xb946)
		// @205F: iastore
		// @2060: dup
		// @2061: sipush 1056 (0x0420)
		// @2064: ldc_w 47464 (0xb968)
		// @2067: iastore
		// @2068: dup
		// @2069: sipush 1057 (0x0421)
		// @206C: ldc_w 47499 (0xb98b)
		// @206F: iastore
		// @2070: dup
		// @2071: sipush 1058 (0x0422)
		// @2074: ldc_w 47534 (0xb9ae)
		// @2077: iastore
		// @2078: dup
		// @2079: sipush 1059 (0x0423)
		// @207C: ldc_w 47568 (0xb9d0)
		// @207F: iastore
		// @2080: dup
		// @2081: sipush 1060 (0x0424)
		// @2084: ldc_w 47603 (0xb9f3)
		// @2087: iastore
		// @2088: dup
		// @2089: sipush 1061 (0x0425)
		// @208C: ldc_w 47637 (0xba15)
		// @208F: iastore
		// @2090: dup
		// @2091: sipush 1062 (0x0426)
		// @2094: ldc_w 47672 (0xba38)
		// @2097: iastore
		// @2098: dup
		// @2099: sipush 1063 (0x0427)
		// @209C: ldc_w 47706 (0xba5a)
		// @209F: iastore
		// @20A0: dup
		// @20A1: sipush 1064 (0x0428)
		// @20A4: ldc_w 47741 (0xba7d)
		// @20A7: iastore
		// @20A8: dup
		// @20A9: sipush 1065 (0x0429)
		// @20AC: ldc_w 47775 (0xba9f)
		// @20AF: iastore
		// @20B0: dup
		// @20B1: sipush 1066 (0x042A)
		// @20B4: ldc_w 47809 (0xbac1)
		// @20B7: iastore
		// @20B8: dup
		// @20B9: sipush 1067 (0x042B)
		// @20BC: ldc_w 47844 (0xbae4)
		// @20BF: iastore
		// @20C0: dup
		// @20C1: sipush 1068 (0x042C)
		// @20C4: ldc_w 47878 (0xbb06)
		// @20C7: iastore
		// @20C8: dup
		// @20C9: sipush 1069 (0x042D)
		// @20CC: ldc_w 47912 (0xbb28)
		// @20CF: iastore
		// @20D0: dup
		// @20D1: sipush 1070 (0x042E)
		// @20D4: ldc_w 47947 (0xbb4b)
		// @20D7: iastore
		// @20D8: dup
		// @20D9: sipush 1071 (0x042F)
		// @20DC: ldc_w 47981 (0xbb6d)
		// @20DF: iastore
		// @20E0: dup
		// @20E1: sipush 1072 (0x0430)
		// @20E4: ldc_w 48015 (0xbb8f)
		// @20E7: iastore
		// @20E8: dup
		// @20E9: sipush 1073 (0x0431)
		// @20EC: ldc_w 48049 (0xbbb1)
		// @20EF: iastore
		// @20F0: dup
		// @20F1: sipush 1074 (0x0432)
		// @20F4: ldc_w 48084 (0xbbd4)
		// @20F7: iastore
		// @20F8: dup
		// @20F9: sipush 1075 (0x0433)
		// @20FC: ldc_w 48118 (0xbbf6)
		// @20FF: iastore
		// @2100: dup
		// @2101: sipush 1076 (0x0434)
		// @2104: ldc_w 48152 (0xbc18)
		// @2107: iastore
		// @2108: dup
		// @2109: sipush 1077 (0x0435)
		// @210C: ldc_w 48186 (0xbc3a)
		// @210F: iastore
		// @2110: dup
		// @2111: sipush 1078 (0x0436)
		// @2114: ldc_w 48220 (0xbc5c)
		// @2117: iastore
		// @2118: dup
		// @2119: sipush 1079 (0x0437)
		// @211C: ldc_w 48254 (0xbc7e)
		// @211F: iastore
		// @2120: dup
		// @2121: sipush 1080 (0x0438)
		// @2124: ldc_w 48288 (0xbca0)
		// @2127: iastore
		// @2128: dup
		// @2129: sipush 1081 (0x0439)
		// @212C: ldc_w 48322 (0xbcc2)
		// @212F: iastore
		// @2130: dup
		// @2131: sipush 1082 (0x043A)
		// @2134: ldc_w 48356 (0xbce4)
		// @2137: iastore
		// @2138: dup
		// @2139: sipush 1083 (0x043B)
		// @213C: ldc_w 48390 (0xbd06)
		// @213F: iastore
		// @2140: dup
		// @2141: sipush 1084 (0x043C)
		// @2144: ldc_w 48424 (0xbd28)
		// @2147: iastore
		// @2148: dup
		// @2149: sipush 1085 (0x043D)
		// @214C: ldc_w 48458 (0xbd4a)
		// @214F: iastore
		// @2150: dup
		// @2151: sipush 1086 (0x043E)
		// @2154: ldc_w 48491 (0xbd6b)
		// @2157: iastore
		// @2158: dup
		// @2159: sipush 1087 (0x043F)
		// @215C: ldc_w 48525 (0xbd8d)
		// @215F: iastore
		// @2160: dup
		// @2161: sipush 1088 (0x0440)
		// @2164: ldc_w 48559 (0xbdaf)
		// @2167: iastore
		// @2168: dup
		// @2169: sipush 1089 (0x0441)
		// @216C: ldc_w 48593 (0xbdd1)
		// @216F: iastore
		// @2170: dup
		// @2171: sipush 1090 (0x0442)
		// @2174: ldc_w 48626 (0xbdf2)
		// @2177: iastore
		// @2178: dup
		// @2179: sipush 1091 (0x0443)
		// @217C: ldc_w 48660 (0xbe14)
		// @217F: iastore
		// @2180: dup
		// @2181: sipush 1092 (0x0444)
		// @2184: ldc_w 48694 (0xbe36)
		// @2187: iastore
		// @2188: dup
		// @2189: sipush 1093 (0x0445)
		// @218C: ldc_w 48727 (0xbe57)
		// @218F: iastore
		// @2190: dup
		// @2191: sipush 1094 (0x0446)
		// @2194: ldc_w 48761 (0xbe79)
		// @2197: iastore
		// @2198: dup
		// @2199: sipush 1095 (0x0447)
		// @219C: ldc_w 48795 (0xbe9b)
		// @219F: iastore
		// @21A0: dup
		// @21A1: sipush 1096 (0x0448)
		// @21A4: ldc_w 48828 (0xbebc)
		// @21A7: iastore
		// @21A8: dup
		// @21A9: sipush 1097 (0x0449)
		// @21AC: ldc_w 48862 (0xbede)
		// @21AF: iastore
		// @21B0: dup
		// @21B1: sipush 1098 (0x044A)
		// @21B4: ldc_w 48895 (0xbeff)
		// @21B7: iastore
		// @21B8: dup
		// @21B9: sipush 1099 (0x044B)
		// @21BC: ldc_w 48929 (0xbf21)
		// @21BF: iastore
		// @21C0: dup
		// @21C1: sipush 1100 (0x044C)
		// @21C4: ldc_w 48962 (0xbf42)
		// @21C7: iastore
		// @21C8: dup
		// @21C9: sipush 1101 (0x044D)
		// @21CC: ldc_w 48995 (0xbf63)
		// @21CF: iastore
		// @21D0: dup
		// @21D1: sipush 1102 (0x044E)
		// @21D4: ldc_w 49029 (0xbf85)
		// @21D7: iastore
		// @21D8: dup
		// @21D9: sipush 1103 (0x044F)
		// @21DC: ldc_w 49062 (0xbfa6)
		// @21DF: iastore
		// @21E0: dup
		// @21E1: sipush 1104 (0x0450)
		// @21E4: ldc_w 49095 (0xbfc7)
		// @21E7: iastore
		// @21E8: dup
		// @21E9: sipush 1105 (0x0451)
		// @21EC: ldc_w 49129 (0xbfe9)
		// @21EF: iastore
		// @21F0: dup
		// @21F1: sipush 1106 (0x0452)
		// @21F4: ldc_w 49162 (0xc00a)
		// @21F7: iastore
		// @21F8: dup
		// @21F9: sipush 1107 (0x0453)
		// @21FC: ldc_w 49195 (0xc02b)
		// @21FF: iastore
		// @2200: dup
		// @2201: sipush 1108 (0x0454)
		// @2204: ldc_w 49228 (0xc04c)
		// @2207: iastore
		// @2208: dup
		// @2209: sipush 1109 (0x0455)
		// @220C: ldc_w 49262 (0xc06e)
		// @220F: iastore
		// @2210: dup
		// @2211: sipush 1110 (0x0456)
		// @2214: ldc_w 49295 (0xc08f)
		// @2217: iastore
		// @2218: dup
		// @2219: sipush 1111 (0x0457)
		// @221C: ldc_w 49328 (0xc0b0)
		// @221F: iastore
		// @2220: dup
		// @2221: sipush 1112 (0x0458)
		// @2224: ldc_w 49361 (0xc0d1)
		// @2227: iastore
		// @2228: dup
		// @2229: sipush 1113 (0x0459)
		// @222C: ldc_w 49394 (0xc0f2)
		// @222F: iastore
		// @2230: dup
		// @2231: sipush 1114 (0x045A)
		// @2234: ldc_w 49427 (0xc113)
		// @2237: iastore
		// @2238: dup
		// @2239: sipush 1115 (0x045B)
		// @223C: ldc_w 49460 (0xc134)
		// @223F: iastore
		// @2240: dup
		// @2241: sipush 1116 (0x045C)
		// @2244: ldc_w 49493 (0xc155)
		// @2247: iastore
		// @2248: dup
		// @2249: sipush 1117 (0x045D)
		// @224C: ldc_w 49526 (0xc176)
		// @224F: iastore
		// @2250: dup
		// @2251: sipush 1118 (0x045E)
		// @2254: ldc_w 49559 (0xc197)
		// @2257: iastore
		// @2258: dup
		// @2259: sipush 1119 (0x045F)
		// @225C: ldc_w 49592 (0xc1b8)
		// @225F: iastore
		// @2260: dup
		// @2261: sipush 1120 (0x0460)
		// @2264: ldc_w 49624 (0xc1d8)
		// @2267: iastore
		// @2268: dup
		// @2269: sipush 1121 (0x0461)
		// @226C: ldc_w 49657 (0xc1f9)
		// @226F: iastore
		// @2270: dup
		// @2271: sipush 1122 (0x0462)
		// @2274: ldc_w 49690 (0xc21a)
		// @2277: iastore
		// @2278: dup
		// @2279: sipush 1123 (0x0463)
		// @227C: ldc_w 49723 (0xc23b)
		// @227F: iastore
		// @2280: dup
		// @2281: sipush 1124 (0x0464)
		// @2284: ldc_w 49756 (0xc25c)
		// @2287: iastore
		// @2288: dup
		// @2289: sipush 1125 (0x0465)
		// @228C: ldc_w 49788 (0xc27c)
		// @228F: iastore
		// @2290: dup
		// @2291: sipush 1126 (0x0466)
		// @2294: ldc_w 49821 (0xc29d)
		// @2297: iastore
		// @2298: dup
		// @2299: sipush 1127 (0x0467)
		// @229C: ldc_w 49854 (0xc2be)
		// @229F: iastore
		// @22A0: dup
		// @22A1: sipush 1128 (0x0468)
		// @22A4: ldc_w 49886 (0xc2de)
		// @22A7: iastore
		// @22A8: dup
		// @22A9: sipush 1129 (0x0469)
		// @22AC: ldc_w 49919 (0xc2ff)
		// @22AF: iastore
		// @22B0: dup
		// @22B1: sipush 1130 (0x046A)
		// @22B4: ldc_w 49951 (0xc31f)
		// @22B7: iastore
		// @22B8: dup
		// @22B9: sipush 1131 (0x046B)
		// @22BC: ldc_w 49984 (0xc340)
		// @22BF: iastore
		// @22C0: dup
		// @22C1: sipush 1132 (0x046C)
		// @22C4: ldc_w 50016 (0xc360)
		// @22C7: iastore
		// @22C8: dup
		// @22C9: sipush 1133 (0x046D)
		// @22CC: ldc_w 50049 (0xc381)
		// @22CF: iastore
		// @22D0: dup
		// @22D1: sipush 1134 (0x046E)
		// @22D4: ldc_w 50081 (0xc3a1)
		// @22D7: iastore
		// @22D8: dup
		// @22D9: sipush 1135 (0x046F)
		// @22DC: ldc_w 50114 (0xc3c2)
		// @22DF: iastore
		// @22E0: dup
		// @22E1: sipush 1136 (0x0470)
		// @22E4: ldc_w 50146 (0xc3e2)
		// @22E7: iastore
		// @22E8: dup
		// @22E9: sipush 1137 (0x0471)
		// @22EC: ldc_w 50178 (0xc402)
		// @22EF: iastore
		// @22F0: dup
		// @22F1: sipush 1138 (0x0472)
		// @22F4: ldc_w 50211 (0xc423)
		// @22F7: iastore
		// @22F8: dup
		// @22F9: sipush 1139 (0x0473)
		// @22FC: ldc_w 50243 (0xc443)
		// @22FF: iastore
		// @2300: dup
		// @2301: sipush 1140 (0x0474)
		// @2304: ldc_w 50275 (0xc463)
		// @2307: iastore
		// @2308: dup
		// @2309: sipush 1141 (0x0475)
		// @230C: ldc_w 50307 (0xc483)
		// @230F: iastore
		// @2310: dup
		// @2311: sipush 1142 (0x0476)
		// @2314: ldc_w 50340 (0xc4a4)
		// @2317: iastore
		// @2318: dup
		// @2319: sipush 1143 (0x0477)
		// @231C: ldc_w 50372 (0xc4c4)
		// @231F: iastore
		// @2320: dup
		// @2321: sipush 1144 (0x0478)
		// @2324: ldc_w 50404 (0xc4e4)
		// @2327: iastore
		// @2328: dup
		// @2329: sipush 1145 (0x0479)
		// @232C: ldc_w 50436 (0xc504)
		// @232F: iastore
		// @2330: dup
		// @2331: sipush 1146 (0x047A)
		// @2334: ldc_w 50468 (0xc524)
		// @2337: iastore
		// @2338: dup
		// @2339: sipush 1147 (0x047B)
		// @233C: ldc_w 50500 (0xc544)
		// @233F: iastore
		// @2340: dup
		// @2341: sipush 1148 (0x047C)
		// @2344: ldc_w 50532 (0xc564)
		// @2347: iastore
		// @2348: dup
		// @2349: sipush 1149 (0x047D)
		// @234C: ldc_w 50564 (0xc584)
		// @234F: iastore
		// @2350: dup
		// @2351: sipush 1150 (0x047E)
		// @2354: ldc_w 50596 (0xc5a4)
		// @2357: iastore
		// @2358: dup
		// @2359: sipush 1151 (0x047F)
		// @235C: ldc_w 50628 (0xc5c4)
		// @235F: iastore
		// @2360: dup
		// @2361: sipush 1152 (0x0480)
		// @2364: ldc_w 50660 (0xc5e4)
		// @2367: iastore
		// @2368: dup
		// @2369: sipush 1153 (0x0481)
		// @236C: ldc_w 50692 (0xc604)
		// @236F: iastore
		// @2370: dup
		// @2371: sipush 1154 (0x0482)
		// @2374: ldc_w 50724 (0xc624)
		// @2377: iastore
		// @2378: dup
		// @2379: sipush 1155 (0x0483)
		// @237C: ldc_w 50756 (0xc644)
		// @237F: iastore
		// @2380: dup
		// @2381: sipush 1156 (0x0484)
		// @2384: ldc_w 50787 (0xc663)
		// @2387: iastore
		// @2388: dup
		// @2389: sipush 1157 (0x0485)
		// @238C: ldc_w 50819 (0xc683)
		// @238F: iastore
		// @2390: dup
		// @2391: sipush 1158 (0x0486)
		// @2394: ldc_w 50851 (0xc6a3)
		// @2397: iastore
		// @2398: dup
		// @2399: sipush 1159 (0x0487)
		// @239C: ldc_w 50882 (0xc6c2)
		// @239F: iastore
		// @23A0: dup
		// @23A1: sipush 1160 (0x0488)
		// @23A4: ldc_w 50914 (0xc6e2)
		// @23A7: iastore
		// @23A8: dup
		// @23A9: sipush 1161 (0x0489)
		// @23AC: ldc_w 50946 (0xc702)
		// @23AF: iastore
		// @23B0: dup
		// @23B1: sipush 1162 (0x048A)
		// @23B4: ldc_w 50977 (0xc721)
		// @23B7: iastore
		// @23B8: dup
		// @23B9: sipush 1163 (0x048B)
		// @23BC: ldc_w 51009 (0xc741)
		// @23BF: iastore
		// @23C0: dup
		// @23C1: sipush 1164 (0x048C)
		// @23C4: ldc_w 51041 (0xc761)
		// @23C7: iastore
		// @23C8: dup
		// @23C9: sipush 1165 (0x048D)
		// @23CC: ldc_w 51072 (0xc780)
		// @23CF: iastore
		// @23D0: dup
		// @23D1: sipush 1166 (0x048E)
		// @23D4: ldc_w 51104 (0xc7a0)
		// @23D7: iastore
		// @23D8: dup
		// @23D9: sipush 1167 (0x048F)
		// @23DC: ldc_w 51135 (0xc7bf)
		// @23DF: iastore
		// @23E0: dup
		// @23E1: sipush 1168 (0x0490)
		// @23E4: ldc_w 51166 (0xc7de)
		// @23E7: iastore
		// @23E8: dup
		// @23E9: sipush 1169 (0x0491)
		// @23EC: ldc_w 51198 (0xc7fe)
		// @23EF: iastore
		// @23F0: dup
		// @23F1: sipush 1170 (0x0492)
		// @23F4: ldc_w 51229 (0xc81d)
		// @23F7: iastore
		// @23F8: dup
		// @23F9: sipush 1171 (0x0493)
		// @23FC: ldc_w 51260 (0xc83c)
		// @23FF: iastore
		// @2400: dup
		// @2401: sipush 1172 (0x0494)
		// @2404: ldc_w 51292 (0xc85c)
		// @2407: iastore
		// @2408: dup
		// @2409: sipush 1173 (0x0495)
		// @240C: ldc_w 51323 (0xc87b)
		// @240F: iastore
		// @2410: dup
		// @2411: sipush 1174 (0x0496)
		// @2414: ldc_w 51354 (0xc89a)
		// @2417: iastore
		// @2418: dup
		// @2419: sipush 1175 (0x0497)
		// @241C: ldc_w 51386 (0xc8ba)
		// @241F: iastore
		// @2420: dup
		// @2421: sipush 1176 (0x0498)
		// @2424: ldc_w 51417 (0xc8d9)
		// @2427: iastore
		// @2428: dup
		// @2429: sipush 1177 (0x0499)
		// @242C: ldc_w 51448 (0xc8f8)
		// @242F: iastore
		// @2430: dup
		// @2431: sipush 1178 (0x049A)
		// @2434: ldc_w 51479 (0xc917)
		// @2437: iastore
		// @2438: dup
		// @2439: sipush 1179 (0x049B)
		// @243C: ldc_w 51510 (0xc936)
		// @243F: iastore
		// @2440: dup
		// @2441: sipush 1180 (0x049C)
		// @2444: ldc_w 51541 (0xc955)
		// @2447: iastore
		// @2448: dup
		// @2449: sipush 1181 (0x049D)
		// @244C: ldc_w 51572 (0xc974)
		// @244F: iastore
		// @2450: dup
		// @2451: sipush 1182 (0x049E)
		// @2454: ldc_w 51603 (0xc993)
		// @2457: iastore
		// @2458: dup
		// @2459: sipush 1183 (0x049F)
		// @245C: ldc_w 51634 (0xc9b2)
		// @245F: iastore
		// @2460: dup
		// @2461: sipush 1184 (0x04A0)
		// @2464: ldc_w 51665 (0xc9d1)
		// @2467: iastore
		// @2468: dup
		// @2469: sipush 1185 (0x04A1)
		// @246C: ldc_w 51696 (0xc9f0)
		// @246F: iastore
		// @2470: dup
		// @2471: sipush 1186 (0x04A2)
		// @2474: ldc_w 51727 (0xca0f)
		// @2477: iastore
		// @2478: dup
		// @2479: sipush 1187 (0x04A3)
		// @247C: ldc_w 51758 (0xca2e)
		// @247F: iastore
		// @2480: dup
		// @2481: sipush 1188 (0x04A4)
		// @2484: ldc_w 51789 (0xca4d)
		// @2487: iastore
		// @2488: dup
		// @2489: sipush 1189 (0x04A5)
		// @248C: ldc_w 51819 (0xca6b)
		// @248F: iastore
		// @2490: dup
		// @2491: sipush 1190 (0x04A6)
		// @2494: ldc_w 51850 (0xca8a)
		// @2497: iastore
		// @2498: dup
		// @2499: sipush 1191 (0x04A7)
		// @249C: ldc_w 51881 (0xcaa9)
		// @249F: iastore
		// @24A0: dup
		// @24A1: sipush 1192 (0x04A8)
		// @24A4: ldc_w 51911 (0xcac7)
		// @24A7: iastore
		// @24A8: dup
		// @24A9: sipush 1193 (0x04A9)
		// @24AC: ldc_w 51942 (0xcae6)
		// @24AF: iastore
		// @24B0: dup
		// @24B1: sipush 1194 (0x04AA)
		// @24B4: ldc_w 51973 (0xcb05)
		// @24B7: iastore
		// @24B8: dup
		// @24B9: sipush 1195 (0x04AB)
		// @24BC: ldc_w 52003 (0xcb23)
		// @24BF: iastore
		// @24C0: dup
		// @24C1: sipush 1196 (0x04AC)
		// @24C4: ldc_w 52034 (0xcb42)
		// @24C7: iastore
		// @24C8: dup
		// @24C9: sipush 1197 (0x04AD)
		// @24CC: ldc_w 52065 (0xcb61)
		// @24CF: iastore
		// @24D0: dup
		// @24D1: sipush 1198 (0x04AE)
		// @24D4: ldc_w 52095 (0xcb7f)
		// @24D7: iastore
		// @24D8: dup
		// @24D9: sipush 1199 (0x04AF)
		// @24DC: ldc_w 52126 (0xcb9e)
		// @24DF: iastore
		// @24E0: dup
		// @24E1: sipush 1200 (0x04B0)
		// @24E4: ldc_w 52156 (0xcbbc)
		// @24E7: iastore
		// @24E8: dup
		// @24E9: sipush 1201 (0x04B1)
		// @24EC: ldc_w 52186 (0xcbda)
		// @24EF: iastore
		// @24F0: dup
		// @24F1: sipush 1202 (0x04B2)
		// @24F4: ldc_w 52217 (0xcbf9)
		// @24F7: iastore
		// @24F8: dup
		// @24F9: sipush 1203 (0x04B3)
		// @24FC: ldc_w 52247 (0xcc17)
		// @24FF: iastore
		// @2500: dup
		// @2501: sipush 1204 (0x04B4)
		// @2504: ldc_w 52277 (0xcc35)
		// @2507: iastore
		// @2508: dup
		// @2509: sipush 1205 (0x04B5)
		// @250C: ldc_w 52308 (0xcc54)
		// @250F: iastore
		// @2510: dup
		// @2511: sipush 1206 (0x04B6)
		// @2514: ldc_w 52338 (0xcc72)
		// @2517: iastore
		// @2518: dup
		// @2519: sipush 1207 (0x04B7)
		// @251C: ldc_w 52368 (0xcc90)
		// @251F: iastore
		// @2520: dup
		// @2521: sipush 1208 (0x04B8)
		// @2524: ldc_w 52398 (0xccae)
		// @2527: iastore
		// @2528: dup
		// @2529: sipush 1209 (0x04B9)
		// @252C: ldc_w 52429 (0xcccd)
		// @252F: iastore
		// @2530: dup
		// @2531: sipush 1210 (0x04BA)
		// @2534: ldc_w 52459 (0xcceb)
		// @2537: iastore
		// @2538: dup
		// @2539: sipush 1211 (0x04BB)
		// @253C: ldc_w 52489 (0xcd09)
		// @253F: iastore
		// @2540: dup
		// @2541: sipush 1212 (0x04BC)
		// @2544: ldc_w 52519 (0xcd27)
		// @2547: iastore
		// @2548: dup
		// @2549: sipush 1213 (0x04BD)
		// @254C: ldc_w 52549 (0xcd45)
		// @254F: iastore
		// @2550: dup
		// @2551: sipush 1214 (0x04BE)
		// @2554: ldc_w 52579 (0xcd63)
		// @2557: iastore
		// @2558: dup
		// @2559: sipush 1215 (0x04BF)
		// @255C: ldc_w 52609 (0xcd81)
		// @255F: iastore
		// @2560: dup
		// @2561: sipush 1216 (0x04C0)
		// @2564: ldc_w 52639 (0xcd9f)
		// @2567: iastore
		// @2568: dup
		// @2569: sipush 1217 (0x04C1)
		// @256C: ldc_w 52669 (0xcdbd)
		// @256F: iastore
		// @2570: dup
		// @2571: sipush 1218 (0x04C2)
		// @2574: ldc_w 52699 (0xcddb)
		// @2577: iastore
		// @2578: dup
		// @2579: sipush 1219 (0x04C3)
		// @257C: ldc_w 52729 (0xcdf9)
		// @257F: iastore
		// @2580: dup
		// @2581: sipush 1220 (0x04C4)
		// @2584: ldc_w 52759 (0xce17)
		// @2587: iastore
		// @2588: dup
		// @2589: sipush 1221 (0x04C5)
		// @258C: ldc_w 52788 (0xce34)
		// @258F: iastore
		// @2590: dup
		// @2591: sipush 1222 (0x04C6)
		// @2594: ldc_w 52818 (0xce52)
		// @2597: iastore
		// @2598: dup
		// @2599: sipush 1223 (0x04C7)
		// @259C: ldc_w 52848 (0xce70)
		// @259F: iastore
		// @25A0: dup
		// @25A1: sipush 1224 (0x04C8)
		// @25A4: ldc_w 52878 (0xce8e)
		// @25A7: iastore
		// @25A8: dup
		// @25A9: sipush 1225 (0x04C9)
		// @25AC: ldc_w 52907 (0xceab)
		// @25AF: iastore
		// @25B0: dup
		// @25B1: sipush 1226 (0x04CA)
		// @25B4: ldc_w 52937 (0xcec9)
		// @25B7: iastore
		// @25B8: dup
		// @25B9: sipush 1227 (0x04CB)
		// @25BC: ldc_w 52967 (0xcee7)
		// @25BF: iastore
		// @25C0: dup
		// @25C1: sipush 1228 (0x04CC)
		// @25C4: ldc_w 52996 (0xcf04)
		// @25C7: iastore
		// @25C8: dup
		// @25C9: sipush 1229 (0x04CD)
		// @25CC: ldc_w 53026 (0xcf22)
		// @25CF: iastore
		// @25D0: dup
		// @25D1: sipush 1230 (0x04CE)
		// @25D4: ldc_w 53055 (0xcf3f)
		// @25D7: iastore
		// @25D8: dup
		// @25D9: sipush 1231 (0x04CF)
		// @25DC: ldc_w 53085 (0xcf5d)
		// @25DF: iastore
		// @25E0: dup
		// @25E1: sipush 1232 (0x04D0)
		// @25E4: ldc_w 53114 (0xcf7a)
		// @25E7: iastore
		// @25E8: dup
		// @25E9: sipush 1233 (0x04D1)
		// @25EC: ldc_w 53144 (0xcf98)
		// @25EF: iastore
		// @25F0: dup
		// @25F1: sipush 1234 (0x04D2)
		// @25F4: ldc_w 53173 (0xcfb5)
		// @25F7: iastore
		// @25F8: dup
		// @25F9: sipush 1235 (0x04D3)
		// @25FC: ldc_w 53202 (0xcfd2)
		// @25FF: iastore
		// @2600: dup
		// @2601: sipush 1236 (0x04D4)
		// @2604: ldc_w 53232 (0xcff0)
		// @2607: iastore
		// @2608: dup
		// @2609: sipush 1237 (0x04D5)
		// @260C: ldc_w 53261 (0xd00d)
		// @260F: iastore
		// @2610: dup
		// @2611: sipush 1238 (0x04D6)
		// @2614: ldc_w 53290 (0xd02a)
		// @2617: iastore
		// @2618: dup
		// @2619: sipush 1239 (0x04D7)
		// @261C: ldc_w 53319 (0xd047)
		// @261F: iastore
		// @2620: dup
		// @2621: sipush 1240 (0x04D8)
		// @2624: ldc_w 53349 (0xd065)
		// @2627: iastore
		// @2628: dup
		// @2629: sipush 1241 (0x04D9)
		// @262C: ldc_w 53378 (0xd082)
		// @262F: iastore
		// @2630: dup
		// @2631: sipush 1242 (0x04DA)
		// @2634: ldc_w 53407 (0xd09f)
		// @2637: iastore
		// @2638: dup
		// @2639: sipush 1243 (0x04DB)
		// @263C: ldc_w 53436 (0xd0bc)
		// @263F: iastore
		// @2640: dup
		// @2641: sipush 1244 (0x04DC)
		// @2644: ldc_w 53465 (0xd0d9)
		// @2647: iastore
		// @2648: dup
		// @2649: sipush 1245 (0x04DD)
		// @264C: ldc_w 53494 (0xd0f6)
		// @264F: iastore
		// @2650: dup
		// @2651: sipush 1246 (0x04DE)
		// @2654: ldc_w 53523 (0xd113)
		// @2657: iastore
		// @2658: dup
		// @2659: sipush 1247 (0x04DF)
		// @265C: ldc_w 53552 (0xd130)
		// @265F: iastore
		// @2660: dup
		// @2661: sipush 1248 (0x04E0)
		// @2664: ldc_w 53581 (0xd14d)
		// @2667: iastore
		// @2668: dup
		// @2669: sipush 1249 (0x04E1)
		// @266C: ldc_w 53610 (0xd16a)
		// @266F: iastore
		// @2670: dup
		// @2671: sipush 1250 (0x04E2)
		// @2674: ldc_w 53639 (0xd187)
		// @2677: iastore
		// @2678: dup
		// @2679: sipush 1251 (0x04E3)
		// @267C: ldc_w 53668 (0xd1a4)
		// @267F: iastore
		// @2680: dup
		// @2681: sipush 1252 (0x04E4)
		// @2684: ldc_w 53697 (0xd1c1)
		// @2687: iastore
		// @2688: dup
		// @2689: sipush 1253 (0x04E5)
		// @268C: ldc_w 53726 (0xd1de)
		// @268F: iastore
		// @2690: dup
		// @2691: sipush 1254 (0x04E6)
		// @2694: ldc_w 53754 (0xd1fa)
		// @2697: iastore
		// @2698: dup
		// @2699: sipush 1255 (0x04E7)
		// @269C: ldc_w 53783 (0xd217)
		// @269F: iastore
		// @26A0: dup
		// @26A1: sipush 1256 (0x04E8)
		// @26A4: ldc_w 53812 (0xd234)
		// @26A7: iastore
		// @26A8: dup
		// @26A9: sipush 1257 (0x04E9)
		// @26AC: ldc_w 53840 (0xd250)
		// @26AF: iastore
		// @26B0: dup
		// @26B1: sipush 1258 (0x04EA)
		// @26B4: ldc_w 53869 (0xd26d)
		// @26B7: iastore
		// @26B8: dup
		// @26B9: sipush 1259 (0x04EB)
		// @26BC: ldc_w 53898 (0xd28a)
		// @26BF: iastore
		// @26C0: dup
		// @26C1: sipush 1260 (0x04EC)
		// @26C4: ldc_w 53926 (0xd2a6)
		// @26C7: iastore
		// @26C8: dup
		// @26C9: sipush 1261 (0x04ED)
		// @26CC: ldc_w 53955 (0xd2c3)
		// @26CF: iastore
		// @26D0: dup
		// @26D1: sipush 1262 (0x04EE)
		// @26D4: ldc_w 53983 (0xd2df)
		// @26D7: iastore
		// @26D8: dup
		// @26D9: sipush 1263 (0x04EF)
		// @26DC: ldc_w 54012 (0xd2fc)
		// @26DF: iastore
		// @26E0: dup
		// @26E1: sipush 1264 (0x04F0)
		// @26E4: ldc_w 54040 (0xd318)
		// @26E7: iastore
		// @26E8: dup
		// @26E9: sipush 1265 (0x04F1)
		// @26EC: ldc_w 54069 (0xd335)
		// @26EF: iastore
		// @26F0: dup
		// @26F1: sipush 1266 (0x04F2)
		// @26F4: ldc_w 54097 (0xd351)
		// @26F7: iastore
		// @26F8: dup
		// @26F9: sipush 1267 (0x04F3)
		// @26FC: ldc_w 54125 (0xd36d)
		// @26FF: iastore
		// @2700: dup
		// @2701: sipush 1268 (0x04F4)
		// @2704: ldc_w 54154 (0xd38a)
		// @2707: iastore
		// @2708: dup
		// @2709: sipush 1269 (0x04F5)
		// @270C: ldc_w 54182 (0xd3a6)
		// @270F: iastore
		// @2710: dup
		// @2711: sipush 1270 (0x04F6)
		// @2714: ldc_w 54210 (0xd3c2)
		// @2717: iastore
		// @2718: dup
		// @2719: sipush 1271 (0x04F7)
		// @271C: ldc_w 54239 (0xd3df)
		// @271F: iastore
		// @2720: dup
		// @2721: sipush 1272 (0x04F8)
		// @2724: ldc_w 54267 (0xd3fb)
		// @2727: iastore
		// @2728: dup
		// @2729: sipush 1273 (0x04F9)
		// @272C: ldc_w 54295 (0xd417)
		// @272F: iastore
		// @2730: dup
		// @2731: sipush 1274 (0x04FA)
		// @2734: ldc_w 54323 (0xd433)
		// @2737: iastore
		// @2738: dup
		// @2739: sipush 1275 (0x04FB)
		// @273C: ldc_w 54351 (0xd44f)
		// @273F: iastore
		// @2740: dup
		// @2741: sipush 1276 (0x04FC)
		// @2744: ldc_w 54379 (0xd46b)
		// @2747: iastore
		// @2748: dup
		// @2749: sipush 1277 (0x04FD)
		// @274C: ldc_w 54407 (0xd487)
		// @274F: iastore
		// @2750: dup
		// @2751: sipush 1278 (0x04FE)
		// @2754: ldc_w 54435 (0xd4a3)
		// @2757: iastore
		// @2758: dup
		// @2759: sipush 1279 (0x04FF)
		// @275C: ldc_w 54463 (0xd4bf)
		// @275F: iastore
		// @2760: dup
		// @2761: sipush 1280 (0x0500)
		// @2764: ldc_w 54491 (0xd4db)
		// @2767: iastore
		// @2768: dup
		// @2769: sipush 1281 (0x0501)
		// @276C: ldc_w 54519 (0xd4f7)
		// @276F: iastore
		// @2770: dup
		// @2771: sipush 1282 (0x0502)
		// @2774: ldc_w 54547 (0xd513)
		// @2777: iastore
		// @2778: dup
		// @2779: sipush 1283 (0x0503)
		// @277C: ldc_w 54575 (0xd52f)
		// @277F: iastore
		// @2780: dup
		// @2781: sipush 1284 (0x0504)
		// @2784: ldc_w 54603 (0xd54b)
		// @2787: iastore
		// @2788: dup
		// @2789: sipush 1285 (0x0505)
		// @278C: ldc_w 54630 (0xd566)
		// @278F: iastore
		// @2790: dup
		// @2791: sipush 1286 (0x0506)
		// @2794: ldc_w 54658 (0xd582)
		// @2797: iastore
		// @2798: dup
		// @2799: sipush 1287 (0x0507)
		// @279C: ldc_w 54686 (0xd59e)
		// @279F: iastore
		// @27A0: dup
		// @27A1: sipush 1288 (0x0508)
		// @27A4: ldc_w 54714 (0xd5ba)
		// @27A7: iastore
		// @27A8: dup
		// @27A9: sipush 1289 (0x0509)
		// @27AC: ldc_w 54741 (0xd5d5)
		// @27AF: iastore
		// @27B0: dup
		// @27B1: sipush 1290 (0x050A)
		// @27B4: ldc_w 54769 (0xd5f1)
		// @27B7: iastore
		// @27B8: dup
		// @27B9: sipush 1291 (0x050B)
		// @27BC: ldc_w 54796 (0xd60c)
		// @27BF: iastore
		// @27C0: dup
		// @27C1: sipush 1292 (0x050C)
		// @27C4: ldc_w 54824 (0xd628)
		// @27C7: iastore
		// @27C8: dup
		// @27C9: sipush 1293 (0x050D)
		// @27CC: ldc_w 54852 (0xd644)
		// @27CF: iastore
		// @27D0: dup
		// @27D1: sipush 1294 (0x050E)
		// @27D4: ldc_w 54879 (0xd65f)
		// @27D7: iastore
		// @27D8: dup
		// @27D9: sipush 1295 (0x050F)
		// @27DC: ldc_w 54906 (0xd67a)
		// @27DF: iastore
		// @27E0: dup
		// @27E1: sipush 1296 (0x0510)
		// @27E4: ldc_w 54934 (0xd696)
		// @27E7: iastore
		// @27E8: dup
		// @27E9: sipush 1297 (0x0511)
		// @27EC: ldc_w 54961 (0xd6b1)
		// @27EF: iastore
		// @27F0: dup
		// @27F1: sipush 1298 (0x0512)
		// @27F4: ldc_w 54989 (0xd6cd)
		// @27F7: iastore
		// @27F8: dup
		// @27F9: sipush 1299 (0x0513)
		// @27FC: ldc_w 55016 (0xd6e8)
		// @27FF: iastore
		// @2800: dup
		// @2801: sipush 1300 (0x0514)
		// @2804: ldc_w 55043 (0xd703)
		// @2807: iastore
		// @2808: dup
		// @2809: sipush 1301 (0x0515)
		// @280C: ldc_w 55071 (0xd71f)
		// @280F: iastore
		// @2810: dup
		// @2811: sipush 1302 (0x0516)
		// @2814: ldc_w 55098 (0xd73a)
		// @2817: iastore
		// @2818: dup
		// @2819: sipush 1303 (0x0517)
		// @281C: ldc_w 55125 (0xd755)
		// @281F: iastore
		// @2820: dup
		// @2821: sipush 1304 (0x0518)
		// @2824: ldc_w 55152 (0xd770)
		// @2827: iastore
		// @2828: dup
		// @2829: sipush 1305 (0x0519)
		// @282C: ldc_w 55179 (0xd78b)
		// @282F: iastore
		// @2830: dup
		// @2831: sipush 1306 (0x051A)
		// @2834: ldc_w 55206 (0xd7a6)
		// @2837: iastore
		// @2838: dup
		// @2839: sipush 1307 (0x051B)
		// @283C: ldc_w 55233 (0xd7c1)
		// @283F: iastore
		// @2840: dup
		// @2841: sipush 1308 (0x051C)
		// @2844: ldc_w 55260 (0xd7dc)
		// @2847: iastore
		// @2848: dup
		// @2849: sipush 1309 (0x051D)
		// @284C: ldc_w 55288 (0xd7f8)
		// @284F: iastore
		// @2850: dup
		// @2851: sipush 1310 (0x051E)
		// @2854: ldc_w 55314 (0xd812)
		// @2857: iastore
		// @2858: dup
		// @2859: sipush 1311 (0x051F)
		// @285C: ldc_w 55341 (0xd82d)
		// @285F: iastore
		// @2860: dup
		// @2861: sipush 1312 (0x0520)
		// @2864: ldc_w 55368 (0xd848)
		// @2867: iastore
		// @2868: dup
		// @2869: sipush 1313 (0x0521)
		// @286C: ldc_w 55395 (0xd863)
		// @286F: iastore
		// @2870: dup
		// @2871: sipush 1314 (0x0522)
		// @2874: ldc_w 55422 (0xd87e)
		// @2877: iastore
		// @2878: dup
		// @2879: sipush 1315 (0x0523)
		// @287C: ldc_w 55449 (0xd899)
		// @287F: iastore
		// @2880: dup
		// @2881: sipush 1316 (0x0524)
		// @2884: ldc_w 55476 (0xd8b4)
		// @2887: iastore
		// @2888: dup
		// @2889: sipush 1317 (0x0525)
		// @288C: ldc_w 55502 (0xd8ce)
		// @288F: iastore
		// @2890: dup
		// @2891: sipush 1318 (0x0526)
		// @2894: ldc_w 55529 (0xd8e9)
		// @2897: iastore
		// @2898: dup
		// @2899: sipush 1319 (0x0527)
		// @289C: ldc_w 55556 (0xd904)
		// @289F: iastore
		// @28A0: dup
		// @28A1: sipush 1320 (0x0528)
		// @28A4: ldc_w 55582 (0xd91e)
		// @28A7: iastore
		// @28A8: dup
		// @28A9: sipush 1321 (0x0529)
		// @28AC: ldc_w 55609 (0xd939)
		// @28AF: iastore
		// @28B0: dup
		// @28B1: sipush 1322 (0x052A)
		// @28B4: ldc_w 55636 (0xd954)
		// @28B7: iastore
		// @28B8: dup
		// @28B9: sipush 1323 (0x052B)
		// @28BC: ldc_w 55662 (0xd96e)
		// @28BF: iastore
		// @28C0: dup
		// @28C1: sipush 1324 (0x052C)
		// @28C4: ldc_w 55689 (0xd989)
		// @28C7: iastore
		// @28C8: dup
		// @28C9: sipush 1325 (0x052D)
		// @28CC: ldc_w 55715 (0xd9a3)
		// @28CF: iastore
		// @28D0: dup
		// @28D1: sipush 1326 (0x052E)
		// @28D4: ldc_w 55742 (0xd9be)
		// @28D7: iastore
		// @28D8: dup
		// @28D9: sipush 1327 (0x052F)
		// @28DC: ldc_w 55768 (0xd9d8)
		// @28DF: iastore
		// @28E0: dup
		// @28E1: sipush 1328 (0x0530)
		// @28E4: ldc_w 55794 (0xd9f2)
		// @28E7: iastore
		// @28E8: dup
		// @28E9: sipush 1329 (0x0531)
		// @28EC: ldc_w 55821 (0xda0d)
		// @28EF: iastore
		// @28F0: dup
		// @28F1: sipush 1330 (0x0532)
		// @28F4: ldc_w 55847 (0xda27)
		// @28F7: iastore
		// @28F8: dup
		// @28F9: sipush 1331 (0x0533)
		// @28FC: ldc_w 55873 (0xda41)
		// @28FF: iastore
		// @2900: dup
		// @2901: sipush 1332 (0x0534)
		// @2904: ldc_w 55900 (0xda5c)
		// @2907: iastore
		// @2908: dup
		// @2909: sipush 1333 (0x0535)
		// @290C: ldc_w 55926 (0xda76)
		// @290F: iastore
		// @2910: dup
		// @2911: sipush 1334 (0x0536)
		// @2914: ldc_w 55952 (0xda90)
		// @2917: iastore
		// @2918: dup
		// @2919: sipush 1335 (0x0537)
		// @291C: ldc_w 55978 (0xdaaa)
		// @291F: iastore
		// @2920: dup
		// @2921: sipush 1336 (0x0538)
		// @2924: ldc_w 56004 (0xdac4)
		// @2927: iastore
		// @2928: dup
		// @2929: sipush 1337 (0x0539)
		// @292C: ldc_w 56030 (0xdade)
		// @292F: iastore
		// @2930: dup
		// @2931: sipush 1338 (0x053A)
		// @2934: ldc_w 56056 (0xdaf8)
		// @2937: iastore
		// @2938: dup
		// @2939: sipush 1339 (0x053B)
		// @293C: ldc_w 56082 (0xdb12)
		// @293F: iastore
		// @2940: dup
		// @2941: sipush 1340 (0x053C)
		// @2944: ldc_w 56108 (0xdb2c)
		// @2947: iastore
		// @2948: dup
		// @2949: sipush 1341 (0x053D)
		// @294C: ldc_w 56134 (0xdb46)
		// @294F: iastore
		// @2950: dup
		// @2951: sipush 1342 (0x053E)
		// @2954: ldc_w 56160 (0xdb60)
		// @2957: iastore
		// @2958: dup
		// @2959: sipush 1343 (0x053F)
		// @295C: ldc_w 56186 (0xdb7a)
		// @295F: iastore
		// @2960: dup
		// @2961: sipush 1344 (0x0540)
		// @2964: ldc_w 56212 (0xdb94)
		// @2967: iastore
		// @2968: dup
		// @2969: sipush 1345 (0x0541)
		// @296C: ldc_w 56238 (0xdbae)
		// @296F: iastore
		// @2970: dup
		// @2971: sipush 1346 (0x0542)
		// @2974: ldc_w 56264 (0xdbc8)
		// @2977: iastore
		// @2978: dup
		// @2979: sipush 1347 (0x0543)
		// @297C: ldc_w 56289 (0xdbe1)
		// @297F: iastore
		// @2980: dup
		// @2981: sipush 1348 (0x0544)
		// @2984: ldc_w 56315 (0xdbfb)
		// @2987: iastore
		// @2988: dup
		// @2989: sipush 1349 (0x0545)
		// @298C: ldc_w 56341 (0xdc15)
		// @298F: iastore
		// @2990: dup
		// @2991: sipush 1350 (0x0546)
		// @2994: ldc_w 56367 (0xdc2f)
		// @2997: iastore
		// @2998: dup
		// @2999: sipush 1351 (0x0547)
		// @299C: ldc_w 56392 (0xdc48)
		// @299F: iastore
		// @29A0: dup
		// @29A1: sipush 1352 (0x0548)
		// @29A4: ldc_w 56418 (0xdc62)
		// @29A7: iastore
		// @29A8: dup
		// @29A9: sipush 1353 (0x0549)
		// @29AC: ldc_w 56443 (0xdc7b)
		// @29AF: iastore
		// @29B0: dup
		// @29B1: sipush 1354 (0x054A)
		// @29B4: ldc_w 56469 (0xdc95)
		// @29B7: iastore
		// @29B8: dup
		// @29B9: sipush 1355 (0x054B)
		// @29BC: ldc_w 56494 (0xdcae)
		// @29BF: iastore
		// @29C0: dup
		// @29C1: sipush 1356 (0x054C)
		// @29C4: ldc_w 56520 (0xdcc8)
		// @29C7: iastore
		// @29C8: dup
		// @29C9: sipush 1357 (0x054D)
		// @29CC: ldc_w 56545 (0xdce1)
		// @29CF: iastore
		// @29D0: dup
		// @29D1: sipush 1358 (0x054E)
		// @29D4: ldc_w 56571 (0xdcfb)
		// @29D7: iastore
		// @29D8: dup
		// @29D9: sipush 1359 (0x054F)
		// @29DC: ldc_w 56596 (0xdd14)
		// @29DF: iastore
		// @29E0: dup
		// @29E1: sipush 1360 (0x0550)
		// @29E4: ldc_w 56621 (0xdd2d)
		// @29E7: iastore
		// @29E8: dup
		// @29E9: sipush 1361 (0x0551)
		// @29EC: ldc_w 56647 (0xdd47)
		// @29EF: iastore
		// @29F0: dup
		// @29F1: sipush 1362 (0x0552)
		// @29F4: ldc_w 56672 (0xdd60)
		// @29F7: iastore
		// @29F8: dup
		// @29F9: sipush 1363 (0x0553)
		// @29FC: ldc_w 56697 (0xdd79)
		// @29FF: iastore
		// @2A00: dup
		// @2A01: sipush 1364 (0x0554)
		// @2A04: ldc_w 56722 (0xdd92)
		// @2A07: iastore
		// @2A08: dup
		// @2A09: sipush 1365 (0x0555)
		// @2A0C: ldc_w 56747 (0xddab)
		// @2A0F: iastore
		// @2A10: dup
		// @2A11: sipush 1366 (0x0556)
		// @2A14: ldc_w 56773 (0xddc5)
		// @2A17: iastore
		// @2A18: dup
		// @2A19: sipush 1367 (0x0557)
		// @2A1C: ldc_w 56798 (0xddde)
		// @2A1F: iastore
		// @2A20: dup
		// @2A21: sipush 1368 (0x0558)
		// @2A24: ldc_w 56823 (0xddf7)
		// @2A27: iastore
		// @2A28: dup
		// @2A29: sipush 1369 (0x0559)
		// @2A2C: ldc_w 56848 (0xde10)
		// @2A2F: iastore
		// @2A30: dup
		// @2A31: sipush 1370 (0x055A)
		// @2A34: ldc_w 56873 (0xde29)
		// @2A37: iastore
		// @2A38: dup
		// @2A39: sipush 1371 (0x055B)
		// @2A3C: ldc_w 56898 (0xde42)
		// @2A3F: iastore
		// @2A40: dup
		// @2A41: sipush 1372 (0x055C)
		// @2A44: ldc_w 56923 (0xde5b)
		// @2A47: iastore
		// @2A48: dup
		// @2A49: sipush 1373 (0x055D)
		// @2A4C: ldc_w 56948 (0xde74)
		// @2A4F: iastore
		// @2A50: dup
		// @2A51: sipush 1374 (0x055E)
		// @2A54: ldc_w 56972 (0xde8c)
		// @2A57: iastore
		// @2A58: dup
		// @2A59: sipush 1375 (0x055F)
		// @2A5C: ldc_w 56997 (0xdea5)
		// @2A5F: iastore
		// @2A60: dup
		// @2A61: sipush 1376 (0x0560)
		// @2A64: ldc_w 57022 (0xdebe)
		// @2A67: iastore
		// @2A68: dup
		// @2A69: sipush 1377 (0x0561)
		// @2A6C: ldc_w 57047 (0xded7)
		// @2A6F: iastore
		// @2A70: dup
		// @2A71: sipush 1378 (0x0562)
		// @2A74: ldc_w 57072 (0xdef0)
		// @2A77: iastore
		// @2A78: dup
		// @2A79: sipush 1379 (0x0563)
		// @2A7C: ldc_w 57096 (0xdf08)
		// @2A7F: iastore
		// @2A80: dup
		// @2A81: sipush 1380 (0x0564)
		// @2A84: ldc_w 57121 (0xdf21)
		// @2A87: iastore
		// @2A88: dup
		// @2A89: sipush 1381 (0x0565)
		// @2A8C: ldc_w 57145 (0xdf39)
		// @2A8F: iastore
		// @2A90: dup
		// @2A91: sipush 1382 (0x0566)
		// @2A94: ldc_w 57170 (0xdf52)
		// @2A97: iastore
		// @2A98: dup
		// @2A99: sipush 1383 (0x0567)
		// @2A9C: ldc_w 57195 (0xdf6b)
		// @2A9F: iastore
		// @2AA0: dup
		// @2AA1: sipush 1384 (0x0568)
		// @2AA4: ldc_w 57219 (0xdf83)
		// @2AA7: iastore
		// @2AA8: dup
		// @2AA9: sipush 1385 (0x0569)
		// @2AAC: ldc_w 57244 (0xdf9c)
		// @2AAF: iastore
		// @2AB0: dup
		// @2AB1: sipush 1386 (0x056A)
		// @2AB4: ldc_w 57268 (0xdfb4)
		// @2AB7: iastore
		// @2AB8: dup
		// @2AB9: sipush 1387 (0x056B)
		// @2ABC: ldc_w 57293 (0xdfcd)
		// @2ABF: iastore
		// @2AC0: dup
		// @2AC1: sipush 1388 (0x056C)
		// @2AC4: ldc_w 57317 (0xdfe5)
		// @2AC7: iastore
		// @2AC8: dup
		// @2AC9: sipush 1389 (0x056D)
		// @2ACC: ldc_w 57341 (0xdffd)
		// @2ACF: iastore
		// @2AD0: dup
		// @2AD1: sipush 1390 (0x056E)
		// @2AD4: ldc_w 57366 (0xe016)
		// @2AD7: iastore
		// @2AD8: dup
		// @2AD9: sipush 1391 (0x056F)
		// @2ADC: ldc_w 57390 (0xe02e)
		// @2ADF: iastore
		// @2AE0: dup
		// @2AE1: sipush 1392 (0x0570)
		// @2AE4: ldc_w 57414 (0xe046)
		// @2AE7: iastore
		// @2AE8: dup
		// @2AE9: sipush 1393 (0x0571)
		// @2AEC: ldc_w 57438 (0xe05e)
		// @2AEF: iastore
		// @2AF0: dup
		// @2AF1: sipush 1394 (0x0572)
		// @2AF4: ldc_w 57463 (0xe077)
		// @2AF7: iastore
		// @2AF8: dup
		// @2AF9: sipush 1395 (0x0573)
		// @2AFC: ldc_w 57487 (0xe08f)
		// @2AFF: iastore
		// @2B00: dup
		// @2B01: sipush 1396 (0x0574)
		// @2B04: ldc_w 57511 (0xe0a7)
		// @2B07: iastore
		// @2B08: dup
		// @2B09: sipush 1397 (0x0575)
		// @2B0C: ldc_w 57535 (0xe0bf)
		// @2B0F: iastore
		// @2B10: dup
		// @2B11: sipush 1398 (0x0576)
		// @2B14: ldc_w 57559 (0xe0d7)
		// @2B17: iastore
		// @2B18: dup
		// @2B19: sipush 1399 (0x0577)
		// @2B1C: ldc_w 57583 (0xe0ef)
		// @2B1F: iastore
		// @2B20: dup
		// @2B21: sipush 1400 (0x0578)
		// @2B24: ldc_w 57607 (0xe107)
		// @2B27: iastore
		// @2B28: dup
		// @2B29: sipush 1401 (0x0579)
		// @2B2C: ldc_w 57631 (0xe11f)
		// @2B2F: iastore
		// @2B30: dup
		// @2B31: sipush 1402 (0x057A)
		// @2B34: ldc_w 57655 (0xe137)
		// @2B37: iastore
		// @2B38: dup
		// @2B39: sipush 1403 (0x057B)
		// @2B3C: ldc_w 57679 (0xe14f)
		// @2B3F: iastore
		// @2B40: dup
		// @2B41: sipush 1404 (0x057C)
		// @2B44: ldc_w 57703 (0xe167)
		// @2B47: iastore
		// @2B48: dup
		// @2B49: sipush 1405 (0x057D)
		// @2B4C: ldc_w 57726 (0xe17e)
		// @2B4F: iastore
		// @2B50: dup
		// @2B51: sipush 1406 (0x057E)
		// @2B54: ldc_w 57750 (0xe196)
		// @2B57: iastore
		// @2B58: dup
		// @2B59: sipush 1407 (0x057F)
		// @2B5C: ldc_w 57774 (0xe1ae)
		// @2B5F: iastore
		// @2B60: dup
		// @2B61: sipush 1408 (0x0580)
		// @2B64: ldc_w 57798 (0xe1c6)
		// @2B67: iastore
		// @2B68: dup
		// @2B69: sipush 1409 (0x0581)
		// @2B6C: ldc_w 57821 (0xe1dd)
		// @2B6F: iastore
		// @2B70: dup
		// @2B71: sipush 1410 (0x0582)
		// @2B74: ldc_w 57845 (0xe1f5)
		// @2B77: iastore
		// @2B78: dup
		// @2B79: sipush 1411 (0x0583)
		// @2B7C: ldc_w 57869 (0xe20d)
		// @2B7F: iastore
		// @2B80: dup
		// @2B81: sipush 1412 (0x0584)
		// @2B84: ldc_w 57892 (0xe224)
		// @2B87: iastore
		// @2B88: dup
		// @2B89: sipush 1413 (0x0585)
		// @2B8C: ldc_w 57916 (0xe23c)
		// @2B8F: iastore
		// @2B90: dup
		// @2B91: sipush 1414 (0x0586)
		// @2B94: ldc_w 57939 (0xe253)
		// @2B97: iastore
		// @2B98: dup
		// @2B99: sipush 1415 (0x0587)
		// @2B9C: ldc_w 57963 (0xe26b)
		// @2B9F: iastore
		// @2BA0: dup
		// @2BA1: sipush 1416 (0x0588)
		// @2BA4: ldc_w 57986 (0xe282)
		// @2BA7: iastore
		// @2BA8: dup
		// @2BA9: sipush 1417 (0x0589)
		// @2BAC: ldc_w 58009 (0xe299)
		// @2BAF: iastore
		// @2BB0: dup
		// @2BB1: sipush 1418 (0x058A)
		// @2BB4: ldc_w 58033 (0xe2b1)
		// @2BB7: iastore
		// @2BB8: dup
		// @2BB9: sipush 1419 (0x058B)
		// @2BBC: ldc_w 58056 (0xe2c8)
		// @2BBF: iastore
		// @2BC0: dup
		// @2BC1: sipush 1420 (0x058C)
		// @2BC4: ldc_w 58079 (0xe2df)
		// @2BC7: iastore
		// @2BC8: dup
		// @2BC9: sipush 1421 (0x058D)
		// @2BCC: ldc_w 58103 (0xe2f7)
		// @2BCF: iastore
		// @2BD0: dup
		// @2BD1: sipush 1422 (0x058E)
		// @2BD4: ldc_w 58126 (0xe30e)
		// @2BD7: iastore
		// @2BD8: dup
		// @2BD9: sipush 1423 (0x058F)
		// @2BDC: ldc_w 58149 (0xe325)
		// @2BDF: iastore
		// @2BE0: dup
		// @2BE1: sipush 1424 (0x0590)
		// @2BE4: ldc_w 58172 (0xe33c)
		// @2BE7: iastore
		// @2BE8: dup
		// @2BE9: sipush 1425 (0x0591)
		// @2BEC: ldc_w 58195 (0xe353)
		// @2BEF: iastore
		// @2BF0: dup
		// @2BF1: sipush 1426 (0x0592)
		// @2BF4: ldc_w 58219 (0xe36b)
		// @2BF7: iastore
		// @2BF8: dup
		// @2BF9: sipush 1427 (0x0593)
		// @2BFC: ldc_w 58242 (0xe382)
		// @2BFF: iastore
		// @2C00: dup
		// @2C01: sipush 1428 (0x0594)
		// @2C04: ldc_w 58265 (0xe399)
		// @2C07: iastore
		// @2C08: dup
		// @2C09: sipush 1429 (0x0595)
		// @2C0C: ldc_w 58288 (0xe3b0)
		// @2C0F: iastore
		// @2C10: dup
		// @2C11: sipush 1430 (0x0596)
		// @2C14: ldc_w 58311 (0xe3c7)
		// @2C17: iastore
		// @2C18: dup
		// @2C19: sipush 1431 (0x0597)
		// @2C1C: ldc_w 58334 (0xe3de)
		// @2C1F: iastore
		// @2C20: dup
		// @2C21: sipush 1432 (0x0598)
		// @2C24: ldc_w 58356 (0xe3f4)
		// @2C27: iastore
		// @2C28: dup
		// @2C29: sipush 1433 (0x0599)
		// @2C2C: ldc_w 58379 (0xe40b)
		// @2C2F: iastore
		// @2C30: dup
		// @2C31: sipush 1434 (0x059A)
		// @2C34: ldc_w 58402 (0xe422)
		// @2C37: iastore
		// @2C38: dup
		// @2C39: sipush 1435 (0x059B)
		// @2C3C: ldc_w 58425 (0xe439)
		// @2C3F: iastore
		// @2C40: dup
		// @2C41: sipush 1436 (0x059C)
		// @2C44: ldc_w 58448 (0xe450)
		// @2C47: iastore
		// @2C48: dup
		// @2C49: sipush 1437 (0x059D)
		// @2C4C: ldc_w 58470 (0xe466)
		// @2C4F: iastore
		// @2C50: dup
		// @2C51: sipush 1438 (0x059E)
		// @2C54: ldc_w 58493 (0xe47d)
		// @2C57: iastore
		// @2C58: dup
		// @2C59: sipush 1439 (0x059F)
		// @2C5C: ldc_w 58516 (0xe494)
		// @2C5F: iastore
		// @2C60: dup
		// @2C61: sipush 1440 (0x05A0)
		// @2C64: ldc_w 58538 (0xe4aa)
		// @2C67: iastore
		// @2C68: dup
		// @2C69: sipush 1441 (0x05A1)
		// @2C6C: ldc_w 58561 (0xe4c1)
		// @2C6F: iastore
		// @2C70: dup
		// @2C71: sipush 1442 (0x05A2)
		// @2C74: ldc_w 58583 (0xe4d7)
		// @2C77: iastore
		// @2C78: dup
		// @2C79: sipush 1443 (0x05A3)
		// @2C7C: ldc_w 58606 (0xe4ee)
		// @2C7F: iastore
		// @2C80: dup
		// @2C81: sipush 1444 (0x05A4)
		// @2C84: ldc_w 58628 (0xe504)
		// @2C87: iastore
		// @2C88: dup
		// @2C89: sipush 1445 (0x05A5)
		// @2C8C: ldc_w 58651 (0xe51b)
		// @2C8F: iastore
		// @2C90: dup
		// @2C91: sipush 1446 (0x05A6)
		// @2C94: ldc_w 58673 (0xe531)
		// @2C97: iastore
		// @2C98: dup
		// @2C99: sipush 1447 (0x05A7)
		// @2C9C: ldc_w 58696 (0xe548)
		// @2C9F: iastore
		// @2CA0: dup
		// @2CA1: sipush 1448 (0x05A8)
		// @2CA4: ldc_w 58718 (0xe55e)
		// @2CA7: iastore
		// @2CA8: dup
		// @2CA9: sipush 1449 (0x05A9)
		// @2CAC: ldc_w 58740 (0xe574)
		// @2CAF: iastore
		// @2CB0: dup
		// @2CB1: sipush 1450 (0x05AA)
		// @2CB4: ldc_w 58763 (0xe58b)
		// @2CB7: iastore
		// @2CB8: dup
		// @2CB9: sipush 1451 (0x05AB)
		// @2CBC: ldc_w 58785 (0xe5a1)
		// @2CBF: iastore
		// @2CC0: dup
		// @2CC1: sipush 1452 (0x05AC)
		// @2CC4: ldc_w 58807 (0xe5b7)
		// @2CC7: iastore
		// @2CC8: dup
		// @2CC9: sipush 1453 (0x05AD)
		// @2CCC: ldc_w 58829 (0xe5cd)
		// @2CCF: iastore
		// @2CD0: dup
		// @2CD1: sipush 1454 (0x05AE)
		// @2CD4: ldc_w 58851 (0xe5e3)
		// @2CD7: iastore
		// @2CD8: dup
		// @2CD9: sipush 1455 (0x05AF)
		// @2CDC: ldc_w 58873 (0xe5f9)
		// @2CDF: iastore
		// @2CE0: dup
		// @2CE1: sipush 1456 (0x05B0)
		// @2CE4: ldc_w 58896 (0xe610)
		// @2CE7: iastore
		// @2CE8: dup
		// @2CE9: sipush 1457 (0x05B1)
		// @2CEC: ldc_w 58918 (0xe626)
		// @2CEF: iastore
		// @2CF0: dup
		// @2CF1: sipush 1458 (0x05B2)
		// @2CF4: ldc_w 58940 (0xe63c)
		// @2CF7: iastore
		// @2CF8: dup
		// @2CF9: sipush 1459 (0x05B3)
		// @2CFC: ldc_w 58962 (0xe652)
		// @2CFF: iastore
		// @2D00: dup
		// @2D01: sipush 1460 (0x05B4)
		// @2D04: ldc_w 58983 (0xe667)
		// @2D07: iastore
		// @2D08: dup
		// @2D09: sipush 1461 (0x05B5)
		// @2D0C: ldc_w 59005 (0xe67d)
		// @2D0F: iastore
		// @2D10: dup
		// @2D11: sipush 1462 (0x05B6)
		// @2D14: ldc_w 59027 (0xe693)
		// @2D17: iastore
		// @2D18: dup
		// @2D19: sipush 1463 (0x05B7)
		// @2D1C: ldc_w 59049 (0xe6a9)
		// @2D1F: iastore
		// @2D20: dup
		// @2D21: sipush 1464 (0x05B8)
		// @2D24: ldc_w 59071 (0xe6bf)
		// @2D27: iastore
		// @2D28: dup
		// @2D29: sipush 1465 (0x05B9)
		// @2D2C: ldc_w 59093 (0xe6d5)
		// @2D2F: iastore
		// @2D30: dup
		// @2D31: sipush 1466 (0x05BA)
		// @2D34: ldc_w 59114 (0xe6ea)
		// @2D37: iastore
		// @2D38: dup
		// @2D39: sipush 1467 (0x05BB)
		// @2D3C: ldc_w 59136 (0xe700)
		// @2D3F: iastore
		// @2D40: dup
		// @2D41: sipush 1468 (0x05BC)
		// @2D44: ldc_w 59158 (0xe716)
		// @2D47: iastore
		// @2D48: dup
		// @2D49: sipush 1469 (0x05BD)
		// @2D4C: ldc_w 59179 (0xe72b)
		// @2D4F: iastore
		// @2D50: dup
		// @2D51: sipush 1470 (0x05BE)
		// @2D54: ldc_w 59201 (0xe741)
		// @2D57: iastore
		// @2D58: dup
		// @2D59: sipush 1471 (0x05BF)
		// @2D5C: ldc_w 59222 (0xe756)
		// @2D5F: iastore
		// @2D60: dup
		// @2D61: sipush 1472 (0x05C0)
		// @2D64: ldc_w 59244 (0xe76c)
		// @2D67: iastore
		// @2D68: dup
		// @2D69: sipush 1473 (0x05C1)
		// @2D6C: ldc_w 59265 (0xe781)
		// @2D6F: iastore
		// @2D70: dup
		// @2D71: sipush 1474 (0x05C2)
		// @2D74: ldc_w 59287 (0xe797)
		// @2D77: iastore
		// @2D78: dup
		// @2D79: sipush 1475 (0x05C3)
		// @2D7C: ldc_w 59308 (0xe7ac)
		// @2D7F: iastore
		// @2D80: dup
		// @2D81: sipush 1476 (0x05C4)
		// @2D84: ldc_w 59330 (0xe7c2)
		// @2D87: iastore
		// @2D88: dup
		// @2D89: sipush 1477 (0x05C5)
		// @2D8C: ldc_w 59351 (0xe7d7)
		// @2D8F: iastore
		// @2D90: dup
		// @2D91: sipush 1478 (0x05C6)
		// @2D94: ldc_w 59372 (0xe7ec)
		// @2D97: iastore
		// @2D98: dup
		// @2D99: sipush 1479 (0x05C7)
		// @2D9C: ldc_w 59393 (0xe801)
		// @2D9F: iastore
		// @2DA0: dup
		// @2DA1: sipush 1480 (0x05C8)
		// @2DA4: ldc_w 59415 (0xe817)
		// @2DA7: iastore
		// @2DA8: dup
		// @2DA9: sipush 1481 (0x05C9)
		// @2DAC: ldc_w 59436 (0xe82c)
		// @2DAF: iastore
		// @2DB0: dup
		// @2DB1: sipush 1482 (0x05CA)
		// @2DB4: ldc_w 59457 (0xe841)
		// @2DB7: iastore
		// @2DB8: dup
		// @2DB9: sipush 1483 (0x05CB)
		// @2DBC: ldc_w 59478 (0xe856)
		// @2DBF: iastore
		// @2DC0: dup
		// @2DC1: sipush 1484 (0x05CC)
		// @2DC4: ldc_w 59499 (0xe86b)
		// @2DC7: iastore
		// @2DC8: dup
		// @2DC9: sipush 1485 (0x05CD)
		// @2DCC: ldc_w 59520 (0xe880)
		// @2DCF: iastore
		// @2DD0: dup
		// @2DD1: sipush 1486 (0x05CE)
		// @2DD4: ldc_w 59541 (0xe895)
		// @2DD7: iastore
		// @2DD8: dup
		// @2DD9: sipush 1487 (0x05CF)
		// @2DDC: ldc_w 59562 (0xe8aa)
		// @2DDF: iastore
		// @2DE0: dup
		// @2DE1: sipush 1488 (0x05D0)
		// @2DE4: ldc_w 59583 (0xe8bf)
		// @2DE7: iastore
		// @2DE8: dup
		// @2DE9: sipush 1489 (0x05D1)
		// @2DEC: ldc_w 59604 (0xe8d4)
		// @2DEF: iastore
		// @2DF0: dup
		// @2DF1: sipush 1490 (0x05D2)
		// @2DF4: ldc_w 59625 (0xe8e9)
		// @2DF7: iastore
		// @2DF8: dup
		// @2DF9: sipush 1491 (0x05D3)
		// @2DFC: ldc_w 59646 (0xe8fe)
		// @2DFF: iastore
		// @2E00: dup
		// @2E01: sipush 1492 (0x05D4)
		// @2E04: ldc_w 59667 (0xe913)
		// @2E07: iastore
		// @2E08: dup
		// @2E09: sipush 1493 (0x05D5)
		// @2E0C: ldc_w 59687 (0xe927)
		// @2E0F: iastore
		// @2E10: dup
		// @2E11: sipush 1494 (0x05D6)
		// @2E14: ldc_w 59708 (0xe93c)
		// @2E17: iastore
		// @2E18: dup
		// @2E19: sipush 1495 (0x05D7)
		// @2E1C: ldc_w 59729 (0xe951)
		// @2E1F: iastore
		// @2E20: dup
		// @2E21: sipush 1496 (0x05D8)
		// @2E24: ldc_w 59750 (0xe966)
		// @2E27: iastore
		// @2E28: dup
		// @2E29: sipush 1497 (0x05D9)
		// @2E2C: ldc_w 59770 (0xe97a)
		// @2E2F: iastore
		// @2E30: dup
		// @2E31: sipush 1498 (0x05DA)
		// @2E34: ldc_w 59791 (0xe98f)
		// @2E37: iastore
		// @2E38: dup
		// @2E39: sipush 1499 (0x05DB)
		// @2E3C: ldc_w 59811 (0xe9a3)
		// @2E3F: iastore
		// @2E40: dup
		// @2E41: sipush 1500 (0x05DC)
		// @2E44: ldc_w 59832 (0xe9b8)
		// @2E47: iastore
		// @2E48: dup
		// @2E49: sipush 1501 (0x05DD)
		// @2E4C: ldc_w 59852 (0xe9cc)
		// @2E4F: iastore
		// @2E50: dup
		// @2E51: sipush 1502 (0x05DE)
		// @2E54: ldc_w 59873 (0xe9e1)
		// @2E57: iastore
		// @2E58: dup
		// @2E59: sipush 1503 (0x05DF)
		// @2E5C: ldc_w 59893 (0xe9f5)
		// @2E5F: iastore
		// @2E60: dup
		// @2E61: sipush 1504 (0x05E0)
		// @2E64: ldc_w 59914 (0xea0a)
		// @2E67: iastore
		// @2E68: dup
		// @2E69: sipush 1505 (0x05E1)
		// @2E6C: ldc_w 59934 (0xea1e)
		// @2E6F: iastore
		// @2E70: dup
		// @2E71: sipush 1506 (0x05E2)
		// @2E74: ldc_w 59954 (0xea32)
		// @2E77: iastore
		// @2E78: dup
		// @2E79: sipush 1507 (0x05E3)
		// @2E7C: ldc_w 59975 (0xea47)
		// @2E7F: iastore
		// @2E80: dup
		// @2E81: sipush 1508 (0x05E4)
		// @2E84: ldc_w 59995 (0xea5b)
		// @2E87: iastore
		// @2E88: dup
		// @2E89: sipush 1509 (0x05E5)
		// @2E8C: ldc_w 60015 (0xea6f)
		// @2E8F: iastore
		// @2E90: dup
		// @2E91: sipush 1510 (0x05E6)
		// @2E94: ldc_w 60035 (0xea83)
		// @2E97: iastore
		// @2E98: dup
		// @2E99: sipush 1511 (0x05E7)
		// @2E9C: ldc_w 60055 (0xea97)
		// @2E9F: iastore
		// @2EA0: dup
		// @2EA1: sipush 1512 (0x05E8)
		// @2EA4: ldc_w 60075 (0xeaab)
		// @2EA7: iastore
		// @2EA8: dup
		// @2EA9: sipush 1513 (0x05E9)
		// @2EAC: ldc_w 60096 (0xeac0)
		// @2EAF: iastore
		// @2EB0: dup
		// @2EB1: sipush 1514 (0x05EA)
		// @2EB4: ldc_w 60116 (0xead4)
		// @2EB7: iastore
		// @2EB8: dup
		// @2EB9: sipush 1515 (0x05EB)
		// @2EBC: ldc_w 60136 (0xeae8)
		// @2EBF: iastore
		// @2EC0: dup
		// @2EC1: sipush 1516 (0x05EC)
		// @2EC4: ldc_w 60156 (0xeafc)
		// @2EC7: iastore
		// @2EC8: dup
		// @2EC9: sipush 1517 (0x05ED)
		// @2ECC: ldc_w 60175 (0xeb0f)
		// @2ECF: iastore
		// @2ED0: dup
		// @2ED1: sipush 1518 (0x05EE)
		// @2ED4: ldc_w 60195 (0xeb23)
		// @2ED7: iastore
		// @2ED8: dup
		// @2ED9: sipush 1519 (0x05EF)
		// @2EDC: ldc_w 60215 (0xeb37)
		// @2EDF: iastore
		// @2EE0: dup
		// @2EE1: sipush 1520 (0x05F0)
		// @2EE4: ldc_w 60235 (0xeb4b)
		// @2EE7: iastore
		// @2EE8: dup
		// @2EE9: sipush 1521 (0x05F1)
		// @2EEC: ldc_w 60255 (0xeb5f)
		// @2EEF: iastore
		// @2EF0: dup
		// @2EF1: sipush 1522 (0x05F2)
		// @2EF4: ldc_w 60275 (0xeb73)
		// @2EF7: iastore
		// @2EF8: dup
		// @2EF9: sipush 1523 (0x05F3)
		// @2EFC: ldc_w 60294 (0xeb86)
		// @2EFF: iastore
		// @2F00: dup
		// @2F01: sipush 1524 (0x05F4)
		// @2F04: ldc_w 60314 (0xeb9a)
		// @2F07: iastore
		// @2F08: dup
		// @2F09: sipush 1525 (0x05F5)
		// @2F0C: ldc_w 60334 (0xebae)
		// @2F0F: iastore
		// @2F10: dup
		// @2F11: sipush 1526 (0x05F6)
		// @2F14: ldc_w 60353 (0xebc1)
		// @2F17: iastore
		// @2F18: dup
		// @2F19: sipush 1527 (0x05F7)
		// @2F1C: ldc_w 60373 (0xebd5)
		// @2F1F: iastore
		// @2F20: dup
		// @2F21: sipush 1528 (0x05F8)
		// @2F24: ldc_w 60392 (0xebe8)
		// @2F27: iastore
		// @2F28: dup
		// @2F29: sipush 1529 (0x05F9)
		// @2F2C: ldc_w 60412 (0xebfc)
		// @2F2F: iastore
		// @2F30: dup
		// @2F31: sipush 1530 (0x05FA)
		// @2F34: ldc_w 60431 (0xec0f)
		// @2F37: iastore
		// @2F38: dup
		// @2F39: sipush 1531 (0x05FB)
		// @2F3C: ldc_w 60451 (0xec23)
		// @2F3F: iastore
		// @2F40: dup
		// @2F41: sipush 1532 (0x05FC)
		// @2F44: ldc_w 60470 (0xec36)
		// @2F47: iastore
		// @2F48: dup
		// @2F49: sipush 1533 (0x05FD)
		// @2F4C: ldc_w 60490 (0xec4a)
		// @2F4F: iastore
		// @2F50: dup
		// @2F51: sipush 1534 (0x05FE)
		// @2F54: ldc_w 60509 (0xec5d)
		// @2F57: iastore
		// @2F58: dup
		// @2F59: sipush 1535 (0x05FF)
		// @2F5C: ldc_w 60528 (0xec70)
		// @2F5F: iastore
		// @2F60: dup
		// @2F61: sipush 1536 (0x0600)
		// @2F64: ldc_w 60547 (0xec83)
		// @2F67: iastore
		// @2F68: dup
		// @2F69: sipush 1537 (0x0601)
		// @2F6C: ldc_w 60567 (0xec97)
		// @2F6F: iastore
		// @2F70: dup
		// @2F71: sipush 1538 (0x0602)
		// @2F74: ldc_w 60586 (0xecaa)
		// @2F77: iastore
		// @2F78: dup
		// @2F79: sipush 1539 (0x0603)
		// @2F7C: ldc_w 60605 (0xecbd)
		// @2F7F: iastore
		// @2F80: dup
		// @2F81: sipush 1540 (0x0604)
		// @2F84: ldc_w 60624 (0xecd0)
		// @2F87: iastore
		// @2F88: dup
		// @2F89: sipush 1541 (0x0605)
		// @2F8C: ldc_w 60643 (0xece3)
		// @2F8F: iastore
		// @2F90: dup
		// @2F91: sipush 1542 (0x0606)
		// @2F94: ldc_w 60662 (0xecf6)
		// @2F97: iastore
		// @2F98: dup
		// @2F99: sipush 1543 (0x0607)
		// @2F9C: ldc_w 60681 (0xed09)
		// @2F9F: iastore
		// @2FA0: dup
		// @2FA1: sipush 1544 (0x0608)
		// @2FA4: ldc_w 60700 (0xed1c)
		// @2FA7: iastore
		// @2FA8: dup
		// @2FA9: sipush 1545 (0x0609)
		// @2FAC: ldc_w 60719 (0xed2f)
		// @2FAF: iastore
		// @2FB0: dup
		// @2FB1: sipush 1546 (0x060A)
		// @2FB4: ldc_w 60738 (0xed42)
		// @2FB7: iastore
		// @2FB8: dup
		// @2FB9: sipush 1547 (0x060B)
		// @2FBC: ldc_w 60757 (0xed55)
		// @2FBF: iastore
		// @2FC0: dup
		// @2FC1: sipush 1548 (0x060C)
		// @2FC4: ldc_w 60776 (0xed68)
		// @2FC7: iastore
		// @2FC8: dup
		// @2FC9: sipush 1549 (0x060D)
		// @2FCC: ldc_w 60794 (0xed7a)
		// @2FCF: iastore
		// @2FD0: dup
		// @2FD1: sipush 1550 (0x060E)
		// @2FD4: ldc_w 60813 (0xed8d)
		// @2FD7: iastore
		// @2FD8: dup
		// @2FD9: sipush 1551 (0x060F)
		// @2FDC: ldc_w 60832 (0xeda0)
		// @2FDF: iastore
		// @2FE0: dup
		// @2FE1: sipush 1552 (0x0610)
		// @2FE4: ldc_w 60851 (0xedb3)
		// @2FE7: iastore
		// @2FE8: dup
		// @2FE9: sipush 1553 (0x0611)
		// @2FEC: ldc_w 60869 (0xedc5)
		// @2FEF: iastore
		// @2FF0: dup
		// @2FF1: sipush 1554 (0x0612)
		// @2FF4: ldc_w 60888 (0xedd8)
		// @2FF7: iastore
		// @2FF8: dup
		// @2FF9: sipush 1555 (0x0613)
		// @2FFC: ldc_w 60906 (0xedea)
		// @2FFF: iastore
		// @3000: dup
		// @3001: sipush 1556 (0x0614)
		// @3004: ldc_w 60925 (0xedfd)
		// @3007: iastore
		// @3008: dup
		// @3009: sipush 1557 (0x0615)
		// @300C: ldc_w 60943 (0xee0f)
		// @300F: iastore
		// @3010: dup
		// @3011: sipush 1558 (0x0616)
		// @3014: ldc_w 60962 (0xee22)
		// @3017: iastore
		// @3018: dup
		// @3019: sipush 1559 (0x0617)
		// @301C: ldc_w 60980 (0xee34)
		// @301F: iastore
		// @3020: dup
		// @3021: sipush 1560 (0x0618)
		// @3024: ldc_w 60999 (0xee47)
		// @3027: iastore
		// @3028: dup
		// @3029: sipush 1561 (0x0619)
		// @302C: ldc_w 61017 (0xee59)
		// @302F: iastore
		// @3030: dup
		// @3031: sipush 1562 (0x061A)
		// @3034: ldc_w 61035 (0xee6b)
		// @3037: iastore
		// @3038: dup
		// @3039: sipush 1563 (0x061B)
		// @303C: ldc_w 61054 (0xee7e)
		// @303F: iastore
		// @3040: dup
		// @3041: sipush 1564 (0x061C)
		// @3044: ldc_w 61072 (0xee90)
		// @3047: iastore
		// @3048: dup
		// @3049: sipush 1565 (0x061D)
		// @304C: ldc_w 61090 (0xeea2)
		// @304F: iastore
		// @3050: dup
		// @3051: sipush 1566 (0x061E)
		// @3054: ldc_w 61108 (0xeeb4)
		// @3057: iastore
		// @3058: dup
		// @3059: sipush 1567 (0x061F)
		// @305C: ldc_w 61127 (0xeec7)
		// @305F: iastore
		// @3060: dup
		// @3061: sipush 1568 (0x0620)
		// @3064: ldc_w 61145 (0xeed9)
		// @3067: iastore
		// @3068: dup
		// @3069: sipush 1569 (0x0621)
		// @306C: ldc_w 61163 (0xeeeb)
		// @306F: iastore
		// @3070: dup
		// @3071: sipush 1570 (0x0622)
		// @3074: ldc_w 61181 (0xeefd)
		// @3077: iastore
		// @3078: dup
		// @3079: sipush 1571 (0x0623)
		// @307C: ldc_w 61199 (0xef0f)
		// @307F: iastore
		// @3080: dup
		// @3081: sipush 1572 (0x0624)
		// @3084: ldc_w 61217 (0xef21)
		// @3087: iastore
		// @3088: dup
		// @3089: sipush 1573 (0x0625)
		// @308C: ldc_w 61235 (0xef33)
		// @308F: iastore
		// @3090: dup
		// @3091: sipush 1574 (0x0626)
		// @3094: ldc_w 61253 (0xef45)
		// @3097: iastore
		// @3098: dup
		// @3099: sipush 1575 (0x0627)
		// @309C: ldc_w 61270 (0xef56)
		// @309F: iastore
		// @30A0: dup
		// @30A1: sipush 1576 (0x0628)
		// @30A4: ldc_w 61288 (0xef68)
		// @30A7: iastore
		// @30A8: dup
		// @30A9: sipush 1577 (0x0629)
		// @30AC: ldc_w 61306 (0xef7a)
		// @30AF: iastore
		// @30B0: dup
		// @30B1: sipush 1578 (0x062A)
		// @30B4: ldc_w 61324 (0xef8c)
		// @30B7: iastore
		// @30B8: dup
		// @30B9: sipush 1579 (0x062B)
		// @30BC: ldc_w 61341 (0xef9d)
		// @30BF: iastore
		// @30C0: dup
		// @30C1: sipush 1580 (0x062C)
		// @30C4: ldc_w 61359 (0xefaf)
		// @30C7: iastore
		// @30C8: dup
		// @30C9: sipush 1581 (0x062D)
		// @30CC: ldc_w 61377 (0xefc1)
		// @30CF: iastore
		// @30D0: dup
		// @30D1: sipush 1582 (0x062E)
		// @30D4: ldc_w 61394 (0xefd2)
		// @30D7: iastore
		// @30D8: dup
		// @30D9: sipush 1583 (0x062F)
		// @30DC: ldc_w 61412 (0xefe4)
		// @30DF: iastore
		// @30E0: dup
		// @30E1: sipush 1584 (0x0630)
		// @30E4: ldc_w 61429 (0xeff5)
		// @30E7: iastore
		// @30E8: dup
		// @30E9: sipush 1585 (0x0631)
		// @30EC: ldc_w 61447 (0xf007)
		// @30EF: iastore
		// @30F0: dup
		// @30F1: sipush 1586 (0x0632)
		// @30F4: ldc_w 61464 (0xf018)
		// @30F7: iastore
		// @30F8: dup
		// @30F9: sipush 1587 (0x0633)
		// @30FC: ldc_w 61482 (0xf02a)
		// @30FF: iastore
		// @3100: dup
		// @3101: sipush 1588 (0x0634)
		// @3104: ldc_w 61499 (0xf03b)
		// @3107: iastore
		// @3108: dup
		// @3109: sipush 1589 (0x0635)
		// @310C: ldc_w 61517 (0xf04d)
		// @310F: iastore
		// @3110: dup
		// @3111: sipush 1590 (0x0636)
		// @3114: ldc_w 61534 (0xf05e)
		// @3117: iastore
		// @3118: dup
		// @3119: sipush 1591 (0x0637)
		// @311C: ldc_w 61551 (0xf06f)
		// @311F: iastore
		// @3120: dup
		// @3121: sipush 1592 (0x0638)
		// @3124: ldc_w 61568 (0xf080)
		// @3127: iastore
		// @3128: dup
		// @3129: sipush 1593 (0x0639)
		// @312C: ldc_w 61586 (0xf092)
		// @312F: iastore
		// @3130: dup
		// @3131: sipush 1594 (0x063A)
		// @3134: ldc_w 61603 (0xf0a3)
		// @3137: iastore
		// @3138: dup
		// @3139: sipush 1595 (0x063B)
		// @313C: ldc_w 61620 (0xf0b4)
		// @313F: iastore
		// @3140: dup
		// @3141: sipush 1596 (0x063C)
		// @3144: ldc_w 61637 (0xf0c5)
		// @3147: iastore
		// @3148: dup
		// @3149: sipush 1597 (0x063D)
		// @314C: ldc_w 61654 (0xf0d6)
		// @314F: iastore
		// @3150: dup
		// @3151: sipush 1598 (0x063E)
		// @3154: ldc_w 61671 (0xf0e7)
		// @3157: iastore
		// @3158: dup
		// @3159: sipush 1599 (0x063F)
		// @315C: ldc_w 61688 (0xf0f8)
		// @315F: iastore
		// @3160: dup
		// @3161: sipush 1600 (0x0640)
		// @3164: ldc_w 61705 (0xf109)
		// @3167: iastore
		// @3168: dup
		// @3169: sipush 1601 (0x0641)
		// @316C: ldc_w 61722 (0xf11a)
		// @316F: iastore
		// @3170: dup
		// @3171: sipush 1602 (0x0642)
		// @3174: ldc_w 61739 (0xf12b)
		// @3177: iastore
		// @3178: dup
		// @3179: sipush 1603 (0x0643)
		// @317C: ldc_w 61756 (0xf13c)
		// @317F: iastore
		// @3180: dup
		// @3181: sipush 1604 (0x0644)
		// @3184: ldc_w 61772 (0xf14c)
		// @3187: iastore
		// @3188: dup
		// @3189: sipush 1605 (0x0645)
		// @318C: ldc_w 61789 (0xf15d)
		// @318F: iastore
		// @3190: dup
		// @3191: sipush 1606 (0x0646)
		// @3194: ldc_w 61806 (0xf16e)
		// @3197: iastore
		// @3198: dup
		// @3199: sipush 1607 (0x0647)
		// @319C: ldc_w 61823 (0xf17f)
		// @319F: iastore
		// @31A0: dup
		// @31A1: sipush 1608 (0x0648)
		// @31A4: ldc_w 61839 (0xf18f)
		// @31A7: iastore
		// @31A8: dup
		// @31A9: sipush 1609 (0x0649)
		// @31AC: ldc_w 61856 (0xf1a0)
		// @31AF: iastore
		// @31B0: dup
		// @31B1: sipush 1610 (0x064A)
		// @31B4: ldc_w 61873 (0xf1b1)
		// @31B7: iastore
		// @31B8: dup
		// @31B9: sipush 1611 (0x064B)
		// @31BC: ldc_w 61889 (0xf1c1)
		// @31BF: iastore
		// @31C0: dup
		// @31C1: sipush 1612 (0x064C)
		// @31C4: ldc_w 61906 (0xf1d2)
		// @31C7: iastore
		// @31C8: dup
		// @31C9: sipush 1613 (0x064D)
		// @31CC: ldc_w 61922 (0xf1e2)
		// @31CF: iastore
		// @31D0: dup
		// @31D1: sipush 1614 (0x064E)
		// @31D4: ldc_w 61939 (0xf1f3)
		// @31D7: iastore
		// @31D8: dup
		// @31D9: sipush 1615 (0x064F)
		// @31DC: ldc_w 61955 (0xf203)
		// @31DF: iastore
		// @31E0: dup
		// @31E1: sipush 1616 (0x0650)
		// @31E4: ldc_w 61971 (0xf213)
		// @31E7: iastore
		// @31E8: dup
		// @31E9: sipush 1617 (0x0651)
		// @31EC: ldc_w 61988 (0xf224)
		// @31EF: iastore
		// @31F0: dup
		// @31F1: sipush 1618 (0x0652)
		// @31F4: ldc_w 62004 (0xf234)
		// @31F7: iastore
		// @31F8: dup
		// @31F9: sipush 1619 (0x0653)
		// @31FC: ldc_w 62020 (0xf244)
		// @31FF: iastore
		// @3200: dup
		// @3201: sipush 1620 (0x0654)
		// @3204: ldc_w 62036 (0xf254)
		// @3207: iastore
		// @3208: dup
		// @3209: sipush 1621 (0x0655)
		// @320C: ldc_w 62053 (0xf265)
		// @320F: iastore
		// @3210: dup
		// @3211: sipush 1622 (0x0656)
		// @3214: ldc_w 62069 (0xf275)
		// @3217: iastore
		// @3218: dup
		// @3219: sipush 1623 (0x0657)
		// @321C: ldc_w 62085 (0xf285)
		// @321F: iastore
		// @3220: dup
		// @3221: sipush 1624 (0x0658)
		// @3224: ldc_w 62101 (0xf295)
		// @3227: iastore
		// @3228: dup
		// @3229: sipush 1625 (0x0659)
		// @322C: ldc_w 62117 (0xf2a5)
		// @322F: iastore
		// @3230: dup
		// @3231: sipush 1626 (0x065A)
		// @3234: ldc_w 62133 (0xf2b5)
		// @3237: iastore
		// @3238: dup
		// @3239: sipush 1627 (0x065B)
		// @323C: ldc_w 62149 (0xf2c5)
		// @323F: iastore
		// @3240: dup
		// @3241: sipush 1628 (0x065C)
		// @3244: ldc_w 62165 (0xf2d5)
		// @3247: iastore
		// @3248: dup
		// @3249: sipush 1629 (0x065D)
		// @324C: ldc_w 62181 (0xf2e5)
		// @324F: iastore
		// @3250: dup
		// @3251: sipush 1630 (0x065E)
		// @3254: ldc_w 62197 (0xf2f5)
		// @3257: iastore
		// @3258: dup
		// @3259: sipush 1631 (0x065F)
		// @325C: ldc_w 62212 (0xf304)
		// @325F: iastore
		// @3260: dup
		// @3261: sipush 1632 (0x0660)
		// @3264: ldc_w 62228 (0xf314)
		// @3267: iastore
		// @3268: dup
		// @3269: sipush 1633 (0x0661)
		// @326C: ldc_w 62244 (0xf324)
		// @326F: iastore
		// @3270: dup
		// @3271: sipush 1634 (0x0662)
		// @3274: ldc_w 62260 (0xf334)
		// @3277: iastore
		// @3278: dup
		// @3279: sipush 1635 (0x0663)
		// @327C: ldc_w 62275 (0xf343)
		// @327F: iastore
		// @3280: dup
		// @3281: sipush 1636 (0x0664)
		// @3284: ldc_w 62291 (0xf353)
		// @3287: iastore
		// @3288: dup
		// @3289: sipush 1637 (0x0665)
		// @328C: ldc_w 62307 (0xf363)
		// @328F: iastore
		// @3290: dup
		// @3291: sipush 1638 (0x0666)
		// @3294: ldc_w 62322 (0xf372)
		// @3297: iastore
		// @3298: dup
		// @3299: sipush 1639 (0x0667)
		// @329C: ldc_w 62338 (0xf382)
		// @329F: iastore
		// @32A0: dup
		// @32A1: sipush 1640 (0x0668)
		// @32A4: ldc_w 62353 (0xf391)
		// @32A7: iastore
		// @32A8: dup
		// @32A9: sipush 1641 (0x0669)
		// @32AC: ldc_w 62369 (0xf3a1)
		// @32AF: iastore
		// @32B0: dup
		// @32B1: sipush 1642 (0x066A)
		// @32B4: ldc_w 62384 (0xf3b0)
		// @32B7: iastore
		// @32B8: dup
		// @32B9: sipush 1643 (0x066B)
		// @32BC: ldc_w 62400 (0xf3c0)
		// @32BF: iastore
		// @32C0: dup
		// @32C1: sipush 1644 (0x066C)
		// @32C4: ldc_w 62415 (0xf3cf)
		// @32C7: iastore
		// @32C8: dup
		// @32C9: sipush 1645 (0x066D)
		// @32CC: ldc_w 62430 (0xf3de)
		// @32CF: iastore
		// @32D0: dup
		// @32D1: sipush 1646 (0x066E)
		// @32D4: ldc_w 62445 (0xf3ed)
		// @32D7: iastore
		// @32D8: dup
		// @32D9: sipush 1647 (0x066F)
		// @32DC: ldc_w 62461 (0xf3fd)
		// @32DF: iastore
		// @32E0: dup
		// @32E1: sipush 1648 (0x0670)
		// @32E4: ldc_w 62476 (0xf40c)
		// @32E7: iastore
		// @32E8: dup
		// @32E9: sipush 1649 (0x0671)
		// @32EC: ldc_w 62491 (0xf41b)
		// @32EF: iastore
		// @32F0: dup
		// @32F1: sipush 1650 (0x0672)
		// @32F4: ldc_w 62506 (0xf42a)
		// @32F7: iastore
		// @32F8: dup
		// @32F9: sipush 1651 (0x0673)
		// @32FC: ldc_w 62521 (0xf439)
		// @32FF: iastore
		// @3300: dup
		// @3301: sipush 1652 (0x0674)
		// @3304: ldc_w 62536 (0xf448)
		// @3307: iastore
		// @3308: dup
		// @3309: sipush 1653 (0x0675)
		// @330C: ldc_w 62551 (0xf457)
		// @330F: iastore
		// @3310: dup
		// @3311: sipush 1654 (0x0676)
		// @3314: ldc_w 62566 (0xf466)
		// @3317: iastore
		// @3318: dup
		// @3319: sipush 1655 (0x0677)
		// @331C: ldc_w 62581 (0xf475)
		// @331F: iastore
		// @3320: dup
		// @3321: sipush 1656 (0x0678)
		// @3324: ldc_w 62596 (0xf484)
		// @3327: iastore
		// @3328: dup
		// @3329: sipush 1657 (0x0679)
		// @332C: ldc_w 62611 (0xf493)
		// @332F: iastore
		// @3330: dup
		// @3331: sipush 1658 (0x067A)
		// @3334: ldc_w 62626 (0xf4a2)
		// @3337: iastore
		// @3338: dup
		// @3339: sipush 1659 (0x067B)
		// @333C: ldc_w 62641 (0xf4b1)
		// @333F: iastore
		// @3340: dup
		// @3341: sipush 1660 (0x067C)
		// @3344: ldc_w 62655 (0xf4bf)
		// @3347: iastore
		// @3348: dup
		// @3349: sipush 1661 (0x067D)
		// @334C: ldc_w 62670 (0xf4ce)
		// @334F: iastore
		// @3350: dup
		// @3351: sipush 1662 (0x067E)
		// @3354: ldc_w 62685 (0xf4dd)
		// @3357: iastore
		// @3358: dup
		// @3359: sipush 1663 (0x067F)
		// @335C: ldc_w 62699 (0xf4eb)
		// @335F: iastore
		// @3360: dup
		// @3361: sipush 1664 (0x0680)
		// @3364: ldc_w 62714 (0xf4fa)
		// @3367: iastore
		// @3368: dup
		// @3369: sipush 1665 (0x0681)
		// @336C: ldc_w 62729 (0xf509)
		// @336F: iastore
		// @3370: dup
		// @3371: sipush 1666 (0x0682)
		// @3374: ldc_w 62743 (0xf517)
		// @3377: iastore
		// @3378: dup
		// @3379: sipush 1667 (0x0683)
		// @337C: ldc_w 62758 (0xf526)
		// @337F: iastore
		// @3380: dup
		// @3381: sipush 1668 (0x0684)
		// @3384: ldc_w 62772 (0xf534)
		// @3387: iastore
		// @3388: dup
		// @3389: sipush 1669 (0x0685)
		// @338C: ldc_w 62787 (0xf543)
		// @338F: iastore
		// @3390: dup
		// @3391: sipush 1670 (0x0686)
		// @3394: ldc_w 62801 (0xf551)
		// @3397: iastore
		// @3398: dup
		// @3399: sipush 1671 (0x0687)
		// @339C: ldc_w 62815 (0xf55f)
		// @339F: iastore
		// @33A0: dup
		// @33A1: sipush 1672 (0x0688)
		// @33A4: ldc_w 62830 (0xf56e)
		// @33A7: iastore
		// @33A8: dup
		// @33A9: sipush 1673 (0x0689)
		// @33AC: ldc_w 62844 (0xf57c)
		// @33AF: iastore
		// @33B0: dup
		// @33B1: sipush 1674 (0x068A)
		// @33B4: ldc_w 62858 (0xf58a)
		// @33B7: iastore
		// @33B8: dup
		// @33B9: sipush 1675 (0x068B)
		// @33BC: ldc_w 62872 (0xf598)
		// @33BF: iastore
		// @33C0: dup
		// @33C1: sipush 1676 (0x068C)
		// @33C4: ldc_w 62886 (0xf5a6)
		// @33C7: iastore
		// @33C8: dup
		// @33C9: sipush 1677 (0x068D)
		// @33CC: ldc_w 62901 (0xf5b5)
		// @33CF: iastore
		// @33D0: dup
		// @33D1: sipush 1678 (0x068E)
		// @33D4: ldc_w 62915 (0xf5c3)
		// @33D7: iastore
		// @33D8: dup
		// @33D9: sipush 1679 (0x068F)
		// @33DC: ldc_w 62929 (0xf5d1)
		// @33DF: iastore
		// @33E0: dup
		// @33E1: sipush 1680 (0x0690)
		// @33E4: ldc_w 62943 (0xf5df)
		// @33E7: iastore
		// @33E8: dup
		// @33E9: sipush 1681 (0x0691)
		// @33EC: ldc_w 62957 (0xf5ed)
		// @33EF: iastore
		// @33F0: dup
		// @33F1: sipush 1682 (0x0692)
		// @33F4: ldc_w 62971 (0xf5fb)
		// @33F7: iastore
		// @33F8: dup
		// @33F9: sipush 1683 (0x0693)
		// @33FC: ldc_w 62985 (0xf609)
		// @33FF: iastore
		// @3400: dup
		// @3401: sipush 1684 (0x0694)
		// @3404: ldc_w 62998 (0xf616)
		// @3407: iastore
		// @3408: dup
		// @3409: sipush 1685 (0x0695)
		// @340C: ldc_w 63012 (0xf624)
		// @340F: iastore
		// @3410: dup
		// @3411: sipush 1686 (0x0696)
		// @3414: ldc_w 63026 (0xf632)
		// @3417: iastore
		// @3418: dup
		// @3419: sipush 1687 (0x0697)
		// @341C: ldc_w 63040 (0xf640)
		// @341F: iastore
		// @3420: dup
		// @3421: sipush 1688 (0x0698)
		// @3424: ldc_w 63054 (0xf64e)
		// @3427: iastore
		// @3428: dup
		// @3429: sipush 1689 (0x0699)
		// @342C: ldc_w 63067 (0xf65b)
		// @342F: iastore
		// @3430: dup
		// @3431: sipush 1690 (0x069A)
		// @3434: ldc_w 63081 (0xf669)
		// @3437: iastore
		// @3438: dup
		// @3439: sipush 1691 (0x069B)
		// @343C: ldc_w 63095 (0xf677)
		// @343F: iastore
		// @3440: dup
		// @3441: sipush 1692 (0x069C)
		// @3444: ldc_w 63108 (0xf684)
		// @3447: iastore
		// @3448: dup
		// @3449: sipush 1693 (0x069D)
		// @344C: ldc_w 63122 (0xf692)
		// @344F: iastore
		// @3450: dup
		// @3451: sipush 1694 (0x069E)
		// @3454: ldc_w 63135 (0xf69f)
		// @3457: iastore
		// @3458: dup
		// @3459: sipush 1695 (0x069F)
		// @345C: ldc_w 63149 (0xf6ad)
		// @345F: iastore
		// @3460: dup
		// @3461: sipush 1696 (0x06A0)
		// @3464: ldc_w 63162 (0xf6ba)
		// @3467: iastore
		// @3468: dup
		// @3469: sipush 1697 (0x06A1)
		// @346C: ldc_w 63175 (0xf6c7)
		// @346F: iastore
		// @3470: dup
		// @3471: sipush 1698 (0x06A2)
		// @3474: ldc_w 63189 (0xf6d5)
		// @3477: iastore
		// @3478: dup
		// @3479: sipush 1699 (0x06A3)
		// @347C: ldc_w 63202 (0xf6e2)
		// @347F: iastore
		// @3480: dup
		// @3481: sipush 1700 (0x06A4)
		// @3484: ldc_w 63215 (0xf6ef)
		// @3487: iastore
		// @3488: dup
		// @3489: sipush 1701 (0x06A5)
		// @348C: ldc_w 63229 (0xf6fd)
		// @348F: iastore
		// @3490: dup
		// @3491: sipush 1702 (0x06A6)
		// @3494: ldc_w 63242 (0xf70a)
		// @3497: iastore
		// @3498: dup
		// @3499: sipush 1703 (0x06A7)
		// @349C: ldc_w 63255 (0xf717)
		// @349F: iastore
		// @34A0: dup
		// @34A1: sipush 1704 (0x06A8)
		// @34A4: ldc_w 63268 (0xf724)
		// @34A7: iastore
		// @34A8: dup
		// @34A9: sipush 1705 (0x06A9)
		// @34AC: ldc_w 63281 (0xf731)
		// @34AF: iastore
		// @34B0: dup
		// @34B1: sipush 1706 (0x06AA)
		// @34B4: ldc_w 63294 (0xf73e)
		// @34B7: iastore
		// @34B8: dup
		// @34B9: sipush 1707 (0x06AB)
		// @34BC: ldc_w 63307 (0xf74b)
		// @34BF: iastore
		// @34C0: dup
		// @34C1: sipush 1708 (0x06AC)
		// @34C4: ldc_w 63320 (0xf758)
		// @34C7: iastore
		// @34C8: dup
		// @34C9: sipush 1709 (0x06AD)
		// @34CC: ldc_w 63333 (0xf765)
		// @34CF: iastore
		// @34D0: dup
		// @34D1: sipush 1710 (0x06AE)
		// @34D4: ldc_w 63346 (0xf772)
		// @34D7: iastore
		// @34D8: dup
		// @34D9: sipush 1711 (0x06AF)
		// @34DC: ldc_w 63359 (0xf77f)
		// @34DF: iastore
		// @34E0: dup
		// @34E1: sipush 1712 (0x06B0)
		// @34E4: ldc_w 63372 (0xf78c)
		// @34E7: iastore
		// @34E8: dup
		// @34E9: sipush 1713 (0x06B1)
		// @34EC: ldc_w 63385 (0xf799)
		// @34EF: iastore
		// @34F0: dup
		// @34F1: sipush 1714 (0x06B2)
		// @34F4: ldc_w 63397 (0xf7a5)
		// @34F7: iastore
		// @34F8: dup
		// @34F9: sipush 1715 (0x06B3)
		// @34FC: ldc_w 63410 (0xf7b2)
		// @34FF: iastore
		// @3500: dup
		// @3501: sipush 1716 (0x06B4)
		// @3504: ldc_w 63423 (0xf7bf)
		// @3507: iastore
		// @3508: dup
		// @3509: sipush 1717 (0x06B5)
		// @350C: ldc_w 63435 (0xf7cb)
		// @350F: iastore
		// @3510: dup
		// @3511: sipush 1718 (0x06B6)
		// @3514: ldc_w 63448 (0xf7d8)
		// @3517: iastore
		// @3518: dup
		// @3519: sipush 1719 (0x06B7)
		// @351C: ldc_w 63461 (0xf7e5)
		// @351F: iastore
		// @3520: dup
		// @3521: sipush 1720 (0x06B8)
		// @3524: ldc_w 63473 (0xf7f1)
		// @3527: iastore
		// @3528: dup
		// @3529: sipush 1721 (0x06B9)
		// @352C: ldc_w 63486 (0xf7fe)
		// @352F: iastore
		// @3530: dup
		// @3531: sipush 1722 (0x06BA)
		// @3534: ldc_w 63498 (0xf80a)
		// @3537: iastore
		// @3538: dup
		// @3539: sipush 1723 (0x06BB)
		// @353C: ldc_w 63510 (0xf816)
		// @353F: iastore
		// @3540: dup
		// @3541: sipush 1724 (0x06BC)
		// @3544: ldc_w 63523 (0xf823)
		// @3547: iastore
		// @3548: dup
		// @3549: sipush 1725 (0x06BD)
		// @354C: ldc_w 63535 (0xf82f)
		// @354F: iastore
		// @3550: dup
		// @3551: sipush 1726 (0x06BE)
		// @3554: ldc_w 63547 (0xf83b)
		// @3557: iastore
		// @3558: dup
		// @3559: sipush 1727 (0x06BF)
		// @355C: ldc_w 63560 (0xf848)
		// @355F: iastore
		// @3560: dup
		// @3561: sipush 1728 (0x06C0)
		// @3564: ldc_w 63572 (0xf854)
		// @3567: iastore
		// @3568: dup
		// @3569: sipush 1729 (0x06C1)
		// @356C: ldc_w 63584 (0xf860)
		// @356F: iastore
		// @3570: dup
		// @3571: sipush 1730 (0x06C2)
		// @3574: ldc_w 63596 (0xf86c)
		// @3577: iastore
		// @3578: dup
		// @3579: sipush 1731 (0x06C3)
		// @357C: ldc_w 63608 (0xf878)
		// @357F: iastore
		// @3580: dup
		// @3581: sipush 1732 (0x06C4)
		// @3584: ldc_w 63621 (0xf885)
		// @3587: iastore
		// @3588: dup
		// @3589: sipush 1733 (0x06C5)
		// @358C: ldc_w 63633 (0xf891)
		// @358F: iastore
		// @3590: dup
		// @3591: sipush 1734 (0x06C6)
		// @3594: ldc_w 63645 (0xf89d)
		// @3597: iastore
		// @3598: dup
		// @3599: sipush 1735 (0x06C7)
		// @359C: ldc_w 63657 (0xf8a9)
		// @359F: iastore
		// @35A0: dup
		// @35A1: sipush 1736 (0x06C8)
		// @35A4: ldc_w 63668 (0xf8b4)
		// @35A7: iastore
		// @35A8: dup
		// @35A9: sipush 1737 (0x06C9)
		// @35AC: ldc_w 63680 (0xf8c0)
		// @35AF: iastore
		// @35B0: dup
		// @35B1: sipush 1738 (0x06CA)
		// @35B4: ldc_w 63692 (0xf8cc)
		// @35B7: iastore
		// @35B8: dup
		// @35B9: sipush 1739 (0x06CB)
		// @35BC: ldc_w 63704 (0xf8d8)
		// @35BF: iastore
		// @35C0: dup
		// @35C1: sipush 1740 (0x06CC)
		// @35C4: ldc_w 63716 (0xf8e4)
		// @35C7: iastore
		// @35C8: dup
		// @35C9: sipush 1741 (0x06CD)
		// @35CC: ldc_w 63728 (0xf8f0)
		// @35CF: iastore
		// @35D0: dup
		// @35D1: sipush 1742 (0x06CE)
		// @35D4: ldc_w 63739 (0xf8fb)
		// @35D7: iastore
		// @35D8: dup
		// @35D9: sipush 1743 (0x06CF)
		// @35DC: ldc_w 63751 (0xf907)
		// @35DF: iastore
		// @35E0: dup
		// @35E1: sipush 1744 (0x06D0)
		// @35E4: ldc_w 63763 (0xf913)
		// @35E7: iastore
		// @35E8: dup
		// @35E9: sipush 1745 (0x06D1)
		// @35EC: ldc_w 63774 (0xf91e)
		// @35EF: iastore
		// @35F0: dup
		// @35F1: sipush 1746 (0x06D2)
		// @35F4: ldc_w 63786 (0xf92a)
		// @35F7: iastore
		// @35F8: dup
		// @35F9: sipush 1747 (0x06D3)
		// @35FC: ldc_w 63797 (0xf935)
		// @35FF: iastore
		// @3600: dup
		// @3601: sipush 1748 (0x06D4)
		// @3604: ldc_w 63809 (0xf941)
		// @3607: iastore
		// @3608: dup
		// @3609: sipush 1749 (0x06D5)
		// @360C: ldc_w 63820 (0xf94c)
		// @360F: iastore
		// @3610: dup
		// @3611: sipush 1750 (0x06D6)
		// @3614: ldc_w 63832 (0xf958)
		// @3617: iastore
		// @3618: dup
		// @3619: sipush 1751 (0x06D7)
		// @361C: ldc_w 63843 (0xf963)
		// @361F: iastore
		// @3620: dup
		// @3621: sipush 1752 (0x06D8)
		// @3624: ldc_w 63854 (0xf96e)
		// @3627: iastore
		// @3628: dup
		// @3629: sipush 1753 (0x06D9)
		// @362C: ldc_w 63866 (0xf97a)
		// @362F: iastore
		// @3630: dup
		// @3631: sipush 1754 (0x06DA)
		// @3634: ldc_w 63877 (0xf985)
		// @3637: iastore
		// @3638: dup
		// @3639: sipush 1755 (0x06DB)
		// @363C: ldc_w 63888 (0xf990)
		// @363F: iastore
		// @3640: dup
		// @3641: sipush 1756 (0x06DC)
		// @3644: ldc_w 63899 (0xf99b)
		// @3647: iastore
		// @3648: dup
		// @3649: sipush 1757 (0x06DD)
		// @364C: ldc_w 63910 (0xf9a6)
		// @364F: iastore
		// @3650: dup
		// @3651: sipush 1758 (0x06DE)
		// @3654: ldc_w 63922 (0xf9b2)
		// @3657: iastore
		// @3658: dup
		// @3659: sipush 1759 (0x06DF)
		// @365C: ldc_w 63933 (0xf9bd)
		// @365F: iastore
		// @3660: dup
		// @3661: sipush 1760 (0x06E0)
		// @3664: ldc_w 63944 (0xf9c8)
		// @3667: iastore
		// @3668: dup
		// @3669: sipush 1761 (0x06E1)
		// @366C: ldc_w 63955 (0xf9d3)
		// @366F: iastore
		// @3670: dup
		// @3671: sipush 1762 (0x06E2)
		// @3674: ldc_w 63966 (0xf9de)
		// @3677: iastore
		// @3678: dup
		// @3679: sipush 1763 (0x06E3)
		// @367C: ldc_w 63976 (0xf9e8)
		// @367F: iastore
		// @3680: dup
		// @3681: sipush 1764 (0x06E4)
		// @3684: ldc_w 63987 (0xf9f3)
		// @3687: iastore
		// @3688: dup
		// @3689: sipush 1765 (0x06E5)
		// @368C: ldc_w 63998 (0xf9fe)
		// @368F: iastore
		// @3690: dup
		// @3691: sipush 1766 (0x06E6)
		// @3694: ldc_w 64009 (0xfa09)
		// @3697: iastore
		// @3698: dup
		// @3699: sipush 1767 (0x06E7)
		// @369C: ldc_w 64020 (0xfa14)
		// @369F: iastore
		// @36A0: dup
		// @36A1: sipush 1768 (0x06E8)
		// @36A4: ldc_w 64031 (0xfa1f)
		// @36A7: iastore
		// @36A8: dup
		// @36A9: sipush 1769 (0x06E9)
		// @36AC: ldc_w 64041 (0xfa29)
		// @36AF: iastore
		// @36B0: dup
		// @36B1: sipush 1770 (0x06EA)
		// @36B4: ldc_w 64052 (0xfa34)
		// @36B7: iastore
		// @36B8: dup
		// @36B9: sipush 1771 (0x06EB)
		// @36BC: ldc_w 64062 (0xfa3e)
		// @36BF: iastore
		// @36C0: dup
		// @36C1: sipush 1772 (0x06EC)
		// @36C4: ldc_w 64073 (0xfa49)
		// @36C7: iastore
		// @36C8: dup
		// @36C9: sipush 1773 (0x06ED)
		// @36CC: ldc_w 64084 (0xfa54)
		// @36CF: iastore
		// @36D0: dup
		// @36D1: sipush 1774 (0x06EE)
		// @36D4: ldc_w 64094 (0xfa5e)
		// @36D7: iastore
		// @36D8: dup
		// @36D9: sipush 1775 (0x06EF)
		// @36DC: ldc_w 64105 (0xfa69)
		// @36DF: iastore
		// @36E0: dup
		// @36E1: sipush 1776 (0x06F0)
		// @36E4: ldc_w 64115 (0xfa73)
		// @36E7: iastore
		// @36E8: dup
		// @36E9: sipush 1777 (0x06F1)
		// @36EC: ldc_w 64125 (0xfa7d)
		// @36EF: iastore
		// @36F0: dup
		// @36F1: sipush 1778 (0x06F2)
		// @36F4: ldc_w 64136 (0xfa88)
		// @36F7: iastore
		// @36F8: dup
		// @36F9: sipush 1779 (0x06F3)
		// @36FC: ldc_w 64146 (0xfa92)
		// @36FF: iastore
		// @3700: dup
		// @3701: sipush 1780 (0x06F4)
		// @3704: ldc_w 64156 (0xfa9c)
		// @3707: iastore
		// @3708: dup
		// @3709: sipush 1781 (0x06F5)
		// @370C: ldc_w 64167 (0xfaa7)
		// @370F: iastore
		// @3710: dup
		// @3711: sipush 1782 (0x06F6)
		// @3714: ldc_w 64177 (0xfab1)
		// @3717: iastore
		// @3718: dup
		// @3719: sipush 1783 (0x06F7)
		// @371C: ldc_w 64187 (0xfabb)
		// @371F: iastore
		// @3720: dup
		// @3721: sipush 1784 (0x06F8)
		// @3724: ldc_w 64197 (0xfac5)
		// @3727: iastore
		// @3728: dup
		// @3729: sipush 1785 (0x06F9)
		// @372C: ldc_w 64207 (0xfacf)
		// @372F: iastore
		// @3730: dup
		// @3731: sipush 1786 (0x06FA)
		// @3734: ldc_w 64217 (0xfad9)
		// @3737: iastore
		// @3738: dup
		// @3739: sipush 1787 (0x06FB)
		// @373C: ldc_w 64227 (0xfae3)
		// @373F: iastore
		// @3740: dup
		// @3741: sipush 1788 (0x06FC)
		// @3744: ldc_w 64237 (0xfaed)
		// @3747: iastore
		// @3748: dup
		// @3749: sipush 1789 (0x06FD)
		// @374C: ldc_w 64247 (0xfaf7)
		// @374F: iastore
		// @3750: dup
		// @3751: sipush 1790 (0x06FE)
		// @3754: ldc_w 64257 (0xfb01)
		// @3757: iastore
		// @3758: dup
		// @3759: sipush 1791 (0x06FF)
		// @375C: ldc_w 64267 (0xfb0b)
		// @375F: iastore
		// @3760: dup
		// @3761: sipush 1792 (0x0700)
		// @3764: ldc_w 64277 (0xfb15)
		// @3767: iastore
		// @3768: dup
		// @3769: sipush 1793 (0x0701)
		// @376C: ldc_w 64287 (0xfb1f)
		// @376F: iastore
		// @3770: dup
		// @3771: sipush 1794 (0x0702)
		// @3774: ldc_w 64296 (0xfb28)
		// @3777: iastore
		// @3778: dup
		// @3779: sipush 1795 (0x0703)
		// @377C: ldc_w 64306 (0xfb32)
		// @377F: iastore
		// @3780: dup
		// @3781: sipush 1796 (0x0704)
		// @3784: ldc_w 64316 (0xfb3c)
		// @3787: iastore
		// @3788: dup
		// @3789: sipush 1797 (0x0705)
		// @378C: ldc_w 64325 (0xfb45)
		// @378F: iastore
		// @3790: dup
		// @3791: sipush 1798 (0x0706)
		// @3794: ldc_w 64335 (0xfb4f)
		// @3797: iastore
		// @3798: dup
		// @3799: sipush 1799 (0x0707)
		// @379C: ldc_w 64344 (0xfb58)
		// @379F: iastore
		// @37A0: dup
		// @37A1: sipush 1800 (0x0708)
		// @37A4: ldc_w 64354 (0xfb62)
		// @37A7: iastore
		// @37A8: dup
		// @37A9: sipush 1801 (0x0709)
		// @37AC: ldc_w 64363 (0xfb6b)
		// @37AF: iastore
		// @37B0: dup
		// @37B1: sipush 1802 (0x070A)
		// @37B4: ldc_w 64373 (0xfb75)
		// @37B7: iastore
		// @37B8: dup
		// @37B9: sipush 1803 (0x070B)
		// @37BC: ldc_w 64382 (0xfb7e)
		// @37BF: iastore
		// @37C0: dup
		// @37C1: sipush 1804 (0x070C)
		// @37C4: ldc_w 64392 (0xfb88)
		// @37C7: iastore
		// @37C8: dup
		// @37C9: sipush 1805 (0x070D)
		// @37CC: ldc_w 64401 (0xfb91)
		// @37CF: iastore
		// @37D0: dup
		// @37D1: sipush 1806 (0x070E)
		// @37D4: ldc_w 64410 (0xfb9a)
		// @37D7: iastore
		// @37D8: dup
		// @37D9: sipush 1807 (0x070F)
		// @37DC: ldc_w 64420 (0xfba4)
		// @37DF: iastore
		// @37E0: dup
		// @37E1: sipush 1808 (0x0710)
		// @37E4: ldc_w 64429 (0xfbad)
		// @37E7: iastore
		// @37E8: dup
		// @37E9: sipush 1809 (0x0711)
		// @37EC: ldc_w 64438 (0xfbb6)
		// @37EF: iastore
		// @37F0: dup
		// @37F1: sipush 1810 (0x0712)
		// @37F4: ldc_w 64447 (0xfbbf)
		// @37F7: iastore
		// @37F8: dup
		// @37F9: sipush 1811 (0x0713)
		// @37FC: ldc_w 64456 (0xfbc8)
		// @37FF: iastore
		// @3800: dup
		// @3801: sipush 1812 (0x0714)
		// @3804: ldc_w 64465 (0xfbd1)
		// @3807: iastore
		// @3808: dup
		// @3809: sipush 1813 (0x0715)
		// @380C: ldc_w 64474 (0xfbda)
		// @380F: iastore
		// @3810: dup
		// @3811: sipush 1814 (0x0716)
		// @3814: ldc_w 64483 (0xfbe3)
		// @3817: iastore
		// @3818: dup
		// @3819: sipush 1815 (0x0717)
		// @381C: ldc_w 64492 (0xfbec)
		// @381F: iastore
		// @3820: dup
		// @3821: sipush 1816 (0x0718)
		// @3824: ldc_w 64501 (0xfbf5)
		// @3827: iastore
		// @3828: dup
		// @3829: sipush 1817 (0x0719)
		// @382C: ldc_w 64510 (0xfbfe)
		// @382F: iastore
		// @3830: dup
		// @3831: sipush 1818 (0x071A)
		// @3834: ldc_w 64519 (0xfc07)
		// @3837: iastore
		// @3838: dup
		// @3839: sipush 1819 (0x071B)
		// @383C: ldc_w 64528 (0xfc10)
		// @383F: iastore
		// @3840: dup
		// @3841: sipush 1820 (0x071C)
		// @3844: ldc_w 64536 (0xfc18)
		// @3847: iastore
		// @3848: dup
		// @3849: sipush 1821 (0x071D)
		// @384C: ldc_w 64545 (0xfc21)
		// @384F: iastore
		// @3850: dup
		// @3851: sipush 1822 (0x071E)
		// @3854: ldc_w 64554 (0xfc2a)
		// @3857: iastore
		// @3858: dup
		// @3859: sipush 1823 (0x071F)
		// @385C: ldc_w 64563 (0xfc33)
		// @385F: iastore
		// @3860: dup
		// @3861: sipush 1824 (0x0720)
		// @3864: ldc_w 64571 (0xfc3b)
		// @3867: iastore
		// @3868: dup
		// @3869: sipush 1825 (0x0721)
		// @386C: ldc_w 64580 (0xfc44)
		// @386F: iastore
		// @3870: dup
		// @3871: sipush 1826 (0x0722)
		// @3874: ldc_w 64588 (0xfc4c)
		// @3877: iastore
		// @3878: dup
		// @3879: sipush 1827 (0x0723)
		// @387C: ldc_w 64597 (0xfc55)
		// @387F: iastore
		// @3880: dup
		// @3881: sipush 1828 (0x0724)
		// @3884: ldc_w 64605 (0xfc5d)
		// @3887: iastore
		// @3888: dup
		// @3889: sipush 1829 (0x0725)
		// @388C: ldc_w 64614 (0xfc66)
		// @388F: iastore
		// @3890: dup
		// @3891: sipush 1830 (0x0726)
		// @3894: ldc_w 64622 (0xfc6e)
		// @3897: iastore
		// @3898: dup
		// @3899: sipush 1831 (0x0727)
		// @389C: ldc_w 64630 (0xfc76)
		// @389F: iastore
		// @38A0: dup
		// @38A1: sipush 1832 (0x0728)
		// @38A4: ldc_w 64639 (0xfc7f)
		// @38A7: iastore
		// @38A8: dup
		// @38A9: sipush 1833 (0x0729)
		// @38AC: ldc_w 64647 (0xfc87)
		// @38AF: iastore
		// @38B0: dup
		// @38B1: sipush 1834 (0x072A)
		// @38B4: ldc_w 64655 (0xfc8f)
		// @38B7: iastore
		// @38B8: dup
		// @38B9: sipush 1835 (0x072B)
		// @38BC: ldc_w 64663 (0xfc97)
		// @38BF: iastore
		// @38C0: dup
		// @38C1: sipush 1836 (0x072C)
		// @38C4: ldc_w 64672 (0xfca0)
		// @38C7: iastore
		// @38C8: dup
		// @38C9: sipush 1837 (0x072D)
		// @38CC: ldc_w 64680 (0xfca8)
		// @38CF: iastore
		// @38D0: dup
		// @38D1: sipush 1838 (0x072E)
		// @38D4: ldc_w 64688 (0xfcb0)
		// @38D7: iastore
		// @38D8: dup
		// @38D9: sipush 1839 (0x072F)
		// @38DC: ldc_w 64696 (0xfcb8)
		// @38DF: iastore
		// @38E0: dup
		// @38E1: sipush 1840 (0x0730)
		// @38E4: ldc_w 64704 (0xfcc0)
		// @38E7: iastore
		// @38E8: dup
		// @38E9: sipush 1841 (0x0731)
		// @38EC: ldc_w 64712 (0xfcc8)
		// @38EF: iastore
		// @38F0: dup
		// @38F1: sipush 1842 (0x0732)
		// @38F4: ldc_w 64720 (0xfcd0)
		// @38F7: iastore
		// @38F8: dup
		// @38F9: sipush 1843 (0x0733)
		// @38FC: ldc_w 64728 (0xfcd8)
		// @38FF: iastore
		// @3900: dup
		// @3901: sipush 1844 (0x0734)
		// @3904: ldc_w 64735 (0xfcdf)
		// @3907: iastore
		// @3908: dup
		// @3909: sipush 1845 (0x0735)
		// @390C: ldc_w 64743 (0xfce7)
		// @390F: iastore
		// @3910: dup
		// @3911: sipush 1846 (0x0736)
		// @3914: ldc_w 64751 (0xfcef)
		// @3917: iastore
		// @3918: dup
		// @3919: sipush 1847 (0x0737)
		// @391C: ldc_w 64759 (0xfcf7)
		// @391F: iastore
		// @3920: dup
		// @3921: sipush 1848 (0x0738)
		// @3924: ldc_w 64766 (0xfcfe)
		// @3927: iastore
		// @3928: dup
		// @3929: sipush 1849 (0x0739)
		// @392C: ldc_w 64774 (0xfd06)
		// @392F: iastore
		// @3930: dup
		// @3931: sipush 1850 (0x073A)
		// @3934: ldc_w 64782 (0xfd0e)
		// @3937: iastore
		// @3938: dup
		// @3939: sipush 1851 (0x073B)
		// @393C: ldc_w 64789 (0xfd15)
		// @393F: iastore
		// @3940: dup
		// @3941: sipush 1852 (0x073C)
		// @3944: ldc_w 64797 (0xfd1d)
		// @3947: iastore
		// @3948: dup
		// @3949: sipush 1853 (0x073D)
		// @394C: ldc_w 64804 (0xfd24)
		// @394F: iastore
		// @3950: dup
		// @3951: sipush 1854 (0x073E)
		// @3954: ldc_w 64812 (0xfd2c)
		// @3957: iastore
		// @3958: dup
		// @3959: sipush 1855 (0x073F)
		// @395C: ldc_w 64819 (0xfd33)
		// @395F: iastore
		// @3960: dup
		// @3961: sipush 1856 (0x0740)
		// @3964: ldc_w 64827 (0xfd3b)
		// @3967: iastore
		// @3968: dup
		// @3969: sipush 1857 (0x0741)
		// @396C: ldc_w 64834 (0xfd42)
		// @396F: iastore
		// @3970: dup
		// @3971: sipush 1858 (0x0742)
		// @3974: ldc_w 64841 (0xfd49)
		// @3977: iastore
		// @3978: dup
		// @3979: sipush 1859 (0x0743)
		// @397C: ldc_w 64849 (0xfd51)
		// @397F: iastore
		// @3980: dup
		// @3981: sipush 1860 (0x0744)
		// @3984: ldc_w 64856 (0xfd58)
		// @3987: iastore
		// @3988: dup
		// @3989: sipush 1861 (0x0745)
		// @398C: ldc_w 64863 (0xfd5f)
		// @398F: iastore
		// @3990: dup
		// @3991: sipush 1862 (0x0746)
		// @3994: ldc_w 64870 (0xfd66)
		// @3997: iastore
		// @3998: dup
		// @3999: sipush 1863 (0x0747)
		// @399C: ldc_w 64877 (0xfd6d)
		// @399F: iastore
		// @39A0: dup
		// @39A1: sipush 1864 (0x0748)
		// @39A4: ldc_w 64884 (0xfd74)
		// @39A7: iastore
		// @39A8: dup
		// @39A9: sipush 1865 (0x0749)
		// @39AC: ldc_w 64892 (0xfd7c)
		// @39AF: iastore
		// @39B0: dup
		// @39B1: sipush 1866 (0x074A)
		// @39B4: ldc_w 64899 (0xfd83)
		// @39B7: iastore
		// @39B8: dup
		// @39B9: sipush 1867 (0x074B)
		// @39BC: ldc_w 64905 (0xfd89)
		// @39BF: iastore
		// @39C0: dup
		// @39C1: sipush 1868 (0x074C)
		// @39C4: ldc_w 64912 (0xfd90)
		// @39C7: iastore
		// @39C8: dup
		// @39C9: sipush 1869 (0x074D)
		// @39CC: ldc_w 64919 (0xfd97)
		// @39CF: iastore
		// @39D0: dup
		// @39D1: sipush 1870 (0x074E)
		// @39D4: ldc_w 64926 (0xfd9e)
		// @39D7: iastore
		// @39D8: dup
		// @39D9: sipush 1871 (0x074F)
		// @39DC: ldc_w 64933 (0xfda5)
		// @39DF: iastore
		// @39E0: dup
		// @39E1: sipush 1872 (0x0750)
		// @39E4: ldc_w 64940 (0xfdac)
		// @39E7: iastore
		// @39E8: dup
		// @39E9: sipush 1873 (0x0751)
		// @39EC: ldc_w 64947 (0xfdb3)
		// @39EF: iastore
		// @39F0: dup
		// @39F1: sipush 1874 (0x0752)
		// @39F4: ldc_w 64953 (0xfdb9)
		// @39F7: iastore
		// @39F8: dup
		// @39F9: sipush 1875 (0x0753)
		// @39FC: ldc_w 64960 (0xfdc0)
		// @39FF: iastore
		// @3A00: dup
		// @3A01: sipush 1876 (0x0754)
		// @3A04: ldc_w 64967 (0xfdc7)
		// @3A07: iastore
		// @3A08: dup
		// @3A09: sipush 1877 (0x0755)
		// @3A0C: ldc_w 64973 (0xfdcd)
		// @3A0F: iastore
		// @3A10: dup
		// @3A11: sipush 1878 (0x0756)
		// @3A14: ldc_w 64980 (0xfdd4)
		// @3A17: iastore
		// @3A18: dup
		// @3A19: sipush 1879 (0x0757)
		// @3A1C: ldc_w 64986 (0xfdda)
		// @3A1F: iastore
		// @3A20: dup
		// @3A21: sipush 1880 (0x0758)
		// @3A24: ldc_w 64993 (0xfde1)
		// @3A27: iastore
		// @3A28: dup
		// @3A29: sipush 1881 (0x0759)
		// @3A2C: ldc_w 64999 (0xfde7)
		// @3A2F: iastore
		// @3A30: dup
		// @3A31: sipush 1882 (0x075A)
		// @3A34: ldc_w 65006 (0xfdee)
		// @3A37: iastore
		// @3A38: dup
		// @3A39: sipush 1883 (0x075B)
		// @3A3C: ldc_w 65012 (0xfdf4)
		// @3A3F: iastore
		// @3A40: dup
		// @3A41: sipush 1884 (0x075C)
		// @3A44: ldc_w 65018 (0xfdfa)
		// @3A47: iastore
		// @3A48: dup
		// @3A49: sipush 1885 (0x075D)
		// @3A4C: ldc_w 65025 (0xfe01)
		// @3A4F: iastore
		// @3A50: dup
		// @3A51: sipush 1886 (0x075E)
		// @3A54: ldc_w 65031 (0xfe07)
		// @3A57: iastore
		// @3A58: dup
		// @3A59: sipush 1887 (0x075F)
		// @3A5C: ldc_w 65037 (0xfe0d)
		// @3A5F: iastore
		// @3A60: dup
		// @3A61: sipush 1888 (0x0760)
		// @3A64: ldc_w 65043 (0xfe13)
		// @3A67: iastore
		// @3A68: dup
		// @3A69: sipush 1889 (0x0761)
		// @3A6C: ldc_w 65049 (0xfe19)
		// @3A6F: iastore
		// @3A70: dup
		// @3A71: sipush 1890 (0x0762)
		// @3A74: ldc_w 65055 (0xfe1f)
		// @3A77: iastore
		// @3A78: dup
		// @3A79: sipush 1891 (0x0763)
		// @3A7C: ldc_w 65061 (0xfe25)
		// @3A7F: iastore
		// @3A80: dup
		// @3A81: sipush 1892 (0x0764)
		// @3A84: ldc_w 65067 (0xfe2b)
		// @3A87: iastore
		// @3A88: dup
		// @3A89: sipush 1893 (0x0765)
		// @3A8C: ldc_w 65073 (0xfe31)
		// @3A8F: iastore
		// @3A90: dup
		// @3A91: sipush 1894 (0x0766)
		// @3A94: ldc_w 65079 (0xfe37)
		// @3A97: iastore
		// @3A98: dup
		// @3A99: sipush 1895 (0x0767)
		// @3A9C: ldc_w 65085 (0xfe3d)
		// @3A9F: iastore
		// @3AA0: dup
		// @3AA1: sipush 1896 (0x0768)
		// @3AA4: ldc_w 65091 (0xfe43)
		// @3AA7: iastore
		// @3AA8: dup
		// @3AA9: sipush 1897 (0x0769)
		// @3AAC: ldc_w 65097 (0xfe49)
		// @3AAF: iastore
		// @3AB0: dup
		// @3AB1: sipush 1898 (0x076A)
		// @3AB4: ldc_w 65103 (0xfe4f)
		// @3AB7: iastore
		// @3AB8: dup
		// @3AB9: sipush 1899 (0x076B)
		// @3ABC: ldc_w 65109 (0xfe55)
		// @3ABF: iastore
		// @3AC0: dup
		// @3AC1: sipush 1900 (0x076C)
		// @3AC4: ldc_w 65114 (0xfe5a)
		// @3AC7: iastore
		// @3AC8: dup
		// @3AC9: sipush 1901 (0x076D)
		// @3ACC: ldc_w 65120 (0xfe60)
		// @3ACF: iastore
		// @3AD0: dup
		// @3AD1: sipush 1902 (0x076E)
		// @3AD4: ldc_w 65126 (0xfe66)
		// @3AD7: iastore
		// @3AD8: dup
		// @3AD9: sipush 1903 (0x076F)
		// @3ADC: ldc_w 65131 (0xfe6b)
		// @3ADF: iastore
		// @3AE0: dup
		// @3AE1: sipush 1904 (0x0770)
		// @3AE4: ldc_w 65137 (0xfe71)
		// @3AE7: iastore
		// @3AE8: dup
		// @3AE9: sipush 1905 (0x0771)
		// @3AEC: ldc_w 65142 (0xfe76)
		// @3AEF: iastore
		// @3AF0: dup
		// @3AF1: sipush 1906 (0x0772)
		// @3AF4: ldc_w 65148 (0xfe7c)
		// @3AF7: iastore
		// @3AF8: dup
		// @3AF9: sipush 1907 (0x0773)
		// @3AFC: ldc_w 65153 (0xfe81)
		// @3AFF: iastore
		// @3B00: dup
		// @3B01: sipush 1908 (0x0774)
		// @3B04: ldc_w 65159 (0xfe87)
		// @3B07: iastore
		// @3B08: dup
		// @3B09: sipush 1909 (0x0775)
		// @3B0C: ldc_w 65164 (0xfe8c)
		// @3B0F: iastore
		// @3B10: dup
		// @3B11: sipush 1910 (0x0776)
		// @3B14: ldc_w 65169 (0xfe91)
		// @3B17: iastore
		// @3B18: dup
		// @3B19: sipush 1911 (0x0777)
		// @3B1C: ldc_w 65175 (0xfe97)
		// @3B1F: iastore
		// @3B20: dup
		// @3B21: sipush 1912 (0x0778)
		// @3B24: ldc_w 65180 (0xfe9c)
		// @3B27: iastore
		// @3B28: dup
		// @3B29: sipush 1913 (0x0779)
		// @3B2C: ldc_w 65185 (0xfea1)
		// @3B2F: iastore
		// @3B30: dup
		// @3B31: sipush 1914 (0x077A)
		// @3B34: ldc_w 65190 (0xfea6)
		// @3B37: iastore
		// @3B38: dup
		// @3B39: sipush 1915 (0x077B)
		// @3B3C: ldc_w 65195 (0xfeab)
		// @3B3F: iastore
		// @3B40: dup
		// @3B41: sipush 1916 (0x077C)
		// @3B44: ldc_w 65200 (0xfeb0)
		// @3B47: iastore
		// @3B48: dup
		// @3B49: sipush 1917 (0x077D)
		// @3B4C: ldc_w 65205 (0xfeb5)
		// @3B4F: iastore
		// @3B50: dup
		// @3B51: sipush 1918 (0x077E)
		// @3B54: ldc_w 65210 (0xfeba)
		// @3B57: iastore
		// @3B58: dup
		// @3B59: sipush 1919 (0x077F)
		// @3B5C: ldc_w 65215 (0xfebf)
		// @3B5F: iastore
		// @3B60: dup
		// @3B61: sipush 1920 (0x0780)
		// @3B64: ldc_w 65220 (0xfec4)
		// @3B67: iastore
		// @3B68: dup
		// @3B69: sipush 1921 (0x0781)
		// @3B6C: ldc_w 65225 (0xfec9)
		// @3B6F: iastore
		// @3B70: dup
		// @3B71: sipush 1922 (0x0782)
		// @3B74: ldc_w 65230 (0xfece)
		// @3B77: iastore
		// @3B78: dup
		// @3B79: sipush 1923 (0x0783)
		// @3B7C: ldc_w 65235 (0xfed3)
		// @3B7F: iastore
		// @3B80: dup
		// @3B81: sipush 1924 (0x0784)
		// @3B84: ldc_w 65240 (0xfed8)
		// @3B87: iastore
		// @3B88: dup
		// @3B89: sipush 1925 (0x0785)
		// @3B8C: ldc_w 65245 (0xfedd)
		// @3B8F: iastore
		// @3B90: dup
		// @3B91: sipush 1926 (0x0786)
		// @3B94: ldc_w 65249 (0xfee1)
		// @3B97: iastore
		// @3B98: dup
		// @3B99: sipush 1927 (0x0787)
		// @3B9C: ldc_w 65254 (0xfee6)
		// @3B9F: iastore
		// @3BA0: dup
		// @3BA1: sipush 1928 (0x0788)
		// @3BA4: ldc_w 65259 (0xfeeb)
		// @3BA7: iastore
		// @3BA8: dup
		// @3BA9: sipush 1929 (0x0789)
		// @3BAC: ldc_w 65263 (0xfeef)
		// @3BAF: iastore
		// @3BB0: dup
		// @3BB1: sipush 1930 (0x078A)
		// @3BB4: ldc_w 65268 (0xfef4)
		// @3BB7: iastore
		// @3BB8: dup
		// @3BB9: sipush 1931 (0x078B)
		// @3BBC: ldc_w 65272 (0xfef8)
		// @3BBF: iastore
		// @3BC0: dup
		// @3BC1: sipush 1932 (0x078C)
		// @3BC4: ldc_w 65277 (0xfefd)
		// @3BC7: iastore
		// @3BC8: dup
		// @3BC9: sipush 1933 (0x078D)
		// @3BCC: ldc_w 65281 (0xff01)
		// @3BCF: iastore
		// @3BD0: dup
		// @3BD1: sipush 1934 (0x078E)
		// @3BD4: ldc_w 65286 (0xff06)
		// @3BD7: iastore
		// @3BD8: dup
		// @3BD9: sipush 1935 (0x078F)
		// @3BDC: ldc_w 65290 (0xff0a)
		// @3BDF: iastore
		// @3BE0: dup
		// @3BE1: sipush 1936 (0x0790)
		// @3BE4: ldc_w 65294 (0xff0e)
		// @3BE7: iastore
		// @3BE8: dup
		// @3BE9: sipush 1937 (0x0791)
		// @3BEC: ldc_w 65299 (0xff13)
		// @3BEF: iastore
		// @3BF0: dup
		// @3BF1: sipush 1938 (0x0792)
		// @3BF4: ldc_w 65303 (0xff17)
		// @3BF7: iastore
		// @3BF8: dup
		// @3BF9: sipush 1939 (0x0793)
		// @3BFC: ldc_w 65307 (0xff1b)
		// @3BFF: iastore
		// @3C00: dup
		// @3C01: sipush 1940 (0x0794)
		// @3C04: ldc_w 65311 (0xff1f)
		// @3C07: iastore
		// @3C08: dup
		// @3C09: sipush 1941 (0x0795)
		// @3C0C: ldc_w 65315 (0xff23)
		// @3C0F: iastore
		// @3C10: dup
		// @3C11: sipush 1942 (0x0796)
		// @3C14: ldc_w 65320 (0xff28)
		// @3C17: iastore
		// @3C18: dup
		// @3C19: sipush 1943 (0x0797)
		// @3C1C: ldc_w 65324 (0xff2c)
		// @3C1F: iastore
		// @3C20: dup
		// @3C21: sipush 1944 (0x0798)
		// @3C24: ldc_w 65328 (0xff30)
		// @3C27: iastore
		// @3C28: dup
		// @3C29: sipush 1945 (0x0799)
		// @3C2C: ldc_w 65332 (0xff34)
		// @3C2F: iastore
		// @3C30: dup
		// @3C31: sipush 1946 (0x079A)
		// @3C34: ldc_w 65336 (0xff38)
		// @3C37: iastore
		// @3C38: dup
		// @3C39: sipush 1947 (0x079B)
		// @3C3C: ldc_w 65339 (0xff3b)
		// @3C3F: iastore
		// @3C40: dup
		// @3C41: sipush 1948 (0x079C)
		// @3C44: ldc_w 65343 (0xff3f)
		// @3C47: iastore
		// @3C48: dup
		// @3C49: sipush 1949 (0x079D)
		// @3C4C: ldc_w 65347 (0xff43)
		// @3C4F: iastore
		// @3C50: dup
		// @3C51: sipush 1950 (0x079E)
		// @3C54: ldc_w 65351 (0xff47)
		// @3C57: iastore
		// @3C58: dup
		// @3C59: sipush 1951 (0x079F)
		// @3C5C: ldc_w 65355 (0xff4b)
		// @3C5F: iastore
		// @3C60: dup
		// @3C61: sipush 1952 (0x07A0)
		// @3C64: ldc_w 65358 (0xff4e)
		// @3C67: iastore
		// @3C68: dup
		// @3C69: sipush 1953 (0x07A1)
		// @3C6C: ldc_w 65362 (0xff52)
		// @3C6F: iastore
		// @3C70: dup
		// @3C71: sipush 1954 (0x07A2)
		// @3C74: ldc_w 65366 (0xff56)
		// @3C77: iastore
		// @3C78: dup
		// @3C79: sipush 1955 (0x07A3)
		// @3C7C: ldc_w 65369 (0xff59)
		// @3C7F: iastore
		// @3C80: dup
		// @3C81: sipush 1956 (0x07A4)
		// @3C84: ldc_w 65373 (0xff5d)
		// @3C87: iastore
		// @3C88: dup
		// @3C89: sipush 1957 (0x07A5)
		// @3C8C: ldc_w 65376 (0xff60)
		// @3C8F: iastore
		// @3C90: dup
		// @3C91: sipush 1958 (0x07A6)
		// @3C94: ldc_w 65380 (0xff64)
		// @3C97: iastore
		// @3C98: dup
		// @3C99: sipush 1959 (0x07A7)
		// @3C9C: ldc_w 65383 (0xff67)
		// @3C9F: iastore
		// @3CA0: dup
		// @3CA1: sipush 1960 (0x07A8)
		// @3CA4: ldc_w 65387 (0xff6b)
		// @3CA7: iastore
		// @3CA8: dup
		// @3CA9: sipush 1961 (0x07A9)
		// @3CAC: ldc_w 65390 (0xff6e)
		// @3CAF: iastore
		// @3CB0: dup
		// @3CB1: sipush 1962 (0x07AA)
		// @3CB4: ldc_w 65393 (0xff71)
		// @3CB7: iastore
		// @3CB8: dup
		// @3CB9: sipush 1963 (0x07AB)
		// @3CBC: ldc_w 65397 (0xff75)
		// @3CBF: iastore
		// @3CC0: dup
		// @3CC1: sipush 1964 (0x07AC)
		// @3CC4: ldc_w 65400 (0xff78)
		// @3CC7: iastore
		// @3CC8: dup
		// @3CC9: sipush 1965 (0x07AD)
		// @3CCC: ldc_w 65403 (0xff7b)
		// @3CCF: iastore
		// @3CD0: dup
		// @3CD1: sipush 1966 (0x07AE)
		// @3CD4: ldc_w 65406 (0xff7e)
		// @3CD7: iastore
		// @3CD8: dup
		// @3CD9: sipush 1967 (0x07AF)
		// @3CDC: ldc_w 65410 (0xff82)
		// @3CDF: iastore
		// @3CE0: dup
		// @3CE1: sipush 1968 (0x07B0)
		// @3CE4: ldc_w 65413 (0xff85)
		// @3CE7: iastore
		// @3CE8: dup
		// @3CE9: sipush 1969 (0x07B1)
		// @3CEC: ldc_w 65416 (0xff88)
		// @3CEF: iastore
		// @3CF0: dup
		// @3CF1: sipush 1970 (0x07B2)
		// @3CF4: ldc_w 65419 (0xff8b)
		// @3CF7: iastore
		// @3CF8: dup
		// @3CF9: sipush 1971 (0x07B3)
		// @3CFC: ldc_w 65422 (0xff8e)
		// @3CFF: iastore
		// @3D00: dup
		// @3D01: sipush 1972 (0x07B4)
		// @3D04: ldc_w 65425 (0xff91)
		// @3D07: iastore
		// @3D08: dup
		// @3D09: sipush 1973 (0x07B5)
		// @3D0C: ldc_w 65428 (0xff94)
		// @3D0F: iastore
		// @3D10: dup
		// @3D11: sipush 1974 (0x07B6)
		// @3D14: ldc_w 65430 (0xff96)
		// @3D17: iastore
		// @3D18: dup
		// @3D19: sipush 1975 (0x07B7)
		// @3D1C: ldc_w 65433 (0xff99)
		// @3D1F: iastore
		// @3D20: dup
		// @3D21: sipush 1976 (0x07B8)
		// @3D24: ldc_w 65436 (0xff9c)
		// @3D27: iastore
		// @3D28: dup
		// @3D29: sipush 1977 (0x07B9)
		// @3D2C: ldc_w 65439 (0xff9f)
		// @3D2F: iastore
		// @3D30: dup
		// @3D31: sipush 1978 (0x07BA)
		// @3D34: ldc_w 65442 (0xffa2)
		// @3D37: iastore
		// @3D38: dup
		// @3D39: sipush 1979 (0x07BB)
		// @3D3C: ldc_w 65444 (0xffa4)
		// @3D3F: iastore
		// @3D40: dup
		// @3D41: sipush 1980 (0x07BC)
		// @3D44: ldc_w 65447 (0xffa7)
		// @3D47: iastore
		// @3D48: dup
		// @3D49: sipush 1981 (0x07BD)
		// @3D4C: ldc_w 65449 (0xffa9)
		// @3D4F: iastore
		// @3D50: dup
		// @3D51: sipush 1982 (0x07BE)
		// @3D54: ldc_w 65452 (0xffac)
		// @3D57: iastore
		// @3D58: dup
		// @3D59: sipush 1983 (0x07BF)
		// @3D5C: ldc_w 65455 (0xffaf)
		// @3D5F: iastore
		// @3D60: dup
		// @3D61: sipush 1984 (0x07C0)
		// @3D64: ldc_w 65457 (0xffb1)
		// @3D67: iastore
		// @3D68: dup
		// @3D69: sipush 1985 (0x07C1)
		// @3D6C: ldc_w 65460 (0xffb4)
		// @3D6F: iastore
		// @3D70: dup
		// @3D71: sipush 1986 (0x07C2)
		// @3D74: ldc_w 65462 (0xffb6)
		// @3D77: iastore
		// @3D78: dup
		// @3D79: sipush 1987 (0x07C3)
		// @3D7C: ldc_w 65464 (0xffb8)
		// @3D7F: iastore
		// @3D80: dup
		// @3D81: sipush 1988 (0x07C4)
		// @3D84: ldc_w 65467 (0xffbb)
		// @3D87: iastore
		// @3D88: dup
		// @3D89: sipush 1989 (0x07C5)
		// @3D8C: ldc_w 65469 (0xffbd)
		// @3D8F: iastore
		// @3D90: dup
		// @3D91: sipush 1990 (0x07C6)
		// @3D94: ldc_w 65471 (0xffbf)
		// @3D97: iastore
		// @3D98: dup
		// @3D99: sipush 1991 (0x07C7)
		// @3D9C: ldc_w 65473 (0xffc1)
		// @3D9F: iastore
		// @3DA0: dup
		// @3DA1: sipush 1992 (0x07C8)
		// @3DA4: ldc_w 65476 (0xffc4)
		// @3DA7: iastore
		// @3DA8: dup
		// @3DA9: sipush 1993 (0x07C9)
		// @3DAC: ldc_w 65478 (0xffc6)
		// @3DAF: iastore
		// @3DB0: dup
		// @3DB1: sipush 1994 (0x07CA)
		// @3DB4: ldc_w 65480 (0xffc8)
		// @3DB7: iastore
		// @3DB8: dup
		// @3DB9: sipush 1995 (0x07CB)
		// @3DBC: ldc_w 65482 (0xffca)
		// @3DBF: iastore
		// @3DC0: dup
		// @3DC1: sipush 1996 (0x07CC)
		// @3DC4: ldc_w 65484 (0xffcc)
		// @3DC7: iastore
		// @3DC8: dup
		// @3DC9: sipush 1997 (0x07CD)
		// @3DCC: ldc_w 65486 (0xffce)
		// @3DCF: iastore
		// @3DD0: dup
		// @3DD1: sipush 1998 (0x07CE)
		// @3DD4: ldc_w 65488 (0xffd0)
		// @3DD7: iastore
		// @3DD8: dup
		// @3DD9: sipush 1999 (0x07CF)
		// @3DDC: ldc_w 65490 (0xffd2)
		// @3DDF: iastore
		// @3DE0: dup
		// @3DE1: sipush 2000 (0x07D0)
		// @3DE4: ldc_w 65492 (0xffd4)
		// @3DE7: iastore
		// @3DE8: dup
		// @3DE9: sipush 2001 (0x07D1)
		// @3DEC: ldc_w 65493 (0xffd5)
		// @3DEF: iastore
		// @3DF0: dup
		// @3DF1: sipush 2002 (0x07D2)
		// @3DF4: ldc_w 65495 (0xffd7)
		// @3DF7: iastore
		// @3DF8: dup
		// @3DF9: sipush 2003 (0x07D3)
		// @3DFC: ldc_w 65497 (0xffd9)
		// @3DFF: iastore
		// @3E00: dup
		// @3E01: sipush 2004 (0x07D4)
		// @3E04: ldc_w 65499 (0xffdb)
		// @3E07: iastore
		// @3E08: dup
		// @3E09: sipush 2005 (0x07D5)
		// @3E0C: ldc_w 65500 (0xffdc)
		// @3E0F: iastore
		// @3E10: dup
		// @3E11: sipush 2006 (0x07D6)
		// @3E14: ldc_w 65502 (0xffde)
		// @3E17: iastore
		// @3E18: dup
		// @3E19: sipush 2007 (0x07D7)
		// @3E1C: ldc_w 65504 (0xffe0)
		// @3E1F: iastore
		// @3E20: dup
		// @3E21: sipush 2008 (0x07D8)
		// @3E24: ldc_w 65505 (0xffe1)
		// @3E27: iastore
		// @3E28: dup
		// @3E29: sipush 2009 (0x07D9)
		// @3E2C: ldc_w 65507 (0xffe3)
		// @3E2F: iastore
		// @3E30: dup
		// @3E31: sipush 2010 (0x07DA)
		// @3E34: ldc_w 65508 (0xffe4)
		// @3E37: iastore
		// @3E38: dup
		// @3E39: sipush 2011 (0x07DB)
		// @3E3C: ldc_w 65510 (0xffe6)
		// @3E3F: iastore
		// @3E40: dup
		// @3E41: sipush 2012 (0x07DC)
		// @3E44: ldc_w 65511 (0xffe7)
		// @3E47: iastore
		// @3E48: dup
		// @3E49: sipush 2013 (0x07DD)
		// @3E4C: ldc_w 65512 (0xffe8)
		// @3E4F: iastore
		// @3E50: dup
		// @3E51: sipush 2014 (0x07DE)
		// @3E54: ldc_w 65514 (0xffea)
		// @3E57: iastore
		// @3E58: dup
		// @3E59: sipush 2015 (0x07DF)
		// @3E5C: ldc_w 65515 (0xffeb)
		// @3E5F: iastore
		// @3E60: dup
		// @3E61: sipush 2016 (0x07E0)
		// @3E64: ldc_w 65516 (0xffec)
		// @3E67: iastore
		// @3E68: dup
		// @3E69: sipush 2017 (0x07E1)
		// @3E6C: ldc_w 65517 (0xffed)
		// @3E6F: iastore
		// @3E70: dup
		// @3E71: sipush 2018 (0x07E2)
		// @3E74: ldc_w 65519 (0xffef)
		// @3E77: iastore
		// @3E78: dup
		// @3E79: sipush 2019 (0x07E3)
		// @3E7C: ldc_w 65520 (0xfff0)
		// @3E7F: iastore
		// @3E80: dup
		// @3E81: sipush 2020 (0x07E4)
		// @3E84: ldc_w 65521 (0xfff1)
		// @3E87: iastore
		// @3E88: dup
		// @3E89: sipush 2021 (0x07E5)
		// @3E8C: ldc_w 65522 (0xfff2)
		// @3E8F: iastore
		// @3E90: dup
		// @3E91: sipush 2022 (0x07E6)
		// @3E94: ldc_w 65523 (0xfff3)
		// @3E97: iastore
		// @3E98: dup
		// @3E99: sipush 2023 (0x07E7)
		// @3E9C: ldc_w 65524 (0xfff4)
		// @3E9F: iastore
		// @3EA0: dup
		// @3EA1: sipush 2024 (0x07E8)
		// @3EA4: ldc_w 65525 (0xfff5)
		// @3EA7: iastore
		// @3EA8: dup
		// @3EA9: sipush 2025 (0x07E9)
		// @3EAC: ldc_w 65526 (0xfff6)
		// @3EAF: iastore
		// @3EB0: dup
		// @3EB1: sipush 2026 (0x07EA)
		// @3EB4: ldc_w 65527 (0xfff7)
		// @3EB7: iastore
		// @3EB8: dup
		// @3EB9: sipush 2027 (0x07EB)
		// @3EBC: ldc_w 65527 (0xfff7)
		// @3EBF: iastore
		// @3EC0: dup
		// @3EC1: sipush 2028 (0x07EC)
		// @3EC4: ldc_w 65528 (0xfff8)
		// @3EC7: iastore
		// @3EC8: dup
		// @3EC9: sipush 2029 (0x07ED)
		// @3ECC: ldc_w 65529 (0xfff9)
		// @3ECF: iastore
		// @3ED0: dup
		// @3ED1: sipush 2030 (0x07EE)
		// @3ED4: ldc_w 65530 (0xfffa)
		// @3ED7: iastore
		// @3ED8: dup
		// @3ED9: sipush 2031 (0x07EF)
		// @3EDC: ldc_w 65530 (0xfffa)
		// @3EDF: iastore
		// @3EE0: dup
		// @3EE1: sipush 2032 (0x07F0)
		// @3EE4: ldc_w 65531 (0xfffb)
		// @3EE7: iastore
		// @3EE8: dup
		// @3EE9: sipush 2033 (0x07F1)
		// @3EEC: ldc_w 65532 (0xfffc)
		// @3EEF: iastore
		// @3EF0: dup
		// @3EF1: sipush 2034 (0x07F2)
		// @3EF4: ldc_w 65532 (0xfffc)
		// @3EF7: iastore
		// @3EF8: dup
		// @3EF9: sipush 2035 (0x07F3)
		// @3EFC: ldc_w 65533 (0xfffd)
		// @3EFF: iastore
		// @3F00: dup
		// @3F01: sipush 2036 (0x07F4)
		// @3F04: ldc_w 65533 (0xfffd)
		// @3F07: iastore
		// @3F08: dup
		// @3F09: sipush 2037 (0x07F5)
		// @3F0C: ldc_w 65534 (0xfffe)
		// @3F0F: iastore
		// @3F10: dup
		// @3F11: sipush 2038 (0x07F6)
		// @3F14: ldc_w 65534 (0xfffe)
		// @3F17: iastore
		// @3F18: dup
		// @3F19: sipush 2039 (0x07F7)
		// @3F1C: ldc_w 65534 (0xfffe)
		// @3F1F: iastore
		// @3F20: dup
		// @3F21: sipush 2040 (0x07F8)
		// @3F24: ldc_w 65535 (0xffff)
		// @3F27: iastore
		// @3F28: dup
		// @3F29: sipush 2041 (0x07F9)
		// @3F2C: ldc_w 65535 (0xffff)
		// @3F2F: iastore
		// @3F30: dup
		// @3F31: sipush 2042 (0x07FA)
		// @3F34: ldc_w 65535 (0xffff)
		// @3F37: iastore
		// @3F38: dup
		// @3F39: sipush 2043 (0x07FB)
		// @3F3C: ldc_w 65536 (0x10000)
		// @3F3F: iastore
		// @3F40: dup
		// @3F41: sipush 2044 (0x07FC)
		// @3F44: ldc_w 65536 (0x10000)
		// @3F47: iastore
		// @3F48: dup
		// @3F49: sipush 2045 (0x07FD)
		// @3F4C: ldc_w 65536 (0x10000)
		// @3F4F: iastore
		// @3F50: dup
		// @3F51: sipush 2046 (0x07FE)
		// @3F54: ldc_w 65536 (0x10000)
		// @3F57: iastore
		// @3F58: dup
		// @3F59: sipush 2047 (0x07FF)
		// @3F5C: ldc_w 65536 (0x10000)
		// @3F5F: iastore
		// @3F60: dup
		// @3F61: sipush 2048 (0x0800)
		// @3F64: ldc_w 65536 (0x10000)
		// @3F67: iastore
		// @3F68: putstatic int[] game.C_100266_me.field_106653_c
		// @3F6B: iconst_2
		// @3F6C: anewarray java.lang.String[]
		// @3F6F: dup
		// @3F70: iconst_0
		// @3F71: iconst_3
		// @3F72: anewarray java.lang.String
		// @3F75: dup
		// @3F76: iconst_0
		// @3F77: ldc_w "yw\u00041MS}\u001f7\u0004N}\u001dc\u0000Uk\u0005c\u000fE8\u0010c\tE~\u00106\u0001T8\"/\u000cV}]c,Qm\u0018/\u000c\u0000w\u0003c*Ot\u0014.MTwQ3\u0001AaQ*\u0003\u0000z\u00100\u0004C8\u001c,\tE"
		// @3F7A: invokestatic game.C_100266_me.func_106643_z(java.lang.String)char[]
		// @3F7D: invokestatic game.C_100266_me.func_106642_z(char[])java.lang.String
		// @3F80: aastore
		// @3F81: dup
		// @3F82: iconst_1
		// @3F83: ldc_w "yw\u0004c\u0003E}\u0015c\u000c\u0000|\u0014%\u000cUt\u0005c>Ly\u0007&A\u0000Y\u00006\u0004LyQ,\u001f\u0000_\u001e/\u0008M8\u0005,MPt\u0010:MIvQ!\u000cSq\u0012c\u0000O|\u0014"
		// @3F86: invokestatic game.C_100266_me.func_106643_z(java.lang.String)char[]
		// @3F89: invokestatic game.C_100266_me.func_106642_z(char[])java.lang.String
		// @3F8C: aastore
		// @3F8D: dup
		// @3F8E: iconst_2
		// @3F8F: ldc_w "\u001c=A}MN}\u0014'\u001e\u0000yQ'\u0008Fy\u0004/\u0019\u0000K\u001d\"\u001bE4Q\u0002\u001cUq\u001d\"MOjQ\u0004\u0002L}\u001cc\u0019O8\u0001/\u000cY8\u0018-MBy\u0002*\u000e\u0000u\u001e'\u0008"
		// @3F92: invokestatic game.C_100266_me.func_106643_z(java.lang.String)char[]
		// @3F95: invokestatic game.C_100266_me.func_106642_z(char[])java.lang.String
		// @3F98: aastore
		// @3F99: aastore
		// @3F9A: dup
		// @3F9B: iconst_1
		// @3F9C: iconst_3
		// @3F9D: anewarray java.lang.String
		// @3FA0: dup
		// @3FA1: iconst_0
		// @3FA2: ldc_w "yw\u00041MS}\u001f7\u0004N}\u001dc\u0005AkQ7\u0002O8\u0019*\nH8\u0010c\u0019E{\u0019c\u001bAt\u0004&MTwQ \u0002Mh\u00147\u0008\u0000q\u001fc\u001eTy\u001f'\u000cR|Q.\u0002D}"
		// @3FA5: invokestatic game.C_100266_me.func_106643_z(java.lang.String)char[]
		// @3FA8: invokestatic game.C_100266_me.func_106642_z(char[])java.lang.String
		// @3FAB: aastore
		// @3FAC: dup
		// @3FAD: iconst_1
		// @3FAE: ldc_w "yw\u00041MS}\u001f7\u0004N}\u001dc\u0005AkQ7\u0002O8\u0019*\nH8\u0010c\u0019E{\u0019c\u001bAt\u0004&MTwQ \u0002Mh\u00147\u0008\u0000q\u001fc\u001eTy\u001f'\u000cR|Q.\u0002D}"
		// @3FB1: invokestatic game.C_100266_me.func_106643_z(java.lang.String)char[]
		// @3FB4: invokestatic game.C_100266_me.func_106642_z(char[])java.lang.String
		// @3FB7: aastore
		// @3FB8: dup
		// @3FB9: iconst_2
		// @3FBA: ldc_w "\u001c=A}JS8\u0002&\u0003Tq\u001f&\u0001\u0000p\u00100MTw\u001ec\u0005I\u007f\u0019c\u000c\u0000l\u0014 \u0005\u0000n\u0010/\u0018E8\u0005,MCw\u001c3\u0008T}Q*\u0003\u0000k\u0005\"\u0003Dy\u0003'MMw\u0015&"
		// @3FBD: invokestatic game.C_100266_me.func_106643_z(java.lang.String)char[]
		// @3FC0: invokestatic game.C_100266_me.func_106642_z(char[])java.lang.String
		// @3FC3: aastore
		// @3FC4: aastore
		// @3FC5: putstatic java.lang.String[][] game.C_100266_me.field_106654_a
		// @3FC8: ldc_w "Q"
		// @3FCB: putstatic java.lang.String game.C_100266_me.field_106652_b
		// @3FCE: return
	}
	
	private static char[] func_106643_z(String arg0)
	{
		// @00: aload_0
		// @01: invokevirtual java.lang.String.toCharArray()char[]
		// @04: dup
		// @05: arraylength
		// @06: iconst_2
		// @07: if_icmpge @13
		// @0A: dup
		// @0B: iconst_0
		// @0C: dup2
		// @0D: caload
		// @0E: bipush 109 (0x6D)
		// @10: ixor
		// @11: i2c
		// @12: castore
		// @13: areturn
	}
	
	private static String func_106642_z(char[] arg0)
	{
		// @00: aload_0
		// @01: dup
		// @02: arraylength
		// @03: swap
		// @04: iconst_0
		// @05: istore_1
		// @06: goto @4C
		// @09: dup
		// @0A: iload_1
		// @0B: dup2
		// @0C: caload
		// @0D: iload_1
		// @0E: iconst_5
		// @0F: irem
		// @10: tableswitch def: @44, for 0: @30, for 1: @35, for 2: @3A, for 3: @3F
		// @30: bipush 32 (0x20)
		// @32: goto @46
		// @35: bipush 24 (0x18)
		// @37: goto @46
		// @3A: bipush 113 (0x71)
		// @3C: goto @46
		// @3F: bipush 67 (0x43)
		// @41: goto @46
		// @44: bipush 109 (0x6D)
		// @46: ixor
		// @47: i2c
		// @48: castore
		// @49: iinc #1 +1
		// @4C: swap
		// @4D: dup_x1
		// @4E: iload_1
		// @4F: if_icmpgt @09
		// @52: new java.lang.String
		// @55: dup_x1
		// @56: swap
		// @57: invokespecial java.lang.String.<init>(char[])void
		// @5A: invokevirtual java.lang.String.intern()java.lang.String
		// @5D: areturn
	}
}
