package game;

final class C_100281_ng extends C_100336_im
{
	private int field_103457_G;
	private int field_103459_M;
	static String field_103473_R;
	static C_100037_wb[] field_103467_T;
	int field_103454_D;
	static String[] field_103455_E;
	static String field_103456_F;
	static String field_103465_K;
	boolean field_103471_P;
	private C_100037_wb field_103463_I;
	private int field_103460_N;
	private C_100037_wb field_103472_S;
	private int field_103458_L;
	private int field_103470_Q;
	static String field_103461_O;
	static C_100153_be[] field_103462_H;
	private C_100037_wb field_103469_V;
	private int field_103466_U;
	private C_100037_wb[] field_103464_J;
	private static final String[] field_103468_W;
	
	final void func_102524_a(int arg0, int arg1, int arg2, int arg3, byte arg4)
	{
		// @00: bipush 9 (0x09)
		// @02: bipush -11 (0xF5)
		// @04: iload #5
		// @06: isub
		// @07: bipush 48 (0x30)
		// @09: idiv
		// @0A: idiv
		// @0B: istore #6
		// @0D: aload_0
		// @0E: iload_1
		// @0F: iload_2
		// @10: iload_3
		// @11: iload #4
		// @13: bipush 47 (0x2F)
		// @15: invokespecial game.C_100336_im.func_102524_a(int, int, int, int, byte)void
		// @18: aload_0
		// @19: sipush 15852 (0x3DEC)
		// @1C: invokespecial game.C_100281_ng.func_103452_h(int)void
		// @1F: goto @6B
		// @22: astore #6
		// @24: aload #6
		// @26: new java.lang.StringBuilder
		// @29: dup
		// @2A: invokespecial java.lang.StringBuilder.<init>()void
		// @2D: getstatic java.lang.String[] game.C_100281_ng.field_103468_W
		// @30: iconst_0
		// @31: aaload
		// @32: invokevirtual java.lang.StringBuilder.append(java.lang.String)java.lang.StringBuilder
		// @35: iload_1
		// @36: invokevirtual java.lang.StringBuilder.append(int)java.lang.StringBuilder
		// @39: bipush 44 (0x2C)
		// @3B: invokevirtual java.lang.StringBuilder.append(char)java.lang.StringBuilder
		// @3E: iload_2
		// @3F: invokevirtual java.lang.StringBuilder.append(int)java.lang.StringBuilder
		// @42: bipush 44 (0x2C)
		// @44: invokevirtual java.lang.StringBuilder.append(char)java.lang.StringBuilder
		// @47: iload_3
		// @48: invokevirtual java.lang.StringBuilder.append(int)java.lang.StringBuilder
		// @4B: bipush 44 (0x2C)
		// @4D: invokevirtual java.lang.StringBuilder.append(char)java.lang.StringBuilder
		// @50: iload #4
		// @52: invokevirtual java.lang.StringBuilder.append(int)java.lang.StringBuilder
		// @55: bipush 44 (0x2C)
		// @57: invokevirtual java.lang.StringBuilder.append(char)java.lang.StringBuilder
		// @5A: iload #5
		// @5C: invokevirtual java.lang.StringBuilder.append(int)java.lang.StringBuilder
		// @5F: bipush 41 (0x29)
		// @61: invokevirtual java.lang.StringBuilder.append(char)java.lang.StringBuilder
		// @64: invokevirtual java.lang.StringBuilder.toString()java.lang.String
		// @67: invokestatic game.C_100181_cf.func_105695_a(java.lang.Throwable, java.lang.String)game.C_100170_cm
		// @6A: athrow
		// @6B: return
	}
	
	C_100281_ng(int arg0, int arg1, int arg2, int arg3, int arg4, int arg5, int arg6)
	{
		// @00: aload_0
		// @01: iload_1
		// @02: iload_2
		// @03: iload_3
		// @04: iload #4
		// @06: iload #5
		// @08: iload #6
		// @0A: iload #7
		// @0C: iload #6
		// @0E: ldc 16711422 (0xfefefe)
		// @10: iand
		// @11: ldc -2012674591 (0x880905e1)
		// @13: ishr
		// @14: iload #7
		// @16: ldc 16711422 (0xfefefe)
		// @18: iand
		// @19: ldc 707618433 (0x2a2d6681)
		// @1B: ishr
		// @1C: invokespecial game.C_100281_ng.<init>(int, int, int, int, int, int, int, int, int)void
		// @1F: return
	}
	
	final void func_102528_a(int arg0, int arg1, int arg2, byte arg3)
	{
		// @00: iconst_0
		// @01: iload_1
		// @02: if_icmpeq @06
		// @05: return
		// @06: aload_0
		// @07: getfield int game.C_100281_ng.field_102538_m
		// @0A: iload_3
		// @0B: iadd
		// @0C: istore #5
		// @0E: iload_2
		// @0F: aload_0
		// @10: getfield int game.C_100281_ng.field_102541_w
		// @13: iadd
		// @14: istore #6
		// @16: aload_0
		// @17: aload_0
		// @18: getfield game.C_100037_wb[] game.C_100281_ng.field_103464_J
		// @1B: iconst_0
		// @1C: aaload
		// @1D: iload #5
		// @1F: bipush -107 (0x95)
		// @21: iload #6
		// @23: invokespecial game.C_100281_ng.func_103449_a(game.C_100037_wb, int, byte, int)void
		// @26: iload #4
		// @28: bipush -126 (0x82)
		// @2A: if_icmplt @37
		// @2D: aload_0
		// @2E: bipush -42 (0xD6)
		// @30: invokespecial game.C_100281_ng.func_103452_h(int)void
		// @33: goto @37
		// @36: athrow
		// @37: ldc 65536 (0x10000)
		// @39: aload_0
		// @3A: getfield int game.C_100281_ng.field_103454_D
		// @3D: if_icmple @7D
		// @40: bipush 70 (0x46)
		// @42: aload_0
		// @43: getfield int game.C_100281_ng.field_102544_t
		// @46: iload #6
		// @48: iadd
		// @49: iload #6
		// @4B: aload_0
		// @4C: getfield int game.C_100281_ng.field_102537_l
		// @4F: iload #5
		// @51: iadd
		// @52: aload_0
		// @53: getfield int game.C_100281_ng.field_102537_l
		// @56: aload_0
		// @57: getfield int game.C_100281_ng.field_103454_D
		// @5A: imul
		// @5B: ldc 1312944688 (0x4e41f230)
		// @5D: ishr
		// @5E: iload #5
		// @60: iadd
		// @61: invokestatic game.C_100209_qb.func_102687_b(int, int, int, int, int)void
		// @64: aload_0
		// @65: aload_0
		// @66: getfield game.C_100037_wb[] game.C_100281_ng.field_103464_J
		// @69: iconst_1
		// @6A: aaload
		// @6B: iload #5
		// @6D: bipush -117 (0x8B)
		// @6F: iload #6
		// @71: invokespecial game.C_100281_ng.func_103449_a(game.C_100037_wb, int, byte, int)void
		// @74: bipush -77 (0xB3)
		// @76: invokestatic game.C_100200_ba.func_105842_a(byte)void
		// @79: goto @7D
		// @7C: athrow
		// @7D: goto @C0
		// @80: astore #5
		// @82: aload #5
		// @84: new java.lang.StringBuilder
		// @87: dup
		// @88: invokespecial java.lang.StringBuilder.<init>()void
		// @8B: getstatic java.lang.String[] game.C_100281_ng.field_103468_W
		// @8E: bipush 9 (0x09)
		// @90: aaload
		// @91: invokevirtual java.lang.StringBuilder.append(java.lang.String)java.lang.StringBuilder
		// @94: iload_1
		// @95: invokevirtual java.lang.StringBuilder.append(int)java.lang.StringBuilder
		// @98: bipush 44 (0x2C)
		// @9A: invokevirtual java.lang.StringBuilder.append(char)java.lang.StringBuilder
		// @9D: iload_2
		// @9E: invokevirtual java.lang.StringBuilder.append(int)java.lang.StringBuilder
		// @A1: bipush 44 (0x2C)
		// @A3: invokevirtual java.lang.StringBuilder.append(char)java.lang.StringBuilder
		// @A6: iload_3
		// @A7: invokevirtual java.lang.StringBuilder.append(int)java.lang.StringBuilder
		// @AA: bipush 44 (0x2C)
		// @AC: invokevirtual java.lang.StringBuilder.append(char)java.lang.StringBuilder
		// @AF: iload #4
		// @B1: invokevirtual java.lang.StringBuilder.append(int)java.lang.StringBuilder
		// @B4: bipush 41 (0x29)
		// @B6: invokevirtual java.lang.StringBuilder.append(char)java.lang.StringBuilder
		// @B9: invokevirtual java.lang.StringBuilder.toString()java.lang.String
		// @BC: invokestatic game.C_100181_cf.func_105695_a(java.lang.Throwable, java.lang.String)game.C_100170_cm
		// @BF: athrow
		// @C0: return
	}
	
	private final C_100037_wb func_103451_i(int arg0)
	{
		// @00: getstatic int game.SteelSentinels.field_105275_O
		// @03: istore #9
		// @05: iload_1
		// @06: sipush 22550 (0x5816)
		// @09: if_icmpeq @11
		// @0C: aconst_null
		// @0D: checkcast game.C_100037_wb
		// @10: areturn
		// @11: aload_0
		// @12: getfield int game.C_100281_ng.field_102544_t
		// @15: ldc -1236924511 (0xb64607a1)
		// @17: ishr
		// @18: istore_2
		// @19: new game.C_100037_wb
		// @1C: dup
		// @1D: iload_2
		// @1E: aload_0
		// @1F: getfield int game.C_100281_ng.field_102544_t
		// @22: invokespecial game.C_100037_wb.<init>(int, int)void
		// @25: astore_3
		// @26: aload_3
		// @27: bipush -4 (0xFC)
		// @29: invokestatic game.C_100138_bo.func_100398_a(game.C_100037_wb, int)void
		// @2C: iconst_0
		// @2D: istore #4
		// @2F: aload_0
		// @30: getfield int game.C_100281_ng.field_102544_t
		// @33: iconst_m1
		// @34: ixor
		// @35: iload #4
		// @37: iconst_m1
		// @38: ixor
		// @39: if_icmpge @BA
		// @3C: iconst_0
		// @3D: iload #9
		// @3F: ifne @BC
		// @42: istore #5
		// @44: iload #5
		// @46: iconst_m1
		// @47: ixor
		// @48: iload_2
		// @49: iconst_m1
		// @4A: ixor
		// @4B: if_icmple @B2
		// @4E: iload #5
		// @50: i2d
		// @51: iload #5
		// @53: i2d
		// @54: dmul
		// @55: aload_0
		// @56: getfield int game.C_100281_ng.field_102544_t
		// @59: iload #4
		// @5B: isub
		// @5C: iload #4
		// @5E: imul
		// @5F: i2d
		// @60: ddiv
		// @61: dstore #6
		// @63: iconst_1
		// @64: istore #8
		// @66: dconst_1
		// @67: dload #6
		// @69: dcmpl
		// @6A: iload #9
		// @6C: ifne @35
		// @6F: ifgt @75
		// @72: goto @95
		// @75: dconst_1
		// @76: dload #6
		// @78: dsub
		// @79: invokestatic java.lang.Math.sqrt(double)double
		// @7C: dstore #6
		// @7E: dload #6
		// @80: dconst_1
		// @81: dcmpl
		// @82: iflt @8C
		// @85: sipush 255 (0x00FF)
		// @88: goto @93
		// @8B: athrow
		// @8C: dload #6
		// @8E: ldc2_w 255.0
		// @91: dmul
		// @92: d2i
		// @93: istore #8
		// @95: iload #5
		// @97: iload #4
		// @99: iload #8
		// @9B: ldc 751784560 (0x2ccf5270)
		// @9D: ishl
		// @9E: iload #8
		// @A0: iload #8
		// @A2: ldc -748039128 (0xd369d428)
		// @A4: ishl
		// @A5: ior
		// @A6: ior
		// @A7: invokestatic game.C_100196_rb.func_105797_b(int, int, int)void
		// @AA: iinc #5 +1
		// @AD: iload #9
		// @AF: ifeq @44
		// @B2: iinc #4 +1
		// @B5: iload #9
		// @B7: ifeq @2F
		// @BA: bipush -77 (0xB3)
		// @BC: invokestatic game.C_100200_ba.func_105842_a(byte)void
		// @BF: aload_3
		// @C0: areturn
		// @C1: astore_2
		// @C2: aload_2
		// @C3: new java.lang.StringBuilder
		// @C6: dup
		// @C7: invokespecial java.lang.StringBuilder.<init>()void
		// @CA: getstatic java.lang.String[] game.C_100281_ng.field_103468_W
		// @CD: bipush 8 (0x08)
		// @CF: aaload
		// @D0: invokevirtual java.lang.StringBuilder.append(java.lang.String)java.lang.StringBuilder
		// @D3: iload_1
		// @D4: invokevirtual java.lang.StringBuilder.append(int)java.lang.StringBuilder
		// @D7: bipush 41 (0x29)
		// @D9: invokevirtual java.lang.StringBuilder.append(char)java.lang.StringBuilder
		// @DC: invokevirtual java.lang.StringBuilder.toString()java.lang.String
		// @DF: invokestatic game.C_100181_cf.func_105695_a(java.lang.Throwable, java.lang.String)game.C_100170_cm
		// @E2: athrow
	}
	
	final void func_103453_b(int arg0, int arg1, int arg2)
	{
		// @00: aload_0
		// @01: iload_1
		// @02: putfield int game.C_100281_ng.field_103466_U
		// @05: iload_3
		// @06: ldc 16711935 (0xff00ff)
		// @08: if_icmpeq @0C
		// @0B: return
		// @0C: aload_0
		// @0D: ldc 16711422 (0xfefefe)
		// @0F: iload_1
		// @10: iand
		// @11: ldc -2144497791 (0x802d8f81)
		// @13: ishr
		// @14: putfield int game.C_100281_ng.field_103460_N
		// @17: aload_0
		// @18: iload_2
		// @19: putfield int game.C_100281_ng.field_103459_M
		// @1C: aload_0
		// @1D: iload_2
		// @1E: ldc 16711422 (0xfefefe)
		// @20: iand
		// @21: ldc 162462369 (0x9aefaa1)
		// @23: ishr
		// @24: putfield int game.C_100281_ng.field_103458_L
		// @27: aload_0
		// @28: iload_3
		// @29: ldc 16727315 (0xff3d13)
		// @2B: ixor
		// @2C: invokespecial game.C_100281_ng.func_103452_h(int)void
		// @2F: goto @68
		// @32: astore #4
		// @34: aload #4
		// @36: new java.lang.StringBuilder
		// @39: dup
		// @3A: invokespecial java.lang.StringBuilder.<init>()void
		// @3D: getstatic java.lang.String[] game.C_100281_ng.field_103468_W
		// @40: bipush 10 (0x0A)
		// @42: aaload
		// @43: invokevirtual java.lang.StringBuilder.append(java.lang.String)java.lang.StringBuilder
		// @46: iload_1
		// @47: invokevirtual java.lang.StringBuilder.append(int)java.lang.StringBuilder
		// @4A: bipush 44 (0x2C)
		// @4C: invokevirtual java.lang.StringBuilder.append(char)java.lang.StringBuilder
		// @4F: iload_2
		// @50: invokevirtual java.lang.StringBuilder.append(int)java.lang.StringBuilder
		// @53: bipush 44 (0x2C)
		// @55: invokevirtual java.lang.StringBuilder.append(char)java.lang.StringBuilder
		// @58: iload_3
		// @59: invokevirtual java.lang.StringBuilder.append(int)java.lang.StringBuilder
		// @5C: bipush 41 (0x29)
		// @5E: invokevirtual java.lang.StringBuilder.append(char)java.lang.StringBuilder
		// @61: invokevirtual java.lang.StringBuilder.toString()java.lang.String
		// @64: invokestatic game.C_100181_cf.func_105695_a(java.lang.Throwable, java.lang.String)game.C_100170_cm
		// @67: athrow
		// @68: return
	}
	
	static final void func_103450_a(C_100112_r arg0, int arg1, int arg2, int arg3, int arg4, int arg5, int arg6, String arg7)
	{
		// @00: iload_3
		// @01: ldc 16711422 (0xfefefe)
		// @03: if_icmpeq @11
		// @06: aconst_null
		// @07: checkcast java.lang.String
		// @0A: putstatic java.lang.String game.C_100281_ng.field_103465_K
		// @0D: goto @11
		// @10: athrow
		// @11: getstatic game.C_100037_wb[] game.C_100285_nk.field_106786_j
		// @14: astore #8
		// @16: iload_2
		// @17: iload #5
		// @19: iload_3
		// @1A: ldc -16711341 (0xff010153)
		// @1C: ixor
		// @1D: iload_1
		// @1E: aload #8
		// @20: iload #6
		// @22: invokestatic game.C_100157_db.func_103554_a(int, int, int, int, game.C_100037_wb[], int)void
		// @25: aconst_null
		// @26: aload #7
		// @28: if_acmpeq @4C
		// @2B: aload_0
		// @2C: aload #7
		// @2E: iload_2
		// @2F: iload_1
		// @30: iconst_2
		// @31: idiv
		// @32: iadd
		// @33: iload #5
		// @35: iload #6
		// @37: iconst_2
		// @38: idiv
		// @39: ineg
		// @3A: isub
		// @3B: aload_0
		// @3C: getfield int game.C_100112_r.field_101769_u
		// @3F: iconst_2
		// @40: idiv
		// @41: iadd
		// @42: iload #4
		// @44: iconst_m1
		// @45: invokevirtual game.C_100112_r.func_101744_b(java.lang.String, int, int, int, int)void
		// @48: goto @4C
		// @4B: athrow
		// @4C: goto @D8
		// @4F: astore #8
		// @51: aload #8
		// @53: new java.lang.StringBuilder
		// @56: dup
		// @57: invokespecial java.lang.StringBuilder.<init>()void
		// @5A: getstatic java.lang.String[] game.C_100281_ng.field_103468_W
		// @5D: bipush 12 (0x0C)
		// @5F: aaload
		// @60: invokevirtual java.lang.StringBuilder.append(java.lang.String)java.lang.StringBuilder
		// @63: aload_0
		// @64: ifnull @70
		// @67: getstatic java.lang.String[] game.C_100281_ng.field_103468_W
		// @6A: iconst_3
		// @6B: aaload
		// @6C: goto @75
		// @6F: athrow
		// @70: getstatic java.lang.String[] game.C_100281_ng.field_103468_W
		// @73: iconst_1
		// @74: aaload
		// @75: invokevirtual java.lang.StringBuilder.append(java.lang.String)java.lang.StringBuilder
		// @78: bipush 44 (0x2C)
		// @7A: invokevirtual java.lang.StringBuilder.append(char)java.lang.StringBuilder
		// @7D: iload_1
		// @7E: invokevirtual java.lang.StringBuilder.append(int)java.lang.StringBuilder
		// @81: bipush 44 (0x2C)
		// @83: invokevirtual java.lang.StringBuilder.append(char)java.lang.StringBuilder
		// @86: iload_2
		// @87: invokevirtual java.lang.StringBuilder.append(int)java.lang.StringBuilder
		// @8A: bipush 44 (0x2C)
		// @8C: invokevirtual java.lang.StringBuilder.append(char)java.lang.StringBuilder
		// @8F: iload_3
		// @90: invokevirtual java.lang.StringBuilder.append(int)java.lang.StringBuilder
		// @93: bipush 44 (0x2C)
		// @95: invokevirtual java.lang.StringBuilder.append(char)java.lang.StringBuilder
		// @98: iload #4
		// @9A: invokevirtual java.lang.StringBuilder.append(int)java.lang.StringBuilder
		// @9D: bipush 44 (0x2C)
		// @9F: invokevirtual java.lang.StringBuilder.append(char)java.lang.StringBuilder
		// @A2: iload #5
		// @A4: invokevirtual java.lang.StringBuilder.append(int)java.lang.StringBuilder
		// @A7: bipush 44 (0x2C)
		// @A9: invokevirtual java.lang.StringBuilder.append(char)java.lang.StringBuilder
		// @AC: iload #6
		// @AE: invokevirtual java.lang.StringBuilder.append(int)java.lang.StringBuilder
		// @B1: bipush 44 (0x2C)
		// @B3: invokevirtual java.lang.StringBuilder.append(char)java.lang.StringBuilder
		// @B6: aload #7
		// @B8: ifnull @C4
		// @BB: getstatic java.lang.String[] game.C_100281_ng.field_103468_W
		// @BE: iconst_3
		// @BF: aaload
		// @C0: goto @C9
		// @C3: athrow
		// @C4: getstatic java.lang.String[] game.C_100281_ng.field_103468_W
		// @C7: iconst_1
		// @C8: aaload
		// @C9: invokevirtual java.lang.StringBuilder.append(java.lang.String)java.lang.StringBuilder
		// @CC: bipush 41 (0x29)
		// @CE: invokevirtual java.lang.StringBuilder.append(char)java.lang.StringBuilder
		// @D1: invokevirtual java.lang.StringBuilder.toString()java.lang.String
		// @D4: invokestatic game.C_100181_cf.func_105695_a(java.lang.Throwable, java.lang.String)game.C_100170_cm
		// @D7: athrow
		// @D8: return
	}
	
	private final void func_103452_h(int arg0)
	{
		// @00: iload_1
		// @01: sipush 15852 (0x3DEC)
		// @04: if_icmpeq @5F
		// @07: aconst_null
		// @08: checkcast game.C_100098_h
		// @0B: bipush -65 (0xBF)
		// @0D: bipush -12 (0xF4)
		// @0F: aconst_null
		// @10: checkcast java.lang.String[]
		// @13: aconst_null
		// @14: checkcast game.C_100098_h
		// @17: aconst_null
		// @18: checkcast game.C_100153_be[]
		// @1B: aconst_null
		// @1C: checkcast java.lang.String[]
		// @1F: aconst_null
		// @20: checkcast java.lang.String[][]
		// @23: checkcast java.lang.String[][]
		// @26: aconst_null
		// @27: checkcast game.C_100037_wb[][]
		// @2A: checkcast game.C_100037_wb[][]
		// @2D: aconst_null
		// @2E: checkcast game.C_100037_wb[][]
		// @31: checkcast game.C_100037_wb[][]
		// @34: aconst_null
		// @35: checkcast int[]
		// @38: bipush -80 (0xB0)
		// @3A: aconst_null
		// @3B: checkcast java.lang.String[][]
		// @3E: checkcast java.lang.String[][]
		// @41: iconst_0
		// @42: aconst_null
		// @43: checkcast java.lang.String[]
		// @46: aconst_null
		// @47: checkcast game.C_100098_h
		// @4A: aconst_null
		// @4B: checkcast int[]
		// @4E: aconst_null
		// @4F: checkcast byte[]
		// @52: bipush -8 (0xF8)
		// @54: aconst_null
		// @55: checkcast byte[]
		// @58: invokestatic game.C_100281_ng.func_103444_a(game.C_100098_h, int, int, java.lang.String[], game.C_100098_h, game.C_100153_be[], java.lang.String[], java.lang.String[][], game.C_100037_wb[][], game.C_100037_wb[][], int[], int, java.lang.String[][], boolean, java.lang.String[], game.C_100098_h, int[], byte[], int, byte[])void
		// @5B: goto @5F
		// @5E: athrow
		// @5F: aload_0
		// @60: iconst_2
		// @61: anewarray game.C_100037_wb
		// @64: dup
		// @65: iconst_0
		// @66: aload_0
		// @67: aload_0
		// @68: getfield int game.C_100281_ng.field_103466_U
		// @6B: ldc -2144497791 (0x802d8f81)
		// @6D: aload_0
		// @6E: getfield int game.C_100281_ng.field_103459_M
		// @71: invokespecial game.C_100281_ng.func_103445_c(int, int, int)game.C_100037_wb
		// @74: aastore
		// @75: dup
		// @76: iconst_1
		// @77: aload_0
		// @78: aload_0
		// @79: getfield int game.C_100281_ng.field_103460_N
		// @7C: ldc -2144497791 (0x802d8f81)
		// @7E: aload_0
		// @7F: getfield int game.C_100281_ng.field_103458_L
		// @82: invokespecial game.C_100281_ng.func_103445_c(int, int, int)game.C_100037_wb
		// @85: aastore
		// @86: putfield game.C_100037_wb[] game.C_100281_ng.field_103464_J
		// @89: aload_0
		// @8A: aload_0
		// @8B: sipush 22550 (0x5816)
		// @8E: invokespecial game.C_100281_ng.func_103451_i(int)game.C_100037_wb
		// @91: putfield game.C_100037_wb game.C_100281_ng.field_103463_I
		// @94: aload_0
		// @95: aload_0
		// @96: getfield game.C_100037_wb game.C_100281_ng.field_103463_I
		// @99: invokevirtual game.C_100037_wb.func_102371_f()game.C_100037_wb
		// @9C: putfield game.C_100037_wb game.C_100281_ng.field_103469_V
		// @9F: aload_0
		// @A0: new game.C_100037_wb
		// @A3: dup
		// @A4: aload_0
		// @A5: getfield int game.C_100281_ng.field_102544_t
		// @A8: ldc -402727263 (0xe7fedea1)
		// @AA: ishr
		// @AB: aload_0
		// @AC: getfield int game.C_100281_ng.field_102544_t
		// @AF: invokespecial game.C_100037_wb.<init>(int, int)void
		// @B2: putfield game.C_100037_wb game.C_100281_ng.field_103472_S
		// @B5: goto @DA
		// @B8: astore_2
		// @B9: aload_2
		// @BA: new java.lang.StringBuilder
		// @BD: dup
		// @BE: invokespecial java.lang.StringBuilder.<init>()void
		// @C1: getstatic java.lang.String[] game.C_100281_ng.field_103468_W
		// @C4: bipush 6 (0x06)
		// @C6: aaload
		// @C7: invokevirtual java.lang.StringBuilder.append(java.lang.String)java.lang.StringBuilder
		// @CA: iload_1
		// @CB: invokevirtual java.lang.StringBuilder.append(int)java.lang.StringBuilder
		// @CE: bipush 41 (0x29)
		// @D0: invokevirtual java.lang.StringBuilder.append(char)java.lang.StringBuilder
		// @D3: invokevirtual java.lang.StringBuilder.toString()java.lang.String
		// @D6: invokestatic game.C_100181_cf.func_105695_a(java.lang.Throwable, java.lang.String)game.C_100170_cm
		// @D9: athrow
		// @DA: return
	}
	
	private final void func_103449_a(C_100037_wb arg0, int arg1, byte arg2, int arg3)
	{
		// @000: getstatic int game.SteelSentinels.field_105275_O
		// @003: istore #8
		// @005: aload_0
		// @006: getfield int game.C_100281_ng.field_102537_l
		// @009: iload_2
		// @00A: iadd
		// @00B: istore #5
		// @00D: iload_3
		// @00E: bipush -75 (0xB5)
		// @010: if_icmplt @01D
		// @013: aload_0
		// @014: bipush -79 (0xB1)
		// @016: putfield int game.C_100281_ng.field_103458_L
		// @019: goto @01D
		// @01C: athrow
		// @01D: bipush 88 (0x58)
		// @01F: aload_0
		// @020: getfield int game.C_100281_ng.field_102544_t
		// @023: iload #4
		// @025: iadd
		// @026: iload #4
		// @028: aload_0
		// @029: getfield game.C_100037_wb game.C_100281_ng.field_103463_I
		// @02C: getfield int game.C_100037_wb.field_102339_s
		// @02F: ineg
		// @030: iload #5
		// @032: iadd
		// @033: aload_0
		// @034: getfield game.C_100037_wb game.C_100281_ng.field_103463_I
		// @037: getfield int game.C_100037_wb.field_102339_s
		// @03A: iload_2
		// @03B: iadd
		// @03C: invokestatic game.C_100209_qb.func_102687_b(int, int, int, int, int)void
		// @03F: iload_2
		// @040: aload_0
		// @041: getfield int game.C_100281_ng.field_103457_G
		// @044: isub
		// @045: istore #6
		// @047: iload #5
		// @049: iconst_m1
		// @04A: ixor
		// @04B: iload #6
		// @04D: iconst_m1
		// @04E: ixor
		// @04F: if_icmpge @071
		// @052: aload_1
		// @053: iload #6
		// @055: iload #4
		// @057: invokevirtual game.C_100037_wb.func_102353_h(int, int)void
		// @05A: iload #6
		// @05C: aload_1
		// @05D: getfield int game.C_100037_wb.field_102339_s
		// @060: iadd
		// @061: istore #6
		// @063: iload #8
		// @065: ifne @076
		// @068: iload #8
		// @06A: ifeq @047
		// @06D: goto @071
		// @070: athrow
		// @071: bipush -77 (0xB3)
		// @073: invokestatic game.C_100200_ba.func_105842_a(byte)void
		// @076: getstatic int game.C_100196_rb.field_105827_i
		// @079: iconst_m1
		// @07A: ixor
		// @07B: iload_2
		// @07C: aload_0
		// @07D: getfield game.C_100037_wb game.C_100281_ng.field_103463_I
		// @080: getfield int game.C_100037_wb.field_102339_s
		// @083: iadd
		// @084: iconst_m1
		// @085: ixor
		// @086: if_icmplt @0C8
		// @089: aload_0
		// @08A: getfield game.C_100037_wb game.C_100281_ng.field_103472_S
		// @08D: bipush -4 (0xFC)
		// @08F: invokestatic game.C_100138_bo.func_100398_a(game.C_100037_wb, int)void
		// @092: aload_1
		// @093: aload_0
		// @094: getfield int game.C_100281_ng.field_103457_G
		// @097: ineg
		// @098: iconst_0
		// @099: invokevirtual game.C_100037_wb.func_102353_h(int, int)void
		// @09C: aload_1
		// @09D: aload_0
		// @09E: getfield int game.C_100281_ng.field_103470_Q
		// @0A1: iconst_2
		// @0A2: imul
		// @0A3: aload_0
		// @0A4: getfield int game.C_100281_ng.field_103457_G
		// @0A7: isub
		// @0A8: iconst_0
		// @0A9: invokevirtual game.C_100037_wb.func_102353_h(int, int)void
		// @0AC: aload_0
		// @0AD: getfield game.C_100037_wb game.C_100281_ng.field_103469_V
		// @0B0: iconst_0
		// @0B1: iconst_0
		// @0B2: invokevirtual game.C_100037_wb.func_102368_d(int, int)void
		// @0B5: bipush -77 (0xB3)
		// @0B7: invokestatic game.C_100200_ba.func_105842_a(byte)void
		// @0BA: aload_0
		// @0BB: getfield game.C_100037_wb game.C_100281_ng.field_103472_S
		// @0BE: iload_2
		// @0BF: iload #4
		// @0C1: invokevirtual game.C_100037_wb.func_102353_h(int, int)void
		// @0C4: goto @0C8
		// @0C7: athrow
		// @0C8: getstatic int game.C_100196_rb.field_105820_b
		// @0CB: aload_0
		// @0CC: getfield game.C_100037_wb game.C_100281_ng.field_103463_I
		// @0CF: getfield int game.C_100037_wb.field_102339_s
		// @0D2: ineg
		// @0D3: iload #5
		// @0D5: iadd
		// @0D6: if_icmplt @151
		// @0D9: aload_0
		// @0DA: getfield game.C_100037_wb game.C_100281_ng.field_103472_S
		// @0DD: bipush -4 (0xFC)
		// @0DF: invokestatic game.C_100138_bo.func_100398_a(game.C_100037_wb, int)void
		// @0E2: aload_0
		// @0E3: getfield int game.C_100281_ng.field_102537_l
		// @0E6: aload_0
		// @0E7: getfield game.C_100037_wb game.C_100281_ng.field_103463_I
		// @0EA: getfield int game.C_100037_wb.field_102339_s
		// @0ED: isub
		// @0EE: aload_0
		// @0EF: getfield int game.C_100281_ng.field_103457_G
		// @0F2: iadd
		// @0F3: istore #7
		// @0F5: iconst_2
		// @0F6: aload_0
		// @0F7: getfield int game.C_100281_ng.field_103470_Q
		// @0FA: imul
		// @0FB: iload #7
		// @0FD: if_icmpge @119
		// @100: iload #7
		// @102: iconst_2
		// @103: aload_0
		// @104: getfield int game.C_100281_ng.field_103470_Q
		// @107: imul
		// @108: isub
		// @109: istore #7
		// @10B: iload #8
		// @10D: ifne @13D
		// @110: iload #8
		// @112: ifeq @0F5
		// @115: goto @119
		// @118: athrow
		// @119: aload_1
		// @11A: iload #7
		// @11C: ineg
		// @11D: iconst_0
		// @11E: invokevirtual game.C_100037_wb.func_102353_h(int, int)void
		// @121: aload_1
		// @122: iconst_2
		// @123: aload_0
		// @124: getfield int game.C_100281_ng.field_103470_Q
		// @127: imul
		// @128: iload #7
		// @12A: isub
		// @12B: iconst_0
		// @12C: invokevirtual game.C_100037_wb.func_102353_h(int, int)void
		// @12F: aload_0
		// @130: getfield game.C_100037_wb game.C_100281_ng.field_103463_I
		// @133: iconst_0
		// @134: iconst_0
		// @135: invokevirtual game.C_100037_wb.func_102368_d(int, int)void
		// @138: bipush -77 (0xB3)
		// @13A: invokestatic game.C_100200_ba.func_105842_a(byte)void
		// @13D: aload_0
		// @13E: getfield game.C_100037_wb game.C_100281_ng.field_103472_S
		// @141: iload #5
		// @143: aload_0
		// @144: getfield game.C_100037_wb game.C_100281_ng.field_103463_I
		// @147: getfield int game.C_100037_wb.field_102339_s
		// @14A: ineg
		// @14B: iadd
		// @14C: iload #4
		// @14E: invokevirtual game.C_100037_wb.func_102353_h(int, int)void
		// @151: goto @1A4
		// @154: astore #5
		// @156: aload #5
		// @158: new java.lang.StringBuilder
		// @15B: dup
		// @15C: invokespecial java.lang.StringBuilder.<init>()void
		// @15F: getstatic java.lang.String[] game.C_100281_ng.field_103468_W
		// @162: iconst_4
		// @163: aaload
		// @164: invokevirtual java.lang.StringBuilder.append(java.lang.String)java.lang.StringBuilder
		// @167: aload_1
		// @168: ifnull @174
		// @16B: getstatic java.lang.String[] game.C_100281_ng.field_103468_W
		// @16E: iconst_3
		// @16F: aaload
		// @170: goto @179
		// @173: athrow
		// @174: getstatic java.lang.String[] game.C_100281_ng.field_103468_W
		// @177: iconst_1
		// @178: aaload
		// @179: invokevirtual java.lang.StringBuilder.append(java.lang.String)java.lang.StringBuilder
		// @17C: bipush 44 (0x2C)
		// @17E: invokevirtual java.lang.StringBuilder.append(char)java.lang.StringBuilder
		// @181: iload_2
		// @182: invokevirtual java.lang.StringBuilder.append(int)java.lang.StringBuilder
		// @185: bipush 44 (0x2C)
		// @187: invokevirtual java.lang.StringBuilder.append(char)java.lang.StringBuilder
		// @18A: iload_3
		// @18B: invokevirtual java.lang.StringBuilder.append(int)java.lang.StringBuilder
		// @18E: bipush 44 (0x2C)
		// @190: invokevirtual java.lang.StringBuilder.append(char)java.lang.StringBuilder
		// @193: iload #4
		// @195: invokevirtual java.lang.StringBuilder.append(int)java.lang.StringBuilder
		// @198: bipush 41 (0x29)
		// @19A: invokevirtual java.lang.StringBuilder.append(char)java.lang.StringBuilder
		// @19D: invokevirtual java.lang.StringBuilder.toString()java.lang.String
		// @1A0: invokestatic game.C_100181_cf.func_105695_a(java.lang.Throwable, java.lang.String)game.C_100170_cm
		// @1A3: athrow
		// @1A4: return
	}
	
	private final C_100037_wb func_103445_c(int arg0, int arg1, int arg2)
	{
		// @000: getstatic int game.SteelSentinels.field_105275_O
		// @003: istore #13
		// @005: iload_2
		// @006: ldc -2144497791 (0x802d8f81)
		// @008: if_icmpeq @01D
		// @00B: aload_0
		// @00C: bipush -70 (0xBA)
		// @00E: bipush 6 (0x06)
		// @010: bipush -38 (0xDA)
		// @012: bipush 72 (0x48)
		// @014: bipush -24 (0xE8)
		// @016: invokevirtual game.C_100281_ng.func_102524_a(int, int, int, int, byte)void
		// @019: goto @01D
		// @01C: athrow
		// @01D: new game.C_100037_wb
		// @020: dup
		// @021: iconst_2
		// @022: aload_0
		// @023: getfield int game.C_100281_ng.field_103470_Q
		// @026: imul
		// @027: aload_0
		// @028: getfield int game.C_100281_ng.field_102544_t
		// @02B: invokespecial game.C_100037_wb.<init>(int, int)void
		// @02E: astore #4
		// @030: aload #4
		// @032: bipush -4 (0xFC)
		// @034: invokestatic game.C_100138_bo.func_100398_a(game.C_100037_wb, int)void
		// @037: aload_0
		// @038: getfield int game.C_100281_ng.field_102544_t
		// @03B: ldc -2114985183 (0x81efe321)
		// @03D: ishr
		// @03E: istore #5
		// @040: iconst_0
		// @041: istore #6
		// @043: aload_0
		// @044: getfield int game.C_100281_ng.field_102544_t
		// @047: iconst_m1
		// @048: ixor
		// @049: iload #6
		// @04B: iconst_m1
		// @04C: ixor
		// @04D: if_icmpge @14C
		// @050: aload_0
		// @051: getfield int game.C_100281_ng.field_103470_Q
		// @054: iconst_2
		// @055: imul
		// @056: iconst_1
		// @057: isub
		// @058: iload #6
		// @05A: ldc 1533518337 (0x5b67a201)
		// @05C: ishr
		// @05D: imul
		// @05E: iconst_2
		// @05F: aload_0
		// @060: getfield int game.C_100281_ng.field_103470_Q
		// @063: imul
		// @064: irem
		// @065: istore #7
		// @067: iload_3
		// @068: ldc 16711935 (0xff00ff)
		// @06A: iand
		// @06B: istore #8
		// @06D: ldc 65280 (0xff00)
		// @06F: iload_3
		// @070: iand
		// @071: istore #9
		// @073: iload #5
		// @075: ineg
		// @076: iload #6
		// @078: iadd
		// @079: istore #10
		// @07B: sipush 128 (0x0080)
		// @07E: ldc2_w 128.0
		// @081: iload #5
		// @083: iload #5
		// @085: imul
		// @086: iload #10
		// @088: iload #10
		// @08A: imul
		// @08B: isub
		// @08C: i2d
		// @08D: invokestatic java.lang.Math.sqrt(double)double
		// @090: iload #5
		// @092: i2d
		// @093: ddiv
		// @094: dmul
		// @095: d2i
		// @096: ineg
		// @097: isub
		// @098: istore #11
		// @09A: sipush 256 (0x0100)
		// @09D: iload #13
		// @09F: ifne @14E
		// @0A2: iload #11
		// @0A4: if_icmple @0C3
		// @0A7: goto @0AB
		// @0AA: athrow
		// @0AB: ldc 16711680 (0xff0000)
		// @0AD: iload #11
		// @0AF: iload #9
		// @0B1: imul
		// @0B2: iand
		// @0B3: iload #11
		// @0B5: iload #8
		// @0B7: imul
		// @0B8: ldc -16711936 (0xff00ff00)
		// @0BA: iand
		// @0BB: ior
		// @0BC: ldc -53099160 (0xfcd5c568)
		// @0BE: iushr
		// @0BF: goto @0C8
		// @0C2: athrow
		// @0C3: iload #8
		// @0C5: iload #9
		// @0C7: ior
		// @0C8: istore #12
		// @0CA: iload #7
		// @0CC: iload #6
		// @0CE: aload_0
		// @0CF: getfield int game.C_100281_ng.field_103470_Q
		// @0D2: iload #12
		// @0D4: invokestatic game.C_100196_rb.func_105807_g(int, int, int, int)void
		// @0D7: aload_0
		// @0D8: getfield int game.C_100281_ng.field_103470_Q
		// @0DB: iconst_2
		// @0DC: imul
		// @0DD: ineg
		// @0DE: iload #7
		// @0E0: iadd
		// @0E1: iload #6
		// @0E3: aload_0
		// @0E4: getfield int game.C_100281_ng.field_103470_Q
		// @0E7: iload #12
		// @0E9: invokestatic game.C_100196_rb.func_105807_g(int, int, int, int)void
		// @0EC: iload_1
		// @0ED: ldc 65280 (0xff00)
		// @0EF: iand
		// @0F0: istore #9
		// @0F2: ldc 16711935 (0xff00ff)
		// @0F4: iload_1
		// @0F5: iand
		// @0F6: istore #8
		// @0F8: iload #11
		// @0FA: sipush 256 (0x0100)
		// @0FD: if_icmplt @109
		// @100: iload #8
		// @102: iload #9
		// @104: ior
		// @105: goto @11D
		// @108: athrow
		// @109: ldc 16711680 (0xff0000)
		// @10B: iload #11
		// @10D: iload #9
		// @10F: imul
		// @110: iand
		// @111: iload #11
		// @113: iload #8
		// @115: imul
		// @116: ldc -16711936 (0xff00ff00)
		// @118: iand
		// @119: ior
		// @11A: ldc 1915440232 (0x722b4c68)
		// @11C: iushr
		// @11D: istore #12
		// @11F: iload #7
		// @121: aload_0
		// @122: getfield int game.C_100281_ng.field_103470_Q
		// @125: iadd
		// @126: iload #6
		// @128: aload_0
		// @129: getfield int game.C_100281_ng.field_103470_Q
		// @12C: iload #12
		// @12E: invokestatic game.C_100196_rb.func_105807_g(int, int, int, int)void
		// @131: aload_0
		// @132: getfield int game.C_100281_ng.field_103470_Q
		// @135: ineg
		// @136: iload #7
		// @138: iadd
		// @139: iload #6
		// @13B: aload_0
		// @13C: getfield int game.C_100281_ng.field_103470_Q
		// @13F: iload #12
		// @141: invokestatic game.C_100196_rb.func_105807_g(int, int, int, int)void
		// @144: iinc #6 +1
		// @147: iload #13
		// @149: ifeq @043
		// @14C: bipush -77 (0xB3)
		// @14E: invokestatic game.C_100200_ba.func_105842_a(byte)void
		// @151: aload #4
		// @153: areturn
		// @154: astore #4
		// @156: aload #4
		// @158: new java.lang.StringBuilder
		// @15B: dup
		// @15C: invokespecial java.lang.StringBuilder.<init>()void
		// @15F: getstatic java.lang.String[] game.C_100281_ng.field_103468_W
		// @162: bipush 13 (0x0D)
		// @164: aaload
		// @165: invokevirtual java.lang.StringBuilder.append(java.lang.String)java.lang.StringBuilder
		// @168: iload_1
		// @169: invokevirtual java.lang.StringBuilder.append(int)java.lang.StringBuilder
		// @16C: bipush 44 (0x2C)
		// @16E: invokevirtual java.lang.StringBuilder.append(char)java.lang.StringBuilder
		// @171: iload_2
		// @172: invokevirtual java.lang.StringBuilder.append(int)java.lang.StringBuilder
		// @175: bipush 44 (0x2C)
		// @177: invokevirtual java.lang.StringBuilder.append(char)java.lang.StringBuilder
		// @17A: iload_3
		// @17B: invokevirtual java.lang.StringBuilder.append(int)java.lang.StringBuilder
		// @17E: bipush 41 (0x29)
		// @180: invokevirtual java.lang.StringBuilder.append(char)java.lang.StringBuilder
		// @183: invokevirtual java.lang.StringBuilder.toString()java.lang.String
		// @186: invokestatic game.C_100181_cf.func_105695_a(java.lang.Throwable, java.lang.String)game.C_100170_cm
		// @189: athrow
	}
	
	final void func_102513_a(C_100336_im arg0, int arg1, int arg2, int arg3)
	{
		// @00: aload_0
		// @01: getfield boolean game.C_100281_ng.field_103471_P
		// @04: ifne @0B
		// @07: goto @39
		// @0A: athrow
		// @0B: aload_0
		// @0C: dup
		// @0D: getfield int game.C_100281_ng.field_103457_G
		// @10: iconst_1
		// @11: iadd
		// @12: putfield int game.C_100281_ng.field_103457_G
		// @15: aload_0
		// @16: getfield int game.C_100281_ng.field_103470_Q
		// @19: iconst_2
		// @1A: imul
		// @1B: iconst_m1
		// @1C: ixor
		// @1D: aload_0
		// @1E: getfield int game.C_100281_ng.field_103457_G
		// @21: iconst_m1
		// @22: ixor
		// @23: if_icmpgt @2A
		// @26: goto @39
		// @29: athrow
		// @2A: aload_0
		// @2B: dup
		// @2C: getfield int game.C_100281_ng.field_103457_G
		// @2F: iconst_2
		// @30: aload_0
		// @31: getfield int game.C_100281_ng.field_103470_Q
		// @34: imul
		// @35: isub
		// @36: putfield int game.C_100281_ng.field_103457_G
		// @39: iload_3
		// @3A: iconst_2
		// @3B: if_icmpeq @48
		// @3E: aload_0
		// @3F: bipush 54 (0x36)
		// @41: putfield int game.C_100281_ng.field_103458_L
		// @44: goto @48
		// @47: athrow
		// @48: goto @9B
		// @4B: astore #5
		// @4D: aload #5
		// @4F: new java.lang.StringBuilder
		// @52: dup
		// @53: invokespecial java.lang.StringBuilder.<init>()void
		// @56: getstatic java.lang.String[] game.C_100281_ng.field_103468_W
		// @59: iconst_2
		// @5A: aaload
		// @5B: invokevirtual java.lang.StringBuilder.append(java.lang.String)java.lang.StringBuilder
		// @5E: aload_1
		// @5F: ifnull @6B
		// @62: getstatic java.lang.String[] game.C_100281_ng.field_103468_W
		// @65: iconst_3
		// @66: aaload
		// @67: goto @70
		// @6A: athrow
		// @6B: getstatic java.lang.String[] game.C_100281_ng.field_103468_W
		// @6E: iconst_1
		// @6F: aaload
		// @70: invokevirtual java.lang.StringBuilder.append(java.lang.String)java.lang.StringBuilder
		// @73: bipush 44 (0x2C)
		// @75: invokevirtual java.lang.StringBuilder.append(char)java.lang.StringBuilder
		// @78: iload_2
		// @79: invokevirtual java.lang.StringBuilder.append(int)java.lang.StringBuilder
		// @7C: bipush 44 (0x2C)
		// @7E: invokevirtual java.lang.StringBuilder.append(char)java.lang.StringBuilder
		// @81: iload_3
		// @82: invokevirtual java.lang.StringBuilder.append(int)java.lang.StringBuilder
		// @85: bipush 44 (0x2C)
		// @87: invokevirtual java.lang.StringBuilder.append(char)java.lang.StringBuilder
		// @8A: iload #4
		// @8C: invokevirtual java.lang.StringBuilder.append(int)java.lang.StringBuilder
		// @8F: bipush 41 (0x29)
		// @91: invokevirtual java.lang.StringBuilder.append(char)java.lang.StringBuilder
		// @94: invokevirtual java.lang.StringBuilder.toString()java.lang.String
		// @97: invokestatic game.C_100181_cf.func_105695_a(java.lang.Throwable, java.lang.String)game.C_100170_cm
		// @9A: athrow
		// @9B: return
	}
	
	static final void func_103444_a(C_100098_h arg0, int arg1, int arg2, String[] arg3, C_100098_h arg4, C_100153_be[] arg5, String[] arg6, String[][] arg7, C_100037_wb[][] arg8, C_100037_wb[][] arg9, int[] arg10, int arg11, String[][] arg12, boolean arg13, String[] arg14, C_100098_h arg15, int[] arg16, byte[] arg17, int arg18, byte[] arg19)
	{
		// @000: iload_2
		// @001: sipush -24373 (0xA0CB)
		// @004: if_icmpeq @008
		// @007: return
		// @008: bipush -110 (0x92)
		// @00A: aload #5
		// @00C: aload_0
		// @00D: aload #10
		// @00F: aload #15
		// @011: invokestatic game.C_100205_qf.func_103675_a(byte, game.C_100153_be[], game.C_100098_h, int[], game.C_100098_h)void
		// @014: aload #15
		// @016: bipush 121 (0x79)
		// @018: invokestatic game.C_100149_bi.func_105146_a(game.C_100098_h, int)void
		// @01B: aload #15
		// @01D: iload #18
		// @01F: aload #12
		// @021: aload #16
		// @023: iload_1
		// @024: aload #8
		// @026: aload #17
		// @028: aload #19
		// @02A: aload #9
		// @02C: aload #14
		// @02E: bipush -80 (0xB0)
		// @030: aload_3
		// @031: aload #6
		// @033: iload #11
		// @035: aload #7
		// @037: invokestatic game.C_100090_l.func_104492_a(game.C_100098_h, int, java.lang.String[][], int[], int, game.C_100037_wb[][], byte[], byte[], game.C_100037_wb[][], java.lang.String[], byte, java.lang.String[], java.lang.String[], int, java.lang.String[][])void
		// @03A: iload #13
		// @03C: aload #4
		// @03E: sipush 18958 (0x4A0E)
		// @041: aload #15
		// @043: invokestatic game.C_100137_bn.func_105029_a(boolean, game.C_100098_h, int, game.C_100098_h)void
		// @046: bipush 17 (0x11)
		// @048: invokestatic game.C_100161_sd.func_105422_a(byte)void
		// @04B: bipush 19 (0x13)
		// @04D: invokestatic game.C_100263_mb.func_106500_a(byte)void
		// @050: iload_2
		// @051: sipush 24405 (0x5F55)
		// @054: ixor
		// @055: invokestatic game.C_100330_ig.func_107277_a(int)void
		// @058: goto @239
		// @05B: astore #20
		// @05D: aload #20
		// @05F: new java.lang.StringBuilder
		// @062: dup
		// @063: invokespecial java.lang.StringBuilder.<init>()void
		// @066: getstatic java.lang.String[] game.C_100281_ng.field_103468_W
		// @069: bipush 11 (0x0B)
		// @06B: aaload
		// @06C: invokevirtual java.lang.StringBuilder.append(java.lang.String)java.lang.StringBuilder
		// @06F: aload_0
		// @070: ifnull @07C
		// @073: getstatic java.lang.String[] game.C_100281_ng.field_103468_W
		// @076: iconst_3
		// @077: aaload
		// @078: goto @081
		// @07B: athrow
		// @07C: getstatic java.lang.String[] game.C_100281_ng.field_103468_W
		// @07F: iconst_1
		// @080: aaload
		// @081: invokevirtual java.lang.StringBuilder.append(java.lang.String)java.lang.StringBuilder
		// @084: bipush 44 (0x2C)
		// @086: invokevirtual java.lang.StringBuilder.append(char)java.lang.StringBuilder
		// @089: iload_1
		// @08A: invokevirtual java.lang.StringBuilder.append(int)java.lang.StringBuilder
		// @08D: bipush 44 (0x2C)
		// @08F: invokevirtual java.lang.StringBuilder.append(char)java.lang.StringBuilder
		// @092: iload_2
		// @093: invokevirtual java.lang.StringBuilder.append(int)java.lang.StringBuilder
		// @096: bipush 44 (0x2C)
		// @098: invokevirtual java.lang.StringBuilder.append(char)java.lang.StringBuilder
		// @09B: aload_3
		// @09C: ifnull @0A8
		// @09F: getstatic java.lang.String[] game.C_100281_ng.field_103468_W
		// @0A2: iconst_3
		// @0A3: aaload
		// @0A4: goto @0AD
		// @0A7: athrow
		// @0A8: getstatic java.lang.String[] game.C_100281_ng.field_103468_W
		// @0AB: iconst_1
		// @0AC: aaload
		// @0AD: invokevirtual java.lang.StringBuilder.append(java.lang.String)java.lang.StringBuilder
		// @0B0: bipush 44 (0x2C)
		// @0B2: invokevirtual java.lang.StringBuilder.append(char)java.lang.StringBuilder
		// @0B5: aload #4
		// @0B7: ifnull @0C3
		// @0BA: getstatic java.lang.String[] game.C_100281_ng.field_103468_W
		// @0BD: iconst_3
		// @0BE: aaload
		// @0BF: goto @0C8
		// @0C2: athrow
		// @0C3: getstatic java.lang.String[] game.C_100281_ng.field_103468_W
		// @0C6: iconst_1
		// @0C7: aaload
		// @0C8: invokevirtual java.lang.StringBuilder.append(java.lang.String)java.lang.StringBuilder
		// @0CB: bipush 44 (0x2C)
		// @0CD: invokevirtual java.lang.StringBuilder.append(char)java.lang.StringBuilder
		// @0D0: aload #5
		// @0D2: ifnull @0DE
		// @0D5: getstatic java.lang.String[] game.C_100281_ng.field_103468_W
		// @0D8: iconst_3
		// @0D9: aaload
		// @0DA: goto @0E3
		// @0DD: athrow
		// @0DE: getstatic java.lang.String[] game.C_100281_ng.field_103468_W
		// @0E1: iconst_1
		// @0E2: aaload
		// @0E3: invokevirtual java.lang.StringBuilder.append(java.lang.String)java.lang.StringBuilder
		// @0E6: bipush 44 (0x2C)
		// @0E8: invokevirtual java.lang.StringBuilder.append(char)java.lang.StringBuilder
		// @0EB: aload #6
		// @0ED: ifnull @0F9
		// @0F0: getstatic java.lang.String[] game.C_100281_ng.field_103468_W
		// @0F3: iconst_3
		// @0F4: aaload
		// @0F5: goto @0FE
		// @0F8: athrow
		// @0F9: getstatic java.lang.String[] game.C_100281_ng.field_103468_W
		// @0FC: iconst_1
		// @0FD: aaload
		// @0FE: invokevirtual java.lang.StringBuilder.append(java.lang.String)java.lang.StringBuilder
		// @101: bipush 44 (0x2C)
		// @103: invokevirtual java.lang.StringBuilder.append(char)java.lang.StringBuilder
		// @106: aload #7
		// @108: ifnull @114
		// @10B: getstatic java.lang.String[] game.C_100281_ng.field_103468_W
		// @10E: iconst_3
		// @10F: aaload
		// @110: goto @119
		// @113: athrow
		// @114: getstatic java.lang.String[] game.C_100281_ng.field_103468_W
		// @117: iconst_1
		// @118: aaload
		// @119: invokevirtual java.lang.StringBuilder.append(java.lang.String)java.lang.StringBuilder
		// @11C: bipush 44 (0x2C)
		// @11E: invokevirtual java.lang.StringBuilder.append(char)java.lang.StringBuilder
		// @121: aload #8
		// @123: ifnull @12F
		// @126: getstatic java.lang.String[] game.C_100281_ng.field_103468_W
		// @129: iconst_3
		// @12A: aaload
		// @12B: goto @134
		// @12E: athrow
		// @12F: getstatic java.lang.String[] game.C_100281_ng.field_103468_W
		// @132: iconst_1
		// @133: aaload
		// @134: invokevirtual java.lang.StringBuilder.append(java.lang.String)java.lang.StringBuilder
		// @137: bipush 44 (0x2C)
		// @139: invokevirtual java.lang.StringBuilder.append(char)java.lang.StringBuilder
		// @13C: aload #9
		// @13E: ifnull @14A
		// @141: getstatic java.lang.String[] game.C_100281_ng.field_103468_W
		// @144: iconst_3
		// @145: aaload
		// @146: goto @14F
		// @149: athrow
		// @14A: getstatic java.lang.String[] game.C_100281_ng.field_103468_W
		// @14D: iconst_1
		// @14E: aaload
		// @14F: invokevirtual java.lang.StringBuilder.append(java.lang.String)java.lang.StringBuilder
		// @152: bipush 44 (0x2C)
		// @154: invokevirtual java.lang.StringBuilder.append(char)java.lang.StringBuilder
		// @157: aload #10
		// @159: ifnull @165
		// @15C: getstatic java.lang.String[] game.C_100281_ng.field_103468_W
		// @15F: iconst_3
		// @160: aaload
		// @161: goto @16A
		// @164: athrow
		// @165: getstatic java.lang.String[] game.C_100281_ng.field_103468_W
		// @168: iconst_1
		// @169: aaload
		// @16A: invokevirtual java.lang.StringBuilder.append(java.lang.String)java.lang.StringBuilder
		// @16D: bipush 44 (0x2C)
		// @16F: invokevirtual java.lang.StringBuilder.append(char)java.lang.StringBuilder
		// @172: iload #11
		// @174: invokevirtual java.lang.StringBuilder.append(int)java.lang.StringBuilder
		// @177: bipush 44 (0x2C)
		// @179: invokevirtual java.lang.StringBuilder.append(char)java.lang.StringBuilder
		// @17C: aload #12
		// @17E: ifnull @18A
		// @181: getstatic java.lang.String[] game.C_100281_ng.field_103468_W
		// @184: iconst_3
		// @185: aaload
		// @186: goto @18F
		// @189: athrow
		// @18A: getstatic java.lang.String[] game.C_100281_ng.field_103468_W
		// @18D: iconst_1
		// @18E: aaload
		// @18F: invokevirtual java.lang.StringBuilder.append(java.lang.String)java.lang.StringBuilder
		// @192: bipush 44 (0x2C)
		// @194: invokevirtual java.lang.StringBuilder.append(char)java.lang.StringBuilder
		// @197: iload #13
		// @199: invokevirtual java.lang.StringBuilder.append(boolean)java.lang.StringBuilder
		// @19C: bipush 44 (0x2C)
		// @19E: invokevirtual java.lang.StringBuilder.append(char)java.lang.StringBuilder
		// @1A1: aload #14
		// @1A3: ifnull @1AF
		// @1A6: getstatic java.lang.String[] game.C_100281_ng.field_103468_W
		// @1A9: iconst_3
		// @1AA: aaload
		// @1AB: goto @1B4
		// @1AE: athrow
		// @1AF: getstatic java.lang.String[] game.C_100281_ng.field_103468_W
		// @1B2: iconst_1
		// @1B3: aaload
		// @1B4: invokevirtual java.lang.StringBuilder.append(java.lang.String)java.lang.StringBuilder
		// @1B7: bipush 44 (0x2C)
		// @1B9: invokevirtual java.lang.StringBuilder.append(char)java.lang.StringBuilder
		// @1BC: aload #15
		// @1BE: ifnull @1CA
		// @1C1: getstatic java.lang.String[] game.C_100281_ng.field_103468_W
		// @1C4: iconst_3
		// @1C5: aaload
		// @1C6: goto @1CF
		// @1C9: athrow
		// @1CA: getstatic java.lang.String[] game.C_100281_ng.field_103468_W
		// @1CD: iconst_1
		// @1CE: aaload
		// @1CF: invokevirtual java.lang.StringBuilder.append(java.lang.String)java.lang.StringBuilder
		// @1D2: bipush 44 (0x2C)
		// @1D4: invokevirtual java.lang.StringBuilder.append(char)java.lang.StringBuilder
		// @1D7: aload #16
		// @1D9: ifnull @1E5
		// @1DC: getstatic java.lang.String[] game.C_100281_ng.field_103468_W
		// @1DF: iconst_3
		// @1E0: aaload
		// @1E1: goto @1EA
		// @1E4: athrow
		// @1E5: getstatic java.lang.String[] game.C_100281_ng.field_103468_W
		// @1E8: iconst_1
		// @1E9: aaload
		// @1EA: invokevirtual java.lang.StringBuilder.append(java.lang.String)java.lang.StringBuilder
		// @1ED: bipush 44 (0x2C)
		// @1EF: invokevirtual java.lang.StringBuilder.append(char)java.lang.StringBuilder
		// @1F2: aload #17
		// @1F4: ifnull @200
		// @1F7: getstatic java.lang.String[] game.C_100281_ng.field_103468_W
		// @1FA: iconst_3
		// @1FB: aaload
		// @1FC: goto @205
		// @1FF: athrow
		// @200: getstatic java.lang.String[] game.C_100281_ng.field_103468_W
		// @203: iconst_1
		// @204: aaload
		// @205: invokevirtual java.lang.StringBuilder.append(java.lang.String)java.lang.StringBuilder
		// @208: bipush 44 (0x2C)
		// @20A: invokevirtual java.lang.StringBuilder.append(char)java.lang.StringBuilder
		// @20D: iload #18
		// @20F: invokevirtual java.lang.StringBuilder.append(int)java.lang.StringBuilder
		// @212: bipush 44 (0x2C)
		// @214: invokevirtual java.lang.StringBuilder.append(char)java.lang.StringBuilder
		// @217: aload #19
		// @219: ifnull @225
		// @21C: getstatic java.lang.String[] game.C_100281_ng.field_103468_W
		// @21F: iconst_3
		// @220: aaload
		// @221: goto @22A
		// @224: athrow
		// @225: getstatic java.lang.String[] game.C_100281_ng.field_103468_W
		// @228: iconst_1
		// @229: aaload
		// @22A: invokevirtual java.lang.StringBuilder.append(java.lang.String)java.lang.StringBuilder
		// @22D: bipush 41 (0x29)
		// @22F: invokevirtual java.lang.StringBuilder.append(char)java.lang.StringBuilder
		// @232: invokevirtual java.lang.StringBuilder.toString()java.lang.String
		// @235: invokestatic game.C_100181_cf.func_105695_a(java.lang.Throwable, java.lang.String)game.C_100170_cm
		// @238: athrow
		// @239: return
	}
	
	public static void func_103447_a(byte arg0)
	{
		// @00: aconst_null
		// @01: putstatic java.lang.String game.C_100281_ng.field_103456_F
		// @04: aconst_null
		// @05: putstatic game.C_100037_wb[] game.C_100281_ng.field_103467_T
		// @08: aconst_null
		// @09: putstatic java.lang.String game.C_100281_ng.field_103461_O
		// @0C: aconst_null
		// @0D: putstatic java.lang.String game.C_100281_ng.field_103465_K
		// @10: aconst_null
		// @11: putstatic java.lang.String game.C_100281_ng.field_103473_R
		// @14: aconst_null
		// @15: putstatic java.lang.String[] game.C_100281_ng.field_103455_E
		// @18: aconst_null
		// @19: putstatic game.C_100153_be[] game.C_100281_ng.field_103462_H
		// @1C: iload_0
		// @1D: bipush -52 (0xCC)
		// @1F: if_icmpeq @29
		// @22: aconst_null
		// @23: checkcast java.lang.String
		// @26: putstatic java.lang.String game.C_100281_ng.field_103461_O
		// @29: goto @4E
		// @2C: astore_1
		// @2D: aload_1
		// @2E: new java.lang.StringBuilder
		// @31: dup
		// @32: invokespecial java.lang.StringBuilder.<init>()void
		// @35: getstatic java.lang.String[] game.C_100281_ng.field_103468_W
		// @38: bipush 7 (0x07)
		// @3A: aaload
		// @3B: invokevirtual java.lang.StringBuilder.append(java.lang.String)java.lang.StringBuilder
		// @3E: iload_0
		// @3F: invokevirtual java.lang.StringBuilder.append(int)java.lang.StringBuilder
		// @42: bipush 41 (0x29)
		// @44: invokevirtual java.lang.StringBuilder.append(char)java.lang.StringBuilder
		// @47: invokevirtual java.lang.StringBuilder.toString()java.lang.String
		// @4A: invokestatic game.C_100181_cf.func_105695_a(java.lang.Throwable, java.lang.String)game.C_100170_cm
		// @4D: athrow
		// @4E: return
	}
	
	private C_100281_ng(int arg0, int arg1, int arg2, int arg3, int arg4, int arg5, int arg6, int arg7, int arg8)
	{
		// @00: aload_0
		// @01: invokespecial game.C_100336_im.<init>()void
		// @04: aload_0
		// @05: iload #9
		// @07: putfield int game.C_100281_ng.field_103460_N
		// @0A: aload_0
		// @0B: iload #5
		// @0D: putfield int game.C_100281_ng.field_103470_Q
		// @10: aload_0
		// @11: iload #7
		// @13: putfield int game.C_100281_ng.field_103466_U
		// @16: aload_0
		// @17: iload #8
		// @19: putfield int game.C_100281_ng.field_103458_L
		// @1C: aload_0
		// @1D: iload #6
		// @1F: putfield int game.C_100281_ng.field_103459_M
		// @22: aload_0
		// @23: iload #4
		// @25: iload_2
		// @26: iload_1
		// @27: iload_3
		// @28: bipush -85 (0xAB)
		// @2A: invokevirtual game.C_100281_ng.func_102524_a(int, int, int, int, byte)void
		// @2D: goto @A1
		// @30: astore #10
		// @32: aload #10
		// @34: new java.lang.StringBuilder
		// @37: dup
		// @38: invokespecial java.lang.StringBuilder.<init>()void
		// @3B: getstatic java.lang.String[] game.C_100281_ng.field_103468_W
		// @3E: iconst_5
		// @3F: aaload
		// @40: invokevirtual java.lang.StringBuilder.append(java.lang.String)java.lang.StringBuilder
		// @43: iload_1
		// @44: invokevirtual java.lang.StringBuilder.append(int)java.lang.StringBuilder
		// @47: bipush 44 (0x2C)
		// @49: invokevirtual java.lang.StringBuilder.append(char)java.lang.StringBuilder
		// @4C: iload_2
		// @4D: invokevirtual java.lang.StringBuilder.append(int)java.lang.StringBuilder
		// @50: bipush 44 (0x2C)
		// @52: invokevirtual java.lang.StringBuilder.append(char)java.lang.StringBuilder
		// @55: iload_3
		// @56: invokevirtual java.lang.StringBuilder.append(int)java.lang.StringBuilder
		// @59: bipush 44 (0x2C)
		// @5B: invokevirtual java.lang.StringBuilder.append(char)java.lang.StringBuilder
		// @5E: iload #4
		// @60: invokevirtual java.lang.StringBuilder.append(int)java.lang.StringBuilder
		// @63: bipush 44 (0x2C)
		// @65: invokevirtual java.lang.StringBuilder.append(char)java.lang.StringBuilder
		// @68: iload #5
		// @6A: invokevirtual java.lang.StringBuilder.append(int)java.lang.StringBuilder
		// @6D: bipush 44 (0x2C)
		// @6F: invokevirtual java.lang.StringBuilder.append(char)java.lang.StringBuilder
		// @72: iload #6
		// @74: invokevirtual java.lang.StringBuilder.append(int)java.lang.StringBuilder
		// @77: bipush 44 (0x2C)
		// @79: invokevirtual java.lang.StringBuilder.append(char)java.lang.StringBuilder
		// @7C: iload #7
		// @7E: invokevirtual java.lang.StringBuilder.append(int)java.lang.StringBuilder
		// @81: bipush 44 (0x2C)
		// @83: invokevirtual java.lang.StringBuilder.append(char)java.lang.StringBuilder
		// @86: iload #8
		// @88: invokevirtual java.lang.StringBuilder.append(int)java.lang.StringBuilder
		// @8B: bipush 44 (0x2C)
		// @8D: invokevirtual java.lang.StringBuilder.append(char)java.lang.StringBuilder
		// @90: iload #9
		// @92: invokevirtual java.lang.StringBuilder.append(int)java.lang.StringBuilder
		// @95: bipush 41 (0x29)
		// @97: invokevirtual java.lang.StringBuilder.append(char)java.lang.StringBuilder
		// @9A: invokevirtual java.lang.StringBuilder.toString()java.lang.String
		// @9D: invokestatic game.C_100181_cf.func_105695_a(java.lang.Throwable, java.lang.String)game.C_100170_cm
		// @A0: athrow
		// @A1: return
	}
	
	static
	{
		// @000: bipush 14 (0x0E)
		// @002: anewarray java.lang.String
		// @005: dup
		// @006: iconst_0
		// @007: ldc "e,z\u0005\\#"
		// @009: invokestatic game.C_100281_ng.func_103448_z(java.lang.String)char[]
		// @00C: invokestatic game.C_100281_ng.func_103446_z(char[])java.lang.String
		// @00F: aastore
		// @010: dup
		// @011: iconst_1
		// @012: ldc "e>8%"
		// @014: invokestatic game.C_100281_ng.func_103448_z(java.lang.String)char[]
		// @017: invokestatic game.C_100281_ng.func_103446_z(char[])java.lang.String
		// @01A: aastore
		// @01B: dup
		// @01C: iconst_2
		// @01D: ldc "e,z\u00185"
		// @01F: invokestatic game.C_100281_ng.func_103448_z(java.lang.String)char[]
		// @022: invokestatic game.C_100281_ng.func_103446_z(char[])java.lang.String
		// @025: aastore
		// @026: dup
		// @027: iconst_3
		// @028: ldc "pezg`"
		// @02A: invokestatic game.C_100281_ng.func_103448_z(java.lang.String)char[]
		// @02D: invokestatic game.C_100281_ng.func_103446_z(char[])java.lang.String
		// @030: aastore
		// @031: dup
		// @032: iconst_4
		// @033: ldc "e,z\u00015"
		// @035: invokestatic game.C_100281_ng.func_103448_z(java.lang.String)char[]
		// @038: invokestatic game.C_100281_ng.func_103446_z(char[])java.lang.String
		// @03B: aastore
		// @03C: dup
		// @03D: iconst_5
		// @03E: ldc "e,zute\" w5"
		// @040: invokestatic game.C_100281_ng.func_103448_z(java.lang.String)char[]
		// @043: invokestatic game.C_100281_ng.func_103446_z(char[])java.lang.String
		// @046: aastore
		// @047: dup
		// @048: bipush 6 (0x06)
		// @04A: ldc "e,z\u00085"
		// @04C: invokestatic game.C_100281_ng.func_103448_z(java.lang.String)char[]
		// @04F: invokestatic game.C_100281_ng.func_103446_z(char[])java.lang.String
		// @052: aastore
		// @053: dup
		// @054: bipush 7 (0x07)
		// @056: ldc "e,z\u000e5"
		// @058: invokestatic game.C_100281_ng.func_103448_z(java.lang.String)char[]
		// @05B: invokestatic game.C_100281_ng.func_103446_z(char[])java.lang.String
		// @05E: aastore
		// @05F: dup
		// @060: bipush 8 (0x08)
		// @062: ldc "e,z\u001b5"
		// @064: invokestatic game.C_100281_ng.func_103448_z(java.lang.String)char[]
		// @067: invokestatic game.C_100281_ng.func_103446_z(char[])java.lang.String
		// @06A: aastore
		// @06B: dup
		// @06C: bipush 9 (0x09)
		// @06E: ldc "e,z\n5"
		// @070: invokestatic game.C_100281_ng.func_103448_z(java.lang.String)char[]
		// @073: invokestatic game.C_100281_ng.func_103446_z(char[])java.lang.String
		// @076: aastore
		// @077: dup
		// @078: bipush 10 (0x0A)
		// @07A: ldc "e,z\u000c5"
		// @07C: invokestatic game.C_100281_ng.func_103448_z(java.lang.String)char[]
		// @07F: invokestatic game.C_100281_ng.func_103446_z(char[])java.lang.String
		// @082: aastore
		// @083: dup
		// @084: bipush 11 (0x0B)
		// @086: ldc "e,z\r5"
		// @088: invokestatic game.C_100281_ng.func_103448_z(java.lang.String)char[]
		// @08B: invokestatic game.C_100281_ng.func_103446_z(char[])java.lang.String
		// @08E: aastore
		// @08F: dup
		// @090: bipush 12 (0x0C)
		// @092: ldc "e,z\u000b5"
		// @094: invokestatic game.C_100281_ng.func_103448_z(java.lang.String)char[]
		// @097: invokestatic game.C_100281_ng.func_103446_z(char[])java.lang.String
		// @09A: aastore
		// @09B: dup
		// @09C: bipush 13 (0x0D)
		// @09E: ldc "e,z\u00005"
		// @0A0: invokestatic game.C_100281_ng.func_103448_z(java.lang.String)char[]
		// @0A3: invokestatic game.C_100281_ng.func_103446_z(char[])java.lang.String
		// @0A6: aastore
		// @0A7: putstatic java.lang.String[] game.C_100281_ng.field_103468_W
		// @0AA: bipush 39 (0x27)
		// @0AC: anewarray java.lang.String
		// @0AF: dup
		// @0B0: iconst_0
		// @0B1: ldc "I*8%tx?=*n+\u00065:in9"
		// @0B3: invokestatic game.C_100281_ng.func_103448_z(java.lang.String)char[]
		// @0B6: invokestatic game.C_100281_ng.func_103446_z(char[])java.lang.String
		// @0B9: aastore
		// @0BA: dup
		// @0BB: iconst_1
		// @0BC: ldc "F\"':tg.t\u0008nx*!%i"
		// @0BE: invokestatic game.C_100281_ng.func_103448_z(java.lang.String)char[]
		// @0C1: invokestatic game.C_100281_ng.func_103446_z(char[])java.lang.String
		// @0C4: aastore
		// @0C5: dup
		// @0C6: iconst_2
		// @0C7: ldc "I*8%tx?=*=J8'(hg?"
		// @0C9: invokestatic game.C_100281_ng.func_103448_z(java.lang.String)char[]
		// @0CC: invokestatic game.C_100281_ng.func_103446_z(char[])java.lang.String
		// @0CF: aastore
		// @0D0: dup
		// @0D1: iconst_3
		// @0D2: ldc "F\"':tg.t\rxm.:-xy"
		// @0D4: invokestatic game.C_100281_ng.func_103448_z(java.lang.String)char[]
		// @0D7: invokestatic game.C_100281_ng.func_103446_z(char[])java.lang.String
		// @0DA: aastore
		// @0DB: dup
		// @0DC: iconst_4
		// @0DD: ldc "H$!'in9t\u0008i\u007f*7\""
		// @0DF: invokestatic game.C_100281_ng.func_103448_z(java.lang.String)char[]
		// @0E2: invokestatic game.C_100281_ng.func_103446_z(char[])java.lang.String
		// @0E5: aastore
		// @0E6: dup
		// @0E7: iconst_5
		// @0E8: ldc "J\"&iYn-1'yn9"
		// @0EA: invokestatic game.C_100281_ng.func_103448_z(java.lang.String)char[]
		// @0ED: invokestatic game.C_100281_ng.func_103446_z(char[])java.lang.String
		// @0F0: aastore
		// @0F1: dup
		// @0F2: bipush 6 (0x06)
		// @0F4: ldc "F.7!|}\" 0"
		// @0F6: invokestatic game.C_100281_ng.func_103448_z(java.lang.String)char[]
		// @0F9: invokestatic game.C_100281_ng.func_103446_z(char[])java.lang.String
		// @0FC: aastore
		// @0FD: dup
		// @0FE: bipush 7 (0x07)
		// @100: ldc "[.&/xh?=&s"
		// @102: invokestatic game.C_100281_ng.func_103448_z(java.lang.String)char[]
		// @105: invokestatic game.C_100281_ng.func_103446_z(char[])java.lang.String
		// @108: aastore
		// @109: dup
		// @10A: bipush 8 (0x08)
		// @10C: ldc "X&1%in9"
		// @10E: invokestatic game.C_100281_ng.func_103448_z(java.lang.String)char[]
		// @111: invokestatic game.C_100281_ng.func_103446_z(char[])java.lang.String
		// @114: aastore
		// @115: dup
		// @116: bipush 9 (0x09)
		// @118: ldc "F*'=xyk;/=\\*&"
		// @11A: invokestatic game.C_100281_ng.func_103448_z(java.lang.String)char[]
		// @11D: invokestatic game.C_100281_ng.func_103446_z(char[])java.lang.String
		// @120: aastore
		// @121: dup
		// @122: bipush 10 (0x0A)
		// @124: ldc "_*3iOj&$(zn"
		// @126: invokestatic game.C_100281_ng.func_103448_z(java.lang.String)char[]
		// @129: invokestatic game.C_100281_ng.func_103446_z(char[])java.lang.String
		// @12C: aastore
		// @12D: dup
		// @12E: bipush 11 (0x0B)
		// @130: ldc "L>:'te,t/ryk\u0000(zx"
		// @132: invokestatic game.C_100281_ng.func_103448_z(java.lang.String)char[]
		// @135: invokestatic game.C_100281_ng.func_103446_z(char[])java.lang.String
		// @138: aastore
		// @139: dup
		// @13A: bipush 12 (0x0C)
		// @13C: ldc "M>' rek\u0000(z"
		// @13E: invokestatic game.C_100281_ng.func_103448_z(java.lang.String)char[]
		// @141: invokestatic game.C_100281_ng.func_103446_z(char[])java.lang.String
		// @144: aastore
		// @145: dup
		// @146: bipush 13 (0x0D)
		// @148: ldc "_*3.xok\u001d="
		// @14A: invokestatic game.C_100281_ng.func_103448_z(java.lang.String)char[]
		// @14D: invokestatic game.C_100281_ng.func_103446_z(char[])java.lang.String
		// @150: aastore
		// @151: dup
		// @152: bipush 14 (0x0E)
		// @154: ldc "N%1;zb8='z+\u001f5."
		// @156: invokestatic game.C_100281_ng.func_103448_z(java.lang.String)char[]
		// @159: invokestatic game.C_100281_ng.func_103446_z(char[])java.lang.String
		// @15C: aastore
		// @15D: dup
		// @15E: bipush 15 (0x0F)
		// @160: ldc "_.5$=_*3.xy"
		// @162: invokestatic game.C_100281_ng.func_103448_z(java.lang.String)char[]
		// @165: invokestatic game.C_100281_ng.func_103446_z(char[])java.lang.String
		// @168: aastore
		// @169: dup
		// @16A: bipush 16 (0x10)
		// @16C: ldc "O.'=od21;"
		// @16E: invokestatic game.C_100281_ng.func_103448_z(java.lang.String)char[]
		// @171: invokestatic game.C_100281_ng.func_103446_z(char[])java.lang.String
		// @174: aastore
		// @175: dup
		// @176: bipush 17 (0x11)
		// @178: ldc "B9;'=X.:=te.8"
		// @17A: invokestatic game.C_100281_ng.func_103448_z(java.lang.String)char[]
		// @17D: invokestatic game.C_100281_ng.func_103446_z(char[])java.lang.String
		// @180: aastore
		// @181: dup
		// @182: bipush 18 (0x12)
		// @184: ldc "X?1,q+\u00181'ib%1%"
		// @186: invokestatic game.C_100281_ng.func_103448_z(java.lang.String)char[]
		// @189: invokestatic game.C_100281_ng.func_103446_z(char[])java.lang.String
		// @18C: aastore
		// @18D: dup
		// @18E: bipush 19 (0x13)
		// @190: ldc "J'8&d+\u00181'ib%1%"
		// @192: invokestatic game.C_100281_ng.func_103448_z(java.lang.String)char[]
		// @195: invokestatic game.C_100281_ng.func_103446_z(char[])java.lang.String
		// @198: aastore
		// @199: dup
		// @19A: bipush 20 (0x14)
		// @19C: ldc "_\" (sb>9iNn%  sn'"
		// @19E: invokestatic game.C_100281_ng.func_103448_z(java.lang.String)char[]
		// @1A1: invokestatic game.C_100281_ng.func_103446_z(char[])java.lang.String
		// @1A4: aastore
		// @1A5: dup
		// @1A6: bipush 21 (0x15)
		// @1A8: ldc "['5=te>9iNn%  sn'"
		// @1AA: invokestatic game.C_100281_ng.func_103448_z(java.lang.String)char[]
		// @1AD: invokestatic game.C_100281_ng.func_103446_z(char[])java.lang.String
		// @1B0: aastore
		// @1B1: dup
		// @1B2: bipush 22 (0x16)
		// @1B4: ldc "J/5$|e?t\u001axe?='xg"
		// @1B6: invokestatic game.C_100281_ng.func_103448_z(java.lang.String)char[]
		// @1B9: invokestatic game.C_100281_ng.func_103446_z(char[])java.lang.String
		// @1BC: aastore
		// @1BD: dup
		// @1BE: bipush 23 (0x17)
		// @1C0: ldc "O\"5$re/t\u001axe?='xg"
		// @1C2: invokestatic game.C_100281_ng.func_103448_z(java.lang.String)char[]
		// @1C5: invokestatic game.C_100281_ng.func_103446_z(char[])java.lang.String
		// @1C8: aastore
		// @1C9: dup
		// @1CA: bipush 24 (0x18)
		// @1CC: ldc "H$9,\u007fj(?"
		// @1CE: invokestatic game.C_100281_ng.func_103448_z(java.lang.String)char[]
		// @1D1: invokestatic game.C_100281_ng.func_103446_z(char[])java.lang.String
		// @1D4: aastore
		// @1D5: dup
		// @1D6: bipush 25 (0x19)
		// @1D8: ldc "J%0iT\u007fk\u0017&n\u007f8t\u0001r|k\u0019<~ct"
		// @1DA: invokestatic game.C_100281_ng.func_103448_z(java.lang.String)char[]
		// @1DD: invokestatic game.C_100281_ng.func_103446_z(char[])java.lang.String
		// @1E0: aastore
		// @1E1: dup
		// @1E2: bipush 26 (0x1A)
		// @1E4: ldc "].:.xj%7,"
		// @1E6: invokestatic game.C_100281_ng.func_103448_z(java.lang.String)char[]
		// @1E9: invokestatic game.C_100281_ng.func_103446_z(char[])java.lang.String
		// @1EC: aastore
		// @1ED: dup
		// @1EE: bipush 27 (0x1B)
		// @1F0: ldc "O.2,so.&"
		// @1F2: invokestatic game.C_100281_ng.func_103448_z(java.lang.String)char[]
		// @1F5: invokestatic game.C_100281_ng.func_103446_z(char[])java.lang.String
		// @1F8: aastore
		// @1F9: dup
		// @1FA: bipush 28 (0x1C)
		// @1FC: ldc "F*'=xyk\u0010,{n%0,o"
		// @1FE: invokestatic game.C_100281_ng.func_103448_z(java.lang.String)char[]
		// @201: invokestatic game.C_100281_ng.func_103446_z(char[])java.lang.String
		// @204: aastore
		// @205: dup
		// @206: bipush 29 (0x1D)
		// @208: ldc "I$;$xy*:."
		// @20A: invokestatic game.C_100281_ng.func_103448_z(java.lang.String)char[]
		// @20D: invokestatic game.C_100281_ng.func_103446_z(char[])java.lang.String
		// @210: aastore
		// @211: dup
		// @212: bipush 30 (0x1E)
		// @214: ldc "X'='zx#;="
		// @216: invokestatic game.C_100281_ng.func_103448_z(java.lang.String)char[]
		// @219: invokestatic game.C_100281_ng.func_103446_z(char[])java.lang.String
		// @21C: aastore
		// @21D: dup
		// @21E: bipush 31 (0x1F)
		// @220: ldc "_#1i_b,t\u001bxok\u0016<i\u007f$:"
		// @222: invokestatic game.C_100281_ng.func_103448_z(java.lang.String)char[]
		// @225: invokestatic game.C_100281_ng.func_103446_z(char[])java.lang.String
		// @228: aastore
		// @229: dup
		// @22A: bipush 32 (0x20)
		// @22C: ldc "B';%tj%t\u0001xy$"
		// @22E: invokestatic game.C_100281_ng.func_103448_z(java.lang.String)char[]
		// @231: invokestatic game.C_100281_ng.func_103446_z(char[])java.lang.String
		// @234: aastore
		// @235: dup
		// @236: bipush 33 (0x21)
		// @238: ldc "X\"8?xyk\u0003 se.&"
		// @23A: invokestatic game.C_100281_ng.func_103448_z(java.lang.String)char[]
		// @23D: invokestatic game.C_100281_ng.func_103446_z(char[])java.lang.String
		// @240: aastore
		// @241: dup
		// @242: bipush 34 (0x22)
		// @244: ldc "L$8-=\\\":'xy"
		// @246: invokestatic game.C_100281_ng.func_103448_z(java.lang.String)char[]
		// @249: invokestatic game.C_100281_ng.func_103446_z(char[])java.lang.String
		// @24C: aastore
		// @24D: dup
		// @24E: bipush 35 (0x23)
		// @250: ldc "X\"8?xyk\u001c,od"
		// @252: invokestatic game.C_100281_ng.func_103448_z(java.lang.String)char[]
		// @255: invokestatic game.C_100281_ng.func_103446_z(char[])java.lang.String
		// @258: aastore
		// @259: dup
		// @25A: bipush 36 (0x24)
		// @25C: ldc "L$8-=C.&&"
		// @25E: invokestatic game.C_100281_ng.func_103448_z(java.lang.String)char[]
		// @261: invokestatic game.C_100281_ng.func_103446_z(char[])java.lang.String
		// @264: aastore
		// @265: dup
		// @266: bipush 37 (0x25)
		// @268: ldc "H$:8hn9;;"
		// @26A: invokestatic game.C_100281_ng.func_103448_z(java.lang.String)char[]
		// @26D: invokestatic game.C_100281_ng.func_103446_z(char[])java.lang.String
		// @270: aastore
		// @271: dup
		// @272: bipush 38 (0x26)
		// @274: ldc "[?1;rh\"0,"
		// @276: invokestatic game.C_100281_ng.func_103448_z(java.lang.String)char[]
		// @279: invokestatic game.C_100281_ng.func_103446_z(char[])java.lang.String
		// @27C: aastore
		// @27D: putstatic java.lang.String[] game.C_100281_ng.field_103455_E
		// @280: ldc "_#=:=h$:=od't n+/=:|i'1-3+\u001f;ixe*6%x+\" e=h'=*v+$:i!h$8t,m|b(+5wqy#7d7&q5k='=\u007f#1ir{?=&sxk9,s~e"
		// @282: invokestatic game.C_100281_ng.func_103448_z(java.lang.String)char[]
		// @285: invokestatic game.C_100281_ng.func_103446_z(char[])java.lang.String
		// @288: putstatic java.lang.String game.C_100281_ng.field_103465_K
		// @28B: ldc "Y. <oek &=H*99|b,:"
		// @28D: invokestatic game.C_100281_ng.func_103448_z(java.lang.String)char[]
		// @290: invokestatic game.C_100281_ng.func_103446_z(char[])java.lang.String
		// @293: putstatic java.lang.String game.C_100281_ng.field_103456_F
		// @296: ldc "F\"':td%tu8;u"
		// @298: invokestatic game.C_100281_ng.func_103448_z(java.lang.String)char[]
		// @29B: invokestatic game.C_100281_ng.func_103446_z(char[])java.lang.String
		// @29E: putstatic java.lang.String game.C_100281_ng.field_103473_R
		// @2A1: return
	}
	
	private static char[] func_103448_z(String arg0)
	{
		// @00: aload_0
		// @01: invokevirtual java.lang.String.toCharArray()char[]
		// @04: dup
		// @05: arraylength
		// @06: iconst_2
		// @07: if_icmpge @13
		// @0A: dup
		// @0B: iconst_0
		// @0C: dup2
		// @0D: caload
		// @0E: bipush 29 (0x1D)
		// @10: ixor
		// @11: i2c
		// @12: castore
		// @13: areturn
	}
	
	private static String func_103446_z(char[] arg0)
	{
		// @00: aload_0
		// @01: dup
		// @02: arraylength
		// @03: swap
		// @04: iconst_0
		// @05: istore_1
		// @06: goto @4C
		// @09: dup
		// @0A: iload_1
		// @0B: dup2
		// @0C: caload
		// @0D: iload_1
		// @0E: iconst_5
		// @0F: irem
		// @10: tableswitch def: @44, for 0: @30, for 1: @35, for 2: @3A, for 3: @3F
		// @30: bipush 11 (0x0B)
		// @32: goto @46
		// @35: bipush 75 (0x4B)
		// @37: goto @46
		// @3A: bipush 84 (0x54)
		// @3C: goto @46
		// @3F: bipush 73 (0x49)
		// @41: goto @46
		// @44: bipush 29 (0x1D)
		// @46: ixor
		// @47: i2c
		// @48: castore
		// @49: iinc #1 +1
		// @4C: swap
		// @4D: dup_x1
		// @4E: iload_1
		// @4F: if_icmpgt @09
		// @52: new java.lang.String
		// @55: dup_x1
		// @56: swap
		// @57: invokespecial java.lang.String.<init>(char[])void
		// @5A: invokevirtual java.lang.String.intern()java.lang.String
		// @5D: areturn
	}
}
