package game;

final class C_100226_ae
{
	static C_100202_qi field_106148_d;
	static int[][] field_106152_a;
	static String field_106146_f;
	static boolean field_106149_e;
	static volatile boolean field_106154_h;
	static int[] field_106150_b;
	static String field_106155_i;
	static C_100302_ka field_106147_g;
	static int[] field_106151_c;
	private static final String[] field_106153_z;
	
	static final void func_106145_a(int arg0, boolean arg1)
	{
		// @00: getstatic game.C_100029_gn game.C_100085_a.field_102576_K
		// @03: iconst_0
		// @04: iload_0
		// @05: iconst_0
		// @06: invokevirtual game.C_100029_gn.func_102523_a(int, int, int)void
		// @09: goto @36
		// @0C: astore_2
		// @0D: aload_2
		// @0E: new java.lang.StringBuilder
		// @11: dup
		// @12: invokespecial java.lang.StringBuilder.<init>()void
		// @15: getstatic java.lang.String[] game.C_100226_ae.field_106153_z
		// @18: iconst_1
		// @19: aaload
		// @1A: invokevirtual java.lang.StringBuilder.append(java.lang.String)java.lang.StringBuilder
		// @1D: iload_0
		// @1E: invokevirtual java.lang.StringBuilder.append(int)java.lang.StringBuilder
		// @21: bipush 44 (0x2C)
		// @23: invokevirtual java.lang.StringBuilder.append(char)java.lang.StringBuilder
		// @26: iload_1
		// @27: invokevirtual java.lang.StringBuilder.append(boolean)java.lang.StringBuilder
		// @2A: bipush 41 (0x29)
		// @2C: invokevirtual java.lang.StringBuilder.append(char)java.lang.StringBuilder
		// @2F: invokevirtual java.lang.StringBuilder.toString()java.lang.String
		// @32: invokestatic game.C_100181_cf.func_105695_a(java.lang.Throwable, java.lang.String)game.C_100170_cm
		// @35: athrow
		// @36: return
	}
	
	public static void func_106139_a(int arg0)
	{
		// @00: aconst_null
		// @01: putstatic int[] game.C_100226_ae.field_106151_c
		// @04: aconst_null
		// @05: putstatic int[] game.C_100226_ae.field_106150_b
		// @08: aconst_null
		// @09: checkcast int[][]
		// @0C: putstatic int[][] game.C_100226_ae.field_106152_a
		// @0F: iload_0
		// @10: ifeq @20
		// @13: iconst_0
		// @14: aconst_null
		// @15: checkcast game.C_100327_ib
		// @18: invokestatic game.C_100226_ae.func_106142_a(boolean, game.C_100327_ib)game.C_100327_ib
		// @1B: pop
		// @1C: goto @20
		// @1F: athrow
		// @20: aconst_null
		// @21: putstatic game.C_100302_ka game.C_100226_ae.field_106147_g
		// @24: aconst_null
		// @25: putstatic java.lang.String game.C_100226_ae.field_106146_f
		// @28: aconst_null
		// @29: putstatic java.lang.String game.C_100226_ae.field_106155_i
		// @2C: aconst_null
		// @2D: putstatic game.C_100202_qi game.C_100226_ae.field_106148_d
		// @30: goto @55
		// @33: astore_1
		// @34: aload_1
		// @35: new java.lang.StringBuilder
		// @38: dup
		// @39: invokespecial java.lang.StringBuilder.<init>()void
		// @3C: getstatic java.lang.String[] game.C_100226_ae.field_106153_z
		// @3F: bipush 8 (0x08)
		// @41: aaload
		// @42: invokevirtual java.lang.StringBuilder.append(java.lang.String)java.lang.StringBuilder
		// @45: iload_0
		// @46: invokevirtual java.lang.StringBuilder.append(int)java.lang.StringBuilder
		// @49: bipush 41 (0x29)
		// @4B: invokevirtual java.lang.StringBuilder.append(char)java.lang.StringBuilder
		// @4E: invokevirtual java.lang.StringBuilder.toString()java.lang.String
		// @51: invokestatic game.C_100181_cf.func_105695_a(java.lang.Throwable, java.lang.String)game.C_100170_cm
		// @54: athrow
		// @55: return
	}
	
	static final void func_106144_a(boolean arg0, int arg1, int arg2, int arg3, byte arg4, boolean arg5, boolean arg6, int arg7, int arg8, int arg9, boolean arg10, boolean arg11)
	{
		// @00: iload #4
		// @02: bipush -8 (0xF8)
		// @04: if_icmple @08
		// @07: return
		// @08: iload #7
		// @0A: iload #5
		// @0C: iload #8
		// @0E: iload_0
		// @0F: ldc 16777215 (0xffffff)
		// @11: ldc 16777215 (0xffffff)
		// @13: iload #10
		// @15: iload #11
		// @17: iload #9
		// @19: iload #6
		// @1B: iload_1
		// @1C: iload_3
		// @1D: bipush 107 (0x6B)
		// @1F: iload_2
		// @20: invokestatic game.C_100215_ai.func_106002_a(int, boolean, int, boolean, int, int, boolean, boolean, int, boolean, int, int, byte, int)void
		// @23: goto @B4
		// @26: astore #12
		// @28: aload #12
		// @2A: new java.lang.StringBuilder
		// @2D: dup
		// @2E: invokespecial java.lang.StringBuilder.<init>()void
		// @31: getstatic java.lang.String[] game.C_100226_ae.field_106153_z
		// @34: iconst_2
		// @35: aaload
		// @36: invokevirtual java.lang.StringBuilder.append(java.lang.String)java.lang.StringBuilder
		// @39: iload_0
		// @3A: invokevirtual java.lang.StringBuilder.append(boolean)java.lang.StringBuilder
		// @3D: bipush 44 (0x2C)
		// @3F: invokevirtual java.lang.StringBuilder.append(char)java.lang.StringBuilder
		// @42: iload_1
		// @43: invokevirtual java.lang.StringBuilder.append(int)java.lang.StringBuilder
		// @46: bipush 44 (0x2C)
		// @48: invokevirtual java.lang.StringBuilder.append(char)java.lang.StringBuilder
		// @4B: iload_2
		// @4C: invokevirtual java.lang.StringBuilder.append(int)java.lang.StringBuilder
		// @4F: bipush 44 (0x2C)
		// @51: invokevirtual java.lang.StringBuilder.append(char)java.lang.StringBuilder
		// @54: iload_3
		// @55: invokevirtual java.lang.StringBuilder.append(int)java.lang.StringBuilder
		// @58: bipush 44 (0x2C)
		// @5A: invokevirtual java.lang.StringBuilder.append(char)java.lang.StringBuilder
		// @5D: iload #4
		// @5F: invokevirtual java.lang.StringBuilder.append(int)java.lang.StringBuilder
		// @62: bipush 44 (0x2C)
		// @64: invokevirtual java.lang.StringBuilder.append(char)java.lang.StringBuilder
		// @67: iload #5
		// @69: invokevirtual java.lang.StringBuilder.append(boolean)java.lang.StringBuilder
		// @6C: bipush 44 (0x2C)
		// @6E: invokevirtual java.lang.StringBuilder.append(char)java.lang.StringBuilder
		// @71: iload #6
		// @73: invokevirtual java.lang.StringBuilder.append(boolean)java.lang.StringBuilder
		// @76: bipush 44 (0x2C)
		// @78: invokevirtual java.lang.StringBuilder.append(char)java.lang.StringBuilder
		// @7B: iload #7
		// @7D: invokevirtual java.lang.StringBuilder.append(int)java.lang.StringBuilder
		// @80: bipush 44 (0x2C)
		// @82: invokevirtual java.lang.StringBuilder.append(char)java.lang.StringBuilder
		// @85: iload #8
		// @87: invokevirtual java.lang.StringBuilder.append(int)java.lang.StringBuilder
		// @8A: bipush 44 (0x2C)
		// @8C: invokevirtual java.lang.StringBuilder.append(char)java.lang.StringBuilder
		// @8F: iload #9
		// @91: invokevirtual java.lang.StringBuilder.append(int)java.lang.StringBuilder
		// @94: bipush 44 (0x2C)
		// @96: invokevirtual java.lang.StringBuilder.append(char)java.lang.StringBuilder
		// @99: iload #10
		// @9B: invokevirtual java.lang.StringBuilder.append(boolean)java.lang.StringBuilder
		// @9E: bipush 44 (0x2C)
		// @A0: invokevirtual java.lang.StringBuilder.append(char)java.lang.StringBuilder
		// @A3: iload #11
		// @A5: invokevirtual java.lang.StringBuilder.append(boolean)java.lang.StringBuilder
		// @A8: bipush 41 (0x29)
		// @AA: invokevirtual java.lang.StringBuilder.append(char)java.lang.StringBuilder
		// @AD: invokevirtual java.lang.StringBuilder.toString()java.lang.String
		// @B0: invokestatic game.C_100181_cf.func_105695_a(java.lang.Throwable, java.lang.String)game.C_100170_cm
		// @B3: athrow
		// @B4: return
	}
	
	static final C_100327_ib func_106142_a(boolean arg0, C_100327_ib arg1)
	{
		// @00: aload_1
		// @01: getfield int game.C_100327_ib.field_102502_z
		// @04: istore_2
		// @05: aload_1
		// @06: getfield int game.C_100327_ib.field_102491_K
		// @09: istore_3
		// @0A: aload_1
		// @0B: dup
		// @0C: getfield int game.C_100327_ib.field_102491_K
		// @0F: bipush 64 (0x40)
		// @11: isub
		// @12: putfield int game.C_100327_ib.field_102491_K
		// @15: new game.C_100327_ib
		// @18: dup
		// @19: getstatic game.C_100153_be game.C_100115_ej.field_102041_Xb
		// @1C: iconst_1
		// @1D: iload_2
		// @1E: iload_3
		// @1F: iconst_0
		// @20: iconst_0
		// @21: iconst_1
		// @22: anewarray game.C_100049_vf
		// @25: dup
		// @26: iconst_0
		// @27: new game.C_100049_vf
		// @2A: dup
		// @2B: iload_2
		// @2C: iload_3
		// @2D: bipush 64 (0x40)
		// @2F: isub
		// @30: iconst_0
		// @31: iconst_0
		// @32: aload_1
		// @33: iload_0
		// @34: invokespecial game.C_100049_vf.<init>(int, int, int, int, game.C_100327_ib, boolean)void
		// @37: aastore
		// @38: invokespecial game.C_100327_ib.<init>(game.C_100153_be, int, int, int, int, int, game.C_100049_vf[])void
		// @3B: astore #4
		// @3D: aload #4
		// @3F: aload_1
		// @40: getfield int game.C_100327_ib.field_102494_P
		// @43: putfield int game.C_100327_ib.field_102494_P
		// @46: aload_1
		// @47: iconst_m1
		// @48: putfield int game.C_100327_ib.field_102494_P
		// @4B: aload #4
		// @4D: areturn
		// @4E: astore_2
		// @4F: aload_2
		// @50: new java.lang.StringBuilder
		// @53: dup
		// @54: invokespecial java.lang.StringBuilder.<init>()void
		// @57: getstatic java.lang.String[] game.C_100226_ae.field_106153_z
		// @5A: bipush 7 (0x07)
		// @5C: aaload
		// @5D: invokevirtual java.lang.StringBuilder.append(java.lang.String)java.lang.StringBuilder
		// @60: iload_0
		// @61: invokevirtual java.lang.StringBuilder.append(boolean)java.lang.StringBuilder
		// @64: bipush 44 (0x2C)
		// @66: invokevirtual java.lang.StringBuilder.append(char)java.lang.StringBuilder
		// @69: aload_1
		// @6A: ifnull @76
		// @6D: getstatic java.lang.String[] game.C_100226_ae.field_106153_z
		// @70: iconst_3
		// @71: aaload
		// @72: goto @7C
		// @75: athrow
		// @76: getstatic java.lang.String[] game.C_100226_ae.field_106153_z
		// @79: bipush 6 (0x06)
		// @7B: aaload
		// @7C: invokevirtual java.lang.StringBuilder.append(java.lang.String)java.lang.StringBuilder
		// @7F: bipush 41 (0x29)
		// @81: invokevirtual java.lang.StringBuilder.append(char)java.lang.StringBuilder
		// @84: invokevirtual java.lang.StringBuilder.toString()java.lang.String
		// @87: invokestatic game.C_100181_cf.func_105695_a(java.lang.Throwable, java.lang.String)game.C_100170_cm
		// @8A: athrow
	}
	
	static final void func_106138_a(boolean arg0, C_100294_ki arg1, String arg2)
	{
		// @000: getstatic int game.SteelSentinels.field_105275_O
		// @003: istore #8
		// @005: bipush -2 (0xFE)
		// @007: getstatic int game.C_100055_ed.field_104245_a
		// @00A: if_icmpeq @010
		// @00D: goto @011
		// @010: return
		// @011: iload_0
		// @012: iconst_1
		// @013: if_icmpeq @021
		// @016: aconst_null
		// @017: checkcast java.lang.String
		// @01A: putstatic java.lang.String game.C_100226_ae.field_106155_i
		// @01D: goto @021
		// @020: athrow
		// @021: getstatic game.C_100115_ej game.C_100081_ue.field_100670_q
		// @024: getfield int game.C_100115_ej.field_101886_Kb
		// @027: bipush 20 (0x14)
		// @029: getstatic game.C_100112_r game.C_100053_vn.field_102827_cb
		// @02C: new java.lang.StringBuilder
		// @02F: dup
		// @030: invokespecial java.lang.StringBuilder.<init>()void
		// @033: ldc "["
		// @035: invokevirtual java.lang.StringBuilder.append(java.lang.String)java.lang.StringBuilder
		// @038: sipush -30945 (0x871F)
		// @03B: iconst_2
		// @03C: anewarray java.lang.String
		// @03F: dup
		// @040: iconst_0
		// @041: aload_1
		// @042: getfield java.lang.String[] game.C_100294_ki.field_106974_Y
		// @045: iconst_0
		// @046: aaload
		// @047: aastore
		// @048: dup
		// @049: iconst_1
		// @04A: getstatic java.lang.String[] game.C_100226_ae.field_106153_z
		// @04D: iconst_4
		// @04E: aaload
		// @04F: aastore
		// @050: getstatic java.lang.String game.C_100287_nm.field_106823_g
		// @053: invokestatic game.C_100132_td.func_104965_a(int, java.lang.String[], java.lang.String)java.lang.String
		// @056: invokevirtual java.lang.StringBuilder.append(java.lang.String)java.lang.StringBuilder
		// @059: invokevirtual java.lang.StringBuilder.toString()java.lang.String
		// @05C: invokevirtual game.C_100112_r.func_101739_b(java.lang.String)int
		// @05F: iadd
		// @060: isub
		// @061: istore_3
		// @062: iload_3
		// @063: getstatic game.C_100112_r game.C_100053_vn.field_102827_cb
		// @066: aload_2
		// @067: invokevirtual game.C_100112_r.func_101739_b(java.lang.String)int
		// @06A: if_icmpge @0C3
		// @06D: getstatic game.C_100112_r game.C_100053_vn.field_102827_cb
		// @070: aload_2
		// @071: bipush 71 (0x47)
		// @073: iconst_1
		// @074: newarray int[]
		// @076: dup
		// @077: iconst_0
		// @078: iload_3
		// @079: iastore
		// @07A: invokestatic game.C_100130_tf.func_104957_a(game.C_100112_r, java.lang.String, byte, int[])java.lang.String[]
		// @07D: astore #4
		// @07F: aload #4
		// @081: astore #5
		// @083: iconst_0
		// @084: istore #6
		// @086: iload #6
		// @088: aload #5
		// @08A: arraylength
		// @08B: if_icmpge @0BE
		// @08E: aload #5
		// @090: iload #6
		// @092: aaload
		// @093: astore #7
		// @095: aload_1
		// @096: getfield java.lang.String[] game.C_100294_ki.field_106974_Y
		// @099: iconst_0
		// @09A: aaload
		// @09B: ldc -1221466785 (0xb731e55f)
		// @09D: iconst_0
		// @09E: iconst_1
		// @09F: aconst_null
		// @0A0: aload #7
		// @0A2: invokestatic game.C_100019_wl.func_103834_a(java.lang.String, int, int, int, java.lang.String, java.lang.String)void
		// @0A5: getstatic int game.C_100220_ac.field_106062_j
		// @0A8: iconst_1
		// @0A9: isub
		// @0AA: putstatic int game.C_100220_ac.field_106062_j
		// @0AD: iinc #6 +1
		// @0B0: iload #8
		// @0B2: ifne @0DE
		// @0B5: iload #8
		// @0B7: ifeq @086
		// @0BA: goto @0BE
		// @0BD: athrow
		// @0BE: iload #8
		// @0C0: ifeq @0DE
		// @0C3: aload_1
		// @0C4: getfield java.lang.String[] game.C_100294_ki.field_106974_Y
		// @0C7: iconst_0
		// @0C8: aaload
		// @0C9: ldc -1221466785 (0xb731e55f)
		// @0CB: iconst_0
		// @0CC: iconst_1
		// @0CD: aconst_null
		// @0CE: aload_2
		// @0CF: invokestatic game.C_100019_wl.func_103834_a(java.lang.String, int, int, int, java.lang.String, java.lang.String)void
		// @0D2: getstatic int game.C_100220_ac.field_106062_j
		// @0D5: iconst_1
		// @0D6: isub
		// @0D7: putstatic int game.C_100220_ac.field_106062_j
		// @0DA: goto @0DE
		// @0DD: athrow
		// @0DE: goto @138
		// @0E1: astore_3
		// @0E2: aload_3
		// @0E3: new java.lang.StringBuilder
		// @0E6: dup
		// @0E7: invokespecial java.lang.StringBuilder.<init>()void
		// @0EA: getstatic java.lang.String[] game.C_100226_ae.field_106153_z
		// @0ED: iconst_5
		// @0EE: aaload
		// @0EF: invokevirtual java.lang.StringBuilder.append(java.lang.String)java.lang.StringBuilder
		// @0F2: iload_0
		// @0F3: invokevirtual java.lang.StringBuilder.append(boolean)java.lang.StringBuilder
		// @0F6: bipush 44 (0x2C)
		// @0F8: invokevirtual java.lang.StringBuilder.append(char)java.lang.StringBuilder
		// @0FB: aload_1
		// @0FC: ifnull @108
		// @0FF: getstatic java.lang.String[] game.C_100226_ae.field_106153_z
		// @102: iconst_3
		// @103: aaload
		// @104: goto @10E
		// @107: athrow
		// @108: getstatic java.lang.String[] game.C_100226_ae.field_106153_z
		// @10B: bipush 6 (0x06)
		// @10D: aaload
		// @10E: invokevirtual java.lang.StringBuilder.append(java.lang.String)java.lang.StringBuilder
		// @111: bipush 44 (0x2C)
		// @113: invokevirtual java.lang.StringBuilder.append(char)java.lang.StringBuilder
		// @116: aload_2
		// @117: ifnull @123
		// @11A: getstatic java.lang.String[] game.C_100226_ae.field_106153_z
		// @11D: iconst_3
		// @11E: aaload
		// @11F: goto @129
		// @122: athrow
		// @123: getstatic java.lang.String[] game.C_100226_ae.field_106153_z
		// @126: bipush 6 (0x06)
		// @128: aaload
		// @129: invokevirtual java.lang.StringBuilder.append(java.lang.String)java.lang.StringBuilder
		// @12C: bipush 41 (0x29)
		// @12E: invokevirtual java.lang.StringBuilder.append(char)java.lang.StringBuilder
		// @131: invokevirtual java.lang.StringBuilder.toString()java.lang.String
		// @134: invokestatic game.C_100181_cf.func_105695_a(java.lang.Throwable, java.lang.String)game.C_100170_cm
		// @137: athrow
		// @138: return
	}
	
	static final void func_106143_b(int arg0, boolean arg1)
	{
		// @000: bipush 30 (0x1E)
		// @002: getstatic int game.C_100196_rb.field_105821_c
		// @005: iconst_0
		// @006: sipush 640 (0x0280)
		// @009: getstatic int game.C_100196_rb.field_105819_e
		// @00C: iadd
		// @00D: ldc -1998163583 (0x88e67181)
		// @00F: ishr
		// @010: sipush -640 (0xFD80)
		// @013: getstatic int game.C_100196_rb.field_105819_e
		// @016: iadd
		// @017: ldc 1495424097 (0x59225c61)
		// @019: ishr
		// @01A: invokestatic game.C_100209_qb.func_102687_b(int, int, int, int, int)void
		// @01D: getstatic int game.C_100015_wh.field_103782_d
		// @020: iconst_m1
		// @021: ixor
		// @022: iconst_m1
		// @023: if_icmpge @07A
		// @026: aconst_null
		// @027: getstatic game.C_100037_wb game.C_100094_j.field_104545_f
		// @02A: if_acmpeq @042
		// @02D: goto @031
		// @030: athrow
		// @031: getstatic game.C_100037_wb game.C_100094_j.field_104545_f
		// @034: getstatic game.C_100302_ka game.C_100231_oc.field_102208_bc
		// @037: getfield int game.C_100302_ka.field_101841_Pb
		// @03A: iconst_0
		// @03B: invokevirtual game.C_100037_wb.func_102386_f(int, int)void
		// @03E: goto @042
		// @041: athrow
		// @042: getstatic game.C_100302_ka game.C_100231_oc.field_102208_bc
		// @045: bipush -126 (0x82)
		// @047: iload_1
		// @048: ifeq @05A
		// @04B: getstatic boolean game.C_100188_rj.field_105735_f
		// @04E: ifne @05A
		// @051: goto @055
		// @054: athrow
		// @055: iconst_1
		// @056: goto @05B
		// @059: athrow
		// @05A: iconst_0
		// @05B: invokevirtual game.C_100302_ka.func_101809_a(byte, boolean)void
		// @05E: getstatic game.C_100302_ka game.C_100081_ue.field_100676_j
		// @061: bipush -127 (0x81)
		// @063: iload_1
		// @064: ifeq @076
		// @067: getstatic boolean game.C_100188_rj.field_105735_f
		// @06A: ifne @076
		// @06D: goto @071
		// @070: athrow
		// @071: iconst_1
		// @072: goto @077
		// @075: athrow
		// @076: iconst_0
		// @077: invokevirtual game.C_100302_ka.func_101809_a(byte, boolean)void
		// @07A: iload_0
		// @07B: bipush -62 (0xC2)
		// @07D: if_icmple @081
		// @080: return
		// @081: iconst_m1
		// @082: getstatic int game.C_100102_w.field_104635_b
		// @085: iconst_m1
		// @086: ixor
		// @087: if_icmpgt @09B
		// @08A: iconst_m1
		// @08B: getstatic int game.C_100100_i.field_102014_hc
		// @08E: iconst_m1
		// @08F: ixor
		// @090: if_icmpgt @09B
		// @093: goto @097
		// @096: athrow
		// @097: goto @0EB
		// @09A: athrow
		// @09B: aconst_null
		// @09C: getstatic game.C_100037_wb game.C_100094_j.field_104545_f
		// @09F: if_acmpne @0A6
		// @0A2: goto @0B3
		// @0A5: athrow
		// @0A6: getstatic game.C_100037_wb game.C_100094_j.field_104545_f
		// @0A9: getstatic game.C_100302_ka game.C_100314_lf.field_101335_mc
		// @0AC: getfield int game.C_100302_ka.field_101841_Pb
		// @0AF: iconst_0
		// @0B0: invokevirtual game.C_100037_wb.func_102386_f(int, int)void
		// @0B3: getstatic game.C_100302_ka game.C_100314_lf.field_101335_mc
		// @0B6: bipush -128 (0x80)
		// @0B8: iload_1
		// @0B9: ifeq @0CB
		// @0BC: getstatic boolean game.C_100003_ga.field_103535_w
		// @0BF: ifne @0CB
		// @0C2: goto @0C6
		// @0C5: athrow
		// @0C6: iconst_1
		// @0C7: goto @0CC
		// @0CA: athrow
		// @0CB: iconst_0
		// @0CC: invokevirtual game.C_100302_ka.func_101809_a(byte, boolean)void
		// @0CF: getstatic game.C_100302_ka game.C_100318_hj.field_107196_d
		// @0D2: bipush -128 (0x80)
		// @0D4: iload_1
		// @0D5: ifeq @0E7
		// @0D8: getstatic boolean game.C_100003_ga.field_103535_w
		// @0DB: ifne @0E7
		// @0DE: goto @0E2
		// @0E1: athrow
		// @0E2: iconst_1
		// @0E3: goto @0E8
		// @0E6: athrow
		// @0E7: iconst_0
		// @0E8: invokevirtual game.C_100302_ka.func_101809_a(byte, boolean)void
		// @0EB: bipush -77 (0xB3)
		// @0ED: invokestatic game.C_100200_ba.func_105842_a(byte)void
		// @0F0: goto @11D
		// @0F3: astore_2
		// @0F4: aload_2
		// @0F5: new java.lang.StringBuilder
		// @0F8: dup
		// @0F9: invokespecial java.lang.StringBuilder.<init>()void
		// @0FC: getstatic java.lang.String[] game.C_100226_ae.field_106153_z
		// @0FF: iconst_0
		// @100: aaload
		// @101: invokevirtual java.lang.StringBuilder.append(java.lang.String)java.lang.StringBuilder
		// @104: iload_0
		// @105: invokevirtual java.lang.StringBuilder.append(int)java.lang.StringBuilder
		// @108: bipush 44 (0x2C)
		// @10A: invokevirtual java.lang.StringBuilder.append(char)java.lang.StringBuilder
		// @10D: iload_1
		// @10E: invokevirtual java.lang.StringBuilder.append(boolean)java.lang.StringBuilder
		// @111: bipush 41 (0x29)
		// @113: invokevirtual java.lang.StringBuilder.append(char)java.lang.StringBuilder
		// @116: invokevirtual java.lang.StringBuilder.toString()java.lang.String
		// @119: invokestatic game.C_100181_cf.func_105695_a(java.lang.Throwable, java.lang.String)game.C_100170_cm
		// @11C: athrow
		// @11D: return
	}
	
	static
	{
		// @00: bipush 9 (0x09)
		// @02: anewarray java.lang.String
		// @05: dup
		// @06: iconst_0
		// @07: ldc "PfK'/"
		// @09: invokestatic game.C_100226_ae.func_106141_z(java.lang.String)char[]
		// @0C: invokestatic game.C_100226_ae.func_106140_z(char[])java.lang.String
		// @0F: aastore
		// @10: dup
		// @11: iconst_1
		// @12: ldc "PfK&/"
		// @14: invokestatic game.C_100226_ae.func_106141_z(java.lang.String)char[]
		// @17: invokestatic game.C_100226_ae.func_106140_z(char[])java.lang.String
		// @1A: aastore
		// @1B: dup
		// @1C: iconst_2
		// @1D: ldc "PfK!/"
		// @1F: invokestatic game.C_100226_ae.func_106141_z(java.lang.String)char[]
		// @22: invokestatic game.C_100226_ae.func_106140_z(char[])java.lang.String
		// @25: aastore
		// @26: dup
		// @27: iconst_3
		// @28: ldc "J-KKz"
		// @2A: invokestatic game.C_100226_ae.func_106141_z(java.lang.String)char[]
		// @2D: invokestatic game.C_100226_ae.func_106140_z(char[])java.lang.String
		// @30: aastore
		// @31: dup
		// @32: iconst_4
		// @33: ldc "l#"
		// @35: invokestatic game.C_100226_ae.func_106141_z(java.lang.String)char[]
		// @38: invokestatic game.C_100226_ae.func_106140_z(char[])java.lang.String
		// @3B: aastore
		// @3C: dup
		// @3D: iconst_5
		// @3E: ldc "PfK$/"
		// @40: invokestatic game.C_100226_ae.func_106141_z(java.lang.String)char[]
		// @43: invokestatic game.C_100226_ae.func_106140_z(char[])java.lang.String
		// @46: aastore
		// @47: dup
		// @48: bipush 6 (0x06)
		// @4A: ldc "_v\t\t"
		// @4C: invokestatic game.C_100226_ae.func_106141_z(java.lang.String)char[]
		// @4F: invokestatic game.C_100226_ae.func_106140_z(char[])java.lang.String
		// @52: aastore
		// @53: dup
		// @54: bipush 7 (0x07)
		// @56: ldc "PfK#/"
		// @58: invokestatic game.C_100226_ae.func_106141_z(java.lang.String)char[]
		// @5B: invokestatic game.C_100226_ae.func_106140_z(char[])java.lang.String
		// @5E: aastore
		// @5F: dup
		// @60: bipush 8 (0x08)
		// @62: ldc "PfK /"
		// @64: invokestatic game.C_100226_ae.func_106141_z(java.lang.String)char[]
		// @67: invokestatic game.C_100226_ae.func_106140_z(char[])java.lang.String
		// @6A: aastore
		// @6B: putstatic java.lang.String[] game.C_100226_ae.field_106153_z
		// @6E: iconst_3
		// @6F: anewarray int[]
		// @72: dup
		// @73: iconst_0
		// @74: aconst_null
		// @75: aastore
		// @76: dup
		// @77: iconst_1
		// @78: iconst_3
		// @79: newarray int[]
		// @7B: dup
		// @7C: iconst_0
		// @7D: iconst_1
		// @7E: iastore
		// @7F: dup
		// @80: iconst_1
		// @81: iconst_2
		// @82: iastore
		// @83: dup
		// @84: iconst_2
		// @85: iconst_4
		// @86: iastore
		// @87: aastore
		// @88: dup
		// @89: iconst_2
		// @8A: aconst_null
		// @8B: aastore
		// @8C: putstatic int[][] game.C_100226_ae.field_106152_a
		// @8F: ldc "~m"
		// @91: invokestatic game.C_100226_ae.func_106141_z(java.lang.String)char[]
		// @94: invokestatic game.C_100226_ae.func_106140_z(char[])java.lang.String
		// @97: putstatic java.lang.String game.C_100226_ae.field_106146_f
		// @9A: new game.C_100202_qi
		// @9D: dup
		// @9E: invokespecial game.C_100202_qi.<init>()void
		// @A1: putstatic game.C_100202_qi game.C_100226_ae.field_106148_d
		// @A4: bipush 8 (0x08)
		// @A6: newarray int[]
		// @A8: dup
		// @A9: iconst_0
		// @AA: iconst_2
		// @AB: iastore
		// @AC: dup
		// @AD: iconst_1
		// @AE: bipush 20 (0x14)
		// @B0: iastore
		// @B1: dup
		// @B2: iconst_2
		// @B3: bipush 21 (0x15)
		// @B5: iastore
		// @B6: dup
		// @B7: iconst_3
		// @B8: bipush 6 (0x06)
		// @BA: iastore
		// @BB: dup
		// @BC: iconst_4
		// @BD: bipush 37 (0x25)
		// @BF: iastore
		// @C0: dup
		// @C1: iconst_5
		// @C2: bipush 45 (0x2D)
		// @C4: iastore
		// @C5: dup
		// @C6: bipush 6 (0x06)
		// @C8: iconst_5
		// @C9: iastore
		// @CA: dup
		// @CB: bipush 7 (0x07)
		// @CD: bipush 13 (0x0D)
		// @CF: iastore
		// @D0: putstatic int[] game.C_100226_ae.field_106150_b
		// @D3: aconst_null
		// @D4: putstatic game.C_100302_ka game.C_100226_ae.field_106147_g
		// @D7: ldc "bj\u0008\u000ckPqE\u0017fEj\u000b\u0002"
		// @D9: invokestatic game.C_100226_ae.func_106141_z(java.lang.String)char[]
		// @DC: invokestatic game.C_100226_ae.func_106140_z(char[])java.lang.String
		// @DF: putstatic java.lang.String game.C_100226_ae.field_106155_i
		// @E2: iconst_1
		// @E3: putstatic boolean game.C_100226_ae.field_106154_h
		// @E6: sipush 128 (0x0080)
		// @E9: newarray int[]
		// @EB: putstatic int[] game.C_100226_ae.field_106151_c
		// @EE: return
	}
	
	private static char[] func_106141_z(String arg0)
	{
		// @00: aload_0
		// @01: invokevirtual java.lang.String.toCharArray()char[]
		// @04: dup
		// @05: arraylength
		// @06: iconst_2
		// @07: if_icmpge @13
		// @0A: dup
		// @0B: iconst_0
		// @0C: dup2
		// @0D: caload
		// @0E: bipush 7 (0x07)
		// @10: ixor
		// @11: i2c
		// @12: castore
		// @13: areturn
	}
	
	private static String func_106140_z(char[] arg0)
	{
		// @00: aload_0
		// @01: dup
		// @02: arraylength
		// @03: swap
		// @04: iconst_0
		// @05: istore_1
		// @06: goto @4B
		// @09: dup
		// @0A: iload_1
		// @0B: dup2
		// @0C: caload
		// @0D: iload_1
		// @0E: iconst_5
		// @0F: irem
		// @10: tableswitch def: @43, for 0: @30, for 1: @35, for 2: @39, for 3: @3E
		// @30: bipush 49 (0x31)
		// @32: goto @45
		// @35: iconst_3
		// @36: goto @45
		// @39: bipush 101 (0x65)
		// @3B: goto @45
		// @3E: bipush 101 (0x65)
		// @40: goto @45
		// @43: bipush 7 (0x07)
		// @45: ixor
		// @46: i2c
		// @47: castore
		// @48: iinc #1 +1
		// @4B: swap
		// @4C: dup_x1
		// @4D: iload_1
		// @4E: if_icmpgt @09
		// @51: new java.lang.String
		// @54: dup_x1
		// @55: swap
		// @56: invokespecial java.lang.String.<init>(char[])void
		// @59: invokevirtual java.lang.String.intern()java.lang.String
		// @5C: areturn
	}
}
