package game;

final class C_100315_la
{
	static String field_107180_a;
	static long field_107177_e;
	static C_100268_mk field_107179_c;
	static int[] field_107178_b;
	static String field_107176_d;
	static String field_107174_f;
	static String field_107175_g;
	private static final String[] field_107181_z;
	
	static final void func_107172_a(byte arg0)
	{
		// @000: getstatic int game.SteelSentinels.field_105275_O
		// @003: istore #19
		// @005: bipush 12 (0x0C)
		// @007: newarray int[]
		// @009: dup
		// @00A: iconst_0
		// @00B: iconst_0
		// @00C: iastore
		// @00D: dup
		// @00E: iconst_1
		// @00F: iconst_0
		// @010: iastore
		// @011: dup
		// @012: iconst_2
		// @013: sipush -8144 (0xE030)
		// @016: iastore
		// @017: dup
		// @018: iconst_3
		// @019: ldc 65536 (0x10000)
		// @01B: iastore
		// @01C: dup
		// @01D: iconst_4
		// @01E: iconst_0
		// @01F: iastore
		// @020: dup
		// @021: iconst_5
		// @022: iconst_0
		// @023: iastore
		// @024: dup
		// @025: bipush 6 (0x06)
		// @027: iconst_0
		// @028: iastore
		// @029: dup
		// @02A: bipush 7 (0x07)
		// @02C: ldc -65536 (0xffff0000)
		// @02E: iastore
		// @02F: dup
		// @030: bipush 8 (0x08)
		// @032: iconst_0
		// @033: iastore
		// @034: dup
		// @035: bipush 9 (0x09)
		// @037: iconst_0
		// @038: iastore
		// @039: dup
		// @03A: bipush 10 (0x0A)
		// @03C: iconst_0
		// @03D: iastore
		// @03E: dup
		// @03F: bipush 11 (0x0B)
		// @041: ldc 65536 (0x10000)
		// @043: iastore
		// @044: putstatic int[] game.C_100327_ib.field_102490_J
		// @047: iload_0
		// @048: bipush 12 (0x0C)
		// @04A: if_icmpgt @04E
		// @04D: return
		// @04E: getstatic game.C_100277_nc[] game.C_100103_eh.field_104668_a
		// @051: arraylength
		// @052: istore_1
		// @053: iload_1
		// @054: newarray int[]
		// @056: astore_2
		// @057: iconst_0
		// @058: istore_3
		// @059: iload_3
		// @05A: iload_1
		// @05B: if_icmpge @152
		// @05E: getstatic game.C_100277_nc[] game.C_100103_eh.field_104668_a
		// @061: iload_3
		// @062: aaload
		// @063: astore #4
		// @065: aload #4
		// @067: bipush -113 (0x8F)
		// @069: invokevirtual game.C_100277_nc.func_106692_a(byte)void
		// @06C: iload_3
		// @06D: sipush 1100 (0x044C)
		// @070: invokestatic game.C_100170_cm.func_105535_a(int, int)void
		// @073: aload #4
		// @075: getfield int game.C_100277_nc.field_106716_P
		// @078: aload #4
		// @07A: getfield int game.C_100277_nc.field_106740_r
		// @07D: iadd
		// @07E: ldc 842418625 (0x323649c1)
		// @080: ishr
		// @081: istore #5
		// @083: aload #4
		// @085: getfield int game.C_100277_nc.field_106696_D
		// @088: aload #4
		// @08A: getfield int game.C_100277_nc.field_106720_f
		// @08D: ineg
		// @08E: isub
		// @08F: ldc 1911874049 (0x71f4e201)
		// @091: ishr
		// @092: istore #6
		// @094: aload #4
		// @096: getfield int game.C_100277_nc.field_106700_A
		// @099: aload #4
		// @09B: getfield int game.C_100277_nc.field_106709_J
		// @09E: iadd
		// @09F: ldc -1866421215 (0x90c0ac21)
		// @0A1: ishr
		// @0A2: istore #7
		// @0A4: getstatic int[] game.C_100327_ib.field_102490_J
		// @0A7: bipush 9 (0x09)
		// @0A9: iaload
		// @0AA: ldc -1641457598 (0x9e295842)
		// @0AC: ishr
		// @0AD: istore #8
		// @0AF: getstatic int[] game.C_100327_ib.field_102490_J
		// @0B2: bipush 10 (0x0A)
		// @0B4: iaload
		// @0B5: ldc 252311234 (0xf09f6c2)
		// @0B7: ishr
		// @0B8: istore #9
		// @0BA: getstatic int[] game.C_100327_ib.field_102490_J
		// @0BD: bipush 11 (0x0B)
		// @0BF: iaload
		// @0C0: ldc 432800994 (0x19cc04e2)
		// @0C2: ishr
		// @0C3: istore #10
		// @0C5: getstatic int[] game.C_100052_eb.field_104230_e
		// @0C8: iconst_3
		// @0C9: iaload
		// @0CA: iload #8
		// @0CC: imul
		// @0CD: iload #9
		// @0CF: getstatic int[] game.C_100052_eb.field_104230_e
		// @0D2: iconst_4
		// @0D3: iaload
		// @0D4: imul
		// @0D5: ineg
		// @0D6: isub
		// @0D7: getstatic int[] game.C_100052_eb.field_104230_e
		// @0DA: iconst_5
		// @0DB: iaload
		// @0DC: iload #10
		// @0DE: imul
		// @0DF: iadd
		// @0E0: ldc -713981298 (0xd571828e)
		// @0E2: ishr
		// @0E3: istore #11
		// @0E5: iload #9
		// @0E7: getstatic int[] game.C_100052_eb.field_104230_e
		// @0EA: bipush 7 (0x07)
		// @0EC: iaload
		// @0ED: imul
		// @0EE: getstatic int[] game.C_100052_eb.field_104230_e
		// @0F1: bipush 6 (0x06)
		// @0F3: iaload
		// @0F4: iload #8
		// @0F6: imul
		// @0F7: getstatic int[] game.C_100052_eb.field_104230_e
		// @0FA: bipush 8 (0x08)
		// @0FC: iaload
		// @0FD: iload #10
		// @0FF: imul
		// @100: iadd
		// @101: iadd
		// @102: ldc -1565969074 (0xa2a9354e)
		// @104: ishr
		// @105: istore #12
		// @107: iload #10
		// @109: getstatic int[] game.C_100052_eb.field_104230_e
		// @10C: bipush 11 (0x0B)
		// @10E: iaload
		// @10F: imul
		// @110: getstatic int[] game.C_100052_eb.field_104230_e
		// @113: bipush 9 (0x09)
		// @115: iaload
		// @116: iload #8
		// @118: imul
		// @119: iadd
		// @11A: iload #9
		// @11C: getstatic int[] game.C_100052_eb.field_104230_e
		// @11F: bipush 10 (0x0A)
		// @121: iaload
		// @122: imul
		// @123: iadd
		// @124: ldc 1164445998 (0x4568092e)
		// @126: ishr
		// @127: istore #13
		// @129: aload_2
		// @12A: iload_3
		// @12B: iload #11
		// @12D: iload #5
		// @12F: imul
		// @130: iload #12
		// @132: iload #6
		// @134: imul
		// @135: ineg
		// @136: iload #7
		// @138: iload #13
		// @13A: imul
		// @13B: isub
		// @13C: isub
		// @13D: ldc 1944322896 (0x73e40350)
		// @13F: ishr
		// @140: iastore
		// @141: iinc #3 +1
		// @144: iload #19
		// @146: ifne @15C
		// @149: iload #19
		// @14B: ifeq @059
		// @14E: goto @152
		// @151: athrow
		// @152: getstatic int[] game.C_100327_ib.field_102490_J
		// @155: bipush 9 (0x09)
		// @157: iaload
		// @158: ldc -398482392 (0xe83fa428)
		// @15A: ishr
		// @15B: istore_3
		// @15C: getstatic int[] game.C_100327_ib.field_102490_J
		// @15F: bipush 10 (0x0A)
		// @161: iaload
		// @162: ldc -794792760 (0xd0a06cc8)
		// @164: ishr
		// @165: istore #4
		// @167: getstatic int[] game.C_100327_ib.field_102490_J
		// @16A: bipush 11 (0x0B)
		// @16C: iaload
		// @16D: ldc 1588317160 (0x5eabcbe8)
		// @16F: ishr
		// @170: istore #5
		// @172: getstatic int game.C_100015_wh.field_103783_e
		// @175: ldc -535237820 (0xe018eb44)
		// @177: ishl
		// @178: istore #6
		// @17A: iconst_0
		// @17B: istore #7
		// @17D: iconst_3
		// @17E: iload #6
		// @180: invokestatic game.C_100284_nj.func_106768_a(int, int)int
		// @183: ldc -810551608 (0xcfaff6c8)
		// @185: ishr
		// @186: istore #8
		// @188: iload #6
		// @18A: iconst_0
		// @18B: invokestatic game.C_100273_mm.func_106673_a(int, boolean)int
		// @18E: ldc 830357352 (0x317e3f68)
		// @190: ishr
		// @191: istore #9
		// @193: getstatic int game.C_100015_wh.field_103781_g
		// @196: iconst_m1
		// @197: ixor
		// @198: ifeq @1C1
		// @19B: iconst_m1
		// @19C: getstatic int game.C_100338_jc.field_105370_l
		// @19F: if_icmpne @1AA
		// @1A2: goto @1A6
		// @1A5: athrow
		// @1A6: goto @1C1
		// @1A9: athrow
		// @1AA: getstatic int game.C_100015_wh.field_103781_g
		// @1AD: sipush -320 (0xFEC0)
		// @1B0: iadd
		// @1B1: istore #7
		// @1B3: getstatic int game.C_100338_jc.field_105370_l
		// @1B6: ineg
		// @1B7: sipush 240 (0x00F0)
		// @1BA: iadd
		// @1BB: istore #8
		// @1BD: bipush -128 (0x80)
		// @1BF: istore #9
		// @1C1: ldc2_w 256.0
		// @1C4: iload #9
		// @1C6: iload #9
		// @1C8: imul
		// @1C9: iload #7
		// @1CB: iload #7
		// @1CD: imul
		// @1CE: iadd
		// @1CF: iload #8
		// @1D1: iload #8
		// @1D3: imul
		// @1D4: iadd
		// @1D5: i2d
		// @1D6: invokestatic java.lang.Math.sqrt(double)double
		// @1D9: ddiv
		// @1DA: dstore #10
		// @1DC: iload #9
		// @1DE: i2d
		// @1DF: dload #10
		// @1E1: dmul
		// @1E2: d2i
		// @1E3: istore #9
		// @1E5: iload #8
		// @1E7: i2d
		// @1E8: dload #10
		// @1EA: dmul
		// @1EB: d2i
		// @1EC: istore #8
		// @1EE: iload #7
		// @1F0: i2d
		// @1F1: dload #10
		// @1F3: dmul
		// @1F4: d2i
		// @1F5: istore #7
		// @1F7: iload #7
		// @1F9: iload_3
		// @1FA: isub
		// @1FB: istore #12
		// @1FD: iload #8
		// @1FF: iload #4
		// @201: ineg
		// @202: iadd
		// @203: istore #13
		// @205: iload #5
		// @207: ineg
		// @208: iload #9
		// @20A: iadd
		// @20B: istore #14
		// @20D: ldc2_w 256.0
		// @210: iload #14
		// @212: iload #14
		// @214: imul
		// @215: iload #12
		// @217: iload #12
		// @219: imul
		// @21A: iload #13
		// @21C: iload #13
		// @21E: imul
		// @21F: ineg
		// @220: isub
		// @221: iadd
		// @222: i2d
		// @223: invokestatic java.lang.Math.sqrt(double)double
		// @226: ddiv
		// @227: dstore #10
		// @229: iload #13
		// @22B: i2d
		// @22C: dload #10
		// @22E: dmul
		// @22F: d2i
		// @230: istore #13
		// @232: iload #12
		// @234: i2d
		// @235: dload #10
		// @237: dmul
		// @238: d2i
		// @239: istore #12
		// @23B: iload #14
		// @23D: i2d
		// @23E: dload #10
		// @240: dmul
		// @241: d2i
		// @242: istore #14
		// @244: iconst_0
		// @245: istore #15
		// @247: getstatic game.C_100277_nc[] game.C_100103_eh.field_104668_a
		// @24A: arraylength
		// @24B: iconst_m1
		// @24C: ixor
		// @24D: iload #15
		// @24F: iconst_m1
		// @250: ixor
		// @251: if_icmpge @2F4
		// @254: iconst_0
		// @255: istore #16
		// @257: iload #19
		// @259: ifne @318
		// @25C: iconst_1
		// @25D: istore #17
		// @25F: iload #17
		// @261: getstatic game.C_100277_nc[] game.C_100103_eh.field_104668_a
		// @264: arraylength
		// @265: if_icmpge @287
		// @268: aload_2
		// @269: iload #17
		// @26B: iaload
		// @26C: aload_2
		// @26D: iload #16
		// @26F: iaload
		// @270: iload #19
		// @272: ifne @251
		// @275: if_icmpgt @27B
		// @278: goto @27F
		// @27B: iload #17
		// @27D: istore #16
		// @27F: iinc #17 +1
		// @282: iload #19
		// @284: ifeq @25F
		// @287: aload_2
		// @288: iload #16
		// @28A: ldc -2147483648 (0x80000000)
		// @28C: iastore
		// @28D: getstatic game.C_100277_nc[] game.C_100103_eh.field_104668_a
		// @290: iload #16
		// @292: aaload
		// @293: astore #17
		// @295: iload #16
		// @297: sipush 1100 (0x044C)
		// @29A: invokestatic game.C_100170_cm.func_105535_a(int, int)void
		// @29D: iconst_0
		// @29E: istore #18
		// @2A0: iload #18
		// @2A2: iconst_3
		// @2A3: if_icmpge @2C9
		// @2A6: getstatic int[] game.C_100052_eb.field_104230_e
		// @2A9: iload #18
		// @2AB: dup2
		// @2AC: iaload
		// @2AD: getstatic int[][] game.C_100063_dj.field_104295_c
		// @2B0: iload #15
		// @2B2: aaload
		// @2B3: iload #18
		// @2B5: iaload
		// @2B6: iadd
		// @2B7: iastore
		// @2B8: iinc #18 +1
		// @2BB: iload #19
		// @2BD: ifne @2EF
		// @2C0: iload #19
		// @2C2: ifeq @2A0
		// @2C5: goto @2C9
		// @2C8: athrow
		// @2C9: iconst_0
		// @2CA: getstatic int[] game.C_100327_ib.field_102490_J
		// @2CD: iconst_0
		// @2CE: bipush 7 (0x07)
		// @2D0: getstatic int[] game.C_100052_eb.field_104230_e
		// @2D3: aload #17
		// @2D5: iconst_1
		// @2D6: invokestatic game.C_100283_ni.func_106746_a(boolean, int[], boolean, int, int[], game.C_100277_nc, boolean)void
		// @2D9: ldc -1224802049 (0xb6ff00ff)
		// @2DB: iload #8
		// @2DD: aload #17
		// @2DF: iload #13
		// @2E1: iload #14
		// @2E3: iload #12
		// @2E5: iload #9
		// @2E7: iload #7
		// @2E9: invokestatic game.C_100343_jf.func_104821_a(int, int, game.C_100277_nc, int, int, int, int, int)void
		// @2EC: iinc #15 +1
		// @2EF: iload #19
		// @2F1: ifeq @247
		// @2F4: goto @318
		// @2F7: astore_1
		// @2F8: aload_1
		// @2F9: new java.lang.StringBuilder
		// @2FC: dup
		// @2FD: invokespecial java.lang.StringBuilder.<init>()void
		// @300: getstatic java.lang.String[] game.C_100315_la.field_107181_z
		// @303: iconst_1
		// @304: aaload
		// @305: invokevirtual java.lang.StringBuilder.append(java.lang.String)java.lang.StringBuilder
		// @308: iload_0
		// @309: invokevirtual java.lang.StringBuilder.append(int)java.lang.StringBuilder
		// @30C: bipush 41 (0x29)
		// @30E: invokevirtual java.lang.StringBuilder.append(char)java.lang.StringBuilder
		// @311: invokevirtual java.lang.StringBuilder.toString()java.lang.String
		// @314: invokestatic game.C_100181_cf.func_105695_a(java.lang.Throwable, java.lang.String)game.C_100170_cm
		// @317: athrow
		// @318: return
	}
	
	public static void func_107170_a(int arg0)
	{
		// @00: aconst_null
		// @01: putstatic java.lang.String game.C_100315_la.field_107180_a
		// @04: aconst_null
		// @05: putstatic game.C_100268_mk game.C_100315_la.field_107179_c
		// @08: aconst_null
		// @09: putstatic java.lang.String game.C_100315_la.field_107175_g
		// @0C: iload_0
		// @0D: sipush 24724 (0x6094)
		// @10: if_icmpeq @1C
		// @13: bipush 51 (0x33)
		// @15: invokestatic game.C_100315_la.func_107172_a(byte)void
		// @18: goto @1C
		// @1B: athrow
		// @1C: aconst_null
		// @1D: putstatic java.lang.String game.C_100315_la.field_107174_f
		// @20: aconst_null
		// @21: putstatic java.lang.String game.C_100315_la.field_107176_d
		// @24: aconst_null
		// @25: putstatic int[] game.C_100315_la.field_107178_b
		// @28: goto @4C
		// @2B: astore_1
		// @2C: aload_1
		// @2D: new java.lang.StringBuilder
		// @30: dup
		// @31: invokespecial java.lang.StringBuilder.<init>()void
		// @34: getstatic java.lang.String[] game.C_100315_la.field_107181_z
		// @37: iconst_0
		// @38: aaload
		// @39: invokevirtual java.lang.StringBuilder.append(java.lang.String)java.lang.StringBuilder
		// @3C: iload_0
		// @3D: invokevirtual java.lang.StringBuilder.append(int)java.lang.StringBuilder
		// @40: bipush 41 (0x29)
		// @42: invokevirtual java.lang.StringBuilder.append(char)java.lang.StringBuilder
		// @45: invokevirtual java.lang.StringBuilder.toString()java.lang.String
		// @48: invokestatic game.C_100181_cf.func_105695_a(java.lang.Throwable, java.lang.String)game.C_100170_cm
		// @4B: athrow
		// @4C: return
	}
	
	static
	{
		// @00: iconst_2
		// @01: anewarray java.lang.String
		// @04: dup
		// @05: iconst_0
		// @06: ldc ".}h\u001f6"
		// @08: invokestatic game.C_100315_la.func_107173_z(java.lang.String)char[]
		// @0B: invokestatic game.C_100315_la.func_107171_z(char[])java.lang.String
		// @0E: aastore
		// @0F: dup
		// @10: iconst_1
		// @11: ldc ".}h\u001c6"
		// @13: invokestatic game.C_100315_la.func_107173_z(java.lang.String)char[]
		// @16: invokestatic game.C_100315_la.func_107171_z(char[])java.lang.String
		// @19: aastore
		// @1A: putstatic java.lang.String[] game.C_100315_la.field_107181_z
		// @1D: ldc "\u0012p''{0<\u0008?s'&f"
		// @1F: invokestatic game.C_100315_la.func_107173_z(java.lang.String)char[]
		// @22: invokestatic game.C_100315_la.func_107171_z(char[])java.lang.String
		// @25: putstatic java.lang.String game.C_100315_la.field_107180_a
		// @28: new game.C_100268_mk
		// @2B: dup
		// @2C: invokespecial game.C_100268_mk.<init>()void
		// @2F: putstatic game.C_100268_mk game.C_100315_la.field_107179_c
		// @32: ldc "\u0003p*~y#q#-"
		// @34: invokestatic game.C_100315_la.func_107173_z(java.lang.String)char[]
		// @37: invokestatic game.C_100315_la.func_107171_z(char[])java.lang.String
		// @3A: putstatic java.lang.String game.C_100315_la.field_107174_f
		// @3D: ldc "\u0001S\u000b\u000eQ\u000cY\u0008\nMx"
		// @3F: invokestatic game.C_100315_la.func_107173_z(java.lang.String)char[]
		// @42: invokestatic game.C_100315_la.func_107171_z(char[])java.lang.String
		// @45: putstatic java.lang.String game.C_100315_la.field_107176_d
		// @48: ldc "\u000br0?r+xf0\u007f/y"
		// @4A: invokestatic game.C_100315_la.func_107173_z(java.lang.String)char[]
		// @4D: invokestatic game.C_100315_la.func_107171_z(char[])java.lang.String
		// @50: putstatic java.lang.String game.C_100315_la.field_107175_g
		// @53: return
	}
	
	private static char[] func_107173_z(String arg0)
	{
		// @00: aload_0
		// @01: invokevirtual java.lang.String.toCharArray()char[]
		// @04: dup
		// @05: arraylength
		// @06: iconst_2
		// @07: if_icmpge @13
		// @0A: dup
		// @0B: iconst_0
		// @0C: dup2
		// @0D: caload
		// @0E: bipush 30 (0x1E)
		// @10: ixor
		// @11: i2c
		// @12: castore
		// @13: areturn
	}
	
	private static String func_107171_z(char[] arg0)
	{
		// @00: aload_0
		// @01: dup
		// @02: arraylength
		// @03: swap
		// @04: iconst_0
		// @05: istore_1
		// @06: goto @4C
		// @09: dup
		// @0A: iload_1
		// @0B: dup2
		// @0C: caload
		// @0D: iload_1
		// @0E: iconst_5
		// @0F: irem
		// @10: tableswitch def: @44, for 0: @30, for 1: @35, for 2: @3A, for 3: @3F
		// @30: bipush 66 (0x42)
		// @32: goto @46
		// @35: bipush 28 (0x1C)
		// @37: goto @46
		// @3A: bipush 70 (0x46)
		// @3C: goto @46
		// @3F: bipush 94 (0x5E)
		// @41: goto @46
		// @44: bipush 30 (0x1E)
		// @46: ixor
		// @47: i2c
		// @48: castore
		// @49: iinc #1 +1
		// @4C: swap
		// @4D: dup_x1
		// @4E: iload_1
		// @4F: if_icmpgt @09
		// @52: new java.lang.String
		// @55: dup_x1
		// @56: swap
		// @57: invokespecial java.lang.String.<init>(char[])void
		// @5A: invokevirtual java.lang.String.intern()java.lang.String
		// @5D: areturn
	}
}
