package game;

final class C_100021_wn
{
	static boolean field_103871_b;
	static String field_103872_c;
	static String field_103869_d;
	static C_100265_mh field_103868_f;
	static int[] field_103870_e;
	static String[][] field_103873_a;
	private static final String[] field_103874_z;
	
	static final C_100037_wb func_103861_a(byte arg0, String arg1, C_100098_h arg2, String arg3)
	{
		// @00: iload_0
		// @01: bipush 80 (0x50)
		// @03: if_icmpgt @11
		// @06: aconst_null
		// @07: checkcast java.lang.String
		// @0A: putstatic java.lang.String game.C_100021_wn.field_103869_d
		// @0D: goto @11
		// @10: athrow
		// @11: aload_2
		// @12: sipush -10719 (0xD621)
		// @15: aload_1
		// @16: invokevirtual game.C_100098_h.func_104601_b(int, java.lang.String)int
		// @19: istore #4
		// @1B: aload_2
		// @1C: aload_3
		// @1D: iload #4
		// @1F: iconst_0
		// @20: invokevirtual game.C_100098_h.func_104600_a(java.lang.String, int, int)int
		// @23: istore #5
		// @25: aload_2
		// @26: iload #5
		// @28: iload #4
		// @2A: sipush 3239 (0x0CA7)
		// @2D: invokestatic game.C_100234_ob.func_106272_a(game.C_100098_h, int, int, int)game.C_100037_wb
		// @30: areturn
		// @31: astore #4
		// @33: aload #4
		// @35: new java.lang.StringBuilder
		// @38: dup
		// @39: invokespecial java.lang.StringBuilder.<init>()void
		// @3C: getstatic java.lang.String[] game.C_100021_wn.field_103874_z
		// @3F: iconst_4
		// @40: aaload
		// @41: invokevirtual java.lang.StringBuilder.append(java.lang.String)java.lang.StringBuilder
		// @44: iload_0
		// @45: invokevirtual java.lang.StringBuilder.append(int)java.lang.StringBuilder
		// @48: bipush 44 (0x2C)
		// @4A: invokevirtual java.lang.StringBuilder.append(char)java.lang.StringBuilder
		// @4D: aload_1
		// @4E: ifnull @5A
		// @51: getstatic java.lang.String[] game.C_100021_wn.field_103874_z
		// @54: iconst_3
		// @55: aaload
		// @56: goto @5F
		// @59: athrow
		// @5A: getstatic java.lang.String[] game.C_100021_wn.field_103874_z
		// @5D: iconst_2
		// @5E: aaload
		// @5F: invokevirtual java.lang.StringBuilder.append(java.lang.String)java.lang.StringBuilder
		// @62: bipush 44 (0x2C)
		// @64: invokevirtual java.lang.StringBuilder.append(char)java.lang.StringBuilder
		// @67: aload_2
		// @68: ifnull @74
		// @6B: getstatic java.lang.String[] game.C_100021_wn.field_103874_z
		// @6E: iconst_3
		// @6F: aaload
		// @70: goto @79
		// @73: athrow
		// @74: getstatic java.lang.String[] game.C_100021_wn.field_103874_z
		// @77: iconst_2
		// @78: aaload
		// @79: invokevirtual java.lang.StringBuilder.append(java.lang.String)java.lang.StringBuilder
		// @7C: bipush 44 (0x2C)
		// @7E: invokevirtual java.lang.StringBuilder.append(char)java.lang.StringBuilder
		// @81: aload_3
		// @82: ifnull @8E
		// @85: getstatic java.lang.String[] game.C_100021_wn.field_103874_z
		// @88: iconst_3
		// @89: aaload
		// @8A: goto @93
		// @8D: athrow
		// @8E: getstatic java.lang.String[] game.C_100021_wn.field_103874_z
		// @91: iconst_2
		// @92: aaload
		// @93: invokevirtual java.lang.StringBuilder.append(java.lang.String)java.lang.StringBuilder
		// @96: bipush 41 (0x29)
		// @98: invokevirtual java.lang.StringBuilder.append(char)java.lang.StringBuilder
		// @9B: invokevirtual java.lang.StringBuilder.toString()java.lang.String
		// @9E: invokestatic game.C_100181_cf.func_105695_a(java.lang.Throwable, java.lang.String)game.C_100170_cm
		// @A1: athrow
	}
	
	static final C_100061_dh func_103860_a(byte arg0, boolean arg1, int arg2)
	{
		// @000: getstatic int game.SteelSentinels.field_105275_O
		// @003: istore #19
		// @005: iload_0
		// @006: bipush 29 (0x1D)
		// @008: if_icmpgt @017
		// @00B: iconst_1
		// @00C: iconst_0
		// @00D: bipush -69 (0xBB)
		// @00F: invokestatic game.C_100021_wn.func_103860_a(byte, boolean, int)game.C_100061_dh
		// @012: pop
		// @013: goto @017
		// @016: athrow
		// @017: getstatic game.C_100100_i game.C_100012_fh.field_100507_G
		// @01A: getfield game.C_100115_ej game.C_100100_i.field_102016_ec
		// @01D: iconst_m1
		// @01E: iconst_2
		// @01F: getstatic int game.C_100033_gj.field_101917_jc
		// @022: iadd
		// @023: iload_2
		// @024: getstatic int game.C_100033_gj.field_101917_jc
		// @027: bipush -2 (0xFE)
		// @029: isub
		// @02A: imul
		// @02B: iconst_3
		// @02C: imul
		// @02D: getstatic game.C_100100_i game.C_100012_fh.field_100507_G
		// @030: getfield game.C_100115_ej game.C_100100_i.field_102016_ec
		// @033: getstatic game.C_100115_ej game.C_100346_ja.field_103486_m
		// @036: if_acmpne @03E
		// @039: iconst_1
		// @03A: goto @03F
		// @03D: athrow
		// @03E: iconst_0
		// @03F: iconst_2
		// @040: iload_1
		// @041: invokevirtual game.C_100115_ej.func_102034_a(int, int, int, boolean, int, boolean)boolean
		// @044: istore_3
		// @045: getstatic game.C_100100_i game.C_100012_fh.field_100507_G
		// @048: getfield game.C_100302_ka game.C_100100_i.field_102015_Yb
		// @04B: getfield game.C_100202_qi game.C_100302_ka.field_101891_Ob
		// @04E: astore #4
		// @050: aconst_null
		// @051: astore #5
		// @053: getstatic int game.C_100062_dk.field_104281_d
		// @056: iconst_2
		// @057: if_icmpne @493
		// @05A: getstatic game.C_100302_ka game.C_100280_nf.field_101176_p
		// @05D: iconst_1
		// @05E: putfield boolean game.C_100302_ka.field_101864_W
		// @061: getstatic game.C_100302_ka game.C_100104_v.field_104690_e
		// @064: sipush -30945 (0x871F)
		// @067: iconst_1
		// @068: anewarray java.lang.String
		// @06B: dup
		// @06C: iconst_0
		// @06D: getstatic java.lang.String game.C_100119_ua.field_104909_i
		// @070: aastore
		// @071: getstatic java.lang.String game.C_100309_lk.field_103269_S
		// @074: invokestatic game.C_100132_td.func_104965_a(int, java.lang.String[], java.lang.String)java.lang.String
		// @077: putfield java.lang.String game.C_100302_ka.field_101890_ab
		// @07A: getstatic game.C_100100_i game.C_100012_fh.field_100507_G
		// @07D: getfield game.C_100115_ej game.C_100100_i.field_102016_ec
		// @080: getfield game.C_100302_ka game.C_100115_ej.field_102040_Zb
		// @083: aconst_null
		// @084: putfield java.lang.String game.C_100302_ka.field_101890_ab
		// @087: aconst_null
		// @088: astore #6
		// @08A: aload #4
		// @08C: bipush 20 (0x14)
		// @08E: invokevirtual game.C_100202_qi.func_105899_c(int)game.C_100158_da
		// @091: checkcast game.C_100061_dh
		// @094: astore #7
		// @096: aload #7
		// @098: ifnull @3EE
		// @09B: iconst_0
		// @09C: istore #8
		// @09E: iload #19
		// @0A0: ifne @43F
		// @0A3: aconst_null
		// @0A4: aload #7
		// @0A6: getfield game.C_100202_qi game.C_100061_dh.field_101891_Ob
		// @0A9: if_acmpne @116
		// @0AC: goto @0B0
		// @0AF: athrow
		// @0B0: aload #7
		// @0B2: new game.C_100302_ka
		// @0B5: dup
		// @0B6: lconst_0
		// @0B7: getstatic game.C_100302_ka game.C_100160_sm.field_105414_e
		// @0BA: invokespecial game.C_100302_ka.<init>(long, game.C_100302_ka)void
		// @0BD: putfield game.C_100302_ka game.C_100061_dh.field_101982_Xb
		// @0C0: aload #7
		// @0C2: bipush -78 (0xB2)
		// @0C4: aload #7
		// @0C6: getfield game.C_100302_ka game.C_100061_dh.field_101982_Xb
		// @0C9: invokevirtual game.C_100061_dh.func_101824_b(int, game.C_100302_ka)void
		// @0CC: aload #7
		// @0CE: new game.C_100302_ka
		// @0D1: dup
		// @0D2: lconst_0
		// @0D3: getstatic game.C_100302_ka game.C_100299_kd.field_107022_C
		// @0D6: invokespecial game.C_100302_ka.<init>(long, game.C_100302_ka)void
		// @0D9: putfield game.C_100302_ka game.C_100061_dh.field_101998_lc
		// @0DC: aload #7
		// @0DE: bipush -127 (0x81)
		// @0E0: aload #7
		// @0E2: getfield game.C_100302_ka game.C_100061_dh.field_101998_lc
		// @0E5: invokevirtual game.C_100061_dh.func_101824_b(int, game.C_100302_ka)void
		// @0E8: aload #7
		// @0EA: new game.C_100302_ka
		// @0ED: dup
		// @0EE: lconst_0
		// @0EF: getstatic game.C_100302_ka game.C_100160_sm.field_105414_e
		// @0F2: invokespecial game.C_100302_ka.<init>(long, game.C_100302_ka)void
		// @0F5: putfield game.C_100302_ka game.C_100061_dh.field_101999_bc
		// @0F8: aload #7
		// @0FA: bipush -106 (0x96)
		// @0FC: aload #7
		// @0FE: getfield game.C_100302_ka game.C_100061_dh.field_101999_bc
		// @101: invokevirtual game.C_100061_dh.func_101824_b(int, game.C_100302_ka)void
		// @104: aload #7
		// @106: getfield game.C_100302_ka game.C_100061_dh.field_101998_lc
		// @109: iconst_2
		// @10A: putfield int game.C_100302_ka.field_101850_Fb
		// @10D: aload #7
		// @10F: iconst_0
		// @110: invokevirtual game.C_100061_dh.func_101821_k(int)void
		// @113: iconst_1
		// @114: istore #8
		// @116: aload #7
		// @118: getstatic game.C_100100_i game.C_100012_fh.field_100507_G
		// @11B: getfield game.C_100302_ka game.C_100100_i.field_102015_Yb
		// @11E: getfield int game.C_100302_ka.field_101886_Kb
		// @121: putfield int game.C_100061_dh.field_101886_Kb
		// @124: iconst_0
		// @125: istore #9
		// @127: aload #7
		// @129: getfield java.lang.String game.C_100061_dh.field_101996_kc
		// @12C: ifnonnull @13C
		// @12F: ldc 13369344 (0xcc0000)
		// @131: istore #10
		// @133: ldc 16737894 (0xff6666)
		// @135: istore #11
		// @137: iload #19
		// @139: ifeq @160
		// @13C: aload #7
		// @13E: getfield java.lang.String game.C_100061_dh.field_101996_kc
		// @141: getstatic java.lang.String game.C_100119_ua.field_104909_i
		// @144: if_acmpeq @158
		// @147: goto @14B
		// @14A: athrow
		// @14B: ldc 13421568 (0xcccc00)
		// @14D: istore #10
		// @14F: ldc 16777062 (0xffff66)
		// @151: istore #11
		// @153: iload #19
		// @155: ifeq @160
		// @158: ldc 52224 (0xcc00)
		// @15A: istore #10
		// @15C: ldc 6750054 (0x66ff66)
		// @15E: istore #11
		// @160: iconst_0
		// @161: istore #12
		// @163: aconst_null
		// @164: aload #7
		// @166: getfield java.lang.String game.C_100061_dh.field_101997_ac
		// @169: if_acmpeq @1B0
		// @16C: aload #7
		// @16E: getfield java.lang.String game.C_100061_dh.field_101997_ac
		// @171: ldc ""
		// @173: invokevirtual java.lang.String.equals(java.lang.Object)boolean
		// @176: ifeq @181
		// @179: goto @17D
		// @17C: athrow
		// @17D: goto @1B0
		// @180: athrow
		// @181: aload #7
		// @183: getfield game.C_100302_ka game.C_100061_dh.field_101999_bc
		// @186: iload #11
		// @188: putfield int game.C_100302_ka.field_101860_K
		// @18B: aload #7
		// @18D: getfield game.C_100302_ka game.C_100061_dh.field_101999_bc
		// @190: getstatic game.C_100037_wb game.C_100063_dj.field_104291_g
		// @193: putfield game.C_100037_wb game.C_100302_ka.field_101887_nb
		// @196: iconst_1
		// @197: istore #12
		// @199: aload #7
		// @19B: getfield game.C_100302_ka game.C_100061_dh.field_101999_bc
		// @19E: iconst_0
		// @19F: getstatic int game.C_100033_gj.field_101917_jc
		// @1A2: iconst_m1
		// @1A3: iload #9
		// @1A5: getstatic game.C_100037_wb game.C_100063_dj.field_104291_g
		// @1A8: getfield int game.C_100037_wb.field_102341_y
		// @1AB: iconst_3
		// @1AC: iadd
		// @1AD: invokevirtual game.C_100302_ka.func_101825_a(int, int, int, int, int)void
		// @1B0: aload #7
		// @1B2: getfield game.C_100302_ka game.C_100061_dh.field_101982_Xb
		// @1B5: aload #7
		// @1B7: getfield game.C_100302_ka game.C_100061_dh.field_101998_lc
		// @1BA: iload #11
		// @1BC: dup_x1
		// @1BD: putfield int game.C_100302_ka.field_101860_K
		// @1C0: putfield int game.C_100302_ka.field_101860_K
		// @1C3: aload #7
		// @1C5: getfield game.C_100302_ka game.C_100061_dh.field_101982_Xb
		// @1C8: aload #7
		// @1CA: getfield game.C_100302_ka game.C_100061_dh.field_101998_lc
		// @1CD: iload #11
		// @1CF: dup_x1
		// @1D0: putfield int game.C_100302_ka.field_101868_Ab
		// @1D3: putfield int game.C_100302_ka.field_101868_Ab
		// @1D6: aload #7
		// @1D8: getfield game.C_100302_ka game.C_100061_dh.field_101982_Xb
		// @1DB: aload #7
		// @1DD: getfield game.C_100302_ka game.C_100061_dh.field_101998_lc
		// @1E0: iload #10
		// @1E2: dup_x1
		// @1E3: putfield int game.C_100302_ka.field_101830_gb
		// @1E6: putfield int game.C_100302_ka.field_101830_gb
		// @1E9: aload #7
		// @1EB: getfield game.C_100302_ka game.C_100061_dh.field_101982_Xb
		// @1EE: aload #7
		// @1F0: getfield game.C_100302_ka game.C_100061_dh.field_101998_lc
		// @1F3: iload #11
		// @1F5: dup_x1
		// @1F6: putfield int game.C_100302_ka.field_101872_Nb
		// @1F9: putfield int game.C_100302_ka.field_101872_Nb
		// @1FC: iconst_0
		// @1FD: istore #13
		// @1FF: bipush -82 (0xAE)
		// @201: aload #7
		// @203: getfield int game.C_100061_dh.field_101886_Kb
		// @206: iadd
		// @207: istore #14
		// @209: iload #12
		// @20B: ifeq @21F
		// @20E: iconst_3
		// @20F: getstatic game.C_100037_wb game.C_100063_dj.field_104291_g
		// @212: getfield int game.C_100037_wb.field_102341_y
		// @215: iadd
		// @216: istore #13
		// @218: iload #14
		// @21A: iload #13
		// @21C: isub
		// @21D: istore #14
		// @21F: aload #7
		// @221: getfield game.C_100302_ka game.C_100061_dh.field_101982_Xb
		// @224: iconst_0
		// @225: iload #14
		// @227: if_icmpge @240
		// @22A: aload #7
		// @22C: getfield game.C_100302_ka game.C_100061_dh.field_101982_Xb
		// @22F: getfield game.C_100112_r game.C_100302_ka.field_101845_sb
		// @232: aload #7
		// @234: getfield java.lang.String game.C_100061_dh.field_101993_nc
		// @237: iload #14
		// @239: invokestatic game.C_100112_r.func_101748_a(game.C_100112_r, java.lang.String, int)java.lang.String
		// @23C: goto @245
		// @23F: athrow
		// @240: aload #7
		// @242: getfield java.lang.String game.C_100061_dh.field_101993_nc
		// @245: putfield java.lang.String game.C_100302_ka.field_101890_ab
		// @248: aload #7
		// @24A: getfield game.C_100302_ka game.C_100061_dh.field_101982_Xb
		// @24D: iload #13
		// @24F: getstatic int game.C_100033_gj.field_101917_jc
		// @252: iconst_m1
		// @253: iload #9
		// @255: iload #14
		// @257: invokevirtual game.C_100302_ka.func_101825_a(int, int, int, int, int)void
		// @25A: aload #7
		// @25C: getfield game.C_100302_ka game.C_100061_dh.field_101998_lc
		// @25F: aload #7
		// @261: getfield java.lang.String game.C_100061_dh.field_101996_kc
		// @264: ifnull @270
		// @267: aload #7
		// @269: getfield java.lang.String game.C_100061_dh.field_101996_kc
		// @26C: goto @273
		// @26F: athrow
		// @270: getstatic java.lang.String game.C_100027_hc.field_102593_T
		// @273: putfield java.lang.String game.C_100302_ka.field_101890_ab
		// @276: aload #7
		// @278: getfield game.C_100302_ka game.C_100061_dh.field_101998_lc
		// @27B: aload #7
		// @27D: getfield int game.C_100061_dh.field_101886_Kb
		// @280: bipush -80 (0xB0)
		// @282: iadd
		// @283: getstatic int game.C_100033_gj.field_101917_jc
		// @286: iconst_m1
		// @287: iload #9
		// @289: bipush 80 (0x50)
		// @28B: invokevirtual game.C_100302_ka.func_101825_a(int, int, int, int, int)void
		// @28E: aload #7
		// @290: getfield game.C_100302_ka game.C_100061_dh.field_101982_Xb
		// @293: getfield java.lang.String game.C_100302_ka.field_101890_ab
		// @296: aload #7
		// @298: getfield java.lang.String game.C_100061_dh.field_101993_nc
		// @29B: invokevirtual java.lang.String.equals(java.lang.Object)boolean
		// @29E: ifne @2A6
		// @2A1: iconst_1
		// @2A2: goto @2A7
		// @2A5: athrow
		// @2A6: iconst_0
		// @2A7: istore #15
		// @2A9: iload #9
		// @2AB: getstatic int game.C_100033_gj.field_101917_jc
		// @2AE: iadd
		// @2AF: istore #9
		// @2B1: iload_3
		// @2B2: ifne @2C7
		// @2B5: aload #7
		// @2B7: aload #7
		// @2B9: getfield int game.C_100061_dh.field_101848_lb
		// @2BC: ineg
		// @2BD: iload #9
		// @2BF: iadd
		// @2C0: putfield int game.C_100061_dh.field_101832_tb
		// @2C3: goto @2C7
		// @2C6: athrow
		// @2C7: iload #8
		// @2C9: ifne @2D0
		// @2CC: goto @2DF
		// @2CF: athrow
		// @2D0: getstatic game.C_100100_i game.C_100012_fh.field_100507_G
		// @2D3: getfield game.C_100302_ka game.C_100100_i.field_102015_Yb
		// @2D6: aload #7
		// @2D8: iconst_0
		// @2D9: aload #6
		// @2DB: iconst_2
		// @2DC: invokevirtual game.C_100302_ka.func_101823_a(game.C_100302_ka, boolean, game.C_100302_ka, int)void
		// @2DF: aload #7
		// @2E1: astore #6
		// @2E3: aload #7
		// @2E5: getfield game.C_100302_ka game.C_100061_dh.field_101999_bc
		// @2E8: ifnull @30B
		// @2EB: aload #7
		// @2ED: getfield game.C_100302_ka game.C_100061_dh.field_101999_bc
		// @2F0: getfield boolean game.C_100302_ka.field_101839_db
		// @2F3: ifeq @30B
		// @2F6: goto @2FA
		// @2F9: athrow
		// @2FA: aload #7
		// @2FC: getfield java.lang.String game.C_100061_dh.field_101997_ac
		// @2FF: putstatic java.lang.String game.C_100321_hi.field_107220_c
		// @302: iload #19
		// @304: ifeq @3DD
		// @307: goto @30B
		// @30A: athrow
		// @30B: iconst_m1
		// @30C: aload #7
		// @30E: getfield int game.C_100061_dh.field_101854_N
		// @311: iconst_m1
		// @312: ixor
		// @313: if_icmpeq @3B9
		// @316: goto @31A
		// @319: athrow
		// @31A: aload #7
		// @31C: getfield java.lang.String game.C_100061_dh.field_101993_nc
		// @31F: astore #16
		// @321: aconst_null
		// @322: iconst_m1
		// @323: lconst_0
		// @324: bipush -118 (0x8A)
		// @326: iconst_m1
		// @327: aconst_null
		// @328: aload #16
		// @32A: aload #7
		// @32C: getstatic game.C_100100_i game.C_100012_fh.field_100507_G
		// @32F: getfield game.C_100115_ej game.C_100100_i.field_102016_ec
		// @332: invokestatic game.C_100096_un.func_104559_a(java.lang.String, int, long, int, int, int[], java.lang.String, game.C_100302_ka, game.C_100115_ej)void
		// @335: aload #7
		// @337: astore #5
		// @339: aload #7
		// @33B: getfield java.lang.String game.C_100061_dh.field_101996_kc
		// @33E: ifnull @3B4
		// @341: iconst_2
		// @342: getstatic game.C_100022_hf game.C_100136_th.field_102623_R
		// @345: getfield java.lang.String game.C_100022_hf.field_103901_o
		// @348: invokestatic game.C_100312_ld.func_107150_a(int, java.lang.String)boolean
		// @34B: ifne @3B4
		// @34E: goto @352
		// @351: athrow
		// @352: getstatic boolean game.C_100272_mn.field_102435_K
		// @355: ifeq @360
		// @358: goto @35C
		// @35B: athrow
		// @35C: goto @3B4
		// @35F: athrow
		// @360: getstatic boolean game.C_100164_se.field_105449_g
		// @363: ifne @38D
		// @366: getstatic game.C_100022_hf game.C_100136_th.field_102623_R
		// @369: astore #17
		// @36B: sipush -30945 (0x871F)
		// @36E: iconst_1
		// @36F: anewarray java.lang.String
		// @372: dup
		// @373: iconst_0
		// @374: aload #16
		// @376: aastore
		// @377: getstatic java.lang.String game.C_100233_oa.field_106238_e
		// @37A: invokestatic game.C_100132_td.func_104965_a(int, java.lang.String[], java.lang.String)java.lang.String
		// @37D: astore #18
		// @37F: aload #17
		// @381: getfield game.C_100270_mi game.C_100022_hf.field_103903_m
		// @384: bipush 63 (0x3F)
		// @386: bipush 8 (0x08)
		// @388: aload #18
		// @38A: invokevirtual game.C_100270_mi.func_102250_a(int, int, java.lang.String)void
		// @38D: getstatic game.C_100022_hf game.C_100136_th.field_102623_R
		// @390: astore #17
		// @392: sipush -30945 (0x871F)
		// @395: iconst_1
		// @396: anewarray java.lang.String
		// @399: dup
		// @39A: iconst_0
		// @39B: aload #16
		// @39D: aastore
		// @39E: getstatic java.lang.String game.C_100227_af.field_106169_c
		// @3A1: invokestatic game.C_100132_td.func_104965_a(int, java.lang.String[], java.lang.String)java.lang.String
		// @3A4: astore #18
		// @3A6: aload #17
		// @3A8: getfield game.C_100270_mi game.C_100022_hf.field_103903_m
		// @3AB: bipush 107 (0x6B)
		// @3AD: bipush 18 (0x12)
		// @3AF: aload #18
		// @3B1: invokevirtual game.C_100270_mi.func_102250_a(int, int, java.lang.String)void
		// @3B4: iload #19
		// @3B6: ifeq @3DD
		// @3B9: aload #7
		// @3BB: getfield game.C_100302_ka game.C_100061_dh.field_101982_Xb
		// @3BE: getfield boolean game.C_100302_ka.field_101839_db
		// @3C1: ifeq @3DD
		// @3C4: goto @3C8
		// @3C7: athrow
		// @3C8: iload #15
		// @3CA: ifne @3D5
		// @3CD: goto @3D1
		// @3D0: athrow
		// @3D1: goto @3DD
		// @3D4: athrow
		// @3D5: aload #7
		// @3D7: getfield java.lang.String game.C_100061_dh.field_101993_nc
		// @3DA: putstatic java.lang.String game.C_100321_hi.field_107220_c
		// @3DD: aload #4
		// @3DF: bipush 36 (0x24)
		// @3E1: invokevirtual game.C_100202_qi.func_105907_c(byte)game.C_100158_da
		// @3E4: checkcast game.C_100061_dh
		// @3E7: astore #7
		// @3E9: iload #19
		// @3EB: ifeq @096
		// @3EE: iconst_m1
		// @3EF: getstatic game.C_100100_i game.C_100012_fh.field_100507_G
		// @3F2: getfield game.C_100302_ka game.C_100100_i.field_102021_Vb
		// @3F5: getfield int game.C_100302_ka.field_101854_N
		// @3F8: iconst_m1
		// @3F9: ixor
		// @3FA: if_icmpeq @43F
		// @3FD: new game.C_100118_ub
		// @400: dup
		// @401: getstatic game.C_100100_i game.C_100012_fh.field_100507_G
		// @404: getfield game.C_100302_ka game.C_100100_i.field_102021_Vb
		// @407: getfield int game.C_100302_ka.field_101840_Eb
		// @40A: getstatic game.C_100100_i game.C_100012_fh.field_100507_G
		// @40D: getfield game.C_100302_ka game.C_100100_i.field_102021_Vb
		// @410: getfield int game.C_100302_ka.field_101835_xb
		// @413: getstatic game.C_100100_i game.C_100012_fh.field_100507_G
		// @416: getfield game.C_100302_ka game.C_100100_i.field_102021_Vb
		// @419: getfield int game.C_100302_ka.field_101886_Kb
		// @41C: getstatic game.C_100100_i game.C_100012_fh.field_100507_G
		// @41F: getfield game.C_100302_ka game.C_100100_i.field_102021_Vb
		// @422: getfield int game.C_100302_ka.field_101848_lb
		// @425: getstatic java.lang.String game.C_100172_ck.field_102114_Yb
		// @428: getstatic game.C_100302_ka game.C_100138_bo.field_100405_b
		// @42B: getstatic game.C_100302_ka game.C_100129_tg.field_102750_sb
		// @42E: getstatic game.C_100302_ka game.C_100129_tg.field_102750_sb
		// @431: invokespecial game.C_100118_ub.<init>(int, int, int, int, java.lang.String, game.C_100302_ka, game.C_100302_ka, game.C_100302_ka)void
		// @434: putstatic game.C_100118_ub game.C_100038_wa.field_104073_n
		// @437: iconst_0
		// @438: putstatic int game.C_100209_qb.field_102688_Kb
		// @43B: goto @43F
		// @43E: athrow
		// @43F: getstatic game.C_100100_i game.C_100012_fh.field_100507_G
		// @442: getfield game.C_100302_ka game.C_100100_i.field_102013_Xb
		// @445: getfield int game.C_100302_ka.field_101854_N
		// @448: iconst_m1
		// @449: ixor
		// @44A: iconst_m1
		// @44B: if_icmpne @452
		// @44E: goto @490
		// @451: athrow
		// @452: new game.C_100118_ub
		// @455: dup
		// @456: getstatic game.C_100100_i game.C_100012_fh.field_100507_G
		// @459: getfield game.C_100302_ka game.C_100100_i.field_102013_Xb
		// @45C: getfield int game.C_100302_ka.field_101840_Eb
		// @45F: getstatic game.C_100100_i game.C_100012_fh.field_100507_G
		// @462: getfield game.C_100302_ka game.C_100100_i.field_102013_Xb
		// @465: getfield int game.C_100302_ka.field_101835_xb
		// @468: getstatic game.C_100100_i game.C_100012_fh.field_100507_G
		// @46B: getfield game.C_100302_ka game.C_100100_i.field_102013_Xb
		// @46E: getfield int game.C_100302_ka.field_101886_Kb
		// @471: getstatic game.C_100100_i game.C_100012_fh.field_100507_G
		// @474: getfield game.C_100302_ka game.C_100100_i.field_102013_Xb
		// @477: getfield int game.C_100302_ka.field_101848_lb
		// @47A: getstatic java.lang.String game.C_100321_hi.field_107221_a
		// @47D: getstatic game.C_100302_ka game.C_100138_bo.field_100405_b
		// @480: getstatic game.C_100302_ka game.C_100129_tg.field_102750_sb
		// @483: getstatic game.C_100302_ka game.C_100129_tg.field_102750_sb
		// @486: invokespecial game.C_100118_ub.<init>(int, int, int, int, java.lang.String, game.C_100302_ka, game.C_100302_ka, game.C_100302_ka)void
		// @489: putstatic game.C_100118_ub game.C_100038_wa.field_104073_n
		// @48C: iconst_1
		// @48D: putstatic int game.C_100209_qb.field_102688_Kb
		// @490: goto @4DF
		// @493: getstatic game.C_100302_ka game.C_100104_v.field_104690_e
		// @496: getstatic java.lang.String game.C_100306_kn.field_107139_j
		// @499: putfield java.lang.String game.C_100302_ka.field_101890_ab
		// @49C: getstatic game.C_100302_ka game.C_100280_nf.field_101176_p
		// @49F: iconst_0
		// @4A0: putfield boolean game.C_100302_ka.field_101864_W
		// @4A3: getstatic int game.C_100062_dk.field_104281_d
		// @4A6: iconst_1
		// @4A7: if_icmpne @4C2
		// @4AA: getstatic game.C_100100_i game.C_100012_fh.field_100507_G
		// @4AD: getfield game.C_100115_ej game.C_100100_i.field_102016_ec
		// @4B0: getfield game.C_100302_ka game.C_100115_ej.field_102040_Zb
		// @4B3: getstatic java.lang.String game.C_100228_nn.field_106194_h
		// @4B6: putfield java.lang.String game.C_100302_ka.field_101890_ab
		// @4B9: iload #19
		// @4BB: ifeq @4D5
		// @4BE: goto @4C2
		// @4C1: athrow
		// @4C2: getstatic game.C_100100_i game.C_100012_fh.field_100507_G
		// @4C5: getfield game.C_100115_ej game.C_100100_i.field_102016_ec
		// @4C8: getfield game.C_100302_ka game.C_100115_ej.field_102040_Zb
		// @4CB: getstatic java.lang.String game.C_100185_rm.field_105485_e
		// @4CE: putfield java.lang.String game.C_100302_ka.field_101890_ab
		// @4D1: goto @4D5
		// @4D4: athrow
		// @4D5: iconst_1
		// @4D6: getstatic game.C_100100_i game.C_100012_fh.field_100507_G
		// @4D9: getfield game.C_100302_ka game.C_100100_i.field_102015_Yb
		// @4DC: invokestatic game.C_100107_u.func_104760_a(boolean, game.C_100302_ka)void
		// @4DF: aload #5
		// @4E1: areturn
		// @4E2: astore_3
		// @4E3: aload_3
		// @4E4: new java.lang.StringBuilder
		// @4E7: dup
		// @4E8: invokespecial java.lang.StringBuilder.<init>()void
		// @4EB: getstatic java.lang.String[] game.C_100021_wn.field_103874_z
		// @4EE: bipush 7 (0x07)
		// @4F0: aaload
		// @4F1: invokevirtual java.lang.StringBuilder.append(java.lang.String)java.lang.StringBuilder
		// @4F4: iload_0
		// @4F5: invokevirtual java.lang.StringBuilder.append(int)java.lang.StringBuilder
		// @4F8: bipush 44 (0x2C)
		// @4FA: invokevirtual java.lang.StringBuilder.append(char)java.lang.StringBuilder
		// @4FD: iload_1
		// @4FE: invokevirtual java.lang.StringBuilder.append(boolean)java.lang.StringBuilder
		// @501: bipush 44 (0x2C)
		// @503: invokevirtual java.lang.StringBuilder.append(char)java.lang.StringBuilder
		// @506: iload_2
		// @507: invokevirtual java.lang.StringBuilder.append(int)java.lang.StringBuilder
		// @50A: bipush 41 (0x29)
		// @50C: invokevirtual java.lang.StringBuilder.append(char)java.lang.StringBuilder
		// @50F: invokevirtual java.lang.StringBuilder.toString()java.lang.String
		// @512: invokestatic game.C_100181_cf.func_105695_a(java.lang.Throwable, java.lang.String)game.C_100170_cm
		// @515: athrow
	}
	
	public static void func_103864_a(byte arg0)
	{
		// @00: aconst_null
		// @01: putstatic java.lang.String game.C_100021_wn.field_103872_c
		// @04: aconst_null
		// @05: putstatic int[] game.C_100021_wn.field_103870_e
		// @08: aconst_null
		// @09: putstatic java.lang.String game.C_100021_wn.field_103869_d
		// @0C: iload_0
		// @0D: bipush -123 (0x85)
		// @0F: if_icmpeq @13
		// @12: return
		// @13: aconst_null
		// @14: putstatic game.C_100265_mh game.C_100021_wn.field_103868_f
		// @17: aconst_null
		// @18: checkcast java.lang.String[][]
		// @1B: putstatic java.lang.String[][] game.C_100021_wn.field_103873_a
		// @1E: goto @42
		// @21: astore_1
		// @22: aload_1
		// @23: new java.lang.StringBuilder
		// @26: dup
		// @27: invokespecial java.lang.StringBuilder.<init>()void
		// @2A: getstatic java.lang.String[] game.C_100021_wn.field_103874_z
		// @2D: iconst_1
		// @2E: aaload
		// @2F: invokevirtual java.lang.StringBuilder.append(java.lang.String)java.lang.StringBuilder
		// @32: iload_0
		// @33: invokevirtual java.lang.StringBuilder.append(int)java.lang.StringBuilder
		// @36: bipush 41 (0x29)
		// @38: invokevirtual java.lang.StringBuilder.append(char)java.lang.StringBuilder
		// @3B: invokevirtual java.lang.StringBuilder.toString()java.lang.String
		// @3E: invokestatic game.C_100181_cf.func_105695_a(java.lang.Throwable, java.lang.String)game.C_100170_cm
		// @41: athrow
		// @42: return
	}
	
	static final C_100096_un func_103866_a(int arg0, String arg1)
	{
		// @00: getstatic game.C_100068_vc game.C_100191_rg.field_100845_o
		// @03: getstatic game.C_100068_vc game.C_100148_bh.field_101797_B
		// @06: if_acmpeq @0D
		// @09: goto @0F
		// @0C: athrow
		// @0D: aconst_null
		// @0E: areturn
		// @0F: iload_0
		// @10: sipush -9031 (0xDCB9)
		// @13: if_icmpeq @2C
		// @16: bipush -69 (0xBB)
		// @18: aconst_null
		// @19: checkcast java.lang.String
		// @1C: aconst_null
		// @1D: checkcast game.C_100098_h
		// @20: aconst_null
		// @21: checkcast java.lang.String
		// @24: invokestatic game.C_100021_wn.func_103861_a(byte, java.lang.String, game.C_100098_h, java.lang.String)game.C_100037_wb
		// @27: pop
		// @28: goto @2C
		// @2B: athrow
		// @2C: getstatic game.C_100068_vc game.C_100191_rg.field_100845_o
		// @2F: getstatic game.C_100068_vc game.C_100213_ak.field_105993_g
		// @32: if_acmpne @4D
		// @35: aload_1
		// @36: getstatic java.lang.String game.C_100061_dh.field_101989_ic
		// @39: invokevirtual java.lang.String.equals(java.lang.Object)boolean
		// @3C: ifeq @4D
		// @3F: goto @43
		// @42: athrow
		// @43: getstatic game.C_100068_vc game.C_100220_ac.field_106056_e
		// @46: putstatic game.C_100068_vc game.C_100191_rg.field_100845_o
		// @49: getstatic game.C_100096_un game.C_100077_d.field_103320_W
		// @4C: areturn
		// @4D: aload_1
		// @4E: putstatic java.lang.String game.C_100061_dh.field_101989_ic
		// @51: aconst_null
		// @52: putstatic game.C_100096_un game.C_100077_d.field_103320_W
		// @55: getstatic game.C_100068_vc game.C_100148_bh.field_101797_B
		// @58: putstatic game.C_100068_vc game.C_100191_rg.field_100845_o
		// @5B: aconst_null
		// @5C: areturn
		// @5D: astore_2
		// @5E: aload_2
		// @5F: new java.lang.StringBuilder
		// @62: dup
		// @63: invokespecial java.lang.StringBuilder.<init>()void
		// @66: getstatic java.lang.String[] game.C_100021_wn.field_103874_z
		// @69: iconst_5
		// @6A: aaload
		// @6B: invokevirtual java.lang.StringBuilder.append(java.lang.String)java.lang.StringBuilder
		// @6E: iload_0
		// @6F: invokevirtual java.lang.StringBuilder.append(int)java.lang.StringBuilder
		// @72: bipush 44 (0x2C)
		// @74: invokevirtual java.lang.StringBuilder.append(char)java.lang.StringBuilder
		// @77: aload_1
		// @78: ifnull @84
		// @7B: getstatic java.lang.String[] game.C_100021_wn.field_103874_z
		// @7E: iconst_3
		// @7F: aaload
		// @80: goto @89
		// @83: athrow
		// @84: getstatic java.lang.String[] game.C_100021_wn.field_103874_z
		// @87: iconst_2
		// @88: aaload
		// @89: invokevirtual java.lang.StringBuilder.append(java.lang.String)java.lang.StringBuilder
		// @8C: bipush 41 (0x29)
		// @8E: invokevirtual java.lang.StringBuilder.append(char)java.lang.StringBuilder
		// @91: invokevirtual java.lang.StringBuilder.toString()java.lang.String
		// @94: invokestatic game.C_100181_cf.func_105695_a(java.lang.Throwable, java.lang.String)game.C_100170_cm
		// @97: athrow
	}
	
	static final int func_103867_a(int arg0, int arg1)
	{
		// @00: iinc #0 +239
		// @03: iload_0
		// @04: iflt @1D
		// @07: iload_0
		// @08: iconst_m1
		// @09: ixor
		// @0A: getstatic int[] game.C_100001_ge.field_100562_d
		// @0D: arraylength
		// @0E: iconst_m1
		// @0F: ixor
		// @10: if_icmple @1D
		// @13: goto @17
		// @16: athrow
		// @17: getstatic int[] game.C_100001_ge.field_100562_d
		// @1A: iload_0
		// @1B: iaload
		// @1C: ireturn
		// @1D: iload_1
		// @1E: sipush -8444 (0xDF04)
		// @21: if_icmpeq @2F
		// @24: aconst_null
		// @25: checkcast game.C_100265_mh
		// @28: putstatic game.C_100265_mh game.C_100021_wn.field_103868_f
		// @2B: goto @2F
		// @2E: athrow
		// @2F: iconst_m1
		// @30: ireturn
		// @31: astore_2
		// @32: aload_2
		// @33: new java.lang.StringBuilder
		// @36: dup
		// @37: invokespecial java.lang.StringBuilder.<init>()void
		// @3A: getstatic java.lang.String[] game.C_100021_wn.field_103874_z
		// @3D: bipush 6 (0x06)
		// @3F: aaload
		// @40: invokevirtual java.lang.StringBuilder.append(java.lang.String)java.lang.StringBuilder
		// @43: iload_0
		// @44: invokevirtual java.lang.StringBuilder.append(int)java.lang.StringBuilder
		// @47: bipush 44 (0x2C)
		// @49: invokevirtual java.lang.StringBuilder.append(char)java.lang.StringBuilder
		// @4C: iload_1
		// @4D: invokevirtual java.lang.StringBuilder.append(int)java.lang.StringBuilder
		// @50: bipush 41 (0x29)
		// @52: invokevirtual java.lang.StringBuilder.append(char)java.lang.StringBuilder
		// @55: invokevirtual java.lang.StringBuilder.toString()java.lang.String
		// @58: invokestatic game.C_100181_cf.func_105695_a(java.lang.Throwable, java.lang.String)game.C_100170_cm
		// @5B: athrow
	}
	
	static final void func_103862_a(int arg0)
	{
		// @00: getstatic game.C_100302_ka game.C_100097_k.field_104578_f
		// @03: getstatic game.C_100302_ka game.C_100151_bc.field_102932_cb
		// @06: getstatic game.C_100302_ka game.C_100085_a.field_102572_O
		// @09: bipush 44 (0x2C)
		// @0B: getstatic game.C_100302_ka game.C_100129_tg.field_102750_sb
		// @0E: invokestatic game.C_100045_vj.func_100600_a(game.C_100302_ka, game.C_100302_ka, game.C_100302_ka, byte, game.C_100302_ka)void
		// @11: iload_0
		// @12: sipush 200 (0x00C8)
		// @15: if_icmpeq @1F
		// @18: aconst_null
		// @19: checkcast java.lang.String
		// @1C: putstatic java.lang.String game.C_100021_wn.field_103872_c
		// @1F: goto @43
		// @22: astore_1
		// @23: aload_1
		// @24: new java.lang.StringBuilder
		// @27: dup
		// @28: invokespecial java.lang.StringBuilder.<init>()void
		// @2B: getstatic java.lang.String[] game.C_100021_wn.field_103874_z
		// @2E: iconst_0
		// @2F: aaload
		// @30: invokevirtual java.lang.StringBuilder.append(java.lang.String)java.lang.StringBuilder
		// @33: iload_0
		// @34: invokevirtual java.lang.StringBuilder.append(int)java.lang.StringBuilder
		// @37: bipush 41 (0x29)
		// @39: invokevirtual java.lang.StringBuilder.append(char)java.lang.StringBuilder
		// @3C: invokevirtual java.lang.StringBuilder.toString()java.lang.String
		// @3F: invokestatic game.C_100181_cf.func_105695_a(java.lang.Throwable, java.lang.String)game.C_100170_cm
		// @42: athrow
		// @43: return
	}
	
	static
	{
		// @000: bipush 8 (0x08)
		// @002: anewarray java.lang.String
		// @005: dup
		// @006: iconst_0
		// @007: ldc "3\u0005\u0002\u007fX"
		// @009: invokestatic game.C_100021_wn.func_103865_z(java.lang.String)char[]
		// @00C: invokestatic game.C_100021_wn.func_103863_z(char[])java.lang.String
		// @00F: aastore
		// @010: dup
		// @011: iconst_1
		// @012: ldc "3\u0005\u0002~X"
		// @014: invokestatic game.C_100021_wn.func_103865_z(java.lang.String)char[]
		// @017: invokestatic game.C_100021_wn.func_103863_z(char[])java.lang.String
		// @01A: aastore
		// @01B: dup
		// @01C: iconst_2
		// @01D: ldc "*\u001e@V"
		// @01F: invokestatic game.C_100021_wn.func_103865_z(java.lang.String)char[]
		// @022: invokestatic game.C_100021_wn.func_103863_z(char[])java.lang.String
		// @025: aastore
		// @026: dup
		// @027: iconst_3
		// @028: ldc "?E\u0002\u0014\r"
		// @02A: invokestatic game.C_100021_wn.func_103865_z(java.lang.String)char[]
		// @02D: invokestatic game.C_100021_wn.func_103863_z(char[])java.lang.String
		// @030: aastore
		// @031: dup
		// @032: iconst_4
		// @033: ldc "3\u0005\u0002{X"
		// @035: invokestatic game.C_100021_wn.func_103865_z(java.lang.String)char[]
		// @038: invokestatic game.C_100021_wn.func_103863_z(char[])java.lang.String
		// @03B: aastore
		// @03C: dup
		// @03D: iconst_5
		// @03E: ldc "3\u0005\u0002xX"
		// @040: invokestatic game.C_100021_wn.func_103865_z(java.lang.String)char[]
		// @043: invokestatic game.C_100021_wn.func_103863_z(char[])java.lang.String
		// @046: aastore
		// @047: dup
		// @048: bipush 6 (0x06)
		// @04A: ldc "3\u0005\u0002|X"
		// @04C: invokestatic game.C_100021_wn.func_103865_z(java.lang.String)char[]
		// @04F: invokestatic game.C_100021_wn.func_103863_z(char[])java.lang.String
		// @052: aastore
		// @053: dup
		// @054: bipush 7 (0x07)
		// @056: ldc "3\u0005\u0002yX"
		// @058: invokestatic game.C_100021_wn.func_103865_z(java.lang.String)char[]
		// @05B: invokestatic game.C_100021_wn.func_103863_z(char[])java.lang.String
		// @05E: aastore
		// @05F: putstatic java.lang.String[] game.C_100021_wn.field_103874_z
		// @062: ldc "\u0011\u0005JU\u00020\u001eB[\u0004!\u0007U\u001a\t+\u001e^\u001a\u0013+\u0005JS\u00171\u0019MN\u0019+\u0005\u000c^\u001f!\u0018B\u001d\u0004d\u0018YJ\u0000+\u0019X\u001a\u00161\u0007@I\u00136\u000eITP)\u0004H_^"
		// @064: invokestatic game.C_100021_wn.func_103865_z(java.lang.String)char[]
		// @067: invokestatic game.C_100021_wn.func_103863_z(char[])java.lang.String
		// @06A: putstatic java.lang.String game.C_100021_wn.field_103872_c
		// @06D: ldc "\n\u0004X\u001a\t!\u001f\u000c[\u0013,\u0002IL\u0015 "
		// @06F: invokestatic game.C_100021_wn.func_103865_z(java.lang.String)char[]
		// @072: invokestatic game.C_100021_wn.func_103863_z(char[])java.lang.String
		// @075: putstatic java.lang.String game.C_100021_wn.field_103869_d
		// @078: iconst_0
		// @079: putstatic boolean game.C_100021_wn.field_103871_b
		// @07C: iconst_3
		// @07D: anewarray java.lang.String[]
		// @080: dup
		// @081: iconst_0
		// @082: iconst_2
		// @083: anewarray java.lang.String
		// @086: dup
		// @087: iconst_0
		// @088: ldc "\u0010\nON\u0019'\n@\u0006\u00126UxM\u001fi\u0018IY\u001f*\u000f\u000c^\u0015(\nU\u001a\u0012!\rCH\u0015d\nON\u0019+\u0005_"
		// @08A: invokestatic game.C_100021_wn.func_103865_z(java.lang.String)char[]
		// @08D: invokestatic game.C_100021_wn.func_103863_z(char[])java.lang.String
		// @090: aastore
		// @091: dup
		// @092: iconst_1
		// @093: ldc "\u0005\u0008XS\u001f*WNHN\u0012\u000e^CP(\u0002XN\u001c!KH_\u001c%\u0012\u000cX\u0015\"\u0004^_P%\u0008XS\u001f*\u0018\u0002\u0006\u00126U\u0010Y\u001f(VJ\\@t[\u001c\u0004$,\u0002_\u001a\u001d+\u000fI\u001a\u00197KCT\u001c=K^_\u0013+\u0006A_\u001e \u000eH\u001a\u0019\"KUU\u0005d\u0003ML\u0015d\n\u000c]\u001f+\u000f\u000cS\u001e0\u000e^T\u00150KOU\u001e*\u000eON\u0019+\u0005\u0002\u0006_'\u0004@\u0004"
		// @095: invokestatic game.C_100021_wn.func_103865_z(java.lang.String)char[]
		// @098: invokestatic game.C_100021_wn.func_103863_z(char[])java.lang.String
		// @09B: aastore
		// @09C: aastore
		// @09D: dup
		// @09E: iconst_1
		// @09F: iconst_5
		// @0A0: anewarray java.lang.String
		// @0A3: dup
		// @0A4: iconst_0
		// @0A5: ldc "\u000b\u0005@CP0\u0003I\u001a\u0014!\rMO\u001c0KZ_\u00027\u0002CT\u0003d\u0004J\u001a\u0004,\u000e\u000ci\u001c%\u001dI\u0016P\u0005\u001aYS\u001c%KMT\u0014d,CV\u0015)KMH\u0015d\n@V\u001f3\u000eH\u001a\u0007-\u001fDS\u001ed\u0018A[\u001c(\u000e^\u001a\u0012%\u001fXV\u00157E"
		// @0A7: invokestatic game.C_100021_wn.func_103865_z(java.lang.String)char[]
		// @0AA: invokestatic game.C_100021_wn.func_103863_z(char[])java.lang.String
		// @0AD: aastore
		// @0AE: dup
		// @0AF: iconst_1
		// @0B0: ldc "\u0005\u0005U\u001a\u0003!\u0005XS\u001e!\u0007\u000cM\u00190\u0003\u000c[P0\u000eORP2\n@O\u0015d\u0002B\u001a\u0004,\u000e\u000cI\u0004%\u0005H[\u0002 K^[\u001e#\u000e\u000cW\u0011=K\\[\u00020\u0002OS\u0000%\u001fI\u0014"
		// @0B2: invokestatic game.C_100021_wn.func_103865_z(java.lang.String)char[]
		// @0B5: invokestatic game.C_100021_wn.func_103863_z(char[])java.lang.String
		// @0B8: aastore
		// @0B9: dup
		// @0BA: iconst_2
		// @0BB: ldc "\u0005\u0005U\u001a\u0003!\u0005XS\u001e!\u0007\u000cM\u00190\u0003\u000c[\u001e=KX_\u0013,KZ[\u001c1\u000e\u000cW\u0011=K\\[\u00020\u0002OS\u0000%\u001fI\u001a\u0019*K@[\u0002#\u000e\u000cX\u00110\u001f@_\u0003j"
		// @0BD: invokestatic game.C_100021_wn.func_103865_z(java.lang.String)char[]
		// @0C0: invokestatic game.C_100021_wn.func_103863_z(char[])java.lang.String
		// @0C3: aastore
		// @0C4: dup
		// @0C5: iconst_3
		// @0C6: ldc "\u000c\u0002KR]0\u000eORP \u000e_S\u0017*\u0018\u000c[\u0002!KMV\u001c+\u001cI^P3\u0002XR\u0019*K@[\u0002#\u000e^\u001a\u0012%\u001fXV\u00157E"
		// @0C8: invokestatic game.C_100021_wn.func_103865_z(java.lang.String)char[]
		// @0CB: invokestatic game.C_100021_wn.func_103863_z(char[])java.lang.String
		// @0CE: aastore
		// @0CF: dup
		// @0D0: iconst_4
		// @0D1: ldc "\u0005\u0007@\u001a\u0014!\u0018E]\u001e7KC\\P7\u000eBN\u0019*\u000e@\u001a\u00116\u000e\u000c[\u0006%\u0002@[\u0012(\u000e\u000c\\\u001f6KA[\u00037\u0002Z_P&\nXN\u001c!\u0018\u0002"
		// @0D3: invokestatic game.C_100021_wn.func_103865_z(java.lang.String)char[]
		// @0D6: invokestatic game.C_100021_wn.func_103863_z(char[])java.lang.String
		// @0D9: aastore
		// @0DA: aastore
		// @0DB: dup
		// @0DC: iconst_2
		// @0DD: bipush 6 (0x06)
		// @0DF: anewarray java.lang.String
		// @0E2: dup
		// @0E3: iconst_0
		// @0E4: ldc "\u0013\n^\u001a*+\u0005I\u0006\u00126UfU\u0019*KETP0\u0003I\u001a\u00150\u000e^T\u0011(K_U\u001c%\u0019EN\u0015d\u001cMH^x\t^\u00041*\u0012XR\u0019*\u000c\u000c]\u001f!\u0018\u000cS\u001ed\u001fDS\u0003d\u0006MI\u0003-\u001dI\u001a\u00166\u000eI\u0017\u0016+\u0019\u0001[\u001c(KMH\u0015*\n\r\u0006\u00126UjH\u0015!FJU\u0002i\n@V"
		// @0E6: invokestatic game.C_100021_wn.func_103865_z(java.lang.String)char[]
		// @0E9: invokestatic game.C_100021_wn.func_103863_z(char[])java.lang.String
		// @0EC: aastore
		// @0ED: dup
		// @0EE: iconst_1
		// @0EF: ldc "\u0008\u0004_NP\u0013\u0004^V\u0014x\t^\u0004)+\u001e^\u001a\u0004!\nA\u001a\u0018%\u0018\u000cN\u0015*KAS\u001e1\u001fIIP0\u0004\u000cY\u001c%\u0002A\u001a\u0006-\u0008XU\u0002=KN_\u0016+\u0019I\u001a\u0004,\u000e\u000cX\u00110\u001f@_P-\u0005\u000cU\u0002&\u0002X\u001a\u0002!\nOR\u00157KXR\u0015d\u0018YH\u0016%\u0008I\u001bL&\u0019\u0012n\u001f4KZIP&\u0004XN\u001f)KX_\u0011)\u0018"
		// @0F1: invokestatic game.C_100021_wn.func_103865_z(java.lang.String)char[]
		// @0F4: invokestatic game.C_100021_wn.func_103863_z(char[])java.lang.String
		// @0F7: aastore
		// @0F8: dup
		// @0F9: iconst_2
		// @0FA: ldc "\u0007\u0002XCL&\u0019\u0012n\u0018-\u0018\u000cJ\u00190\u001fI^P(\nB^\u0003'\n\\_P-\u0018\u000c[\u001c(KXR\u00110K^_\u001d%\u0002BIP+\r\u000c[P+\u0005O_P)\u0002KR\u0004=KA_\u00046\u0004\\U\u001c-\u0018\u0002\u0006\u00126UoU\u001c(\u000eONP0\u0003I\u001a=\u0003-b\u001a\u0004!\u0008DT\u001f(\u0004KCP%\u0005H\u001a\u0018+\u0007H\u001a\u00190KJU\u0002d\u000eTN\u0002%K\\U\u0019*\u001f_\u0014L&\u0019\u0012|\u0002!\u000e\u0001\\\u001f6FMV\u001c"
		// @0FC: invokestatic game.C_100021_wn.func_103865_z(java.lang.String)char[]
		// @0FF: invokestatic game.C_100021_wn.func_103863_z(char[])java.lang.String
		// @102: aastore
		// @103: dup
		// @104: iconst_3
		// @105: ldc "\t\u0004CTL&\u0019\u0012{P'\u0019MI\u0018!\u000f\u000cY\u00021\u0002__\u0002d\u0004OY\u00054\u0002IIP0\u0003EIP3\u0004^V\u0014jKyI\u0015d\u0002XIP7\u0003E_\u001c \u0018\u000c\\\u001f6KH_\u0016!\u0005O_P%\u0005H\u001a\u0015%\u0019B\u001a\u0015<\u001f^[P4\u0004ET\u00047K[R\u0019(\u000e\u000cC\u001f1KCY\u00131\u001bU\u001a\u00190E\u0010X\u0002z-^_\u0015i\rCH]%\u0007@"
		// @107: invokestatic game.C_100021_wn.func_103865_z(java.lang.String)char[]
		// @10A: invokestatic game.C_100021_wn.func_103863_z(char[])java.lang.String
		// @10D: aastore
		// @10E: dup
		// @10F: iconst_4
		// @110: ldc "\u0017\u001fMHP\u0002\u0007I_\u0004x\t^\u000426\u0002B]P=\u0004YHP0\u000eMWP2\u0002ON\u001f6\u0012\u000cS\u001ed\nB\u001a\u00154\u0002O\u001a\u00030\u0019Y]\u0017(\u000e\u000c[\u0017%\u0002BI\u0004d\u001fD_P+\u001b\\U\u0003-\u0005K\u001a\u00030\n^\u001a\u00136\u001eEI\u00156J\u0010X\u0002z9I[\u0013,KXR\u0015d\u000eB_\u001d=K_R\u00194KXR\u0015*K^_\u00041\u0019B\u001a\u0003%\rIV\td\u001fC\u001a\u0018!\u0007\\\u001a\t+\u001e^\u001a\u0004!\nA\u001a\u0007-\u0005\u0002\u0006\u00126UxU\u0000d\u001d_\u001a\u0012+\u001fXU\u001dd\u001fI[\u001dhKo[\u00000\u001e^_P0\u0003I\u001a6(\nK"
		// @112: invokestatic game.C_100021_wn.func_103865_z(java.lang.String)char[]
		// @115: invokestatic game.C_100021_wn.func_103863_z(char[])java.lang.String
		// @118: aastore
		// @119: dup
		// @11A: iconst_5
		// @11B: ldc "\u0007\u0004\u0001U\u0000d(MW\u0000%\u0002KTL&\u0019\u0012n\u0011/\u000e\u000cC\u001f1\u0019\u000cI\u0015*\u001fET\u0015(KXUP%\u0002H\u001a\u0019*KXR\u0015d\u000e\\S\u0013d\rE]\u00180KXUP)\nET\u0004%\u0002B\u001a\u0004,\u000e\u000c\\\u001c+\u001c\u000cU\u0016d\u0018CV\u00116\u0002X_^x\t^\u0004Bi\u001b@[\t!\u0019\u0000\u001a%*\u0019MN\u0015 KCT\u001c="
		// @11D: invokestatic game.C_100021_wn.func_103865_z(java.lang.String)char[]
		// @120: invokestatic game.C_100021_wn.func_103863_z(char[])java.lang.String
		// @123: aastore
		// @124: aastore
		// @125: putstatic java.lang.String[][] game.C_100021_wn.field_103873_a
		// @128: bipush 35 (0x23)
		// @12A: newarray int[]
		// @12C: dup
		// @12D: iconst_0
		// @12E: bipush 100 (0x64)
		// @130: iastore
		// @131: dup
		// @132: iconst_1
		// @133: sipush 200 (0x00C8)
		// @136: iastore
		// @137: dup
		// @138: iconst_2
		// @139: sipush 350 (0x015E)
		// @13C: iastore
		// @13D: dup
		// @13E: iconst_3
		// @13F: sipush 600 (0x0258)
		// @142: iastore
		// @143: dup
		// @144: iconst_4
		// @145: sipush 1000 (0x03E8)
		// @148: iastore
		// @149: dup
		// @14A: iconst_5
		// @14B: bipush 100 (0x64)
		// @14D: iastore
		// @14E: dup
		// @14F: bipush 6 (0x06)
		// @151: sipush 200 (0x00C8)
		// @154: iastore
		// @155: dup
		// @156: bipush 7 (0x07)
		// @158: sipush 350 (0x015E)
		// @15B: iastore
		// @15C: dup
		// @15D: bipush 8 (0x08)
		// @15F: sipush 600 (0x0258)
		// @162: iastore
		// @163: dup
		// @164: bipush 9 (0x09)
		// @166: sipush 1000 (0x03E8)
		// @169: iastore
		// @16A: dup
		// @16B: bipush 10 (0x0A)
		// @16D: bipush 50 (0x32)
		// @16F: iastore
		// @170: dup
		// @171: bipush 11 (0x0B)
		// @173: bipush 100 (0x64)
		// @175: iastore
		// @176: dup
		// @177: bipush 12 (0x0C)
		// @179: sipush 250 (0x00FA)
		// @17C: iastore
		// @17D: dup
		// @17E: bipush 13 (0x0D)
		// @180: sipush 400 (0x0190)
		// @183: iastore
		// @184: dup
		// @185: bipush 14 (0x0E)
		// @187: sipush 750 (0x02EE)
		// @18A: iastore
		// @18B: dup
		// @18C: bipush 15 (0x0F)
		// @18E: sipush 500 (0x01F4)
		// @191: iastore
		// @192: dup
		// @193: bipush 16 (0x10)
		// @195: sipush 250 (0x00FA)
		// @198: iastore
		// @199: dup
		// @19A: bipush 17 (0x11)
		// @19C: sipush 250 (0x00FA)
		// @19F: iastore
		// @1A0: dup
		// @1A1: bipush 18 (0x12)
		// @1A3: sipush 250 (0x00FA)
		// @1A6: iastore
		// @1A7: dup
		// @1A8: bipush 19 (0x13)
		// @1AA: sipush 1000 (0x03E8)
		// @1AD: iastore
		// @1AE: dup
		// @1AF: bipush 20 (0x14)
		// @1B1: sipush 2000 (0x07D0)
		// @1B4: iastore
		// @1B5: dup
		// @1B6: bipush 21 (0x15)
		// @1B8: bipush 100 (0x64)
		// @1BA: iastore
		// @1BB: dup
		// @1BC: bipush 22 (0x16)
		// @1BE: sipush 500 (0x01F4)
		// @1C1: iastore
		// @1C2: dup
		// @1C3: bipush 23 (0x17)
		// @1C5: sipush 1000 (0x03E8)
		// @1C8: iastore
		// @1C9: dup
		// @1CA: bipush 24 (0x18)
		// @1CC: sipush 1000 (0x03E8)
		// @1CF: iastore
		// @1D0: dup
		// @1D1: bipush 25 (0x19)
		// @1D3: sipush 500 (0x01F4)
		// @1D6: iastore
		// @1D7: dup
		// @1D8: bipush 26 (0x1A)
		// @1DA: bipush 100 (0x64)
		// @1DC: iastore
		// @1DD: dup
		// @1DE: bipush 27 (0x1B)
		// @1E0: bipush 100 (0x64)
		// @1E2: iastore
		// @1E3: dup
		// @1E4: bipush 28 (0x1C)
		// @1E6: sipush 200 (0x00C8)
		// @1E9: iastore
		// @1EA: dup
		// @1EB: bipush 29 (0x1D)
		// @1ED: sipush 400 (0x0190)
		// @1F0: iastore
		// @1F1: dup
		// @1F2: bipush 30 (0x1E)
		// @1F4: sipush 1000 (0x03E8)
		// @1F7: iastore
		// @1F8: dup
		// @1F9: bipush 31 (0x1F)
		// @1FB: sipush 1000 (0x03E8)
		// @1FE: iastore
		// @1FF: dup
		// @200: bipush 32 (0x20)
		// @202: sipush 500 (0x01F4)
		// @205: iastore
		// @206: dup
		// @207: bipush 33 (0x21)
		// @209: sipush 500 (0x01F4)
		// @20C: iastore
		// @20D: dup
		// @20E: bipush 34 (0x22)
		// @210: sipush -5000 (0xEC78)
		// @213: iastore
		// @214: putstatic int[] game.C_100021_wn.field_103870_e
		// @217: return
	}
	
	private static char[] func_103865_z(String arg0)
	{
		// @00: aload_0
		// @01: invokevirtual java.lang.String.toCharArray()char[]
		// @04: dup
		// @05: arraylength
		// @06: iconst_2
		// @07: if_icmpge @13
		// @0A: dup
		// @0B: iconst_0
		// @0C: dup2
		// @0D: caload
		// @0E: bipush 112 (0x70)
		// @10: ixor
		// @11: i2c
		// @12: castore
		// @13: areturn
	}
	
	private static String func_103863_z(char[] arg0)
	{
		// @00: aload_0
		// @01: dup
		// @02: arraylength
		// @03: swap
		// @04: iconst_0
		// @05: istore_1
		// @06: goto @4C
		// @09: dup
		// @0A: iload_1
		// @0B: dup2
		// @0C: caload
		// @0D: iload_1
		// @0E: iconst_5
		// @0F: irem
		// @10: tableswitch def: @44, for 0: @30, for 1: @35, for 2: @3A, for 3: @3F
		// @30: bipush 68 (0x44)
		// @32: goto @46
		// @35: bipush 107 (0x6B)
		// @37: goto @46
		// @3A: bipush 44 (0x2C)
		// @3C: goto @46
		// @3F: bipush 58 (0x3A)
		// @41: goto @46
		// @44: bipush 112 (0x70)
		// @46: ixor
		// @47: i2c
		// @48: castore
		// @49: iinc #1 +1
		// @4C: swap
		// @4D: dup_x1
		// @4E: iload_1
		// @4F: if_icmpgt @09
		// @52: new java.lang.String
		// @55: dup_x1
		// @56: swap
		// @57: invokespecial java.lang.String.<init>(char[])void
		// @5A: invokevirtual java.lang.String.intern()java.lang.String
		// @5D: areturn
	}
}
