package game;

import java.applet.Applet;

final class C_100113_ek
{
	static C_100098_h field_104881_c;
	static int field_104882_a;
	static String field_104878_d;
	static int field_104880_b;
	static int field_104876_f;
	static String field_104879_e;
	static volatile int field_104884_h;
	private String field_104877_g;
	private static final String[] field_104883_z;
	
	final boolean func_104871_a(String arg0, int arg1)
	{
		// @00: iload_2
		// @01: sipush 26736 (0x6870)
		// @04: if_icmpeq @09
		// @07: iconst_1
		// @08: ireturn
		// @09: aload_0
		// @0A: getfield java.lang.String game.C_100113_ek.field_104877_g
		// @0D: aload_1
		// @0E: invokevirtual java.lang.String.equals(java.lang.Object)boolean
		// @11: ireturn
		// @12: astore_3
		// @13: aload_3
		// @14: new java.lang.StringBuilder
		// @17: dup
		// @18: invokespecial java.lang.StringBuilder.<init>()void
		// @1B: getstatic java.lang.String[] game.C_100113_ek.field_104883_z
		// @1E: iconst_1
		// @1F: aaload
		// @20: invokevirtual java.lang.StringBuilder.append(java.lang.String)java.lang.StringBuilder
		// @23: aload_1
		// @24: ifnull @30
		// @27: getstatic java.lang.String[] game.C_100113_ek.field_104883_z
		// @2A: iconst_0
		// @2B: aaload
		// @2C: goto @35
		// @2F: athrow
		// @30: getstatic java.lang.String[] game.C_100113_ek.field_104883_z
		// @33: iconst_2
		// @34: aaload
		// @35: invokevirtual java.lang.StringBuilder.append(java.lang.String)java.lang.StringBuilder
		// @38: bipush 44 (0x2C)
		// @3A: invokevirtual java.lang.StringBuilder.append(char)java.lang.StringBuilder
		// @3D: iload_2
		// @3E: invokevirtual java.lang.StringBuilder.append(int)java.lang.StringBuilder
		// @41: bipush 41 (0x29)
		// @43: invokevirtual java.lang.StringBuilder.append(char)java.lang.StringBuilder
		// @46: invokevirtual java.lang.StringBuilder.toString()java.lang.String
		// @49: invokestatic game.C_100181_cf.func_105695_a(java.lang.Throwable, java.lang.String)game.C_100170_cm
		// @4C: athrow
	}
	
	final void func_104874_a(Applet arg0, byte arg1)
	{
		// @00: bipush 109 (0x6D)
		// @02: bipush 36 (0x24)
		// @04: iload_2
		// @05: isub
		// @06: bipush 40 (0x28)
		// @08: idiv
		// @09: idiv
		// @0A: istore_3
		// @0B: iconst_0
		// @0C: aload_1
		// @0D: getstatic java.lang.String[] game.C_100113_ek.field_104883_z
		// @10: iconst_5
		// @11: aaload
		// @12: aload_0
		// @13: getfield java.lang.String game.C_100113_ek.field_104877_g
		// @16: ldc2_w 31536000
		// @19: invokestatic game.C_100252_pn.func_105492_a(boolean, java.applet.Applet, java.lang.String, java.lang.String, long)void
		// @1C: goto @5B
		// @1F: astore_3
		// @20: aload_3
		// @21: new java.lang.StringBuilder
		// @24: dup
		// @25: invokespecial java.lang.StringBuilder.<init>()void
		// @28: getstatic java.lang.String[] game.C_100113_ek.field_104883_z
		// @2B: bipush 6 (0x06)
		// @2D: aaload
		// @2E: invokevirtual java.lang.StringBuilder.append(java.lang.String)java.lang.StringBuilder
		// @31: aload_1
		// @32: ifnull @3E
		// @35: getstatic java.lang.String[] game.C_100113_ek.field_104883_z
		// @38: iconst_0
		// @39: aaload
		// @3A: goto @43
		// @3D: athrow
		// @3E: getstatic java.lang.String[] game.C_100113_ek.field_104883_z
		// @41: iconst_2
		// @42: aaload
		// @43: invokevirtual java.lang.StringBuilder.append(java.lang.String)java.lang.StringBuilder
		// @46: bipush 44 (0x2C)
		// @48: invokevirtual java.lang.StringBuilder.append(char)java.lang.StringBuilder
		// @4B: iload_2
		// @4C: invokevirtual java.lang.StringBuilder.append(int)java.lang.StringBuilder
		// @4F: bipush 41 (0x29)
		// @51: invokevirtual java.lang.StringBuilder.append(char)java.lang.StringBuilder
		// @54: invokevirtual java.lang.StringBuilder.toString()java.lang.String
		// @57: invokestatic game.C_100181_cf.func_105695_a(java.lang.Throwable, java.lang.String)game.C_100170_cm
		// @5A: athrow
		// @5B: return
	}
	
	static final void func_104875_a(int arg0, boolean arg1, int arg2)
	{
		// @000: getstatic int game.SteelSentinels.field_105275_O
		// @003: istore #15
		// @005: iload_0
		// @006: ifeq @015
		// @009: bipush 102 (0x66)
		// @00B: iconst_1
		// @00C: bipush 28 (0x1C)
		// @00E: invokestatic game.C_100113_ek.func_104875_a(int, boolean, int)void
		// @011: goto @015
		// @014: athrow
		// @015: getstatic game.C_100100_i game.C_100202_qi.field_105913_f
		// @018: getfield game.C_100115_ej game.C_100100_i.field_102016_ec
		// @01B: iconst_m1
		// @01C: iconst_2
		// @01D: getstatic int game.C_100033_gj.field_101917_jc
		// @020: iadd
		// @021: iconst_3
		// @022: getstatic int game.C_100033_gj.field_101917_jc
		// @025: bipush -2 (0xFE)
		// @027: isub
		// @028: imul
		// @029: iload_2
		// @02A: imul
		// @02B: getstatic game.C_100100_i game.C_100202_qi.field_105913_f
		// @02E: getfield game.C_100115_ej game.C_100100_i.field_102016_ec
		// @031: getstatic game.C_100115_ej game.C_100346_ja.field_103486_m
		// @034: if_acmpne @03C
		// @037: iconst_1
		// @038: goto @03D
		// @03B: athrow
		// @03C: iconst_0
		// @03D: iconst_2
		// @03E: iload_1
		// @03F: invokevirtual game.C_100115_ej.func_102034_a(int, int, int, boolean, int, boolean)boolean
		// @042: istore_3
		// @043: getstatic game.C_100100_i game.C_100202_qi.field_105913_f
		// @046: getfield game.C_100302_ka game.C_100100_i.field_102015_Yb
		// @049: getfield game.C_100202_qi game.C_100302_ka.field_101891_Ob
		// @04C: astore #4
		// @04E: getstatic int game.C_100062_dk.field_104281_d
		// @051: iconst_2
		// @052: if_icmpeq @08C
		// @055: getstatic int game.C_100062_dk.field_104281_d
		// @058: iconst_m1
		// @059: ixor
		// @05A: bipush -2 (0xFE)
		// @05C: if_icmpeq @08C
		// @05F: goto @063
		// @062: athrow
		// @063: getstatic game.C_100100_i game.C_100202_qi.field_105913_f
		// @066: getfield game.C_100115_ej game.C_100100_i.field_102016_ec
		// @069: getfield game.C_100302_ka game.C_100115_ej.field_102040_Zb
		// @06C: getstatic java.lang.String game.C_100185_rm.field_105485_e
		// @06F: putfield java.lang.String game.C_100302_ka.field_101890_ab
		// @072: getstatic game.C_100100_i game.C_100202_qi.field_105913_f
		// @075: iconst_0
		// @076: putfield boolean game.C_100100_i.field_101864_W
		// @079: iconst_1
		// @07A: getstatic game.C_100100_i game.C_100202_qi.field_105913_f
		// @07D: getfield game.C_100302_ka game.C_100100_i.field_102015_Yb
		// @080: invokestatic game.C_100107_u.func_104760_a(boolean, game.C_100302_ka)void
		// @083: iload #15
		// @085: ifeq @385
		// @088: goto @08C
		// @08B: athrow
		// @08C: getstatic game.C_100100_i game.C_100202_qi.field_105913_f
		// @08F: getfield game.C_100115_ej game.C_100100_i.field_102016_ec
		// @092: getfield game.C_100302_ka game.C_100115_ej.field_102040_Zb
		// @095: aconst_null
		// @096: putfield java.lang.String game.C_100302_ka.field_101890_ab
		// @099: getstatic game.C_100100_i game.C_100202_qi.field_105913_f
		// @09C: iconst_1
		// @09D: putfield boolean game.C_100100_i.field_101864_W
		// @0A0: aconst_null
		// @0A1: astore #5
		// @0A3: aload #4
		// @0A5: bipush 12 (0x0C)
		// @0A7: invokevirtual game.C_100202_qi.func_105899_c(int)game.C_100158_da
		// @0AA: checkcast game.C_100061_dh
		// @0AD: astore #6
		// @0AF: aload #6
		// @0B1: ifnull @2E3
		// @0B4: iconst_0
		// @0B5: istore #7
		// @0B7: iload #15
		// @0B9: ifne @330
		// @0BC: aconst_null
		// @0BD: aload #6
		// @0BF: getfield game.C_100202_qi game.C_100061_dh.field_101891_Ob
		// @0C2: if_acmpeq @0CD
		// @0C5: goto @0C9
		// @0C8: athrow
		// @0C9: goto @10E
		// @0CC: athrow
		// @0CD: aload #6
		// @0CF: new game.C_100302_ka
		// @0D2: dup
		// @0D3: lconst_0
		// @0D4: getstatic game.C_100302_ka game.C_100160_sm.field_105414_e
		// @0D7: invokespecial game.C_100302_ka.<init>(long, game.C_100302_ka)void
		// @0DA: putfield game.C_100302_ka game.C_100061_dh.field_101982_Xb
		// @0DD: aload #6
		// @0DF: bipush -116 (0x8C)
		// @0E1: aload #6
		// @0E3: getfield game.C_100302_ka game.C_100061_dh.field_101982_Xb
		// @0E6: invokevirtual game.C_100061_dh.func_101824_b(int, game.C_100302_ka)void
		// @0E9: aload #6
		// @0EB: new game.C_100302_ka
		// @0EE: dup
		// @0EF: lconst_0
		// @0F0: getstatic game.C_100302_ka game.C_100160_sm.field_105414_e
		// @0F3: invokespecial game.C_100302_ka.<init>(long, game.C_100302_ka)void
		// @0F6: putfield game.C_100302_ka game.C_100061_dh.field_101999_bc
		// @0F9: aload #6
		// @0FB: bipush -90 (0xA6)
		// @0FD: aload #6
		// @0FF: getfield game.C_100302_ka game.C_100061_dh.field_101999_bc
		// @102: invokevirtual game.C_100061_dh.func_101824_b(int, game.C_100302_ka)void
		// @105: aload #6
		// @107: iconst_0
		// @108: invokevirtual game.C_100061_dh.func_101821_k(int)void
		// @10B: iconst_1
		// @10C: istore #7
		// @10E: aload #6
		// @110: getstatic game.C_100100_i game.C_100202_qi.field_105913_f
		// @113: getfield game.C_100302_ka game.C_100100_i.field_102015_Yb
		// @116: getfield int game.C_100302_ka.field_101886_Kb
		// @119: putfield int game.C_100061_dh.field_101886_Kb
		// @11C: aload #6
		// @11E: getfield game.C_100302_ka game.C_100061_dh.field_101982_Xb
		// @121: iconst_0
		// @122: getstatic int game.C_100033_gj.field_101917_jc
		// @125: iconst_m1
		// @126: iconst_0
		// @127: aload #6
		// @129: getfield int game.C_100061_dh.field_101886_Kb
		// @12C: invokevirtual game.C_100302_ka.func_101825_a(int, int, int, int, int)void
		// @12F: iconst_0
		// @130: istore #8
		// @132: aload #6
		// @134: getfield java.lang.String game.C_100061_dh.field_101997_ac
		// @137: ifnull @17D
		// @13A: aload #6
		// @13C: getfield java.lang.String game.C_100061_dh.field_101997_ac
		// @13F: ldc ""
		// @141: invokevirtual java.lang.String.equals(java.lang.Object)boolean
		// @144: ifeq @14F
		// @147: goto @14B
		// @14A: athrow
		// @14B: goto @17D
		// @14E: athrow
		// @14F: aload #6
		// @151: getfield game.C_100302_ka game.C_100061_dh.field_101999_bc
		// @154: ldc 16737894 (0xff6666)
		// @156: putfield int game.C_100302_ka.field_101860_K
		// @159: aload #6
		// @15B: getfield game.C_100302_ka game.C_100061_dh.field_101999_bc
		// @15E: getstatic game.C_100037_wb game.C_100063_dj.field_104291_g
		// @161: putfield game.C_100037_wb game.C_100302_ka.field_101887_nb
		// @164: aload #6
		// @166: getfield game.C_100302_ka game.C_100061_dh.field_101999_bc
		// @169: iconst_0
		// @16A: getstatic int game.C_100033_gj.field_101917_jc
		// @16D: iconst_m1
		// @16E: iconst_0
		// @16F: getstatic game.C_100037_wb game.C_100063_dj.field_104291_g
		// @172: getfield int game.C_100037_wb.field_102341_y
		// @175: iconst_3
		// @176: iadd
		// @177: invokevirtual game.C_100302_ka.func_101825_a(int, int, int, int, int)void
		// @17A: iconst_1
		// @17B: istore #8
		// @17D: iconst_0
		// @17E: istore #9
		// @180: aload #6
		// @182: getfield int game.C_100061_dh.field_101886_Kb
		// @185: istore #10
		// @187: iload #8
		// @189: ifeq @19D
		// @18C: iconst_3
		// @18D: getstatic game.C_100037_wb game.C_100063_dj.field_104291_g
		// @190: getfield int game.C_100037_wb.field_102341_y
		// @193: iadd
		// @194: istore #9
		// @196: iload #10
		// @198: iload #9
		// @19A: isub
		// @19B: istore #10
		// @19D: aload #6
		// @19F: getfield game.C_100302_ka game.C_100061_dh.field_101982_Xb
		// @1A2: iconst_m1
		// @1A3: iload #10
		// @1A5: iconst_m1
		// @1A6: ixor
		// @1A7: if_icmple @1C0
		// @1AA: aload #6
		// @1AC: getfield game.C_100302_ka game.C_100061_dh.field_101982_Xb
		// @1AF: getfield game.C_100112_r game.C_100302_ka.field_101845_sb
		// @1B2: aload #6
		// @1B4: getfield java.lang.String game.C_100061_dh.field_101993_nc
		// @1B7: iload #10
		// @1B9: invokestatic game.C_100112_r.func_101748_a(game.C_100112_r, java.lang.String, int)java.lang.String
		// @1BC: goto @1C5
		// @1BF: athrow
		// @1C0: aload #6
		// @1C2: getfield java.lang.String game.C_100061_dh.field_101993_nc
		// @1C5: putfield java.lang.String game.C_100302_ka.field_101890_ab
		// @1C8: aload #6
		// @1CA: getfield game.C_100302_ka game.C_100061_dh.field_101982_Xb
		// @1CD: getfield java.lang.String game.C_100302_ka.field_101890_ab
		// @1D0: aload #6
		// @1D2: getfield java.lang.String game.C_100061_dh.field_101993_nc
		// @1D5: invokevirtual java.lang.String.equals(java.lang.Object)boolean
		// @1D8: ifne @1E0
		// @1DB: iconst_1
		// @1DC: goto @1E1
		// @1DF: athrow
		// @1E0: iconst_0
		// @1E1: istore #11
		// @1E3: aload #6
		// @1E5: getfield game.C_100302_ka game.C_100061_dh.field_101982_Xb
		// @1E8: iload #9
		// @1EA: getstatic int game.C_100033_gj.field_101917_jc
		// @1ED: iconst_m1
		// @1EE: iconst_0
		// @1EF: iload #10
		// @1F1: invokevirtual game.C_100302_ka.func_101825_a(int, int, int, int, int)void
		// @1F4: iload_3
		// @1F5: ifeq @1FC
		// @1F8: goto @20B
		// @1FB: athrow
		// @1FC: aload #6
		// @1FE: aload #6
		// @200: getfield int game.C_100061_dh.field_101848_lb
		// @203: ineg
		// @204: getstatic int game.C_100033_gj.field_101917_jc
		// @207: iadd
		// @208: putfield int game.C_100061_dh.field_101832_tb
		// @20B: iload #7
		// @20D: ifne @214
		// @210: goto @223
		// @213: athrow
		// @214: getstatic game.C_100100_i game.C_100202_qi.field_105913_f
		// @217: getfield game.C_100302_ka game.C_100100_i.field_102015_Yb
		// @21A: aload #6
		// @21C: iconst_0
		// @21D: aload #5
		// @21F: iconst_2
		// @220: invokevirtual game.C_100302_ka.func_101823_a(game.C_100302_ka, boolean, game.C_100302_ka, int)void
		// @223: aload #6
		// @225: getfield game.C_100302_ka game.C_100061_dh.field_101999_bc
		// @228: ifnull @23A
		// @22B: aload #6
		// @22D: getfield game.C_100302_ka game.C_100061_dh.field_101999_bc
		// @230: getfield boolean game.C_100302_ka.field_101839_db
		// @233: ifne @263
		// @236: goto @23A
		// @239: athrow
		// @23A: aload #6
		// @23C: getfield game.C_100302_ka game.C_100061_dh.field_101982_Xb
		// @23F: getfield boolean game.C_100302_ka.field_101839_db
		// @242: ifeq @26F
		// @245: goto @249
		// @248: athrow
		// @249: iload #11
		// @24B: ifeq @26F
		// @24E: goto @252
		// @251: athrow
		// @252: aload #6
		// @254: getfield java.lang.String game.C_100061_dh.field_101993_nc
		// @257: putstatic java.lang.String game.C_100321_hi.field_107220_c
		// @25A: iload #15
		// @25C: ifeq @26F
		// @25F: goto @263
		// @262: athrow
		// @263: aload #6
		// @265: getfield java.lang.String game.C_100061_dh.field_101997_ac
		// @268: putstatic java.lang.String game.C_100321_hi.field_107220_c
		// @26B: goto @26F
		// @26E: athrow
		// @26F: iconst_0
		// @270: aload #6
		// @272: getfield int game.C_100061_dh.field_101854_N
		// @275: if_icmpne @27C
		// @278: goto @2CE
		// @27B: athrow
		// @27C: aload #6
		// @27E: getfield java.lang.String game.C_100061_dh.field_101993_nc
		// @281: iconst_m1
		// @282: lconst_0
		// @283: bipush -100 (0x9C)
		// @285: iconst_m1
		// @286: aconst_null
		// @287: aload #6
		// @289: getfield java.lang.String game.C_100061_dh.field_101990_oc
		// @28C: aload #6
		// @28E: getstatic game.C_100100_i game.C_100202_qi.field_105913_f
		// @291: getfield game.C_100115_ej game.C_100100_i.field_102016_ec
		// @294: invokestatic game.C_100096_un.func_104559_a(java.lang.String, int, long, int, int, int[], java.lang.String, game.C_100302_ka, game.C_100115_ej)void
		// @297: getstatic game.C_100022_hf game.C_100136_th.field_102623_R
		// @29A: astore #12
		// @29C: getstatic java.lang.String game.C_100029_gn.field_103367_P
		// @29F: astore #13
		// @2A1: aload #12
		// @2A3: getfield game.C_100270_mi game.C_100022_hf.field_103903_m
		// @2A6: bipush 65 (0x41)
		// @2A8: bipush 7 (0x07)
		// @2AA: aload #13
		// @2AC: invokevirtual game.C_100270_mi.func_102250_a(int, int, java.lang.String)void
		// @2AF: getstatic game.C_100022_hf game.C_100136_th.field_102623_R
		// @2B2: astore #12
		// @2B4: getstatic int game.C_100340_je.field_102981_m
		// @2B7: istore #13
		// @2B9: getstatic int game.C_100125_tm.field_100745_p
		// @2BC: istore #14
		// @2BE: aload #12
		// @2C0: getfield game.C_100270_mi game.C_100022_hf.field_103903_m
		// @2C3: iload #13
		// @2C5: iload #14
		// @2C7: iconst_0
		// @2C8: bipush 74 (0x4A)
		// @2CA: iconst_0
		// @2CB: invokevirtual game.C_100270_mi.func_102261_b(int, int, int, int, int)void
		// @2CE: aload #6
		// @2D0: astore #5
		// @2D2: aload #4
		// @2D4: bipush 71 (0x47)
		// @2D6: invokevirtual game.C_100202_qi.func_105907_c(byte)game.C_100158_da
		// @2D9: checkcast game.C_100061_dh
		// @2DC: astore #6
		// @2DE: iload #15
		// @2E0: ifeq @0AF
		// @2E3: getstatic game.C_100100_i game.C_100202_qi.field_105913_f
		// @2E6: getfield game.C_100302_ka game.C_100100_i.field_102021_Vb
		// @2E9: getfield int game.C_100302_ka.field_101854_N
		// @2EC: iconst_m1
		// @2ED: ixor
		// @2EE: iconst_m1
		// @2EF: if_icmpne @2F6
		// @2F2: goto @334
		// @2F5: athrow
		// @2F6: new game.C_100118_ub
		// @2F9: dup
		// @2FA: getstatic game.C_100100_i game.C_100202_qi.field_105913_f
		// @2FD: getfield game.C_100302_ka game.C_100100_i.field_102021_Vb
		// @300: getfield int game.C_100302_ka.field_101840_Eb
		// @303: getstatic game.C_100100_i game.C_100202_qi.field_105913_f
		// @306: getfield game.C_100302_ka game.C_100100_i.field_102021_Vb
		// @309: getfield int game.C_100302_ka.field_101835_xb
		// @30C: getstatic game.C_100100_i game.C_100202_qi.field_105913_f
		// @30F: getfield game.C_100302_ka game.C_100100_i.field_102021_Vb
		// @312: getfield int game.C_100302_ka.field_101886_Kb
		// @315: getstatic game.C_100100_i game.C_100202_qi.field_105913_f
		// @318: getfield game.C_100302_ka game.C_100100_i.field_102021_Vb
		// @31B: getfield int game.C_100302_ka.field_101848_lb
		// @31E: getstatic java.lang.String game.C_100233_oa.field_106235_f
		// @321: getstatic game.C_100302_ka game.C_100138_bo.field_100405_b
		// @324: getstatic game.C_100302_ka game.C_100129_tg.field_102750_sb
		// @327: getstatic game.C_100302_ka game.C_100129_tg.field_102750_sb
		// @32A: invokespecial game.C_100118_ub.<init>(int, int, int, int, java.lang.String, game.C_100302_ka, game.C_100302_ka, game.C_100302_ka)void
		// @32D: putstatic game.C_100118_ub game.C_100038_wa.field_104073_n
		// @330: iconst_2
		// @331: putstatic int game.C_100209_qb.field_102688_Kb
		// @334: iconst_m1
		// @335: getstatic game.C_100100_i game.C_100202_qi.field_105913_f
		// @338: getfield game.C_100302_ka game.C_100100_i.field_102013_Xb
		// @33B: getfield int game.C_100302_ka.field_101854_N
		// @33E: iconst_m1
		// @33F: ixor
		// @340: if_icmpne @347
		// @343: goto @385
		// @346: athrow
		// @347: new game.C_100118_ub
		// @34A: dup
		// @34B: getstatic game.C_100100_i game.C_100202_qi.field_105913_f
		// @34E: getfield game.C_100302_ka game.C_100100_i.field_102013_Xb
		// @351: getfield int game.C_100302_ka.field_101840_Eb
		// @354: getstatic game.C_100100_i game.C_100202_qi.field_105913_f
		// @357: getfield game.C_100302_ka game.C_100100_i.field_102013_Xb
		// @35A: getfield int game.C_100302_ka.field_101835_xb
		// @35D: getstatic game.C_100100_i game.C_100202_qi.field_105913_f
		// @360: getfield game.C_100302_ka game.C_100100_i.field_102013_Xb
		// @363: getfield int game.C_100302_ka.field_101886_Kb
		// @366: getstatic game.C_100100_i game.C_100202_qi.field_105913_f
		// @369: getfield game.C_100302_ka game.C_100100_i.field_102013_Xb
		// @36C: getfield int game.C_100302_ka.field_101848_lb
		// @36F: getstatic java.lang.String game.C_100132_td.field_104972_d
		// @372: getstatic game.C_100302_ka game.C_100138_bo.field_100405_b
		// @375: getstatic game.C_100302_ka game.C_100129_tg.field_102750_sb
		// @378: getstatic game.C_100302_ka game.C_100129_tg.field_102750_sb
		// @37B: invokespecial game.C_100118_ub.<init>(int, int, int, int, java.lang.String, game.C_100302_ka, game.C_100302_ka, game.C_100302_ka)void
		// @37E: putstatic game.C_100118_ub game.C_100038_wa.field_104073_n
		// @381: iconst_3
		// @382: putstatic int game.C_100209_qb.field_102688_Kb
		// @385: goto @3BB
		// @388: astore_3
		// @389: aload_3
		// @38A: new java.lang.StringBuilder
		// @38D: dup
		// @38E: invokespecial java.lang.StringBuilder.<init>()void
		// @391: getstatic java.lang.String[] game.C_100113_ek.field_104883_z
		// @394: iconst_4
		// @395: aaload
		// @396: invokevirtual java.lang.StringBuilder.append(java.lang.String)java.lang.StringBuilder
		// @399: iload_0
		// @39A: invokevirtual java.lang.StringBuilder.append(int)java.lang.StringBuilder
		// @39D: bipush 44 (0x2C)
		// @39F: invokevirtual java.lang.StringBuilder.append(char)java.lang.StringBuilder
		// @3A2: iload_1
		// @3A3: invokevirtual java.lang.StringBuilder.append(boolean)java.lang.StringBuilder
		// @3A6: bipush 44 (0x2C)
		// @3A8: invokevirtual java.lang.StringBuilder.append(char)java.lang.StringBuilder
		// @3AB: iload_2
		// @3AC: invokevirtual java.lang.StringBuilder.append(int)java.lang.StringBuilder
		// @3AF: bipush 41 (0x29)
		// @3B1: invokevirtual java.lang.StringBuilder.append(char)java.lang.StringBuilder
		// @3B4: invokevirtual java.lang.StringBuilder.toString()java.lang.String
		// @3B7: invokestatic game.C_100181_cf.func_105695_a(java.lang.Throwable, java.lang.String)game.C_100170_cm
		// @3BA: athrow
		// @3BB: return
	}
	
	public final String toString()
	{
		// @00: new java.lang.IllegalStateException
		// @03: dup
		// @04: invokespecial java.lang.IllegalStateException.<init>()void
		// @07: athrow
		// @08: astore_1
		// @09: aload_1
		// @0A: getstatic java.lang.String[] game.C_100113_ek.field_104883_z
		// @0D: iconst_3
		// @0E: aaload
		// @0F: invokestatic game.C_100181_cf.func_105695_a(java.lang.Throwable, java.lang.String)game.C_100170_cm
		// @12: athrow
	}
	
	static final C_100107_u func_104869_a(String arg0, long arg1, String arg2, byte arg3, boolean arg4)
	{
		// @00: iload #4
		// @02: bipush -53 (0xCB)
		// @04: if_icmplt @13
		// @07: bipush 16 (0x10)
		// @09: iconst_0
		// @0A: bipush 92 (0x5C)
		// @0C: invokestatic game.C_100113_ek.func_104875_a(int, boolean, int)void
		// @0F: goto @13
		// @12: athrow
		// @13: lload_1
		// @14: ldc2_w -1
		// @17: lxor
		// @18: ldc2_w -1
		// @1B: lcmp
		// @1C: ifne @27
		// @1F: aload_3
		// @20: ifnonnull @3E
		// @23: goto @27
		// @26: athrow
		// @27: iload #5
		// @29: ifne @34
		// @2C: goto @30
		// @2F: athrow
		// @30: goto @48
		// @33: athrow
		// @34: new game.C_100180_ce
		// @37: dup
		// @38: lload_1
		// @39: aload_0
		// @3A: invokespecial game.C_100180_ce.<init>(long, java.lang.String)void
		// @3D: areturn
		// @3E: new game.C_100343_jf
		// @41: dup
		// @42: aload_3
		// @43: aload_0
		// @44: invokespecial game.C_100343_jf.<init>(java.lang.String, java.lang.String)void
		// @47: areturn
		// @48: new game.C_100303_kk
		// @4B: dup
		// @4C: lload_1
		// @4D: aload_0
		// @4E: invokespecial game.C_100303_kk.<init>(long, java.lang.String)void
		// @51: areturn
		// @52: astore #6
		// @54: aload #6
		// @56: new java.lang.StringBuilder
		// @59: dup
		// @5A: invokespecial java.lang.StringBuilder.<init>()void
		// @5D: getstatic java.lang.String[] game.C_100113_ek.field_104883_z
		// @60: bipush 8 (0x08)
		// @62: aaload
		// @63: invokevirtual java.lang.StringBuilder.append(java.lang.String)java.lang.StringBuilder
		// @66: aload_0
		// @67: ifnull @73
		// @6A: getstatic java.lang.String[] game.C_100113_ek.field_104883_z
		// @6D: iconst_0
		// @6E: aaload
		// @6F: goto @78
		// @72: athrow
		// @73: getstatic java.lang.String[] game.C_100113_ek.field_104883_z
		// @76: iconst_2
		// @77: aaload
		// @78: invokevirtual java.lang.StringBuilder.append(java.lang.String)java.lang.StringBuilder
		// @7B: bipush 44 (0x2C)
		// @7D: invokevirtual java.lang.StringBuilder.append(char)java.lang.StringBuilder
		// @80: lload_1
		// @81: invokevirtual java.lang.StringBuilder.append(long)java.lang.StringBuilder
		// @84: bipush 44 (0x2C)
		// @86: invokevirtual java.lang.StringBuilder.append(char)java.lang.StringBuilder
		// @89: aload_3
		// @8A: ifnull @96
		// @8D: getstatic java.lang.String[] game.C_100113_ek.field_104883_z
		// @90: iconst_0
		// @91: aaload
		// @92: goto @9B
		// @95: athrow
		// @96: getstatic java.lang.String[] game.C_100113_ek.field_104883_z
		// @99: iconst_2
		// @9A: aaload
		// @9B: invokevirtual java.lang.StringBuilder.append(java.lang.String)java.lang.StringBuilder
		// @9E: bipush 44 (0x2C)
		// @A0: invokevirtual java.lang.StringBuilder.append(char)java.lang.StringBuilder
		// @A3: iload #4
		// @A5: invokevirtual java.lang.StringBuilder.append(int)java.lang.StringBuilder
		// @A8: bipush 44 (0x2C)
		// @AA: invokevirtual java.lang.StringBuilder.append(char)java.lang.StringBuilder
		// @AD: iload #5
		// @AF: invokevirtual java.lang.StringBuilder.append(boolean)java.lang.StringBuilder
		// @B2: bipush 41 (0x29)
		// @B4: invokevirtual java.lang.StringBuilder.append(char)java.lang.StringBuilder
		// @B7: invokevirtual java.lang.StringBuilder.toString()java.lang.String
		// @BA: invokestatic game.C_100181_cf.func_105695_a(java.lang.Throwable, java.lang.String)game.C_100170_cm
		// @BD: athrow
	}
	
	public static void func_104870_a(int arg0)
	{
		// @00: iload_0
		// @01: ifeq @0D
		// @04: bipush -128 (0x80)
		// @06: invokestatic game.C_100113_ek.func_104870_a(int)void
		// @09: goto @0D
		// @0C: athrow
		// @0D: aconst_null
		// @0E: putstatic java.lang.String game.C_100113_ek.field_104879_e
		// @11: aconst_null
		// @12: putstatic java.lang.String game.C_100113_ek.field_104878_d
		// @15: aconst_null
		// @16: putstatic game.C_100098_h game.C_100113_ek.field_104881_c
		// @19: goto @3E
		// @1C: astore_1
		// @1D: aload_1
		// @1E: new java.lang.StringBuilder
		// @21: dup
		// @22: invokespecial java.lang.StringBuilder.<init>()void
		// @25: getstatic java.lang.String[] game.C_100113_ek.field_104883_z
		// @28: bipush 7 (0x07)
		// @2A: aaload
		// @2B: invokevirtual java.lang.StringBuilder.append(java.lang.String)java.lang.StringBuilder
		// @2E: iload_0
		// @2F: invokevirtual java.lang.StringBuilder.append(int)java.lang.StringBuilder
		// @32: bipush 41 (0x29)
		// @34: invokevirtual java.lang.StringBuilder.append(char)java.lang.StringBuilder
		// @37: invokevirtual java.lang.StringBuilder.toString()java.lang.String
		// @3A: invokestatic game.C_100181_cf.func_105695_a(java.lang.Throwable, java.lang.String)game.C_100170_cm
		// @3D: athrow
		// @3E: return
	}
	
	C_100113_ek(String arg0)
	{
		// @00: aload_0
		// @01: invokespecial java.lang.Object.<init>()void
		// @04: aload_0
		// @05: aload_1
		// @06: putfield java.lang.String game.C_100113_ek.field_104877_g
		// @09: goto @3F
		// @0C: astore_2
		// @0D: aload_2
		// @0E: new java.lang.StringBuilder
		// @11: dup
		// @12: invokespecial java.lang.StringBuilder.<init>()void
		// @15: getstatic java.lang.String[] game.C_100113_ek.field_104883_z
		// @18: bipush 9 (0x09)
		// @1A: aaload
		// @1B: invokevirtual java.lang.StringBuilder.append(java.lang.String)java.lang.StringBuilder
		// @1E: aload_1
		// @1F: ifnull @2B
		// @22: getstatic java.lang.String[] game.C_100113_ek.field_104883_z
		// @25: iconst_0
		// @26: aaload
		// @27: goto @30
		// @2A: athrow
		// @2B: getstatic java.lang.String[] game.C_100113_ek.field_104883_z
		// @2E: iconst_2
		// @2F: aaload
		// @30: invokevirtual java.lang.StringBuilder.append(java.lang.String)java.lang.StringBuilder
		// @33: bipush 41 (0x29)
		// @35: invokevirtual java.lang.StringBuilder.append(char)java.lang.StringBuilder
		// @38: invokevirtual java.lang.StringBuilder.toString()java.lang.String
		// @3B: invokestatic game.C_100181_cf.func_105695_a(java.lang.Throwable, java.lang.String)game.C_100170_cm
		// @3E: athrow
		// @3F: return
	}
	
	static
	{
		// @00: bipush 10 (0x0A)
		// @02: anewarray java.lang.String
		// @05: dup
		// @06: iconst_0
		// @07: ldc "utM1>"
		// @09: invokestatic game.C_100113_ek.func_104873_z(java.lang.String)char[]
		// @0C: invokestatic game.C_100113_ek.func_104872_z(char[])java.lang.String
		// @0F: aastore
		// @10: dup
		// @11: iconst_1
		// @12: ldc "k1MZk"
		// @14: invokestatic game.C_100113_ek.func_104873_z(java.lang.String)char[]
		// @17: invokestatic game.C_100113_ek.func_104872_z(char[])java.lang.String
		// @1A: aastore
		// @1B: dup
		// @1C: iconst_2
		// @1D: ldc "`/\u000fs"
		// @1F: invokestatic game.C_100113_ek.func_104873_z(java.lang.String)char[]
		// @22: invokestatic game.C_100113_ek.func_104872_z(char[])java.lang.String
		// @25: aastore
		// @26: dup
		// @27: iconst_3
		// @28: ldc "k1Mk,].\u0011v-irJ"
		// @2A: invokestatic game.C_100113_ek.func_104873_z(java.lang.String)char[]
		// @2D: invokestatic game.C_100113_ek.func_104872_z(char[])java.lang.String
		// @30: aastore
		// @31: dup
		// @32: iconst_4
		// @33: ldc "k1M[k"
		// @35: invokestatic game.C_100113_ek.func_104873_z(java.lang.String)char[]
		// @38: invokestatic game.C_100113_ek.func_104872_z(char[])java.lang.String
		// @3B: aastore
		// @3C: dup
		// @3D: iconst_5
		// @3E: ldc "d;\u0004z;#6\u0002l7#6\u000cx*`w\u000ez7f5\u0007"
		// @40: invokestatic game.C_100113_ek.func_104873_z(java.lang.String)char[]
		// @43: invokestatic game.C_100113_ek.func_104872_z(char[])java.lang.String
		// @46: aastore
		// @47: dup
		// @48: bipush 6 (0x06)
		// @4A: ldc "k1M]k"
		// @4C: invokestatic game.C_100113_ek.func_104873_z(java.lang.String)char[]
		// @4F: invokestatic game.C_100113_ek.func_104872_z(char[])java.lang.String
		// @52: aastore
		// @53: dup
		// @54: bipush 7 (0x07)
		// @56: ldc "k1M^k"
		// @58: invokestatic game.C_100113_ek.func_104873_z(java.lang.String)char[]
		// @5B: invokestatic game.C_100113_ek.func_104872_z(char[])java.lang.String
		// @5E: aastore
		// @5F: dup
		// @60: bipush 8 (0x08)
		// @62: ldc "k1M\\k"
		// @64: invokestatic game.C_100113_ek.func_104873_z(java.lang.String)char[]
		// @67: invokestatic game.C_100113_ek.func_104872_z(char[])java.lang.String
		// @6A: aastore
		// @6B: dup
		// @6C: bipush 9 (0x09)
		// @6E: ldc "k1M#*`3\u0017!k"
		// @70: invokestatic game.C_100113_ek.func_104873_z(java.lang.String)char[]
		// @73: invokestatic game.C_100113_ek.func_104872_z(char[])java.lang.String
		// @76: aastore
		// @77: putstatic java.lang.String[] game.C_100113_ek.field_104883_z
		// @7A: iconst_0
		// @7B: putstatic int game.C_100113_ek.field_104880_b
		// @7E: iconst_m1
		// @7F: putstatic int game.C_100113_ek.field_104876_f
		// @82: iconst_0
		// @83: putstatic int game.C_100113_ek.field_104882_a
		// @86: iconst_m1
		// @87: putstatic int game.C_100113_ek.field_104884_h
		// @8A: ldc "M6\n|("
		// @8C: invokestatic game.C_100113_ek.func_104873_z(java.lang.String)char[]
		// @8F: invokestatic game.C_100113_ek.func_104872_z(char[])java.lang.String
		// @92: putstatic java.lang.String game.C_100113_ek.field_104879_e
		// @95: ldc "Y;\nk*`=Cy,|z_:s0z\u0017pc}.\u0002m7..\u000bzci;\u000ezm t"
		// @97: invokestatic game.C_100113_ek.func_104873_z(java.lang.String)char[]
		// @9A: invokestatic game.C_100113_ek.func_104872_z(char[])java.lang.String
		// @9D: putstatic java.lang.String game.C_100113_ek.field_104878_d
		// @A0: return
	}
	
	private static char[] func_104873_z(String arg0)
	{
		// @00: aload_0
		// @01: invokevirtual java.lang.String.toCharArray()char[]
		// @04: dup
		// @05: arraylength
		// @06: iconst_2
		// @07: if_icmpge @13
		// @0A: dup
		// @0B: iconst_0
		// @0C: dup2
		// @0D: caload
		// @0E: bipush 67 (0x43)
		// @10: ixor
		// @11: i2c
		// @12: castore
		// @13: areturn
	}
	
	private static String func_104872_z(char[] arg0)
	{
		// @00: aload_0
		// @01: dup
		// @02: arraylength
		// @03: swap
		// @04: iconst_0
		// @05: istore_1
		// @06: goto @4C
		// @09: dup
		// @0A: iload_1
		// @0B: dup2
		// @0C: caload
		// @0D: iload_1
		// @0E: iconst_5
		// @0F: irem
		// @10: tableswitch def: @44, for 0: @30, for 1: @35, for 2: @3A, for 3: @3F
		// @30: bipush 14 (0x0E)
		// @32: goto @46
		// @35: bipush 90 (0x5A)
		// @37: goto @46
		// @3A: bipush 99 (0x63)
		// @3C: goto @46
		// @3F: bipush 31 (0x1F)
		// @41: goto @46
		// @44: bipush 67 (0x43)
		// @46: ixor
		// @47: i2c
		// @48: castore
		// @49: iinc #1 +1
		// @4C: swap
		// @4D: dup_x1
		// @4E: iload_1
		// @4F: if_icmpgt @09
		// @52: new java.lang.String
		// @55: dup_x1
		// @56: swap
		// @57: invokespecial java.lang.String.<init>(char[])void
		// @5A: invokevirtual java.lang.String.intern()java.lang.String
		// @5D: areturn
	}
}
