package game;

import java.net.URL;

final class C_100278_nd extends C_100280_nf
{
	private int field_101201_v;
	static String field_101202_u;
	static String[] field_101204_z;
	static String field_101206_x;
	static String field_101205_y;
	private C_100038_wa field_101200_w;
	private static final String[] field_101203_A;
	
	final int func_101194_o(int arg0)
	{
		// @00: iload_1
		// @01: sipush 255 (0x00FF)
		// @04: if_icmpeq @0A
		// @07: bipush 53 (0x35)
		// @09: ireturn
		// @0A: sipush 255 (0x00FF)
		// @0D: aload_0
		// @0E: getfield byte[] game.C_100278_nd.field_101179_l
		// @11: aload_0
		// @12: dup
		// @13: getfield int game.C_100278_nd.field_101177_n
		// @16: dup_x1
		// @17: iconst_1
		// @18: iadd
		// @19: putfield int game.C_100278_nd.field_101177_n
		// @1C: baload
		// @1D: aload_0
		// @1E: getfield game.C_100038_wa game.C_100278_nd.field_101200_w
		// @21: sipush 256 (0x0100)
		// @24: invokevirtual game.C_100038_wa.func_104061_a(int)int
		// @27: isub
		// @28: iand
		// @29: ireturn
		// @2A: astore_2
		// @2B: aload_2
		// @2C: new java.lang.StringBuilder
		// @2F: dup
		// @30: invokespecial java.lang.StringBuilder.<init>()void
		// @33: getstatic java.lang.String[] game.C_100278_nd.field_101203_A
		// @36: bipush 17 (0x11)
		// @38: aaload
		// @39: invokevirtual java.lang.StringBuilder.append(java.lang.String)java.lang.StringBuilder
		// @3C: iload_1
		// @3D: invokevirtual java.lang.StringBuilder.append(int)java.lang.StringBuilder
		// @40: bipush 41 (0x29)
		// @42: invokevirtual java.lang.StringBuilder.append(char)java.lang.StringBuilder
		// @45: invokevirtual java.lang.StringBuilder.toString()java.lang.String
		// @48: invokestatic game.C_100181_cf.func_105695_a(java.lang.Throwable, java.lang.String)game.C_100170_cm
		// @4B: athrow
	}
	
	final void func_101187_e(boolean arg0)
	{
		// @00: iload_1
		// @01: iconst_1
		// @02: if_icmpeq @0E
		// @05: aload_0
		// @06: iconst_1
		// @07: invokevirtual game.C_100278_nd.func_101187_e(boolean)void
		// @0A: goto @0E
		// @0D: athrow
		// @0E: aload_0
		// @0F: aload_0
		// @10: getfield int game.C_100278_nd.field_101177_n
		// @13: bipush 8 (0x08)
		// @15: imul
		// @16: putfield int game.C_100278_nd.field_101201_v
		// @19: goto @3D
		// @1C: astore_2
		// @1D: aload_2
		// @1E: new java.lang.StringBuilder
		// @21: dup
		// @22: invokespecial java.lang.StringBuilder.<init>()void
		// @25: getstatic java.lang.String[] game.C_100278_nd.field_101203_A
		// @28: iconst_5
		// @29: aaload
		// @2A: invokevirtual java.lang.StringBuilder.append(java.lang.String)java.lang.StringBuilder
		// @2D: iload_1
		// @2E: invokevirtual java.lang.StringBuilder.append(boolean)java.lang.StringBuilder
		// @31: bipush 41 (0x29)
		// @33: invokevirtual java.lang.StringBuilder.append(char)java.lang.StringBuilder
		// @36: invokevirtual java.lang.StringBuilder.toString()java.lang.String
		// @39: invokestatic game.C_100181_cf.func_105695_a(java.lang.Throwable, java.lang.String)game.C_100170_cm
		// @3C: athrow
		// @3D: return
	}
	
	static final void func_101190_a(int arg0, int arg1, int arg2, int arg3, int arg4, int arg5, int arg6, int arg7)
	{
		// @000: getstatic int game.SteelSentinels.field_105275_O
		// @003: istore #11
		// @005: iload_2
		// @006: iload_3
		// @007: iload #7
		// @009: iload #4
		// @00B: iload_0
		// @00C: invokestatic game.C_100196_rb.func_105802_e(int, int, int, int, int)void
		// @00F: iload #7
		// @011: iload #4
		// @013: iload #6
		// @015: iload #5
		// @017: iload_0
		// @018: invokestatic game.C_100196_rb.func_105802_e(int, int, int, int, int)void
		// @01B: iload #6
		// @01D: iload #5
		// @01F: iload_2
		// @020: iload_3
		// @021: iload_0
		// @022: invokestatic game.C_100196_rb.func_105802_e(int, int, int, int, int)void
		// @025: iload #4
		// @027: iconst_m1
		// @028: ixor
		// @029: iload_3
		// @02A: iconst_m1
		// @02B: ixor
		// @02C: if_icmpgt @033
		// @02F: goto @047
		// @032: athrow
		// @033: iload_2
		// @034: istore #8
		// @036: iload #7
		// @038: istore_2
		// @039: iload #8
		// @03B: istore #7
		// @03D: iload_3
		// @03E: istore #8
		// @040: iload #4
		// @042: istore_3
		// @043: iload #8
		// @045: istore #4
		// @047: iload_3
		// @048: iload #5
		// @04A: if_icmpgt @051
		// @04D: goto @065
		// @050: athrow
		// @051: iload_2
		// @052: istore #8
		// @054: iload #6
		// @056: istore_2
		// @057: iload #8
		// @059: istore #6
		// @05B: iload_3
		// @05C: istore #8
		// @05E: iload #5
		// @060: istore_3
		// @061: iload #8
		// @063: istore #5
		// @065: iload_1
		// @066: ifeq @06A
		// @069: return
		// @06A: iload #4
		// @06C: iload #5
		// @06E: if_icmple @089
		// @071: iload #7
		// @073: istore #8
		// @075: iload #6
		// @077: istore #7
		// @079: iload #8
		// @07B: istore #6
		// @07D: iload #4
		// @07F: istore #8
		// @081: iload #5
		// @083: istore #4
		// @085: iload #8
		// @087: istore #5
		// @089: iload #7
		// @08B: iconst_m1
		// @08C: ixor
		// @08D: iload #6
		// @08F: iconst_m1
		// @090: ixor
		// @091: if_icmple @14E
		// @094: iload_3
		// @095: istore #10
		// @097: iload #4
		// @099: iconst_m1
		// @09A: ixor
		// @09B: iload #10
		// @09D: iconst_m1
		// @09E: ixor
		// @09F: if_icmpge @0ED
		// @0A2: iload_2
		// @0A3: iload_3
		// @0A4: ineg
		// @0A5: iload #10
		// @0A7: iadd
		// @0A8: iload #6
		// @0AA: iload_2
		// @0AB: ineg
		// @0AC: iadd
		// @0AD: imul
		// @0AE: iload_3
		// @0AF: ineg
		// @0B0: iload #5
		// @0B2: iadd
		// @0B3: idiv
		// @0B4: iadd
		// @0B5: istore #9
		// @0B7: iload_2
		// @0B8: iload_3
		// @0B9: ineg
		// @0BA: iload #10
		// @0BC: iadd
		// @0BD: iload #7
		// @0BF: iload_2
		// @0C0: isub
		// @0C1: imul
		// @0C2: iload #4
		// @0C4: iload_3
		// @0C5: ineg
		// @0C6: iadd
		// @0C7: idiv
		// @0C8: ineg
		// @0C9: isub
		// @0CA: istore #8
		// @0CC: iload #8
		// @0CE: iload #10
		// @0D0: iload #9
		// @0D2: iload #8
		// @0D4: ineg
		// @0D5: iconst_1
		// @0D6: iadd
		// @0D7: iadd
		// @0D8: iload_0
		// @0D9: invokestatic game.C_100196_rb.func_105807_g(int, int, int, int)void
		// @0DC: iinc #10 +1
		// @0DF: iload #11
		// @0E1: ifne @0F1
		// @0E4: iload #11
		// @0E6: ifeq @097
		// @0E9: goto @0ED
		// @0EC: athrow
		// @0ED: iload #4
		// @0EF: istore #10
		// @0F1: iload #5
		// @0F3: iconst_m1
		// @0F4: ixor
		// @0F5: iload #10
		// @0F7: iconst_m1
		// @0F8: ixor
		// @0F9: if_icmpge @149
		// @0FC: iload_2
		// @0FD: iload_3
		// @0FE: ineg
		// @0FF: iload #10
		// @101: iadd
		// @102: iload_2
		// @103: ineg
		// @104: iload #6
		// @106: iadd
		// @107: imul
		// @108: iload_3
		// @109: ineg
		// @10A: iload #5
		// @10C: iadd
		// @10D: idiv
		// @10E: iadd
		// @10F: istore #9
		// @111: iload #7
		// @113: iload #6
		// @115: iload #7
		// @117: isub
		// @118: iload #4
		// @11A: ineg
		// @11B: iload #10
		// @11D: iadd
		// @11E: imul
		// @11F: iload #5
		// @121: iload #4
		// @123: ineg
		// @124: iadd
		// @125: idiv
		// @126: iadd
		// @127: istore #8
		// @129: iload #8
		// @12B: iload #10
		// @12D: iconst_1
		// @12E: iload #9
		// @130: iadd
		// @131: iload #8
		// @133: isub
		// @134: iload_0
		// @135: invokestatic game.C_100196_rb.func_105807_g(int, int, int, int)void
		// @138: iinc #10 +1
		// @13B: iload #11
		// @13D: ifne @200
		// @140: iload #11
		// @142: ifeq @0F1
		// @145: goto @149
		// @148: athrow
		// @149: iload #11
		// @14B: ifeq @200
		// @14E: iload_3
		// @14F: istore #10
		// @151: iload #10
		// @153: iload #4
		// @155: if_icmpge @1A3
		// @158: iload #7
		// @15A: iload_2
		// @15B: ineg
		// @15C: iadd
		// @15D: iload_3
		// @15E: ineg
		// @15F: iload #10
		// @161: iadd
		// @162: imul
		// @163: iload_3
		// @164: ineg
		// @165: iload #4
		// @167: iadd
		// @168: idiv
		// @169: iload_2
		// @16A: iadd
		// @16B: istore #9
		// @16D: iload_2
		// @16E: iload_2
		// @16F: ineg
		// @170: iload #6
		// @172: iadd
		// @173: iload #10
		// @175: iload_3
		// @176: ineg
		// @177: iadd
		// @178: imul
		// @179: iload #5
		// @17B: iload_3
		// @17C: ineg
		// @17D: iadd
		// @17E: idiv
		// @17F: ineg
		// @180: isub
		// @181: istore #8
		// @183: iload #8
		// @185: iload #10
		// @187: iload #9
		// @189: iload #8
		// @18B: iconst_1
		// @18C: isub
		// @18D: isub
		// @18E: iload_0
		// @18F: invokestatic game.C_100196_rb.func_105807_g(int, int, int, int)void
		// @192: iinc #10 +1
		// @195: iload #11
		// @197: ifne @1A7
		// @19A: iload #11
		// @19C: ifeq @151
		// @19F: goto @1A3
		// @1A2: athrow
		// @1A3: iload #4
		// @1A5: istore #10
		// @1A7: iload #5
		// @1A9: iconst_m1
		// @1AA: ixor
		// @1AB: iload #10
		// @1AD: iconst_m1
		// @1AE: ixor
		// @1AF: if_icmpge @200
		// @1B2: iload #7
		// @1B4: iload #6
		// @1B6: iload #7
		// @1B8: isub
		// @1B9: iload #4
		// @1BB: ineg
		// @1BC: iload #10
		// @1BE: iadd
		// @1BF: imul
		// @1C0: iload #5
		// @1C2: iload #4
		// @1C4: ineg
		// @1C5: iadd
		// @1C6: idiv
		// @1C7: iadd
		// @1C8: istore #9
		// @1CA: iload_2
		// @1CB: ineg
		// @1CC: iload #6
		// @1CE: iadd
		// @1CF: iload_3
		// @1D0: ineg
		// @1D1: iload #10
		// @1D3: iadd
		// @1D4: imul
		// @1D5: iload_3
		// @1D6: ineg
		// @1D7: iload #5
		// @1D9: iadd
		// @1DA: idiv
		// @1DB: iload_2
		// @1DC: iadd
		// @1DD: istore #8
		// @1DF: iload #8
		// @1E1: iload #10
		// @1E3: iconst_1
		// @1E4: iload #8
		// @1E6: ineg
		// @1E7: iadd
		// @1E8: iload #9
		// @1EA: iadd
		// @1EB: iload_0
		// @1EC: invokestatic game.C_100196_rb.func_105807_g(int, int, int, int)void
		// @1EF: iinc #10 +1
		// @1F2: iload #11
		// @1F4: ifne @269
		// @1F7: iload #11
		// @1F9: ifeq @1A7
		// @1FC: goto @200
		// @1FF: athrow
		// @200: goto @269
		// @203: astore #8
		// @205: aload #8
		// @207: new java.lang.StringBuilder
		// @20A: dup
		// @20B: invokespecial java.lang.StringBuilder.<init>()void
		// @20E: getstatic java.lang.String[] game.C_100278_nd.field_101203_A
		// @211: iconst_0
		// @212: aaload
		// @213: invokevirtual java.lang.StringBuilder.append(java.lang.String)java.lang.StringBuilder
		// @216: iload_0
		// @217: invokevirtual java.lang.StringBuilder.append(int)java.lang.StringBuilder
		// @21A: bipush 44 (0x2C)
		// @21C: invokevirtual java.lang.StringBuilder.append(char)java.lang.StringBuilder
		// @21F: iload_1
		// @220: invokevirtual java.lang.StringBuilder.append(int)java.lang.StringBuilder
		// @223: bipush 44 (0x2C)
		// @225: invokevirtual java.lang.StringBuilder.append(char)java.lang.StringBuilder
		// @228: iload_2
		// @229: invokevirtual java.lang.StringBuilder.append(int)java.lang.StringBuilder
		// @22C: bipush 44 (0x2C)
		// @22E: invokevirtual java.lang.StringBuilder.append(char)java.lang.StringBuilder
		// @231: iload_3
		// @232: invokevirtual java.lang.StringBuilder.append(int)java.lang.StringBuilder
		// @235: bipush 44 (0x2C)
		// @237: invokevirtual java.lang.StringBuilder.append(char)java.lang.StringBuilder
		// @23A: iload #4
		// @23C: invokevirtual java.lang.StringBuilder.append(int)java.lang.StringBuilder
		// @23F: bipush 44 (0x2C)
		// @241: invokevirtual java.lang.StringBuilder.append(char)java.lang.StringBuilder
		// @244: iload #5
		// @246: invokevirtual java.lang.StringBuilder.append(int)java.lang.StringBuilder
		// @249: bipush 44 (0x2C)
		// @24B: invokevirtual java.lang.StringBuilder.append(char)java.lang.StringBuilder
		// @24E: iload #6
		// @250: invokevirtual java.lang.StringBuilder.append(int)java.lang.StringBuilder
		// @253: bipush 44 (0x2C)
		// @255: invokevirtual java.lang.StringBuilder.append(char)java.lang.StringBuilder
		// @258: iload #7
		// @25A: invokevirtual java.lang.StringBuilder.append(int)java.lang.StringBuilder
		// @25D: bipush 41 (0x29)
		// @25F: invokevirtual java.lang.StringBuilder.append(char)java.lang.StringBuilder
		// @262: invokevirtual java.lang.StringBuilder.toString()java.lang.String
		// @265: invokestatic game.C_100181_cf.func_105695_a(java.lang.Throwable, java.lang.String)game.C_100170_cm
		// @268: athrow
		// @269: return
	}
	
	static final void func_101196_k(int arg0, int arg1)
	{
		// @00: aconst_null
		// @01: getstatic game.C_100214_al[] game.C_100330_ig.field_107287_b
		// @04: if_acmpeq @27
		// @07: aconst_null
		// @08: getstatic game.C_100214_al[] game.C_100330_ig.field_107287_b
		// @0B: iload_0
		// @0C: aaload
		// @0D: if_acmpeq @27
		// @10: goto @14
		// @13: athrow
		// @14: getstatic int[] game.C_100169_co.field_105526_b
		// @17: iload_0
		// @18: iaload
		// @19: getstatic game.C_100214_al[] game.C_100330_ig.field_107287_b
		// @1C: iload_0
		// @1D: aaload
		// @1E: iconst_0
		// @1F: invokestatic game.C_100180_ce.func_104800_a(int, game.C_100214_al, int)game.C_100179_ch
		// @22: pop
		// @23: goto @27
		// @26: athrow
		// @27: iload_1
		// @28: bipush 8 (0x08)
		// @2A: if_icmpeq @38
		// @2D: aconst_null
		// @2E: checkcast java.lang.String
		// @31: putstatic java.lang.String game.C_100278_nd.field_101206_x
		// @34: goto @38
		// @37: athrow
		// @38: goto @65
		// @3B: astore_2
		// @3C: aload_2
		// @3D: new java.lang.StringBuilder
		// @40: dup
		// @41: invokespecial java.lang.StringBuilder.<init>()void
		// @44: getstatic java.lang.String[] game.C_100278_nd.field_101203_A
		// @47: iconst_4
		// @48: aaload
		// @49: invokevirtual java.lang.StringBuilder.append(java.lang.String)java.lang.StringBuilder
		// @4C: iload_0
		// @4D: invokevirtual java.lang.StringBuilder.append(int)java.lang.StringBuilder
		// @50: bipush 44 (0x2C)
		// @52: invokevirtual java.lang.StringBuilder.append(char)java.lang.StringBuilder
		// @55: iload_1
		// @56: invokevirtual java.lang.StringBuilder.append(int)java.lang.StringBuilder
		// @59: bipush 41 (0x29)
		// @5B: invokevirtual java.lang.StringBuilder.append(char)java.lang.StringBuilder
		// @5E: invokevirtual java.lang.StringBuilder.toString()java.lang.String
		// @61: invokestatic game.C_100181_cf.func_105695_a(java.lang.Throwable, java.lang.String)game.C_100170_cm
		// @64: athrow
		// @65: return
	}
	
	final void func_101189_h(int arg0, int arg1)
	{
		// @00: aload_0
		// @01: getfield byte[] game.C_100278_nd.field_101179_l
		// @04: aload_0
		// @05: dup
		// @06: getfield int game.C_100278_nd.field_101177_n
		// @09: dup_x1
		// @0A: iconst_1
		// @0B: iadd
		// @0C: putfield int game.C_100278_nd.field_101177_n
		// @0F: iload_1
		// @10: aload_0
		// @11: getfield game.C_100038_wa game.C_100278_nd.field_101200_w
		// @14: sipush 256 (0x0100)
		// @17: invokevirtual game.C_100038_wa.func_104061_a(int)int
		// @1A: iadd
		// @1B: i2b
		// @1C: bastore
		// @1D: iload_2
		// @1E: bipush 102 (0x66)
		// @20: if_icmpge @2B
		// @23: aload_0
		// @24: aconst_null
		// @25: checkcast game.C_100038_wa
		// @28: putfield game.C_100038_wa game.C_100278_nd.field_101200_w
		// @2B: goto @59
		// @2E: astore_3
		// @2F: aload_3
		// @30: new java.lang.StringBuilder
		// @33: dup
		// @34: invokespecial java.lang.StringBuilder.<init>()void
		// @37: getstatic java.lang.String[] game.C_100278_nd.field_101203_A
		// @3A: bipush 19 (0x13)
		// @3C: aaload
		// @3D: invokevirtual java.lang.StringBuilder.append(java.lang.String)java.lang.StringBuilder
		// @40: iload_1
		// @41: invokevirtual java.lang.StringBuilder.append(int)java.lang.StringBuilder
		// @44: bipush 44 (0x2C)
		// @46: invokevirtual java.lang.StringBuilder.append(char)java.lang.StringBuilder
		// @49: iload_2
		// @4A: invokevirtual java.lang.StringBuilder.append(int)java.lang.StringBuilder
		// @4D: bipush 41 (0x29)
		// @4F: invokevirtual java.lang.StringBuilder.append(char)java.lang.StringBuilder
		// @52: invokevirtual java.lang.StringBuilder.toString()java.lang.String
		// @55: invokestatic game.C_100181_cf.func_105695_a(java.lang.Throwable, java.lang.String)game.C_100170_cm
		// @58: athrow
		// @59: return
	}
	
	static final C_100061_dh func_101197_b(String arg0, int arg1)
	{
		// @00: getstatic int game.SteelSentinels.field_105275_O
		// @03: istore #6
		// @05: getstatic game.C_100105_eg game.C_100170_cm.field_105536_f
		// @08: ifnull @22
		// @0B: aconst_null
		// @0C: aload_0
		// @0D: if_acmpeq @22
		// @10: goto @14
		// @13: athrow
		// @14: aload_0
		// @15: invokevirtual java.lang.String.length()int
		// @18: iconst_m1
		// @19: ixor
		// @1A: iconst_m1
		// @1B: if_icmpne @24
		// @1E: goto @22
		// @21: athrow
		// @22: aconst_null
		// @23: areturn
		// @24: bipush -12 (0xF4)
		// @26: bipush -5 (0xFB)
		// @28: iload_1
		// @29: isub
		// @2A: bipush 61 (0x3D)
		// @2C: idiv
		// @2D: idiv
		// @2E: istore_2
		// @2F: bipush -83 (0xAD)
		// @31: aload_0
		// @32: invokestatic game.C_100106_ef.func_104742_a(byte, java.lang.CharSequence)java.lang.String
		// @35: astore_3
		// @36: aload_3
		// @37: ifnull @3E
		// @3A: goto @40
		// @3D: athrow
		// @3E: aconst_null
		// @3F: areturn
		// @40: getstatic game.C_100105_eg game.C_100170_cm.field_105536_f
		// @43: sipush -16397 (0xBFF3)
		// @46: aload_3
		// @47: invokevirtual java.lang.String.hashCode()int
		// @4A: i2l
		// @4B: invokevirtual game.C_100105_eg.func_104724_a(int, long)game.C_100325_id
		// @4E: checkcast game.C_100061_dh
		// @51: astore #4
		// @53: aload #4
		// @55: ifnull @81
		// @58: bipush -95 (0xA1)
		// @5A: aload #4
		// @5C: getfield java.lang.String game.C_100061_dh.field_101993_nc
		// @5F: invokestatic game.C_100106_ef.func_104742_a(byte, java.lang.CharSequence)java.lang.String
		// @62: astore #5
		// @64: aload #5
		// @66: aload_3
		// @67: invokevirtual java.lang.String.equals(java.lang.Object)boolean
		// @6A: ifeq @70
		// @6D: aload #4
		// @6F: areturn
		// @70: getstatic game.C_100105_eg game.C_100170_cm.field_105536_f
		// @73: iconst_m1
		// @74: invokevirtual game.C_100105_eg.func_104732_a(int)game.C_100325_id
		// @77: checkcast game.C_100061_dh
		// @7A: astore #4
		// @7C: iload #6
		// @7E: ifeq @53
		// @81: aconst_null
		// @82: areturn
		// @83: astore_2
		// @84: aload_2
		// @85: new java.lang.StringBuilder
		// @88: dup
		// @89: invokespecial java.lang.StringBuilder.<init>()void
		// @8C: getstatic java.lang.String[] game.C_100278_nd.field_101203_A
		// @8F: bipush 20 (0x14)
		// @91: aaload
		// @92: invokevirtual java.lang.StringBuilder.append(java.lang.String)java.lang.StringBuilder
		// @95: aload_0
		// @96: ifnull @A2
		// @99: getstatic java.lang.String[] game.C_100278_nd.field_101203_A
		// @9C: iconst_3
		// @9D: aaload
		// @9E: goto @A7
		// @A1: athrow
		// @A2: getstatic java.lang.String[] game.C_100278_nd.field_101203_A
		// @A5: iconst_1
		// @A6: aaload
		// @A7: invokevirtual java.lang.StringBuilder.append(java.lang.String)java.lang.StringBuilder
		// @AA: bipush 44 (0x2C)
		// @AC: invokevirtual java.lang.StringBuilder.append(char)java.lang.StringBuilder
		// @AF: iload_1
		// @B0: invokevirtual java.lang.StringBuilder.append(int)java.lang.StringBuilder
		// @B3: bipush 41 (0x29)
		// @B5: invokevirtual java.lang.StringBuilder.append(char)java.lang.StringBuilder
		// @B8: invokevirtual java.lang.StringBuilder.toString()java.lang.String
		// @BB: invokestatic game.C_100181_cf.func_105695_a(java.lang.Throwable, java.lang.String)game.C_100170_cm
		// @BE: athrow
	}
	
	C_100278_nd(byte[] arg0)
	{
		// @0: aload_0
		// @1: aload_1
		// @2: invokespecial game.C_100280_nf.<init>(byte[])void
		// @5: return
	}
	
	C_100278_nd(int arg0)
	{
		// @0: aload_0
		// @1: iload_1
		// @2: invokespecial game.C_100280_nf.<init>(int)void
		// @5: return
	}
	
	final void func_101191_p(int arg0)
	{
		// @00: iload_1
		// @01: bipush 117 (0x75)
		// @03: if_icmpgt @11
		// @06: bipush 116 (0x74)
		// @08: bipush 29 (0x1D)
		// @0A: invokestatic game.C_100278_nd.func_101199_j(int, int)void
		// @0D: goto @11
		// @10: athrow
		// @11: aload_0
		// @12: aload_0
		// @13: getfield int game.C_100278_nd.field_101201_v
		// @16: bipush 7 (0x07)
		// @18: iadd
		// @19: bipush 8 (0x08)
		// @1B: idiv
		// @1C: putfield int game.C_100278_nd.field_101177_n
		// @1F: goto @44
		// @22: astore_2
		// @23: aload_2
		// @24: new java.lang.StringBuilder
		// @27: dup
		// @28: invokespecial java.lang.StringBuilder.<init>()void
		// @2B: getstatic java.lang.String[] game.C_100278_nd.field_101203_A
		// @2E: bipush 6 (0x06)
		// @30: aaload
		// @31: invokevirtual java.lang.StringBuilder.append(java.lang.String)java.lang.StringBuilder
		// @34: iload_1
		// @35: invokevirtual java.lang.StringBuilder.append(int)java.lang.StringBuilder
		// @38: bipush 41 (0x29)
		// @3A: invokevirtual java.lang.StringBuilder.append(char)java.lang.StringBuilder
		// @3D: invokevirtual java.lang.StringBuilder.toString()java.lang.String
		// @40: invokestatic game.C_100181_cf.func_105695_a(java.lang.Throwable, java.lang.String)game.C_100170_cm
		// @43: athrow
		// @44: return
	}
	
	final void func_101184_a(int[] arg0, boolean arg1)
	{
		// @00: iload_2
		// @01: ifeq @0F
		// @04: aconst_null
		// @05: checkcast java.lang.String[]
		// @08: putstatic java.lang.String[] game.C_100278_nd.field_101204_z
		// @0B: goto @0F
		// @0E: athrow
		// @0F: aload_0
		// @10: new game.C_100038_wa
		// @13: dup
		// @14: aload_1
		// @15: invokespecial game.C_100038_wa.<init>(int[])void
		// @18: putfield game.C_100038_wa game.C_100278_nd.field_101200_w
		// @1B: goto @5A
		// @1E: astore_3
		// @1F: aload_3
		// @20: new java.lang.StringBuilder
		// @23: dup
		// @24: invokespecial java.lang.StringBuilder.<init>()void
		// @27: getstatic java.lang.String[] game.C_100278_nd.field_101203_A
		// @2A: bipush 18 (0x12)
		// @2C: aaload
		// @2D: invokevirtual java.lang.StringBuilder.append(java.lang.String)java.lang.StringBuilder
		// @30: aload_1
		// @31: ifnull @3D
		// @34: getstatic java.lang.String[] game.C_100278_nd.field_101203_A
		// @37: iconst_3
		// @38: aaload
		// @39: goto @42
		// @3C: athrow
		// @3D: getstatic java.lang.String[] game.C_100278_nd.field_101203_A
		// @40: iconst_1
		// @41: aaload
		// @42: invokevirtual java.lang.StringBuilder.append(java.lang.String)java.lang.StringBuilder
		// @45: bipush 44 (0x2C)
		// @47: invokevirtual java.lang.StringBuilder.append(char)java.lang.StringBuilder
		// @4A: iload_2
		// @4B: invokevirtual java.lang.StringBuilder.append(boolean)java.lang.StringBuilder
		// @4E: bipush 41 (0x29)
		// @50: invokevirtual java.lang.StringBuilder.append(char)java.lang.StringBuilder
		// @53: invokevirtual java.lang.StringBuilder.toString()java.lang.String
		// @56: invokestatic game.C_100181_cf.func_105695_a(java.lang.Throwable, java.lang.String)game.C_100170_cm
		// @59: athrow
		// @5A: return
	}
	
	static final URL func_101193_a(String arg0, byte arg1, String arg2, int arg3, URL arg4)
	{
		// @000: getstatic int game.SteelSentinels.field_105275_O
		// @003: istore #9
		// @005: aload #4
		// @007: invokevirtual java.net.URL.getFile()java.lang.String
		// @00A: astore #5
		// @00C: iconst_0
		// @00D: istore #6
		// @00F: aload #5
		// @011: iload #6
		// @013: getstatic java.lang.String[] game.C_100278_nd.field_101203_A
		// @016: bipush 12 (0x0C)
		// @018: aaload
		// @019: iconst_0
		// @01A: iconst_3
		// @01B: invokevirtual java.lang.String.regionMatches(int, java.lang.String, int, int)boolean
		// @01E: ifne @024
		// @021: goto @070
		// @024: aload #5
		// @026: bipush 47 (0x2F)
		// @028: iload #6
		// @02A: iconst_m1
		// @02B: isub
		// @02C: invokevirtual java.lang.String.indexOf(int, int)int
		// @02F: istore #7
		// @031: iload #7
		// @033: ifge @03A
		// @036: goto @070
		// @039: athrow
		// @03A: iconst_m1
		// @03B: iload_3
		// @03C: iconst_m1
		// @03D: ixor
		// @03E: if_icmplt @067
		// @041: new java.lang.StringBuilder
		// @044: dup
		// @045: invokespecial java.lang.StringBuilder.<init>()void
		// @048: aload #5
		// @04A: iconst_0
		// @04B: iload #6
		// @04D: invokevirtual java.lang.String.substring(int, int)java.lang.String
		// @050: invokevirtual java.lang.StringBuilder.append(java.lang.String)java.lang.StringBuilder
		// @053: aload #5
		// @055: iload #7
		// @057: invokevirtual java.lang.String.substring(int)java.lang.String
		// @05A: invokevirtual java.lang.StringBuilder.append(java.lang.String)java.lang.StringBuilder
		// @05D: invokevirtual java.lang.StringBuilder.toString()java.lang.String
		// @060: astore #5
		// @062: iload #9
		// @064: ifeq @00F
		// @067: iload #7
		// @069: istore #6
		// @06B: iload #9
		// @06D: ifeq @00F
		// @070: aload #5
		// @072: iload #6
		// @074: getstatic java.lang.String[] game.C_100278_nd.field_101203_A
		// @077: bipush 13 (0x0D)
		// @079: aaload
		// @07A: iconst_0
		// @07B: iconst_3
		// @07C: invokevirtual java.lang.String.regionMatches(int, java.lang.String, int, int)boolean
		// @07F: ifeq @0A4
		// @082: aload #5
		// @084: bipush 47 (0x2F)
		// @086: iconst_1
		// @087: iload #6
		// @089: iadd
		// @08A: invokevirtual java.lang.String.indexOf(int, int)int
		// @08D: istore #7
		// @08F: iload #7
		// @091: iconst_m1
		// @092: ixor
		// @093: iconst_m1
		// @094: if_icmple @09B
		// @097: goto @0A4
		// @09A: athrow
		// @09B: iload #7
		// @09D: istore #6
		// @09F: iload #9
		// @0A1: ifeq @00F
		// @0A4: aload #5
		// @0A6: iload #6
		// @0A8: getstatic java.lang.String[] game.C_100278_nd.field_101203_A
		// @0AB: bipush 10 (0x0A)
		// @0AD: aaload
		// @0AE: iconst_0
		// @0AF: iconst_3
		// @0B0: invokevirtual java.lang.String.regionMatches(int, java.lang.String, int, int)boolean
		// @0B3: ifne @0BA
		// @0B6: goto @103
		// @0B9: athrow
		// @0BA: aload #5
		// @0BC: bipush 47 (0x2F)
		// @0BE: iconst_1
		// @0BF: iload #6
		// @0C1: iadd
		// @0C2: invokevirtual java.lang.String.indexOf(int, int)int
		// @0C5: istore #7
		// @0C7: iload #7
		// @0C9: ifge @0D0
		// @0CC: goto @103
		// @0CF: athrow
		// @0D0: aload_0
		// @0D1: ifnull @0FA
		// @0D4: new java.lang.StringBuilder
		// @0D7: dup
		// @0D8: invokespecial java.lang.StringBuilder.<init>()void
		// @0DB: aload #5
		// @0DD: iconst_0
		// @0DE: iload #6
		// @0E0: invokevirtual java.lang.String.substring(int, int)java.lang.String
		// @0E3: invokevirtual java.lang.StringBuilder.append(java.lang.String)java.lang.StringBuilder
		// @0E6: aload #5
		// @0E8: iload #7
		// @0EA: invokevirtual java.lang.String.substring(int)java.lang.String
		// @0ED: invokevirtual java.lang.StringBuilder.append(java.lang.String)java.lang.StringBuilder
		// @0F0: invokevirtual java.lang.StringBuilder.toString()java.lang.String
		// @0F3: astore #5
		// @0F5: iload #9
		// @0F7: ifeq @00F
		// @0FA: iload #7
		// @0FC: istore #6
		// @0FE: iload #9
		// @100: ifeq @00F
		// @103: aload #5
		// @105: iload #6
		// @107: getstatic java.lang.String[] game.C_100278_nd.field_101203_A
		// @10A: bipush 9 (0x09)
		// @10C: aaload
		// @10D: iconst_0
		// @10E: iconst_3
		// @10F: invokevirtual java.lang.String.regionMatches(int, java.lang.String, int, int)boolean
		// @112: ifne @12F
		// @115: aload #5
		// @117: iload #6
		// @119: getstatic java.lang.String[] game.C_100278_nd.field_101203_A
		// @11C: bipush 8 (0x08)
		// @11E: aaload
		// @11F: iconst_0
		// @120: iconst_3
		// @121: invokevirtual java.lang.String.regionMatches(int, java.lang.String, int, int)boolean
		// @124: ifne @12F
		// @127: goto @12B
		// @12A: athrow
		// @12B: goto @17B
		// @12E: athrow
		// @12F: aload #5
		// @131: bipush 47 (0x2F)
		// @133: iload #6
		// @135: iconst_m1
		// @136: isub
		// @137: invokevirtual java.lang.String.indexOf(int, int)int
		// @13A: istore #7
		// @13C: iload #7
		// @13E: iflt @178
		// @141: aload_2
		// @142: ifnonnull @152
		// @145: goto @149
		// @148: athrow
		// @149: iload #7
		// @14B: istore #6
		// @14D: iload #9
		// @14F: ifeq @00F
		// @152: new java.lang.StringBuilder
		// @155: dup
		// @156: invokespecial java.lang.StringBuilder.<init>()void
		// @159: aload #5
		// @15B: iconst_0
		// @15C: iload #6
		// @15E: invokevirtual java.lang.String.substring(int, int)java.lang.String
		// @161: invokevirtual java.lang.StringBuilder.append(java.lang.String)java.lang.StringBuilder
		// @164: aload #5
		// @166: iload #7
		// @168: invokevirtual java.lang.String.substring(int)java.lang.String
		// @16B: invokevirtual java.lang.StringBuilder.append(java.lang.String)java.lang.StringBuilder
		// @16E: invokevirtual java.lang.StringBuilder.toString()java.lang.String
		// @171: astore #5
		// @173: iload #9
		// @175: ifeq @00F
		// @178: goto @17B
		// @17B: new java.lang.StringBuilder
		// @17E: dup
		// @17F: iload #6
		// @181: invokespecial java.lang.StringBuilder.<init>(int)void
		// @184: astore #7
		// @186: aload #7
		// @188: aload #5
		// @18A: iconst_0
		// @18B: iload #6
		// @18D: invokevirtual java.lang.String.substring(int, int)java.lang.String
		// @190: invokevirtual java.lang.StringBuilder.append(java.lang.String)java.lang.StringBuilder
		// @193: pop
		// @194: iload_3
		// @195: ifgt @19C
		// @198: goto @1B2
		// @19B: athrow
		// @19C: aload #7
		// @19E: getstatic java.lang.String[] game.C_100278_nd.field_101203_A
		// @1A1: bipush 12 (0x0C)
		// @1A3: aaload
		// @1A4: invokevirtual java.lang.StringBuilder.append(java.lang.String)java.lang.StringBuilder
		// @1A7: pop
		// @1A8: aload #7
		// @1AA: iload_3
		// @1AB: invokestatic java.lang.Integer.toString(int)java.lang.String
		// @1AE: invokevirtual java.lang.StringBuilder.append(java.lang.String)java.lang.StringBuilder
		// @1B1: pop
		// @1B2: aconst_null
		// @1B3: aload_0
		// @1B4: if_acmpeq @1D9
		// @1B7: aload_0
		// @1B8: invokevirtual java.lang.String.length()int
		// @1BB: ifgt @1C6
		// @1BE: goto @1C2
		// @1C1: athrow
		// @1C2: goto @1D9
		// @1C5: athrow
		// @1C6: aload #7
		// @1C8: getstatic java.lang.String[] game.C_100278_nd.field_101203_A
		// @1CB: bipush 10 (0x0A)
		// @1CD: aaload
		// @1CE: invokevirtual java.lang.StringBuilder.append(java.lang.String)java.lang.StringBuilder
		// @1D1: pop
		// @1D2: aload #7
		// @1D4: aload_0
		// @1D5: invokevirtual java.lang.StringBuilder.append(java.lang.String)java.lang.StringBuilder
		// @1D8: pop
		// @1D9: iload_1
		// @1DA: bipush -14 (0xF2)
		// @1DC: if_icmpeq @1EA
		// @1DF: bipush 50 (0x32)
		// @1E1: bipush -97 (0x9F)
		// @1E3: invokestatic game.C_100278_nd.func_101199_j(int, int)void
		// @1E6: goto @1EA
		// @1E9: athrow
		// @1EA: aload_2
		// @1EB: ifnull @211
		// @1EE: iconst_0
		// @1EF: aload_2
		// @1F0: invokevirtual java.lang.String.length()int
		// @1F3: if_icmplt @1FE
		// @1F6: goto @1FA
		// @1F9: athrow
		// @1FA: goto @211
		// @1FD: athrow
		// @1FE: aload #7
		// @200: getstatic java.lang.String[] game.C_100278_nd.field_101203_A
		// @203: bipush 9 (0x09)
		// @205: aaload
		// @206: invokevirtual java.lang.StringBuilder.append(java.lang.String)java.lang.StringBuilder
		// @209: pop
		// @20A: aload #7
		// @20C: aload_2
		// @20D: invokevirtual java.lang.StringBuilder.append(java.lang.String)java.lang.StringBuilder
		// @210: pop
		// @211: iload #6
		// @213: iconst_m1
		// @214: ixor
		// @215: aload #5
		// @217: invokevirtual java.lang.String.length()int
		// @21A: iconst_m1
		// @21B: ixor
		// @21C: if_icmple @23A
		// @21F: aload #7
		// @221: aload #5
		// @223: iload #6
		// @225: aload #5
		// @227: invokevirtual java.lang.String.length()int
		// @22A: invokevirtual java.lang.String.substring(int, int)java.lang.String
		// @22D: invokevirtual java.lang.StringBuilder.append(java.lang.String)java.lang.StringBuilder
		// @230: pop
		// @231: iload #9
		// @233: ifeq @246
		// @236: goto @23A
		// @239: athrow
		// @23A: aload #7
		// @23C: bipush 47 (0x2F)
		// @23E: invokevirtual java.lang.StringBuilder.append(char)java.lang.StringBuilder
		// @241: pop
		// @242: goto @246
		// @245: athrow
		// @246: new java.net.URL
		// @249: dup
		// @24A: aload #4
		// @24C: aload #7
		// @24E: invokevirtual java.lang.StringBuilder.toString()java.lang.String
		// @251: invokespecial java.net.URL.<init>(java.net.URL, java.lang.String)void
		// @254: areturn
		// @255: astore #8
		// @257: aload #8
		// @259: invokevirtual java.lang.Exception.printStackTrace()void
		// @25C: aload #4
		// @25E: areturn
		// @25F: astore #5
		// @261: aload #5
		// @263: new java.lang.StringBuilder
		// @266: dup
		// @267: invokespecial java.lang.StringBuilder.<init>()void
		// @26A: getstatic java.lang.String[] game.C_100278_nd.field_101203_A
		// @26D: bipush 11 (0x0B)
		// @26F: aaload
		// @270: invokevirtual java.lang.StringBuilder.append(java.lang.String)java.lang.StringBuilder
		// @273: aload_0
		// @274: ifnull @280
		// @277: getstatic java.lang.String[] game.C_100278_nd.field_101203_A
		// @27A: iconst_3
		// @27B: aaload
		// @27C: goto @285
		// @27F: athrow
		// @280: getstatic java.lang.String[] game.C_100278_nd.field_101203_A
		// @283: iconst_1
		// @284: aaload
		// @285: invokevirtual java.lang.StringBuilder.append(java.lang.String)java.lang.StringBuilder
		// @288: bipush 44 (0x2C)
		// @28A: invokevirtual java.lang.StringBuilder.append(char)java.lang.StringBuilder
		// @28D: iload_1
		// @28E: invokevirtual java.lang.StringBuilder.append(int)java.lang.StringBuilder
		// @291: bipush 44 (0x2C)
		// @293: invokevirtual java.lang.StringBuilder.append(char)java.lang.StringBuilder
		// @296: aload_2
		// @297: ifnull @2A3
		// @29A: getstatic java.lang.String[] game.C_100278_nd.field_101203_A
		// @29D: iconst_3
		// @29E: aaload
		// @29F: goto @2A8
		// @2A2: athrow
		// @2A3: getstatic java.lang.String[] game.C_100278_nd.field_101203_A
		// @2A6: iconst_1
		// @2A7: aaload
		// @2A8: invokevirtual java.lang.StringBuilder.append(java.lang.String)java.lang.StringBuilder
		// @2AB: bipush 44 (0x2C)
		// @2AD: invokevirtual java.lang.StringBuilder.append(char)java.lang.StringBuilder
		// @2B0: iload_3
		// @2B1: invokevirtual java.lang.StringBuilder.append(int)java.lang.StringBuilder
		// @2B4: bipush 44 (0x2C)
		// @2B6: invokevirtual java.lang.StringBuilder.append(char)java.lang.StringBuilder
		// @2B9: aload #4
		// @2BB: ifnull @2C7
		// @2BE: getstatic java.lang.String[] game.C_100278_nd.field_101203_A
		// @2C1: iconst_3
		// @2C2: aaload
		// @2C3: goto @2CC
		// @2C6: athrow
		// @2C7: getstatic java.lang.String[] game.C_100278_nd.field_101203_A
		// @2CA: iconst_1
		// @2CB: aaload
		// @2CC: invokevirtual java.lang.StringBuilder.append(java.lang.String)java.lang.StringBuilder
		// @2CF: bipush 41 (0x29)
		// @2D1: invokevirtual java.lang.StringBuilder.append(char)java.lang.StringBuilder
		// @2D4: invokevirtual java.lang.StringBuilder.toString()java.lang.String
		// @2D7: invokestatic game.C_100181_cf.func_105695_a(java.lang.Throwable, java.lang.String)game.C_100170_cm
		// @2DA: athrow
	}
	
	final int func_101195_i(int arg0, int arg1)
	{
		// @00: getstatic int game.SteelSentinels.field_105275_O
		// @03: istore #6
		// @05: iload_2
		// @06: sipush 15738 (0x3D7A)
		// @09: if_icmpeq @15
		// @0C: bipush 82 (0x52)
		// @0E: invokestatic game.C_100278_nd.func_101188_m(int)void
		// @11: goto @15
		// @14: athrow
		// @15: aload_0
		// @16: getfield int game.C_100278_nd.field_101201_v
		// @19: ldc 1894776515 (0x70effec3)
		// @1B: ishr
		// @1C: istore_3
		// @1D: bipush 8 (0x08)
		// @1F: bipush 7 (0x07)
		// @21: aload_0
		// @22: getfield int game.C_100278_nd.field_101201_v
		// @25: iand
		// @26: ineg
		// @27: iadd
		// @28: istore #4
		// @2A: iconst_0
		// @2B: istore #5
		// @2D: aload_0
		// @2E: dup
		// @2F: getfield int game.C_100278_nd.field_101201_v
		// @32: iload_1
		// @33: iadd
		// @34: putfield int game.C_100278_nd.field_101201_v
		// @37: iload_1
		// @38: iload #4
		// @3A: if_icmple @6F
		// @3D: iload #5
		// @3F: getstatic int[] game.C_100273_mm.field_106680_g
		// @42: iload #4
		// @44: iaload
		// @45: aload_0
		// @46: getfield byte[] game.C_100278_nd.field_101179_l
		// @49: iload_3
		// @4A: iinc #3 +1
		// @4D: baload
		// @4E: iand
		// @4F: iload #4
		// @51: ineg
		// @52: iload_1
		// @53: iadd
		// @54: ishl
		// @55: iadd
		// @56: istore #5
		// @58: iload_1
		// @59: iload #4
		// @5B: isub
		// @5C: istore_1
		// @5D: bipush 8 (0x08)
		// @5F: istore #4
		// @61: iload #6
		// @63: ifne @95
		// @66: iload #6
		// @68: ifeq @37
		// @6B: goto @6F
		// @6E: athrow
		// @6F: iload_1
		// @70: iconst_m1
		// @71: ixor
		// @72: iload #4
		// @74: iconst_m1
		// @75: ixor
		// @76: if_icmpeq @95
		// @79: iload #5
		// @7B: aload_0
		// @7C: getfield byte[] game.C_100278_nd.field_101179_l
		// @7F: iload_3
		// @80: baload
		// @81: iload #4
		// @83: iload_1
		// @84: ineg
		// @85: iadd
		// @86: ishr
		// @87: getstatic int[] game.C_100273_mm.field_106680_g
		// @8A: iload_1
		// @8B: iaload
		// @8C: iand
		// @8D: iadd
		// @8E: istore #5
		// @90: iload #6
		// @92: ifeq @A7
		// @95: iload #5
		// @97: getstatic int[] game.C_100273_mm.field_106680_g
		// @9A: iload #4
		// @9C: iaload
		// @9D: aload_0
		// @9E: getfield byte[] game.C_100278_nd.field_101179_l
		// @A1: iload_3
		// @A2: baload
		// @A3: iand
		// @A4: iadd
		// @A5: istore #5
		// @A7: iload #5
		// @A9: ireturn
		// @AA: astore_3
		// @AB: aload_3
		// @AC: new java.lang.StringBuilder
		// @AF: dup
		// @B0: invokespecial java.lang.StringBuilder.<init>()void
		// @B3: getstatic java.lang.String[] game.C_100278_nd.field_101203_A
		// @B6: bipush 15 (0x0F)
		// @B8: aaload
		// @B9: invokevirtual java.lang.StringBuilder.append(java.lang.String)java.lang.StringBuilder
		// @BC: iload_1
		// @BD: invokevirtual java.lang.StringBuilder.append(int)java.lang.StringBuilder
		// @C0: bipush 44 (0x2C)
		// @C2: invokevirtual java.lang.StringBuilder.append(char)java.lang.StringBuilder
		// @C5: iload_2
		// @C6: invokevirtual java.lang.StringBuilder.append(int)java.lang.StringBuilder
		// @C9: bipush 41 (0x29)
		// @CB: invokevirtual java.lang.StringBuilder.append(char)java.lang.StringBuilder
		// @CE: invokevirtual java.lang.StringBuilder.toString()java.lang.String
		// @D1: invokestatic game.C_100181_cf.func_105695_a(java.lang.Throwable, java.lang.String)game.C_100170_cm
		// @D4: athrow
	}
	
	static final boolean func_101192_n(int arg0)
	{
		// @00: iload_0
		// @01: sipush 5732 (0x1664)
		// @04: if_icmpeq @09
		// @07: iconst_0
		// @08: ireturn
		// @09: getstatic int game.C_100218_am.field_103115_N
		// @0C: istore_1
		// @0D: iload_1
		// @0E: bipush 10 (0x0A)
		// @10: if_icmpeq @26
		// @13: iconst_m1
		// @14: iload_1
		// @15: if_icmpne @3C
		// @18: goto @1C
		// @1B: athrow
		// @1C: getstatic int game.SteelSentinels.field_105275_O
		// @1F: ifeq @3A
		// @22: goto @26
		// @25: athrow
		// @26: getstatic int game.C_100194_rd.field_103072_v
		// @29: iconst_m1
		// @2A: ixor
		// @2B: iconst_m1
		// @2C: if_icmpne @38
		// @2F: goto @33
		// @32: athrow
		// @33: iconst_1
		// @34: goto @39
		// @37: athrow
		// @38: iconst_0
		// @39: ireturn
		// @3A: iconst_0
		// @3B: ireturn
		// @3C: iconst_1
		// @3D: ireturn
		// @3E: astore_1
		// @3F: aload_1
		// @40: new java.lang.StringBuilder
		// @43: dup
		// @44: invokespecial java.lang.StringBuilder.<init>()void
		// @47: getstatic java.lang.String[] game.C_100278_nd.field_101203_A
		// @4A: bipush 14 (0x0E)
		// @4C: aaload
		// @4D: invokevirtual java.lang.StringBuilder.append(java.lang.String)java.lang.StringBuilder
		// @50: iload_0
		// @51: invokevirtual java.lang.StringBuilder.append(int)java.lang.StringBuilder
		// @54: bipush 41 (0x29)
		// @56: invokevirtual java.lang.StringBuilder.append(char)java.lang.StringBuilder
		// @59: invokevirtual java.lang.StringBuilder.toString()java.lang.String
		// @5C: invokestatic game.C_100181_cf.func_105695_a(java.lang.Throwable, java.lang.String)game.C_100170_cm
		// @5F: athrow
	}
	
	public static void func_101188_m(int arg0)
	{
		// @00: aconst_null
		// @01: putstatic java.lang.String[] game.C_100278_nd.field_101204_z
		// @04: aconst_null
		// @05: putstatic java.lang.String game.C_100278_nd.field_101205_y
		// @08: aconst_null
		// @09: putstatic java.lang.String game.C_100278_nd.field_101202_u
		// @0C: iload_0
		// @0D: bipush 11 (0x0B)
		// @0F: if_icmpgt @1D
		// @12: aconst_null
		// @13: checkcast java.lang.String
		// @16: putstatic java.lang.String game.C_100278_nd.field_101205_y
		// @19: goto @1D
		// @1C: athrow
		// @1D: aconst_null
		// @1E: putstatic java.lang.String game.C_100278_nd.field_101206_x
		// @21: goto @46
		// @24: astore_1
		// @25: aload_1
		// @26: new java.lang.StringBuilder
		// @29: dup
		// @2A: invokespecial java.lang.StringBuilder.<init>()void
		// @2D: getstatic java.lang.String[] game.C_100278_nd.field_101203_A
		// @30: bipush 16 (0x10)
		// @32: aaload
		// @33: invokevirtual java.lang.StringBuilder.append(java.lang.String)java.lang.StringBuilder
		// @36: iload_0
		// @37: invokevirtual java.lang.StringBuilder.append(int)java.lang.StringBuilder
		// @3A: bipush 41 (0x29)
		// @3C: invokevirtual java.lang.StringBuilder.append(char)java.lang.StringBuilder
		// @3F: invokevirtual java.lang.StringBuilder.toString()java.lang.String
		// @42: invokestatic game.C_100181_cf.func_105695_a(java.lang.Throwable, java.lang.String)game.C_100170_cm
		// @45: athrow
		// @46: return
	}
	
	final void func_101198_a(int arg0, int arg1, int arg2, byte[] arg3)
	{
		// @00: getstatic int game.SteelSentinels.field_105275_O
		// @03: istore #6
		// @05: iload_2
		// @06: sipush 29119 (0x71BF)
		// @09: if_icmpeq @0D
		// @0C: return
		// @0D: iconst_0
		// @0E: istore #5
		// @10: iload_1
		// @11: iload #5
		// @13: if_icmple @4B
		// @16: aload #4
		// @18: iload_3
		// @19: iload #5
		// @1B: iadd
		// @1C: aload_0
		// @1D: getfield byte[] game.C_100278_nd.field_101179_l
		// @20: aload_0
		// @21: dup
		// @22: getfield int game.C_100278_nd.field_101177_n
		// @25: dup_x1
		// @26: iconst_1
		// @27: iadd
		// @28: putfield int game.C_100278_nd.field_101177_n
		// @2B: baload
		// @2C: aload_0
		// @2D: getfield game.C_100038_wa game.C_100278_nd.field_101200_w
		// @30: sipush 256 (0x0100)
		// @33: invokevirtual game.C_100038_wa.func_104061_a(int)int
		// @36: ineg
		// @37: iadd
		// @38: i2b
		// @39: bastore
		// @3A: iinc #5 +1
		// @3D: iload #6
		// @3F: ifne @9E
		// @42: iload #6
		// @44: ifeq @10
		// @47: goto @4B
		// @4A: athrow
		// @4B: goto @9E
		// @4E: astore #5
		// @50: aload #5
		// @52: new java.lang.StringBuilder
		// @55: dup
		// @56: invokespecial java.lang.StringBuilder.<init>()void
		// @59: getstatic java.lang.String[] game.C_100278_nd.field_101203_A
		// @5C: iconst_2
		// @5D: aaload
		// @5E: invokevirtual java.lang.StringBuilder.append(java.lang.String)java.lang.StringBuilder
		// @61: iload_1
		// @62: invokevirtual java.lang.StringBuilder.append(int)java.lang.StringBuilder
		// @65: bipush 44 (0x2C)
		// @67: invokevirtual java.lang.StringBuilder.append(char)java.lang.StringBuilder
		// @6A: iload_2
		// @6B: invokevirtual java.lang.StringBuilder.append(int)java.lang.StringBuilder
		// @6E: bipush 44 (0x2C)
		// @70: invokevirtual java.lang.StringBuilder.append(char)java.lang.StringBuilder
		// @73: iload_3
		// @74: invokevirtual java.lang.StringBuilder.append(int)java.lang.StringBuilder
		// @77: bipush 44 (0x2C)
		// @79: invokevirtual java.lang.StringBuilder.append(char)java.lang.StringBuilder
		// @7C: aload #4
		// @7E: ifnull @8A
		// @81: getstatic java.lang.String[] game.C_100278_nd.field_101203_A
		// @84: iconst_3
		// @85: aaload
		// @86: goto @8F
		// @89: athrow
		// @8A: getstatic java.lang.String[] game.C_100278_nd.field_101203_A
		// @8D: iconst_1
		// @8E: aaload
		// @8F: invokevirtual java.lang.StringBuilder.append(java.lang.String)java.lang.StringBuilder
		// @92: bipush 41 (0x29)
		// @94: invokevirtual java.lang.StringBuilder.append(char)java.lang.StringBuilder
		// @97: invokevirtual java.lang.StringBuilder.toString()java.lang.String
		// @9A: invokestatic game.C_100181_cf.func_105695_a(java.lang.Throwable, java.lang.String)game.C_100170_cm
		// @9D: athrow
		// @9E: return
	}
	
	static final void func_101199_j(int arg0, int arg1)
	{
		// @00: iload_0
		// @01: bipush 48 (0x30)
		// @03: iand
		// @04: ldc 1149797796 (0x448885a4)
		// @06: ishr
		// @07: putstatic int game.C_100053_vn.field_102830_fb
		// @0A: getstatic int game.C_100053_vn.field_102830_fb
		// @0D: iconst_2
		// @0E: if_icmpgt @15
		// @11: goto @19
		// @14: athrow
		// @15: iconst_2
		// @16: putstatic int game.C_100053_vn.field_102830_fb
		// @19: bipush 15 (0x0F)
		// @1B: iload_0
		// @1C: iand
		// @1D: ldc -1949004894 (0x8bd48ba2)
		// @1F: ishr
		// @20: putstatic int game.C_100220_ac.field_106065_i
		// @23: iload_0
		// @24: iconst_3
		// @25: iand
		// @26: putstatic int game.C_100162_sc.field_102860_Q
		// @29: getstatic int game.C_100220_ac.field_106065_i
		// @2C: iconst_2
		// @2D: if_icmple @38
		// @30: iconst_2
		// @31: putstatic int game.C_100220_ac.field_106065_i
		// @34: goto @38
		// @37: athrow
		// @38: bipush -3 (0xFD)
		// @3A: getstatic int game.C_100162_sc.field_102860_Q
		// @3D: iconst_m1
		// @3E: ixor
		// @3F: if_icmple @4A
		// @42: iconst_2
		// @43: putstatic int game.C_100162_sc.field_102860_Q
		// @46: goto @4A
		// @49: athrow
		// @4A: iload_1
		// @4B: bipush 49 (0x31)
		// @4D: if_icmpgt @68
		// @50: aconst_null
		// @51: checkcast java.lang.String
		// @54: bipush 31 (0x1F)
		// @56: aconst_null
		// @57: checkcast java.lang.String
		// @5A: bipush -105 (0x97)
		// @5C: aconst_null
		// @5D: checkcast java.net.URL
		// @60: invokestatic game.C_100278_nd.func_101193_a(java.lang.String, byte, java.lang.String, int, java.net.URL)java.net.URL
		// @63: pop
		// @64: goto @68
		// @67: athrow
		// @68: goto @96
		// @6B: astore_2
		// @6C: aload_2
		// @6D: new java.lang.StringBuilder
		// @70: dup
		// @71: invokespecial java.lang.StringBuilder.<init>()void
		// @74: getstatic java.lang.String[] game.C_100278_nd.field_101203_A
		// @77: bipush 7 (0x07)
		// @79: aaload
		// @7A: invokevirtual java.lang.StringBuilder.append(java.lang.String)java.lang.StringBuilder
		// @7D: iload_0
		// @7E: invokevirtual java.lang.StringBuilder.append(int)java.lang.StringBuilder
		// @81: bipush 44 (0x2C)
		// @83: invokevirtual java.lang.StringBuilder.append(char)java.lang.StringBuilder
		// @86: iload_1
		// @87: invokevirtual java.lang.StringBuilder.append(int)java.lang.StringBuilder
		// @8A: bipush 41 (0x29)
		// @8C: invokevirtual java.lang.StringBuilder.append(char)java.lang.StringBuilder
		// @8F: invokevirtual java.lang.StringBuilder.toString()java.lang.String
		// @92: invokestatic game.C_100181_cf.func_105695_a(java.lang.Throwable, java.lang.String)game.C_100170_cm
		// @95: athrow
		// @96: return
	}
	
	static
	{
		// @000: bipush 21 (0x15)
		// @002: anewarray java.lang.String
		// @005: dup
		// @006: iconst_0
		// @007: ldc "\u000fq\u0013TDI"
		// @009: invokestatic game.C_100278_nd.func_101186_z(java.lang.String)char[]
		// @00C: invokestatic game.C_100278_nd.func_101185_z(char[])java.lang.String
		// @00F: aastore
		// @010: dup
		// @011: iconst_1
		// @012: ldc "\u000f`Qz"
		// @014: invokestatic game.C_100278_nd.func_101186_z(java.lang.String)char[]
		// @017: invokestatic game.C_100278_nd.func_101185_z(char[])java.lang.String
		// @01A: aastore
		// @01B: dup
		// @01C: iconst_2
		// @01D: ldc "\u000fq\u0013\\DI"
		// @01F: invokestatic game.C_100278_nd.func_101186_z(java.lang.String)char[]
		// @022: invokestatic game.C_100278_nd.func_101185_z(char[])java.lang.String
		// @025: aastore
		// @026: dup
		// @027: iconst_3
		// @028: ldc "\u001a;\u00138{"
		// @02A: invokestatic game.C_100278_nd.func_101186_z(java.lang.String)char[]
		// @02D: invokestatic game.C_100278_nd.func_101185_z(char[])java.lang.String
		// @030: aastore
		// @031: dup
		// @032: iconst_4
		// @033: ldc "\u000fq\u0013YDI"
		// @035: invokestatic game.C_100278_nd.func_101186_z(java.lang.String)char[]
		// @038: invokestatic game.C_100278_nd.func_101185_z(char[])java.lang.String
		// @03B: aastore
		// @03C: dup
		// @03D: iconst_5
		// @03E: ldc "\u000fq\u0013UDI"
		// @040: invokestatic game.C_100278_nd.func_101186_z(java.lang.String)char[]
		// @043: invokestatic game.C_100278_nd.func_101185_z(char[])java.lang.String
		// @046: aastore
		// @047: dup
		// @048: bipush 6 (0x06)
		// @04A: ldc "\u000fq\u0013SDI"
		// @04C: invokestatic game.C_100278_nd.func_101186_z(java.lang.String)char[]
		// @04F: invokestatic game.C_100278_nd.func_101185_z(char[])java.lang.String
		// @052: aastore
		// @053: dup
		// @054: bipush 7 (0x07)
		// @056: ldc "\u000fq\u0013]DI"
		// @058: invokestatic game.C_100278_nd.func_101186_z(java.lang.String)char[]
		// @05B: invokestatic game.C_100278_nd.func_101185_z(char[])java.lang.String
		// @05E: aastore
		// @05F: dup
		// @060: bipush 8 (0x08)
		// @062: ldc "Nv\u0000"
		// @064: invokestatic game.C_100278_nd.func_101186_z(java.lang.String)char[]
		// @067: invokestatic game.C_100278_nd.func_101185_z(char[])java.lang.String
		// @06A: aastore
		// @06B: dup
		// @06C: bipush 9 (0x09)
		// @06E: ldc "Nf\u0000"
		// @070: invokestatic game.C_100278_nd.func_101186_z(java.lang.String)char[]
		// @073: invokestatic game.C_100278_nd.func_101185_z(char[])java.lang.String
		// @076: aastore
		// @077: dup
		// @078: bipush 10 (0x0A)
		// @07A: ldc "Ne\u0000"
		// @07C: invokestatic game.C_100278_nd.func_101186_z(java.lang.String)char[]
		// @07F: invokestatic game.C_100278_nd.func_101185_z(char[])java.lang.String
		// @082: aastore
		// @083: dup
		// @084: bipush 11 (0x0B)
		// @086: ldc "\u000fq\u0013PDI"
		// @088: invokestatic game.C_100278_nd.func_101186_z(java.lang.String)char[]
		// @08B: invokestatic game.C_100278_nd.func_101185_z(char[])java.lang.String
		// @08E: aastore
		// @08F: dup
		// @090: bipush 12 (0x0C)
		// @092: ldc "Ny\u0000"
		// @094: invokestatic game.C_100278_nd.func_101186_z(java.lang.String)char[]
		// @097: invokestatic game.C_100278_nd.func_101185_z(char[])java.lang.String
		// @09A: aastore
		// @09B: dup
		// @09C: bipush 13 (0x0D)
		// @09E: ldc "Nt\u0000"
		// @0A0: invokestatic game.C_100278_nd.func_101186_z(java.lang.String)char[]
		// @0A3: invokestatic game.C_100278_nd.func_101185_z(char[])java.lang.String
		// @0A6: aastore
		// @0A7: dup
		// @0A8: bipush 14 (0x0E)
		// @0AA: ldc "\u000fq\u0013QDI"
		// @0AC: invokestatic game.C_100278_nd.func_101186_z(java.lang.String)char[]
		// @0AF: invokestatic game.C_100278_nd.func_101185_z(char[])java.lang.String
		// @0B2: aastore
		// @0B3: dup
		// @0B4: bipush 15 (0x0F)
		// @0B6: ldc "\u000fq\u0013XDI"
		// @0B8: invokestatic game.C_100278_nd.func_101186_z(java.lang.String)char[]
		// @0BB: invokestatic game.C_100278_nd.func_101185_z(char[])java.lang.String
		// @0BE: aastore
		// @0BF: dup
		// @0C0: bipush 16 (0x10)
		// @0C2: ldc "\u000fq\u0013RDI"
		// @0C4: invokestatic game.C_100278_nd.func_101186_z(java.lang.String)char[]
		// @0C7: invokestatic game.C_100278_nd.func_101185_z(char[])java.lang.String
		// @0CA: aastore
		// @0CB: dup
		// @0CC: bipush 17 (0x11)
		// @0CE: ldc "\u000fq\u0013_DI"
		// @0D0: invokestatic game.C_100278_nd.func_101186_z(java.lang.String)char[]
		// @0D3: invokestatic game.C_100278_nd.func_101185_z(char[])java.lang.String
		// @0D6: aastore
		// @0D7: dup
		// @0D8: bipush 18 (0x12)
		// @0DA: ldc "\u000fq\u0013[DI"
		// @0DC: invokestatic game.C_100278_nd.func_101186_z(java.lang.String)char[]
		// @0DF: invokestatic game.C_100278_nd.func_101185_z(char[])java.lang.String
		// @0E2: aastore
		// @0E3: dup
		// @0E4: bipush 19 (0x13)
		// @0E6: ldc "\u000fq\u0013ZDI"
		// @0E8: invokestatic game.C_100278_nd.func_101186_z(java.lang.String)char[]
		// @0EB: invokestatic game.C_100278_nd.func_101185_z(char[])java.lang.String
		// @0EE: aastore
		// @0EF: dup
		// @0F0: bipush 20 (0x14)
		// @0F2: ldc "\u000fq\u0013^DI"
		// @0F4: invokestatic game.C_100278_nd.func_101186_z(java.lang.String)char[]
		// @0F7: invokestatic game.C_100278_nd.func_101185_z(char[])java.lang.String
		// @0FA: aastore
		// @0FB: putstatic java.lang.String[] game.C_100278_nd.field_101203_A
		// @0FE: ldc ",pPtc\u0013f\u001a6D\u0004{Xpo\u0015f"
		// @100: invokestatic game.C_100278_nd.func_101186_z(java.lang.String)char[]
		// @103: invokestatic game.C_100278_nd.func_101185_z(char[])java.lang.String
		// @106: putstatic java.lang.String game.C_100278_nd.field_101206_x
		// @109: ldc "'gR{&]0\r(<A"
		// @10B: invokestatic game.C_100278_nd.func_101186_z(java.lang.String)char[]
		// @10E: invokestatic game.C_100278_nd.func_101185_z(char[])java.lang.String
		// @111: putstatic java.lang.String game.C_100278_nd.field_101205_y
		// @114: bipush 64 (0x40)
		// @116: anewarray java.lang.String
		// @119: dup
		// @11A: iconst_0
		// @11B: ldc ",zNb&\n|Qzu]0\r("
		// @11D: invokestatic game.C_100278_nd.func_101186_z(java.lang.String)char[]
		// @120: invokestatic game.C_100278_nd.func_101185_z(char[])java.lang.String
		// @123: aastore
		// @124: dup
		// @125: iconst_1
		// @126: ldc "A=dysArRb&]0\r(/"
		// @128: invokestatic game.C_100278_nd.func_101186_z(java.lang.String)char[]
		// @12B: invokestatic game.C_100278_nd.func_101185_z(char[])java.lang.String
		// @12E: aastore
		// @12F: dup
		// @130: iconst_2
		// @131: ldc ",zNb&\u0005tPwa\u00045Ysg\ra\u000136_"
		// @133: invokestatic game.C_100278_nd.func_101186_z(java.lang.String)char[]
		// @136: invokestatic game.C_100278_nd.func_101185_z(char[])java.lang.String
		// @139: aastore
		// @13A: dup
		// @13B: iconst_3
		// @13C: ldc "A=dysAqXwj\u00155\u000136_<"
		// @13E: invokestatic game.C_100278_nd.func_101186_z(java.lang.String)char[]
		// @141: invokestatic game.C_100278_nd.func_101185_z(char[])java.lang.String
		// @144: aastore
		// @145: dup
		// @146: iconst_4
		// @147: ldc "-zSqc\u0012a\u001d}o\ryTxaAfIdc\u0000~\u000136_"
		// @149: invokestatic game.C_100278_nd.func_101186_z(java.lang.String)char[]
		// @14C: invokestatic game.C_100278_nd.func_101185_z(char[])java.lang.String
		// @14F: aastore
		// @150: dup
		// @151: iconst_5
		// @152: ldc "A=dys\u0013f\u00076:D%\u0003?"
		// @154: invokestatic game.C_100278_nd.func_101186_z(java.lang.String)char[]
		// @157: invokestatic game.C_100278_nd.func_101185_z(char[])java.lang.String
		// @15A: aastore
		// @15B: dup
		// @15C: bipush 6 (0x06)
		// @15E: ldc "'|OerA~Tzj"
		// @160: invokestatic game.C_100278_nd.func_101186_z(java.lang.String)char[]
		// @163: invokestatic game.C_100278_nd.func_101185_z(char[])java.lang.String
		// @166: aastore
		// @167: dup
		// @168: bipush 7 (0x07)
		// @16A: aconst_null
		// @16B: aastore
		// @16C: dup
		// @16D: bipush 8 (0x08)
		// @16F: ldc "'pJsu\u00155Ysg\u0015}N*#Q+"
		// @171: invokestatic game.C_100278_nd.func_101186_z(java.lang.String)char[]
		// @174: invokestatic game.C_100278_nd.func_101185_z(char[])java.lang.String
		// @177: aastore
		// @178: dup
		// @179: bipush 9 (0x09)
		// @17B: ldc "A=dysAqTsbA)\u0018&8H"
		// @17D: invokestatic game.C_100278_nd.func_101186_z(java.lang.String)char[]
		// @180: invokestatic game.C_100278_nd.func_101185_z(char[])java.lang.String
		// @183: aastore
		// @184: dup
		// @185: bipush 10 (0x0A)
		// @187: ldc "1pOpc\u0002a"
		// @189: invokestatic game.C_100278_nd.func_101186_z(java.lang.String)char[]
		// @18C: invokestatic game.C_100278_nd.func_101185_z(char[])java.lang.String
		// @18F: aastore
		// @190: dup
		// @191: bipush 11 (0x0B)
		// @193: ldc "A=dysAqTsbA)\u0018&8H"
		// @195: invokestatic game.C_100278_nd.func_101186_z(java.lang.String)char[]
		// @198: invokestatic game.C_100278_nd.func_101185_z(char[])java.lang.String
		// @19B: aastore
		// @19C: dup
		// @19D: bipush 12 (0x0C)
		// @19F: ldc "2zQs&\u0012`O`o\u0017zO"
		// @1A1: invokestatic game.C_100278_nd.func_101186_z(java.lang.String)char[]
		// @1A4: invokestatic game.C_100278_nd.func_101185_z(char[])java.lang.String
		// @1A7: aastore
		// @1A8: dup
		// @1A9: bipush 13 (0x0D)
		// @1AB: aconst_null
		// @1AC: aastore
		// @1AD: dup
		// @1AE: bipush 14 (0x0E)
		// @1B0: ldc "-zSqc\u0012a\u001dpj\u0008rUb:D%\u0003"
		// @1B2: invokestatic game.C_100278_nd.func_101186_z(java.lang.String)char[]
		// @1B5: invokestatic game.C_100278_nd.func_101185_z(char[])java.lang.String
		// @1B8: aastore
		// @1B9: dup
		// @1BA: bipush 15 (0x0F)
		// @1BC: ldc "A=dys\u0013f\u00076:D%\u0003?"
		// @1BE: invokestatic game.C_100278_nd.func_101186_z(java.lang.String)char[]
		// @1C1: invokestatic game.C_100278_nd.func_101185_z(char[])java.lang.String
		// @1C4: aastore
		// @1C5: dup
		// @1C6: bipush 16 (0x10)
		// @1C8: ldc ")|Z~c\u0012a\u001dee\u000egX"
		// @1CA: invokestatic game.C_100278_nd.func_101186_z(java.lang.String)char[]
		// @1CD: invokestatic game.C_100278_nd.func_101185_z(char[])java.lang.String
		// @1D0: aastore
		// @1D1: dup
		// @1D2: bipush 17 (0x11)
		// @1D4: aconst_null
		// @1D5: aastore
		// @1D6: dup
		// @1D7: bipush 18 (0x12)
		// @1D9: ldc ",zNb&\u0008{Ist\u0002pMbo\u000e{N*#Q+"
		// @1DB: invokestatic game.C_100278_nd.func_101186_z(java.lang.String)char[]
		// @1DE: invokestatic game.C_100278_nd.func_101185_z(char[])java.lang.String
		// @1E1: aastore
		// @1E2: dup
		// @1E3: bipush 19 (0x13)
		// @1E5: ldc "A=dysArRb&]0\r(/"
		// @1E7: invokestatic game.C_100278_nd.func_101186_z(java.lang.String)char[]
		// @1EA: invokestatic game.C_100278_nd.func_101185_z(char[])java.lang.String
		// @1ED: aastore
		// @1EE: dup
		// @1EF: bipush 20 (0x14)
		// @1F1: ldc "#pNb&\n|Qz&\u0002zPti]0\r("
		// @1F3: invokestatic game.C_100278_nd.func_101186_z(java.lang.String)char[]
		// @1F6: invokestatic game.C_100278_nd.func_101185_z(char[])java.lang.String
		// @1F9: aastore
		// @1FA: dup
		// @1FB: bipush 21 (0x15)
		// @1FD: ldc "A=dys\u0013f\u00076:D%\u0003?"
		// @1FF: invokestatic game.C_100278_nd.func_101186_z(java.lang.String)char[]
		// @202: invokestatic game.C_100278_nd.func_101185_z(char[])java.lang.String
		// @205: aastore
		// @206: dup
		// @207: bipush 22 (0x16)
		// @209: ldc ",zNb&\u000cpQscA~Tzj\u0012)\u0018&8"
		// @20B: invokestatic game.C_100278_nd.func_101186_z(java.lang.String)char[]
		// @20E: invokestatic game.C_100278_nd.func_101185_z(char[])java.lang.String
		// @211: aastore
		// @212: dup
		// @213: bipush 23 (0x17)
		// @215: ldc "A=dysArRb&]0\r(/"
		// @217: invokestatic game.C_100278_nd.func_101186_z(java.lang.String)char[]
		// @21A: invokestatic game.C_100278_nd.func_101185_z(char[])java.lang.String
		// @21D: aastore
		// @21E: dup
		// @21F: bipush 24 (0x18)
		// @221: ldc ",zNb&\u0006`S9`\rtV6m\u0008yQe:D%\u0003"
		// @223: invokestatic game.C_100278_nd.func_101186_z(java.lang.String)char[]
		// @226: invokestatic game.C_100278_nd.func_101185_z(char[])java.lang.String
		// @229: aastore
		// @22A: dup
		// @22B: bipush 25 (0x19)
		// @22D: ldc "A=dysArRb&]0\r(/"
		// @22F: invokestatic game.C_100278_nd.func_101186_z(java.lang.String)char[]
		// @232: invokestatic game.C_100278_nd.func_101185_z(char[])java.lang.String
		// @235: aastore
		// @236: dup
		// @237: bipush 26 (0x1A)
		// @239: ldc ",zNb&\u0002tSxi\u000f:Pyt\u0015tO6m\u0008yQe:D%\u0003"
		// @23B: invokestatic game.C_100278_nd.func_101186_z(java.lang.String)char[]
		// @23E: invokestatic game.C_100278_nd.func_101185_z(char[])java.lang.String
		// @241: aastore
		// @242: dup
		// @243: bipush 27 (0x1B)
		// @245: ldc "A=dysArRb&]0\r(/"
		// @247: invokestatic game.C_100278_nd.func_101186_z(java.lang.String)char[]
		// @24A: invokestatic game.C_100278_nd.func_101185_z(char[])java.lang.String
		// @24D: aastore
		// @24E: dup
		// @24F: bipush 28 (0x1C)
		// @251: ldc ",zNb&\u0013tTz&\u0006`S6m\u0008yQe:D%\u0003"
		// @253: invokestatic game.C_100278_nd.func_101186_z(java.lang.String)char[]
		// @256: invokestatic game.C_100278_nd.func_101185_z(char[])java.lang.String
		// @259: aastore
		// @25A: dup
		// @25B: bipush 29 (0x1D)
		// @25D: ldc "A=dysArRb&]0\r(/"
		// @25F: invokestatic game.C_100278_nd.func_101186_z(java.lang.String)char[]
		// @262: invokestatic game.C_100278_nd.func_101185_z(char[])java.lang.String
		// @265: aastore
		// @266: dup
		// @267: bipush 30 (0x1E)
		// @269: ldc ",zNb&\u0003p\\{&\n|Qzu]0\r("
		// @26B: invokestatic game.C_100278_nd.func_101186_z(java.lang.String)char[]
		// @26E: invokestatic game.C_100278_nd.func_101185_z(char[])java.lang.String
		// @271: aastore
		// @272: dup
		// @273: bipush 31 (0x1F)
		// @275: ldc "A=dysArRb&]0\r(/"
		// @277: invokestatic game.C_100278_nd.func_101186_z(java.lang.String)char[]
		// @27A: invokestatic game.C_100278_nd.func_101185_z(char[])java.lang.String
		// @27D: aastore
		// @27E: dup
		// @27F: bipush 32 (0x20)
		// @281: ldc ",zNb&\u0011y\\ek\u00005V\u007fj\rf\u000136_"
		// @283: invokestatic game.C_100278_nd.func_101186_z(java.lang.String)char[]
		// @286: invokestatic game.C_100278_nd.func_101185_z(char[])java.lang.String
		// @289: aastore
		// @28A: dup
		// @28B: bipush 33 (0x21)
		// @28D: ldc "A=dysArRb&]0\r(/"
		// @28F: invokestatic game.C_100278_nd.func_101186_z(java.lang.String)char[]
		// @292: invokestatic game.C_100278_nd.func_101185_z(char[])java.lang.String
		// @295: aastore
		// @296: dup
		// @297: bipush 34 (0x22)
		// @299: ldc ",zNb&\u0013z^}c\u0015:P\u007fu\u0012|Qs&\n|Qzu]0\r("
		// @29B: invokestatic game.C_100278_nd.func_101186_z(java.lang.String)char[]
		// @29E: invokestatic game.C_100278_nd.func_101185_z(char[])java.lang.String
		// @2A1: aastore
		// @2A2: dup
		// @2A3: bipush 35 (0x23)
		// @2A5: ldc "A=dysArRb&]0\r(/"
		// @2A7: invokestatic game.C_100278_nd.func_101186_z(java.lang.String)char[]
		// @2AA: invokestatic game.C_100278_nd.func_101185_z(char[])java.lang.String
		// @2AD: aastore
		// @2AE: dup
		// @2AF: bipush 36 (0x24)
		// @2B1: ldc ",zNb&\n|QzuAbTbnAtIyk\u0008vN*#Q+"
		// @2B3: invokestatic game.C_100278_nd.func_101186_z(java.lang.String)char[]
		// @2B6: invokestatic game.C_100278_nd.func_101185_z(char[])java.lang.String
		// @2B9: aastore
		// @2BA: dup
		// @2BB: bipush 37 (0x25)
		// @2BD: ldc "A=dysArRb&]0\r(/"
		// @2BF: invokestatic game.C_100278_nd.func_101186_z(java.lang.String)char[]
		// @2C2: invokestatic game.C_100278_nd.func_101185_z(char[])java.lang.String
		// @2C5: aastore
		// @2C6: dup
		// @2C7: bipush 38 (0x26)
		// @2C9: ldc ",zNb&\u0012}Tf&\u0004{Xda\u0008fXe:D%\u0003"
		// @2CB: invokestatic game.C_100278_nd.func_101186_z(java.lang.String)char[]
		// @2CE: invokestatic game.C_100278_nd.func_101185_z(char[])java.lang.String
		// @2D1: aastore
		// @2D2: dup
		// @2D3: bipush 39 (0x27)
		// @2D5: ldc "A=dysArRb&]0\r(/"
		// @2D7: invokestatic game.C_100278_nd.func_101186_z(java.lang.String)char[]
		// @2DA: invokestatic game.C_100278_nd.func_101185_z(char[])java.lang.String
		// @2DD: aastore
		// @2DE: dup
		// @2DF: bipush 40 (0x28)
		// @2E1: ldc "'|OerAaR6c\u000fpOqo\u0012p\u001den\u0008e"
		// @2E3: invokestatic game.C_100278_nd.func_101186_z(java.lang.String)char[]
		// @2E6: invokestatic game.C_100278_nd.func_101185_z(char[])java.lang.String
		// @2E9: aastore
		// @2EA: dup
		// @2EB: bipush 41 (0x29)
		// @2ED: aconst_null
		// @2EE: aastore
		// @2EF: dup
		// @2F0: bipush 42 (0x2A)
		// @2F2: ldc "*|Qzc\u00055Pyu\u00155Xxc\u0013rTec\u00055Xxc\u000c|Xe:D%\u0003"
		// @2F4: invokestatic game.C_100278_nd.func_101186_z(java.lang.String)char[]
		// @2F7: invokestatic game.C_100278_nd.func_101185_z(char[])java.lang.String
		// @2FA: aastore
		// @2FB: dup
		// @2FC: bipush 43 (0x2B)
		// @2FE: ldc "A=dysArRb&]0\r(/"
		// @300: invokestatic game.C_100278_nd.func_101186_z(java.lang.String)char[]
		// @303: invokestatic game.C_100278_nd.func_101185_z(char[])java.lang.String
		// @306: aastore
		// @307: dup
		// @308: bipush 44 (0x2C)
		// @30A: ldc "'|S\u007fu\tpY6q\u0008aU6K&Ss"
		// @30C: invokestatic game.C_100278_nd.func_101186_z(java.lang.String)char[]
		// @30F: invokestatic game.C_100278_nd.func_101185_z(char[])java.lang.String
		// @312: aastore
		// @313: dup
		// @314: bipush 45 (0x2D)
		// @316: aconst_null
		// @317: aastore
		// @318: dup
		// @319: bipush 46 (0x2E)
		// @31B: ldc ",zNb&\n|QzuAbU\u007fj\u00045Uyj\u0005|Sq&,R{X:D%\u0003"
		// @31D: invokestatic game.C_100278_nd.func_101186_z(java.lang.String)char[]
		// @320: invokestatic game.C_100278_nd.func_101185_z(char[])java.lang.String
		// @323: aastore
		// @324: dup
		// @325: bipush 47 (0x2F)
		// @327: ldc "A=dysArRb&]0\r(/"
		// @329: invokestatic game.C_100278_nd.func_101186_z(java.lang.String)char[]
		// @32C: invokestatic game.C_100278_nd.func_101185_z(char[])java.lang.String
		// @32F: aastore
		// @330: dup
		// @331: bipush 48 (0x30)
		// @333: ldc ",zNb&\u0015|Ps&\u0016|I~&,R{X:D%\u0003"
		// @335: invokestatic game.C_100278_nd.func_101186_z(java.lang.String)char[]
		// @338: invokestatic game.C_100278_nd.func_101185_z(char[])java.lang.String
		// @33B: aastore
		// @33C: dup
		// @33D: bipush 49 (0x31)
		// @33F: ldc "A=dys\u0013f\u00076:D%\u0003?"
		// @341: invokestatic game.C_100278_nd.func_101186_z(java.lang.String)char[]
		// @344: invokestatic game.C_100278_nd.func_101185_z(char[])java.lang.String
		// @347: aastore
		// @348: dup
		// @349: bipush 50 (0x32)
		// @34B: ldc ")|Z~c\u0012a\u001dee\u000egTxaAaXwk]0\r("
		// @34D: invokestatic game.C_100278_nd.func_101186_z(java.lang.String)char[]
		// @350: invokestatic game.C_100278_nd.func_101185_z(char[])java.lang.String
		// @353: aastore
		// @354: dup
		// @355: bipush 51 (0x33)
		// @357: ldc "A=dys\u00135Isg\u000c/\u001d*#Q+\u0014"
		// @359: invokestatic game.C_100278_nd.func_101186_z(java.lang.String)char[]
		// @35C: invokestatic game.C_100278_nd.func_101185_z(char[])java.lang.String
		// @35F: aastore
		// @360: dup
		// @361: bipush 52 (0x34)
		// @363: ldc "#zNe&\n|Qzc\u0013"
		// @365: invokestatic game.C_100278_nd.func_101186_z(java.lang.String)char[]
		// @368: invokestatic game.C_100278_nd.func_101185_z(char[])java.lang.String
		// @36B: aastore
		// @36C: dup
		// @36D: bipush 53 (0x35)
		// @36F: aconst_null
		// @370: aastore
		// @371: dup
		// @372: bipush 54 (0x36)
		// @374: ldc "#pNb&\u0012{Tfc\u00135\\ue\u0014g\\u\u007f]0\r("
		// @376: invokestatic game.C_100278_nd.func_101186_z(java.lang.String)char[]
		// @379: invokestatic game.C_100278_nd.func_101185_z(char[])java.lang.String
		// @37C: aastore
		// @37D: dup
		// @37E: bipush 55 (0x37)
		// @380: ldc "A=dys\u0013f\u00076:D%\u0003?"
		// @382: invokestatic game.C_100278_nd.func_101186_z(java.lang.String)char[]
		// @385: invokestatic game.C_100278_nd.func_101185_z(char[])java.lang.String
		// @388: aastore
		// @389: dup
		// @38A: bipush 56 (0x38)
		// @38C: ldc ",zNb&\u0011zJstL`Me:D%\u0003"
		// @38E: invokestatic game.C_100278_nd.func_101186_z(java.lang.String)char[]
		// @391: invokestatic game.C_100278_nd.func_101185_z(char[])java.lang.String
		// @394: aastore
		// @395: dup
		// @396: bipush 57 (0x39)
		// @398: ldc "A=dysArRb&]0\r(/"
		// @39A: invokestatic game.C_100278_nd.func_101186_z(java.lang.String)char[]
		// @39D: invokestatic game.C_100278_nd.func_101185_z(char[])java.lang.String
		// @3A0: aastore
		// @3A1: dup
		// @3A2: bipush 58 (0x3A)
		// @3A4: ldc ",zNb&\n|QzuAz[6K&Ss6u\u0004{I\u007fh\u0004yN*#Q+"
		// @3A6: invokestatic game.C_100278_nd.func_101186_z(java.lang.String)char[]
		// @3A9: invokestatic game.C_100278_nd.func_101185_z(char[])java.lang.String
		// @3AC: aastore
		// @3AD: dup
		// @3AE: bipush 59 (0x3B)
		// @3B0: ldc "A=dysArRb&]0\r(/"
		// @3B2: invokestatic game.C_100278_nd.func_101186_z(java.lang.String)char[]
		// @3B5: invokestatic game.C_100278_nd.func_101185_z(char[])java.lang.String
		// @3B8: aastore
		// @3B9: dup
		// @3BA: bipush 60 (0x3C)
		// @3BC: ldc ",zNb&\u0015|Ps&\u0008{\u001dbn\u00045Xxc\u0013rD6u\t|Xzb]0\r("
		// @3BE: invokestatic game.C_100278_nd.func_101186_z(java.lang.String)char[]
		// @3C1: invokestatic game.C_100278_nd.func_101185_z(char[])java.lang.String
		// @3C4: aastore
		// @3C5: dup
		// @3C6: bipush 61 (0x3D)
		// @3C8: ldc "A=dys\u0013f\u00076:D%\u0003?"
		// @3CA: invokestatic game.C_100278_nd.func_101186_z(java.lang.String)char[]
		// @3CD: invokestatic game.C_100278_nd.func_101185_z(char[])java.lang.String
		// @3D0: aastore
		// @3D1: dup
		// @3D2: bipush 62 (0x3E)
		// @3D4: ldc ",zNb&\u0003tI6m\u0008yQe:D%\u0003"
		// @3D6: invokestatic game.C_100278_nd.func_101186_z(java.lang.String)char[]
		// @3D9: invokestatic game.C_100278_nd.func_101185_z(char[])java.lang.String
		// @3DC: aastore
		// @3DD: dup
		// @3DE: bipush 63 (0x3F)
		// @3E0: ldc "A=dysArRb&]0\r(/"
		// @3E2: invokestatic game.C_100278_nd.func_101186_z(java.lang.String)char[]
		// @3E5: invokestatic game.C_100278_nd.func_101185_z(char[])java.lang.String
		// @3E8: aastore
		// @3E9: putstatic java.lang.String[] game.C_100278_nd.field_101204_z
		// @3EC: ldc "1yXwu\u00045QyaA|S6g\u00125\\6u\u0014wNut\u0008wTxaAxX{d\u0004g\u001dbiAt^uc\u0012f\u001dbn\u0008f\u001dpc\u0000aHdcO"
		// @3EE: invokestatic game.C_100278_nd.func_101186_z(java.lang.String)char[]
		// @3F1: invokestatic game.C_100278_nd.func_101185_z(char[])java.lang.String
		// @3F4: putstatic java.lang.String game.C_100278_nd.field_101202_u
		// @3F7: return
	}
	
	private static char[] func_101186_z(String arg0)
	{
		// @00: aload_0
		// @01: invokevirtual java.lang.String.toCharArray()char[]
		// @04: dup
		// @05: arraylength
		// @06: iconst_2
		// @07: if_icmpge @13
		// @0A: dup
		// @0B: iconst_0
		// @0C: dup2
		// @0D: caload
		// @0E: bipush 6 (0x06)
		// @10: ixor
		// @11: i2c
		// @12: castore
		// @13: areturn
	}
	
	private static String func_101185_z(char[] arg0)
	{
		// @00: aload_0
		// @01: dup
		// @02: arraylength
		// @03: swap
		// @04: iconst_0
		// @05: istore_1
		// @06: goto @4C
		// @09: dup
		// @0A: iload_1
		// @0B: dup2
		// @0C: caload
		// @0D: iload_1
		// @0E: iconst_5
		// @0F: irem
		// @10: tableswitch def: @44, for 0: @30, for 1: @35, for 2: @3A, for 3: @3F
		// @30: bipush 97 (0x61)
		// @32: goto @46
		// @35: bipush 21 (0x15)
		// @37: goto @46
		// @3A: bipush 61 (0x3D)
		// @3C: goto @46
		// @3F: bipush 22 (0x16)
		// @41: goto @46
		// @44: bipush 6 (0x06)
		// @46: ixor
		// @47: i2c
		// @48: castore
		// @49: iinc #1 +1
		// @4C: swap
		// @4D: dup_x1
		// @4E: iload_1
		// @4F: if_icmpgt @09
		// @52: new java.lang.String
		// @55: dup_x1
		// @56: swap
		// @57: invokespecial java.lang.String.<init>(char[])void
		// @5A: invokevirtual java.lang.String.intern()java.lang.String
		// @5D: areturn
	}
}
