package game;

import java.awt.Component;

final class C_100064_ve extends C_100340_je
{
	private String field_103019_r;
	static int[] field_103015_v;
	static int[] field_103014_w;
	static C_100098_h field_103021_y;
	static String field_103016_u;
	static C_100202_qi field_103022_x;
	static boolean field_103011_A;
	static C_100037_wb field_103013_C;
	static String field_103020_z;
	static C_100037_wb[] field_103017_t;
	private boolean field_103018_s;
	static String field_103012_B;
	private static final String[] field_103010_D;
	
	final String func_102975_a(byte arg0, String arg1)
	{
		// @00: bipush -14 (0xF2)
		// @02: aload_2
		// @03: invokestatic game.SteelSentinels.func_105260_a(byte, java.lang.CharSequence)java.lang.String
		// @06: astore_3
		// @07: aload_3
		// @08: ifnull @0D
		// @0B: aload_3
		// @0C: areturn
		// @0D: aload_2
		// @0E: aload_0
		// @0F: getfield java.lang.String game.C_100064_ve.field_103019_r
		// @12: invokevirtual java.lang.String.equals(java.lang.Object)boolean
		// @15: ifeq @1C
		// @18: goto @4A
		// @1B: athrow
		// @1C: sipush -9031 (0xDCB9)
		// @1F: aload_2
		// @20: invokestatic game.C_100021_wn.func_103866_a(int, java.lang.String)game.C_100096_un
		// @23: astore #4
		// @25: aload #4
		// @27: ifnull @3A
		// @2A: aload #4
		// @2C: getfield java.lang.String game.C_100096_un.field_104567_a
		// @2F: ifnonnull @3A
		// @32: goto @36
		// @35: athrow
		// @36: goto @3C
		// @39: athrow
		// @3A: aconst_null
		// @3B: areturn
		// @3C: aload_0
		// @3D: aload #4
		// @3F: getfield boolean game.C_100096_un.field_104565_b
		// @42: putfield boolean game.C_100064_ve.field_103018_s
		// @45: aload_0
		// @46: aload_2
		// @47: putfield java.lang.String game.C_100064_ve.field_103019_r
		// @4A: aload_0
		// @4B: getfield boolean game.C_100064_ve.field_103018_s
		// @4E: ifne @55
		// @51: getstatic java.lang.String game.C_100100_i.field_102023_bc
		// @54: areturn
		// @55: iload_1
		// @56: bipush 16 (0x10)
		// @58: if_icmpeq @67
		// @5B: bipush 71 (0x47)
		// @5D: bipush -38 (0xDA)
		// @5F: invokestatic game.C_100064_ve.func_103007_a(char, byte)boolean
		// @62: pop
		// @63: goto @67
		// @66: athrow
		// @67: getstatic java.lang.String game.C_100012_fh.field_100505_E
		// @6A: areturn
		// @6B: astore_3
		// @6C: aload_3
		// @6D: new java.lang.StringBuilder
		// @70: dup
		// @71: invokespecial java.lang.StringBuilder.<init>()void
		// @74: getstatic java.lang.String[] game.C_100064_ve.field_103010_D
		// @77: bipush 8 (0x08)
		// @79: aaload
		// @7A: invokevirtual java.lang.StringBuilder.append(java.lang.String)java.lang.StringBuilder
		// @7D: iload_1
		// @7E: invokevirtual java.lang.StringBuilder.append(int)java.lang.StringBuilder
		// @81: bipush 44 (0x2C)
		// @83: invokevirtual java.lang.StringBuilder.append(char)java.lang.StringBuilder
		// @86: aload_2
		// @87: ifnull @93
		// @8A: getstatic java.lang.String[] game.C_100064_ve.field_103010_D
		// @8D: iconst_4
		// @8E: aaload
		// @8F: goto @98
		// @92: athrow
		// @93: getstatic java.lang.String[] game.C_100064_ve.field_103010_D
		// @96: iconst_2
		// @97: aaload
		// @98: invokevirtual java.lang.StringBuilder.append(java.lang.String)java.lang.StringBuilder
		// @9B: bipush 41 (0x29)
		// @9D: invokevirtual java.lang.StringBuilder.append(char)java.lang.StringBuilder
		// @A0: invokevirtual java.lang.StringBuilder.toString()java.lang.String
		// @A3: invokestatic game.C_100181_cf.func_105695_a(java.lang.Throwable, java.lang.String)game.C_100170_cm
		// @A6: athrow
	}
	
	C_100064_ve(C_100309_lk arg0)
	{
		// @0: aload_0
		// @1: aload_1
		// @2: invokespecial game.C_100340_je.<init>(game.C_100309_lk)void
		// @5: aload_0
		// @6: iconst_0
		// @7: putfield boolean game.C_100064_ve.field_103018_s
		// @A: return
	}
	
	static final void func_103003_a(int arg0, boolean arg1, C_100201_qj arg2, C_100210_qa arg3, Component arg4, boolean arg5)
	{
		// @00: aload_2
		// @01: iload_0
		// @02: iload #5
		// @04: iload_0
		// @05: aload #4
		// @07: iload_1
		// @08: aload_3
		// @09: sipush 1024 (0x0400)
		// @0C: invokestatic game.C_100098_h.func_104586_a(game.C_100201_qj, int, boolean, int, java.awt.Component, boolean, game.C_100210_qa, int)void
		// @0F: goto @97
		// @12: astore #6
		// @14: aload #6
		// @16: new java.lang.StringBuilder
		// @19: dup
		// @1A: invokespecial java.lang.StringBuilder.<init>()void
		// @1D: getstatic java.lang.String[] game.C_100064_ve.field_103010_D
		// @20: iconst_3
		// @21: aaload
		// @22: invokevirtual java.lang.StringBuilder.append(java.lang.String)java.lang.StringBuilder
		// @25: iload_0
		// @26: invokevirtual java.lang.StringBuilder.append(int)java.lang.StringBuilder
		// @29: bipush 44 (0x2C)
		// @2B: invokevirtual java.lang.StringBuilder.append(char)java.lang.StringBuilder
		// @2E: iload_1
		// @2F: invokevirtual java.lang.StringBuilder.append(boolean)java.lang.StringBuilder
		// @32: bipush 44 (0x2C)
		// @34: invokevirtual java.lang.StringBuilder.append(char)java.lang.StringBuilder
		// @37: aload_2
		// @38: ifnull @44
		// @3B: getstatic java.lang.String[] game.C_100064_ve.field_103010_D
		// @3E: iconst_4
		// @3F: aaload
		// @40: goto @49
		// @43: athrow
		// @44: getstatic java.lang.String[] game.C_100064_ve.field_103010_D
		// @47: iconst_2
		// @48: aaload
		// @49: invokevirtual java.lang.StringBuilder.append(java.lang.String)java.lang.StringBuilder
		// @4C: bipush 44 (0x2C)
		// @4E: invokevirtual java.lang.StringBuilder.append(char)java.lang.StringBuilder
		// @51: aload_3
		// @52: ifnull @5E
		// @55: getstatic java.lang.String[] game.C_100064_ve.field_103010_D
		// @58: iconst_4
		// @59: aaload
		// @5A: goto @63
		// @5D: athrow
		// @5E: getstatic java.lang.String[] game.C_100064_ve.field_103010_D
		// @61: iconst_2
		// @62: aaload
		// @63: invokevirtual java.lang.StringBuilder.append(java.lang.String)java.lang.StringBuilder
		// @66: bipush 44 (0x2C)
		// @68: invokevirtual java.lang.StringBuilder.append(char)java.lang.StringBuilder
		// @6B: aload #4
		// @6D: ifnull @79
		// @70: getstatic java.lang.String[] game.C_100064_ve.field_103010_D
		// @73: iconst_4
		// @74: aaload
		// @75: goto @7E
		// @78: athrow
		// @79: getstatic java.lang.String[] game.C_100064_ve.field_103010_D
		// @7C: iconst_2
		// @7D: aaload
		// @7E: invokevirtual java.lang.StringBuilder.append(java.lang.String)java.lang.StringBuilder
		// @81: bipush 44 (0x2C)
		// @83: invokevirtual java.lang.StringBuilder.append(char)java.lang.StringBuilder
		// @86: iload #5
		// @88: invokevirtual java.lang.StringBuilder.append(boolean)java.lang.StringBuilder
		// @8B: bipush 41 (0x29)
		// @8D: invokevirtual java.lang.StringBuilder.append(char)java.lang.StringBuilder
		// @90: invokevirtual java.lang.StringBuilder.toString()java.lang.String
		// @93: invokestatic game.C_100181_cf.func_105695_a(java.lang.Throwable, java.lang.String)game.C_100170_cm
		// @96: athrow
		// @97: return
	}
	
	public static void func_103008_g(int arg0)
	{
		// @00: aconst_null
		// @01: putstatic java.lang.String game.C_100064_ve.field_103012_B
		// @04: aconst_null
		// @05: putstatic java.lang.String game.C_100064_ve.field_103016_u
		// @08: aconst_null
		// @09: putstatic int[] game.C_100064_ve.field_103014_w
		// @0C: aconst_null
		// @0D: putstatic game.C_100037_wb[] game.C_100064_ve.field_103017_t
		// @10: aconst_null
		// @11: putstatic game.C_100037_wb game.C_100064_ve.field_103013_C
		// @14: aconst_null
		// @15: putstatic game.C_100098_h game.C_100064_ve.field_103021_y
		// @18: aconst_null
		// @19: putstatic game.C_100202_qi game.C_100064_ve.field_103022_x
		// @1C: iload_0
		// @1D: sipush -22192 (0xA950)
		// @20: if_icmpeq @24
		// @23: return
		// @24: aconst_null
		// @25: putstatic int[] game.C_100064_ve.field_103015_v
		// @28: aconst_null
		// @29: putstatic java.lang.String game.C_100064_ve.field_103020_z
		// @2C: goto @50
		// @2F: astore_1
		// @30: aload_1
		// @31: new java.lang.StringBuilder
		// @34: dup
		// @35: invokespecial java.lang.StringBuilder.<init>()void
		// @38: getstatic java.lang.String[] game.C_100064_ve.field_103010_D
		// @3B: iconst_1
		// @3C: aaload
		// @3D: invokevirtual java.lang.StringBuilder.append(java.lang.String)java.lang.StringBuilder
		// @40: iload_0
		// @41: invokevirtual java.lang.StringBuilder.append(int)java.lang.StringBuilder
		// @44: bipush 41 (0x29)
		// @46: invokevirtual java.lang.StringBuilder.append(char)java.lang.StringBuilder
		// @49: invokevirtual java.lang.StringBuilder.toString()java.lang.String
		// @4C: invokestatic game.C_100181_cf.func_105695_a(java.lang.Throwable, java.lang.String)game.C_100170_cm
		// @4F: athrow
		// @50: return
	}
	
	static final int func_103009_a(int arg0, int arg1)
	{
		// @000: getstatic int game.SteelSentinels.field_105275_O
		// @003: istore_3
		// @004: iload_0
		// @005: bipush -21 (0xEB)
		// @007: if_icmple @015
		// @00A: aconst_null
		// @00B: checkcast java.lang.String
		// @00E: putstatic java.lang.String game.C_100064_ve.field_103016_u
		// @011: goto @015
		// @014: athrow
		// @015: iload_1
		// @016: istore_2
		// @017: iconst_0
		// @018: iload_2
		// @019: if_icmpne @024
		// @01C: iload_3
		// @01D: ifeq @106
		// @020: goto @024
		// @023: athrow
		// @024: iconst_1
		// @025: iload_2
		// @026: if_icmpne @035
		// @029: goto @02D
		// @02C: athrow
		// @02D: iload_3
		// @02E: ifeq @108
		// @031: goto @035
		// @034: athrow
		// @035: iconst_2
		// @036: iload_2
		// @037: if_icmpne @046
		// @03A: goto @03E
		// @03D: athrow
		// @03E: iload_3
		// @03F: ifeq @10A
		// @042: goto @046
		// @045: athrow
		// @046: iload_2
		// @047: iconst_3
		// @048: if_icmpeq @10C
		// @04B: goto @04F
		// @04E: athrow
		// @04F: iconst_4
		// @050: iload_2
		// @051: if_icmpne @060
		// @054: goto @058
		// @057: athrow
		// @058: iload_3
		// @059: ifeq @10E
		// @05C: goto @060
		// @05F: athrow
		// @060: bipush 20 (0x14)
		// @062: iload_2
		// @063: if_icmpne @072
		// @066: goto @06A
		// @069: athrow
		// @06A: iload_3
		// @06B: ifeq @110
		// @06E: goto @072
		// @071: athrow
		// @072: iload_2
		// @073: iconst_m1
		// @074: ixor
		// @075: bipush -6 (0xFA)
		// @077: if_icmpeq @113
		// @07A: goto @07E
		// @07D: athrow
		// @07E: bipush 6 (0x06)
		// @080: iload_2
		// @081: if_icmpne @090
		// @084: goto @088
		// @087: athrow
		// @088: iload_3
		// @089: ifeq @115
		// @08C: goto @090
		// @08F: athrow
		// @090: bipush 7 (0x07)
		// @092: iload_2
		// @093: if_icmpeq @117
		// @096: goto @09A
		// @099: athrow
		// @09A: bipush -9 (0xF7)
		// @09C: iload_2
		// @09D: iconst_m1
		// @09E: ixor
		// @09F: if_icmpne @0AE
		// @0A2: goto @0A6
		// @0A5: athrow
		// @0A6: iload_3
		// @0A7: ifeq @119
		// @0AA: goto @0AE
		// @0AD: athrow
		// @0AE: iload_2
		// @0AF: bipush 9 (0x09)
		// @0B1: if_icmpeq @11B
		// @0B4: goto @0B8
		// @0B7: athrow
		// @0B8: iload_2
		// @0B9: iconst_m1
		// @0BA: ixor
		// @0BB: bipush -11 (0xF5)
		// @0BD: if_icmpeq @11D
		// @0C0: goto @0C4
		// @0C3: athrow
		// @0C4: iload_2
		// @0C5: iconst_m1
		// @0C6: ixor
		// @0C7: bipush -12 (0xF4)
		// @0C9: if_icmpeq @11F
		// @0CC: goto @0D0
		// @0CF: athrow
		// @0D0: bipush -13 (0xF3)
		// @0D2: iload_2
		// @0D3: iconst_m1
		// @0D4: ixor
		// @0D5: if_icmpne @0E4
		// @0D8: goto @0DC
		// @0DB: athrow
		// @0DC: iload_3
		// @0DD: ifeq @121
		// @0E0: goto @0E4
		// @0E3: athrow
		// @0E4: iload_2
		// @0E5: iconst_m1
		// @0E6: ixor
		// @0E7: bipush -14 (0xF2)
		// @0E9: if_icmpne @0F8
		// @0EC: goto @0F0
		// @0EF: athrow
		// @0F0: iload_3
		// @0F1: ifeq @123
		// @0F4: goto @0F8
		// @0F7: athrow
		// @0F8: iload_2
		// @0F9: bipush 14 (0x0E)
		// @0FB: if_icmpeq @126
		// @0FE: goto @102
		// @101: athrow
		// @102: goto @129
		// @105: athrow
		// @106: iconst_1
		// @107: ireturn
		// @108: iconst_2
		// @109: ireturn
		// @10A: iconst_3
		// @10B: ireturn
		// @10C: iconst_4
		// @10D: ireturn
		// @10E: iconst_5
		// @10F: ireturn
		// @110: bipush 10 (0x0A)
		// @112: ireturn
		// @113: iconst_1
		// @114: ireturn
		// @115: iconst_2
		// @116: ireturn
		// @117: iconst_3
		// @118: ireturn
		// @119: iconst_4
		// @11A: ireturn
		// @11B: iconst_5
		// @11C: ireturn
		// @11D: iconst_1
		// @11E: ireturn
		// @11F: iconst_2
		// @120: ireturn
		// @121: iconst_5
		// @122: ireturn
		// @123: bipush 10 (0x0A)
		// @125: ireturn
		// @126: bipush 20 (0x14)
		// @128: ireturn
		// @129: iconst_0
		// @12A: ireturn
		// @12B: astore_2
		// @12C: aload_2
		// @12D: new java.lang.StringBuilder
		// @130: dup
		// @131: invokespecial java.lang.StringBuilder.<init>()void
		// @134: getstatic java.lang.String[] game.C_100064_ve.field_103010_D
		// @137: iconst_0
		// @138: aaload
		// @139: invokevirtual java.lang.StringBuilder.append(java.lang.String)java.lang.StringBuilder
		// @13C: iload_0
		// @13D: invokevirtual java.lang.StringBuilder.append(int)java.lang.StringBuilder
		// @140: bipush 44 (0x2C)
		// @142: invokevirtual java.lang.StringBuilder.append(char)java.lang.StringBuilder
		// @145: iload_1
		// @146: invokevirtual java.lang.StringBuilder.append(int)java.lang.StringBuilder
		// @149: bipush 41 (0x29)
		// @14B: invokevirtual java.lang.StringBuilder.append(char)java.lang.StringBuilder
		// @14E: invokevirtual java.lang.StringBuilder.toString()java.lang.String
		// @151: invokestatic game.C_100181_cf.func_105695_a(java.lang.Throwable, java.lang.String)game.C_100170_cm
		// @154: athrow
	}
	
	final void func_103006_c(boolean arg0)
	{
		// @00: iload_1
		// @01: ifeq @05
		// @04: return
		// @05: aload_0
		// @06: aconst_null
		// @07: putfield java.lang.String game.C_100064_ve.field_103019_r
		// @0A: goto @2F
		// @0D: astore_2
		// @0E: aload_2
		// @0F: new java.lang.StringBuilder
		// @12: dup
		// @13: invokespecial java.lang.StringBuilder.<init>()void
		// @16: getstatic java.lang.String[] game.C_100064_ve.field_103010_D
		// @19: bipush 7 (0x07)
		// @1B: aaload
		// @1C: invokevirtual java.lang.StringBuilder.append(java.lang.String)java.lang.StringBuilder
		// @1F: iload_1
		// @20: invokevirtual java.lang.StringBuilder.append(boolean)java.lang.StringBuilder
		// @23: bipush 41 (0x29)
		// @25: invokevirtual java.lang.StringBuilder.append(char)java.lang.StringBuilder
		// @28: invokevirtual java.lang.StringBuilder.toString()java.lang.String
		// @2B: invokestatic game.C_100181_cf.func_105695_a(java.lang.Throwable, java.lang.String)game.C_100170_cm
		// @2E: athrow
		// @2F: return
	}
	
	final C_100133_tk func_102974_b(String arg0, int arg1)
	{
		// @00: aload_1
		// @01: iload_2
		// @02: bipush 38 (0x26)
		// @04: ixor
		// @05: invokestatic game.C_100174_sb.func_105602_a(java.lang.CharSequence, int)boolean
		// @08: ifne @0F
		// @0B: getstatic game.C_100133_tk game.C_100256_pk.field_100466_a
		// @0E: areturn
		// @0F: aload_1
		// @10: aload_0
		// @11: getfield java.lang.String game.C_100064_ve.field_103019_r
		// @14: invokevirtual java.lang.String.equals(java.lang.Object)boolean
		// @17: ifeq @1E
		// @1A: goto @49
		// @1D: athrow
		// @1E: iload_2
		// @1F: sipush -9031 (0xDCB9)
		// @22: iadd
		// @23: aload_1
		// @24: invokestatic game.C_100021_wn.func_103866_a(int, java.lang.String)game.C_100096_un
		// @27: astore_3
		// @28: aload_3
		// @29: ifnull @38
		// @2C: aconst_null
		// @2D: aload_3
		// @2E: getfield java.lang.String game.C_100096_un.field_104567_a
		// @31: if_acmpeq @3C
		// @34: goto @38
		// @37: athrow
		// @38: getstatic game.C_100133_tk game.C_100238_ol.field_101696_R
		// @3B: areturn
		// @3C: aload_0
		// @3D: aload_3
		// @3E: getfield boolean game.C_100096_un.field_104565_b
		// @41: putfield boolean game.C_100064_ve.field_103018_s
		// @44: aload_0
		// @45: aload_1
		// @46: putfield java.lang.String game.C_100064_ve.field_103019_r
		// @49: iload_2
		// @4A: ifeq @5C
		// @4D: aload_0
		// @4E: aconst_null
		// @4F: checkcast java.lang.String
		// @52: bipush -65 (0xBF)
		// @54: invokevirtual game.C_100064_ve.func_102974_b(java.lang.String, int)game.C_100133_tk
		// @57: pop
		// @58: goto @5C
		// @5B: athrow
		// @5C: aload_0
		// @5D: getfield boolean game.C_100064_ve.field_103018_s
		// @60: ifne @6A
		// @63: getstatic game.C_100133_tk game.C_100256_pk.field_100466_a
		// @66: goto @6D
		// @69: athrow
		// @6A: getstatic game.C_100133_tk game.C_100079_e.field_102670_tb
		// @6D: areturn
		// @6E: astore_3
		// @6F: aload_3
		// @70: new java.lang.StringBuilder
		// @73: dup
		// @74: invokespecial java.lang.StringBuilder.<init>()void
		// @77: getstatic java.lang.String[] game.C_100064_ve.field_103010_D
		// @7A: iconst_5
		// @7B: aaload
		// @7C: invokevirtual java.lang.StringBuilder.append(java.lang.String)java.lang.StringBuilder
		// @7F: aload_1
		// @80: ifnull @8C
		// @83: getstatic java.lang.String[] game.C_100064_ve.field_103010_D
		// @86: iconst_4
		// @87: aaload
		// @88: goto @91
		// @8B: athrow
		// @8C: getstatic java.lang.String[] game.C_100064_ve.field_103010_D
		// @8F: iconst_2
		// @90: aaload
		// @91: invokevirtual java.lang.StringBuilder.append(java.lang.String)java.lang.StringBuilder
		// @94: bipush 44 (0x2C)
		// @96: invokevirtual java.lang.StringBuilder.append(char)java.lang.StringBuilder
		// @99: iload_2
		// @9A: invokevirtual java.lang.StringBuilder.append(int)java.lang.StringBuilder
		// @9D: bipush 41 (0x29)
		// @9F: invokevirtual java.lang.StringBuilder.append(char)java.lang.StringBuilder
		// @A2: invokevirtual java.lang.StringBuilder.toString()java.lang.String
		// @A5: invokestatic game.C_100181_cf.func_105695_a(java.lang.Throwable, java.lang.String)game.C_100170_cm
		// @A8: athrow
	}
	
	static final boolean func_103007_a(char arg0, byte arg1)
	{
		// @00: iload_1
		// @01: bipush -100 (0x9C)
		// @03: if_icmpeq @08
		// @06: iconst_0
		// @07: ireturn
		// @08: bipush 48 (0x30)
		// @0A: iload_0
		// @0B: if_icmpgt @1F
		// @0E: iload_0
		// @0F: iconst_m1
		// @10: ixor
		// @11: bipush -58 (0xC6)
		// @13: if_icmplt @1F
		// @16: goto @1A
		// @19: athrow
		// @1A: iconst_1
		// @1B: goto @20
		// @1E: athrow
		// @1F: iconst_0
		// @20: ireturn
		// @21: astore_2
		// @22: aload_2
		// @23: new java.lang.StringBuilder
		// @26: dup
		// @27: invokespecial java.lang.StringBuilder.<init>()void
		// @2A: getstatic java.lang.String[] game.C_100064_ve.field_103010_D
		// @2D: bipush 6 (0x06)
		// @2F: aaload
		// @30: invokevirtual java.lang.StringBuilder.append(java.lang.String)java.lang.StringBuilder
		// @33: iload_0
		// @34: invokevirtual java.lang.StringBuilder.append(char)java.lang.StringBuilder
		// @37: bipush 44 (0x2C)
		// @39: invokevirtual java.lang.StringBuilder.append(char)java.lang.StringBuilder
		// @3C: iload_1
		// @3D: invokevirtual java.lang.StringBuilder.append(int)java.lang.StringBuilder
		// @40: bipush 41 (0x29)
		// @42: invokevirtual java.lang.StringBuilder.append(char)java.lang.StringBuilder
		// @45: invokevirtual java.lang.StringBuilder.toString()java.lang.String
		// @48: invokestatic game.C_100181_cf.func_105695_a(java.lang.Throwable, java.lang.String)game.C_100170_cm
		// @4B: athrow
	}
	
	static
	{
		// @000: bipush 9 (0x09)
		// @002: anewarray java.lang.String
		// @005: dup
		// @006: iconst_0
		// @007: ldc "Q\u0016={a"
		// @009: invokestatic game.C_100064_ve.func_103005_z(java.lang.String)char[]
		// @00C: invokestatic game.C_100064_ve.func_103004_z(char[])java.lang.String
		// @00F: aastore
		// @010: dup
		// @011: iconst_1
		// @012: ldc "Q\u0016=\u007fa"
		// @014: invokestatic game.C_100064_ve.func_103005_z(java.lang.String)char[]
		// @017: invokestatic game.C_100064_ve.func_103004_z(char[])java.lang.String
		// @01A: aastore
		// @01B: dup
		// @01C: iconst_2
		// @01D: ldc "I\u0006\u007fR"
		// @01F: invokestatic game.C_100064_ve.func_103005_z(java.lang.String)char[]
		// @022: invokestatic game.C_100064_ve.func_103004_z(char[])java.lang.String
		// @025: aastore
		// @026: dup
		// @027: iconst_3
		// @028: ldc "Q\u0016=za"
		// @02A: invokestatic game.C_100064_ve.func_103005_z(java.lang.String)char[]
		// @02D: invokestatic game.C_100064_ve.func_103004_z(char[])java.lang.String
		// @030: aastore
		// @031: dup
		// @032: iconst_4
		// @033: ldc "\\]=\u00104"
		// @035: invokestatic game.C_100064_ve.func_103005_z(java.lang.String)char[]
		// @038: invokestatic game.C_100064_ve.func_103004_z(char[])java.lang.String
		// @03B: aastore
		// @03C: dup
		// @03D: iconst_5
		// @03E: ldc "Q\u0016=xa"
		// @040: invokestatic game.C_100064_ve.func_103005_z(java.lang.String)char[]
		// @043: invokestatic game.C_100064_ve.func_103004_z(char[])java.lang.String
		// @046: aastore
		// @047: dup
		// @048: bipush 6 (0x06)
		// @04A: ldc "Q\u0016=}a"
		// @04C: invokestatic game.C_100064_ve.func_103005_z(java.lang.String)char[]
		// @04F: invokestatic game.C_100064_ve.func_103004_z(char[])java.lang.String
		// @052: aastore
		// @053: dup
		// @054: bipush 7 (0x07)
		// @056: ldc "Q\u0016=ya"
		// @058: invokestatic game.C_100064_ve.func_103005_z(java.lang.String)char[]
		// @05B: invokestatic game.C_100064_ve.func_103004_z(char[])java.lang.String
		// @05E: aastore
		// @05F: dup
		// @060: bipush 8 (0x08)
		// @062: ldc "Q\u0016=|a"
		// @064: invokestatic game.C_100064_ve.func_103005_z(java.lang.String)char[]
		// @067: invokestatic game.C_100064_ve.func_103004_z(char[])java.lang.String
		// @06A: aastore
		// @06B: putstatic java.lang.String[] game.C_100064_ve.field_103010_D
		// @06E: ldc "D"
		// @070: putstatic java.lang.String game.C_100064_ve.field_103016_u
		// @073: iconst_0
		// @074: putstatic boolean game.C_100064_ve.field_103011_A
		// @077: ldc "i\u001c3M9B\u0010g_=H\u0001`"
		// @079: invokestatic game.C_100064_ve.func_103005_z(java.lang.String)char[]
		// @07C: invokestatic game.C_100064_ve.func_103004_z(char[])java.lang.String
		// @07F: putstatic java.lang.String game.C_100064_ve.field_103020_z
		// @082: bipush 110 (0x6E)
		// @084: newarray int[]
		// @086: putstatic int[] game.C_100064_ve.field_103015_v
		// @089: getstatic int[] game.C_100064_ve.field_103015_v
		// @08C: bipush 60 (0x3C)
		// @08E: sipush 400 (0x0190)
		// @091: iastore
		// @092: getstatic int[] game.C_100064_ve.field_103015_v
		// @095: bipush 27 (0x1B)
		// @097: bipush 75 (0x4B)
		// @099: iastore
		// @09A: getstatic int[] game.C_100064_ve.field_103015_v
		// @09D: bipush 56 (0x38)
		// @09F: sipush 400 (0x0190)
		// @0A2: iastore
		// @0A3: getstatic int[] game.C_100064_ve.field_103015_v
		// @0A6: bipush 84 (0x54)
		// @0A8: sipush 2000 (0x07D0)
		// @0AB: iastore
		// @0AC: getstatic int[] game.C_100064_ve.field_103015_v
		// @0AF: bipush 71 (0x47)
		// @0B1: sipush 500 (0x01F4)
		// @0B4: iastore
		// @0B5: getstatic int[] game.C_100064_ve.field_103015_v
		// @0B8: bipush 44 (0x2C)
		// @0BA: sipush 750 (0x02EE)
		// @0BD: iastore
		// @0BE: getstatic int[] game.C_100064_ve.field_103015_v
		// @0C1: bipush 78 (0x4E)
		// @0C3: sipush 500 (0x01F4)
		// @0C6: iastore
		// @0C7: getstatic int[] game.C_100064_ve.field_103015_v
		// @0CA: bipush 19 (0x13)
		// @0CC: bipush 75 (0x4B)
		// @0CE: iastore
		// @0CF: getstatic int[] game.C_100064_ve.field_103015_v
		// @0D2: bipush 92 (0x5C)
		// @0D4: sipush 5000 (0x1388)
		// @0D7: iastore
		// @0D8: getstatic int[] game.C_100064_ve.field_103015_v
		// @0DB: bipush 61 (0x3D)
		// @0DD: sipush 200 (0x00C8)
		// @0E0: iastore
		// @0E1: getstatic int[] game.C_100064_ve.field_103015_v
		// @0E4: bipush 76 (0x4C)
		// @0E6: sipush 600 (0x0258)
		// @0E9: iastore
		// @0EA: getstatic int[] game.C_100064_ve.field_103015_v
		// @0ED: bipush 86 (0x56)
		// @0EF: sipush 800 (0x0320)
		// @0F2: iastore
		// @0F3: getstatic int[] game.C_100064_ve.field_103015_v
		// @0F6: bipush 31 (0x1F)
		// @0F8: sipush 150 (0x0096)
		// @0FB: iastore
		// @0FC: getstatic int[] game.C_100064_ve.field_103015_v
		// @0FF: bipush 58 (0x3A)
		// @101: sipush 250 (0x00FA)
		// @104: iastore
		// @105: getstatic int[] game.C_100064_ve.field_103015_v
		// @108: bipush 82 (0x52)
		// @10A: sipush 600 (0x0258)
		// @10D: iastore
		// @10E: getstatic int[] game.C_100064_ve.field_103015_v
		// @111: bipush 32 (0x20)
		// @113: bipush 100 (0x64)
		// @115: iastore
		// @116: getstatic int[] game.C_100064_ve.field_103015_v
		// @119: bipush 63 (0x3F)
		// @11B: sipush 200 (0x00C8)
		// @11E: iastore
		// @11F: getstatic int[] game.C_100064_ve.field_103015_v
		// @122: bipush 79 (0x4F)
		// @124: sipush 2000 (0x07D0)
		// @127: iastore
		// @128: getstatic int[] game.C_100064_ve.field_103015_v
		// @12B: bipush 68 (0x44)
		// @12D: sipush 500 (0x01F4)
		// @130: iastore
		// @131: getstatic int[] game.C_100064_ve.field_103015_v
		// @134: bipush 85 (0x55)
		// @136: sipush 800 (0x0320)
		// @139: iastore
		// @13A: getstatic int[] game.C_100064_ve.field_103015_v
		// @13D: bipush 88 (0x58)
		// @13F: sipush 3000 (0x0BB8)
		// @142: iastore
		// @143: getstatic int[] game.C_100064_ve.field_103015_v
		// @146: bipush 57 (0x39)
		// @148: sipush 400 (0x0190)
		// @14B: iastore
		// @14C: getstatic int[] game.C_100064_ve.field_103015_v
		// @14F: bipush 50 (0x32)
		// @151: sipush 1000 (0x03E8)
		// @154: iastore
		// @155: getstatic int[] game.C_100064_ve.field_103015_v
		// @158: bipush 74 (0x4A)
		// @15A: sipush 500 (0x01F4)
		// @15D: iastore
		// @15E: getstatic int[] game.C_100064_ve.field_103015_v
		// @161: bipush 43 (0x2B)
		// @163: sipush 500 (0x01F4)
		// @166: iastore
		// @167: getstatic int[] game.C_100064_ve.field_103015_v
		// @16A: bipush 87 (0x57)
		// @16C: sipush 1000 (0x03E8)
		// @16F: iastore
		// @170: getstatic int[] game.C_100064_ve.field_103015_v
		// @173: bipush 70 (0x46)
		// @175: sipush 500 (0x01F4)
		// @178: iastore
		// @179: getstatic int[] game.C_100064_ve.field_103015_v
		// @17C: bipush 35 (0x23)
		// @17E: sipush 250 (0x00FA)
		// @181: iastore
		// @182: getstatic int[] game.C_100064_ve.field_103015_v
		// @185: bipush 69 (0x45)
		// @187: sipush 1000 (0x03E8)
		// @18A: iastore
		// @18B: getstatic int[] game.C_100064_ve.field_103015_v
		// @18E: bipush 51 (0x33)
		// @190: sipush 200 (0x00C8)
		// @193: iastore
		// @194: getstatic int[] game.C_100064_ve.field_103015_v
		// @197: bipush 66 (0x42)
		// @199: sipush 500 (0x01F4)
		// @19C: iastore
		// @19D: getstatic int[] game.C_100064_ve.field_103015_v
		// @1A0: bipush 83 (0x53)
		// @1A2: sipush 600 (0x0258)
		// @1A5: iastore
		// @1A6: getstatic int[] game.C_100064_ve.field_103015_v
		// @1A9: bipush 30 (0x1E)
		// @1AB: bipush 100 (0x64)
		// @1AD: iastore
		// @1AE: getstatic int[] game.C_100064_ve.field_103015_v
		// @1B1: bipush 80 (0x50)
		// @1B3: sipush 800 (0x0320)
		// @1B6: iastore
		// @1B7: getstatic int[] game.C_100064_ve.field_103015_v
		// @1BA: bipush 20 (0x14)
		// @1BC: bipush 75 (0x4B)
		// @1BE: iastore
		// @1BF: getstatic int[] game.C_100064_ve.field_103015_v
		// @1C2: bipush 24 (0x18)
		// @1C4: bipush 25 (0x19)
		// @1C6: iastore
		// @1C7: getstatic int[] game.C_100064_ve.field_103015_v
		// @1CA: bipush 22 (0x16)
		// @1CC: bipush 100 (0x64)
		// @1CE: iastore
		// @1CF: getstatic int[] game.C_100064_ve.field_103015_v
		// @1D2: bipush 17 (0x11)
		// @1D4: bipush 25 (0x19)
		// @1D6: iastore
		// @1D7: getstatic int[] game.C_100064_ve.field_103015_v
		// @1DA: bipush 52 (0x34)
		// @1DC: sipush 1337 (0x0539)
		// @1DF: iastore
		// @1E0: getstatic int[] game.C_100064_ve.field_103015_v
		// @1E3: bipush 67 (0x43)
		// @1E5: sipush 400 (0x0190)
		// @1E8: iastore
		// @1E9: getstatic int[] game.C_100064_ve.field_103015_v
		// @1EC: bipush 34 (0x22)
		// @1EE: sipush 200 (0x00C8)
		// @1F1: iastore
		// @1F2: getstatic int[] game.C_100064_ve.field_103015_v
		// @1F5: bipush 49 (0x31)
		// @1F7: sipush 1000 (0x03E8)
		// @1FA: iastore
		// @1FB: getstatic int[] game.C_100064_ve.field_103015_v
		// @1FE: bipush 48 (0x30)
		// @200: sipush 1000 (0x03E8)
		// @203: iastore
		// @204: getstatic int[] game.C_100064_ve.field_103015_v
		// @207: bipush 95 (0x5F)
		// @209: sipush 1000 (0x03E8)
		// @20C: iastore
		// @20D: getstatic int[] game.C_100064_ve.field_103015_v
		// @210: bipush 55 (0x37)
		// @212: sipush 750 (0x02EE)
		// @215: iastore
		// @216: getstatic int[] game.C_100064_ve.field_103015_v
		// @219: bipush 93 (0x5D)
		// @21B: sipush 2000 (0x07D0)
		// @21E: iastore
		// @21F: getstatic int[] game.C_100064_ve.field_103015_v
		// @222: bipush 33 (0x21)
		// @224: sipush 200 (0x00C8)
		// @227: iastore
		// @228: getstatic int[] game.C_100064_ve.field_103015_v
		// @22B: bipush 18 (0x12)
		// @22D: bipush 25 (0x19)
		// @22F: iastore
		// @230: getstatic int[] game.C_100064_ve.field_103015_v
		// @233: bipush 62 (0x3E)
		// @235: sipush 750 (0x02EE)
		// @238: iastore
		// @239: getstatic int[] game.C_100064_ve.field_103015_v
		// @23C: bipush 75 (0x4B)
		// @23E: sipush 2000 (0x07D0)
		// @241: iastore
		// @242: getstatic int[] game.C_100064_ve.field_103015_v
		// @245: bipush 53 (0x35)
		// @247: sipush 300 (0x012C)
		// @24A: iastore
		// @24B: getstatic int[] game.C_100064_ve.field_103015_v
		// @24E: bipush 21 (0x15)
		// @250: bipush 75 (0x4B)
		// @252: iastore
		// @253: getstatic int[] game.C_100064_ve.field_103015_v
		// @256: bipush 89 (0x59)
		// @258: sipush 1000 (0x03E8)
		// @25B: iastore
		// @25C: getstatic int[] game.C_100064_ve.field_103015_v
		// @25F: bipush 54 (0x36)
		// @261: sipush 400 (0x0190)
		// @264: iastore
		// @265: getstatic int[] game.C_100064_ve.field_103015_v
		// @268: bipush 46 (0x2E)
		// @26A: sipush 750 (0x02EE)
		// @26D: iastore
		// @26E: getstatic int[] game.C_100064_ve.field_103015_v
		// @271: bipush 28 (0x1C)
		// @273: bipush 75 (0x4B)
		// @275: iastore
		// @276: getstatic int[] game.C_100064_ve.field_103015_v
		// @279: bipush 77 (0x4D)
		// @27B: sipush 600 (0x0258)
		// @27E: iastore
		// @27F: getstatic int[] game.C_100064_ve.field_103015_v
		// @282: bipush 81 (0x51)
		// @284: sipush 800 (0x0320)
		// @287: iastore
		// @288: getstatic int[] game.C_100064_ve.field_103015_v
		// @28B: bipush 59 (0x3B)
		// @28D: sipush 200 (0x00C8)
		// @290: iastore
		// @291: getstatic int[] game.C_100064_ve.field_103015_v
		// @294: bipush 25 (0x19)
		// @296: bipush 25 (0x19)
		// @298: iastore
		// @299: getstatic int[] game.C_100064_ve.field_103015_v
		// @29C: bipush 36 (0x24)
		// @29E: sipush 200 (0x00C8)
		// @2A1: iastore
		// @2A2: getstatic int[] game.C_100064_ve.field_103015_v
		// @2A5: bipush 23 (0x17)
		// @2A7: bipush 25 (0x19)
		// @2A9: iastore
		// @2AA: getstatic int[] game.C_100064_ve.field_103015_v
		// @2AD: bipush 91 (0x5B)
		// @2AF: sipush 800 (0x0320)
		// @2B2: iastore
		// @2B3: getstatic int[] game.C_100064_ve.field_103015_v
		// @2B6: iconst_0
		// @2B7: sipush 500 (0x01F4)
		// @2BA: iastore
		// @2BB: getstatic int[] game.C_100064_ve.field_103015_v
		// @2BE: bipush 29 (0x1D)
		// @2C0: bipush 100 (0x64)
		// @2C2: iastore
		// @2C3: getstatic int[] game.C_100064_ve.field_103015_v
		// @2C6: bipush 47 (0x2F)
		// @2C8: sipush 750 (0x02EE)
		// @2CB: iastore
		// @2CC: getstatic int[] game.C_100064_ve.field_103015_v
		// @2CF: bipush 73 (0x49)
		// @2D1: sipush 600 (0x0258)
		// @2D4: iastore
		// @2D5: getstatic int[] game.C_100064_ve.field_103015_v
		// @2D8: iconst_3
		// @2D9: sipush 300 (0x012C)
		// @2DC: iastore
		// @2DD: getstatic int[] game.C_100064_ve.field_103015_v
		// @2E0: bipush 38 (0x26)
		// @2E2: sipush 200 (0x00C8)
		// @2E5: iastore
		// @2E6: getstatic int[] game.C_100064_ve.field_103015_v
		// @2E9: bipush 26 (0x1A)
		// @2EB: bipush 25 (0x19)
		// @2ED: iastore
		// @2EE: getstatic int[] game.C_100064_ve.field_103015_v
		// @2F1: iconst_2
		// @2F2: sipush 400 (0x0190)
		// @2F5: iastore
		// @2F6: getstatic int[] game.C_100064_ve.field_103015_v
		// @2F9: iconst_1
		// @2FA: sipush 200 (0x00C8)
		// @2FD: iastore
		// @2FE: getstatic int[] game.C_100064_ve.field_103015_v
		// @301: bipush 90 (0x5A)
		// @303: sipush 1000 (0x03E8)
		// @306: iastore
		// @307: getstatic int[] game.C_100064_ve.field_103015_v
		// @30A: bipush 45 (0x2D)
		// @30C: sipush 750 (0x02EE)
		// @30F: iastore
		// @310: getstatic int[] game.C_100064_ve.field_103015_v
		// @313: bipush 72 (0x48)
		// @315: sipush 1000 (0x03E8)
		// @318: iastore
		// @319: getstatic int[] game.C_100064_ve.field_103015_v
		// @31C: bipush 64 (0x40)
		// @31E: sipush 500 (0x01F4)
		// @321: iastore
		// @322: getstatic int[] game.C_100064_ve.field_103015_v
		// @325: bipush 37 (0x25)
		// @327: bipush 100 (0x64)
		// @329: iastore
		// @32A: getstatic int[] game.C_100064_ve.field_103015_v
		// @32D: bipush 65 (0x41)
		// @32F: sipush 750 (0x02EE)
		// @332: iastore
		// @333: ldc "\u001bV#\u0000iO\u0012`\u001e+B\u0016}\u001e;B\u001e|H,C]"
		// @335: invokestatic game.C_100064_ve.func_103005_z(java.lang.String)char[]
		// @338: invokestatic game.C_100064_ve.func_103004_z(char[])java.lang.String
		// @33B: putstatic java.lang.String game.C_100064_ve.field_103012_B
		// @33E: new game.C_100202_qi
		// @341: dup
		// @342: invokespecial game.C_100202_qi.<init>()void
		// @345: putstatic game.C_100202_qi game.C_100064_ve.field_103022_x
		// @348: return
	}
	
	private static char[] func_103005_z(String arg0)
	{
		// @00: aload_0
		// @01: invokevirtual java.lang.String.toCharArray()char[]
		// @04: dup
		// @05: arraylength
		// @06: iconst_2
		// @07: if_icmpge @13
		// @0A: dup
		// @0B: iconst_0
		// @0C: dup2
		// @0D: caload
		// @0E: bipush 73 (0x49)
		// @10: ixor
		// @11: i2c
		// @12: castore
		// @13: areturn
	}
	
	private static String func_103004_z(char[] arg0)
	{
		// @00: aload_0
		// @01: dup
		// @02: arraylength
		// @03: swap
		// @04: iconst_0
		// @05: istore_1
		// @06: goto @4C
		// @09: dup
		// @0A: iload_1
		// @0B: dup2
		// @0C: caload
		// @0D: iload_1
		// @0E: iconst_5
		// @0F: irem
		// @10: tableswitch def: @44, for 0: @30, for 1: @35, for 2: @3A, for 3: @3F
		// @30: bipush 39 (0x27)
		// @32: goto @46
		// @35: bipush 115 (0x73)
		// @37: goto @46
		// @3A: bipush 19 (0x13)
		// @3C: goto @46
		// @3F: bipush 62 (0x3E)
		// @41: goto @46
		// @44: bipush 73 (0x49)
		// @46: ixor
		// @47: i2c
		// @48: castore
		// @49: iinc #1 +1
		// @4C: swap
		// @4D: dup_x1
		// @4E: iload_1
		// @4F: if_icmpgt @09
		// @52: new java.lang.String
		// @55: dup_x1
		// @56: swap
		// @57: invokespecial java.lang.String.<init>(char[])void
		// @5A: invokevirtual java.lang.String.intern()java.lang.String
		// @5D: areturn
	}
}
