package game;

import java.applet.Applet;

final class C_100151_bc extends C_100085_a implements C_100224_ag, C_100334_ik
{
	static C_100193_re field_102942_S;
	private String field_102946_bb;
	private C_100218_am field_102948_Z;
	static int[][] field_102939_V;
	private boolean field_102947_X;
	private boolean field_102938_W;
	static C_100302_ka field_102932_cb;
	private C_100218_am field_102934_fb;
	static int field_102940_Q;
	static int field_102931_db;
	static String field_102936_U;
	private boolean field_102937_T;
	static C_100026_hb field_102945_Y;
	static String field_102941_P;
	private C_100309_lk field_102944_ab;
	private C_100309_lk field_102933_eb;
	private C_100218_am field_102943_R;
	private static final String[] field_102935_gb;
	
	static final void func_102927_a(int arg0, Applet arg1)
	{
		// @00: aload_1
		// @01: getstatic java.lang.String[] game.C_100151_bc.field_102935_gb
		// @04: bipush 9 (0x09)
		// @06: aaload
		// @07: invokevirtual java.applet.Applet.getParameter(java.lang.String)java.lang.String
		// @0A: astore_2
		// @0B: bipush -9 (0xF7)
		// @0D: bipush -49 (0xCF)
		// @0F: iload_0
		// @10: isub
		// @11: bipush 54 (0x36)
		// @13: idiv
		// @14: idiv
		// @15: istore_3
		// @16: aconst_null
		// @17: aload_2
		// @18: if_acmpeq @2E
		// @1B: lconst_0
		// @1C: bipush 97 (0x61)
		// @1E: aload_2
		// @1F: invokestatic game.C_100271_mj.func_103427_a(int, java.lang.CharSequence)long
		// @22: lcmp
		// @23: ifeq @2E
		// @26: goto @2A
		// @29: athrow
		// @2A: goto @2F
		// @2D: athrow
		// @2E: return
		// @2F: goto @6E
		// @32: astore_2
		// @33: aload_2
		// @34: new java.lang.StringBuilder
		// @37: dup
		// @38: invokespecial java.lang.StringBuilder.<init>()void
		// @3B: getstatic java.lang.String[] game.C_100151_bc.field_102935_gb
		// @3E: bipush 8 (0x08)
		// @40: aaload
		// @41: invokevirtual java.lang.StringBuilder.append(java.lang.String)java.lang.StringBuilder
		// @44: iload_0
		// @45: invokevirtual java.lang.StringBuilder.append(int)java.lang.StringBuilder
		// @48: bipush 44 (0x2C)
		// @4A: invokevirtual java.lang.StringBuilder.append(char)java.lang.StringBuilder
		// @4D: aload_1
		// @4E: ifnull @5A
		// @51: getstatic java.lang.String[] game.C_100151_bc.field_102935_gb
		// @54: iconst_2
		// @55: aaload
		// @56: goto @5F
		// @59: athrow
		// @5A: getstatic java.lang.String[] game.C_100151_bc.field_102935_gb
		// @5D: iconst_3
		// @5E: aaload
		// @5F: invokevirtual java.lang.StringBuilder.append(java.lang.String)java.lang.StringBuilder
		// @62: bipush 41 (0x29)
		// @64: invokevirtual java.lang.StringBuilder.append(char)java.lang.StringBuilder
		// @67: invokevirtual java.lang.StringBuilder.toString()java.lang.String
		// @6A: invokestatic game.C_100181_cf.func_105695_a(java.lang.Throwable, java.lang.String)game.C_100170_cm
		// @6D: athrow
		// @6E: return
	}
	
	public final void func_102580_a(byte arg0, C_100309_lk arg1)
	{
		// @00: iload_1
		// @01: bipush 79 (0x4F)
		// @03: if_icmpgt @0B
		// @06: bipush -29 (0xE3)
		// @08: putstatic int game.C_100151_bc.field_102940_Q
		// @0B: goto @4A
		// @0E: astore_3
		// @0F: aload_3
		// @10: new java.lang.StringBuilder
		// @13: dup
		// @14: invokespecial java.lang.StringBuilder.<init>()void
		// @17: getstatic java.lang.String[] game.C_100151_bc.field_102935_gb
		// @1A: bipush 12 (0x0C)
		// @1C: aaload
		// @1D: invokevirtual java.lang.StringBuilder.append(java.lang.String)java.lang.StringBuilder
		// @20: iload_1
		// @21: invokevirtual java.lang.StringBuilder.append(int)java.lang.StringBuilder
		// @24: bipush 44 (0x2C)
		// @26: invokevirtual java.lang.StringBuilder.append(char)java.lang.StringBuilder
		// @29: aload_2
		// @2A: ifnull @36
		// @2D: getstatic java.lang.String[] game.C_100151_bc.field_102935_gb
		// @30: iconst_2
		// @31: aaload
		// @32: goto @3B
		// @35: athrow
		// @36: getstatic java.lang.String[] game.C_100151_bc.field_102935_gb
		// @39: iconst_3
		// @3A: aaload
		// @3B: invokevirtual java.lang.StringBuilder.append(java.lang.String)java.lang.StringBuilder
		// @3E: bipush 41 (0x29)
		// @40: invokevirtual java.lang.StringBuilder.append(char)java.lang.StringBuilder
		// @43: invokevirtual java.lang.StringBuilder.toString()java.lang.String
		// @46: invokestatic game.C_100181_cf.func_105695_a(java.lang.Throwable, java.lang.String)game.C_100170_cm
		// @49: athrow
		// @4A: return
	}
	
	final boolean func_102506_a(char arg0, int arg1, int arg2, C_100336_im arg3)
	{
		// @00: aload_0
		// @01: iload_1
		// @02: iload_2
		// @03: iload_3
		// @04: aload #4
		// @06: invokespecial game.C_100085_a.func_102506_a(char, int, int, game.C_100336_im)boolean
		// @09: ifeq @0E
		// @0C: iconst_1
		// @0D: ireturn
		// @0E: iload_2
		// @0F: bipush 98 (0x62)
		// @11: if_icmpeq @18
		// @14: goto @24
		// @17: athrow
		// @18: aload_0
		// @19: aload #4
		// @1B: iload_3
		// @1C: sipush 22625 (0x5861)
		// @1F: ixor
		// @20: invokevirtual game.C_100151_bc.func_102555_a(game.C_100336_im, int)boolean
		// @23: ireturn
		// @24: iload_2
		// @25: bipush 99 (0x63)
		// @27: if_icmpne @34
		// @2A: aload_0
		// @2B: sipush -17543 (0xBB79)
		// @2E: aload #4
		// @30: invokevirtual game.C_100151_bc.func_102558_b(int, game.C_100336_im)boolean
		// @33: ireturn
		// @34: iconst_0
		// @35: ireturn
		// @36: astore #5
		// @38: aload #5
		// @3A: new java.lang.StringBuilder
		// @3D: dup
		// @3E: invokespecial java.lang.StringBuilder.<init>()void
		// @41: getstatic java.lang.String[] game.C_100151_bc.field_102935_gb
		// @44: bipush 11 (0x0B)
		// @46: aaload
		// @47: invokevirtual java.lang.StringBuilder.append(java.lang.String)java.lang.StringBuilder
		// @4A: iload_1
		// @4B: invokevirtual java.lang.StringBuilder.append(char)java.lang.StringBuilder
		// @4E: bipush 44 (0x2C)
		// @50: invokevirtual java.lang.StringBuilder.append(char)java.lang.StringBuilder
		// @53: iload_2
		// @54: invokevirtual java.lang.StringBuilder.append(int)java.lang.StringBuilder
		// @57: bipush 44 (0x2C)
		// @59: invokevirtual java.lang.StringBuilder.append(char)java.lang.StringBuilder
		// @5C: iload_3
		// @5D: invokevirtual java.lang.StringBuilder.append(int)java.lang.StringBuilder
		// @60: bipush 44 (0x2C)
		// @62: invokevirtual java.lang.StringBuilder.append(char)java.lang.StringBuilder
		// @65: aload #4
		// @67: ifnull @73
		// @6A: getstatic java.lang.String[] game.C_100151_bc.field_102935_gb
		// @6D: iconst_2
		// @6E: aaload
		// @6F: goto @78
		// @72: athrow
		// @73: getstatic java.lang.String[] game.C_100151_bc.field_102935_gb
		// @76: iconst_3
		// @77: aaload
		// @78: invokevirtual java.lang.StringBuilder.append(java.lang.String)java.lang.StringBuilder
		// @7B: bipush 41 (0x29)
		// @7D: invokevirtual java.lang.StringBuilder.append(char)java.lang.StringBuilder
		// @80: invokevirtual java.lang.StringBuilder.toString()java.lang.String
		// @83: invokestatic game.C_100181_cf.func_105695_a(java.lang.Throwable, java.lang.String)game.C_100170_cm
		// @86: athrow
	}
	
	final void func_102528_a(int arg0, int arg1, int arg2, byte arg3)
	{
		// @00: aconst_null
		// @01: aload_0
		// @02: getfield java.lang.String game.C_100151_bc.field_102946_bb
		// @05: if_acmpeq @40
		// @08: getstatic game.C_100112_r game.C_100230_of.field_106205_g
		// @0B: aload_0
		// @0C: getfield java.lang.String game.C_100151_bc.field_102946_bb
		// @0F: iload_3
		// @10: aload_0
		// @11: getfield int game.C_100151_bc.field_102538_m
		// @14: bipush -20 (0xEC)
		// @16: isub
		// @17: iadd
		// @18: iload_2
		// @19: aload_0
		// @1A: getfield int game.C_100151_bc.field_102541_w
		// @1D: ineg
		// @1E: bipush 15 (0x0F)
		// @20: isub
		// @21: isub
		// @22: aload_0
		// @23: getfield int game.C_100151_bc.field_102537_l
		// @26: bipush 40 (0x28)
		// @28: isub
		// @29: aload_0
		// @2A: getfield int game.C_100151_bc.field_102544_t
		// @2D: ldc 16777215 (0xffffff)
		// @2F: iconst_m1
		// @30: iconst_1
		// @31: iconst_0
		// @32: getstatic game.C_100112_r game.C_100230_of.field_106205_g
		// @35: getfield int game.C_100112_r.field_101772_Q
		// @38: invokevirtual game.C_100112_r.func_101729_a(java.lang.String, int, int, int, int, int, int, int, int, int)int
		// @3B: pop
		// @3C: goto @40
		// @3F: athrow
		// @40: iload #4
		// @42: bipush -126 (0x82)
		// @44: if_icmple @50
		// @47: iconst_1
		// @48: invokestatic game.C_100151_bc.func_102928_a(boolean)game.C_100256_pk
		// @4B: pop
		// @4C: goto @50
		// @4F: athrow
		// @50: aload_0
		// @51: getfield game.C_100218_am game.C_100151_bc.field_102934_fb
		// @54: ifnull @70
		// @57: iload_3
		// @58: bipush -10 (0xF6)
		// @5A: isub
		// @5B: iload_2
		// @5C: sipush 134 (0x0086)
		// @5F: iadd
		// @60: bipush -20 (0xEC)
		// @62: aload_0
		// @63: getfield int game.C_100151_bc.field_102537_l
		// @66: iadd
		// @67: ldc 4210752 (0x404040)
		// @69: invokestatic game.C_100196_rb.func_105807_g(int, int, int, int)void
		// @6C: goto @70
		// @6F: athrow
		// @70: aload_0
		// @71: iload_1
		// @72: iload_2
		// @73: iload_3
		// @74: bipush -127 (0x81)
		// @76: invokespecial game.C_100085_a.func_102528_a(int, int, int, byte)void
		// @79: goto @BB
		// @7C: astore #5
		// @7E: aload #5
		// @80: new java.lang.StringBuilder
		// @83: dup
		// @84: invokespecial java.lang.StringBuilder.<init>()void
		// @87: getstatic java.lang.String[] game.C_100151_bc.field_102935_gb
		// @8A: iconst_0
		// @8B: aaload
		// @8C: invokevirtual java.lang.StringBuilder.append(java.lang.String)java.lang.StringBuilder
		// @8F: iload_1
		// @90: invokevirtual java.lang.StringBuilder.append(int)java.lang.StringBuilder
		// @93: bipush 44 (0x2C)
		// @95: invokevirtual java.lang.StringBuilder.append(char)java.lang.StringBuilder
		// @98: iload_2
		// @99: invokevirtual java.lang.StringBuilder.append(int)java.lang.StringBuilder
		// @9C: bipush 44 (0x2C)
		// @9E: invokevirtual java.lang.StringBuilder.append(char)java.lang.StringBuilder
		// @A1: iload_3
		// @A2: invokevirtual java.lang.StringBuilder.append(int)java.lang.StringBuilder
		// @A5: bipush 44 (0x2C)
		// @A7: invokevirtual java.lang.StringBuilder.append(char)java.lang.StringBuilder
		// @AA: iload #4
		// @AC: invokevirtual java.lang.StringBuilder.append(int)java.lang.StringBuilder
		// @AF: bipush 41 (0x29)
		// @B1: invokevirtual java.lang.StringBuilder.append(char)java.lang.StringBuilder
		// @B4: invokevirtual java.lang.StringBuilder.toString()java.lang.String
		// @B7: invokestatic game.C_100181_cf.func_105695_a(java.lang.Throwable, java.lang.String)game.C_100170_cm
		// @BA: athrow
		// @BB: return
	}
	
	public final void func_102581_a(int arg0, int arg1, byte arg2, C_100218_am arg3, int arg4)
	{
		// @00: getstatic int game.SteelSentinels.field_105275_O
		// @03: istore #7
		// @05: aload_0
		// @06: getfield game.C_100218_am game.C_100151_bc.field_102948_Z
		// @09: aload #4
		// @0B: if_acmpeq @76
		// @0E: aload #4
		// @10: aload_0
		// @11: getfield game.C_100218_am game.C_100151_bc.field_102934_fb
		// @14: if_acmpeq @68
		// @17: goto @1B
		// @1A: athrow
		// @1B: aload_0
		// @1C: getfield game.C_100218_am game.C_100151_bc.field_102943_R
		// @1F: aload #4
		// @21: if_acmpeq @2C
		// @24: goto @28
		// @27: athrow
		// @28: goto @7F
		// @2B: athrow
		// @2C: aload_0
		// @2D: getfield boolean game.C_100151_bc.field_102938_W
		// @30: ifne @5B
		// @33: aload_0
		// @34: getfield boolean game.C_100151_bc.field_102947_X
		// @37: ifeq @4C
		// @3A: goto @3E
		// @3D: athrow
		// @3E: bipush -101 (0x9B)
		// @40: invokestatic game.C_100158_da.func_100588_b(byte)void
		// @43: iload #7
		// @45: ifeq @7F
		// @48: goto @4C
		// @4B: athrow
		// @4C: sipush 11152 (0x2B90)
		// @4F: invokestatic game.C_100272_mn.func_102420_k(int)void
		// @52: iload #7
		// @54: ifeq @7F
		// @57: goto @5B
		// @5A: athrow
		// @5B: iconst_0
		// @5C: invokestatic game.C_100071_va.func_101653_c(boolean)void
		// @5F: iload #7
		// @61: ifeq @7F
		// @64: goto @68
		// @67: athrow
		// @68: bipush -112 (0x90)
		// @6A: invokestatic game.C_100211_qd.func_102124_l(int)void
		// @6D: iload #7
		// @6F: ifeq @7F
		// @72: goto @76
		// @75: athrow
		// @76: aload_0
		// @77: iconst_m1
		// @78: invokespecial game.C_100151_bc.func_102929_k(int)void
		// @7B: goto @7F
		// @7E: athrow
		// @7F: bipush -124 (0x84)
		// @81: bipush -2 (0xFE)
		// @83: iload_3
		// @84: isub
		// @85: bipush 52 (0x34)
		// @87: idiv
		// @88: idiv
		// @89: istore #6
		// @8B: goto @E8
		// @8E: astore #6
		// @90: aload #6
		// @92: new java.lang.StringBuilder
		// @95: dup
		// @96: invokespecial java.lang.StringBuilder.<init>()void
		// @99: getstatic java.lang.String[] game.C_100151_bc.field_102935_gb
		// @9C: iconst_1
		// @9D: aaload
		// @9E: invokevirtual java.lang.StringBuilder.append(java.lang.String)java.lang.StringBuilder
		// @A1: iload_1
		// @A2: invokevirtual java.lang.StringBuilder.append(int)java.lang.StringBuilder
		// @A5: bipush 44 (0x2C)
		// @A7: invokevirtual java.lang.StringBuilder.append(char)java.lang.StringBuilder
		// @AA: iload_2
		// @AB: invokevirtual java.lang.StringBuilder.append(int)java.lang.StringBuilder
		// @AE: bipush 44 (0x2C)
		// @B0: invokevirtual java.lang.StringBuilder.append(char)java.lang.StringBuilder
		// @B3: iload_3
		// @B4: invokevirtual java.lang.StringBuilder.append(int)java.lang.StringBuilder
		// @B7: bipush 44 (0x2C)
		// @B9: invokevirtual java.lang.StringBuilder.append(char)java.lang.StringBuilder
		// @BC: aload #4
		// @BE: ifnull @CA
		// @C1: getstatic java.lang.String[] game.C_100151_bc.field_102935_gb
		// @C4: iconst_2
		// @C5: aaload
		// @C6: goto @CF
		// @C9: athrow
		// @CA: getstatic java.lang.String[] game.C_100151_bc.field_102935_gb
		// @CD: iconst_3
		// @CE: aaload
		// @CF: invokevirtual java.lang.StringBuilder.append(java.lang.String)java.lang.StringBuilder
		// @D2: bipush 44 (0x2C)
		// @D4: invokevirtual java.lang.StringBuilder.append(char)java.lang.StringBuilder
		// @D7: iload #5
		// @D9: invokevirtual java.lang.StringBuilder.append(int)java.lang.StringBuilder
		// @DC: bipush 41 (0x29)
		// @DE: invokevirtual java.lang.StringBuilder.append(char)java.lang.StringBuilder
		// @E1: invokevirtual java.lang.StringBuilder.toString()java.lang.String
		// @E4: invokestatic game.C_100181_cf.func_105695_a(java.lang.Throwable, java.lang.String)game.C_100170_cm
		// @E7: athrow
		// @E8: return
	}
	
	final void func_102924_a(byte arg0)
	{
		// @00: aload_0
		// @01: getfield game.C_100309_lk game.C_100151_bc.field_102933_eb
		// @04: iconst_0
		// @05: invokevirtual game.C_100309_lk.func_103239_c(boolean)void
		// @08: iload_1
		// @09: bipush -77 (0xB3)
		// @0B: if_icmpeq @0F
		// @0E: return
		// @0F: aload_0
		// @10: getfield game.C_100309_lk game.C_100151_bc.field_102944_ab
		// @13: iconst_0
		// @14: invokevirtual game.C_100309_lk.func_103239_c(boolean)void
		// @17: goto @3C
		// @1A: astore_2
		// @1B: aload_2
		// @1C: new java.lang.StringBuilder
		// @1F: dup
		// @20: invokespecial java.lang.StringBuilder.<init>()void
		// @23: getstatic java.lang.String[] game.C_100151_bc.field_102935_gb
		// @26: bipush 14 (0x0E)
		// @28: aaload
		// @29: invokevirtual java.lang.StringBuilder.append(java.lang.String)java.lang.StringBuilder
		// @2C: iload_1
		// @2D: invokevirtual java.lang.StringBuilder.append(int)java.lang.StringBuilder
		// @30: bipush 41 (0x29)
		// @32: invokevirtual java.lang.StringBuilder.append(char)java.lang.StringBuilder
		// @35: invokevirtual java.lang.StringBuilder.toString()java.lang.String
		// @38: invokestatic game.C_100181_cf.func_105695_a(java.lang.Throwable, java.lang.String)game.C_100170_cm
		// @3B: athrow
		// @3C: return
	}
	
	final String func_102926_g(byte arg0)
	{
		// @00: iload_1
		// @01: bipush -60 (0xC4)
		// @03: if_icmplt @0B
		// @06: aconst_null
		// @07: checkcast java.lang.String
		// @0A: areturn
		// @0B: aconst_null
		// @0C: aload_0
		// @0D: getfield game.C_100309_lk game.C_100151_bc.field_102933_eb
		// @10: getfield java.lang.String game.C_100309_lk.field_102534_C
		// @13: if_acmpne @19
		// @16: ldc ""
		// @18: areturn
		// @19: aload_0
		// @1A: getfield game.C_100309_lk game.C_100151_bc.field_102933_eb
		// @1D: getfield java.lang.String game.C_100309_lk.field_102534_C
		// @20: areturn
		// @21: astore_2
		// @22: aload_2
		// @23: new java.lang.StringBuilder
		// @26: dup
		// @27: invokespecial java.lang.StringBuilder.<init>()void
		// @2A: getstatic java.lang.String[] game.C_100151_bc.field_102935_gb
		// @2D: bipush 15 (0x0F)
		// @2F: aaload
		// @30: invokevirtual java.lang.StringBuilder.append(java.lang.String)java.lang.StringBuilder
		// @33: iload_1
		// @34: invokevirtual java.lang.StringBuilder.append(int)java.lang.StringBuilder
		// @37: bipush 41 (0x29)
		// @39: invokevirtual java.lang.StringBuilder.append(char)java.lang.StringBuilder
		// @3C: invokevirtual java.lang.StringBuilder.toString()java.lang.String
		// @3F: invokestatic game.C_100181_cf.func_105695_a(java.lang.Throwable, java.lang.String)game.C_100170_cm
		// @42: athrow
	}
	
	public final void func_102579_a(int arg0, C_100309_lk arg1)
	{
		// @00: aload_0
		// @01: getfield game.C_100309_lk game.C_100151_bc.field_102933_eb
		// @04: aload_2
		// @05: if_acmpne @19
		// @08: aload_0
		// @09: getfield game.C_100309_lk game.C_100151_bc.field_102944_ab
		// @0C: iload_1
		// @0D: bipush -19 (0xED)
		// @0F: iadd
		// @10: aload_0
		// @11: invokevirtual game.C_100309_lk.func_102522_a(int, game.C_100336_im)boolean
		// @14: pop
		// @15: goto @19
		// @18: athrow
		// @19: iload_1
		// @1A: bipush 20 (0x14)
		// @1C: if_icmpeq @20
		// @1F: return
		// @20: aload_0
		// @21: getfield game.C_100309_lk game.C_100151_bc.field_102944_ab
		// @24: aload_2
		// @25: if_acmpne @2D
		// @28: aload_0
		// @29: iconst_m1
		// @2A: invokespecial game.C_100151_bc.func_102929_k(int)void
		// @2D: goto @6C
		// @30: astore_3
		// @31: aload_3
		// @32: new java.lang.StringBuilder
		// @35: dup
		// @36: invokespecial java.lang.StringBuilder.<init>()void
		// @39: getstatic java.lang.String[] game.C_100151_bc.field_102935_gb
		// @3C: bipush 6 (0x06)
		// @3E: aaload
		// @3F: invokevirtual java.lang.StringBuilder.append(java.lang.String)java.lang.StringBuilder
		// @42: iload_1
		// @43: invokevirtual java.lang.StringBuilder.append(int)java.lang.StringBuilder
		// @46: bipush 44 (0x2C)
		// @48: invokevirtual java.lang.StringBuilder.append(char)java.lang.StringBuilder
		// @4B: aload_2
		// @4C: ifnull @58
		// @4F: getstatic java.lang.String[] game.C_100151_bc.field_102935_gb
		// @52: iconst_2
		// @53: aaload
		// @54: goto @5D
		// @57: athrow
		// @58: getstatic java.lang.String[] game.C_100151_bc.field_102935_gb
		// @5B: iconst_3
		// @5C: aaload
		// @5D: invokevirtual java.lang.StringBuilder.append(java.lang.String)java.lang.StringBuilder
		// @60: bipush 41 (0x29)
		// @62: invokevirtual java.lang.StringBuilder.append(char)java.lang.StringBuilder
		// @65: invokevirtual java.lang.StringBuilder.toString()java.lang.String
		// @68: invokestatic game.C_100181_cf.func_105695_a(java.lang.Throwable, java.lang.String)game.C_100170_cm
		// @6B: athrow
		// @6C: return
	}
	
	private final void func_102929_k(int arg0)
	{
		// @00: iload_1
		// @01: iconst_m1
		// @02: if_icmpeq @10
		// @05: aconst_null
		// @06: checkcast java.lang.String
		// @09: putstatic java.lang.String game.C_100151_bc.field_102941_P
		// @0C: goto @10
		// @0F: athrow
		// @10: bipush -88 (0xA8)
		// @12: invokestatic game.C_100260_mc.func_102218_n(int)boolean
		// @15: ifne @41
		// @18: aload_0
		// @19: getfield game.C_100309_lk game.C_100151_bc.field_102933_eb
		// @1C: getfield java.lang.String game.C_100309_lk.field_102534_C
		// @1F: invokevirtual java.lang.String.length()int
		// @22: ifle @53
		// @25: goto @29
		// @28: athrow
		// @29: aload_0
		// @2A: getfield game.C_100309_lk game.C_100151_bc.field_102944_ab
		// @2D: getfield java.lang.String game.C_100309_lk.field_102534_C
		// @30: invokevirtual java.lang.String.length()int
		// @33: iconst_m1
		// @34: ixor
		// @35: iconst_m1
		// @36: if_icmplt @41
		// @39: goto @3D
		// @3C: athrow
		// @3D: goto @53
		// @40: athrow
		// @41: iconst_2
		// @42: aload_0
		// @43: getfield game.C_100309_lk game.C_100151_bc.field_102933_eb
		// @46: getfield java.lang.String game.C_100309_lk.field_102534_C
		// @49: aload_0
		// @4A: getfield game.C_100309_lk game.C_100151_bc.field_102944_ab
		// @4D: getfield java.lang.String game.C_100309_lk.field_102534_C
		// @50: invokestatic game.C_100031_gl.func_103956_a(int, java.lang.String, java.lang.String)void
		// @53: goto @78
		// @56: astore_2
		// @57: aload_2
		// @58: new java.lang.StringBuilder
		// @5B: dup
		// @5C: invokespecial java.lang.StringBuilder.<init>()void
		// @5F: getstatic java.lang.String[] game.C_100151_bc.field_102935_gb
		// @62: bipush 7 (0x07)
		// @64: aaload
		// @65: invokevirtual java.lang.StringBuilder.append(java.lang.String)java.lang.StringBuilder
		// @68: iload_1
		// @69: invokevirtual java.lang.StringBuilder.append(int)java.lang.StringBuilder
		// @6C: bipush 41 (0x29)
		// @6E: invokevirtual java.lang.StringBuilder.append(char)java.lang.StringBuilder
		// @71: invokevirtual java.lang.StringBuilder.toString()java.lang.String
		// @74: invokestatic game.C_100181_cf.func_105695_a(java.lang.Throwable, java.lang.String)game.C_100170_cm
		// @77: athrow
		// @78: return
	}
	
	static final C_100256_pk func_102928_a(boolean arg0)
	{
		// @00: getstatic game.C_100256_pk game.C_100166_sg.field_105463_g
		// @03: ifnonnull @2B
		// @06: new game.C_100256_pk
		// @09: dup
		// @0A: getstatic game.C_100112_r game.C_100318_hj.field_107198_b
		// @0D: bipush 20 (0x14)
		// @0F: iconst_0
		// @10: iconst_0
		// @11: iconst_0
		// @12: ldc 11579568 (0xb0b0b0)
		// @14: iconst_m1
		// @15: iconst_0
		// @16: iconst_0
		// @17: getstatic game.C_100112_r game.C_100318_hj.field_107198_b
		// @1A: getfield int game.C_100112_r.field_101772_Q
		// @1D: iconst_m1
		// @1E: ldc 2147483647 (0x7fffffff)
		// @20: iconst_1
		// @21: invokespecial game.C_100256_pk.<init>(game.C_100112_r, int, int, int, int, int, int, int, int, int, int, int, boolean)void
		// @24: putstatic game.C_100256_pk game.C_100166_sg.field_105463_g
		// @27: goto @2B
		// @2A: athrow
		// @2B: iload_0
		// @2C: ifeq @34
		// @2F: aconst_null
		// @30: checkcast game.C_100256_pk
		// @33: areturn
		// @34: getstatic game.C_100256_pk game.C_100166_sg.field_105463_g
		// @37: areturn
		// @38: astore_1
		// @39: aload_1
		// @3A: new java.lang.StringBuilder
		// @3D: dup
		// @3E: invokespecial java.lang.StringBuilder.<init>()void
		// @41: getstatic java.lang.String[] game.C_100151_bc.field_102935_gb
		// @44: iconst_5
		// @45: aaload
		// @46: invokevirtual java.lang.StringBuilder.append(java.lang.String)java.lang.StringBuilder
		// @49: iload_0
		// @4A: invokevirtual java.lang.StringBuilder.append(boolean)java.lang.StringBuilder
		// @4D: bipush 41 (0x29)
		// @4F: invokevirtual java.lang.StringBuilder.append(char)java.lang.StringBuilder
		// @52: invokevirtual java.lang.StringBuilder.toString()java.lang.String
		// @55: invokestatic game.C_100181_cf.func_105695_a(java.lang.Throwable, java.lang.String)game.C_100170_cm
		// @58: athrow
	}
	
	public static void func_102930_f(byte arg0)
	{
		// @00: aconst_null
		// @01: putstatic game.C_100026_hb game.C_100151_bc.field_102945_Y
		// @04: aconst_null
		// @05: putstatic java.lang.String game.C_100151_bc.field_102941_P
		// @08: aconst_null
		// @09: putstatic game.C_100193_re game.C_100151_bc.field_102942_S
		// @0C: aconst_null
		// @0D: putstatic java.lang.String game.C_100151_bc.field_102936_U
		// @10: aconst_null
		// @11: putstatic game.C_100302_ka game.C_100151_bc.field_102932_cb
		// @14: aconst_null
		// @15: checkcast int[][]
		// @18: putstatic int[][] game.C_100151_bc.field_102939_V
		// @1B: iload_0
		// @1C: bipush -30 (0xE2)
		// @1E: if_icmpeq @26
		// @21: iconst_1
		// @22: invokestatic game.C_100151_bc.func_102928_a(boolean)game.C_100256_pk
		// @25: pop
		// @26: goto @4B
		// @29: astore_1
		// @2A: aload_1
		// @2B: new java.lang.StringBuilder
		// @2E: dup
		// @2F: invokespecial java.lang.StringBuilder.<init>()void
		// @32: getstatic java.lang.String[] game.C_100151_bc.field_102935_gb
		// @35: bipush 10 (0x0A)
		// @37: aaload
		// @38: invokevirtual java.lang.StringBuilder.append(java.lang.String)java.lang.StringBuilder
		// @3B: iload_0
		// @3C: invokevirtual java.lang.StringBuilder.append(int)java.lang.StringBuilder
		// @3F: bipush 41 (0x29)
		// @41: invokevirtual java.lang.StringBuilder.append(char)java.lang.StringBuilder
		// @44: invokevirtual java.lang.StringBuilder.toString()java.lang.String
		// @47: invokestatic game.C_100181_cf.func_105695_a(java.lang.Throwable, java.lang.String)game.C_100170_cm
		// @4A: athrow
		// @4B: return
	}
	
	final void func_102922_a(String arg0, byte arg1)
	{
		// @00: aload_0
		// @01: getfield game.C_100309_lk game.C_100151_bc.field_102933_eb
		// @04: astore_3
		// @05: aload_1
		// @06: astore #4
		// @08: aload_3
		// @09: iconst_0
		// @0A: iconst_1
		// @0B: aload #4
		// @0D: invokevirtual game.C_100309_lk.func_103251_a(boolean, boolean, java.lang.String)void
		// @10: bipush 6 (0x06)
		// @12: iload_2
		// @13: bipush -32 (0xE0)
		// @15: isub
		// @16: bipush 51 (0x33)
		// @18: idiv
		// @19: irem
		// @1A: istore #5
		// @1C: aload_0
		// @1D: getfield game.C_100309_lk game.C_100151_bc.field_102944_ab
		// @20: iconst_0
		// @21: invokevirtual game.C_100309_lk.func_103239_c(boolean)void
		// @24: goto @62
		// @27: astore_3
		// @28: aload_3
		// @29: new java.lang.StringBuilder
		// @2C: dup
		// @2D: invokespecial java.lang.StringBuilder.<init>()void
		// @30: getstatic java.lang.String[] game.C_100151_bc.field_102935_gb
		// @33: iconst_4
		// @34: aaload
		// @35: invokevirtual java.lang.StringBuilder.append(java.lang.String)java.lang.StringBuilder
		// @38: aload_1
		// @39: ifnull @45
		// @3C: getstatic java.lang.String[] game.C_100151_bc.field_102935_gb
		// @3F: iconst_2
		// @40: aaload
		// @41: goto @4A
		// @44: athrow
		// @45: getstatic java.lang.String[] game.C_100151_bc.field_102935_gb
		// @48: iconst_3
		// @49: aaload
		// @4A: invokevirtual java.lang.StringBuilder.append(java.lang.String)java.lang.StringBuilder
		// @4D: bipush 44 (0x2C)
		// @4F: invokevirtual java.lang.StringBuilder.append(char)java.lang.StringBuilder
		// @52: iload_2
		// @53: invokevirtual java.lang.StringBuilder.append(int)java.lang.StringBuilder
		// @56: bipush 41 (0x29)
		// @58: invokevirtual java.lang.StringBuilder.append(char)java.lang.StringBuilder
		// @5B: invokevirtual java.lang.StringBuilder.toString()java.lang.String
		// @5E: invokestatic game.C_100181_cf.func_105695_a(java.lang.Throwable, java.lang.String)game.C_100170_cm
		// @61: athrow
		// @62: return
	}
	
	C_100151_bc(String arg0, String arg1, boolean arg2, boolean arg3, boolean arg4)
	{
		// @000: getstatic int game.SteelSentinels.field_105275_O
		// @003: istore #11
		// @005: aload_0
		// @006: iconst_0
		// @007: iconst_0
		// @008: sipush 310 (0x0136)
		// @00B: sipush 190 (0x00BE)
		// @00E: aconst_null
		// @00F: invokespecial game.C_100085_a.<init>(int, int, int, int, game.C_100326_ic)void
		// @012: aload_0
		// @013: iload_3
		// @014: putfield boolean game.C_100151_bc.field_102938_W
		// @017: aload_0
		// @018: iload #4
		// @01A: putfield boolean game.C_100151_bc.field_102937_T
		// @01D: aload_0
		// @01E: iload #5
		// @020: putfield boolean game.C_100151_bc.field_102947_X
		// @023: aload_0
		// @024: aload_2
		// @025: putfield java.lang.String game.C_100151_bc.field_102946_bb
		// @028: aload_0
		// @029: getfield boolean game.C_100151_bc.field_102938_W
		// @02C: ifeq @04A
		// @02F: aload_0
		// @030: getfield boolean game.C_100151_bc.field_102937_T
		// @033: ifne @041
		// @036: aload_0
		// @037: getfield boolean game.C_100151_bc.field_102947_X
		// @03A: ifeq @04A
		// @03D: goto @041
		// @040: athrow
		// @041: new java.lang.IllegalStateException
		// @044: dup
		// @045: invokespecial java.lang.IllegalStateException.<init>()void
		// @048: athrow
		// @049: athrow
		// @04A: aload_0
		// @04B: new game.C_100078_ul
		// @04E: dup
		// @04F: aload_1
		// @050: aload_0
		// @051: bipush 100 (0x64)
		// @053: invokespecial game.C_100078_ul.<init>(java.lang.String, game.C_100337_in, int)void
		// @056: putfield game.C_100309_lk game.C_100151_bc.field_102933_eb
		// @059: aload_0
		// @05A: new game.C_100078_ul
		// @05D: dup
		// @05E: ldc ""
		// @060: aload_0
		// @061: bipush 20 (0x14)
		// @063: invokespecial game.C_100078_ul.<init>(java.lang.String, game.C_100337_in, int)void
		// @066: putfield game.C_100309_lk game.C_100151_bc.field_102944_ab
		// @069: aload_0
		// @06A: getfield boolean game.C_100151_bc.field_102938_W
		// @06D: ifeq @09F
		// @070: aload_0
		// @071: new game.C_100218_am
		// @074: dup
		// @075: getstatic java.lang.String game.C_100027_hc.field_102601_bb
		// @078: aconst_null
		// @079: invokespecial game.C_100218_am.<init>(java.lang.String, game.C_100337_in)void
		// @07C: putfield game.C_100218_am game.C_100151_bc.field_102948_Z
		// @07F: aload_0
		// @080: new game.C_100218_am
		// @083: dup
		// @084: getstatic java.lang.String game.C_100239_oi.field_102298_C
		// @087: aconst_null
		// @088: invokespecial game.C_100218_am.<init>(java.lang.String, game.C_100337_in)void
		// @08B: putfield game.C_100218_am game.C_100151_bc.field_102943_R
		// @08E: aload_0
		// @08F: getfield game.C_100309_lk game.C_100151_bc.field_102933_eb
		// @092: iconst_0
		// @093: putfield boolean game.C_100309_lk.field_103113_L
		// @096: iload #11
		// @098: ifeq @0E8
		// @09B: goto @09F
		// @09E: athrow
		// @09F: aload_0
		// @0A0: new game.C_100218_am
		// @0A3: dup
		// @0A4: getstatic java.lang.String game.C_100197_ra.field_100865_t
		// @0A7: aconst_null
		// @0A8: invokespecial game.C_100218_am.<init>(java.lang.String, game.C_100337_in)void
		// @0AB: putfield game.C_100218_am game.C_100151_bc.field_102948_Z
		// @0AE: aload_0
		// @0AF: new game.C_100218_am
		// @0B2: dup
		// @0B3: aload_0
		// @0B4: getfield boolean game.C_100151_bc.field_102947_X
		// @0B7: ifeq @0C5
		// @0BA: goto @0BE
		// @0BD: athrow
		// @0BE: getstatic java.lang.String game.C_100287_nm.field_106833_i
		// @0C1: goto @0C8
		// @0C4: athrow
		// @0C5: getstatic java.lang.String game.C_100245_pf.field_106390_a
		// @0C8: aconst_null
		// @0C9: invokespecial game.C_100218_am.<init>(java.lang.String, game.C_100337_in)void
		// @0CC: putfield game.C_100218_am game.C_100151_bc.field_102943_R
		// @0CF: aload_0
		// @0D0: getfield boolean game.C_100151_bc.field_102937_T
		// @0D3: ifne @0D9
		// @0D6: goto @0E8
		// @0D9: aload_0
		// @0DA: new game.C_100218_am
		// @0DD: dup
		// @0DE: getstatic java.lang.String game.C_100203_ql.field_105930_b
		// @0E1: aload_0
		// @0E2: invokespecial game.C_100218_am.<init>(java.lang.String, game.C_100337_in)void
		// @0E5: putfield game.C_100218_am game.C_100151_bc.field_102934_fb
		// @0E8: aload_0
		// @0E9: getfield game.C_100309_lk game.C_100151_bc.field_102933_eb
		// @0EC: new game.C_100114_q
		// @0EF: dup
		// @0F0: ldc 10000536 (0x989898)
		// @0F2: invokespecial game.C_100114_q.<init>(int)void
		// @0F5: putfield game.C_100326_ic game.C_100309_lk.field_102533_B
		// @0F8: aload_0
		// @0F9: getfield game.C_100309_lk game.C_100151_bc.field_102944_ab
		// @0FC: new game.C_100012_fh
		// @0FF: dup
		// @100: ldc 10000536 (0x989898)
		// @102: invokespecial game.C_100012_fh.<init>(int)void
		// @105: putfield game.C_100326_ic game.C_100309_lk.field_102533_B
		// @108: new game.C_100310_lj
		// @10B: dup
		// @10C: invokespecial game.C_100310_lj.<init>()void
		// @10F: astore #6
		// @111: aload_0
		// @112: getfield game.C_100218_am game.C_100151_bc.field_102948_Z
		// @115: aload #6
		// @117: putfield game.C_100326_ic game.C_100218_am.field_102533_B
		// @11A: aconst_null
		// @11B: aload_0
		// @11C: getfield game.C_100218_am game.C_100151_bc.field_102943_R
		// @11F: if_acmpne @126
		// @122: goto @12F
		// @125: athrow
		// @126: aload_0
		// @127: getfield game.C_100218_am game.C_100151_bc.field_102943_R
		// @12A: aload #6
		// @12C: putfield game.C_100326_ic game.C_100218_am.field_102533_B
		// @12F: aconst_null
		// @130: aload_0
		// @131: getfield game.C_100218_am game.C_100151_bc.field_102934_fb
		// @134: if_acmpeq @144
		// @137: aload_0
		// @138: getfield game.C_100218_am game.C_100151_bc.field_102934_fb
		// @13B: aload #6
		// @13D: putfield game.C_100326_ic game.C_100218_am.field_102533_B
		// @140: goto @144
		// @143: athrow
		// @144: aload_0
		// @145: getfield game.C_100309_lk game.C_100151_bc.field_102933_eb
		// @148: getstatic java.lang.String game.C_100079_e.field_102665_Gb
		// @14B: putfield java.lang.String game.C_100309_lk.field_102536_o
		// @14E: aload_0
		// @14F: getfield game.C_100218_am game.C_100151_bc.field_102934_fb
		// @152: ifnonnull @159
		// @155: goto @163
		// @158: athrow
		// @159: aload_0
		// @15A: getfield game.C_100218_am game.C_100151_bc.field_102934_fb
		// @15D: getstatic java.lang.String game.C_100169_co.field_105528_a
		// @160: putfield java.lang.String game.C_100218_am.field_102536_o
		// @163: aload_0
		// @164: getfield boolean game.C_100151_bc.field_102938_W
		// @167: ifeq @17D
		// @16A: aload_0
		// @16B: getfield game.C_100218_am game.C_100151_bc.field_102943_R
		// @16E: getstatic java.lang.String game.C_100156_sk.field_105388_s
		// @171: putfield java.lang.String game.C_100218_am.field_102536_o
		// @174: iload #11
		// @176: ifeq @1BB
		// @179: goto @17D
		// @17C: athrow
		// @17D: aload_0
		// @17E: getfield boolean game.C_100151_bc.field_102947_X
		// @181: ifeq @1A9
		// @184: goto @188
		// @187: athrow
		// @188: aload_0
		// @189: getfield game.C_100218_am game.C_100151_bc.field_102943_R
		// @18C: getstatic java.lang.String game.C_100155_dc.field_105348_g
		// @18F: putfield java.lang.String game.C_100218_am.field_102536_o
		// @192: aload_0
		// @193: getfield game.C_100218_am game.C_100151_bc.field_102943_R
		// @196: new game.C_100082_uf
		// @199: dup
		// @19A: invokespecial game.C_100082_uf.<init>()void
		// @19D: putfield game.C_100326_ic game.C_100218_am.field_102533_B
		// @1A0: iload #11
		// @1A2: ifeq @1BB
		// @1A5: goto @1A9
		// @1A8: athrow
		// @1A9: aload_0
		// @1AA: getfield game.C_100218_am game.C_100151_bc.field_102943_R
		// @1AD: new game.C_100082_uf
		// @1B0: dup
		// @1B1: invokespecial game.C_100082_uf.<init>()void
		// @1B4: putfield game.C_100326_ic game.C_100218_am.field_102533_B
		// @1B7: goto @1BB
		// @1BA: athrow
		// @1BB: aload_0
		// @1BC: bipush 15 (0x0F)
		// @1BE: putfield int game.C_100151_bc.field_102541_w
		// @1C1: getstatic game.C_100112_r game.C_100230_of.field_106205_g
		// @1C4: astore #7
		// @1C6: aload_0
		// @1C7: getfield java.lang.String game.C_100151_bc.field_102946_bb
		// @1CA: ifnonnull @1D1
		// @1CD: goto @1F1
		// @1D0: athrow
		// @1D1: aload_0
		// @1D2: dup
		// @1D3: getfield int game.C_100151_bc.field_102541_w
		// @1D6: iconst_5
		// @1D7: aload #7
		// @1D9: aload_0
		// @1DA: getfield java.lang.String game.C_100151_bc.field_102946_bb
		// @1DD: aload_0
		// @1DE: getfield int game.C_100151_bc.field_102537_l
		// @1E1: bipush -40 (0xD8)
		// @1E3: iadd
		// @1E4: aload #7
		// @1E6: getfield int game.C_100112_r.field_101772_Q
		// @1E9: invokevirtual game.C_100112_r.func_101734_a(java.lang.String, int, int)int
		// @1EC: iadd
		// @1ED: iadd
		// @1EE: putfield int game.C_100151_bc.field_102541_w
		// @1F1: getstatic java.lang.String game.C_100341_jd.field_102639_qb
		// @1F4: astore #8
		// @1F6: iconst_1
		// @1F7: iconst_0
		// @1F8: invokestatic game.C_100206_qe.func_105938_b(boolean)java.applet.Applet
		// @1FB: invokestatic game.C_100186_rl.func_105717_a(int, java.applet.Applet)game.C_100113_ek
		// @1FE: astore #9
		// @200: aload #9
		// @202: getstatic game.C_100113_ek game.C_100121_ud.field_100715_F
		// @205: if_acmpne @212
		// @208: getstatic java.lang.String game.C_100256_pk.field_100461_g
		// @20B: astore #8
		// @20D: iload #11
		// @20F: ifeq @227
		// @212: getstatic game.C_100113_ek game.C_100280_nf.field_101181_j
		// @215: aload #9
		// @217: if_acmpeq @222
		// @21A: goto @21E
		// @21D: athrow
		// @21E: goto @227
		// @221: athrow
		// @222: getstatic java.lang.String game.C_100078_ul.field_103288_kb
		// @225: astore #8
		// @227: aload_0
		// @228: new game.C_100271_mj
		// @22B: dup
		// @22C: bipush 10 (0x0A)
		// @22E: aload_0
		// @22F: getfield int game.C_100151_bc.field_102541_w
		// @232: bipush -20 (0xEC)
		// @234: aload_0
		// @235: getfield int game.C_100151_bc.field_102537_l
		// @238: iadd
		// @239: bipush 25 (0x19)
		// @23B: aload_0
		// @23C: getfield game.C_100309_lk game.C_100151_bc.field_102933_eb
		// @23F: iconst_0
		// @240: bipush 80 (0x50)
		// @242: iconst_3
		// @243: aload #7
		// @245: ldc 16777215 (0xffffff)
		// @247: aload #8
		// @249: invokespecial game.C_100271_mj.<init>(int, int, int, int, game.C_100336_im, boolean, int, int, game.C_100112_r, int, java.lang.String)void
		// @24C: dup
		// @24D: astore #10
		// @24F: iconst_1
		// @250: invokevirtual game.C_100151_bc.func_102561_b(game.C_100336_im, int)void
		// @253: aload_0
		// @254: dup
		// @255: getfield int game.C_100151_bc.field_102541_w
		// @258: aload #10
		// @25A: getfield int game.C_100336_im.field_102544_t
		// @25D: bipush -5 (0xFB)
		// @25F: isub
		// @260: iadd
		// @261: putfield int game.C_100151_bc.field_102541_w
		// @264: aload_0
		// @265: new game.C_100271_mj
		// @268: dup
		// @269: bipush 10 (0x0A)
		// @26B: aload_0
		// @26C: getfield int game.C_100151_bc.field_102541_w
		// @26F: bipush -20 (0xEC)
		// @271: aload_0
		// @272: getfield int game.C_100151_bc.field_102537_l
		// @275: iadd
		// @276: bipush 25 (0x19)
		// @278: aload_0
		// @279: getfield game.C_100309_lk game.C_100151_bc.field_102944_ab
		// @27C: iconst_0
		// @27D: bipush 80 (0x50)
		// @27F: iconst_3
		// @280: aload #7
		// @282: ldc 16777215 (0xffffff)
		// @284: getstatic java.lang.String game.C_100003_ga.field_103531_j
		// @287: invokespecial game.C_100271_mj.<init>(int, int, int, int, game.C_100336_im, boolean, int, int, game.C_100112_r, int, java.lang.String)void
		// @28A: dup
		// @28B: astore #10
		// @28D: iconst_1
		// @28E: invokevirtual game.C_100151_bc.func_102561_b(game.C_100336_im, int)void
		// @291: aload_0
		// @292: dup
		// @293: getfield int game.C_100151_bc.field_102541_w
		// @296: aload #10
		// @298: getfield int game.C_100336_im.field_102544_t
		// @29B: iconst_5
		// @29C: iadd
		// @29D: iadd
		// @29E: putfield int game.C_100151_bc.field_102541_w
		// @2A1: aload_0
		// @2A2: getfield game.C_100218_am game.C_100151_bc.field_102948_Z
		// @2A5: aload_0
		// @2A6: putfield game.C_100337_in game.C_100218_am.field_102543_u
		// @2A9: aconst_null
		// @2AA: aload_0
		// @2AB: getfield game.C_100218_am game.C_100151_bc.field_102934_fb
		// @2AE: if_acmpne @2B5
		// @2B1: goto @2BD
		// @2B4: athrow
		// @2B5: aload_0
		// @2B6: getfield game.C_100218_am game.C_100151_bc.field_102934_fb
		// @2B9: aload_0
		// @2BA: putfield game.C_100337_in game.C_100218_am.field_102543_u
		// @2BD: aload_0
		// @2BE: getfield game.C_100218_am game.C_100151_bc.field_102943_R
		// @2C1: ifnull @2D0
		// @2C4: aload_0
		// @2C5: getfield game.C_100218_am game.C_100151_bc.field_102943_R
		// @2C8: aload_0
		// @2C9: putfield game.C_100337_in game.C_100218_am.field_102543_u
		// @2CC: goto @2D0
		// @2CF: athrow
		// @2D0: aconst_null
		// @2D1: aload_0
		// @2D2: getfield game.C_100218_am game.C_100151_bc.field_102934_fb
		// @2D5: if_acmpne @307
		// @2D8: aload_0
		// @2D9: getfield game.C_100218_am game.C_100151_bc.field_102948_Z
		// @2DC: bipush 30 (0x1E)
		// @2DE: aload_0
		// @2DF: getfield int game.C_100151_bc.field_102541_w
		// @2E2: bipush 8 (0x08)
		// @2E4: bipush -6 (0xFA)
		// @2E6: aload_0
		// @2E7: getfield int game.C_100151_bc.field_102537_l
		// @2EA: iadd
		// @2EB: bipush -10 (0xF6)
		// @2ED: iadd
		// @2EE: bipush 116 (0x74)
		// @2F0: invokevirtual game.C_100218_am.func_102524_a(int, int, int, int, byte)void
		// @2F3: aload_0
		// @2F4: dup
		// @2F5: getfield int game.C_100151_bc.field_102541_w
		// @2F8: bipush 35 (0x23)
		// @2FA: iadd
		// @2FB: putfield int game.C_100151_bc.field_102541_w
		// @2FE: iload #11
		// @300: ifeq @32E
		// @303: goto @307
		// @306: athrow
		// @307: aload_0
		// @308: getfield game.C_100218_am game.C_100151_bc.field_102948_Z
		// @30B: bipush 30 (0x1E)
		// @30D: aload_0
		// @30E: getfield int game.C_100151_bc.field_102541_w
		// @311: bipush 85 (0x55)
		// @313: aload_0
		// @314: getfield int game.C_100151_bc.field_102537_l
		// @317: bipush -95 (0xA1)
		// @319: iadd
		// @31A: bipush -104 (0x98)
		// @31C: invokevirtual game.C_100218_am.func_102524_a(int, int, int, int, byte)void
		// @31F: aload_0
		// @320: dup
		// @321: getfield int game.C_100151_bc.field_102541_w
		// @324: bipush 60 (0x3C)
		// @326: iadd
		// @327: putfield int game.C_100151_bc.field_102541_w
		// @32A: goto @32E
		// @32D: athrow
		// @32E: aload_0
		// @32F: getfield game.C_100218_am game.C_100151_bc.field_102934_fb
		// @332: ifnonnull @339
		// @335: goto @35C
		// @338: athrow
		// @339: aload_0
		// @33A: getfield game.C_100218_am game.C_100151_bc.field_102934_fb
		// @33D: bipush 30 (0x1E)
		// @33F: aload_0
		// @340: getfield int game.C_100151_bc.field_102541_w
		// @343: bipush 8 (0x08)
		// @345: aload_0
		// @346: getfield int game.C_100151_bc.field_102537_l
		// @349: bipush -16 (0xF0)
		// @34B: iadd
		// @34C: bipush 71 (0x47)
		// @34E: invokevirtual game.C_100218_am.func_102524_a(int, int, int, int, byte)void
		// @351: aload_0
		// @352: dup
		// @353: getfield int game.C_100151_bc.field_102541_w
		// @356: bipush 35 (0x23)
		// @358: iadd
		// @359: putfield int game.C_100151_bc.field_102541_w
		// @35C: aconst_null
		// @35D: aload_0
		// @35E: getfield game.C_100218_am game.C_100151_bc.field_102943_R
		// @361: if_acmpeq @3CB
		// @364: aload_0
		// @365: getfield boolean game.C_100151_bc.field_102938_W
		// @368: ifne @3A1
		// @36B: goto @36F
		// @36E: athrow
		// @36F: aload_0
		// @370: getfield boolean game.C_100151_bc.field_102947_X
		// @373: ifne @3A1
		// @376: goto @37A
		// @379: athrow
		// @37A: aload_0
		// @37B: getfield game.C_100218_am game.C_100151_bc.field_102943_R
		// @37E: bipush 20 (0x14)
		// @380: aload_0
		// @381: getfield int game.C_100151_bc.field_102541_w
		// @384: bipush 8 (0x08)
		// @386: bipush 40 (0x28)
		// @388: bipush 72 (0x48)
		// @38A: invokevirtual game.C_100218_am.func_102524_a(int, int, int, int, byte)void
		// @38D: aload_0
		// @38E: dup
		// @38F: getfield int game.C_100151_bc.field_102541_w
		// @392: bipush 25 (0x19)
		// @394: iadd
		// @395: putfield int game.C_100151_bc.field_102541_w
		// @398: iload #11
		// @39A: ifeq @3CB
		// @39D: goto @3A1
		// @3A0: athrow
		// @3A1: aload_0
		// @3A2: getfield game.C_100218_am game.C_100151_bc.field_102943_R
		// @3A5: bipush 30 (0x1E)
		// @3A7: aload_0
		// @3A8: getfield int game.C_100151_bc.field_102541_w
		// @3AB: bipush 8 (0x08)
		// @3AD: bipush -10 (0xF6)
		// @3AF: aload_0
		// @3B0: getfield int game.C_100151_bc.field_102537_l
		// @3B3: iadd
		// @3B4: bipush -6 (0xFA)
		// @3B6: iadd
		// @3B7: bipush 63 (0x3F)
		// @3B9: invokevirtual game.C_100218_am.func_102524_a(int, int, int, int, byte)void
		// @3BC: aload_0
		// @3BD: dup
		// @3BE: getfield int game.C_100151_bc.field_102541_w
		// @3C1: bipush 35 (0x23)
		// @3C3: iadd
		// @3C4: putfield int game.C_100151_bc.field_102541_w
		// @3C7: goto @3CB
		// @3CA: athrow
		// @3CB: aload_0
		// @3CC: iconst_3
		// @3CD: aload_0
		// @3CE: getfield int game.C_100151_bc.field_102541_w
		// @3D1: iadd
		// @3D2: iconst_0
		// @3D3: iconst_0
		// @3D4: aload_0
		// @3D5: getfield int game.C_100151_bc.field_102537_l
		// @3D8: bipush -104 (0x98)
		// @3DA: invokevirtual game.C_100151_bc.func_102524_a(int, int, int, int, byte)void
		// @3DD: aload_0
		// @3DE: aload_0
		// @3DF: getfield game.C_100218_am game.C_100151_bc.field_102948_Z
		// @3E2: iconst_1
		// @3E3: invokevirtual game.C_100151_bc.func_102561_b(game.C_100336_im, int)void
		// @3E6: aconst_null
		// @3E7: aload_0
		// @3E8: getfield game.C_100218_am game.C_100151_bc.field_102934_fb
		// @3EB: if_acmpeq @3FB
		// @3EE: aload_0
		// @3EF: aload_0
		// @3F0: getfield game.C_100218_am game.C_100151_bc.field_102934_fb
		// @3F3: iconst_1
		// @3F4: invokevirtual game.C_100151_bc.func_102561_b(game.C_100336_im, int)void
		// @3F7: goto @3FB
		// @3FA: athrow
		// @3FB: aload_0
		// @3FC: getfield game.C_100218_am game.C_100151_bc.field_102943_R
		// @3FF: ifnonnull @406
		// @402: goto @40F
		// @405: athrow
		// @406: aload_0
		// @407: aload_0
		// @408: getfield game.C_100218_am game.C_100151_bc.field_102943_R
		// @40B: iconst_1
		// @40C: invokevirtual game.C_100151_bc.func_102561_b(game.C_100336_im, int)void
		// @40F: goto @47E
		// @412: astore #6
		// @414: aload #6
		// @416: new java.lang.StringBuilder
		// @419: dup
		// @41A: invokespecial java.lang.StringBuilder.<init>()void
		// @41D: getstatic java.lang.String[] game.C_100151_bc.field_102935_gb
		// @420: bipush 13 (0x0D)
		// @422: aaload
		// @423: invokevirtual java.lang.StringBuilder.append(java.lang.String)java.lang.StringBuilder
		// @426: aload_1
		// @427: ifnull @433
		// @42A: getstatic java.lang.String[] game.C_100151_bc.field_102935_gb
		// @42D: iconst_2
		// @42E: aaload
		// @42F: goto @438
		// @432: athrow
		// @433: getstatic java.lang.String[] game.C_100151_bc.field_102935_gb
		// @436: iconst_3
		// @437: aaload
		// @438: invokevirtual java.lang.StringBuilder.append(java.lang.String)java.lang.StringBuilder
		// @43B: bipush 44 (0x2C)
		// @43D: invokevirtual java.lang.StringBuilder.append(char)java.lang.StringBuilder
		// @440: aload_2
		// @441: ifnull @44D
		// @444: getstatic java.lang.String[] game.C_100151_bc.field_102935_gb
		// @447: iconst_2
		// @448: aaload
		// @449: goto @452
		// @44C: athrow
		// @44D: getstatic java.lang.String[] game.C_100151_bc.field_102935_gb
		// @450: iconst_3
		// @451: aaload
		// @452: invokevirtual java.lang.StringBuilder.append(java.lang.String)java.lang.StringBuilder
		// @455: bipush 44 (0x2C)
		// @457: invokevirtual java.lang.StringBuilder.append(char)java.lang.StringBuilder
		// @45A: iload_3
		// @45B: invokevirtual java.lang.StringBuilder.append(boolean)java.lang.StringBuilder
		// @45E: bipush 44 (0x2C)
		// @460: invokevirtual java.lang.StringBuilder.append(char)java.lang.StringBuilder
		// @463: iload #4
		// @465: invokevirtual java.lang.StringBuilder.append(boolean)java.lang.StringBuilder
		// @468: bipush 44 (0x2C)
		// @46A: invokevirtual java.lang.StringBuilder.append(char)java.lang.StringBuilder
		// @46D: iload #5
		// @46F: invokevirtual java.lang.StringBuilder.append(boolean)java.lang.StringBuilder
		// @472: bipush 41 (0x29)
		// @474: invokevirtual java.lang.StringBuilder.append(char)java.lang.StringBuilder
		// @477: invokevirtual java.lang.StringBuilder.toString()java.lang.String
		// @47A: invokestatic game.C_100181_cf.func_105695_a(java.lang.Throwable, java.lang.String)game.C_100170_cm
		// @47D: athrow
		// @47E: return
	}
	
	static
	{
		// @00: bipush 16 (0x10)
		// @02: anewarray java.lang.String
		// @05: dup
		// @06: iconst_0
		// @07: ldc "$3g\u0017c"
		// @09: invokestatic game.C_100151_bc.func_102925_z(java.lang.String)char[]
		// @0C: invokestatic game.C_100151_bc.func_102923_z(char[])java.lang.String
		// @0F: aastore
		// @10: dup
		// @11: iconst_1
		// @12: ldc "$3g\u001e\nn"
		// @14: invokestatic game.C_100151_bc.func_102925_z(java.lang.String)char[]
		// @17: invokestatic game.C_100151_bc.func_102923_z(char[])java.lang.String
		// @1A: aastore
		// @1B: dup
		// @1C: iconst_2
		// @1D: ldc "=~gz6"
		// @1F: invokestatic game.C_100151_bc.func_102925_z(java.lang.String)char[]
		// @22: invokestatic game.C_100151_bc.func_102923_z(char[])java.lang.String
		// @25: aastore
		// @26: dup
		// @27: iconst_3
		// @28: ldc "(%%8"
		// @2A: invokestatic game.C_100151_bc.func_102925_z(java.lang.String)char[]
		// @2D: invokestatic game.C_100151_bc.func_102923_z(char[])java.lang.String
		// @30: aastore
		// @31: dup
		// @32: iconst_4
		// @33: ldc "$3g\u0019\nn"
		// @35: invokestatic game.C_100151_bc.func_102925_z(java.lang.String)char[]
		// @38: invokestatic game.C_100151_bc.func_102923_z(char[])java.lang.String
		// @3B: aastore
		// @3C: dup
		// @3D: iconst_5
		// @3E: ldc "$3g\u0013\nn"
		// @40: invokestatic game.C_100151_bc.func_102925_z(java.lang.String)char[]
		// @43: invokestatic game.C_100151_bc.func_102923_z(char[])java.lang.String
		// @46: aastore
		// @47: dup
		// @48: bipush 6 (0x06)
		// @4A: ldc "$3g\u001d\nn"
		// @4C: invokestatic game.C_100151_bc.func_102925_z(java.lang.String)char[]
		// @4F: invokestatic game.C_100151_bc.func_102923_z(char[])java.lang.String
		// @52: aastore
		// @53: dup
		// @54: bipush 7 (0x07)
		// @56: ldc "$3g\u0005\nn"
		// @58: invokestatic game.C_100151_bc.func_102925_z(java.lang.String)char[]
		// @5B: invokestatic game.C_100151_bc.func_102923_z(char[])java.lang.String
		// @5E: aastore
		// @5F: dup
		// @60: bipush 8 (0x08)
		// @62: ldc "$3g\u001c\nn"
		// @64: invokestatic game.C_100151_bc.func_102925_z(java.lang.String)char[]
		// @67: invokestatic game.C_100151_bc.func_102923_z(char[])java.lang.String
		// @6A: aastore
		// @6B: dup
		// @6C: bipush 9 (0x09)
		// @6E: ldc "3#,&%'=,"
		// @70: invokestatic game.C_100151_bc.func_102925_z(java.lang.String)char[]
		// @73: invokestatic game.C_100151_bc.func_102923_z(char[])java.lang.String
		// @76: aastore
		// @77: dup
		// @78: bipush 10 (0x0A)
		// @7A: ldc "$3g\u001a\nn"
		// @7C: invokestatic game.C_100151_bc.func_102925_z(java.lang.String)char[]
		// @7F: invokestatic game.C_100151_bc.func_102923_z(char[])java.lang.String
		// @82: aastore
		// @83: dup
		// @84: bipush 11 (0x0B)
		// @86: ldc "$3g\u0012\nn"
		// @88: invokestatic game.C_100151_bc.func_102925_z(java.lang.String)char[]
		// @8B: invokestatic game.C_100151_bc.func_102923_z(char[])java.lang.String
		// @8E: aastore
		// @8F: dup
		// @90: bipush 12 (0x0C)
		// @92: ldc "$3g\u001f\nn"
		// @94: invokestatic game.C_100151_bc.func_102925_z(java.lang.String)char[]
		// @97: invokestatic game.C_100151_bc.func_102923_z(char[])java.lang.String
		// @9A: aastore
		// @9B: dup
		// @9C: bipush 13 (0x0D)
		// @9E: ldc "$3gh\"(9=jc"
		// @A0: invokestatic game.C_100151_bc.func_102925_z(java.lang.String)char[]
		// @A3: invokestatic game.C_100151_bc.func_102923_z(char[])java.lang.String
		// @A6: aastore
		// @A7: dup
		// @A8: bipush 14 (0x0E)
		// @AA: ldc "$3g\u001b\nn"
		// @AC: invokestatic game.C_100151_bc.func_102925_z(java.lang.String)char[]
		// @AF: invokestatic game.C_100151_bc.func_102923_z(char[])java.lang.String
		// @B2: aastore
		// @B3: dup
		// @B4: bipush 15 (0x0F)
		// @B6: ldc "$3g\u0004\nn"
		// @B8: invokestatic game.C_100151_bc.func_102925_z(java.lang.String)char[]
		// @BB: invokestatic game.C_100151_bc.func_102923_z(char[])java.lang.String
		// @BE: aastore
		// @BF: putstatic java.lang.String[] game.C_100151_bc.field_102935_gb
		// @C2: iconst_1
		// @C3: putstatic int game.C_100151_bc.field_102940_Q
		// @C6: ldc "\u001f?<t*6 ,59f$&t)#p=1'*9'3k5?$1$(5i-$3\"i$*5#>;9\"pdt;*5('.f4&:l2q"
		// @C8: invokestatic game.C_100151_bc.func_102925_z(java.lang.String)char[]
		// @CB: invokestatic game.C_100151_bc.func_102923_z(char[])java.lang.String
		// @CE: putstatic java.lang.String game.C_100151_bc.field_102936_U
		// @D1: ldc "\u00051$19'p%1-2\u007f;=,.$st\u0002(&,&?#4"
		// @D3: invokestatic game.C_100151_bc.func_102925_z(java.lang.String)char[]
		// @D6: invokestatic game.C_100151_bc.func_102923_z(char[])java.lang.String
		// @D9: putstatic java.lang.String game.C_100151_bc.field_102941_P
		// @DC: iconst_0
		// @DD: putstatic int game.C_100151_bc.field_102931_db
		// @E0: return
	}
	
	private static char[] func_102925_z(String arg0)
	{
		// @00: aload_0
		// @01: invokevirtual java.lang.String.toCharArray()char[]
		// @04: dup
		// @05: arraylength
		// @06: iconst_2
		// @07: if_icmpge @13
		// @0A: dup
		// @0B: iconst_0
		// @0C: dup2
		// @0D: caload
		// @0E: bipush 75 (0x4B)
		// @10: ixor
		// @11: i2c
		// @12: castore
		// @13: areturn
	}
	
	private static String func_102923_z(char[] arg0)
	{
		// @00: aload_0
		// @01: dup
		// @02: arraylength
		// @03: swap
		// @04: iconst_0
		// @05: istore_1
		// @06: goto @4C
		// @09: dup
		// @0A: iload_1
		// @0B: dup2
		// @0C: caload
		// @0D: iload_1
		// @0E: iconst_5
		// @0F: irem
		// @10: tableswitch def: @44, for 0: @30, for 1: @35, for 2: @3A, for 3: @3F
		// @30: bipush 70 (0x46)
		// @32: goto @46
		// @35: bipush 80 (0x50)
		// @37: goto @46
		// @3A: bipush 73 (0x49)
		// @3C: goto @46
		// @3F: bipush 84 (0x54)
		// @41: goto @46
		// @44: bipush 75 (0x4B)
		// @46: ixor
		// @47: i2c
		// @48: castore
		// @49: iinc #1 +1
		// @4C: swap
		// @4D: dup_x1
		// @4E: iload_1
		// @4F: if_icmpgt @09
		// @52: new java.lang.String
		// @55: dup_x1
		// @56: swap
		// @57: invokespecial java.lang.String.<init>(char[])void
		// @5A: invokevirtual java.lang.String.intern()java.lang.String
		// @5D: areturn
	}
}
