package game;

final class C_100003_ga
{
	private int field_103528_o;
	static C_100105_eg field_103533_h;
	private int field_103523_A;
	static boolean field_103535_w;
	private int field_103537_u;
	private int field_103524_c;
	private int field_103543_z;
	private int field_103538_t;
	private float field_103534_i;
	static String field_103531_j;
	static int field_103544_y;
	private int field_103532_k;
	static String field_103527_n;
	private int field_103526_a;
	static String field_103540_r;
	static int field_103539_s;
	private int field_103530_m;
	private C_100232_od field_103518_f;
	private int field_103521_e;
	private int field_103536_v;
	static int field_103545_x;
	static C_100112_r field_103541_q;
	private int field_103519_g;
	private int field_103542_p;
	private boolean field_103520_d;
	private int field_103522_b;
	private int field_103529_l;
	private static final String[] field_103525_B;
	
	final C_100009_fg func_103510_a(int arg0)
	{
		// @00: aload_0
		// @01: getstatic int game.C_100270_mi.field_102282_cc
		// @04: putfield int game.C_100003_ga.field_103538_t
		// @07: aload_0
		// @08: getstatic int game.C_100165_sh.field_100769_s
		// @0B: putfield int game.C_100003_ga.field_103532_k
		// @0E: aload_0
		// @0F: getfield game.C_100232_od game.C_100003_ga.field_103518_f
		// @12: aload_0
		// @13: getfield int game.C_100003_ga.field_103542_p
		// @16: sipush 15597 (0x3CED)
		// @19: aload_0
		// @1A: getfield int game.C_100003_ga.field_103519_g
		// @1D: invokeinterface game.C_100232_od.func_106221_a(int, int, int)void
		// @22: iload_1
		// @23: bipush 87 (0x57)
		// @25: if_icmpge @39
		// @28: aconst_null
		// @29: checkcast game.C_100127_tl
		// @2C: bipush 53 (0x35)
		// @2E: bipush 65 (0x41)
		// @30: bipush -120 (0x88)
		// @32: invokestatic game.C_100003_ga.func_103517_a(game.C_100127_tl, int, byte, int)void
		// @35: goto @39
		// @38: athrow
		// @39: iconst_0
		// @3A: putstatic boolean game.C_100188_rj.field_105736_d
		// @3D: aload_0
		// @3E: getfield int game.C_100003_ga.field_103519_g
		// @41: iconst_0
		// @42: aload_0
		// @43: getfield int game.C_100003_ga.field_103542_p
		// @46: bipush -28 (0xE4)
		// @48: getstatic game.C_100201_qj game.C_100178_cg.field_105692_a
		// @4B: iconst_0
		// @4C: invokestatic game.C_100095_fe.func_103374_a(int, int, int, byte, game.C_100201_qj, int)game.C_100009_fg
		// @4F: astore_2
		// @50: aload_2
		// @51: ifnonnull @5E
		// @54: aload_0
		// @55: bipush 89 (0x59)
		// @57: invokevirtual game.C_100003_ga.func_103511_c(byte)void
		// @5A: goto @5E
		// @5D: athrow
		// @5E: aload_2
		// @5F: areturn
		// @60: astore_2
		// @61: aload_2
		// @62: new java.lang.StringBuilder
		// @65: dup
		// @66: invokespecial java.lang.StringBuilder.<init>()void
		// @69: getstatic java.lang.String[] game.C_100003_ga.field_103525_B
		// @6C: iconst_0
		// @6D: aaload
		// @6E: invokevirtual java.lang.StringBuilder.append(java.lang.String)java.lang.StringBuilder
		// @71: iload_1
		// @72: invokevirtual java.lang.StringBuilder.append(int)java.lang.StringBuilder
		// @75: bipush 41 (0x29)
		// @77: invokevirtual java.lang.StringBuilder.append(char)java.lang.StringBuilder
		// @7A: invokevirtual java.lang.StringBuilder.toString()java.lang.String
		// @7D: invokestatic game.C_100181_cf.func_105695_a(java.lang.Throwable, java.lang.String)game.C_100170_cm
		// @80: athrow
	}
	
	static final void func_103505_b(int arg0)
	{
		// @000: getstatic int game.SteelSentinels.field_105275_O
		// @003: istore_2
		// @004: iload_0
		// @005: bipush 12 (0x0C)
		// @007: if_icmpeq @01B
		// @00A: aconst_null
		// @00B: checkcast game.C_100127_tl
		// @00E: bipush -63 (0xC1)
		// @010: bipush -101 (0x9B)
		// @012: bipush 105 (0x69)
		// @014: invokestatic game.C_100003_ga.func_103517_a(game.C_100127_tl, int, byte, int)void
		// @017: goto @01B
		// @01A: athrow
		// @01B: aconst_null
		// @01C: getstatic game.C_100265_mh game.C_100127_tl.field_104948_b
		// @01F: if_acmpeq @02F
		// @022: getstatic game.C_100265_mh game.C_100127_tl.field_104948_b
		// @025: getfield boolean game.C_100265_mh.field_106600_K
		// @028: ifne @0BA
		// @02B: goto @02F
		// @02E: athrow
		// @02F: iconst_0
		// @030: getstatic game.C_100265_mh game.C_100127_tl.field_104948_b
		// @033: getfield game.C_100294_ki game.C_100265_mh.field_106591_B
		// @036: getfield int game.C_100294_ki.field_106985_o
		// @039: iconst_1
		// @03A: getstatic int game.C_100055_ed.field_104245_a
		// @03D: ishl
		// @03E: iand
		// @03F: if_icmpeq @057
		// @042: goto @046
		// @045: athrow
		// @046: getstatic java.lang.String[] game.C_100268_mk.field_106669_b
		// @049: bipush 12 (0x0C)
		// @04B: getstatic java.lang.String game.C_100105_eg.field_104741_h
		// @04E: aastore
		// @04F: iload_2
		// @050: ifeq @14A
		// @053: goto @057
		// @056: athrow
		// @057: getstatic game.C_100265_mh game.C_100127_tl.field_104948_b
		// @05A: getfield game.C_100294_ki game.C_100265_mh.field_106591_B
		// @05D: getfield int game.C_100294_ki.field_106985_o
		// @060: ifne @0A9
		// @063: goto @067
		// @066: athrow
		// @067: iconst_1
		// @068: getstatic game.C_100265_mh game.C_100127_tl.field_104948_b
		// @06B: getfield game.C_100294_ki game.C_100265_mh.field_106591_B
		// @06E: getfield int game.C_100294_ki.field_106999_q
		// @071: ishl
		// @072: iconst_1
		// @073: isub
		// @074: iconst_1
		// @075: getstatic int game.C_100055_ed.field_104245_a
		// @078: ishl
		// @079: getstatic game.C_100265_mh game.C_100127_tl.field_104948_b
		// @07C: getfield int game.C_100265_mh.field_106587_E
		// @07F: ior
		// @080: if_icmpeq @098
		// @083: goto @087
		// @086: athrow
		// @087: getstatic java.lang.String[] game.C_100268_mk.field_106669_b
		// @08A: bipush 12 (0x0C)
		// @08C: getstatic java.lang.String game.C_100081_ue.field_100668_s
		// @08F: aastore
		// @090: iload_2
		// @091: ifeq @14A
		// @094: goto @098
		// @097: athrow
		// @098: getstatic java.lang.String[] game.C_100268_mk.field_106669_b
		// @09B: bipush 12 (0x0C)
		// @09D: getstatic java.lang.String game.C_100025_he.field_103936_a
		// @0A0: aastore
		// @0A1: iload_2
		// @0A2: ifeq @14A
		// @0A5: goto @0A9
		// @0A8: athrow
		// @0A9: getstatic java.lang.String[] game.C_100268_mk.field_106669_b
		// @0AC: bipush 12 (0x0C)
		// @0AE: getstatic java.lang.String game.C_100015_wh.field_103784_b
		// @0B1: aastore
		// @0B2: iload_2
		// @0B3: ifeq @14A
		// @0B6: goto @0BA
		// @0B9: athrow
		// @0BA: iconst_m1
		// @0BB: iconst_1
		// @0BC: getstatic int game.C_100055_ed.field_104245_a
		// @0BF: ishl
		// @0C0: getstatic game.C_100265_mh game.C_100127_tl.field_104948_b
		// @0C3: getfield game.C_100294_ki game.C_100265_mh.field_106591_B
		// @0C6: getfield int game.C_100294_ki.field_106985_o
		// @0C9: iand
		// @0CA: iconst_m1
		// @0CB: ixor
		// @0CC: if_icmpeq @0E4
		// @0CF: goto @0D3
		// @0D2: athrow
		// @0D3: getstatic java.lang.String[] game.C_100268_mk.field_106669_b
		// @0D6: bipush 12 (0x0C)
		// @0D8: getstatic java.lang.String game.C_100090_l.field_104496_b
		// @0DB: aastore
		// @0DC: iload_2
		// @0DD: ifeq @14A
		// @0E0: goto @0E4
		// @0E3: athrow
		// @0E4: iconst_m1
		// @0E5: getstatic game.C_100265_mh game.C_100127_tl.field_104948_b
		// @0E8: getfield game.C_100294_ki game.C_100265_mh.field_106591_B
		// @0EB: getfield int game.C_100294_ki.field_106985_o
		// @0EE: iconst_m1
		// @0EF: ixor
		// @0F0: if_icmpne @13D
		// @0F3: goto @0F7
		// @0F6: athrow
		// @0F7: iconst_1
		// @0F8: getstatic int game.C_100055_ed.field_104245_a
		// @0FB: ishl
		// @0FC: getstatic game.C_100265_mh game.C_100127_tl.field_104948_b
		// @0FF: getfield int game.C_100265_mh.field_106587_E
		// @102: ior
		// @103: iconst_m1
		// @104: ixor
		// @105: iconst_1
		// @106: getstatic game.C_100265_mh game.C_100127_tl.field_104948_b
		// @109: getfield game.C_100294_ki game.C_100265_mh.field_106591_B
		// @10C: getfield int game.C_100294_ki.field_106999_q
		// @10F: ishl
		// @110: iconst_1
		// @111: isub
		// @112: iconst_m1
		// @113: ixor
		// @114: if_icmpne @12C
		// @117: goto @11B
		// @11A: athrow
		// @11B: getstatic java.lang.String[] game.C_100268_mk.field_106669_b
		// @11E: bipush 12 (0x0C)
		// @120: getstatic java.lang.String game.C_100102_w.field_104651_r
		// @123: aastore
		// @124: iload_2
		// @125: ifeq @14A
		// @128: goto @12C
		// @12B: athrow
		// @12C: getstatic java.lang.String[] game.C_100268_mk.field_106669_b
		// @12F: bipush 12 (0x0C)
		// @131: getstatic java.lang.String game.C_100089_fa.field_103725_d
		// @134: aastore
		// @135: iload_2
		// @136: ifeq @14A
		// @139: goto @13D
		// @13C: athrow
		// @13D: getstatic java.lang.String[] game.C_100268_mk.field_106669_b
		// @140: bipush 12 (0x0C)
		// @142: getstatic java.lang.String game.C_100033_gj.field_101929_bc
		// @145: aastore
		// @146: goto @14A
		// @149: athrow
		// @14A: goto @16F
		// @14D: astore_1
		// @14E: aload_1
		// @14F: new java.lang.StringBuilder
		// @152: dup
		// @153: invokespecial java.lang.StringBuilder.<init>()void
		// @156: getstatic java.lang.String[] game.C_100003_ga.field_103525_B
		// @159: bipush 9 (0x09)
		// @15B: aaload
		// @15C: invokevirtual java.lang.StringBuilder.append(java.lang.String)java.lang.StringBuilder
		// @15F: iload_0
		// @160: invokevirtual java.lang.StringBuilder.append(int)java.lang.StringBuilder
		// @163: bipush 41 (0x29)
		// @165: invokevirtual java.lang.StringBuilder.append(char)java.lang.StringBuilder
		// @168: invokevirtual java.lang.StringBuilder.toString()java.lang.String
		// @16B: invokestatic game.C_100181_cf.func_105695_a(java.lang.Throwable, java.lang.String)game.C_100170_cm
		// @16E: athrow
		// @16F: return
	}
	
	final void func_103516_a(boolean arg0)
	{
		// @00: aconst_null
		// @01: getstatic game.C_100009_fg game.C_100146_bf.field_105128_n
		// @04: if_acmpeq @08
		// @07: return
		// @08: iconst_0
		// @09: getstatic int game.C_100212_qc.field_105976_b
		// @0C: if_icmpge @13
		// @0F: goto @18
		// @12: athrow
		// @13: aload_0
		// @14: iconst_0
		// @15: putfield boolean game.C_100003_ga.field_103520_d
		// @18: aload_0
		// @19: getfield boolean game.C_100003_ga.field_103520_d
		// @1C: ifeq @23
		// @1F: goto @90
		// @22: athrow
		// @23: aload_0
		// @24: getfield int game.C_100003_ga.field_103522_b
		// @27: getstatic int game.C_100270_mi.field_102282_cc
		// @2A: if_icmple @45
		// @2D: aload_0
		// @2E: getfield int game.C_100003_ga.field_103522_b
		// @31: getstatic int game.C_100270_mi.field_102282_cc
		// @34: ineg
		// @35: iadd
		// @36: iconst_2
		// @37: idiv
		// @38: putstatic int game.C_100227_af.field_106166_d
		// @3B: getstatic int game.SteelSentinels.field_105275_O
		// @3E: ifeq @5B
		// @41: goto @45
		// @44: athrow
		// @45: iconst_m1
		// @46: aload_0
		// @47: getfield int game.C_100003_ga.field_103522_b
		// @4A: iconst_m1
		// @4B: ixor
		// @4C: if_icmple @5B
		// @4F: goto @53
		// @52: athrow
		// @53: iconst_0
		// @54: putstatic int game.C_100227_af.field_106166_d
		// @57: goto @5B
		// @5A: athrow
		// @5B: getstatic int game.C_100270_mi.field_102282_cc
		// @5E: aload_0
		// @5F: getfield int game.C_100003_ga.field_103530_m
		// @62: if_icmpne @7B
		// @65: getstatic int game.C_100165_sh.field_100769_s
		// @68: iconst_m1
		// @69: ixor
		// @6A: aload_0
		// @6B: getfield int game.C_100003_ga.field_103528_o
		// @6E: iconst_m1
		// @6F: ixor
		// @70: if_icmpne @7B
		// @73: goto @77
		// @76: athrow
		// @77: goto @8F
		// @7A: athrow
		// @7B: aload_0
		// @7C: getfield game.C_100232_od game.C_100003_ga.field_103518_f
		// @7F: aload_0
		// @80: getfield int game.C_100003_ga.field_103528_o
		// @83: sipush 15597 (0x3CED)
		// @86: aload_0
		// @87: getfield int game.C_100003_ga.field_103530_m
		// @8A: invokeinterface game.C_100232_od.func_106221_a(int, int, int)void
		// @8F: return
		// @90: iconst_m1
		// @91: aload_0
		// @92: dup
		// @93: getfield int game.C_100003_ga.field_103529_l
		// @96: iconst_1
		// @97: isub
		// @98: dup_x1
		// @99: putfield int game.C_100003_ga.field_103529_l
		// @9C: iconst_m1
		// @9D: ixor
		// @9E: if_icmple @A2
		// @A1: return
		// @A2: aload_0
		// @A3: aload_0
		// @A4: getfield int game.C_100003_ga.field_103524_c
		// @A7: putfield int game.C_100003_ga.field_103529_l
		// @AA: iload_1
		// @AB: iconst_1
		// @AC: if_icmpeq @B9
		// @AF: aload_0
		// @B0: bipush -66 (0xBE)
		// @B2: invokevirtual game.C_100003_ga.func_103511_c(byte)void
		// @B5: goto @B9
		// @B8: athrow
		// @B9: getstatic int game.C_100272_mn.field_102431_O
		// @BC: aload_0
		// @BD: getfield int game.C_100003_ga.field_103526_a
		// @C0: if_icmpge @C9
		// @C3: aload_0
		// @C4: iconst_0
		// @C5: putfield boolean game.C_100003_ga.field_103520_d
		// @C8: return
		// @C9: aload_0
		// @CA: bipush -119 (0x89)
		// @CC: invokespecial game.C_100003_ga.func_103508_a(byte)void
		// @CF: goto @F4
		// @D2: astore_2
		// @D3: aload_2
		// @D4: new java.lang.StringBuilder
		// @D7: dup
		// @D8: invokespecial java.lang.StringBuilder.<init>()void
		// @DB: getstatic java.lang.String[] game.C_100003_ga.field_103525_B
		// @DE: bipush 12 (0x0C)
		// @E0: aaload
		// @E1: invokevirtual java.lang.StringBuilder.append(java.lang.String)java.lang.StringBuilder
		// @E4: iload_1
		// @E5: invokevirtual java.lang.StringBuilder.append(boolean)java.lang.StringBuilder
		// @E8: bipush 41 (0x29)
		// @EA: invokevirtual java.lang.StringBuilder.append(char)java.lang.StringBuilder
		// @ED: invokevirtual java.lang.StringBuilder.toString()java.lang.String
		// @F0: invokestatic game.C_100181_cf.func_105695_a(java.lang.Throwable, java.lang.String)game.C_100170_cm
		// @F3: athrow
		// @F4: return
	}
	
	final void func_103511_c(byte arg0)
	{
		// @00: aload_0
		// @01: getfield game.C_100232_od game.C_100003_ga.field_103518_f
		// @04: aload_0
		// @05: getfield int game.C_100003_ga.field_103532_k
		// @08: iload_1
		// @09: sipush 15508 (0x3C94)
		// @0C: iadd
		// @0D: aload_0
		// @0E: getfield int game.C_100003_ga.field_103538_t
		// @11: invokeinterface game.C_100232_od.func_106221_a(int, int, int)void
		// @16: iload_1
		// @17: bipush 89 (0x59)
		// @19: if_icmpeq @22
		// @1C: aload_0
		// @1D: bipush 91 (0x5B)
		// @1F: putfield int game.C_100003_ga.field_103537_u
		// @22: goto @46
		// @25: astore_2
		// @26: aload_2
		// @27: new java.lang.StringBuilder
		// @2A: dup
		// @2B: invokespecial java.lang.StringBuilder.<init>()void
		// @2E: getstatic java.lang.String[] game.C_100003_ga.field_103525_B
		// @31: iconst_1
		// @32: aaload
		// @33: invokevirtual java.lang.StringBuilder.append(java.lang.String)java.lang.StringBuilder
		// @36: iload_1
		// @37: invokevirtual java.lang.StringBuilder.append(int)java.lang.StringBuilder
		// @3A: bipush 41 (0x29)
		// @3C: invokevirtual java.lang.StringBuilder.append(char)java.lang.StringBuilder
		// @3F: invokevirtual java.lang.StringBuilder.toString()java.lang.String
		// @42: invokestatic game.C_100181_cf.func_105695_a(java.lang.Throwable, java.lang.String)game.C_100170_cm
		// @45: athrow
		// @46: return
	}
	
	final void func_103513_a(int arg0, int arg1, int arg2)
	{
		// @00: iload_2
		// @01: iconst_m1
		// @02: if_icmpeq @0F
		// @05: aload_0
		// @06: bipush -118 (0x8A)
		// @08: putfield int game.C_100003_ga.field_103526_a
		// @0B: goto @0F
		// @0E: athrow
		// @0F: aload_0
		// @10: iload_3
		// @11: putfield int game.C_100003_ga.field_103537_u
		// @14: aload_0
		// @15: iload_1
		// @16: putfield int game.C_100003_ga.field_103522_b
		// @19: goto @51
		// @1C: astore #4
		// @1E: aload #4
		// @20: new java.lang.StringBuilder
		// @23: dup
		// @24: invokespecial java.lang.StringBuilder.<init>()void
		// @27: getstatic java.lang.String[] game.C_100003_ga.field_103525_B
		// @2A: iconst_2
		// @2B: aaload
		// @2C: invokevirtual java.lang.StringBuilder.append(java.lang.String)java.lang.StringBuilder
		// @2F: iload_1
		// @30: invokevirtual java.lang.StringBuilder.append(int)java.lang.StringBuilder
		// @33: bipush 44 (0x2C)
		// @35: invokevirtual java.lang.StringBuilder.append(char)java.lang.StringBuilder
		// @38: iload_2
		// @39: invokevirtual java.lang.StringBuilder.append(int)java.lang.StringBuilder
		// @3C: bipush 44 (0x2C)
		// @3E: invokevirtual java.lang.StringBuilder.append(char)java.lang.StringBuilder
		// @41: iload_3
		// @42: invokevirtual java.lang.StringBuilder.append(int)java.lang.StringBuilder
		// @45: bipush 41 (0x29)
		// @47: invokevirtual java.lang.StringBuilder.append(char)java.lang.StringBuilder
		// @4A: invokevirtual java.lang.StringBuilder.toString()java.lang.String
		// @4D: invokestatic game.C_100181_cf.func_105695_a(java.lang.Throwable, java.lang.String)game.C_100170_cm
		// @50: athrow
		// @51: return
	}
	
	public static void func_103514_b(boolean arg0)
	{
		// @00: aconst_null
		// @01: putstatic game.C_100112_r game.C_100003_ga.field_103541_q
		// @04: aconst_null
		// @05: putstatic java.lang.String game.C_100003_ga.field_103527_n
		// @08: aconst_null
		// @09: putstatic java.lang.String game.C_100003_ga.field_103540_r
		// @0C: iload_0
		// @0D: ifeq @19
		// @10: bipush -49 (0xCF)
		// @12: invokestatic game.C_100003_ga.func_103512_b(byte)void
		// @15: goto @19
		// @18: athrow
		// @19: aconst_null
		// @1A: putstatic game.C_100105_eg game.C_100003_ga.field_103533_h
		// @1D: aconst_null
		// @1E: putstatic java.lang.String game.C_100003_ga.field_103531_j
		// @21: goto @46
		// @24: astore_1
		// @25: aload_1
		// @26: new java.lang.StringBuilder
		// @29: dup
		// @2A: invokespecial java.lang.StringBuilder.<init>()void
		// @2D: getstatic java.lang.String[] game.C_100003_ga.field_103525_B
		// @30: bipush 11 (0x0B)
		// @32: aaload
		// @33: invokevirtual java.lang.StringBuilder.append(java.lang.String)java.lang.StringBuilder
		// @36: iload_0
		// @37: invokevirtual java.lang.StringBuilder.append(boolean)java.lang.StringBuilder
		// @3A: bipush 41 (0x29)
		// @3C: invokevirtual java.lang.StringBuilder.append(char)java.lang.StringBuilder
		// @3F: invokevirtual java.lang.StringBuilder.toString()java.lang.String
		// @42: invokestatic game.C_100181_cf.func_105695_a(java.lang.Throwable, java.lang.String)game.C_100170_cm
		// @45: athrow
		// @46: return
	}
	
	final boolean func_103515_c(int arg0)
	{
		// @00: iload_1
		// @01: sipush 13393 (0x3451)
		// @04: if_icmpeq @09
		// @07: iconst_1
		// @08: ireturn
		// @09: aload_0
		// @0A: getfield int game.C_100003_ga.field_103526_a
		// @0D: iconst_m1
		// @0E: ixor
		// @0F: getstatic int game.C_100272_mn.field_102431_O
		// @12: iconst_m1
		// @13: ixor
		// @14: if_icmplt @26
		// @17: getstatic int game.C_100212_qc.field_105976_b
		// @1A: ifle @26
		// @1D: goto @21
		// @20: athrow
		// @21: iconst_1
		// @22: goto @27
		// @25: athrow
		// @26: iconst_0
		// @27: ireturn
		// @28: astore_2
		// @29: aload_2
		// @2A: new java.lang.StringBuilder
		// @2D: dup
		// @2E: invokespecial java.lang.StringBuilder.<init>()void
		// @31: getstatic java.lang.String[] game.C_100003_ga.field_103525_B
		// @34: bipush 6 (0x06)
		// @36: aaload
		// @37: invokevirtual java.lang.StringBuilder.append(java.lang.String)java.lang.StringBuilder
		// @3A: iload_1
		// @3B: invokevirtual java.lang.StringBuilder.append(int)java.lang.StringBuilder
		// @3E: bipush 41 (0x29)
		// @40: invokevirtual java.lang.StringBuilder.append(char)java.lang.StringBuilder
		// @43: invokevirtual java.lang.StringBuilder.toString()java.lang.String
		// @46: invokestatic game.C_100181_cf.func_105695_a(java.lang.Throwable, java.lang.String)game.C_100170_cm
		// @49: athrow
	}
	
	private final void func_103508_a(byte arg0)
	{
		// @000: getstatic int game.SteelSentinels.field_105275_O
		// @003: istore #5
		// @005: iload_1
		// @006: bipush -31 (0xE1)
		// @008: if_icmplt @016
		// @00B: aconst_null
		// @00C: checkcast java.lang.String
		// @00F: putstatic java.lang.String game.C_100003_ga.field_103527_n
		// @012: goto @016
		// @015: athrow
		// @016: aload_0
		// @017: getfield int game.C_100003_ga.field_103522_b
		// @01A: istore_2
		// @01B: aload_0
		// @01C: getfield int game.C_100003_ga.field_103537_u
		// @01F: istore_3
		// @020: aload_0
		// @021: sipush 13393 (0x3451)
		// @024: invokevirtual game.C_100003_ga.func_103515_c(int)boolean
		// @027: ifne @030
		// @02A: aload_0
		// @02B: iconst_0
		// @02C: putfield boolean game.C_100003_ga.field_103520_d
		// @02F: return
		// @030: iload_3
		// @031: aload_0
		// @032: getfield int game.C_100003_ga.field_103536_v
		// @035: if_icmpgt @052
		// @038: aload_0
		// @039: getfield int game.C_100003_ga.field_103523_A
		// @03C: iload_3
		// @03D: if_icmpgt @048
		// @040: goto @044
		// @043: athrow
		// @044: goto @057
		// @047: athrow
		// @048: aload_0
		// @049: getfield int game.C_100003_ga.field_103523_A
		// @04C: istore_3
		// @04D: iload #5
		// @04F: ifeq @057
		// @052: aload_0
		// @053: getfield int game.C_100003_ga.field_103536_v
		// @056: istore_3
		// @057: aload_0
		// @058: getfield int game.C_100003_ga.field_103543_z
		// @05B: iload_2
		// @05C: if_icmpge @069
		// @05F: aload_0
		// @060: getfield int game.C_100003_ga.field_103543_z
		// @063: istore_2
		// @064: iload #5
		// @066: ifeq @082
		// @069: iload_2
		// @06A: iconst_m1
		// @06B: ixor
		// @06C: aload_0
		// @06D: getfield int game.C_100003_ga.field_103521_e
		// @070: iconst_m1
		// @071: ixor
		// @072: if_icmpgt @07D
		// @075: goto @079
		// @078: athrow
		// @079: goto @082
		// @07C: athrow
		// @07D: aload_0
		// @07E: getfield int game.C_100003_ga.field_103521_e
		// @081: istore_2
		// @082: aload_0
		// @083: getfield float game.C_100003_ga.field_103534_i
		// @086: fconst_0
		// @087: fcmpl
		// @088: ifle @0C1
		// @08B: ldc 0.5
		// @08D: aload_0
		// @08E: getfield float game.C_100003_ga.field_103534_i
		// @091: iload_3
		// @092: i2f
		// @093: fmul
		// @094: fadd
		// @095: f2i
		// @096: istore #4
		// @098: iload_2
		// @099: iload #4
		// @09B: if_icmpge @0AC
		// @09E: iload_2
		// @09F: i2f
		// @0A0: aload_0
		// @0A1: getfield float game.C_100003_ga.field_103534_i
		// @0A4: fdiv
		// @0A5: f2i
		// @0A6: istore_3
		// @0A7: iload #5
		// @0A9: ifeq @0C1
		// @0AC: iload #4
		// @0AE: iconst_m1
		// @0AF: ixor
		// @0B0: iload_2
		// @0B1: iconst_m1
		// @0B2: ixor
		// @0B3: if_icmpgt @0BE
		// @0B6: goto @0BA
		// @0B9: athrow
		// @0BA: goto @0C1
		// @0BD: athrow
		// @0BE: iload #4
		// @0C0: istore_2
		// @0C1: iload_2
		// @0C2: getstatic int game.C_100270_mi.field_102282_cc
		// @0C5: if_icmpne @0D7
		// @0C8: getstatic int game.C_100165_sh.field_100769_s
		// @0CB: iconst_m1
		// @0CC: ixor
		// @0CD: iload_3
		// @0CE: iconst_m1
		// @0CF: ixor
		// @0D0: if_icmpeq @0E9
		// @0D3: goto @0D7
		// @0D6: athrow
		// @0D7: aload_0
		// @0D8: getfield game.C_100232_od game.C_100003_ga.field_103518_f
		// @0DB: iload_3
		// @0DC: sipush 15597 (0x3CED)
		// @0DF: iload_2
		// @0E0: invokeinterface game.C_100232_od.func_106221_a(int, int, int)void
		// @0E5: goto @0E9
		// @0E8: athrow
		// @0E9: aload_0
		// @0EA: getfield int game.C_100003_ga.field_103522_b
		// @0ED: ifle @101
		// @0F0: aload_0
		// @0F1: getfield int game.C_100003_ga.field_103522_b
		// @0F4: getstatic int game.C_100270_mi.field_102282_cc
		// @0F7: isub
		// @0F8: iconst_2
		// @0F9: idiv
		// @0FA: putstatic int game.C_100227_af.field_106166_d
		// @0FD: goto @101
		// @100: athrow
		// @101: goto @126
		// @104: astore_2
		// @105: aload_2
		// @106: new java.lang.StringBuilder
		// @109: dup
		// @10A: invokespecial java.lang.StringBuilder.<init>()void
		// @10D: getstatic java.lang.String[] game.C_100003_ga.field_103525_B
		// @110: bipush 8 (0x08)
		// @112: aaload
		// @113: invokevirtual java.lang.StringBuilder.append(java.lang.String)java.lang.StringBuilder
		// @116: iload_1
		// @117: invokevirtual java.lang.StringBuilder.append(int)java.lang.StringBuilder
		// @11A: bipush 41 (0x29)
		// @11C: invokevirtual java.lang.StringBuilder.append(char)java.lang.StringBuilder
		// @11F: invokevirtual java.lang.StringBuilder.toString()java.lang.String
		// @122: invokestatic game.C_100181_cf.func_105695_a(java.lang.Throwable, java.lang.String)game.C_100170_cm
		// @125: athrow
		// @126: return
	}
	
	static final void func_103512_b(byte arg0)
	{
		// @00: getstatic game.C_100104_v game.C_100311_le.field_104714_w
		// @03: iconst_0
		// @04: putfield int game.C_100104_v.field_104697_m
		// @07: getstatic game.C_100104_v game.C_100311_le.field_104714_w
		// @0A: iconst_0
		// @0B: putfield int game.C_100104_v.field_104694_n
		// @0E: bipush -116 (0x8C)
		// @10: bipush 36 (0x24)
		// @12: iload_0
		// @13: isub
		// @14: bipush 40 (0x28)
		// @16: idiv
		// @17: idiv
		// @18: istore_1
		// @19: goto @3E
		// @1C: astore_1
		// @1D: aload_1
		// @1E: new java.lang.StringBuilder
		// @21: dup
		// @22: invokespecial java.lang.StringBuilder.<init>()void
		// @25: getstatic java.lang.String[] game.C_100003_ga.field_103525_B
		// @28: bipush 10 (0x0A)
		// @2A: aaload
		// @2B: invokevirtual java.lang.StringBuilder.append(java.lang.String)java.lang.StringBuilder
		// @2E: iload_0
		// @2F: invokevirtual java.lang.StringBuilder.append(int)java.lang.StringBuilder
		// @32: bipush 41 (0x29)
		// @34: invokevirtual java.lang.StringBuilder.append(char)java.lang.StringBuilder
		// @37: invokevirtual java.lang.StringBuilder.toString()java.lang.String
		// @3A: invokestatic game.C_100181_cf.func_105695_a(java.lang.Throwable, java.lang.String)game.C_100170_cm
		// @3D: athrow
		// @3E: return
	}
	
	static final void func_103517_a(C_100127_tl arg0, int arg1, byte arg2, int arg3)
	{
		// @00: iload_3
		// @01: putstatic int game.C_100165_sh.field_100779_k
		// @04: bipush 42 (0x2A)
		// @06: iload_2
		// @07: bipush -58 (0xC6)
		// @09: isub
		// @0A: bipush 60 (0x3C)
		// @0C: idiv
		// @0D: idiv
		// @0E: istore #4
		// @10: iload_1
		// @11: putstatic int game.C_100034_gi.field_104032_c
		// @14: aload_0
		// @15: putstatic game.C_100127_tl game.C_100071_va.field_101666_s
		// @18: goto @6B
		// @1B: astore #4
		// @1D: aload #4
		// @1F: new java.lang.StringBuilder
		// @22: dup
		// @23: invokespecial java.lang.StringBuilder.<init>()void
		// @26: getstatic java.lang.String[] game.C_100003_ga.field_103525_B
		// @29: bipush 13 (0x0D)
		// @2B: aaload
		// @2C: invokevirtual java.lang.StringBuilder.append(java.lang.String)java.lang.StringBuilder
		// @2F: aload_0
		// @30: ifnull @3C
		// @33: getstatic java.lang.String[] game.C_100003_ga.field_103525_B
		// @36: iconst_5
		// @37: aaload
		// @38: goto @41
		// @3B: athrow
		// @3C: getstatic java.lang.String[] game.C_100003_ga.field_103525_B
		// @3F: iconst_4
		// @40: aaload
		// @41: invokevirtual java.lang.StringBuilder.append(java.lang.String)java.lang.StringBuilder
		// @44: bipush 44 (0x2C)
		// @46: invokevirtual java.lang.StringBuilder.append(char)java.lang.StringBuilder
		// @49: iload_1
		// @4A: invokevirtual java.lang.StringBuilder.append(int)java.lang.StringBuilder
		// @4D: bipush 44 (0x2C)
		// @4F: invokevirtual java.lang.StringBuilder.append(char)java.lang.StringBuilder
		// @52: iload_2
		// @53: invokevirtual java.lang.StringBuilder.append(int)java.lang.StringBuilder
		// @56: bipush 44 (0x2C)
		// @58: invokevirtual java.lang.StringBuilder.append(char)java.lang.StringBuilder
		// @5B: iload_3
		// @5C: invokevirtual java.lang.StringBuilder.append(int)java.lang.StringBuilder
		// @5F: bipush 41 (0x29)
		// @61: invokevirtual java.lang.StringBuilder.append(char)java.lang.StringBuilder
		// @64: invokevirtual java.lang.StringBuilder.toString()java.lang.String
		// @67: invokestatic game.C_100181_cf.func_105695_a(java.lang.Throwable, java.lang.String)game.C_100170_cm
		// @6A: athrow
		// @6B: return
	}
	
	static final C_100107_u func_103506_a(String arg0, boolean arg1, String arg2, int arg3)
	{
		// @00: bipush 115 (0x73)
		// @02: bipush -40 (0xD8)
		// @04: iload_3
		// @05: isub
		// @06: bipush 34 (0x22)
		// @08: idiv
		// @09: irem
		// @0A: istore #4
		// @0C: lconst_0
		// @0D: lstore #5
		// @0F: aconst_null
		// @10: astore #7
		// @12: aload_2
		// @13: bipush 64 (0x40)
		// @15: invokevirtual java.lang.String.indexOf(int)int
		// @18: iconst_m1
		// @19: ixor
		// @1A: ifeq @23
		// @1D: aload_2
		// @1E: astore #7
		// @20: goto @2B
		// @23: bipush 97 (0x61)
		// @25: aload_2
		// @26: invokestatic game.C_100271_mj.func_103427_a(int, java.lang.CharSequence)long
		// @29: lstore #5
		// @2B: aload_0
		// @2C: lload #5
		// @2E: aload #7
		// @30: bipush -95 (0xA1)
		// @32: iload_1
		// @33: invokestatic game.C_100113_ek.func_104869_a(java.lang.String, long, java.lang.String, byte, boolean)game.C_100107_u
		// @36: areturn
		// @37: astore #4
		// @39: aload #4
		// @3B: new java.lang.StringBuilder
		// @3E: dup
		// @3F: invokespecial java.lang.StringBuilder.<init>()void
		// @42: getstatic java.lang.String[] game.C_100003_ga.field_103525_B
		// @45: iconst_3
		// @46: aaload
		// @47: invokevirtual java.lang.StringBuilder.append(java.lang.String)java.lang.StringBuilder
		// @4A: aload_0
		// @4B: ifnull @57
		// @4E: getstatic java.lang.String[] game.C_100003_ga.field_103525_B
		// @51: iconst_5
		// @52: aaload
		// @53: goto @5C
		// @56: athrow
		// @57: getstatic java.lang.String[] game.C_100003_ga.field_103525_B
		// @5A: iconst_4
		// @5B: aaload
		// @5C: invokevirtual java.lang.StringBuilder.append(java.lang.String)java.lang.StringBuilder
		// @5F: bipush 44 (0x2C)
		// @61: invokevirtual java.lang.StringBuilder.append(char)java.lang.StringBuilder
		// @64: iload_1
		// @65: invokevirtual java.lang.StringBuilder.append(boolean)java.lang.StringBuilder
		// @68: bipush 44 (0x2C)
		// @6A: invokevirtual java.lang.StringBuilder.append(char)java.lang.StringBuilder
		// @6D: aload_2
		// @6E: ifnull @7A
		// @71: getstatic java.lang.String[] game.C_100003_ga.field_103525_B
		// @74: iconst_5
		// @75: aaload
		// @76: goto @7F
		// @79: athrow
		// @7A: getstatic java.lang.String[] game.C_100003_ga.field_103525_B
		// @7D: iconst_4
		// @7E: aaload
		// @7F: invokevirtual java.lang.StringBuilder.append(java.lang.String)java.lang.StringBuilder
		// @82: bipush 44 (0x2C)
		// @84: invokevirtual java.lang.StringBuilder.append(char)java.lang.StringBuilder
		// @87: iload_3
		// @88: invokevirtual java.lang.StringBuilder.append(int)java.lang.StringBuilder
		// @8B: bipush 41 (0x29)
		// @8D: invokevirtual java.lang.StringBuilder.append(char)java.lang.StringBuilder
		// @90: invokevirtual java.lang.StringBuilder.toString()java.lang.String
		// @93: invokestatic game.C_100181_cf.func_105695_a(java.lang.Throwable, java.lang.String)game.C_100170_cm
		// @96: athrow
	}
	
	private C_100003_ga() throws Throwable
	{
		// @00: aload_0
		// @01: invokespecial java.lang.Object.<init>()void
		// @04: new java.lang.Error
		// @07: dup
		// @08: invokespecial java.lang.Error.<init>()void
		// @0B: athrow
		// @0C: astore_1
		// @0D: aload_1
		// @0E: getstatic java.lang.String[] game.C_100003_ga.field_103525_B
		// @11: bipush 7 (0x07)
		// @13: aaload
		// @14: invokestatic game.C_100181_cf.func_105695_a(java.lang.Throwable, java.lang.String)game.C_100170_cm
		// @17: athrow
	}
	
	static
	{
		// @00: bipush 14 (0x0E)
		// @02: anewarray java.lang.String
		// @05: dup
		// @06: iconst_0
		// @07: ldc "dn^\\z"
		// @09: invokestatic game.C_100003_ga.func_103509_z(java.lang.String)char[]
		// @0C: invokestatic game.C_100003_ga.func_103507_z(char[])java.lang.String
		// @0F: aastore
		// @10: dup
		// @11: iconst_1
		// @12: ldc "dn^Wz"
		// @14: invokestatic game.C_100003_ga.func_103509_z(java.lang.String)char[]
		// @17: invokestatic game.C_100003_ga.func_103507_z(char[])java.lang.String
		// @1A: aastore
		// @1B: dup
		// @1C: iconst_2
		// @1D: ldc "dn^[z"
		// @1F: invokestatic game.C_100003_ga.func_103509_z(java.lang.String)char[]
		// @22: invokestatic game.C_100003_ga.func_103507_z(char[])java.lang.String
		// @25: aastore
		// @26: dup
		// @27: iconst_3
		// @28: ldc "dn^Uz"
		// @2A: invokestatic game.C_100003_ga.func_103509_z(java.lang.String)char[]
		// @2D: invokestatic game.C_100003_ga.func_103507_z(char[])java.lang.String
		// @30: aastore
		// @31: dup
		// @32: iconst_4
		// @33: ldc "mz\u001cr"
		// @35: invokestatic game.C_100003_ga.func_103509_z(java.lang.String)char[]
		// @38: invokestatic game.C_100003_ga.func_103507_z(char[])java.lang.String
		// @3B: aastore
		// @3C: dup
		// @3D: iconst_5
		// @3E: ldc "x!^0/"
		// @40: invokestatic game.C_100003_ga.func_103509_z(java.lang.String)char[]
		// @43: invokestatic game.C_100003_ga.func_103507_z(char[])java.lang.String
		// @46: aastore
		// @47: dup
		// @48: bipush 6 (0x06)
		// @4A: ldc "dn^]z"
		// @4C: invokestatic game.C_100003_ga.func_103509_z(java.lang.String)char[]
		// @4F: invokestatic game.C_100003_ga.func_103507_z(char[])java.lang.String
		// @52: aastore
		// @53: dup
		// @54: bipush 7 (0x07)
		// @56: ldc "dn^\";mf\u0004 z*"
		// @58: invokestatic game.C_100003_ga.func_103509_z(java.lang.String)char[]
		// @5B: invokestatic game.C_100003_ga.func_103507_z(char[])java.lang.String
		// @5E: aastore
		// @5F: dup
		// @60: bipush 8 (0x08)
		// @62: ldc "dn^Tz"
		// @64: invokestatic game.C_100003_ga.func_103509_z(java.lang.String)char[]
		// @67: invokestatic game.C_100003_ga.func_103507_z(char[])java.lang.String
		// @6A: aastore
		// @6B: dup
		// @6C: bipush 9 (0x09)
		// @6E: ldc "dn^Xz"
		// @70: invokestatic game.C_100003_ga.func_103509_z(java.lang.String)char[]
		// @73: invokestatic game.C_100003_ga.func_103507_z(char[])java.lang.String
		// @76: aastore
		// @77: dup
		// @78: bipush 10 (0x0A)
		// @7A: ldc "dn^_z"
		// @7C: invokestatic game.C_100003_ga.func_103509_z(java.lang.String)char[]
		// @7F: invokestatic game.C_100003_ga.func_103507_z(char[])java.lang.String
		// @82: aastore
		// @83: dup
		// @84: bipush 11 (0x0B)
		// @86: ldc "dn^Vz"
		// @88: invokestatic game.C_100003_ga.func_103509_z(java.lang.String)char[]
		// @8B: invokestatic game.C_100003_ga.func_103507_z(char[])java.lang.String
		// @8E: aastore
		// @8F: dup
		// @90: bipush 12 (0x0C)
		// @92: ldc "dn^Zz"
		// @94: invokestatic game.C_100003_ga.func_103509_z(java.lang.String)char[]
		// @97: invokestatic game.C_100003_ga.func_103507_z(char[])java.lang.String
		// @9A: aastore
		// @9B: dup
		// @9C: bipush 13 (0x0D)
		// @9E: ldc "dn^Yz"
		// @A0: invokestatic game.C_100003_ga.func_103509_z(java.lang.String)char[]
		// @A3: invokestatic game.C_100003_ga.func_103507_z(char[])java.lang.String
		// @A6: aastore
		// @A7: putstatic java.lang.String[] game.C_100003_ga.field_103525_B
		// @AA: ldc "Nj\u001ek"
		// @AC: invokestatic game.C_100003_ga.func_103509_z(java.lang.String)char[]
		// @AF: invokestatic game.C_100003_ga.func_103507_z(char[])java.lang.String
		// @B2: putstatic java.lang.String game.C_100003_ga.field_103527_n
		// @B5: ldc "?*@ rkn\u0003>%j{\u0018z bx\u001e>&kjPl7rz\u0015m&#{\u001f>8lf\u001e0"
		// @B7: invokestatic game.C_100003_ga.func_103509_z(java.lang.String)char[]
		// @BA: invokestatic game.C_100003_ga.func_103507_z(char[])java.lang.String
		// @BD: putstatic java.lang.String game.C_100003_ga.field_103540_r
		// @C0: ldc "Sn\u0003m%l}\u0014$r"
		// @C2: invokestatic game.C_100003_ga.func_103509_z(java.lang.String)char[]
		// @C5: invokestatic game.C_100003_ga.func_103507_z(char[])java.lang.String
		// @C8: putstatic java.lang.String game.C_100003_ga.field_103531_j
		// @CB: iconst_0
		// @CC: putstatic int game.C_100003_ga.field_103545_x
		// @CF: return
	}
	
	private static char[] func_103509_z(String arg0)
	{
		// @00: aload_0
		// @01: invokevirtual java.lang.String.toCharArray()char[]
		// @04: dup
		// @05: arraylength
		// @06: iconst_2
		// @07: if_icmpge @13
		// @0A: dup
		// @0B: iconst_0
		// @0C: dup2
		// @0D: caload
		// @0E: bipush 82 (0x52)
		// @10: ixor
		// @11: i2c
		// @12: castore
		// @13: areturn
	}
	
	private static String func_103507_z(char[] arg0)
	{
		// @00: aload_0
		// @01: dup
		// @02: arraylength
		// @03: swap
		// @04: iconst_0
		// @05: istore_1
		// @06: goto @4B
		// @09: dup
		// @0A: iload_1
		// @0B: dup2
		// @0C: caload
		// @0D: iload_1
		// @0E: iconst_5
		// @0F: irem
		// @10: tableswitch def: @43, for 0: @30, for 1: @34, for 2: @39, for 3: @3E
		// @30: iconst_3
		// @31: goto @45
		// @34: bipush 15 (0x0F)
		// @36: goto @45
		// @39: bipush 112 (0x70)
		// @3B: goto @45
		// @3E: bipush 30 (0x1E)
		// @40: goto @45
		// @43: bipush 82 (0x52)
		// @45: ixor
		// @46: i2c
		// @47: castore
		// @48: iinc #1 +1
		// @4B: swap
		// @4C: dup_x1
		// @4D: iload_1
		// @4E: if_icmpgt @09
		// @51: new java.lang.String
		// @54: dup_x1
		// @55: swap
		// @56: invokespecial java.lang.String.<init>(char[])void
		// @59: invokevirtual java.lang.String.intern()java.lang.String
		// @5C: areturn
	}
}
