package game;

final class C_100247_pa
{
	static boolean field_106416_c;
	static boolean field_106414_d;
	static String field_106417_a;
	static boolean field_106415_b;
	private static final String[] field_106418_z;
	
	static final void func_106413_a(int arg0, C_100112_r arg1, C_100098_h arg2)
	{
		// @000: getstatic int game.SteelSentinels.field_105275_O
		// @003: istore #9
		// @005: getstatic int game.C_100062_dk.field_104280_g
		// @008: istore_3
		// @009: new game.C_100302_ka
		// @00C: dup
		// @00D: lconst_0
		// @00E: aconst_null
		// @00F: invokespecial game.C_100302_ka.<init>(long, game.C_100302_ka)void
		// @012: putstatic game.C_100302_ka game.C_100245_pf.field_106388_b
		// @015: aconst_null
		// @016: aload_2
		// @017: if_acmpne @025
		// @01A: iconst_1
		// @01B: getstatic java.lang.String[] game.C_100247_pa.field_106418_z
		// @01E: iconst_2
		// @01F: aaload
		// @020: aconst_null
		// @021: invokestatic game.C_100036_gg.func_103142_a(int, java.lang.String, java.lang.Throwable)void
		// @024: return
		// @025: aload_2
		// @026: iconst_0
		// @027: putfield int game.C_100098_h.field_104614_d
		// @02A: aload_2
		// @02B: iconst_0
		// @02C: putfield boolean game.C_100098_h.field_104621_i
		// @02F: new game.C_100283_ni
		// @032: dup
		// @033: iload_3
		// @034: aload_2
		// @035: aload_2
		// @036: invokespecial game.C_100283_ni.<init>(int, game.C_100098_h, game.C_100098_h)void
		// @039: putstatic game.C_100283_ni game.C_100027_hc.field_102603_X
		// @03C: new game.C_100137_bn
		// @03F: dup
		// @040: iload_3
		// @041: aload_2
		// @042: aload_2
		// @043: new game.C_100063_dj
		// @046: dup
		// @047: invokespecial game.C_100063_dj.<init>()void
		// @04A: invokespecial game.C_100137_bn.<init>(int, game.C_100098_h, game.C_100098_h, game.C_100199_qm)void
		// @04D: putstatic game.C_100137_bn game.C_100302_ka.field_101847_wb
		// @050: bipush 117 (0x75)
		// @052: invokestatic game.C_100133_tk.func_104994_b(int)game.C_100073_f
		// @055: astore #4
		// @057: aconst_null
		// @058: aload #4
		// @05A: if_acmpne @068
		// @05D: iconst_1
		// @05E: getstatic java.lang.String[] game.C_100247_pa.field_106418_z
		// @061: iconst_0
		// @062: aaload
		// @063: aconst_null
		// @064: invokestatic game.C_100036_gg.func_103142_a(int, java.lang.String, java.lang.Throwable)void
		// @067: return
		// @068: aload #4
		// @06A: iconst_m1
		// @06B: invokestatic game.C_100125_tm.func_100743_a(game.C_100073_f, int)void
		// @06E: ldc 4020342 (0x3d5876)
		// @070: ldc 8947848 (0x888888)
		// @072: ldc 65793 (0x10101)
		// @074: ldc 1513239 (0x171717)
		// @076: aconst_null
		// @077: ldc 1513239 (0x171717)
		// @079: iconst_0
		// @07A: ldc 65793 (0x10101)
		// @07C: ldc 2245737 (0x224469)
		// @07E: ldc 1127256 (0x113358)
		// @080: ldc 65793 (0x10101)
		// @082: iconst_0
		// @083: ldc 5138823 (0x4e6987)
		// @085: invokestatic game.C_100210_qa.func_101012_a(int, int, int, int, game.C_100112_r, int, int, int, int, int, int, int, int)game.C_100302_ka
		// @088: putstatic game.C_100302_ka game.C_100195_rc.field_105774_a
		// @08B: iconst_0
		// @08C: iconst_0
		// @08D: iconst_0
		// @08E: iconst_0
		// @08F: aload_1
		// @090: iconst_0
		// @091: iconst_0
		// @092: iconst_0
		// @093: iconst_0
		// @094: iconst_0
		// @095: iconst_0
		// @096: ldc 16764006 (0xffcc66)
		// @098: iconst_0
		// @099: invokestatic game.C_100210_qa.func_101012_a(int, int, int, int, game.C_100112_r, int, int, int, int, int, int, int, int)game.C_100302_ka
		// @09C: putstatic game.C_100302_ka game.C_100111_el.field_104868_i
		// @09F: iload_0
		// @0A0: bipush 74 (0x4A)
		// @0A2: if_icmpge @0A6
		// @0A5: return
		// @0A6: iconst_0
		// @0A7: iconst_0
		// @0A8: iconst_0
		// @0A9: iconst_0
		// @0AA: aload_1
		// @0AB: iconst_0
		// @0AC: iconst_0
		// @0AD: iconst_0
		// @0AE: iconst_0
		// @0AF: iconst_0
		// @0B0: iconst_0
		// @0B1: ldc 16777215 (0xffffff)
		// @0B3: iconst_0
		// @0B4: invokestatic game.C_100210_qa.func_101012_a(int, int, int, int, game.C_100112_r, int, int, int, int, int, int, int, int)game.C_100302_ka
		// @0B7: putstatic game.C_100302_ka game.C_100123_uc.field_104923_b
		// @0BA: getstatic int game.C_100196_rb.field_105819_e
		// @0BD: istore #5
		// @0BF: getstatic int game.C_100196_rb.field_105821_c
		// @0C2: istore #6
		// @0C4: getstatic int[] game.C_100196_rb.field_105818_d
		// @0C7: astore #7
		// @0C9: new game.C_100037_wb
		// @0CC: dup
		// @0CD: bipush 10 (0x0A)
		// @0CF: bipush 14 (0x0E)
		// @0D1: invokespecial game.C_100037_wb.<init>(int, int)void
		// @0D4: putstatic game.C_100037_wb game.C_100087_n.field_100705_y
		// @0D7: getstatic game.C_100037_wb game.C_100087_n.field_100705_y
		// @0DA: invokevirtual game.C_100037_wb.func_102379_d()void
		// @0DD: iconst_2
		// @0DE: istore #8
		// @0E0: bipush 7 (0x07)
		// @0E2: iload #8
		// @0E4: if_icmple @10C
		// @0E7: iload #8
		// @0E9: iconst_1
		// @0EA: iload #8
		// @0EC: iadd
		// @0ED: iload #8
		// @0EF: ldc 706274497 (0x2a18e4c1)
		// @0F1: ishl
		// @0F2: ineg
		// @0F3: bipush 14 (0x0E)
		// @0F5: iadd
		// @0F6: ldc 16777215 (0xffffff)
		// @0F8: invokestatic game.C_100196_rb.func_105778_a(int, int, int, int)void
		// @0FB: iinc #8 +1
		// @0FE: iload #9
		// @100: ifne @136
		// @103: iload #9
		// @105: ifeq @0E0
		// @108: goto @10C
		// @10B: athrow
		// @10C: aload #7
		// @10E: iload #5
		// @110: iload #6
		// @112: invokestatic game.C_100196_rb.func_105808_a(int[], int, int)void
		// @115: getstatic game.C_100302_ka game.C_100111_el.field_104868_i
		// @118: aload #4
		// @11A: getstatic game.C_100302_ka game.C_100195_rc.field_105774_a
		// @11D: sipush 20136 (0x4EA8)
		// @120: getstatic game.C_100302_ka game.C_100123_uc.field_104923_b
		// @123: invokestatic game.C_100127_tl.func_104939_a(game.C_100302_ka, game.C_100073_f, game.C_100302_ka, int, game.C_100302_ka)game.C_100033_gj
		// @126: putstatic game.C_100033_gj game.C_100336_im.field_102547_q
		// @129: getstatic game.C_100302_ka game.C_100245_pf.field_106388_b
		// @12C: new game.C_100202_qi
		// @12F: dup
		// @130: invokespecial game.C_100202_qi.<init>()void
		// @133: putfield game.C_100202_qi game.C_100302_ka.field_101891_Ob
		// @136: goto @18E
		// @139: astore_3
		// @13A: aload_3
		// @13B: new java.lang.StringBuilder
		// @13E: dup
		// @13F: invokespecial java.lang.StringBuilder.<init>()void
		// @142: getstatic java.lang.String[] game.C_100247_pa.field_106418_z
		// @145: iconst_3
		// @146: aaload
		// @147: invokevirtual java.lang.StringBuilder.append(java.lang.String)java.lang.StringBuilder
		// @14A: iload_0
		// @14B: invokevirtual java.lang.StringBuilder.append(int)java.lang.StringBuilder
		// @14E: bipush 44 (0x2C)
		// @150: invokevirtual java.lang.StringBuilder.append(char)java.lang.StringBuilder
		// @153: aload_1
		// @154: ifnull @160
		// @157: getstatic java.lang.String[] game.C_100247_pa.field_106418_z
		// @15A: iconst_4
		// @15B: aaload
		// @15C: goto @165
		// @15F: athrow
		// @160: getstatic java.lang.String[] game.C_100247_pa.field_106418_z
		// @163: iconst_1
		// @164: aaload
		// @165: invokevirtual java.lang.StringBuilder.append(java.lang.String)java.lang.StringBuilder
		// @168: bipush 44 (0x2C)
		// @16A: invokevirtual java.lang.StringBuilder.append(char)java.lang.StringBuilder
		// @16D: aload_2
		// @16E: ifnull @17A
		// @171: getstatic java.lang.String[] game.C_100247_pa.field_106418_z
		// @174: iconst_4
		// @175: aaload
		// @176: goto @17F
		// @179: athrow
		// @17A: getstatic java.lang.String[] game.C_100247_pa.field_106418_z
		// @17D: iconst_1
		// @17E: aaload
		// @17F: invokevirtual java.lang.StringBuilder.append(java.lang.String)java.lang.StringBuilder
		// @182: bipush 41 (0x29)
		// @184: invokevirtual java.lang.StringBuilder.append(char)java.lang.StringBuilder
		// @187: invokevirtual java.lang.StringBuilder.toString()java.lang.String
		// @18A: invokestatic game.C_100181_cf.func_105695_a(java.lang.Throwable, java.lang.String)game.C_100170_cm
		// @18D: athrow
		// @18E: return
	}
	
	static final void func_106411_a(byte arg0)
	{
		// @00: iload_0
		// @01: bipush 71 (0x47)
		// @03: if_icmpge @0E
		// @06: iconst_1
		// @07: putstatic boolean game.C_100247_pa.field_106416_c
		// @0A: goto @0E
		// @0D: athrow
		// @0E: getstatic java.lang.String game.C_100257_ln.field_106485_a
		// @11: aconst_null
		// @12: bipush -92 (0xA4)
		// @14: invokestatic game.C_100179_ch.func_100803_a(java.lang.String, java.lang.String, int)void
		// @17: goto @3B
		// @1A: astore_1
		// @1B: aload_1
		// @1C: new java.lang.StringBuilder
		// @1F: dup
		// @20: invokespecial java.lang.StringBuilder.<init>()void
		// @23: getstatic java.lang.String[] game.C_100247_pa.field_106418_z
		// @26: iconst_5
		// @27: aaload
		// @28: invokevirtual java.lang.StringBuilder.append(java.lang.String)java.lang.StringBuilder
		// @2B: iload_0
		// @2C: invokevirtual java.lang.StringBuilder.append(int)java.lang.StringBuilder
		// @2F: bipush 41 (0x29)
		// @31: invokevirtual java.lang.StringBuilder.append(char)java.lang.StringBuilder
		// @34: invokevirtual java.lang.StringBuilder.toString()java.lang.String
		// @37: invokestatic game.C_100181_cf.func_105695_a(java.lang.Throwable, java.lang.String)game.C_100170_cm
		// @3A: athrow
		// @3B: return
	}
	
	public static void func_106409_a(int arg0)
	{
		// @00: iload_0
		// @01: ifeq @0D
		// @04: bipush 50 (0x32)
		// @06: invokestatic game.C_100247_pa.func_106411_a(byte)void
		// @09: goto @0D
		// @0C: athrow
		// @0D: aconst_null
		// @0E: putstatic java.lang.String game.C_100247_pa.field_106417_a
		// @11: goto @36
		// @14: astore_1
		// @15: aload_1
		// @16: new java.lang.StringBuilder
		// @19: dup
		// @1A: invokespecial java.lang.StringBuilder.<init>()void
		// @1D: getstatic java.lang.String[] game.C_100247_pa.field_106418_z
		// @20: bipush 6 (0x06)
		// @22: aaload
		// @23: invokevirtual java.lang.StringBuilder.append(java.lang.String)java.lang.StringBuilder
		// @26: iload_0
		// @27: invokevirtual java.lang.StringBuilder.append(int)java.lang.StringBuilder
		// @2A: bipush 41 (0x29)
		// @2C: invokevirtual java.lang.StringBuilder.append(char)java.lang.StringBuilder
		// @2F: invokevirtual java.lang.StringBuilder.toString()java.lang.String
		// @32: invokestatic game.C_100181_cf.func_105695_a(java.lang.Throwable, java.lang.String)game.C_100170_cm
		// @35: athrow
		// @36: return
	}
	
	static
	{
		// @00: bipush 7 (0x07)
		// @02: anewarray java.lang.String
		// @05: dup
		// @06: iconst_0
		// @07: ldc "hZ+"
		// @09: invokestatic game.C_100247_pa.func_106412_z(java.lang.String)char[]
		// @0C: invokestatic game.C_100247_pa.func_106410_z(char[])java.lang.String
		// @0F: aastore
		// @10: dup
		// @11: iconst_1
		// @12: ldc "Wlu\u0017"
		// @14: invokestatic game.C_100247_pa.func_106412_z(java.lang.String)char[]
		// @17: invokestatic game.C_100247_pa.func_106410_z(char[])java.lang.String
		// @1A: aastore
		// @1B: dup
		// @1C: iconst_2
		// @1D: ldc "hZ("
		// @1F: invokestatic game.C_100247_pa.func_106412_z(java.lang.String)char[]
		// @22: invokestatic game.C_100247_pa.func_106410_z(char[])java.lang.String
		// @25: aastore
		// @26: dup
		// @27: iconst_3
		// @28: ldc "Ix78["
		// @2A: invokestatic game.C_100247_pa.func_106412_z(java.lang.String)char[]
		// @2D: invokestatic game.C_100247_pa.func_106410_z(char[])java.lang.String
		// @30: aastore
		// @31: dup
		// @32: iconst_4
		// @33: ldc "B77U\u000e"
		// @35: invokestatic game.C_100247_pa.func_106412_z(java.lang.String)char[]
		// @38: invokestatic game.C_100247_pa.func_106410_z(char[])java.lang.String
		// @3B: aastore
		// @3C: dup
		// @3D: iconst_5
		// @3E: ldc "Ix79["
		// @40: invokestatic game.C_100247_pa.func_106412_z(java.lang.String)char[]
		// @43: invokestatic game.C_100247_pa.func_106410_z(char[])java.lang.String
		// @46: aastore
		// @47: dup
		// @48: bipush 6 (0x06)
		// @4A: ldc "Ix7:["
		// @4C: invokestatic game.C_100247_pa.func_106412_z(java.lang.String)char[]
		// @4F: invokestatic game.C_100247_pa.func_106410_z(char[])java.lang.String
		// @52: aastore
		// @53: putstatic java.lang.String[] game.C_100247_pa.field_106418_z
		// @56: iconst_0
		// @57: putstatic boolean game.C_100247_pa.field_106414_d
		// @5A: ldc "`vl[\u001bXo|[\u001dVm9\u0002\u0016M9l\u0015\u001fVzr\u001e\u0017\u0019mq\u0012\u0000\u0019vi\u000f\u001aVw9\u001d\u001cK9l\u0008\u0016\u0017"
		// @5C: invokestatic game.C_100247_pa.func_106412_z(java.lang.String)char[]
		// @5F: invokestatic game.C_100247_pa.func_106410_z(char[])java.lang.String
		// @62: putstatic java.lang.String game.C_100247_pa.field_106417_a
		// @65: return
	}
	
	private static char[] func_106412_z(String arg0)
	{
		// @00: aload_0
		// @01: invokevirtual java.lang.String.toCharArray()char[]
		// @04: dup
		// @05: arraylength
		// @06: iconst_2
		// @07: if_icmpge @13
		// @0A: dup
		// @0B: iconst_0
		// @0C: dup2
		// @0D: caload
		// @0E: bipush 115 (0x73)
		// @10: ixor
		// @11: i2c
		// @12: castore
		// @13: areturn
	}
	
	private static String func_106410_z(char[] arg0)
	{
		// @00: aload_0
		// @01: dup
		// @02: arraylength
		// @03: swap
		// @04: iconst_0
		// @05: istore_1
		// @06: goto @4C
		// @09: dup
		// @0A: iload_1
		// @0B: dup2
		// @0C: caload
		// @0D: iload_1
		// @0E: iconst_5
		// @0F: irem
		// @10: tableswitch def: @44, for 0: @30, for 1: @35, for 2: @3A, for 3: @3F
		// @30: bipush 57 (0x39)
		// @32: goto @46
		// @35: bipush 25 (0x19)
		// @37: goto @46
		// @3A: bipush 25 (0x19)
		// @3C: goto @46
		// @3F: bipush 123 (0x7B)
		// @41: goto @46
		// @44: bipush 115 (0x73)
		// @46: ixor
		// @47: i2c
		// @48: castore
		// @49: iinc #1 +1
		// @4C: swap
		// @4D: dup_x1
		// @4E: iload_1
		// @4F: if_icmpgt @09
		// @52: new java.lang.String
		// @55: dup_x1
		// @56: swap
		// @57: invokespecial java.lang.String.<init>(char[])void
		// @5A: invokevirtual java.lang.String.intern()java.lang.String
		// @5D: areturn
	}
}
