package game;

final class C_100133_tk
{
	static String field_104995_f;
	static int[] field_104996_g;
	static int[] field_104999_b;
	static int[] field_105001_a;
	static char[] field_104997_d;
	static C_100202_qi field_105000_c;
	static int[] field_104998_e;
	private static final String[] field_105002_z;
	
	static final void func_104993_a(int arg0, int arg1)
	{
		// @00: getstatic int game.SteelSentinels.field_105275_O
		// @03: istore_3
		// @04: iconst_1
		// @05: bipush 89 (0x59)
		// @07: getstatic int game.C_100118_ub.field_102061_bc
		// @0A: iconst_0
		// @0B: getstatic int game.C_100321_hi.field_107224_l
		// @0E: iload_0
		// @0F: getstatic int game.C_100186_rl.field_105726_a
		// @12: invokestatic game.C_100051_ea.func_103297_a(boolean, byte, int, int, int, int, int)void
		// @15: iconst_0
		// @16: istore_2
		// @17: iload_1
		// @18: sipush 8224 (0x2020)
		// @1B: if_icmpeq @29
		// @1E: aconst_null
		// @1F: checkcast java.lang.String
		// @22: putstatic java.lang.String game.C_100133_tk.field_104995_f
		// @25: goto @29
		// @28: athrow
		// @29: getstatic int game.C_100186_rl.field_105726_a
		// @2C: iconst_m1
		// @2D: ixor
		// @2E: iload_2
		// @2F: iconst_m1
		// @30: ixor
		// @31: if_icmpge @4C
		// @34: getstatic int[] game.C_100219_an.field_100876_n
		// @37: iload_2
		// @38: iload_0
		// @39: ineg
		// @3A: isub
		// @3B: iload_2
		// @3C: iastore
		// @3D: iinc #2 +1
		// @40: iload_3
		// @41: ifne @61
		// @44: iload_3
		// @45: ifeq @29
		// @48: goto @4C
		// @4B: athrow
		// @4C: iconst_0
		// @4D: bipush 89 (0x59)
		// @4F: getstatic int game.C_100161_sd.field_105426_b
		// @52: iload_0
		// @53: getstatic int game.C_100255_pj.y
		// @56: iload_0
		// @57: iload_0
		// @58: iadd
		// @59: getstatic int game.C_100186_rl.field_105726_a
		// @5C: iload_0
		// @5D: iadd
		// @5E: invokestatic game.C_100051_ea.func_103297_a(boolean, byte, int, int, int, int, int)void
		// @61: getstatic int game.C_100186_rl.field_105726_a
		// @64: iload_0
		// @65: if_icmple @70
		// @68: iload_0
		// @69: putstatic int game.C_100186_rl.field_105726_a
		// @6C: goto @70
		// @6F: athrow
		// @70: goto @9D
		// @73: astore_2
		// @74: aload_2
		// @75: new java.lang.StringBuilder
		// @78: dup
		// @79: invokespecial java.lang.StringBuilder.<init>()void
		// @7C: getstatic java.lang.String[] game.C_100133_tk.field_105002_z
		// @7F: iconst_2
		// @80: aaload
		// @81: invokevirtual java.lang.StringBuilder.append(java.lang.String)java.lang.StringBuilder
		// @84: iload_0
		// @85: invokevirtual java.lang.StringBuilder.append(int)java.lang.StringBuilder
		// @88: bipush 44 (0x2C)
		// @8A: invokevirtual java.lang.StringBuilder.append(char)java.lang.StringBuilder
		// @8D: iload_1
		// @8E: invokevirtual java.lang.StringBuilder.append(int)java.lang.StringBuilder
		// @91: bipush 41 (0x29)
		// @93: invokevirtual java.lang.StringBuilder.append(char)java.lang.StringBuilder
		// @96: invokevirtual java.lang.StringBuilder.toString()java.lang.String
		// @99: invokestatic game.C_100181_cf.func_105695_a(java.lang.Throwable, java.lang.String)game.C_100170_cm
		// @9C: athrow
		// @9D: return
	}
	
	static final void func_104989_a(byte arg0, int arg1, long arg2)
	{
		// @00: getstatic game.C_100278_nd game.C_100115_ej.field_102043_Yb
		// @03: astore #4
		// @05: aload #4
		// @07: iload_1
		// @08: bipush 122 (0x7A)
		// @0A: invokevirtual game.C_100278_nd.func_101189_h(int, int)void
		// @0D: aload #4
		// @0F: dup
		// @10: getfield int game.C_100278_nd.field_101177_n
		// @13: iconst_1
		// @14: iadd
		// @15: putfield int game.C_100278_nd.field_101177_n
		// @18: aload #4
		// @1A: getfield int game.C_100278_nd.field_101177_n
		// @1D: istore #5
		// @1F: aload #4
		// @21: sipush 7838 (0x1E9E)
		// @24: bipush 7 (0x07)
		// @26: invokevirtual game.C_100278_nd.func_101169_f(int, int)void
		// @29: aload #4
		// @2B: iconst_0
		// @2C: lload_2
		// @2D: invokevirtual game.C_100278_nd.func_101131_a(int, long)void
		// @30: iload_0
		// @31: bipush 27 (0x1B)
		// @33: if_icmpeq @37
		// @36: return
		// @37: aload #4
		// @39: iload #5
		// @3B: ineg
		// @3C: aload #4
		// @3E: getfield int game.C_100278_nd.field_101177_n
		// @41: iadd
		// @42: bipush -128 (0x80)
		// @44: invokevirtual game.C_100278_nd.func_101139_c(int, byte)void
		// @47: goto @7F
		// @4A: astore #4
		// @4C: aload #4
		// @4E: new java.lang.StringBuilder
		// @51: dup
		// @52: invokespecial java.lang.StringBuilder.<init>()void
		// @55: getstatic java.lang.String[] game.C_100133_tk.field_105002_z
		// @58: iconst_0
		// @59: aaload
		// @5A: invokevirtual java.lang.StringBuilder.append(java.lang.String)java.lang.StringBuilder
		// @5D: iload_0
		// @5E: invokevirtual java.lang.StringBuilder.append(int)java.lang.StringBuilder
		// @61: bipush 44 (0x2C)
		// @63: invokevirtual java.lang.StringBuilder.append(char)java.lang.StringBuilder
		// @66: iload_1
		// @67: invokevirtual java.lang.StringBuilder.append(int)java.lang.StringBuilder
		// @6A: bipush 44 (0x2C)
		// @6C: invokevirtual java.lang.StringBuilder.append(char)java.lang.StringBuilder
		// @6F: lload_2
		// @70: invokevirtual java.lang.StringBuilder.append(long)java.lang.StringBuilder
		// @73: bipush 41 (0x29)
		// @75: invokevirtual java.lang.StringBuilder.append(char)java.lang.StringBuilder
		// @78: invokevirtual java.lang.StringBuilder.toString()java.lang.String
		// @7B: invokestatic game.C_100181_cf.func_105695_a(java.lang.Throwable, java.lang.String)game.C_100170_cm
		// @7E: athrow
		// @7F: return
	}
	
	static final long func_104988_c(int arg0)
	{
		// @00: iload_0
		// @01: bipush 8 (0x08)
		// @03: if_icmpge @0F
		// @06: bipush -7 (0xF9)
		// @08: invokestatic game.C_100133_tk.func_104990_a(int)void
		// @0B: goto @0F
		// @0E: athrow
		// @0F: getstatic long game.C_100236_on.field_100908_p
		// @12: lneg
		// @13: bipush -44 (0xD4)
		// @15: invokestatic game.C_100198_qn.func_105828_a(byte)long
		// @18: ladd
		// @19: lreturn
		// @1A: astore_1
		// @1B: aload_1
		// @1C: new java.lang.StringBuilder
		// @1F: dup
		// @20: invokespecial java.lang.StringBuilder.<init>()void
		// @23: getstatic java.lang.String[] game.C_100133_tk.field_105002_z
		// @26: iconst_4
		// @27: aaload
		// @28: invokevirtual java.lang.StringBuilder.append(java.lang.String)java.lang.StringBuilder
		// @2B: iload_0
		// @2C: invokevirtual java.lang.StringBuilder.append(int)java.lang.StringBuilder
		// @2F: bipush 41 (0x29)
		// @31: invokevirtual java.lang.StringBuilder.append(char)java.lang.StringBuilder
		// @34: invokevirtual java.lang.StringBuilder.toString()java.lang.String
		// @37: invokestatic game.C_100181_cf.func_105695_a(java.lang.Throwable, java.lang.String)game.C_100170_cm
		// @3A: athrow
	}
	
	public final String toString()
	{
		// @00: new java.lang.IllegalStateException
		// @03: dup
		// @04: invokespecial java.lang.IllegalStateException.<init>()void
		// @07: athrow
		// @08: astore_1
		// @09: aload_1
		// @0A: getstatic java.lang.String[] game.C_100133_tk.field_105002_z
		// @0D: iconst_3
		// @0E: aaload
		// @0F: invokestatic game.C_100181_cf.func_105695_a(java.lang.Throwable, java.lang.String)game.C_100170_cm
		// @12: athrow
	}
	
	public static void func_104990_a(int arg0)
	{
		// @00: aconst_null
		// @01: putstatic game.C_100202_qi game.C_100133_tk.field_105000_c
		// @04: aconst_null
		// @05: putstatic java.lang.String game.C_100133_tk.field_104995_f
		// @08: aconst_null
		// @09: putstatic int[] game.C_100133_tk.field_104999_b
		// @0C: iload_0
		// @0D: sipush 339 (0x0153)
		// @10: if_icmpeq @1E
		// @13: bipush -105 (0x97)
		// @15: bipush 36 (0x24)
		// @17: invokestatic game.C_100133_tk.func_104993_a(int, int)void
		// @1A: goto @1E
		// @1D: athrow
		// @1E: aconst_null
		// @1F: putstatic char[] game.C_100133_tk.field_104997_d
		// @22: aconst_null
		// @23: putstatic int[] game.C_100133_tk.field_104996_g
		// @26: aconst_null
		// @27: putstatic int[] game.C_100133_tk.field_104998_e
		// @2A: aconst_null
		// @2B: putstatic int[] game.C_100133_tk.field_105001_a
		// @2E: goto @52
		// @31: astore_1
		// @32: aload_1
		// @33: new java.lang.StringBuilder
		// @36: dup
		// @37: invokespecial java.lang.StringBuilder.<init>()void
		// @3A: getstatic java.lang.String[] game.C_100133_tk.field_105002_z
		// @3D: iconst_1
		// @3E: aaload
		// @3F: invokevirtual java.lang.StringBuilder.append(java.lang.String)java.lang.StringBuilder
		// @42: iload_0
		// @43: invokevirtual java.lang.StringBuilder.append(int)java.lang.StringBuilder
		// @46: bipush 41 (0x29)
		// @48: invokevirtual java.lang.StringBuilder.append(char)java.lang.StringBuilder
		// @4B: invokevirtual java.lang.StringBuilder.toString()java.lang.String
		// @4E: invokestatic game.C_100181_cf.func_105695_a(java.lang.Throwable, java.lang.String)game.C_100170_cm
		// @51: athrow
		// @52: return
	}
	
	static final C_100073_f func_104994_b(int arg0)
	{
		// @00: getstatic int game.SteelSentinels.field_105275_O
		// @03: istore_3
		// @04: iload_0
		// @05: bipush 109 (0x6D)
		// @07: if_icmpgt @0F
		// @0A: aconst_null
		// @0B: checkcast game.C_100073_f
		// @0E: areturn
		// @0F: iconst_0
		// @10: istore_1
		// @11: getstatic game.C_100283_ni game.C_100027_hc.field_102603_X
		// @14: iload_1
		// @15: bipush 6 (0x06)
		// @17: invokevirtual game.C_100283_ni.func_106754_a(int, int)game.C_100073_f
		// @1A: astore_2
		// @1B: aload_2
		// @1C: getfield boolean game.C_100073_f.field_101715_t
		// @1F: ifeq @2C
		// @22: iload_3
		// @23: ifne @2F
		// @26: goto @2A
		// @29: athrow
		// @2A: aload_2
		// @2B: areturn
		// @2C: iinc #1 +1
		// @2F: goto @11
		// @32: astore_1
		// @33: aconst_null
		// @34: areturn
		// @35: astore_1
		// @36: aload_1
		// @37: new java.lang.StringBuilder
		// @3A: dup
		// @3B: invokespecial java.lang.StringBuilder.<init>()void
		// @3E: getstatic java.lang.String[] game.C_100133_tk.field_105002_z
		// @41: iconst_5
		// @42: aaload
		// @43: invokevirtual java.lang.StringBuilder.append(java.lang.String)java.lang.StringBuilder
		// @46: iload_0
		// @47: invokevirtual java.lang.StringBuilder.append(int)java.lang.StringBuilder
		// @4A: bipush 41 (0x29)
		// @4C: invokevirtual java.lang.StringBuilder.append(char)java.lang.StringBuilder
		// @4F: invokevirtual java.lang.StringBuilder.toString()java.lang.String
		// @52: invokestatic game.C_100181_cf.func_105695_a(java.lang.Throwable, java.lang.String)game.C_100170_cm
		// @55: athrow
	}
	
	static
	{
		// @000: bipush 6 (0x06)
		// @002: anewarray java.lang.String
		// @005: dup
		// @006: iconst_0
		// @007: ldc "\u001b1@\u000bH"
		// @009: invokestatic game.C_100133_tk.func_104992_z(java.lang.String)char[]
		// @00C: invokestatic game.C_100133_tk.func_104991_z(char[])java.lang.String
		// @00F: aastore
		// @010: dup
		// @011: iconst_1
		// @012: ldc "\u001b1@\u000fH"
		// @014: invokestatic game.C_100133_tk.func_104992_z(java.lang.String)char[]
		// @017: invokestatic game.C_100133_tk.func_104991_z(char[])java.lang.String
		// @01A: aastore
		// @01B: dup
		// @01C: iconst_2
		// @01D: ldc "\u001b1@\nH"
		// @01F: invokestatic game.C_100133_tk.func_104992_z(java.lang.String)char[]
		// @022: invokestatic game.C_100133_tk.func_104991_z(char[])java.lang.String
		// @025: aastore
		// @026: dup
		// @027: iconst_3
		// @028: ldc "\u001b1@:\u000f<.\u001c'\u000e\u0008rG"
		// @02A: invokestatic game.C_100133_tk.func_104992_z(java.lang.String)char[]
		// @02D: invokestatic game.C_100133_tk.func_104991_z(char[])java.lang.String
		// @030: aastore
		// @031: dup
		// @032: iconst_4
		// @033: ldc "\u001b1@\rH"
		// @035: invokestatic game.C_100133_tk.func_104992_z(java.lang.String)char[]
		// @038: invokestatic game.C_100133_tk.func_104991_z(char[])java.lang.String
		// @03B: aastore
		// @03C: dup
		// @03D: iconst_5
		// @03E: ldc "\u001b1@\u000cH"
		// @040: invokestatic game.C_100133_tk.func_104992_z(java.lang.String)char[]
		// @043: invokestatic game.C_100133_tk.func_104991_z(char[])java.lang.String
		// @046: aastore
		// @047: putstatic java.lang.String[] game.C_100133_tk.field_105002_z
		// @04A: bipush 32 (0x20)
		// @04C: newarray int[]
		// @04E: putstatic int[] game.C_100133_tk.field_104996_g
		// @051: bipush 12 (0x0C)
		// @053: newarray int[]
		// @055: dup
		// @056: iconst_0
		// @057: ldc 65535 (0xffff)
		// @059: iastore
		// @05A: dup
		// @05B: iconst_1
		// @05C: ldc 15614976 (0xee4400)
		// @05E: iastore
		// @05F: dup
		// @060: iconst_2
		// @061: ldc 65280 (0xff00)
		// @063: iastore
		// @064: dup
		// @065: iconst_3
		// @066: ldc 6711039 (0x6666ff)
		// @068: iastore
		// @069: dup
		// @06A: iconst_4
		// @06B: ldc 16776960 (0xffff00)
		// @06D: iastore
		// @06E: dup
		// @06F: iconst_5
		// @070: ldc 16711935 (0xff00ff)
		// @072: iastore
		// @073: dup
		// @074: bipush 6 (0x06)
		// @076: ldc 2236962 (0x222222)
		// @078: iastore
		// @079: dup
		// @07A: bipush 7 (0x07)
		// @07C: ldc 16777215 (0xffffff)
		// @07E: iastore
		// @07F: dup
		// @080: bipush 8 (0x08)
		// @082: ldc 16737894 (0xff6666)
		// @084: iastore
		// @085: dup
		// @086: bipush 9 (0x09)
		// @088: ldc 6750054 (0x66ff66)
		// @08A: iastore
		// @08B: dup
		// @08C: bipush 10 (0x0A)
		// @08E: ldc 16777062 (0xffff66)
		// @090: iastore
		// @091: dup
		// @092: bipush 11 (0x0B)
		// @094: ldc 16738047 (0xff66ff)
		// @096: iastore
		// @097: putstatic int[] game.C_100133_tk.field_104999_b
		// @09A: bipush 32 (0x20)
		// @09C: newarray char[]
		// @09E: dup
		// @09F: iconst_0
		// @0A0: sipush 8364 (0x20AC)
		// @0A3: castore
		// @0A4: dup
		// @0A5: iconst_1
		// @0A6: iconst_0
		// @0A7: castore
		// @0A8: dup
		// @0A9: iconst_2
		// @0AA: sipush 8218 (0x201A)
		// @0AD: castore
		// @0AE: dup
		// @0AF: iconst_3
		// @0B0: sipush 402 (0x0192)
		// @0B3: castore
		// @0B4: dup
		// @0B5: iconst_4
		// @0B6: sipush 8222 (0x201E)
		// @0B9: castore
		// @0BA: dup
		// @0BB: iconst_5
		// @0BC: sipush 8230 (0x2026)
		// @0BF: castore
		// @0C0: dup
		// @0C1: bipush 6 (0x06)
		// @0C3: sipush 8224 (0x2020)
		// @0C6: castore
		// @0C7: dup
		// @0C8: bipush 7 (0x07)
		// @0CA: sipush 8225 (0x2021)
		// @0CD: castore
		// @0CE: dup
		// @0CF: bipush 8 (0x08)
		// @0D1: sipush 710 (0x02C6)
		// @0D4: castore
		// @0D5: dup
		// @0D6: bipush 9 (0x09)
		// @0D8: sipush 8240 (0x2030)
		// @0DB: castore
		// @0DC: dup
		// @0DD: bipush 10 (0x0A)
		// @0DF: sipush 352 (0x0160)
		// @0E2: castore
		// @0E3: dup
		// @0E4: bipush 11 (0x0B)
		// @0E6: sipush 8249 (0x2039)
		// @0E9: castore
		// @0EA: dup
		// @0EB: bipush 12 (0x0C)
		// @0ED: sipush 338 (0x0152)
		// @0F0: castore
		// @0F1: dup
		// @0F2: bipush 13 (0x0D)
		// @0F4: iconst_0
		// @0F5: castore
		// @0F6: dup
		// @0F7: bipush 14 (0x0E)
		// @0F9: sipush 381 (0x017D)
		// @0FC: castore
		// @0FD: dup
		// @0FE: bipush 15 (0x0F)
		// @100: iconst_0
		// @101: castore
		// @102: dup
		// @103: bipush 16 (0x10)
		// @105: iconst_0
		// @106: castore
		// @107: dup
		// @108: bipush 17 (0x11)
		// @10A: sipush 8216 (0x2018)
		// @10D: castore
		// @10E: dup
		// @10F: bipush 18 (0x12)
		// @111: sipush 8217 (0x2019)
		// @114: castore
		// @115: dup
		// @116: bipush 19 (0x13)
		// @118: sipush 8220 (0x201C)
		// @11B: castore
		// @11C: dup
		// @11D: bipush 20 (0x14)
		// @11F: sipush 8221 (0x201D)
		// @122: castore
		// @123: dup
		// @124: bipush 21 (0x15)
		// @126: sipush 8226 (0x2022)
		// @129: castore
		// @12A: dup
		// @12B: bipush 22 (0x16)
		// @12D: sipush 8211 (0x2013)
		// @130: castore
		// @131: dup
		// @132: bipush 23 (0x17)
		// @134: sipush 8212 (0x2014)
		// @137: castore
		// @138: dup
		// @139: bipush 24 (0x18)
		// @13B: sipush 732 (0x02DC)
		// @13E: castore
		// @13F: dup
		// @140: bipush 25 (0x19)
		// @142: sipush 8482 (0x2122)
		// @145: castore
		// @146: dup
		// @147: bipush 26 (0x1A)
		// @149: sipush 353 (0x0161)
		// @14C: castore
		// @14D: dup
		// @14E: bipush 27 (0x1B)
		// @150: sipush 8250 (0x203A)
		// @153: castore
		// @154: dup
		// @155: bipush 28 (0x1C)
		// @157: sipush 339 (0x0153)
		// @15A: castore
		// @15B: dup
		// @15C: bipush 29 (0x1D)
		// @15E: iconst_0
		// @15F: castore
		// @160: dup
		// @161: bipush 30 (0x1E)
		// @163: sipush 382 (0x017E)
		// @166: castore
		// @167: dup
		// @168: bipush 31 (0x1F)
		// @16A: sipush 376 (0x0178)
		// @16D: castore
		// @16E: putstatic char[] game.C_100133_tk.field_104997_d
		// @171: ldc "*\t-nMO9\u000f \u0003\n6N:\u0008\u0006)N\"\t\u0001?"
		// @173: invokestatic game.C_100133_tk.func_104992_z(java.lang.String)char[]
		// @176: invokestatic game.C_100133_tk.func_104991_z(char[])java.lang.String
		// @179: putstatic java.lang.String game.C_100133_tk.field_104995_f
		// @17C: sipush 8192 (0x2000)
		// @17F: newarray int[]
		// @181: putstatic int[] game.C_100133_tk.field_105001_a
		// @184: getstatic int[] game.C_100133_tk.field_104999_b
		// @187: putstatic int[] game.C_100133_tk.field_104998_e
		// @18A: new game.C_100202_qi
		// @18D: dup
		// @18E: invokespecial game.C_100202_qi.<init>()void
		// @191: putstatic game.C_100202_qi game.C_100133_tk.field_105000_c
		// @194: return
	}
	
	private static char[] func_104992_z(String arg0)
	{
		// @00: aload_0
		// @01: invokevirtual java.lang.String.toCharArray()char[]
		// @04: dup
		// @05: arraylength
		// @06: iconst_2
		// @07: if_icmpge @13
		// @0A: dup
		// @0B: iconst_0
		// @0C: dup2
		// @0D: caload
		// @0E: bipush 96 (0x60)
		// @10: ixor
		// @11: i2c
		// @12: castore
		// @13: areturn
	}
	
	private static String func_104991_z(char[] arg0)
	{
		// @00: aload_0
		// @01: dup
		// @02: arraylength
		// @03: swap
		// @04: iconst_0
		// @05: istore_1
		// @06: goto @4C
		// @09: dup
		// @0A: iload_1
		// @0B: dup2
		// @0C: caload
		// @0D: iload_1
		// @0E: iconst_5
		// @0F: irem
		// @10: tableswitch def: @44, for 0: @30, for 1: @35, for 2: @3A, for 3: @3F
		// @30: bipush 111 (0x6F)
		// @32: goto @46
		// @35: bipush 90 (0x5A)
		// @37: goto @46
		// @3A: bipush 110 (0x6E)
		// @3C: goto @46
		// @3F: bipush 78 (0x4E)
		// @41: goto @46
		// @44: bipush 96 (0x60)
		// @46: ixor
		// @47: i2c
		// @48: castore
		// @49: iinc #1 +1
		// @4C: swap
		// @4D: dup_x1
		// @4E: iload_1
		// @4F: if_icmpgt @09
		// @52: new java.lang.String
		// @55: dup_x1
		// @56: swap
		// @57: invokespecial java.lang.String.<init>(char[])void
		// @5A: invokevirtual java.lang.String.intern()java.lang.String
		// @5D: areturn
	}
}
