package game;

final class C_100029_gn extends C_100030_gm
{
	static C_100193_re field_103368_S;
	static String field_103367_P;
	static String field_103364_T;
	static String field_103370_O;
	static boolean field_103363_U;
	static int field_103366_Q;
	private C_100202_qi field_103369_R;
	private static final String[] field_103365_V;
	
	static final boolean func_103356_l(int arg0)
	{
		// @000: getstatic int game.SteelSentinels.field_105275_O
		// @003: istore_3
		// @004: iconst_0
		// @005: istore_1
		// @006: iload_1
		// @007: iconst_m1
		// @008: ixor
		// @009: getstatic int[][] game.C_100122_em.field_102073_Xb
		// @00C: arraylength
		// @00D: iconst_m1
		// @00E: ixor
		// @00F: if_icmple @02D
		// @012: getstatic int[][] game.C_100122_em.field_102073_Xb
		// @015: iload_1
		// @016: aaload
		// @017: iload_3
		// @018: ifne @051
		// @01B: ifnull @02D
		// @01E: goto @022
		// @021: athrow
		// @022: iinc #1 +1
		// @025: iload_3
		// @026: ifeq @006
		// @029: goto @02D
		// @02C: athrow
		// @02D: getstatic game.C_100115_ej game.C_100017_wj.field_103823_k
		// @030: getfield game.C_100302_ka game.C_100115_ej.field_102036_Wb
		// @033: bipush -100 (0x9C)
		// @035: getstatic game.C_100115_ej game.C_100017_wj.field_103823_k
		// @038: getfield int game.C_100115_ej.field_101848_lb
		// @03B: iadd
		// @03C: getstatic game.C_100115_ej game.C_100017_wj.field_103823_k
		// @03F: getfield game.C_100302_ka game.C_100115_ej.field_102036_Wb
		// @042: getfield int game.C_100302_ka.field_101848_lb
		// @045: ineg
		// @046: iadd
		// @047: putfield int game.C_100302_ka.field_101880_Gb
		// @04A: iconst_1
		// @04B: putstatic int game.C_100200_ba.field_105852_c
		// @04E: getstatic int[] game.C_100074_g.field_104410_e
		// @051: iconst_0
		// @052: getstatic game.C_100115_ej game.C_100017_wj.field_103823_k
		// @055: getfield game.C_100302_ka game.C_100115_ej.field_102036_Wb
		// @058: getfield int game.C_100302_ka.field_101880_Gb
		// @05B: iastore
		// @05C: bipush -31 (0xE1)
		// @05E: invokestatic game.C_100203_ql.func_105921_a(int)void
		// @061: iload_1
		// @062: iconst_m1
		// @063: ixor
		// @064: getstatic int[][] game.C_100122_em.field_102073_Xb
		// @067: arraylength
		// @068: iconst_m1
		// @069: ixor
		// @06A: if_icmple @071
		// @06D: goto @081
		// @070: athrow
		// @071: getstatic game.C_100037_wb[] game.C_100219_an.field_100878_m
		// @074: iconst_0
		// @075: aaload
		// @076: putstatic game.C_100037_wb game.C_100144_bm.field_102094_ac
		// @079: getstatic java.lang.String game.C_100155_dc.field_105349_d
		// @07C: putstatic java.lang.String game.C_100129_tg.field_102743_Db
		// @07F: iconst_0
		// @080: ireturn
		// @081: bipush 109 (0x6D)
		// @083: iconst_1
		// @084: iload_0
		// @085: isub
		// @086: bipush 45 (0x2D)
		// @088: idiv
		// @089: idiv
		// @08A: istore_2
		// @08B: getstatic game.C_100327_ib game.C_100343_jf.field_104834_p
		// @08E: getstatic int[] game.C_100301_kb.field_107089_g
		// @091: bipush -125 (0x83)
		// @093: invokestatic game.C_100260_mc.func_102219_a(game.C_100327_ib, int[], byte)int[]
		// @096: putstatic int[] game.C_100280_nf.field_101178_o
		// @099: getstatic int[][] game.C_100122_em.field_102073_Xb
		// @09C: iload_1
		// @09D: aaload
		// @09E: ifnull @0B6
		// @0A1: getstatic int[] game.C_100280_nf.field_101178_o
		// @0A4: arraylength
		// @0A5: getstatic int[][] game.C_100122_em.field_102073_Xb
		// @0A8: iload_1
		// @0A9: aaload
		// @0AA: arraylength
		// @0AB: if_icmpne @0B6
		// @0AE: goto @0B2
		// @0B1: athrow
		// @0B2: goto @0C1
		// @0B5: athrow
		// @0B6: getstatic int[][] game.C_100122_em.field_102073_Xb
		// @0B9: iload_1
		// @0BA: getstatic int[] game.C_100280_nf.field_101178_o
		// @0BD: arraylength
		// @0BE: newarray int[]
		// @0C0: aastore
		// @0C1: getstatic int[] game.C_100280_nf.field_101178_o
		// @0C4: iconst_0
		// @0C5: getstatic int[][] game.C_100122_em.field_102073_Xb
		// @0C8: iload_1
		// @0C9: aaload
		// @0CA: iconst_0
		// @0CB: getstatic int[] game.C_100280_nf.field_101178_o
		// @0CE: arraylength
		// @0CF: invokestatic game.C_100120_en.func_104913_a(int[], int, int[], int, int)void
		// @0D2: sipush 1000 (0x03E8)
		// @0D5: getstatic game.C_100327_ib game.C_100343_jf.field_104834_p
		// @0D8: iload_1
		// @0D9: invokestatic game.C_100013_fn.func_103736_a(int, game.C_100327_ib, int)void
		// @0DC: iconst_1
		// @0DD: ireturn
		// @0DE: astore_1
		// @0DF: aload_1
		// @0E0: new java.lang.StringBuilder
		// @0E3: dup
		// @0E4: invokespecial java.lang.StringBuilder.<init>()void
		// @0E7: getstatic java.lang.String[] game.C_100029_gn.field_103365_V
		// @0EA: bipush 6 (0x06)
		// @0EC: aaload
		// @0ED: invokevirtual java.lang.StringBuilder.append(java.lang.String)java.lang.StringBuilder
		// @0F0: iload_0
		// @0F1: invokevirtual java.lang.StringBuilder.append(int)java.lang.StringBuilder
		// @0F4: bipush 41 (0x29)
		// @0F6: invokevirtual java.lang.StringBuilder.append(char)java.lang.StringBuilder
		// @0F9: invokevirtual java.lang.StringBuilder.toString()java.lang.String
		// @0FC: invokestatic game.C_100181_cf.func_105695_a(java.lang.Throwable, java.lang.String)game.C_100170_cm
		// @0FF: athrow
	}
	
	public static void func_103360_k(int arg0)
	{
		// @00: aconst_null
		// @01: putstatic game.C_100193_re game.C_100029_gn.field_103368_S
		// @04: iload_0
		// @05: iconst_1
		// @06: if_icmpeq @14
		// @09: aconst_null
		// @0A: checkcast java.lang.String
		// @0D: putstatic java.lang.String game.C_100029_gn.field_103367_P
		// @10: goto @14
		// @13: athrow
		// @14: aconst_null
		// @15: putstatic java.lang.String game.C_100029_gn.field_103364_T
		// @18: aconst_null
		// @19: putstatic java.lang.String game.C_100029_gn.field_103370_O
		// @1C: aconst_null
		// @1D: putstatic java.lang.String game.C_100029_gn.field_103367_P
		// @20: goto @44
		// @23: astore_1
		// @24: aload_1
		// @25: new java.lang.StringBuilder
		// @28: dup
		// @29: invokespecial java.lang.StringBuilder.<init>()void
		// @2C: getstatic java.lang.String[] game.C_100029_gn.field_103365_V
		// @2F: iconst_3
		// @30: aaload
		// @31: invokevirtual java.lang.StringBuilder.append(java.lang.String)java.lang.StringBuilder
		// @34: iload_0
		// @35: invokevirtual java.lang.StringBuilder.append(int)java.lang.StringBuilder
		// @38: bipush 41 (0x29)
		// @3A: invokevirtual java.lang.StringBuilder.append(char)java.lang.StringBuilder
		// @3D: invokevirtual java.lang.StringBuilder.toString()java.lang.String
		// @40: invokestatic game.C_100181_cf.func_105695_a(java.lang.Throwable, java.lang.String)game.C_100170_cm
		// @43: athrow
		// @44: return
	}
	
	final void func_103359_a(C_100336_im arg0, int arg1)
	{
		// @00: iload_2
		// @01: sipush 2839 (0x0B17)
		// @04: if_icmpeq @12
		// @07: aload_0
		// @08: bipush 74 (0x4A)
		// @0A: invokevirtual game.C_100029_gn.func_103339_j(int)game.C_100336_im
		// @0D: pop
		// @0E: goto @12
		// @11: athrow
		// @12: aload_1
		// @13: instanceof game.C_100136_th
		// @16: ifeq @1D
		// @19: goto @25
		// @1C: athrow
		// @1D: new java.lang.IllegalArgumentException
		// @20: dup
		// @21: invokespecial java.lang.IllegalArgumentException.<init>()void
		// @24: athrow
		// @25: aload_1
		// @26: checkcast game.C_100136_th
		// @29: astore_3
		// @2A: aload_0
		// @2B: getfield game.C_100202_qi game.C_100029_gn.field_103369_R
		// @2E: sipush 15828 (0x3DD4)
		// @31: aload_3
		// @32: invokevirtual game.C_100202_qi.func_105903_b(int, game.C_100158_da)void
		// @35: aload_3
		// @36: iconst_1
		// @37: putfield boolean game.C_100136_th.field_102619_V
		// @3A: aload_3
		// @3B: iload_2
		// @3C: sipush 2838 (0x0B16)
		// @3F: ixor
		// @40: aload_0
		// @41: invokevirtual game.C_100136_th.func_102522_a(int, game.C_100336_im)boolean
		// @44: pop
		// @45: goto @86
		// @48: astore_3
		// @49: aload_3
		// @4A: new java.lang.StringBuilder
		// @4D: dup
		// @4E: invokespecial java.lang.StringBuilder.<init>()void
		// @51: getstatic java.lang.String[] game.C_100029_gn.field_103365_V
		// @54: bipush 8 (0x08)
		// @56: aaload
		// @57: invokevirtual java.lang.StringBuilder.append(java.lang.String)java.lang.StringBuilder
		// @5A: aload_1
		// @5B: ifnull @68
		// @5E: getstatic java.lang.String[] game.C_100029_gn.field_103365_V
		// @61: bipush 10 (0x0A)
		// @63: aaload
		// @64: goto @6E
		// @67: athrow
		// @68: getstatic java.lang.String[] game.C_100029_gn.field_103365_V
		// @6B: bipush 9 (0x09)
		// @6D: aaload
		// @6E: invokevirtual java.lang.StringBuilder.append(java.lang.String)java.lang.StringBuilder
		// @71: bipush 44 (0x2C)
		// @73: invokevirtual java.lang.StringBuilder.append(char)java.lang.StringBuilder
		// @76: iload_2
		// @77: invokevirtual java.lang.StringBuilder.append(int)java.lang.StringBuilder
		// @7A: bipush 41 (0x29)
		// @7C: invokevirtual java.lang.StringBuilder.append(char)java.lang.StringBuilder
		// @7F: invokevirtual java.lang.StringBuilder.toString()java.lang.String
		// @82: invokestatic game.C_100181_cf.func_105695_a(java.lang.Throwable, java.lang.String)game.C_100170_cm
		// @85: athrow
		// @86: return
	}
	
	final void func_103362_n(int arg0)
	{
		// @00: getstatic int game.SteelSentinels.field_105275_O
		// @03: istore #4
		// @05: new game.C_100019_wl
		// @08: dup
		// @09: aload_0
		// @0A: getfield game.C_100202_qi game.C_100029_gn.field_103369_R
		// @0D: invokespecial game.C_100019_wl.<init>(game.C_100202_qi)void
		// @10: astore_2
		// @11: aload_2
		// @12: bipush -128 (0x80)
		// @14: invokevirtual game.C_100019_wl.func_103827_a(byte)game.C_100158_da
		// @17: checkcast game.C_100136_th
		// @1A: astore_3
		// @1B: aconst_null
		// @1C: aload_3
		// @1D: if_acmpeq @3E
		// @20: aload_3
		// @21: iconst_0
		// @22: putfield boolean game.C_100136_th.field_102619_V
		// @25: aload_2
		// @26: sipush -30820 (0x879C)
		// @29: invokevirtual game.C_100019_wl.func_103836_b(int)game.C_100158_da
		// @2C: checkcast game.C_100136_th
		// @2F: astore_3
		// @30: iload #4
		// @32: ifne @43
		// @35: iload #4
		// @37: ifeq @1B
		// @3A: goto @3E
		// @3D: athrow
		// @3E: aload_0
		// @3F: aconst_null
		// @40: putfield game.C_100336_im game.C_100029_gn.field_103351_J
		// @43: iload_1
		// @44: iconst_5
		// @45: if_icmpeq @53
		// @48: aconst_null
		// @49: checkcast java.lang.String
		// @4C: putstatic java.lang.String game.C_100029_gn.field_103364_T
		// @4F: goto @53
		// @52: athrow
		// @53: goto @77
		// @56: astore_2
		// @57: aload_2
		// @58: new java.lang.StringBuilder
		// @5B: dup
		// @5C: invokespecial java.lang.StringBuilder.<init>()void
		// @5F: getstatic java.lang.String[] game.C_100029_gn.field_103365_V
		// @62: iconst_4
		// @63: aaload
		// @64: invokevirtual java.lang.StringBuilder.append(java.lang.String)java.lang.StringBuilder
		// @67: iload_1
		// @68: invokevirtual java.lang.StringBuilder.append(int)java.lang.StringBuilder
		// @6B: bipush 41 (0x29)
		// @6D: invokevirtual java.lang.StringBuilder.append(char)java.lang.StringBuilder
		// @70: invokevirtual java.lang.StringBuilder.toString()java.lang.String
		// @73: invokestatic game.C_100181_cf.func_105695_a(java.lang.Throwable, java.lang.String)game.C_100170_cm
		// @76: athrow
		// @77: return
	}
	
	final void func_103358_m(int arg0)
	{
		// @00: iload_1
		// @01: sipush -708 (0xFD3C)
		// @04: if_icmpeq @12
		// @07: aconst_null
		// @08: checkcast java.lang.String
		// @0B: putstatic java.lang.String game.C_100029_gn.field_103370_O
		// @0E: goto @12
		// @11: athrow
		// @12: new game.C_100019_wl
		// @15: dup
		// @16: aload_0
		// @17: getfield game.C_100202_qi game.C_100029_gn.field_103369_R
		// @1A: invokespecial game.C_100019_wl.<init>(game.C_100202_qi)void
		// @1D: astore_2
		// @1E: aload_2
		// @1F: bipush -128 (0x80)
		// @21: invokevirtual game.C_100019_wl.func_103827_a(byte)game.C_100158_da
		// @24: checkcast game.C_100136_th
		// @27: astore_3
		// @28: aload_3
		// @29: ifnull @54
		// @2C: aload_3
		// @2D: iload_1
		// @2E: sipush 956 (0x03BC)
		// @31: iadd
		// @32: invokevirtual game.C_100136_th.func_102613_k(int)boolean
		// @35: ifne @40
		// @38: goto @3C
		// @3B: athrow
		// @3C: goto @46
		// @3F: athrow
		// @40: aload_3
		// @41: bipush 45 (0x2D)
		// @43: invokevirtual game.C_100136_th.func_100583_c(int)void
		// @46: aload_2
		// @47: sipush -30820 (0x879C)
		// @4A: invokevirtual game.C_100019_wl.func_103836_b(int)game.C_100158_da
		// @4D: checkcast game.C_100136_th
		// @50: astore_3
		// @51: goto @28
		// @54: aload_0
		// @55: aload_0
		// @56: bipush 126 (0x7E)
		// @58: invokevirtual game.C_100029_gn.func_103353_g(byte)game.C_100136_th
		// @5B: putfield game.C_100336_im game.C_100029_gn.field_103351_J
		// @5E: goto @83
		// @61: astore_2
		// @62: aload_2
		// @63: new java.lang.StringBuilder
		// @66: dup
		// @67: invokespecial java.lang.StringBuilder.<init>()void
		// @6A: getstatic java.lang.String[] game.C_100029_gn.field_103365_V
		// @6D: bipush 7 (0x07)
		// @6F: aaload
		// @70: invokevirtual java.lang.StringBuilder.append(java.lang.String)java.lang.StringBuilder
		// @73: iload_1
		// @74: invokevirtual java.lang.StringBuilder.append(int)java.lang.StringBuilder
		// @77: bipush 41 (0x29)
		// @79: invokevirtual java.lang.StringBuilder.append(char)java.lang.StringBuilder
		// @7C: invokevirtual java.lang.StringBuilder.toString()java.lang.String
		// @7F: invokestatic game.C_100181_cf.func_105695_a(java.lang.Throwable, java.lang.String)game.C_100170_cm
		// @82: athrow
		// @83: return
	}
	
	final void func_103361_f(byte arg0)
	{
		// @00: getstatic int game.SteelSentinels.field_105275_O
		// @03: istore #4
		// @05: new game.C_100019_wl
		// @08: dup
		// @09: aload_0
		// @0A: getfield game.C_100202_qi game.C_100029_gn.field_103369_R
		// @0D: invokespecial game.C_100019_wl.<init>(game.C_100202_qi)void
		// @10: astore_2
		// @11: aload_2
		// @12: bipush -128 (0x80)
		// @14: invokevirtual game.C_100019_wl.func_103827_a(byte)game.C_100158_da
		// @17: checkcast game.C_100136_th
		// @1A: astore_3
		// @1B: aload_3
		// @1C: ifnull @4C
		// @1F: aload_3
		// @20: bipush -98 (0x9E)
		// @22: invokevirtual game.C_100136_th.func_102606_a(byte)boolean
		// @25: iload #4
		// @27: ifne @4D
		// @2A: ifne @34
		// @2D: goto @31
		// @30: athrow
		// @31: goto @3A
		// @34: aload_3
		// @35: bipush 45 (0x2D)
		// @37: invokevirtual game.C_100136_th.func_100583_c(int)void
		// @3A: aload_2
		// @3B: iload_1
		// @3C: sipush -30832 (0x8790)
		// @3F: iadd
		// @40: invokevirtual game.C_100019_wl.func_103836_b(int)game.C_100158_da
		// @43: checkcast game.C_100136_th
		// @46: astore_3
		// @47: iload #4
		// @49: ifeq @1B
		// @4C: iload_1
		// @4D: bipush 12 (0x0C)
		// @4F: if_icmpeq @5C
		// @52: aload_0
		// @53: bipush -109 (0x93)
		// @55: invokevirtual game.C_100029_gn.func_103361_f(byte)void
		// @58: goto @5C
		// @5B: athrow
		// @5C: goto @80
		// @5F: astore_2
		// @60: aload_2
		// @61: new java.lang.StringBuilder
		// @64: dup
		// @65: invokespecial java.lang.StringBuilder.<init>()void
		// @68: getstatic java.lang.String[] game.C_100029_gn.field_103365_V
		// @6B: iconst_0
		// @6C: aaload
		// @6D: invokevirtual java.lang.StringBuilder.append(java.lang.String)java.lang.StringBuilder
		// @70: iload_1
		// @71: invokevirtual java.lang.StringBuilder.append(int)java.lang.StringBuilder
		// @74: bipush 41 (0x29)
		// @76: invokevirtual java.lang.StringBuilder.append(char)java.lang.StringBuilder
		// @79: invokevirtual java.lang.StringBuilder.toString()java.lang.String
		// @7C: invokestatic game.C_100181_cf.func_105695_a(java.lang.Throwable, java.lang.String)game.C_100170_cm
		// @7F: athrow
		// @80: return
	}
	
	public C_100029_gn()
	{
		// @00: aload_0
		// @01: iconst_0
		// @02: iconst_0
		// @03: getstatic int game.C_100313_lg.field_107165_e
		// @06: getstatic int game.C_100340_je.field_102984_k
		// @09: aconst_null
		// @0A: aconst_null
		// @0B: invokespecial game.C_100030_gm.<init>(int, int, int, int, game.C_100326_ic, game.C_100337_in)void
		// @0E: aload_0
		// @0F: new game.C_100202_qi
		// @12: dup
		// @13: invokespecial game.C_100202_qi.<init>()void
		// @16: putfield game.C_100202_qi game.C_100029_gn.field_103369_R
		// @19: return
	}
	
	final C_100336_im func_103339_j(int arg0)
	{
		// @00: getstatic int game.SteelSentinels.field_105275_O
		// @03: istore #4
		// @05: iload_1
		// @06: sipush -22255 (0xA911)
		// @09: if_icmpeq @17
		// @0C: aload_0
		// @0D: bipush -99 (0x9D)
		// @0F: invokevirtual game.C_100029_gn.func_103339_j(int)game.C_100336_im
		// @12: pop
		// @13: goto @17
		// @16: athrow
		// @17: new game.C_100019_wl
		// @1A: dup
		// @1B: aload_0
		// @1C: getfield game.C_100202_qi game.C_100029_gn.field_103369_R
		// @1F: invokespecial game.C_100019_wl.<init>(game.C_100202_qi)void
		// @22: astore_2
		// @23: aload_2
		// @24: bipush -128 (0x80)
		// @26: invokevirtual game.C_100019_wl.func_103827_a(byte)game.C_100158_da
		// @29: checkcast game.C_100136_th
		// @2C: astore_3
		// @2D: aload_3
		// @2E: ifnull @56
		// @31: aload_3
		// @32: getfield boolean game.C_100136_th.field_102619_V
		// @35: ifne @3C
		// @38: goto @46
		// @3B: athrow
		// @3C: aload_3
		// @3D: iload_1
		// @3E: sipush 22254 (0x56EE)
		// @41: iadd
		// @42: invokevirtual game.C_100136_th.func_102559_j(int)game.C_100336_im
		// @45: areturn
		// @46: aload_2
		// @47: sipush -30820 (0x879C)
		// @4A: invokevirtual game.C_100019_wl.func_103836_b(int)game.C_100158_da
		// @4D: checkcast game.C_100136_th
		// @50: astore_3
		// @51: iload #4
		// @53: ifeq @2D
		// @56: aconst_null
		// @57: areturn
		// @58: astore_2
		// @59: aload_2
		// @5A: new java.lang.StringBuilder
		// @5D: dup
		// @5E: invokespecial java.lang.StringBuilder.<init>()void
		// @61: getstatic java.lang.String[] game.C_100029_gn.field_103365_V
		// @64: iconst_1
		// @65: aaload
		// @66: invokevirtual java.lang.StringBuilder.append(java.lang.String)java.lang.StringBuilder
		// @69: iload_1
		// @6A: invokevirtual java.lang.StringBuilder.append(int)java.lang.StringBuilder
		// @6D: bipush 41 (0x29)
		// @6F: invokevirtual java.lang.StringBuilder.append(char)java.lang.StringBuilder
		// @72: invokevirtual java.lang.StringBuilder.toString()java.lang.String
		// @75: invokestatic game.C_100181_cf.func_105695_a(java.lang.Throwable, java.lang.String)game.C_100170_cm
		// @78: athrow
	}
	
	final C_100136_th func_103353_g(byte arg0)
	{
		// @00: new game.C_100019_wl
		// @03: dup
		// @04: aload_0
		// @05: getfield game.C_100202_qi game.C_100029_gn.field_103369_R
		// @08: invokespecial game.C_100019_wl.<init>(game.C_100202_qi)void
		// @0B: astore_2
		// @0C: aload_2
		// @0D: bipush -128 (0x80)
		// @0F: invokevirtual game.C_100019_wl.func_103827_a(byte)game.C_100158_da
		// @12: checkcast game.C_100136_th
		// @15: astore_3
		// @16: aconst_null
		// @17: aload_3
		// @18: if_acmpeq @3A
		// @1B: aload_3
		// @1C: getfield boolean game.C_100136_th.field_102619_V
		// @1F: ifne @2A
		// @22: goto @26
		// @25: athrow
		// @26: goto @2C
		// @29: athrow
		// @2A: aload_3
		// @2B: areturn
		// @2C: aload_2
		// @2D: sipush -30820 (0x879C)
		// @30: invokevirtual game.C_100019_wl.func_103836_b(int)game.C_100158_da
		// @33: checkcast game.C_100136_th
		// @36: astore_3
		// @37: goto @16
		// @3A: iload_1
		// @3B: bipush 126 (0x7E)
		// @3D: if_icmpeq @4B
		// @40: aconst_null
		// @41: checkcast java.lang.String
		// @44: putstatic java.lang.String game.C_100029_gn.field_103370_O
		// @47: goto @4B
		// @4A: athrow
		// @4B: aconst_null
		// @4C: areturn
		// @4D: astore_2
		// @4E: aload_2
		// @4F: new java.lang.StringBuilder
		// @52: dup
		// @53: invokespecial java.lang.StringBuilder.<init>()void
		// @56: getstatic java.lang.String[] game.C_100029_gn.field_103365_V
		// @59: iconst_2
		// @5A: aaload
		// @5B: invokevirtual java.lang.StringBuilder.append(java.lang.String)java.lang.StringBuilder
		// @5E: iload_1
		// @5F: invokevirtual java.lang.StringBuilder.append(int)java.lang.StringBuilder
		// @62: bipush 41 (0x29)
		// @64: invokevirtual java.lang.StringBuilder.append(char)java.lang.StringBuilder
		// @67: invokevirtual java.lang.StringBuilder.toString()java.lang.String
		// @6A: invokestatic game.C_100181_cf.func_105695_a(java.lang.Throwable, java.lang.String)game.C_100170_cm
		// @6D: athrow
	}
	
	final void func_102528_a(int arg0, int arg1, int arg2, byte arg3)
	{
		// @00: getstatic int game.SteelSentinels.field_105275_O
		// @03: istore #7
		// @05: aconst_null
		// @06: aload_0
		// @07: getfield game.C_100326_ic game.C_100029_gn.field_102533_B
		// @0A: if_acmpne @11
		// @0D: goto @21
		// @10: athrow
		// @11: aload_0
		// @12: getfield game.C_100326_ic game.C_100029_gn.field_102533_B
		// @15: iconst_1
		// @16: sipush -26568 (0x9838)
		// @19: iload_3
		// @1A: iload_2
		// @1B: aload_0
		// @1C: invokeinterface game.C_100326_ic.func_100362_a(boolean, int, int, int, game.C_100336_im)void
		// @21: new game.C_100019_wl
		// @24: dup
		// @25: aload_0
		// @26: getfield game.C_100202_qi game.C_100029_gn.field_103369_R
		// @29: invokespecial game.C_100019_wl.<init>(game.C_100202_qi)void
		// @2C: astore #5
		// @2E: aload #5
		// @30: iconst_1
		// @31: invokevirtual game.C_100019_wl.func_103837_b(boolean)game.C_100158_da
		// @34: checkcast game.C_100336_im
		// @37: astore #6
		// @39: iload #4
		// @3B: bipush -126 (0x82)
		// @3D: if_icmplt @41
		// @40: return
		// @41: aconst_null
		// @42: aload #6
		// @44: if_acmpeq @77
		// @47: aload #6
		// @49: iload_1
		// @4A: iload_2
		// @4B: aload_0
		// @4C: getfield int game.C_100029_gn.field_102541_w
		// @4F: ineg
		// @50: isub
		// @51: aload_0
		// @52: getfield int game.C_100029_gn.field_102538_m
		// @55: iload_3
		// @56: iadd
		// @57: bipush -127 (0x81)
		// @59: invokevirtual game.C_100336_im.func_102528_a(int, int, int, byte)void
		// @5C: aload #5
		// @5E: sipush -21976 (0xAA28)
		// @61: invokevirtual game.C_100019_wl.func_103828_c(int)game.C_100158_da
		// @64: checkcast game.C_100336_im
		// @67: astore #6
		// @69: iload #7
		// @6B: ifne @B9
		// @6E: iload #7
		// @70: ifeq @41
		// @73: goto @77
		// @76: athrow
		// @77: goto @B9
		// @7A: astore #5
		// @7C: aload #5
		// @7E: new java.lang.StringBuilder
		// @81: dup
		// @82: invokespecial java.lang.StringBuilder.<init>()void
		// @85: getstatic java.lang.String[] game.C_100029_gn.field_103365_V
		// @88: iconst_5
		// @89: aaload
		// @8A: invokevirtual java.lang.StringBuilder.append(java.lang.String)java.lang.StringBuilder
		// @8D: iload_1
		// @8E: invokevirtual java.lang.StringBuilder.append(int)java.lang.StringBuilder
		// @91: bipush 44 (0x2C)
		// @93: invokevirtual java.lang.StringBuilder.append(char)java.lang.StringBuilder
		// @96: iload_2
		// @97: invokevirtual java.lang.StringBuilder.append(int)java.lang.StringBuilder
		// @9A: bipush 44 (0x2C)
		// @9C: invokevirtual java.lang.StringBuilder.append(char)java.lang.StringBuilder
		// @9F: iload_3
		// @A0: invokevirtual java.lang.StringBuilder.append(int)java.lang.StringBuilder
		// @A3: bipush 44 (0x2C)
		// @A5: invokevirtual java.lang.StringBuilder.append(char)java.lang.StringBuilder
		// @A8: iload #4
		// @AA: invokevirtual java.lang.StringBuilder.append(int)java.lang.StringBuilder
		// @AD: bipush 41 (0x29)
		// @AF: invokevirtual java.lang.StringBuilder.append(char)java.lang.StringBuilder
		// @B2: invokevirtual java.lang.StringBuilder.toString()java.lang.String
		// @B5: invokestatic game.C_100181_cf.func_105695_a(java.lang.Throwable, java.lang.String)game.C_100170_cm
		// @B8: athrow
		// @B9: return
	}
	
	static final C_100037_wb[] func_103354_a(int arg0, int arg1, int arg2, int arg3, boolean arg4, boolean arg5)
	{
		// @000: getstatic int[] game.C_100196_rb.field_105818_d
		// @003: astore #6
		// @005: getstatic int game.C_100196_rb.field_105819_e
		// @008: istore #7
		// @00A: getstatic int game.C_100196_rb.field_105821_c
		// @00D: istore #8
		// @00F: iload_2
		// @010: sipush 7293 (0x1C7D)
		// @013: if_icmpeq @021
		// @016: aconst_null
		// @017: checkcast java.lang.String
		// @01A: putstatic java.lang.String game.C_100029_gn.field_103370_O
		// @01D: goto @021
		// @020: athrow
		// @021: new game.C_100037_wb
		// @024: dup
		// @025: bipush 16 (0x10)
		// @027: iload_3
		// @028: invokespecial game.C_100037_wb.<init>(int, int)void
		// @02B: astore #9
		// @02D: aload #9
		// @02F: invokevirtual game.C_100037_wb.func_102379_d()void
		// @032: iconst_0
		// @033: iconst_0
		// @034: bipush 16 (0x10)
		// @036: iload_3
		// @037: iload_1
		// @038: iload_0
		// @039: invokestatic game.C_100196_rb.func_105798_b(int, int, int, int, int, int)void
		// @03C: aconst_null
		// @03D: astore #10
		// @03F: iload #5
		// @041: ifne @048
		// @044: goto @077
		// @047: athrow
		// @048: aload #9
		// @04A: invokevirtual game.C_100037_wb.func_102381_e()game.C_100037_wb
		// @04D: astore #10
		// @04F: aload #10
		// @051: invokevirtual game.C_100037_wb.func_102379_d()void
		// @054: iconst_0
		// @055: iconst_0
		// @056: iconst_5
		// @057: iconst_0
		// @058: invokestatic game.C_100196_rb.func_105807_g(int, int, int, int)void
		// @05B: iconst_0
		// @05C: iconst_1
		// @05D: iconst_3
		// @05E: iconst_0
		// @05F: invokestatic game.C_100196_rb.func_105807_g(int, int, int, int)void
		// @062: iconst_0
		// @063: iconst_2
		// @064: iconst_2
		// @065: iconst_0
		// @066: invokestatic game.C_100196_rb.func_105807_g(int, int, int, int)void
		// @069: iconst_0
		// @06A: iconst_3
		// @06B: iconst_1
		// @06C: iconst_0
		// @06D: invokestatic game.C_100196_rb.func_105807_g(int, int, int, int)void
		// @070: iconst_0
		// @071: iconst_4
		// @072: iconst_1
		// @073: iconst_0
		// @074: invokestatic game.C_100196_rb.func_105807_g(int, int, int, int)void
		// @077: aconst_null
		// @078: astore #11
		// @07A: iload #4
		// @07C: ifeq @0B3
		// @07F: aload #9
		// @081: invokevirtual game.C_100037_wb.func_102381_e()game.C_100037_wb
		// @084: astore #11
		// @086: aload #11
		// @088: invokevirtual game.C_100037_wb.func_102379_d()void
		// @08B: bipush 11 (0x0B)
		// @08D: iconst_0
		// @08E: iconst_5
		// @08F: iconst_0
		// @090: invokestatic game.C_100196_rb.func_105807_g(int, int, int, int)void
		// @093: bipush 13 (0x0D)
		// @095: iconst_1
		// @096: iconst_3
		// @097: iconst_0
		// @098: invokestatic game.C_100196_rb.func_105807_g(int, int, int, int)void
		// @09B: bipush 14 (0x0E)
		// @09D: iconst_2
		// @09E: iconst_2
		// @09F: iconst_0
		// @0A0: invokestatic game.C_100196_rb.func_105807_g(int, int, int, int)void
		// @0A3: bipush 15 (0x0F)
		// @0A5: iconst_3
		// @0A6: iconst_1
		// @0A7: iconst_0
		// @0A8: invokestatic game.C_100196_rb.func_105807_g(int, int, int, int)void
		// @0AB: bipush 15 (0x0F)
		// @0AD: iconst_4
		// @0AE: iconst_1
		// @0AF: iconst_0
		// @0B0: invokestatic game.C_100196_rb.func_105807_g(int, int, int, int)void
		// @0B3: aload #6
		// @0B5: iload #7
		// @0B7: iload #8
		// @0B9: invokestatic game.C_100196_rb.func_105808_a(int[], int, int)void
		// @0BC: bipush 9 (0x09)
		// @0BE: anewarray game.C_100037_wb
		// @0C1: dup
		// @0C2: iconst_0
		// @0C3: aconst_null
		// @0C4: aastore
		// @0C5: dup
		// @0C6: iconst_1
		// @0C7: aconst_null
		// @0C8: aastore
		// @0C9: dup
		// @0CA: iconst_2
		// @0CB: aconst_null
		// @0CC: aastore
		// @0CD: dup
		// @0CE: iconst_3
		// @0CF: aload #10
		// @0D1: aastore
		// @0D2: dup
		// @0D3: iconst_4
		// @0D4: aload #9
		// @0D6: aastore
		// @0D7: dup
		// @0D8: iconst_5
		// @0D9: aload #11
		// @0DB: aastore
		// @0DC: dup
		// @0DD: bipush 6 (0x06)
		// @0DF: aconst_null
		// @0E0: aastore
		// @0E1: dup
		// @0E2: bipush 7 (0x07)
		// @0E4: aconst_null
		// @0E5: aastore
		// @0E6: dup
		// @0E7: bipush 8 (0x08)
		// @0E9: aconst_null
		// @0EA: aastore
		// @0EB: areturn
		// @0EC: astore #6
		// @0EE: aload #6
		// @0F0: new java.lang.StringBuilder
		// @0F3: dup
		// @0F4: invokespecial java.lang.StringBuilder.<init>()void
		// @0F7: getstatic java.lang.String[] game.C_100029_gn.field_103365_V
		// @0FA: bipush 11 (0x0B)
		// @0FC: aaload
		// @0FD: invokevirtual java.lang.StringBuilder.append(java.lang.String)java.lang.StringBuilder
		// @100: iload_0
		// @101: invokevirtual java.lang.StringBuilder.append(int)java.lang.StringBuilder
		// @104: bipush 44 (0x2C)
		// @106: invokevirtual java.lang.StringBuilder.append(char)java.lang.StringBuilder
		// @109: iload_1
		// @10A: invokevirtual java.lang.StringBuilder.append(int)java.lang.StringBuilder
		// @10D: bipush 44 (0x2C)
		// @10F: invokevirtual java.lang.StringBuilder.append(char)java.lang.StringBuilder
		// @112: iload_2
		// @113: invokevirtual java.lang.StringBuilder.append(int)java.lang.StringBuilder
		// @116: bipush 44 (0x2C)
		// @118: invokevirtual java.lang.StringBuilder.append(char)java.lang.StringBuilder
		// @11B: iload_3
		// @11C: invokevirtual java.lang.StringBuilder.append(int)java.lang.StringBuilder
		// @11F: bipush 44 (0x2C)
		// @121: invokevirtual java.lang.StringBuilder.append(char)java.lang.StringBuilder
		// @124: iload #4
		// @126: invokevirtual java.lang.StringBuilder.append(boolean)java.lang.StringBuilder
		// @129: bipush 44 (0x2C)
		// @12B: invokevirtual java.lang.StringBuilder.append(char)java.lang.StringBuilder
		// @12E: iload #5
		// @130: invokevirtual java.lang.StringBuilder.append(boolean)java.lang.StringBuilder
		// @133: bipush 41 (0x29)
		// @135: invokevirtual java.lang.StringBuilder.append(char)java.lang.StringBuilder
		// @138: invokevirtual java.lang.StringBuilder.toString()java.lang.String
		// @13B: invokestatic game.C_100181_cf.func_105695_a(java.lang.Throwable, java.lang.String)game.C_100170_cm
		// @13E: athrow
	}
	
	static
	{
		// @00: bipush 12 (0x0C)
		// @02: anewarray java.lang.String
		// @05: dup
		// @06: iconst_0
		// @07: ldc ")\u0019&})"
		// @09: invokestatic game.C_100029_gn.func_103357_z(java.lang.String)char[]
		// @0C: invokestatic game.C_100029_gn.func_103355_z(char[])java.lang.String
		// @0F: aastore
		// @10: dup
		// @11: iconst_1
		// @12: ldc ")\u0019&q@f"
		// @14: invokestatic game.C_100029_gn.func_103357_z(java.lang.String)char[]
		// @17: invokestatic game.C_100029_gn.func_103355_z(char[])java.lang.String
		// @1A: aastore
		// @1B: dup
		// @1C: iconst_2
		// @1D: ldc ")\u0019&~)"
		// @1F: invokestatic game.C_100029_gn.func_103357_z(java.lang.String)char[]
		// @22: invokestatic game.C_100029_gn.func_103355_z(char[])java.lang.String
		// @25: aastore
		// @26: dup
		// @27: iconst_3
		// @28: ldc ")\u0019&{)"
		// @2A: invokestatic game.C_100029_gn.func_103357_z(java.lang.String)char[]
		// @2D: invokestatic game.C_100029_gn.func_103355_z(char[])java.lang.String
		// @30: aastore
		// @31: dup
		// @32: iconst_4
		// @33: ldc ")\u0019&p@f"
		// @35: invokestatic game.C_100029_gn.func_103357_z(java.lang.String)char[]
		// @38: invokestatic game.C_100029_gn.func_103355_z(char[])java.lang.String
		// @3B: aastore
		// @3C: dup
		// @3D: iconst_5
		// @3E: ldc ")\u0019&|)"
		// @40: invokestatic game.C_100029_gn.func_103357_z(java.lang.String)char[]
		// @43: invokestatic game.C_100029_gn.func_103355_z(char[])java.lang.String
		// @46: aastore
		// @47: dup
		// @48: bipush 6 (0x06)
		// @4A: ldc ")\u0019&v)"
		// @4C: invokestatic game.C_100029_gn.func_103357_z(java.lang.String)char[]
		// @4F: invokestatic game.C_100029_gn.func_103355_z(char[])java.lang.String
		// @52: aastore
		// @53: dup
		// @54: bipush 7 (0x07)
		// @56: ldc ")\u0019&z)"
		// @58: invokestatic game.C_100029_gn.func_103357_z(java.lang.String)char[]
		// @5B: invokestatic game.C_100029_gn.func_103355_z(char[])java.lang.String
		// @5E: aastore
		// @5F: dup
		// @60: bipush 8 (0x08)
		// @62: ldc ")\u0019&w)"
		// @64: invokestatic game.C_100029_gn.func_103357_z(java.lang.String)char[]
		// @67: invokestatic game.C_100029_gn.func_103355_z(char[])java.lang.String
		// @6A: aastore
		// @6B: dup
		// @6C: bipush 9 (0x09)
		// @6E: ldc " \u0002dS"
		// @70: invokestatic game.C_100029_gn.func_103357_z(java.lang.String)char[]
		// @73: invokestatic game.C_100029_gn.func_103355_z(char[])java.lang.String
		// @76: aastore
		// @77: dup
		// @78: bipush 10 (0x0A)
		// @7A: ldc "5Y&\u0011|"
		// @7C: invokestatic game.C_100029_gn.func_103357_z(java.lang.String)char[]
		// @7F: invokestatic game.C_100029_gn.func_103355_z(char[])java.lang.String
		// @82: aastore
		// @83: dup
		// @84: bipush 11 (0x0B)
		// @86: ldc ")\u0019&x)"
		// @88: invokestatic game.C_100029_gn.func_103357_z(java.lang.String)char[]
		// @8B: invokestatic game.C_100029_gn.func_103355_z(char[])java.lang.String
		// @8E: aastore
		// @8F: putstatic java.lang.String[] game.C_100029_gn.field_103365_V
		// @92: ldc "\r6D~L\u0007#Q\u001fH\u0000W4\u001a1pW[zB\u00019Ll"
		// @94: invokestatic game.C_100029_gn.func_103357_z(java.lang.String)char[]
		// @97: invokestatic game.C_100029_gn.func_103355_z(char[])java.lang.String
		// @9A: putstatic java.lang.String game.C_100029_gn.field_103370_O
		// @9D: ldc "\u0019\u001efXr\"\u0018|"
		// @9F: invokestatic game.C_100029_gn.func_103357_z(java.lang.String)char[]
		// @A2: invokestatic game.C_100029_gn.func_103355_z(char[])java.lang.String
		// @A5: putstatic java.lang.String game.C_100029_gn.field_103364_T
		// @A8: ldc "\u001c\u0012ePw+Wf^l+"
		// @AA: invokestatic game.C_100029_gn.func_103357_z(java.lang.String)char[]
		// @AD: invokestatic game.C_100029_gn.func_103355_z(char[])java.lang.String
		// @B0: putstatic java.lang.String game.C_100029_gn.field_103367_P
		// @B3: return
	}
	
	private static char[] func_103357_z(String arg0)
	{
		// @00: aload_0
		// @01: invokevirtual java.lang.String.toCharArray()char[]
		// @04: dup
		// @05: arraylength
		// @06: iconst_2
		// @07: if_icmpge @12
		// @0A: dup
		// @0B: iconst_0
		// @0C: dup2
		// @0D: caload
		// @0E: iconst_1
		// @0F: ixor
		// @10: i2c
		// @11: castore
		// @12: areturn
	}
	
	private static String func_103355_z(char[] arg0)
	{
		// @00: aload_0
		// @01: dup
		// @02: arraylength
		// @03: swap
		// @04: iconst_0
		// @05: istore_1
		// @06: goto @4B
		// @09: dup
		// @0A: iload_1
		// @0B: dup2
		// @0C: caload
		// @0D: iload_1
		// @0E: iconst_5
		// @0F: irem
		// @10: tableswitch def: @44, for 0: @30, for 1: @35, for 2: @3A, for 3: @3F
		// @30: bipush 78 (0x4E)
		// @32: goto @45
		// @35: bipush 119 (0x77)
		// @37: goto @45
		// @3A: bipush 8 (0x08)
		// @3C: goto @45
		// @3F: bipush 63 (0x3F)
		// @41: goto @45
		// @44: iconst_1
		// @45: ixor
		// @46: i2c
		// @47: castore
		// @48: iinc #1 +1
		// @4B: swap
		// @4C: dup_x1
		// @4D: iload_1
		// @4E: if_icmpgt @09
		// @51: new java.lang.String
		// @54: dup_x1
		// @55: swap
		// @56: invokespecial java.lang.String.<init>(char[])void
		// @59: invokevirtual java.lang.String.intern()java.lang.String
		// @5C: areturn
	}
}
