package game;

final class C_100234_ob
{
	private int field_106276_e;
	String field_106278_c;
	private C_100332_ii[] field_106273_f;
	float field_106275_d;
	static String field_106279_a;
	private int field_106277_b;
	private int field_106274_g;
	private static final String[] field_106280_z;
	
	private final void func_106271_a(int arg0, C_100332_ii arg1, int arg2)
	{
		// @00: iload_1
		// @01: bipush -36 (0xDC)
		// @03: if_icmplt @0F
		// @06: bipush 47 (0x2F)
		// @08: invokestatic game.C_100234_ob.func_106266_a(byte)void
		// @0B: goto @0F
		// @0E: athrow
		// @0F: iconst_1
		// @10: aload_0
		// @11: getfield int game.C_100234_ob.field_106276_e
		// @14: iadd
		// @15: i2f
		// @16: iload_3
		// @17: i2f
		// @18: ldc 100.0
		// @1A: fdiv
		// @1B: fadd
		// @1C: fstore #4
		// @1E: iconst_0
		// @1F: iload_3
		// @20: if_icmpeq @54
		// @23: aload_0
		// @24: new java.lang.StringBuilder
		// @27: dup
		// @28: invokespecial java.lang.StringBuilder.<init>()void
		// @2B: aload_2
		// @2C: getfield java.lang.String game.C_100332_ii.field_107318_j
		// @2F: invokevirtual java.lang.StringBuilder.append(java.lang.String)java.lang.StringBuilder
		// @32: getstatic java.lang.String[] game.C_100234_ob.field_106280_z
		// @35: bipush 9 (0x09)
		// @37: aaload
		// @38: invokevirtual java.lang.StringBuilder.append(java.lang.String)java.lang.StringBuilder
		// @3B: iload_3
		// @3C: invokevirtual java.lang.StringBuilder.append(int)java.lang.StringBuilder
		// @3F: ldc "%"
		// @41: invokevirtual java.lang.StringBuilder.append(java.lang.String)java.lang.StringBuilder
		// @44: invokevirtual java.lang.StringBuilder.toString()java.lang.String
		// @47: putfield java.lang.String game.C_100234_ob.field_106278_c
		// @4A: getstatic int game.SteelSentinels.field_105275_O
		// @4D: ifeq @60
		// @50: goto @54
		// @53: athrow
		// @54: aload_0
		// @55: aload_2
		// @56: getfield java.lang.String game.C_100332_ii.field_107308_g
		// @59: putfield java.lang.String game.C_100234_ob.field_106278_c
		// @5C: goto @60
		// @5F: athrow
		// @60: aload_0
		// @61: fload #4
		// @63: aload_0
		// @64: getfield int game.C_100234_ob.field_106277_b
		// @67: i2f
		// @68: fmul
		// @69: iconst_1
		// @6A: aload_0
		// @6B: getfield int game.C_100234_ob.field_106274_g
		// @6E: iadd
		// @6F: i2f
		// @70: fdiv
		// @71: putfield float game.C_100234_ob.field_106275_d
		// @74: goto @BE
		// @77: astore #4
		// @79: aload #4
		// @7B: new java.lang.StringBuilder
		// @7E: dup
		// @7F: invokespecial java.lang.StringBuilder.<init>()void
		// @82: getstatic java.lang.String[] game.C_100234_ob.field_106280_z
		// @85: bipush 10 (0x0A)
		// @87: aaload
		// @88: invokevirtual java.lang.StringBuilder.append(java.lang.String)java.lang.StringBuilder
		// @8B: iload_1
		// @8C: invokevirtual java.lang.StringBuilder.append(int)java.lang.StringBuilder
		// @8F: bipush 44 (0x2C)
		// @91: invokevirtual java.lang.StringBuilder.append(char)java.lang.StringBuilder
		// @94: aload_2
		// @95: ifnull @A1
		// @98: getstatic java.lang.String[] game.C_100234_ob.field_106280_z
		// @9B: iconst_1
		// @9C: aaload
		// @9D: goto @A6
		// @A0: athrow
		// @A1: getstatic java.lang.String[] game.C_100234_ob.field_106280_z
		// @A4: iconst_0
		// @A5: aaload
		// @A6: invokevirtual java.lang.StringBuilder.append(java.lang.String)java.lang.StringBuilder
		// @A9: bipush 44 (0x2C)
		// @AB: invokevirtual java.lang.StringBuilder.append(char)java.lang.StringBuilder
		// @AE: iload_3
		// @AF: invokevirtual java.lang.StringBuilder.append(int)java.lang.StringBuilder
		// @B2: bipush 41 (0x29)
		// @B4: invokevirtual java.lang.StringBuilder.append(char)java.lang.StringBuilder
		// @B7: invokevirtual java.lang.StringBuilder.toString()java.lang.String
		// @BA: invokestatic game.C_100181_cf.func_105695_a(java.lang.Throwable, java.lang.String)game.C_100170_cm
		// @BD: athrow
		// @BE: return
	}
	
	static final void func_106266_a(byte arg0)
	{
		// @000: getstatic java.lang.String[] game.C_100268_mk.field_106669_b
		// @003: ifnull @007
		// @006: return
		// @007: bipush 48 (0x30)
		// @009: anewarray java.lang.String
		// @00C: putstatic java.lang.String[] game.C_100268_mk.field_106669_b
		// @00F: getstatic java.lang.String[] game.C_100268_mk.field_106669_b
		// @012: iconst_5
		// @013: getstatic java.lang.String game.C_100110_s.field_104844_d
		// @016: aastore
		// @017: getstatic java.lang.String[] game.C_100268_mk.field_106669_b
		// @01A: iconst_1
		// @01B: getstatic java.lang.String game.C_100256_pk.field_100467_n
		// @01E: aastore
		// @01F: getstatic java.lang.String[] game.C_100268_mk.field_106669_b
		// @022: bipush 8 (0x08)
		// @024: aconst_null
		// @025: aastore
		// @026: getstatic java.lang.String[] game.C_100268_mk.field_106669_b
		// @029: bipush 11 (0x0B)
		// @02B: getstatic java.lang.String game.C_100185_rm.field_105488_a
		// @02E: aastore
		// @02F: getstatic java.lang.String[] game.C_100268_mk.field_106669_b
		// @032: bipush 9 (0x09)
		// @034: getstatic java.lang.String game.C_100217_ao.field_106033_f
		// @037: aastore
		// @038: getstatic java.lang.String[] game.C_100268_mk.field_106669_b
		// @03B: bipush 6 (0x06)
		// @03D: getstatic java.lang.String game.C_100181_cf.field_105710_h
		// @040: aastore
		// @041: getstatic java.lang.String[] game.C_100268_mk.field_106669_b
		// @044: iconst_3
		// @045: getstatic java.lang.String game.C_100272_mn.field_102430_N
		// @048: aastore
		// @049: getstatic java.lang.String[] game.C_100268_mk.field_106669_b
		// @04C: bipush 13 (0x0D)
		// @04E: getstatic java.lang.String game.C_100099_fb.field_103041_A
		// @051: aastore
		// @052: getstatic java.lang.String[] game.C_100268_mk.field_106669_b
		// @055: bipush 7 (0x07)
		// @057: getstatic java.lang.String game.C_100003_ga.field_103527_n
		// @05A: aastore
		// @05B: getstatic java.lang.String[] game.C_100268_mk.field_106669_b
		// @05E: iconst_2
		// @05F: getstatic java.lang.String game.C_100210_qa.field_101049_E
		// @062: aastore
		// @063: iload_0
		// @064: bipush 109 (0x6D)
		// @066: if_icmpeq @074
		// @069: aconst_null
		// @06A: checkcast java.lang.String
		// @06D: putstatic java.lang.String game.C_100234_ob.field_106279_a
		// @070: goto @074
		// @073: athrow
		// @074: getstatic java.lang.String[] game.C_100268_mk.field_106669_b
		// @077: iconst_4
		// @078: getstatic java.lang.String game.C_100327_ib.field_102486_N
		// @07B: aastore
		// @07C: getstatic java.lang.String[] game.C_100268_mk.field_106669_b
		// @07F: iconst_0
		// @080: getstatic java.lang.String game.C_100236_on.field_100898_m
		// @083: aastore
		// @084: getstatic java.lang.String[] game.C_100268_mk.field_106669_b
		// @087: bipush 40 (0x28)
		// @089: getstatic java.lang.String game.C_100208_qg.field_105955_g
		// @08C: aastore
		// @08D: getstatic java.lang.String[] game.C_100268_mk.field_106669_b
		// @090: bipush 14 (0x0E)
		// @092: getstatic java.lang.String[] game.C_100283_ni.field_106756_g
		// @095: iconst_0
		// @096: aaload
		// @097: aastore
		// @098: getstatic java.lang.String[] game.C_100268_mk.field_106669_b
		// @09B: bipush 15 (0x0F)
		// @09D: getstatic java.lang.String[] game.C_100283_ni.field_106756_g
		// @0A0: iconst_1
		// @0A1: aaload
		// @0A2: aastore
		// @0A3: getstatic java.lang.String[] game.C_100268_mk.field_106669_b
		// @0A6: bipush 47 (0x2F)
		// @0A8: getstatic boolean game.C_100247_pa.field_106414_d
		// @0AB: ifeq @0B5
		// @0AE: getstatic java.lang.String game.C_100033_gj.field_101922_mc
		// @0B1: goto @0B8
		// @0B4: athrow
		// @0B5: getstatic java.lang.String game.C_100220_ac.field_106063_k
		// @0B8: aastore
		// @0B9: getstatic java.lang.String[] game.C_100268_mk.field_106669_b
		// @0BC: bipush 28 (0x1C)
		// @0BE: getstatic java.lang.String game.C_100085_a.field_102570_M
		// @0C1: aastore
		// @0C2: getstatic java.lang.String[] game.C_100268_mk.field_106669_b
		// @0C5: bipush 34 (0x22)
		// @0C7: getstatic java.lang.String game.C_100272_mn.field_102427_P
		// @0CA: aastore
		// @0CB: getstatic java.lang.String[] game.C_100268_mk.field_106669_b
		// @0CE: bipush 42 (0x2A)
		// @0D0: getstatic boolean game.C_100216_aj.field_104462_t
		// @0D3: ifne @0DD
		// @0D6: getstatic java.lang.String game.C_100138_bo.field_100413_h
		// @0D9: goto @0E0
		// @0DC: athrow
		// @0DD: getstatic java.lang.String game.C_100164_se.field_105453_c
		// @0E0: aastore
		// @0E1: getstatic java.lang.String[] game.C_100268_mk.field_106669_b
		// @0E4: bipush 29 (0x1D)
		// @0E6: getstatic java.lang.String game.C_100090_l.field_104495_d
		// @0E9: aastore
		// @0EA: getstatic java.lang.String[] game.C_100268_mk.field_106669_b
		// @0ED: bipush 43 (0x2B)
		// @0EF: getstatic boolean game.C_100094_j.field_104552_j
		// @0F2: ifeq @0FC
		// @0F5: getstatic java.lang.String game.C_100151_bc.field_102941_P
		// @0F8: goto @0FF
		// @0FB: athrow
		// @0FC: getstatic java.lang.String game.C_100141_tc.field_105057_f
		// @0FF: aastore
		// @100: getstatic java.lang.String[] game.C_100268_mk.field_106669_b
		// @103: bipush 22 (0x16)
		// @105: getstatic java.lang.String game.C_100235_om.field_106291_c
		// @108: aastore
		// @109: getstatic java.lang.String[] game.C_100268_mk.field_106669_b
		// @10C: bipush 32 (0x20)
		// @10E: getstatic java.lang.String game.C_100111_el.field_104861_e
		// @111: aastore
		// @112: getstatic java.lang.String[] game.C_100268_mk.field_106669_b
		// @115: bipush 17 (0x11)
		// @117: getstatic java.lang.String[] game.C_100343_jf.field_104831_s
		// @11A: iconst_0
		// @11B: aaload
		// @11C: aastore
		// @11D: getstatic java.lang.String[] game.C_100268_mk.field_106669_b
		// @120: bipush 27 (0x1B)
		// @122: getstatic java.lang.String game.C_100314_lf.field_101330_U
		// @125: aastore
		// @126: getstatic java.lang.String[] game.C_100268_mk.field_106669_b
		// @129: bipush 18 (0x12)
		// @12B: getstatic java.lang.String[] game.C_100343_jf.field_104831_s
		// @12E: iconst_1
		// @12F: aaload
		// @130: aastore
		// @131: getstatic java.lang.String[] game.C_100268_mk.field_106669_b
		// @134: bipush 33 (0x21)
		// @136: getstatic java.lang.String game.C_100325_id.field_101481_q
		// @139: aastore
		// @13A: getstatic java.lang.String[] game.C_100268_mk.field_106669_b
		// @13D: bipush 24 (0x18)
		// @13F: getstatic java.lang.String game.C_100217_ao.field_106044_h
		// @142: aastore
		// @143: getstatic java.lang.String[] game.C_100268_mk.field_106669_b
		// @146: bipush 44 (0x2C)
		// @148: getstatic boolean game.C_100102_w.field_104632_g
		// @14B: ifeq @155
		// @14E: getstatic java.lang.String game.C_100041_wf.field_104105_e
		// @151: goto @158
		// @154: athrow
		// @155: getstatic java.lang.String game.C_100059_df.field_101606_K
		// @158: aastore
		// @159: getstatic java.lang.String[] game.C_100268_mk.field_106669_b
		// @15C: bipush 37 (0x25)
		// @15E: getstatic boolean game.C_100050_vg.field_100637_q
		// @161: ifeq @16B
		// @164: getstatic java.lang.String game.C_100316_lc.field_102413_t
		// @167: goto @16E
		// @16A: athrow
		// @16B: getstatic java.lang.String game.C_100081_ue.field_100675_m
		// @16E: aastore
		// @16F: getstatic java.lang.String[] game.C_100268_mk.field_106669_b
		// @172: bipush 35 (0x23)
		// @174: getstatic java.lang.String game.C_100215_ai.field_106018_a
		// @177: aastore
		// @178: getstatic java.lang.String[] game.C_100268_mk.field_106669_b
		// @17B: bipush 46 (0x2E)
		// @17D: getstatic java.lang.String game.C_100249_pc.field_102327_F
		// @180: aastore
		// @181: getstatic java.lang.String[] game.C_100268_mk.field_106669_b
		// @184: bipush 31 (0x1F)
		// @186: getstatic java.lang.String game.C_100066_dl.field_101634_B
		// @189: aastore
		// @18A: getstatic java.lang.String[] game.C_100268_mk.field_106669_b
		// @18D: bipush 16 (0x10)
		// @18F: getstatic java.lang.String[] game.C_100283_ni.field_106756_g
		// @192: iconst_2
		// @193: aaload
		// @194: aastore
		// @195: getstatic java.lang.String[] game.C_100268_mk.field_106669_b
		// @198: bipush 19 (0x13)
		// @19A: getstatic java.lang.String game.C_100255_pj.field_105247_C
		// @19D: aastore
		// @19E: getstatic java.lang.String[] game.C_100268_mk.field_106669_b
		// @1A1: bipush 45 (0x2D)
		// @1A3: getstatic java.lang.String game.C_100016_wi.field_103803_e
		// @1A6: aastore
		// @1A7: getstatic java.lang.String[] game.C_100268_mk.field_106669_b
		// @1AA: bipush 26 (0x1A)
		// @1AC: getstatic java.lang.String game.C_100295_kh.field_105288_f
		// @1AF: aastore
		// @1B0: getstatic java.lang.String[] game.C_100268_mk.field_106669_b
		// @1B3: bipush 30 (0x1E)
		// @1B5: getstatic java.lang.String game.C_100018_wk.field_101552_z
		// @1B8: aastore
		// @1B9: getstatic java.lang.String[] game.C_100268_mk.field_106669_b
		// @1BC: bipush 20 (0x14)
		// @1BE: getstatic java.lang.String game.C_100051_ea.field_103306_T
		// @1C1: aastore
		// @1C2: getstatic java.lang.String[] game.C_100268_mk.field_106669_b
		// @1C5: bipush 38 (0x26)
		// @1C7: ldc ""
		// @1C9: aastore
		// @1CA: getstatic java.lang.String[] game.C_100268_mk.field_106669_b
		// @1CD: bipush 39 (0x27)
		// @1CF: getstatic java.lang.String game.C_100295_kh.field_105292_b
		// @1D2: aastore
		// @1D3: getstatic java.lang.String[] game.C_100268_mk.field_106669_b
		// @1D6: bipush 25 (0x19)
		// @1D8: getstatic java.lang.String game.C_100060_di.field_104272_c
		// @1DB: aastore
		// @1DC: getstatic java.lang.String[] game.C_100268_mk.field_106669_b
		// @1DF: bipush 21 (0x15)
		// @1E1: getstatic java.lang.String game.C_100181_cf.field_105702_g
		// @1E4: aastore
		// @1E5: getstatic java.lang.String[] game.C_100268_mk.field_106669_b
		// @1E8: bipush 41 (0x29)
		// @1EA: getstatic boolean game.C_100034_gi.field_104036_j
		// @1ED: ifeq @1F7
		// @1F0: getstatic java.lang.String game.C_100027_hc.field_102597_P
		// @1F3: goto @1FA
		// @1F6: athrow
		// @1F7: getstatic java.lang.String game.C_100116_ei.field_104122_b
		// @1FA: aastore
		// @1FB: getstatic java.lang.String[] game.C_100268_mk.field_106669_b
		// @1FE: bipush 23 (0x17)
		// @200: getstatic java.lang.String game.C_100091_m.field_104519_h
		// @203: aastore
		// @204: sipush -30945 (0x871F)
		// @207: iconst_1
		// @208: anewarray java.lang.String
		// @20B: dup
		// @20C: iconst_0
		// @20D: getstatic java.lang.String[] game.C_100234_ob.field_106280_z
		// @210: bipush 7 (0x07)
		// @212: aaload
		// @213: getstatic java.lang.String game.C_100220_ac.field_106063_k
		// @216: iload_0
		// @217: sipush 25528 (0x63B8)
		// @21A: ixor
		// @21B: getstatic java.lang.String[] game.C_100234_ob.field_106280_z
		// @21E: iconst_5
		// @21F: aaload
		// @220: invokestatic game.C_100018_wk.func_101497_a(java.lang.String, java.lang.String, int, java.lang.String)java.lang.String
		// @223: aastore
		// @224: getstatic java.lang.String game.C_100281_ng.field_103465_K
		// @227: invokestatic game.C_100132_td.func_104965_a(int, java.lang.String[], java.lang.String)java.lang.String
		// @22A: putstatic java.lang.String game.C_100281_ng.field_103465_K
		// @22D: sipush -30945 (0x871F)
		// @230: iconst_1
		// @231: anewarray java.lang.String
		// @234: dup
		// @235: iconst_0
		// @236: getstatic java.lang.String[] game.C_100234_ob.field_106280_z
		// @239: bipush 7 (0x07)
		// @23B: aaload
		// @23C: getstatic java.lang.String game.C_100033_gj.field_101922_mc
		// @23F: sipush 25557 (0x63D5)
		// @242: getstatic java.lang.String[] game.C_100234_ob.field_106280_z
		// @245: iconst_5
		// @246: aaload
		// @247: invokestatic game.C_100018_wk.func_101497_a(java.lang.String, java.lang.String, int, java.lang.String)java.lang.String
		// @24A: aastore
		// @24B: getstatic java.lang.String game.C_100104_v.field_104698_j
		// @24E: invokestatic game.C_100132_td.func_104965_a(int, java.lang.String[], java.lang.String)java.lang.String
		// @251: putstatic java.lang.String game.C_100104_v.field_104698_j
		// @254: goto @279
		// @257: astore_1
		// @258: aload_1
		// @259: new java.lang.StringBuilder
		// @25C: dup
		// @25D: invokespecial java.lang.StringBuilder.<init>()void
		// @260: getstatic java.lang.String[] game.C_100234_ob.field_106280_z
		// @263: bipush 6 (0x06)
		// @265: aaload
		// @266: invokevirtual java.lang.StringBuilder.append(java.lang.String)java.lang.StringBuilder
		// @269: iload_0
		// @26A: invokevirtual java.lang.StringBuilder.append(int)java.lang.StringBuilder
		// @26D: bipush 41 (0x29)
		// @26F: invokevirtual java.lang.StringBuilder.append(char)java.lang.StringBuilder
		// @272: invokevirtual java.lang.StringBuilder.toString()java.lang.String
		// @275: invokestatic game.C_100181_cf.func_105695_a(java.lang.Throwable, java.lang.String)game.C_100170_cm
		// @278: athrow
		// @279: return
	}
	
	final boolean func_106270_b(byte arg0)
	{
		// @000: getstatic int game.SteelSentinels.field_105275_O
		// @003: istore_3
		// @004: aload_0
		// @005: getfield int game.C_100234_ob.field_106276_e
		// @008: aload_0
		// @009: getfield int game.C_100234_ob.field_106274_g
		// @00C: if_icmpge @0F9
		// @00F: aload_0
		// @010: getfield game.C_100332_ii[] game.C_100234_ob.field_106273_f
		// @013: aload_0
		// @014: getfield int game.C_100234_ob.field_106276_e
		// @017: aaload
		// @018: astore_2
		// @019: aload_2
		// @01A: getfield game.C_100098_h game.C_100332_ii.field_107316_l
		// @01D: iconst_0
		// @01E: invokevirtual game.C_100098_h.func_104597_a(boolean)boolean
		// @021: iload_3
		// @022: ifne @0FA
		// @025: ifne @036
		// @028: goto @02C
		// @02B: athrow
		// @02C: aload_0
		// @02D: bipush -110 (0x92)
		// @02F: aload_2
		// @030: iconst_0
		// @031: invokespecial game.C_100234_ob.func_106271_a(int, game.C_100332_ii, int)void
		// @034: iconst_0
		// @035: ireturn
		// @036: iconst_m1
		// @037: aload_2
		// @038: getfield int game.C_100332_ii.field_107310_e
		// @03B: iconst_m1
		// @03C: ixor
		// @03D: if_icmplt @06F
		// @040: aload_2
		// @041: getfield game.C_100098_h game.C_100332_ii.field_107316_l
		// @044: aload_2
		// @045: getfield int game.C_100332_ii.field_107310_e
		// @048: bipush -125 (0x83)
		// @04A: invokevirtual game.C_100098_h.func_104605_d(int, int)boolean
		// @04D: ifeq @058
		// @050: goto @054
		// @053: athrow
		// @054: goto @06F
		// @057: athrow
		// @058: aload_0
		// @059: bipush -46 (0xD2)
		// @05B: aload_2
		// @05C: aload_2
		// @05D: getfield game.C_100098_h game.C_100332_ii.field_107316_l
		// @060: aload_2
		// @061: getfield int game.C_100332_ii.field_107310_e
		// @064: sipush -12578 (0xCEDE)
		// @067: invokevirtual game.C_100098_h.func_104594_a(int, int)int
		// @06A: invokespecial game.C_100234_ob.func_106271_a(int, game.C_100332_ii, int)void
		// @06D: iconst_0
		// @06E: ireturn
		// @06F: aconst_null
		// @070: aload_2
		// @071: getfield java.lang.String game.C_100332_ii.field_107317_m
		// @074: if_acmpeq @0A6
		// @077: aload_2
		// @078: getfield game.C_100098_h game.C_100332_ii.field_107316_l
		// @07B: aload_2
		// @07C: getfield java.lang.String game.C_100332_ii.field_107317_m
		// @07F: iconst_0
		// @080: invokevirtual game.C_100098_h.func_104593_a(java.lang.String, boolean)boolean
		// @083: ifeq @08E
		// @086: goto @08A
		// @089: athrow
		// @08A: goto @0A6
		// @08D: athrow
		// @08E: aload_0
		// @08F: iload_1
		// @090: bipush -22 (0xEA)
		// @092: iadd
		// @093: aload_2
		// @094: aload_2
		// @095: getfield game.C_100098_h game.C_100332_ii.field_107316_l
		// @098: bipush 124 (0x7C)
		// @09A: aload_2
		// @09B: getfield java.lang.String game.C_100332_ii.field_107317_m
		// @09E: invokevirtual game.C_100098_h.func_104602_a(byte, java.lang.String)int
		// @0A1: invokespecial game.C_100234_ob.func_106271_a(int, game.C_100332_ii, int)void
		// @0A4: iconst_0
		// @0A5: ireturn
		// @0A6: iconst_m1
		// @0A7: aload_2
		// @0A8: getfield int game.C_100332_ii.field_107310_e
		// @0AB: iconst_m1
		// @0AC: ixor
		// @0AD: if_icmpge @0EB
		// @0B0: aconst_null
		// @0B1: aload_2
		// @0B2: getfield java.lang.String game.C_100332_ii.field_107317_m
		// @0B5: if_acmpne @0EB
		// @0B8: goto @0BC
		// @0BB: athrow
		// @0BC: aconst_null
		// @0BD: aload_2
		// @0BE: getfield java.lang.String game.C_100332_ii.field_107318_j
		// @0C1: if_acmpeq @0EB
		// @0C4: goto @0C8
		// @0C7: athrow
		// @0C8: aload_2
		// @0C9: getfield game.C_100098_h game.C_100332_ii.field_107316_l
		// @0CC: iload_1
		// @0CD: bipush 41 (0x29)
		// @0CF: iadd
		// @0D0: invokevirtual game.C_100098_h.func_104598_a(int)boolean
		// @0D3: ifne @0EB
		// @0D6: goto @0DA
		// @0D9: athrow
		// @0DA: aload_0
		// @0DB: bipush -94 (0xA2)
		// @0DD: aload_2
		// @0DE: aload_2
		// @0DF: getfield game.C_100098_h game.C_100332_ii.field_107316_l
		// @0E2: iconst_0
		// @0E3: invokevirtual game.C_100098_h.func_104590_b(boolean)int
		// @0E6: invokespecial game.C_100234_ob.func_106271_a(int, game.C_100332_ii, int)void
		// @0E9: iconst_0
		// @0EA: ireturn
		// @0EB: aload_0
		// @0EC: dup
		// @0ED: getfield int game.C_100234_ob.field_106276_e
		// @0F0: iconst_1
		// @0F1: iadd
		// @0F2: putfield int game.C_100234_ob.field_106276_e
		// @0F5: iload_3
		// @0F6: ifeq @004
		// @0F9: iload_1
		// @0FA: bipush -41 (0xD7)
		// @0FC: if_icmpeq @10B
		// @0FF: aload_0
		// @100: aconst_null
		// @101: checkcast game.C_100332_ii[]
		// @104: putfield game.C_100332_ii[] game.C_100234_ob.field_106273_f
		// @107: goto @10B
		// @10A: athrow
		// @10B: iconst_1
		// @10C: ireturn
		// @10D: astore_2
		// @10E: aload_2
		// @10F: new java.lang.StringBuilder
		// @112: dup
		// @113: invokespecial java.lang.StringBuilder.<init>()void
		// @116: getstatic java.lang.String[] game.C_100234_ob.field_106280_z
		// @119: iconst_4
		// @11A: aaload
		// @11B: invokevirtual java.lang.StringBuilder.append(java.lang.String)java.lang.StringBuilder
		// @11E: iload_1
		// @11F: invokevirtual java.lang.StringBuilder.append(int)java.lang.StringBuilder
		// @122: bipush 41 (0x29)
		// @124: invokevirtual java.lang.StringBuilder.append(char)java.lang.StringBuilder
		// @127: invokevirtual java.lang.StringBuilder.toString()java.lang.String
		// @12A: invokestatic game.C_100181_cf.func_105695_a(java.lang.Throwable, java.lang.String)game.C_100170_cm
		// @12D: athrow
	}
	
	static final C_100037_wb func_106272_a(C_100098_h arg0, int arg1, int arg2, int arg3)
	{
		// @00: iload_1
		// @01: iconst_1
		// @02: aload_0
		// @03: iload_2
		// @04: invokestatic game.C_100333_ij.func_107341_a(int, boolean, game.C_100098_h, int)boolean
		// @07: ifne @0C
		// @0A: aconst_null
		// @0B: areturn
		// @0C: iload_3
		// @0D: sipush 3239 (0x0CA7)
		// @10: if_icmpeq @22
		// @13: aconst_null
		// @14: checkcast java.lang.CharSequence
		// @17: iconst_1
		// @18: ldc 65510 (0xffe6)
		// @1A: invokestatic game.C_100234_ob.func_106269_a(java.lang.CharSequence, boolean, char)boolean
		// @1D: pop
		// @1E: goto @22
		// @21: athrow
		// @22: bipush -50 (0xCE)
		// @24: invokestatic game.C_100158_da.func_100584_a(int)game.C_100037_wb
		// @27: areturn
		// @28: astore #4
		// @2A: aload #4
		// @2C: new java.lang.StringBuilder
		// @2F: dup
		// @30: invokespecial java.lang.StringBuilder.<init>()void
		// @33: getstatic java.lang.String[] game.C_100234_ob.field_106280_z
		// @36: bipush 12 (0x0C)
		// @38: aaload
		// @39: invokevirtual java.lang.StringBuilder.append(java.lang.String)java.lang.StringBuilder
		// @3C: aload_0
		// @3D: ifnull @49
		// @40: getstatic java.lang.String[] game.C_100234_ob.field_106280_z
		// @43: iconst_1
		// @44: aaload
		// @45: goto @4E
		// @48: athrow
		// @49: getstatic java.lang.String[] game.C_100234_ob.field_106280_z
		// @4C: iconst_0
		// @4D: aaload
		// @4E: invokevirtual java.lang.StringBuilder.append(java.lang.String)java.lang.StringBuilder
		// @51: bipush 44 (0x2C)
		// @53: invokevirtual java.lang.StringBuilder.append(char)java.lang.StringBuilder
		// @56: iload_1
		// @57: invokevirtual java.lang.StringBuilder.append(int)java.lang.StringBuilder
		// @5A: bipush 44 (0x2C)
		// @5C: invokevirtual java.lang.StringBuilder.append(char)java.lang.StringBuilder
		// @5F: iload_2
		// @60: invokevirtual java.lang.StringBuilder.append(int)java.lang.StringBuilder
		// @63: bipush 44 (0x2C)
		// @65: invokevirtual java.lang.StringBuilder.append(char)java.lang.StringBuilder
		// @68: iload_3
		// @69: invokevirtual java.lang.StringBuilder.append(int)java.lang.StringBuilder
		// @6C: bipush 41 (0x29)
		// @6E: invokevirtual java.lang.StringBuilder.append(char)java.lang.StringBuilder
		// @71: invokevirtual java.lang.StringBuilder.toString()java.lang.String
		// @74: invokestatic game.C_100181_cf.func_105695_a(java.lang.Throwable, java.lang.String)game.C_100170_cm
		// @77: athrow
	}
	
	static final void func_106265_a(int arg0, int arg1, int arg2, boolean arg3, byte arg4, int arg5, int arg6)
	{
		// @00: getstatic int game.C_100113_ek.field_104880_b
		// @03: iconst_m1
		// @04: ixor
		// @05: bipush -3 (0xFD)
		// @07: if_icmpeq @15
		// @0A: getstatic java.lang.String game.C_100090_l.field_104498_a
		// @0D: astore #7
		// @0F: getstatic int game.SteelSentinels.field_105275_O
		// @12: ifeq @1A
		// @15: getstatic java.lang.String game.C_100260_mc.field_102245_lc
		// @18: astore #7
		// @1A: iload_1
		// @1B: iload_2
		// @1C: sipush -1692 (0xF964)
		// @1F: aload #7
		// @21: iload_0
		// @22: iload #6
		// @24: iload_3
		// @25: iload #5
		// @27: invokestatic game.C_100000_gd.func_100349_a(int, int, int, java.lang.String, int, int, boolean, int)void
		// @2A: iload #4
		// @2C: bipush -52 (0xCC)
		// @2E: if_icmple @3C
		// @31: aconst_null
		// @32: checkcast java.lang.String
		// @35: putstatic java.lang.String game.C_100234_ob.field_106279_a
		// @38: goto @3C
		// @3B: athrow
		// @3C: goto @9C
		// @3F: astore #7
		// @41: aload #7
		// @43: new java.lang.StringBuilder
		// @46: dup
		// @47: invokespecial java.lang.StringBuilder.<init>()void
		// @4A: getstatic java.lang.String[] game.C_100234_ob.field_106280_z
		// @4D: bipush 8 (0x08)
		// @4F: aaload
		// @50: invokevirtual java.lang.StringBuilder.append(java.lang.String)java.lang.StringBuilder
		// @53: iload_0
		// @54: invokevirtual java.lang.StringBuilder.append(int)java.lang.StringBuilder
		// @57: bipush 44 (0x2C)
		// @59: invokevirtual java.lang.StringBuilder.append(char)java.lang.StringBuilder
		// @5C: iload_1
		// @5D: invokevirtual java.lang.StringBuilder.append(int)java.lang.StringBuilder
		// @60: bipush 44 (0x2C)
		// @62: invokevirtual java.lang.StringBuilder.append(char)java.lang.StringBuilder
		// @65: iload_2
		// @66: invokevirtual java.lang.StringBuilder.append(int)java.lang.StringBuilder
		// @69: bipush 44 (0x2C)
		// @6B: invokevirtual java.lang.StringBuilder.append(char)java.lang.StringBuilder
		// @6E: iload_3
		// @6F: invokevirtual java.lang.StringBuilder.append(boolean)java.lang.StringBuilder
		// @72: bipush 44 (0x2C)
		// @74: invokevirtual java.lang.StringBuilder.append(char)java.lang.StringBuilder
		// @77: iload #4
		// @79: invokevirtual java.lang.StringBuilder.append(int)java.lang.StringBuilder
		// @7C: bipush 44 (0x2C)
		// @7E: invokevirtual java.lang.StringBuilder.append(char)java.lang.StringBuilder
		// @81: iload #5
		// @83: invokevirtual java.lang.StringBuilder.append(int)java.lang.StringBuilder
		// @86: bipush 44 (0x2C)
		// @88: invokevirtual java.lang.StringBuilder.append(char)java.lang.StringBuilder
		// @8B: iload #6
		// @8D: invokevirtual java.lang.StringBuilder.append(int)java.lang.StringBuilder
		// @90: bipush 41 (0x29)
		// @92: invokevirtual java.lang.StringBuilder.append(char)java.lang.StringBuilder
		// @95: invokevirtual java.lang.StringBuilder.toString()java.lang.String
		// @98: invokestatic game.C_100181_cf.func_105695_a(java.lang.Throwable, java.lang.String)game.C_100170_cm
		// @9B: athrow
		// @9C: return
	}
	
	static final boolean func_106269_a(CharSequence arg0, boolean arg1, char arg2)
	{
		// @00: iload_2
		// @01: bipush 103 (0x67)
		// @03: invokestatic game.C_100129_tg.func_102732_a(char, int)boolean
		// @06: ifne @0B
		// @09: iconst_0
		// @0A: ireturn
		// @0B: aconst_null
		// @0C: aload_0
		// @0D: if_acmpne @12
		// @10: iconst_0
		// @11: ireturn
		// @12: iload_1
		// @13: iconst_1
		// @14: if_icmpeq @29
		// @17: aconst_null
		// @18: checkcast game.C_100098_h
		// @1B: bipush 12 (0x0C)
		// @1D: bipush -77 (0xB3)
		// @1F: bipush -49 (0xCF)
		// @21: invokestatic game.C_100234_ob.func_106272_a(game.C_100098_h, int, int, int)game.C_100037_wb
		// @24: pop
		// @25: goto @29
		// @28: athrow
		// @29: aload_0
		// @2A: invokeinterface java.lang.CharSequence.length()int
		// @2F: istore_3
		// @30: iload_3
		// @31: bipush 12 (0x0C)
		// @33: if_icmplt @38
		// @36: iconst_0
		// @37: ireturn
		// @38: bipush -96 (0xA0)
		// @3A: iload_2
		// @3B: invokestatic game.C_100053_vn.func_102812_a(int, char)boolean
		// @3E: ifne @45
		// @41: goto @4E
		// @44: athrow
		// @45: iload_3
		// @46: iconst_m1
		// @47: ixor
		// @48: iconst_m1
		// @49: if_icmpne @4E
		// @4C: iconst_0
		// @4D: ireturn
		// @4E: iconst_1
		// @4F: ireturn
		// @50: astore_3
		// @51: aload_3
		// @52: new java.lang.StringBuilder
		// @55: dup
		// @56: invokespecial java.lang.StringBuilder.<init>()void
		// @59: getstatic java.lang.String[] game.C_100234_ob.field_106280_z
		// @5C: iconst_2
		// @5D: aaload
		// @5E: invokevirtual java.lang.StringBuilder.append(java.lang.String)java.lang.StringBuilder
		// @61: aload_0
		// @62: ifnull @6E
		// @65: getstatic java.lang.String[] game.C_100234_ob.field_106280_z
		// @68: iconst_1
		// @69: aaload
		// @6A: goto @73
		// @6D: athrow
		// @6E: getstatic java.lang.String[] game.C_100234_ob.field_106280_z
		// @71: iconst_0
		// @72: aaload
		// @73: invokevirtual java.lang.StringBuilder.append(java.lang.String)java.lang.StringBuilder
		// @76: bipush 44 (0x2C)
		// @78: invokevirtual java.lang.StringBuilder.append(char)java.lang.StringBuilder
		// @7B: iload_1
		// @7C: invokevirtual java.lang.StringBuilder.append(boolean)java.lang.StringBuilder
		// @7F: bipush 44 (0x2C)
		// @81: invokevirtual java.lang.StringBuilder.append(char)java.lang.StringBuilder
		// @84: iload_2
		// @85: invokevirtual java.lang.StringBuilder.append(char)java.lang.StringBuilder
		// @88: bipush 41 (0x29)
		// @8A: invokevirtual java.lang.StringBuilder.append(char)java.lang.StringBuilder
		// @8D: invokevirtual java.lang.StringBuilder.toString()java.lang.String
		// @90: invokestatic game.C_100181_cf.func_105695_a(java.lang.Throwable, java.lang.String)game.C_100170_cm
		// @93: athrow
	}
	
	public static void func_106263_a(int arg0)
	{
		// @00: bipush -33 (0xDF)
		// @02: bipush -27 (0xE5)
		// @04: iload_0
		// @05: isub
		// @06: bipush 40 (0x28)
		// @08: idiv
		// @09: irem
		// @0A: istore_1
		// @0B: aconst_null
		// @0C: putstatic java.lang.String game.C_100234_ob.field_106279_a
		// @0F: goto @34
		// @12: astore_1
		// @13: aload_1
		// @14: new java.lang.StringBuilder
		// @17: dup
		// @18: invokespecial java.lang.StringBuilder.<init>()void
		// @1B: getstatic java.lang.String[] game.C_100234_ob.field_106280_z
		// @1E: bipush 13 (0x0D)
		// @20: aaload
		// @21: invokevirtual java.lang.StringBuilder.append(java.lang.String)java.lang.StringBuilder
		// @24: iload_0
		// @25: invokevirtual java.lang.StringBuilder.append(int)java.lang.StringBuilder
		// @28: bipush 41 (0x29)
		// @2A: invokevirtual java.lang.StringBuilder.append(char)java.lang.StringBuilder
		// @2D: invokevirtual java.lang.StringBuilder.toString()java.lang.String
		// @30: invokestatic game.C_100181_cf.func_105695_a(java.lang.Throwable, java.lang.String)game.C_100170_cm
		// @33: athrow
		// @34: return
	}
	
	private C_100234_ob() throws Throwable
	{
		// @00: aload_0
		// @01: invokespecial java.lang.Object.<init>()void
		// @04: new java.lang.Error
		// @07: dup
		// @08: invokespecial java.lang.Error.<init>()void
		// @0B: athrow
		// @0C: astore_1
		// @0D: aload_1
		// @0E: getstatic java.lang.String[] game.C_100234_ob.field_106280_z
		// @11: bipush 11 (0x0B)
		// @13: aaload
		// @14: invokestatic game.C_100181_cf.func_105695_a(java.lang.Throwable, java.lang.String)game.C_100170_cm
		// @17: athrow
	}
	
	static final boolean func_106268_c(byte arg0)
	{
		// @00: iload_0
		// @01: bipush -25 (0xE7)
		// @03: if_icmpeq @0F
		// @06: bipush 43 (0x2B)
		// @08: invokestatic game.C_100234_ob.func_106263_a(int)void
		// @0B: goto @0F
		// @0E: athrow
		// @0F: getstatic boolean game.C_100010_ff.field_103697_l
		// @12: ireturn
		// @13: astore_1
		// @14: aload_1
		// @15: new java.lang.StringBuilder
		// @18: dup
		// @19: invokespecial java.lang.StringBuilder.<init>()void
		// @1C: getstatic java.lang.String[] game.C_100234_ob.field_106280_z
		// @1F: iconst_3
		// @20: aaload
		// @21: invokevirtual java.lang.StringBuilder.append(java.lang.String)java.lang.StringBuilder
		// @24: iload_0
		// @25: invokevirtual java.lang.StringBuilder.append(int)java.lang.StringBuilder
		// @28: bipush 41 (0x29)
		// @2A: invokevirtual java.lang.StringBuilder.append(char)java.lang.StringBuilder
		// @2D: invokevirtual java.lang.StringBuilder.toString()java.lang.String
		// @30: invokestatic game.C_100181_cf.func_105695_a(java.lang.Throwable, java.lang.String)game.C_100170_cm
		// @33: athrow
	}
	
	static
	{
		// @00: bipush 14 (0x0E)
		// @02: anewarray java.lang.String
		// @05: dup
		// @06: iconst_0
		// @07: ldc "\u00033\u0002x"
		// @09: invokestatic game.C_100234_ob.func_106267_z(java.lang.String)char[]
		// @0C: invokestatic game.C_100234_ob.func_106264_z(char[])java.lang.String
		// @0F: aastore
		// @10: dup
		// @11: iconst_1
		// @12: ldc "\u0016h@:+"
		// @14: invokestatic game.C_100234_ob.func_106267_z(java.lang.String)char[]
		// @17: invokestatic game.C_100234_ob.func_106264_z(char[])java.lang.String
		// @1A: aastore
		// @1B: dup
		// @1C: iconst_2
		// @1D: ldc "\u0002$@Q~"
		// @1F: invokestatic game.C_100234_ob.func_106267_z(java.lang.String)char[]
		// @22: invokestatic game.C_100234_ob.func_106264_z(char[])java.lang.String
		// @25: aastore
		// @26: dup
		// @27: iconst_3
		// @28: ldc "\u0002$@\\~"
		// @2A: invokestatic game.C_100234_ob.func_106267_z(java.lang.String)char[]
		// @2D: invokestatic game.C_100234_ob.func_106264_z(char[])java.lang.String
		// @30: aastore
		// @31: dup
		// @32: iconst_4
		// @33: ldc "\u0002$@W~"
		// @35: invokestatic game.C_100234_ob.func_106267_z(java.lang.String)char[]
		// @38: invokestatic game.C_100234_ob.func_106264_z(char[])java.lang.String
		// @3B: aastore
		// @3C: dup
		// @3D: iconst_5
		// @3E: ldc "Q/\u0003sk_pP"
		// @40: invokestatic game.C_100234_ob.func_106267_z(java.lang.String)char[]
		// @43: invokestatic game.C_100234_ob.func_106264_z(char[])java.lang.String
		// @46: aastore
		// @47: dup
		// @48: bipush 6 (0x06)
		// @4A: ldc "\u0002$@R~"
		// @4C: invokestatic game.C_100234_ob.func_106267_z(java.lang.String)char[]
		// @4F: invokestatic game.C_100234_ob.func_106264_z(char[])java.lang.String
		// @52: aastore
		// @53: dup
		// @54: bipush 7 (0x07)
		// @56: ldc "Q/\u0003sk\\qP"
		// @58: invokestatic game.C_100234_ob.func_106267_z(java.lang.String)char[]
		// @5B: invokestatic game.C_100234_ob.func_106264_z(char[])java.lang.String
		// @5E: aastore
		// @5F: dup
		// @60: bipush 8 (0x08)
		// @62: ldc "\u0002$@S~"
		// @64: invokestatic game.C_100234_ob.func_106267_z(java.lang.String)char[]
		// @67: invokestatic game.C_100234_ob.func_106264_z(char[])java.lang.String
		// @6A: aastore
		// @6B: dup
		// @6C: bipush 9 (0x09)
		// @6E: ldc "MkN"
		// @70: invokestatic game.C_100234_ob.func_106267_z(java.lang.String)char[]
		// @73: invokestatic game.C_100234_ob.func_106264_z(char[])java.lang.String
		// @76: aastore
		// @77: dup
		// @78: bipush 10 (0x0A)
		// @7A: ldc "\u0002$@P~"
		// @7C: invokestatic game.C_100234_ob.func_106267_z(java.lang.String)char[]
		// @7F: invokestatic game.C_100234_ob.func_106264_z(char[])java.lang.String
		// @82: aastore
		// @83: dup
		// @84: bipush 11 (0x0B)
		// @86: ldc "\u0002$@(?\u0003/\u001a*~D"
		// @88: invokestatic game.C_100234_ob.func_106267_z(java.lang.String)char[]
		// @8B: invokestatic game.C_100234_ob.func_106264_z(char[])java.lang.String
		// @8E: aastore
		// @8F: dup
		// @90: bipush 12 (0x0C)
		// @92: ldc "\u0002$@U~"
		// @94: invokestatic game.C_100234_ob.func_106267_z(java.lang.String)char[]
		// @97: invokestatic game.C_100234_ob.func_106264_z(char[])java.lang.String
		// @9A: aastore
		// @9B: dup
		// @9C: bipush 13 (0x0D)
		// @9E: ldc "\u0002$@V~"
		// @A0: invokestatic game.C_100234_ob.func_106267_z(java.lang.String)char[]
		// @A3: invokestatic game.C_100234_ob.func_106264_z(char[])java.lang.String
		// @A6: aastore
		// @A7: putstatic java.lang.String[] game.C_100234_ob.field_106280_z
		// @AA: ldc "<3\u0007w=M\u0005\u0006u\"M!\u000fy3"
		// @AC: invokestatic game.C_100234_ob.func_106267_z(java.lang.String)char[]
		// @AF: invokestatic game.C_100234_ob.func_106264_z(char[])java.lang.String
		// @B2: putstatic java.lang.String game.C_100234_ob.field_106279_a
		// @B5: return
	}
	
	private static char[] func_106267_z(String arg0)
	{
		// @00: aload_0
		// @01: invokevirtual java.lang.String.toCharArray()char[]
		// @04: dup
		// @05: arraylength
		// @06: iconst_2
		// @07: if_icmpge @13
		// @0A: dup
		// @0B: iconst_0
		// @0C: dup2
		// @0D: caload
		// @0E: bipush 86 (0x56)
		// @10: ixor
		// @11: i2c
		// @12: castore
		// @13: areturn
	}
	
	private static String func_106264_z(char[] arg0)
	{
		// @00: aload_0
		// @01: dup
		// @02: arraylength
		// @03: swap
		// @04: iconst_0
		// @05: istore_1
		// @06: goto @4C
		// @09: dup
		// @0A: iload_1
		// @0B: dup2
		// @0C: caload
		// @0D: iload_1
		// @0E: iconst_5
		// @0F: irem
		// @10: tableswitch def: @44, for 0: @30, for 1: @35, for 2: @3A, for 3: @3F
		// @30: bipush 109 (0x6D)
		// @32: goto @46
		// @35: bipush 70 (0x46)
		// @37: goto @46
		// @3A: bipush 110 (0x6E)
		// @3C: goto @46
		// @3F: bipush 20 (0x14)
		// @41: goto @46
		// @44: bipush 86 (0x56)
		// @46: ixor
		// @47: i2c
		// @48: castore
		// @49: iinc #1 +1
		// @4C: swap
		// @4D: dup_x1
		// @4E: iload_1
		// @4F: if_icmpgt @09
		// @52: new java.lang.String
		// @55: dup_x1
		// @56: swap
		// @57: invokespecial java.lang.String.<init>(char[])void
		// @5A: invokevirtual java.lang.String.intern()java.lang.String
		// @5D: areturn
	}
}
