package game;

final class C_100320_hh extends C_100289_jl implements C_100334_ik
{
	static String field_102911_U;
	private C_100077_d field_102921_K;
	static String[][] field_102914_Q;
	private C_100218_am field_102915_P;
	static int[] field_102920_O;
	static boolean[][] field_102912_T;
	static String field_102919_N;
	static String field_102916_S;
	static String field_102918_M;
	static String field_102917_R;
	private static final String[] field_102913_V;
	
	final void func_102528_a(int arg0, int arg1, int arg2, byte arg3)
	{
		// @00: iload #4
		// @02: bipush -126 (0x82)
		// @04: if_icmplt @15
		// @07: aconst_null
		// @08: checkcast boolean[][]
		// @0B: checkcast boolean[][]
		// @0E: putstatic boolean[][] game.C_100320_hh.field_102912_T
		// @11: goto @15
		// @14: athrow
		// @15: aload_0
		// @16: iload_1
		// @17: iload_2
		// @18: iload_3
		// @19: bipush -128 (0x80)
		// @1B: invokespecial game.C_100289_jl.func_102528_a(int, int, int, byte)void
		// @1E: getstatic game.C_100112_r game.C_100318_hj.field_107198_b
		// @21: getstatic java.lang.String game.C_100103_eh.field_104671_k
		// @24: iconst_4
		// @25: aload_0
		// @26: getfield int game.C_100320_hh.field_102538_m
		// @29: iadd
		// @2A: iload_3
		// @2B: iadd
		// @2C: iconst_4
		// @2D: iload_2
		// @2E: aload_0
		// @2F: getfield int game.C_100320_hh.field_102541_w
		// @32: ineg
		// @33: getstatic game.C_100112_r game.C_100318_hj.field_107198_b
		// @36: getfield int game.C_100112_r.field_101772_Q
		// @39: ineg
		// @3A: iadd
		// @3B: isub
		// @3C: iadd
		// @3D: ldc 16777215 (0xffffff)
		// @3F: iconst_m1
		// @40: invokevirtual game.C_100112_r.func_101749_c(java.lang.String, int, int, int, int)void
		// @43: goto @86
		// @46: astore #5
		// @48: aload #5
		// @4A: new java.lang.StringBuilder
		// @4D: dup
		// @4E: invokespecial java.lang.StringBuilder.<init>()void
		// @51: getstatic java.lang.String[] game.C_100320_hh.field_102913_V
		// @54: bipush 8 (0x08)
		// @56: aaload
		// @57: invokevirtual java.lang.StringBuilder.append(java.lang.String)java.lang.StringBuilder
		// @5A: iload_1
		// @5B: invokevirtual java.lang.StringBuilder.append(int)java.lang.StringBuilder
		// @5E: bipush 44 (0x2C)
		// @60: invokevirtual java.lang.StringBuilder.append(char)java.lang.StringBuilder
		// @63: iload_2
		// @64: invokevirtual java.lang.StringBuilder.append(int)java.lang.StringBuilder
		// @67: bipush 44 (0x2C)
		// @69: invokevirtual java.lang.StringBuilder.append(char)java.lang.StringBuilder
		// @6C: iload_3
		// @6D: invokevirtual java.lang.StringBuilder.append(int)java.lang.StringBuilder
		// @70: bipush 44 (0x2C)
		// @72: invokevirtual java.lang.StringBuilder.append(char)java.lang.StringBuilder
		// @75: iload #4
		// @77: invokevirtual java.lang.StringBuilder.append(int)java.lang.StringBuilder
		// @7A: bipush 41 (0x29)
		// @7C: invokevirtual java.lang.StringBuilder.append(char)java.lang.StringBuilder
		// @7F: invokevirtual java.lang.StringBuilder.toString()java.lang.String
		// @82: invokestatic game.C_100181_cf.func_105695_a(java.lang.Throwable, java.lang.String)game.C_100170_cm
		// @85: athrow
		// @86: return
	}
	
	public final void func_102581_a(int arg0, int arg1, byte arg2, C_100218_am arg3, int arg4)
	{
		// @00: aload_0
		// @01: getfield game.C_100077_d game.C_100320_hh.field_102921_K
		// @04: iconst_1
		// @05: invokevirtual game.C_100077_d.func_103100_a(boolean)game.C_100308_lh
		// @08: bipush 77 (0x4D)
		// @0A: invokeinterface game.C_100308_lh.func_102950_a(byte)game.C_100133_tk
		// @0F: getstatic game.C_100133_tk game.C_100079_e.field_102670_tb
		// @12: if_acmpne @18
		// @15: goto @19
		// @18: return
		// @19: bipush 123 (0x7B)
		// @1B: aload_0
		// @1C: getfield game.C_100077_d game.C_100320_hh.field_102921_K
		// @1F: bipush -104 (0x98)
		// @21: invokevirtual game.C_100077_d.func_103299_k(int)int
		// @24: aload_0
		// @25: getfield game.C_100077_d game.C_100320_hh.field_102921_K
		// @28: iconst_m1
		// @29: invokevirtual game.C_100077_d.func_103303_n(int)int
		// @2C: aload_0
		// @2D: getfield game.C_100077_d game.C_100320_hh.field_102921_K
		// @30: bipush -111 (0x91)
		// @32: invokevirtual game.C_100077_d.func_103300_a(byte)int
		// @35: invokestatic game.C_100243_pd.func_106354_a(byte, int, int, int)void
		// @38: bipush -109 (0x93)
		// @3A: bipush -2 (0xFE)
		// @3C: iload_3
		// @3D: isub
		// @3E: bipush 52 (0x34)
		// @40: idiv
		// @41: irem
		// @42: istore #6
		// @44: goto @A1
		// @47: astore #6
		// @49: aload #6
		// @4B: new java.lang.StringBuilder
		// @4E: dup
		// @4F: invokespecial java.lang.StringBuilder.<init>()void
		// @52: getstatic java.lang.String[] game.C_100320_hh.field_102913_V
		// @55: iconst_5
		// @56: aaload
		// @57: invokevirtual java.lang.StringBuilder.append(java.lang.String)java.lang.StringBuilder
		// @5A: iload_1
		// @5B: invokevirtual java.lang.StringBuilder.append(int)java.lang.StringBuilder
		// @5E: bipush 44 (0x2C)
		// @60: invokevirtual java.lang.StringBuilder.append(char)java.lang.StringBuilder
		// @63: iload_2
		// @64: invokevirtual java.lang.StringBuilder.append(int)java.lang.StringBuilder
		// @67: bipush 44 (0x2C)
		// @69: invokevirtual java.lang.StringBuilder.append(char)java.lang.StringBuilder
		// @6C: iload_3
		// @6D: invokevirtual java.lang.StringBuilder.append(int)java.lang.StringBuilder
		// @70: bipush 44 (0x2C)
		// @72: invokevirtual java.lang.StringBuilder.append(char)java.lang.StringBuilder
		// @75: aload #4
		// @77: ifnull @83
		// @7A: getstatic java.lang.String[] game.C_100320_hh.field_102913_V
		// @7D: iconst_1
		// @7E: aaload
		// @7F: goto @88
		// @82: athrow
		// @83: getstatic java.lang.String[] game.C_100320_hh.field_102913_V
		// @86: iconst_0
		// @87: aaload
		// @88: invokevirtual java.lang.StringBuilder.append(java.lang.String)java.lang.StringBuilder
		// @8B: bipush 44 (0x2C)
		// @8D: invokevirtual java.lang.StringBuilder.append(char)java.lang.StringBuilder
		// @90: iload #5
		// @92: invokevirtual java.lang.StringBuilder.append(int)java.lang.StringBuilder
		// @95: bipush 41 (0x29)
		// @97: invokevirtual java.lang.StringBuilder.append(char)java.lang.StringBuilder
		// @9A: invokevirtual java.lang.StringBuilder.toString()java.lang.String
		// @9D: invokestatic game.C_100181_cf.func_105695_a(java.lang.Throwable, java.lang.String)game.C_100170_cm
		// @A0: athrow
		// @A1: return
	}
	
	static final C_100096_un func_102907_a(int arg0, String[] arg1)
	{
		// @00: new game.C_100096_un
		// @03: dup
		// @04: iconst_0
		// @05: invokespecial game.C_100096_un.<init>(boolean)void
		// @08: astore_2
		// @09: iload_0
		// @0A: bipush -25 (0xE7)
		// @0C: if_icmpeq @1D
		// @0F: iconst_0
		// @10: bipush -66 (0xBE)
		// @12: bipush 22 (0x16)
		// @14: bipush 14 (0x0E)
		// @16: invokestatic game.C_100320_hh.func_102910_a(boolean, int, byte, int)void
		// @19: goto @1D
		// @1C: athrow
		// @1D: aload_2
		// @1E: aload_1
		// @1F: putfield java.lang.String[] game.C_100096_un.field_104571_i
		// @22: aload_2
		// @23: areturn
		// @24: astore_2
		// @25: aload_2
		// @26: new java.lang.StringBuilder
		// @29: dup
		// @2A: invokespecial java.lang.StringBuilder.<init>()void
		// @2D: getstatic java.lang.String[] game.C_100320_hh.field_102913_V
		// @30: iconst_2
		// @31: aaload
		// @32: invokevirtual java.lang.StringBuilder.append(java.lang.String)java.lang.StringBuilder
		// @35: iload_0
		// @36: invokevirtual java.lang.StringBuilder.append(int)java.lang.StringBuilder
		// @39: bipush 44 (0x2C)
		// @3B: invokevirtual java.lang.StringBuilder.append(char)java.lang.StringBuilder
		// @3E: aload_1
		// @3F: ifnull @4B
		// @42: getstatic java.lang.String[] game.C_100320_hh.field_102913_V
		// @45: iconst_1
		// @46: aaload
		// @47: goto @50
		// @4A: athrow
		// @4B: getstatic java.lang.String[] game.C_100320_hh.field_102913_V
		// @4E: iconst_0
		// @4F: aaload
		// @50: invokevirtual java.lang.StringBuilder.append(java.lang.String)java.lang.StringBuilder
		// @53: bipush 41 (0x29)
		// @55: invokevirtual java.lang.StringBuilder.append(char)java.lang.StringBuilder
		// @58: invokevirtual java.lang.StringBuilder.toString()java.lang.String
		// @5B: invokestatic game.C_100181_cf.func_105695_a(java.lang.Throwable, java.lang.String)game.C_100170_cm
		// @5E: athrow
	}
	
	final void func_102513_a(C_100336_im arg0, int arg1, int arg2, int arg3)
	{
		// @00: aload_0
		// @01: aload_1
		// @02: iload_2
		// @03: iload_3
		// @04: iconst_0
		// @05: ixor
		// @06: iload #4
		// @08: invokespecial game.C_100289_jl.func_102513_a(game.C_100336_im, int, int, int)void
		// @0B: iload_3
		// @0C: iconst_2
		// @0D: if_icmpeq @11
		// @10: return
		// @11: aload_0
		// @12: getfield game.C_100218_am game.C_100320_hh.field_102915_P
		// @15: aload_0
		// @16: getfield game.C_100077_d game.C_100320_hh.field_102921_K
		// @19: iconst_1
		// @1A: invokevirtual game.C_100077_d.func_103100_a(boolean)game.C_100308_lh
		// @1D: bipush 77 (0x4D)
		// @1F: invokeinterface game.C_100308_lh.func_102950_a(byte)game.C_100133_tk
		// @24: getstatic game.C_100133_tk game.C_100079_e.field_102670_tb
		// @27: if_acmpne @2F
		// @2A: iconst_1
		// @2B: goto @30
		// @2E: athrow
		// @2F: iconst_0
		// @30: putfield boolean game.C_100218_am.field_103113_L
		// @33: goto @87
		// @36: astore #5
		// @38: aload #5
		// @3A: new java.lang.StringBuilder
		// @3D: dup
		// @3E: invokespecial java.lang.StringBuilder.<init>()void
		// @41: getstatic java.lang.String[] game.C_100320_hh.field_102913_V
		// @44: bipush 9 (0x09)
		// @46: aaload
		// @47: invokevirtual java.lang.StringBuilder.append(java.lang.String)java.lang.StringBuilder
		// @4A: aload_1
		// @4B: ifnull @57
		// @4E: getstatic java.lang.String[] game.C_100320_hh.field_102913_V
		// @51: iconst_1
		// @52: aaload
		// @53: goto @5C
		// @56: athrow
		// @57: getstatic java.lang.String[] game.C_100320_hh.field_102913_V
		// @5A: iconst_0
		// @5B: aaload
		// @5C: invokevirtual java.lang.StringBuilder.append(java.lang.String)java.lang.StringBuilder
		// @5F: bipush 44 (0x2C)
		// @61: invokevirtual java.lang.StringBuilder.append(char)java.lang.StringBuilder
		// @64: iload_2
		// @65: invokevirtual java.lang.StringBuilder.append(int)java.lang.StringBuilder
		// @68: bipush 44 (0x2C)
		// @6A: invokevirtual java.lang.StringBuilder.append(char)java.lang.StringBuilder
		// @6D: iload_3
		// @6E: invokevirtual java.lang.StringBuilder.append(int)java.lang.StringBuilder
		// @71: bipush 44 (0x2C)
		// @73: invokevirtual java.lang.StringBuilder.append(char)java.lang.StringBuilder
		// @76: iload #4
		// @78: invokevirtual java.lang.StringBuilder.append(int)java.lang.StringBuilder
		// @7B: bipush 41 (0x29)
		// @7D: invokevirtual java.lang.StringBuilder.append(char)java.lang.StringBuilder
		// @80: invokevirtual java.lang.StringBuilder.toString()java.lang.String
		// @83: invokestatic game.C_100181_cf.func_105695_a(java.lang.Throwable, java.lang.String)game.C_100170_cm
		// @86: athrow
		// @87: return
	}
	
	final void func_102892_i(int arg0)
	{
		// @00: iload_1
		// @01: bipush -122 (0x86)
		// @03: if_icmplt @0F
		// @06: bipush 64 (0x40)
		// @08: invokestatic game.C_100320_hh.func_102906_l(int)void
		// @0B: goto @0F
		// @0E: athrow
		// @0F: sipush 250 (0x00FA)
		// @12: istore_2
		// @13: aload_0
		// @14: getfield game.C_100077_d game.C_100320_hh.field_102921_K
		// @17: bipush 25 (0x19)
		// @19: bipush 20 (0x14)
		// @1B: aload_0
		// @1C: getfield int game.C_100320_hh.field_102544_t
		// @1F: iadd
		// @20: bipush -25 (0xE7)
		// @22: iadd
		// @23: ldc -184967519 (0xf4f99ea1)
		// @25: ishr
		// @26: aload_0
		// @27: getfield int game.C_100320_hh.field_102537_l
		// @2A: iload_2
		// @2B: isub
		// @2C: ldc 1531927137 (0x5b4f5a61)
		// @2E: ishr
		// @2F: sipush 140 (0x008C)
		// @32: bipush -60 (0xC4)
		// @34: invokevirtual game.C_100077_d.func_102524_a(int, int, int, int, byte)void
		// @37: aload_0
		// @38: getfield game.C_100218_am game.C_100320_hh.field_102915_P
		// @3B: bipush 30 (0x1E)
		// @3D: bipush -10 (0xF6)
		// @3F: aload_0
		// @40: getfield int game.C_100320_hh.field_102544_t
		// @43: iadd
		// @44: ldc -692326687 (0xd6bbeee1)
		// @46: ishr
		// @47: iconst_2
		// @48: iadd
		// @49: sipush 150 (0x0096)
		// @4C: aload_0
		// @4D: getfield int game.C_100320_hh.field_102537_l
		// @50: iload_2
		// @51: ineg
		// @52: iadd
		// @53: ldc 1778662849 (0x6a043dc1)
		// @55: ishr
		// @56: iadd
		// @57: bipush 100 (0x64)
		// @59: bipush -79 (0xB1)
		// @5B: invokevirtual game.C_100218_am.func_102524_a(int, int, int, int, byte)void
		// @5E: goto @82
		// @61: astore_2
		// @62: aload_2
		// @63: new java.lang.StringBuilder
		// @66: dup
		// @67: invokespecial java.lang.StringBuilder.<init>()void
		// @6A: getstatic java.lang.String[] game.C_100320_hh.field_102913_V
		// @6D: iconst_4
		// @6E: aaload
		// @6F: invokevirtual java.lang.StringBuilder.append(java.lang.String)java.lang.StringBuilder
		// @72: iload_1
		// @73: invokevirtual java.lang.StringBuilder.append(int)java.lang.StringBuilder
		// @76: bipush 41 (0x29)
		// @78: invokevirtual java.lang.StringBuilder.append(char)java.lang.StringBuilder
		// @7B: invokevirtual java.lang.StringBuilder.toString()java.lang.String
		// @7E: invokestatic game.C_100181_cf.func_105695_a(java.lang.Throwable, java.lang.String)game.C_100170_cm
		// @81: athrow
		// @82: return
	}
	
	C_100320_hh(int arg0, int arg1, int arg2, int arg3)
	{
		// @00: aload_0
		// @01: iload_1
		// @02: iload_2
		// @03: iload_3
		// @04: iload #4
		// @06: aconst_null
		// @07: invokespecial game.C_100289_jl.<init>(int, int, int, int, game.C_100326_ic)void
		// @0A: aload_0
		// @0B: new game.C_100077_d
		// @0E: dup
		// @0F: new game.C_100114_q
		// @12: dup
		// @13: ldc 10000536 (0x989898)
		// @15: invokespecial game.C_100114_q.<init>(int)void
		// @18: getstatic boolean game.C_100195_rc.field_105773_c
		// @1B: iconst_0
		// @1C: iconst_0
		// @1D: sipush 140 (0x008C)
		// @20: bipush 25 (0x19)
		// @22: invokespecial game.C_100077_d.<init>(game.C_100326_ic, boolean, int, int, int, int)void
		// @25: putfield game.C_100077_d game.C_100320_hh.field_102921_K
		// @28: aload_0
		// @29: getfield game.C_100077_d game.C_100320_hh.field_102921_K
		// @2C: new game.C_100275_na
		// @2F: dup
		// @30: invokespecial game.C_100275_na.<init>()void
		// @33: bipush -124 (0x84)
		// @35: invokevirtual game.C_100077_d.func_103296_a(game.C_100275_na, int)void
		// @38: aload_0
		// @39: new game.C_100218_am
		// @3C: dup
		// @3D: getstatic java.lang.String game.C_100272_mn.field_102429_M
		// @40: aload_0
		// @41: invokespecial game.C_100218_am.<init>(java.lang.String, game.C_100337_in)void
		// @44: putfield game.C_100218_am game.C_100320_hh.field_102915_P
		// @47: aload_0
		// @48: iconst_2
		// @49: anewarray game.C_100336_im
		// @4C: dup
		// @4D: iconst_0
		// @4E: aload_0
		// @4F: getfield game.C_100077_d game.C_100320_hh.field_102921_K
		// @52: aastore
		// @53: dup
		// @54: iconst_1
		// @55: aload_0
		// @56: getfield game.C_100218_am game.C_100320_hh.field_102915_P
		// @59: aastore
		// @5A: putfield game.C_100336_im[] game.C_100320_hh.field_102903_I
		// @5D: aload_0
		// @5E: getfield game.C_100218_am game.C_100320_hh.field_102915_P
		// @61: new game.C_100310_lj
		// @64: dup
		// @65: invokespecial game.C_100310_lj.<init>()void
		// @68: putfield game.C_100326_ic game.C_100218_am.field_102533_B
		// @6B: aload_0
		// @6C: sipush 10945 (0x2AC1)
		// @6F: invokevirtual game.C_100320_hh.func_102530_f(int)void
		// @72: goto @B4
		// @75: astore #5
		// @77: aload #5
		// @79: new java.lang.StringBuilder
		// @7C: dup
		// @7D: invokespecial java.lang.StringBuilder.<init>()void
		// @80: getstatic java.lang.String[] game.C_100320_hh.field_102913_V
		// @83: iconst_3
		// @84: aaload
		// @85: invokevirtual java.lang.StringBuilder.append(java.lang.String)java.lang.StringBuilder
		// @88: iload_1
		// @89: invokevirtual java.lang.StringBuilder.append(int)java.lang.StringBuilder
		// @8C: bipush 44 (0x2C)
		// @8E: invokevirtual java.lang.StringBuilder.append(char)java.lang.StringBuilder
		// @91: iload_2
		// @92: invokevirtual java.lang.StringBuilder.append(int)java.lang.StringBuilder
		// @95: bipush 44 (0x2C)
		// @97: invokevirtual java.lang.StringBuilder.append(char)java.lang.StringBuilder
		// @9A: iload_3
		// @9B: invokevirtual java.lang.StringBuilder.append(int)java.lang.StringBuilder
		// @9E: bipush 44 (0x2C)
		// @A0: invokevirtual java.lang.StringBuilder.append(char)java.lang.StringBuilder
		// @A3: iload #4
		// @A5: invokevirtual java.lang.StringBuilder.append(int)java.lang.StringBuilder
		// @A8: bipush 41 (0x29)
		// @AA: invokevirtual java.lang.StringBuilder.append(char)java.lang.StringBuilder
		// @AD: invokevirtual java.lang.StringBuilder.toString()java.lang.String
		// @B0: invokestatic game.C_100181_cf.func_105695_a(java.lang.Throwable, java.lang.String)game.C_100170_cm
		// @B3: athrow
		// @B4: return
	}
	
	static final void func_102910_a(boolean arg0, int arg1, byte arg2, int arg3)
	{
		// @000: getstatic int game.SteelSentinels.field_105275_O
		// @003: istore #7
		// @005: getstatic int game.C_100239_oi.field_102312_P
		// @008: iconst_m1
		// @009: ixor
		// @00A: getstatic int game.C_100038_wa.field_104077_j
		// @00D: iconst_m1
		// @00E: ixor
		// @00F: if_icmpge @01E
		// @012: getstatic int game.C_100038_wa.field_104077_j
		// @015: iconst_1
		// @016: iadd
		// @017: putstatic int game.C_100038_wa.field_104077_j
		// @01A: goto @01E
		// @01D: athrow
		// @01E: getstatic int game.C_100280_nf.field_101173_s
		// @021: getstatic game.C_100185_rm game.C_100049_vf.field_104206_l
		// @024: getfield int game.C_100185_rm.field_105491_i
		// @027: if_icmpne @02E
		// @02A: goto @049
		// @02D: athrow
		// @02E: getstatic int game.C_100303_kk.field_104788_o
		// @031: getstatic game.C_100185_rm game.C_100049_vf.field_104206_l
		// @034: getfield int game.C_100185_rm.field_105491_i
		// @037: getstatic int game.C_100280_nf.field_101173_s
		// @03A: ineg
		// @03B: iadd
		// @03C: iadd
		// @03D: putstatic int game.C_100303_kk.field_104788_o
		// @040: getstatic game.C_100185_rm game.C_100049_vf.field_104206_l
		// @043: getfield int game.C_100185_rm.field_105491_i
		// @046: putstatic int game.C_100280_nf.field_101173_s
		// @049: iconst_0
		// @04A: getstatic int game.C_100038_wa.field_104077_j
		// @04D: if_icmplt @051
		// @050: return
		// @051: sipush 22547 (0x5813)
		// @054: invokestatic game.C_100327_ib.func_102468_p(int)void
		// @057: getstatic game.C_100302_ka game.C_100265_mh.field_106621_l
		// @05A: iload_0
		// @05B: bipush -111 (0x91)
		// @05D: invokevirtual game.C_100302_ka.func_101819_a(boolean, byte)void
		// @060: iload_2
		// @061: bipush 55 (0x37)
		// @063: if_icmpgt @067
		// @066: return
		// @067: getstatic game.C_100320_hh game.C_100047_vh.field_104150_d
		// @06A: ifnull @09F
		// @06D: getstatic boolean game.C_100272_mn.field_102435_K
		// @070: ifeq @097
		// @073: goto @077
		// @076: athrow
		// @077: getstatic game.C_100320_hh game.C_100047_vh.field_104150_d
		// @07A: getstatic game.C_100302_ka game.C_100265_mh.field_106621_l
		// @07D: getfield int game.C_100302_ka.field_101835_xb
		// @080: iload_0
		// @081: getstatic game.C_100302_ka game.C_100265_mh.field_106621_l
		// @084: getfield int game.C_100302_ka.field_101840_Eb
		// @087: sipush -2408 (0xF698)
		// @08A: invokevirtual game.C_100320_hh.func_102529_a(int, boolean, int, int)boolean
		// @08D: pop
		// @08E: iload #7
		// @090: ifeq @09F
		// @093: goto @097
		// @096: athrow
		// @097: aconst_null
		// @098: putstatic game.C_100320_hh game.C_100047_vh.field_104150_d
		// @09B: goto @09F
		// @09E: athrow
		// @09F: iconst_0
		// @0A0: istore #4
		// @0A2: iconst_5
		// @0A3: iload #4
		// @0A5: if_icmple @108
		// @0A8: getstatic game.C_100302_ka[] game.C_100152_bd.field_105211_i
		// @0AB: iload #4
		// @0AD: aaload
		// @0AE: astore #5
		// @0B0: iload #7
		// @0B2: ifne @118
		// @0B5: aconst_null
		// @0B6: aload #5
		// @0B8: if_acmpeq @100
		// @0BB: goto @0BF
		// @0BE: athrow
		// @0BF: aload #5
		// @0C1: getfield int game.C_100302_ka.field_101854_N
		// @0C4: ifeq @0D8
		// @0C7: goto @0CB
		// @0CA: athrow
		// @0CB: aload #5
		// @0CD: bipush 105 (0x69)
		// @0CF: iload #4
		// @0D1: invokestatic game.C_100127_tl.func_104940_a(game.C_100302_ka, int, int)void
		// @0D4: goto @0D8
		// @0D7: athrow
		// @0D8: sipush 5308 (0x14BC)
		// @0DB: iload #4
		// @0DD: invokestatic game.C_100218_am.func_103108_a(int, int)int
		// @0E0: istore #6
		// @0E2: getstatic game.C_100302_ka[] game.C_100067_vd.field_104323_h
		// @0E5: iload #4
		// @0E7: aaload
		// @0E8: getstatic game.C_100037_wb[] game.C_100165_sh.field_100771_q
		// @0EB: iload #6
		// @0ED: aaload
		// @0EE: putfield game.C_100037_wb game.C_100302_ka.field_101887_nb
		// @0F1: getstatic game.C_100302_ka[] game.C_100288_jn.field_106845_a
		// @0F4: iload #4
		// @0F6: aaload
		// @0F7: getstatic java.lang.String[] game.C_100000_gd.field_100360_a
		// @0FA: iload #6
		// @0FC: aaload
		// @0FD: putfield java.lang.String game.C_100302_ka.field_101890_ab
		// @100: iinc #4 +1
		// @103: iload #7
		// @105: ifeq @0A2
		// @108: getstatic game.C_100302_ka game.C_100031_gl.field_103963_g
		// @10B: getfield int game.C_100302_ka.field_101854_N
		// @10E: iconst_m1
		// @10F: ixor
		// @110: iconst_m1
		// @111: if_icmpne @118
		// @114: goto @14F
		// @117: athrow
		// @118: new game.C_100260_mc
		// @11B: dup
		// @11C: getstatic game.C_100302_ka game.C_100031_gl.field_103963_g
		// @11F: getfield int game.C_100302_ka.field_101840_Eb
		// @122: getstatic game.C_100302_ka game.C_100031_gl.field_103963_g
		// @125: getfield int game.C_100302_ka.field_101835_xb
		// @128: getstatic game.C_100302_ka game.C_100031_gl.field_103963_g
		// @12B: getfield int game.C_100302_ka.field_101886_Kb
		// @12E: getstatic game.C_100302_ka game.C_100031_gl.field_103963_g
		// @131: getfield int game.C_100302_ka.field_101848_lb
		// @134: iload_3
		// @135: getstatic game.C_100302_ka game.C_100097_k.field_104578_f
		// @138: getstatic game.C_100302_ka game.C_100151_bc.field_102932_cb
		// @13B: getstatic game.C_100302_ka game.C_100164_se.field_105456_h
		// @13E: getstatic game.C_100302_ka game.C_100129_tg.field_102750_sb
		// @141: getstatic game.C_100122_em game.C_100119_ua.field_104902_b
		// @144: getstatic game.C_100302_ka game.C_100236_on.field_100906_r
		// @147: aconst_null
		// @148: lconst_0
		// @149: invokespecial game.C_100260_mc.<init>(int, int, int, int, int, game.C_100302_ka, game.C_100302_ka, game.C_100302_ka, game.C_100302_ka, game.C_100122_em, game.C_100302_ka, java.lang.String, long)void
		// @14C: putstatic game.C_100260_mc game.C_100228_nn.field_106189_c
		// @14F: iconst_5
		// @150: iload_1
		// @151: getstatic int game.C_100244_pe.field_106375_d
		// @154: getstatic int game.C_100033_gj.field_101917_jc
		// @157: invokestatic game.C_100298_ke.func_103207_b(int, int, int, int)game.C_100240_oj
		// @15A: astore #4
		// @15C: aconst_null
		// @15D: aload #4
		// @15F: if_acmpne @166
		// @162: goto @16D
		// @165: athrow
		// @166: aload #4
		// @168: bipush 122 (0x7A)
		// @16A: invokestatic game.C_100101_fc.func_103389_a(game.C_100240_oj, int)void
		// @16D: bipush 126 (0x7E)
		// @16F: invokestatic game.C_100238_ol.func_101686_d(byte)java.lang.String
		// @172: astore #5
		// @174: aconst_null
		// @175: aload #5
		// @177: if_acmpeq @183
		// @17A: aload #5
		// @17C: putstatic java.lang.String game.C_100321_hi.field_107220_c
		// @17F: goto @183
		// @182: athrow
		// @183: goto @1C5
		// @186: astore #4
		// @188: aload #4
		// @18A: new java.lang.StringBuilder
		// @18D: dup
		// @18E: invokespecial java.lang.StringBuilder.<init>()void
		// @191: getstatic java.lang.String[] game.C_100320_hh.field_102913_V
		// @194: bipush 7 (0x07)
		// @196: aaload
		// @197: invokevirtual java.lang.StringBuilder.append(java.lang.String)java.lang.StringBuilder
		// @19A: iload_0
		// @19B: invokevirtual java.lang.StringBuilder.append(boolean)java.lang.StringBuilder
		// @19E: bipush 44 (0x2C)
		// @1A0: invokevirtual java.lang.StringBuilder.append(char)java.lang.StringBuilder
		// @1A3: iload_1
		// @1A4: invokevirtual java.lang.StringBuilder.append(int)java.lang.StringBuilder
		// @1A7: bipush 44 (0x2C)
		// @1A9: invokevirtual java.lang.StringBuilder.append(char)java.lang.StringBuilder
		// @1AC: iload_2
		// @1AD: invokevirtual java.lang.StringBuilder.append(int)java.lang.StringBuilder
		// @1B0: bipush 44 (0x2C)
		// @1B2: invokevirtual java.lang.StringBuilder.append(char)java.lang.StringBuilder
		// @1B5: iload_3
		// @1B6: invokevirtual java.lang.StringBuilder.append(int)java.lang.StringBuilder
		// @1B9: bipush 41 (0x29)
		// @1BB: invokevirtual java.lang.StringBuilder.append(char)java.lang.StringBuilder
		// @1BE: invokevirtual java.lang.StringBuilder.toString()java.lang.String
		// @1C1: invokestatic game.C_100181_cf.func_105695_a(java.lang.Throwable, java.lang.String)game.C_100170_cm
		// @1C4: athrow
		// @1C5: return
	}
	
	public static void func_102906_l(int arg0)
	{
		// @00: aconst_null
		// @01: checkcast java.lang.String[][]
		// @04: putstatic java.lang.String[][] game.C_100320_hh.field_102914_Q
		// @07: aconst_null
		// @08: putstatic java.lang.String game.C_100320_hh.field_102916_S
		// @0B: aconst_null
		// @0C: checkcast boolean[][]
		// @0F: putstatic boolean[][] game.C_100320_hh.field_102912_T
		// @12: aconst_null
		// @13: putstatic java.lang.String game.C_100320_hh.field_102911_U
		// @16: aconst_null
		// @17: putstatic java.lang.String game.C_100320_hh.field_102919_N
		// @1A: aconst_null
		// @1B: putstatic java.lang.String game.C_100320_hh.field_102918_M
		// @1E: aconst_null
		// @1F: putstatic int[] game.C_100320_hh.field_102920_O
		// @22: iload_0
		// @23: sipush 250 (0x00FA)
		// @26: if_icmpeq @37
		// @29: bipush -7 (0xF9)
		// @2B: aconst_null
		// @2C: checkcast java.lang.String[]
		// @2F: invokestatic game.C_100320_hh.func_102907_a(int, java.lang.String[])game.C_100096_un
		// @32: pop
		// @33: goto @37
		// @36: athrow
		// @37: aconst_null
		// @38: putstatic java.lang.String game.C_100320_hh.field_102917_R
		// @3B: goto @60
		// @3E: astore_1
		// @3F: aload_1
		// @40: new java.lang.StringBuilder
		// @43: dup
		// @44: invokespecial java.lang.StringBuilder.<init>()void
		// @47: getstatic java.lang.String[] game.C_100320_hh.field_102913_V
		// @4A: bipush 6 (0x06)
		// @4C: aaload
		// @4D: invokevirtual java.lang.StringBuilder.append(java.lang.String)java.lang.StringBuilder
		// @50: iload_0
		// @51: invokevirtual java.lang.StringBuilder.append(int)java.lang.StringBuilder
		// @54: bipush 41 (0x29)
		// @56: invokevirtual java.lang.StringBuilder.append(char)java.lang.StringBuilder
		// @59: invokevirtual java.lang.StringBuilder.toString()java.lang.String
		// @5C: invokestatic game.C_100181_cf.func_105695_a(java.lang.Throwable, java.lang.String)game.C_100170_cm
		// @5F: athrow
		// @60: return
	}
	
	static
	{
		// @000: bipush 10 (0x0A)
		// @002: anewarray java.lang.String
		// @005: dup
		// @006: iconst_0
		// @007: ldc "b\u000e[\t"
		// @009: invokestatic game.C_100320_hh.func_102909_z(java.lang.String)char[]
		// @00C: invokestatic game.C_100320_hh.func_102908_z(char[])java.lang.String
		// @00F: aastore
		// @010: dup
		// @011: iconst_1
		// @012: ldc "wU\u0019K\u0014"
		// @014: invokestatic game.C_100320_hh.func_102909_z(java.lang.String)char[]
		// @017: invokestatic game.C_100320_hh.func_102908_z(char[])java.lang.String
		// @01A: aastore
		// @01B: dup
		// @01C: iconst_2
		// @01D: ldc "d\u0013\u0019-($"
		// @01F: invokestatic game.C_100320_hh.func_102909_z(java.lang.String)char[]
		// @022: invokestatic game.C_100320_hh.func_102908_z(char[])java.lang.String
		// @025: aastore
		// @026: dup
		// @027: iconst_3
		// @028: ldc "d\u0013\u0019Y\u0000b\u0012C[A"
		// @02A: invokestatic game.C_100320_hh.func_102909_z(java.lang.String)char[]
		// @02D: invokestatic game.C_100320_hh.func_102908_z(char[])java.lang.String
		// @030: aastore
		// @031: dup
		// @032: iconst_4
		// @033: ldc "d\u0013\u0019\"($"
		// @035: invokestatic game.C_100320_hh.func_102909_z(java.lang.String)char[]
		// @038: invokestatic game.C_100320_hh.func_102908_z(char[])java.lang.String
		// @03B: aastore
		// @03C: dup
		// @03D: iconst_5
		// @03E: ldc "d\u0013\u0019/($"
		// @040: invokestatic game.C_100320_hh.func_102909_z(java.lang.String)char[]
		// @043: invokestatic game.C_100320_hh.func_102908_z(char[])java.lang.String
		// @046: aastore
		// @047: dup
		// @048: bipush 6 (0x06)
		// @04A: ldc "d\u0013\u0019,($"
		// @04C: invokestatic game.C_100320_hh.func_102909_z(java.lang.String)char[]
		// @04F: invokestatic game.C_100320_hh.func_102908_z(char[])java.lang.String
		// @052: aastore
		// @053: dup
		// @054: bipush 7 (0x07)
		// @056: ldc "d\u0013\u0019(($"
		// @058: invokestatic game.C_100320_hh.func_102909_z(java.lang.String)char[]
		// @05B: invokestatic game.C_100320_hh.func_102908_z(char[])java.lang.String
		// @05E: aastore
		// @05F: dup
		// @060: bipush 8 (0x08)
		// @062: ldc "d\u0013\u0019&A"
		// @064: invokestatic game.C_100320_hh.func_102909_z(java.lang.String)char[]
		// @067: invokestatic game.C_100320_hh.func_102908_z(char[])java.lang.String
		// @06A: aastore
		// @06B: dup
		// @06C: bipush 9 (0x09)
		// @06E: ldc "d\u0013\u00194A"
		// @070: invokestatic game.C_100320_hh.func_102909_z(java.lang.String)char[]
		// @073: invokestatic game.C_100320_hh.func_102908_z(char[])java.lang.String
		// @076: aastore
		// @077: putstatic java.lang.String[] game.C_100320_hh.field_102913_V
		// @07A: bipush 94 (0x5E)
		// @07C: anewarray java.lang.String[]
		// @07F: dup
		// @080: iconst_0
		// @081: iconst_1
		// @082: anewarray java.lang.String
		// @085: dup
		// @086: iconst_0
		// @087: ldc "0\u0013\t,\u0007x\tX\u0001\u001co\u000f^\n\u0007"
		// @089: invokestatic game.C_100320_hh.func_102909_z(java.lang.String)char[]
		// @08C: invokestatic game.C_100320_hh.func_102908_z(char[])java.lang.String
		// @08F: aastore
		// @090: aastore
		// @091: dup
		// @092: iconst_1
		// @093: iconst_2
		// @094: anewarray java.lang.String
		// @097: dup
		// @098: iconst_0
		// @099: ldc "0\u000fX\u0015WO\u0014Y\u0002\u001bm\u000fB\t\u0008x\u0012X\u000b\u001a,\u0014YE\u0003c\u0012Y\u000c\u0007k[C\r\u000c,(R\u000b\u001de\u0015R\tIO\u0014Z\u0007\u0008x[s\u000c\u001fe\u0008^\n\u0007\"GU\u0017W0\u0019E[+m\u000fC\t\u000c\u007f[V\u0017\u000c,\tV\u0002\u0000b\u001c\u0017\u0007\u000cx\u000cR\u0000\u0007,\u001c^\u0004\u0007x[V\u0017\u0004c\u000eE\u0000\r,\tX\u0007\u0006x\u0008\u001bE\u0002b\u0014@\u000bIm\u0008\u0017\u0016\u000cb\u000f^\u000b\u000c`\u0008\u0019E(\u007f[VE\u001ai\u0015C\u000c\u0007i\u0017\u0017\u0006\u0006a\u0016V\u000b\ri\t\u001bE\u0010c\u000e\u0017\u0012\u0000`\u0017\u0017\t\u000cm\tYE\u001dc[T\n\u0007x\tX\tIm[A\u0004\u001be\u001eC\u001cIc\u001d\u0017\u0016\u000cb\u000f^\u000b\u000c`\u0008\u0017\u0012\u0000x\u0013\u0017\u0001\u0000j\u001dR\u0017\u000cb\u000f\u0017\u0004\u001ba\u001aZ\u0000\u0007x\u0008\u0017\u0004\u0007h[V\u0007\u0000`\u0012C\u000c\u000c\u007fU\u000b\u0007\u001b29NE\u0005i\u001aE\u000b\u0000b\u001c\u0017\u0011\u0001i[V\u0017\u001d,\u0014QE\u001ai\u0015C\u000c\u0007i\u0017\u0017\u0000\u0007k\u0012Y\u0000\u000c~\u0012Y\u0002E,\u0002X\u0010Io\u001aYE\ri\u0008^\u0002\u0007,\u0015R\u0012Im\u0015SE\u000bi\u000fC\u0000\u001b,\u0008R\u000b\u001de\u0015R\t\u001a [T\n\u0004n\u0012Y\u000c\u0007k[C\r\u000c,\u0019R\u0016\u001d,\u001dR\u0004\u001dy\tR\u0016Ic\u001d\u0017\n\u001dd\u001eEE\u0004c\u001fR\t\u001a [V\u000b\r,\u0012Y\u0006\u0006~\u000bX\u0017\u0008x\u0012Y\u0002Ib\u001e@E\u001di\u0018_\u000b\u0006`\u0014P\u001cIu\u0014BE\u0001m\rRE\u0008o\nB\u000c\u001bi\u001f\u0019Y\u000b~E\u000b\u0007\u001b2,R\t\nc\u0016RE\u001dc[\u000b\u0006\u0006`F\u0006\u0003^:\u001a\u0001[:x\u001eR\tI_\u001eY\u0011\u0000b\u001e[\u0016U#\u0018X\tW\""
		// @09B: invokestatic game.C_100320_hh.func_102909_z(java.lang.String)char[]
		// @09E: invokestatic game.C_100320_hh.func_102908_z(char[])java.lang.String
		// @0A1: aastore
		// @0A2: dup
		// @0A3: iconst_1
		// @0A4: ldc "0\u000b^\u0006Y2"
		// @0A6: invokestatic game.C_100320_hh.func_102909_z(java.lang.String)char[]
		// @0A9: invokestatic game.C_100320_hh.func_102908_z(char[])java.lang.String
		// @0AC: aastore
		// @0AD: aastore
		// @0AE: dup
		// @0AF: iconst_2
		// @0B0: iconst_1
		// @0B1: anewarray java.lang.String
		// @0B4: dup
		// @0B5: iconst_0
		// @0B6: ldc "0\u0013\t'\u0008\u007f\u0012TE*c\u0015C\u0017\u0006`\u0008"
		// @0B8: invokestatic game.C_100320_hh.func_102909_z(java.lang.String)char[]
		// @0BB: invokestatic game.C_100320_hh.func_102908_z(char[])java.lang.String
		// @0BE: aastore
		// @0BF: aastore
		// @0C0: dup
		// @0C1: iconst_3
		// @0C2: iconst_2
		// @0C3: anewarray java.lang.String
		// @0C6: dup
		// @0C7: iconst_0
		// @0C8: ldc "0\u000fX\u0015W0\u0012Z\u0002T=I\tEUe\u0016PXX?E\u0017Y\u0000a\u001c\nT]2[\u000b\u000c\u0004kF\u0006PW0\u0019E[Uo\u0014[XXjL\u0001\u0004_2(T\u0017\u0006`\u0017\u0017\u0004\u001bc\u000eY\u0001Ia\u001aGYFo\u0014[[Un\t\tY\u000b~E\u000b\u000c\u0004kF\u0006SW0\u0019E[Uo\u0014[XXjL\u0001\u0004_28R\u000b\u001d~\u001e\u0017\u0006\u0008a\u001eE\u0004Ic\u0015\u0017\u001c\u0006y\t\u0017\u0016\u000cb\u000f^\u000b\u000c`G\u0018\u0006\u0006`E\u000b\u0007\u001b2GU\u0017W0\u0012Z\u0002T=E\u0017\u0004\u0007h[\u000b\u000c\u0004kF\u0005[Un\t\tY\nc\u0017\nT\u000f;MVSW_\u000c^\u0011\nd[@\u0000\u0008|\u0014Y\u0016U#\u0018X\tW0\u0019E[Un\t\tY\u0000a\u001c\nVW,\u001aY\u0001I0\u0012Z\u0002T9E\u000b\u0007\u001b2GT\n\u00051JQR_mM\t6\u001dm\tCE\u001ai\u0015C\u000c\u0007i\u0017\u0017\u0008\u0006z\u001eZ\u0000\u0007xG\u0018\u0006\u0006`E\u000b\u0007\u001b2GU\u0017W0\u0012Z\u0002T8E\u000b\u0007\u001b2GT\n\u00051JQR_mM\t-\u0008`\u000f\u0017\u0016\u000cb\u000f^\u000b\u000c`[Z\n\u001fi\u0016R\u000b\u001d0TT\n\u00052"
		// @0CA: invokestatic game.C_100320_hh.func_102909_z(java.lang.String)char[]
		// @0CD: invokestatic game.C_100320_hh.func_102908_z(char[])java.lang.String
		// @0D0: aastore
		// @0D1: dup
		// @0D2: iconst_1
		// @0D3: ldc "0\u000fX\u0015W0\u0012Z\u0002T:E\u0017\t\u000cj\u000f\u0017\u0006\u0005e\u0018\\Y\u000b~E\u000b\u0006\u0006`F\u0006\u0003^:\u001a\u0001[/e\tRE\u001ai\u0017R\u0006\u001di\u001f\u0017\u0012\u000cm\u000bX\u000bU#\u0018X\tW0\u0019E[Un\t\tY\u0000a\u001c\nTY2P\u000b\u000c\u0004kF\u0001[Ic\t\u0017Y\u0000a\u001c\nRW0\u0019E[Uo\u0014[XXjL\u0001\u0004_21B\u0008\u0019,\u0014EE\u001dd\tB\u0016\u001d0TT\n\u00052GU\u0017W0\u0019E[Ue\u0016PXX=E\u001cY\u0000a\u001c\nSW0\u0019E[Uo\u0014[XXjL\u0001\u0004_2/V\u0017\u000ei\u000f\u0017\u0000\u0007i\u0016NYFo\u0014[[Un\t\tY\u000b~E\u000b\u000c\u0004kF\u0007[Un\t\tY\nc\u0017\nT\u000f;MVSWO\u0017X\u0016\u000c!\u0018X\u0008\u000bm\u000f\u0017\u0004\u001dx\u001aT\u000eI$\u0012QE\u0008z\u001a^\t\u0008n\u0017RLU#\u0018X\tW"
		// @0D5: invokestatic game.C_100320_hh.func_102909_z(java.lang.String)char[]
		// @0D8: invokestatic game.C_100320_hh.func_102908_z(char[])java.lang.String
		// @0DB: aastore
		// @0DC: aastore
		// @0DD: dup
		// @0DE: iconst_4
		// @0DF: iconst_1
		// @0E0: anewarray java.lang.String
		// @0E3: dup
		// @0E4: iconst_0
		// @0E5: ldc "0\u0013\t\"\u0008a\u001e\u001a\u0011\u0000a\u001e\u0017(\u0006h\u001eD"
		// @0E7: invokestatic game.C_100320_hh.func_102909_z(java.lang.String)char[]
		// @0EA: invokestatic game.C_100320_hh.func_102908_z(char[])java.lang.String
		// @0ED: aastore
		// @0EE: aastore
		// @0EF: dup
		// @0F0: iconst_5
		// @0F1: iconst_1
		// @0F2: anewarray java.lang.String
		// @0F5: dup
		// @0F6: iconst_0
		// @0F7: ldc "_\u001eY\u0011\u0000b\u001e[\u0016Im\tRE\u001c\u007f\u000eV\t\u0005u[D\u0000\u0007x[C\nIn\u001aC\u0011\u0005i[X\u000bIm\u0017^\u0000\u0007,\u000b[\u0004\u0007i\u000fDE\u0008b\u001f\u0017\u0006\u0006b\u000fE\n\u0005`\u001eSE\u001bi\u0016X\u0011\u000c`\u0002\u0019E9m\tCE\u0006j[C\r\u000c,\u0008\\\u000c\u0005`[X\u0003Im[D\u0000\u0007x\u0012Y\u0000\u0005,\u0018X\u0008\u0004m\u0015S\u0000\u001b,\u0012DE\u0008`\u0017X\u0012\u0000b\u001c\u0017\u0003\u0006~[C\r\u000c,\u000f^\u0008\u000c,\u0012CE\u001dm\u0010R\u0016Ij\u0014EE\u0010c\u000eEE\u0000b\u0008C\u0017\u001co\u000f^\n\u0007\u007f[C\nIn\u001e\u0017\u0017\u000co\u001e^\u0013\u000ch[V\u000b\r,\u001aT\u0011\u000ch[B\u0015\u0006b[U\u001cIu\u0014B\u0017I\u007f\u001eY\u0011\u0000b\u001e[KIX\u0013RE\u0008a\u0014B\u000b\u001d,\u0014QE\u001de\u0016RE\ri\u000bR\u000b\r\u007f[X\u000bIx\u0013RE\u000em\u0016RH\u001de\u0016RE\u0004c\u001fRK"
		// @0F9: invokestatic game.C_100320_hh.func_102909_z(java.lang.String)char[]
		// @0FC: invokestatic game.C_100320_hh.func_102908_z(char[])java.lang.String
		// @0FF: aastore
		// @100: aastore
		// @101: dup
		// @102: bipush 6 (0x06)
		// @104: iconst_1
		// @105: anewarray java.lang.String
		// @108: dup
		// @109: iconst_0
		// @10A: ldc "0\u0018X\tT=\u001d\u0000S\u0008:Ec\u0004\nx\u0012T\u0004\u0005,\u0016X\u0001\u000c0TT\n\u00052GU\u0017WI\u001aT\rIc\u001d\u0017\u001c\u0006y\t\u0017\u0004\nx\u0012X\u000b\u001a,\u0012DE\ri\u0017V\u001c\u000ch[U\u001cIx\u000cXE\u001ai\u0018X\u000b\r\u007f[U\u0000\u000fc\tRE\u0000x[C\u0004\u0002i\u0008\u0017\u0015\u0005m\u0018RKIX\u0013^\u0016Ia\u0014S\u0000I~\u001eD\u0010\u0005x\u0008\u0017\u000c\u0007,\u001a\u0017\u0008\u0006~\u001e\u0017\u000c\u0007z\u0014[\u0013\u000ch[P\u0004\u0004i[X\u0003Ic\u000eCH\u001dd\u0012Y\u000e\u0000b\u001c\u0017\u001c\u0006y\t\u0017\n\u0019|\u0014Y\u0000\u0007x\u0008\u0017\u0004\u0007h[G\u0017\u000c|\u001aE\u000c\u0007k[Q\n\u001b,\u000f_\u0000\u0000~[R\u0013\u000c~\u0002\u0017\u0008\u0006z\u001e\u0019"
		// @10C: invokestatic game.C_100320_hh.func_102909_z(java.lang.String)char[]
		// @10F: invokestatic game.C_100320_hh.func_102908_z(char[])java.lang.String
		// @112: aastore
		// @113: aastore
		// @114: dup
		// @115: bipush 7 (0x07)
		// @117: iconst_1
		// @118: anewarray java.lang.String
		// @11B: dup
		// @11C: iconst_0
		// @11D: ldc "0\u0018X\tT=\u001d\u0000S\u0008:Ev\u0006\u001de\u0014YE\u0004c\u001fRYFo\u0014[[Un\t\t1\u0001i\tRE\u0000\u007f[A\u0000\u001bu[[\u000c\u001dx\u0017RE\ri\u0017V\u001cIn\u001eC\u0012\u000ci\u0015\u0017\u001c\u0006y\t\u0017\u000c\u0007\u007f\u000fE\u0010\nx\u0012X\u000b\u001a,\u0019R\u000c\u0007k[D\u0000\u0007x[V\u000b\r,\u0002X\u0010\u001b,\u0008R\u000b\u001de\u0015R\tIm\u0018C\u000c\u0007k[X\u000bIx\u0013R\u0008G,/_\u000c\u001a,\u0016V\u000e\u000c\u007f[Q\n\u001b,\u001dV\u0016\u001d [_\u0000\nx\u0012TE\u000em\u0016R\u0015\u0005m\u0002\u001bE\u000by\u000f\u0017\u000c\u001d,\u0012DE\u0006b\u0017NE\u001bi\u0018X\u0008\u0004i\u0015S\u0000\r,\u001dX\u0017I|\u0017V\u001c\u000c~\u0008\u0017\u0012\u0000x\u0013\u0017\u0004Ij\u001aD\u0011Ie\u0015C\u0000\u001bb\u001eCE\nc\u0015Y\u0000\nx\u0012X\u000bG"
		// @11F: invokestatic game.C_100320_hh.func_102909_z(java.lang.String)char[]
		// @122: invokestatic game.C_100320_hh.func_102908_z(char[])java.lang.String
		// @125: aastore
		// @126: aastore
		// @127: dup
		// @128: bipush 8 (0x08)
		// @12A: iconst_1
		// @12B: anewarray java.lang.String
		// @12E: dup
		// @12F: iconst_0
		// @130: ldc "E\u0015\u0017\u0011\u0008o\u000f^\u0006\u0008`[Z\n\riW\u0017\u0000\u0008o\u0013\u0017\u0003\u0000~\u0012Y\u0002Io\u0014Z\u0008\u0008b\u001f\u0017\u001c\u0006y[^\u0016\u001ay\u001e\u0017\u0012\u0000`\u0017\u0017\u0004\u0019|\u001eV\u0017Ie\u0015\u0017\u001c\u0006y\t\u0017\u0012\u000cm\u000bX\u000bI}\u000eR\u0010\u000c\"[c\r\u0000\u007f[D\r\u0006{\u0008\u0017\u0011\u0001i[S\u000c\u000fj\u001eE\u0000\u0007x[G\u0000\u0007h\u0012Y\u0002Ij\u0012E\u000c\u0007k[V\u0006\u001de\u0014Y\u0016E,\u0016X\u0013\u0000b\u001c\u0017\u0017\u0000k\u0013C\u0012\u0008~\u001fDE\u0008\u007f[C\r\u000ce\t\u0017\u0000\u0011i\u0018B\u0011\u0000c\u0015\u0017\u0004\u0019|\tX\u0004\nd\u001eDK"
		// @132: invokestatic game.C_100320_hh.func_102909_z(java.lang.String)char[]
		// @135: invokestatic game.C_100320_hh.func_102908_z(char[])java.lang.String
		// @138: aastore
		// @139: aastore
		// @13A: dup
		// @13B: bipush 9 (0x09)
		// @13D: iconst_1
		// @13E: anewarray java.lang.String
		// @141: dup
		// @142: iconst_0
		// @143: ldc "0\u0013\t(\u0006z\u001eZ\u0000\u0007x"
		// @145: invokestatic game.C_100320_hh.func_102909_z(java.lang.String)char[]
		// @148: invokestatic game.C_100320_hh.func_102908_z(char[])java.lang.String
		// @14B: aastore
		// @14C: aastore
		// @14D: dup
		// @14E: bipush 10 (0x0A)
		// @150: iconst_1
		// @151: anewarray java.lang.String
		// @154: dup
		// @155: iconst_0
		// @156: ldc "0\u0012Z\u0002T?E\u0017EUo\u0014[XXjL\u0001\u0004_2(C\u0004\u001bx[Z\n\u001fe\u0015PE\u0005i\u001dCYFo\u0014[[Un\t\tY\u000b~E\u000b\u000c\u0004kF\u0002[I,GT\n\u00051JQR_mM\t6\u001dm\tCE\u0004c\r^\u000b\u000e,\t^\u0002\u0001xG\u0018\u0006\u0006`E\u000b\u0007\u001b2GU\u0017W0\u0012Z\u0002T8E\u0017EUo\u0014[XXjL\u0001\u0004_2(C\n\u0019,\u0016X\u0013\u0000b\u001c\u000bJ\nc\u0017\t"
		// @158: invokestatic game.C_100320_hh.func_102909_z(java.lang.String)char[]
		// @15B: invokestatic game.C_100320_hh.func_102908_z(char[])java.lang.String
		// @15E: aastore
		// @15F: aastore
		// @160: dup
		// @161: bipush 11 (0x0B)
		// @163: iconst_1
		// @164: anewarray java.lang.String
		// @167: dup
		// @168: iconst_0
		// @169: ldc "_\u001eY\u0011\u0000b\u001e[\u0016Io\u0014Y\u0011\u0000b\u000eRE\u0004c\r^\u000b\u000e,\u0012YE\u001dd\u001e\u0017\u0001\u0000~\u001eT\u0011\u0000c\u0015\u0017\u0011\u0001i\u0002\u0017\u0004\u001bi[C\n\u0005h[B\u000b\u001de\u0017\u0017\u0011\u0001i\u0012EE\u0006~\u001fR\u0017\u001a,\u0018_\u0004\u0007k\u001e\u0019"
		// @16B: invokestatic game.C_100320_hh.func_102909_z(java.lang.String)char[]
		// @16E: invokestatic game.C_100320_hh.func_102908_z(char[])java.lang.String
		// @171: aastore
		// @172: aastore
		// @173: dup
		// @174: bipush 12 (0x0C)
		// @176: iconst_2
		// @177: anewarray java.lang.String
		// @17A: dup
		// @17B: iconst_0
		// @17C: ldc "0\u000b^\u0006Z2"
		// @17E: invokestatic game.C_100320_hh.func_102909_z(java.lang.String)char[]
		// @181: invokestatic game.C_100320_hh.func_102908_z(char[])java.lang.String
		// @184: aastore
		// @185: dup
		// @186: iconst_1
		// @187: ldc "0\u0018X\tT=\u001d\u0000S\u0008:E}\u0010\u0004|\u0012Y\u0002U#\u0018X\tW0\u0019E[Ue\u0016PXX<E\u0017NIa\u0014A\u0000Ia\u0014B\u0016\u000c,[\u000b\u0006\u0006`F\u0006\u0003^:\u001a\u0001[:d\u0014@E\u0003y\u0016G\u000c\u0007k[C\u0017\u0008f\u001eT\u0011\u0006~\u0002\u000bJ\nc\u0017\tY\u000b~E\u000b\u000c\u0004kF\u0006UW,P\u0017Y\u0000a\u001c\nSW,[\u000b\u0006\u0006`F\u0006\u0003^:\u001a\u0001[#y\u0016GYFo\u0014[[Un\t\t$\u0005x\u001eE\u000b\u0008x\u0012A\u0000\u0005uA\u000b\u0007\u001b2G^\u0008\u000e1L\tEB,\u0016X\u0013\u000c,\u0016X\u0010\u001ai[\u0017Y\nc\u0017\nT\u000f;MVSW_\u0013X\u0012If\u000eZ\u0015\u0000b\u001c\u0017\u0011\u001bm\u0011R\u0006\u001dc\tNYFo\u0014[[Un\t\t7\u000c`\u001eV\u0016\u000c,G^\u0008\u000e1L\tEI0\u0018X\tT=\u001d\u0000S\u0008:E}\u0010\u0004|G\u0018\u0006\u0006`E"
		// @189: invokestatic game.C_100320_hh.func_102909_z(java.lang.String)char[]
		// @18C: invokestatic game.C_100320_hh.func_102908_z(char[])java.lang.String
		// @18F: aastore
		// @190: aastore
		// @191: dup
		// @192: bipush 13 (0x0D)
		// @194: iconst_2
		// @195: anewarray java.lang.String
		// @198: dup
		// @199: iconst_0
		// @19A: ldc "0\u000b^\u0006]2"
		// @19C: invokestatic game.C_100320_hh.func_102909_z(java.lang.String)char[]
		// @19F: invokestatic game.C_100320_hh.func_102908_z(char[])java.lang.String
		// @1A2: aastore
		// @1A3: dup
		// @1A4: iconst_1
		// @1A5: ldc "0\u0018X\tT=\u001d\u0000S\u0008:Ec\r\u001by\u0008C\u000c\u0007kG\u0018\u0006\u0006`E\u000b\u0007\u001b2.D\u0000Ix\u0013RE\u0003y\u0016G\u000c\u0007k[T\n\u0007x\tX\t\u001a,\u000c_\u000c\u0005i[^\u000bIx\u0013RE\u0008e\t\u0017\u0011\u0006,\u000f_\u0017\u001c\u007f\u000f\u0019Y\u000b~Ec\r\u001by\u0008C\u000c\u0007k[B\u0016\u000c\u007f[B\u0015Ii\u0015R\u0017\u000eu[V\u000b\r,\u0018V\u000bI~\u001eD\u0010\u0005x[^\u000bIi\u0015R\u0017\u000eu[[\n\u001a\u007f[\u001f\u0016\u000ci[\u000b\u0006\u0006`F\u0006\u0003^:\u001a\u0001[,B>e\"00TT\n\u00052R\u0019"
		// @1A7: invokestatic game.C_100320_hh.func_102909_z(java.lang.String)char[]
		// @1AA: invokestatic game.C_100320_hh.func_102908_z(char[])java.lang.String
		// @1AD: aastore
		// @1AE: aastore
		// @1AF: dup
		// @1B0: bipush 14 (0x0E)
		// @1B2: iconst_1
		// @1B3: anewarray java.lang.String
		// @1B6: dup
		// @1B7: iconst_0
		// @1B8: ldc "B\u0014CE\u000cz\u001eE\u001cI\u007f\u001eY\u0011\u0000b\u001e[E\nm\u0015\u0017\u000f\u001ca\u000b\u0017\n\u001b,\u000f_\u0017\u001c\u007f\u000f\u0019E0c\u000eEE\u001ai\u0015C\u000c\u0007i\u0017\u0010\u0016Im\u0019^\t\u0000x\u0012R\u0016Im\tRE\u001ad\u0014@\u000bIe\u0015\u0017\u0011\u0001i[\u0010&\u0006b\u001d^\u0002\u001c~\u001aC\u000c\u0006b\\\u0017\u0016\n~\u001eR\u000bG"
		// @1BA: invokestatic game.C_100320_hh.func_102909_z(java.lang.String)char[]
		// @1BD: invokestatic game.C_100320_hh.func_102908_z(char[])java.lang.String
		// @1C0: aastore
		// @1C1: aastore
		// @1C2: dup
		// @1C3: bipush 15 (0x0F)
		// @1C5: iconst_1
		// @1C6: anewarray java.lang.String
		// @1C9: dup
		// @1CA: iconst_0
		// @1CB: ldc "0\u0013\t6\u0001c\u0014C\u000c\u0007k[V\u000b\r,/V\u0017\u000ei\u000f^\u000b\u000e"
		// @1CD: invokestatic game.C_100320_hh.func_102909_z(java.lang.String)char[]
		// @1D0: invokestatic game.C_100320_hh.func_102908_z(char[])java.lang.String
		// @1D3: aastore
		// @1D4: aastore
		// @1D5: dup
		// @1D6: bipush 16 (0x10)
		// @1D8: iconst_1
		// @1D9: anewarray java.lang.String
		// @1DC: dup
		// @1DD: iconst_0
		// @1DE: ldc "0\u0012Z\u0002T:E\u0017\t\u000cj\u000f\u0017\u0006\u0005e\u0018\\EI0\u0018X\tT=\u001d\u0000S\u0008:Eq\u000c\u001bi[@\u0000\u0008|\u0014YYFo\u0014[[Un\t\tY\u000b~E\u000b\u000c\u0004kF\u0001[Id\u001e[\u0001Ih\u0014@\u000bI,GT\n\u00051JQR_mM\t&\u0006b\u000f^\u000b\u001ci[Q\u000c\u001be\u0015PE\u001dd\u001e\u0017\u0012\u000cm\u000bX\u000bIm\u000f\u0017\u000c\u001d\u007f[X\u0015\u001de\u0016B\u0008Ij\u0012E\u000c\u0007k[E\u0004\u001diG\u0018\u0006\u0006`E\u000b\u0007\u001b2"
		// @1E0: invokestatic game.C_100320_hh.func_102909_z(java.lang.String)char[]
		// @1E3: invokestatic game.C_100320_hh.func_102908_z(char[])java.lang.String
		// @1E6: aastore
		// @1E7: aastore
		// @1E8: dup
		// @1E9: bipush 17 (0x11)
		// @1EB: iconst_1
		// @1EC: anewarray java.lang.String
		// @1EF: dup
		// @1F0: iconst_0
		// @1F1: ldc "E\u001d\u0017\u001c\u0006y[T\t\u0000o\u0010\u0017\u0011\u0006,\u001d^\u0017\u000c,\u0016B\t\u001de\u000b[\u0000Ix\u0012Z\u0000\u001a,\u0012YE\u001bm\u000b^\u0001I\u007f\u000eT\u0006\u000c\u007f\u0008^\n\u0007 [N\n\u001c,\u000c^\t\u0005,\u001d^\t\u0005,\u0002X\u0010\u001b,\u0008R\u000b\u001de\u0015R\tN\u007f[V\u0006\u001de\u0014YE\u0018y\u001eB\u0000I{\u0012C\rIj\u0012E\u000c\u0007k[V\u0006\u001de\u0014Y\u0016E,\u000c_\u000c\nd[Z\u0004\u0010,\u000bE\u0000\u001fi\u0015CE\u0010c\u000e\u0017\u0011\u0008g\u0012Y\u0002Ic\u000f_\u0000\u001b,\u001aT\u0011\u0000c\u0015DK"
		// @1F3: invokestatic game.C_100320_hh.func_102909_z(java.lang.String)char[]
		// @1F6: invokestatic game.C_100320_hh.func_102908_z(char[])java.lang.String
		// @1F9: aastore
		// @1FA: aastore
		// @1FB: dup
		// @1FC: bipush 18 (0x12)
		// @1FE: iconst_1
		// @1FF: anewarray java.lang.String
		// @202: dup
		// @203: iconst_0
		// @204: ldc "0\u0019E[Ue\u0016PXX2[V\u000b\r,G^\u0008\u000e1I\tEI0\u0018X\tT=\u001d\u0000S\u0008:Ed\u0012\u0000x\u0018_E\u001ei\u001aG\n\u0007\u007fG\u0018\u0006\u0006`E"
		// @206: invokestatic game.C_100320_hh.func_102909_z(java.lang.String)char[]
		// @209: invokestatic game.C_100320_hh.func_102908_z(char[])java.lang.String
		// @20C: aastore
		// @20D: aastore
		// @20E: dup
		// @20F: bipush 19 (0x13)
		// @211: iconst_1
		// @212: anewarray java.lang.String
		// @215: dup
		// @216: iconst_0
		// @217: ldc "U\u0014BE\nm\u0015\u0017\u0004\u0005\u007f\u0014\u0017\u0016\u001ee\u000fT\rI{\u001eV\u0015\u0006b\u0008\u0017\u0007\u0010,\u0018[\u000c\ng\u0012Y\u0002Ic\u0015\u0017\u0011\u0001i[^\u0006\u0006b\u0008\u0017\u0004\u001d,\u000f_\u0000In\u001aD\u0000Ic\u001d\u0017\u0011\u0001i[D\u0006\u001bi\u001eYIIc\t\u0017\u0007\u0010,\u000bE\u0000\u001a\u007f\u0012Y\u0002Ix\u0013RE\u0007y\u0016U\u0000\u001b,\u0010R\u001c\u001a\"GU\u0017W,"
		// @219: invokestatic game.C_100320_hh.func_102909_z(java.lang.String)char[]
		// @21C: invokestatic game.C_100320_hh.func_102908_z(char[])java.lang.String
		// @21F: aastore
		// @220: aastore
		// @221: dup
		// @222: bipush 20 (0x14)
		// @224: iconst_1
		// @225: anewarray java.lang.String
		// @228: dup
		// @229: iconst_0
		// @22A: ldc "0\u000b^\u0006_2"
		// @22C: invokestatic game.C_100320_hh.func_102909_z(java.lang.String)char[]
		// @22F: invokestatic game.C_100320_hh.func_102908_z(char[])java.lang.String
		// @232: aastore
		// @233: aastore
		// @234: dup
		// @235: bipush 21 (0x15)
		// @237: iconst_1
		// @238: anewarray java.lang.String
		// @23B: dup
		// @23C: iconst_0
		// @23D: ldc "0\u0019E[Uo\u0014[XXjL\u0001\u0004_2/V\u0017\u000ei\u000f^\u000b\u000e0TT\n\u00052"
		// @23F: invokestatic game.C_100320_hh.func_102909_z(java.lang.String)char[]
		// @242: invokestatic game.C_100320_hh.func_102908_z(char[])java.lang.String
		// @245: aastore
		// @246: aastore
		// @247: dup
		// @248: bipush 22 (0x16)
		// @24A: iconst_1
		// @24B: anewarray java.lang.String
		// @24E: dup
		// @24F: iconst_0
		// @250: ldc "0\u0019E[Ue\u0016PXX=E\u0017NUe\u0016PX_2[\u0017Y\nc\u0017\nT\u000f;MVSWX\u001aE\u0002\u000cx[C\r\u000c,\u0008R\u000b\u001de\u0015R\tIm\u000f\u0017\u001c\u0006y\t\u0017\u0008\u0006y\u0008RE\u0019c\u0012Y\u0011\u000c~G\u0018\u0006\u0006`E\u000b\u0007\u001b2["
		// @252: invokestatic game.C_100320_hh.func_102909_z(java.lang.String)char[]
		// @255: invokestatic game.C_100320_hh.func_102908_z(char[])java.lang.String
		// @258: aastore
		// @259: aastore
		// @25A: dup
		// @25B: bipush 23 (0x17)
		// @25D: iconst_2
		// @25E: anewarray java.lang.String
		// @261: dup
		// @262: iconst_0
		// @263: ldc "0\u000b^\u0006\\2"
		// @265: invokestatic game.C_100320_hh.func_102909_z(java.lang.String)char[]
		// @268: invokestatic game.C_100320_hh.func_102908_z(char[])java.lang.String
		// @26B: aastore
		// @26C: dup
		// @26D: iconst_1
		// @26E: ldc "X\u001aE\u0002\u000cx\u0012Y\u0002I~\u001eF\u0010\u0000~\u001eDE\u001dd\u001e\u0017\u0011\u0008~\u001cR\u0011\u000c~[Z\n\ry\u0017RE\u001dc[U\u0000Ie\u0015D\u0011\u0008`\u0017R\u0001Ic\u0015\u0017\u001c\u0006y\t\u0017\u0016\u000cb\u000f^\u000b\u000c`U"
		// @270: invokestatic game.C_100320_hh.func_102909_z(java.lang.String)char[]
		// @273: invokestatic game.C_100320_hh.func_102908_z(char[])java.lang.String
		// @276: aastore
		// @277: aastore
		// @278: dup
		// @279: bipush 24 (0x18)
		// @27B: iconst_2
		// @27C: anewarray java.lang.String
		// @27F: dup
		// @280: iconst_0
		// @281: ldc "0\u000b^\u0006^2"
		// @283: invokestatic game.C_100320_hh.func_102909_z(java.lang.String)char[]
		// @286: invokestatic game.C_100320_hh.func_102908_z(char[])java.lang.String
		// @289: aastore
		// @28A: dup
		// @28B: iconst_1
		// @28C: ldc "^\u001eSE\u0004m\t\\\u0000\u001b\u007f[V\u0017\u0006y\u0015SE\u0008,\u0008R\u000b\u001de\u0015R\tIe\u0015S\u000c\nm\u000fRE\u0010c\u000eEE\ny\tE\u0000\u0007x[C\u0004\u001bk\u001eCE\u0005c\u0018\\KI[\u0013^\t\u000c,\u0002X\u0010Id\u001aA\u0000Im[C\u0004\u001bk\u001eCE\u0005c\u0018\\IIa\u0012D\u0016\u0000`\u001eDEAn\u000eCE\u0007c\u000f\u0017\u0017\u0006o\u0010R\u0011\u001a%[@\u000c\u0005`[_\n\u0004i[^\u000bIc\u0015\u0017\u001c\u0006y\t\u0017\u0011\u0008~\u001cR\u0011G,:[\u0016\u0006 [S\u000c\u001bi\u0018CE\u000fe\tRE\u001ei\u001aG\n\u0007\u007f[\u001f\u0002\u001cb\u0008\u0017\u0004\u0007h[[\u0004\u001ai\tDLI{\u0012[\tIj\u0012E\u0000Ih\u0012E\u0000\nx\u0017NE\u0008x[N\n\u001c~[C\u0004\u001bk\u001eCK"
		// @28E: invokestatic game.C_100320_hh.func_102909_z(java.lang.String)char[]
		// @291: invokestatic game.C_100320_hh.func_102908_z(char[])java.lang.String
		// @294: aastore
		// @295: aastore
		// @296: dup
		// @297: bipush 25 (0x19)
		// @299: iconst_1
		// @29A: anewarray java.lang.String
		// @29D: dup
		// @29E: iconst_0
		// @29F: ldc "M[C\u0004\u001bk\u001eCE\u0005c\u0018\\E\u0006b\u0017NE\u0005m\u0008C\u0016Ij\u0014EE\u0008,\u0019E\u000c\u000cj[C\u000c\u0004iW\u0017\u0004\u0007h[@\u000c\u0005`[U\u0000I`\u0014D\u0011Ia\u000eT\rIa\u0014E\u0000I}\u000e^\u0006\u0002`\u0002\u0017\u000c\u000f,\u0002X\u0010\u001b,\u001eY\u0000\u0004u[_\u0004\u001a,\u000f_\u0000Ia\u0012D\u0016\u0000`\u001e\u0017\u0016\n~\u001aZ\u0007\u0005i\t\u0017\u0008\u0006h\u000e[\u0000G0\u0019E[=m\tP\u0000\u001de\u0015PE\u0008,\u0008R\u000b\u001de\u0015R\tI{\u0012[\tIm\u0017D\nIi\u0003G\u0000\u0007h[\u0006E\u001cb\u0012CE\u0006j[R\u000b\u000c~\u001cNE\u000f~\u0014ZE\u0010c\u000eEE\nm\u000bV\u0006\u0000x\u0014E\u0016G"
		// @2A1: invokestatic game.C_100320_hh.func_102909_z(java.lang.String)char[]
		// @2A4: invokestatic game.C_100320_hh.func_102908_z(char[])java.lang.String
		// @2A7: aastore
		// @2A8: aastore
		// @2A9: dup
		// @2AA: bipush 26 (0x1A)
		// @2AC: iconst_1
		// @2AD: anewarray java.lang.String
		// @2B0: dup
		// @2B1: iconst_0
		// @2B2: ldc "0\u0019E[Ue\u0016PXX=E\u0017NUe\u0016PXX;E\u0017EUo\u0014[XXjL\u0001\u0004_2?E\n\u0019,\u000fV\u0017\u000ei\u000f\u0017\t\u0006o\u0010\u000bJ\nc\u0017\tY\u000b~E\u001f$\u0005x\u001eE\u000b\u0008x\u0012A\u0000\u0005uW\u0017\u0006\u0005e\u0018\\E\u0006b[C\r\u000c,7x&\",\u0012T\n\u0007,\u0012YE\u0010c\u000eEE!Y?\u0019LUn\t\t'\u000c,\u0018V\u0017\u000cj\u000e[E\u0006j[V\u0006\ne\u001fR\u000b\u001dm\u0017[\u001cI|\tR\u0016\u001ae\u0015PEUe\u0016PXX;E\u0017\u0012\u0001e\u0017RE\u001d~\u0002^\u000b\u000e,\u000fXE\u001dm\tP\u0000\u001d\"GU\u0017W0\tZ\u0007\nm\u0015T\u0000\u0005c\u0015X\u0003\u000f2"
		// @2B4: invokestatic game.C_100320_hh.func_102909_z(java.lang.String)char[]
		// @2B7: invokestatic game.C_100320_hh.func_102908_z(char[])java.lang.String
		// @2BA: aastore
		// @2BB: aastore
		// @2BC: dup
		// @2BD: bipush 27 (0x1B)
		// @2BF: iconst_1
		// @2C0: anewarray java.lang.String
		// @2C3: dup
		// @2C4: iconst_0
		// @2C5: ldc "0\u0018X\tT=\u001d\u0000S\u0008:Et\n\u0004|\u0017R\u0011\u000c,\u000fE\u0004\u0000b\u0012Y\u0002Ia\u0012D\u0016\u0000c\u0015\u0017SIx\u0014\u0017\u0007\u000c,\u000fE\u0004\u0000b\u001eSE\u0000b[C\u0004\u001bk\u001eC\u000c\u0007kU\u000bJ\nc\u0017\t"
		// @2C7: invokestatic game.C_100320_hh.func_102909_z(java.lang.String)char[]
		// @2CA: invokestatic game.C_100320_hh.func_102908_z(char[])java.lang.String
		// @2CD: aastore
		// @2CE: aastore
		// @2CF: dup
		// @2D0: bipush 28 (0x1C)
		// @2D2: iconst_1
		// @2D3: anewarray java.lang.String
		// @2D6: dup
		// @2D7: iconst_0
		// @2D8: ldc "0\u0013\t \u0007i\tP\u001c"
		// @2DA: invokestatic game.C_100320_hh.func_102909_z(java.lang.String)char[]
		// @2DD: invokestatic game.C_100320_hh.func_102908_z(char[])java.lang.String
		// @2E0: aastore
		// @2E1: aastore
		// @2E2: dup
		// @2E3: bipush 29 (0x1D)
		// @2E5: iconst_1
		// @2E6: anewarray java.lang.String
		// @2E9: dup
		// @2EA: iconst_0
		// @2EB: ldc "U\u0014B\u0017I\u007f\u001eY\u0011\u0000b\u001e[E\u0001m\u0008\u0017\u0004Ij\u0012Y\u000c\u001di[D\u0011\u0006~\u001e\u0017\n\u000f,\u001eY\u0000\u001bk\u0002\u0017\u0011\u0006,\u000eD\u0000Ie\u0015\u0017\u0007\u0008x\u000f[\u0000E,\u000c_\u000c\nd[E\u0000\nd\u001aE\u0002\u000c\u007f[X\u0013\u000c~GY\u0007\u001a|EC\u000c\u0004iU"
		// @2ED: invokestatic game.C_100320_hh.func_102909_z(java.lang.String)char[]
		// @2F0: invokestatic game.C_100320_hh.func_102908_z(char[])java.lang.String
		// @2F3: aastore
		// @2F4: aastore
		// @2F5: dup
		// @2F6: bipush 30 (0x1E)
		// @2F8: iconst_1
		// @2F9: anewarray java.lang.String
		// @2FC: dup
		// @2FD: iconst_0
		// @2FE: ldc "X\u0013RE\u000fc\u0017[\n\u001ee\u0015PE\u0008o\u000f^\n\u0007\u007f[S\u0000\u0019`\u001eC\u0000Iu\u0014B\u0017Ii\u0015R\u0017\u000euA\u000b\u0007\u001b2GT\n\u00051JQR_mM\t#\u0000~\u0012Y\u0002Ii\u0015R\u0017\u000eu[@\u0000\u0008|\u0014Y\u0016U#\u0018X\tW,SD\u0010\nd[V\u0016I`\u001aD\u0000\u001b\u007fR\u000b\u0007\u001b2GT\n\u00051JQR_mM\t(\u0000hVV\u000c\u001b,\u000f_\u0017\u001c\u007f\u000f^\u000b\u000e0TT\n\u00052GU\u0017W0\u0018X\tT=\u001d\u0000S\u0008:Ep\u0000\u001dx\u0012Y\u0002Im[C\u0004\u001bk\u001eCE\u0005c\u0018\\YFo\u0014[["
		// @300: invokestatic game.C_100320_hh.func_102909_z(java.lang.String)char[]
		// @303: invokestatic game.C_100320_hh.func_102908_z(char[])java.lang.String
		// @306: aastore
		// @307: aastore
		// @308: dup
		// @309: bipush 31 (0x1F)
		// @30B: iconst_1
		// @30C: anewarray java.lang.String
		// @30F: dup
		// @310: iconst_0
		// @311: ldc "U\u0014B\u0017I\u007f\u001eY\u0011\u0000b\u001e[E\u001ee\u0017[E\u001bi\u0018_\u0004\u001bk\u001e\u0017\u000c\u001d\u007f[R\u000b\u000c~\u001cNE\u000fm\u0008C\u0000\u001b,\u000c_\u0000\u0007,\u0012CE\u0000\u007f[D\u0011\u0008x\u0012X\u000b\u0008~\u0002\u0017\u0004\u0007h[Y\n\u001d,\u001eY\u0002\u0008k\u001eSE\u0000b[U\u0004\u001dx\u0017RKUn\t\t \u0018y\u0012GE\u001bi\u001aT\u0011\u0006~[Z\n\ry\u0017R\u0016Ix\u0014\u0017\u0017\u000co\u0013V\u0017\u000ei[R\u000b\u000c~\u001cNE\u000fm\u0008C\u0000\u001b\"GU\u0017WI\nB\u000c\u0019,\u0018V\u0015\u0008o\u0012C\n\u001b,\u0016X\u0001\u001c`\u001eDE\u001dc[^\u000b\n~\u001eV\u0016\u000c,\u000f_\u0000Io\u001aG\u0004\ne\u000fNE\u0006j[N\n\u001c~[R\u000b\u000c~\u001cNE\u000bm\u0015\\K"
		// @313: invokestatic game.C_100320_hh.func_102909_z(java.lang.String)char[]
		// @316: invokestatic game.C_100320_hh.func_102908_z(char[])java.lang.String
		// @319: aastore
		// @31A: aastore
		// @31B: dup
		// @31C: bipush 32 (0x20)
		// @31E: iconst_2
		// @31F: anewarray java.lang.String
		// @322: dup
		// @323: iconst_0
		// @324: ldc "0\u000b^\u0006Q2"
		// @326: invokestatic game.C_100320_hh.func_102909_z(java.lang.String)char[]
		// @329: invokestatic game.C_100320_hh.func_102908_z(char[])java.lang.String
		// @32C: aastore
		// @32D: dup
		// @32E: iconst_1
		// @32F: ldc "E\u001d\u0017\u0004\u0007,\u001aT\u0011\u0000c\u0015\u0017\u0006\u0008y\u0008R\u0016Iu\u0014B\u0017I\u007f\u001eY\u0011\u0000b\u001e[E\u001dc[B\u0016\u000c,\u000eGE\u0008`\u0017\u0017\u000c\u001d\u007f[E\u0000\u0004m\u0012Y\u000c\u0007k[R\u000b\u000c~\u001cNIIe\u000f\u0017\u0012\u0000`\u0017\u0017\u0016\u0001y\u000f\u0017\u0001\u0006{\u0015\u0017\u0003\u0006~[VE\u000fi\u000c\u0017\u0016\u000co\u0014Y\u0001\u001a,\u001aY\u0001Ii\u0016^\u0011I\u007f\u000fR\u0004\u0004\"GU\u0017WH\u000eE\u000c\u0007k[R\u000b\u000c~\u001cNE\u0005c\u0008DE\u0010c\u000e\u0017\u0006\u0008b\u0015X\u0011Ia\u0014A\u0000E,\u0011B\u0008\u0019 [X\u0017Iy\u0008RE\u0008b\u0002\u0017\u0004\u000be\u0017^\u0011\u0010,\u000f_\u0004\u001d,\tR\u0014\u001ce\tR\u0016Ii\u0015R\u0017\u000euU\u000b\u0007\u001b2,R\u0004\u0019c\u0015DE\u001dd\u001aCE\rc[Y\n\u001d,\u000eD\u0000Ii\u0015R\u0017\u000eu[T\u0004\u0007,\u0008C\u000c\u0005`[U\u0000Ij\u0012E\u0000\r\"[`\r\u0000`\u001e\u0017\u000c\u0007,\u001aYE\u000cb\u001eE\u0002\u0010,\u0017X\u0016\u001a,\u0008C\u0004\u001di[N\n\u001c~[D\u0000\u0007x\u0012Y\u0000\u0005,\u0012DE\u001fi\tNE\u001fy\u0017Y\u0000\u001bm\u0019[\u0000Ix\u0014\u0017\u0004\u001dx\u001aT\u000eE,\u0008XE\u0000x[^\u0016In\u001eD\u0011Im\rX\u000c\ri\u001f\u0019"
		// @331: invokestatic game.C_100320_hh.func_102909_z(java.lang.String)char[]
		// @334: invokestatic game.C_100320_hh.func_102908_z(char[])java.lang.String
		// @337: aastore
		// @338: aastore
		// @339: dup
		// @33A: bipush 33 (0x21)
		// @33C: iconst_1
		// @33D: anewarray java.lang.String
		// @340: dup
		// @341: iconst_0
		// @342: ldc "I\u0015R\u0017\u000eu[P\u0000\u0007i\tV\u0011\u0000c\u0015\u0017\u000c\u001a,\u001aQ\u0003\u000co\u000fR\u0001In\u0002\u0017 $\\[@\u0000\u0008|\u0014Y\u0016I$\u0008R\u0000In\u001e[\n\u001e%U"
		// @344: invokestatic game.C_100320_hh.func_102909_z(java.lang.String)char[]
		// @347: invokestatic game.C_100320_hh.func_102908_z(char[])java.lang.String
		// @34A: aastore
		// @34B: aastore
		// @34C: dup
		// @34D: bipush 34 (0x22)
		// @34F: iconst_1
		// @350: anewarray java.lang.String
		// @353: dup
		// @354: iconst_0
		// @355: ldc "0\u0013\t!\u0008a\u001aP\u0000IX\u0002G\u0000\u001a"
		// @357: invokestatic game.C_100320_hh.func_102909_z(java.lang.String)char[]
		// @35A: invokestatic game.C_100320_hh.func_102908_z(char[])java.lang.String
		// @35D: aastore
		// @35E: aastore
		// @35F: dup
		// @360: bipush 35 (0x23)
		// @362: iconst_2
		// @363: anewarray java.lang.String
		// @366: dup
		// @367: iconst_0
		// @368: ldc "0\u000b^\u0006P2"
		// @36A: invokestatic game.C_100320_hh.func_102909_z(java.lang.String)char[]
		// @36D: invokestatic game.C_100320_hh.func_102908_z(char[])java.lang.String
		// @370: aastore
		// @371: dup
		// @372: iconst_1
		// @373: ldc "0\u0018X\tT=\u001d\u0000S\u0008:E|\u000c\u0007i\u000f^\u0006IH\u001aZ\u0004\u000eiG\u0018\u0006\u0006`E\u000b\u0007\u001b22Y\u0006\u0005y\u001fR\u0016Ia\u0012Y\u000c\u000ey\u0015DII~\u001a^\tIk\u000eY\u0016Im\u0015SE\u000f`\u001a\\E\u001ei\u001aG\n\u0007\u007fU\u0017.\u0000b\u001eC\u000c\n,\u001fV\u0008\u0008k\u001e\u0017\u000c\u001a,\tR\u0001\u001co\u001eSE\u0000j[C\r\u000c,\tR\u0006\u0000|\u0012R\u000b\u001d,\u0013V\u0016Ix\u0013RE\u001bi\u0012Y\u0003\u0006~\u0018R\u0001Im\tZ\n\u001c~[Z\n\ry\u0017RK"
		// @375: invokestatic game.C_100320_hh.func_102909_z(java.lang.String)char[]
		// @378: invokestatic game.C_100320_hh.func_102908_z(char[])java.lang.String
		// @37B: aastore
		// @37C: aastore
		// @37D: dup
		// @37E: bipush 36 (0x24)
		// @380: iconst_2
		// @381: anewarray java.lang.String
		// @384: dup
		// @385: iconst_0
		// @386: ldc "0\u000b^\u0006X<E"
		// @388: invokestatic game.C_100320_hh.func_102909_z(java.lang.String)char[]
		// @38B: invokestatic game.C_100320_hh.func_102908_z(char[])java.lang.String
		// @38E: aastore
		// @38F: dup
		// @390: iconst_1
		// @391: ldc "0\u0018X\tT=\u001d\u0000S\u0008:Er\u001d\u0019`\u0014D\u000c\u001fi[s\u0004\u0004m\u001cRYFo\u0014[[Un\t\t,\u0007o\u0017B\u0001\u000c\u007f[D\r\u000c`\u0017DII~\u0014T\u000e\u000cx\u0008\u0017\u0004\u0007h[Z\u000c\u001a\u007f\u0012[\u0000\u001a\"[r\u001d\u0019`\u0014D\u000c\u001fi[S\u0004\u0004m\u001cRE\u0000\u007f[E\u0000\ry\u0018R\u0001Ie\u001d\u0017\u0011\u0001i[E\u0000\ne\u000b^\u0000\u0007x[_\u0004\u001a,\u000f_\u0000I~\u001eV\u0006\u001de\rRE\u0008~\u0016X\u0010\u001b,\u0016X\u0001\u001c`\u001e\u0019E b\u001f^\u0017\u000co\u000f\u0017\u0000\u0011|\u0017X\u0016\u0000z\u001e\u0017\u0001\u0008a\u001aP\u0000Io\u001aYE\u000bi[V\u0007\u001ac\tU\u0000\r,\u0019NE\u001ad\u0012R\t\r\u007fU"
		// @393: invokestatic game.C_100320_hh.func_102909_z(java.lang.String)char[]
		// @396: invokestatic game.C_100320_hh.func_102908_z(char[])java.lang.String
		// @399: aastore
		// @39A: aastore
		// @39B: dup
		// @39C: bipush 37 (0x25)
		// @39E: iconst_2
		// @39F: anewarray java.lang.String
		// @3A2: dup
		// @3A3: iconst_0
		// @3A4: ldc "0\u000b^\u0006X=E"
		// @3A6: invokestatic game.C_100320_hh.func_102909_z(java.lang.String)char[]
		// @3A9: invokestatic game.C_100320_hh.func_102908_z(char[])java.lang.String
		// @3AC: aastore
		// @3AD: dup
		// @3AE: iconst_1
		// @3AF: ldc "0\u0018X\tT=\u001d\u0000S\u0008:Er\u000b\u000c~\u001cNE-m\u0016V\u0002\u000c0TT\n\u00052GU\u0017WE\u0015T\t\u001ch\u001eDE\u0005m\u0008R\u0017\u001a,\u001aY\u0001I|\u0017V\u0016\u0004m[@\u0000\u0008|\u0014Y\u0016G,>Y\u0000\u001bk\u0002\u0017\u0001\u0008a\u001aP\u0000Ie\u0008\u0017\u0004\u000b\u007f\u0014E\u0007\u000ch[R\u0003\u000fe\u0018^\u0000\u0007x\u0017NE\u000bu[D\r\u0000i\u0017S\u000c\u0007k[D\u001c\u001ax\u001eZ\u0016G"
		// @3B1: invokestatic game.C_100320_hh.func_102909_z(java.lang.String)char[]
		// @3B4: invokestatic game.C_100320_hh.func_102908_z(char[])java.lang.String
		// @3B7: aastore
		// @3B8: aastore
		// @3B9: dup
		// @3BA: bipush 38 (0x26)
		// @3BC: iconst_2
		// @3BD: anewarray java.lang.String
		// @3C0: dup
		// @3C1: iconst_0
		// @3C2: ldc "0\u000b^\u0006X>E"
		// @3C4: invokestatic game.C_100320_hh.func_102909_z(java.lang.String)char[]
		// @3C7: invokestatic game.C_100320_hh.func_102908_z(char[])java.lang.String
		// @3CA: aastore
		// @3CB: dup
		// @3CC: iconst_1
		// @3CD: ldc "0\u0018X\tT=\u001d\u0000S\u0008:Er(9,?V\u0008\u0008k\u001e\u000bJ\nc\u0017\tY\u000b~E`\u0000\u0008|\u0014Y\u0016In\u001aD\u0000\r,\u0014YE\u000c`\u001eT\u0011\u001bc\u0016V\u0002\u0007i\u000f^\u0006I|\u000e[\u0016\u000c,Sr(9%[C\u0000\nd\u0015X\t\u0006k\u0002\u0017\u0001\u001bm\u0012YE\u001dd\u001e^\u0017Ix\u001aE\u0002\u000cx\\DE\u001ad\u0012R\t\r\u007f[V\u000b\r,\u001eY\u0000\u001bk\u0002\u001bE\u0008b\u001f\u0017\u0016\u001dc\u000b\u0017\u0004\u000fj\u001eT\u0011\u000ch[D\u0000\u0007x\u0012Y\u0000\u0005\u007f[Q\u0017\u0006a[T\r\u0008~\u001c^\u000b\u000e,\u000f_\u0000\u0000~[T\u0004\u0019m\u0018^\u0011\u0006~\u0008\u0017\n\u001b,\tR\u0006\u0006z\u001eE\u000c\u0007k[Q\u0017\u0006a[R\u000b\u000c~\u001cNE\u0005c\u0008DKUn\t\t1\u0001i[R\u000b\u000c~\u001cNE\r~\u001a^\u000b\u0000b\u001c\u0017\u0000\u000fj\u001eT\u0011\u001a,\u0018V\u000bIn\u001e\u0017\u000b\u001c`\u0017^\u0003\u0000i\u001f\u0017\u0007\u0010,\u000f_\u0000II6gE\u0001m\tS\u0000\u0007e\u0015PE\u0004c\u001fB\t\u000c [C\r\u0006y\u001c_E\u001ad\u0012R\t\r\u007f[V\u0017\u000c,\u0008C\u000c\u0005`[V\u0003\u000fi\u0018C\u0000\r\""
		// @3CF: invokestatic game.C_100320_hh.func_102909_z(java.lang.String)char[]
		// @3D2: invokestatic game.C_100320_hh.func_102908_z(char[])java.lang.String
		// @3D5: aastore
		// @3D6: aastore
		// @3D7: dup
		// @3D8: bipush 39 (0x27)
		// @3DA: iconst_1
		// @3DB: anewarray java.lang.String
		// @3DE: dup
		// @3DF: iconst_0
		// @3E0: ldc "X\u0013RE\re\u001dQ\u0000\u001bi\u0015CE\n`\u001aD\u0016\u000c\u007f[X\u0003I{\u001eV\u0015\u0006b\u0008\u0017\u0004\u0007h[C\r\u000ce\t\u0017\u0000\u000fj\u001eT\u0011\u001a,\u001aE\u0000Ih\u001eD\u0006\u001be\u0019R\u0001Ie\u0015\u0017$\u0019|\u001eY\u0001\u0000tGY\u0007\u001a|EuK"
		// @3E2: invokestatic game.C_100320_hh.func_102909_z(java.lang.String)char[]
		// @3E5: invokestatic game.C_100320_hh.func_102908_z(char[])java.lang.String
		// @3E8: aastore
		// @3E9: aastore
		// @3EA: dup
		// @3EB: bipush 40 (0x28)
		// @3ED: iconst_1
		// @3EE: anewarray java.lang.String
		// @3F1: dup
		// @3F2: iconst_0
		// @3F3: ldc "0\u0013\t6\u000cb\u000f^\u000b\u000c`[t\n\u0007j\u0012P\u0010\u001bm\u000f^\n\u0007"
		// @3F5: invokestatic game.C_100320_hh.func_102909_z(java.lang.String)char[]
		// @3F8: invokestatic game.C_100320_hh.func_102908_z(char[])java.lang.String
		// @3FB: aastore
		// @3FC: aastore
		// @3FD: dup
		// @3FE: bipush 41 (0x29)
		// @400: iconst_1
		// @401: anewarray java.lang.String
		// @404: dup
		// @405: iconst_0
		// @406: ldc "C\u0015T\u0000Iu\u0014BE\u0001m\rRE\u001cb\u0017X\u0006\u0002i\u001f\u0017\u0016\u0006a\u001e\u0017\u0016\u000cb\u000f^\u000b\u000c`\u0008\u001bE\u0010c\u000e\u0017\u0006\u0008b[B\u0016\u000c,\u000f_\u0000I+8X\u000b\u000fe\u001cB\u0017\u0008x\u0012X\u000bN,\u0016R\u000b\u001c,\u000fXE\u001ai\u0017R\u0006\u001d,\u001aY\u0001Io\u000eD\u0011\u0006a\u0012D\u0000Ix\u0013RE\u001ai\u0015C\u000c\u0007i\u0017\u0017\u001c\u0006y[@\u0004\u0007x[C\nIx\u001a\\\u0000Ie\u0015C\nIn\u001aC\u0011\u0005iU\u00171\u0001i[D\u0011\u000c|\u0008\u0017\u000c\u0007z\u0014[\u0013\u000ch[^\u000bIh\u001eD\u000c\u000eb\u0012Y\u0002Im[D\u0000\u0007x\u0012Y\u0000\u0005,\u001aE\u0000S0\u0019E["
		// @408: invokestatic game.C_100320_hh.func_102909_z(java.lang.String)char[]
		// @40B: invokestatic game.C_100320_hh.func_102908_z(char[])java.lang.String
		// @40E: aastore
		// @40F: aastore
		// @410: dup
		// @411: bipush 42 (0x2A)
		// @413: iconst_1
		// @414: anewarray java.lang.String
		// @417: dup
		// @418: iconst_0
		// @419: ldc "0\u0018X\tT=\u001d\u0000S\u0008:Ed\u0000\u0005i\u0018CE\nd\u001aD\u0016\u0000\u007fG\u0018\u0006\u0006`E\u000b\u0007\u001b2/_\u000c\u001a,\u001c^\u0013\u000c\u007f[N\n\u001c,\u001a\u0017\u0016\u001dm\u0015S\u0004\u001bh[Z\n\ri\u0017\u0017\u0016\u000cb\u000f^\u000b\u000c`[@\u000c\u001dd[C\r\u0008x[T\r\u0008\u007f\u0008^\u0016G"
		// @41B: invokestatic game.C_100320_hh.func_102909_z(java.lang.String)char[]
		// @41E: invokestatic game.C_100320_hh.func_102908_z(char[])java.lang.String
		// @421: aastore
		// @422: aastore
		// @423: dup
		// @424: bipush 43 (0x2B)
		// @426: iconst_1
		// @427: anewarray java.lang.String
		// @42A: dup
		// @42B: iconst_0
		// @42C: ldc "0\u0018X\tT=\u001d\u0000S\u0008:Ev\u0011\u001dm\u0018_E\nc\u0016G\n\u0007i\u0015C\u0016U#\u0018X\tW0\u0019E[=d\u0012DE\u001du\u000b^\u0006\u0008`\u0017NE\u0004i\u001aY\u0016Io\u0013X\n\u001ae\u0015PE\u001dd\u001e\u0017\r\u000cm\u001f\u001bE\u0008~\u0016DE\u0008b\u001f\u0017\u0016\u0001c\u000e[\u0001\u000c~U"
		// @42E: invokestatic game.C_100320_hh.func_102909_z(java.lang.String)char[]
		// @431: invokestatic game.C_100320_hh.func_102908_z(char[])java.lang.String
		// @434: aastore
		// @435: aastore
		// @436: dup
		// @437: bipush 44 (0x2C)
		// @439: iconst_1
		// @43A: anewarray java.lang.String
		// @43D: dup
		// @43E: iconst_0
		// @43F: ldc "0\u0018X\tT=\u001d\u0000S\u0008:Eq\u000c\u001d,\u000cR\u0004\u0019c\u0015DYFo\u0014[[Un\t\t1\u0001i[Y\u0010\u0004n\u001eEE\u0008b\u001f\u0017\u0016\u0000v\u001e\u0017\n\u000f,\u000cR\u0004\u0019c\u0015DE\u0010c\u000e\u0017\u0006\u0008b[Q\u000c\u001d,\u001fR\u0015\u000cb\u001fDE\u0006b[C\r\u000c,\u0018_\u0004\u001a\u007f\u0012DE\u0008b\u001f\u0017\u0006\u0006a\u000bX\u000b\u000cb\u000fDE\u0010c\u000e\u0017\u0004\u001bi[B\u0016\u0000b\u001c\u0019"
		// @441: invokestatic game.C_100320_hh.func_102909_z(java.lang.String)char[]
		// @444: invokestatic game.C_100320_hh.func_102908_z(char[])java.lang.String
		// @447: aastore
		// @448: aastore
		// @449: dup
		// @44A: bipush 45 (0x2D)
		// @44C: iconst_1
		// @44D: anewarray java.lang.String
		// @450: dup
		// @451: iconst_0
		// @452: ldc "0\u0018X\tT=\u001d\u0000S\u0008:Er\u0014\u001ce\u000b\u0017\u0008\u0006h\u000e[\u0000\u001a0TT\n\u00052GU\u0017WX\u0013R\u0016\u000c,\u001aQ\u0003\u000co\u000f\u0017\u0011\u0001i[V\u0007\u0000`\u0012C\u000c\u000c\u007f[X\u0003Iu\u0014B\u0017I\u007f\u001eY\u0011\u0000b\u001e[IIi\u001aT\rIe\u0015\u0017\u0004Ih\u0012Q\u0003\u000c~\u001eY\u0011I{\u001aNKUn\t\tY\u000b~Ec\r\u000c,\u001d^\u0017\u001ax[C\u000c\u0004i[N\n\u001c,\u001eY\u0011\u000c~[C\r\u000c,\\t\n\u0007j\u0012P\u0010\u001bm\u000f^\n\u0007+[D\u0006\u001bi\u001eYIIx\u0013REUo\u0014[XXjL\u0001\u0004_28X\u000b\u000fe\u001c\u00171\u001bm\u0012Y\u000c\u0007k[g\u0017\u0006k\tV\u0008U#\u0018X\tW,\u000c^\t\u0005,\u0019R\u0002\u0000bW\u0017\u0011\u0006,\u001cB\u000c\ri[N\n\u001c,\u000f_\u0017\u0006y\u001c_E\u001dd\u001e\u0017\u0015\u001bc\u0018R\u0016\u001ai\u0008\u0017\n\u000f,\u0018X\u000b\u000fe\u001cB\u0017\u0008x\u0012X\u000bIm\u0015SE\u000cb\u001c^\u000b\u000ci\t^\u000b\u000e\"[c\nI~\u001eG\u0000\u0008x[C\r\u000c,\u000fE\u0004\u0000b\u0012Y\u0002I|\tX\u0002\u001bm\u0016\u001bE\u000ec[C\nIx\u0013RENO\u0014Y\u0003\u0000k\u000eE\u0004\u001de\u0014YBI\u007f\u0018E\u0000\u000cb[V\u000b\r,\u000bE\u0000\u001a\u007f[C\r\u000c,GT\n\u00051JQR_mM\t-,@+\u000bJ\nc\u0017\tE\u000by\u000fC\n\u0007,\u001aCE\u001dd\u001e\u0017\u0007\u0006x\u000fX\u0008I`\u001eQ\u0011Ic\u001d\u0017\u0011\u0001i[D\u0006\u001bi\u001eYK"
		// @454: invokestatic game.C_100320_hh.func_102909_z(java.lang.String)char[]
		// @457: invokestatic game.C_100320_hh.func_102908_z(char[])java.lang.String
		// @45A: aastore
		// @45B: aastore
		// @45C: dup
		// @45D: bipush 46 (0x2E)
		// @45F: iconst_1
		// @460: anewarray java.lang.String
		// @463: dup
		// @464: iconst_0
		// @465: ldc "0\u0013\t1\u000co\u0013\u00173\u0008`\u000eR"
		// @467: invokestatic game.C_100320_hh.func_102909_z(java.lang.String)char[]
		// @46A: invokestatic game.C_100320_hh.func_102908_z(char[])java.lang.String
		// @46D: aastore
		// @46E: aastore
		// @46F: dup
		// @470: bipush 47 (0x2F)
		// @472: iconst_1
		// @473: anewarray java.lang.String
		// @476: dup
		// @477: iconst_0
		// @478: ldc "I\rR\u0017\u0010,\u0018_\u0004\u001a\u007f\u0012DIIo\u0014Z\u0015\u0006b\u001eY\u0011E,\u000cR\u0004\u0019c\u0015\u0017\u0004\u0007h[Z\n\ry\u0017RE\u0001m\u0008\u0017\u0004Ib\u000eZ\u0007\u000c~[V\u0016\u001ac\u0018^\u0004\u001di\u001f\u0017\u0012\u0000x\u0013\u0017\u0011\u0001i[T\n\u001ax[X\u0003I|\tX\u0001\u001co\u0012Y\u0002Ix\u0013RE\u001di\u0018_\u000b\u0006`\u0014P\u001cIx\u0013V\u0011Ie\u000f\u0017\u0010\u001ai\u0008\u0019E=d\u0012DEIb\u000eZ\u0007\u000c~[^\u0016Io\u001a[\t\u000ch[C\r\u000c,\u000fR\u0006\u0001,\rV\t\u001ciU\u0017$\u001a,\u0002X\u0010Im\u0018F\u0010\u0000~\u001e\u0017\u0007\u000cx\u000fR\u0017Ix\u001eT\r\u0007c\u0017X\u0002\u0010,\u001aY\u0001Ii\nB\u000c\u0019,\u0012CE\u0006b[N\n\u001c~[D\u0000\u0007x\u0012Y\u0000\u0005 [C\r\u000c,\u000fX\u0011\u0008`[C\u0000\nd[A\u0004\u0005y\u001e\u0017\n\u000f,\u0002X\u0010\u001b,\u0008R\u000b\u001de\u0015R\tI{\u0012[\tIe\u0015T\u0017\u000cm\u0008RIIm\u0008\u0017\u0016\u0001c\u000cYE\u0000b[C\r\u000c,\u000fR\u0006\u0001,\rV\t\u001ci[P\u0004\u001ck\u001e\u0017\n\u0007,\u000f_\u0000I+8X\u000b\u000fe\u001cB\u0017\u0008x\u0012X\u000bN,\u0008T\u0017\u000ci\u0015\u0019Y\u000b~E\u0017"
		// @47A: invokestatic game.C_100320_hh.func_102909_z(java.lang.String)char[]
		// @47D: invokestatic game.C_100320_hh.func_102908_z(char[])java.lang.String
		// @480: aastore
		// @481: aastore
		// @482: dup
		// @483: bipush 48 (0x30)
		// @485: iconst_1
		// @486: anewarray java.lang.String
		// @489: dup
		// @48A: iconst_0
		// @48B: ldc "0\u000b^\u0006[9E"
		// @48D: invokestatic game.C_100320_hh.func_102909_z(java.lang.String)char[]
		// @490: invokestatic game.C_100320_hh.func_102908_z(char[])java.lang.String
		// @493: aastore
		// @494: aastore
		// @495: dup
		// @496: bipush 49 (0x31)
		// @498: iconst_1
		// @499: anewarray java.lang.String
		// @49C: dup
		// @49D: iconst_0
		// @49E: ldc "0\u0019E[ b[V\u000b\u0010,\u0019V\u0011\u001d`\u001e\u001bE\ri\u0008C\u0017\u0006u\u0012Y\u0002I\u007f\u001eY\u0011\u0000b\u001e[\u0016I{\u0012C\rIm[_\u000c\u000ed\u001eEE\u001di\u0018_E\u001fm\u0017B\u0000Ie\u0008\u0017\u0012\u0006~\u000f_E\u0004c\tRE\u001dc[N\n\u001c~[D\u0006\u0006~\u001e\u0019Y\u000b~Ed\u0000\u0007x\u0012Y\u0000\u0005\u007f[X\u0013\u000c~[VE\ni\tC\u0004\u0000b[C\u0000\nd[A\u0004\u0005y\u001e\u0017\u0004\u001bi[T\t\u0008\u007f\u0008R\u0001Im\u0008\u0017Y\nc\u0017\nT\u000f;MVSWm\u001fA\u0004\u0007o\u001eSYFo\u0014[[G,:S\u0013\u0008b\u0018R\u0001Im\u0015SE\u001ax\u001aY\u0001\u0008~\u001f\u0017\u0016\u000cb\u000f^\u000b\u000c`\u0008\u0017\u0012\u0000`\u0017\u0017\u000b\u0006x[C\u001c\u0019e\u0018V\t\u0005u[G\u0004\u001bx\u0012T\u000c\u0019m\u000fRE\u0000b[C\r\u000c,\u0008V\u0008\u000c,\u0019V\u0011\u001d`\u001eDKI0\u0019E[ b[C\r\u000c,\u0016B\t\u001de\u000b[\u0004\u0010i\t\u0017\t\u0006n\u0019NIIu\u0014BE\nm\u0015\u0017\u0016\u000c`\u001eT\u0011Ix\u0013REUo\u0014[XXjL\u0001\u0004_2\u000fR\u0006\u0001b\u0014[\n\u000eu[[\u0000\u001fi\u0017\u000bJ\nc\u0017\tE\u0006j[C\r\u000c,\u0019V\u0011\u001d`\u001eDE\u0010c\u000e\u0017\u0012\u0008b\u000f\u0017\u0011\u0006,\u000bV\u0017\u001de\u0018^\u0015\u0008x\u001e\u0017\u000c\u0007\"GU\u0017W0\u0019E[Uo\u0014[XXjL\u0001\u0004_29V\u0016\u0000oG\u0018\u0006\u0006`E\u000b\u0007\u001b2/_\u000c\u001a,\u0014Y\t\u0010,\u000bR\u0017\u0004e\u000fDE\u0019`\u001aN\u0000\u001b\u007f[B\u0016\u0000b\u001c\u0017\u0011\u0001i[S\u0000\u000fm\u000e[\u0011Ia\u0014S\u0000\u0005\u007f[X\u0003Ix\u0013RE.c\u0017R\u0008U\u007f\u0013N[E,([\u0004\u001fiGD\r\u00102[V\u000b\r,:F\u0010\u0000`\u001a\u001a\u0006\u0005m\u0008DE\u001ai\u0015C\u000c\u0007i\u0017DK"
		// @4A0: invokestatic game.C_100320_hh.func_102909_z(java.lang.String)char[]
		// @4A3: invokestatic game.C_100320_hh.func_102908_z(char[])java.lang.String
		// @4A6: aastore
		// @4A7: aastore
		// @4A8: dup
		// @4A9: bipush 50 (0x32)
		// @4AB: iconst_1
		// @4AC: anewarray java.lang.String
		// @4AF: dup
		// @4B0: iconst_0
		// @4B1: ldc "0\u0018X\tT=\u001d\u0000S\u0008:Ed\u0011\u0008b\u001fV\u0017\r0TT\n\u00052GU\u0017WX\u0013^\u0016I{\u0012[\tIb\u0014CE\u0019i\tZ\u000c\u001d,\u000b[\u0004\u0010i\tDE\u001ee\u000f_E\u001ai\u0015C\u000c\u0007i\u0017DE\u0006j[V\u000bIm\u001fA\u0004\u0007o\u001eSE\u001di\u0018_E\u001fm\u0017B\u0000G"
		// @4B3: invokestatic game.C_100320_hh.func_102909_z(java.lang.String)char[]
		// @4B6: invokestatic game.C_100320_hh.func_102908_z(char[])java.lang.String
		// @4B9: aastore
		// @4BA: aastore
		// @4BB: dup
		// @4BC: bipush 51 (0x33)
		// @4BE: iconst_1
		// @4BF: anewarray java.lang.String
		// @4C2: dup
		// @4C3: iconst_0
		// @4C4: ldc "0\u0018X\tT=\u001d\u0000S\u0008:Ev\u0001\u001fm\u0015T\u0000\r0TT\n\u00052GU\u0017WX\u0013^\u0016I|\u001eE\u0008\u0000x\u0008\u0017\u0015\u0005m\u0002R\u0017\u001a,\u000eD\u000c\u0007k[D\u0000\u0007x\u0012Y\u0000\u0005\u007f[X\u0003Im\u0015NE\u001di\u0018_E\u001fm\u0017B\u0000G0\u0019E[Un\t\t,\u000f,\u0002X\u0010Io\u0013X\n\u001ai[C\nIk\u0014\u0017\u000c\u0007x\u0014\u0017\u0004\rz\u001aY\u0006\u000ch[C\u0000\nd[[\u0000\u001fi\u0017\u0017\u0002\u0008a\u001eDIIu\u0014BE\u0001m\rRE\u001dd\u001e\u0017\n\u0019|\u0014E\u0011\u001cb\u0012C\u001cIx\u0014\u0017\u0000\u0008~\u0015\u0017\u0008\u0006~\u001e\u0017\u0016\u0006`\u001aE\u000c\u001diW\u0017\u0007\u001cx[N\n\u001c,\u000c^\t\u0005,\u0019RE\u000fm\u0018^\u000b\u000e,\u000b[\u0004\u0010i\tDE\u001ee\u000f_E\u0008`\u0017\u0017\u0011\u0001i[Z\n\u001ax[S\u0000\u0008h\u0017NE\u001di\u0018_\u000b\u0006`\u0014P\u001cG"
		// @4C6: invokestatic game.C_100320_hh.func_102909_z(java.lang.String)char[]
		// @4C9: invokestatic game.C_100320_hh.func_102908_z(char[])java.lang.String
		// @4CC: aastore
		// @4CD: aastore
		// @4CE: dup
		// @4CF: bipush 52 (0x34)
		// @4D1: iconst_1
		// @4D2: anewarray java.lang.String
		// @4D5: dup
		// @4D6: iconst_0
		// @4D7: ldc "0\u0013\t \u0007k\u0012Y\u0000\u000c~\u0012Y\u0002"
		// @4D9: invokestatic game.C_100320_hh.func_102909_z(java.lang.String)char[]
		// @4DC: invokestatic game.C_100320_hh.func_102908_z(char[])java.lang.String
		// @4DF: aastore
		// @4E0: aastore
		// @4E1: dup
		// @4E2: bipush 53 (0x35)
		// @4E4: iconst_1
		// @4E5: anewarray java.lang.String
		// @4E8: dup
		// @4E9: iconst_0
		// @4EA: ldc "C\u0015RE\u001em\u0002\u0017\u0011\u0006,\u001aT\u0014\u001ce\tRE\u0007i\u000c\u0017\u0011\u000co\u0013Y\n\u0005c\u001cNE\u0000\u007f[C\nIi\u0003G\u0000\u0007h[\u000b\u0006\u0006`F\u0006\u0003^:\u001a\u0001[\u001ac\u0017V\u0017\u0000x\u001e\u000bJ\nc\u0017\tE\u0006b[R\u000b\u000ee\u0015R\u0000\u001be\u0015PKI_\u0014[\u0004\u001be\u000fRE\nm\u0015\u0017\u0007\u000c,\u001eV\u0017\u0007i\u001f\u0017\u000c\u0007,\u0016B\t\u001de\u000b[\u0004\u0010i\t\u0017\u0002\u0008a\u001eDII|\u001aE\u0011\u0000o\u000e[\u0004\u001b`\u0002\u00177\u0008x\u001eSE\u000em\u0016R\u0016G,2YE\u000cm\u0018_E\u001dm\u0019\u0017\n\u000f,\u000f_\u0000I+8X\u000b\u000fe\u001cB\u0017\u0008x\u0012X\u000bN,\u0008T\u0017\u000ci\u0015\u0017\u0011\u0001i\tRE\u0000\u007f[VE\u0005e\u0008CE\u0006j[R\u000b\u000ee\u0015R\u0000\u001bi\u001f\u0017\u000c\u001di\u0016DE\u000fc\u0017[\n\u001ei\u001f\u0017\u0007\u0010,\u001a\u0017\t\u0000\u007f\u000f\u0017\n\u000f,\u0012C\u0000\u0004\u007f[C\r\u0008x[N\n\u001c,\u0013V\u0013\u000c,\u0015X\u0011Iu\u001eCE\u000cb\u001c^\u000b\u000ci\tR\u0001G,6X\u0017\u000c,\u0012C\u0000\u0004\u007f[V\u0015\u0019i\u001aEE\u0006b[C\r\u0000\u007f[[\u000c\u001ax[V\u0016Iu\u0014BE\u0008h\rV\u000b\ni[^\u000bIx\u001eT\r\u0007c\u0017X\u0002\u0010\"GU\u0017W,"
		// @4EC: invokestatic game.C_100320_hh.func_102909_z(java.lang.String)char[]
		// @4EF: invokestatic game.C_100320_hh.func_102908_z(char[])java.lang.String
		// @4F2: aastore
		// @4F3: aastore
		// @4F4: dup
		// @4F5: bipush 54 (0x36)
		// @4F7: iconst_2
		// @4F8: anewarray java.lang.String
		// @4FB: dup
		// @4FC: iconst_0
		// @4FD: ldc "0\u000b^\u0006[>E"
		// @4FF: invokestatic game.C_100320_hh.func_102909_z(java.lang.String)char[]
		// @502: invokestatic game.C_100320_hh.func_102908_z(char[])java.lang.String
		// @505: aastore
		// @506: dup
		// @507: iconst_1
		// @508: ldc "M\u0015NE\u0000x\u001eZE\u001dd\u001aCE\u0001m\u0008\u0017\u0004Ik\tR\u0000\u0007,\u001eY\u0002\u0000b\u001eR\u0017In\u000eC\u0011\u0006b[^\u0016I\u007f\u0014Z\u0000\u001dd\u0012Y\u0002Iu\u0014BE\nm\u0015\u0017\u0000\u0007k\u0012Y\u0000\u000c~[E\u000c\u000ed\u000f\u0017\u0004\u001em\u0002\u0017\u0007\u0010,\u0018[\u000c\ng\u0012Y\u0002Ic\u0015\u0017\u0011\u0001i[U\u0010\u001dx\u0014YKIC\u0015T\u0000Ix\u0013RE\u0000x\u001eZE\u0001m\u0008\u0017\u0007\u000ci\u0015\u0017\u0000\u0007k\u0012Y\u0000\u000c~\u001eSIIu\u0014BE\nm\u0015\u0017\u0004\rh[^\u0011Ix\u0014\u0017\u0004\u0007u[D\u0000\u0007x\u0012Y\u0000\u0005,\u000c^\u0011\u0001,\u001a\u0017\u0016\u001ce\u000fV\u0007\u0005i[D\t\u0006xU"
		// @50A: invokestatic game.C_100320_hh.func_102909_z(java.lang.String)char[]
		// @50D: invokestatic game.C_100320_hh.func_102908_z(char[])java.lang.String
		// @510: aastore
		// @511: aastore
		// @512: dup
		// @513: bipush 55 (0x37)
		// @515: iconst_1
		// @516: anewarray java.lang.String
		// @519: dup
		// @51A: iconst_0
		// @51B: ldc ",GU\u0017WC\u0015\u0017\u0011\u0001i[T\r\u0008\u007f\u0008^\u0016Ix\u001aUII|\u0014^\u000b\u001d,\u0002X\u0010\u001b,\u0016X\u0010\u001ai[V\u0011Im\u0015\u0017\u0000\u0007k\u0012Y\u0000\u000c~[U\u0010\u001dx\u0014YE\u001dc[D\u0000\u000c,\u000f_\u0000I`\u0012D\u0011Ic\u001d\u0017\u0001\u000cj\u001aB\t\u001d,\u0012C\u0000\u0004\u007f[X\u000bIx\u0013V\u0011I\u007f\u001eY\u0011\u0000b\u001e[KI[\u0013R\u000bIu\u0014BE\u0001m\rRE\u001cb\u0017X\u0006\u0002i\u001f\u0017\u0000\u001fi\tNE\u0000x\u001eZE\u0000b[C\r\u0008x[[\u000c\u001axW\u0017\u0011\u0001i[Y\u0000\u001e,\u0018_\u0004\u001a\u007f\u0012DE\u001ee\u0017[E\u000bi[B\u000b\u0005c\u0018\\\u0000\r,\u001aDE\u001ei\u0017[K"
		// @51D: invokestatic game.C_100320_hh.func_102909_z(java.lang.String)char[]
		// @520: invokestatic game.C_100320_hh.func_102908_z(char[])java.lang.String
		// @523: aastore
		// @524: aastore
		// @525: dup
		// @526: bipush 56 (0x38)
		// @528: iconst_1
		// @529: anewarray java.lang.String
		// @52C: dup
		// @52D: iconst_0
		// @52E: ldc "A\u001aY\u001cIe\u000fR\u0008\u001a,\u0018V\u000bIn\u001e\u0017\u0010\u0007`\u0014T\u000e\u000ch[U\u001cIo\u0014Z\u0015\u0005i\u000f^\u000b\u000e,\u000fE\u0004\u0000b\u0012Y\u0002Im\u0015SE\nm\u0016G\u0004\u0000k\u0015\u0017\u0008\u0000\u007f\u0008^\n\u0007\u007fU"
		// @530: invokestatic game.C_100320_hh.func_102909_z(java.lang.String)char[]
		// @533: invokestatic game.C_100320_hh.func_102908_z(char[])java.lang.String
		// @536: aastore
		// @537: aastore
		// @538: dup
		// @539: bipush 57 (0x39)
		// @53B: iconst_1
		// @53C: anewarray java.lang.String
		// @53F: dup
		// @540: iconst_0
		// @541: ldc "0\u0013\t\"\u0008a\u001eG\t\u0008u[z\n\ri\u0008"
		// @543: invokestatic game.C_100320_hh.func_102909_z(java.lang.String)char[]
		// @546: invokestatic game.C_100320_hh.func_102908_z(char[])java.lang.String
		// @549: aastore
		// @54A: aastore
		// @54B: dup
		// @54C: bipush 58 (0x3A)
		// @54E: iconst_1
		// @54F: anewarray java.lang.String
		// @552: dup
		// @553: iconst_0
		// @554: ldc "0\u0018X\tT=\u001d\u0000S\u0008:Eu$=X7r# I7s6U#\u0018X\tW0\u0019E[=d\u001eE\u0000Im\tRE\u001ai\rR\u0017\u0008`[Y\u0000\u0008~\u0019NE\u0019`\u001aY\u0000\u001d\u007f[@\r\u000c~\u001e\u0017\u0016\u000cb\u000f^\u000b\u000c`\u0008\u0017\u0013\u0000i[Q\n\u001b,\u0008B\u0015\u001bi\u0016V\u0006\u0010\"[r\u0004\nd[U\u0004\u001dx\u0017R\u0003\u0000i\u0017SE\u0001m\u0008\u0017\u000c\u001d\u007f[X\u0012\u0007,\u001eY\u0013\u0000~\u0014Y\u0008\u000cb\u000f\u0017\u0011\u0001m\u000f\u0017\u0004\u000fj\u001eT\u0011\u001a,\u000f_\u0000In\u001aC\u0011\u0005iU"
		// @556: invokestatic game.C_100320_hh.func_102909_z(java.lang.String)char[]
		// @559: invokestatic game.C_100320_hh.func_102908_z(char[])java.lang.String
		// @55C: aastore
		// @55D: aastore
		// @55E: dup
		// @55F: bipush 59 (0x3B)
		// @561: iconst_1
		// @562: anewarray java.lang.String
		// @565: dup
		// @566: iconst_0
		// @567: ldc "0\u000fX\u0015W0\u0018X\tT=\u001d\u0000S\u0008:E`\u0004\u001b,!X\u000b\u000c0TT\n\u00052GU\u0017WM[E\u0010\u0000b\u001eSE\u0005m\u0015S\u0016\nm\u000bRE\u001ee\u000f_E\u001bc\u0018\\\u0016Im\u0015SE\nm\rR\u0016G,>A\u0000\u001bu[X\u0011\u0001i\t\u0017\u0016\u000cb\u000f^\u000b\u000c`[_\u0000\u001bi[^\u0016Iu\u0014B\u0017Ii\u0015R\u0008\u0010\"[n\n\u001c,\u0008_\n\u001c`\u001f\u0017\u0004\u0005\u007f\u0014\u0017\u0012\u0008x\u0018_E\u0006y\u000f\u0017\u0003\u0006~[V\u0010\u001dc\u0016V\u0011\u000ch[T\n\u0004n\u001aCE\r~\u0014Y\u0000\u001a,\u001fE\u0004\u001eb[U\u001cIx\u0013RE\u001ac\u000eY\u0001Ic\u001d\u0017\u0007\u0008x\u000f[\u0000G"
		// @569: invokestatic game.C_100320_hh.func_102909_z(java.lang.String)char[]
		// @56C: invokestatic game.C_100320_hh.func_102908_z(char[])java.lang.String
		// @56F: aastore
		// @570: aastore
		// @571: dup
		// @572: bipush 60 (0x3C)
		// @574: iconst_1
		// @575: anewarray java.lang.String
		// @578: dup
		// @579: iconst_0
		// @57A: ldc "0\u000fX\u0015W0\u0018X\tT=\u001d\u0000S\u0008:E{\n\u001ax[`\n\u001b`\u001f\u000bJ\nc\u0017\tY\u000b~En\n\u001c~[C\u0000\u0008a[D\u0011\u001by\u001cP\t\u000c,\u001aP\u0004\u0000b\u0008CE\u0006|\u000bX\u0016\u0000b\u001c\u0017\u0003\u0006~\u0018R\u0016Ic\u0015\u0017\u0004In\u001aE\u0017\u000cb[@\n\u001b`\u001f\u0017\u0012\u0001e\u0017RE\u001ax\u001aEE\n~\u000e^\u0016\u000c~\u0008\u0017\u0007\u0008x\u000f[\u0000Ie\u0015\u0017\n\u001bn\u0012CKIE\u000f\u0017\u0006\u0008b[X\u000b\u0005u[U\u0000Im[Z\u0004\u001dx\u001eEE\u0006j[C\u000c\u0004i[U\u0000\u000fc\tRE\u001dd\u001e\u0017\u0007\u0008x\u000f[\u0000Ie\u0015\u0017\u0016\u0019m\u0018RE\u001bi\u001aT\r\u000c\u007f[C\r\u000c,\u0008B\u0017\u000fm\u0018RK"
		// @57C: invokestatic game.C_100320_hh.func_102909_z(java.lang.String)char[]
		// @57F: invokestatic game.C_100320_hh.func_102908_z(char[])java.lang.String
		// @582: aastore
		// @583: aastore
		// @584: dup
		// @585: bipush 61 (0x3D)
		// @587: iconst_1
		// @588: anewarray java.lang.String
		// @58B: dup
		// @58C: iconst_0
		// @58D: ldc "0\u000fX\u0015W0\u0018X\tT=\u001d\u0000S\u0008:Et\u000c\u001duG\u0018\u0006\u0006`E\u000b\u0007\u001b2:Z\n\u0007k[C\r\u000c,\tB\u000c\u0007\u007f[X\u0003Im[X\u000b\ni[Z\u000c\u000ed\u000fNE\u0004i\u000fE\n\u0019c\u0017^\u0016Ix\u0013R\u0017\u000c,\u0012DE\u0008,\rV\t\u001cm\u0019[\u0000I|\u0012R\u0006\u000c,\u0014QE\u001di\u0018_\u000b\u0006`\u0014P\u001cIx\u0014\u0017\u0017\u000cx\t^\u0000\u001fiU\u0017!\u000c\u007f\u000fE\n\u0010,\u000c_\n\u000cz\u001eEE\u0001m\u0008\u0017\u000c\u001d [D\u0011\u000cm\u0017\u0017\u000c\u001d,\u001dX\u0017Iu\u0014B\u0017\u001ai\u0017QE\u0008b\u001f\u0017\u0000\u0008~\u0015\u0017\u0015\u0006e\u0015C\u0016Im\u0017[E\u001dd\u001e\u0017\u0011\u0000a\u001e\u0017\u001c\u0006y[_\n\u0005h[X\u000bIx\u0014\u0017\u000c\u001d\""
		// @58F: invokestatic game.C_100320_hh.func_102909_z(java.lang.String)char[]
		// @592: invokestatic game.C_100320_hh.func_102908_z(char[])java.lang.String
		// @595: aastore
		// @596: aastore
		// @597: dup
		// @598: bipush 62 (0x3E)
		// @59A: iconst_1
		// @59B: anewarray java.lang.String
		// @59E: dup
		// @59F: iconst_0
		// @5A0: ldc "0\u000fX\u0015W0\u0018X\tT=\u001d\u0000S\u0008:Ez\n\u0006bG\u0018\u0006\u0006`E\u000b\u0007\u001b2:\u0017\u0006\u001bm\u0008_\u0000\r,\u0018E\u0010\u0000\u007f\u001eEE\u0006o\u0018B\u0015\u0000i\u0008\u0017\u0011\u0001e\u0008\u0017\u0012\u0006~\u0017SKIE\u000fDE\u001ax\u0012[\tD{\u0014E\u000e\u0000b\u001c\u0017\u0016\u0001e\u001e[\u0001\u001a,\u0019[\n\ng[R\u000b\u000c~\u001cNE\u001ei\u001aG\n\u0007\u007fU\u0017 \u0008~\u0015\u0017\u0015\u0006e\u0015C\u0016Ij\u0014EE\u0006o\u0018B\u0015\u0010e\u0015PE\u001dd\u001e\u0017\u0016\u0001e\u001e[\u0001\u001a\""
		// @5A2: invokestatic game.C_100320_hh.func_102909_z(java.lang.String)char[]
		// @5A5: invokestatic game.C_100320_hh.func_102908_z(char[])java.lang.String
		// @5A8: aastore
		// @5A9: aastore
		// @5AA: dup
		// @5AB: bipush 63 (0x3F)
		// @5AD: iconst_1
		// @5AE: anewarray java.lang.String
		// @5B1: dup
		// @5B2: iconst_0
		// @5B3: ldc "0\u000fX\u0015W0\u0018X\tT=\u001d\u0000S\u0008:Ed\u0011\u0008~[q\t\u000ci\u000f\u000bJ\nc\u0017\tY\u000b~Ec\u0012\u0006,\u000fR\u0004\u0004\u007f[U\u0004\u001dx\u0017RE\u0000b[X\u0017\u000be\u000f\u0017\n\u0007,\u001c^\u0004\u0007x[D\u0011\u0008~[T\u0017\u001ce\u0008R\u0017\u001a\"[~\u0003Iu\u0014BE\nm\u0015\u0017\u0017\u000cm\u0018_E\u001dd\u001e\u0017\u0000\u0007i\u0016NE\n~\u000e^\u0016\u000c~[V\u000b\r,\tR\u0011\u001c~\u0015\u0017\u0016\u0008j\u001e[\u001cE,\u0002X\u0010\u001b,\u0008_\u000c\u0019,\u000c^\t\u0005,\u0019RE\u0008n\u0017RE\u001dc[T\r\u0008~\u001cRE\u0000x\u0008\u0017\u0000\u0007c\tZ\nD`\u001aD\u0000\u001b\"[z\u0004\u0002i[D\u0010\u001bi[D\n\u0004i\u0014Y\u0000Ie\u0008\u0017\n\u0007,\u0002X\u0010\u001b,\u0008_\u000c\u0019,\u000fXE\ri\u001dR\u000b\r,\u0012CE\u0008k\u001a^\u000b\u001ax[^\u000b\u001fm\u001fR\u0017\u001a\""
		// @5B5: invokestatic game.C_100320_hh.func_102909_z(java.lang.String)char[]
		// @5B8: invokestatic game.C_100320_hh.func_102908_z(char[])java.lang.String
		// @5BB: aastore
		// @5BC: aastore
		// @5BD: dup
		// @5BE: bipush 64 (0x40)
		// @5C0: iconst_1
		// @5C1: anewarray java.lang.String
		// @5C4: dup
		// @5C5: iconst_0
		// @5C6: ldc "0\u0018X\tT=\u001d\u0000S\u0008:Et$$\\:~\"'_G\u0018\u0006\u0006`E\u000b\u0007\u001b2/XE\u0008h\rV\u000b\ni[^\u000bI~\u001aY\u000eIm\u0015SE\u0001i\u0017GE\u0010c\u000eEE\u0019i\u0014G\t\u000c,\u001fR\u0013\u000c`\u0014GE\u0007i\u000c\u0017\u0011\u000co\u0013Y\n\u0005c\u001cNE\u000fm\u0008CIIx\u0013R\u0017\u000c,\u001aE\u0000Ib\u000eZ\u0000\u001bc\u000eDE\u0004e\u0008D\u000c\u0006b\u0008\u0017\u001c\u0006y[T\u0004\u0007,\u000eY\u0001\u000c~\u000fV\u000e\u000c\"[r\u0004\nd[X\u000b\u000c,\u001c^\u0013\u000c\u007f[N\n\u001c,\u001a\u0017\u0016\u0019i\u0018^\u0003\u0000o[D\u0000\u0007x\u0012Y\u0000\u0005,\u001fR\u0016\u0000k\u0015\u0017\u0004\u0007h[D\u0000\u0007h\u0008\u0017\u001c\u0006y[X\u0010\u001d,\u000fXE\ri\u001dR\u0004\u001d,\u000f_\u0000Ii\u0015R\u0008\u0000i\u0008\u0010E\u000fc\tT\u0000\u001a\"GU\u0017WX\u0013RE\u000fe\tD\u0011Ix\u001eYE\u0008~\u001e\u0017Y\nc\u0017\nT\u000f;MVSWx\tV\u000c\u0007e\u0015PE\u0004e\u0008D\u000c\u0006b\u0008\u000bJ\nc\u0017\tKI\\\tX\u0002\u001bi\u0008D\u000c\u0007k[C\r\u001bc\u000eP\rIx\u0013R\u0016\u000c,\u000eY\t\u0006o\u0010DE\u001dd\u001e\u0017\u0011\u0001~\u001eRE\u000bm\u0008^\u0006Ia\u0014S\u0000\u0005\u007f[X\u0003I\u007f\u001eY\u0011\u0000b\u001e[E\u0000b[T\n\u0004a\u0014YE\u001c\u007f\u001e\u0019Y\u000b~Eq\u0010\u001bx\u0013R\u0017Ia\u0012D\u0016\u0000c\u0015DE\u0008~\u001e\u0017\u0004\u001fm\u0012[\u0004\u000b`\u001e\u0017\n\u0007,\u000f_\u0000I0\u0018X\tT=\u001d\u0000S\u0008:Et\u0004\u0004|\u001a^\u0002\u0007\u007fG\u0018\u0006\u0006`E\u0017\u0016\n~\u001eR\u000bG,/_\u0000\u001ai[P\u000c\u001fi[N\n\u001c,\u001aT\u0006\u000c\u007f\u0008\u0017\u0011\u0006,\u0016X\u0017\u000c,\u000fR\u0006\u0001b\u0014[\n\u000eu[V\u0016Iu\u0014BE\nc\u0016G\t\u000cx\u001e\u0017\u0011\u0001i\u0016\u0019E b[C\r\u000c\u007f\u001e\u0017\u0008\u0000\u007f\u0008^\n\u0007\u007f[N\n\u001c,\u000c^\t\u0005,\u0013V\u0013\u000c,\u001a\u0017\t\u0000a\u0012C\u0000\r,\u0015B\u0008\u000bi\t\u0017\n\u000f,\tR\u0016\u0019m\u000cY\u0016E,\u000c_\u000c\nd[@\u000c\u0005`[C\u0000\u001ax[N\n\u001c~[D\u000e\u0000`\u0017DE\u0008\u007f[VE\u001ai\u0015C\u000c\u0007i\u0017\u0017\u0006\u0006a\u0016V\u000b\ri\t\u0019"
		// @5C8: invokestatic game.C_100320_hh.func_102909_z(java.lang.String)char[]
		// @5CB: invokestatic game.C_100320_hh.func_102908_z(char[])java.lang.String
		// @5CE: aastore
		// @5CF: aastore
		// @5D0: dup
		// @5D1: bipush 65 (0x41)
		// @5D3: iconst_1
		// @5D4: anewarray java.lang.String
		// @5D7: dup
		// @5D8: iconst_0
		// @5D9: ldc "0\u0018X\tT=\u001d\u0000S\u0008:Et*DC+\u000bJ\nc\u0017\t"
		// @5DB: invokestatic game.C_100320_hh.func_102909_z(java.lang.String)char[]
		// @5DE: invokestatic game.C_100320_hh.func_102908_z(char[])java.lang.String
		// @5E1: aastore
		// @5E2: aastore
		// @5E3: dup
		// @5E4: bipush 66 (0x42)
		// @5E6: iconst_1
		// @5E7: anewarray java.lang.String
		// @5EA: dup
		// @5EB: iconst_0
		// @5EC: ldc "0\u000b^\u0006X5E"
		// @5EE: invokestatic game.C_100320_hh.func_102909_z(java.lang.String)char[]
		// @5F1: invokestatic game.C_100320_hh.func_102908_z(char[])java.lang.String
		// @5F4: aastore
		// @5F5: aastore
		// @5F6: dup
		// @5F7: bipush 67 (0x43)
		// @5F9: iconst_1
		// @5FA: anewarray java.lang.String
		// @5FD: dup
		// @5FE: iconst_0
		// @5FF: ldc "U\u0014BE\u0008b\u001f\u0017\u0004\u0007,\u001a[\t\u0010,\u001cXE\u001dc[@\u0004\u001b,\u001aP\u0004\u0000b\u0008CE\u001em\rR\u0016Ic\u001d\u0017\u0000\u0007i\u0016^\u0000\u001a\"GU\u0017WU\u0014BE\u0008b\u001f\u0017\u001c\u0006y\t\u0017\u0004\u0005`\u0002\u0017\u0016\u001dm\tCE\u001ee\u000f_E\u0008,\u0017^\u0008\u0000x\u001eSE\u0007y\u0016U\u0000\u001b,\u0014QE\u001ai\u0015C\u000c\u0007i\u0017\u0017\u0017\u000c\u007f\u000bV\u0012\u0007\u007fW\u0017\u0012\u0001e\u0018_E\u0008~\u001e\u0017\u0010\u001ai\u001f\u0017\u0010\u0019,\u000c_\u0000\u0007,\u001e^\u0011\u0001i\t\u0017\n\u000f,\u0002X\u0010\u001b,\u0008R\u000b\u001de\u0015R\t\u001a,\u0012DE\ri\u0008C\u0017\u0006u\u001eSKIK\u001a^\u000b\u0000b\u001c\u0017\u0000\u0007c\u000eP\rI|\u0014^\u000b\u001d\u007f[R\u0004\u001bb\u0008\u0017\u001c\u0006y[R\u001d\u001d~\u001a\u0017\u0017\u000c\u007f\u000bV\u0012\u0007\u007fU\u0017$\u0007u[S\u0004\u0004m\u001cRE\u0010c\u000e\u0017\u000c\u0007j\u0017^\u0006\u001d,\u0014YE\u0010c\u000eEE\u0008`\u0017NE\u001ee\u0017[E\u001bi\u001fB\u0006\u000c,\u0002X\u0010\u001b,\u0008T\n\u001biU"
		// @601: invokestatic game.C_100320_hh.func_102909_z(java.lang.String)char[]
		// @604: invokestatic game.C_100320_hh.func_102908_z(char[])java.lang.String
		// @607: aastore
		// @608: aastore
		// @609: dup
		// @60A: bipush 68 (0x44)
		// @60C: iconst_1
		// @60D: anewarray java.lang.String
		// @610: dup
		// @611: iconst_0
		// @612: ldc "0\u0018X\tT=\u001d\u0000S\u0008:Ec$._G\u0018\u0006\u0006`E\u000b\u0007\u001b2:CE\u001dd\u001e\u0017\u0000\u0007h[X\u0003Im[Z\u0010\u0005x\u0012G\t\u0008u\u001eEE\u000em\u0016RIIu\u0014BE\u0004m\u0002\u0017\u0007\u000c,\u001a@\u0004\u001bh\u001eSE\u0006b\u001e\u0017\n\u001b,\u0016X\u0017\u000c,\\C\u0004\u000e\u007f\\\u0019E=m\u001cDE\u0008~\u001e\u0017\u0004\u001em\tS\u0000\r,\u001dX\u0017I\u007f\u000eT\u0006\u000c\u007f\u0008\u0017\u000c\u0007,\u001a\u0017\u000b\u001ca\u0019R\u0017Ic\u001d\u0017\u0006\u0008x\u001eP\n\u001be\u001eDII\u007f\u000eT\rIm\u0008\u0017B$c\u0008CE\"e\u0017[\u0016N,\u0014EENA\u0014D\u0011IH\u001aZ\u0004\u000ei\\\u0019E=d\u001e\u0017\u000b\u001ca\u0019R\u0017\u001a,\u0014QE\u001dm\u001cDE\u0010c\u000e\u0017\r\u0008z\u001e\u0017\u0004\n}\u000e^\u0017\u000ch[^\u000bI^\u001aC\u0000\r,\u001cV\u0008\u000c\u007f[V\u0017\u000c,\u0008_\n\u001eb[V\u0011Ix\u0013RE\u001ae\u001fR\u0016Ic\u001d\u0017\u0011\u0001i[v\u0006\u0001e\u001eA\u0000\u0004i\u0015C\u0016I\u007f\u0018E\u0000\u000cbU"
		// @614: invokestatic game.C_100320_hh.func_102909_z(java.lang.String)char[]
		// @617: invokestatic game.C_100320_hh.func_102908_z(char[])java.lang.String
		// @61A: aastore
		// @61B: aastore
		// @61C: dup
		// @61D: bipush 69 (0x45)
		// @61F: iconst_1
		// @620: anewarray java.lang.String
		// @623: dup
		// @624: iconst_0
		// @625: ldc "0\u0013\t$\u0019|\u001eY\u0001\u0000t[v_ID\u0012D\u0011\u0006~\u0002"
		// @627: invokestatic game.C_100320_hh.func_102909_z(java.lang.String)char[]
		// @62A: invokestatic game.C_100320_hh.func_102908_z(char[])java.lang.String
		// @62D: aastore
		// @62E: aastore
		// @62F: dup
		// @630: bipush 70 (0x46)
		// @632: iconst_1
		// @633: anewarray java.lang.String
		// @636: dup
		// @637: iconst_0
		// @638: ldc "E\u0015\u0017\u0011\u0001i[N\u0000\u0008~[\u0003WY<W\u0017\u0004I\u007f\u0018X\u0010\u001d,\u0008_\u000c\u0019,\u0014QE\u001dd\u001e\u00171\u000c~\tV\u000bIj\u0017R\u0000\u001d,\tR\u0015\u0006~\u000fR\u0001Ic\u0015\u0017\u0011\u0001i[G\u0017\u000c\u007f\u001eY\u0006\u000c,\u0014QE\u0000b\u000fR\u000b\u001ai[D\n\u0005m\t^\u0016Ii\u0015R\u0017\u000eu[E\u0000\u001ai\tA\u0000\u001a,\u0012YE\u001dd\u001e\u0017,\u0005c\u0017^\u0004\u0007,\u0008C\u0004\u001b,\u0008N\u0016\u001di\u0016\u0019E j[T\n\u001b~\u001eT\u0011\u0005u[C\u0004\u0019|\u001eSIIx\u0013RE\u001ac\u0017V\u0017\u0000x\u001e\u0017\u0015\u001bc\u001fB\u0006\u001de\u0014YE\nc\u000e[\u0001Ix\u0014G\u0015\u0005i[C\r\u000c,\u001cV\t\u0008o\u000f^\u0006Ii\u0018X\u000b\u0006a\u0002\u0019E'i\u000cDE\u0006j[C\r\u000c,\u001f^\u0016\nc\rR\u0017\u0010,\u000cV\u0016I\u007f\u000eG\u0015\u001bi\u0008D\u0000\r [U\u0010\u001d [D\n\u0006bW\u0017\u0008\u001c`\u000f^\u0015\u0005i[Z\u000c\u0007e\u0015PE\u0006~\u001cV\u000b\u0000\u007f\u001aC\u000c\u0006b\u0008\u0017\u0017\u001c\u007f\u0013R\u0001Ix\u0014\u0017\u0011\u0001i[D\u001c\u001ax\u001eZKUn\t\tQY,\u0002R\u0004\u001b\u007f[X\u000bE,\u000f_\u0000In\u001aC\u0011\u0005i[D\u0011\u0000`\u0017\u0017\u0017\u0008k\u001eDE\u000fc\t\u0017\u0006\u0006b\u000fE\n\u0005,\u0014QE\u001dd\u001e\u0017\u0016\u0010\u007f\u000fR\u0008G,(R\u000b\u001de\u0015R\tI|\u0012[\n\u001d\u007f[Q\u0017\u0006a[V\t\u0005,\u0008R\u0006\u001dc\tDE\u0006j[C\r\u000c,\u001cV\t\u0008t\u0002\u0017\u000b\u0006{[T\n\u0004i[C\nIx\u0013RE `\u0014[\u000c\u0008b[D\u001c\u001ax\u001eZE\u000fc\t\u0017\u0002\u0005c\tNE\u0008b\u001f\u0017\u0003\u0006~\u000fB\u000b\u000c\"[v\t\u0005e\u001aY\u0006\u000c\u007f[V\u0017\u000c,\u0014Y\t\u0010,\u001eA\u0000\u001b,\u000fR\u0008\u0019c\tV\u0017\u0010 [V\u0016Ix\u0013RE\r~\u0012A\u0000Ij\u0014EE\u001ac\u0017V\u0017\u0000x\u001e\u0017\u0011\u0001y\u0015S\u0000\u001b\u007f[Q\n\u001b{\u001aE\u0001\u001a\""
		// @63A: invokestatic game.C_100320_hh.func_102909_z(java.lang.String)char[]
		// @63D: invokestatic game.C_100320_hh.func_102908_z(char[])java.lang.String
		// @640: aastore
		// @641: aastore
		// @642: dup
		// @643: bipush 71 (0x47)
		// @645: iconst_1
		// @646: anewarray java.lang.String
		// @649: dup
		// @64A: iconst_0
		// @64B: ldc "0\u0013\t$\u0019|\u001eY\u0001\u0000t[u_I[\u001eV\u0015\u0006bGY\u0007\u001a|Et\t\u0008\u007f\u0008R\u0016"
		// @64D: invokestatic game.C_100320_hh.func_102909_z(java.lang.String)char[]
		// @650: invokestatic game.C_100320_hh.func_102908_z(char[])java.lang.String
		// @653: aastore
		// @654: aastore
		// @655: dup
		// @656: bipush 72 (0x48)
		// @658: iconst_1
		// @659: anewarray java.lang.String
		// @65C: dup
		// @65D: iconst_0
		// @65E: ldc "H\u0012Q\u0003\u000c~\u001eY\u0011I{\u001eV\u0015\u0006b\u0008\u0017\u0004\u001bi[U\u0004\u001ai\u001f\u0017\n\u0007,\u001f^\u0003\u000fi\tR\u000b\u001d,\u000fR\u0006\u0001b\u0014[\n\u000eu[V\u000b\r,\u0013V\u0013\u000c,\u000c^\u0001\u000c`\u0002\u0017\u0001\u0000j\u001dR\u0017\u0000b\u001c\u0017\u0000\u000fj\u001eT\u0011\u001a\"["
		// @660: invokestatic game.C_100320_hh.func_102909_z(java.lang.String)char[]
		// @663: invokestatic game.C_100320_hh.func_102908_z(char[])java.lang.String
		// @666: aastore
		// @667: aastore
		// @668: dup
		// @669: bipush 73 (0x49)
		// @66B: iconst_4
		// @66C: anewarray java.lang.String
		// @66F: dup
		// @670: iconst_0
		// @671: ldc "0\u000b^\u0006X<O\t"
		// @673: invokestatic game.C_100320_hh.func_102909_z(java.lang.String)char[]
		// @676: invokestatic game.C_100320_hh.func_102908_z(char[])java.lang.String
		// @679: aastore
		// @67A: dup
		// @67B: iconst_1
		// @67C: ldc "0\u0018X\tT=\u001d\u0000S\u0008:Et\t\u0006\u007f\u001e\u0017\u0004\u001a\u007f\u001aB\t\u001d,\u001cB\u000b\u001a0TT\n\u00052GU\u0017WB\u0014YE\u000cb\u001eE\u0002\u0010!\u0019V\u0016\u000ch[@\u0000\u0008|\u0014Y\u0016Ix\u0013V\u0011Ie\u0015Q\t\u0000o\u000f\u0017\u000e\u0000b\u001eC\u000c\n,\u001fV\u0008\u0008k\u001e\u0019E=d\u001eD\u0000Id\u001aA\u0000Im[[\u000c\u0004e\u000fR\u0001I~\u001aY\u0002\u000c\""
		// @67E: invokestatic game.C_100320_hh.func_102909_z(java.lang.String)char[]
		// @681: invokestatic game.C_100320_hh.func_102908_z(char[])java.lang.String
		// @684: aastore
		// @685: dup
		// @686: iconst_2
		// @687: ldc "0\u000b^\u0006X<N\t"
		// @689: invokestatic game.C_100320_hh.func_102909_z(java.lang.String)char[]
		// @68C: invokestatic game.C_100320_hh.func_102908_z(char[])java.lang.String
		// @68F: aastore
		// @690: dup
		// @691: iconst_3
		// @692: ldc "0\u0018X\tT=\u001d\u0000S\u0008:Eq\t\u0008g[T\u0004\u0007b\u0014Y\u0016U#\u0018X\tW0\u0019E[-i\u001dR\u000b\u001ae\rRE\u001ei\u001aG\n\u0007\u007f[B\u0016\u000ch[C\nIh\u001eC\n\u0007m\u000fRE\u001bc\u0018\\\u0000\u001d\u007f[V\u000b\r,\u0016^\u0016\u001ae\u0017R\u0016Ie\u0015\u0017\u0011\u0001i[V\u000c\u001b\"[q\t\u0008g[^\u000b\u000f`\u0012T\u0011\u001a,\u0010^\u000b\u000cx\u0012TE\rm\u0016V\u0002\u000c\""
		// @694: invokestatic game.C_100320_hh.func_102909_z(java.lang.String)char[]
		// @697: invokestatic game.C_100320_hh.func_102908_z(char[])java.lang.String
		// @69A: aastore
		// @69B: aastore
		// @69C: dup
		// @69D: bipush 74 (0x4A)
		// @69F: iconst_4
		// @6A0: anewarray java.lang.String
		// @6A3: dup
		// @6A4: iconst_0
		// @6A5: ldc "0\u000b^\u0006X<M\t"
		// @6A7: invokestatic game.C_100320_hh.func_102909_z(java.lang.String)char[]
		// @6AA: invokestatic game.C_100320_hh.func_102908_z(char[])java.lang.String
		// @6AD: aastore
		// @6AE: dup
		// @6AF: iconst_1
		// @6B0: ldc "0\u0018X\tT=\u001d\u0000S\u0008:Er\u001d\u0019`\u0014D\u000c\u001fi[T\u0004\u0007b\u0014Y\u0016U#\u0018X\tW0\u0019E['c\u0015\u0017\u0000\u0007i\tP\u001cDn\u001aD\u0000\r,\u000cR\u0004\u0019c\u0015DE\u001dd\u001aCE\u0005m\u000eY\u0006\u0001,\u0008_\u0000\u0005`\u0008\u0017\u0011\u0001m\u000f\u0017\u000c\u0007j\u0017^\u0006\u001d,\u001eO\u0015\u0005c\u0008^\u0013\u000c,\u001fV\u0008\u0008k\u001e\u0019"
		// @6B2: invokestatic game.C_100320_hh.func_102909_z(java.lang.String)char[]
		// @6B5: invokestatic game.C_100320_hh.func_102908_z(char[])java.lang.String
		// @6B8: aastore
		// @6B9: dup
		// @6BA: iconst_2
		// @6BB: ldc "0\u000b^\u0006X<L\t"
		// @6BD: invokestatic game.C_100320_hh.func_102909_z(java.lang.String)char[]
		// @6C0: invokestatic game.C_100320_hh.func_102908_z(char[])java.lang.String
		// @6C3: aastore
		// @6C4: dup
		// @6C5: iconst_3
		// @6C6: ldc "0\u0018X\tT=\u001d\u0000S\u0008:Ee\u000c\u000f`\u001eSE\nm\u0015Y\n\u0007\u007fG\u0018\u0006\u0006`E\u000b\u0007\u001b27X\u000b\u000e!\tV\u000b\u000eiW\u0017\u000b\u0006b[R\u000b\u000c~\u001cNH\u000bm\u0008R\u0001Ik\u000eY\u0016Ix\u0013V\u0011Ie\u0015Q\t\u0000o\u000f\u0017\u0000\u0011|\u0017X\u0016\u0000z\u001e\u0017\u0001\u0008a\u001aP\u0000G,/_\u0000\u0010,\u001aE\u0000I|\u001aE\u0011\u0000o\u000e[\u0004\u001b`\u0002\u0017\u0000\u000fj\u001eT\u0011\u0000z\u001e\u0017\u0004\u001d,\u0017X\u000b\u000e,\tV\u000b\u000eiU"
		// @6C8: invokestatic game.C_100320_hh.func_102909_z(java.lang.String)char[]
		// @6CB: invokestatic game.C_100320_hh.func_102908_z(char[])java.lang.String
		// @6CE: aastore
		// @6CF: aastore
		// @6D0: dup
		// @6D1: bipush 75 (0x4B)
		// @6D3: iconst_4
		// @6D4: anewarray java.lang.String
		// @6D7: dup
		// @6D8: iconst_0
		// @6D9: ldc "0\u000b^\u0006X<C\t"
		// @6DB: invokestatic game.C_100320_hh.func_102909_z(java.lang.String)char[]
		// @6DE: invokestatic game.C_100320_hh.func_102908_z(char[])java.lang.String
		// @6E1: aastore
		// @6E2: dup
		// @6E3: iconst_1
		// @6E4: ldc "0\u0018X\tT=\u001d\u0000S\u0008:Ev\u0017\u001de\u0017[\u0000\u001buG\u0018\u0006\u0006`E\u000b\u0007\u001b2>O\u0015\u0005c\u0008^\u0013\u000c,\u0019V\t\u0005e\u0008C\u000c\n,\u000cR\u0004\u0019c\u0015DE\u001dd\u001aCE\u0008~\u001e\u0017\n\u0007`\u0002\u0017\u0004\u001ba\u001eSE\u0008j\u000fR\u0017Ik\u0014^\u000b\u000e,\u0008X\u0008\u000c,\u001f^\u0016\u001dm\u0015T\u0000G,7R\u0016\u001a,\u001eQ\u0003\u000co\u000f^\u0013\u000c,\u001aCE\u001ad\u0014E\u0011I~\u001aY\u0002\u000c\""
		// @6E6: invokestatic game.C_100320_hh.func_102909_z(java.lang.String)char[]
		// @6E9: invokestatic game.C_100320_hh.func_102908_z(char[])java.lang.String
		// @6EC: aastore
		// @6ED: dup
		// @6EE: iconst_2
		// @6EF: ldc "0\u000b^\u0006X>H\t"
		// @6F1: invokestatic game.C_100320_hh.func_102909_z(java.lang.String)char[]
		// @6F4: invokestatic game.C_100320_hh.func_102908_z(char[])java.lang.String
		// @6F7: aastore
		// @6F8: dup
		// @6F9: iconst_3
		// @6FA: ldc "0\u0018X\tT=\u001d\u0000S\u0008:Eu\n\u0004n\u0008\u000bJ\nc\u0017\tY\u000b~Ec\r\u000c\u007f\u001e\u0017\u0003\u0008`\u0017\u0017\n\u0007,\u0002X\u0010\u001b,\u001eY\u0000\u0004e\u001eDIIe\u0015Q\t\u0000o\u000f^\u000b\u000e,\u001eO\u0015\u0005c\u0008^\u0013\u000c,\u001fV\u0008\u0008k\u001e\u0019"
		// @6FC: invokestatic game.C_100320_hh.func_102909_z(java.lang.String)char[]
		// @6FF: invokestatic game.C_100320_hh.func_102908_z(char[])java.lang.String
		// @702: aastore
		// @703: aastore
		// @704: dup
		// @705: bipush 76 (0x4C)
		// @707: iconst_4
		// @708: anewarray java.lang.String
		// @70B: dup
		// @70C: iconst_0
		// @70D: ldc "0\u000b^\u0006X<B\t"
		// @70F: invokestatic game.C_100320_hh.func_102909_z(java.lang.String)char[]
		// @712: invokestatic game.C_100320_hh.func_102908_z(char[])java.lang.String
		// @715: aastore
		// @716: dup
		// @717: iconst_1
		// @718: ldc "0\u0018X\tT=\u001d\u0000S\u0008:Er\u000b\u000c~\u001c^\u0016\u000ch[\\\u000c\u0007i\u000f^\u0006I{\u001eV\u0015\u0006b\u0008\u000bJ\nc\u0017\tY\u000b~E\u007f\u000c\u000edVD\u0015\u000ci\u001f\u0017\u0012\u000cm\u000bX\u000b\u001a,\u000f_\u0004\u001d,\u000eD\u0000Ii\u0015R\u0017\u000eu[^\u000bIj\u0012E\u000c\u0007k[V\u000b\r,\u0012Y\u0003\u0005e\u0018CE\u0002e\u0015R\u0011\u0000o[S\u0004\u0004m\u001cRK"
		// @71A: invokestatic game.C_100320_hh.func_102909_z(java.lang.String)char[]
		// @71D: invokestatic game.C_100320_hh.func_102908_z(char[])java.lang.String
		// @720: aastore
		// @721: dup
		// @722: iconst_2
		// @723: ldc "0\u000b^\u0006X=K\t"
		// @725: invokestatic game.C_100320_hh.func_102909_z(java.lang.String)char[]
		// @728: invokestatic game.C_100320_hh.func_102908_z(char[])java.lang.String
		// @72B: aastore
		// @72C: dup
		// @72D: iconst_3
		// @72E: ldc "0\u0018X\tT=\u001d\u0000S\u0008:E{\u0004\u001ai\t\u0017\u0012\u000cm\u000bX\u000b\u001a0TT\n\u00052GU\u0017W@\u001aD\u0000\u001b\u007f[B\u0016\u000c,\u000eGE\u000cb\u001eE\u0002\u0010,\u001aY\u0001Ie\u0015Q\t\u0000o\u000f\u0017\u0000\u0007i\tP\u001cIh\u001aZ\u0004\u000ei[X\u000bIx\u0013R\u000c\u001b,\u000fV\u0017\u000ei\u000f\u0019"
		// @730: invokestatic game.C_100320_hh.func_102909_z(java.lang.String)char[]
		// @733: invokestatic game.C_100320_hh.func_102908_z(char[])java.lang.String
		// @736: aastore
		// @737: aastore
		// @738: dup
		// @739: bipush 77 (0x4D)
		// @73B: iconst_4
		// @73C: anewarray java.lang.String
		// @73F: dup
		// @740: iconst_0
		// @741: ldc "0\u000b^\u0006X=J\t"
		// @743: invokestatic game.C_100320_hh.func_102909_z(java.lang.String)char[]
		// @746: invokestatic game.C_100320_hh.func_102908_z(char[])java.lang.String
		// @749: aastore
		// @74A: dup
		// @74B: iconst_1
		// @74C: ldc "0\u0018X\tT=\u001d\u0000S\u0008:Ed\u0010\u0019i\t\u0017\t\u0008\u007f\u001eEE\u001ei\u001aG\n\u0007\u007fG\u0018\u0006\u0006`E\u000b\u0007\u001b2(B\u0015\u000c~[[\u0004\u001ai\tDE\u001c\u007f\u001e\u0017\u0010\u0019,\u001a\u0017\t\u0006x[X\u0003Ii\u0015R\u0017\u000eu[C\nIe\u0015Q\t\u0000o\u000f\u0017\u0000\u0011x\tR\u0008\u000c,\u001eY\u0000\u001bk\u0002\u0017\u0001\u0008a\u001aP\u0000G"
		// @74E: invokestatic game.C_100320_hh.func_102909_z(java.lang.String)char[]
		// @751: invokestatic game.C_100320_hh.func_102908_z(char[])java.lang.String
		// @754: aastore
		// @755: dup
		// @756: iconst_2
		// @757: ldc "0\u000b^\u0006X=I\t"
		// @759: invokestatic game.C_100320_hh.func_102909_z(java.lang.String)char[]
		// @75C: invokestatic game.C_100320_hh.func_102908_z(char[])java.lang.String
		// @75F: aastore
		// @760: dup
		// @761: iconst_3
		// @762: ldc "0\u0018X\tT=\u001d\u0000S\u0008:Eg\t\u0008\u007f\u0016VE\u001ei\u001aG\n\u0007\u007fG\u0018\u0006\u0006`E\u000b\u0007\u001b2>Y\u0000\u001bk\u0002\u001a\u0007\u0008\u007f\u001eSE\u001ei\u001aG\n\u0007\u007f[C\r\u0008x[D\u0015\u001bm\u0002\u0017\u000c\u0006b\u0012D\u0000\r,\u001cV\u0016E,\u0012Y\u0003\u0005e\u0018C\u000c\u0007k[R\u000b\u000c~\u001cNE\rm\u0016V\u0002\u000c\""
		// @764: invokestatic game.C_100320_hh.func_102909_z(java.lang.String)char[]
		// @767: invokestatic game.C_100320_hh.func_102908_z(char[])java.lang.String
		// @76A: aastore
		// @76B: aastore
		// @76C: dup
		// @76D: bipush 78 (0x4E)
		// @76F: iconst_4
		// @770: anewarray java.lang.String
		// @773: dup
		// @774: iconst_0
		// @775: ldc "0\u000b^\u0006X=H\t"
		// @777: invokestatic game.C_100320_hh.func_102909_z(java.lang.String)char[]
		// @77A: invokestatic game.C_100320_hh.func_102908_z(char[])java.lang.String
		// @77D: aastore
		// @77E: dup
		// @77F: iconst_1
		// @780: ldc "0\u0018X\tT=\u001d\u0000S\u0008:Er(9,\u000cR\u0004\u0019c\u0015DYFo\u0014[[Un\t\t1\u0001i\u0008RE\u001ei\u001aG\n\u0007\u007f[S\u0000\u0019`\u001eC\u0000I\u007f\u0013^\u0000\u0005h\u0008\u001bE\u0008b\u001f\u0017\u0001\u001bm\u0012YE\u001dd\u001e\u0017\u0000\u0007i\tP\u001cIc\u001d\u0017\u0004\u0007u[C\u0004\u001bk\u001eC\u0016Ix\u0013V\u0011Ih\u0014\u0017\u000b\u0006x[G\n\u001a\u007f\u001eD\u0016Ix\u0013RE,A+\u0017\r\u0008~\u001fR\u000b\u0000b\u001c\u0017\u0008\u0006h\u000e[\u0000G"
		// @782: invokestatic game.C_100320_hh.func_102909_z(java.lang.String)char[]
		// @785: invokestatic game.C_100320_hh.func_102908_z(char[])java.lang.String
		// @788: aastore
		// @789: dup
		// @78A: iconst_2
		// @78B: ldc "0\u000b^\u0006X=O\t"
		// @78D: invokestatic game.C_100320_hh.func_102909_z(java.lang.String)char[]
		// @790: invokestatic game.C_100320_hh.func_102908_z(char[])java.lang.String
		// @793: aastore
		// @794: dup
		// @795: iconst_3
		// @796: ldc "0\u0018X\tT=\u001d\u0000S\u0008:Ee\u0004\u0019e\u001eEE\u0004e\u0008D\u000c\u0005i\u0008\u000bJ\nc\u0017\tY\u000b~Eu\u0004\u001ae\u0018\u0017\u0004\u0000~[S\u000c\u001a~\u000eG\u0011\u0000c\u0015\u0017\u0008\u0000\u007f\u0008^\t\u000c\u007f[C\r\u0008x[^\u000b\u000f`\u0012T\u0011Ii\u0003G\t\u0006\u007f\u0012A\u0000Ih\u001aZ\u0004\u000eiU"
		// @798: invokestatic game.C_100320_hh.func_102909_z(java.lang.String)char[]
		// @79B: invokestatic game.C_100320_hh.func_102908_z(char[])java.lang.String
		// @79E: aastore
		// @79F: aastore
		// @7A0: dup
		// @7A1: bipush 79 (0x4F)
		// @7A3: iconst_4
		// @7A4: anewarray java.lang.String
		// @7A7: dup
		// @7A8: iconst_0
		// @7A9: ldc "0\u000b^\u0006X=N\t"
		// @7AB: invokestatic game.C_100320_hh.func_102909_z(java.lang.String)char[]
		// @7AE: invokestatic game.C_100320_hh.func_102908_z(char[])java.lang.String
		// @7B1: aastore
		// @7B2: dup
		// @7B3: iconst_1
		// @7B4: ldc "0\u0018X\tT=\u001d\u0000S\u0008:Ev\u000c\u001b,\u001fR\u0004\u001dd[Z\u000c\u001a\u007f\u0012[\u0000\u001a0TT\n\u00052GU\u0017W\\\u0014@\u0000\u001bj\u000e[E\u0004e\u0008D\u000c\u0005i\u0008\u0017\u0011\u0001m\u000f\u0017\u0008\u0008g\u001e\u0017\u0004\u000c~\u0012V\tIo\u0014Z\u0007\u0008x[_\u0004\u001bh[C\nIa\u001a^\u000b\u001dm\u0012YK"
		// @7B6: invokestatic game.C_100320_hh.func_102909_z(java.lang.String)char[]
		// @7B9: invokestatic game.C_100320_hh.func_102908_z(char[])java.lang.String
		// @7BC: aastore
		// @7BD: dup
		// @7BE: iconst_2
		// @7BF: ldc "0\u000b^\u0006X=M\t"
		// @7C1: invokestatic game.C_100320_hh.func_102909_z(java.lang.String)char[]
		// @7C4: invokestatic game.C_100320_hh.func_102908_z(char[])java.lang.String
		// @7C7: aastore
		// @7C8: dup
		// @7C9: iconst_3
		// @7CA: ldc "0\u0018X\tT=\u001d\u0000S\u0008:Eg\u000c\u000c~\u0018R\u0017I~\u0014T\u000e\u000cx\u0008\u000bJ\nc\u0017\tY\u000b~Eu\u0004\u001ae\u0018\u001bE\u0005c\u0015PH\u001bm\u0015P\u0000I~\u0014T\u000e\u000cx\u0008\u0017\u0011\u0001m\u000f\u0017\u000c\u0007j\u0017^\u0006\u001d,\u001eO\u0015\u0005c\u0008^\u0013\u000c,\u001fV\u0008\u0008k\u001e\u0019"
		// @7CC: invokestatic game.C_100320_hh.func_102909_z(java.lang.String)char[]
		// @7CF: invokestatic game.C_100320_hh.func_102908_z(char[])java.lang.String
		// @7D2: aastore
		// @7D3: aastore
		// @7D4: dup
		// @7D5: bipush 80 (0x50)
		// @7D7: iconst_4
		// @7D8: anewarray java.lang.String
		// @7DB: dup
		// @7DC: iconst_0
		// @7DD: ldc "0\u000b^\u0006X=L\t"
		// @7DF: invokestatic game.C_100320_hh.func_102909_z(java.lang.String)char[]
		// @7E2: invokestatic game.C_100320_hh.func_102908_z(char[])java.lang.String
		// @7E5: aastore
		// @7E6: dup
		// @7E7: iconst_1
		// @7E8: ldc "0\u0018X\tT=\u001d\u0000S\u0008:Er(9,\tX\u0006\u0002i\u000fDYFo\u0014[[Un\t\t$\u0007,>z5Im\u000fC\u0004\ng[S\u0000\u0005e\rR\u0017\u000ch[U\u001cI~\u0014T\u000e\u000cxU"
		// @7EA: invokestatic game.C_100320_hh.func_102909_z(java.lang.String)char[]
		// @7ED: invokestatic game.C_100320_hh.func_102908_z(char[])java.lang.String
		// @7F0: aastore
		// @7F1: dup
		// @7F2: iconst_2
		// @7F3: ldc "0\u000b^\u0006X=C\t"
		// @7F5: invokestatic game.C_100320_hh.func_102909_z(java.lang.String)char[]
		// @7F8: invokestatic game.C_100320_hh.func_102908_z(char[])java.lang.String
		// @7FB: aastore
		// @7FC: dup
		// @7FD: iconst_3
		// @7FE: ldc "0\u0018X\tT=\u001d\u0000S\u0008:Ev\u000c\u001bn\u000eE\u0016\u001d,\tX\u0006\u0002i\u000fDYFo\u0014[[Un\t\t7\u0006o\u0010R\u0011\u001a,\u000f_\u0004\u001d,\u001eO\u0015\u0005c\u001fRE\u0000b[C\r\u000c,\u0008\\\u001cE,\u001d^\t\u0005e\u0015PE\u001dd\u001e\u0017\u0004\u0000~[@\u000c\u001dd[S\u000c\u001a~\u000eG\u0011\u0000z\u001e\u0017\u0016\u0001~\u001aG\u000b\u000c`U"
		// @800: invokestatic game.C_100320_hh.func_102909_z(java.lang.String)char[]
		// @803: invokestatic game.C_100320_hh.func_102908_z(char[])java.lang.String
		// @806: aastore
		// @807: aastore
		// @808: dup
		// @809: bipush 81 (0x51)
		// @80B: iconst_4
		// @80C: anewarray java.lang.String
		// @80F: dup
		// @810: iconst_0
		// @811: ldc "0\u000b^\u0006X=B\t"
		// @813: invokestatic game.C_100320_hh.func_102909_z(java.lang.String)char[]
		// @816: invokestatic game.C_100320_hh.func_102908_z(char[])java.lang.String
		// @819: aastore
		// @81A: dup
		// @81B: iconst_1
		// @81C: ldc "0\u0018X\tT=\u001d\u0000S\u0008:Ez\u0010\u0005x\u0012E\n\ng\u001eC\u0016U#\u0018X\tW0\u0019E[%c\u0015PH\u001bm\u0015P\u0000I~\u0014T\u000e\u000cx\u0008\u0017\u0011\u0001m\u000f\u0017\u0000\u0011|\u0017X\u0001\u000c,\u0012Y\u0011\u0006,\u0016B\t\u001de\u000b[\u0000I{\u001aE\r\u000cm\u001fDK"
		// @81E: invokestatic game.C_100320_hh.func_102909_z(java.lang.String)char[]
		// @821: invokestatic game.C_100320_hh.func_102908_z(char[])java.lang.String
		// @824: aastore
		// @825: dup
		// @826: iconst_2
		// @827: ldc "0\u000b^\u0006X>K\t"
		// @829: invokestatic game.C_100320_hh.func_102909_z(java.lang.String)char[]
		// @82C: invokestatic game.C_100320_hh.func_102908_z(char[])java.lang.String
		// @82F: aastore
		// @830: dup
		// @831: iconst_3
		// @832: ldc "0\u0018X\tT=\u001d\u0000S\u0008:E\u007f\u0000\u0008z\u0002\u0017\u0017\u0006o\u0010R\u0011\u001a0TT\n\u00052GU\u0017WD\u0012P\rD|\u0014@\u0000\u001bi\u001f\u0017\u0017\u0006o\u0010R\u0011\u001a,\u000f_\u0004\u001d,\u001d^\u0017\u000c,\u0014A\u0000\u001b,\u001a\u0017\t\u0006b\u001c\u0017\u0001\u0000\u007f\u000fV\u000b\ni[V\u000b\r,\u001fR\t\u0000z\u001eEE\u000ct\u000b[\n\u001ae\rRE\rm\u0016V\u0002\u000c,\u0014A\u0000\u001b,\u001a\u0017\u0012\u0000h\u001e\u0017\u0017\u0008h\u0012B\u0016G"
		// @834: invokestatic game.C_100320_hh.func_102909_z(java.lang.String)char[]
		// @837: invokestatic game.C_100320_hh.func_102908_z(char[])java.lang.String
		// @83A: aastore
		// @83B: aastore
		// @83C: dup
		// @83D: bipush 82 (0x52)
		// @83F: iconst_2
		// @840: anewarray java.lang.String
		// @843: dup
		// @844: iconst_0
		// @845: ldc "0\u000b^\u0006X>J\t"
		// @847: invokestatic game.C_100320_hh.func_102909_z(java.lang.String)char[]
		// @84A: invokestatic game.C_100320_hh.func_102908_z(char[])java.lang.String
		// @84D: aastore
		// @84E: dup
		// @84F: iconst_1
		// @850: ldc "0\u0018X\tT=\u001d\u0000S\u0008:Es\u0000\u001ax\tB\u0006\u001dc\t\u0017\u0017\u0006o\u0010R\u0011\u001a0TT\n\u00052GU\u0017WI\u0003C\u0017\u000ca\u001e[\u001cI|\u0014@\u0000\u001bj\u000e[E\u001bc\u0018\\\u0000\u001d\u007fW\u0017\u0006\u0008|\u001aU\t\u000c,\u0014QE\ri\u0008C\u0017\u0006u\u0012Y\u0002Im\u0015N\u0011\u0001e\u0015PE\u0000b[C\r\u000ce\t\u0017\u0015\u0008x\u0013\u0019"
		// @852: invokestatic game.C_100320_hh.func_102909_z(java.lang.String)char[]
		// @855: invokestatic game.C_100320_hh.func_102908_z(char[])java.lang.String
		// @858: aastore
		// @859: aastore
		// @85A: dup
		// @85B: bipush 83 (0x53)
		// @85D: iconst_1
		// @85E: anewarray java.lang.String
		// @861: dup
		// @862: iconst_0
		// @863: ldc "0\u0019E[+i[V\u0012\u0008~\u001e\u0017\u0011\u0001m\u000f\u0017\u0012\u000cm\u000bX\u000bIo\u0017V\u0016\u001ai\u0008\u0017\u0004\u001bi[S\u000c\u001ax\u0012Y\u0006\u001d,\u001dE\n\u0004,\u000cR\u0004\u0019c\u0015\u0017\u0016\u0000v\u001eDKUn\t\t$I{\u001eV\u0015\u0006b[D\u000c\u0013i[T\u0004\u0007,\u0019REUo\u0014[XXjL\u0001\u0004_2\u0017^\u0002\u0001xG\u0018\u0006\u0006`E\u001bEUo\u0014[XXjL\u0001\u0004_2\u0013R\u0004\u001fuG\u0018\u0006\u0006`E\u001bEUo\u0014[XXjL\u0001\u0004_2\u0014E\u0001\u0007m\u0015T\u0000U#\u0018X\tW [@\r\u0000`\u001e\u0017\u0017\u0006o\u0010R\u0011\u001a,\u001aY\u0001Ia\u0012D\u0016\u0000`\u001eDE\u0004m\u0002\u0017\u0007\u000c,\u0018V\u0011\u000ck\u0014E\u000c\u001ai\u001f\u0017\u0004\u001a,GT\n\u00051JQR_mM\t\u0017\u0006o\u0010R\u0011U#\u0018X\tW,\u0014EEUo\u0014[XXjL\u0001\u0004_2\u0017V\u0017\u000ei[E\n\ng\u001eCYFo\u0014[[I\u007f\u0012M\u0000G0\u0019E[(,\u000cR\u0004\u0019c\u0015\u0017\u0006\u0008b[X\u000b\u0005u[U\u0000Ii\nB\u000c\u0019|\u001eSE\u0000b[VE\u001a`\u0014CE\u0006j[C\r\u000c,\u001aG\u0015\u001bc\u000bE\u000c\u0008x\u001e\u0017\u0016\u0000v\u001e\u0019"
		// @865: invokestatic game.C_100320_hh.func_102909_z(java.lang.String)char[]
		// @868: invokestatic game.C_100320_hh.func_102908_z(char[])java.lang.String
		// @86B: aastore
		// @86C: aastore
		// @86D: dup
		// @86E: bipush 84 (0x54)
		// @870: iconst_1
		// @871: anewarray java.lang.String
		// @874: dup
		// @875: iconst_0
		// @876: ldc "J\u0014EE\u0000b\u0008C\u0004\u0007o\u001e\u001bE\u0000b[C\r\u000c,GT\n\u00051\u001dQ\u0003\u000f4K\t\u0015\u0005m\u0008Z\u0004U#\u0018X\tW,\u000cR\u0004\u0019c\u0015\u0017\u0006\u0005m\u0008D_Un\t\t1\u0001i[\u000b\u0006\u0006`F\u0006\u0003^:\u001a\u0001[\u0005e\u001c_\u0011U#\u0018X\tW,\u000b[\u0004\u001aa\u001a\u0017\u0012\u000cm\u000bX\u000bIe\u0008\u0017\u0011\u0001i[\u000b\u0006\u0006`FQ\u0003\u000fjC\u0007[\u0019`\u001aD\u0008\u0008,\u0008G\u0017\u0008uG\u0018\u0006\u0006`E\u001bY\u000b~EC\r\u000c,GT\n\u00051JQR_mM\t\r\u000cm\rNYFo\u0014[[I|\u0017V\u0016\u0004m[@\u0000\u0008|\u0014YE\u0000\u007f[C\r\u000c,GT\n\u00051\u001dQ\u0003\u000f4K\t\u0015\u0005m\u0008Z\u0004Io\u001aY\u000b\u0006bG\u0018\u0006\u0006`E\u001bY\u000b~EV\u000b\r,\u000f_\u0000I0\u0018X\tT=\u001d\u0000S\u0008:EX\u0017\rb\u001aY\u0006\u000c0TT\n\u00052[G\t\u0008\u007f\u0016VE\u001ei\u001aG\n\u0007,\u0012DE\u001dd\u001e\u0017Y\nc\u0017\n\u0003\u000fj\u001d\u000fUWj\u000eD\u000c\u0006b[T\u0004\u0007b\u0014YYFo\u0014[[G0\u0019E[=d\u001eD\u0000I{\u001eV\u0015\u0006b\u0008\u0017\u0004\u001bi[D\u000c\u0004e\u0017V\u0017Ie\u0015\u0017\u0000\u000fj\u001eT\u0011E,\u0019B\u0011Ix\u0013R\u001cIh\u0012Q\u0003\u000c~[^\u000bI|\u0014@\u0000\u001b [E\u0004\u0007k\u001e\u0017\u0004\u0007h[C\u0000\nd[A\u0004\u0005y\u001e\u0019"
		// @878: invokestatic game.C_100320_hh.func_102909_z(java.lang.String)char[]
		// @87B: invokestatic game.C_100320_hh.func_102908_z(char[])java.lang.String
		// @87E: aastore
		// @87F: aastore
		// @880: dup
		// @881: bipush 85 (0x55)
		// @883: iconst_1
		// @884: anewarray java.lang.String
		// @887: dup
		// @888: iconst_0
		// @889: ldc "0\u0013\t$\u0019|\u001eY\u0001\u0000t[t_I\\\u0014@\u0000\u001b0\u0008_\u001cWy\u000bD"
		// @88B: invokestatic game.C_100320_hh.func_102909_z(java.lang.String)char[]
		// @88E: invokestatic game.C_100320_hh.func_102908_z(char[])java.lang.String
		// @891: aastore
		// @892: aastore
		// @893: dup
		// @894: bipush 86 (0x56)
		// @896: iconst_1
		// @897: anewarray java.lang.String
		// @89A: dup
		// @89B: iconst_0
		// @89C: ldc "H\u000eE\u000c\u0007k[T\n\u0004n\u001aCE\u0010c\u000e\u0017\u0008\u0008u[R\u000b\nc\u000eY\u0011\u000c~[C\u0000\nd\u0015X\t\u0006k\u0002\u0017\u0011\u0001m\u000f\u0017\u001c\u0006y[T\u0004\u0007,\u0012Z\u0008\u000ch\u0012V\u0011\u000c`\u0002\u0017\u0016\nm\rR\u000b\u000ei[V\u000b\r,\u000bB\u0011Ix\u0014\u0017\u0012\u0006~\u0010\u0019E:y\u0018_E\u001di\u0018_\u000b\u0006`\u0014P\u001cIa\u001aNE\ri\u000fR\u0017\u0000c\tV\u0011\u000c,\u001aQ\u0011\u000c~[VE\u000b~\u0012R\u0003Ix\u0012Z\u0000E,\u0014EE\u0004m\u0002\u0017\n\u0007`\u0002\u0017\u0003\u001cb\u0018C\u000c\u0006b[X\u000b\niW\u0017\u0007\u001cx[^\u0011Io\u001aYE\u000ee\rRE\u0010c\u000eEE\u001ai\u0015C\u000c\u0007i\u0017\u0017\u0004I\u007f\u0013X\u0017\u001d!\u000fR\u0017\u0004,\u001aS\u0013\u0008b\u000fV\u0002\u000c,\u0012YE\u000bm\u000fC\t\u000c\""
		// @89E: invokestatic game.C_100320_hh.func_102909_z(java.lang.String)char[]
		// @8A1: invokestatic game.C_100320_hh.func_102908_z(char[])java.lang.String
		// @8A4: aastore
		// @8A5: aastore
		// @8A6: dup
		// @8A7: bipush 87 (0x57)
		// @8A9: iconst_1
		// @8AA: anewarray java.lang.String
		// @8AD: dup
		// @8AE: iconst_0
		// @8AF: ldc "X\u0013R\u0016\u000c,GT\n\u00051JQR_mM\t\u0015\u0006{\u001eEH\u001c|\u0008\u000bJ\nc\u0017\tE\u0008~\u001e\u0017\u0010\u001ay\u001a[\t\u0010,\u0016X\u0001\u001c`\u001eDE\u000f~\u0014ZE\u0006x\u0013R\u0017Ih\u001eD\u0011\u001bc\u0002R\u0001I\u007f\u001eY\u0011\u0000b\u001e[\u0016E,\u0019B\u0011I\u007f\u0014Z\u0000Im\tRE\u001bm\tRE\u0019e\u001eT\u0000\u001a,\u0014QE\u001di\u0018_\u000b\u0006`\u0014P\u001cIx\u0013V\u0011Iu\u0012R\t\r,\u000bX\u0012\u000c~\u0008\u0017\u000b\u0006x[V\u0013\u0008e\u0017V\u0007\u0005i[^\u000bIa\u0014S\u0010\u0005i\u0008\u0019E:c\u0016RE\u0008~\u001e\u0017\u0004\nx\u0012A\u0004\u001di\u001f\u0017\u000c\u0004a\u001eS\u000c\u0008x\u001e[\u001cIx\u0013R\u001cIm\tRE\u0019e\u0018\\\u0000\r,\u000eGIIm\u0015SE\u001ac\u0016RE\nm\u0015\u0017\u0007\u000c,\u0013R\t\r,\u001dX\u0017Im[Q\u000c\u0011i\u001f\u0017\u0001\u001c~\u001aC\u000c\u0006bU\u0017$I\u007f\u001eY\u0011\u0000b\u001e[E\nm\u0015\u0017\n\u0007`\u0002\u0017\r\u0006`\u001f\u0017\n\u0007i[G\n\u001ei\t\u001a\u0010\u0019,\u001aCE\u0008,\u000f^\u0008\u000c\""
		// @8B1: invokestatic game.C_100320_hh.func_102909_z(java.lang.String)char[]
		// @8B4: invokestatic game.C_100320_hh.func_102908_z(char[])java.lang.String
		// @8B7: aastore
		// @8B8: aastore
		// @8B9: dup
		// @8BA: bipush 88 (0x58)
		// @8BC: iconst_4
		// @8BD: anewarray java.lang.String
		// @8C0: dup
		// @8C1: iconst_0
		// @8C2: ldc "0\u000b^\u0006[?O\t"
		// @8C4: invokestatic game.C_100320_hh.func_102909_z(java.lang.String)char[]
		// @8C7: invokestatic game.C_100320_hh.func_102908_z(char[])java.lang.String
		// @8CA: aastore
		// @8CB: dup
		// @8CC: iconst_1
		// @8CD: ldc "0\u0018X\tT=\u001d\u0000S\u0008:E\u007f\u001c\u0019i\t\u0017\u0017\u000c`\u0014V\u0001\u000c~G\u0018\u0006\u0006`E\u000b\u0007\u001b2:[\t\u0006{\u0008\u0017\u001c\u0006y\t\u0017\u0016\u000cb\u000f^\u000b\u000c`[C\nI~\u001e[\n\u0008h[D\u0008\u0008`\u0017\u0017\u0017\u0006o\u0010R\u0011\u001a,\u001aY\u0001Ia\u0012D\u0016\u0000`\u001eDE\u001ee\u000f_E\u0001m\tS\t\u0010,\u001aY\u001cIh\u001e[\u0004\u0010\""
		// @8CF: invokestatic game.C_100320_hh.func_102909_z(java.lang.String)char[]
		// @8D2: invokestatic game.C_100320_hh.func_102908_z(char[])java.lang.String
		// @8D5: aastore
		// @8D6: dup
		// @8D7: iconst_2
		// @8D8: ldc_w "0\u000b^\u0006[?N\t"
		// @8DB: invokestatic game.C_100320_hh.func_102909_z(java.lang.String)char[]
		// @8DE: invokestatic game.C_100320_hh.func_102908_z(char[])java.lang.String
		// @8E1: aastore
		// @8E2: dup
		// @8E3: iconst_3
		// @8E4: ldc_w "0\u0018X\tT=\u001d\u0000S\u0008:E\u007f\u0000\u0008`\u000f_E\u0019`\u000eDYFo\u0014[[Un\t\t,\u0007o\tR\u0004\u001ai\u0008\u0017\u001c\u0006y\t\u0017\u0016\u000cb\u000f^\u000b\u000c`\\DE\u0004m\u0003^\u0008\u001ca[_\u0000\u0008`\u000f_E\u0008b\u001f\u0017\u000c\u0007\u007f\u000fV\u000b\u001d`\u0002\u0017\u0017\u000c|\u001a^\u0017\u001a,\u001aY\u001cIh\u001aZ\u0004\u000ei[N\n\u001c~[D\u0000\u0007x\u0012Y\u0000\u0005,\u0008B\u0016\u001dm\u0012Y\u0000\r,\u000bE\u000c\u0006~[C\nIk\u001eC\u0011\u0000b\u001c\u0017\u0011\u0001i[G\n\u001ei\t\u001a\u0010\u0019\""
		// @8E7: invokestatic game.C_100320_hh.func_102909_z(java.lang.String)char[]
		// @8EA: invokestatic game.C_100320_hh.func_102908_z(char[])java.lang.String
		// @8ED: aastore
		// @8EE: aastore
		// @8EF: dup
		// @8F0: bipush 89 (0x59)
		// @8F2: iconst_4
		// @8F3: anewarray java.lang.String
		// @8F6: dup
		// @8F7: iconst_0
		// @8F8: ldc_w "0\u000b^\u0006[?M\t"
		// @8FB: invokestatic game.C_100320_hh.func_102909_z(java.lang.String)char[]
		// @8FE: invokestatic game.C_100320_hh.func_102908_z(char[])java.lang.String
		// @901: aastore
		// @902: dup
		// @903: iconst_1
		// @904: ldc_w "0\u0018X\tT=\u001d\u0000S\u0008:E~\u000b\u000fe\u0015^\u0011\u000c,\u001eY\u0000\u001bk\u0002\u000bJ\nc\u0017\tY\u000b~Et\n\u0007x\u0012Y\u0010\u0006y\u0008[\u001cI~\u001eG\t\u000cb\u0012D\r\u000c\u007f[N\n\u001c~[D\u0000\u0007x\u0012Y\u0000\u0005+\u0008\u0017\u0000\u0007i\tP\u001cE,\u001c^\u0013\u0000b\u001c\u0017\u001c\u0006y[VE\u0005e\u0016^\u0011\u0005i\u0008DE\u001bi\u0008X\u0010\u001bo\u001e\u0017\u0010\u0007x\u0012[E\u001dd\u001e\u0017\u0015\u0006{\u001eEH\u001c|[R\u001d\u0019e\tR\u0016G"
		// @907: invokestatic game.C_100320_hh.func_102909_z(java.lang.String)char[]
		// @90A: invokestatic game.C_100320_hh.func_102908_z(char[])java.lang.String
		// @90D: aastore
		// @90E: dup
		// @90F: iconst_2
		// @910: ldc_w "0\u000b^\u0006[?L\t"
		// @913: invokestatic game.C_100320_hh.func_102909_z(java.lang.String)char[]
		// @916: invokestatic game.C_100320_hh.func_102908_z(char[])java.lang.String
		// @919: aastore
		// @91A: dup
		// @91B: iconst_3
		// @91C: ldc_w "0\u0018X\tT=\u001d\u0000S\u0008:E~\u0008\u0019i\tA\u000c\u0006y\u0008\u000bJ\nc\u0017\tY\u000b~Eg\u0017\u0006x\u001eT\u0011\u001a,\u0002X\u0010\u001b,\u0008R\u000b\u001de\u0015R\tIj\tX\u0008Id\u001aE\u0008Im\u0015SE\u0002i\u001eG\u0016Ie\u000f\u0017\u0004\u001d,\u0016V\u001d\u0000a\u000eZE\u0001i\u001a[\u0011\u0001,\u000eY\u0011\u0000`[C\r\u000c,\u000bX\u0012\u000c~VB\u0015Ii\u0003G\u000c\u001bi\u0008\u0019"
		// @91F: invokestatic game.C_100320_hh.func_102909_z(java.lang.String)char[]
		// @922: invokestatic game.C_100320_hh.func_102908_z(char[])java.lang.String
		// @925: aastore
		// @926: aastore
		// @927: dup
		// @928: bipush 90 (0x5A)
		// @92A: iconst_4
		// @92B: anewarray java.lang.String
		// @92E: dup
		// @92F: iconst_0
		// @930: ldc_w "0\u000b^\u0006[?C\t"
		// @933: invokestatic game.C_100320_hh.func_102909_z(java.lang.String)char[]
		// @936: invokestatic game.C_100320_hh.func_102908_z(char[])java.lang.String
		// @939: aastore
		// @93A: dup
		// @93B: iconst_1
		// @93C: ldc_w "0\u0018X\tT=\u001d\u0000S\u0008:Ed\u0015\u000ci\u001f\u000bJ\nc\u0017\tY\u000b~Er\u000b\u0008n\u0017R\u0016Iu\u0014B\u0017I\u007f\u001eY\u0011\u0000b\u001e[E\u001dc[Z\n\u001fi[A\u0000\u001bu[F\u0010\u0000o\u0010[\u001cIm\u0017X\u000b\u000e,\u000f_\u0000Ik\tX\u0010\u0007hU"
		// @93F: invokestatic game.C_100320_hh.func_102909_z(java.lang.String)char[]
		// @942: invokestatic game.C_100320_hh.func_102908_z(char[])java.lang.String
		// @945: aastore
		// @946: dup
		// @947: iconst_2
		// @948: ldc_w "0\u000b^\u0006[?B\t"
		// @94B: invokestatic game.C_100320_hh.func_102909_z(java.lang.String)char[]
		// @94E: invokestatic game.C_100320_hh.func_102908_z(char[])java.lang.String
		// @951: aastore
		// @952: dup
		// @953: iconst_3
		// @954: ldc_w "0\u0018X\tT=\u001d\u0000S\u0008:Ef\u0010\u0008h\tVE\u0019`\u001aC\u000c\u0007kG\u0018\u0006\u0006`E\u000b\u0007\u001b2<^\u0013\u000c\u007f[N\n\u001c~[D\u0000\u0007x\u0012Y\u0000\u0005,\u000f_\u0000In\u001eY\u0000\u000fe\u000f\u0017\n\u000f,\tR\u0004\nx\u0012A\u0000Im\tZ\n\u001c~W\u0017\u0017\u000ce\u0015Q\n\u001bo\u001eSE\u0008~\u0016X\u0010\u001b [r(9,\u0013V\u0017\ri\u0015^\u000b\u000e,\u001aY\u0001Ii\u0015R\u0017\u000ee\u0008R\u0001Im\tZ\n\u001c~U"
		// @957: invokestatic game.C_100320_hh.func_102909_z(java.lang.String)char[]
		// @95A: invokestatic game.C_100320_hh.func_102908_z(char[])java.lang.String
		// @95D: aastore
		// @95E: aastore
		// @95F: dup
		// @960: bipush 91 (0x5B)
		// @962: iconst_4
		// @963: anewarray java.lang.String
		// @966: dup
		// @967: iconst_0
		// @968: ldc_w "0\u000b^\u0006[8K\t"
		// @96B: invokestatic game.C_100320_hh.func_102909_z(java.lang.String)char[]
		// @96E: invokestatic game.C_100320_hh.func_102908_z(char[])java.lang.String
		// @971: aastore
		// @972: dup
		// @973: iconst_1
		// @974: ldc_w "0\u0018X\tT=\u001d\u0000S\u0008:Ef\u0010\u0008h\tVE\rm\u0016V\u0002\u000c0TT\n\u00052GU\u0017WA\u001a\\\u0000\u001a,\u001a[\tIc\u001d\u0017\u001c\u0006y\t\u0017\u0012\u000cm\u000bX\u000b\u001a,\u001dX\u0010\u001b,\u000f^\u0008\u000c\u007f[V\u0016I|\u0014@\u0000\u001bj\u000e[K"
		// @977: invokestatic game.C_100320_hh.func_102909_z(java.lang.String)char[]
		// @97A: invokestatic game.C_100320_hh.func_102908_z(char[])java.lang.String
		// @97D: aastore
		// @97E: dup
		// @97F: iconst_2
		// @980: ldc_w "0\u000b^\u0006[8J\t"
		// @983: invokestatic game.C_100320_hh.func_102909_z(java.lang.String)char[]
		// @986: invokestatic game.C_100320_hh.func_102908_z(char[])java.lang.String
		// @989: aastore
		// @98A: dup
		// @98B: iconst_3
		// @98C: ldc_w "0\u0018X\tT=\u001d\u0000S\u0008:Er(9,\u000cR\u0004\u0019c\u0015DYFo\u0014[[Un\t\t$\rh\u0008\u0017\u0004\u0007,>z5Ii\u001dQ\u0000\nx[C\nIm\u0017[E\u0010c\u000eEE\u001ei\u001aG\n\u0007\u007fU"
		// @98F: invokestatic game.C_100320_hh.func_102909_z(java.lang.String)char[]
		// @992: invokestatic game.C_100320_hh.func_102908_z(char[])java.lang.String
		// @995: aastore
		// @996: aastore
		// @997: dup
		// @998: bipush 92 (0x5C)
		// @99A: iconst_4
		// @99B: anewarray java.lang.String
		// @99E: dup
		// @99F: iconst_0
		// @9A0: ldc_w "0\u000b^\u0006[8H\t"
		// @9A3: invokestatic game.C_100320_hh.func_102909_z(java.lang.String)char[]
		// @9A6: invokestatic game.C_100320_hh.func_102908_z(char[])java.lang.String
		// @9A9: aastore
		// @9AA: dup
		// @9AB: iconst_1
		// @9AC: ldc_w "0\u0018X\tT=\u001d\u0000S\u0008:Ee\n\ng\u001eCE\u001ax\t^\u000e\u000c0TT\n\u00052GU\u0017W_\u001eY\u0001\u001a,\u0014B\u0011Im\u0015\u0017\u000c\u0004a\u001eS\u000c\u0008x\u001e\u0017\u0016\u0000k\u0015V\tIx\u0014\u0017\u0004I\u007f\u0013^\u0015Ie\u0015\u0017\n\u001bn\u0012CII{\u0013^\u0006\u0001,\u0019X\u0008\u000bm\tS\u0016Ix\u0013RE\u000bm\u000fC\t\u000cj\u0012R\t\r,\u000c^\u0011\u0001,\u0013R\u0004\u001fu[E\n\ng\u001eC\u0016G"
		// @9AF: invokestatic game.C_100320_hh.func_102909_z(java.lang.String)char[]
		// @9B2: invokestatic game.C_100320_hh.func_102908_z(char[])java.lang.String
		// @9B5: aastore
		// @9B6: dup
		// @9B7: iconst_2
		// @9B8: ldc_w "0\u000b^\u0006[8I\t"
		// @9BB: invokestatic game.C_100320_hh.func_102909_z(java.lang.String)char[]
		// @9BE: invokestatic game.C_100320_hh.func_102908_z(char[])java.lang.String
		// @9C1: aastore
		// @9C2: dup
		// @9C3: iconst_3
		// @9C4: ldc_w "0\u0018X\tT=\u001d\u0000S\u0008:Ez\"/BG\u0018\u0006\u0006`E\u000b\u0007\u001b2\"X\u0010Ii\u001aE\u000bI|\u0014^\u000b\u001d\u007f[V\t\u0005,\u000f_\u0000Ix\u0012Z\u0000Iu\u0014BE\u0008~\u001e\u0017\r\u0006`\u001f^\u000b\u000e,\u000f_\u000c\u001a,\rV\t\u001cm\u0019[\u0000Ix\u001eT\r\u0007c\u0017X\u0002\u0010 [U\u0010\u001d,\u0017X\u0016\u000c,\u000f_\u0000Ix\u001eT\r\u0007c\u0017X\u0002\u0010,\u000c_\u0000\u0007,\u0002X\u0010\u001b,\u0008R\u000b\u001de\u0015R\tIe\u0008\u0017\u0001\u000c\u007f\u000fE\n\u0010i\u001f\u0019"
		// @9C7: invokestatic game.C_100320_hh.func_102909_z(java.lang.String)char[]
		// @9CA: invokestatic game.C_100320_hh.func_102908_z(char[])java.lang.String
		// @9CD: aastore
		// @9CE: aastore
		// @9CF: dup
		// @9D0: bipush 93 (0x5D)
		// @9D2: iconst_2
		// @9D3: anewarray java.lang.String
		// @9D6: dup
		// @9D7: iconst_0
		// @9D8: ldc_w "0\u000b^\u0006[8O\t"
		// @9DB: invokestatic game.C_100320_hh.func_102909_z(java.lang.String)char[]
		// @9DE: invokestatic game.C_100320_hh.func_102908_z(char[])java.lang.String
		// @9E1: aastore
		// @9E2: dup
		// @9E3: iconst_1
		// @9E4: ldc_w "0\u0018X\tT=\u001d\u0000S\u0008:E\u0006H<|G\u0018\u0006\u0006`E\u000b\u0007\u001b2<^\u0013\u000c\u007f[N\n\u001c~[D\u0000\u0007x\u0012Y\u0000\u0005,\u001aYE\u000ct\u000fE\u0004Io\u0013V\u000b\ni[C\nI~\u001eD\u0015\u0008{\u0015\u0019"
		// @9E7: invokestatic game.C_100320_hh.func_102909_z(java.lang.String)char[]
		// @9EA: invokestatic game.C_100320_hh.func_102908_z(char[])java.lang.String
		// @9ED: aastore
		// @9EE: aastore
		// @9EF: putstatic java.lang.String[][] game.C_100320_hh.field_102914_Q
		// @9F2: ldc_w "K\u001aZ\u0000Ij\u000e[\t"
		// @9F5: invokestatic game.C_100320_hh.func_102909_z(java.lang.String)char[]
		// @9F8: invokestatic game.C_100320_hh.func_102908_z(char[])java.lang.String
		// @9FB: putstatic java.lang.String game.C_100320_hh.field_102911_U
		// @9FE: ldc_w "X\u0012Z\u0000S,GT\n\u00051\u001dQ\u0003\u000fj\u001d\tYL<E\u000bJ\nc\u0017\t"
		// @A01: invokestatic game.C_100320_hh.func_102909_z(java.lang.String)char[]
		// @A04: invokestatic game.C_100320_hh.func_102908_z(char[])java.lang.String
		// @A07: putstatic java.lang.String game.C_100320_hh.field_102919_N
		// @A0A: ldc_w "N:\u0010$%,7x7-,4qE @4{,("
		// @A0D: invokestatic game.C_100320_hh.func_102909_z(java.lang.String)char[]
		// @A10: invokestatic game.C_100320_hh.func_102908_z(char[])java.lang.String
		// @A13: putstatic java.lang.String game.C_100320_hh.field_102918_M
		// @A16: sipush 8192 (0x2000)
		// @A19: newarray int[]
		// @A1B: putstatic int[] game.C_100320_hh.field_102920_O
		// @A1E: ldc_w "J\u0012E\u000c\u0007k[V\u0017\n"
		// @A21: invokestatic game.C_100320_hh.func_102909_z(java.lang.String)char[]
		// @A24: invokestatic game.C_100320_hh.func_102908_z(char[])java.lang.String
		// @A27: putstatic java.lang.String game.C_100320_hh.field_102916_S
		// @A2A: ldc_w "^\u001eD\u0015\u000co\u000f"
		// @A2D: invokestatic game.C_100320_hh.func_102909_z(java.lang.String)char[]
		// @A30: invokestatic game.C_100320_hh.func_102908_z(char[])java.lang.String
		// @A33: putstatic java.lang.String game.C_100320_hh.field_102917_R
		// @A36: return
	}
	
	private static char[] func_102909_z(String arg0)
	{
		// @00: aload_0
		// @01: invokevirtual java.lang.String.toCharArray()char[]
		// @04: dup
		// @05: arraylength
		// @06: iconst_2
		// @07: if_icmpge @13
		// @0A: dup
		// @0B: iconst_0
		// @0C: dup2
		// @0D: caload
		// @0E: bipush 105 (0x69)
		// @10: ixor
		// @11: i2c
		// @12: castore
		// @13: areturn
	}
	
	private static String func_102908_z(char[] arg0)
	{
		// @00: aload_0
		// @01: dup
		// @02: arraylength
		// @03: swap
		// @04: iconst_0
		// @05: istore_1
		// @06: goto @4C
		// @09: dup
		// @0A: iload_1
		// @0B: dup2
		// @0C: caload
		// @0D: iload_1
		// @0E: iconst_5
		// @0F: irem
		// @10: tableswitch def: @44, for 0: @30, for 1: @35, for 2: @3A, for 3: @3F
		// @30: bipush 12 (0x0C)
		// @32: goto @46
		// @35: bipush 123 (0x7B)
		// @37: goto @46
		// @3A: bipush 55 (0x37)
		// @3C: goto @46
		// @3F: bipush 101 (0x65)
		// @41: goto @46
		// @44: bipush 105 (0x69)
		// @46: ixor
		// @47: i2c
		// @48: castore
		// @49: iinc #1 +1
		// @4C: swap
		// @4D: dup_x1
		// @4E: iload_1
		// @4F: if_icmpgt @09
		// @52: new java.lang.String
		// @55: dup_x1
		// @56: swap
		// @57: invokespecial java.lang.String.<init>(char[])void
		// @5A: invokevirtual java.lang.String.intern()java.lang.String
		// @5D: areturn
	}
}
