package game;

final class C_100100_i extends C_100302_ka
{
	static int field_102014_hc;
	C_100302_ka field_102021_Vb;
	C_100302_ka field_102013_Xb;
	static String field_102010_dc;
	C_100302_ka field_102015_Yb;
	C_100115_ej field_102016_ec;
	static float field_102011_gc;
	static C_100037_wb[] field_102017_fc;
	static int[] field_102020_Ub;
	static int field_102012_Zb;
	static String field_102023_bc;
	static int[] field_102018_Wb;
	static String field_102022_ac;
	static C_100003_ga field_102024_cc;
	private static final String[] field_102019_ic;
	
	final void func_102008_a(int arg0, int arg1, int arg2, int arg3, int arg4, int arg5, int arg6, int arg7)
	{
		// @00: iload #7
		// @02: sipush -30196 (0x8A0C)
		// @05: if_icmpeq @09
		// @08: return
		// @09: aload_0
		// @0A: iload #4
		// @0C: putfield int game.C_100100_i.field_101880_Gb
		// @0F: aload_0
		// @10: iload_3
		// @11: putfield int game.C_100100_i.field_101841_Pb
		// @14: aload_0
		// @15: iload #8
		// @17: putfield int game.C_100100_i.field_101886_Kb
		// @1A: aload_0
		// @1B: iload_1
		// @1C: putfield int game.C_100100_i.field_101848_lb
		// @1F: aload_0
		// @20: iload #5
		// @22: iload #6
		// @24: iload_2
		// @25: bipush -72 (0xB8)
		// @27: invokevirtual game.C_100100_i.func_102002_a(int, int, int, byte)void
		// @2A: goto @94
		// @2D: astore #9
		// @2F: aload #9
		// @31: new java.lang.StringBuilder
		// @34: dup
		// @35: invokespecial java.lang.StringBuilder.<init>()void
		// @38: getstatic java.lang.String[] game.C_100100_i.field_102019_ic
		// @3B: iconst_0
		// @3C: aaload
		// @3D: invokevirtual java.lang.StringBuilder.append(java.lang.String)java.lang.StringBuilder
		// @40: iload_1
		// @41: invokevirtual java.lang.StringBuilder.append(int)java.lang.StringBuilder
		// @44: bipush 44 (0x2C)
		// @46: invokevirtual java.lang.StringBuilder.append(char)java.lang.StringBuilder
		// @49: iload_2
		// @4A: invokevirtual java.lang.StringBuilder.append(int)java.lang.StringBuilder
		// @4D: bipush 44 (0x2C)
		// @4F: invokevirtual java.lang.StringBuilder.append(char)java.lang.StringBuilder
		// @52: iload_3
		// @53: invokevirtual java.lang.StringBuilder.append(int)java.lang.StringBuilder
		// @56: bipush 44 (0x2C)
		// @58: invokevirtual java.lang.StringBuilder.append(char)java.lang.StringBuilder
		// @5B: iload #4
		// @5D: invokevirtual java.lang.StringBuilder.append(int)java.lang.StringBuilder
		// @60: bipush 44 (0x2C)
		// @62: invokevirtual java.lang.StringBuilder.append(char)java.lang.StringBuilder
		// @65: iload #5
		// @67: invokevirtual java.lang.StringBuilder.append(int)java.lang.StringBuilder
		// @6A: bipush 44 (0x2C)
		// @6C: invokevirtual java.lang.StringBuilder.append(char)java.lang.StringBuilder
		// @6F: iload #6
		// @71: invokevirtual java.lang.StringBuilder.append(int)java.lang.StringBuilder
		// @74: bipush 44 (0x2C)
		// @76: invokevirtual java.lang.StringBuilder.append(char)java.lang.StringBuilder
		// @79: iload #7
		// @7B: invokevirtual java.lang.StringBuilder.append(int)java.lang.StringBuilder
		// @7E: bipush 44 (0x2C)
		// @80: invokevirtual java.lang.StringBuilder.append(char)java.lang.StringBuilder
		// @83: iload #8
		// @85: invokevirtual java.lang.StringBuilder.append(int)java.lang.StringBuilder
		// @88: bipush 41 (0x29)
		// @8A: invokevirtual java.lang.StringBuilder.append(char)java.lang.StringBuilder
		// @8D: invokevirtual java.lang.StringBuilder.toString()java.lang.String
		// @90: invokestatic game.C_100181_cf.func_105695_a(java.lang.Throwable, java.lang.String)game.C_100170_cm
		// @93: athrow
		// @94: return
	}
	
	final void func_102002_a(int arg0, int arg1, int arg2, byte arg3)
	{
		// @00: aload_0
		// @01: getfield int game.C_100100_i.field_101886_Kb
		// @04: iload_3
		// @05: iadd
		// @06: iconst_2
		// @07: idiv
		// @08: istore #5
		// @0A: iload_1
		// @0B: ineg
		// @0C: aload_0
		// @0D: getfield int game.C_100100_i.field_101848_lb
		// @10: iadd
		// @11: istore #6
		// @13: aload_0
		// @14: getfield game.C_100115_ej game.C_100100_i.field_102016_ec
		// @17: iload_3
		// @18: iload #6
		// @1A: iload_3
		// @1B: ineg
		// @1C: iadd
		// @1D: iconst_0
		// @1E: iconst_0
		// @1F: aload_0
		// @20: getfield int game.C_100100_i.field_101886_Kb
		// @23: iconst_0
		// @24: iload_2
		// @25: invokevirtual game.C_100115_ej.func_102030_a(int, int, int, int, int, int, int)void
		// @28: aload_0
		// @29: getfield game.C_100302_ka game.C_100100_i.field_102021_Vb
		// @2C: iload_1
		// @2D: putfield int game.C_100302_ka.field_101848_lb
		// @30: aload_0
		// @31: getfield game.C_100302_ka game.C_100100_i.field_102021_Vb
		// @34: iload #6
		// @36: putfield int game.C_100302_ka.field_101880_Gb
		// @39: iload #4
		// @3B: bipush -46 (0xD2)
		// @3D: if_icmple @50
		// @40: aload_0
		// @41: bipush -94 (0xA2)
		// @43: bipush -46 (0xD2)
		// @45: bipush -104 (0x98)
		// @47: bipush 115 (0x73)
		// @49: invokevirtual game.C_100100_i.func_102002_a(int, int, int, byte)void
		// @4C: goto @50
		// @4F: athrow
		// @50: aload_0
		// @51: getfield game.C_100302_ka game.C_100100_i.field_102021_Vb
		// @54: iload #5
		// @56: iload_3
		// @57: isub
		// @58: putfield int game.C_100302_ka.field_101886_Kb
		// @5B: aload_0
		// @5C: getfield game.C_100302_ka game.C_100100_i.field_102021_Vb
		// @5F: iconst_0
		// @60: putfield int game.C_100302_ka.field_101841_Pb
		// @63: aload_0
		// @64: getfield game.C_100302_ka game.C_100100_i.field_102013_Xb
		// @67: iload #5
		// @69: putfield int game.C_100302_ka.field_101841_Pb
		// @6C: aload_0
		// @6D: getfield game.C_100302_ka game.C_100100_i.field_102013_Xb
		// @70: iload #6
		// @72: putfield int game.C_100302_ka.field_101880_Gb
		// @75: aload_0
		// @76: getfield game.C_100302_ka game.C_100100_i.field_102013_Xb
		// @79: iload_1
		// @7A: putfield int game.C_100302_ka.field_101848_lb
		// @7D: aload_0
		// @7E: getfield game.C_100302_ka game.C_100100_i.field_102013_Xb
		// @81: iload #5
		// @83: ineg
		// @84: aload_0
		// @85: getfield int game.C_100100_i.field_101886_Kb
		// @88: iadd
		// @89: putfield int game.C_100302_ka.field_101886_Kb
		// @8C: goto @CF
		// @8F: astore #5
		// @91: aload #5
		// @93: new java.lang.StringBuilder
		// @96: dup
		// @97: invokespecial java.lang.StringBuilder.<init>()void
		// @9A: getstatic java.lang.String[] game.C_100100_i.field_102019_ic
		// @9D: bipush 9 (0x09)
		// @9F: aaload
		// @A0: invokevirtual java.lang.StringBuilder.append(java.lang.String)java.lang.StringBuilder
		// @A3: iload_1
		// @A4: invokevirtual java.lang.StringBuilder.append(int)java.lang.StringBuilder
		// @A7: bipush 44 (0x2C)
		// @A9: invokevirtual java.lang.StringBuilder.append(char)java.lang.StringBuilder
		// @AC: iload_2
		// @AD: invokevirtual java.lang.StringBuilder.append(int)java.lang.StringBuilder
		// @B0: bipush 44 (0x2C)
		// @B2: invokevirtual java.lang.StringBuilder.append(char)java.lang.StringBuilder
		// @B5: iload_3
		// @B6: invokevirtual java.lang.StringBuilder.append(int)java.lang.StringBuilder
		// @B9: bipush 44 (0x2C)
		// @BB: invokevirtual java.lang.StringBuilder.append(char)java.lang.StringBuilder
		// @BE: iload #4
		// @C0: invokevirtual java.lang.StringBuilder.append(int)java.lang.StringBuilder
		// @C3: bipush 41 (0x29)
		// @C5: invokevirtual java.lang.StringBuilder.append(char)java.lang.StringBuilder
		// @C8: invokevirtual java.lang.StringBuilder.toString()java.lang.String
		// @CB: invokestatic game.C_100181_cf.func_105695_a(java.lang.Throwable, java.lang.String)game.C_100170_cm
		// @CE: athrow
		// @CF: return
	}
	
	static final int func_102001_a(byte arg0, int arg1, int arg2)
	{
		// @00: getstatic int game.SteelSentinels.field_105275_O
		// @03: istore #5
		// @05: iconst_1
		// @06: istore_3
		// @07: bipush 53 (0x35)
		// @09: iload_0
		// @0A: bipush -13 (0xF3)
		// @0C: isub
		// @0D: bipush 61 (0x3D)
		// @0F: idiv
		// @10: idiv
		// @11: istore #4
		// @13: iload_1
		// @14: iconst_1
		// @15: if_icmple @3E
		// @18: iconst_1
		// @19: iload_1
		// @1A: iand
		// @1B: iconst_m1
		// @1C: ixor
		// @1D: iconst_m1
		// @1E: iload #5
		// @20: ifne @40
		// @23: if_icmpne @2D
		// @26: goto @2A
		// @29: athrow
		// @2A: goto @31
		// @2D: iload_3
		// @2E: iload_2
		// @2F: imul
		// @30: istore_3
		// @31: iload_1
		// @32: iconst_1
		// @33: ishr
		// @34: istore_1
		// @35: iload_2
		// @36: iload_2
		// @37: imul
		// @38: istore_2
		// @39: iload #5
		// @3B: ifeq @13
		// @3E: iload_1
		// @3F: iconst_1
		// @40: if_icmpne @47
		// @43: iload_3
		// @44: iload_2
		// @45: imul
		// @46: ireturn
		// @47: iload_3
		// @48: ireturn
		// @49: astore_3
		// @4A: aload_3
		// @4B: new java.lang.StringBuilder
		// @4E: dup
		// @4F: invokespecial java.lang.StringBuilder.<init>()void
		// @52: getstatic java.lang.String[] game.C_100100_i.field_102019_ic
		// @55: bipush 6 (0x06)
		// @57: aaload
		// @58: invokevirtual java.lang.StringBuilder.append(java.lang.String)java.lang.StringBuilder
		// @5B: iload_0
		// @5C: invokevirtual java.lang.StringBuilder.append(int)java.lang.StringBuilder
		// @5F: bipush 44 (0x2C)
		// @61: invokevirtual java.lang.StringBuilder.append(char)java.lang.StringBuilder
		// @64: iload_1
		// @65: invokevirtual java.lang.StringBuilder.append(int)java.lang.StringBuilder
		// @68: bipush 44 (0x2C)
		// @6A: invokevirtual java.lang.StringBuilder.append(char)java.lang.StringBuilder
		// @6D: iload_2
		// @6E: invokevirtual java.lang.StringBuilder.append(int)java.lang.StringBuilder
		// @71: bipush 41 (0x29)
		// @73: invokevirtual java.lang.StringBuilder.append(char)java.lang.StringBuilder
		// @76: invokevirtual java.lang.StringBuilder.toString()java.lang.String
		// @79: invokestatic game.C_100181_cf.func_105695_a(java.lang.Throwable, java.lang.String)game.C_100170_cm
		// @7C: athrow
	}
	
	static final C_100037_wb[] func_102007_a(int arg0, boolean arg1, int arg2, C_100098_h arg3)
	{
		// @00: iload_2
		// @01: iconst_1
		// @02: aload_3
		// @03: iload_0
		// @04: invokestatic game.C_100333_ij.func_107341_a(int, boolean, game.C_100098_h, int)boolean
		// @07: ifeq @0E
		// @0A: goto @10
		// @0D: athrow
		// @0E: aconst_null
		// @0F: areturn
		// @10: iload_1
		// @11: ifeq @19
		// @14: aconst_null
		// @15: checkcast game.C_100037_wb[]
		// @18: areturn
		// @19: sipush -22437 (0xA85B)
		// @1C: invokestatic game.C_100257_ln.func_106475_a(int)game.C_100037_wb[]
		// @1F: areturn
		// @20: astore #4
		// @22: aload #4
		// @24: new java.lang.StringBuilder
		// @27: dup
		// @28: invokespecial java.lang.StringBuilder.<init>()void
		// @2B: getstatic java.lang.String[] game.C_100100_i.field_102019_ic
		// @2E: iconst_4
		// @2F: aaload
		// @30: invokevirtual java.lang.StringBuilder.append(java.lang.String)java.lang.StringBuilder
		// @33: iload_0
		// @34: invokevirtual java.lang.StringBuilder.append(int)java.lang.StringBuilder
		// @37: bipush 44 (0x2C)
		// @39: invokevirtual java.lang.StringBuilder.append(char)java.lang.StringBuilder
		// @3C: iload_1
		// @3D: invokevirtual java.lang.StringBuilder.append(boolean)java.lang.StringBuilder
		// @40: bipush 44 (0x2C)
		// @42: invokevirtual java.lang.StringBuilder.append(char)java.lang.StringBuilder
		// @45: iload_2
		// @46: invokevirtual java.lang.StringBuilder.append(int)java.lang.StringBuilder
		// @49: bipush 44 (0x2C)
		// @4B: invokevirtual java.lang.StringBuilder.append(char)java.lang.StringBuilder
		// @4E: aload_3
		// @4F: ifnull @5B
		// @52: getstatic java.lang.String[] game.C_100100_i.field_102019_ic
		// @55: iconst_5
		// @56: aaload
		// @57: goto @60
		// @5A: athrow
		// @5B: getstatic java.lang.String[] game.C_100100_i.field_102019_ic
		// @5E: iconst_3
		// @5F: aaload
		// @60: invokevirtual java.lang.StringBuilder.append(java.lang.String)java.lang.StringBuilder
		// @63: bipush 41 (0x29)
		// @65: invokevirtual java.lang.StringBuilder.append(char)java.lang.StringBuilder
		// @68: invokevirtual java.lang.StringBuilder.toString()java.lang.String
		// @6B: invokestatic game.C_100181_cf.func_105695_a(java.lang.Throwable, java.lang.String)game.C_100170_cm
		// @6E: athrow
	}
	
	static final boolean func_102004_l(int arg0)
	{
		// @00: iload_0
		// @01: bipush -33 (0xDF)
		// @03: if_icmple @10
		// @06: bipush 122 (0x7A)
		// @08: invokestatic game.C_100100_i.func_102004_l(int)boolean
		// @0B: pop
		// @0C: goto @10
		// @0F: athrow
		// @10: bipush -25 (0xE7)
		// @12: invokestatic game.C_100234_ob.func_106268_c(byte)boolean
		// @15: ifne @2A
		// @18: getstatic int game.C_100212_qc.field_105976_b
		// @1B: iconst_m1
		// @1C: ixor
		// @1D: iconst_m1
		// @1E: if_icmpge @2A
		// @21: goto @25
		// @24: athrow
		// @25: iconst_1
		// @26: goto @2B
		// @29: athrow
		// @2A: iconst_0
		// @2B: ireturn
		// @2C: astore_1
		// @2D: aload_1
		// @2E: new java.lang.StringBuilder
		// @31: dup
		// @32: invokespecial java.lang.StringBuilder.<init>()void
		// @35: getstatic java.lang.String[] game.C_100100_i.field_102019_ic
		// @38: iconst_1
		// @39: aaload
		// @3A: invokevirtual java.lang.StringBuilder.append(java.lang.String)java.lang.StringBuilder
		// @3D: iload_0
		// @3E: invokevirtual java.lang.StringBuilder.append(int)java.lang.StringBuilder
		// @41: bipush 41 (0x29)
		// @43: invokevirtual java.lang.StringBuilder.append(char)java.lang.StringBuilder
		// @46: invokevirtual java.lang.StringBuilder.toString()java.lang.String
		// @49: invokestatic game.C_100181_cf.func_105695_a(java.lang.Throwable, java.lang.String)game.C_100170_cm
		// @4C: athrow
	}
	
	static final void func_102009_a(int arg0, int arg1, C_100037_wb[] arg2, int arg3, int arg4, int arg5)
	{
		// @000: getstatic int game.SteelSentinels.field_105275_O
		// @003: istore #22
		// @005: aconst_null
		// @006: aload_2
		// @007: if_acmpne @00B
		// @00A: return
		// @00B: iconst_0
		// @00C: iload_1
		// @00D: if_icmpge @016
		// @010: iconst_0
		// @011: iload #4
		// @013: if_icmplt @017
		// @016: return
		// @017: aconst_null
		// @018: aload_2
		// @019: iconst_3
		// @01A: aaload
		// @01B: if_acmpeq @028
		// @01E: aload_2
		// @01F: iconst_3
		// @020: aaload
		// @021: getfield int game.C_100037_wb.field_102341_y
		// @024: goto @029
		// @027: athrow
		// @028: iconst_0
		// @029: istore #6
		// @02B: aload_2
		// @02C: iconst_5
		// @02D: aaload
		// @02E: ifnonnull @036
		// @031: iconst_0
		// @032: goto @03C
		// @035: athrow
		// @036: aload_2
		// @037: iconst_5
		// @038: aaload
		// @039: getfield int game.C_100037_wb.field_102341_y
		// @03C: istore #7
		// @03E: aconst_null
		// @03F: aload_2
		// @040: iconst_1
		// @041: aaload
		// @042: if_acmpeq @04F
		// @045: aload_2
		// @046: iconst_1
		// @047: aaload
		// @048: getfield int game.C_100037_wb.field_102340_z
		// @04B: goto @050
		// @04E: athrow
		// @04F: iconst_0
		// @050: istore #8
		// @052: aload_2
		// @053: bipush 7 (0x07)
		// @055: aaload
		// @056: ifnull @064
		// @059: aload_2
		// @05A: bipush 7 (0x07)
		// @05C: aaload
		// @05D: getfield int game.C_100037_wb.field_102340_z
		// @060: goto @065
		// @063: athrow
		// @064: iconst_0
		// @065: istore #9
		// @067: iload_3
		// @068: iload_1
		// @069: iadd
		// @06A: istore #10
		// @06C: iload #4
		// @06E: iload #5
		// @070: iadd
		// @071: istore #11
		// @073: iload #6
		// @075: iload_3
		// @076: iadd
		// @077: istore #12
		// @079: iload #10
		// @07B: iload #7
		// @07D: ineg
		// @07E: iadd
		// @07F: istore #13
		// @081: iload #5
		// @083: iload #8
		// @085: iadd
		// @086: istore #14
		// @088: iload #11
		// @08A: iload #9
		// @08C: isub
		// @08D: istore #15
		// @08F: iload #12
		// @091: istore #16
		// @093: iload #13
		// @095: istore #17
		// @097: iload #17
		// @099: iconst_m1
		// @09A: ixor
		// @09B: iload #16
		// @09D: iconst_m1
		// @09E: ixor
		// @09F: if_icmple @0B4
		// @0A2: iload_3
		// @0A3: iload_1
		// @0A4: iload #6
		// @0A6: imul
		// @0A7: iload #6
		// @0A9: iload #7
		// @0AB: ineg
		// @0AC: isub
		// @0AD: idiv
		// @0AE: iadd
		// @0AF: dup
		// @0B0: istore #17
		// @0B2: istore #16
		// @0B4: iload #14
		// @0B6: istore #18
		// @0B8: iload #15
		// @0BA: istore #19
		// @0BC: getstatic int[] game.C_100145_ta.field_100432_i
		// @0BF: invokestatic game.C_100196_rb.func_105801_a(int[])void
		// @0C2: iload #19
		// @0C4: iconst_m1
		// @0C5: ixor
		// @0C6: iload #18
		// @0C8: iconst_m1
		// @0C9: ixor
		// @0CA: if_icmpgt @0D1
		// @0CD: goto @0E5
		// @0D0: athrow
		// @0D1: iload #5
		// @0D3: iload #8
		// @0D5: iload #4
		// @0D7: imul
		// @0D8: iload #8
		// @0DA: iload #9
		// @0DC: ineg
		// @0DD: isub
		// @0DE: idiv
		// @0DF: iadd
		// @0E0: dup
		// @0E1: istore #19
		// @0E3: istore #18
		// @0E5: aload_2
		// @0E6: iconst_0
		// @0E7: aaload
		// @0E8: ifnonnull @0EF
		// @0EB: goto @108
		// @0EE: athrow
		// @0EF: iload_3
		// @0F0: iload #5
		// @0F2: iload #16
		// @0F4: iload #18
		// @0F6: invokestatic game.C_100196_rb.func_105779_e(int, int, int, int)void
		// @0F9: aload_2
		// @0FA: iconst_0
		// @0FB: aaload
		// @0FC: iload_3
		// @0FD: iload #5
		// @0FF: invokevirtual game.C_100037_wb.func_102353_h(int, int)void
		// @102: getstatic int[] game.C_100145_ta.field_100432_i
		// @105: invokestatic game.C_100196_rb.func_105777_b(int[])void
		// @108: aload_2
		// @109: iconst_2
		// @10A: aaload
		// @10B: ifnull @12D
		// @10E: iload #17
		// @110: iload #5
		// @112: iload #10
		// @114: iload #18
		// @116: invokestatic game.C_100196_rb.func_105779_e(int, int, int, int)void
		// @119: aload_2
		// @11A: iconst_2
		// @11B: aaload
		// @11C: iload #13
		// @11E: iload #5
		// @120: invokevirtual game.C_100037_wb.func_102353_h(int, int)void
		// @123: getstatic int[] game.C_100145_ta.field_100432_i
		// @126: invokestatic game.C_100196_rb.func_105777_b(int[])void
		// @129: goto @12D
		// @12C: athrow
		// @12D: aload_2
		// @12E: bipush 6 (0x06)
		// @130: aaload
		// @131: ifnull @152
		// @134: iload_3
		// @135: iload #19
		// @137: iload #16
		// @139: iload #11
		// @13B: invokestatic game.C_100196_rb.func_105779_e(int, int, int, int)void
		// @13E: aload_2
		// @13F: bipush 6 (0x06)
		// @141: aaload
		// @142: iload_3
		// @143: iload #15
		// @145: invokevirtual game.C_100037_wb.func_102353_h(int, int)void
		// @148: getstatic int[] game.C_100145_ta.field_100432_i
		// @14B: invokestatic game.C_100196_rb.func_105777_b(int[])void
		// @14E: goto @152
		// @151: athrow
		// @152: aconst_null
		// @153: aload_2
		// @154: bipush 8 (0x08)
		// @156: aaload
		// @157: if_acmpeq @17A
		// @15A: iload #17
		// @15C: iload #19
		// @15E: iload #10
		// @160: iload #11
		// @162: invokestatic game.C_100196_rb.func_105779_e(int, int, int, int)void
		// @165: aload_2
		// @166: bipush 8 (0x08)
		// @168: aaload
		// @169: iload #13
		// @16B: iload #15
		// @16D: invokevirtual game.C_100037_wb.func_102353_h(int, int)void
		// @170: getstatic int[] game.C_100145_ta.field_100432_i
		// @173: invokestatic game.C_100196_rb.func_105777_b(int[])void
		// @176: goto @17A
		// @179: athrow
		// @17A: aload_2
		// @17B: iconst_1
		// @17C: aaload
		// @17D: ifnull @1D4
		// @180: aload_2
		// @181: iconst_1
		// @182: aaload
		// @183: getfield int game.C_100037_wb.field_102341_y
		// @186: ifne @191
		// @189: goto @18D
		// @18C: athrow
		// @18D: goto @1D4
		// @190: athrow
		// @191: iload #16
		// @193: iload #5
		// @195: iload #17
		// @197: iload #18
		// @199: invokestatic game.C_100196_rb.func_105779_e(int, int, int, int)void
		// @19C: iload #12
		// @19E: istore #20
		// @1A0: iload #13
		// @1A2: iconst_m1
		// @1A3: ixor
		// @1A4: iload #20
		// @1A6: iconst_m1
		// @1A7: ixor
		// @1A8: if_icmpge @1CE
		// @1AB: aload_2
		// @1AC: iconst_1
		// @1AD: aaload
		// @1AE: iload #20
		// @1B0: iload #5
		// @1B2: invokevirtual game.C_100037_wb.func_102353_h(int, int)void
		// @1B5: iload #20
		// @1B7: aload_2
		// @1B8: iconst_1
		// @1B9: aaload
		// @1BA: getfield int game.C_100037_wb.field_102341_y
		// @1BD: iadd
		// @1BE: istore #20
		// @1C0: iload #22
		// @1C2: ifne @1D4
		// @1C5: iload #22
		// @1C7: ifeq @1A0
		// @1CA: goto @1CE
		// @1CD: athrow
		// @1CE: getstatic int[] game.C_100145_ta.field_100432_i
		// @1D1: invokestatic game.C_100196_rb.func_105777_b(int[])void
		// @1D4: aload_2
		// @1D5: bipush 7 (0x07)
		// @1D7: aaload
		// @1D8: ifnull @231
		// @1DB: aload_2
		// @1DC: bipush 7 (0x07)
		// @1DE: aaload
		// @1DF: getfield int game.C_100037_wb.field_102341_y
		// @1E2: iconst_m1
		// @1E3: ixor
		// @1E4: iconst_m1
		// @1E5: if_icmpne @1F0
		// @1E8: goto @1EC
		// @1EB: athrow
		// @1EC: goto @231
		// @1EF: athrow
		// @1F0: iload #16
		// @1F2: iload #19
		// @1F4: iload #17
		// @1F6: iload #11
		// @1F8: invokestatic game.C_100196_rb.func_105779_e(int, int, int, int)void
		// @1FB: iload #12
		// @1FD: istore #20
		// @1FF: iload #13
		// @201: iload #20
		// @203: if_icmple @22B
		// @206: aload_2
		// @207: bipush 7 (0x07)
		// @209: aaload
		// @20A: iload #20
		// @20C: iload #15
		// @20E: invokevirtual game.C_100037_wb.func_102353_h(int, int)void
		// @211: iload #20
		// @213: aload_2
		// @214: bipush 7 (0x07)
		// @216: aaload
		// @217: getfield int game.C_100037_wb.field_102341_y
		// @21A: iadd
		// @21B: istore #20
		// @21D: iload #22
		// @21F: ifne @231
		// @222: iload #22
		// @224: ifeq @1FF
		// @227: goto @22B
		// @22A: athrow
		// @22B: getstatic int[] game.C_100145_ta.field_100432_i
		// @22E: invokestatic game.C_100196_rb.func_105777_b(int[])void
		// @231: aload_2
		// @232: iconst_3
		// @233: aaload
		// @234: ifnull @288
		// @237: aload_2
		// @238: iconst_3
		// @239: aaload
		// @23A: getfield int game.C_100037_wb.field_102340_z
		// @23D: iconst_m1
		// @23E: ixor
		// @23F: iconst_m1
		// @240: if_icmpne @24B
		// @243: goto @247
		// @246: athrow
		// @247: goto @288
		// @24A: athrow
		// @24B: iload_3
		// @24C: iload #18
		// @24E: iload #16
		// @250: iload #19
		// @252: invokestatic game.C_100196_rb.func_105779_e(int, int, int, int)void
		// @255: iload #14
		// @257: istore #20
		// @259: iload #15
		// @25B: iload #20
		// @25D: if_icmple @282
		// @260: aload_2
		// @261: iconst_3
		// @262: aaload
		// @263: iload_3
		// @264: iload #20
		// @266: invokevirtual game.C_100037_wb.func_102353_h(int, int)void
		// @269: iload #20
		// @26B: aload_2
		// @26C: iconst_3
		// @26D: aaload
		// @26E: getfield int game.C_100037_wb.field_102340_z
		// @271: iadd
		// @272: istore #20
		// @274: iload #22
		// @276: ifne @288
		// @279: iload #22
		// @27B: ifeq @259
		// @27E: goto @282
		// @281: athrow
		// @282: getstatic int[] game.C_100145_ta.field_100432_i
		// @285: invokestatic game.C_100196_rb.func_105777_b(int[])void
		// @288: aconst_null
		// @289: aload_2
		// @28A: iconst_5
		// @28B: aaload
		// @28C: if_acmpeq @2E2
		// @28F: iconst_m1
		// @290: aload_2
		// @291: iconst_5
		// @292: aaload
		// @293: getfield int game.C_100037_wb.field_102340_z
		// @296: iconst_m1
		// @297: ixor
		// @298: if_icmpne @2A3
		// @29B: goto @29F
		// @29E: athrow
		// @29F: goto @2E2
		// @2A2: athrow
		// @2A3: iload #17
		// @2A5: iload #18
		// @2A7: iload #10
		// @2A9: iload #19
		// @2AB: invokestatic game.C_100196_rb.func_105779_e(int, int, int, int)void
		// @2AE: iload #14
		// @2B0: istore #20
		// @2B2: iload #15
		// @2B4: iload #20
		// @2B6: if_icmple @2DC
		// @2B9: aload_2
		// @2BA: iconst_5
		// @2BB: aaload
		// @2BC: iload #13
		// @2BE: iload #20
		// @2C0: invokevirtual game.C_100037_wb.func_102353_h(int, int)void
		// @2C3: iload #20
		// @2C5: aload_2
		// @2C6: iconst_5
		// @2C7: aaload
		// @2C8: getfield int game.C_100037_wb.field_102340_z
		// @2CB: iadd
		// @2CC: istore #20
		// @2CE: iload #22
		// @2D0: ifne @2E2
		// @2D3: iload #22
		// @2D5: ifeq @2B2
		// @2D8: goto @2DC
		// @2DB: athrow
		// @2DC: getstatic int[] game.C_100145_ta.field_100432_i
		// @2DF: invokestatic game.C_100196_rb.func_105777_b(int[])void
		// @2E2: iload_0
		// @2E3: iconst_m1
		// @2E4: if_icmpeq @2E8
		// @2E7: return
		// @2E8: aload_2
		// @2E9: iconst_4
		// @2EA: aaload
		// @2EB: ifnull @371
		// @2EE: aload_2
		// @2EF: iconst_4
		// @2F0: aaload
		// @2F1: getfield int game.C_100037_wb.field_102341_y
		// @2F4: iconst_m1
		// @2F5: ixor
		// @2F6: iconst_m1
		// @2F7: if_icmpeq @371
		// @2FA: goto @2FE
		// @2FD: athrow
		// @2FE: iconst_m1
		// @2FF: aload_2
		// @300: iconst_4
		// @301: aaload
		// @302: getfield int game.C_100037_wb.field_102340_z
		// @305: iconst_m1
		// @306: ixor
		// @307: if_icmpeq @371
		// @30A: goto @30E
		// @30D: athrow
		// @30E: iload #16
		// @310: iload #18
		// @312: iload #17
		// @314: iload #19
		// @316: invokestatic game.C_100196_rb.func_105779_e(int, int, int, int)void
		// @319: iload #14
		// @31B: istore #20
		// @31D: iload #15
		// @31F: iconst_m1
		// @320: ixor
		// @321: iload #20
		// @323: iconst_m1
		// @324: ixor
		// @325: if_icmpge @36B
		// @328: iload #22
		// @32A: ifne @371
		// @32D: iload #12
		// @32F: istore #21
		// @331: iload #13
		// @333: iload #21
		// @335: if_icmple @35B
		// @338: aload_2
		// @339: iconst_4
		// @33A: aaload
		// @33B: iload #21
		// @33D: iload #20
		// @33F: invokevirtual game.C_100037_wb.func_102353_h(int, int)void
		// @342: iload #21
		// @344: aload_2
		// @345: iconst_4
		// @346: aaload
		// @347: getfield int game.C_100037_wb.field_102341_y
		// @34A: iadd
		// @34B: istore #21
		// @34D: iload #22
		// @34F: ifne @366
		// @352: iload #22
		// @354: ifeq @331
		// @357: goto @35B
		// @35A: athrow
		// @35B: iload #20
		// @35D: aload_2
		// @35E: iconst_4
		// @35F: aaload
		// @360: getfield int game.C_100037_wb.field_102340_z
		// @363: iadd
		// @364: istore #20
		// @366: iload #22
		// @368: ifeq @31D
		// @36B: getstatic int[] game.C_100145_ta.field_100432_i
		// @36E: invokestatic game.C_100196_rb.func_105777_b(int[])void
		// @371: goto @3D8
		// @374: astore #6
		// @376: aload #6
		// @378: new java.lang.StringBuilder
		// @37B: dup
		// @37C: invokespecial java.lang.StringBuilder.<init>()void
		// @37F: getstatic java.lang.String[] game.C_100100_i.field_102019_ic
		// @382: bipush 7 (0x07)
		// @384: aaload
		// @385: invokevirtual java.lang.StringBuilder.append(java.lang.String)java.lang.StringBuilder
		// @388: iload_0
		// @389: invokevirtual java.lang.StringBuilder.append(int)java.lang.StringBuilder
		// @38C: bipush 44 (0x2C)
		// @38E: invokevirtual java.lang.StringBuilder.append(char)java.lang.StringBuilder
		// @391: iload_1
		// @392: invokevirtual java.lang.StringBuilder.append(int)java.lang.StringBuilder
		// @395: bipush 44 (0x2C)
		// @397: invokevirtual java.lang.StringBuilder.append(char)java.lang.StringBuilder
		// @39A: aload_2
		// @39B: ifnull @3A7
		// @39E: getstatic java.lang.String[] game.C_100100_i.field_102019_ic
		// @3A1: iconst_5
		// @3A2: aaload
		// @3A3: goto @3AC
		// @3A6: athrow
		// @3A7: getstatic java.lang.String[] game.C_100100_i.field_102019_ic
		// @3AA: iconst_3
		// @3AB: aaload
		// @3AC: invokevirtual java.lang.StringBuilder.append(java.lang.String)java.lang.StringBuilder
		// @3AF: bipush 44 (0x2C)
		// @3B1: invokevirtual java.lang.StringBuilder.append(char)java.lang.StringBuilder
		// @3B4: iload_3
		// @3B5: invokevirtual java.lang.StringBuilder.append(int)java.lang.StringBuilder
		// @3B8: bipush 44 (0x2C)
		// @3BA: invokevirtual java.lang.StringBuilder.append(char)java.lang.StringBuilder
		// @3BD: iload #4
		// @3BF: invokevirtual java.lang.StringBuilder.append(int)java.lang.StringBuilder
		// @3C2: bipush 44 (0x2C)
		// @3C4: invokevirtual java.lang.StringBuilder.append(char)java.lang.StringBuilder
		// @3C7: iload #5
		// @3C9: invokevirtual java.lang.StringBuilder.append(int)java.lang.StringBuilder
		// @3CC: bipush 41 (0x29)
		// @3CE: invokevirtual java.lang.StringBuilder.append(char)java.lang.StringBuilder
		// @3D1: invokevirtual java.lang.StringBuilder.toString()java.lang.String
		// @3D4: invokestatic game.C_100181_cf.func_105695_a(java.lang.Throwable, java.lang.String)game.C_100170_cm
		// @3D7: athrow
		// @3D8: return
	}
	
	C_100100_i(long arg0, C_100302_ka arg1, C_100302_ka arg2, C_100231_oc arg3, C_100302_ka arg4, String arg5, String arg6)
	{
		// @000: aload_0
		// @001: lload_1
		// @002: aload_3
		// @003: invokespecial game.C_100302_ka.<init>(long, game.C_100302_ka)void
		// @006: aload_0
		// @007: new game.C_100302_ka
		// @00A: dup
		// @00B: lconst_0
		// @00C: aconst_null
		// @00D: invokespecial game.C_100302_ka.<init>(long, game.C_100302_ka)void
		// @010: putfield game.C_100302_ka game.C_100100_i.field_102015_Yb
		// @013: aload_0
		// @014: new game.C_100115_ej
		// @017: dup
		// @018: lconst_0
		// @019: aload_0
		// @01A: getfield game.C_100302_ka game.C_100100_i.field_102015_Yb
		// @01D: aload #4
		// @01F: aload #5
		// @021: invokespecial game.C_100115_ej.<init>(long, game.C_100302_ka, game.C_100302_ka, game.C_100231_oc)void
		// @024: putfield game.C_100115_ej game.C_100100_i.field_102016_ec
		// @027: aload_0
		// @028: new game.C_100302_ka
		// @02B: dup
		// @02C: lconst_0
		// @02D: aload #6
		// @02F: invokespecial game.C_100302_ka.<init>(long, game.C_100302_ka)void
		// @032: putfield game.C_100302_ka game.C_100100_i.field_102021_Vb
		// @035: aload_0
		// @036: new game.C_100302_ka
		// @039: dup
		// @03A: lconst_0
		// @03B: aload #6
		// @03D: invokespecial game.C_100302_ka.<init>(long, game.C_100302_ka)void
		// @040: putfield game.C_100302_ka game.C_100100_i.field_102013_Xb
		// @043: aload_0
		// @044: getfield game.C_100302_ka game.C_100100_i.field_102021_Vb
		// @047: aload #7
		// @049: putfield java.lang.String game.C_100302_ka.field_101890_ab
		// @04C: aload_0
		// @04D: getfield game.C_100302_ka game.C_100100_i.field_102013_Xb
		// @050: aload #8
		// @052: putfield java.lang.String game.C_100302_ka.field_101890_ab
		// @055: aload_0
		// @056: bipush -99 (0x9D)
		// @058: aload_0
		// @059: getfield game.C_100115_ej game.C_100100_i.field_102016_ec
		// @05C: invokevirtual game.C_100100_i.func_101824_b(int, game.C_100302_ka)void
		// @05F: aload_0
		// @060: bipush -123 (0x85)
		// @062: aload_0
		// @063: getfield game.C_100302_ka game.C_100100_i.field_102021_Vb
		// @066: invokevirtual game.C_100100_i.func_101824_b(int, game.C_100302_ka)void
		// @069: aload_0
		// @06A: bipush -98 (0x9E)
		// @06C: aload_0
		// @06D: getfield game.C_100302_ka game.C_100100_i.field_102013_Xb
		// @070: invokevirtual game.C_100100_i.func_101824_b(int, game.C_100302_ka)void
		// @073: goto @13B
		// @076: astore #9
		// @078: aload #9
		// @07A: new java.lang.StringBuilder
		// @07D: dup
		// @07E: invokespecial java.lang.StringBuilder.<init>()void
		// @081: getstatic java.lang.String[] game.C_100100_i.field_102019_ic
		// @084: bipush 8 (0x08)
		// @086: aaload
		// @087: invokevirtual java.lang.StringBuilder.append(java.lang.String)java.lang.StringBuilder
		// @08A: lload_1
		// @08B: invokevirtual java.lang.StringBuilder.append(long)java.lang.StringBuilder
		// @08E: bipush 44 (0x2C)
		// @090: invokevirtual java.lang.StringBuilder.append(char)java.lang.StringBuilder
		// @093: aload_3
		// @094: ifnull @0A0
		// @097: getstatic java.lang.String[] game.C_100100_i.field_102019_ic
		// @09A: iconst_5
		// @09B: aaload
		// @09C: goto @0A5
		// @09F: athrow
		// @0A0: getstatic java.lang.String[] game.C_100100_i.field_102019_ic
		// @0A3: iconst_3
		// @0A4: aaload
		// @0A5: invokevirtual java.lang.StringBuilder.append(java.lang.String)java.lang.StringBuilder
		// @0A8: bipush 44 (0x2C)
		// @0AA: invokevirtual java.lang.StringBuilder.append(char)java.lang.StringBuilder
		// @0AD: aload #4
		// @0AF: ifnull @0BB
		// @0B2: getstatic java.lang.String[] game.C_100100_i.field_102019_ic
		// @0B5: iconst_5
		// @0B6: aaload
		// @0B7: goto @0C0
		// @0BA: athrow
		// @0BB: getstatic java.lang.String[] game.C_100100_i.field_102019_ic
		// @0BE: iconst_3
		// @0BF: aaload
		// @0C0: invokevirtual java.lang.StringBuilder.append(java.lang.String)java.lang.StringBuilder
		// @0C3: bipush 44 (0x2C)
		// @0C5: invokevirtual java.lang.StringBuilder.append(char)java.lang.StringBuilder
		// @0C8: aload #5
		// @0CA: ifnull @0D6
		// @0CD: getstatic java.lang.String[] game.C_100100_i.field_102019_ic
		// @0D0: iconst_5
		// @0D1: aaload
		// @0D2: goto @0DB
		// @0D5: athrow
		// @0D6: getstatic java.lang.String[] game.C_100100_i.field_102019_ic
		// @0D9: iconst_3
		// @0DA: aaload
		// @0DB: invokevirtual java.lang.StringBuilder.append(java.lang.String)java.lang.StringBuilder
		// @0DE: bipush 44 (0x2C)
		// @0E0: invokevirtual java.lang.StringBuilder.append(char)java.lang.StringBuilder
		// @0E3: aload #6
		// @0E5: ifnull @0F1
		// @0E8: getstatic java.lang.String[] game.C_100100_i.field_102019_ic
		// @0EB: iconst_5
		// @0EC: aaload
		// @0ED: goto @0F6
		// @0F0: athrow
		// @0F1: getstatic java.lang.String[] game.C_100100_i.field_102019_ic
		// @0F4: iconst_3
		// @0F5: aaload
		// @0F6: invokevirtual java.lang.StringBuilder.append(java.lang.String)java.lang.StringBuilder
		// @0F9: bipush 44 (0x2C)
		// @0FB: invokevirtual java.lang.StringBuilder.append(char)java.lang.StringBuilder
		// @0FE: aload #7
		// @100: ifnull @10C
		// @103: getstatic java.lang.String[] game.C_100100_i.field_102019_ic
		// @106: iconst_5
		// @107: aaload
		// @108: goto @111
		// @10B: athrow
		// @10C: getstatic java.lang.String[] game.C_100100_i.field_102019_ic
		// @10F: iconst_3
		// @110: aaload
		// @111: invokevirtual java.lang.StringBuilder.append(java.lang.String)java.lang.StringBuilder
		// @114: bipush 44 (0x2C)
		// @116: invokevirtual java.lang.StringBuilder.append(char)java.lang.StringBuilder
		// @119: aload #8
		// @11B: ifnull @127
		// @11E: getstatic java.lang.String[] game.C_100100_i.field_102019_ic
		// @121: iconst_5
		// @122: aaload
		// @123: goto @12C
		// @126: athrow
		// @127: getstatic java.lang.String[] game.C_100100_i.field_102019_ic
		// @12A: iconst_3
		// @12B: aaload
		// @12C: invokevirtual java.lang.StringBuilder.append(java.lang.String)java.lang.StringBuilder
		// @12F: bipush 41 (0x29)
		// @131: invokevirtual java.lang.StringBuilder.append(char)java.lang.StringBuilder
		// @134: invokevirtual java.lang.StringBuilder.toString()java.lang.String
		// @137: invokestatic game.C_100181_cf.func_105695_a(java.lang.Throwable, java.lang.String)game.C_100170_cm
		// @13A: athrow
		// @13B: return
	}
	
	C_100100_i(long arg0, C_100100_i arg1, String arg2, String arg3)
	{
		// @00: aload_0
		// @01: lload_1
		// @02: aload_3
		// @03: aload_3
		// @04: getfield game.C_100115_ej game.C_100100_i.field_102016_ec
		// @07: getfield game.C_100302_ka game.C_100115_ej.field_102040_Zb
		// @0A: aload_3
		// @0B: getfield game.C_100115_ej game.C_100100_i.field_102016_ec
		// @0E: getfield game.C_100231_oc game.C_100115_ej.field_102038_Vb
		// @11: aload_3
		// @12: getfield game.C_100302_ka game.C_100100_i.field_102021_Vb
		// @15: aload #4
		// @17: aload #5
		// @19: invokespecial game.C_100100_i.<init>(long, game.C_100302_ka, game.C_100302_ka, game.C_100231_oc, game.C_100302_ka, java.lang.String, java.lang.String)void
		// @1C: return
	}
	
	public static void func_102006_f(byte arg0)
	{
		// @00: aconst_null
		// @01: putstatic java.lang.String game.C_100100_i.field_102023_bc
		// @04: aconst_null
		// @05: putstatic int[] game.C_100100_i.field_102018_Wb
		// @08: aconst_null
		// @09: putstatic int[] game.C_100100_i.field_102020_Ub
		// @0C: aconst_null
		// @0D: putstatic game.C_100003_ga game.C_100100_i.field_102024_cc
		// @10: aconst_null
		// @11: putstatic game.C_100037_wb[] game.C_100100_i.field_102017_fc
		// @14: aconst_null
		// @15: putstatic java.lang.String game.C_100100_i.field_102022_ac
		// @18: iload_0
		// @19: bipush -51 (0xCD)
		// @1B: if_icmpeq @1F
		// @1E: return
		// @1F: aconst_null
		// @20: putstatic java.lang.String game.C_100100_i.field_102010_dc
		// @23: goto @47
		// @26: astore_1
		// @27: aload_1
		// @28: new java.lang.StringBuilder
		// @2B: dup
		// @2C: invokespecial java.lang.StringBuilder.<init>()void
		// @2F: getstatic java.lang.String[] game.C_100100_i.field_102019_ic
		// @32: iconst_2
		// @33: aaload
		// @34: invokevirtual java.lang.StringBuilder.append(java.lang.String)java.lang.StringBuilder
		// @37: iload_0
		// @38: invokevirtual java.lang.StringBuilder.append(int)java.lang.StringBuilder
		// @3B: bipush 41 (0x29)
		// @3D: invokevirtual java.lang.StringBuilder.append(char)java.lang.StringBuilder
		// @40: invokevirtual java.lang.StringBuilder.toString()java.lang.String
		// @43: invokestatic game.C_100181_cf.func_105695_a(java.lang.Throwable, java.lang.String)game.C_100170_cm
		// @46: athrow
		// @47: return
	}
	
	static
	{
		// @000: bipush 10 (0x0A)
		// @002: anewarray java.lang.String
		// @005: dup
		// @006: iconst_0
		// @007: ldc "\u0014z\"/"
		// @009: invokestatic game.C_100100_i.func_102005_z(java.lang.String)char[]
		// @00C: invokestatic game.C_100100_i.func_102003_z(char[])java.lang.String
		// @00F: aastore
		// @010: dup
		// @011: iconst_1
		// @012: ldc "\u0014z&/"
		// @014: invokestatic game.C_100100_i.func_102005_z(java.lang.String)char[]
		// @017: invokestatic game.C_100100_i.func_102003_z(char[])java.lang.String
		// @01A: aastore
		// @01B: dup
		// @01C: iconst_2
		// @01D: ldc "\u0014z%/"
		// @01F: invokestatic game.C_100100_i.func_102005_z(java.lang.String)char[]
		// @022: invokestatic game.C_100100_i.func_102003_z(char[])java.lang.String
		// @025: aastore
		// @026: dup
		// @027: iconst_3
		// @028: ldc "\u0013!\u000fk"
		// @02A: invokestatic game.C_100100_i.func_102005_z(java.lang.String)char[]
		// @02D: invokestatic game.C_100100_i.func_102003_z(char[])java.lang.String
		// @030: aastore
		// @031: dup
		// @032: iconst_4
		// @033: ldc "\u0014z /"
		// @035: invokestatic game.C_100100_i.func_102005_z(java.lang.String)char[]
		// @038: invokestatic game.C_100100_i.func_102003_z(char[])java.lang.String
		// @03B: aastore
		// @03C: dup
		// @03D: iconst_5
		// @03E: ldc "\u0006zM)Q"
		// @040: invokestatic game.C_100100_i.func_102005_z(java.lang.String)char[]
		// @043: invokestatic game.C_100100_i.func_102003_z(char[])java.lang.String
		// @046: aastore
		// @047: dup
		// @048: bipush 6 (0x06)
		// @04A: ldc "\u0014z$/"
		// @04C: invokestatic game.C_100100_i.func_102005_z(java.lang.String)char[]
		// @04F: invokestatic game.C_100100_i.func_102003_z(char[])java.lang.String
		// @052: aastore
		// @053: dup
		// @054: bipush 7 (0x07)
		// @056: ldc "\u0014z'/"
		// @058: invokestatic game.C_100100_i.func_102005_z(java.lang.String)char[]
		// @05B: invokestatic game.C_100100_i.func_102003_z(char[])java.lang.String
		// @05E: aastore
		// @05F: dup
		// @060: bipush 8 (0x08)
		// @062: ldc "\u0014z_nB\u0014 ]/"
		// @064: invokestatic game.C_100100_i.func_102005_z(java.lang.String)char[]
		// @067: invokestatic game.C_100100_i.func_102003_z(char[])java.lang.String
		// @06A: aastore
		// @06B: dup
		// @06C: bipush 9 (0x09)
		// @06E: ldc "\u0014z!/"
		// @070: invokestatic game.C_100100_i.func_102005_z(java.lang.String)char[]
		// @073: invokestatic game.C_100100_i.func_102003_z(char[])java.lang.String
		// @076: aastore
		// @077: putstatic java.lang.String[] game.C_100100_i.field_102019_ic
		// @07A: ldc "><\u0002s\u000c\u000b=\u0006p\u000c\u00155\u0010'N\u00181\r'_\u001e&\u000ck@\u00180Cr\\St0d^\u00128\u000f'H\u0012#\r'X\u0012t\u0000oM\tz"
		// @07C: invokestatic game.C_100100_i.func_102005_z(java.lang.String)char[]
		// @07F: invokestatic game.C_100100_i.func_102003_z(char[])java.lang.String
		// @082: putstatic java.lang.String game.C_100100_i.field_102010_dc
		// @085: ldc 65536 (0x10000)
		// @087: newarray int[]
		// @089: putstatic int[] game.C_100100_i.field_102020_Ub
		// @08C: ldc 65536 (0x10000)
		// @08E: newarray int[]
		// @090: putstatic int[] game.C_100100_i.field_102018_Wb
		// @093: ldc ")<\u0002s\u000c\u00135\u000eb\u000c\u0014'CiC\tt\u0002qM\u00148\u0002e@\u0018"
		// @095: invokestatic game.C_100100_i.func_102005_z(java.lang.String)char[]
		// @098: invokestatic game.C_100100_i.func_102003_z(char[])java.lang.String
		// @09B: putstatic java.lang.String game.C_100100_i.field_102023_bc
		// @09E: iconst_0
		// @09F: istore_0
		// @0A0: ldc 65536 (0x10000)
		// @0A2: iload_0
		// @0A3: if_icmple @0C3
		// @0A6: ldc2_w 256.0
		// @0A9: iload_0
		// @0AA: i2d
		// @0AB: invokestatic java.lang.Math.sqrt(double)double
		// @0AE: dsub
		// @0AF: dstore_1
		// @0B0: getstatic int[] game.C_100100_i.field_102020_Ub
		// @0B3: iload_0
		// @0B4: ldc2_w 0.5
		// @0B7: dload_1
		// @0B8: dload_1
		// @0B9: dmul
		// @0BA: dadd
		// @0BB: d2i
		// @0BC: iastore
		// @0BD: iinc #0 +1
		// @0C0: goto @0A0
		// @0C3: iconst_0
		// @0C4: istore_0
		// @0C5: ldc 65536 (0x10000)
		// @0C7: iload_0
		// @0C8: if_icmple @0F0
		// @0CB: iload_0
		// @0CC: i2d
		// @0CD: invokestatic java.lang.Math.sqrt(double)double
		// @0D0: dstore_1
		// @0D1: getstatic int[] game.C_100100_i.field_102018_Wb
		// @0D4: iload_0
		// @0D5: iload_0
		// @0D6: i2d
		// @0D7: ldc2_w 0.0234375
		// @0DA: dmul
		// @0DB: ldc2_w 768.5
		// @0DE: dload_1
		// @0DF: ldc2_w 9.0
		// @0E2: dmul
		// @0E3: dsub
		// @0E4: dadd
		// @0E5: invokestatic java.lang.Math.floor(double)double
		// @0E8: d2i
		// @0E9: iastore
		// @0EA: iinc #0 +1
		// @0ED: goto @0C5
		// @0F0: ldc ")<\nt\u000c\u0014'C;\tMjDt\u000c/!\rb\u007f\u001e5\u0013b\u000c\u001e8\u0002i\u000c\u00142CsD\u0018-CoM\u000b1ChB\u0018z"
		// @0F2: invokestatic game.C_100100_i.func_102005_z(java.lang.String)char[]
		// @0F5: invokestatic game.C_100100_i.func_102003_z(char[])java.lang.String
		// @0F8: putstatic java.lang.String game.C_100100_i.field_102022_ac
		// @0FB: aconst_null
		// @0FC: putstatic game.C_100003_ga game.C_100100_i.field_102024_cc
		// @0FF: return
	}
	
	private static char[] func_102005_z(String arg0)
	{
		// @00: aload_0
		// @01: invokevirtual java.lang.String.toCharArray()char[]
		// @04: dup
		// @05: arraylength
		// @06: iconst_2
		// @07: if_icmpge @13
		// @0A: dup
		// @0B: iconst_0
		// @0C: dup2
		// @0D: caload
		// @0E: bipush 44 (0x2C)
		// @10: ixor
		// @11: i2c
		// @12: castore
		// @13: areturn
	}
	
	private static String func_102003_z(char[] arg0)
	{
		// @00: aload_0
		// @01: dup
		// @02: arraylength
		// @03: swap
		// @04: iconst_0
		// @05: istore_1
		// @06: goto @4C
		// @09: dup
		// @0A: iload_1
		// @0B: dup2
		// @0C: caload
		// @0D: iload_1
		// @0E: iconst_5
		// @0F: irem
		// @10: tableswitch def: @44, for 0: @30, for 1: @35, for 2: @3A, for 3: @3F
		// @30: bipush 125 (0x7D)
		// @32: goto @46
		// @35: bipush 84 (0x54)
		// @37: goto @46
		// @3A: bipush 99 (0x63)
		// @3C: goto @46
		// @3F: bipush 7 (0x07)
		// @41: goto @46
		// @44: bipush 44 (0x2C)
		// @46: ixor
		// @47: i2c
		// @48: castore
		// @49: iinc #1 +1
		// @4C: swap
		// @4D: dup_x1
		// @4E: iload_1
		// @4F: if_icmpgt @09
		// @52: new java.lang.String
		// @55: dup_x1
		// @56: swap
		// @57: invokespecial java.lang.String.<init>(char[])void
		// @5A: invokevirtual java.lang.String.intern()java.lang.String
		// @5D: areturn
	}
}
