package game;

final class C_100154_sl
{
	private boolean field_105335_a;
	static C_100098_h field_105338_k;
	static C_100302_ka field_105332_e;
	static boolean field_105336_j;
	static C_100037_wb[] field_105329_f;
	static String field_105339_h;
	static boolean field_105330_g;
	static boolean field_105333_b;
	static String[] field_105334_c;
	static C_100153_be[] field_105331_d;
	private String field_105340_i;
	private static final String[] field_105337_z;
	
	public static void func_105322_b(int arg0)
	{
		// @00: aconst_null
		// @01: putstatic java.lang.String[] game.C_100154_sl.field_105334_c
		// @04: aconst_null
		// @05: putstatic game.C_100302_ka game.C_100154_sl.field_105332_e
		// @08: aconst_null
		// @09: putstatic java.lang.String game.C_100154_sl.field_105339_h
		// @0C: aconst_null
		// @0D: putstatic game.C_100037_wb[] game.C_100154_sl.field_105329_f
		// @10: aconst_null
		// @11: putstatic game.C_100098_h game.C_100154_sl.field_105338_k
		// @14: bipush 94 (0x5E)
		// @16: bipush -8 (0xF8)
		// @18: iload_0
		// @19: isub
		// @1A: bipush 53 (0x35)
		// @1C: idiv
		// @1D: irem
		// @1E: istore_1
		// @1F: aconst_null
		// @20: putstatic game.C_100153_be[] game.C_100154_sl.field_105331_d
		// @23: goto @48
		// @26: astore_1
		// @27: aload_1
		// @28: new java.lang.StringBuilder
		// @2B: dup
		// @2C: invokespecial java.lang.StringBuilder.<init>()void
		// @2F: getstatic java.lang.String[] game.C_100154_sl.field_105337_z
		// @32: bipush 8 (0x08)
		// @34: aaload
		// @35: invokevirtual java.lang.StringBuilder.append(java.lang.String)java.lang.StringBuilder
		// @38: iload_0
		// @39: invokevirtual java.lang.StringBuilder.append(int)java.lang.StringBuilder
		// @3C: bipush 41 (0x29)
		// @3E: invokevirtual java.lang.StringBuilder.append(char)java.lang.StringBuilder
		// @41: invokevirtual java.lang.StringBuilder.toString()java.lang.String
		// @44: invokestatic game.C_100181_cf.func_105695_a(java.lang.Throwable, java.lang.String)game.C_100170_cm
		// @47: athrow
		// @48: return
	}
	
	C_100154_sl(String arg0)
	{
		// @0: aload_0
		// @1: aload_1
		// @2: iconst_0
		// @3: invokespecial game.C_100154_sl.<init>(java.lang.String, boolean)void
		// @6: return
	}
	
	final String func_105321_c(int arg0)
	{
		// @00: iload_1
		// @01: bipush -100 (0x9C)
		// @03: if_icmplt @0B
		// @06: aconst_null
		// @07: checkcast java.lang.String
		// @0A: areturn
		// @0B: aload_0
		// @0C: getfield java.lang.String game.C_100154_sl.field_105340_i
		// @0F: areturn
		// @10: astore_2
		// @11: aload_2
		// @12: new java.lang.StringBuilder
		// @15: dup
		// @16: invokespecial java.lang.StringBuilder.<init>()void
		// @19: getstatic java.lang.String[] game.C_100154_sl.field_105337_z
		// @1C: iconst_0
		// @1D: aaload
		// @1E: invokevirtual java.lang.StringBuilder.append(java.lang.String)java.lang.StringBuilder
		// @21: iload_1
		// @22: invokevirtual java.lang.StringBuilder.append(int)java.lang.StringBuilder
		// @25: bipush 41 (0x29)
		// @27: invokevirtual java.lang.StringBuilder.append(char)java.lang.StringBuilder
		// @2A: invokevirtual java.lang.StringBuilder.toString()java.lang.String
		// @2D: invokestatic game.C_100181_cf.func_105695_a(java.lang.Throwable, java.lang.String)game.C_100170_cm
		// @30: athrow
	}
	
	static final void func_105328_a(boolean arg0, int arg1, int arg2, int arg3)
	{
		// @00: getstatic boolean game.C_100021_wn.field_103871_b
		// @03: ifeq @09
		// @06: goto @0A
		// @09: return
		// @0A: getstatic game.C_100302_ka game.C_100245_pf.field_106388_b
		// @0D: iload_0
		// @0E: bipush -107 (0x95)
		// @10: invokevirtual game.C_100302_ka.func_101819_a(boolean, byte)void
		// @13: getstatic game.C_100033_gj game.C_100159_sn.field_105401_e
		// @16: iconst_0
		// @17: invokevirtual game.C_100033_gj.func_101895_l(int)boolean
		// @1A: istore #4
		// @1C: getstatic int game.C_100102_w.field_104636_c
		// @1F: ifeq @37
		// @22: iload #4
		// @24: ifeq @2F
		// @27: goto @2B
		// @2A: athrow
		// @2B: goto @37
		// @2E: athrow
		// @2F: sipush -24528 (0xA030)
		// @32: invokestatic game.C_100285_nk.func_106775_c(int)void
		// @35: iconst_0
		// @36: istore_0
		// @37: iload_0
		// @38: ifne @3F
		// @3B: goto @48
		// @3E: athrow
		// @3F: getstatic game.C_100033_gj game.C_100159_sn.field_105401_e
		// @42: iconst_m1
		// @43: iload_1
		// @44: iload_2
		// @45: invokevirtual game.C_100033_gj.func_101900_a(int, int, int)void
		// @48: iload #4
		// @4A: ifeq @5A
		// @4D: getstatic game.C_100302_ka game.C_100245_pf.field_106388_b
		// @50: iload_0
		// @51: bipush 46 (0x2E)
		// @53: invokevirtual game.C_100302_ka.func_101819_a(boolean, byte)void
		// @56: goto @5A
		// @59: athrow
		// @5A: getstatic game.C_100033_gj game.C_100159_sn.field_105401_e
		// @5D: bipush -94 (0xA2)
		// @5F: invokevirtual game.C_100033_gj.func_101905_n(int)int
		// @62: getstatic game.C_100033_gj game.C_100159_sn.field_105401_e
		// @65: getfield int game.C_100033_gj.field_101840_Eb
		// @68: ineg
		// @69: isub
		// @6A: istore #5
		// @6C: iload #5
		// @6E: iconst_m1
		// @6F: ixor
		// @70: iload_3
		// @71: if_icmplt @A1
		// @74: iload #5
		// @76: iconst_m1
		// @77: ixor
		// @78: sipush -636 (0xFD84)
		// @7B: if_icmple @AD
		// @7E: goto @82
		// @81: athrow
		// @82: iconst_m1
		// @83: getstatic int game.C_100231_oc.field_102200_Wb
		// @86: iconst_m1
		// @87: ixor
		// @88: if_icmpgt @93
		// @8B: goto @8F
		// @8E: athrow
		// @8F: goto @AD
		// @92: athrow
		// @93: getstatic int game.C_100231_oc.field_102200_Wb
		// @96: iconst_5
		// @97: isub
		// @98: putstatic int game.C_100231_oc.field_102200_Wb
		// @9B: getstatic int game.SteelSentinels.field_105275_O
		// @9E: ifeq @AD
		// @A1: getstatic int game.C_100231_oc.field_102200_Wb
		// @A4: iconst_5
		// @A5: iadd
		// @A6: putstatic int game.C_100231_oc.field_102200_Wb
		// @A9: goto @AD
		// @AC: athrow
		// @AD: goto @EE
		// @B0: astore #4
		// @B2: aload #4
		// @B4: new java.lang.StringBuilder
		// @B7: dup
		// @B8: invokespecial java.lang.StringBuilder.<init>()void
		// @BB: getstatic java.lang.String[] game.C_100154_sl.field_105337_z
		// @BE: iconst_1
		// @BF: aaload
		// @C0: invokevirtual java.lang.StringBuilder.append(java.lang.String)java.lang.StringBuilder
		// @C3: iload_0
		// @C4: invokevirtual java.lang.StringBuilder.append(boolean)java.lang.StringBuilder
		// @C7: bipush 44 (0x2C)
		// @C9: invokevirtual java.lang.StringBuilder.append(char)java.lang.StringBuilder
		// @CC: iload_1
		// @CD: invokevirtual java.lang.StringBuilder.append(int)java.lang.StringBuilder
		// @D0: bipush 44 (0x2C)
		// @D2: invokevirtual java.lang.StringBuilder.append(char)java.lang.StringBuilder
		// @D5: iload_2
		// @D6: invokevirtual java.lang.StringBuilder.append(int)java.lang.StringBuilder
		// @D9: bipush 44 (0x2C)
		// @DB: invokevirtual java.lang.StringBuilder.append(char)java.lang.StringBuilder
		// @DE: iload_3
		// @DF: invokevirtual java.lang.StringBuilder.append(int)java.lang.StringBuilder
		// @E2: bipush 41 (0x29)
		// @E4: invokevirtual java.lang.StringBuilder.append(char)java.lang.StringBuilder
		// @E7: invokevirtual java.lang.StringBuilder.toString()java.lang.String
		// @EA: invokestatic game.C_100181_cf.func_105695_a(java.lang.Throwable, java.lang.String)game.C_100170_cm
		// @ED: athrow
		// @EE: return
	}
	
	static final void func_105327_a(int arg0, int arg1, C_100002_gf arg2, boolean arg3)
	{
		// @00: aconst_null
		// @01: getstatic game.C_100253_ph game.C_100203_ql.field_105927_f
		// @04: if_acmpne @0B
		// @07: goto @15
		// @0A: athrow
		// @0B: aload_2
		// @0C: iload_0
		// @0D: bipush -99 (0x9D)
		// @0F: iload_3
		// @10: ldc 1048576 (0x100000)
		// @12: invokestatic game.C_100312_ld.func_107148_a(game.C_100002_gf, int, byte, boolean, int)void
		// @15: getstatic game.C_100210_qa game.C_100004_gb.field_103576_k
		// @18: ifnonnull @1F
		// @1B: goto @75
		// @1E: athrow
		// @1F: getstatic game.C_100177_cj game.C_100313_lg.field_107164_d
		// @22: dup
		// @23: astore #4
		// @25: monitorenter
		// @26: getstatic game.C_100210_qa game.C_100004_gb.field_103576_k
		// @29: iload_0
		// @2A: iconst_m1
		// @2B: sipush 8192 (0x2000)
		// @2E: invokevirtual game.C_100210_qa.func_101025_c(int, int, int)void
		// @31: aload_2
		// @32: getstatic game.C_100002_gf game.C_100235_om.field_106292_a
		// @35: if_acmpeq @3B
		// @38: goto @3F
		// @3B: aload #4
		// @3D: monitorexit
		// @3E: return
		// @3F: getstatic game.C_100210_qa game.C_100004_gb.field_103576_k
		// @42: bipush 125 (0x7D)
		// @44: invokevirtual game.C_100210_qa.func_101028_a(byte)void
		// @47: getstatic game.C_100177_cj game.C_100313_lg.field_107164_d
		// @4A: invokevirtual game.C_100177_cj.func_105636_g()void
		// @4D: aload_2
		// @4E: putstatic game.C_100002_gf game.C_100235_om.field_106292_a
		// @51: aconst_null
		// @52: getstatic game.C_100002_gf game.C_100235_om.field_106292_a
		// @55: if_acmpne @5C
		// @58: goto @67
		// @5B: athrow
		// @5C: getstatic game.C_100210_qa game.C_100004_gb.field_103576_k
		// @5F: iload_3
		// @60: iconst_0
		// @61: getstatic game.C_100002_gf game.C_100235_om.field_106292_a
		// @64: invokevirtual game.C_100210_qa.func_101035_a(boolean, boolean, game.C_100002_gf)void
		// @67: aload #4
		// @69: monitorexit
		// @6A: goto @75
		// @6D: astore #5
		// @6F: aload #4
		// @71: monitorexit
		// @72: aload #5
		// @74: athrow
		// @75: iload_1
		// @76: ldc 1048576 (0x100000)
		// @78: if_icmpeq @89
		// @7B: iconst_1
		// @7C: bipush -77 (0xB3)
		// @7E: bipush 92 (0x5C)
		// @80: bipush -43 (0xD5)
		// @82: invokestatic game.C_100154_sl.func_105328_a(boolean, int, int, int)void
		// @85: goto @89
		// @88: athrow
		// @89: goto @DB
		// @8C: astore #4
		// @8E: aload #4
		// @90: new java.lang.StringBuilder
		// @93: dup
		// @94: invokespecial java.lang.StringBuilder.<init>()void
		// @97: getstatic java.lang.String[] game.C_100154_sl.field_105337_z
		// @9A: iconst_5
		// @9B: aaload
		// @9C: invokevirtual java.lang.StringBuilder.append(java.lang.String)java.lang.StringBuilder
		// @9F: iload_0
		// @A0: invokevirtual java.lang.StringBuilder.append(int)java.lang.StringBuilder
		// @A3: bipush 44 (0x2C)
		// @A5: invokevirtual java.lang.StringBuilder.append(char)java.lang.StringBuilder
		// @A8: iload_1
		// @A9: invokevirtual java.lang.StringBuilder.append(int)java.lang.StringBuilder
		// @AC: bipush 44 (0x2C)
		// @AE: invokevirtual java.lang.StringBuilder.append(char)java.lang.StringBuilder
		// @B1: aload_2
		// @B2: ifnull @BE
		// @B5: getstatic java.lang.String[] game.C_100154_sl.field_105337_z
		// @B8: iconst_3
		// @B9: aaload
		// @BA: goto @C3
		// @BD: athrow
		// @BE: getstatic java.lang.String[] game.C_100154_sl.field_105337_z
		// @C1: iconst_4
		// @C2: aaload
		// @C3: invokevirtual java.lang.StringBuilder.append(java.lang.String)java.lang.StringBuilder
		// @C6: bipush 44 (0x2C)
		// @C8: invokevirtual java.lang.StringBuilder.append(char)java.lang.StringBuilder
		// @CB: iload_3
		// @CC: invokevirtual java.lang.StringBuilder.append(boolean)java.lang.StringBuilder
		// @CF: bipush 41 (0x29)
		// @D1: invokevirtual java.lang.StringBuilder.append(char)java.lang.StringBuilder
		// @D4: invokevirtual java.lang.StringBuilder.toString()java.lang.String
		// @D7: invokestatic game.C_100181_cf.func_105695_a(java.lang.Throwable, java.lang.String)game.C_100170_cm
		// @DA: athrow
		// @DB: return
	}
	
	static final Boolean func_105324_d(int arg0)
	{
		// @00: getstatic java.lang.Boolean game.C_100285_nk.field_106783_b
		// @03: astore_1
		// @04: iload_0
		// @05: ifeq @13
		// @08: aconst_null
		// @09: checkcast game.C_100037_wb[]
		// @0C: putstatic game.C_100037_wb[] game.C_100154_sl.field_105329_f
		// @0F: goto @13
		// @12: athrow
		// @13: aconst_null
		// @14: putstatic java.lang.Boolean game.C_100285_nk.field_106783_b
		// @17: aload_1
		// @18: areturn
		// @19: astore_1
		// @1A: aload_1
		// @1B: new java.lang.StringBuilder
		// @1E: dup
		// @1F: invokespecial java.lang.StringBuilder.<init>()void
		// @22: getstatic java.lang.String[] game.C_100154_sl.field_105337_z
		// @25: bipush 7 (0x07)
		// @27: aaload
		// @28: invokevirtual java.lang.StringBuilder.append(java.lang.String)java.lang.StringBuilder
		// @2B: iload_0
		// @2C: invokevirtual java.lang.StringBuilder.append(int)java.lang.StringBuilder
		// @2F: bipush 41 (0x29)
		// @31: invokevirtual java.lang.StringBuilder.append(char)java.lang.StringBuilder
		// @34: invokevirtual java.lang.StringBuilder.toString()java.lang.String
		// @37: invokestatic game.C_100181_cf.func_105695_a(java.lang.Throwable, java.lang.String)game.C_100170_cm
		// @3A: athrow
	}
	
	final boolean func_105326_a(int arg0)
	{
		// @00: bipush 13 (0x0D)
		// @02: iload_1
		// @03: bipush -36 (0xDC)
		// @05: isub
		// @06: bipush 39 (0x27)
		// @08: idiv
		// @09: irem
		// @0A: istore_2
		// @0B: aload_0
		// @0C: getfield boolean game.C_100154_sl.field_105335_a
		// @0F: ireturn
		// @10: astore_2
		// @11: aload_2
		// @12: new java.lang.StringBuilder
		// @15: dup
		// @16: invokespecial java.lang.StringBuilder.<init>()void
		// @19: getstatic java.lang.String[] game.C_100154_sl.field_105337_z
		// @1C: iconst_2
		// @1D: aaload
		// @1E: invokevirtual java.lang.StringBuilder.append(java.lang.String)java.lang.StringBuilder
		// @21: iload_1
		// @22: invokevirtual java.lang.StringBuilder.append(int)java.lang.StringBuilder
		// @25: bipush 41 (0x29)
		// @27: invokevirtual java.lang.StringBuilder.append(char)java.lang.StringBuilder
		// @2A: invokevirtual java.lang.StringBuilder.toString()java.lang.String
		// @2D: invokestatic game.C_100181_cf.func_105695_a(java.lang.Throwable, java.lang.String)game.C_100170_cm
		// @30: athrow
	}
	
	C_100154_sl(String arg0, boolean arg1)
	{
		// @00: aload_0
		// @01: invokespecial java.lang.Object.<init>()void
		// @04: aload_0
		// @05: aload_1
		// @06: putfield java.lang.String game.C_100154_sl.field_105340_i
		// @09: aload_0
		// @0A: iload_2
		// @0B: putfield boolean game.C_100154_sl.field_105335_a
		// @0E: aconst_null
		// @0F: aload_0
		// @10: getfield java.lang.String game.C_100154_sl.field_105340_i
		// @13: if_acmpne @1C
		// @16: aload_0
		// @17: ldc ""
		// @19: putfield java.lang.String game.C_100154_sl.field_105340_i
		// @1C: aload_0
		// @1D: getfield java.lang.String game.C_100154_sl.field_105340_i
		// @20: invokevirtual java.lang.String.length()int
		// @23: ifeq @2A
		// @26: goto @2F
		// @29: athrow
		// @2A: aload_0
		// @2B: iconst_0
		// @2C: putfield boolean game.C_100154_sl.field_105335_a
		// @2F: goto @6E
		// @32: astore_3
		// @33: aload_3
		// @34: new java.lang.StringBuilder
		// @37: dup
		// @38: invokespecial java.lang.StringBuilder.<init>()void
		// @3B: getstatic java.lang.String[] game.C_100154_sl.field_105337_z
		// @3E: bipush 6 (0x06)
		// @40: aaload
		// @41: invokevirtual java.lang.StringBuilder.append(java.lang.String)java.lang.StringBuilder
		// @44: aload_1
		// @45: ifnull @51
		// @48: getstatic java.lang.String[] game.C_100154_sl.field_105337_z
		// @4B: iconst_3
		// @4C: aaload
		// @4D: goto @56
		// @50: athrow
		// @51: getstatic java.lang.String[] game.C_100154_sl.field_105337_z
		// @54: iconst_4
		// @55: aaload
		// @56: invokevirtual java.lang.StringBuilder.append(java.lang.String)java.lang.StringBuilder
		// @59: bipush 44 (0x2C)
		// @5B: invokevirtual java.lang.StringBuilder.append(char)java.lang.StringBuilder
		// @5E: iload_2
		// @5F: invokevirtual java.lang.StringBuilder.append(boolean)java.lang.StringBuilder
		// @62: bipush 41 (0x29)
		// @64: invokevirtual java.lang.StringBuilder.append(char)java.lang.StringBuilder
		// @67: invokevirtual java.lang.StringBuilder.toString()java.lang.String
		// @6A: invokestatic game.C_100181_cf.func_105695_a(java.lang.Throwable, java.lang.String)game.C_100170_cm
		// @6D: athrow
		// @6E: return
	}
	
	static
	{
		// @000: bipush 9 (0x09)
		// @002: anewarray java.lang.String
		// @005: dup
		// @006: iconst_0
		// @007: ldc "1<,\u0014u"
		// @009: invokestatic game.C_100154_sl.func_105325_z(java.lang.String)char[]
		// @00C: invokestatic game.C_100154_sl.func_105323_z(char[])java.lang.String
		// @00F: aastore
		// @010: dup
		// @011: iconst_1
		// @012: ldc "1<,\u0015u"
		// @014: invokestatic game.C_100154_sl.func_105325_z(java.lang.String)char[]
		// @017: invokestatic game.C_100154_sl.func_105323_z(char[])java.lang.String
		// @01A: aastore
		// @01B: dup
		// @01C: iconst_2
		// @01D: ldc "1<,\u0010u"
		// @01F: invokestatic game.C_100154_sl.func_105325_z(java.lang.String)char[]
		// @022: invokestatic game.C_100154_sl.func_105323_z(char[])java.lang.String
		// @025: aastore
		// @026: dup
		// @027: iconst_3
		// @028: ldc "9~,\u007f "
		// @02A: invokestatic game.C_100154_sl.func_105325_z(java.lang.String)char[]
		// @02D: invokestatic game.C_100154_sl.func_105323_z(char[])java.lang.String
		// @030: aastore
		// @031: dup
		// @032: iconst_4
		// @033: ldc ",%n="
		// @035: invokestatic game.C_100154_sl.func_105325_z(java.lang.String)char[]
		// @038: invokestatic game.C_100154_sl.func_105323_z(char[])java.lang.String
		// @03B: aastore
		// @03C: dup
		// @03D: iconst_5
		// @03E: ldc "1<,\u0012u"
		// @040: invokestatic game.C_100154_sl.func_105325_z(java.lang.String)char[]
		// @043: invokestatic game.C_100154_sl.func_105323_z(char[])java.lang.String
		// @046: aastore
		// @047: dup
		// @048: bipush 6 (0x06)
		// @04A: ldc "1<,m4,9vou"
		// @04C: invokestatic game.C_100154_sl.func_105325_z(java.lang.String)char[]
		// @04F: invokestatic game.C_100154_sl.func_105323_z(char[])java.lang.String
		// @052: aastore
		// @053: dup
		// @054: bipush 7 (0x07)
		// @056: ldc "1<,\u0013u"
		// @058: invokestatic game.C_100154_sl.func_105325_z(java.lang.String)char[]
		// @05B: invokestatic game.C_100154_sl.func_105323_z(char[])java.lang.String
		// @05E: aastore
		// @05F: dup
		// @060: bipush 8 (0x08)
		// @062: ldc "1<,\u0017u"
		// @064: invokestatic game.C_100154_sl.func_105325_z(java.lang.String)char[]
		// @067: invokestatic game.C_100154_sl.func_105323_z(char[])java.lang.String
		// @06A: aastore
		// @06B: putstatic java.lang.String[] game.C_100154_sl.field_105337_z
		// @06E: iconst_0
		// @06F: putstatic boolean game.C_100154_sl.field_105336_j
		// @072: iconst_1
		// @073: putstatic boolean game.C_100154_sl.field_105330_g
		// @076: ldc "\u0017>r0>)9l6}1?w?9b5d78!$q"
		// @078: invokestatic game.C_100154_sl.func_105325_z(java.lang.String)char[]
		// @07B: invokestatic game.C_100154_sl.func_105323_z(char[])java.lang.String
		// @07E: putstatic java.lang.String game.C_100154_sl.field_105339_h
		// @081: bipush 36 (0x24)
		// @083: anewarray java.lang.String
		// @086: dup
		// @087: iconst_0
		// @088: ldc "~u3o}$5n=}+>v>}~u2oz1pd=<)"
		// @08A: invokestatic game.C_100154_sl.func_105325_z(java.lang.String)char[]
		// @08D: invokestatic game.C_100154_sl.func_105323_z(char[])java.lang.String
		// @090: aastore
		// @091: dup
		// @092: iconst_1
		// @093: ldc "~u3o}51qq-'\"d>/#$g5} )\"mxrn%\"}/9l8:7>"
		// @095: invokestatic game.C_100154_sl.func_105325_z(java.lang.String)char[]
		// @098: invokestatic game.C_100154_sl.func_105323_z(char[])java.lang.String
		// @09B: aastore
		// @09C: dup
		// @09D: iconst_2
		// @09E: ldc "~u3o}51qq4,3k?801v49b2{qag`<"
		// @0A0: invokestatic game.C_100154_sl.func_105325_z(java.lang.String)char[]
		// @0A3: invokestatic game.C_100154_sl.func_105323_z(char[])java.lang.String
		// @0A6: aastore
		// @0A7: dup
		// @0A8: iconst_3
		// @0A9: ldc "~u3o}$5n%}~u2oz1pg=8!$p>.61v8>b6m#>'"
		// @0AB: invokestatic game.C_100154_sl.func_105325_z(java.lang.String)char[]
		// @0AE: invokestatic game.C_100154_sl.func_105323_z(char[])java.lang.String
		// @0B1: aastore
		// @0B2: dup
		// @0B3: iconst_4
		// @0B4: ldc "~u3o}51qq1##g#8&p`(}~u2o"
		// @0B6: invokestatic game.C_100154_sl.func_105325_z(java.lang.String)char[]
		// @0B9: invokestatic game.C_100154_sl.func_105323_z(char[])java.lang.String
		// @0BC: aastore
		// @0BD: dup
		// @0BE: iconst_5
		// @0BF: ldc "~u3o}51qq0'<v49b2{qag`<"
		// @0C1: invokestatic game.C_100154_sl.func_105325_z(java.lang.String)char[]
		// @0C4: invokestatic game.C_100154_sl.func_105323_z(char[])java.lang.String
		// @0C7: aastore
		// @0C8: dup
		// @0C9: bipush 6 (0x06)
		// @0CB: ldc "~u3o}!?w=9,wvq9-4e4}~u2oz1po8.19n4"
		// @0CD: invokestatic game.C_100154_sl.func_105325_z(java.lang.String)char[]
		// @0D0: invokestatic game.C_100154_sl.func_105323_z(char[])java.lang.String
		// @0D3: aastore
		// @0D4: dup
		// @0D5: bipush 7 (0x07)
		// @0D7: ldc "~u3o}51qq-+5p28&p`(}~u2o"
		// @0D9: invokestatic game.C_100154_sl.func_105325_z(java.lang.String)char[]
		// @0DC: invokestatic game.C_100154_sl.func_105323_z(char[])java.lang.String
		// @0DF: aastore
		// @0E0: dup
		// @0E1: bipush 8 (0x08)
		// @0E3: ldc "~u3o}18m#)o3k#>79v49b2g2<7#gq2$p>tm|"
		// @0E5: invokestatic game.C_100154_sl.func_105325_z(java.lang.String)char[]
		// @0E8: invokestatic game.C_100154_sl.func_105323_z(char[])java.lang.String
		// @0EB: aastore
		// @0EC: dup
		// @0ED: bipush 9 (0x09)
		// @0EF: ldc "~u3o}51qq;01e68&p`(}~u2o"
		// @0F1: invokestatic game.C_100154_sl.func_105325_z(java.lang.String)char[]
		// @0F4: invokestatic game.C_100154_sl.func_105323_z(char[])java.lang.String
		// @0F7: aastore
		// @0F8: dup
		// @0F9: bipush 10 (0x0A)
		// @0FB: ldc "~u3o}51qq8.5a%/-3w%8&p`(}~u2o"
		// @0FD: invokestatic game.C_100154_sl.func_105325_z(java.lang.String)char[]
		// @100: invokestatic game.C_100154_sl.func_105323_z(char[])java.lang.String
		// @103: aastore
		// @104: dup
		// @105: bipush 11 (0x0B)
		// @107: ldc "~u3o}$5n=}+>v>}~u2oz1pj4<4)\"71#;"
		// @109: invokestatic game.C_100154_sl.func_105325_z(java.lang.String)char[]
		// @10C: invokestatic game.C_100154_sl.func_105323_z(char[])java.lang.String
		// @10F: aastore
		// @110: dup
		// @111: bipush 12 (0x0C)
		// @113: ldc "~u3o}51qq-'\"d>/#$g5} )\"mxrn%\"}*5c'$b7w?"
		// @115: invokestatic game.C_100154_sl.func_105325_z(java.lang.String)char[]
		// @118: invokestatic game.C_100154_sl.func_105323_z(char[])java.lang.String
		// @11B: aastore
		// @11C: dup
		// @11D: bipush 13 (0x0D)
		// @11F: ldc "~u3o}&5a89'4\"%2b3c%>*p>tm|wqq.*5n="
		// @121: invokestatic game.C_100154_sl.func_105325_z(java.lang.String)char[]
		// @124: invokestatic game.C_100154_sl.func_105323_z(char[])java.lang.String
		// @127: aastore
		// @128: dup
		// @129: bipush 14 (0x0E)
		// @12B: ldc "~u3o}$5n=}$?w=}-6\"mxrn%\"}#\"v81.5p("
		// @12D: invokestatic game.C_100154_sl.func_105325_z(java.lang.String)char[]
		// @130: invokestatic game.C_100154_sl.func_105323_z(char[])java.lang.String
		// @133: aastore
		// @134: dup
		// @135: bipush 15 (0x0F)
		// @137: ldc "~u3o}51qq.,9r49b2{qag`<"
		// @139: invokestatic game.C_100154_sl.func_105325_z(java.lang.String)char[]
		// @13C: invokestatic game.C_100154_sl.func_105323_z(char[])java.lang.String
		// @13F: aastore
		// @140: dup
		// @141: bipush 16 (0x10)
		// @143: ldc "~u3o}%?vq801q49b2{qag`<"
		// @145: invokestatic game.C_100154_sl.func_105325_z(java.lang.String)char[]
		// @148: invokestatic game.C_100154_sl.func_105323_z(char[])java.lang.String
		// @14B: aastore
		// @14C: dup
		// @14D: bipush 17 (0x11)
		// @14F: ldc "~u3o}51qq)#%e9)b1`>(6pv98b m&80pm7}.9e9)b2{qag`<"
		// @151: invokestatic game.C_100154_sl.func_105325_z(java.lang.String)char[]
		// @154: invokestatic game.C_100154_sl.func_105323_z(char[])java.lang.String
		// @157: aastore
		// @158: dup
		// @159: bipush 18 (0x12)
		// @15B: ldc "~u3o}51qq+# m#415fq?;p>tm|"
		// @15D: invokestatic game.C_100154_sl.func_105325_z(java.lang.String)char[]
		// @160: invokestatic game.C_100154_sl.func_105323_z(char[])java.lang.String
		// @163: aastore
		// @164: dup
		// @165: bipush 19 (0x13)
		// @167: ldc "~u3o}51qq8,7w=;'4\"3$bl'ace#\"#2!;g%}1 p4<&"
		// @169: invokestatic game.C_100154_sl.func_105325_z(java.lang.String)char[]
		// @16C: invokestatic game.C_100154_sl.func_105323_z(char[])java.lang.String
		// @16F: aastore
		// @170: dup
		// @171: bipush 20 (0x14)
		// @173: ldc "~u3o}%?vq<b p4.'>vq;0?oqag`<"
		// @175: invokestatic game.C_100154_sl.func_105325_z(java.lang.String)char[]
		// @178: invokestatic game.C_100154_sl.func_105323_z(char[])java.lang.String
		// @17B: aastore
		// @17C: dup
		// @17D: bipush 21 (0x15)
		// @17F: ldc "~u3o}!1w656p>tm|wqq1+7j%3+>e"
		// @181: invokestatic game.C_100154_sl.func_105325_z(java.lang.String)char[]
		// @184: invokestatic game.C_100154_sl.func_105323_z(char[])java.lang.String
		// @187: aastore
		// @188: dup
		// @189: bipush 22 (0x16)
		// @18B: ldc ""
		// @18D: aastore
		// @18E: dup
		// @18F: bipush 23 (0x17)
		// @191: ldc ""
		// @193: aastore
		// @194: dup
		// @195: bipush 24 (0x18)
		// @197: ldc ""
		// @199: aastore
		// @19A: dup
		// @19B: bipush 25 (0x19)
		// @19D: ldc ""
		// @19F: aastore
		// @1A0: dup
		// @1A1: bipush 26 (0x1A)
		// @1A3: ldc "~u3o}.?m:8&pf>*,pv98b2c#/'<\">;bl'ace#\"$16\"cq:7>"
		// @1A5: invokestatic game.C_100154_sl.func_105325_z(java.lang.String)char[]
		// @1A8: invokestatic game.C_100154_sl.func_105323_z(char[])java.lang.String
		// @1AB: aastore
		// @1AC: dup
		// @1AD: bipush 27 (0x1B)
		// @1AF: ldc "~u3o}0?f4}~u2oz1pq98.<"
		// @1B1: invokestatic game.C_100154_sl.func_105325_z(java.lang.String)char[]
		// @1B4: invokestatic game.C_100154_sl.func_105323_z(char[])java.lang.String
		// @1B7: aastore
		// @1B8: dup
		// @1B9: bipush 28 (0x1C)
		// @1BB: ldc "~u3o}*1fq9'1v9}01k?8&pf>*,pd#2/p>tm|"
		// @1BD: invokestatic game.C_100154_sl.func_105325_z(java.lang.String)char[]
		// @1C0: invokestatic game.C_100154_sl.func_105323_z(char[])java.lang.String
		// @1C3: aastore
		// @1C4: dup
		// @1C5: bipush 29 (0x1D)
		// @1C7: ldc "~u3o}51qq)7\"l49b9l%2b#n0:b2{qag`<"
		// @1C9: invokestatic game.C_100154_sl.func_105325_z(java.lang.String)char[]
		// @1CC: invokestatic game.C_100154_sl.func_105323_z(char[])java.lang.String
		// @1CF: aastore
		// @1D0: dup
		// @1D1: bipush 30 (0x1E)
		// @1D3: ldc "~u3o}1$c#8&pk?)-p>tm|wqq.7>\"720pv>2b<m?:"
		// @1D5: invokestatic game.C_100154_sl.func_105325_z(java.lang.String)char[]
		// @1D8: invokestatic game.C_100154_sl.func_105323_z(char[])java.lang.String
		// @1DB: aastore
		// @1DC: dup
		// @1DD: bipush 31 (0x1F)
		// @1DF: ldc "~u3o}51qq<6?o8.'4\"3$bl'ac"
		// @1E1: invokestatic game.C_100154_sl.func_105325_z(java.lang.String)char[]
		// @1E4: invokestatic game.C_100154_sl.func_105323_z(char[])java.lang.String
		// @1E7: aastore
		// @1E8: dup
		// @1E9: bipush 32 (0x20)
		// @1EB: ldc "~u3o}$5n=}6?\"mxrn%\"}(%f68/5l%"
		// @1ED: invokestatic game.C_100154_sl.func_105325_z(java.lang.String)char[]
		// @1F0: invokestatic game.C_100154_sl.func_105323_z(char[])java.lang.String
		// @1F3: aastore
		// @1F4: dup
		// @1F5: bipush 33 (0x21)
		// @1F7: ldc "~u3o}51qq1-#vq**5lqag`<v.b\"m26'$\"727>fq46#\"<<0;"
		// @1F9: invokestatic game.C_100154_sl.func_105325_z(java.lang.String)char[]
		// @1FC: invokestatic game.C_100154_sl.func_105323_z(char[])java.lang.String
		// @1FF: aastore
		// @200: dup
		// @201: bipush 34 (0x22)
		// @203: ldc "~u3o}$1k=8&pv>}#&m89bl'ace#\"<41#k=8"
		// @205: invokestatic game.C_100154_sl.func_105325_z(java.lang.String)char[]
		// @208: invokestatic game.C_100154_sl.func_105323_z(char[])java.lang.String
		// @20B: aastore
		// @20C: dup
		// @20D: bipush 35 (0x23)
		// @20F: ldc "~u3o}05a4445fq.'\"g?46)\"7/-=\"mxrn"
		// @211: invokestatic game.C_100154_sl.func_105325_z(java.lang.String)char[]
		// @214: invokestatic game.C_100154_sl.func_105323_z(char[])java.lang.String
		// @217: aastore
		// @218: putstatic java.lang.String[] game.C_100154_sl.field_105334_c
		// @21B: iconst_0
		// @21C: putstatic boolean game.C_100154_sl.field_105333_b
		// @21F: return
	}
	
	private static char[] func_105325_z(String arg0)
	{
		// @00: aload_0
		// @01: invokevirtual java.lang.String.toCharArray()char[]
		// @04: dup
		// @05: arraylength
		// @06: iconst_2
		// @07: if_icmpge @13
		// @0A: dup
		// @0B: iconst_0
		// @0C: dup2
		// @0D: caload
		// @0E: bipush 93 (0x5D)
		// @10: ixor
		// @11: i2c
		// @12: castore
		// @13: areturn
	}
	
	private static String func_105323_z(char[] arg0)
	{
		// @00: aload_0
		// @01: dup
		// @02: arraylength
		// @03: swap
		// @04: iconst_0
		// @05: istore_1
		// @06: goto @4B
		// @09: dup
		// @0A: iload_1
		// @0B: dup2
		// @0C: caload
		// @0D: iload_1
		// @0E: iconst_5
		// @0F: irem
		// @10: tableswitch def: @43, for 0: @30, for 1: @35, for 2: @3A, for 3: @3E
		// @30: bipush 66 (0x42)
		// @32: goto @45
		// @35: bipush 80 (0x50)
		// @37: goto @45
		// @3A: iconst_2
		// @3B: goto @45
		// @3E: bipush 81 (0x51)
		// @40: goto @45
		// @43: bipush 93 (0x5D)
		// @45: ixor
		// @46: i2c
		// @47: castore
		// @48: iinc #1 +1
		// @4B: swap
		// @4C: dup_x1
		// @4D: iload_1
		// @4E: if_icmpgt @09
		// @51: new java.lang.String
		// @54: dup_x1
		// @55: swap
		// @56: invokespecial java.lang.String.<init>(char[])void
		// @59: invokevirtual java.lang.String.intern()java.lang.String
		// @5C: areturn
	}
}
