package game;

final class C_100131_te extends C_100158_da
{
	static String field_100760_o;
	static String field_100757_q;
	static C_100037_wb field_100759_n;
	static byte[] field_100763_j;
	static boolean field_100758_p;
	int field_100761_l;
	byte[] field_100765_k;
	static C_100268_mk field_100762_m;
	private static final String[] field_100764_z;
	
	public static void func_100756_e(int arg0)
	{
		// @00: aconst_null
		// @01: putstatic java.lang.String game.C_100131_te.field_100757_q
		// @04: aconst_null
		// @05: putstatic game.C_100037_wb game.C_100131_te.field_100759_n
		// @08: aconst_null
		// @09: putstatic game.C_100268_mk game.C_100131_te.field_100762_m
		// @0C: iload_0
		// @0D: sipush -29102 (0x8E52)
		// @10: if_icmpeq @14
		// @13: return
		// @14: aconst_null
		// @15: putstatic java.lang.String game.C_100131_te.field_100760_o
		// @18: aconst_null
		// @19: putstatic byte[] game.C_100131_te.field_100763_j
		// @1C: goto @40
		// @1F: astore_1
		// @20: aload_1
		// @21: new java.lang.StringBuilder
		// @24: dup
		// @25: invokespecial java.lang.StringBuilder.<init>()void
		// @28: getstatic java.lang.String[] game.C_100131_te.field_100764_z
		// @2B: iconst_0
		// @2C: aaload
		// @2D: invokevirtual java.lang.StringBuilder.append(java.lang.String)java.lang.StringBuilder
		// @30: iload_0
		// @31: invokevirtual java.lang.StringBuilder.append(int)java.lang.StringBuilder
		// @34: bipush 41 (0x29)
		// @36: invokevirtual java.lang.StringBuilder.append(char)java.lang.StringBuilder
		// @39: invokevirtual java.lang.StringBuilder.toString()java.lang.String
		// @3C: invokestatic game.C_100181_cf.func_105695_a(java.lang.Throwable, java.lang.String)game.C_100170_cm
		// @3F: athrow
		// @40: return
	}
	
	static final int func_100753_a(byte arg0)
	{
		// @00: iload_0
		// @01: bipush 109 (0x6D)
		// @03: if_icmpge @11
		// @06: aconst_null
		// @07: checkcast byte[]
		// @0A: putstatic byte[] game.C_100131_te.field_100763_j
		// @0D: goto @11
		// @10: athrow
		// @11: ldc2_w 1000000000
		// @14: getstatic long game.C_100042_we.field_104142_i
		// @17: ldiv
		// @18: l2i
		// @19: ireturn
		// @1A: astore_1
		// @1B: aload_1
		// @1C: new java.lang.StringBuilder
		// @1F: dup
		// @20: invokespecial java.lang.StringBuilder.<init>()void
		// @23: getstatic java.lang.String[] game.C_100131_te.field_100764_z
		// @26: iconst_4
		// @27: aaload
		// @28: invokevirtual java.lang.StringBuilder.append(java.lang.String)java.lang.StringBuilder
		// @2B: iload_0
		// @2C: invokevirtual java.lang.StringBuilder.append(int)java.lang.StringBuilder
		// @2F: bipush 41 (0x29)
		// @31: invokevirtual java.lang.StringBuilder.append(char)java.lang.StringBuilder
		// @34: invokevirtual java.lang.StringBuilder.toString()java.lang.String
		// @37: invokestatic game.C_100181_cf.func_105695_a(java.lang.Throwable, java.lang.String)game.C_100170_cm
		// @3A: athrow
	}
	
	C_100131_te(byte[] arg0)
	{
		// @00: aload_0
		// @01: invokespecial game.C_100158_da.<init>()void
		// @04: aload_0
		// @05: aload_1
		// @06: putfield byte[] game.C_100131_te.field_100765_k
		// @09: goto @3E
		// @0C: astore_2
		// @0D: aload_2
		// @0E: new java.lang.StringBuilder
		// @11: dup
		// @12: invokespecial java.lang.StringBuilder.<init>()void
		// @15: getstatic java.lang.String[] game.C_100131_te.field_100764_z
		// @18: iconst_2
		// @19: aaload
		// @1A: invokevirtual java.lang.StringBuilder.append(java.lang.String)java.lang.StringBuilder
		// @1D: aload_1
		// @1E: ifnull @2A
		// @21: getstatic java.lang.String[] game.C_100131_te.field_100764_z
		// @24: iconst_1
		// @25: aaload
		// @26: goto @2F
		// @29: athrow
		// @2A: getstatic java.lang.String[] game.C_100131_te.field_100764_z
		// @2D: iconst_3
		// @2E: aaload
		// @2F: invokevirtual java.lang.StringBuilder.append(java.lang.String)java.lang.StringBuilder
		// @32: bipush 41 (0x29)
		// @34: invokevirtual java.lang.StringBuilder.append(char)java.lang.StringBuilder
		// @37: invokevirtual java.lang.StringBuilder.toString()java.lang.String
		// @3A: invokestatic game.C_100181_cf.func_105695_a(java.lang.Throwable, java.lang.String)game.C_100170_cm
		// @3D: athrow
		// @3E: return
	}
	
	static
	{
		// @00: iconst_5
		// @01: anewarray java.lang.String
		// @04: dup
		// @05: iconst_0
		// @06: ldc "1 %<i"
		// @08: invokestatic game.C_100131_te.func_100755_z(java.lang.String)char[]
		// @0B: invokestatic game.C_100131_te.func_100754_z(char[])java.lang.String
		// @0E: aastore
		// @0F: dup
		// @10: iconst_1
		// @11: ldc ">k%S<"
		// @13: invokestatic game.C_100131_te.func_100755_z(java.lang.String)char[]
		// @16: invokestatic game.C_100131_te.func_100754_z(char[])java.lang.String
		// @19: aastore
		// @1A: dup
		// @1B: iconst_2
		// @1C: ldc "1 %A(+,\u007fCi"
		// @1E: invokestatic game.C_100131_te.func_100755_z(java.lang.String)char[]
		// @21: invokestatic game.C_100131_te.func_100754_z(char[])java.lang.String
		// @24: aastore
		// @25: dup
		// @26: iconst_3
		// @27: ldc "+0g\u0011"
		// @29: invokestatic game.C_100131_te.func_100755_z(java.lang.String)char[]
		// @2C: invokestatic game.C_100131_te.func_100754_z(char[])java.lang.String
		// @2F: aastore
		// @30: dup
		// @31: iconst_4
		// @32: ldc "1 %?i"
		// @34: invokestatic game.C_100131_te.func_100755_z(java.lang.String)char[]
		// @37: invokestatic game.C_100131_te.func_100754_z(char[])java.lang.String
		// @3A: aastore
		// @3B: putstatic java.lang.String[] game.C_100131_te.field_100764_z
		// @3E: ldc "\u0004ec\u0014&-6h\u00123 ed\u001bay`;Ca-$x]#  e] &-b\u00187 !*"
		// @40: invokestatic game.C_100131_te.func_100755_z(java.lang.String)char[]
		// @43: invokestatic game.C_100131_te.func_100754_z(char[])java.lang.String
		// @46: putstatic java.lang.String game.C_100131_te.field_100760_o
		// @49: iconst_0
		// @4A: putstatic boolean game.C_100131_te.field_100758_p
		// @4D: ldc "\u00140b\u001e*e\u0006c\u001c5e)d\u001f#<"
		// @4F: invokestatic game.C_100131_te.func_100755_z(java.lang.String)char[]
		// @52: invokestatic game.C_100131_te.func_100754_z(char[])java.lang.String
		// @55: putstatic java.lang.String game.C_100131_te.field_100757_q
		// @58: new game.C_100268_mk
		// @5B: dup
		// @5C: invokespecial game.C_100268_mk.<init>()void
		// @5F: putstatic game.C_100268_mk game.C_100131_te.field_100762_m
		// @62: return
	}
	
	private static char[] func_100755_z(String arg0)
	{
		// @00: aload_0
		// @01: invokevirtual java.lang.String.toCharArray()char[]
		// @04: dup
		// @05: arraylength
		// @06: iconst_2
		// @07: if_icmpge @13
		// @0A: dup
		// @0B: iconst_0
		// @0C: dup2
		// @0D: caload
		// @0E: bipush 65 (0x41)
		// @10: ixor
		// @11: i2c
		// @12: castore
		// @13: areturn
	}
	
	private static String func_100754_z(char[] arg0)
	{
		// @00: aload_0
		// @01: dup
		// @02: arraylength
		// @03: swap
		// @04: iconst_0
		// @05: istore_1
		// @06: goto @4C
		// @09: dup
		// @0A: iload_1
		// @0B: dup2
		// @0C: caload
		// @0D: iload_1
		// @0E: iconst_5
		// @0F: irem
		// @10: tableswitch def: @44, for 0: @30, for 1: @35, for 2: @3A, for 3: @3F
		// @30: bipush 69 (0x45)
		// @32: goto @46
		// @35: bipush 69 (0x45)
		// @37: goto @46
		// @3A: bipush 11 (0x0B)
		// @3C: goto @46
		// @3F: bipush 125 (0x7D)
		// @41: goto @46
		// @44: bipush 65 (0x41)
		// @46: ixor
		// @47: i2c
		// @48: castore
		// @49: iinc #1 +1
		// @4C: swap
		// @4D: dup_x1
		// @4E: iload_1
		// @4F: if_icmpgt @09
		// @52: new java.lang.String
		// @55: dup_x1
		// @56: swap
		// @57: invokespecial java.lang.String.<init>(char[])void
		// @5A: invokevirtual java.lang.String.intern()java.lang.String
		// @5D: areturn
	}
}
