package game;

final class C_100122_em extends C_100302_ka
{
	private C_100302_ka field_102070_dc;
	static String field_102076_fc;
	static String field_102079_Vb;
	static int[][] field_102073_Xb;
	private C_100302_ka field_102082_cc;
	static String field_102072_Zb;
	static int field_102078_Ub;
	static int field_102080_ac;
	static C_100037_wb[] field_102075_ec;
	static C_100302_ka field_102081_bc;
	static int[] field_102077_Wb;
	static String field_102074_Yb;
	private static final String[] field_102071_gc;
	
	private C_100122_em(long arg0, C_100302_ka arg1, C_100302_ka arg2, String arg3)
	{
		// @00: aload_0
		// @01: lload_1
		// @02: aconst_null
		// @03: invokespecial game.C_100302_ka.<init>(long, game.C_100302_ka)void
		// @06: aload_0
		// @07: new game.C_100302_ka
		// @0A: dup
		// @0B: lconst_0
		// @0C: aload_3
		// @0D: invokespecial game.C_100302_ka.<init>(long, game.C_100302_ka)void
		// @10: putfield game.C_100302_ka game.C_100122_em.field_102070_dc
		// @13: aload_0
		// @14: new game.C_100302_ka
		// @17: dup
		// @18: lconst_0
		// @19: aload #4
		// @1B: invokespecial game.C_100302_ka.<init>(long, game.C_100302_ka)void
		// @1E: putfield game.C_100302_ka game.C_100122_em.field_102082_cc
		// @21: aload_0
		// @22: getfield game.C_100302_ka game.C_100122_em.field_102082_cc
		// @25: aload #5
		// @27: putfield java.lang.String game.C_100302_ka.field_101890_ab
		// @2A: aload_0
		// @2B: bipush -94 (0xA2)
		// @2D: aload_0
		// @2E: getfield game.C_100302_ka game.C_100122_em.field_102070_dc
		// @31: invokevirtual game.C_100122_em.func_101824_b(int, game.C_100302_ka)void
		// @34: aload_0
		// @35: bipush -71 (0xB9)
		// @37: aload_0
		// @38: getfield game.C_100302_ka game.C_100122_em.field_102082_cc
		// @3B: invokevirtual game.C_100122_em.func_101824_b(int, game.C_100302_ka)void
		// @3E: aload_0
		// @3F: iconst_0
		// @40: invokevirtual game.C_100122_em.func_101821_k(int)void
		// @43: goto @B9
		// @46: astore #6
		// @48: aload #6
		// @4A: new java.lang.StringBuilder
		// @4D: dup
		// @4E: invokespecial java.lang.StringBuilder.<init>()void
		// @51: getstatic java.lang.String[] game.C_100122_em.field_102071_gc
		// @54: iconst_4
		// @55: aaload
		// @56: invokevirtual java.lang.StringBuilder.append(java.lang.String)java.lang.StringBuilder
		// @59: lload_1
		// @5A: invokevirtual java.lang.StringBuilder.append(long)java.lang.StringBuilder
		// @5D: bipush 44 (0x2C)
		// @5F: invokevirtual java.lang.StringBuilder.append(char)java.lang.StringBuilder
		// @62: aload_3
		// @63: ifnull @6F
		// @66: getstatic java.lang.String[] game.C_100122_em.field_102071_gc
		// @69: iconst_3
		// @6A: aaload
		// @6B: goto @74
		// @6E: athrow
		// @6F: getstatic java.lang.String[] game.C_100122_em.field_102071_gc
		// @72: iconst_5
		// @73: aaload
		// @74: invokevirtual java.lang.StringBuilder.append(java.lang.String)java.lang.StringBuilder
		// @77: bipush 44 (0x2C)
		// @79: invokevirtual java.lang.StringBuilder.append(char)java.lang.StringBuilder
		// @7C: aload #4
		// @7E: ifnull @8A
		// @81: getstatic java.lang.String[] game.C_100122_em.field_102071_gc
		// @84: iconst_3
		// @85: aaload
		// @86: goto @8F
		// @89: athrow
		// @8A: getstatic java.lang.String[] game.C_100122_em.field_102071_gc
		// @8D: iconst_5
		// @8E: aaload
		// @8F: invokevirtual java.lang.StringBuilder.append(java.lang.String)java.lang.StringBuilder
		// @92: bipush 44 (0x2C)
		// @94: invokevirtual java.lang.StringBuilder.append(char)java.lang.StringBuilder
		// @97: aload #5
		// @99: ifnull @A5
		// @9C: getstatic java.lang.String[] game.C_100122_em.field_102071_gc
		// @9F: iconst_3
		// @A0: aaload
		// @A1: goto @AA
		// @A4: athrow
		// @A5: getstatic java.lang.String[] game.C_100122_em.field_102071_gc
		// @A8: iconst_5
		// @A9: aaload
		// @AA: invokevirtual java.lang.StringBuilder.append(java.lang.String)java.lang.StringBuilder
		// @AD: bipush 41 (0x29)
		// @AF: invokevirtual java.lang.StringBuilder.append(char)java.lang.StringBuilder
		// @B2: invokevirtual java.lang.StringBuilder.toString()java.lang.String
		// @B5: invokestatic game.C_100181_cf.func_105695_a(java.lang.Throwable, java.lang.String)game.C_100170_cm
		// @B8: athrow
		// @B9: return
	}
	
	final void func_102065_a(int arg0, int arg1, int arg2, int arg3, int arg4, int arg5)
	{
		// @00: bipush -17 (0xEF)
		// @02: bipush -55 (0xC9)
		// @04: iload_2
		// @05: isub
		// @06: bipush 58 (0x3A)
		// @08: idiv
		// @09: irem
		// @0A: istore #7
		// @0C: aload_0
		// @0D: iload #6
		// @0F: iload #5
		// @11: iconst_m1
		// @12: iload_1
		// @13: iload #4
		// @15: invokevirtual game.C_100122_em.func_101825_a(int, int, int, int, int)void
		// @18: aload_0
		// @19: iload_3
		// @1A: iconst_1
		// @1B: invokespecial game.C_100122_em.func_102069_a(int, boolean)void
		// @1E: goto @74
		// @21: astore #7
		// @23: aload #7
		// @25: new java.lang.StringBuilder
		// @28: dup
		// @29: invokespecial java.lang.StringBuilder.<init>()void
		// @2C: getstatic java.lang.String[] game.C_100122_em.field_102071_gc
		// @2F: iconst_0
		// @30: aaload
		// @31: invokevirtual java.lang.StringBuilder.append(java.lang.String)java.lang.StringBuilder
		// @34: iload_1
		// @35: invokevirtual java.lang.StringBuilder.append(int)java.lang.StringBuilder
		// @38: bipush 44 (0x2C)
		// @3A: invokevirtual java.lang.StringBuilder.append(char)java.lang.StringBuilder
		// @3D: iload_2
		// @3E: invokevirtual java.lang.StringBuilder.append(int)java.lang.StringBuilder
		// @41: bipush 44 (0x2C)
		// @43: invokevirtual java.lang.StringBuilder.append(char)java.lang.StringBuilder
		// @46: iload_3
		// @47: invokevirtual java.lang.StringBuilder.append(int)java.lang.StringBuilder
		// @4A: bipush 44 (0x2C)
		// @4C: invokevirtual java.lang.StringBuilder.append(char)java.lang.StringBuilder
		// @4F: iload #4
		// @51: invokevirtual java.lang.StringBuilder.append(int)java.lang.StringBuilder
		// @54: bipush 44 (0x2C)
		// @56: invokevirtual java.lang.StringBuilder.append(char)java.lang.StringBuilder
		// @59: iload #5
		// @5B: invokevirtual java.lang.StringBuilder.append(int)java.lang.StringBuilder
		// @5E: bipush 44 (0x2C)
		// @60: invokevirtual java.lang.StringBuilder.append(char)java.lang.StringBuilder
		// @63: iload #6
		// @65: invokevirtual java.lang.StringBuilder.append(int)java.lang.StringBuilder
		// @68: bipush 41 (0x29)
		// @6A: invokevirtual java.lang.StringBuilder.append(char)java.lang.StringBuilder
		// @6D: invokevirtual java.lang.StringBuilder.toString()java.lang.String
		// @70: invokestatic game.C_100181_cf.func_105695_a(java.lang.Throwable, java.lang.String)game.C_100170_cm
		// @73: athrow
		// @74: return
	}
	
	public static void func_102066_f(byte arg0)
	{
		// @00: iload_0
		// @01: bipush -51 (0xCD)
		// @03: if_icmple @0F
		// @06: bipush -77 (0xB3)
		// @08: putstatic int game.C_100122_em.field_102078_Ub
		// @0B: goto @0F
		// @0E: athrow
		// @0F: aconst_null
		// @10: putstatic game.C_100037_wb[] game.C_100122_em.field_102075_ec
		// @13: aconst_null
		// @14: putstatic java.lang.String game.C_100122_em.field_102076_fc
		// @17: aconst_null
		// @18: putstatic java.lang.String game.C_100122_em.field_102074_Yb
		// @1B: aconst_null
		// @1C: putstatic int[] game.C_100122_em.field_102077_Wb
		// @1F: aconst_null
		// @20: putstatic java.lang.String game.C_100122_em.field_102072_Zb
		// @23: aconst_null
		// @24: putstatic java.lang.String game.C_100122_em.field_102079_Vb
		// @27: aconst_null
		// @28: putstatic game.C_100302_ka game.C_100122_em.field_102081_bc
		// @2B: aconst_null
		// @2C: checkcast int[][]
		// @2F: putstatic int[][] game.C_100122_em.field_102073_Xb
		// @32: goto @56
		// @35: astore_1
		// @36: aload_1
		// @37: new java.lang.StringBuilder
		// @3A: dup
		// @3B: invokespecial java.lang.StringBuilder.<init>()void
		// @3E: getstatic java.lang.String[] game.C_100122_em.field_102071_gc
		// @41: iconst_2
		// @42: aaload
		// @43: invokevirtual java.lang.StringBuilder.append(java.lang.String)java.lang.StringBuilder
		// @46: iload_0
		// @47: invokevirtual java.lang.StringBuilder.append(int)java.lang.StringBuilder
		// @4A: bipush 41 (0x29)
		// @4C: invokevirtual java.lang.StringBuilder.append(char)java.lang.StringBuilder
		// @4F: invokevirtual java.lang.StringBuilder.toString()java.lang.String
		// @52: invokestatic game.C_100181_cf.func_105695_a(java.lang.Throwable, java.lang.String)game.C_100170_cm
		// @55: athrow
		// @56: return
	}
	
	private final void func_102069_a(int arg0, boolean arg1)
	{
		// @00: aload_0
		// @01: getfield game.C_100302_ka game.C_100122_em.field_102070_dc
		// @04: iconst_0
		// @05: aload_0
		// @06: getfield int game.C_100122_em.field_101848_lb
		// @09: iconst_m1
		// @0A: iconst_0
		// @0B: aload_0
		// @0C: getfield game.C_100302_ka game.C_100122_em.field_102070_dc
		// @0F: ldc 218000 (0x35390)
		// @11: invokevirtual game.C_100302_ka.func_101818_j(int)int
		// @14: invokevirtual game.C_100302_ka.func_101825_a(int, int, int, int, int)void
		// @17: aload_0
		// @18: getfield game.C_100302_ka game.C_100122_em.field_102070_dc
		// @1B: getfield int game.C_100302_ka.field_101886_Kb
		// @1E: iload_1
		// @1F: ineg
		// @20: isub
		// @21: istore_3
		// @22: iload_2
		// @23: iconst_1
		// @24: if_icmpeq @28
		// @27: return
		// @28: aload_0
		// @29: getfield game.C_100302_ka game.C_100122_em.field_102082_cc
		// @2C: iload_3
		// @2D: aload_0
		// @2E: getfield int game.C_100122_em.field_101848_lb
		// @31: iconst_m1
		// @32: iconst_0
		// @33: aload_0
		// @34: getfield int game.C_100122_em.field_101886_Kb
		// @37: iload_3
		// @38: isub
		// @39: invokevirtual game.C_100302_ka.func_101825_a(int, int, int, int, int)void
		// @3C: goto @6A
		// @3F: astore_3
		// @40: aload_3
		// @41: new java.lang.StringBuilder
		// @44: dup
		// @45: invokespecial java.lang.StringBuilder.<init>()void
		// @48: getstatic java.lang.String[] game.C_100122_em.field_102071_gc
		// @4B: bipush 6 (0x06)
		// @4D: aaload
		// @4E: invokevirtual java.lang.StringBuilder.append(java.lang.String)java.lang.StringBuilder
		// @51: iload_1
		// @52: invokevirtual java.lang.StringBuilder.append(int)java.lang.StringBuilder
		// @55: bipush 44 (0x2C)
		// @57: invokevirtual java.lang.StringBuilder.append(char)java.lang.StringBuilder
		// @5A: iload_2
		// @5B: invokevirtual java.lang.StringBuilder.append(boolean)java.lang.StringBuilder
		// @5E: bipush 41 (0x29)
		// @60: invokevirtual java.lang.StringBuilder.append(char)java.lang.StringBuilder
		// @63: invokevirtual java.lang.StringBuilder.toString()java.lang.String
		// @66: invokestatic game.C_100181_cf.func_105695_a(java.lang.Throwable, java.lang.String)game.C_100170_cm
		// @69: athrow
		// @6A: return
	}
	
	static final C_100098_h func_102067_a(boolean arg0, boolean arg1, boolean arg2, int arg3, boolean arg4, int arg5)
	{
		// @000: aconst_null
		// @001: astore #6
		// @003: getstatic game.C_100201_qj game.C_100252_pn.field_105504_l
		// @006: getfield game.C_100005_fk game.C_100201_qj.field_105892_p
		// @009: ifnonnull @010
		// @00C: goto @04D
		// @00F: athrow
		// @010: new game.C_100301_kb
		// @013: dup
		// @014: getstatic game.C_100201_qj game.C_100252_pn.field_105504_l
		// @017: getfield game.C_100005_fk game.C_100201_qj.field_105892_p
		// @01A: sipush 5200 (0x1450)
		// @01D: iconst_0
		// @01E: invokespecial game.C_100301_kb.<init>(game.C_100005_fk, int, int)void
		// @021: putstatic game.C_100301_kb game.C_100266_me.field_106657_h
		// @024: getstatic game.C_100201_qj game.C_100252_pn.field_105504_l
		// @027: aconst_null
		// @028: putfield game.C_100005_fk game.C_100201_qj.field_105892_p
		// @02B: new game.C_100091_m
		// @02E: dup
		// @02F: sipush 255 (0x00FF)
		// @032: getstatic game.C_100301_kb game.C_100266_me.field_106657_h
		// @035: new game.C_100301_kb
		// @038: dup
		// @039: getstatic game.C_100201_qj game.C_100252_pn.field_105504_l
		// @03C: getfield game.C_100005_fk game.C_100201_qj.field_105888_t
		// @03F: sipush 12000 (0x2EE0)
		// @042: iconst_0
		// @043: invokespecial game.C_100301_kb.<init>(game.C_100005_fk, int, int)void
		// @046: ldc 2097152 (0x200000)
		// @048: invokespecial game.C_100091_m.<init>(int, game.C_100301_kb, game.C_100301_kb, int)void
		// @04B: astore #6
		// @04D: aconst_null
		// @04E: astore #7
		// @050: aconst_null
		// @051: getstatic game.C_100301_kb game.C_100266_me.field_106657_h
		// @054: if_acmpne @05B
		// @057: goto @0B4
		// @05A: athrow
		// @05B: getstatic game.C_100301_kb[] game.C_100225_ah.field_106136_p
		// @05E: ifnull @065
		// @061: goto @072
		// @064: athrow
		// @065: getstatic game.C_100201_qj game.C_100252_pn.field_105504_l
		// @068: getfield game.C_100005_fk[] game.C_100201_qj.field_105883_h
		// @06B: arraylength
		// @06C: anewarray game.C_100301_kb
		// @06F: putstatic game.C_100301_kb[] game.C_100225_ah.field_106136_p
		// @072: aconst_null
		// @073: getstatic game.C_100301_kb[] game.C_100225_ah.field_106136_p
		// @076: iload_3
		// @077: aaload
		// @078: if_acmpne @0A0
		// @07B: getstatic game.C_100301_kb[] game.C_100225_ah.field_106136_p
		// @07E: iload_3
		// @07F: new game.C_100301_kb
		// @082: dup
		// @083: getstatic game.C_100201_qj game.C_100252_pn.field_105504_l
		// @086: getfield game.C_100005_fk[] game.C_100201_qj.field_105883_h
		// @089: iload_3
		// @08A: aaload
		// @08B: sipush 12000 (0x2EE0)
		// @08E: iconst_0
		// @08F: invokespecial game.C_100301_kb.<init>(game.C_100005_fk, int, int)void
		// @092: aastore
		// @093: getstatic game.C_100201_qj game.C_100252_pn.field_105504_l
		// @096: getfield game.C_100005_fk[] game.C_100201_qj.field_105883_h
		// @099: iload_3
		// @09A: aconst_null
		// @09B: aastore
		// @09C: goto @0A0
		// @09F: athrow
		// @0A0: new game.C_100091_m
		// @0A3: dup
		// @0A4: iload_3
		// @0A5: getstatic game.C_100301_kb game.C_100266_me.field_106657_h
		// @0A8: getstatic game.C_100301_kb[] game.C_100225_ah.field_106136_p
		// @0AB: iload_3
		// @0AC: aaload
		// @0AD: ldc 2097152 (0x200000)
		// @0AF: invokespecial game.C_100091_m.<init>(int, game.C_100301_kb, game.C_100301_kb, int)void
		// @0B2: astore #7
		// @0B4: getstatic game.C_100208_qg game.C_100271_mj.field_103440_O
		// @0B7: sipush 19286 (0x4B56)
		// @0BA: iload_1
		// @0BB: iload_3
		// @0BC: aload #7
		// @0BE: aload #6
		// @0C0: invokevirtual game.C_100208_qg.func_105953_a(int, boolean, int, game.C_100091_m, game.C_100091_m)game.C_100216_aj
		// @0C3: astore #8
		// @0C5: iload_0
		// @0C6: iconst_1
		// @0C7: if_icmpeq @0D5
		// @0CA: aconst_null
		// @0CB: checkcast java.lang.String
		// @0CE: putstatic java.lang.String game.C_100122_em.field_102079_Vb
		// @0D1: goto @0D5
		// @0D4: athrow
		// @0D5: iload_2
		// @0D6: ifne @0DD
		// @0D9: goto @0E5
		// @0DC: athrow
		// @0DD: aload #8
		// @0DF: sipush 1358 (0x054E)
		// @0E2: invokevirtual game.C_100216_aj.func_104440_c(int)void
		// @0E5: new game.C_100098_h
		// @0E8: dup
		// @0E9: aload #8
		// @0EB: iload #4
		// @0ED: iload #5
		// @0EF: invokespecial game.C_100098_h.<init>(game.C_100080_b, boolean, int)void
		// @0F2: areturn
		// @0F3: astore #6
		// @0F5: new java.lang.RuntimeException
		// @0F8: dup
		// @0F9: aload #6
		// @0FB: invokevirtual java.io.IOException.toString()java.lang.String
		// @0FE: invokespecial java.lang.RuntimeException.<init>(java.lang.String)void
		// @101: athrow
		// @102: astore #6
		// @104: aload #6
		// @106: new java.lang.StringBuilder
		// @109: dup
		// @10A: invokespecial java.lang.StringBuilder.<init>()void
		// @10D: getstatic java.lang.String[] game.C_100122_em.field_102071_gc
		// @110: iconst_1
		// @111: aaload
		// @112: invokevirtual java.lang.StringBuilder.append(java.lang.String)java.lang.StringBuilder
		// @115: iload_0
		// @116: invokevirtual java.lang.StringBuilder.append(boolean)java.lang.StringBuilder
		// @119: bipush 44 (0x2C)
		// @11B: invokevirtual java.lang.StringBuilder.append(char)java.lang.StringBuilder
		// @11E: iload_1
		// @11F: invokevirtual java.lang.StringBuilder.append(boolean)java.lang.StringBuilder
		// @122: bipush 44 (0x2C)
		// @124: invokevirtual java.lang.StringBuilder.append(char)java.lang.StringBuilder
		// @127: iload_2
		// @128: invokevirtual java.lang.StringBuilder.append(boolean)java.lang.StringBuilder
		// @12B: bipush 44 (0x2C)
		// @12D: invokevirtual java.lang.StringBuilder.append(char)java.lang.StringBuilder
		// @130: iload_3
		// @131: invokevirtual java.lang.StringBuilder.append(int)java.lang.StringBuilder
		// @134: bipush 44 (0x2C)
		// @136: invokevirtual java.lang.StringBuilder.append(char)java.lang.StringBuilder
		// @139: iload #4
		// @13B: invokevirtual java.lang.StringBuilder.append(boolean)java.lang.StringBuilder
		// @13E: bipush 44 (0x2C)
		// @140: invokevirtual java.lang.StringBuilder.append(char)java.lang.StringBuilder
		// @143: iload #5
		// @145: invokevirtual java.lang.StringBuilder.append(int)java.lang.StringBuilder
		// @148: bipush 41 (0x29)
		// @14A: invokevirtual java.lang.StringBuilder.append(char)java.lang.StringBuilder
		// @14D: invokevirtual java.lang.StringBuilder.toString()java.lang.String
		// @150: invokestatic game.C_100181_cf.func_105695_a(java.lang.Throwable, java.lang.String)game.C_100170_cm
		// @153: athrow
	}
	
	C_100122_em(long arg0, C_100037_wb arg1, C_100037_wb arg2, int arg3, C_100302_ka arg4, String arg5)
	{
		// @00: aload_0
		// @01: lload_1
		// @02: aconst_null
		// @03: aload #6
		// @05: aload #7
		// @07: invokespecial game.C_100122_em.<init>(long, game.C_100302_ka, game.C_100302_ka, java.lang.String)void
		// @0A: aload_0
		// @0B: getfield game.C_100302_ka game.C_100122_em.field_102070_dc
		// @0E: iload #5
		// @10: putfield int game.C_100302_ka.field_101858_J
		// @13: aload_0
		// @14: getfield game.C_100302_ka game.C_100122_em.field_102070_dc
		// @17: aload_3
		// @18: putfield game.C_100037_wb game.C_100302_ka.field_101855_O
		// @1B: aload_0
		// @1C: getfield game.C_100302_ka game.C_100122_em.field_102070_dc
		// @1F: aload #4
		// @21: putfield game.C_100037_wb game.C_100302_ka.field_101887_nb
		// @24: goto @BF
		// @27: astore #8
		// @29: aload #8
		// @2B: new java.lang.StringBuilder
		// @2E: dup
		// @2F: invokespecial java.lang.StringBuilder.<init>()void
		// @32: getstatic java.lang.String[] game.C_100122_em.field_102071_gc
		// @35: iconst_4
		// @36: aaload
		// @37: invokevirtual java.lang.StringBuilder.append(java.lang.String)java.lang.StringBuilder
		// @3A: lload_1
		// @3B: invokevirtual java.lang.StringBuilder.append(long)java.lang.StringBuilder
		// @3E: bipush 44 (0x2C)
		// @40: invokevirtual java.lang.StringBuilder.append(char)java.lang.StringBuilder
		// @43: aload_3
		// @44: ifnull @50
		// @47: getstatic java.lang.String[] game.C_100122_em.field_102071_gc
		// @4A: iconst_3
		// @4B: aaload
		// @4C: goto @55
		// @4F: athrow
		// @50: getstatic java.lang.String[] game.C_100122_em.field_102071_gc
		// @53: iconst_5
		// @54: aaload
		// @55: invokevirtual java.lang.StringBuilder.append(java.lang.String)java.lang.StringBuilder
		// @58: bipush 44 (0x2C)
		// @5A: invokevirtual java.lang.StringBuilder.append(char)java.lang.StringBuilder
		// @5D: aload #4
		// @5F: ifnull @6B
		// @62: getstatic java.lang.String[] game.C_100122_em.field_102071_gc
		// @65: iconst_3
		// @66: aaload
		// @67: goto @70
		// @6A: athrow
		// @6B: getstatic java.lang.String[] game.C_100122_em.field_102071_gc
		// @6E: iconst_5
		// @6F: aaload
		// @70: invokevirtual java.lang.StringBuilder.append(java.lang.String)java.lang.StringBuilder
		// @73: bipush 44 (0x2C)
		// @75: invokevirtual java.lang.StringBuilder.append(char)java.lang.StringBuilder
		// @78: iload #5
		// @7A: invokevirtual java.lang.StringBuilder.append(int)java.lang.StringBuilder
		// @7D: bipush 44 (0x2C)
		// @7F: invokevirtual java.lang.StringBuilder.append(char)java.lang.StringBuilder
		// @82: aload #6
		// @84: ifnull @90
		// @87: getstatic java.lang.String[] game.C_100122_em.field_102071_gc
		// @8A: iconst_3
		// @8B: aaload
		// @8C: goto @95
		// @8F: athrow
		// @90: getstatic java.lang.String[] game.C_100122_em.field_102071_gc
		// @93: iconst_5
		// @94: aaload
		// @95: invokevirtual java.lang.StringBuilder.append(java.lang.String)java.lang.StringBuilder
		// @98: bipush 44 (0x2C)
		// @9A: invokevirtual java.lang.StringBuilder.append(char)java.lang.StringBuilder
		// @9D: aload #7
		// @9F: ifnull @AB
		// @A2: getstatic java.lang.String[] game.C_100122_em.field_102071_gc
		// @A5: iconst_3
		// @A6: aaload
		// @A7: goto @B0
		// @AA: athrow
		// @AB: getstatic java.lang.String[] game.C_100122_em.field_102071_gc
		// @AE: iconst_5
		// @AF: aaload
		// @B0: invokevirtual java.lang.StringBuilder.append(java.lang.String)java.lang.StringBuilder
		// @B3: bipush 41 (0x29)
		// @B5: invokevirtual java.lang.StringBuilder.append(char)java.lang.StringBuilder
		// @B8: invokevirtual java.lang.StringBuilder.toString()java.lang.String
		// @BB: invokestatic game.C_100181_cf.func_105695_a(java.lang.Throwable, java.lang.String)game.C_100170_cm
		// @BE: athrow
		// @BF: return
	}
	
	final int func_102068_a(int arg0, int arg1)
	{
		// @00: iload_2
		// @01: bipush 8 (0x08)
		// @03: if_icmpeq @09
		// @06: bipush 20 (0x14)
		// @08: ireturn
		// @09: aload_0
		// @0A: getfield game.C_100302_ka game.C_100122_em.field_102070_dc
		// @0D: ldc 218000 (0x35390)
		// @0F: invokevirtual game.C_100302_ka.func_101818_j(int)int
		// @12: iload_1
		// @13: aload_0
		// @14: getfield game.C_100302_ka game.C_100122_em.field_102082_cc
		// @17: iload_2
		// @18: ldc 218008 (0x35398)
		// @1A: ixor
		// @1B: invokevirtual game.C_100302_ka.func_101818_j(int)int
		// @1E: ineg
		// @1F: isub
		// @20: iadd
		// @21: ireturn
		// @22: astore_3
		// @23: aload_3
		// @24: new java.lang.StringBuilder
		// @27: dup
		// @28: invokespecial java.lang.StringBuilder.<init>()void
		// @2B: getstatic java.lang.String[] game.C_100122_em.field_102071_gc
		// @2E: bipush 7 (0x07)
		// @30: aaload
		// @31: invokevirtual java.lang.StringBuilder.append(java.lang.String)java.lang.StringBuilder
		// @34: iload_1
		// @35: invokevirtual java.lang.StringBuilder.append(int)java.lang.StringBuilder
		// @38: bipush 44 (0x2C)
		// @3A: invokevirtual java.lang.StringBuilder.append(char)java.lang.StringBuilder
		// @3D: iload_2
		// @3E: invokevirtual java.lang.StringBuilder.append(int)java.lang.StringBuilder
		// @41: bipush 41 (0x29)
		// @43: invokevirtual java.lang.StringBuilder.append(char)java.lang.StringBuilder
		// @46: invokevirtual java.lang.StringBuilder.toString()java.lang.String
		// @49: invokestatic game.C_100181_cf.func_105695_a(java.lang.Throwable, java.lang.String)game.C_100170_cm
		// @4C: athrow
	}
	
	C_100122_em(long arg0, C_100122_em arg1, String arg2)
	{
		// @00: aload_0
		// @01: lload_1
		// @02: aload_3
		// @03: getfield game.C_100302_ka game.C_100122_em.field_102070_dc
		// @06: aload_3
		// @07: getfield game.C_100302_ka game.C_100122_em.field_102082_cc
		// @0A: aload #4
		// @0C: invokespecial game.C_100122_em.<init>(long, game.C_100302_ka, game.C_100302_ka, java.lang.String)void
		// @0F: return
	}
	
	static
	{
		// @00: bipush 8 (0x08)
		// @02: anewarray java.lang.String
		// @05: dup
		// @06: iconst_0
		// @07: ldc "Nfl/\u0008"
		// @09: invokestatic game.C_100122_em.func_102064_z(java.lang.String)char[]
		// @0C: invokestatic game.C_100122_em.func_102063_z(char[])java.lang.String
		// @0F: aastore
		// @10: dup
		// @11: iconst_1
		// @12: ldc "Nfl,\u0008"
		// @14: invokestatic game.C_100122_em.func_102064_z(java.lang.String)char[]
		// @17: invokestatic game.C_100122_em.func_102063_z(char[])java.lang.String
		// @1A: aastore
		// @1B: dup
		// @1C: iconst_2
		// @1D: ldc "Nfl*\u0008"
		// @1F: invokestatic game.C_100122_em.func_102064_z(java.lang.String)char[]
		// @22: invokestatic game.C_100122_em.func_102063_z(char[])java.lang.String
		// @25: aastore
		// @26: dup
		// @27: iconst_3
		// @28: ldc "P%l@]"
		// @2A: invokestatic game.C_100122_em.func_102064_z(java.lang.String)char[]
		// @2D: invokestatic game.C_100122_em.func_102063_z(char[])java.lang.String
		// @30: aastore
		// @31: dup
		// @32: iconst_4
		// @33: ldc "NflRIEb6P\u0008"
		// @35: invokestatic game.C_100122_em.func_102064_z(java.lang.String)char[]
		// @38: invokestatic game.C_100122_em.func_102063_z(char[])java.lang.String
		// @3B: aastore
		// @3C: dup
		// @3D: iconst_5
		// @3E: ldc "E~.\u0002"
		// @40: invokestatic game.C_100122_em.func_102064_z(java.lang.String)char[]
		// @43: invokestatic game.C_100122_em.func_102063_z(char[])java.lang.String
		// @46: aastore
		// @47: dup
		// @48: bipush 6 (0x06)
		// @4A: ldc "Nfl+\u0008"
		// @4C: invokestatic game.C_100122_em.func_102064_z(java.lang.String)char[]
		// @4F: invokestatic game.C_100122_em.func_102063_z(char[])java.lang.String
		// @52: aastore
		// @53: dup
		// @54: bipush 7 (0x07)
		// @56: ldc "Nfl-\u0008"
		// @58: invokestatic game.C_100122_em.func_102064_z(java.lang.String)char[]
		// @5B: invokestatic game.C_100122_em.func_102063_z(char[])java.lang.String
		// @5E: aastore
		// @5F: putstatic java.lang.String[] game.C_100122_em.field_102071_gc
		// @62: ldc "|b6\u0006DYj5NIE}+\u001aA_b-\u0000\u0000_dbR\u0005\u001b5b\u001aO\u000ba-\u0007N\u000b\u007f*\u0007S\u000bl#\u0003E"
		// @64: invokestatic game.C_100122_em.func_102064_z(java.lang.String)char[]
		// @67: invokestatic game.C_100122_em.func_102063_z(char[])java.lang.String
		// @6A: putstatic java.lang.String game.C_100122_em.field_102076_fc
		// @6D: iconst_3
		// @6E: anewarray int[]
		// @71: dup
		// @72: iconst_0
		// @73: aconst_null
		// @74: aastore
		// @75: dup
		// @76: iconst_1
		// @77: aconst_null
		// @78: aastore
		// @79: dup
		// @7A: iconst_2
		// @7B: aconst_null
		// @7C: aastore
		// @7D: putstatic int[][] game.C_100122_em.field_102073_Xb
		// @80: ldc "\u0017.sP\u0000\\j1NTDdb\rLDx'NTD+#NRDh)\u000bT\u000bb,\u001aEYh'\u001eTNob\u000cY\u000b7g^\u001e"
		// @82: invokestatic game.C_100122_em.func_102064_z(java.lang.String)char[]
		// @85: invokestatic game.C_100122_em.func_102063_z(char[])java.lang.String
		// @88: putstatic java.lang.String game.C_100122_em.field_102072_Zb
		// @8B: iconst_0
		// @8C: putstatic int game.C_100122_em.field_102080_ac
		// @8F: getstatic int[][] game.C_100122_em.field_102073_Xb
		// @92: arraylength
		// @93: anewarray game.C_100037_wb
		// @96: putstatic game.C_100037_wb[] game.C_100122_em.field_102075_ec
		// @99: bipush 6 (0x06)
		// @9B: newarray int[]
		// @9D: dup
		// @9E: iconst_0
		// @9F: bipush 17 (0x11)
		// @A1: iastore
		// @A2: dup
		// @A3: iconst_1
		// @A4: bipush 18 (0x12)
		// @A6: iastore
		// @A7: dup
		// @A8: iconst_2
		// @A9: iconst_3
		// @AA: iastore
		// @AB: dup
		// @AC: iconst_3
		// @AD: bipush 22 (0x16)
		// @AF: iastore
		// @B0: dup
		// @B1: iconst_4
		// @B2: iconst_m1
		// @B3: iastore
		// @B4: dup
		// @B5: iconst_5
		// @B6: bipush 8 (0x08)
		// @B8: iastore
		// @B9: putstatic int[] game.C_100122_em.field_102077_Wb
		// @BC: ldc "Z"
		// @BE: putstatic java.lang.String game.C_100122_em.field_102074_Yb
		// @C1: return
	}
	
	private static char[] func_102064_z(String arg0)
	{
		// @00: aload_0
		// @01: invokevirtual java.lang.String.toCharArray()char[]
		// @04: dup
		// @05: arraylength
		// @06: iconst_2
		// @07: if_icmpge @13
		// @0A: dup
		// @0B: iconst_0
		// @0C: dup2
		// @0D: caload
		// @0E: bipush 32 (0x20)
		// @10: ixor
		// @11: i2c
		// @12: castore
		// @13: areturn
	}
	
	private static String func_102063_z(char[] arg0)
	{
		// @00: aload_0
		// @01: dup
		// @02: arraylength
		// @03: swap
		// @04: iconst_0
		// @05: istore_1
		// @06: goto @4C
		// @09: dup
		// @0A: iload_1
		// @0B: dup2
		// @0C: caload
		// @0D: iload_1
		// @0E: iconst_5
		// @0F: irem
		// @10: tableswitch def: @44, for 0: @30, for 1: @35, for 2: @3A, for 3: @3F
		// @30: bipush 43 (0x2B)
		// @32: goto @46
		// @35: bipush 11 (0x0B)
		// @37: goto @46
		// @3A: bipush 66 (0x42)
		// @3C: goto @46
		// @3F: bipush 110 (0x6E)
		// @41: goto @46
		// @44: bipush 32 (0x20)
		// @46: ixor
		// @47: i2c
		// @48: castore
		// @49: iinc #1 +1
		// @4C: swap
		// @4D: dup_x1
		// @4E: iload_1
		// @4F: if_icmpgt @09
		// @52: new java.lang.String
		// @55: dup_x1
		// @56: swap
		// @57: invokespecial java.lang.String.<init>(char[])void
		// @5A: invokevirtual java.lang.String.intern()java.lang.String
		// @5D: areturn
	}
}
