package game;

import java.nio.ByteBuffer;

final class C_100042_we extends C_100116_ei
{
	static C_100153_be[] field_104138_j;
	static C_100002_gf field_104134_n;
	static C_100037_wb field_104141_h;
	static long field_104142_i;
	static C_100302_ka field_104131_r;
	static String field_104135_o;
	static C_100037_wb[] field_104136_l;
	private ByteBuffer field_104140_k;
	static String field_104133_p;
	static int[] field_104132_q;
	static int field_104137_m;
	private static final String[] field_104139_z;
	
	final byte[] func_104115_a(int arg0)
	{
		// @00: iload_1
		// @01: sipush 200 (0x00C8)
		// @04: if_icmpeq @0C
		// @07: aconst_null
		// @08: checkcast byte[]
		// @0B: areturn
		// @0C: aload_0
		// @0D: getfield java.nio.ByteBuffer game.C_100042_we.field_104140_k
		// @10: invokevirtual java.nio.ByteBuffer.capacity()int
		// @13: newarray byte[]
		// @15: astore_2
		// @16: aload_0
		// @17: getfield java.nio.ByteBuffer game.C_100042_we.field_104140_k
		// @1A: iconst_0
		// @1B: invokevirtual java.nio.ByteBuffer.position(int)java.nio.Buffer
		// @1E: pop
		// @1F: aload_0
		// @20: getfield java.nio.ByteBuffer game.C_100042_we.field_104140_k
		// @23: aload_2
		// @24: invokevirtual java.nio.ByteBuffer.get(byte[])java.nio.ByteBuffer
		// @27: pop
		// @28: aload_2
		// @29: areturn
		// @2A: astore_2
		// @2B: aload_2
		// @2C: new java.lang.StringBuilder
		// @2F: dup
		// @30: invokespecial java.lang.StringBuilder.<init>()void
		// @33: getstatic java.lang.String[] game.C_100042_we.field_104139_z
		// @36: iconst_5
		// @37: aaload
		// @38: invokevirtual java.lang.StringBuilder.append(java.lang.String)java.lang.StringBuilder
		// @3B: iload_1
		// @3C: invokevirtual java.lang.StringBuilder.append(int)java.lang.StringBuilder
		// @3F: bipush 41 (0x29)
		// @41: invokevirtual java.lang.StringBuilder.append(char)java.lang.StringBuilder
		// @44: invokevirtual java.lang.StringBuilder.toString()java.lang.String
		// @47: invokestatic game.C_100181_cf.func_105695_a(java.lang.Throwable, java.lang.String)game.C_100170_cm
		// @4A: athrow
	}
	
	static final int[] func_104129_b(int arg0, int arg1)
	{
		// @000: getstatic int game.SteelSentinels.field_105275_O
		// @003: istore_3
		// @004: iload_1
		// @005: istore_2
		// @006: iconst_0
		// @007: iload_2
		// @008: if_icmpne @013
		// @00B: iload_3
		// @00C: ifeq @0B1
		// @00F: goto @013
		// @012: athrow
		// @013: iload_2
		// @014: iconst_m1
		// @015: ixor
		// @016: bipush -56 (0xC8)
		// @018: if_icmpne @027
		// @01B: goto @01F
		// @01E: athrow
		// @01F: iload_3
		// @020: ifeq @0B5
		// @023: goto @027
		// @026: athrow
		// @027: bipush 57 (0x39)
		// @029: iload_2
		// @02A: if_icmpeq @0B9
		// @02D: goto @031
		// @030: athrow
		// @031: iload_2
		// @032: iconst_m1
		// @033: ixor
		// @034: bipush -63 (0xC1)
		// @036: if_icmpeq @0BD
		// @039: goto @03D
		// @03C: athrow
		// @03D: bipush -66 (0xBE)
		// @03F: iload_2
		// @040: iconst_m1
		// @041: ixor
		// @042: if_icmpne @051
		// @045: goto @049
		// @048: athrow
		// @049: iload_3
		// @04A: ifeq @0C1
		// @04D: goto @051
		// @050: athrow
		// @051: iload_2
		// @052: bipush 69 (0x45)
		// @054: if_icmpne @063
		// @057: goto @05B
		// @05A: athrow
		// @05B: iload_3
		// @05C: ifeq @0C5
		// @05F: goto @063
		// @062: athrow
		// @063: iload_2
		// @064: bipush 72 (0x48)
		// @066: if_icmpeq @0C9
		// @069: goto @06D
		// @06C: athrow
		// @06D: iload_2
		// @06E: bipush 75 (0x4B)
		// @070: if_icmpne @07F
		// @073: goto @077
		// @076: athrow
		// @077: iload_3
		// @078: ifeq @0CD
		// @07B: goto @07F
		// @07E: athrow
		// @07F: bipush 79 (0x4F)
		// @081: iload_2
		// @082: if_icmpeq @0D1
		// @085: goto @089
		// @088: athrow
		// @089: bipush -85 (0xAB)
		// @08B: iload_2
		// @08C: iconst_m1
		// @08D: ixor
		// @08E: if_icmpeq @0D5
		// @091: goto @095
		// @094: athrow
		// @095: bipush 88 (0x58)
		// @097: iload_2
		// @098: if_icmpeq @0D9
		// @09B: goto @09F
		// @09E: athrow
		// @09F: bipush 92 (0x5C)
		// @0A1: iload_2
		// @0A2: if_icmpne @0E1
		// @0A5: goto @0A9
		// @0A8: athrow
		// @0A9: iload_3
		// @0AA: ifeq @0DD
		// @0AD: goto @0B1
		// @0B0: athrow
		// @0B1: getstatic int[] game.C_100005_fk.field_103604_v
		// @0B4: areturn
		// @0B5: getstatic int[] game.C_100005_fk.field_103605_u
		// @0B8: areturn
		// @0B9: getstatic int[] game.C_100005_fk.field_103607_s
		// @0BC: areturn
		// @0BD: getstatic int[] game.C_100005_fk.field_103606_t
		// @0C0: areturn
		// @0C1: getstatic int[] game.C_100005_fk.field_103602_h
		// @0C4: areturn
		// @0C5: getstatic int[] game.C_100005_fk.field_103610_p
		// @0C8: areturn
		// @0C9: getstatic int[] game.C_100005_fk.field_103597_o
		// @0CC: areturn
		// @0CD: getstatic int[] game.C_100005_fk.field_103592_e
		// @0D0: areturn
		// @0D1: getstatic int[] game.C_100005_fk.field_103600_j
		// @0D4: areturn
		// @0D5: getstatic int[] game.C_100061_dh.field_102000_cc
		// @0D8: areturn
		// @0D9: getstatic int[] game.C_100346_ja.field_103488_k
		// @0DC: areturn
		// @0DD: getstatic int[] game.C_100032_gk.field_103139_bb
		// @0E0: areturn
		// @0E1: bipush 86 (0x56)
		// @0E3: iload_0
		// @0E4: bipush 13 (0x0D)
		// @0E6: isub
		// @0E7: bipush 34 (0x22)
		// @0E9: idiv
		// @0EA: irem
		// @0EB: istore_2
		// @0EC: aconst_null
		// @0ED: areturn
		// @0EE: astore_2
		// @0EF: aload_2
		// @0F0: new java.lang.StringBuilder
		// @0F3: dup
		// @0F4: invokespecial java.lang.StringBuilder.<init>()void
		// @0F7: getstatic java.lang.String[] game.C_100042_we.field_104139_z
		// @0FA: bipush 6 (0x06)
		// @0FC: aaload
		// @0FD: invokevirtual java.lang.StringBuilder.append(java.lang.String)java.lang.StringBuilder
		// @100: iload_0
		// @101: invokevirtual java.lang.StringBuilder.append(int)java.lang.StringBuilder
		// @104: bipush 44 (0x2C)
		// @106: invokevirtual java.lang.StringBuilder.append(char)java.lang.StringBuilder
		// @109: iload_1
		// @10A: invokevirtual java.lang.StringBuilder.append(int)java.lang.StringBuilder
		// @10D: bipush 41 (0x29)
		// @10F: invokevirtual java.lang.StringBuilder.append(char)java.lang.StringBuilder
		// @112: invokevirtual java.lang.StringBuilder.toString()java.lang.String
		// @115: invokestatic game.C_100181_cf.func_105695_a(java.lang.Throwable, java.lang.String)game.C_100170_cm
		// @118: athrow
	}
	
	final void func_104114_a(byte[] arg0, byte arg1)
	{
		// @00: bipush -78 (0xB2)
		// @02: iload_2
		// @03: iconst_m1
		// @04: isub
		// @05: bipush 54 (0x36)
		// @07: idiv
		// @08: idiv
		// @09: istore_3
		// @0A: aload_0
		// @0B: aload_1
		// @0C: arraylength
		// @0D: invokestatic java.nio.ByteBuffer.allocateDirect(int)java.nio.ByteBuffer
		// @10: putfield java.nio.ByteBuffer game.C_100042_we.field_104140_k
		// @13: aload_0
		// @14: getfield java.nio.ByteBuffer game.C_100042_we.field_104140_k
		// @17: iconst_0
		// @18: invokevirtual java.nio.ByteBuffer.position(int)java.nio.Buffer
		// @1B: pop
		// @1C: aload_0
		// @1D: getfield java.nio.ByteBuffer game.C_100042_we.field_104140_k
		// @20: aload_1
		// @21: invokevirtual java.nio.ByteBuffer.put(byte[])java.nio.ByteBuffer
		// @24: pop
		// @25: goto @63
		// @28: astore_3
		// @29: aload_3
		// @2A: new java.lang.StringBuilder
		// @2D: dup
		// @2E: invokespecial java.lang.StringBuilder.<init>()void
		// @31: getstatic java.lang.String[] game.C_100042_we.field_104139_z
		// @34: iconst_4
		// @35: aaload
		// @36: invokevirtual java.lang.StringBuilder.append(java.lang.String)java.lang.StringBuilder
		// @39: aload_1
		// @3A: ifnull @46
		// @3D: getstatic java.lang.String[] game.C_100042_we.field_104139_z
		// @40: iconst_3
		// @41: aaload
		// @42: goto @4B
		// @45: athrow
		// @46: getstatic java.lang.String[] game.C_100042_we.field_104139_z
		// @49: iconst_2
		// @4A: aaload
		// @4B: invokevirtual java.lang.StringBuilder.append(java.lang.String)java.lang.StringBuilder
		// @4E: bipush 44 (0x2C)
		// @50: invokevirtual java.lang.StringBuilder.append(char)java.lang.StringBuilder
		// @53: iload_2
		// @54: invokevirtual java.lang.StringBuilder.append(int)java.lang.StringBuilder
		// @57: bipush 41 (0x29)
		// @59: invokevirtual java.lang.StringBuilder.append(char)java.lang.StringBuilder
		// @5C: invokevirtual java.lang.StringBuilder.toString()java.lang.String
		// @5F: invokestatic game.C_100181_cf.func_105695_a(java.lang.Throwable, java.lang.String)game.C_100170_cm
		// @62: athrow
		// @63: return
	}
	
	static final void func_104130_a(int arg0, C_100158_da arg1, C_100158_da arg2)
	{
		// @00: aload_1
		// @01: getfield game.C_100158_da game.C_100158_da.field_100599_i
		// @04: ifnull @11
		// @07: aload_1
		// @08: bipush 45 (0x2D)
		// @0A: invokevirtual game.C_100158_da.func_100583_c(int)void
		// @0D: goto @11
		// @10: athrow
		// @11: aload_1
		// @12: aload_2
		// @13: getfield game.C_100158_da game.C_100158_da.field_100599_i
		// @16: putfield game.C_100158_da game.C_100158_da.field_100599_i
		// @19: iload_0
		// @1A: bipush 72 (0x48)
		// @1C: if_icmpeq @30
		// @1F: bipush 76 (0x4C)
		// @21: aconst_null
		// @22: checkcast game.C_100158_da
		// @25: aconst_null
		// @26: checkcast game.C_100158_da
		// @29: invokestatic game.C_100042_we.func_104130_a(int, game.C_100158_da, game.C_100158_da)void
		// @2C: goto @30
		// @2F: athrow
		// @30: aload_1
		// @31: aload_2
		// @32: putfield game.C_100158_da game.C_100158_da.field_100590_f
		// @35: aload_1
		// @36: getfield game.C_100158_da game.C_100158_da.field_100599_i
		// @39: aload_1
		// @3A: putfield game.C_100158_da game.C_100158_da.field_100590_f
		// @3D: aload_1
		// @3E: getfield game.C_100158_da game.C_100158_da.field_100590_f
		// @41: aload_1
		// @42: putfield game.C_100158_da game.C_100158_da.field_100599_i
		// @45: goto @9D
		// @48: astore_3
		// @49: aload_3
		// @4A: new java.lang.StringBuilder
		// @4D: dup
		// @4E: invokespecial java.lang.StringBuilder.<init>()void
		// @51: getstatic java.lang.String[] game.C_100042_we.field_104139_z
		// @54: iconst_1
		// @55: aaload
		// @56: invokevirtual java.lang.StringBuilder.append(java.lang.String)java.lang.StringBuilder
		// @59: iload_0
		// @5A: invokevirtual java.lang.StringBuilder.append(int)java.lang.StringBuilder
		// @5D: bipush 44 (0x2C)
		// @5F: invokevirtual java.lang.StringBuilder.append(char)java.lang.StringBuilder
		// @62: aload_1
		// @63: ifnull @6F
		// @66: getstatic java.lang.String[] game.C_100042_we.field_104139_z
		// @69: iconst_3
		// @6A: aaload
		// @6B: goto @74
		// @6E: athrow
		// @6F: getstatic java.lang.String[] game.C_100042_we.field_104139_z
		// @72: iconst_2
		// @73: aaload
		// @74: invokevirtual java.lang.StringBuilder.append(java.lang.String)java.lang.StringBuilder
		// @77: bipush 44 (0x2C)
		// @79: invokevirtual java.lang.StringBuilder.append(char)java.lang.StringBuilder
		// @7C: aload_2
		// @7D: ifnull @89
		// @80: getstatic java.lang.String[] game.C_100042_we.field_104139_z
		// @83: iconst_3
		// @84: aaload
		// @85: goto @8E
		// @88: athrow
		// @89: getstatic java.lang.String[] game.C_100042_we.field_104139_z
		// @8C: iconst_2
		// @8D: aaload
		// @8E: invokevirtual java.lang.StringBuilder.append(java.lang.String)java.lang.StringBuilder
		// @91: bipush 41 (0x29)
		// @93: invokevirtual java.lang.StringBuilder.append(char)java.lang.StringBuilder
		// @96: invokevirtual java.lang.StringBuilder.toString()java.lang.String
		// @99: invokestatic game.C_100181_cf.func_105695_a(java.lang.Throwable, java.lang.String)game.C_100170_cm
		// @9C: athrow
		// @9D: return
	}
	
	public static void func_104127_a(byte arg0)
	{
		// @00: aconst_null
		// @01: putstatic game.C_100002_gf game.C_100042_we.field_104134_n
		// @04: aconst_null
		// @05: putstatic int[] game.C_100042_we.field_104132_q
		// @08: aconst_null
		// @09: putstatic java.lang.String game.C_100042_we.field_104133_p
		// @0C: aconst_null
		// @0D: putstatic game.C_100302_ka game.C_100042_we.field_104131_r
		// @10: aconst_null
		// @11: putstatic game.C_100037_wb[] game.C_100042_we.field_104136_l
		// @14: iload_0
		// @15: bipush -42 (0xD6)
		// @17: if_icmplt @25
		// @1A: aconst_null
		// @1B: checkcast int[]
		// @1E: putstatic int[] game.C_100042_we.field_104132_q
		// @21: goto @25
		// @24: athrow
		// @25: aconst_null
		// @26: putstatic java.lang.String game.C_100042_we.field_104135_o
		// @29: aconst_null
		// @2A: putstatic game.C_100037_wb game.C_100042_we.field_104141_h
		// @2D: aconst_null
		// @2E: putstatic game.C_100153_be[] game.C_100042_we.field_104138_j
		// @31: goto @55
		// @34: astore_1
		// @35: aload_1
		// @36: new java.lang.StringBuilder
		// @39: dup
		// @3A: invokespecial java.lang.StringBuilder.<init>()void
		// @3D: getstatic java.lang.String[] game.C_100042_we.field_104139_z
		// @40: iconst_0
		// @41: aaload
		// @42: invokevirtual java.lang.StringBuilder.append(java.lang.String)java.lang.StringBuilder
		// @45: iload_0
		// @46: invokevirtual java.lang.StringBuilder.append(int)java.lang.StringBuilder
		// @49: bipush 41 (0x29)
		// @4B: invokevirtual java.lang.StringBuilder.append(char)java.lang.StringBuilder
		// @4E: invokevirtual java.lang.StringBuilder.toString()java.lang.String
		// @51: invokestatic game.C_100181_cf.func_105695_a(java.lang.Throwable, java.lang.String)game.C_100170_cm
		// @54: athrow
		// @55: return
	}
	
	static
	{
		// @00: bipush 7 (0x07)
		// @02: anewarray java.lang.String
		// @05: dup
		// @06: iconst_0
		// @07: ldc "P\u0018*X\u0018"
		// @09: invokestatic game.C_100042_we.func_104128_z(java.lang.String)char[]
		// @0C: invokestatic game.C_100042_we.func_104126_z(char[])java.lang.String
		// @0F: aastore
		// @10: dup
		// @11: iconst_1
		// @12: ldc "P\u0018*W\u0018"
		// @14: invokestatic game.C_100042_we.func_104128_z(java.lang.String)char[]
		// @17: invokestatic game.C_100042_we.func_104126_z(char[])java.lang.String
		// @1A: aastore
		// @1B: dup
		// @1C: iconst_2
		// @1D: ldc "I\u0008hs"
		// @1F: invokestatic game.C_100042_we.func_104128_z(java.lang.String)char[]
		// @22: invokestatic game.C_100042_we.func_104126_z(char[])java.lang.String
		// @25: aastore
		// @26: dup
		// @27: iconst_3
		// @28: ldc "\\S*1M"
		// @2A: invokestatic game.C_100042_we.func_104128_z(java.lang.String)char[]
		// @2D: invokestatic game.C_100042_we.func_104126_z(char[])java.lang.String
		// @30: aastore
		// @31: dup
		// @32: iconst_4
		// @33: ldc "P\u0018*^\u0018"
		// @35: invokestatic game.C_100042_we.func_104128_z(java.lang.String)char[]
		// @38: invokestatic game.C_100042_we.func_104126_z(char[])java.lang.String
		// @3B: aastore
		// @3C: dup
		// @3D: iconst_5
		// @3E: ldc "P\u0018*Z\u0018"
		// @40: invokestatic game.C_100042_we.func_104128_z(java.lang.String)char[]
		// @43: invokestatic game.C_100042_we.func_104126_z(char[])java.lang.String
		// @46: aastore
		// @47: dup
		// @48: bipush 6 (0x06)
		// @4A: ldc "P\u0018*V\u0018"
		// @4C: invokestatic game.C_100042_we.func_104128_z(java.lang.String)char[]
		// @4F: invokestatic game.C_100042_we.func_104126_z(char[])java.lang.String
		// @52: aastore
		// @53: putstatic java.lang.String[] game.C_100042_we.field_104139_z
		// @56: ldc "X"
		// @58: putstatic java.lang.String game.C_100042_we.field_104135_o
		// @5B: ldc2_w 20000000
		// @5E: putstatic long game.C_100042_we.field_104142_i
		// @61: ldc "t\tekET"
		// @63: invokestatic game.C_100042_we.func_104128_z(java.lang.String)char[]
		// @66: invokestatic game.C_100042_we.func_104126_z(char[])java.lang.String
		// @69: putstatic java.lang.String game.C_100042_we.field_104133_p
		// @6C: return
	}
	
	private static char[] func_104128_z(String arg0)
	{
		// @00: aload_0
		// @01: invokevirtual java.lang.String.toCharArray()char[]
		// @04: dup
		// @05: arraylength
		// @06: iconst_2
		// @07: if_icmpge @13
		// @0A: dup
		// @0B: iconst_0
		// @0C: dup2
		// @0D: caload
		// @0E: bipush 48 (0x30)
		// @10: ixor
		// @11: i2c
		// @12: castore
		// @13: areturn
	}
	
	private static String func_104126_z(char[] arg0)
	{
		// @00: aload_0
		// @01: dup
		// @02: arraylength
		// @03: swap
		// @04: iconst_0
		// @05: istore_1
		// @06: goto @4B
		// @09: dup
		// @0A: iload_1
		// @0B: dup2
		// @0C: caload
		// @0D: iload_1
		// @0E: iconst_5
		// @0F: irem
		// @10: tableswitch def: @43, for 0: @30, for 1: @35, for 2: @3A, for 3: @3E
		// @30: bipush 39 (0x27)
		// @32: goto @45
		// @35: bipush 125 (0x7D)
		// @37: goto @45
		// @3A: iconst_4
		// @3B: goto @45
		// @3E: bipush 31 (0x1F)
		// @40: goto @45
		// @43: bipush 48 (0x30)
		// @45: ixor
		// @46: i2c
		// @47: castore
		// @48: iinc #1 +1
		// @4B: swap
		// @4C: dup_x1
		// @4D: iload_1
		// @4E: if_icmpgt @09
		// @51: new java.lang.String
		// @54: dup_x1
		// @55: swap
		// @56: invokespecial java.lang.String.<init>(char[])void
		// @59: invokevirtual java.lang.String.intern()java.lang.String
		// @5C: areturn
	}
}
