package game;

final class C_100220_ac
{
	static C_100333_ij field_106064_h;
	C_100172_ck field_106059_a;
	static String field_106055_d;
	static C_100068_vc field_106056_e;
	static int field_106054_g;
	static String field_106060_l;
	static int field_106062_j;
	static String field_106061_m;
	static int field_106053_f;
	static int field_106058_c;
	static int field_106065_i;
	static String field_106063_k;
	static C_100302_ka field_106057_b;
	private static final String[] field_106066_z;
	
	final void func_106052_a(int arg0, byte arg1, int arg2, int arg3, int arg4)
	{
		// @000: bipush 24 (0x18)
		// @002: istore #6
		// @004: iconst_5
		// @005: istore #7
		// @007: aload_0
		// @008: getfield game.C_100172_ck game.C_100220_ac.field_106059_a
		// @00B: iload_3
		// @00C: iload_1
		// @00D: iload #4
		// @00F: sipush 10250 (0x280A)
		// @012: iload #6
		// @014: iload #7
		// @016: iload #5
		// @018: invokevirtual game.C_100172_ck.func_102102_a(int, int, int, int, int, int, int)void
		// @01B: getstatic game.C_100302_ka game.C_100104_v.field_104690_e
		// @01E: iconst_0
		// @01F: getstatic int game.C_100033_gj.field_101917_jc
		// @022: iconst_m1
		// @023: iconst_0
		// @024: getstatic game.C_100302_ka game.C_100280_nf.field_101176_p
		// @027: getfield int game.C_100302_ka.field_101886_Kb
		// @02A: invokevirtual game.C_100302_ka.func_101825_a(int, int, int, int, int)void
		// @02D: getstatic game.C_100302_ka game.C_100111_el.field_104860_d
		// @030: iconst_0
		// @031: bipush 18 (0x12)
		// @033: iconst_m1
		// @034: iconst_2
		// @035: getstatic int game.C_100033_gj.field_101917_jc
		// @038: iadd
		// @039: bipush -82 (0xAE)
		// @03B: getstatic game.C_100302_ka game.C_100280_nf.field_101176_p
		// @03E: getfield int game.C_100302_ka.field_101886_Kb
		// @041: iadd
		// @042: getstatic int game.C_100099_fb.field_103046_u
		// @045: iconst_2
		// @046: iadd
		// @047: isub
		// @048: invokevirtual game.C_100302_ka.func_101825_a(int, int, int, int, int)void
		// @04B: getstatic game.C_100302_ka game.C_100235_om.field_106289_e
		// @04E: bipush -80 (0xB0)
		// @050: getstatic game.C_100302_ka game.C_100280_nf.field_101176_p
		// @053: getfield int game.C_100302_ka.field_101886_Kb
		// @056: getstatic int game.C_100099_fb.field_103046_u
		// @059: ineg
		// @05A: iadd
		// @05B: iadd
		// @05C: iconst_2
		// @05D: isub
		// @05E: bipush 18 (0x12)
		// @060: iconst_m1
		// @061: iconst_2
		// @062: getstatic int game.C_100033_gj.field_101917_jc
		// @065: iadd
		// @066: getstatic int game.C_100099_fb.field_103046_u
		// @069: bipush 82 (0x52)
		// @06B: iadd
		// @06C: invokevirtual game.C_100302_ka.func_101825_a(int, int, int, int, int)void
		// @06F: getstatic game.C_100100_i game.C_100012_fh.field_100507_G
		// @072: bipush -2 (0xFE)
		// @074: getstatic game.C_100302_ka game.C_100280_nf.field_101176_p
		// @077: getfield int game.C_100302_ka.field_101848_lb
		// @07A: getstatic int game.C_100033_gj.field_101917_jc
		// @07D: isub
		// @07E: bipush -20 (0xEC)
		// @080: iadd
		// @081: iadd
		// @082: iconst_2
		// @083: iconst_0
		// @084: bipush 22 (0x16)
		// @086: getstatic int game.C_100033_gj.field_101917_jc
		// @089: iadd
		// @08A: bipush 20 (0x14)
		// @08C: getstatic int game.C_100099_fb.field_103046_u
		// @08F: sipush -30196 (0x8A0C)
		// @092: getstatic game.C_100302_ka game.C_100280_nf.field_101176_p
		// @095: getfield int game.C_100302_ka.field_101886_Kb
		// @098: invokevirtual game.C_100100_i.func_102008_a(int, int, int, int, int, int, int, int)void
		// @09B: iload_2
		// @09C: bipush -8 (0xF8)
		// @09E: if_icmpeq @0B3
		// @0A1: aload_0
		// @0A2: bipush -21 (0xEB)
		// @0A4: bipush -66 (0xBE)
		// @0A6: bipush -50 (0xCE)
		// @0A8: bipush -126 (0x82)
		// @0AA: bipush -2 (0xFE)
		// @0AC: invokevirtual game.C_100220_ac.func_106052_a(int, byte, int, int, int)void
		// @0AF: goto @0B3
		// @0B2: athrow
		// @0B3: getstatic game.C_100100_i game.C_100202_qi.field_105913_f
		// @0B6: bipush 20 (0x14)
		// @0B8: getstatic int game.C_100099_fb.field_103046_u
		// @0BB: iconst_2
		// @0BC: bipush -47 (0xD1)
		// @0BE: invokevirtual game.C_100100_i.func_102002_a(int, int, int, byte)void
		// @0C1: goto @10D
		// @0C4: astore #6
		// @0C6: aload #6
		// @0C8: new java.lang.StringBuilder
		// @0CB: dup
		// @0CC: invokespecial java.lang.StringBuilder.<init>()void
		// @0CF: getstatic java.lang.String[] game.C_100220_ac.field_106066_z
		// @0D2: iconst_3
		// @0D3: aaload
		// @0D4: invokevirtual java.lang.StringBuilder.append(java.lang.String)java.lang.StringBuilder
		// @0D7: iload_1
		// @0D8: invokevirtual java.lang.StringBuilder.append(int)java.lang.StringBuilder
		// @0DB: bipush 44 (0x2C)
		// @0DD: invokevirtual java.lang.StringBuilder.append(char)java.lang.StringBuilder
		// @0E0: iload_2
		// @0E1: invokevirtual java.lang.StringBuilder.append(int)java.lang.StringBuilder
		// @0E4: bipush 44 (0x2C)
		// @0E6: invokevirtual java.lang.StringBuilder.append(char)java.lang.StringBuilder
		// @0E9: iload_3
		// @0EA: invokevirtual java.lang.StringBuilder.append(int)java.lang.StringBuilder
		// @0ED: bipush 44 (0x2C)
		// @0EF: invokevirtual java.lang.StringBuilder.append(char)java.lang.StringBuilder
		// @0F2: iload #4
		// @0F4: invokevirtual java.lang.StringBuilder.append(int)java.lang.StringBuilder
		// @0F7: bipush 44 (0x2C)
		// @0F9: invokevirtual java.lang.StringBuilder.append(char)java.lang.StringBuilder
		// @0FC: iload #5
		// @0FE: invokevirtual java.lang.StringBuilder.append(int)java.lang.StringBuilder
		// @101: bipush 41 (0x29)
		// @103: invokevirtual java.lang.StringBuilder.append(char)java.lang.StringBuilder
		// @106: invokevirtual java.lang.StringBuilder.toString()java.lang.String
		// @109: invokestatic game.C_100181_cf.func_105695_a(java.lang.Throwable, java.lang.String)game.C_100170_cm
		// @10C: athrow
		// @10D: return
	}
	
	C_100220_ac(String arg0, C_100302_ka arg1)
	{
		// @00: aload_0
		// @01: invokespecial java.lang.Object.<init>()void
		// @04: iconst_3
		// @05: anewarray java.lang.String
		// @08: dup
		// @09: iconst_0
		// @0A: aload_1
		// @0B: aastore
		// @0C: dup
		// @0D: iconst_1
		// @0E: getstatic java.lang.String game.C_100191_rg.field_100843_p
		// @11: aastore
		// @12: dup
		// @13: iconst_2
		// @14: getstatic java.lang.String game.C_100327_ib.field_102487_O
		// @17: aastore
		// @18: astore_3
		// @19: iconst_3
		// @1A: anewarray game.C_100302_ka
		// @1D: dup
		// @1E: iconst_0
		// @1F: aload_2
		// @20: aastore
		// @21: dup
		// @22: iconst_1
		// @23: getstatic game.C_100302_ka game.C_100280_nf.field_101176_p
		// @26: aastore
		// @27: dup
		// @28: iconst_2
		// @29: getstatic game.C_100100_i game.C_100202_qi.field_105913_f
		// @2C: aastore
		// @2D: astore #4
		// @2F: aload_0
		// @30: new game.C_100172_ck
		// @33: dup
		// @34: lconst_0
		// @35: getstatic game.C_100302_ka game.C_100056_de.field_103195_bb
		// @38: aload_3
		// @39: getstatic game.C_100302_ka game.C_100028_ha.field_103944_f
		// @3C: aload #4
		// @3E: iconst_0
		// @3F: invokespecial game.C_100172_ck.<init>(long, game.C_100302_ka, java.lang.String[], game.C_100302_ka, game.C_100302_ka[], int)void
		// @42: putfield game.C_100172_ck game.C_100220_ac.field_106059_a
		// @45: goto @94
		// @48: astore_3
		// @49: aload_3
		// @4A: new java.lang.StringBuilder
		// @4D: dup
		// @4E: invokespecial java.lang.StringBuilder.<init>()void
		// @51: getstatic java.lang.String[] game.C_100220_ac.field_106066_z
		// @54: iconst_1
		// @55: aaload
		// @56: invokevirtual java.lang.StringBuilder.append(java.lang.String)java.lang.StringBuilder
		// @59: aload_1
		// @5A: ifnull @66
		// @5D: getstatic java.lang.String[] game.C_100220_ac.field_106066_z
		// @60: iconst_2
		// @61: aaload
		// @62: goto @6B
		// @65: athrow
		// @66: getstatic java.lang.String[] game.C_100220_ac.field_106066_z
		// @69: iconst_0
		// @6A: aaload
		// @6B: invokevirtual java.lang.StringBuilder.append(java.lang.String)java.lang.StringBuilder
		// @6E: bipush 44 (0x2C)
		// @70: invokevirtual java.lang.StringBuilder.append(char)java.lang.StringBuilder
		// @73: aload_2
		// @74: ifnull @80
		// @77: getstatic java.lang.String[] game.C_100220_ac.field_106066_z
		// @7A: iconst_2
		// @7B: aaload
		// @7C: goto @85
		// @7F: athrow
		// @80: getstatic java.lang.String[] game.C_100220_ac.field_106066_z
		// @83: iconst_0
		// @84: aaload
		// @85: invokevirtual java.lang.StringBuilder.append(java.lang.String)java.lang.StringBuilder
		// @88: bipush 41 (0x29)
		// @8A: invokevirtual java.lang.StringBuilder.append(char)java.lang.StringBuilder
		// @8D: invokevirtual java.lang.StringBuilder.toString()java.lang.String
		// @90: invokestatic game.C_100181_cf.func_105695_a(java.lang.Throwable, java.lang.String)game.C_100170_cm
		// @93: athrow
		// @94: return
	}
	
	public static void func_106047_a(int arg0)
	{
		// @00: aconst_null
		// @01: putstatic java.lang.String game.C_100220_ac.field_106061_m
		// @04: aconst_null
		// @05: putstatic game.C_100068_vc game.C_100220_ac.field_106056_e
		// @08: aconst_null
		// @09: putstatic game.C_100333_ij game.C_100220_ac.field_106064_h
		// @0C: aconst_null
		// @0D: putstatic game.C_100302_ka game.C_100220_ac.field_106057_b
		// @10: aconst_null
		// @11: putstatic java.lang.String game.C_100220_ac.field_106060_l
		// @14: aconst_null
		// @15: putstatic java.lang.String game.C_100220_ac.field_106055_d
		// @18: iload_0
		// @19: bipush 35 (0x23)
		// @1B: if_icmpeq @28
		// @1E: iconst_0
		// @1F: bipush -69 (0xBB)
		// @21: invokestatic game.C_100220_ac.func_106051_a(boolean, int)void
		// @24: goto @28
		// @27: athrow
		// @28: aconst_null
		// @29: putstatic java.lang.String game.C_100220_ac.field_106063_k
		// @2C: goto @51
		// @2F: astore_1
		// @30: aload_1
		// @31: new java.lang.StringBuilder
		// @34: dup
		// @35: invokespecial java.lang.StringBuilder.<init>()void
		// @38: getstatic java.lang.String[] game.C_100220_ac.field_106066_z
		// @3B: bipush 11 (0x0B)
		// @3D: aaload
		// @3E: invokevirtual java.lang.StringBuilder.append(java.lang.String)java.lang.StringBuilder
		// @41: iload_0
		// @42: invokevirtual java.lang.StringBuilder.append(int)java.lang.StringBuilder
		// @45: bipush 41 (0x29)
		// @47: invokevirtual java.lang.StringBuilder.append(char)java.lang.StringBuilder
		// @4A: invokevirtual java.lang.StringBuilder.toString()java.lang.String
		// @4D: invokestatic game.C_100181_cf.func_105695_a(java.lang.Throwable, java.lang.String)game.C_100170_cm
		// @50: athrow
		// @51: return
	}
	
	static final void func_106051_a(boolean arg0, int arg1)
	{
		// @00: iload_0
		// @01: bipush -102 (0x9A)
		// @03: invokestatic game.C_100123_uc.func_104915_a(boolean, byte)void
		// @06: iload_1
		// @07: bipush 51 (0x33)
		// @09: if_icmpgt @1A
		// @0C: aconst_null
		// @0D: checkcast int[]
		// @10: aconst_null
		// @11: checkcast int[]
		// @14: bipush -98 (0x9E)
		// @16: invokestatic game.C_100220_ac.func_106050_a(int[], int[], int)java.lang.String
		// @19: pop
		// @1A: goto @48
		// @1D: astore_2
		// @1E: aload_2
		// @1F: new java.lang.StringBuilder
		// @22: dup
		// @23: invokespecial java.lang.StringBuilder.<init>()void
		// @26: getstatic java.lang.String[] game.C_100220_ac.field_106066_z
		// @29: bipush 12 (0x0C)
		// @2B: aaload
		// @2C: invokevirtual java.lang.StringBuilder.append(java.lang.String)java.lang.StringBuilder
		// @2F: iload_0
		// @30: invokevirtual java.lang.StringBuilder.append(boolean)java.lang.StringBuilder
		// @33: bipush 44 (0x2C)
		// @35: invokevirtual java.lang.StringBuilder.append(char)java.lang.StringBuilder
		// @38: iload_1
		// @39: invokevirtual java.lang.StringBuilder.append(int)java.lang.StringBuilder
		// @3C: bipush 41 (0x29)
		// @3E: invokevirtual java.lang.StringBuilder.append(char)java.lang.StringBuilder
		// @41: invokevirtual java.lang.StringBuilder.toString()java.lang.String
		// @44: invokestatic game.C_100181_cf.func_105695_a(java.lang.Throwable, java.lang.String)game.C_100170_cm
		// @47: athrow
		// @48: return
	}
	
	static final String func_106050_a(int[] arg0, int[] arg1, int arg2)
	{
		// @000: getstatic int game.SteelSentinels.field_105275_O
		// @003: istore #9
		// @005: iconst_0
		// @006: istore_3
		// @007: iconst_0
		// @008: istore #4
		// @00A: iconst_0
		// @00B: istore #6
		// @00D: aload_0
		// @00E: arraylength
		// @00F: iload #6
		// @011: if_icmple @050
		// @014: aload_0
		// @015: iload #6
		// @017: iaload
		// @018: bipush 49 (0x31)
		// @01A: iload #9
		// @01C: ifne @057
		// @01F: if_icmpne @02A
		// @022: goto @026
		// @025: athrow
		// @026: bipush 6 (0x06)
		// @028: istore #4
		// @02A: aload_0
		// @02B: iload #6
		// @02D: iaload
		// @02E: iconst_m1
		// @02F: ixor
		// @030: ifne @037
		// @033: goto @03E
		// @036: athrow
		// @037: iload_3
		// @038: aload_0
		// @039: iload #6
		// @03B: iaload
		// @03C: iadd
		// @03D: istore_3
		// @03E: ldc 8388607 (0x7fffff)
		// @040: iload_3
		// @041: bipush 10 (0x0A)
		// @043: imul
		// @044: iload_3
		// @045: ixor
		// @046: iand
		// @047: istore_3
		// @048: iinc #6 +1
		// @04B: iload #9
		// @04D: ifeq @00D
		// @050: iconst_0
		// @051: istore #6
		// @053: iload #6
		// @055: bipush 8 (0x08)
		// @057: if_icmpge @06C
		// @05A: ldc 8388607 (0x7fffff)
		// @05C: iload_3
		// @05D: iload_3
		// @05E: bipush 10 (0x0A)
		// @060: imul
		// @061: ixor
		// @062: iand
		// @063: istore_3
		// @064: iinc #6 +1
		// @067: iload #9
		// @069: ifeq @053
		// @06C: getstatic java.lang.String[] game.C_100179_ch.field_100813_l
		// @06F: iconst_1
		// @070: aaload
		// @071: astore #5
		// @073: aload_0
		// @074: iconst_0
		// @075: iaload
		// @076: iconst_m1
		// @077: invokestatic game.C_100152_bd.func_105179_a(int, int)int
		// @07A: istore #6
		// @07C: iload #6
		// @07E: iconst_m1
		// @07F: ixor
		// @080: iconst_m1
		// @081: if_icmpgt @09D
		// @084: iload #6
		// @086: getstatic java.lang.String[] game.C_100179_ch.field_100813_l
		// @089: arraylength
		// @08A: if_icmplt @095
		// @08D: goto @091
		// @090: athrow
		// @091: goto @09D
		// @094: athrow
		// @095: getstatic java.lang.String[] game.C_100179_ch.field_100813_l
		// @098: iload #6
		// @09A: aaload
		// @09B: astore #5
		// @09D: iload #6
		// @09F: ifeq @0A6
		// @0A2: goto @0AB
		// @0A5: athrow
		// @0A6: iload_3
		// @0A7: ldc 8176765 (0x7cc47d)
		// @0A9: ixor
		// @0AA: istore_3
		// @0AB: new java.lang.StringBuilder
		// @0AE: dup
		// @0AF: invokespecial java.lang.StringBuilder.<init>()void
		// @0B2: aload #5
		// @0B4: invokevirtual java.lang.StringBuilder.append(java.lang.String)java.lang.StringBuilder
		// @0B7: ldc "-"
		// @0B9: invokevirtual java.lang.StringBuilder.append(java.lang.String)java.lang.StringBuilder
		// @0BC: invokevirtual java.lang.StringBuilder.toString()java.lang.String
		// @0BF: astore #5
		// @0C1: iconst_1
		// @0C2: iload #6
		// @0C4: if_icmpeq @0CB
		// @0C7: goto @0D0
		// @0CA: athrow
		// @0CB: iload_3
		// @0CC: ldc 1155849 (0x11a309)
		// @0CE: ixor
		// @0CF: istore_3
		// @0D0: iload #6
		// @0D2: iconst_2
		// @0D3: if_icmpne @0DB
		// @0D6: iload_3
		// @0D7: ldc 5624312 (0x55d1f8)
		// @0D9: ixor
		// @0DA: istore_3
		// @0DB: bipush -4 (0xFC)
		// @0DD: iload #6
		// @0DF: iconst_m1
		// @0E0: ixor
		// @0E1: if_icmpeq @0E8
		// @0E4: goto @0ED
		// @0E7: athrow
		// @0E8: iload_3
		// @0E9: ldc 7177436 (0x6d84dc)
		// @0EB: ixor
		// @0EC: istore_3
		// @0ED: bipush -5 (0xFB)
		// @0EF: iload #6
		// @0F1: iconst_m1
		// @0F2: ixor
		// @0F3: if_icmpeq @0FA
		// @0F6: goto @0FF
		// @0F9: athrow
		// @0FA: iload_3
		// @0FB: ldc 5318225 (0x512651)
		// @0FD: ixor
		// @0FE: istore_3
		// @0FF: iload #6
		// @101: iconst_m1
		// @102: ixor
		// @103: bipush -6 (0xFA)
		// @105: if_icmpeq @10C
		// @108: goto @111
		// @10B: athrow
		// @10C: iload_3
		// @10D: ldc 18177652 (0x1155e74)
		// @10F: ixor
		// @110: istore_3
		// @111: bipush -7 (0xF9)
		// @113: iload #6
		// @115: iconst_m1
		// @116: ixor
		// @117: if_icmpeq @11E
		// @11A: goto @123
		// @11D: athrow
		// @11E: iload_3
		// @11F: ldc 7171409 (0x6d6d51)
		// @121: ixor
		// @122: istore_3
		// @123: iload #6
		// @125: iconst_m1
		// @126: ixor
		// @127: bipush -8 (0xF8)
		// @129: if_icmpeq @130
		// @12C: goto @135
		// @12F: athrow
		// @130: iload_3
		// @131: ldc 3140392 (0x2feb28)
		// @133: ixor
		// @134: istore_3
		// @135: iload #6
		// @137: iconst_m1
		// @138: ixor
		// @139: bipush -9 (0xF7)
		// @13B: if_icmpne @143
		// @13E: iload_3
		// @13F: ldc 5104464 (0x4de350)
		// @141: ixor
		// @142: istore_3
		// @143: iload #6
		// @145: bipush 9 (0x09)
		// @147: if_icmpeq @14E
		// @14A: goto @153
		// @14D: athrow
		// @14E: iload_3
		// @14F: ldc 5940651 (0x5aa5ab)
		// @151: ixor
		// @152: istore_3
		// @153: iload #6
		// @155: bipush 10 (0x0A)
		// @157: if_icmpne @15F
		// @15A: iload_3
		// @15B: ldc 7257749 (0x6ebe95)
		// @15D: ixor
		// @15E: istore_3
		// @15F: iload #6
		// @161: iconst_m1
		// @162: ixor
		// @163: bipush -12 (0xF4)
		// @165: if_icmpeq @16C
		// @168: goto @171
		// @16B: athrow
		// @16C: iload_3
		// @16D: ldc 2016943 (0x1ec6af)
		// @16F: ixor
		// @170: istore_3
		// @171: iload_3
		// @172: istore #7
		// @174: iconst_0
		// @175: istore #8
		// @177: bipush -6 (0xFA)
		// @179: iload #8
		// @17B: iconst_m1
		// @17C: ixor
		// @17D: if_icmpge @20C
		// @180: iload #7
		// @182: bipush 35 (0x23)
		// @184: irem
		// @185: iconst_m1
		// @186: ixor
		// @187: iconst_m1
		// @188: iload #9
		// @18A: ifne @213
		// @18D: if_icmpge @1A4
		// @190: goto @194
		// @193: athrow
		// @194: iload #7
		// @196: bipush 35 (0x23)
		// @198: irem
		// @199: iconst_m1
		// @19A: ixor
		// @19B: bipush -27 (0xE5)
		// @19D: if_icmpgt @1DB
		// @1A0: goto @1A4
		// @1A3: athrow
		// @1A4: bipush 26 (0x1A)
		// @1A6: iload #7
		// @1A8: bipush 35 (0x23)
		// @1AA: irem
		// @1AB: if_icmpgt @1FD
		// @1AE: goto @1B2
		// @1B1: athrow
		// @1B2: new java.lang.StringBuilder
		// @1B5: dup
		// @1B6: invokespecial java.lang.StringBuilder.<init>()void
		// @1B9: aload #5
		// @1BB: invokevirtual java.lang.StringBuilder.append(java.lang.String)java.lang.StringBuilder
		// @1BE: bipush 48 (0x30)
		// @1C0: iload #7
		// @1C2: bipush 35 (0x23)
		// @1C4: irem
		// @1C5: bipush -26 (0xE6)
		// @1C7: iadd
		// @1C8: bipush 10 (0x0A)
		// @1CA: irem
		// @1CB: ineg
		// @1CC: isub
		// @1CD: i2c
		// @1CE: invokevirtual java.lang.StringBuilder.append(char)java.lang.StringBuilder
		// @1D1: invokevirtual java.lang.StringBuilder.toString()java.lang.String
		// @1D4: astore #5
		// @1D6: iload #9
		// @1D8: ifeq @1FD
		// @1DB: new java.lang.StringBuilder
		// @1DE: dup
		// @1DF: invokespecial java.lang.StringBuilder.<init>()void
		// @1E2: aload #5
		// @1E4: invokevirtual java.lang.StringBuilder.append(java.lang.String)java.lang.StringBuilder
		// @1E7: bipush 65 (0x41)
		// @1E9: iload #7
		// @1EB: bipush 35 (0x23)
		// @1ED: irem
		// @1EE: iconst_1
		// @1EF: isub
		// @1F0: bipush 26 (0x1A)
		// @1F2: irem
		// @1F3: iadd
		// @1F4: i2c
		// @1F5: invokevirtual java.lang.StringBuilder.append(char)java.lang.StringBuilder
		// @1F8: invokevirtual java.lang.StringBuilder.toString()java.lang.String
		// @1FB: astore #5
		// @1FD: iload #7
		// @1FF: bipush 35 (0x23)
		// @201: idiv
		// @202: istore #7
		// @204: iinc #8 +1
		// @207: iload #9
		// @209: ifeq @177
		// @20C: iconst_0
		// @20D: istore #8
		// @20F: aload_1
		// @210: arraylength
		// @211: iload #8
		// @213: if_icmple @3C7
		// @216: iconst_m1
		// @217: aload_1
		// @218: iload #8
		// @21A: iaload
		// @21B: iconst_m1
		// @21C: ixor
		// @21D: iload #9
		// @21F: ifne @3CD
		// @222: goto @226
		// @225: athrow
		// @226: if_icmpne @23A
		// @229: goto @22D
		// @22C: athrow
		// @22D: iconst_1
		// @22E: iload #4
		// @230: if_icmple @23A
		// @233: goto @237
		// @236: athrow
		// @237: iconst_1
		// @238: istore #4
		// @23A: aload_1
		// @23B: iload #8
		// @23D: iaload
		// @23E: iconst_1
		// @23F: if_icmpne @253
		// @242: iload #4
		// @244: iconst_2
		// @245: if_icmplt @250
		// @248: goto @24C
		// @24B: athrow
		// @24C: goto @253
		// @24F: athrow
		// @250: iconst_2
		// @251: istore #4
		// @253: aload_1
		// @254: iload #8
		// @256: iaload
		// @257: iconst_m1
		// @258: ixor
		// @259: bipush -3 (0xFD)
		// @25B: if_icmpne @272
		// @25E: bipush -4 (0xFC)
		// @260: iload #4
		// @262: iconst_m1
		// @263: ixor
		// @264: if_icmplt @26F
		// @267: goto @26B
		// @26A: athrow
		// @26B: goto @272
		// @26E: athrow
		// @26F: iconst_3
		// @270: istore #4
		// @272: bipush -4 (0xFC)
		// @274: aload_1
		// @275: iload #8
		// @277: iaload
		// @278: iconst_m1
		// @279: ixor
		// @27A: if_icmpne @28D
		// @27D: bipush -5 (0xFB)
		// @27F: iload #4
		// @281: iconst_m1
		// @282: ixor
		// @283: if_icmpge @28D
		// @286: goto @28A
		// @289: athrow
		// @28A: iconst_4
		// @28B: istore #4
		// @28D: iconst_4
		// @28E: aload_1
		// @28F: iload #8
		// @291: iaload
		// @292: if_icmpne @2A5
		// @295: bipush -6 (0xFA)
		// @297: iload #4
		// @299: iconst_m1
		// @29A: ixor
		// @29B: if_icmpge @2A5
		// @29E: goto @2A2
		// @2A1: athrow
		// @2A2: iconst_5
		// @2A3: istore #4
		// @2A5: aload_1
		// @2A6: iload #8
		// @2A8: iaload
		// @2A9: iconst_5
		// @2AA: if_icmpne @2BA
		// @2AD: iconst_1
		// @2AE: iload #4
		// @2B0: if_icmple @2BA
		// @2B3: goto @2B7
		// @2B6: athrow
		// @2B7: iconst_1
		// @2B8: istore #4
		// @2BA: bipush -7 (0xF9)
		// @2BC: aload_1
		// @2BD: iload #8
		// @2BF: iaload
		// @2C0: iconst_m1
		// @2C1: ixor
		// @2C2: if_icmpne @2D6
		// @2C5: iconst_2
		// @2C6: iload #4
		// @2C8: if_icmpgt @2D3
		// @2CB: goto @2CF
		// @2CE: athrow
		// @2CF: goto @2D6
		// @2D2: athrow
		// @2D3: iconst_2
		// @2D4: istore #4
		// @2D6: bipush 7 (0x07)
		// @2D8: aload_1
		// @2D9: iload #8
		// @2DB: iaload
		// @2DC: if_icmpne @2F3
		// @2DF: iload #4
		// @2E1: iconst_m1
		// @2E2: ixor
		// @2E3: bipush -4 (0xFC)
		// @2E5: if_icmpgt @2F0
		// @2E8: goto @2EC
		// @2EB: athrow
		// @2EC: goto @2F3
		// @2EF: athrow
		// @2F0: iconst_3
		// @2F1: istore #4
		// @2F3: aload_1
		// @2F4: iload #8
		// @2F6: iaload
		// @2F7: bipush 8 (0x08)
		// @2F9: if_icmpne @309
		// @2FC: iload #4
		// @2FE: iconst_4
		// @2FF: if_icmpge @309
		// @302: goto @306
		// @305: athrow
		// @306: iconst_4
		// @307: istore #4
		// @309: bipush -10 (0xF6)
		// @30B: aload_1
		// @30C: iload #8
		// @30E: iaload
		// @30F: iconst_m1
		// @310: ixor
		// @311: if_icmpne @328
		// @314: iload #4
		// @316: iconst_m1
		// @317: ixor
		// @318: bipush -6 (0xFA)
		// @31A: if_icmpgt @325
		// @31D: goto @321
		// @320: athrow
		// @321: goto @328
		// @324: athrow
		// @325: iconst_5
		// @326: istore #4
		// @328: bipush 10 (0x0A)
		// @32A: aload_1
		// @32B: iload #8
		// @32D: iaload
		// @32E: if_icmpne @342
		// @331: iload #4
		// @333: iconst_1
		// @334: if_icmplt @33F
		// @337: goto @33B
		// @33A: athrow
		// @33B: goto @342
		// @33E: athrow
		// @33F: iconst_1
		// @340: istore #4
		// @342: aload_1
		// @343: iload #8
		// @345: iaload
		// @346: bipush 11 (0x0B)
		// @348: if_icmpne @35C
		// @34B: iconst_2
		// @34C: iload #4
		// @34E: if_icmpgt @359
		// @351: goto @355
		// @354: athrow
		// @355: goto @35C
		// @358: athrow
		// @359: iconst_2
		// @35A: istore #4
		// @35C: aload_1
		// @35D: iload #8
		// @35F: iaload
		// @360: bipush 12 (0x0C)
		// @362: if_icmpne @372
		// @365: iload #4
		// @367: iconst_3
		// @368: if_icmpge @372
		// @36B: goto @36F
		// @36E: athrow
		// @36F: iconst_3
		// @370: istore #4
		// @372: bipush 13 (0x0D)
		// @374: aload_1
		// @375: iload #8
		// @377: iaload
		// @378: if_icmpne @38C
		// @37B: iconst_4
		// @37C: iload #4
		// @37E: if_icmpgt @389
		// @381: goto @385
		// @384: athrow
		// @385: goto @38C
		// @388: athrow
		// @389: iconst_4
		// @38A: istore #4
		// @38C: bipush 14 (0x0E)
		// @38E: aload_1
		// @38F: iload #8
		// @391: iaload
		// @392: if_icmpne @3A5
		// @395: bipush -6 (0xFA)
		// @397: iload #4
		// @399: iconst_m1
		// @39A: ixor
		// @39B: if_icmpge @3A5
		// @39E: goto @3A2
		// @3A1: athrow
		// @3A2: iconst_5
		// @3A3: istore #4
		// @3A5: aload_1
		// @3A6: iload #8
		// @3A8: iaload
		// @3A9: iconst_m1
		// @3AA: ixor
		// @3AB: bipush -21 (0xEB)
		// @3AD: if_icmpne @3BF
		// @3B0: bipush 6 (0x06)
		// @3B2: iload #4
		// @3B4: if_icmple @3BF
		// @3B7: goto @3BB
		// @3BA: athrow
		// @3BB: bipush 6 (0x06)
		// @3BD: istore #4
		// @3BF: iinc #8 +1
		// @3C2: iload #9
		// @3C4: ifeq @20F
		// @3C7: iload #4
		// @3C9: iconst_m1
		// @3CA: ixor
		// @3CB: bipush -2 (0xFE)
		// @3CD: if_icmpne @3EA
		// @3D0: new java.lang.StringBuilder
		// @3D3: dup
		// @3D4: invokespecial java.lang.StringBuilder.<init>()void
		// @3D7: aload #5
		// @3D9: invokevirtual java.lang.StringBuilder.append(java.lang.String)java.lang.StringBuilder
		// @3DC: getstatic java.lang.String[] game.C_100220_ac.field_106066_z
		// @3DF: bipush 10 (0x0A)
		// @3E1: aaload
		// @3E2: invokevirtual java.lang.StringBuilder.append(java.lang.String)java.lang.StringBuilder
		// @3E5: invokevirtual java.lang.StringBuilder.toString()java.lang.String
		// @3E8: astore #5
		// @3EA: iload #4
		// @3EC: iconst_m1
		// @3ED: ixor
		// @3EE: bipush -3 (0xFD)
		// @3F0: if_icmpeq @3F7
		// @3F3: goto @411
		// @3F6: athrow
		// @3F7: new java.lang.StringBuilder
		// @3FA: dup
		// @3FB: invokespecial java.lang.StringBuilder.<init>()void
		// @3FE: aload #5
		// @400: invokevirtual java.lang.StringBuilder.append(java.lang.String)java.lang.StringBuilder
		// @403: getstatic java.lang.String[] game.C_100220_ac.field_106066_z
		// @406: bipush 7 (0x07)
		// @408: aaload
		// @409: invokevirtual java.lang.StringBuilder.append(java.lang.String)java.lang.StringBuilder
		// @40C: invokevirtual java.lang.StringBuilder.toString()java.lang.String
		// @40F: astore #5
		// @411: iconst_3
		// @412: iload #4
		// @414: if_icmpne @431
		// @417: new java.lang.StringBuilder
		// @41A: dup
		// @41B: invokespecial java.lang.StringBuilder.<init>()void
		// @41E: aload #5
		// @420: invokevirtual java.lang.StringBuilder.append(java.lang.String)java.lang.StringBuilder
		// @423: getstatic java.lang.String[] game.C_100220_ac.field_106066_z
		// @426: bipush 8 (0x08)
		// @428: aaload
		// @429: invokevirtual java.lang.StringBuilder.append(java.lang.String)java.lang.StringBuilder
		// @42C: invokevirtual java.lang.StringBuilder.toString()java.lang.String
		// @42F: astore #5
		// @431: iload #4
		// @433: iconst_4
		// @434: if_icmpne @451
		// @437: new java.lang.StringBuilder
		// @43A: dup
		// @43B: invokespecial java.lang.StringBuilder.<init>()void
		// @43E: aload #5
		// @440: invokevirtual java.lang.StringBuilder.append(java.lang.String)java.lang.StringBuilder
		// @443: getstatic java.lang.String[] game.C_100220_ac.field_106066_z
		// @446: bipush 9 (0x09)
		// @448: aaload
		// @449: invokevirtual java.lang.StringBuilder.append(java.lang.String)java.lang.StringBuilder
		// @44C: invokevirtual java.lang.StringBuilder.toString()java.lang.String
		// @44F: astore #5
		// @451: iload #4
		// @453: iconst_m1
		// @454: ixor
		// @455: bipush -6 (0xFA)
		// @457: if_icmpne @474
		// @45A: new java.lang.StringBuilder
		// @45D: dup
		// @45E: invokespecial java.lang.StringBuilder.<init>()void
		// @461: aload #5
		// @463: invokevirtual java.lang.StringBuilder.append(java.lang.String)java.lang.StringBuilder
		// @466: getstatic java.lang.String[] game.C_100220_ac.field_106066_z
		// @469: bipush 6 (0x06)
		// @46B: aaload
		// @46C: invokevirtual java.lang.StringBuilder.append(java.lang.String)java.lang.StringBuilder
		// @46F: invokevirtual java.lang.StringBuilder.toString()java.lang.String
		// @472: astore #5
		// @474: iload #4
		// @476: iconst_m1
		// @477: ixor
		// @478: bipush -7 (0xF9)
		// @47A: if_icmpeq @481
		// @47D: goto @49A
		// @480: athrow
		// @481: new java.lang.StringBuilder
		// @484: dup
		// @485: invokespecial java.lang.StringBuilder.<init>()void
		// @488: aload #5
		// @48A: invokevirtual java.lang.StringBuilder.append(java.lang.String)java.lang.StringBuilder
		// @48D: getstatic java.lang.String[] game.C_100220_ac.field_106066_z
		// @490: iconst_4
		// @491: aaload
		// @492: invokevirtual java.lang.StringBuilder.append(java.lang.String)java.lang.StringBuilder
		// @495: invokevirtual java.lang.StringBuilder.toString()java.lang.String
		// @498: astore #5
		// @49A: iload_2
		// @49B: bipush 7 (0x07)
		// @49D: if_icmpgt @4AB
		// @4A0: aconst_null
		// @4A1: checkcast java.lang.String
		// @4A4: putstatic java.lang.String game.C_100220_ac.field_106060_l
		// @4A7: goto @4AB
		// @4AA: athrow
		// @4AB: aload #5
		// @4AD: areturn
		// @4AE: astore_3
		// @4AF: aload_3
		// @4B0: new java.lang.StringBuilder
		// @4B3: dup
		// @4B4: invokespecial java.lang.StringBuilder.<init>()void
		// @4B7: getstatic java.lang.String[] game.C_100220_ac.field_106066_z
		// @4BA: iconst_5
		// @4BB: aaload
		// @4BC: invokevirtual java.lang.StringBuilder.append(java.lang.String)java.lang.StringBuilder
		// @4BF: aload_0
		// @4C0: ifnull @4CC
		// @4C3: getstatic java.lang.String[] game.C_100220_ac.field_106066_z
		// @4C6: iconst_2
		// @4C7: aaload
		// @4C8: goto @4D1
		// @4CB: athrow
		// @4CC: getstatic java.lang.String[] game.C_100220_ac.field_106066_z
		// @4CF: iconst_0
		// @4D0: aaload
		// @4D1: invokevirtual java.lang.StringBuilder.append(java.lang.String)java.lang.StringBuilder
		// @4D4: bipush 44 (0x2C)
		// @4D6: invokevirtual java.lang.StringBuilder.append(char)java.lang.StringBuilder
		// @4D9: aload_1
		// @4DA: ifnull @4E6
		// @4DD: getstatic java.lang.String[] game.C_100220_ac.field_106066_z
		// @4E0: iconst_2
		// @4E1: aaload
		// @4E2: goto @4EB
		// @4E5: athrow
		// @4E6: getstatic java.lang.String[] game.C_100220_ac.field_106066_z
		// @4E9: iconst_0
		// @4EA: aaload
		// @4EB: invokevirtual java.lang.StringBuilder.append(java.lang.String)java.lang.StringBuilder
		// @4EE: bipush 44 (0x2C)
		// @4F0: invokevirtual java.lang.StringBuilder.append(char)java.lang.StringBuilder
		// @4F3: iload_2
		// @4F4: invokevirtual java.lang.StringBuilder.append(int)java.lang.StringBuilder
		// @4F7: bipush 41 (0x29)
		// @4F9: invokevirtual java.lang.StringBuilder.append(char)java.lang.StringBuilder
		// @4FC: invokevirtual java.lang.StringBuilder.toString()java.lang.String
		// @4FF: invokestatic game.C_100181_cf.func_105695_a(java.lang.Throwable, java.lang.String)game.C_100170_cm
		// @502: athrow
	}
	
	static
	{
		// @00: bipush 13 (0x0D)
		// @02: anewarray java.lang.String
		// @05: dup
		// @06: iconst_0
		// @07: ldc "|tbU"
		// @09: invokestatic game.C_100220_ac.func_106049_z(java.lang.String)char[]
		// @0C: invokestatic game.C_100220_ac.func_106048_z(char[])java.lang.String
		// @0F: aastore
		// @10: dup
		// @11: iconst_1
		// @12: ldc "sb \u0005:|hz\u0007{"
		// @14: invokestatic game.C_100220_ac.func_106049_z(java.lang.String)char[]
		// @17: invokestatic game.C_100220_ac.func_106048_z(char[])java.lang.String
		// @1A: aastore
		// @1B: dup
		// @1C: iconst_2
		// @1D: ldc "i/ \u0017."
		// @1F: invokestatic game.C_100220_ac.func_106049_z(java.lang.String)char[]
		// @22: invokestatic game.C_100220_ac.func_106048_z(char[])java.lang.String
		// @25: aastore
		// @26: dup
		// @27: iconst_3
		// @28: ldc "sb x{"
		// @2A: invokestatic game.C_100220_ac.func_106049_z(java.lang.String)char[]
		// @2D: invokestatic game.C_100220_ac.func_106048_z(char[])java.lang.String
		// @30: aastore
		// @31: dup
		// @32: iconst_4
		// @33: ldc "?=gT4/06\u0007"
		// @35: invokestatic game.C_100220_ac.func_106049_z(java.lang.String)char[]
		// @38: invokestatic game.C_100220_ac.func_106048_z(char[])java.lang.String
		// @3B: aastore
		// @3C: dup
		// @3D: iconst_5
		// @3E: ldc "sb {{"
		// @40: invokestatic game.C_100220_ac.func_106049_z(java.lang.String)char[]
		// @43: invokestatic game.C_100220_ac.func_106048_z(char[])java.lang.String
		// @46: aastore
		// @47: dup
		// @48: bipush 6 (0x06)
		// @4A: ldc "?W;"
		// @4C: invokestatic game.C_100220_ac.func_106049_z(java.lang.String)char[]
		// @4F: invokestatic game.C_100220_ac.func_106048_z(char[])java.lang.String
		// @52: aastore
		// @53: dup
		// @54: bipush 7 (0x07)
		// @56: ldc "?W<"
		// @58: invokestatic game.C_100220_ac.func_106049_z(java.lang.String)char[]
		// @5B: invokestatic game.C_100220_ac.func_106048_z(char[])java.lang.String
		// @5E: aastore
		// @5F: dup
		// @60: bipush 8 (0x08)
		// @62: ldc "?W="
		// @64: invokestatic game.C_100220_ac.func_106049_z(java.lang.String)char[]
		// @67: invokestatic game.C_100220_ac.func_106048_z(char[])java.lang.String
		// @6A: aastore
		// @6B: dup
		// @6C: bipush 9 (0x09)
		// @6E: ldc "?W:"
		// @70: invokestatic game.C_100220_ac.func_106049_z(java.lang.String)char[]
		// @73: invokestatic game.C_100220_ac.func_106048_z(char[])java.lang.String
		// @76: aastore
		// @77: dup
		// @78: bipush 10 (0x0A)
		// @7A: ldc "?W?"
		// @7C: invokestatic game.C_100220_ac.func_106049_z(java.lang.String)char[]
		// @7F: invokestatic game.C_100220_ac.func_106048_z(char[])java.lang.String
		// @82: aastore
		// @83: dup
		// @84: bipush 11 (0x0B)
		// @86: ldc "sb z{"
		// @88: invokestatic game.C_100220_ac.func_106049_z(java.lang.String)char[]
		// @8B: invokestatic game.C_100220_ac.func_106048_z(char[])java.lang.String
		// @8E: aastore
		// @8F: dup
		// @90: bipush 12 (0x0C)
		// @92: ldc "sb }{"
		// @94: invokestatic game.C_100220_ac.func_106049_z(java.lang.String)char[]
		// @97: invokestatic game.C_100220_ac.func_106048_z(char[])java.lang.String
		// @9A: aastore
		// @9B: putstatic java.lang.String[] game.C_100220_ac.field_106066_z
		// @9E: ldc "Znb] 20.\u0005'{lkJm2=+\tm"
		// @A0: invokestatic game.C_100220_ac.func_106049_z(java.lang.String)char[]
		// @A3: invokestatic game.C_100220_ac.func_106048_z(char[])java.lang.String
		// @A6: putstatic java.lang.String game.C_100220_ac.field_106055_d
		// @A9: ldc "E`gM:|f._<`!}V&|e.\\5tdmM "
		// @AB: invokestatic game.C_100220_ac.func_106049_z(java.lang.String)char[]
		// @AE: invokestatic game.C_100220_ac.func_106048_z(char[])java.lang.String
		// @B1: putstatic java.lang.String game.C_100220_ac.field_106060_l
		// @B4: new game.C_100068_vc
		// @B7: dup
		// @B8: invokespecial game.C_100068_vc.<init>()void
		// @BB: putstatic game.C_100068_vc game.C_100220_ac.field_106056_e
		// @BE: ldc "SMZ\u0012o{li\u0004a$?.]!}q}\u0019'ssi\\'2maZ8(!A_5"
		// @C0: invokestatic game.C_100220_ac.func_106049_z(java.lang.String)char[]
		// @C3: invokestatic game.C_100220_ac.func_106048_z(char[])java.lang.String
		// @C6: putstatic java.lang.String game.C_100220_ac.field_106063_k
		// @C9: ldc "Sej\u0019o710\u0019'}!hK:woj\u0019?{rz"
		// @CB: invokestatic game.C_100220_ac.func_106049_z(java.lang.String)char[]
		// @CE: invokestatic game.C_100220_ac.func_106048_z(char[])java.lang.String
		// @D1: putstatic java.lang.String game.C_100220_ac.field_106061_m
		// @D4: iconst_0
		// @D5: putstatic int game.C_100220_ac.field_106058_c
		// @D8: return
	}
	
	private static char[] func_106049_z(String arg0)
	{
		// @00: aload_0
		// @01: invokevirtual java.lang.String.toCharArray()char[]
		// @04: dup
		// @05: arraylength
		// @06: iconst_2
		// @07: if_icmpge @13
		// @0A: dup
		// @0B: iconst_0
		// @0C: dup2
		// @0D: caload
		// @0E: bipush 83 (0x53)
		// @10: ixor
		// @11: i2c
		// @12: castore
		// @13: areturn
	}
	
	private static String func_106048_z(char[] arg0)
	{
		// @00: aload_0
		// @01: dup
		// @02: arraylength
		// @03: swap
		// @04: iconst_0
		// @05: istore_1
		// @06: goto @4B
		// @09: dup
		// @0A: iload_1
		// @0B: dup2
		// @0C: caload
		// @0D: iload_1
		// @0E: iconst_5
		// @0F: irem
		// @10: tableswitch def: @43, for 0: @30, for 1: @35, for 2: @39, for 3: @3E
		// @30: bipush 18 (0x12)
		// @32: goto @45
		// @35: iconst_1
		// @36: goto @45
		// @39: bipush 14 (0x0E)
		// @3B: goto @45
		// @3E: bipush 57 (0x39)
		// @40: goto @45
		// @43: bipush 83 (0x53)
		// @45: ixor
		// @46: i2c
		// @47: castore
		// @48: iinc #1 +1
		// @4B: swap
		// @4C: dup_x1
		// @4D: iload_1
		// @4E: if_icmpgt @09
		// @51: new java.lang.String
		// @54: dup_x1
		// @55: swap
		// @56: invokespecial java.lang.String.<init>(char[])void
		// @59: invokevirtual java.lang.String.intern()java.lang.String
		// @5C: areturn
	}
}
