package game;

import java.applet.Applet;

final class C_100222_aa
{
	static C_100193_re field_106085_c;
	static int field_106083_e;
	private C_100248_pb[] field_106090_h;
	static String field_106082_d;
	static int[] field_106080_f;
	static String field_106091_i;
	static String field_106081_g;
	static C_100068_vc field_106086_a;
	private C_100250_pl field_106089_k;
	static String field_106084_b;
	static String field_106087_j;
	private static final String[] field_106088_z;
	
	static final void func_106073_b(int arg0)
	{
		// @00: bipush 112 (0x70)
		// @02: invokestatic game.C_100325_id.func_101477_h(int)void
		// @05: iload_0
		// @06: bipush 16 (0x10)
		// @08: if_icmpeq @18
		// @0B: bipush -9 (0xF7)
		// @0D: bipush -127 (0x81)
		// @0F: bipush 9 (0x09)
		// @11: bipush 106 (0x6A)
		// @13: bipush 36 (0x24)
		// @15: invokestatic game.C_100222_aa.func_106075_a(int, int, int, byte, int)void
		// @18: goto @3D
		// @1B: astore_1
		// @1C: aload_1
		// @1D: new java.lang.StringBuilder
		// @20: dup
		// @21: invokespecial java.lang.StringBuilder.<init>()void
		// @24: getstatic java.lang.String[] game.C_100222_aa.field_106088_z
		// @27: bipush 6 (0x06)
		// @29: aaload
		// @2A: invokevirtual java.lang.StringBuilder.append(java.lang.String)java.lang.StringBuilder
		// @2D: iload_0
		// @2E: invokevirtual java.lang.StringBuilder.append(int)java.lang.StringBuilder
		// @31: bipush 41 (0x29)
		// @33: invokevirtual java.lang.StringBuilder.append(char)java.lang.StringBuilder
		// @36: invokevirtual java.lang.StringBuilder.toString()java.lang.String
		// @39: invokestatic game.C_100181_cf.func_105695_a(java.lang.Throwable, java.lang.String)game.C_100170_cm
		// @3C: athrow
		// @3D: return
	}
	
	static final void func_106079_a(int arg0, Applet arg1, String arg2, boolean arg3)
	{
		// @00: iload_0
		// @01: sipush -17250 (0xBC9E)
		// @04: if_icmpeq @08
		// @07: return
		// @08: getstatic java.lang.String game.C_100201_qj.field_105872_d
		// @0B: getstatic java.lang.String[] game.C_100222_aa.field_106088_z
		// @0E: iconst_4
		// @0F: aaload
		// @10: invokevirtual java.lang.String.startsWith(java.lang.String)boolean
		// @13: ifeq @2A
		// @16: aload_2
		// @17: iload_0
		// @18: ldc 38197 (0x9535)
		// @1A: iadd
		// @1B: invokestatic game.C_100339_jb.func_107374_a(java.lang.String, int)boolean
		// @1E: ifne @29
		// @21: goto @25
		// @24: athrow
		// @25: goto @2A
		// @28: athrow
		// @29: return
		// @2A: aload_1
		// @2B: invokevirtual java.applet.Applet.getAppletContext()java.applet.AppletContext
		// @2E: new java.net.URL
		// @31: dup
		// @32: aload_2
		// @33: invokespecial java.net.URL.<init>(java.lang.String)void
		// @36: getstatic java.lang.String[] game.C_100222_aa.field_106088_z
		// @39: iconst_0
		// @3A: aaload
		// @3B: invokeinterface java.applet.AppletContext.showDocument(java.net.URL, java.lang.String)void
		// @40: goto @64
		// @43: astore #4
		// @45: iload_0
		// @46: sipush 17251 (0x4363)
		// @49: iadd
		// @4A: new java.lang.StringBuilder
		// @4D: dup
		// @4E: invokespecial java.lang.StringBuilder.<init>()void
		// @51: getstatic java.lang.String[] game.C_100222_aa.field_106088_z
		// @54: iconst_1
		// @55: aaload
		// @56: invokevirtual java.lang.StringBuilder.append(java.lang.String)java.lang.StringBuilder
		// @59: aload_2
		// @5A: invokevirtual java.lang.StringBuilder.append(java.lang.String)java.lang.StringBuilder
		// @5D: invokevirtual java.lang.StringBuilder.toString()java.lang.String
		// @60: aconst_null
		// @61: invokestatic game.C_100036_gg.func_103142_a(int, java.lang.String, java.lang.Throwable)void
		// @64: goto @C7
		// @67: astore #4
		// @69: aload #4
		// @6B: new java.lang.StringBuilder
		// @6E: dup
		// @6F: invokespecial java.lang.StringBuilder.<init>()void
		// @72: getstatic java.lang.String[] game.C_100222_aa.field_106088_z
		// @75: iconst_2
		// @76: aaload
		// @77: invokevirtual java.lang.StringBuilder.append(java.lang.String)java.lang.StringBuilder
		// @7A: iload_0
		// @7B: invokevirtual java.lang.StringBuilder.append(int)java.lang.StringBuilder
		// @7E: bipush 44 (0x2C)
		// @80: invokevirtual java.lang.StringBuilder.append(char)java.lang.StringBuilder
		// @83: aload_1
		// @84: ifnull @90
		// @87: getstatic java.lang.String[] game.C_100222_aa.field_106088_z
		// @8A: iconst_5
		// @8B: aaload
		// @8C: goto @95
		// @8F: athrow
		// @90: getstatic java.lang.String[] game.C_100222_aa.field_106088_z
		// @93: iconst_3
		// @94: aaload
		// @95: invokevirtual java.lang.StringBuilder.append(java.lang.String)java.lang.StringBuilder
		// @98: bipush 44 (0x2C)
		// @9A: invokevirtual java.lang.StringBuilder.append(char)java.lang.StringBuilder
		// @9D: aload_2
		// @9E: ifnull @AA
		// @A1: getstatic java.lang.String[] game.C_100222_aa.field_106088_z
		// @A4: iconst_5
		// @A5: aaload
		// @A6: goto @AF
		// @A9: athrow
		// @AA: getstatic java.lang.String[] game.C_100222_aa.field_106088_z
		// @AD: iconst_3
		// @AE: aaload
		// @AF: invokevirtual java.lang.StringBuilder.append(java.lang.String)java.lang.StringBuilder
		// @B2: bipush 44 (0x2C)
		// @B4: invokevirtual java.lang.StringBuilder.append(char)java.lang.StringBuilder
		// @B7: iload_3
		// @B8: invokevirtual java.lang.StringBuilder.append(boolean)java.lang.StringBuilder
		// @BB: bipush 41 (0x29)
		// @BD: invokevirtual java.lang.StringBuilder.append(char)java.lang.StringBuilder
		// @C0: invokevirtual java.lang.StringBuilder.toString()java.lang.String
		// @C3: invokestatic game.C_100181_cf.func_105695_a(java.lang.Throwable, java.lang.String)game.C_100170_cm
		// @C6: athrow
		// @C7: return
	}
	
	final void func_106078_a(int arg0, String arg1, int arg2, int arg3)
	{
		// @00: iload_3
		// @01: iflt @15
		// @04: aload_0
		// @05: getfield game.C_100248_pb[] game.C_100222_aa.field_106090_h
		// @08: arraylength
		// @09: iload_3
		// @0A: if_icmple @15
		// @0D: goto @11
		// @10: athrow
		// @11: goto @16
		// @14: athrow
		// @15: return
		// @16: iload #4
		// @18: iload_1
		// @19: if_icmpgt @28
		// @1C: iload_1
		// @1D: aload_0
		// @1E: getfield game.C_100250_pl game.C_100222_aa.field_106089_k
		// @21: getfield java.lang.String[] game.C_100250_pl.field_106435_e
		// @24: arraylength
		// @25: if_icmplt @29
		// @28: return
		// @29: aload_0
		// @2A: getfield game.C_100248_pb[] game.C_100222_aa.field_106090_h
		// @2D: iload_3
		// @2E: aaload
		// @2F: getfield java.lang.String[] game.C_100248_pb.field_106427_a
		// @32: iload_1
		// @33: aload_2
		// @34: aastore
		// @35: goto @89
		// @38: astore #5
		// @3A: aload #5
		// @3C: new java.lang.StringBuilder
		// @3F: dup
		// @40: invokespecial java.lang.StringBuilder.<init>()void
		// @43: getstatic java.lang.String[] game.C_100222_aa.field_106088_z
		// @46: bipush 10 (0x0A)
		// @48: aaload
		// @49: invokevirtual java.lang.StringBuilder.append(java.lang.String)java.lang.StringBuilder
		// @4C: iload_1
		// @4D: invokevirtual java.lang.StringBuilder.append(int)java.lang.StringBuilder
		// @50: bipush 44 (0x2C)
		// @52: invokevirtual java.lang.StringBuilder.append(char)java.lang.StringBuilder
		// @55: aload_2
		// @56: ifnull @62
		// @59: getstatic java.lang.String[] game.C_100222_aa.field_106088_z
		// @5C: iconst_5
		// @5D: aaload
		// @5E: goto @67
		// @61: athrow
		// @62: getstatic java.lang.String[] game.C_100222_aa.field_106088_z
		// @65: iconst_3
		// @66: aaload
		// @67: invokevirtual java.lang.StringBuilder.append(java.lang.String)java.lang.StringBuilder
		// @6A: bipush 44 (0x2C)
		// @6C: invokevirtual java.lang.StringBuilder.append(char)java.lang.StringBuilder
		// @6F: iload_3
		// @70: invokevirtual java.lang.StringBuilder.append(int)java.lang.StringBuilder
		// @73: bipush 44 (0x2C)
		// @75: invokevirtual java.lang.StringBuilder.append(char)java.lang.StringBuilder
		// @78: iload #4
		// @7A: invokevirtual java.lang.StringBuilder.append(int)java.lang.StringBuilder
		// @7D: bipush 41 (0x29)
		// @7F: invokevirtual java.lang.StringBuilder.append(char)java.lang.StringBuilder
		// @82: invokevirtual java.lang.StringBuilder.toString()java.lang.String
		// @85: invokestatic game.C_100181_cf.func_105695_a(java.lang.Throwable, java.lang.String)game.C_100170_cm
		// @88: athrow
		// @89: return
	}
	
	static final void func_106075_a(int arg0, int arg1, int arg2, byte arg3, int arg4)
	{
		// @000: getstatic int game.SteelSentinels.field_105275_O
		// @003: istore #32
		// @005: getstatic int[] game.C_100196_rb.field_105818_d
		// @008: arraylength
		// @009: iconst_m1
		// @00A: ixor
		// @00B: ldc -307201 (0xfffb4fff)
		// @00D: if_icmple @011
		// @010: return
		// @011: iload_2
		// @012: istore #5
		// @014: sipush 1000 (0x03E8)
		// @017: iload_0
		// @018: if_icmple @01F
		// @01B: sipush 1000 (0x03E8)
		// @01E: istore_0
		// @01F: iload_1
		// @020: istore #6
		// @022: iload #4
		// @024: iload #4
		// @026: imul
		// @027: istore #7
		// @029: iload #5
		// @02B: iload #4
		// @02D: ineg
		// @02E: iadd
		// @02F: ldc -528442940 (0xe08099c4)
		// @031: ishr
		// @032: istore #8
		// @034: iload #5
		// @036: bipush -15 (0xF1)
		// @038: isub
		// @039: ldc 803825988 (0x2fe96944)
		// @03B: ishr
		// @03C: istore #9
		// @03E: iload #4
		// @040: iload #5
		// @042: bipush 15 (0x0F)
		// @044: iadd
		// @045: iadd
		// @046: ldc -667166588 (0xd83bd884)
		// @048: ishr
		// @049: istore #10
		// @04B: iload #4
		// @04D: ineg
		// @04E: iload #6
		// @050: iadd
		// @051: ldc 757926212 (0x2d2d0944)
		// @053: ishr
		// @054: istore #11
		// @056: iload #6
		// @058: bipush -15 (0xF1)
		// @05A: isub
		// @05B: ldc 2126627140 (0x7ec1c144)
		// @05D: ishr
		// @05E: istore #12
		// @060: sipush -641 (0xFD7F)
		// @063: iload #10
		// @065: iconst_m1
		// @066: ixor
		// @067: if_icmple @06F
		// @06A: sipush 640 (0x0280)
		// @06D: istore #10
		// @06F: iconst_0
		// @070: iload #8
		// @072: if_icmple @078
		// @075: iconst_0
		// @076: istore #8
		// @078: iload #11
		// @07A: iflt @081
		// @07D: goto @084
		// @080: athrow
		// @081: iconst_0
		// @082: istore #11
		// @084: iload #6
		// @086: iload #4
		// @088: ineg
		// @089: bipush 15 (0x0F)
		// @08B: isub
		// @08C: isub
		// @08D: ldc 944383940 (0x384a27c4)
		// @08F: ishr
		// @090: istore #13
		// @092: iload #13
		// @094: sipush 480 (0x01E0)
		// @097: if_icmple @09F
		// @09A: sipush 480 (0x01E0)
		// @09D: istore #13
		// @09F: iload #9
		// @0A1: ifge @0A7
		// @0A4: iconst_0
		// @0A5: istore #9
		// @0A7: iconst_0
		// @0A8: iload #12
		// @0AA: if_icmpgt @0B1
		// @0AD: goto @0B4
		// @0B0: athrow
		// @0B1: iconst_0
		// @0B2: istore #12
		// @0B4: iload_3
		// @0B5: bipush 125 (0x7D)
		// @0B7: if_icmpgt @0C5
		// @0BA: aconst_null
		// @0BB: checkcast game.C_100193_re
		// @0BE: putstatic game.C_100193_re game.C_100222_aa.field_106085_c
		// @0C1: goto @0C5
		// @0C4: athrow
		// @0C5: iload #9
		// @0C7: sipush 640 (0x0280)
		// @0CA: if_icmple @0D2
		// @0CD: sipush 640 (0x0280)
		// @0D0: istore #9
		// @0D2: sipush -481 (0xFE1F)
		// @0D5: iload #12
		// @0D7: iconst_m1
		// @0D8: ixor
		// @0D9: if_icmpgt @0E0
		// @0DC: goto @0E5
		// @0DF: athrow
		// @0E0: sipush 480 (0x01E0)
		// @0E3: istore #12
		// @0E5: iload #5
		// @0E7: ineg
		// @0E8: iload #9
		// @0EA: ldc 425660932 (0x195f1204)
		// @0EC: ishl
		// @0ED: iadd
		// @0EE: istore #14
		// @0F0: iload #14
		// @0F2: iload #14
		// @0F4: imul
		// @0F5: istore #14
		// @0F7: iconst_1
		// @0F8: iload #9
		// @0FA: iadd
		// @0FB: ldc -692895740 (0xd6b34004)
		// @0FD: ishl
		// @0FE: iload #5
		// @100: ineg
		// @101: iadd
		// @102: istore #15
		// @104: iload #15
		// @106: iload #15
		// @108: imul
		// @109: istore #15
		// @10B: iload #5
		// @10D: ineg
		// @10E: iconst_2
		// @10F: iload #9
		// @111: iadd
		// @112: ldc -1584250908 (0xa1923fe4)
		// @114: ishl
		// @115: iadd
		// @116: istore #16
		// @118: iload #16
		// @11A: iload #16
		// @11C: imul
		// @11D: istore #16
		// @11F: iload #14
		// @121: ineg
		// @122: iload #15
		// @124: iadd
		// @125: istore #17
		// @127: iload #15
		// @129: ineg
		// @12A: iload #16
		// @12C: iadd
		// @12D: istore #18
		// @12F: iload #18
		// @131: iload #17
		// @133: ineg
		// @134: iadd
		// @135: istore #19
		// @137: iload #12
		// @139: ldc -607820572 (0xdbc564e4)
		// @13B: ishl
		// @13C: iload #6
		// @13E: isub
		// @13F: istore #20
		// @141: iload #20
		// @143: iload #20
		// @145: imul
		// @146: istore #20
		// @148: iload #6
		// @14A: ineg
		// @14B: iload #12
		// @14D: iconst_1
		// @14E: iadd
		// @14F: ldc -1935142204 (0x8ca812c4)
		// @151: ishl
		// @152: iadd
		// @153: istore #21
		// @155: iload #21
		// @157: iload #21
		// @159: imul
		// @15A: istore #21
		// @15C: iload #6
		// @15E: ineg
		// @15F: iload #12
		// @161: bipush -2 (0xFE)
		// @163: isub
		// @164: ldc 968701956 (0x39bd3804)
		// @166: ishl
		// @167: iadd
		// @168: istore #22
		// @16A: iload #22
		// @16C: iload #22
		// @16E: imul
		// @16F: istore #22
		// @171: iload #21
		// @173: iload #20
		// @175: isub
		// @176: istore #23
		// @178: iload #22
		// @17A: iload #21
		// @17C: isub
		// @17D: istore #24
		// @17F: iload #24
		// @181: iload #23
		// @183: ineg
		// @184: iadd
		// @185: istore #25
		// @187: bipush 16 (0x10)
		// @189: istore #26
		// @18B: iload #7
		// @18D: istore #27
		// @18F: iload #7
		// @191: iconst_m1
		// @192: ixor
		// @193: ldc 2147483647 (0x7fffffff)
		// @195: iload #26
		// @197: iushr
		// @198: iconst_m1
		// @199: ixor
		// @19A: if_icmpge @1B3
		// @19D: iinc #26 +255
		// @1A0: iload #27
		// @1A2: iconst_m1
		// @1A3: isub
		// @1A4: ldc 647901505 (0x269e3141)
		// @1A6: iushr
		// @1A7: iload #32
		// @1A9: ifne @1BC
		// @1AC: istore #27
		// @1AE: iload #32
		// @1B0: ifeq @18F
		// @1B3: iload #9
		// @1B5: sipush 640 (0x0280)
		// @1B8: iload #12
		// @1BA: imul
		// @1BB: iadd
		// @1BC: istore #28
		// @1BE: iload #20
		// @1C0: iload #14
		// @1C2: iadd
		// @1C3: istore #29
		// @1C5: iload #23
		// @1C7: istore #30
		// @1C9: iload #12
		// @1CB: istore #31
		// @1CD: iload #13
		// @1CF: iconst_m1
		// @1D0: ixor
		// @1D1: iload #31
		// @1D3: iconst_m1
		// @1D4: ixor
		// @1D5: if_icmpge @21D
		// @1D8: iload #19
		// @1DA: iload #17
		// @1DC: iload #31
		// @1DE: iload #28
		// @1E0: iload #6
		// @1E2: iload #27
		// @1E4: iload #10
		// @1E6: iload_0
		// @1E7: iload #26
		// @1E9: iload #29
		// @1EB: bipush 124 (0x7C)
		// @1ED: iload #5
		// @1EF: iload #8
		// @1F1: iload #9
		// @1F3: iload #7
		// @1F5: invokestatic game.C_100181_cf.func_105699_a(int, int, int, int, int, int, int, int, int, int, int, int, int, int, int)void
		// @1F8: iload #29
		// @1FA: iload #30
		// @1FC: iadd
		// @1FD: istore #29
		// @1FF: iload #30
		// @201: iload #25
		// @203: iadd
		// @204: istore #30
		// @206: wide (iinc) #28 +640
		// @20C: iinc #31 +1
		// @20F: iload #32
		// @211: ifne @234
		// @214: iload #32
		// @216: ifeq @1CD
		// @219: goto @21D
		// @21C: athrow
		// @21D: iload #9
		// @21F: sipush 640 (0x0280)
		// @222: iload #12
		// @224: imul
		// @225: iadd
		// @226: istore #28
		// @228: iload #23
		// @22A: istore #30
		// @22C: iload #14
		// @22E: iload #20
		// @230: ineg
		// @231: isub
		// @232: istore #29
		// @234: iconst_m1
		// @235: iload #12
		// @237: iadd
		// @238: istore #31
		// @23A: iload #31
		// @23C: iconst_m1
		// @23D: ixor
		// @23E: iload #11
		// @240: iconst_m1
		// @241: ixor
		// @242: if_icmpgt @288
		// @245: iload #30
		// @247: iload #25
		// @249: isub
		// @24A: istore #30
		// @24C: iload #29
		// @24E: iload #30
		// @250: isub
		// @251: istore #29
		// @253: wide (iinc) #28 +64896
		// @259: iload #31
		// @25B: iload #29
		// @25D: iload #17
		// @25F: iload #19
		// @261: iload #26
		// @263: iload #7
		// @265: iload #27
		// @267: iload #8
		// @269: iload #9
		// @26B: iload #10
		// @26D: iload_0
		// @26E: iload #28
		// @270: iload #5
		// @272: iload #6
		// @274: invokestatic game.C_100018_wk.func_101490_a(int, int, int, int, int, int, int, int, int, int, int, int, int, int)void
		// @277: iinc #31 +255
		// @27A: iload #32
		// @27C: ifne @2D4
		// @27F: iload #32
		// @281: ifeq @23A
		// @284: goto @288
		// @287: athrow
		// @288: goto @2D4
		// @28B: astore #5
		// @28D: aload #5
		// @28F: new java.lang.StringBuilder
		// @292: dup
		// @293: invokespecial java.lang.StringBuilder.<init>()void
		// @296: getstatic java.lang.String[] game.C_100222_aa.field_106088_z
		// @299: bipush 9 (0x09)
		// @29B: aaload
		// @29C: invokevirtual java.lang.StringBuilder.append(java.lang.String)java.lang.StringBuilder
		// @29F: iload_0
		// @2A0: invokevirtual java.lang.StringBuilder.append(int)java.lang.StringBuilder
		// @2A3: bipush 44 (0x2C)
		// @2A5: invokevirtual java.lang.StringBuilder.append(char)java.lang.StringBuilder
		// @2A8: iload_1
		// @2A9: invokevirtual java.lang.StringBuilder.append(int)java.lang.StringBuilder
		// @2AC: bipush 44 (0x2C)
		// @2AE: invokevirtual java.lang.StringBuilder.append(char)java.lang.StringBuilder
		// @2B1: iload_2
		// @2B2: invokevirtual java.lang.StringBuilder.append(int)java.lang.StringBuilder
		// @2B5: bipush 44 (0x2C)
		// @2B7: invokevirtual java.lang.StringBuilder.append(char)java.lang.StringBuilder
		// @2BA: iload_3
		// @2BB: invokevirtual java.lang.StringBuilder.append(int)java.lang.StringBuilder
		// @2BE: bipush 44 (0x2C)
		// @2C0: invokevirtual java.lang.StringBuilder.append(char)java.lang.StringBuilder
		// @2C3: iload #4
		// @2C5: invokevirtual java.lang.StringBuilder.append(int)java.lang.StringBuilder
		// @2C8: bipush 41 (0x29)
		// @2CA: invokevirtual java.lang.StringBuilder.append(char)java.lang.StringBuilder
		// @2CD: invokevirtual java.lang.StringBuilder.toString()java.lang.String
		// @2D0: invokestatic game.C_100181_cf.func_105695_a(java.lang.Throwable, java.lang.String)game.C_100170_cm
		// @2D3: athrow
		// @2D4: return
	}
	
	public static void func_106074_a(int arg0)
	{
		// @00: aconst_null
		// @01: putstatic game.C_100193_re game.C_100222_aa.field_106085_c
		// @04: aconst_null
		// @05: putstatic java.lang.String game.C_100222_aa.field_106087_j
		// @08: aconst_null
		// @09: putstatic java.lang.String game.C_100222_aa.field_106084_b
		// @0C: aconst_null
		// @0D: putstatic int[] game.C_100222_aa.field_106080_f
		// @10: aconst_null
		// @11: putstatic java.lang.String game.C_100222_aa.field_106081_g
		// @14: aconst_null
		// @15: putstatic game.C_100068_vc game.C_100222_aa.field_106086_a
		// @18: iload_0
		// @19: sipush -31362 (0x857E)
		// @1C: if_icmpeq @2A
		// @1F: aconst_null
		// @20: checkcast java.lang.String
		// @23: putstatic java.lang.String game.C_100222_aa.field_106081_g
		// @26: goto @2A
		// @29: athrow
		// @2A: aconst_null
		// @2B: putstatic java.lang.String game.C_100222_aa.field_106082_d
		// @2E: aconst_null
		// @2F: putstatic java.lang.String game.C_100222_aa.field_106091_i
		// @32: goto @57
		// @35: astore_1
		// @36: aload_1
		// @37: new java.lang.StringBuilder
		// @3A: dup
		// @3B: invokespecial java.lang.StringBuilder.<init>()void
		// @3E: getstatic java.lang.String[] game.C_100222_aa.field_106088_z
		// @41: bipush 8 (0x08)
		// @43: aaload
		// @44: invokevirtual java.lang.StringBuilder.append(java.lang.String)java.lang.StringBuilder
		// @47: iload_0
		// @48: invokevirtual java.lang.StringBuilder.append(int)java.lang.StringBuilder
		// @4B: bipush 41 (0x29)
		// @4D: invokevirtual java.lang.StringBuilder.append(char)java.lang.StringBuilder
		// @50: invokevirtual java.lang.StringBuilder.toString()java.lang.String
		// @53: invokestatic game.C_100181_cf.func_105695_a(java.lang.Throwable, java.lang.String)game.C_100170_cm
		// @56: athrow
		// @57: return
	}
	
	private C_100222_aa() throws Throwable
	{
		// @00: aload_0
		// @01: invokespecial java.lang.Object.<init>()void
		// @04: new java.lang.Error
		// @07: dup
		// @08: invokespecial java.lang.Error.<init>()void
		// @0B: athrow
		// @0C: astore_1
		// @0D: aload_1
		// @0E: getstatic java.lang.String[] game.C_100222_aa.field_106088_z
		// @11: bipush 7 (0x07)
		// @13: aaload
		// @14: invokestatic game.C_100181_cf.func_105695_a(java.lang.Throwable, java.lang.String)game.C_100170_cm
		// @17: athrow
	}
	
	static
	{
		// @00: bipush 11 (0x0B)
		// @02: anewarray java.lang.String
		// @05: dup
		// @06: iconst_0
		// @07: ldc "6J\u0007Gr\u0002"
		// @09: invokestatic game.C_100222_aa.func_106077_z(java.lang.String)char[]
		// @0C: invokestatic game.C_100222_aa.func_106076_z(char[])java.lang.String
		// @0F: aastore
		// @10: dup
		// @11: iconst_1
		// @12: ldc "$o9\u0017&I"
		// @14: invokestatic game.C_100222_aa.func_106077_z(java.lang.String)char[]
		// @17: invokestatic game.C_100222_aa.func_106076_z(char[])java.lang.String
		// @1A: aastore
		// @1B: dup
		// @1C: iconst_2
		// @1D: ldc "\u0008IEc4"
		// @1F: invokestatic game.C_100222_aa.func_106077_z(java.lang.String)char[]
		// @22: invokestatic game.C_100222_aa.func_106076_z(char[])java.lang.String
		// @25: aastore
		// @26: dup
		// @27: iconst_3
		// @28: ldc "\u0007]\u0007J"
		// @2A: invokestatic game.C_100222_aa.func_106077_z(java.lang.String)char[]
		// @2D: invokestatic game.C_100222_aa.func_106076_z(char[])java.lang.String
		// @30: aastore
		// @31: dup
		// @32: iconst_4
		// @33: ldc "\u001eA\u0005"
		// @35: invokestatic game.C_100222_aa.func_106077_z(java.lang.String)char[]
		// @38: invokestatic game.C_100222_aa.func_106076_z(char[])java.lang.String
		// @3B: aastore
		// @3C: dup
		// @3D: iconst_5
		// @3E: ldc "\u0012\u0006E\u0008a"
		// @40: invokestatic game.C_100222_aa.func_106077_z(java.lang.String)char[]
		// @43: invokestatic game.C_100222_aa.func_106076_z(char[])java.lang.String
		// @46: aastore
		// @47: dup
		// @48: bipush 6 (0x06)
		// @4A: ldc "\u0008IEe4"
		// @4C: invokestatic game.C_100222_aa.func_106077_z(java.lang.String)char[]
		// @4F: invokestatic game.C_100222_aa.func_106076_z(char[])java.lang.String
		// @52: aastore
		// @53: dup
		// @54: bipush 7 (0x07)
		// @56: ldc "\u0008IE\u001au\u0007A\u001f\u00184@"
		// @58: invokestatic game.C_100222_aa.func_106077_z(java.lang.String)char[]
		// @5B: invokestatic game.C_100222_aa.func_106076_z(char[])java.lang.String
		// @5E: aastore
		// @5F: dup
		// @60: bipush 8 (0x08)
		// @62: ldc "\u0008IEd4"
		// @64: invokestatic game.C_100222_aa.func_106077_z(java.lang.String)char[]
		// @67: invokestatic game.C_100222_aa.func_106076_z(char[])java.lang.String
		// @6A: aastore
		// @6B: dup
		// @6C: bipush 9 (0x09)
		// @6E: ldc "\u0008IEg4"
		// @70: invokestatic game.C_100222_aa.func_106077_z(java.lang.String)char[]
		// @73: invokestatic game.C_100222_aa.func_106076_z(char[])java.lang.String
		// @76: aastore
		// @77: dup
		// @78: bipush 10 (0x0A)
		// @7A: ldc "\u0008IEb4"
		// @7C: invokestatic game.C_100222_aa.func_106077_z(java.lang.String)char[]
		// @7F: invokestatic game.C_100222_aa.func_106076_z(char[])java.lang.String
		// @82: aastore
		// @83: putstatic java.lang.String[] game.C_100222_aa.field_106088_z
		// @86: ldc ":G\u0007O\u007f\u0000\\\nRu\u0006F"
		// @88: invokestatic game.C_100222_aa.func_106077_z(java.lang.String)char[]
		// @8B: invokestatic game.C_100222_aa.func_106076_z(char[])java.lang.String
		// @8E: putstatic java.lang.String game.C_100222_aa.field_106091_i
		// @91: ldc "$A\u0018Uu\u0006FK`}\u0000D\u000eB"
		// @93: invokestatic game.C_100222_aa.func_106077_z(java.lang.String)char[]
		// @96: invokestatic game.C_100222_aa.func_106076_z(char[])java.lang.String
		// @99: putstatic java.lang.String game.C_100222_aa.field_106081_g
		// @9C: ldc "*GFIlIo\nKy"
		// @9E: invokestatic game.C_100222_aa.func_106077_z(java.lang.String)char[]
		// @A1: invokestatic game.C_100222_aa.func_106076_z(char[])java.lang.String
		// @A4: putstatic java.lang.String game.C_100222_aa.field_106087_j
		// @A7: ldc ":M\u0005Ru\u0007M\u0007U<,P\u001bGr\u001aA\u0004H"
		// @A9: invokestatic game.C_100222_aa.func_106077_z(java.lang.String)char[]
		// @AC: invokestatic game.C_100222_aa.func_106076_z(char[])java.lang.String
		// @AF: putstatic java.lang.String game.C_100222_aa.field_106082_d
		// @B2: ldc "=z*oR f,\u0006Q {8oS'\u0008W\u0003,W\u0008W\u0003-W"
		// @B4: invokestatic game.C_100222_aa.func_106077_z(java.lang.String)char[]
		// @B7: invokestatic game.C_100222_aa.func_106076_z(char[])java.lang.String
		// @BA: putstatic java.lang.String game.C_100222_aa.field_106084_b
		// @BD: sipush 200 (0x00C8)
		// @C0: putstatic int game.C_100222_aa.field_106083_e
		// @C3: return
	}
	
	private static char[] func_106077_z(String arg0)
	{
		// @00: aload_0
		// @01: invokevirtual java.lang.String.toCharArray()char[]
		// @04: dup
		// @05: arraylength
		// @06: iconst_2
		// @07: if_icmpge @13
		// @0A: dup
		// @0B: iconst_0
		// @0C: dup2
		// @0D: caload
		// @0E: bipush 28 (0x1C)
		// @10: ixor
		// @11: i2c
		// @12: castore
		// @13: areturn
	}
	
	private static String func_106076_z(char[] arg0)
	{
		// @00: aload_0
		// @01: dup
		// @02: arraylength
		// @03: swap
		// @04: iconst_0
		// @05: istore_1
		// @06: goto @4C
		// @09: dup
		// @0A: iload_1
		// @0B: dup2
		// @0C: caload
		// @0D: iload_1
		// @0E: iconst_5
		// @0F: irem
		// @10: tableswitch def: @44, for 0: @30, for 1: @35, for 2: @3A, for 3: @3F
		// @30: bipush 105 (0x69)
		// @32: goto @46
		// @35: bipush 40 (0x28)
		// @37: goto @46
		// @3A: bipush 107 (0x6B)
		// @3C: goto @46
		// @3F: bipush 38 (0x26)
		// @41: goto @46
		// @44: bipush 28 (0x1C)
		// @46: ixor
		// @47: i2c
		// @48: castore
		// @49: iinc #1 +1
		// @4C: swap
		// @4D: dup_x1
		// @4E: iload_1
		// @4F: if_icmpgt @09
		// @52: new java.lang.String
		// @55: dup_x1
		// @56: swap
		// @57: invokespecial java.lang.String.<init>(char[])void
		// @5A: invokevirtual java.lang.String.intern()java.lang.String
		// @5D: areturn
	}
}
