package game;

final class C_100149_bi
{
	static C_100302_ka field_105157_c;
	static String field_105153_g;
	static boolean field_105158_a;
	static C_100037_wb field_105156_b;
	static int field_105155_e;
	static int field_105154_d;
	static int field_105152_f;
	private static final String[] field_105159_z;
	
	static final void func_105151_a(boolean arg0, int arg1)
	{
		// @00: iload_1
		// @01: ifeq @0F
		// @04: aconst_null
		// @05: checkcast java.lang.String
		// @08: putstatic java.lang.String game.C_100149_bi.field_105153_g
		// @0B: goto @0F
		// @0E: athrow
		// @0F: getstatic game.C_100302_ka game.C_100154_sl.field_105332_e
		// @12: bipush -128 (0x80)
		// @14: iload_0
		// @15: invokevirtual game.C_100302_ka.func_101809_a(byte, boolean)void
		// @18: goto @45
		// @1B: astore_2
		// @1C: aload_2
		// @1D: new java.lang.StringBuilder
		// @20: dup
		// @21: invokespecial java.lang.StringBuilder.<init>()void
		// @24: getstatic java.lang.String[] game.C_100149_bi.field_105159_z
		// @27: iconst_1
		// @28: aaload
		// @29: invokevirtual java.lang.StringBuilder.append(java.lang.String)java.lang.StringBuilder
		// @2C: iload_0
		// @2D: invokevirtual java.lang.StringBuilder.append(boolean)java.lang.StringBuilder
		// @30: bipush 44 (0x2C)
		// @32: invokevirtual java.lang.StringBuilder.append(char)java.lang.StringBuilder
		// @35: iload_1
		// @36: invokevirtual java.lang.StringBuilder.append(int)java.lang.StringBuilder
		// @39: bipush 41 (0x29)
		// @3B: invokevirtual java.lang.StringBuilder.append(char)java.lang.StringBuilder
		// @3E: invokevirtual java.lang.StringBuilder.toString()java.lang.String
		// @41: invokestatic game.C_100181_cf.func_105695_a(java.lang.Throwable, java.lang.String)game.C_100170_cm
		// @44: athrow
		// @45: return
	}
	
	public static void func_105147_a(int arg0)
	{
		// @00: iload_0
		// @01: bipush -32 (0xE0)
		// @03: if_icmple @07
		// @06: return
		// @07: aconst_null
		// @08: putstatic game.C_100302_ka game.C_100149_bi.field_105157_c
		// @0B: aconst_null
		// @0C: putstatic game.C_100037_wb game.C_100149_bi.field_105156_b
		// @0F: aconst_null
		// @10: putstatic java.lang.String game.C_100149_bi.field_105153_g
		// @13: goto @37
		// @16: astore_1
		// @17: aload_1
		// @18: new java.lang.StringBuilder
		// @1B: dup
		// @1C: invokespecial java.lang.StringBuilder.<init>()void
		// @1F: getstatic java.lang.String[] game.C_100149_bi.field_105159_z
		// @22: iconst_0
		// @23: aaload
		// @24: invokevirtual java.lang.StringBuilder.append(java.lang.String)java.lang.StringBuilder
		// @27: iload_0
		// @28: invokevirtual java.lang.StringBuilder.append(int)java.lang.StringBuilder
		// @2B: bipush 41 (0x29)
		// @2D: invokevirtual java.lang.StringBuilder.append(char)java.lang.StringBuilder
		// @30: invokevirtual java.lang.StringBuilder.toString()java.lang.String
		// @33: invokestatic game.C_100181_cf.func_105695_a(java.lang.Throwable, java.lang.String)game.C_100170_cm
		// @36: athrow
		// @37: return
	}
	
	static final boolean func_105150_b(int arg0)
	{
		// @00: getstatic int game.C_100056_de.field_103194_Y
		// @03: iconst_m1
		// @04: if_icmpne @2B
		// @07: iconst_1
		// @08: bipush 51 (0x33)
		// @0A: invokestatic game.C_100114_q.func_100483_a(int, byte)boolean
		// @0D: ifeq @18
		// @10: goto @14
		// @13: athrow
		// @14: goto @1A
		// @17: athrow
		// @18: iconst_0
		// @19: ireturn
		// @1A: getstatic game.C_100278_nd game.C_100288_jn.field_106839_f
		// @1D: iconst_0
		// @1E: invokevirtual game.C_100278_nd.func_101156_c(boolean)int
		// @21: putstatic int game.C_100056_de.field_103194_Y
		// @24: getstatic game.C_100278_nd game.C_100288_jn.field_106839_f
		// @27: iconst_0
		// @28: putfield int game.C_100278_nd.field_101177_n
		// @2B: iconst_1
		// @2C: getstatic int game.C_100056_de.field_103194_Y
		// @2F: iconst_m1
		// @30: ixor
		// @31: if_icmpeq @38
		// @34: goto @59
		// @37: athrow
		// @38: iconst_2
		// @39: bipush 51 (0x33)
		// @3B: invokestatic game.C_100114_q.func_100483_a(int, byte)boolean
		// @3E: ifeq @45
		// @41: goto @47
		// @44: athrow
		// @45: iconst_0
		// @46: ireturn
		// @47: getstatic game.C_100278_nd game.C_100288_jn.field_106839_f
		// @4A: bipush -2 (0xFE)
		// @4C: invokevirtual game.C_100278_nd.func_101143_l(int)int
		// @4F: putstatic int game.C_100056_de.field_103194_Y
		// @52: getstatic game.C_100278_nd game.C_100288_jn.field_106839_f
		// @55: iconst_0
		// @56: putfield int game.C_100278_nd.field_101177_n
		// @59: iload_0
		// @5A: ifeq @66
		// @5D: bipush 71 (0x47)
		// @5F: invokestatic game.C_100149_bi.func_105147_a(int)void
		// @62: goto @66
		// @65: athrow
		// @66: getstatic int game.C_100056_de.field_103194_Y
		// @69: bipush 51 (0x33)
		// @6B: invokestatic game.C_100114_q.func_100483_a(int, byte)boolean
		// @6E: ireturn
		// @6F: astore_1
		// @70: aload_1
		// @71: new java.lang.StringBuilder
		// @74: dup
		// @75: invokespecial java.lang.StringBuilder.<init>()void
		// @78: getstatic java.lang.String[] game.C_100149_bi.field_105159_z
		// @7B: iconst_2
		// @7C: aaload
		// @7D: invokevirtual java.lang.StringBuilder.append(java.lang.String)java.lang.StringBuilder
		// @80: iload_0
		// @81: invokevirtual java.lang.StringBuilder.append(int)java.lang.StringBuilder
		// @84: bipush 41 (0x29)
		// @86: invokevirtual java.lang.StringBuilder.append(char)java.lang.StringBuilder
		// @89: invokevirtual java.lang.StringBuilder.toString()java.lang.String
		// @8C: invokestatic game.C_100181_cf.func_105695_a(java.lang.Throwable, java.lang.String)game.C_100170_cm
		// @8F: athrow
	}
	
	static final void func_105146_a(C_100098_h arg0, int arg1)
	{
		// @000: bipush 95 (0x5F)
		// @002: getstatic java.lang.String[] game.C_100149_bi.field_105159_z
		// @005: iconst_5
		// @006: aaload
		// @007: aload_0
		// @008: getstatic java.lang.String[] game.C_100149_bi.field_105159_z
		// @00B: bipush 7 (0x07)
		// @00D: aaload
		// @00E: invokestatic game.C_100021_wn.func_103861_a(byte, java.lang.String, game.C_100098_h, java.lang.String)game.C_100037_wb
		// @011: putstatic game.C_100037_wb game.C_100063_dj.field_104291_g
		// @014: new game.C_100100_i
		// @017: dup
		// @018: lconst_0
		// @019: getstatic game.C_100100_i game.C_100078_ul.field_103283_nb
		// @01C: getstatic java.lang.String game.C_100148_bh.field_101807_y
		// @01F: getstatic java.lang.String game.C_100096_un.field_104562_g
		// @022: invokespecial game.C_100100_i.<init>(long, game.C_100100_i, java.lang.String, java.lang.String)void
		// @025: putstatic game.C_100100_i game.C_100012_fh.field_100507_G
		// @028: new game.C_100100_i
		// @02B: dup
		// @02C: lconst_0
		// @02D: getstatic game.C_100100_i game.C_100078_ul.field_103283_nb
		// @030: getstatic java.lang.String game.C_100046_vk.field_102768_vb
		// @033: getstatic java.lang.String game.C_100029_gn.field_103367_P
		// @036: invokespecial game.C_100100_i.<init>(long, game.C_100100_i, java.lang.String, java.lang.String)void
		// @039: putstatic game.C_100100_i game.C_100202_qi.field_105913_f
		// @03C: new game.C_100302_ka
		// @03F: dup
		// @040: lconst_0
		// @041: aconst_null
		// @042: invokespecial game.C_100302_ka.<init>(long, game.C_100302_ka)void
		// @045: putstatic game.C_100302_ka game.C_100280_nf.field_101176_p
		// @048: new game.C_100302_ka
		// @04B: dup
		// @04C: lconst_0
		// @04D: getstatic game.C_100302_ka game.C_100129_tg.field_102750_sb
		// @050: invokespecial game.C_100302_ka.<init>(long, game.C_100302_ka)void
		// @053: putstatic game.C_100302_ka game.C_100104_v.field_104690_e
		// @056: getstatic game.C_100302_ka game.C_100104_v.field_104690_e
		// @059: iconst_1
		// @05A: putfield int game.C_100302_ka.field_101850_Fb
		// @05D: new game.C_100302_ka
		// @060: dup
		// @061: lconst_0
		// @062: getstatic game.C_100302_ka game.C_100252_pn.field_105515_p
		// @065: getstatic java.lang.String game.C_100332_ii.field_107309_d
		// @068: invokespecial game.C_100302_ka.<init>(long, game.C_100302_ka, java.lang.String)void
		// @06B: putstatic game.C_100302_ka game.C_100111_el.field_104860_d
		// @06E: new game.C_100302_ka
		// @071: dup
		// @072: lconst_0
		// @073: getstatic game.C_100302_ka game.C_100038_wa.field_104074_o
		// @076: getstatic java.lang.String game.C_100010_ff.field_103709_q
		// @079: invokespecial game.C_100302_ka.<init>(long, game.C_100302_ka, java.lang.String)void
		// @07C: putstatic game.C_100302_ka game.C_100235_om.field_106289_e
		// @07F: new game.C_100302_ka
		// @082: dup
		// @083: lconst_0
		// @084: getstatic game.C_100302_ka game.C_100236_on.field_100906_r
		// @087: invokespecial game.C_100302_ka.<init>(long, game.C_100302_ka)void
		// @08A: putstatic game.C_100302_ka game.C_100325_id.field_101489_k
		// @08D: getstatic game.C_100302_ka game.C_100280_nf.field_101176_p
		// @090: bipush -128 (0x80)
		// @092: getstatic game.C_100302_ka game.C_100104_v.field_104690_e
		// @095: invokevirtual game.C_100302_ka.func_101824_b(int, game.C_100302_ka)void
		// @098: getstatic game.C_100302_ka game.C_100280_nf.field_101176_p
		// @09B: bipush -78 (0xB2)
		// @09D: getstatic game.C_100302_ka game.C_100111_el.field_104860_d
		// @0A0: invokevirtual game.C_100302_ka.func_101824_b(int, game.C_100302_ka)void
		// @0A3: getstatic game.C_100302_ka game.C_100280_nf.field_101176_p
		// @0A6: bipush -81 (0xAF)
		// @0A8: getstatic game.C_100302_ka game.C_100235_om.field_106289_e
		// @0AB: invokevirtual game.C_100302_ka.func_101824_b(int, game.C_100302_ka)void
		// @0AE: getstatic game.C_100302_ka game.C_100280_nf.field_101176_p
		// @0B1: bipush -76 (0xB4)
		// @0B3: getstatic game.C_100100_i game.C_100012_fh.field_100507_G
		// @0B6: invokevirtual game.C_100302_ka.func_101824_b(int, game.C_100302_ka)void
		// @0B9: getstatic game.C_100302_ka game.C_100280_nf.field_101176_p
		// @0BC: bipush -93 (0xA3)
		// @0BE: getstatic game.C_100302_ka game.C_100325_id.field_101489_k
		// @0C1: invokevirtual game.C_100302_ka.func_101824_b(int, game.C_100302_ka)void
		// @0C4: getstatic game.C_100100_i game.C_100012_fh.field_100507_G
		// @0C7: getfield game.C_100115_ej game.C_100100_i.field_102016_ec
		// @0CA: getfield game.C_100302_ka game.C_100115_ej.field_102040_Zb
		// @0CD: sipush 32280 (0x7E18)
		// @0D0: getstatic game.C_100302_ka game.C_100129_tg.field_102750_sb
		// @0D3: invokevirtual game.C_100302_ka.func_101810_a(int, game.C_100302_ka)void
		// @0D6: getstatic game.C_100100_i game.C_100012_fh.field_100507_G
		// @0D9: getfield game.C_100115_ej game.C_100100_i.field_102016_ec
		// @0DC: getfield game.C_100302_ka game.C_100115_ej.field_102040_Zb
		// @0DF: iconst_1
		// @0E0: putfield int game.C_100302_ka.field_101858_J
		// @0E3: getstatic game.C_100100_i game.C_100012_fh.field_100507_G
		// @0E6: getfield game.C_100115_ej game.C_100100_i.field_102016_ec
		// @0E9: getfield game.C_100302_ka game.C_100115_ej.field_102040_Zb
		// @0EC: astore_2
		// @0ED: aload_2
		// @0EE: iconst_1
		// @0EF: putfield int game.C_100302_ka.field_101850_Fb
		// @0F2: getstatic game.C_100100_i game.C_100202_qi.field_105913_f
		// @0F5: getfield game.C_100115_ej game.C_100100_i.field_102016_ec
		// @0F8: getfield game.C_100302_ka game.C_100115_ej.field_102040_Zb
		// @0FB: sipush 32280 (0x7E18)
		// @0FE: getstatic game.C_100302_ka game.C_100129_tg.field_102750_sb
		// @101: invokevirtual game.C_100302_ka.func_101810_a(int, game.C_100302_ka)void
		// @104: getstatic game.C_100100_i game.C_100202_qi.field_105913_f
		// @107: getfield game.C_100115_ej game.C_100100_i.field_102016_ec
		// @10A: getfield game.C_100302_ka game.C_100115_ej.field_102040_Zb
		// @10D: iconst_1
		// @10E: putfield int game.C_100302_ka.field_101858_J
		// @111: getstatic game.C_100100_i game.C_100202_qi.field_105913_f
		// @114: getfield game.C_100115_ej game.C_100100_i.field_102016_ec
		// @117: getfield game.C_100302_ka game.C_100115_ej.field_102040_Zb
		// @11A: astore_3
		// @11B: aload_3
		// @11C: iconst_1
		// @11D: putfield int game.C_100302_ka.field_101850_Fb
		// @120: iload_1
		// @121: bipush 117 (0x75)
		// @123: if_icmpge @131
		// @126: aconst_null
		// @127: checkcast game.C_100037_wb
		// @12A: putstatic game.C_100037_wb game.C_100149_bi.field_105156_b
		// @12D: goto @131
		// @130: athrow
		// @131: goto @170
		// @134: astore_2
		// @135: aload_2
		// @136: new java.lang.StringBuilder
		// @139: dup
		// @13A: invokespecial java.lang.StringBuilder.<init>()void
		// @13D: getstatic java.lang.String[] game.C_100149_bi.field_105159_z
		// @140: iconst_3
		// @141: aaload
		// @142: invokevirtual java.lang.StringBuilder.append(java.lang.String)java.lang.StringBuilder
		// @145: aload_0
		// @146: ifnull @152
		// @149: getstatic java.lang.String[] game.C_100149_bi.field_105159_z
		// @14C: iconst_4
		// @14D: aaload
		// @14E: goto @158
		// @151: athrow
		// @152: getstatic java.lang.String[] game.C_100149_bi.field_105159_z
		// @155: bipush 6 (0x06)
		// @157: aaload
		// @158: invokevirtual java.lang.StringBuilder.append(java.lang.String)java.lang.StringBuilder
		// @15B: bipush 44 (0x2C)
		// @15D: invokevirtual java.lang.StringBuilder.append(char)java.lang.StringBuilder
		// @160: iload_1
		// @161: invokevirtual java.lang.StringBuilder.append(int)java.lang.StringBuilder
		// @164: bipush 41 (0x29)
		// @166: invokevirtual java.lang.StringBuilder.append(char)java.lang.StringBuilder
		// @169: invokevirtual java.lang.StringBuilder.toString()java.lang.String
		// @16C: invokestatic game.C_100181_cf.func_105695_a(java.lang.Throwable, java.lang.String)game.C_100170_cm
		// @16F: athrow
		// @170: return
	}
	
	static
	{
		// @00: bipush 8 (0x08)
		// @02: anewarray java.lang.String
		// @05: dup
		// @06: iconst_0
		// @07: ldc "RL\u0014}F"
		// @09: invokestatic game.C_100149_bi.func_105149_z(java.lang.String)char[]
		// @0C: invokestatic game.C_100149_bi.func_105148_z(char[])java.lang.String
		// @0F: aastore
		// @10: dup
		// @11: iconst_1
		// @12: ldc "RL\u0014xF"
		// @14: invokestatic game.C_100149_bi.func_105149_z(java.lang.String)char[]
		// @17: invokestatic game.C_100149_bi.func_105148_z(char[])java.lang.String
		// @1A: aastore
		// @1B: dup
		// @1C: iconst_2
		// @1D: ldc "RL\u0014{F"
		// @1F: invokestatic game.C_100149_bi.func_105149_z(java.lang.String)char[]
		// @22: invokestatic game.C_100149_bi.func_105148_z(char[])java.lang.String
		// @25: aastore
		// @26: dup
		// @27: iconst_3
		// @28: ldc "RL\u0014zF"
		// @2A: invokestatic game.C_100149_bi.func_105149_z(java.lang.String)char[]
		// @2D: invokestatic game.C_100149_bi.func_105148_z(char[])java.lang.String
		// @30: aastore
		// @31: dup
		// @32: iconst_4
		// @33: ldc "K\u000b\u0014\u0017\u0013"
		// @35: invokestatic game.C_100149_bi.func_105149_z(java.lang.String)char[]
		// @38: invokestatic game.C_100149_bi.func_105148_z(char[])java.lang.String
		// @3B: aastore
		// @3C: dup
		// @3D: iconst_5
		// @3E: ldc "RDIP\r"
		// @40: invokestatic game.C_100149_bi.func_105149_z(java.lang.String)char[]
		// @43: invokestatic game.C_100149_bi.func_105148_z(char[])java.lang.String
		// @46: aastore
		// @47: dup
		// @48: bipush 6 (0x06)
		// @4A: ldc "^PVU"
		// @4C: invokestatic game.C_100149_bi.func_105149_z(java.lang.String)char[]
		// @4F: invokestatic game.C_100149_bi.func_105148_z(char[])java.lang.String
		// @52: aastore
		// @53: dup
		// @54: bipush 7 (0x07)
		// @56: ldc "TLII\u0002Q\\eW\u000f]@eZ\u0006QK]\\\n"
		// @58: invokestatic game.C_100149_bi.func_105149_z(java.lang.String)char[]
		// @5B: invokestatic game.C_100149_bi.func_105148_z(char[])java.lang.String
		// @5E: aastore
		// @5F: putstatic java.lang.String[] game.C_100149_bi.field_105159_z
		// @62: ldc "vLH\\T"
		// @64: invokestatic game.C_100149_bi.func_105149_z(java.lang.String)char[]
		// @67: invokestatic game.C_100149_bi.func_105148_z(char[])java.lang.String
		// @6A: putstatic java.lang.String game.C_100149_bi.field_105153_g
		// @6D: iconst_1
		// @6E: putstatic boolean game.C_100149_bi.field_105158_a
		// @71: iconst_m1
		// @72: putstatic int game.C_100149_bi.field_105152_f
		// @75: return
	}
	
	private static char[] func_105149_z(String arg0)
	{
		// @00: aload_0
		// @01: invokevirtual java.lang.String.toCharArray()char[]
		// @04: dup
		// @05: arraylength
		// @06: iconst_2
		// @07: if_icmpge @13
		// @0A: dup
		// @0B: iconst_0
		// @0C: dup2
		// @0D: caload
		// @0E: bipush 110 (0x6E)
		// @10: ixor
		// @11: i2c
		// @12: castore
		// @13: areturn
	}
	
	private static String func_105148_z(char[] arg0)
	{
		// @00: aload_0
		// @01: dup
		// @02: arraylength
		// @03: swap
		// @04: iconst_0
		// @05: istore_1
		// @06: goto @4C
		// @09: dup
		// @0A: iload_1
		// @0B: dup2
		// @0C: caload
		// @0D: iload_1
		// @0E: iconst_5
		// @0F: irem
		// @10: tableswitch def: @44, for 0: @30, for 1: @35, for 2: @3A, for 3: @3F
		// @30: bipush 48 (0x30)
		// @32: goto @46
		// @35: bipush 37 (0x25)
		// @37: goto @46
		// @3A: bipush 58 (0x3A)
		// @3C: goto @46
		// @3F: bipush 57 (0x39)
		// @41: goto @46
		// @44: bipush 110 (0x6E)
		// @46: ixor
		// @47: i2c
		// @48: castore
		// @49: iinc #1 +1
		// @4C: swap
		// @4D: dup_x1
		// @4E: iload_1
		// @4F: if_icmpgt @09
		// @52: new java.lang.String
		// @55: dup_x1
		// @56: swap
		// @57: invokespecial java.lang.String.<init>(char[])void
		// @5A: invokevirtual java.lang.String.intern()java.lang.String
		// @5D: areturn
	}
}
