package game;

import java.applet.Applet;

final class C_100050_vg extends C_100158_da
{
	int field_100627_n;
	static C_100037_wb[] field_100638_p;
	int field_100635_s;
	static int field_100632_k;
	static int field_100636_r;
	static boolean field_100637_q;
	static boolean field_100631_j;
	static long field_100633_u;
	static String[] field_100629_l;
	static String field_100634_t;
	static String field_100628_o;
	static String field_100630_m;
	private static final String[] field_100639_z;
	
	public static void func_100626_e(int arg0)
	{
		// @00: iload_0
		// @01: iconst_1
		// @02: if_icmpeq @10
		// @05: aconst_null
		// @06: checkcast java.lang.String
		// @09: putstatic java.lang.String game.C_100050_vg.field_100634_t
		// @0C: goto @10
		// @0F: athrow
		// @10: aconst_null
		// @11: putstatic java.lang.String game.C_100050_vg.field_100630_m
		// @14: aconst_null
		// @15: putstatic java.lang.String[] game.C_100050_vg.field_100629_l
		// @18: aconst_null
		// @19: putstatic game.C_100037_wb[] game.C_100050_vg.field_100638_p
		// @1C: aconst_null
		// @1D: putstatic java.lang.String game.C_100050_vg.field_100634_t
		// @20: aconst_null
		// @21: putstatic java.lang.String game.C_100050_vg.field_100628_o
		// @24: goto @48
		// @27: astore_1
		// @28: aload_1
		// @29: new java.lang.StringBuilder
		// @2C: dup
		// @2D: invokespecial java.lang.StringBuilder.<init>()void
		// @30: getstatic java.lang.String[] game.C_100050_vg.field_100639_z
		// @33: iconst_0
		// @34: aaload
		// @35: invokevirtual java.lang.StringBuilder.append(java.lang.String)java.lang.StringBuilder
		// @38: iload_0
		// @39: invokevirtual java.lang.StringBuilder.append(int)java.lang.StringBuilder
		// @3C: bipush 41 (0x29)
		// @3E: invokevirtual java.lang.StringBuilder.append(char)java.lang.StringBuilder
		// @41: invokevirtual java.lang.StringBuilder.toString()java.lang.String
		// @44: invokestatic game.C_100181_cf.func_105695_a(java.lang.Throwable, java.lang.String)game.C_100170_cm
		// @47: athrow
		// @48: return
	}
	
	static final C_100302_ka func_100625_a(boolean arg0)
	{
		// @00: iload_0
		// @01: ifeq @0D
		// @04: bipush -54 (0xCA)
		// @06: invokestatic game.C_100050_vg.func_100623_a(byte)void
		// @09: goto @0D
		// @0C: athrow
		// @0D: getstatic game.C_100115_ej game.C_100179_ch.field_100811_n
		// @10: getfield game.C_100302_ka game.C_100115_ej.field_102036_Wb
		// @13: areturn
		// @14: astore_1
		// @15: aload_1
		// @16: new java.lang.StringBuilder
		// @19: dup
		// @1A: invokespecial java.lang.StringBuilder.<init>()void
		// @1D: getstatic java.lang.String[] game.C_100050_vg.field_100639_z
		// @20: bipush 10 (0x0A)
		// @22: aaload
		// @23: invokevirtual java.lang.StringBuilder.append(java.lang.String)java.lang.StringBuilder
		// @26: iload_0
		// @27: invokevirtual java.lang.StringBuilder.append(boolean)java.lang.StringBuilder
		// @2A: bipush 41 (0x29)
		// @2C: invokevirtual java.lang.StringBuilder.append(char)java.lang.StringBuilder
		// @2F: invokevirtual java.lang.StringBuilder.toString()java.lang.String
		// @32: invokestatic game.C_100181_cf.func_105695_a(java.lang.Throwable, java.lang.String)game.C_100170_cm
		// @35: athrow
	}
	
	static final void func_100620_a(int arg0, Applet arg1)
	{
		// @00: iload_0
		// @01: bipush 89 (0x59)
		// @03: if_icmpge @0E
		// @06: iconst_1
		// @07: putstatic boolean game.C_100050_vg.field_100631_j
		// @0A: goto @0E
		// @0D: athrow
		// @0E: new java.net.URL
		// @11: dup
		// @12: aload_1
		// @13: invokevirtual java.applet.Applet.getCodeBase()java.net.URL
		// @16: getstatic java.lang.String[] game.C_100050_vg.field_100639_z
		// @19: bipush 6 (0x06)
		// @1B: aaload
		// @1C: invokespecial java.net.URL.<init>(java.net.URL, java.lang.String)void
		// @1F: astore_2
		// @20: aload_1
		// @21: invokevirtual java.applet.Applet.getAppletContext()java.applet.AppletContext
		// @24: iconst_m1
		// @25: aload_2
		// @26: aload_1
		// @27: invokestatic game.C_100244_pe.func_106368_a(int, java.net.URL, java.applet.Applet)java.net.URL
		// @2A: getstatic java.lang.String[] game.C_100050_vg.field_100639_z
		// @2D: iconst_2
		// @2E: aaload
		// @2F: invokeinterface java.applet.AppletContext.showDocument(java.net.URL, java.lang.String)void
		// @34: goto @3C
		// @37: astore_2
		// @38: aload_2
		// @39: invokevirtual java.lang.Exception.printStackTrace()void
		// @3C: goto @7A
		// @3F: astore_2
		// @40: aload_2
		// @41: new java.lang.StringBuilder
		// @44: dup
		// @45: invokespecial java.lang.StringBuilder.<init>()void
		// @48: getstatic java.lang.String[] game.C_100050_vg.field_100639_z
		// @4B: iconst_5
		// @4C: aaload
		// @4D: invokevirtual java.lang.StringBuilder.append(java.lang.String)java.lang.StringBuilder
		// @50: iload_0
		// @51: invokevirtual java.lang.StringBuilder.append(int)java.lang.StringBuilder
		// @54: bipush 44 (0x2C)
		// @56: invokevirtual java.lang.StringBuilder.append(char)java.lang.StringBuilder
		// @59: aload_1
		// @5A: ifnull @66
		// @5D: getstatic java.lang.String[] game.C_100050_vg.field_100639_z
		// @60: iconst_4
		// @61: aaload
		// @62: goto @6B
		// @65: athrow
		// @66: getstatic java.lang.String[] game.C_100050_vg.field_100639_z
		// @69: iconst_3
		// @6A: aaload
		// @6B: invokevirtual java.lang.StringBuilder.append(java.lang.String)java.lang.StringBuilder
		// @6E: bipush 41 (0x29)
		// @70: invokevirtual java.lang.StringBuilder.append(char)java.lang.StringBuilder
		// @73: invokevirtual java.lang.StringBuilder.toString()java.lang.String
		// @76: invokestatic game.C_100181_cf.func_105695_a(java.lang.Throwable, java.lang.String)game.C_100170_cm
		// @79: athrow
		// @7A: return
	}
	
	private C_100050_vg() throws Throwable
	{
		// @00: aload_0
		// @01: invokespecial game.C_100158_da.<init>()void
		// @04: new java.lang.Error
		// @07: dup
		// @08: invokespecial java.lang.Error.<init>()void
		// @0B: athrow
		// @0C: astore_1
		// @0D: aload_1
		// @0E: getstatic java.lang.String[] game.C_100050_vg.field_100639_z
		// @11: iconst_1
		// @12: aaload
		// @13: invokestatic game.C_100181_cf.func_105695_a(java.lang.Throwable, java.lang.String)game.C_100170_cm
		// @16: athrow
	}
	
	static final boolean func_100621_a(String arg0, int arg1)
	{
		// @00: iload_1
		// @01: sipush -7290 (0xE386)
		// @04: if_icmpeq @10
		// @07: iconst_1
		// @08: invokestatic game.C_100050_vg.func_100625_a(boolean)game.C_100302_ka
		// @0B: pop
		// @0C: goto @10
		// @0F: athrow
		// @10: getstatic java.lang.String game.C_100285_nk.field_106782_e
		// @13: bipush -125 (0x83)
		// @15: aload_0
		// @16: invokestatic game.C_100106_ef.func_104742_a(byte, java.lang.CharSequence)java.lang.String
		// @19: invokevirtual java.lang.String.equals(java.lang.Object)boolean
		// @1C: ireturn
		// @1D: astore_2
		// @1E: aload_2
		// @1F: new java.lang.StringBuilder
		// @22: dup
		// @23: invokespecial java.lang.StringBuilder.<init>()void
		// @26: getstatic java.lang.String[] game.C_100050_vg.field_100639_z
		// @29: bipush 7 (0x07)
		// @2B: aaload
		// @2C: invokevirtual java.lang.StringBuilder.append(java.lang.String)java.lang.StringBuilder
		// @2F: aload_0
		// @30: ifnull @3C
		// @33: getstatic java.lang.String[] game.C_100050_vg.field_100639_z
		// @36: iconst_4
		// @37: aaload
		// @38: goto @41
		// @3B: athrow
		// @3C: getstatic java.lang.String[] game.C_100050_vg.field_100639_z
		// @3F: iconst_3
		// @40: aaload
		// @41: invokevirtual java.lang.StringBuilder.append(java.lang.String)java.lang.StringBuilder
		// @44: bipush 44 (0x2C)
		// @46: invokevirtual java.lang.StringBuilder.append(char)java.lang.StringBuilder
		// @49: iload_1
		// @4A: invokevirtual java.lang.StringBuilder.append(int)java.lang.StringBuilder
		// @4D: bipush 41 (0x29)
		// @4F: invokevirtual java.lang.StringBuilder.append(char)java.lang.StringBuilder
		// @52: invokevirtual java.lang.StringBuilder.toString()java.lang.String
		// @55: invokestatic game.C_100181_cf.func_105695_a(java.lang.Throwable, java.lang.String)game.C_100170_cm
		// @58: athrow
	}
	
	static final void func_100623_a(byte arg0)
	{
		// @000: getstatic int game.SteelSentinels.field_105275_O
		// @003: istore #26
		// @005: getstatic game.C_100278_nd game.C_100288_jn.field_106839_f
		// @008: astore_1
		// @009: iload_0
		// @00A: bipush 86 (0x56)
		// @00C: if_icmpge @01C
		// @00F: bipush -56 (0xC8)
		// @011: aconst_null
		// @012: checkcast java.applet.Applet
		// @015: invokestatic game.C_100050_vg.func_100620_a(int, java.applet.Applet)void
		// @018: goto @01C
		// @01B: athrow
		// @01C: aload_1
		// @01D: iconst_0
		// @01E: invokevirtual game.C_100278_nd.func_101156_c(boolean)int
		// @021: istore_2
		// @022: iload_2
		// @023: iconst_m1
		// @024: ixor
		// @025: iconst_m1
		// @026: if_icmpeq @0D4
		// @029: iload_2
		// @02A: iconst_1
		// @02B: if_icmpeq @061
		// @02E: goto @032
		// @031: athrow
		// @032: iconst_1
		// @033: new java.lang.StringBuilder
		// @036: dup
		// @037: invokespecial java.lang.StringBuilder.<init>()void
		// @03A: getstatic java.lang.String[] game.C_100050_vg.field_100639_z
		// @03D: bipush 9 (0x09)
		// @03F: aaload
		// @040: invokevirtual java.lang.StringBuilder.append(java.lang.String)java.lang.StringBuilder
		// @043: bipush 96 (0x60)
		// @045: invokestatic game.C_100316_lc.func_102399_d(byte)java.lang.String
		// @048: invokevirtual java.lang.StringBuilder.append(java.lang.String)java.lang.StringBuilder
		// @04B: invokevirtual java.lang.StringBuilder.toString()java.lang.String
		// @04E: aconst_null
		// @04F: invokestatic game.C_100036_gg.func_103142_a(int, java.lang.String, java.lang.Throwable)void
		// @052: sipush 13313 (0x3401)
		// @055: invokestatic game.C_100095_fe.func_103371_l(int)void
		// @058: iload #26
		// @05A: ifeq @3AA
		// @05D: goto @061
		// @060: athrow
		// @061: aload_1
		// @062: bipush -2 (0xFE)
		// @064: invokevirtual game.C_100278_nd.func_101143_l(int)int
		// @067: istore_3
		// @068: aload_1
		// @069: sipush -16142 (0xC0F2)
		// @06C: invokevirtual game.C_100278_nd.func_101161_i(int)long
		// @06F: lstore #4
		// @071: getstatic game.C_100202_qi game.C_100178_cg.field_105689_e
		// @074: bipush 58 (0x3A)
		// @076: invokevirtual game.C_100202_qi.func_105899_c(int)game.C_100158_da
		// @079: checkcast game.C_100292_jk
		// @07C: astore #6
		// @07E: aload #6
		// @080: ifnull @0B0
		// @083: iload_3
		// @084: iload #26
		// @086: ifne @0BD
		// @089: aload #6
		// @08B: getfield int game.C_100292_jk.field_101217_p
		// @08E: if_icmpne @09E
		// @091: goto @095
		// @094: athrow
		// @095: iload #26
		// @097: ifeq @0B0
		// @09A: goto @09E
		// @09D: athrow
		// @09E: getstatic game.C_100202_qi game.C_100178_cg.field_105689_e
		// @0A1: bipush 123 (0x7B)
		// @0A3: invokevirtual game.C_100202_qi.func_105907_c(byte)game.C_100158_da
		// @0A6: checkcast game.C_100292_jk
		// @0A9: astore #6
		// @0AB: iload #26
		// @0AD: ifeq @07E
		// @0B0: aconst_null
		// @0B1: aload #6
		// @0B3: if_acmpne @0C1
		// @0B6: sipush 13313 (0x3401)
		// @0B9: goto @0BD
		// @0BC: athrow
		// @0BD: invokestatic game.C_100095_fe.func_103371_l(int)void
		// @0C0: return
		// @0C1: aload #6
		// @0C3: lload #4
		// @0C5: putfield long game.C_100292_jk.field_101216_q
		// @0C8: aload #6
		// @0CA: bipush 45 (0x2D)
		// @0CC: invokevirtual game.C_100292_jk.func_100583_c(int)void
		// @0CF: iload #26
		// @0D1: ifeq @3AA
		// @0D4: aload_1
		// @0D5: bipush -2 (0xFE)
		// @0D7: invokevirtual game.C_100278_nd.func_101143_l(int)int
		// @0DA: istore_3
		// @0DB: getstatic game.C_100202_qi game.C_100143_bl.field_105100_g
		// @0DE: bipush 51 (0x33)
		// @0E0: invokevirtual game.C_100202_qi.func_105899_c(int)game.C_100158_da
		// @0E3: checkcast game.C_100187_rk
		// @0E6: astore #4
		// @0E8: aload #4
		// @0EA: ifnull @111
		// @0ED: iload_3
		// @0EE: iload #26
		// @0F0: ifne @11E
		// @0F3: aload #4
		// @0F5: getfield int game.C_100187_rk.field_100831_u
		// @0F8: if_icmpeq @111
		// @0FB: goto @0FF
		// @0FE: athrow
		// @0FF: getstatic game.C_100202_qi game.C_100143_bl.field_105100_g
		// @102: bipush 114 (0x72)
		// @104: invokevirtual game.C_100202_qi.func_105907_c(byte)game.C_100158_da
		// @107: checkcast game.C_100187_rk
		// @10A: astore #4
		// @10C: iload #26
		// @10E: ifeq @0E8
		// @111: aconst_null
		// @112: aload #4
		// @114: if_acmpeq @11B
		// @117: goto @122
		// @11A: athrow
		// @11B: sipush 13313 (0x3401)
		// @11E: invokestatic game.C_100095_fe.func_103371_l(int)void
		// @121: return
		// @122: aload_1
		// @123: iconst_0
		// @124: invokevirtual game.C_100278_nd.func_101156_c(boolean)int
		// @127: istore #5
		// @129: iconst_0
		// @12A: iload #5
		// @12C: if_icmpeq @39D
		// @12F: aload #4
		// @131: getfield int game.C_100187_rk.field_100833_s
		// @134: istore #6
		// @136: getstatic game.C_100304_kl[] game.C_100240_oj.field_106319_o
		// @139: iconst_0
		// @13A: aaload
		// @13B: iconst_0
		// @13C: putfield boolean game.C_100304_kl.field_107121_i
		// @13F: getstatic game.C_100304_kl[] game.C_100240_oj.field_106319_o
		// @142: iconst_0
		// @143: aaload
		// @144: getstatic java.lang.String game.C_100339_jb.field_107391_h
		// @147: putfield java.lang.String game.C_100304_kl.field_107113_e
		// @14A: getstatic game.C_100304_kl[] game.C_100240_oj.field_106319_o
		// @14D: iconst_0
		// @14E: aaload
		// @14F: aconst_null
		// @150: putfield java.lang.String game.C_100304_kl.field_107120_h
		// @153: aload #4
		// @155: getfield int game.C_100187_rk.field_100826_o
		// @158: istore #7
		// @15A: iconst_1
		// @15B: istore #8
		// @15D: iload #8
		// @15F: iconst_m1
		// @160: ixor
		// @161: iload #5
		// @163: iconst_m1
		// @164: ixor
		// @165: if_icmple @1C3
		// @168: getstatic game.C_100304_kl[] game.C_100240_oj.field_106319_o
		// @16B: iload #8
		// @16D: aaload
		// @16E: aload_1
		// @16F: sipush 9692 (0x25DC)
		// @172: invokevirtual game.C_100278_nd.func_101164_f(int)java.lang.String
		// @175: putfield java.lang.String game.C_100304_kl.field_107113_e
		// @178: getstatic game.C_100304_kl[] game.C_100240_oj.field_106319_o
		// @17B: iload #8
		// @17D: aaload
		// @17E: iconst_0
		// @17F: putfield boolean game.C_100304_kl.field_107121_i
		// @182: iload #26
		// @184: ifne @3A3
		// @187: aload_1
		// @188: iconst_0
		// @189: invokevirtual game.C_100278_nd.func_101156_c(boolean)int
		// @18C: iconst_1
		// @18D: if_icmpne @1AD
		// @190: goto @194
		// @193: athrow
		// @194: getstatic game.C_100304_kl[] game.C_100240_oj.field_106319_o
		// @197: iload #8
		// @199: aaload
		// @19A: aload_1
		// @19B: sipush 9692 (0x25DC)
		// @19E: invokevirtual game.C_100278_nd.func_101164_f(int)java.lang.String
		// @1A1: putfield java.lang.String game.C_100304_kl.field_107120_h
		// @1A4: iload #26
		// @1A6: ifeq @1BB
		// @1A9: goto @1AD
		// @1AC: athrow
		// @1AD: getstatic game.C_100304_kl[] game.C_100240_oj.field_106319_o
		// @1B0: iload #8
		// @1B2: aaload
		// @1B3: aconst_null
		// @1B4: putfield java.lang.String game.C_100304_kl.field_107120_h
		// @1B7: goto @1BB
		// @1BA: athrow
		// @1BB: iinc #8 +1
		// @1BE: iload #26
		// @1C0: ifeq @15D
		// @1C3: aload #4
		// @1C5: iconst_3
		// @1C6: iload #6
		// @1C8: multianewarray java.lang.String[][] (init: 2)
		// @1CC: dup_x1
		// @1CD: putfield java.lang.String[][] game.C_100187_rk.field_100825_n
		// @1D0: astore #8
		// @1D2: iconst_3
		// @1D3: iload #6
		// @1D5: multianewarray java.lang.String[][] (init: 2)
		// @1D9: astore #9
		// @1DB: aload #4
		// @1DD: iconst_3
		// @1DE: iload #6
		// @1E0: multianewarray long[][] (init: 2)
		// @1E4: dup_x1
		// @1E5: putfield long[][] game.C_100187_rk.field_100830_k
		// @1E8: astore #10
		// @1EA: aload #4
		// @1EC: iconst_3
		// @1ED: iload #7
		// @1EF: iload #6
		// @1F1: imul
		// @1F2: multianewarray int[][] (init: 2)
		// @1F6: dup_x1
		// @1F7: putfield int[][] game.C_100187_rk.field_100832_t
		// @1FA: astore #11
		// @1FC: iconst_0
		// @1FD: istore #12
		// @1FF: iconst_0
		// @200: istore #13
		// @202: iconst_0
		// @203: istore #14
		// @205: iconst_0
		// @206: istore #15
		// @208: iconst_0
		// @209: istore #16
		// @20B: iconst_0
		// @20C: istore #17
		// @20E: aload_1
		// @20F: iconst_0
		// @210: invokevirtual game.C_100278_nd.func_101156_c(boolean)int
		// @213: istore #18
		// @215: iload #18
		// @217: iconst_m1
		// @218: ixor
		// @219: iconst_m1
		// @21A: if_icmpge @39D
		// @21D: iconst_0
		// @21E: istore #19
		// @220: iload #19
		// @222: iload #18
		// @224: if_icmpge @39D
		// @227: aload_1
		// @228: iconst_0
		// @229: invokevirtual game.C_100278_nd.func_101156_c(boolean)int
		// @22C: istore #20
		// @22E: getstatic game.C_100304_kl[] game.C_100240_oj.field_106319_o
		// @231: iload #20
		// @233: aaload
		// @234: getfield java.lang.String game.C_100304_kl.field_107113_e
		// @237: astore #21
		// @239: aload_1
		// @23A: sipush -16142 (0xC0F2)
		// @23D: invokevirtual game.C_100278_nd.func_101161_i(int)long
		// @240: lstore #22
		// @242: aload_1
		// @243: getfield int game.C_100278_nd.field_101177_n
		// @246: istore #24
		// @248: iload #26
		// @24A: ifne @3A3
		// @24D: iload #19
		// @24F: iconst_m1
		// @250: ixor
		// @251: iload #6
		// @253: iconst_m1
		// @254: ixor
		// @255: if_icmpgt @260
		// @258: goto @25C
		// @25B: athrow
		// @25C: goto @2B1
		// @25F: athrow
		// @260: aload #8
		// @262: iconst_0
		// @263: aaload
		// @264: iload #12
		// @266: aload #21
		// @268: aastore
		// @269: aload #9
		// @26B: iconst_0
		// @26C: aaload
		// @26D: iload #12
		// @26F: getstatic game.C_100304_kl[] game.C_100240_oj.field_106319_o
		// @272: iload #20
		// @274: aaload
		// @275: getfield java.lang.String game.C_100304_kl.field_107120_h
		// @278: aastore
		// @279: aload #10
		// @27B: iconst_0
		// @27C: aaload
		// @27D: iload #12
		// @27F: lload #22
		// @281: lastore
		// @282: iinc #12 +1
		// @285: iconst_0
		// @286: istore #25
		// @288: iload #7
		// @28A: iload #25
		// @28C: if_icmple @2B1
		// @28F: aload #11
		// @291: iconst_0
		// @292: aaload
		// @293: iload #15
		// @295: iinc #15 +1
		// @298: aload_1
		// @299: sipush -1543 (0xF9F9)
		// @29C: invokevirtual game.C_100278_nd.func_101171_e(int)int
		// @29F: iastore
		// @2A0: iinc #25 +1
		// @2A3: iload #26
		// @2A5: ifne @319
		// @2A8: iload #26
		// @2AA: ifeq @288
		// @2AD: goto @2B1
		// @2B0: athrow
		// @2B1: aload #21
		// @2B3: ifnull @319
		// @2B6: aload #21
		// @2B8: sipush -7290 (0xE386)
		// @2BB: invokestatic game.C_100050_vg.func_100621_a(java.lang.String, int)boolean
		// @2BE: ifeq @319
		// @2C1: goto @2C5
		// @2C4: athrow
		// @2C5: aload #8
		// @2C7: iconst_1
		// @2C8: aaload
		// @2C9: iload #13
		// @2CB: getstatic java.lang.String game.C_100339_jb.field_107391_h
		// @2CE: aastore
		// @2CF: aload #9
		// @2D1: iconst_1
		// @2D2: aaload
		// @2D3: iload #13
		// @2D5: aconst_null
		// @2D6: aastore
		// @2D7: aload #10
		// @2D9: iconst_1
		// @2DA: aaload
		// @2DB: iload #13
		// @2DD: lload #22
		// @2DF: lastore
		// @2E0: iinc #13 +1
		// @2E3: aload_1
		// @2E4: iload #24
		// @2E6: putfield int game.C_100278_nd.field_101177_n
		// @2E9: iconst_0
		// @2EA: istore #25
		// @2EC: iload #7
		// @2EE: iconst_m1
		// @2EF: ixor
		// @2F0: iload #25
		// @2F2: iconst_m1
		// @2F3: ixor
		// @2F4: if_icmpge @319
		// @2F7: aload #11
		// @2F9: iconst_1
		// @2FA: aaload
		// @2FB: iload #16
		// @2FD: iinc #16 +1
		// @300: aload_1
		// @301: sipush -1543 (0xF9F9)
		// @304: invokevirtual game.C_100278_nd.func_101171_e(int)int
		// @307: iastore
		// @308: iinc #25 +1
		// @30B: iload #26
		// @30D: ifne @398
		// @310: iload #26
		// @312: ifeq @2EC
		// @315: goto @319
		// @318: athrow
		// @319: iload #6
		// @31B: iload #14
		// @31D: if_icmple @395
		// @320: getstatic game.C_100304_kl[] game.C_100240_oj.field_106319_o
		// @323: iload #20
		// @325: aaload
		// @326: getfield boolean game.C_100304_kl.field_107121_i
		// @329: ifeq @334
		// @32C: goto @330
		// @32F: athrow
		// @330: goto @395
		// @333: athrow
		// @334: getstatic game.C_100304_kl[] game.C_100240_oj.field_106319_o
		// @337: iload #20
		// @339: aaload
		// @33A: iconst_1
		// @33B: putfield boolean game.C_100304_kl.field_107121_i
		// @33E: aload #8
		// @340: iconst_2
		// @341: aaload
		// @342: iload #14
		// @344: aload #21
		// @346: aastore
		// @347: aload #9
		// @349: iconst_2
		// @34A: aaload
		// @34B: iload #14
		// @34D: getstatic game.C_100304_kl[] game.C_100240_oj.field_106319_o
		// @350: iload #20
		// @352: aaload
		// @353: getfield java.lang.String game.C_100304_kl.field_107120_h
		// @356: aastore
		// @357: aload #10
		// @359: iconst_2
		// @35A: aaload
		// @35B: iload #14
		// @35D: lload #22
		// @35F: lastore
		// @360: iinc #14 +1
		// @363: aload_1
		// @364: iload #24
		// @366: putfield int game.C_100278_nd.field_101177_n
		// @369: iconst_0
		// @36A: istore #25
		// @36C: iload #7
		// @36E: iload #25
		// @370: if_icmple @395
		// @373: aload #11
		// @375: iconst_2
		// @376: aaload
		// @377: iload #17
		// @379: iinc #17 +1
		// @37C: aload_1
		// @37D: sipush -1543 (0xF9F9)
		// @380: invokevirtual game.C_100278_nd.func_101171_e(int)int
		// @383: iastore
		// @384: iinc #25 +1
		// @387: iload #26
		// @389: ifne @398
		// @38C: iload #26
		// @38E: ifeq @36C
		// @391: goto @395
		// @394: athrow
		// @395: iinc #19 +1
		// @398: iload #26
		// @39A: ifeq @220
		// @39D: aload #4
		// @39F: iconst_1
		// @3A0: putfield boolean game.C_100187_rk.field_100829_j
		// @3A3: aload #4
		// @3A5: bipush 45 (0x2D)
		// @3A7: invokevirtual game.C_100187_rk.func_100583_c(int)void
		// @3AA: goto @3CF
		// @3AD: astore_1
		// @3AE: aload_1
		// @3AF: new java.lang.StringBuilder
		// @3B2: dup
		// @3B3: invokespecial java.lang.StringBuilder.<init>()void
		// @3B6: getstatic java.lang.String[] game.C_100050_vg.field_100639_z
		// @3B9: bipush 8 (0x08)
		// @3BB: aaload
		// @3BC: invokevirtual java.lang.StringBuilder.append(java.lang.String)java.lang.StringBuilder
		// @3BF: iload_0
		// @3C0: invokevirtual java.lang.StringBuilder.append(int)java.lang.StringBuilder
		// @3C3: bipush 41 (0x29)
		// @3C5: invokevirtual java.lang.StringBuilder.append(char)java.lang.StringBuilder
		// @3C8: invokevirtual java.lang.StringBuilder.toString()java.lang.String
		// @3CB: invokestatic game.C_100181_cf.func_105695_a(java.lang.Throwable, java.lang.String)game.C_100170_cm
		// @3CE: athrow
		// @3CF: return
	}
	
	static
	{
		// @00: bipush 11 (0x0B)
		// @02: anewarray java.lang.String
		// @05: dup
		// @06: iconst_0
		// @07: ldc "S7BT\u0003"
		// @09: invokestatic game.C_100050_vg.func_100624_z(java.lang.String)char[]
		// @0C: invokestatic game.C_100050_vg.func_100622_z(char[])java.lang.String
		// @0F: aastore
		// @10: dup
		// @11: iconst_1
		// @12: ldc "S7B-BK9\u0018/\u0003\u000c"
		// @14: invokestatic game.C_100050_vg.func_100624_z(java.lang.String)char[]
		// @17: invokestatic game.C_100050_vg.func_100622_z(char[])java.lang.String
		// @1A: aastore
		// @1B: dup
		// @1C: iconst_2
		// @1D: ldc "z$\u0003a"
		// @1F: invokestatic game.C_100050_vg.func_100624_z(java.lang.String)char[]
		// @22: invokestatic game.C_100050_vg.func_100622_z(char[])java.lang.String
		// @25: aastore
		// @26: dup
		// @27: iconst_3
		// @28: ldc "K%\u0000}"
		// @2A: invokestatic game.C_100050_vg.func_100624_z(java.lang.String)char[]
		// @2D: invokestatic game.C_100050_vg.func_100622_z(char[])java.lang.String
		// @30: aastore
		// @31: dup
		// @32: iconst_4
		// @33: ldc "^~B?V"
		// @35: invokestatic game.C_100050_vg.func_100624_z(java.lang.String)char[]
		// @38: invokestatic game.C_100050_vg.func_100622_z(char[])java.lang.String
		// @3B: aastore
		// @3C: dup
		// @3D: iconst_5
		// @3E: ldc "S7BS\u0003"
		// @40: invokestatic game.C_100050_vg.func_100624_z(java.lang.String)char[]
		// @43: invokestatic game.C_100050_vg.func_100622_z(char[])java.lang.String
		// @46: aastore
		// @47: dup
		// @48: bipush 6 (0x06)
		// @4A: ldc "Q?\u001fd[U?\u001ee\u0005R#"
		// @4C: invokestatic game.C_100050_vg.func_100624_z(java.lang.String)char[]
		// @4F: invokestatic game.C_100050_vg.func_100622_z(char[])java.lang.String
		// @52: aastore
		// @53: dup
		// @54: bipush 7 (0x07)
		// @56: ldc "S7BR\u0003"
		// @58: invokestatic game.C_100050_vg.func_100624_z(java.lang.String)char[]
		// @5B: invokestatic game.C_100050_vg.func_100622_z(char[])java.lang.String
		// @5E: aastore
		// @5F: dup
		// @60: bipush 8 (0x08)
		// @62: ldc "S7BP\u0003"
		// @64: invokestatic game.C_100050_vg.func_100624_z(java.lang.String)char[]
		// @67: invokestatic game.C_100050_vg.func_100622_z(char[])java.lang.String
		// @6A: aastore
		// @6B: dup
		// @6C: bipush 9 (0x09)
		// @6E: ldc "m\u0003]+\u000b"
		// @70: invokestatic game.C_100050_vg.func_100624_z(java.lang.String)char[]
		// @73: invokestatic game.C_100050_vg.func_100622_z(char[])java.lang.String
		// @76: aastore
		// @77: dup
		// @78: bipush 10 (0x0A)
		// @7A: ldc "S7BU\u0003"
		// @7C: invokestatic game.C_100050_vg.func_100624_z(java.lang.String)char[]
		// @7F: invokestatic game.C_100050_vg.func_100622_z(char[])java.lang.String
		// @82: aastore
		// @83: putstatic java.lang.String[] game.C_100050_vg.field_100639_z
		// @86: iconst_1
		// @87: putstatic boolean game.C_100050_vg.field_100637_q
		// @8A: iconst_2
		// @8B: anewarray java.lang.String
		// @8E: dup
		// @8F: iconst_0
		// @90: ldc "v8\u0003fBK7LsR\u0005\"\reBK7"
		// @92: invokestatic game.C_100050_vg.func_100624_z(java.lang.String)char[]
		// @95: invokestatic game.C_100050_vg.func_100622_z(char[])java.lang.String
		// @98: aastore
		// @99: dup
		// @9A: iconst_1
		// @9B: ldc "v8\u0003fBK7LsR\u0005'\u0005\u007f\u000bU5\u001erNK$\rvN"
		// @9D: invokestatic game.C_100050_vg.func_100624_z(java.lang.String)char[]
		// @A0: invokestatic game.C_100050_vg.func_100622_z(char[])java.lang.String
		// @A3: aastore
		// @A4: putstatic java.lang.String[] game.C_100050_vg.field_100629_l
		// @A7: ldc "d3\u000ft[Qp\u0005\u007f]L$\reBJ>LeD\u0005lI!\u0015\u0002#LvJH5"
		// @A9: invokestatic game.C_100050_vg.func_100624_z(java.lang.String)char[]
		// @AC: invokestatic game.C_100050_vg.func_100622_z(char[])java.lang.String
		// @AF: putstatic java.lang.String game.C_100050_vg.field_100634_t
		// @B2: ldc "v \tr_D$\u0005\u007fL\u0005lI!\u0015\u0002#LvJH5"
		// @B4: invokestatic game.C_100050_vg.func_100624_z(java.lang.String)char[]
		// @B7: invokestatic game.C_100050_vg.func_100622_z(char[])java.lang.String
		// @BA: putstatic java.lang.String game.C_100050_vg.field_100628_o
		// @BD: return
	}
	
	private static char[] func_100624_z(String arg0)
	{
		// @00: aload_0
		// @01: invokevirtual java.lang.String.toCharArray()char[]
		// @04: dup
		// @05: arraylength
		// @06: iconst_2
		// @07: if_icmpge @13
		// @0A: dup
		// @0B: iconst_0
		// @0C: dup2
		// @0D: caload
		// @0E: bipush 43 (0x2B)
		// @10: ixor
		// @11: i2c
		// @12: castore
		// @13: areturn
	}
	
	private static String func_100622_z(char[] arg0)
	{
		// @00: aload_0
		// @01: dup
		// @02: arraylength
		// @03: swap
		// @04: iconst_0
		// @05: istore_1
		// @06: goto @4C
		// @09: dup
		// @0A: iload_1
		// @0B: dup2
		// @0C: caload
		// @0D: iload_1
		// @0E: iconst_5
		// @0F: irem
		// @10: tableswitch def: @44, for 0: @30, for 1: @35, for 2: @3A, for 3: @3F
		// @30: bipush 37 (0x25)
		// @32: goto @46
		// @35: bipush 80 (0x50)
		// @37: goto @46
		// @3A: bipush 108 (0x6C)
		// @3C: goto @46
		// @3F: bipush 17 (0x11)
		// @41: goto @46
		// @44: bipush 43 (0x2B)
		// @46: ixor
		// @47: i2c
		// @48: castore
		// @49: iinc #1 +1
		// @4C: swap
		// @4D: dup_x1
		// @4E: iload_1
		// @4F: if_icmpgt @09
		// @52: new java.lang.String
		// @55: dup_x1
		// @56: swap
		// @57: invokespecial java.lang.String.<init>(char[])void
		// @5A: invokevirtual java.lang.String.intern()java.lang.String
		// @5D: areturn
	}
}
