package game;

final class C_100235_om
{
	static C_100302_ka field_106289_e;
	static C_100037_wb[] field_106293_n;
	static int[] field_106290_b;
	static C_100002_gf field_106292_a;
	static int[] field_106286_f;
	static String field_106291_c;
	static boolean field_106287_g;
	static int[] field_106297_k;
	static String[][] field_106288_d;
	static C_100302_ka field_106296_j;
	static String field_106295_m;
	static int[] field_106294_l;
	static int[] field_106299_i;
	static String field_106298_h;
	private static final String[] field_106300_z;
	
	static final void func_106285_a(C_100037_wb arg0, int arg1)
	{
		// @000: getstatic int game.SteelSentinels.field_105275_O
		// @003: istore #9
		// @005: iconst_m1
		// @006: iconst_3
		// @007: aload_0
		// @008: getfield int game.C_100037_wb.field_102332_H
		// @00B: aload_0
		// @00C: getfield int game.C_100037_wb.field_102337_u
		// @00F: aload_0
		// @010: getfield int game.C_100037_wb.field_102339_s
		// @013: ior
		// @014: aload_0
		// @015: getfield int game.C_100037_wb.field_102335_w
		// @018: ior
		// @019: ior
		// @01A: iand
		// @01B: iconst_m1
		// @01C: ixor
		// @01D: if_icmpeq @023
		// @020: goto @024
		// @023: return
		// @024: iconst_3
		// @025: aload_0
		// @026: getfield int game.C_100037_wb.field_102335_w
		// @029: iand
		// @02A: aload_0
		// @02B: getfield int game.C_100037_wb.field_102339_s
		// @02E: iadd
		// @02F: istore_2
		// @030: aload_0
		// @031: getfield int game.C_100037_wb.field_102332_H
		// @034: iconst_3
		// @035: iand
		// @036: aload_0
		// @037: getfield int game.C_100037_wb.field_102337_u
		// @03A: iadd
		// @03B: istore_3
		// @03C: iconst_4
		// @03D: iload_2
		// @03E: iconst_3
		// @03F: iand
		// @040: iload_2
		// @041: isub
		// @042: isub
		// @043: istore_2
		// @044: iload_3
		// @045: bipush -4 (0xFC)
		// @047: isub
		// @048: iload_3
		// @049: iconst_3
		// @04A: iand
		// @04B: isub
		// @04C: istore_3
		// @04D: iload_3
		// @04E: iload_2
		// @04F: imul
		// @050: newarray int[]
		// @052: astore #4
		// @054: iconst_0
		// @055: istore #5
		// @057: iconst_3
		// @058: aload_0
		// @059: getfield int game.C_100037_wb.field_102332_H
		// @05C: iand
		// @05D: iload_2
		// @05E: imul
		// @05F: iconst_3
		// @060: aload_0
		// @061: getfield int game.C_100037_wb.field_102335_w
		// @064: iand
		// @065: iadd
		// @066: istore #6
		// @068: iconst_0
		// @069: istore #7
		// @06B: aload_0
		// @06C: getfield int game.C_100037_wb.field_102337_u
		// @06F: iconst_m1
		// @070: ixor
		// @071: iload #7
		// @073: iconst_m1
		// @074: ixor
		// @075: if_icmpge @0C4
		// @078: iconst_0
		// @079: iload #9
		// @07B: ifne @0DB
		// @07E: istore #8
		// @080: aload_0
		// @081: getfield int game.C_100037_wb.field_102339_s
		// @084: iconst_m1
		// @085: ixor
		// @086: iload #8
		// @088: iconst_m1
		// @089: ixor
		// @08A: if_icmpge @0B0
		// @08D: aload #4
		// @08F: iload #6
		// @091: iinc #6 +1
		// @094: aload_0
		// @095: getfield int[] game.C_100037_wb.field_102388_J
		// @098: iload #5
		// @09A: iinc #5 +1
		// @09D: iaload
		// @09E: iastore
		// @09F: iinc #8 +1
		// @0A2: iload #9
		// @0A4: ifne @0BF
		// @0A7: iload #9
		// @0A9: ifeq @080
		// @0AC: goto @0B0
		// @0AF: athrow
		// @0B0: iload #6
		// @0B2: aload_0
		// @0B3: getfield int game.C_100037_wb.field_102339_s
		// @0B6: ineg
		// @0B7: iload_2
		// @0B8: iadd
		// @0B9: iadd
		// @0BA: istore #6
		// @0BC: iinc #7 +1
		// @0BF: iload #9
		// @0C1: ifeq @06B
		// @0C4: aload_0
		// @0C5: dup
		// @0C6: getfield int game.C_100037_wb.field_102332_H
		// @0C9: bipush -4 (0xFC)
		// @0CB: iand
		// @0CC: putfield int game.C_100037_wb.field_102332_H
		// @0CF: aload_0
		// @0D0: dup
		// @0D1: getfield int game.C_100037_wb.field_102335_w
		// @0D4: bipush -4 (0xFC)
		// @0D6: iand
		// @0D7: putfield int game.C_100037_wb.field_102335_w
		// @0DA: iload_1
		// @0DB: bipush 11 (0x0B)
		// @0DD: if_icmpgt @0F9
		// @0E0: aconst_null
		// @0E1: checkcast int[]
		// @0E4: aconst_null
		// @0E5: checkcast int[]
		// @0E8: bipush -95 (0xA1)
		// @0EA: aconst_null
		// @0EB: checkcast int[]
		// @0EE: bipush -82 (0xAE)
		// @0F0: iconst_0
		// @0F1: invokestatic game.C_100235_om.func_106281_a(int[], int[], int, int[], byte, boolean)boolean
		// @0F4: pop
		// @0F5: goto @0F9
		// @0F8: athrow
		// @0F9: aload_0
		// @0FA: iload_2
		// @0FB: putfield int game.C_100037_wb.field_102339_s
		// @0FE: aload_0
		// @0FF: iload_3
		// @100: putfield int game.C_100037_wb.field_102337_u
		// @103: aload_0
		// @104: aload #4
		// @106: putfield int[] game.C_100037_wb.field_102388_J
		// @109: goto @147
		// @10C: astore_2
		// @10D: aload_2
		// @10E: new java.lang.StringBuilder
		// @111: dup
		// @112: invokespecial java.lang.StringBuilder.<init>()void
		// @115: getstatic java.lang.String[] game.C_100235_om.field_106300_z
		// @118: iconst_0
		// @119: aaload
		// @11A: invokevirtual java.lang.StringBuilder.append(java.lang.String)java.lang.StringBuilder
		// @11D: aload_0
		// @11E: ifnull @12A
		// @121: getstatic java.lang.String[] game.C_100235_om.field_106300_z
		// @124: iconst_2
		// @125: aaload
		// @126: goto @12F
		// @129: athrow
		// @12A: getstatic java.lang.String[] game.C_100235_om.field_106300_z
		// @12D: iconst_1
		// @12E: aaload
		// @12F: invokevirtual java.lang.StringBuilder.append(java.lang.String)java.lang.StringBuilder
		// @132: bipush 44 (0x2C)
		// @134: invokevirtual java.lang.StringBuilder.append(char)java.lang.StringBuilder
		// @137: iload_1
		// @138: invokevirtual java.lang.StringBuilder.append(int)java.lang.StringBuilder
		// @13B: bipush 41 (0x29)
		// @13D: invokevirtual java.lang.StringBuilder.append(char)java.lang.StringBuilder
		// @140: invokevirtual java.lang.StringBuilder.toString()java.lang.String
		// @143: invokestatic game.C_100181_cf.func_105695_a(java.lang.Throwable, java.lang.String)game.C_100170_cm
		// @146: athrow
		// @147: return
	}
	
	public static void func_106282_a(int arg0)
	{
		// @00: aconst_null
		// @01: putstatic java.lang.String game.C_100235_om.field_106295_m
		// @04: aconst_null
		// @05: putstatic int[] game.C_100235_om.field_106294_l
		// @08: aconst_null
		// @09: putstatic java.lang.String game.C_100235_om.field_106291_c
		// @0C: aconst_null
		// @0D: putstatic int[] game.C_100235_om.field_106286_f
		// @10: aconst_null
		// @11: putstatic game.C_100302_ka game.C_100235_om.field_106289_e
		// @14: aconst_null
		// @15: putstatic game.C_100002_gf game.C_100235_om.field_106292_a
		// @18: aconst_null
		// @19: checkcast java.lang.String[][]
		// @1C: putstatic java.lang.String[][] game.C_100235_om.field_106288_d
		// @1F: aconst_null
		// @20: putstatic java.lang.String game.C_100235_om.field_106298_h
		// @23: aconst_null
		// @24: putstatic game.C_100302_ka game.C_100235_om.field_106296_j
		// @27: aconst_null
		// @28: putstatic game.C_100037_wb[] game.C_100235_om.field_106293_n
		// @2B: aconst_null
		// @2C: putstatic int[] game.C_100235_om.field_106299_i
		// @2F: iload_0
		// @30: sipush 29982 (0x751E)
		// @33: if_icmpeq @37
		// @36: return
		// @37: aconst_null
		// @38: putstatic int[] game.C_100235_om.field_106297_k
		// @3B: aconst_null
		// @3C: putstatic int[] game.C_100235_om.field_106290_b
		// @3F: goto @63
		// @42: astore_1
		// @43: aload_1
		// @44: new java.lang.StringBuilder
		// @47: dup
		// @48: invokespecial java.lang.StringBuilder.<init>()void
		// @4B: getstatic java.lang.String[] game.C_100235_om.field_106300_z
		// @4E: iconst_3
		// @4F: aaload
		// @50: invokevirtual java.lang.StringBuilder.append(java.lang.String)java.lang.StringBuilder
		// @53: iload_0
		// @54: invokevirtual java.lang.StringBuilder.append(int)java.lang.StringBuilder
		// @57: bipush 41 (0x29)
		// @59: invokevirtual java.lang.StringBuilder.append(char)java.lang.StringBuilder
		// @5C: invokevirtual java.lang.StringBuilder.toString()java.lang.String
		// @5F: invokestatic game.C_100181_cf.func_105695_a(java.lang.Throwable, java.lang.String)game.C_100170_cm
		// @62: athrow
		// @63: return
	}
	
	static final boolean func_106281_a(int[] arg0, int[] arg1, int arg2, int[] arg3, byte arg4, boolean arg5)
	{
		// @000: getstatic int game.SteelSentinels.field_105275_O
		// @003: istore #11
		// @005: iload_2
		// @006: istore #6
		// @008: bipush -35 (0xDD)
		// @00A: iload #6
		// @00C: iconst_m1
		// @00D: ixor
		// @00E: if_icmpeq @053
		// @011: bipush 27 (0x1B)
		// @013: iload #6
		// @015: if_icmpeq @055
		// @018: goto @01C
		// @01B: athrow
		// @01C: bipush -34 (0xDE)
		// @01E: iload #6
		// @020: iconst_m1
		// @021: ixor
		// @022: if_icmpne @032
		// @025: goto @029
		// @028: athrow
		// @029: iload #11
		// @02B: ifeq @055
		// @02E: goto @032
		// @031: athrow
		// @032: bipush 32 (0x20)
		// @034: iload #6
		// @036: if_icmpeq @055
		// @039: goto @03D
		// @03C: athrow
		// @03D: bipush -25 (0xE7)
		// @03F: iload #6
		// @041: iconst_m1
		// @042: ixor
		// @043: if_icmpne @069
		// @046: goto @04A
		// @049: athrow
		// @04A: iload #11
		// @04C: ifeq @05F
		// @04F: goto @053
		// @052: athrow
		// @053: iconst_0
		// @054: ireturn
		// @055: iload #5
		// @057: aload_0
		// @058: bipush 62 (0x3E)
		// @05A: iconst_0
		// @05B: invokestatic game.C_100171_cn.func_105561_a(boolean, int[], int, boolean)boolean
		// @05E: ireturn
		// @05F: iload #5
		// @061: aload_0
		// @062: bipush 84 (0x54)
		// @064: iconst_0
		// @065: invokestatic game.C_100171_cn.func_105561_a(boolean, int[], int, boolean)boolean
		// @068: ireturn
		// @069: getstatic int[] game.C_100017_wj.field_103821_j
		// @06C: astore #6
		// @06E: iconst_0
		// @06F: istore #7
		// @071: iload #7
		// @073: iconst_m1
		// @074: ixor
		// @075: aload #6
		// @077: arraylength
		// @078: iconst_m1
		// @079: ixor
		// @07A: if_icmple @0E1
		// @07D: aload #6
		// @07F: iload #7
		// @081: iaload
		// @082: istore #8
		// @084: iload #8
		// @086: aload_0
		// @087: bipush -125 (0x83)
		// @089: invokestatic game.C_100097_k.func_104572_a(int, int[], int)boolean
		// @08C: iload #11
		// @08E: ifne @0EF
		// @091: ifne @0A8
		// @094: goto @098
		// @097: athrow
		// @098: iload #5
		// @09A: aload_0
		// @09B: iload #8
		// @09D: iconst_0
		// @09E: invokestatic game.C_100171_cn.func_105561_a(boolean, int[], int, boolean)boolean
		// @0A1: ifeq @0D9
		// @0A4: goto @0A8
		// @0A7: athrow
		// @0A8: bipush -50 (0xCE)
		// @0AA: iload #8
		// @0AC: invokestatic game.C_100042_we.func_104129_b(int, int)int[]
		// @0AF: astore #9
		// @0B1: bipush -8 (0xF8)
		// @0B3: aload #9
		// @0B5: arraylength
		// @0B6: iadd
		// @0B7: istore #10
		// @0B9: aload #9
		// @0BB: arraylength
		// @0BC: iload #10
		// @0BE: if_icmple @0D9
		// @0C1: iload_2
		// @0C2: aload #9
		// @0C4: iload #10
		// @0C6: iaload
		// @0C7: iload #11
		// @0C9: ifne @07A
		// @0CC: if_icmpne @0D1
		// @0CF: iconst_1
		// @0D0: ireturn
		// @0D1: iinc #10 +1
		// @0D4: iload #11
		// @0D6: ifeq @0B9
		// @0D9: iinc #7 +1
		// @0DC: iload #11
		// @0DE: ifeq @071
		// @0E1: bipush 41 (0x29)
		// @0E3: iload #4
		// @0E5: bipush 24 (0x18)
		// @0E7: isub
		// @0E8: bipush 62 (0x3E)
		// @0EA: idiv
		// @0EB: irem
		// @0EC: istore #7
		// @0EE: iconst_0
		// @0EF: ireturn
		// @0F0: astore #6
		// @0F2: aload #6
		// @0F4: new java.lang.StringBuilder
		// @0F7: dup
		// @0F8: invokespecial java.lang.StringBuilder.<init>()void
		// @0FB: getstatic java.lang.String[] game.C_100235_om.field_106300_z
		// @0FE: iconst_4
		// @0FF: aaload
		// @100: invokevirtual java.lang.StringBuilder.append(java.lang.String)java.lang.StringBuilder
		// @103: aload_0
		// @104: ifnull @110
		// @107: getstatic java.lang.String[] game.C_100235_om.field_106300_z
		// @10A: iconst_2
		// @10B: aaload
		// @10C: goto @115
		// @10F: athrow
		// @110: getstatic java.lang.String[] game.C_100235_om.field_106300_z
		// @113: iconst_1
		// @114: aaload
		// @115: invokevirtual java.lang.StringBuilder.append(java.lang.String)java.lang.StringBuilder
		// @118: bipush 44 (0x2C)
		// @11A: invokevirtual java.lang.StringBuilder.append(char)java.lang.StringBuilder
		// @11D: aload_1
		// @11E: ifnull @12A
		// @121: getstatic java.lang.String[] game.C_100235_om.field_106300_z
		// @124: iconst_2
		// @125: aaload
		// @126: goto @12F
		// @129: athrow
		// @12A: getstatic java.lang.String[] game.C_100235_om.field_106300_z
		// @12D: iconst_1
		// @12E: aaload
		// @12F: invokevirtual java.lang.StringBuilder.append(java.lang.String)java.lang.StringBuilder
		// @132: bipush 44 (0x2C)
		// @134: invokevirtual java.lang.StringBuilder.append(char)java.lang.StringBuilder
		// @137: iload_2
		// @138: invokevirtual java.lang.StringBuilder.append(int)java.lang.StringBuilder
		// @13B: bipush 44 (0x2C)
		// @13D: invokevirtual java.lang.StringBuilder.append(char)java.lang.StringBuilder
		// @140: aload_3
		// @141: ifnull @14D
		// @144: getstatic java.lang.String[] game.C_100235_om.field_106300_z
		// @147: iconst_2
		// @148: aaload
		// @149: goto @152
		// @14C: athrow
		// @14D: getstatic java.lang.String[] game.C_100235_om.field_106300_z
		// @150: iconst_1
		// @151: aaload
		// @152: invokevirtual java.lang.StringBuilder.append(java.lang.String)java.lang.StringBuilder
		// @155: bipush 44 (0x2C)
		// @157: invokevirtual java.lang.StringBuilder.append(char)java.lang.StringBuilder
		// @15A: iload #4
		// @15C: invokevirtual java.lang.StringBuilder.append(int)java.lang.StringBuilder
		// @15F: bipush 44 (0x2C)
		// @161: invokevirtual java.lang.StringBuilder.append(char)java.lang.StringBuilder
		// @164: iload #5
		// @166: invokevirtual java.lang.StringBuilder.append(boolean)java.lang.StringBuilder
		// @169: bipush 41 (0x29)
		// @16B: invokevirtual java.lang.StringBuilder.append(char)java.lang.StringBuilder
		// @16E: invokevirtual java.lang.StringBuilder.toString()java.lang.String
		// @171: invokestatic game.C_100181_cf.func_105695_a(java.lang.Throwable, java.lang.String)game.C_100170_cm
		// @174: athrow
	}
	
	static
	{
		// @000: iconst_5
		// @001: anewarray java.lang.String
		// @004: dup
		// @005: iconst_0
		// @006: ldc "\u0000O\u001aGG"
		// @008: invokestatic game.C_100235_om.func_106284_z(java.lang.String)char[]
		// @00B: invokestatic game.C_100235_om.func_106283_z(char[])java.lang.String
		// @00E: aastore
		// @00F: dup
		// @010: iconst_1
		// @011: ldc "\u0001WXj"
		// @013: invokestatic game.C_100235_om.func_106284_z(java.lang.String)char[]
		// @016: invokestatic game.C_100235_om.func_106283_z(char[])java.lang.String
		// @019: aastore
		// @01A: dup
		// @01B: iconst_2
		// @01C: ldc "\u0014\u000c\u001a(\u0012"
		// @01E: invokestatic game.C_100235_om.func_106284_z(java.lang.String)char[]
		// @021: invokestatic game.C_100235_om.func_106283_z(char[])java.lang.String
		// @024: aastore
		// @025: dup
		// @026: iconst_3
		// @027: ldc "\u0000O\u001aDG"
		// @029: invokestatic game.C_100235_om.func_106284_z(java.lang.String)char[]
		// @02C: invokestatic game.C_100235_om.func_106283_z(char[])java.lang.String
		// @02F: aastore
		// @030: dup
		// @031: iconst_4
		// @032: ldc "\u0000O\u001aEG"
		// @034: invokestatic game.C_100235_om.func_106284_z(java.lang.String)char[]
		// @037: invokestatic game.C_100235_om.func_106283_z(char[])java.lang.String
		// @03A: aastore
		// @03B: putstatic java.lang.String[] game.C_100235_om.field_106300_z
		// @03E: bipush 20 (0x14)
		// @040: newarray int[]
		// @042: dup
		// @043: iconst_0
		// @044: iconst_0
		// @045: iastore
		// @046: dup
		// @047: iconst_1
		// @048: bipush 49 (0x31)
		// @04A: iastore
		// @04B: dup
		// @04C: iconst_2
		// @04D: bipush 96 (0x60)
		// @04F: iastore
		// @050: dup
		// @051: iconst_3
		// @052: bipush 29 (0x1D)
		// @054: iastore
		// @055: dup
		// @056: iconst_4
		// @057: iconst_1
		// @058: iastore
		// @059: dup
		// @05A: iconst_5
		// @05B: bipush 17 (0x11)
		// @05D: iastore
		// @05E: dup
		// @05F: bipush 6 (0x06)
		// @061: iconst_3
		// @062: iastore
		// @063: dup
		// @064: bipush 7 (0x07)
		// @066: bipush 26 (0x1A)
		// @068: iastore
		// @069: dup
		// @06A: bipush 8 (0x08)
		// @06C: bipush 26 (0x1A)
		// @06E: iastore
		// @06F: dup
		// @070: bipush 9 (0x09)
		// @072: bipush 26 (0x1A)
		// @074: iastore
		// @075: dup
		// @076: bipush 10 (0x0A)
		// @078: iconst_2
		// @079: iastore
		// @07A: dup
		// @07B: bipush 11 (0x0B)
		// @07D: bipush 30 (0x1E)
		// @07F: iastore
		// @080: dup
		// @081: bipush 12 (0x0C)
		// @083: iconst_0
		// @084: iastore
		// @085: dup
		// @086: bipush 13 (0x0D)
		// @088: bipush 21 (0x15)
		// @08A: iastore
		// @08B: dup
		// @08C: bipush 14 (0x0E)
		// @08E: bipush 10 (0x0A)
		// @090: iastore
		// @091: dup
		// @092: bipush 15 (0x0F)
		// @094: bipush 26 (0x1A)
		// @096: iastore
		// @097: dup
		// @098: bipush 16 (0x10)
		// @09A: iconst_m1
		// @09B: iastore
		// @09C: dup
		// @09D: bipush 17 (0x11)
		// @09F: iconst_m1
		// @0A0: iastore
		// @0A1: dup
		// @0A2: bipush 18 (0x12)
		// @0A4: iconst_m1
		// @0A5: iastore
		// @0A6: dup
		// @0A7: bipush 19 (0x13)
		// @0A9: iconst_m1
		// @0AA: iastore
		// @0AB: putstatic int[] game.C_100235_om.field_106290_b
		// @0AE: ldc ".A\\o\n\u0019GYc\u0001\u001bQ"
		// @0B0: invokestatic game.C_100235_om.func_106284_z(java.lang.String)char[]
		// @0B3: invokestatic game.C_100235_om.func_106283_z(char[])java.lang.String
		// @0B6: putstatic java.lang.String game.C_100235_om.field_106291_c
		// @0B9: bipush 10 (0x0A)
		// @0BB: anewarray java.lang.String[]
		// @0BE: dup
		// @0BF: iconst_0
		// @0C0: bipush 24 (0x18)
		// @0C2: anewarray java.lang.String
		// @0C5: dup
		// @0C6: iconst_0
		// @0C7: ldc "8GXe\u0000\u0002G\u0014r\u0000O@Uu\u0006\u000c\u0002Wi\u0001\u001bP[jO\u000eLP&\u0001\u000eT]a\u000e\u001bK[hO\u001bPUo\u0001\u0006LS(O)KFu\u001bO[[sO\u0018KXjO\u0003GUt\u0001OV[&\u0002\u0000TQ&\u0016\u0000WF&\u001c\nL@o\u0001\nN\u0014g\u0003\u0000LS&\u001b\u0007G\u0014a\u001d\u0000WZbAOd[tO\u001bJ]uO\u0016MA&\u0018\u0006NX&\r\n\u0002Au\u0006\u0001E\u0014g\u0001OWZg\u001d\u0002GP&<\u0003CBcB\u000cNUu\u001cOQQh\u001b\u0006LQjA"
		// @0C9: invokestatic game.C_100235_om.func_106284_z(java.lang.String)char[]
		// @0CC: invokestatic game.C_100235_om.func_106283_z(char[])java.lang.String
		// @0CF: aastore
		// @0D0: dup
		// @0D1: iconst_1
		// @0D2: ldc "?PQu\u001cO\u001e]k\u0008R\u0010\u00048O\u001bM\u0014e\u0000\u0001V]h\u001a\n\u000c"
		// @0D4: invokestatic game.C_100235_om.func_106284_z(java.lang.String)char[]
		// @0D7: invokestatic game.C_100235_om.func_106283_z(char[])java.lang.String
		// @0DA: aastore
		// @0DB: dup
		// @0DC: iconst_2
		// @0DD: ldc ";CD&\u001b\u0007G\u0014!.H\u0002_c\u0016OV[&\u001b\nNX&\u0016\u0000WF&\u001c\nL@o\u0001\nN\u0014r\u0000OQ@g\u001d\u001b\u0002Yi\u0019\u0006LS&\u0003\nD@("
		// @0DF: invokestatic game.C_100235_om.func_106284_z(java.lang.String)char[]
		// @0E2: invokestatic game.C_100235_om.func_106283_z(char[])java.lang.String
		// @0E5: aastore
		// @0E6: dup
		// @0E7: iconst_3
		// @0E8: ldc "?PQu\u001cO\u0005u!O\u0000LWcO\u001bM\u0014u\u001b\u000eP@&\u0002\u0000T]h\u0008ONQ`\u001bA"
		// @0EA: invokestatic game.C_100235_om.func_106284_z(java.lang.String)char[]
		// @0ED: invokestatic game.C_100235_om.func_106283_z(char[])java.lang.String
		// @0F0: aastore
		// @0F1: dup
		// @0F2: iconst_4
		// @0F3: ldc "<KZe\nO[[sO\u000ePQ&\u001d\nO[r\n\u0003[\u0014v\u0006\u0003M@o\u0001\u0008\u0002Mi\u001a\u001d\u0002Gc\u0001\u001bKZc\u0003C\u0002@n\n\u001dG\u0014o\u001cOC\u0014u\u0007\u0000P@&\u000b\nNU\u007fO\rG@q\n\nL\u0014q\u0007\nL\u0014\u007f\u0000\u001a\u0002]u\u001c\u001aG\u0014g\u0001OMFb\n\u001d\u0002Uh\u000bOU\\c\u0001OV\\cO\u001cGZr\u0006\u0001GX&\u001d\nAQo\u0019\nQ\u0014g\u0001\u000b\u0002Ue\u001b\u001c\u0002Av\u0000\u0001\u0002]rAO\u001eVtQ;CD&\u001b\u0007G\u0014!+H\u0002_c\u0016OV[&\u0006\u0001Q@t\u001a\u000cV\u0014\u007f\u0000\u001aP\u0014u\n\u0001V]h\n\u0003\u0002@iO\u001cVUt\u001bOO[p\u0006\u0001E\u0014t\u0006\u0008J@("
		// @0F5: invokestatic game.C_100235_om.func_106284_z(java.lang.String)char[]
		// @0F8: invokestatic game.C_100235_om.func_106283_z(char[])java.lang.String
		// @0FB: aastore
		// @0FC: dup
		// @0FD: iconst_5
		// @0FE: ldc "?PQu\u001cO\u0005p!O\u0000LWcO\u001bM\u0014u\u001b\u000eP@&\u0002\u0000T]h\u0008OP]a\u0007\u001b\u000c"
		// @100: invokestatic game.C_100235_om.func_106284_z(java.lang.String)char[]
		// @103: invokestatic game.C_100235_om.func_106283_z(char[])java.lang.String
		// @106: aastore
		// @107: dup
		// @108: bipush 6 (0x06)
		// @10A: ldc "&L\u0014r\u0007\n\u0002Ud\u001c\nLWcO\u0000D\u0014i\u001b\u0007GF&\u0000\u001dFQt\u001cC\u0002Mi\u001a\u001d\u0002Gc\u0001\u001bKZc\u0003OU]j\u0003OAUt\u001d\u0016\u0002[hO\u0018CXm\u0006\u0001E\u001a&?\u001dGGuOHq\u0013&\u001b\u0000\u0002@c\u0003\u0003\u0002]rO\u001bM\u0014n\u000e\u0003V\u001a"
		// @10C: invokestatic game.C_100235_om.func_106284_z(java.lang.String)char[]
		// @10F: invokestatic game.C_100235_om.func_106283_z(char[])java.lang.String
		// @112: aastore
		// @113: dup
		// @114: bipush 7 (0x07)
		// @116: ldc "?PQu\u001cO\u0005g!O\u001bM\u0014u\u001b\u0000R\u0014k\u0000\u0019KZaA"
		// @118: invokestatic game.C_100235_om.func_106284_z(java.lang.String)char[]
		// @11B: invokestatic game.C_100235_om.func_106283_z(char[])java.lang.String
		// @11E: aastore
		// @11F: dup
		// @120: bipush 8 (0x08)
		// @122: ldc ".V\u0014r\u0007\n\u0002Vi\u001b\u001bMY&\u0000\t\u0002Mi\u001a\u001d\u0002Ge\u001d\nGZ&\u0006\u001c\u0002@n\nOO]h\u0006\u0002CD(O;J]uO\u001cJ[q\u001cOV\\cO\u0003MWg\u001b\u0006MZuO\u0000D\u0014u\n\u0001V]h\n\u0003Q\u0014i\u0001OV\\cO\rC@r\u0003\nD]c\u0003\u000b\u000c\u0014R\u0007\n\u0002Vj\u001a\n\u0002Wo\u001d\u000cNQ&\u0006\u001c\u0002Mi\u001a\u001d\u0002Gc\u0001\u001bKZc\u0003C\u0002Uh\u000bOV\\cO\tNUu\u0007\u0006LS&\u001d\nF\u0014e\u0006\u001dAXcO\u0006Q\u0014gO\u001bPUo\u0001\u0006LS&\u000b\u001dMZcAOuUj\u0004O[[s\u001dOQQh\u001b\u0006LQjO\u001bM\u0014r\u0007\n\u0002@t\u000e\u0006L]h\u0008OFFi\u0001\n\u0002Uh\u000bOQ@i\u001fOCG&\u000c\u0003MGcO\u001bM\u0014o\u001bOCG&\u001f\u0000QGo\r\u0003G\u001a"
		// @124: invokestatic game.C_100235_om.func_106284_z(java.lang.String)char[]
		// @127: invokestatic game.C_100235_om.func_106283_z(char[])java.lang.String
		// @12A: aastore
		// @12B: dup
		// @12C: bipush 9 (0x09)
		// @12E: ldc ":QQ&H.\u0005\u0018&H<\u0005\u0018&H+\u0005\u0014r\u0000OR[u\u0006\u001bK[hO\u0016MAtO\u001cGZr\u0006\u0001GX&\u000e\u001b\u0002@n\nOVFg\u0006\u0001KZaO\u000bP[h\nA"
		// @130: invokestatic game.C_100235_om.func_106284_z(java.lang.String)char[]
		// @133: invokestatic game.C_100235_om.func_106283_z(char[])java.lang.String
		// @136: aastore
		// @137: dup
		// @138: bipush 10 (0x0A)
		// @13A: ldc "6MA&\u000c\u000eL\u0014k\u0000\u0019G\u0014r\u0007\n\u0002Wg\u0002\nPU&\r\u0016\u0002\\i\u0003\u000bKZaO\u000bMChO\u001bJQ&\u001d\u0006E\\rO\u0002MAu\nO@Ar\u001b\u0000L\u0014g\u0001\u000b\u0002Yi\u0019\u0006LS&\u001b\u0007G\u0014k\u0000\u001aQQ(O;JQ&\r\u001aV@i\u0001\u001c\u0002[hO\u001bJQ&\u001d\u0006E\\rO\u0000DRc\u001dOQ[k\nOMDr\u0006\u0000LG&\t\u0000P\u0014e\u0007\u000eLSo\u0001\u0008\u0002@n\nOA[h\u001b\u001dMXuAS@F8;\u001d[\u0014r\u0007\nO\u0014i\u001a\u001b\u0002Uh\u000bOA\\i\u0000\u001cG\u0014r\u0007\n\u0002[h\nO[[sO\u001fPQ`\n\u001d\u000c"
		// @13C: invokestatic game.C_100235_om.func_106284_z(java.lang.String)char[]
		// @13F: invokestatic game.C_100235_om.func_106283_z(char[])java.lang.String
		// @142: aastore
		// @143: dup
		// @144: bipush 11 (0x0B)
		// @146: ldc "?PQu\u001cO\u001e]k\u0008R\u0010\u00048O\u001bM\u0014e\u0000\u0001V]h\u001a\n\u000c"
		// @148: invokestatic game.C_100235_om.func_106284_z(java.lang.String)char[]
		// @14B: invokestatic game.C_100235_om.func_106283_z(char[])java.lang.String
		// @14E: aastore
		// @14F: dup
		// @150: bipush 12 (0x0C)
		// @152: ldc ";JQ&<\u0003CBcO\u000eNGiO\u0007CG&\u001b\u0007G\u0014g\r\u0006N]r\u0016OV[&\u0005\u001aOD(O;M\u0014o\u0001\u001cVFs\u000c\u001b\u0002Mi\u001a\u001d\u0002Gc\u0001\u001bKZc\u0003OV[&\u0005\u001aOD*O\u001fPQu\u001cO\u0005c!A"
		// @154: invokestatic game.C_100235_om.func_106284_z(java.lang.String)char[]
		// @157: invokestatic game.C_100235_om.func_106283_z(char[])java.lang.String
		// @15A: aastore
		// @15B: dup
		// @15C: bipush 13 (0x0D)
		// @15E: ldc ":QQ&H8\u0005\u0014r\u0000OHAk\u001fA"
		// @160: invokestatic game.C_100235_om.func_106284_z(java.lang.String)char[]
		// @163: invokestatic game.C_100235_om.func_106283_z(char[])java.lang.String
		// @166: aastore
		// @167: dup
		// @168: bipush 14 (0x0E)
		// @16A: ldc "8J]j\nO[[sO\u0007MXbOHu\u0013*O\u001bJQ&\u001f\u001dM^c\u000c\u001bGP&\u001f\u000eV\\&\u0000\t\u0002Mi\u001a\u001d\u0002^s\u0002\u001f\u0002]uO\u000bKGv\u0003\u000e[QbO\u0000L\u0014\u007f\u0000\u001aP\u0014u\u000c\u001dGQhAOv\\o\u001cOCXj\u0000\u0018Q\u0014\u007f\u0000\u001a\u0002@iO\u000eKY&\u0016\u0000WF&\u0005\u001aOD&\u001f\u001dGWo\u001c\nNM&\r\u0016\u0002Yi\u0019\u0006LS&\u001b\u0007G\u0014k\u0000\u001aQQ(S\rP\nR\u0007\nPQ&\u000e\u001dG\u0014h\u0000\u0018\u0002@n\u001d\nG\u0014b\u001d\u0000LQuO\u0006L\u0014c\u0003\nTUr\n\u000b\u0002Di\u001c\u0006V]i\u0001\u001c\u0002[hO\u001bJQ&\r\u000eV@j\n\tKQj\u000bA\u0002fc\u000e\u000cJ\u0014r\u0007\nO\u0014g\u0003\u0003\u0002V\u007fO\u0005WYv\u0006\u0001E\u001a"
		// @16C: invokestatic game.C_100235_om.func_106284_z(java.lang.String)char[]
		// @16F: invokestatic game.C_100235_om.func_106283_z(char[])java.lang.String
		// @172: aastore
		// @173: dup
		// @174: bipush 15 (0x0F)
		// @176: ldc "'MXbOHu\u0013&\u000e\u0001F\u0014k\u0000\u0019G\u0014r\u0007\n\u0002Yi\u001a\u001cG\u0014r\u0000ORXg\u0001OV\\cO\u001bPUl\n\u000cV[t\u0016OMR&\u0016\u0000WF&\u0005\u001aOD(S\rP\nT\n\u000eA\\&\u000e\u0003N\u0014r\u0007\n\u0002Pt\u0000\u0001GG&\r\u0016\u0002^s\u0002\u001fKZaA"
		// @178: invokestatic game.C_100235_om.func_106284_z(java.lang.String)char[]
		// @17B: invokestatic game.C_100235_om.func_106283_z(char[])java.lang.String
		// @17E: aastore
		// @17F: dup
		// @180: bipush 16 (0x10)
		// @182: ldc "6MAtO<NUp\nOU]j\u0003OL[qO\rG\u0014c\u001e\u001aKDv\n\u000b\u0002Co\u001b\u0007\u0002]r\u001cOQ@g\u0001\u000bCFbO\u000cMYv\u0003\nOQh\u001bOMR&\u000c\u0003MGcB\u000eQGg\u001a\u0003V\u0014a\u001a\u0001Q\u001a&;\u0007GGcO\u000ePQ&\u001c\u0007MFrB\u001dCZa\nC\u0002Po\u001d\nA@+\t\u0006PQ&\u0018\nCDi\u0001\u001c\u000c\u0008d\u001dQo[p\nOV\\cO\u0002MAu\nOV[&\u000e\u0006O\u0014\u007f\u0000\u001aP\u0014q\n\u000eR[h\u001cA\u0002`n\nOU\\o\u001b\n\u0002\u0013r\u001d\u000eHQe\u001b\u0000PM&\u0003\u0006LQ!O\nO]r\u001b\nF\u0014`\u001d\u0000O\u0014\u007f\u0000\u001aP\u0014u\n\u0001V]h\n\u0003\u0002]h\u000b\u0006AUr\n\u001c\u0002@n\nORFi\u0005\nA@c\u000bORUr\u0007OMR&\u0016\u0000WF&\u0018\nCDi\u0001BD]t\nA"
		// @184: invokestatic game.C_100235_om.func_106284_z(java.lang.String)char[]
		// @187: invokestatic game.C_100235_om.func_106283_z(char[])java.lang.String
		// @18A: aastore
		// @18B: dup
		// @18C: bipush 17 (0x11)
		// @18E: ldc "?PQu\u001cO\u001e]k\u0008R\u0010\u00048O\u001bM\u0014e\u0000\u0001V]h\u001a\n\u000c"
		// @190: invokestatic game.C_100235_om.func_106284_z(java.lang.String)char[]
		// @193: invokestatic game.C_100235_om.func_106283_z(char[])java.lang.String
		// @196: aastore
		// @197: dup
		// @198: bipush 18 (0x12)
		// @19A: ldc "*TQt\u0016OUQg\u001f\u0000L\u0014n\u000e\u001c\u0002U&\u0003\u0006O]r\n\u000b\u0002Ro\u001d\u0006LS&\u000e\u001dA\u0018&\u0018\u0007KWnO\u0016MA&\u000c\u000eL\u0014u\n\n\u0002UuO\u000e\u0002@n\u0006\u000cI\u0014d\u0003\u001aG\u0014g\u001d\u000c\u0002Po\u001c\u001fNU\u007f\n\u000b\u0002Zc\u0017\u001b\u0002@iO\u0016MAtO\u001cGZr\u0006\u0001GX(O6MAtO\u0018GUv\u0000\u0001\u0002Co\u0003\u0003\u0002[h\u0003\u0016\u0002Ro\u001d\n\u0002]hO\u000bKFc\u000c\u001bK[h\u001cOKZu\u0006\u000bG\u0014r\u0007\u0006Q\u0014g\u001d\u000c\u000c\u0008d\u001dQwGcO\u001bJQ&\u0003\nD@&\u0002\u0000WGcO\rW@r\u0000\u0001\u0002@iO\tKFcO\u0016MAtO\u0018GUv\u0000\u0001Q\u001a&'\u0000NPo\u0001\u0008\u0002@n\nO@Ar\u001b\u0000L\u0014b\u0000\u0018L\u0014q\u0006\u0003N\u0014`\u0006\u001dG\u0014g\u001bOV\\cO\u0018GUv\u0000\u0001\u0005G&\u0000\u001fV]k\u000e\u0003\u0002Ro\u001d\u0006LS&\u001d\u000eVQ(O:QQ&\u001b\u0007G\u0014e\u0003\u0000QQ+\u000e\u001cQUs\u0003\u001b\u0002Ss\u0001\u001c\u0002@iO\u000bGGr\u001d\u0000[\u0014r\u0007\n\u0002@t\u000e\u0006L]h\u0008OFFi\u0001\n\u000c"
		// @19C: invokestatic game.C_100235_om.func_106284_z(java.lang.String)char[]
		// @19F: invokestatic game.C_100235_om.func_106283_z(char[])java.lang.String
		// @1A2: aastore
		// @1A3: dup
		// @1A4: bipush 19 (0x13)
		// @1A6: ldc ")KFcO\u0018K@nO\u001bJQ&\u0003\nD@&\u0002\u0000WGcO\rW@r\u0000\u0001\u000c\u0008d\u001dQfQu\u001b\u001dMM&\u001b\u0007G\u0014r\u001d\u000eKZo\u0001\u0008\u0002Pt\u0000\u0001G\u0014q\u0006\u001bJ\u0014\u007f\u0000\u001aP\u0014a\u001a\u0001Q\u001a"
		// @1A8: invokestatic game.C_100235_om.func_106284_z(java.lang.String)char[]
		// @1AB: invokestatic game.C_100235_om.func_106283_z(char[])java.lang.String
		// @1AE: aastore
		// @1AF: dup
		// @1B0: bipush 20 (0x14)
		// @1B2: ldc "<MYcO\u0002MVo\u0003\n\u0002Pt\u0000\u0001GG&\u0007\u000eTQ&\r\nGZ&\u001f\u0003CWc\u000bOMZ&\u001b\u0007G\u0014r\u001d\u000eKZo\u0001\u0008\u0002Ro\n\u0003F\u001a&+\nQ@t\u0000\u0016\u0002@n\n\u0002\u0002Uj\u0003A\u0002\u007fc\n\u001f\u0002]hO\u0002KZbO\u001bJUrO\u0016MAtO\u0008WZuO\u0007CBcO\u000e\u0002Xo\u0002\u0006VQbO\u001dCZa\nOCZbO\u000e\u0002Fc\u001c\u001bP]e\u001b\nF\u0014`\u0006\u001dKZaO\u000ePW(S\rP\nT\n\u0002GYd\n\u001d\u000e\u0014\u007f\u0000\u001a\u0002Wg\u0001OO[p\nO[[s\u001dOQQh\u001b\u0006LQjO\u001bM\u0014gO\rG@r\n\u001d\u0002Di\u001c\u0006V]i\u0001OWGo\u0001\u0008\u0002@n\nOO[p\nOIQ\u007f\u001cO\n\u0013GHC\u0002\u0013UHC\u0002\u0013BHF\u0002[tO\r[\u0014l\u001a\u0002R]h\u0008O\n\u0013QHF\u000c"
		// @1B4: invokestatic game.C_100235_om.func_106284_z(java.lang.String)char[]
		// @1B7: invokestatic game.C_100235_om.func_106283_z(char[])java.lang.String
		// @1BA: aastore
		// @1BB: dup
		// @1BC: bipush 21 (0x15)
		// @1BE: ldc "'MXbO\u000bMChO\u001bJQ&\u0003\nD@&\u0002\u0000WGcO\rW@r\u0000\u0001\u0002@iO\u0004GQvO\tKFo\u0001\u0008\u000c\u0008d\u001dQfQu\u001b\u001dMM&\u000e\u0003N\u0014r\u0007\n\u0002@t\u000e\u0006L]h\u0008OFFi\u0001\nQ\u001a"
		// @1C0: invokestatic game.C_100235_om.func_106284_z(java.lang.String)char[]
		// @1C3: invokestatic game.C_100235_om.func_106283_z(char[])java.lang.String
		// @1C6: aastore
		// @1C7: dup
		// @1C8: bipush 22 (0x16)
		// @1CA: ldc "8GXjO\u000bMZcCO[[sO\u0007CBcO\u000cMYv\u0003\nVQbO\u001bJQ&\t\u0006PGrO\u001bPUo\u0001\u0006LS&\u0002\u0006QGo\u0000\u0001\u000c"
		// @1CC: invokestatic game.C_100235_om.func_106284_z(java.lang.String)char[]
		// @1CF: invokestatic game.C_100235_om.func_106283_z(char[])java.lang.String
		// @1D2: aastore
		// @1D3: dup
		// @1D4: bipush 23 (0x17)
		// @1D6: ldc ""
		// @1D8: aastore
		// @1D9: aastore
		// @1DA: dup
		// @1DB: iconst_1
		// @1DC: bipush 30 (0x1E)
		// @1DE: anewarray java.lang.String
		// @1E1: dup
		// @1E2: iconst_0
		// @1E3: ldc "8GXe\u0000\u0002G\u0014r\u0000O[[s\u001dOQQe\u0000\u0001F\u0014r\u001d\u000eKZo\u0001\u0008\u0002Yo\u001c\u001cK[hAOkZ&\u001b\u0007KG&\u001f\u001dMSt\u000e\u0002\u0002Mi\u001aOU]j\u0003ONQg\u001d\u0001\u0002Ud\u0000\u001aV\u0014e\u0000\u0002@UrO\u001aQ]h\u0008OP[e\u0004\nVG(O&L]r\u0006\u000eNX\u007fCOC\u0014d\u000e\u001dP]c\u001dOU]j\u0003OA[h\t\u0006LQ&\u0016\u0000WF&\u001c\nL@o\u0001\nN\u0014r\u0000OC\u0014j\n\u000bEQ&\u0000\u0001\u0002@n\nOGPa\nOMR&\u001b\u0007G\u0014d\u000e\u001bVXc\t\u0006GXbO\u001cM\u0014\u007f\u0000\u001a\u0002Wg\u0001ORFg\u000c\u001bKGcO\u001cJ[i\u001b\u0006LS&\t\u001dMY&\u000eOF]u\u001b\u000eLWcA"
		// @1E5: invokestatic game.C_100235_om.func_106284_z(java.lang.String)char[]
		// @1E8: invokestatic game.C_100235_om.func_106283_z(char[])java.lang.String
		// @1EB: aastore
		// @1EC: dup
		// @1ED: iconst_1
		// @1EE: ldc "?PQu\u001cO\u001e]k\u0008R\u0010\u00048O\u001bM\u0014e\u0000\u0001V]h\u001a\n\u000c"
		// @1F0: invokestatic game.C_100235_om.func_106284_z(java.lang.String)char[]
		// @1F3: invokestatic game.C_100235_om.func_106283_z(char[])java.lang.String
		// @1F6: aastore
		// @1F7: dup
		// @1F8: iconst_2
		// @1F9: ldc ";JQ&<\u0003CBcB\u000cNUu\u001cOQQh\u001b\u0006LQjO\u0006Q\u0014c\u001e\u001aKDv\n\u000b\u0002Co\u001b\u0007\u0002U&\r\u000eVWnO\u0000D\u0014v\u0006\nPWc\u001dOP[e\u0004\nVG*O\u001bJ[s\u0008\u0007\u0002Zi\u001bOL[t\u0002\u000eNX\u007fO\u000eQ\u0014k\u000e\u0001[\u0014g\u001cOV\\o\u001cA\u0002`n\n\u001cG\u0014g\u001d\n\u0002Wn\n\u000eR\u0018&\u0003\u0006E\\rO\u001dMWm\n\u001bQ\u0014r\u0007\u000eV\u0014g\u001d\n\u0002Zi\u0001\nV\\c\u0003\nQG&\u000b\nCPj\u0016OKZ&\u001c\u000eNBi\n\u001c\u000c\u0008d\u001dQrFc\u001c\u001cKZaOHs\u0013&\u0000\u001d\u0002\u0013CHOA\\g\u0001\u0008GG&\u0016\u0000WF&\u000c\u001aPFc\u0001\u001bNM&\u001c\nNQe\u001b\nF\u0014q\n\u000eR[hA"
		// @1FB: invokestatic game.C_100235_om.func_106284_z(java.lang.String)char[]
		// @1FE: invokestatic game.C_100235_om.func_106283_z(char[])java.lang.String
		// @201: aastore
		// @202: dup
		// @203: iconst_3
		// @204: ldc "?PQu\u001cO\u0005q!O\u001bM\u0014u\n\u0003GWrO\u0016MAtO\u001fKQt\u000c\nP\u0014t\u0000\u000cIQr\u001cA"
		// @206: invokestatic game.C_100235_om.func_106284_z(java.lang.String)char[]
		// @209: invokestatic game.C_100235_om.func_106283_z(char[])java.lang.String
		// @20C: aastore
		// @20D: dup
		// @20E: iconst_4
		// @20F: ldc "=MWm\n\u001bQ\u0014b\n\u001bMZg\u001b\n\u0002Cn\n\u0001\u0002@n\n\u0016\u0002Gr\u001d\u0006IQ&\u0008\u001dMAh\u000bOMF&\u000e\u0001M@n\n\u001d\u0002Gi\u0003\u0006F\u0014i\r\u0005GWrAOcZ\u007f\u001b\u0007KZaO\u000cCAa\u0007\u001b\u0002]hO\u001bJQ&\n\u0017RXi\u001c\u0006MZ&\u001d\nAQo\u0019\nQ\u0014b\u000e\u0002CScAS@F8:\u001cG\u0014r\u0007\n\u0002Cn\u0006\u001bG\u0014r\u001d\u000eHQe\u001b\u0000PM&\u0003\u0006LQ&\u001b\u0000\u0002Bo\u001c\u001aCXo\u001c\n\u0002@n\nOP[e\u0004\nV\u0013uO\u001bPUl\n\u000cV[t\u0016A"
		// @211: invokestatic game.C_100235_om.func_106284_z(java.lang.String)char[]
		// @214: invokestatic game.C_100235_om.func_106283_z(char[])java.lang.String
		// @217: aastore
		// @218: dup
		// @219: iconst_5
		// @21A: ldc ")KFcO\u001dMWm\n\u001bQ\u0014g\u001bOV\\cO\u000bP[h\nA"
		// @21C: invokestatic game.C_100235_om.func_106284_z(java.lang.String)char[]
		// @21F: invokestatic game.C_100235_om.func_106283_z(char[])java.lang.String
		// @222: aastore
		// @223: dup
		// @224: bipush 6 (0x06)
		// @226: ldc ".LM&\u001d\u0000A_c\u001bBGEs\u0006\u001fRQbO\u001cGZr\u0006\u0001GX&\u0007\u000eQ\u0014gO\u0003KYo\u001b\nF\u0014h\u001a\u0002@QtO\u001bM\u0014`\u0006\u001dG\u0014d\n\tMFcO\u0006V\u0014t\u001a\u0001Q\u0014i\u001a\u001b\u000c\u0014I\u0019\nP\u0014r\u0006\u0002G\u0018&\u0001\nU\u0014t\u0000\u000cIQr\u001cOU]j\u0003O@Q&\u0003\u0000CPc\u000bOCZbO\u001bJQhO\u001bJQ&\u001c\nL@o\u0001\nN\u0014e\u000e\u0001\u0002Ro\u001d\n\u0002Ua\u000e\u0006L\u001a:\r\u001d\u001cri\u001dOGLv\n\u000bKQh\u000c\u0016\u000e\u0014o\u0001OV\\o\u001cOVAr\u0000\u001dKUjO\u0016MA&\u0018\u0006NX&\u0007\u000eTQ&\u000e\u000cAQu\u001cOV[&\u000eOQDc\n\u000b\u000fXi\u000e\u000bGF(O;J]uO\u0002MPs\u0003\n\u0002Fc\u000b\u001aAQuO\u001dGXi\u000e\u000b\u0002@o\u0002\nQ\u0014`\u0000\u001d\u0002Fi\u000c\u0004G@uO\u000eLP&\u0002\u0006QGo\u0003\nQ\u001a"
		// @228: invokestatic game.C_100235_om.func_106284_z(java.lang.String)char[]
		// @22B: invokestatic game.C_100235_om.func_106283_z(char[])java.lang.String
		// @22E: aastore
		// @22F: dup
		// @230: bipush 7 (0x07)
		// @232: ldc "?KWmO\u001aR\u0014r\u0007\n\u0002Gv\n\nF\u0019j\u0000\u000eFQtO\u001fMCc\u001dBWD&\r\u0016\u0002Cg\u0003\u0004KZaO\u0000TQtO\u0006V\u001a"
		// @234: invokestatic game.C_100235_om.func_106284_z(java.lang.String)char[]
		// @237: invokestatic game.C_100235_om.func_106283_z(char[])java.lang.String
		// @23A: aastore
		// @23B: dup
		// @23C: bipush 8 (0x08)
		// @23E: ldc "\"MFcO\u000bP[h\n\u001c\u0002\\g\u0019\n\u0002Vc\n\u0001\u0002Dj\u000e\u000cGP&\u0000\u0001\u0002@n\nO@Ur\u001b\u0003GRo\n\u0003F\u0018&\u000e\u001b\u0002]h\u000c\u001dGUu\u0006\u0001E\u0014b\u0006\u001cVUh\u000c\nQ\u0014`\u001d\u0000O\u0014\u007f\u0000\u001aP\u0014u\n\u0001V]h\n\u0003\u000c\u0014S\u001c\n\u0002Mi\u001a\u001d\u0002Fi\u000c\u0004G@uO\u001bM\u0014b\n\u001cVFi\u0016OV\\c\u0002A\u0002vc\u0018\u000ePQ&\u001b\u0007C@&\u001d\u0000A_c\u001bOGLv\u0003\u0000Q]i\u0001\u001c\u0002Wg\u0001OFUk\u000e\u0008G\u0014\u007f\u0000\u001aP\u0014u\n\u0001V]h\n\u0003\u0002@i\u0000A\u001eVtQ&D\u0014\u007f\u0000\u001a\u0002Fs\u0001OMArO\u0000D\u0014t\u0000\u000cIQr\u001cC\u0002Mi\u001a\u001d\u0002Ws\u001d\u001cMF&\u0018\u0006NX&\u001b\u001aPZ&\u001d\nF\u0018&\u0006\u0001F]e\u000e\u001bKZaO\u001bJUrO\u0016MA&\u000c\u000eLZi\u001bOD]t\nOWZr\u0006\u0003\u0002Mi\u001a\u001d\u0002Fi\u000c\u0004G@uO\u0007CBcO\rGQhO\u001dGXi\u000e\u000bGP("
		// @240: invokestatic game.C_100235_om.func_106284_z(java.lang.String)char[]
		// @243: invokestatic game.C_100235_om.func_106283_z(char[])java.lang.String
		// @246: aastore
		// @247: dup
		// @248: bipush 9 (0x09)
		// @24A: ldc "+GGr\u001d\u0000[\u0014r\u0007\n\u0002Pt\u0000\u0001GG&\u0018\u0006V\\&\u001d\u0000A_c\u001b\u001c\u000c"
		// @24C: invokestatic game.C_100235_om.func_106284_z(java.lang.String)char[]
		// @24F: invokestatic game.C_100235_om.func_106283_z(char[])java.lang.String
		// @252: aastore
		// @253: dup
		// @254: bipush 10 (0x0A)
		// @256: ldc ";JQt\nOKG&\u0000\u0001G\u0014k\u0000\u001dG\u0014b\u001d\u0000LQ*O\u0000L\u0014r\u0007\n\u0002Xc\t\u001b\u0002\\g\u0001\u000b\u0002Go\u000b\n\u0002[`O\u001bJQ&\r\u000eV@j\n\tKQj\u000bA\u0002ge\u001d\u0000NX&\u0003\nD@&G\r[\u0014n\u0000\u0003F]h\u0008OV\\cO\u001dKSn\u001bOO[s\u001c\n\u0002Vs\u001b\u001bMZ&\u000e\u0001F\u0014b\u001d\u000eESo\u0001\u0008\u0002@n\nOO[s\u001c\n\u000b\u0014r\u0000OD]h\u000bOK@("
		// @258: invokestatic game.C_100235_om.func_106284_z(java.lang.String)char[]
		// @25B: invokestatic game.C_100235_om.func_106283_z(char[])java.lang.String
		// @25E: aastore
		// @25F: dup
		// @260: bipush 11 (0x0B)
		// @262: ldc "'MXbO\u001bJQ&\u001d\u0006E\\rO\u0002MAu\nO@Ar\u001b\u0000L\u0014g\u0001\u000b\u0002Pt\u000e\u0008\u0002@iO\u0002MBcO\u001bJQ&\u000c\u000eOQt\u000eONQ`\u001bA"
		// @264: invokestatic game.C_100235_om.func_106284_z(java.lang.String)char[]
		// @267: invokestatic game.C_100235_om.func_106283_z(char[])java.lang.String
		// @26A: aastore
		// @26B: dup
		// @26C: bipush 12 (0x0C)
		// @26E: ldc "8JQhO\u0016MAtO\u001cGZr\u0006\u0001GX&\u0006\u001c\u0002[`\tBQWt\n\nL\u0018&\u001b\u0007G\u0014o\u0001\u001cG@&\u000b\u0006QDj\u000e\u0016\u0002Uv\u001f\nCFuO\u000eV\u0014r\u0007\n\u0002Ge\u001d\nGZ&\n\u000bEQ&\u000c\u0003MGc\u001c\u001b\u0002@iO\u0016MAtO\u001cGZr\u0006\u0001GX*O\u001bM\u0014t\n\u0002KZbO\u0016MA&\u0018\u0007GFcO\u0016MAtO\u001cGZr\u0006\u0001GX&\u0006\u001c\u000c\u0014E\u0003\u0006A_&\u000e\u0001F\u0014b\u001d\u000eE\u0014r\u0007\n\u0002Fo\u0008\u0007V\u0014k\u0000\u001aQQ&\r\u001aV@i\u0001OV[&\u0002\u0000TQ&\u001b\u0007G\u0014e\u000e\u0002GFgO\u000eP[s\u0001\u000b\u000e\u0014g\u0001\u000b\u0002@n\nOJ]a\u0007\u0003KSn\u001b\nF\u0014d\u0000\u0017\u0002[hO\u0016MAtO\u0002KZo\u0002\u000eR\u0014u\u0007\u0000UG&\u0018\u0007C@&\u001f\u000eP@&\u0000\t\u0002@n\nO@Ur\u001b\u0003GRo\n\u0003F\u0014\u007f\u0000\u001a\u0002Ut\nOAAt\u001d\nL@j\u0016OT]c\u0018\u0006LS("
		// @270: invokestatic game.C_100235_om.func_106284_z(java.lang.String)char[]
		// @273: invokestatic game.C_100235_om.func_106283_z(char[])java.lang.String
		// @276: aastore
		// @277: dup
		// @278: bipush 13 (0x0D)
		// @27A: ldc "=KSn\u001bOAXo\u000c\u0004\u0002Uh\u000bOFFg\u0008OV\\cO\u0002MAu\nOV[&\u0002\u0000TQ&\u001b\u0007G\u0014e\u000e\u0002GFgO\u000eP[s\u0001\u000b\u000c"
		// @27C: invokestatic game.C_100235_om.func_106284_z(java.lang.String)char[]
		// @27F: invokestatic game.C_100235_om.func_106283_z(char[])java.lang.String
		// @282: aastore
		// @283: dup
		// @284: bipush 14 (0x0E)
		// @286: ldc "!MC*O\u001fMGo\u001b\u0006MZ&\u001b\u0007G\u0014e\u000e\u0002GFgO\u001cM\u0014r\u0007\u000eV\u0014\u007f\u0000\u001a\u0002Wg\u0001OQQcO\u001bJQ&\u001b\u001dC]h\u0006\u0001E\u0014b\u001d\u0000LQ&\u0000\u0001\u0002@n\nONQ`\u001bOMR&\u001b\u0007G\u0014k\u000e\u001f\u000e\u0014g\u0001\u000b\u0002Pc\u001c\u001bP[\u007fO\u0006V\u0014q\u0006\u001bJ\u0014\u007f\u0000\u001aP\u0014t\u0000\u000cIQr\u001cA"
		// @288: invokestatic game.C_100235_om.func_106284_z(java.lang.String)char[]
		// @28B: invokestatic game.C_100235_om.func_106283_z(char[])java.lang.String
		// @28E: aastore
		// @28F: dup
		// @290: bipush 15 (0x0F)
		// @292: ldc "+GGr\u001d\u0000[\u0014r\u0007\n\u0002Pt\u0000\u0001G\u0014q\u0006\u001bJ\u0014t\u0000\u000cIQr\u001cA"
		// @294: invokestatic game.C_100235_om.func_106284_z(java.lang.String)char[]
		// @297: invokestatic game.C_100235_om.func_106283_z(char[])java.lang.String
		// @29A: aastore
		// @29B: dup
		// @29C: bipush 16 (0x10)
		// @29E: ldc "8GXjO\u000bMZcAOv[&\r\u001dKZaO\u0016MAtO\u001cGZr\u0006\u0001GX&\r\u000eA_&\u0006\u0001V[&\u0019\u0006GC&\u0018\u0007GFc\u0019\nP\u0014o\u001bOKG*O\u001fPQu\u001cO\u0005b!A"
		// @2A0: invokestatic game.C_100235_om.func_106284_z(java.lang.String)char[]
		// @2A3: invokestatic game.C_100235_om.func_106283_z(char[])java.lang.String
		// @2A6: aastore
		// @2A7: dup
		// @2A8: bipush 17 (0x11)
		// @2AA: ldc "?PQu\u001cO\u0005b!O\u001bM\u0014k\u0000\u0019G\u0014r\u0007\n\u0002Wg\u0002\nPU&\r\u000eA_&\u001b\u0000\u0002Mi\u001a\u001d\u0002Gc\u0001\u001bKZc\u0003A"
		// @2AC: invokestatic game.C_100235_om.func_106284_z(java.lang.String)char[]
		// @2AF: invokestatic game.C_100235_om.func_106283_z(char[])java.lang.String
		// @2B2: aastore
		// @2B3: dup
		// @2B4: bipush 18 (0x12)
		// @2B6: ldc ";JQ&\u0001\nZ@&\u000b\u001dMZc\u001cOCFcO\u0002MBo\u0001\u0008\u0002@g\u001d\u0008G@uAOvF\u007fO\u001bM\u0014g\u0001\u001bKWo\u001f\u000eVQ&\u001b\u0007G]tO\u001fMGo\u001b\u0006MZuO\u001cM\u0014r\u0007\u000eV\u0014\u007f\u0000\u001aP\u0014t\u0000\u000cIQr\u001cOKZr\n\u001dAQv\u001bOV\\c\u0002A"
		// @2B8: invokestatic game.C_100235_om.func_106284_z(java.lang.String)char[]
		// @2BB: invokestatic game.C_100235_om.func_106283_z(char[])java.lang.String
		// @2BE: aastore
		// @2BF: dup
		// @2C0: bipush 19 (0x13)
		// @2C2: ldc "+GGr\u001d\u0000[\u0014r\u0007\n\u0002Yi\u0019\u0006LS&\u000b\u001dMZc\u001cOU]r\u0007OP[e\u0004\nVG("
		// @2C4: invokestatic game.C_100235_om.func_106284_z(java.lang.String)char[]
		// @2C7: invokestatic game.C_100235_om.func_106283_z(char[])java.lang.String
		// @2CA: aastore
		// @2CB: dup
		// @2CC: bipush 20 (0x14)
		// @2CE: ldc "!GLrO\u0016MA&\u0018\u0006NX&\u0003\nCFhO\u000e@[s\u001bOP[e\u0004\nV\u0014b\n\tGZe\nOWGo\u0001\u0008\u0002uK.=fg(O)MF&\u001b\u0007KG&\u0016\u0000W\u0014q\u0006\u0003N\u0014d\nO@Ue\u0004OKZ&\u001b\u0007G\u0014u\u001b\u000eLPg\u001d\u000b\u0002Yi\u000b\nN\u0014U\u0003\u000eTQ("
		// @2D0: invokestatic game.C_100235_om.func_106284_z(java.lang.String)char[]
		// @2D3: invokestatic game.C_100235_om.func_106283_z(char[])java.lang.String
		// @2D6: aastore
		// @2D7: dup
		// @2D8: bipush 21 (0x15)
		// @2DA: ldc "?PQu\u001cO\u001e]k\u0008R\u0010\u00048O\u001bM\u0014e\u0000\u0001V]h\u001a\n\u000c"
		// @2DC: invokestatic game.C_100235_om.func_106284_z(java.lang.String)char[]
		// @2DF: invokestatic game.C_100235_om.func_106283_z(char[])java.lang.String
		// @2E2: aastore
		// @2E3: dup
		// @2E4: bipush 22 (0x16)
		// @2E6: ldc ";JQ&<\u0003CBcB\u000cNUu\u001cOQQh\u001b\u0006LQjO\u000cMYc\u001cOU]r\u0007OcAr\u0000\u0002C@o\u000cOo]u\u001c\u0006NQ&.\u0001F\u0014T\u0000\u000cIQrO+GRc\u0001\u000cG\u0014U\u0016\u001cVQk\u001cO\nuK.=fg/AOv\\o\u001cOD]t\n\u001c\u0002@n\nOqXg\u0019\n\u0005G&\u0008\u001aLG&\u000e\u001b\u0002]h\u000c\u0000O]h\u0008OP[e\u0004\nVG&\u000e\u0001F\u0014k\u0006\u001cQ]j\n\u001c\u0002@iO\u000bG@i\u0001\u000eVQ&\u001b\u0007GY&\r\nD[t\nOV\\c\u0016OEQrO\u001bM[&\u000c\u0003MGcAOcDv\u001d\u0000CWnO\u001bJQ&\u0001\nCFd\u0016OP[e\u0004\nV\u0014b\u001d\u0000LQ&\u001b\u0000\u0002Ue\u001b\u0006TUr\nOcyG=+q\u001a"
		// @2E8: invokestatic game.C_100235_om.func_106284_z(java.lang.String)char[]
		// @2EB: invokestatic game.C_100235_om.func_106283_z(char[])java.lang.String
		// @2EE: aastore
		// @2EF: dup
		// @2F0: bipush 23 (0x17)
		// @2F2: ldc ".RDt\u0000\u000eA\\&\u001b\u0007G\u0014t\u0000\u000cIQrO\u000bP[h\nA"
		// @2F4: invokestatic game.C_100235_om.func_106284_z(java.lang.String)char[]
		// @2F7: invokestatic game.C_100235_om.func_106283_z(char[])java.lang.String
		// @2FA: aastore
		// @2FB: dup
		// @2FC: bipush 24 (0x18)
		// @2FE: ldc ".ouT+<\u0002[h\u0003\u0016\u0002Ci\u001d\u0004Q\u0014q\u0007\nL\u0014\u007f\u0000\u001aP\u0014u\n\u0001V]h\n\u0003\u0002]uO\tCWo\u0001\u0008\u0002@n\nOF]t\n\u000cV]i\u0001OMR&\u000e\u0001\u0002Ur\u001b\u000eA_(OS@F8&\u001b\u0002Wg\u0001OFQu\u001b\u001dMM&\u000eOJ[u\u001b\u0006NQ&\u001c\nL@o\u0001\nN\u0014d\u0016OFQr\u0000\u0001C@o\u0001\u0008\u0002]r\u001cOP[e\u0004\nVG&\u000e\u001b\u0002Xg\u001a\u0001A\\(S\rP\nG\u001f\u001fP[g\u000c\u0007\u0002@n\nOP[e\u0004\nV\u0014b\u001d\u0000LQ&\u001c\u0000\u0002Mi\u001a\u001d\u0002uK.=fg&\u000c\u000eL\u0014b\n\u001cVFi\u0016OK@("
		// @300: invokestatic game.C_100235_om.func_106284_z(java.lang.String)char[]
		// @303: invokestatic game.C_100235_om.func_106283_z(char[])java.lang.String
		// @306: aastore
		// @307: dup
		// @308: bipush 25 (0x19)
		// @30A: ldc "+GGr\u001d\u0000[\u0014r\u0007\n\u0002Fi\u000c\u0004G@&\u000b\u001dMZcA"
		// @30C: invokestatic game.C_100235_om.func_106284_z(java.lang.String)char[]
		// @30F: invokestatic game.C_100235_om.func_106283_z(char[])java.lang.String
		// @312: aastore
		// @313: dup
		// @314: bipush 26 (0x1A)
		// @316: ldc "+GGr\u001d\u0000[\u0014r\u0007\n\u0002Pt\u0000\u0001GG&\u001b\u0000\u0002Wi\u0002\u001fNQr\nOV\\cO\u0002KGu\u0006\u0000L\u001a&;\u0007GM&\u0018\u0006NX&\r\nA[k\nOCSa\u001d\nQGo\u0019\n\u0002Cn\n\u0001\u0002Mi\u001aOD]t\nOMZ&\u001b\u0007GY("
		// @318: invokestatic game.C_100235_om.func_106284_z(java.lang.String)char[]
		// @31B: invokestatic game.C_100235_om.func_106283_z(char[])java.lang.String
		// @31E: aastore
		// @31F: dup
		// @320: bipush 27 (0x1B)
		// @322: ldc "+GGr\u001d\u0000[\u0014g\u0003\u0003\u0002\\i\u001c\u001bKXcO\tMFe\n\u001c\u000c"
		// @324: invokestatic game.C_100235_om.func_106284_z(java.lang.String)char[]
		// @327: invokestatic game.C_100235_om.func_106283_z(char[])java.lang.String
		// @32A: aastore
		// @32B: dup
		// @32C: bipush 28 (0x1C)
		// @32E: ldc "8GXjO\u000bMZcCO[[sO\u0007CBcO\u000cMYv\u0003\nVQbO<NUp\nOP[e\u0004\nV\u0014r\u001d\u000eKZo\u0001\u0008\u000c"
		// @330: invokestatic game.C_100235_om.func_106284_z(java.lang.String)char[]
		// @333: invokestatic game.C_100235_om.func_106283_z(char[])java.lang.String
		// @336: aastore
		// @337: dup
		// @338: bipush 29 (0x1D)
		// @33A: ldc ""
		// @33C: aastore
		// @33D: aastore
		// @33E: dup
		// @33F: iconst_2
		// @340: iconst_0
		// @341: anewarray java.lang.String
		// @344: aastore
		// @345: dup
		// @346: iconst_3
		// @347: bipush 14 (0x0E)
		// @349: anewarray java.lang.String
		// @34C: dup
		// @34D: iconst_0
		// @34E: ldc ")MF&\u001b\u0007G\u0014`\u0000\u0003N[q\u0006\u0001E\u0014k\u0006\u001cQ]i\u0001\u001c\u000e\u0014\u007f\u0000\u001a\u0002Co\u0003\u0003\u0002VcO\u001aQ]h\u0008OCZ&.\u001eW]j\u000eBAXg\u001c\u001c\u0002Gc\u0001\u001bKZc\u0003A\u0002`n\nOcEs\u0006\u0003C\u0014o\u001cOC\u0014`\u000e\u001cV\u0018&\u0003\u0006E\\r\u0018\nKSn\u001bOQQh\u001b\u0006LQjCOAUv\u000e\rNQ&\u0000\t\u0002Uc\u001d\u0006CX&\u001b\u0007PAu\u001bA"
		// @350: invokestatic game.C_100235_om.func_106284_z(java.lang.String)char[]
		// @353: invokestatic game.C_100235_om.func_106283_z(char[])java.lang.String
		// @356: aastore
		// @357: dup
		// @358: iconst_1
		// @359: ldc "?PQu\u001cO\u001e]k\u0008R\u0010\u00048O\u001bM\u0014e\u0000\u0001V]h\u001a\n\u000c"
		// @35B: invokestatic game.C_100235_om.func_106284_z(java.lang.String)char[]
		// @35E: invokestatic game.C_100235_om.func_106283_z(char[])java.lang.String
		// @361: aastore
		// @362: dup
		// @363: iconst_2
		// @364: ldc ";M\u0014r\u0007\u001dWGrCOWGcOHu\u0013&\u000e\u0001F\u0014v\n\u001dD[t\u0002OC\u0014l\u001a\u0002R\u001a&;\u0007GZ*O\u0018J]j\nOKZ&\u001b\u0007G\u0014g\u0006\u001d\u000e\u0014s\u001c\n\u0002\u0013QHOCZbO\u0005WYvO\u000eEUo\u0001A"
		// @366: invokestatic game.C_100235_om.func_106284_z(java.lang.String)char[]
		// @369: invokestatic game.C_100235_om.func_106283_z(char[])java.lang.String
		// @36C: aastore
		// @36D: dup
		// @36E: iconst_3
		// @36F: ldc ":QQ&H8\u0005\u0014g\u0001\u000b\u0002@n\nOO[s\u001c\n\u0002]hO\u001bJQ&\u000e\u0006P\u0014r\u0000OV\\t\u001a\u001cV\u001a"
		// @371: invokestatic game.C_100235_om.func_106284_z(java.lang.String)char[]
		// @374: invokestatic game.C_100235_om.func_106283_z(char[])java.lang.String
		// @377: aastore
		// @378: dup
		// @379: iconst_4
		// @37A: ldc "!MC*O\r[\u0014r\u0007\u001dWGr\u0006\u0001E\u0014k\u001a\u0003V]v\u0003\n\u0002@o\u0002\nQ\u0018&\u001b\u001d[\u0014g\u0001\u000b\u0002Gr\u000e\u0016\u0002]hO\u001bJQ&\u000e\u0006P\u0014`\u0000\u001d\u0002UuO\u0003MZaO\u000eQ\u0014v\u0000\u001cQ]d\u0003\n\u000c"
		// @37C: invokestatic game.C_100235_om.func_106284_z(java.lang.String)char[]
		// @37F: invokestatic game.C_100235_om.func_106283_z(char[])java.lang.String
		// @382: aastore
		// @383: dup
		// @384: iconst_5
		// @385: ldc ":QQ&H8\u0005\u0014g\u0001\u000b\u0002@n\nOO[s\u001c\n\u0002]hO\u001bJQ&\u000e\u0006P\u0014r\u0000OV\\t\u001a\u001cV\u001a"
		// @387: invokestatic game.C_100235_om.func_106284_z(java.lang.String)char[]
		// @38A: invokestatic game.C_100235_om.func_106283_z(char[])java.lang.String
		// @38D: aastore
		// @38E: dup
		// @38F: bipush 6 (0x06)
		// @391: ldc "6MAtO\u001cGZr\u0006\u0001GX&\u0007\u000eQ\u0014t\u001a\u0001\u0002[s\u001bOMR&\n\u0001GFa\u0016A\u0002cn\n\u0001\u0002@n\u0006\u001c\u0002\\g\u001f\u001fGZuCOK@&\u000c\u000eLZi\u001bOO[p\nOWZr\u0006\u0003\u0002]rO\u001dGWi\u0019\nPG(OS@F8;\u0007PAu\u001b\u0006LS&\n\u0017RQh\u000b\u001c\u0002Qh\n\u001dEM*O\rW@&\n\u0001GFa\u0016OPQe\u0007\u000ePSc\u001cOSAo\u000c\u0004NM&\u0006\t\u0002Mi\u001a\u001d\u0002Gc\u0001\u001bKZc\u0003OKG&\u001c\u001bKXjAO\u001eVtQ-G\u0014g\u0018\u000ePQ&\u0000\t\u0002Mi\u001a\u001d\u0002Qh\n\u001dEM&\u0008\u000eWScO\u000eLP&\u001b\u001d[\u0014r\u0000OCBi\u0006\u000b\u0002\u0013c\u0001\nPS\u007fO\u0003MGuHOQ@g\u001b\n\u000c"
		// @393: invokestatic game.C_100235_om.func_106284_z(java.lang.String)char[]
		// @396: invokestatic game.C_100235_om.func_106283_z(char[])java.lang.String
		// @399: aastore
		// @39A: dup
		// @39B: bipush 7 (0x07)
		// @39D: ldc "?PQu\u001cO\u001e]k\u0008R\u0010\u00048O\u001bM\u0014e\u0000\u0001V]h\u001a\n\u000c"
		// @39F: invokestatic game.C_100235_om.func_106284_z(java.lang.String)char[]
		// @3A2: invokestatic game.C_100235_om.func_106283_z(char[])java.lang.String
		// @3A5: aastore
		// @3A6: dup
		// @3A7: bipush 8 (0x08)
		// @3A9: ldc "<MYcO\tN[g\u001b\u0006LS&\u000b\u001dMZc\u001cOJUp\nO@Qc\u0001OFFi\u001f\u001fGP&\u0006\u0001V[&\u001b\u0007G\u0014d\u000e\u001bVXc\t\u0006GXbAOwGcO\u0016MAtO.SAo\u0003\u000e\u0005G&\u001b\u0007PAu\u001bOV[&\t\u0003[\u0014r\u0000OV\\c\u0002A\u0002`t\u0016OL[rO\u001bM\u0014c\u0017\u0007CAu\u001bO[[s\u001dOGZc\u001d\u0008[\u001a"
		// @3AB: invokestatic game.C_100235_om.func_106284_z(java.lang.String)char[]
		// @3AE: invokestatic game.C_100235_om.func_106283_z(char[])java.lang.String
		// @3B1: aastore
		// @3B2: dup
		// @3B3: bipush 9 (0x09)
		// @3B5: ldc ")NM&\u001b\u0000\u0002@n\nODXi\u000e\u001bKZaO\rGUe\u0000\u0001Q\u001a"
		// @3B7: invokestatic game.C_100235_om.func_106284_z(java.lang.String)char[]
		// @3BA: invokestatic game.C_100235_om.func_106283_z(char[])java.lang.String
		// @3BD: aastore
		// @3BE: dup
		// @3BF: bipush 10 (0x0A)
		// @3C1: ldc "6MAtO.SAo\u0003\u000e\u0005G&\u001f\u001aNGcO\u0003CGc\u001dOJUuO\u0001MC&\r\nGZ&\u000e\u000cV]p\u000e\u001bGP(O#CGc\u001d\u001c\u0002Ro\u001d\n\u0002]hO\u000e\u0002Gr\u001d\u000eKSn\u001bON]h\nC\u0002Uh\u000bOKZ`\u0003\u0006A@&\n\u0001GFa\u0016OFUk\u000e\u0008G\u001a&'\u0000UQp\n\u001d\u000e\u0014c\u0019\nPM&\u001c\u0007M@&\u000b\u001dC]h\u001cOQ[k\nOMR&\u0016\u0000WF&\n\u0001GFa\u0016OPQu\n\u001dTQuCOQ[&\t\u0006P]h\u0008OKZ&\u001d\u000eR]bO\u001cWWe\n\u001cQ]i\u0001OAUhO\u0003GUbO\u001bM\u0014c\u0001\nPS\u007fO\u0003MGuAS@F8)\u0006PQ&\u001b\u0007G\u0014j\u000e\u001cGFuO\u000eV\u0014r\u0007\n\u0002Pt\u0000\u0001GG("
		// @3C3: invokestatic game.C_100235_om.func_106284_z(java.lang.String)char[]
		// @3C6: invokestatic game.C_100235_om.func_106283_z(char[])java.lang.String
		// @3C9: aastore
		// @3CA: dup
		// @3CB: bipush 11 (0x0B)
		// @3CD: ldc "+GGr\u001d\u0000[\u0014r\u0007\n\u0002Pt\u0000\u0001GG&\u0018\u0006V\\&\u0003\u000eQQt\u001cA"
		// @3CF: invokestatic game.C_100235_om.func_106284_z(java.lang.String)char[]
		// @3D2: invokestatic game.C_100235_om.func_106283_z(char[])java.lang.String
		// @3D5: aastore
		// @3D6: dup
		// @3D7: bipush 12 (0x0C)
		// @3D9: ldc "8GXjO\u000bMZcCO[[sO\u0007CBcO\u000cMYv\u0003\nVQbO.SAo\u0003\u000e\u0002Qh\n\u001dEM&\u001b\u001dC]h\u0006\u0001E\u001a"
		// @3DB: invokestatic game.C_100235_om.func_106284_z(java.lang.String)char[]
		// @3DE: invokestatic game.C_100235_om.func_106283_z(char[])java.lang.String
		// @3E1: aastore
		// @3E2: dup
		// @3E3: bipush 13 (0x0D)
		// @3E5: ldc ""
		// @3E7: aastore
		// @3E8: aastore
		// @3E9: dup
		// @3EA: iconst_4
		// @3EB: iconst_0
		// @3EC: anewarray java.lang.String
		// @3EF: aastore
		// @3F0: dup
		// @3F1: iconst_5
		// @3F2: bipush 8 (0x08)
		// @3F4: anewarray java.lang.String
		// @3F7: dup
		// @3F8: iconst_0
		// @3F9: ldc "6MAtO\u001cGZr\u0006\u0001GX&\u0006\u001c\u0002Zi\u0018OC\u0014`\u001a\u0003N\u0014b\n\tCAj\u001bOcEs\u0006\u0003C\u001a&&\u0001\u0002Ub\u000b\u0006V]i\u0001OV[&\u001b\u0007G\u0014j\u000e\u001cGFuCOK@&\u0007\u000eQ\u0014k\u0006\u001cQ]j\n\u001c\u0002Uh\u000bOC\u0014r\u000e\u001dEQr\u0006\u0001E\u0014u\u0016\u001cVQkAS@F8;\u0000\u0002@g\u001d\u0008G@&\u000e\u0001\u0002Qh\n\u0002[\u0018&\u0007\u0000NP&\u001b\u0007G\u0014!.#v\u0013&\u0004\n[\u0014g\u0001\u000b\u0002Wj\u0006\u000cI\u0014r\u0007\n\u0002Xc\t\u001b\u0002Yi\u001a\u001cG\u0014d\u001a\u001bV[hO\u0000L\u0014r\u0007\n\u0002Qh\n\u0002[\u001a"
		// @3FB: invokestatic game.C_100235_om.func_106284_z(java.lang.String)char[]
		// @3FE: invokestatic game.C_100235_om.func_106283_z(char[])java.lang.String
		// @401: aastore
		// @402: dup
		// @403: iconst_1
		// @404: ldc "'MXbOHcxRHOCZbO\u000cN]e\u0004OMZ&\u000e\u0001\u0002Qh\n\u0002[\u0014r\u0000OVUt\u0008\nV\u0014o\u001bA"
		// @406: invokestatic game.C_100235_om.func_106284_z(java.lang.String)char[]
		// @409: invokestatic game.C_100235_om.func_106283_z(char[])java.lang.String
		// @40C: aastore
		// @40D: dup
		// @40E: iconst_2
		// @40F: ldc ";JQ&\u001d\nF\u0014k\u000e\u001dIQt\u001cOCFi\u001a\u0001F\u0014r\u0007\n\u0002Qh\n\u0002[\u0014o\u0001\u000bKWg\u001b\n\u0002Mi\u001a\u001d\u0002@g\u001d\u0008G@&\u0003\u0000A_(O8JQhO\u001bJQ&\u0002\u000eP_c\u001d\u001c\u0002Po\u001c\u000eRDc\u000e\u001d\u000e\u0014r\u0007\n\u0002@g\u001d\u0008G@&\u0003\u0000A_&\u0007\u000eQ\u0014c\u0017\u001fKFc\u000bA\u0002sc\u001b\u001bKZaO\u000e\u0002@g\u001d\u0008G@&\u0003\u0000A_&\u001a\u001cGG&^OWZo\u001bOMR&\n\u0001GFa\u0016A\u001eVtQ<GXc\u000c\u001b\u0002Mi\u001a\u001d\u0002Yo\u001c\u001cKXc\u001cO\n\u0013CHF\u0002Uh\u000bOD]t\nOV\\c\u0002OWDq\u000e\u001dFG*O\u000eT[o\u000b\u0006LS&\u000e\u0001[\u0014h\n\u000ePV\u007fO\u0000@Gr\u000e\u000cNQuAOv\\c\u0016OU]j\u0003OJ[k\nOKZ&\u0000\u0001\u0002Mi\u001a\u001d\u0002Ws\u001d\u001dGZrO\u001bCFa\n\u001b\u000c"
		// @411: invokestatic game.C_100235_om.func_106284_z(java.lang.String)char[]
		// @414: invokestatic game.C_100235_om.func_106283_z(char[])java.lang.String
		// @417: aastore
		// @418: dup
		// @419: iconst_3
		// @41A: ldc "+GGr\u001d\u0000[\u0014r\u0007\n\u0002Pt\u0000\u0001GG&\u0018\u0006V\\&\u0002\u0006QGo\u0003\nQ\u001a"
		// @41C: invokestatic game.C_100235_om.func_106284_z(java.lang.String)char[]
		// @41F: invokestatic game.C_100235_om.func_106283_z(char[])java.lang.String
		// @422: aastore
		// @423: dup
		// @424: iconst_4
		// @425: ldc "8J]j\nO[[sO\u0007CBcO\u000e\u0002@g\u001d\u0008G@&\u0003\u0000A_*O\u000eLM&\u000b\u0006PQe\u001bBD]t\nOUQg\u001f\u0000LG&G\u001cWWnO\u000eQ\u0014j\u000e\u001cGFuFOU]j\u0003OCAr\u0000\u0002C@o\u000c\u000eNX\u007fO\u000eKY&\u001b\u0000UUt\u000b\u001c\u0002Mi\u001a\u001d\u0002@g\u001d\u0008G@(S\rP\nO\tO[[sO\nTQtO\u0001GQbO\u001bM\u0014b\u001d\u0000R\u0014gO\u001bCFa\n\u001b\u0002Xi\u000c\u0004\u000e\u0014e\u0003\u0006A_&\u0000\u0001\u0002@n\nOVUt\u0008\nV]h\u0008OKWi\u0001OC@&\u001b\u0007G\u0014d\u0000\u001bV[kB\u001dKSn\u001bOMR&\u0016\u0000WF&\u0006\u0001VQt\t\u000eAQ*O\u0000P\u0014e\u0003\u0006A_&\u001b\u0007G\u0014t\u0006\u0008J@&\u0002\u0000WGcO\rW@r\u0000\u0001\u0002Cn\u0006\u0003G\u0014n\u0000\u0003F]h\u0008O\u0005uJ;H\u000c\u0008d\u001dQfQu\u001b\u001dMM&\u001b\u0007G\u0014h\n\u0017V\u0014d\u000e\u001bA\\&\u0000\t\u0002Pt\u0000\u0001GG&\u0018\u0006V\\&\u0016\u0000WF&\u0003\u000eQQt\u001cA\u0002`g\u001d\u0008G@&\u0003\u0000A_uO\u0002C_cO\u0006V\u0014c\u000e\u001cKQtO\u001bM\u0014n\u0006\u001b\u0002Yi\u0019\u0006LS&\n\u0001GYo\n\u001c\u000c"
		// @427: invokestatic game.C_100235_om.func_106284_z(java.lang.String)char[]
		// @42A: invokestatic game.C_100235_om.func_106283_z(char[])java.lang.String
		// @42D: aastore
		// @42E: dup
		// @42F: iconst_5
		// @430: ldc "+GGr\u001d\u0000[\u0014r\u0007\n\u0002Pt\u0000\u0001GG&\u0018\u0006V\\&\u0003\u000eQQt\u001cA"
		// @432: invokestatic game.C_100235_om.func_106284_z(java.lang.String)char[]
		// @435: invokestatic game.C_100235_om.func_106283_z(char[])java.lang.String
		// @438: aastore
		// @439: dup
		// @43A: bipush 6 (0x06)
		// @43C: ldc "8GXjO\u000bMZcCO[[sO\u0007CBcO\u000cMYv\u0003\nVQbO\u001bJQ&.\u001eW]j\u000eOVUt\u0008\nV]h\u0008OO]u\u001c\u0006MZ("
		// @43E: invokestatic game.C_100235_om.func_106284_z(java.lang.String)char[]
		// @441: invokestatic game.C_100235_om.func_106283_z(char[])java.lang.String
		// @444: aastore
		// @445: dup
		// @446: bipush 7 (0x07)
		// @448: ldc ""
		// @44A: aastore
		// @44B: aastore
		// @44C: dup
		// @44D: bipush 6 (0x06)
		// @44F: iconst_0
		// @450: anewarray java.lang.String
		// @453: aastore
		// @454: dup
		// @455: bipush 7 (0x07)
		// @457: bipush 14 (0x0E)
		// @459: anewarray java.lang.String
		// @45C: dup
		// @45D: iconst_0
		// @45E: ldc ";JQ&\u0002\u0000Q@&\u001f\u0000UQt\t\u001aN\u0014q\n\u000eR[hO\u0006L\u0014gO(MXc\u0002HQ\u0014g\u001d\u001cGZg\u0003OKG&\u001b\u0007G\u0014n\n\u000eTM&\u001d\u0000A_c\u001bA\u0002`n\u0006\u001c\u0002]uO\u000e\u0002Xi\u0001\u0008\u000fFg\u0001\u0008G\u0014t\u0000\u000cIQrO\u0018K@nO\u000eL\u0014c\u0017\u001fN[u\u0006\u0000L\u0014r\u0007\u000eV\u0014e\u000e\u0001\u0002Gc\u0019\nPQj\u0016OFUk\u000e\u0008G\u0014\u007f\u0000\u001aP\u0014u\n\u0001V]h\n\u0003\u0002]`O\u0006V\u0014b\n\u001bMZg\u001b\nQ\u0014r\u0000\u0000\u0002Wj\u0000\u001cG\u001a:\r\u001d\u001c`n\nOe[j\n\u0002\u0005G&\u001c\u000cCZh\n\u001d\u0002Q~\u001b\nLPuO\u001bPUl\n\u000cV[t\u0016ON]h\n\u001c\u000e\u0014g\u0003\u0003MCo\u0001\u0008\u0002Xi\u0001\u0008\u000fFg\u0001\u0008G\u0014q\n\u000eR[h\u001cOV[&\r\n\u0002Ro\u001d\nF\u0014g\u000c\u001dMGuO\u001bJQ&\u0018\u0007MXcO\rC@r\u0003\nD]c\u0003\u000b\u0002Co\u001b\u0007\u0002Ue\u000c\u001aPUe\u0016A"
		// @460: invokestatic game.C_100235_om.func_106284_z(java.lang.String)char[]
		// @463: invokestatic game.C_100235_om.func_106283_z(char[])java.lang.String
		// @466: aastore
		// @467: dup
		// @468: iconst_1
		// @469: ldc "<GXc\u000c\u001b\u0002Mi\u001a\u001d\u0002\\c\u000e\u0019[\u0014t\u0000\u000cIQrO\u001aQ]h\u0008O\u0005e!O\u000eLP&H*\u0005\u001a"
		// @46B: invokestatic game.C_100235_om.func_106284_z(java.lang.String)char[]
		// @46E: invokestatic game.C_100235_om.func_106283_z(char[])java.lang.String
		// @471: aastore
		// @472: dup
		// @473: iconst_2
		// @474: ldc ";JQt\nOKG&\u000eOVFg\u0006\u0001KZaO\u000bP[h\nOMZ&\u001b\u0007G\u0014j\n\tV\u0014u\u0006\u000bG\u0014i\tOV\\cO\rC@r\u0003\nD]c\u0003\u000b\u000c\u0014K\u0000\u0019G\u0014r\u0007\n\u0002Wg\u0002\nPU&\u001b\u0000\u0002Ro\u0001\u000b\u0002]rCOCZbO\tKFcO\u0016MAtO\u0007GUp\u0016OP[e\u0004\nV\u0014g\u001bOK@("
		// @476: invokestatic game.C_100235_om.func_106284_z(java.lang.String)char[]
		// @479: invokestatic game.C_100235_om.func_106283_z(char[])java.lang.String
		// @47C: aastore
		// @47D: dup
		// @47E: iconst_3
		// @47F: ldc "<GXc\u000c\u001b\u0002Mi\u001a\u001d\u0002\\c\u000e\u0019[\u0014t\u0000\u000cIQrO\u000eLP&\t\u0006PQ&\u0006\u001b\u0002UrO\u001bJQ&\u001b\u001dC]h\u0006\u0001E\u0014b\u001d\u0000LQ("
		// @481: invokestatic game.C_100235_om.func_106284_z(java.lang.String)char[]
		// @484: invokestatic game.C_100235_om.func_106283_z(char[])java.lang.String
		// @487: aastore
		// @488: dup
		// @489: iconst_4
		// @48A: ldc "6MAtO\u001cJ[rO\u0018CG&\u001a\u0001QAe\u000c\nQG`\u001a\u0003\u000c\u0014N\n\u000eTM&\u001d\u0000A_c\u001b\u001c\u0002Zi\u001d\u0002CXj\u0016OVUm\nOC\u0014j\u0000\u0001E\u0014r\u0006\u0002G\u0014r\u0000OPQj\u0000\u000eF\u0018&\r\u001aV\u0014`\u0000\u001d\u0002Zi\u0018OV\\o\u001cOU]j\u0003O@Q&\u000e\u000cAQj\n\u001dC@c\u000bOQ[&\u001b\u0007C@&\u0016\u0000W\u0014e\u000e\u0001\u0002@t\u0016OCSg\u0006\u0001\u000c\u0008d\u001dQvF\u007fO\u000eLP&\u001a\u001cG\u0014r\u0007\n\u0002Cn\u0006\u001bG\u0014r\u001d\u000eHQe\u001b\u0000PM&\u0003\u0006LQ&\u001b\u0000\u0002Gc\nOU\\c\u001d\n\u0002@n\nOP[e\u0004\nV\u0014o\u001cOE[o\u0001\u0008\u0002@iO\u0003CZbCO@Q`\u0000\u001dG\u0014\u007f\u0000\u001a\u0002Ro\u001d\n\u0002]rA"
		// @48C: invokestatic game.C_100235_om.func_106284_z(java.lang.String)char[]
		// @48F: invokestatic game.C_100235_om.func_106283_z(char[])java.lang.String
		// @492: aastore
		// @493: dup
		// @494: iconst_5
		// @495: ldc ")KFcO\u000eV\u0014r\u0007\n\u0002@t\u000e\u0006L]h\u0008OFFi\u0001\n\u000c"
		// @497: invokestatic game.C_100235_om.func_106284_z(java.lang.String)char[]
		// @49A: invokestatic game.C_100235_om.func_106283_z(char[])java.lang.String
		// @49D: aastore
		// @49E: dup
		// @49F: bipush 6 (0x06)
		// @4A1: ldc "8GXjO\u000bMZcAOv\\cO\u0001GLrO\u001fJUu\nOMR&\u001b\u001dC]h\u0006\u0001E\u0014s\u001c\nQ\u0014r\u0007\n\u0002si\u0003\nO\u0013uO\u000cCZh\u0000\u0001Q\u001a&<\nNQe\u001bOV\\c\u0002OCG&\u0016\u0000WF&\u000c\u001aPFc\u0001\u001b\u0002Cc\u000e\u001fMZ("
		// @4A3: invokestatic game.C_100235_om.func_106284_z(java.lang.String)char[]
		// @4A6: invokestatic game.C_100235_om.func_106283_z(char[])java.lang.String
		// @4A9: aastore
		// @4AA: dup
		// @4AB: bipush 7 (0x07)
		// @4AD: ldc "<GXc\u000c\u001b\u0002Wg\u0001\u0001MZuA"
		// @4AF: invokestatic game.C_100235_om.func_106284_z(java.lang.String)char[]
		// @4B2: invokestatic game.C_100235_om.func_106283_z(char[])java.lang.String
		// @4B5: aastore
		// @4B6: dup
		// @4B7: bipush 8 (0x08)
		// @4B9: ldc ";JQ&\u000c\u000eLZi\u0001OKG&\u000e\u0001\u0002Q~\u001f\u0003MGo\u0019\n\u0002Vg\u0003\u0003KGr\u0006\u000c\u0002Cc\u000e\u001fMZ(O,CZh\u0000\u0001\u0002Ro\u001d\n\u0002Ri\u0003\u0003MCuO\u000e\u0002Dg\u001d\u000e@[j\u0006\u000c\u0002Ut\u000cOCZbO\u000cCAu\n\u001c\u0002Q~\u001f\u0003MGo\u0019\n\u0002Pg\u0002\u000eEQ&\u0000\u0001\u0002]k\u001f\u000eA@(O&D\u0014\u007f\u0000\u001a\u0002\\i\u0003\u000b\u0002Pi\u0018\u0001\u0002@n\nOO[s\u001c\n\u0002Vs\u001b\u001bMZ*O\u001bJQ&\u000c\u000eLZi\u0001OU]j\u0003OD]t\nOC@&\u0006\u001bQ\u0014i\u001f\u001bKYs\u0002OPUr\nA\u001eVtQ+GGr\u001d\u0000[\u0014r\u0007\n\u0002Zc\u000e\u001d@M&\u000b\u001dMZc\u001cOU]r\u0007O[[s\u001dOAUh\u0001\u0000LG("
		// @4BB: invokestatic game.C_100235_om.func_106284_z(java.lang.String)char[]
		// @4BE: invokestatic game.C_100235_om.func_106283_z(char[])java.lang.String
		// @4C1: aastore
		// @4C2: dup
		// @4C3: bipush 9 (0x09)
		// @4C5: ldc "+GGr\u001d\u0000[\u0014r\u0007\n\u0002Pt\u0000\u0001GG&\u0018\u0006V\\&\u000c\u000eLZi\u0001\u001c\u000c"
		// @4C7: invokestatic game.C_100235_om.func_106284_z(java.lang.String)char[]
		// @4CA: invokestatic game.C_100235_om.func_106283_z(char[])java.lang.String
		// @4CD: aastore
		// @4CE: dup
		// @4CF: bipush 10 (0x0A)
		// @4D1: ldc ";JQ&\r\u000ePFo\n\u001d\u0002Wi\u0001\tKZo\u0001\u0008\u0002Mi\u001a\u001d\u0002Gc\u0001\u001bKZc\u0003OJUuO\u0001MC&\r\nGZ&\u0003\u0006D@c\u000bA\u0002pc\u001c\u001bP[\u007fO\u001bJQ&\u001d\nOUo\u0001\u0006LS&\u000b\u001dMZc\u001cOU]r\u0007OG]r\u0007\nP\u0014i\tO[[s\u001dOCBg\u0006\u0003CVj\nOUQg\u001f\u0000LG("
		// @4D3: invokestatic game.C_100235_om.func_106284_z(java.lang.String)char[]
		// @4D6: invokestatic game.C_100235_om.func_106283_z(char[])java.lang.String
		// @4D9: aastore
		// @4DA: dup
		// @4DB: bipush 11 (0x0B)
		// @4DD: ldc "+GGr\u001d\u0000[\u0014r\u0007\n\u0002Pt\u0000\u0001GG("
		// @4DF: invokestatic game.C_100235_om.func_106284_z(java.lang.String)char[]
		// @4E2: invokestatic game.C_100235_om.func_106283_z(char[])java.lang.String
		// @4E5: aastore
		// @4E6: dup
		// @4E7: bipush 12 (0x0C)
		// @4E9: ldc "8GXjO\u000bMZcCO[[sO\u0007CBcO\u000cMYv\u0003\nVQbO\u001bJQ&\u001b\u001dC]h\u0006\u0001E\u0014k\u0006\u001cQ]i\u0001A"
		// @4EB: invokestatic game.C_100235_om.func_106284_z(java.lang.String)char[]
		// @4EE: invokestatic game.C_100235_om.func_106283_z(char[])java.lang.String
		// @4F1: aastore
		// @4F2: dup
		// @4F3: bipush 13 (0x0D)
		// @4F5: ldc ""
		// @4F7: aastore
		// @4F8: aastore
		// @4F9: dup
		// @4FA: bipush 8 (0x08)
		// @4FC: iconst_0
		// @4FD: anewarray java.lang.String
		// @500: aastore
		// @501: dup
		// @502: bipush 9 (0x09)
		// @504: bipush 14 (0x0E)
		// @506: anewarray java.lang.String
		// @509: dup
		// @50A: iconst_0
		// @50B: ldc ")NUmO\u0006Q\u0014gO\u001aQQ`\u001a\u0003\u0002Pc\t\nLGo\u0019\n\u0002Cc\u000e\u001fMZ&\u000e\u0008C]h\u001c\u001b\u0002Fi\u000c\u0004G@uO\u000eLP&\n\u0001GY\u007fO\u001cGZr\u0006\u0001GXuAOdXg\u0004OD[t\u0002\u001c\u0002U&\u000c\u0003MAbO\u0006L\u0014r\u0007\n\u0002Uo\u001dOU\\c\u001d\n\u0002]rO\u0006Q\u0014`\u0006\u001dGP*O\u0018J]e\u0007OFUk\u000e\u0008GG&\u000e\u0001[@n\u0006\u0001E\u0014v\u000e\u001cQ]h\u0008OV\\t\u0000\u001aE\\&\u0006\u001b\u000c"
		// @50D: invokestatic game.C_100235_om.func_106284_z(java.lang.String)char[]
		// @510: invokestatic game.C_100235_om.func_106283_z(char[])java.lang.String
		// @513: aastore
		// @514: dup
		// @515: iconst_1
		// @516: ldc "<GXc\u000c\u001b\u0002Rj\u000e\u0004\u0002UuO\u0016MAtO\u000cWFt\n\u0001V\u0014q\n\u000eR[hA"
		// @518: invokestatic game.C_100235_om.func_106284_z(java.lang.String)char[]
		// @51B: invokestatic game.C_100235_om.func_106283_z(char[])java.lang.String
		// @51E: aastore
		// @51F: dup
		// @520: iconst_2
		// @521: ldc ".\u0002Pt\u0000\u0001G\u0014o\u001cO@Qo\u0001\u0008\u0002Dj\u000e\u000cGP&\u0006\u0001\u0002@n\nO@Ur\u001b\u0003GRo\n\u0003F\u001a&)\u0006PQ&\t\u0003C_&\u0006\u0001\u0002Rt\u0000\u0001V\u0014i\tOK@&\u000e\u0001F\u0014i\r\u001cGFp\nOV\\cO\u001dGGs\u0003\u001bQ\u001a&-\n\u0002Wg\u001d\nDAjO\u0001M@&\u001b\u0000\u0002Yi\u0019\n\u0002Mi\u001a\u001d\u0002Gc\u0001\u001bKZc\u0003OKZr\u0000OV\\cO\tNUmO\u000cN[s\u000bC\u0002[tO\u0006V\u0014q\u0006\u0003N\u0014t\n\u000cG]p\nOFUk\u000e\u0008G\u001a"
		// @523: invokestatic game.C_100235_om.func_106284_z(java.lang.String)char[]
		// @526: invokestatic game.C_100235_om.func_106283_z(char[])java.lang.String
		// @529: aastore
		// @52A: dup
		// @52B: iconst_3
		// @52C: ldc "+GGr\u001d\u0000[\u0014r\u0007\n\u0002Pt\u0000\u0001G\u0014q\u0006\u001bJ\u0014`\u0003\u000eI\u001a"
		// @52E: invokestatic game.C_100235_om.func_106284_z(java.lang.String)char[]
		// @531: invokestatic game.C_100235_om.func_106283_z(char[])java.lang.String
		// @534: aastore
		// @535: dup
		// @536: iconst_4
		// @537: ldc ")NUmO\u000cCZ&\u000e\u0003Q[&\u000b\nQ@t\u0000\u0016\u0002]h\u000c\u0000O]h\u0008OP[e\u0004\nVG(O.\u0002Fi\u000c\u0004G@&<\u0003CBcO\u0018KXjO\rG\u0014b\u001d\u0000RDc\u000bOKZr\u0000OV\\cO\rC@r\u0003\nD]c\u0003\u000b\u000c\u0014S\u001c\n\u0002Rj\u000e\u0004\u0002@iO\u000bGRc\u0001\u000b\u0002Mi\u001a\u001dQQj\tOCSg\u0006\u0001Q@&\u0006\u001bQ\u0014t\u0000\u000cIQr\u001cA\u001eVtQ=MWm\n\u001bQ\u0014r\u0007\u000eV\u0014b\n\u001bMZg\u001b\n\u0002Wj\u0000\u001cG\u0014c\u0001\u0000WSnO\u001bM\u0014r\u0007\n\u0002gj\u000e\u0019G\u0014q\u0006\u0003N\u0014e\u000e\u001aQQ&\u0006\u001b\u0002Pg\u0002\u000eEQ("
		// @539: invokestatic game.C_100235_om.func_106284_z(java.lang.String)char[]
		// @53C: invokestatic game.C_100235_om.func_106283_z(char[])java.lang.String
		// @53F: aastore
		// @540: dup
		// @541: iconst_5
		// @542: ldc "?PQu\u001cO\u001e]k\u0008R\u0010\u00048O\u001bM\u0014d\n\u0008KZ("
		// @544: invokestatic game.C_100235_om.func_106284_z(java.lang.String)char[]
		// @547: invokestatic game.C_100235_om.func_106283_z(char[])java.lang.String
		// @54A: aastore
		// @54B: dup
		// @54C: bipush 6 (0x06)
		// @54E: ldc ""
		// @550: aastore
		// @551: dup
		// @552: bipush 7 (0x07)
		// @554: ldc "+GGr\u001d\u0000[\u0014r\u0007\n\u0002gj\u000e\u0019G\u001a"
		// @556: invokestatic game.C_100235_om.func_106284_z(java.lang.String)char[]
		// @559: invokestatic game.C_100235_om.func_106283_z(char[])java.lang.String
		// @55C: aastore
		// @55D: dup
		// @55E: bipush 8 (0x08)
		// @560: ldc ";JQ&(\u0000NQkO\u0006Q\u0014g\u001d\u0002GP&\u0018\u0006V\\&\u000e\u0006PVs\u001d\u001cV\u0014t\u0000\u000cIQr\u001cA\u0002`n\n\u001cG\u0014e\u001d\nC@cO\u000e\u0002Wj\u0000\u001aF\u0014i\tODXg\u0004OU\\c\u0001OV\\c\u0016OFQr\u0000\u0001C@cCOU\\o\u000c\u0007\u0002Wg\u0001OFUk\u000e\u0008G\u0014g\u0001\u000b\u0002Vt\u0006\u0001E\u0014b\u0000\u0018L\u0014g\n\u001dKUjO\nLQk\u0006\nQ\u001a"
		// @562: invokestatic game.C_100235_om.func_106284_z(java.lang.String)char[]
		// @565: invokestatic game.C_100235_om.func_106283_z(char[])java.lang.String
		// @568: aastore
		// @569: dup
		// @56A: bipush 9 (0x09)
		// @56C: ldc "<GXc\u000c\u001b\u0002Uo\u001d\rWFu\u001bOP[e\u0004\nVG&\u000e\u001c\u0002Mi\u001a\u001d\u0002Ws\u001d\u001dGZrO\u0018GUv\u0000\u0001\u000c"
		// @56E: invokestatic game.C_100235_om.func_106284_z(java.lang.String)char[]
		// @571: invokestatic game.C_100235_om.func_106283_z(char[])java.lang.String
		// @574: aastore
		// @575: dup
		// @576: bipush 10 (0x0A)
		// @578: ldc ")KFcO\u000eKFd\u001a\u001dQ@&\u0006\u0001V[&\u001b\u0007G\u0014v\u000e\u001bJ\u0014i\tOV\\cO\u000eGFo\u000e\u0003\u0002Pt\u0000\u0001GG&\u001b\u0000\u0002Vt\u0006\u0001E\u0014r\u0007\nO\u0014b\u0000\u0018L\u001a&6\u0000W\u0014e\u000e\u0001\u0002Uj\u001c\u0000\u0002Pc\u001c\u001bP[\u007fO\u001bJQkO\u0018K@nO\u0008WZuO\u0000P\u0014\u007f\u0000\u001aP\u0014i\u001b\u0007GF&\u0018\nCDi\u0001\u001c\u000e\u0014o\tO[[sO\u000cCZ&\u0007\u0006V\u0014r\u0007\nO\u001a:\r\u001d\u001cpc\u001c\u001bP[\u007fO\u001bJQkO\u000eNX&\u001b\u0000\u0002Wi\u0002\u001fNQr\nOV\\cO\u0002KGu\u0006\u0000L\u001a"
		// @57A: invokestatic game.C_100235_om.func_106284_z(java.lang.String)char[]
		// @57D: invokestatic game.C_100235_om.func_106283_z(char[])java.lang.String
		// @580: aastore
		// @581: dup
		// @582: bipush 11 (0x0B)
		// @584: ldc "+GGr\u001d\u0000[\u0014r\u0007\n\u0002Pt\u0000\u0001GG("
		// @586: invokestatic game.C_100235_om.func_106284_z(java.lang.String)char[]
		// @589: invokestatic game.C_100235_om.func_106283_z(char[])java.lang.String
		// @58C: aastore
		// @58D: dup
		// @58E: bipush 12 (0x0C)
		// @590: ldc "8GXjO\u000bMZcAO{[sO\u0007CBcO\u000cMYv\u0003\nVQbO(MXc\u0002OVFg\u0006\u0001KZaA"
		// @592: invokestatic game.C_100235_om.func_106284_z(java.lang.String)char[]
		// @595: invokestatic game.C_100235_om.func_106283_z(char[])java.lang.String
		// @598: aastore
		// @599: dup
		// @59A: bipush 13 (0x0D)
		// @59C: ldc ""
		// @59E: aastore
		// @59F: aastore
		// @5A0: putstatic java.lang.String[][] game.C_100235_om.field_106288_d
		// @5A3: ldc "6MA&\u000c\u000eLZi\u001bOA\\g\u001bOV[&SJ\u0012\n&\r\nAUs\u001c\n\u0002\u0008#_Q\u0002]uO\u0000DRj\u0006\u0001G\u0014o\u0001O[[s\u001dODFo\n\u0001F\u0014j\u0006\u001cV\u001a"
		// @5A5: invokestatic game.C_100235_om.func_106284_z(java.lang.String)char[]
		// @5A8: invokestatic game.C_100235_om.func_106283_z(char[])java.lang.String
		// @5AB: putstatic java.lang.String game.C_100235_om.field_106298_h
		// @5AE: ldc ",WVc\u001cOLQc\u000b\nF\u000e&"
		// @5B0: invokestatic game.C_100235_om.func_106284_z(java.lang.String)char[]
		// @5B3: invokestatic game.C_100235_om.func_106283_z(char[])java.lang.String
		// @5B6: putstatic java.lang.String game.C_100235_om.field_106295_m
		// @5B9: sipush 128 (0x0080)
		// @5BC: newarray int[]
		// @5BE: putstatic int[] game.C_100235_om.field_106286_f
		// @5C1: sipush 128 (0x0080)
		// @5C4: newarray int[]
		// @5C6: putstatic int[] game.C_100235_om.field_106294_l
		// @5C9: iconst_0
		// @5CA: istore_2
		// @5CB: sipush -129 (0xFF7F)
		// @5CE: iload_2
		// @5CF: iconst_m1
		// @5D0: ixor
		// @5D1: if_icmpge @64D
		// @5D4: ldc 1114111 (0x10ffff)
		// @5D6: istore_0
		// @5D7: sipush 255 (0x00FF)
		// @5DA: iload_2
		// @5DB: iconst_1
		// @5DC: iadd
		// @5DD: imul
		// @5DE: sipush 128 (0x0080)
		// @5E1: idiv
		// @5E2: ldc 16711935 (0xff00ff)
		// @5E4: iload_0
		// @5E5: iand
		// @5E6: imul
		// @5E7: istore_1
		// @5E8: getstatic int[] game.C_100235_om.field_106286_f
		// @5EB: iload_2
		// @5EC: ldc 16711680 (0xff0000)
		// @5EE: iload_1
		// @5EF: ineg
		// @5F0: iload_0
		// @5F1: iload_2
		// @5F2: sipush 255 (0x00FF)
		// @5F5: imul
		// @5F6: sipush 255 (0x00FF)
		// @5F9: iadd
		// @5FA: sipush 128 (0x0080)
		// @5FD: idiv
		// @5FE: imul
		// @5FF: iadd
		// @600: invokestatic game.C_100256_pk.func_100449_a(int, int)int
		// @603: iload_1
		// @604: ldc -16711936 (0xff00ff00)
		// @606: invokestatic game.C_100256_pk.func_100449_a(int, int)int
		// @609: iadd
		// @60A: ldc -279075512 (0xef5da548)
		// @60C: iushr
		// @60D: iastore
		// @60E: ldc 16776976 (0xffff10)
		// @610: istore_0
		// @611: iload_0
		// @612: ldc 16711935 (0xff00ff)
		// @614: iand
		// @615: iconst_1
		// @616: iload_2
		// @617: iadd
		// @618: sipush 255 (0x00FF)
		// @61B: imul
		// @61C: sipush 128 (0x0080)
		// @61F: idiv
		// @620: imul
		// @621: istore_1
		// @622: getstatic int[] game.C_100235_om.field_106294_l
		// @625: iload_2
		// @626: ldc -16711936 (0xff00ff00)
		// @628: iload_1
		// @629: invokestatic game.C_100256_pk.func_100449_a(int, int)int
		// @62C: iload_1
		// @62D: ineg
		// @62E: iload_0
		// @62F: iload_2
		// @630: iconst_m1
		// @631: isub
		// @632: sipush 255 (0x00FF)
		// @635: imul
		// @636: sipush 128 (0x0080)
		// @639: idiv
		// @63A: imul
		// @63B: iadd
		// @63C: ldc 16711680 (0xff0000)
		// @63E: invokestatic game.C_100256_pk.func_100449_a(int, int)int
		// @641: ineg
		// @642: isub
		// @643: ldc 594638216 (0x23717588)
		// @645: iushr
		// @646: iastore
		// @647: iinc #2 +1
		// @64A: goto @5CB
		// @64D: sipush 128 (0x0080)
		// @650: newarray int[]
		// @652: putstatic int[] game.C_100235_om.field_106299_i
		// @655: iconst_0
		// @656: istore_2
		// @657: sipush 128 (0x0080)
		// @65A: iload_2
		// @65B: if_icmple @68B
		// @65E: getstatic int[] game.C_100235_om.field_106286_f
		// @661: iload_2
		// @662: iaload
		// @663: sipush 255 (0x00FF)
		// @666: iand
		// @667: istore_3
		// @668: getstatic int[] game.C_100235_om.field_106286_f
		// @66B: iload_2
		// @66C: iaload
		// @66D: ldc 16723063 (0xff2c77)
		// @66F: iand
		// @670: ldc -846450128 (0xcd8c3230)
		// @672: ishr
		// @673: istore #4
		// @675: getstatic int[] game.C_100235_om.field_106299_i
		// @678: iload_2
		// @679: sipush 257 (0x0101)
		// @67C: iload #4
		// @67E: imul
		// @67F: iload_3
		// @680: ldc -1833681552 (0x92b43d70)
		// @682: ishl
		// @683: iadd
		// @684: iastore
		// @685: iinc #2 +1
		// @688: goto @657
		// @68B: sipush 128 (0x0080)
		// @68E: newarray int[]
		// @690: putstatic int[] game.C_100235_om.field_106297_k
		// @693: iconst_0
		// @694: istore_2
		// @695: sipush -129 (0xFF7F)
		// @698: iload_2
		// @699: iconst_m1
		// @69A: ixor
		// @69B: if_icmpge @6C8
		// @69E: sipush 255 (0x00FF)
		// @6A1: getstatic int[] game.C_100235_om.field_106286_f
		// @6A4: iload_2
		// @6A5: iaload
		// @6A6: iand
		// @6A7: istore_3
		// @6A8: getstatic int[] game.C_100235_om.field_106286_f
		// @6AB: iload_2
		// @6AC: iaload
		// @6AD: ldc -1317218704 (0xb17cd670)
		// @6AF: ishr
		// @6B0: sipush 255 (0x00FF)
		// @6B3: iand
		// @6B4: istore #4
		// @6B6: getstatic int[] game.C_100235_om.field_106297_k
		// @6B9: iload_2
		// @6BA: iload #4
		// @6BC: ldc 65792 (0x10100)
		// @6BE: iload_3
		// @6BF: imul
		// @6C0: iadd
		// @6C1: iastore
		// @6C2: iinc #2 +1
		// @6C5: goto @695
		// @6C8: return
	}
	
	private static char[] func_106284_z(String arg0)
	{
		// @00: aload_0
		// @01: invokevirtual java.lang.String.toCharArray()char[]
		// @04: dup
		// @05: arraylength
		// @06: iconst_2
		// @07: if_icmpge @13
		// @0A: dup
		// @0B: iconst_0
		// @0C: dup2
		// @0D: caload
		// @0E: bipush 111 (0x6F)
		// @10: ixor
		// @11: i2c
		// @12: castore
		// @13: areturn
	}
	
	private static String func_106283_z(char[] arg0)
	{
		// @00: aload_0
		// @01: dup
		// @02: arraylength
		// @03: swap
		// @04: iconst_0
		// @05: istore_1
		// @06: goto @4C
		// @09: dup
		// @0A: iload_1
		// @0B: dup2
		// @0C: caload
		// @0D: iload_1
		// @0E: iconst_5
		// @0F: irem
		// @10: tableswitch def: @44, for 0: @30, for 1: @35, for 2: @3A, for 3: @3F
		// @30: bipush 111 (0x6F)
		// @32: goto @46
		// @35: bipush 34 (0x22)
		// @37: goto @46
		// @3A: bipush 52 (0x34)
		// @3C: goto @46
		// @3F: bipush 6 (0x06)
		// @41: goto @46
		// @44: bipush 111 (0x6F)
		// @46: ixor
		// @47: i2c
		// @48: castore
		// @49: iinc #1 +1
		// @4C: swap
		// @4D: dup_x1
		// @4E: iload_1
		// @4F: if_icmpgt @09
		// @52: new java.lang.String
		// @55: dup_x1
		// @56: swap
		// @57: invokespecial java.lang.String.<init>(char[])void
		// @5A: invokevirtual java.lang.String.intern()java.lang.String
		// @5D: areturn
	}
}
