package game;

final class C_100292_jk extends C_100158_da
{
	static char[] field_101218_n;
	int field_101213_t;
	long field_101216_q;
	int[] field_101224_k;
	int field_101219_o;
	int field_101222_j;
	static int field_101215_r;
	int field_101221_m;
	int field_101220_l;
	int field_101214_s;
	int field_101217_p;
	private static final String[] field_101223_z;
	
	static final void func_101209_a(String arg0, byte arg1, int arg2)
	{
		// @000: iload_1
		// @001: bipush -73 (0xB7)
		// @003: if_icmplt @00F
		// @006: bipush 64 (0x40)
		// @008: putstatic int game.C_100292_jk.field_101215_r
		// @00B: goto @00F
		// @00E: athrow
		// @00F: iconst_0
		// @010: putstatic boolean game.C_100198_qn.field_105834_b
		// @013: iconst_0
		// @014: putstatic boolean game.C_100057_dd.field_104259_a
		// @017: getstatic game.C_100282_nh game.C_100027_hc.field_102598_S
		// @01A: ifnull @0D1
		// @01D: getstatic game.C_100282_nh game.C_100027_hc.field_102598_S
		// @020: getfield boolean game.C_100282_nh.field_102619_V
		// @023: ifne @02E
		// @026: goto @02A
		// @029: athrow
		// @02A: goto @0D1
		// @02D: athrow
		// @02E: bipush -9 (0xF7)
		// @030: iload_2
		// @031: iconst_m1
		// @032: ixor
		// @033: if_icmpne @05B
		// @036: getstatic boolean game.C_100186_rl.field_105720_f
		// @039: ifeq @04A
		// @03C: goto @040
		// @03F: athrow
		// @040: getstatic java.lang.String game.C_100114_q.field_100493_z
		// @043: astore_0
		// @044: getstatic int game.SteelSentinels.field_105275_O
		// @047: ifeq @04E
		// @04A: getstatic java.lang.String game.C_100152_bd.field_105208_j
		// @04D: astore_0
		// @04E: iconst_2
		// @04F: istore_2
		// @050: getstatic game.C_100151_bc game.C_100099_fb.field_103039_E
		// @053: getstatic java.lang.String game.C_100322_hn.field_107239_c
		// @056: bipush 68 (0x44)
		// @058: invokevirtual game.C_100151_bc.func_102922_a(java.lang.String, byte)void
		// @05B: iconst_1
		// @05C: istore_3
		// @05D: bipush -11 (0xF5)
		// @05F: iload_2
		// @060: iconst_m1
		// @061: ixor
		// @062: if_icmpne @06B
		// @065: iconst_0
		// @066: invokestatic game.C_100250_pl.func_106432_a(boolean)void
		// @069: iconst_0
		// @06A: istore_3
		// @06B: iload_3
		// @06C: ifne @073
		// @06F: goto @0A8
		// @072: athrow
		// @073: getstatic boolean game.C_100057_dd.field_104259_a
		// @076: ifne @07D
		// @079: goto @08F
		// @07C: athrow
		// @07D: sipush -30945 (0x871F)
		// @080: iconst_1
		// @081: anewarray java.lang.String
		// @084: dup
		// @085: iconst_0
		// @086: aload_0
		// @087: aastore
		// @088: getstatic java.lang.String game.C_100108_ee.field_100384_g
		// @08B: invokestatic game.C_100132_td.func_104965_a(int, java.lang.String[], java.lang.String)java.lang.String
		// @08E: astore_0
		// @08F: getstatic boolean game.C_100291_jj.field_106872_f
		// @092: ifne @099
		// @095: goto @09D
		// @098: athrow
		// @099: getstatic java.lang.String game.C_100086_uh.field_103030_s
		// @09C: astore_0
		// @09D: getstatic game.C_100282_nh game.C_100027_hc.field_102598_S
		// @0A0: iload_2
		// @0A1: sipush 26371 (0x6703)
		// @0A4: aload_0
		// @0A5: invokevirtual game.C_100282_nh.func_102697_a(int, int, java.lang.String)void
		// @0A8: sipush -257 (0xFEFF)
		// @0AB: iload_2
		// @0AC: iconst_m1
		// @0AD: ixor
		// @0AE: if_icmpeq @0D1
		// @0B1: iload_2
		// @0B2: bipush 10 (0x0A)
		// @0B4: if_icmpeq @0D1
		// @0B7: goto @0BB
		// @0BA: athrow
		// @0BB: getstatic boolean game.C_100186_rl.field_105720_f
		// @0BE: ifeq @0C9
		// @0C1: goto @0C5
		// @0C4: athrow
		// @0C5: goto @0D1
		// @0C8: athrow
		// @0C9: getstatic game.C_100151_bc game.C_100099_fb.field_103039_E
		// @0CC: bipush -77 (0xB3)
		// @0CE: invokevirtual game.C_100151_bc.func_102924_a(byte)void
		// @0D1: goto @118
		// @0D4: astore_3
		// @0D5: aload_3
		// @0D6: new java.lang.StringBuilder
		// @0D9: dup
		// @0DA: invokespecial java.lang.StringBuilder.<init>()void
		// @0DD: getstatic java.lang.String[] game.C_100292_jk.field_101223_z
		// @0E0: iconst_1
		// @0E1: aaload
		// @0E2: invokevirtual java.lang.StringBuilder.append(java.lang.String)java.lang.StringBuilder
		// @0E5: aload_0
		// @0E6: ifnull @0F2
		// @0E9: getstatic java.lang.String[] game.C_100292_jk.field_101223_z
		// @0EC: iconst_2
		// @0ED: aaload
		// @0EE: goto @0F7
		// @0F1: athrow
		// @0F2: getstatic java.lang.String[] game.C_100292_jk.field_101223_z
		// @0F5: iconst_0
		// @0F6: aaload
		// @0F7: invokevirtual java.lang.StringBuilder.append(java.lang.String)java.lang.StringBuilder
		// @0FA: bipush 44 (0x2C)
		// @0FC: invokevirtual java.lang.StringBuilder.append(char)java.lang.StringBuilder
		// @0FF: iload_1
		// @100: invokevirtual java.lang.StringBuilder.append(int)java.lang.StringBuilder
		// @103: bipush 44 (0x2C)
		// @105: invokevirtual java.lang.StringBuilder.append(char)java.lang.StringBuilder
		// @108: iload_2
		// @109: invokevirtual java.lang.StringBuilder.append(int)java.lang.StringBuilder
		// @10C: bipush 41 (0x29)
		// @10E: invokevirtual java.lang.StringBuilder.append(char)java.lang.StringBuilder
		// @111: invokevirtual java.lang.StringBuilder.toString()java.lang.String
		// @114: invokestatic game.C_100181_cf.func_105695_a(java.lang.Throwable, java.lang.String)game.C_100170_cm
		// @117: athrow
		// @118: return
	}
	
	public static void func_101211_e(int arg0)
	{
		// @00: aconst_null
		// @01: putstatic char[] game.C_100292_jk.field_101218_n
		// @04: iload_0
		// @05: sipush 8355 (0x20A3)
		// @08: if_icmpeq @12
		// @0B: aconst_null
		// @0C: checkcast char[]
		// @0F: putstatic char[] game.C_100292_jk.field_101218_n
		// @12: goto @36
		// @15: astore_1
		// @16: aload_1
		// @17: new java.lang.StringBuilder
		// @1A: dup
		// @1B: invokespecial java.lang.StringBuilder.<init>()void
		// @1E: getstatic java.lang.String[] game.C_100292_jk.field_101223_z
		// @21: iconst_4
		// @22: aaload
		// @23: invokevirtual java.lang.StringBuilder.append(java.lang.String)java.lang.StringBuilder
		// @26: iload_0
		// @27: invokevirtual java.lang.StringBuilder.append(int)java.lang.StringBuilder
		// @2A: bipush 41 (0x29)
		// @2C: invokevirtual java.lang.StringBuilder.append(char)java.lang.StringBuilder
		// @2F: invokevirtual java.lang.StringBuilder.toString()java.lang.String
		// @32: invokestatic game.C_100181_cf.func_105695_a(java.lang.Throwable, java.lang.String)game.C_100170_cm
		// @35: athrow
		// @36: return
	}
	
	static final boolean func_101212_a(int[] arg0, byte arg1, int[] arg2, int arg3, boolean arg4)
	{
		// @000: getstatic int game.SteelSentinels.field_105275_O
		// @003: istore #10
		// @005: iload_1
		// @006: bipush -30 (0xE2)
		// @008: if_icmple @00D
		// @00B: iconst_0
		// @00C: ireturn
		// @00D: bipush 49 (0x31)
		// @00F: iload_3
		// @010: if_icmpne @032
		// @013: iload #4
		// @015: ifeq @030
		// @018: goto @01C
		// @01B: athrow
		// @01C: bipush 25 (0x19)
		// @01E: bipush 31 (0x1F)
		// @020: aload_2
		// @021: invokestatic game.C_100189_ri.func_105742_a(int, int, int[])boolean
		// @024: ifeq @030
		// @027: goto @02B
		// @02A: athrow
		// @02B: iconst_1
		// @02C: goto @031
		// @02F: athrow
		// @030: iconst_0
		// @031: ireturn
		// @032: getstatic int[] game.C_100017_wj.field_103821_j
		// @035: astore #5
		// @037: iconst_0
		// @038: istore #6
		// @03A: iload #6
		// @03C: iconst_m1
		// @03D: ixor
		// @03E: aload #5
		// @040: arraylength
		// @041: iconst_m1
		// @042: ixor
		// @043: if_icmple @0B3
		// @046: aload #5
		// @048: iload #6
		// @04A: iaload
		// @04B: istore #7
		// @04D: iload #7
		// @04F: aload_0
		// @050: bipush -117 (0x8B)
		// @052: invokestatic game.C_100097_k.func_104572_a(int, int[], int)boolean
		// @055: iload #10
		// @057: ifne @0B4
		// @05A: ifne @075
		// @05D: goto @061
		// @060: athrow
		// @061: iload #4
		// @063: aload_0
		// @064: iload #7
		// @066: iconst_0
		// @067: invokestatic game.C_100171_cn.func_105561_a(boolean, int[], int, boolean)boolean
		// @06A: ifne @075
		// @06D: goto @071
		// @070: athrow
		// @071: goto @0AB
		// @074: athrow
		// @075: bipush 113 (0x71)
		// @077: iload #7
		// @079: invokestatic game.C_100042_we.func_104129_b(int, int)int[]
		// @07C: astore #8
		// @07E: iconst_0
		// @07F: istore #9
		// @081: iload #9
		// @083: iconst_m1
		// @084: ixor
		// @085: bipush -8 (0xF8)
		// @087: aload #8
		// @089: arraylength
		// @08A: iadd
		// @08B: iconst_m1
		// @08C: ixor
		// @08D: if_icmple @0AB
		// @090: iload_3
		// @091: aload #8
		// @093: iload #9
		// @095: iaload
		// @096: iload #10
		// @098: ifne @043
		// @09B: if_icmpeq @0A1
		// @09E: goto @0A3
		// @0A1: iconst_1
		// @0A2: ireturn
		// @0A3: iinc #9 +1
		// @0A6: iload #10
		// @0A8: ifeq @081
		// @0AB: iinc #6 +1
		// @0AE: iload #10
		// @0B0: ifeq @03A
		// @0B3: iconst_0
		// @0B4: ireturn
		// @0B5: astore #5
		// @0B7: aload #5
		// @0B9: new java.lang.StringBuilder
		// @0BC: dup
		// @0BD: invokespecial java.lang.StringBuilder.<init>()void
		// @0C0: getstatic java.lang.String[] game.C_100292_jk.field_101223_z
		// @0C3: iconst_5
		// @0C4: aaload
		// @0C5: invokevirtual java.lang.StringBuilder.append(java.lang.String)java.lang.StringBuilder
		// @0C8: aload_0
		// @0C9: ifnull @0D5
		// @0CC: getstatic java.lang.String[] game.C_100292_jk.field_101223_z
		// @0CF: iconst_2
		// @0D0: aaload
		// @0D1: goto @0DA
		// @0D4: athrow
		// @0D5: getstatic java.lang.String[] game.C_100292_jk.field_101223_z
		// @0D8: iconst_0
		// @0D9: aaload
		// @0DA: invokevirtual java.lang.StringBuilder.append(java.lang.String)java.lang.StringBuilder
		// @0DD: bipush 44 (0x2C)
		// @0DF: invokevirtual java.lang.StringBuilder.append(char)java.lang.StringBuilder
		// @0E2: iload_1
		// @0E3: invokevirtual java.lang.StringBuilder.append(int)java.lang.StringBuilder
		// @0E6: bipush 44 (0x2C)
		// @0E8: invokevirtual java.lang.StringBuilder.append(char)java.lang.StringBuilder
		// @0EB: aload_2
		// @0EC: ifnull @0F8
		// @0EF: getstatic java.lang.String[] game.C_100292_jk.field_101223_z
		// @0F2: iconst_2
		// @0F3: aaload
		// @0F4: goto @0FD
		// @0F7: athrow
		// @0F8: getstatic java.lang.String[] game.C_100292_jk.field_101223_z
		// @0FB: iconst_0
		// @0FC: aaload
		// @0FD: invokevirtual java.lang.StringBuilder.append(java.lang.String)java.lang.StringBuilder
		// @100: bipush 44 (0x2C)
		// @102: invokevirtual java.lang.StringBuilder.append(char)java.lang.StringBuilder
		// @105: iload_3
		// @106: invokevirtual java.lang.StringBuilder.append(int)java.lang.StringBuilder
		// @109: bipush 44 (0x2C)
		// @10B: invokevirtual java.lang.StringBuilder.append(char)java.lang.StringBuilder
		// @10E: iload #4
		// @110: invokevirtual java.lang.StringBuilder.append(boolean)java.lang.StringBuilder
		// @113: bipush 41 (0x29)
		// @115: invokevirtual java.lang.StringBuilder.append(char)java.lang.StringBuilder
		// @118: invokevirtual java.lang.StringBuilder.toString()java.lang.String
		// @11B: invokestatic game.C_100181_cf.func_105695_a(java.lang.Throwable, java.lang.String)game.C_100170_cm
		// @11E: athrow
	}
	
	C_100292_jk(int arg0, int arg1, int arg2, int arg3, int arg4, int arg5, int[] arg6)
	{
		// @00: aload_0
		// @01: invokespecial game.C_100158_da.<init>()void
		// @04: aload_0
		// @05: iload_2
		// @06: putfield int game.C_100292_jk.field_101213_t
		// @09: aload_0
		// @0A: getstatic int game.C_100031_gl.field_103968_a
		// @0D: dup
		// @0E: iconst_1
		// @0F: iadd
		// @10: putstatic int game.C_100031_gl.field_103968_a
		// @13: ldc 65535 (0xffff)
		// @15: iand
		// @16: putfield int game.C_100292_jk.field_101217_p
		// @19: aload_0
		// @1A: iload_3
		// @1B: putfield int game.C_100292_jk.field_101220_l
		// @1E: aload_0
		// @1F: iload #4
		// @21: putfield int game.C_100292_jk.field_101219_o
		// @24: aload_0
		// @25: iload_1
		// @26: putfield int game.C_100292_jk.field_101222_j
		// @29: aload_0
		// @2A: aload #7
		// @2C: putfield int[] game.C_100292_jk.field_101224_k
		// @2F: aload_0
		// @30: iload #5
		// @32: putfield int game.C_100292_jk.field_101214_s
		// @35: aload_0
		// @36: iload #6
		// @38: putfield int game.C_100292_jk.field_101221_m
		// @3B: goto @AC
		// @3E: astore #8
		// @40: aload #8
		// @42: new java.lang.StringBuilder
		// @45: dup
		// @46: invokespecial java.lang.StringBuilder.<init>()void
		// @49: getstatic java.lang.String[] game.C_100292_jk.field_101223_z
		// @4C: iconst_3
		// @4D: aaload
		// @4E: invokevirtual java.lang.StringBuilder.append(java.lang.String)java.lang.StringBuilder
		// @51: iload_1
		// @52: invokevirtual java.lang.StringBuilder.append(int)java.lang.StringBuilder
		// @55: bipush 44 (0x2C)
		// @57: invokevirtual java.lang.StringBuilder.append(char)java.lang.StringBuilder
		// @5A: iload_2
		// @5B: invokevirtual java.lang.StringBuilder.append(int)java.lang.StringBuilder
		// @5E: bipush 44 (0x2C)
		// @60: invokevirtual java.lang.StringBuilder.append(char)java.lang.StringBuilder
		// @63: iload_3
		// @64: invokevirtual java.lang.StringBuilder.append(int)java.lang.StringBuilder
		// @67: bipush 44 (0x2C)
		// @69: invokevirtual java.lang.StringBuilder.append(char)java.lang.StringBuilder
		// @6C: iload #4
		// @6E: invokevirtual java.lang.StringBuilder.append(int)java.lang.StringBuilder
		// @71: bipush 44 (0x2C)
		// @73: invokevirtual java.lang.StringBuilder.append(char)java.lang.StringBuilder
		// @76: iload #5
		// @78: invokevirtual java.lang.StringBuilder.append(int)java.lang.StringBuilder
		// @7B: bipush 44 (0x2C)
		// @7D: invokevirtual java.lang.StringBuilder.append(char)java.lang.StringBuilder
		// @80: iload #6
		// @82: invokevirtual java.lang.StringBuilder.append(int)java.lang.StringBuilder
		// @85: bipush 44 (0x2C)
		// @87: invokevirtual java.lang.StringBuilder.append(char)java.lang.StringBuilder
		// @8A: aload #7
		// @8C: ifnull @98
		// @8F: getstatic java.lang.String[] game.C_100292_jk.field_101223_z
		// @92: iconst_2
		// @93: aaload
		// @94: goto @9D
		// @97: athrow
		// @98: getstatic java.lang.String[] game.C_100292_jk.field_101223_z
		// @9B: iconst_0
		// @9C: aaload
		// @9D: invokevirtual java.lang.StringBuilder.append(java.lang.String)java.lang.StringBuilder
		// @A0: bipush 41 (0x29)
		// @A2: invokevirtual java.lang.StringBuilder.append(char)java.lang.StringBuilder
		// @A5: invokevirtual java.lang.StringBuilder.toString()java.lang.String
		// @A8: invokestatic game.C_100181_cf.func_105695_a(java.lang.Throwable, java.lang.String)game.C_100170_cm
		// @AB: athrow
		// @AC: return
	}
	
	static final void func_101210_f(int arg0)
	{
		// @000: getstatic int game.SteelSentinels.field_105275_O
		// @003: istore_2
		// @004: getstatic game.C_100177_cj game.C_100313_lg.field_107164_d
		// @007: invokevirtual game.C_100177_cj.func_105641_c()void
		// @00A: getstatic game.C_100177_cj game.C_100341_jd.field_102643_gb
		// @00D: invokevirtual game.C_100177_cj.func_105641_c()void
		// @010: getstatic int game.C_100342_jg.field_102725_Qb
		// @013: iconst_1
		// @014: isub
		// @015: putstatic int game.C_100342_jg.field_102725_Qb
		// @018: getstatic int game.C_100342_jg.field_102725_Qb
		// @01B: ifeq @022
		// @01E: goto @0AF
		// @021: athrow
		// @022: sipush 200 (0x00C8)
		// @025: putstatic int game.C_100342_jg.field_102725_Qb
		// @028: getstatic game.C_100202_qi game.C_100226_ae.field_106148_d
		// @02B: bipush 106 (0x6A)
		// @02D: invokevirtual game.C_100202_qi.func_105899_c(int)game.C_100158_da
		// @030: checkcast game.C_100179_ch
		// @033: astore_1
		// @034: aconst_null
		// @035: aload_1
		// @036: if_acmpeq @068
		// @039: aload_1
		// @03A: getfield game.C_100158_da game.C_100179_ch.field_100817_k
		// @03D: sipush 31025 (0x7931)
		// @040: invokevirtual game.C_100158_da.func_100587_d(int)boolean
		// @043: iload_2
		// @044: ifne @0B0
		// @047: ifne @058
		// @04A: goto @04E
		// @04D: athrow
		// @04E: aload_1
		// @04F: bipush 45 (0x2D)
		// @051: invokevirtual game.C_100179_ch.func_100583_c(int)void
		// @054: goto @058
		// @057: athrow
		// @058: getstatic game.C_100202_qi game.C_100226_ae.field_106148_d
		// @05B: bipush 52 (0x34)
		// @05D: invokevirtual game.C_100202_qi.func_105907_c(byte)game.C_100158_da
		// @060: checkcast game.C_100179_ch
		// @063: astore_1
		// @064: iload_2
		// @065: ifeq @034
		// @068: aconst_null
		// @069: getstatic game.C_100202_qi game.C_100205_qf.field_103680_b
		// @06C: if_acmpeq @0AF
		// @06F: getstatic game.C_100202_qi game.C_100205_qf.field_103680_b
		// @072: bipush 68 (0x44)
		// @074: invokevirtual game.C_100202_qi.func_105899_c(int)game.C_100158_da
		// @077: checkcast game.C_100179_ch
		// @07A: astore_1
		// @07B: aconst_null
		// @07C: aload_1
		// @07D: if_acmpeq @0AF
		// @080: aload_1
		// @081: getfield game.C_100158_da game.C_100179_ch.field_100817_k
		// @084: sipush 31025 (0x7931)
		// @087: invokevirtual game.C_100158_da.func_100587_d(int)boolean
		// @08A: iload_2
		// @08B: ifne @0B0
		// @08E: ifne @09F
		// @091: goto @095
		// @094: athrow
		// @095: aload_1
		// @096: bipush 45 (0x2D)
		// @098: invokevirtual game.C_100179_ch.func_100583_c(int)void
		// @09B: goto @09F
		// @09E: athrow
		// @09F: getstatic game.C_100202_qi game.C_100205_qf.field_103680_b
		// @0A2: bipush 75 (0x4B)
		// @0A4: invokevirtual game.C_100202_qi.func_105907_c(byte)game.C_100158_da
		// @0A7: checkcast game.C_100179_ch
		// @0AA: astore_1
		// @0AB: iload_2
		// @0AC: ifeq @07B
		// @0AF: iload_0
		// @0B0: bipush 52 (0x34)
		// @0B2: if_icmpgt @0BE
		// @0B5: bipush -106 (0x96)
		// @0B7: invokestatic game.C_100292_jk.func_101210_f(int)void
		// @0BA: goto @0BE
		// @0BD: athrow
		// @0BE: aconst_null
		// @0BF: getstatic game.C_100210_qa game.C_100004_gb.field_103576_k
		// @0C2: if_acmpeq @0DC
		// @0C5: getstatic game.C_100210_qa game.C_100004_gb.field_103576_k
		// @0C8: bipush -127 (0x81)
		// @0CA: invokevirtual game.C_100210_qa.func_101043_f(int)boolean
		// @0CD: ifeq @0D8
		// @0D0: goto @0D4
		// @0D3: athrow
		// @0D4: goto @0DC
		// @0D7: athrow
		// @0D8: aconst_null
		// @0D9: putstatic game.C_100002_gf game.C_100235_om.field_106292_a
		// @0DC: goto @101
		// @0DF: astore_1
		// @0E0: aload_1
		// @0E1: new java.lang.StringBuilder
		// @0E4: dup
		// @0E5: invokespecial java.lang.StringBuilder.<init>()void
		// @0E8: getstatic java.lang.String[] game.C_100292_jk.field_101223_z
		// @0EB: bipush 6 (0x06)
		// @0ED: aaload
		// @0EE: invokevirtual java.lang.StringBuilder.append(java.lang.String)java.lang.StringBuilder
		// @0F1: iload_0
		// @0F2: invokevirtual java.lang.StringBuilder.append(int)java.lang.StringBuilder
		// @0F5: bipush 41 (0x29)
		// @0F7: invokevirtual java.lang.StringBuilder.append(char)java.lang.StringBuilder
		// @0FA: invokevirtual java.lang.StringBuilder.toString()java.lang.String
		// @0FD: invokestatic game.C_100181_cf.func_105695_a(java.lang.Throwable, java.lang.String)game.C_100170_cm
		// @100: athrow
		// @101: return
	}
	
	static
	{
		// @00: bipush 7 (0x07)
		// @02: anewarray java.lang.String
		// @05: dup
		// @06: iconst_0
		// @07: ldc "u\"\u0019X"
		// @09: invokestatic game.C_100292_jk.func_101208_z(java.lang.String)char[]
		// @0C: invokestatic game.C_100292_jk.func_101207_z(char[])java.lang.String
		// @0F: aastore
		// @10: dup
		// @11: iconst_1
		// @12: ldc "q<[p_"
		// @14: invokestatic game.C_100292_jk.func_101208_z(java.lang.String)char[]
		// @17: invokestatic game.C_100292_jk.func_101207_z(char[])java.lang.String
		// @1A: aastore
		// @1B: dup
		// @1C: iconst_2
		// @1D: ldc "`y[\u001a\n"
		// @1F: invokestatic game.C_100292_jk.func_101208_z(java.lang.String)char[]
		// @22: invokestatic game.C_100292_jk.func_101207_z(char[])java.lang.String
		// @25: aastore
		// @26: dup
		// @27: iconst_3
		// @28: ldc "q<[\u0008\u001eu>\u0001\n_"
		// @2A: invokestatic game.C_100292_jk.func_101208_z(java.lang.String)char[]
		// @2D: invokestatic game.C_100292_jk.func_101207_z(char[])java.lang.String
		// @30: aastore
		// @31: dup
		// @32: iconst_4
		// @33: ldc "q<[w_"
		// @35: invokestatic game.C_100292_jk.func_101208_z(java.lang.String)char[]
		// @38: invokestatic game.C_100292_jk.func_101207_z(char[])java.lang.String
		// @3B: aastore
		// @3C: dup
		// @3D: iconst_5
		// @3E: ldc "q<[u_"
		// @40: invokestatic game.C_100292_jk.func_101208_z(java.lang.String)char[]
		// @43: invokestatic game.C_100292_jk.func_101207_z(char[])java.lang.String
		// @46: aastore
		// @47: dup
		// @48: bipush 6 (0x06)
		// @4A: ldc "q<[v_"
		// @4C: invokestatic game.C_100292_jk.func_101208_z(java.lang.String)char[]
		// @4F: invokestatic game.C_100292_jk.func_101207_z(char[])java.lang.String
		// @52: aastore
		// @53: putstatic java.lang.String[] game.C_100292_jk.field_101223_z
		// @56: iconst_3
		// @57: newarray char[]
		// @59: dup
		// @5A: iconst_0
		// @5B: bipush 91 (0x5B)
		// @5D: castore
		// @5E: dup
		// @5F: iconst_1
		// @60: bipush 93 (0x5D)
		// @62: castore
		// @63: dup
		// @64: iconst_2
		// @65: bipush 35 (0x23)
		// @67: castore
		// @68: putstatic char[] game.C_100292_jk.field_101218_n
		// @6B: return
	}
	
	private static char[] func_101208_z(String arg0)
	{
		// @00: aload_0
		// @01: invokevirtual java.lang.String.toCharArray()char[]
		// @04: dup
		// @05: arraylength
		// @06: iconst_2
		// @07: if_icmpge @13
		// @0A: dup
		// @0B: iconst_0
		// @0C: dup2
		// @0D: caload
		// @0E: bipush 119 (0x77)
		// @10: ixor
		// @11: i2c
		// @12: castore
		// @13: areturn
	}
	
	private static String func_101207_z(char[] arg0)
	{
		// @00: aload_0
		// @01: dup
		// @02: arraylength
		// @03: swap
		// @04: iconst_0
		// @05: istore_1
		// @06: goto @4C
		// @09: dup
		// @0A: iload_1
		// @0B: dup2
		// @0C: caload
		// @0D: iload_1
		// @0E: iconst_5
		// @0F: irem
		// @10: tableswitch def: @44, for 0: @30, for 1: @35, for 2: @3A, for 3: @3F
		// @30: bipush 27 (0x1B)
		// @32: goto @46
		// @35: bipush 87 (0x57)
		// @37: goto @46
		// @3A: bipush 117 (0x75)
		// @3C: goto @46
		// @3F: bipush 52 (0x34)
		// @41: goto @46
		// @44: bipush 119 (0x77)
		// @46: ixor
		// @47: i2c
		// @48: castore
		// @49: iinc #1 +1
		// @4C: swap
		// @4D: dup_x1
		// @4E: iload_1
		// @4F: if_icmpgt @09
		// @52: new java.lang.String
		// @55: dup_x1
		// @56: swap
		// @57: invokespecial java.lang.String.<init>(char[])void
		// @5A: invokevirtual java.lang.String.intern()java.lang.String
		// @5D: areturn
	}
}
