package game;

import java.awt.Component;

final class C_100172_ck extends C_100302_ka
{
	int field_102113_Xb;
	static String field_102122_cc;
	static C_100217_ao field_102110_dc;
	static int field_102116_fc;
	private C_100302_ka field_102119_Vb;
	static String field_102118_Ub;
	private C_100302_ka[] field_102112_Zb;
	private C_100302_ka[] field_102120_ac;
	static boolean field_102115_ec;
	static String field_102121_bc;
	static String field_102114_Yb;
	static boolean field_102117_Wb;
	private static final String[] field_102111_gc;
	
	public static void func_102107_f(byte arg0)
	{
		// @00: iload_0
		// @01: bipush -101 (0x9B)
		// @03: if_icmpeq @11
		// @06: aconst_null
		// @07: checkcast java.lang.String
		// @0A: putstatic java.lang.String game.C_100172_ck.field_102122_cc
		// @0D: goto @11
		// @10: athrow
		// @11: aconst_null
		// @12: putstatic java.lang.String game.C_100172_ck.field_102122_cc
		// @15: aconst_null
		// @16: putstatic game.C_100217_ao game.C_100172_ck.field_102110_dc
		// @19: aconst_null
		// @1A: putstatic java.lang.String game.C_100172_ck.field_102118_Ub
		// @1D: aconst_null
		// @1E: putstatic java.lang.String game.C_100172_ck.field_102121_bc
		// @21: aconst_null
		// @22: putstatic java.lang.String game.C_100172_ck.field_102114_Yb
		// @25: goto @49
		// @28: astore_1
		// @29: aload_1
		// @2A: new java.lang.StringBuilder
		// @2D: dup
		// @2E: invokespecial java.lang.StringBuilder.<init>()void
		// @31: getstatic java.lang.String[] game.C_100172_ck.field_102111_gc
		// @34: iconst_0
		// @35: aaload
		// @36: invokevirtual java.lang.StringBuilder.append(java.lang.String)java.lang.StringBuilder
		// @39: iload_0
		// @3A: invokevirtual java.lang.StringBuilder.append(int)java.lang.StringBuilder
		// @3D: bipush 41 (0x29)
		// @3F: invokevirtual java.lang.StringBuilder.append(char)java.lang.StringBuilder
		// @42: invokevirtual java.lang.StringBuilder.toString()java.lang.String
		// @45: invokestatic game.C_100181_cf.func_105695_a(java.lang.Throwable, java.lang.String)game.C_100170_cm
		// @48: athrow
		// @49: return
	}
	
	private final void func_102108_a(int arg0, int arg1, int arg2)
	{
		// @000: getstatic int game.SteelSentinels.field_105275_O
		// @003: istore #7
		// @005: iconst_0
		// @006: istore #4
		// @008: iload #4
		// @00A: aload_0
		// @00B: getfield game.C_100302_ka[] game.C_100172_ck.field_102112_Zb
		// @00E: arraylength
		// @00F: if_icmpge @075
		// @012: aload_0
		// @013: getfield int game.C_100172_ck.field_101886_Kb
		// @016: iload #4
		// @018: imul
		// @019: aload_0
		// @01A: getfield game.C_100302_ka[] game.C_100172_ck.field_102112_Zb
		// @01D: arraylength
		// @01E: idiv
		// @01F: istore #5
		// @021: iconst_1
		// @022: iload #4
		// @024: iadd
		// @025: aload_0
		// @026: getfield int game.C_100172_ck.field_101886_Kb
		// @029: imul
		// @02A: aload_0
		// @02B: getfield game.C_100302_ka[] game.C_100172_ck.field_102112_Zb
		// @02E: arraylength
		// @02F: idiv
		// @030: istore #6
		// @032: aload_0
		// @033: getfield game.C_100302_ka[] game.C_100172_ck.field_102112_Zb
		// @036: iload #4
		// @038: aaload
		// @039: iload #5
		// @03B: putfield int game.C_100302_ka.field_101841_Pb
		// @03E: aload_0
		// @03F: getfield game.C_100302_ka[] game.C_100172_ck.field_102112_Zb
		// @042: iload #4
		// @044: aaload
		// @045: iconst_0
		// @046: putfield int game.C_100302_ka.field_101880_Gb
		// @049: aload_0
		// @04A: getfield game.C_100302_ka[] game.C_100172_ck.field_102112_Zb
		// @04D: iload #4
		// @04F: aaload
		// @050: iload #6
		// @052: iload #5
		// @054: ineg
		// @055: iadd
		// @056: putfield int game.C_100302_ka.field_101886_Kb
		// @059: aload_0
		// @05A: getfield game.C_100302_ka[] game.C_100172_ck.field_102112_Zb
		// @05D: iload #4
		// @05F: aaload
		// @060: iload_3
		// @061: putfield int game.C_100302_ka.field_101848_lb
		// @064: iinc #4 +1
		// @067: iload #7
		// @069: ifne @08A
		// @06C: iload #7
		// @06E: ifeq @008
		// @071: goto @075
		// @074: athrow
		// @075: aload_0
		// @076: getfield game.C_100302_ka game.C_100172_ck.field_102119_Vb
		// @079: iconst_0
		// @07A: aload_0
		// @07B: getfield int game.C_100172_ck.field_101848_lb
		// @07E: iload_3
		// @07F: ineg
		// @080: iadd
		// @081: iconst_m1
		// @082: iload_3
		// @083: aload_0
		// @084: getfield int game.C_100172_ck.field_101886_Kb
		// @087: invokevirtual game.C_100302_ka.func_101825_a(int, int, int, int, int)void
		// @08A: iconst_0
		// @08B: istore #4
		// @08D: aload_0
		// @08E: getfield game.C_100302_ka[] game.C_100172_ck.field_102120_ac
		// @091: arraylength
		// @092: iload #4
		// @094: if_icmple @0EE
		// @097: aload_0
		// @098: getfield game.C_100302_ka[] game.C_100172_ck.field_102120_ac
		// @09B: iload #4
		// @09D: aaload
		// @09E: iload_2
		// @09F: iload_2
		// @0A0: iconst_2
		// @0A1: imul
		// @0A2: ineg
		// @0A3: aload_0
		// @0A4: getfield game.C_100302_ka game.C_100172_ck.field_102119_Vb
		// @0A7: getfield int game.C_100302_ka.field_101848_lb
		// @0AA: iadd
		// @0AB: iconst_m1
		// @0AC: iload_2
		// @0AD: aload_0
		// @0AE: getfield game.C_100302_ka game.C_100172_ck.field_102119_Vb
		// @0B1: getfield int game.C_100302_ka.field_101886_Kb
		// @0B4: iconst_2
		// @0B5: iload_2
		// @0B6: imul
		// @0B7: isub
		// @0B8: invokevirtual game.C_100302_ka.func_101825_a(int, int, int, int, int)void
		// @0BB: iload #4
		// @0BD: iconst_m1
		// @0BE: ixor
		// @0BF: aload_0
		// @0C0: getfield int game.C_100172_ck.field_102113_Xb
		// @0C3: iconst_m1
		// @0C4: ixor
		// @0C5: iload #7
		// @0C7: ifne @0F1
		// @0CA: if_icmpne @0D4
		// @0CD: goto @0D1
		// @0D0: athrow
		// @0D1: goto @0E6
		// @0D4: aload_0
		// @0D5: getfield game.C_100302_ka[] game.C_100172_ck.field_102120_ac
		// @0D8: iload #4
		// @0DA: aaload
		// @0DB: dup
		// @0DC: getfield int game.C_100302_ka.field_101841_Pb
		// @0DF: sipush 10000 (0x2710)
		// @0E2: iadd
		// @0E3: putfield int game.C_100302_ka.field_101841_Pb
		// @0E6: iinc #4 +1
		// @0E9: iload #7
		// @0EB: ifeq @08D
		// @0EE: iload_1
		// @0EF: bipush 41 (0x29)
		// @0F1: if_icmpge @0FE
		// @0F4: bipush 6 (0x06)
		// @0F6: iconst_1
		// @0F7: invokestatic game.C_100172_ck.func_102109_a(int, boolean)void
		// @0FA: goto @0FE
		// @0FD: athrow
		// @0FE: goto @137
		// @101: astore #4
		// @103: aload #4
		// @105: new java.lang.StringBuilder
		// @108: dup
		// @109: invokespecial java.lang.StringBuilder.<init>()void
		// @10C: getstatic java.lang.String[] game.C_100172_ck.field_102111_gc
		// @10F: bipush 9 (0x09)
		// @111: aaload
		// @112: invokevirtual java.lang.StringBuilder.append(java.lang.String)java.lang.StringBuilder
		// @115: iload_1
		// @116: invokevirtual java.lang.StringBuilder.append(int)java.lang.StringBuilder
		// @119: bipush 44 (0x2C)
		// @11B: invokevirtual java.lang.StringBuilder.append(char)java.lang.StringBuilder
		// @11E: iload_2
		// @11F: invokevirtual java.lang.StringBuilder.append(int)java.lang.StringBuilder
		// @122: bipush 44 (0x2C)
		// @124: invokevirtual java.lang.StringBuilder.append(char)java.lang.StringBuilder
		// @127: iload_3
		// @128: invokevirtual java.lang.StringBuilder.append(int)java.lang.StringBuilder
		// @12B: bipush 41 (0x29)
		// @12D: invokevirtual java.lang.StringBuilder.append(char)java.lang.StringBuilder
		// @130: invokevirtual java.lang.StringBuilder.toString()java.lang.String
		// @133: invokestatic game.C_100181_cf.func_105695_a(java.lang.Throwable, java.lang.String)game.C_100170_cm
		// @136: athrow
		// @137: return
	}
	
	static final void func_102105_m(int arg0)
	{
		// @00: getstatic game.C_100302_ka game.C_100032_gk.field_103137_ab
		// @03: iconst_0
		// @04: bipush 18 (0x12)
		// @06: iconst_m1
		// @07: iconst_0
		// @08: getstatic boolean game.C_100273_mm.field_106682_e
		// @0B: ifeq @1A
		// @0E: bipush 40 (0x28)
		// @10: getstatic int game.C_100099_fb.field_103046_u
		// @13: iadd
		// @14: iconst_4
		// @15: iadd
		// @16: goto @1B
		// @19: athrow
		// @1A: iconst_0
		// @1B: ineg
		// @1C: getstatic game.C_100302_ka game.C_100099_fb.field_103050_z
		// @1F: getfield int game.C_100302_ka.field_101886_Kb
		// @22: iadd
		// @23: invokevirtual game.C_100302_ka.func_101825_a(int, int, int, int, int)void
		// @26: getstatic game.C_100302_ka game.C_100249_pc.field_102336_v
		// @29: getstatic int game.C_100099_fb.field_103046_u
		// @2C: ineg
		// @2D: getstatic game.C_100302_ka game.C_100099_fb.field_103050_z
		// @30: getfield int game.C_100302_ka.field_101886_Kb
		// @33: iadd
		// @34: iload_0
		// @35: iadd
		// @36: bipush -40 (0xD8)
		// @38: iadd
		// @39: bipush 18 (0x12)
		// @3B: iload_0
		// @3C: iconst_1
		// @3D: ixor
		// @3E: iconst_0
		// @3F: bipush 42 (0x2A)
		// @41: getstatic int game.C_100099_fb.field_103046_u
		// @44: iadd
		// @45: invokevirtual game.C_100302_ka.func_101825_a(int, int, int, int, int)void
		// @48: getstatic game.C_100115_ej game.C_100179_ch.field_100811_n
		// @4B: iconst_2
		// @4C: bipush -20 (0xEC)
		// @4E: getstatic game.C_100302_ka game.C_100099_fb.field_103050_z
		// @51: getfield int game.C_100302_ka.field_101848_lb
		// @54: iadd
		// @55: iconst_0
		// @56: iconst_0
		// @57: getstatic game.C_100302_ka game.C_100099_fb.field_103050_z
		// @5A: getfield int game.C_100302_ka.field_101886_Kb
		// @5D: bipush 20 (0x14)
		// @5F: getstatic int game.C_100099_fb.field_103046_u
		// @62: invokevirtual game.C_100115_ej.func_102030_a(int, int, int, int, int, int, int)void
		// @65: goto @89
		// @68: astore_1
		// @69: aload_1
		// @6A: new java.lang.StringBuilder
		// @6D: dup
		// @6E: invokespecial java.lang.StringBuilder.<init>()void
		// @71: getstatic java.lang.String[] game.C_100172_ck.field_102111_gc
		// @74: iconst_3
		// @75: aaload
		// @76: invokevirtual java.lang.StringBuilder.append(java.lang.String)java.lang.StringBuilder
		// @79: iload_0
		// @7A: invokevirtual java.lang.StringBuilder.append(int)java.lang.StringBuilder
		// @7D: bipush 41 (0x29)
		// @7F: invokevirtual java.lang.StringBuilder.append(char)java.lang.StringBuilder
		// @82: invokevirtual java.lang.StringBuilder.toString()java.lang.String
		// @85: invokestatic game.C_100181_cf.func_105695_a(java.lang.Throwable, java.lang.String)game.C_100170_cm
		// @88: athrow
		// @89: return
	}
	
	static final void func_102100_a(int arg0, Component arg1)
	{
		// @00: aload_1
		// @01: getstatic game.C_100323_hl game.C_100264_mg.field_106528_i
		// @04: invokevirtual java.awt.Component.removeKeyListener(java.awt.event.KeyListener)void
		// @07: aload_1
		// @08: getstatic game.C_100323_hl game.C_100264_mg.field_106528_i
		// @0B: invokevirtual java.awt.Component.removeFocusListener(java.awt.event.FocusListener)void
		// @0E: iload_0
		// @0F: putstatic int game.C_100186_rl.field_105724_b
		// @12: goto @52
		// @15: astore_2
		// @16: aload_2
		// @17: new java.lang.StringBuilder
		// @1A: dup
		// @1B: invokespecial java.lang.StringBuilder.<init>()void
		// @1E: getstatic java.lang.String[] game.C_100172_ck.field_102111_gc
		// @21: bipush 11 (0x0B)
		// @23: aaload
		// @24: invokevirtual java.lang.StringBuilder.append(java.lang.String)java.lang.StringBuilder
		// @27: iload_0
		// @28: invokevirtual java.lang.StringBuilder.append(int)java.lang.StringBuilder
		// @2B: bipush 44 (0x2C)
		// @2D: invokevirtual java.lang.StringBuilder.append(char)java.lang.StringBuilder
		// @30: aload_1
		// @31: ifnull @3D
		// @34: getstatic java.lang.String[] game.C_100172_ck.field_102111_gc
		// @37: iconst_4
		// @38: aaload
		// @39: goto @43
		// @3C: athrow
		// @3D: getstatic java.lang.String[] game.C_100172_ck.field_102111_gc
		// @40: bipush 6 (0x06)
		// @42: aaload
		// @43: invokevirtual java.lang.StringBuilder.append(java.lang.String)java.lang.StringBuilder
		// @46: bipush 41 (0x29)
		// @48: invokevirtual java.lang.StringBuilder.append(char)java.lang.StringBuilder
		// @4B: invokevirtual java.lang.StringBuilder.toString()java.lang.String
		// @4E: invokestatic game.C_100181_cf.func_105695_a(java.lang.Throwable, java.lang.String)game.C_100170_cm
		// @51: athrow
		// @52: return
	}
	
	static final boolean func_102103_l(int arg0)
	{
		// @00: iload_0
		// @01: sipush 29613 (0x73AD)
		// @04: if_icmpeq @11
		// @07: bipush -59 (0xC5)
		// @09: iconst_1
		// @0A: invokestatic game.C_100172_ck.func_102109_a(int, boolean)void
		// @0D: goto @11
		// @10: athrow
		// @11: getstatic int game.C_100015_wh.field_103783_e
		// @14: sipush 250 (0x00FA)
		// @17: if_icmple @1F
		// @1A: iconst_1
		// @1B: goto @20
		// @1E: athrow
		// @1F: iconst_0
		// @20: ireturn
		// @21: astore_1
		// @22: aload_1
		// @23: new java.lang.StringBuilder
		// @26: dup
		// @27: invokespecial java.lang.StringBuilder.<init>()void
		// @2A: getstatic java.lang.String[] game.C_100172_ck.field_102111_gc
		// @2D: bipush 10 (0x0A)
		// @2F: aaload
		// @30: invokevirtual java.lang.StringBuilder.append(java.lang.String)java.lang.StringBuilder
		// @33: iload_0
		// @34: invokevirtual java.lang.StringBuilder.append(int)java.lang.StringBuilder
		// @37: bipush 41 (0x29)
		// @39: invokevirtual java.lang.StringBuilder.append(char)java.lang.StringBuilder
		// @3C: invokevirtual java.lang.StringBuilder.toString()java.lang.String
		// @3F: invokestatic game.C_100181_cf.func_105695_a(java.lang.Throwable, java.lang.String)game.C_100170_cm
		// @42: athrow
	}
	
	final void func_102102_a(int arg0, int arg1, int arg2, int arg3, int arg4, int arg5, int arg6)
	{
		// @00: aload_0
		// @01: iload_2
		// @02: putfield int game.C_100172_ck.field_101841_Pb
		// @05: aload_0
		// @06: iload_3
		// @07: putfield int game.C_100172_ck.field_101880_Gb
		// @0A: iload #4
		// @0C: sipush 10250 (0x280A)
		// @0F: if_icmpeq @1B
		// @12: bipush -113 (0x8F)
		// @14: putstatic int game.C_100172_ck.field_102116_fc
		// @17: goto @1B
		// @1A: athrow
		// @1B: aload_0
		// @1C: iload_1
		// @1D: putfield int game.C_100172_ck.field_101886_Kb
		// @20: aload_0
		// @21: iload #7
		// @23: putfield int game.C_100172_ck.field_101848_lb
		// @26: aload_0
		// @27: iload #4
		// @29: sipush -10147 (0xD85D)
		// @2C: iadd
		// @2D: iload #6
		// @2F: iload #5
		// @31: invokespecial game.C_100172_ck.func_102108_a(int, int, int)void
		// @34: goto @94
		// @37: astore #8
		// @39: aload #8
		// @3B: new java.lang.StringBuilder
		// @3E: dup
		// @3F: invokespecial java.lang.StringBuilder.<init>()void
		// @42: getstatic java.lang.String[] game.C_100172_ck.field_102111_gc
		// @45: iconst_2
		// @46: aaload
		// @47: invokevirtual java.lang.StringBuilder.append(java.lang.String)java.lang.StringBuilder
		// @4A: iload_1
		// @4B: invokevirtual java.lang.StringBuilder.append(int)java.lang.StringBuilder
		// @4E: bipush 44 (0x2C)
		// @50: invokevirtual java.lang.StringBuilder.append(char)java.lang.StringBuilder
		// @53: iload_2
		// @54: invokevirtual java.lang.StringBuilder.append(int)java.lang.StringBuilder
		// @57: bipush 44 (0x2C)
		// @59: invokevirtual java.lang.StringBuilder.append(char)java.lang.StringBuilder
		// @5C: iload_3
		// @5D: invokevirtual java.lang.StringBuilder.append(int)java.lang.StringBuilder
		// @60: bipush 44 (0x2C)
		// @62: invokevirtual java.lang.StringBuilder.append(char)java.lang.StringBuilder
		// @65: iload #4
		// @67: invokevirtual java.lang.StringBuilder.append(int)java.lang.StringBuilder
		// @6A: bipush 44 (0x2C)
		// @6C: invokevirtual java.lang.StringBuilder.append(char)java.lang.StringBuilder
		// @6F: iload #5
		// @71: invokevirtual java.lang.StringBuilder.append(int)java.lang.StringBuilder
		// @74: bipush 44 (0x2C)
		// @76: invokevirtual java.lang.StringBuilder.append(char)java.lang.StringBuilder
		// @79: iload #6
		// @7B: invokevirtual java.lang.StringBuilder.append(int)java.lang.StringBuilder
		// @7E: bipush 44 (0x2C)
		// @80: invokevirtual java.lang.StringBuilder.append(char)java.lang.StringBuilder
		// @83: iload #7
		// @85: invokevirtual java.lang.StringBuilder.append(int)java.lang.StringBuilder
		// @88: bipush 41 (0x29)
		// @8A: invokevirtual java.lang.StringBuilder.append(char)java.lang.StringBuilder
		// @8D: invokevirtual java.lang.StringBuilder.toString()java.lang.String
		// @90: invokestatic game.C_100181_cf.func_105695_a(java.lang.Throwable, java.lang.String)game.C_100170_cm
		// @93: athrow
		// @94: return
	}
	
	static final void func_102109_a(int arg0, boolean arg1)
	{
		// @00: iload_0
		// @01: bipush 35 (0x23)
		// @03: if_icmpgt @07
		// @06: return
		// @07: getstatic game.C_100321_hi game.C_100106_ef.field_104753_e
		// @0A: bipush 123 (0x7B)
		// @0C: iload_1
		// @0D: invokevirtual game.C_100321_hi.func_107214_a(int, boolean)void
		// @10: goto @3D
		// @13: astore_2
		// @14: aload_2
		// @15: new java.lang.StringBuilder
		// @18: dup
		// @19: invokespecial java.lang.StringBuilder.<init>()void
		// @1C: getstatic java.lang.String[] game.C_100172_ck.field_102111_gc
		// @1F: iconst_1
		// @20: aaload
		// @21: invokevirtual java.lang.StringBuilder.append(java.lang.String)java.lang.StringBuilder
		// @24: iload_0
		// @25: invokevirtual java.lang.StringBuilder.append(int)java.lang.StringBuilder
		// @28: bipush 44 (0x2C)
		// @2A: invokevirtual java.lang.StringBuilder.append(char)java.lang.StringBuilder
		// @2D: iload_1
		// @2E: invokevirtual java.lang.StringBuilder.append(boolean)java.lang.StringBuilder
		// @31: bipush 41 (0x29)
		// @33: invokevirtual java.lang.StringBuilder.append(char)java.lang.StringBuilder
		// @36: invokevirtual java.lang.StringBuilder.toString()java.lang.String
		// @39: invokestatic game.C_100181_cf.func_105695_a(java.lang.Throwable, java.lang.String)game.C_100170_cm
		// @3C: athrow
		// @3D: return
	}
	
	static final short[] func_102106_a(int arg0, int arg1, short[] arg2, C_100278_nd arg3)
	{
		// @000: getstatic int game.SteelSentinels.field_105275_O
		// @003: istore #9
		// @005: aload_3
		// @006: iload_0
		// @007: sipush 15738 (0x3D7A)
		// @00A: invokevirtual game.C_100278_nd.func_101195_i(int, int)int
		// @00D: istore #4
		// @00F: iload #4
		// @011: ifeq @018
		// @014: goto @01A
		// @017: athrow
		// @018: aconst_null
		// @019: areturn
		// @01A: aload_2
		// @01B: ifnull @031
		// @01E: iload #4
		// @020: iconst_m1
		// @021: ixor
		// @022: aload_2
		// @023: arraylength
		// @024: iconst_m1
		// @025: ixor
		// @026: if_icmpne @031
		// @029: goto @02D
		// @02C: athrow
		// @02D: goto @036
		// @030: athrow
		// @031: iload #4
		// @033: newarray short[]
		// @035: astore_2
		// @036: aload_3
		// @037: iconst_4
		// @038: sipush 15738 (0x3D7A)
		// @03B: invokevirtual game.C_100278_nd.func_101195_i(int, int)int
		// @03E: istore #5
		// @040: bipush 85 (0x55)
		// @042: iload_1
		// @043: bipush 65 (0x41)
		// @045: isub
		// @046: bipush 50 (0x32)
		// @048: idiv
		// @049: irem
		// @04A: istore #7
		// @04C: aload_3
		// @04D: bipush 16 (0x10)
		// @04F: sipush 15738 (0x3D7A)
		// @052: invokevirtual game.C_100278_nd.func_101195_i(int, int)int
		// @055: i2s
		// @056: istore #6
		// @058: iload #5
		// @05A: ifle @092
		// @05D: iconst_0
		// @05E: istore #8
		// @060: iload #4
		// @062: iconst_m1
		// @063: ixor
		// @064: iload #8
		// @066: iconst_m1
		// @067: ixor
		// @068: if_icmpge @08D
		// @06B: aload_2
		// @06C: iload #8
		// @06E: aload_3
		// @06F: iload #5
		// @071: sipush 15738 (0x3D7A)
		// @074: invokevirtual game.C_100278_nd.func_101195_i(int, int)int
		// @077: iload #6
		// @079: iadd
		// @07A: i2s
		// @07B: sastore
		// @07C: iinc #8 +1
		// @07F: iload #9
		// @081: ifne @0B3
		// @084: iload #9
		// @086: ifeq @060
		// @089: goto @08D
		// @08C: athrow
		// @08D: iload #9
		// @08F: ifeq @0B3
		// @092: iconst_0
		// @093: istore #8
		// @095: iload #4
		// @097: iload #8
		// @099: if_icmple @0B3
		// @09C: aload_2
		// @09D: iload #9
		// @09F: ifne @0B4
		// @0A2: iload #8
		// @0A4: iload #6
		// @0A6: sastore
		// @0A7: iinc #8 +1
		// @0AA: iload #9
		// @0AC: ifeq @095
		// @0AF: goto @0B3
		// @0B2: athrow
		// @0B3: aload_2
		// @0B4: areturn
		// @0B5: astore #4
		// @0B7: aload #4
		// @0B9: new java.lang.StringBuilder
		// @0BC: dup
		// @0BD: invokespecial java.lang.StringBuilder.<init>()void
		// @0C0: getstatic java.lang.String[] game.C_100172_ck.field_102111_gc
		// @0C3: bipush 7 (0x07)
		// @0C5: aaload
		// @0C6: invokevirtual java.lang.StringBuilder.append(java.lang.String)java.lang.StringBuilder
		// @0C9: iload_0
		// @0CA: invokevirtual java.lang.StringBuilder.append(int)java.lang.StringBuilder
		// @0CD: bipush 44 (0x2C)
		// @0CF: invokevirtual java.lang.StringBuilder.append(char)java.lang.StringBuilder
		// @0D2: iload_1
		// @0D3: invokevirtual java.lang.StringBuilder.append(int)java.lang.StringBuilder
		// @0D6: bipush 44 (0x2C)
		// @0D8: invokevirtual java.lang.StringBuilder.append(char)java.lang.StringBuilder
		// @0DB: aload_2
		// @0DC: ifnull @0E8
		// @0DF: getstatic java.lang.String[] game.C_100172_ck.field_102111_gc
		// @0E2: iconst_4
		// @0E3: aaload
		// @0E4: goto @0EE
		// @0E7: athrow
		// @0E8: getstatic java.lang.String[] game.C_100172_ck.field_102111_gc
		// @0EB: bipush 6 (0x06)
		// @0ED: aaload
		// @0EE: invokevirtual java.lang.StringBuilder.append(java.lang.String)java.lang.StringBuilder
		// @0F1: bipush 44 (0x2C)
		// @0F3: invokevirtual java.lang.StringBuilder.append(char)java.lang.StringBuilder
		// @0F6: aload_3
		// @0F7: ifnull @103
		// @0FA: getstatic java.lang.String[] game.C_100172_ck.field_102111_gc
		// @0FD: iconst_4
		// @0FE: aaload
		// @0FF: goto @109
		// @102: athrow
		// @103: getstatic java.lang.String[] game.C_100172_ck.field_102111_gc
		// @106: bipush 6 (0x06)
		// @108: aaload
		// @109: invokevirtual java.lang.StringBuilder.append(java.lang.String)java.lang.StringBuilder
		// @10C: bipush 41 (0x29)
		// @10E: invokevirtual java.lang.StringBuilder.append(char)java.lang.StringBuilder
		// @111: invokevirtual java.lang.StringBuilder.toString()java.lang.String
		// @114: invokestatic game.C_100181_cf.func_105695_a(java.lang.Throwable, java.lang.String)game.C_100170_cm
		// @117: athrow
	}
	
	final void func_102099_b(boolean arg0)
	{
		// @00: getstatic int game.SteelSentinels.field_105275_O
		// @03: istore_3
		// @04: iconst_0
		// @05: istore_2
		// @06: iload_2
		// @07: aload_0
		// @08: getfield game.C_100302_ka[] game.C_100172_ck.field_102112_Zb
		// @0B: arraylength
		// @0C: if_icmpge @80
		// @0F: aload_0
		// @10: getfield int game.C_100172_ck.field_102113_Xb
		// @13: iconst_m1
		// @14: ixor
		// @15: iload_3
		// @16: ifne @81
		// @19: iload_2
		// @1A: iconst_m1
		// @1B: ixor
		// @1C: if_icmpeq @79
		// @1F: goto @23
		// @22: athrow
		// @23: iconst_0
		// @24: aload_0
		// @25: getfield game.C_100302_ka[] game.C_100172_ck.field_102112_Zb
		// @28: iload_2
		// @29: aaload
		// @2A: getfield int game.C_100302_ka.field_101854_N
		// @2D: if_icmpne @38
		// @30: goto @34
		// @33: athrow
		// @34: goto @79
		// @37: athrow
		// @38: aload_0
		// @39: getfield game.C_100302_ka[] game.C_100172_ck.field_102112_Zb
		// @3C: aload_0
		// @3D: getfield int game.C_100172_ck.field_102113_Xb
		// @40: aaload
		// @41: iconst_0
		// @42: putfield boolean game.C_100302_ka.field_101861_U
		// @45: aload_0
		// @46: getfield game.C_100302_ka[] game.C_100172_ck.field_102120_ac
		// @49: aload_0
		// @4A: getfield int game.C_100172_ck.field_102113_Xb
		// @4D: aaload
		// @4E: dup
		// @4F: getfield int game.C_100302_ka.field_101841_Pb
		// @52: sipush 10000 (0x2710)
		// @55: iadd
		// @56: putfield int game.C_100302_ka.field_101841_Pb
		// @59: aload_0
		// @5A: iload_2
		// @5B: putfield int game.C_100172_ck.field_102113_Xb
		// @5E: aload_0
		// @5F: getfield game.C_100302_ka[] game.C_100172_ck.field_102112_Zb
		// @62: iload_2
		// @63: aaload
		// @64: iconst_1
		// @65: putfield boolean game.C_100302_ka.field_101861_U
		// @68: aload_0
		// @69: getfield game.C_100302_ka[] game.C_100172_ck.field_102120_ac
		// @6C: iload_2
		// @6D: aaload
		// @6E: dup
		// @6F: getfield int game.C_100302_ka.field_101841_Pb
		// @72: sipush 10000 (0x2710)
		// @75: isub
		// @76: putfield int game.C_100302_ka.field_101841_Pb
		// @79: iinc #2 +1
		// @7C: iload_3
		// @7D: ifeq @06
		// @80: iload_1
		// @81: ifeq @9A
		// @84: aload_0
		// @85: bipush 37 (0x25)
		// @87: bipush 85 (0x55)
		// @89: bipush -9 (0xF7)
		// @8B: bipush 125 (0x7D)
		// @8D: bipush -128 (0x80)
		// @8F: bipush 20 (0x14)
		// @91: bipush -15 (0xF1)
		// @93: invokevirtual game.C_100172_ck.func_102102_a(int, int, int, int, int, int, int)void
		// @96: goto @9A
		// @99: athrow
		// @9A: goto @BF
		// @9D: astore_2
		// @9E: aload_2
		// @9F: new java.lang.StringBuilder
		// @A2: dup
		// @A3: invokespecial java.lang.StringBuilder.<init>()void
		// @A6: getstatic java.lang.String[] game.C_100172_ck.field_102111_gc
		// @A9: bipush 8 (0x08)
		// @AB: aaload
		// @AC: invokevirtual java.lang.StringBuilder.append(java.lang.String)java.lang.StringBuilder
		// @AF: iload_1
		// @B0: invokevirtual java.lang.StringBuilder.append(boolean)java.lang.StringBuilder
		// @B3: bipush 41 (0x29)
		// @B5: invokevirtual java.lang.StringBuilder.append(char)java.lang.StringBuilder
		// @B8: invokevirtual java.lang.StringBuilder.toString()java.lang.String
		// @BB: invokestatic game.C_100181_cf.func_105695_a(java.lang.Throwable, java.lang.String)game.C_100170_cm
		// @BE: athrow
		// @BF: return
	}
	
	C_100172_ck(long arg0, C_100302_ka arg1, String[] arg2, C_100302_ka arg3, C_100302_ka[] arg4, int arg5)
	{
		// @000: getstatic int game.SteelSentinels.field_105275_O
		// @003: istore #10
		// @005: aload_0
		// @006: lload_1
		// @007: aconst_null
		// @008: invokespecial game.C_100302_ka.<init>(long, game.C_100302_ka)void
		// @00B: aload_0
		// @00C: aload #4
		// @00E: arraylength
		// @00F: anewarray game.C_100302_ka
		// @012: putfield game.C_100302_ka[] game.C_100172_ck.field_102112_Zb
		// @015: aload_0
		// @016: new game.C_100302_ka
		// @019: dup
		// @01A: lconst_0
		// @01B: aload #5
		// @01D: invokespecial game.C_100302_ka.<init>(long, game.C_100302_ka)void
		// @020: putfield game.C_100302_ka game.C_100172_ck.field_102119_Vb
		// @023: aload_0
		// @024: aload #6
		// @026: putfield game.C_100302_ka[] game.C_100172_ck.field_102120_ac
		// @029: iconst_0
		// @02A: istore #8
		// @02C: aload #4
		// @02E: arraylength
		// @02F: iconst_m1
		// @030: ixor
		// @031: iload #8
		// @033: iconst_m1
		// @034: ixor
		// @035: if_icmpge @06F
		// @038: new game.C_100302_ka
		// @03B: dup
		// @03C: lconst_0
		// @03D: aload_3
		// @03E: invokespecial game.C_100302_ka.<init>(long, game.C_100302_ka)void
		// @041: astore #9
		// @043: aload #9
		// @045: aload #4
		// @047: iload #8
		// @049: aaload
		// @04A: putfield java.lang.String game.C_100302_ka.field_101890_ab
		// @04D: aload_0
		// @04E: getfield game.C_100302_ka[] game.C_100172_ck.field_102112_Zb
		// @051: iload #8
		// @053: aload #9
		// @055: aastore
		// @056: aload_0
		// @057: bipush -127 (0x81)
		// @059: aload #9
		// @05B: invokevirtual game.C_100172_ck.func_101824_b(int, game.C_100302_ka)void
		// @05E: iinc #8 +1
		// @061: iload #10
		// @063: ifne @079
		// @066: iload #10
		// @068: ifeq @02C
		// @06B: goto @06F
		// @06E: athrow
		// @06F: aload_0
		// @070: bipush -118 (0x8A)
		// @072: aload_0
		// @073: getfield game.C_100302_ka game.C_100172_ck.field_102119_Vb
		// @076: invokevirtual game.C_100172_ck.func_101824_b(int, game.C_100302_ka)void
		// @079: iconst_0
		// @07A: istore #8
		// @07C: aload #6
		// @07E: arraylength
		// @07F: iload #8
		// @081: if_icmple @0A3
		// @084: aload_0
		// @085: getfield game.C_100302_ka game.C_100172_ck.field_102119_Vb
		// @088: bipush -87 (0xA9)
		// @08A: aload #6
		// @08C: iload #8
		// @08E: aaload
		// @08F: invokevirtual game.C_100302_ka.func_101824_b(int, game.C_100302_ka)void
		// @092: iinc #8 +1
		// @095: iload #10
		// @097: ifne @0B4
		// @09A: iload #10
		// @09C: ifeq @07C
		// @09F: goto @0A3
		// @0A2: athrow
		// @0A3: aload_0
		// @0A4: iload #7
		// @0A6: putfield int game.C_100172_ck.field_102113_Xb
		// @0A9: aload_0
		// @0AA: getfield game.C_100302_ka[] game.C_100172_ck.field_102112_Zb
		// @0AD: iload #7
		// @0AF: aaload
		// @0B0: iconst_1
		// @0B1: putfield boolean game.C_100302_ka.field_101861_U
		// @0B4: goto @153
		// @0B7: astore #8
		// @0B9: aload #8
		// @0BB: new java.lang.StringBuilder
		// @0BE: dup
		// @0BF: invokespecial java.lang.StringBuilder.<init>()void
		// @0C2: getstatic java.lang.String[] game.C_100172_ck.field_102111_gc
		// @0C5: iconst_5
		// @0C6: aaload
		// @0C7: invokevirtual java.lang.StringBuilder.append(java.lang.String)java.lang.StringBuilder
		// @0CA: lload_1
		// @0CB: invokevirtual java.lang.StringBuilder.append(long)java.lang.StringBuilder
		// @0CE: bipush 44 (0x2C)
		// @0D0: invokevirtual java.lang.StringBuilder.append(char)java.lang.StringBuilder
		// @0D3: aload_3
		// @0D4: ifnull @0E0
		// @0D7: getstatic java.lang.String[] game.C_100172_ck.field_102111_gc
		// @0DA: iconst_4
		// @0DB: aaload
		// @0DC: goto @0E6
		// @0DF: athrow
		// @0E0: getstatic java.lang.String[] game.C_100172_ck.field_102111_gc
		// @0E3: bipush 6 (0x06)
		// @0E5: aaload
		// @0E6: invokevirtual java.lang.StringBuilder.append(java.lang.String)java.lang.StringBuilder
		// @0E9: bipush 44 (0x2C)
		// @0EB: invokevirtual java.lang.StringBuilder.append(char)java.lang.StringBuilder
		// @0EE: aload #4
		// @0F0: ifnull @0FC
		// @0F3: getstatic java.lang.String[] game.C_100172_ck.field_102111_gc
		// @0F6: iconst_4
		// @0F7: aaload
		// @0F8: goto @102
		// @0FB: athrow
		// @0FC: getstatic java.lang.String[] game.C_100172_ck.field_102111_gc
		// @0FF: bipush 6 (0x06)
		// @101: aaload
		// @102: invokevirtual java.lang.StringBuilder.append(java.lang.String)java.lang.StringBuilder
		// @105: bipush 44 (0x2C)
		// @107: invokevirtual java.lang.StringBuilder.append(char)java.lang.StringBuilder
		// @10A: aload #5
		// @10C: ifnull @118
		// @10F: getstatic java.lang.String[] game.C_100172_ck.field_102111_gc
		// @112: iconst_4
		// @113: aaload
		// @114: goto @11E
		// @117: athrow
		// @118: getstatic java.lang.String[] game.C_100172_ck.field_102111_gc
		// @11B: bipush 6 (0x06)
		// @11D: aaload
		// @11E: invokevirtual java.lang.StringBuilder.append(java.lang.String)java.lang.StringBuilder
		// @121: bipush 44 (0x2C)
		// @123: invokevirtual java.lang.StringBuilder.append(char)java.lang.StringBuilder
		// @126: aload #6
		// @128: ifnull @134
		// @12B: getstatic java.lang.String[] game.C_100172_ck.field_102111_gc
		// @12E: iconst_4
		// @12F: aaload
		// @130: goto @13A
		// @133: athrow
		// @134: getstatic java.lang.String[] game.C_100172_ck.field_102111_gc
		// @137: bipush 6 (0x06)
		// @139: aaload
		// @13A: invokevirtual java.lang.StringBuilder.append(java.lang.String)java.lang.StringBuilder
		// @13D: bipush 44 (0x2C)
		// @13F: invokevirtual java.lang.StringBuilder.append(char)java.lang.StringBuilder
		// @142: iload #7
		// @144: invokevirtual java.lang.StringBuilder.append(int)java.lang.StringBuilder
		// @147: bipush 41 (0x29)
		// @149: invokevirtual java.lang.StringBuilder.append(char)java.lang.StringBuilder
		// @14C: invokevirtual java.lang.StringBuilder.toString()java.lang.String
		// @14F: invokestatic game.C_100181_cf.func_105695_a(java.lang.Throwable, java.lang.String)game.C_100170_cm
		// @152: athrow
		// @153: return
	}
	
	static
	{
		// @00: bipush 12 (0x0C)
		// @02: anewarray java.lang.String
		// @05: dup
		// @06: iconst_0
		// @07: ldc "lsT\u000fv"
		// @09: invokestatic game.C_100172_ck.func_102104_z(java.lang.String)char[]
		// @0C: invokestatic game.C_100172_ck.func_102101_z(char[])java.lang.String
		// @0F: aastore
		// @10: dup
		// @11: iconst_1
		// @12: ldc "lsT\u000bv"
		// @14: invokestatic game.C_100172_ck.func_102104_z(java.lang.String)char[]
		// @17: invokestatic game.C_100172_ck.func_102101_z(char[])java.lang.String
		// @1A: aastore
		// @1B: dup
		// @1C: iconst_2
		// @1D: ldc "lsT\u0008v"
		// @1F: invokestatic game.C_100172_ck.func_102104_z(java.lang.String)char[]
		// @22: invokestatic game.C_100172_ck.func_102101_z(char[])java.lang.String
		// @25: aastore
		// @26: dup
		// @27: iconst_3
		// @28: ldc "lsT\u000ev"
		// @2A: invokestatic game.C_100172_ck.func_102104_z(java.lang.String)char[]
		// @2D: invokestatic game.C_100172_ck.func_102101_z(char[])java.lang.String
		// @30: aastore
		// @31: dup
		// @32: iconst_4
		// @33: ldc "t6Tg#"
		// @35: invokestatic game.C_100172_ck.func_102104_z(java.lang.String)char[]
		// @38: invokestatic game.C_100172_ck.func_102101_z(char[])java.lang.String
		// @3B: aastore
		// @3C: dup
		// @3D: iconst_5
		// @3E: ldc "lsTu7aq\u000ewv"
		// @40: invokestatic game.C_100172_ck.func_102104_z(java.lang.String)char[]
		// @43: invokestatic game.C_100172_ck.func_102101_z(char[])java.lang.String
		// @46: aastore
		// @47: dup
		// @48: bipush 6 (0x06)
		// @4A: ldc "am\u0016%"
		// @4C: invokestatic game.C_100172_ck.func_102104_z(java.lang.String)char[]
		// @4F: invokestatic game.C_100172_ck.func_102101_z(char[])java.lang.String
		// @52: aastore
		// @53: dup
		// @54: bipush 7 (0x07)
		// @56: ldc "lsT\u0001v"
		// @58: invokestatic game.C_100172_ck.func_102104_z(java.lang.String)char[]
		// @5B: invokestatic game.C_100172_ck.func_102101_z(char[])java.lang.String
		// @5E: aastore
		// @5F: dup
		// @60: bipush 8 (0x08)
		// @62: ldc "lsT\u0000v"
		// @64: invokestatic game.C_100172_ck.func_102104_z(java.lang.String)char[]
		// @67: invokestatic game.C_100172_ck.func_102101_z(char[])java.lang.String
		// @6A: aastore
		// @6B: dup
		// @6C: bipush 9 (0x09)
		// @6E: ldc "lsT\rv"
		// @70: invokestatic game.C_100172_ck.func_102104_z(java.lang.String)char[]
		// @73: invokestatic game.C_100172_ck.func_102101_z(char[])java.lang.String
		// @76: aastore
		// @77: dup
		// @78: bipush 10 (0x0A)
		// @7A: ldc "lsT\nv"
		// @7C: invokestatic game.C_100172_ck.func_102104_z(java.lang.String)char[]
		// @7F: invokestatic game.C_100172_ck.func_102101_z(char[])java.lang.String
		// @82: aastore
		// @83: dup
		// @84: bipush 11 (0x0B)
		// @86: ldc "lsT\u000cv"
		// @88: invokestatic game.C_100172_ck.func_102104_z(java.lang.String)char[]
		// @8B: invokestatic game.C_100172_ck.func_102101_z(char[])java.lang.String
		// @8E: aastore
		// @8F: putstatic java.lang.String[] game.C_100172_ck.field_102111_gc
		// @92: iconst_2
		// @93: putstatic int game.C_100172_ck.field_102116_fc
		// @96: ldc "H}\u000ei?l{\u001f:-/l\u0015i0joZ*1bh\u0015';al\ti<v8\u001f1.jv\u001e 0h8\t&2nj\u0013=;/{\u000f+;|8\u0015'~jv\u001d 0j}\u0008 0h6Z\u001c0{q\u0016i'`mZ,0hq\u0014,;}8\u001bi=`u\n&0jv\u000ee~flZ*?av\u0015=~m}Z,/zq\n9;k8\u0015'~n8\t,0{q\u0014,2!"
		// @98: invokestatic game.C_100172_ck.func_102104_z(java.lang.String)char[]
		// @9B: invokestatic game.C_100172_ck.func_102101_z(char[])java.lang.String
		// @9E: putstatic java.lang.String game.C_100172_ck.field_102122_cc
		// @A1: ldc "3=Jw~gy\ti:j{\u0016 0j|Z=6j8\u0013'(fl\u001b=7`vT"
		// @A3: invokestatic game.C_100172_ck.func_102104_z(java.lang.String)char[]
		// @A6: invokestatic game.C_100172_ck.func_102101_z(char[])java.lang.String
		// @A9: putstatic java.lang.String game.C_100172_ck.field_102118_Ub
		// @AC: new game.C_100217_ao
		// @AF: dup
		// @B0: iconst_1
		// @B1: iconst_2
		// @B2: iconst_2
		// @B3: iconst_0
		// @B4: invokespecial game.C_100217_ao.<init>(int, int, int, int)void
		// @B7: putstatic game.C_100217_ao game.C_100172_ck.field_102110_dc
		// @BA: ldc "Jv\u000e,,/v\u001b$;/w\u001ci8}q\u001f':/l\u0015i?k|Z=1/t\u0013:*"
		// @BC: invokestatic game.C_100172_ck.func_102104_z(java.lang.String)char[]
		// @BF: invokestatic game.C_100172_ck.func_102101_z(char[])java.lang.String
		// @C2: putstatic java.lang.String game.C_100172_ck.field_102114_Yb
		// @C5: ldc "Ly\u0014*;c"
		// @C7: invokestatic game.C_100172_ck.func_102104_z(java.lang.String)char[]
		// @CA: invokestatic game.C_100172_ck.func_102101_z(char[])java.lang.String
		// @CD: putstatic java.lang.String game.C_100172_ck.field_102121_bc
		// @D0: return
	}
	
	private static char[] func_102104_z(String arg0)
	{
		// @00: aload_0
		// @01: invokevirtual java.lang.String.toCharArray()char[]
		// @04: dup
		// @05: arraylength
		// @06: iconst_2
		// @07: if_icmpge @13
		// @0A: dup
		// @0B: iconst_0
		// @0C: dup2
		// @0D: caload
		// @0E: bipush 94 (0x5E)
		// @10: ixor
		// @11: i2c
		// @12: castore
		// @13: areturn
	}
	
	private static String func_102101_z(char[] arg0)
	{
		// @00: aload_0
		// @01: dup
		// @02: arraylength
		// @03: swap
		// @04: iconst_0
		// @05: istore_1
		// @06: goto @4C
		// @09: dup
		// @0A: iload_1
		// @0B: dup2
		// @0C: caload
		// @0D: iload_1
		// @0E: iconst_5
		// @0F: irem
		// @10: tableswitch def: @44, for 0: @30, for 1: @35, for 2: @3A, for 3: @3F
		// @30: bipush 15 (0x0F)
		// @32: goto @46
		// @35: bipush 24 (0x18)
		// @37: goto @46
		// @3A: bipush 122 (0x7A)
		// @3C: goto @46
		// @3F: bipush 73 (0x49)
		// @41: goto @46
		// @44: bipush 94 (0x5E)
		// @46: ixor
		// @47: i2c
		// @48: castore
		// @49: iinc #1 +1
		// @4C: swap
		// @4D: dup_x1
		// @4E: iload_1
		// @4F: if_icmpgt @09
		// @52: new java.lang.String
		// @55: dup_x1
		// @56: swap
		// @57: invokespecial java.lang.String.<init>(char[])void
		// @5A: invokevirtual java.lang.String.intern()java.lang.String
		// @5D: areturn
	}
}
