package game;

final class C_100017_wj
{
	static int[] field_103824_h;
	static int field_103815_g;
	static String field_103820_a;
	static int[] field_103821_j;
	static String field_103817_e;
	static C_100037_wb field_103818_b;
	static String field_103825_i;
	static C_100115_ej field_103823_k;
	static String field_103819_c;
	static C_100302_ka field_103816_d;
	static int field_103814_f;
	private static final String[] field_103822_z;
	
	static final void func_103813_b(byte arg0)
	{
		// @000: getstatic int game.SteelSentinels.field_105275_O
		// @003: istore #8
		// @005: iconst_4
		// @006: getstatic int[] game.C_100280_nf.field_101178_o
		// @009: arraylength
		// @00A: iadd
		// @00B: bipush -3 (0xFD)
		// @00D: isub
		// @00E: istore_1
		// @00F: getstatic int[][] game.C_100122_em.field_102073_Xb
		// @012: astore_2
		// @013: aload_2
		// @014: astore_3
		// @015: iconst_0
		// @016: istore #4
		// @018: iload #4
		// @01A: aload_3
		// @01B: arraylength
		// @01C: if_icmpge @03D
		// @01F: aload_3
		// @020: iload #4
		// @022: aaload
		// @023: astore #5
		// @025: aconst_null
		// @026: aload #5
		// @028: if_acmpne @02F
		// @02B: goto @035
		// @02E: athrow
		// @02F: iload_1
		// @030: aload #5
		// @032: arraylength
		// @033: iadd
		// @034: istore_1
		// @035: iinc #4 +1
		// @038: iload #8
		// @03A: ifeq @018
		// @03D: iload_1
		// @03E: newarray byte[]
		// @040: astore_3
		// @041: iconst_0
		// @042: istore #4
		// @044: iconst_0
		// @045: istore #5
		// @047: getstatic boolean game.C_100034_gi.field_104036_j
		// @04A: ifne @051
		// @04D: goto @058
		// @050: athrow
		// @051: iload #5
		// @053: iconst_1
		// @054: ior
		// @055: i2b
		// @056: istore #5
		// @058: getstatic boolean game.C_100050_vg.field_100637_q
		// @05B: ifeq @065
		// @05E: iload #5
		// @060: iconst_2
		// @061: ior
		// @062: i2b
		// @063: istore #5
		// @065: getstatic boolean game.C_100216_aj.field_104462_t
		// @068: ifne @06F
		// @06B: goto @076
		// @06E: athrow
		// @06F: iload #5
		// @071: iconst_4
		// @072: ior
		// @073: i2b
		// @074: istore #5
		// @076: getstatic boolean game.C_100094_j.field_104552_j
		// @079: ifeq @084
		// @07C: iload #5
		// @07E: bipush 8 (0x08)
		// @080: ior
		// @081: i2b
		// @082: istore #5
		// @084: iload_0
		// @085: bipush 98 (0x62)
		// @087: if_icmpge @093
		// @08A: bipush 30 (0x1E)
		// @08C: invokestatic game.C_100017_wj.func_103808_b(int)void
		// @08F: goto @093
		// @092: athrow
		// @093: getstatic boolean game.C_100102_w.field_104632_g
		// @096: ifne @09D
		// @099: goto @0A5
		// @09C: athrow
		// @09D: iload #5
		// @09F: bipush 16 (0x10)
		// @0A1: ior
		// @0A2: i2b
		// @0A3: istore #5
		// @0A5: getstatic boolean game.C_100247_pa.field_106414_d
		// @0A8: ifne @0AF
		// @0AB: goto @0B7
		// @0AE: athrow
		// @0AF: iload #5
		// @0B1: bipush 32 (0x20)
		// @0B3: ior
		// @0B4: i2b
		// @0B5: istore #5
		// @0B7: aload_3
		// @0B8: iload #4
		// @0BA: iinc #4 +1
		// @0BD: iconst_3
		// @0BE: bastore
		// @0BF: aload_3
		// @0C0: iload #4
		// @0C2: iinc #4 +1
		// @0C5: iload #5
		// @0C7: bastore
		// @0C8: aload_3
		// @0C9: iload #4
		// @0CB: iinc #4 +1
		// @0CE: getstatic int game.C_100249_pc.field_102333_I
		// @0D1: i2b
		// @0D2: bastore
		// @0D3: aload_3
		// @0D4: iload #4
		// @0D6: iinc #4 +1
		// @0D9: getstatic int[] game.C_100280_nf.field_101178_o
		// @0DC: arraylength
		// @0DD: i2b
		// @0DE: bastore
		// @0DF: iconst_0
		// @0E0: istore #6
		// @0E2: getstatic int[] game.C_100280_nf.field_101178_o
		// @0E5: arraylength
		// @0E6: iload #6
		// @0E8: if_icmple @10A
		// @0EB: aload_3
		// @0EC: iload #4
		// @0EE: iinc #4 +1
		// @0F1: getstatic int[] game.C_100280_nf.field_101178_o
		// @0F4: iload #6
		// @0F6: iaload
		// @0F7: i2b
		// @0F8: bastore
		// @0F9: iinc #6 +1
		// @0FC: iload #8
		// @0FE: ifne @10D
		// @101: iload #8
		// @103: ifeq @0E2
		// @106: goto @10A
		// @109: athrow
		// @10A: iconst_0
		// @10B: istore #6
		// @10D: aload_2
		// @10E: arraylength
		// @10F: iconst_m1
		// @110: ixor
		// @111: iload #6
		// @113: iconst_m1
		// @114: ixor
		// @115: if_icmpge @184
		// @118: iload #8
		// @11A: ifne @199
		// @11D: goto @121
		// @120: athrow
		// @121: aconst_null
		// @122: aload_2
		// @123: iload #6
		// @125: aaload
		// @126: if_acmpne @13E
		// @129: goto @12D
		// @12C: athrow
		// @12D: aload_3
		// @12E: iload #4
		// @130: iinc #4 +1
		// @133: iconst_0
		// @134: bastore
		// @135: iload #8
		// @137: ifeq @17C
		// @13A: goto @13E
		// @13D: athrow
		// @13E: aload_3
		// @13F: iload #4
		// @141: iinc #4 +1
		// @144: aload_2
		// @145: iload #6
		// @147: aaload
		// @148: arraylength
		// @149: i2b
		// @14A: bastore
		// @14B: iconst_0
		// @14C: istore #7
		// @14E: aload_2
		// @14F: iload #6
		// @151: aaload
		// @152: arraylength
		// @153: iconst_m1
		// @154: ixor
		// @155: iload #7
		// @157: iconst_m1
		// @158: ixor
		// @159: if_icmpge @17C
		// @15C: aload_3
		// @15D: iload #4
		// @15F: iinc #4 +1
		// @162: aload_2
		// @163: iload #6
		// @165: aaload
		// @166: iload #7
		// @168: iaload
		// @169: i2b
		// @16A: bastore
		// @16B: iinc #7 +1
		// @16E: iload #8
		// @170: ifne @17F
		// @173: iload #8
		// @175: ifeq @14E
		// @178: goto @17C
		// @17B: athrow
		// @17C: iinc #6 +1
		// @17F: iload #8
		// @181: ifeq @10D
		// @184: bipush -25 (0xE7)
		// @186: invokestatic game.C_100234_ob.func_106268_c(byte)boolean
		// @189: ifne @199
		// @18C: bipush 6 (0x06)
		// @18E: aload_3
		// @18F: bipush 21 (0x15)
		// @191: invokestatic game.C_100311_le.func_104708_a(int, byte[], byte)game.C_100131_te
		// @194: pop
		// @195: goto @199
		// @198: athrow
		// @199: goto @1BD
		// @19C: astore_1
		// @19D: aload_1
		// @19E: new java.lang.StringBuilder
		// @1A1: dup
		// @1A2: invokespecial java.lang.StringBuilder.<init>()void
		// @1A5: getstatic java.lang.String[] game.C_100017_wj.field_103822_z
		// @1A8: iconst_2
		// @1A9: aaload
		// @1AA: invokevirtual java.lang.StringBuilder.append(java.lang.String)java.lang.StringBuilder
		// @1AD: iload_0
		// @1AE: invokevirtual java.lang.StringBuilder.append(int)java.lang.StringBuilder
		// @1B1: bipush 41 (0x29)
		// @1B3: invokevirtual java.lang.StringBuilder.append(char)java.lang.StringBuilder
		// @1B6: invokevirtual java.lang.StringBuilder.toString()java.lang.String
		// @1B9: invokestatic game.C_100181_cf.func_105695_a(java.lang.Throwable, java.lang.String)game.C_100170_cm
		// @1BC: athrow
		// @1BD: return
	}
	
	static final void func_103809_a(int arg0)
	{
		// @00: bipush 32 (0x20)
		// @02: getstatic int game.C_100216_aj.field_104467_z
		// @05: if_icmplt @18
		// @08: iconst_0
		// @09: bipush 90 (0x5A)
		// @0B: invokestatic game.C_100310_lj.func_100542_a(int, byte)void
		// @0E: getstatic int game.SteelSentinels.field_105275_O
		// @11: ifeq @33
		// @14: goto @18
		// @17: athrow
		// @18: getstatic int game.C_100216_aj.field_104467_z
		// @1B: bipush 32 (0x20)
		// @1D: irem
		// @1E: istore_1
		// @1F: iload_1
		// @20: iconst_m1
		// @21: ixor
		// @22: iconst_m1
		// @23: if_icmpne @29
		// @26: bipush 32 (0x20)
		// @28: istore_1
		// @29: getstatic int game.C_100216_aj.field_104467_z
		// @2C: iload_1
		// @2D: isub
		// @2E: bipush 120 (0x78)
		// @30: invokestatic game.C_100310_lj.func_100542_a(int, byte)void
		// @33: bipush -20 (0xEC)
		// @35: bipush 37 (0x25)
		// @37: iload_0
		// @38: isub
		// @39: bipush 58 (0x3A)
		// @3B: idiv
		// @3C: irem
		// @3D: istore_1
		// @3E: goto @62
		// @41: astore_1
		// @42: aload_1
		// @43: new java.lang.StringBuilder
		// @46: dup
		// @47: invokespecial java.lang.StringBuilder.<init>()void
		// @4A: getstatic java.lang.String[] game.C_100017_wj.field_103822_z
		// @4D: iconst_1
		// @4E: aaload
		// @4F: invokevirtual java.lang.StringBuilder.append(java.lang.String)java.lang.StringBuilder
		// @52: iload_0
		// @53: invokevirtual java.lang.StringBuilder.append(int)java.lang.StringBuilder
		// @56: bipush 41 (0x29)
		// @58: invokevirtual java.lang.StringBuilder.append(char)java.lang.StringBuilder
		// @5B: invokevirtual java.lang.StringBuilder.toString()java.lang.String
		// @5E: invokestatic game.C_100181_cf.func_105695_a(java.lang.Throwable, java.lang.String)game.C_100170_cm
		// @61: athrow
		// @62: return
	}
	
	public static void func_103808_b(int arg0)
	{
		// @00: aconst_null
		// @01: putstatic int[] game.C_100017_wj.field_103821_j
		// @04: aconst_null
		// @05: putstatic game.C_100302_ka game.C_100017_wj.field_103816_d
		// @08: aconst_null
		// @09: putstatic game.C_100037_wb game.C_100017_wj.field_103818_b
		// @0C: aconst_null
		// @0D: putstatic game.C_100115_ej game.C_100017_wj.field_103823_k
		// @10: aconst_null
		// @11: putstatic java.lang.String game.C_100017_wj.field_103817_e
		// @14: iload_0
		// @15: sipush 25688 (0x6458)
		// @18: if_icmpeq @24
		// @1B: bipush 56 (0x38)
		// @1D: invokestatic game.C_100017_wj.func_103808_b(int)void
		// @20: goto @24
		// @23: athrow
		// @24: aconst_null
		// @25: putstatic java.lang.String game.C_100017_wj.field_103819_c
		// @28: aconst_null
		// @29: putstatic java.lang.String game.C_100017_wj.field_103825_i
		// @2C: aconst_null
		// @2D: putstatic java.lang.String game.C_100017_wj.field_103820_a
		// @30: aconst_null
		// @31: putstatic int[] game.C_100017_wj.field_103824_h
		// @34: goto @58
		// @37: astore_1
		// @38: aload_1
		// @39: new java.lang.StringBuilder
		// @3C: dup
		// @3D: invokespecial java.lang.StringBuilder.<init>()void
		// @40: getstatic java.lang.String[] game.C_100017_wj.field_103822_z
		// @43: iconst_3
		// @44: aaload
		// @45: invokevirtual java.lang.StringBuilder.append(java.lang.String)java.lang.StringBuilder
		// @48: iload_0
		// @49: invokevirtual java.lang.StringBuilder.append(int)java.lang.StringBuilder
		// @4C: bipush 41 (0x29)
		// @4E: invokevirtual java.lang.StringBuilder.append(char)java.lang.StringBuilder
		// @51: invokevirtual java.lang.StringBuilder.toString()java.lang.String
		// @54: invokestatic game.C_100181_cf.func_105695_a(java.lang.Throwable, java.lang.String)game.C_100170_cm
		// @57: athrow
		// @58: return
	}
	
	static final void func_103811_a(byte arg0)
	{
		// @00: bipush 25 (0x19)
		// @02: iload_0
		// @03: bipush -53 (0xCB)
		// @05: isub
		// @06: bipush 45 (0x2D)
		// @08: idiv
		// @09: idiv
		// @0A: istore_1
		// @0B: iconst_0
		// @0C: invokestatic game.C_100206_qe.func_105938_b(boolean)java.applet.Applet
		// @0F: sipush 198 (0x00C6)
		// @12: invokestatic game.C_100015_wh.func_103773_a(java.applet.Applet, int)void
		// @15: goto @39
		// @18: astore_1
		// @19: aload_1
		// @1A: new java.lang.StringBuilder
		// @1D: dup
		// @1E: invokespecial java.lang.StringBuilder.<init>()void
		// @21: getstatic java.lang.String[] game.C_100017_wj.field_103822_z
		// @24: iconst_0
		// @25: aaload
		// @26: invokevirtual java.lang.StringBuilder.append(java.lang.String)java.lang.StringBuilder
		// @29: iload_0
		// @2A: invokevirtual java.lang.StringBuilder.append(int)java.lang.StringBuilder
		// @2D: bipush 41 (0x29)
		// @2F: invokevirtual java.lang.StringBuilder.append(char)java.lang.StringBuilder
		// @32: invokevirtual java.lang.StringBuilder.toString()java.lang.String
		// @35: invokestatic game.C_100181_cf.func_105695_a(java.lang.Throwable, java.lang.String)game.C_100170_cm
		// @38: athrow
		// @39: return
	}
	
	static
	{
		// @00: iconst_4
		// @01: anewarray java.lang.String
		// @04: dup
		// @05: iconst_0
		// @06: ldc "\u0017\u000fw@q"
		// @08: invokestatic game.C_100017_wj.func_103812_z(java.lang.String)char[]
		// @0B: invokestatic game.C_100017_wj.func_103810_z(char[])java.lang.String
		// @0E: aastore
		// @0F: dup
		// @10: iconst_1
		// @11: ldc "\u0017\u000fwCq"
		// @13: invokestatic game.C_100017_wj.func_103812_z(java.lang.String)char[]
		// @16: invokestatic game.C_100017_wj.func_103810_z(char[])java.lang.String
		// @19: aastore
		// @1A: dup
		// @1B: iconst_2
		// @1C: ldc "\u0017\u000fwAq"
		// @1E: invokestatic game.C_100017_wj.func_103812_z(java.lang.String)char[]
		// @21: invokestatic game.C_100017_wj.func_103810_z(char[])java.lang.String
		// @24: aastore
		// @25: dup
		// @26: iconst_3
		// @27: ldc "\u0017\u000fwFq"
		// @29: invokestatic game.C_100017_wj.func_103812_z(java.lang.String)char[]
		// @2C: invokestatic game.C_100017_wj.func_103810_z(char[])java.lang.String
		// @2F: aastore
		// @30: putstatic java.lang.String[] game.C_100017_wj.field_103822_z
		// @33: ldc "31\u0018L\u001d!7\u001d"
		// @35: invokestatic game.C_100017_wj.func_103812_z(java.lang.String)char[]
		// @38: invokestatic game.C_100017_wj.func_103810_z(char[])java.lang.String
		// @3B: putstatic java.lang.String game.C_100017_wj.field_103820_a
		// @3E: bipush 12 (0x0C)
		// @40: newarray int[]
		// @42: dup
		// @43: iconst_0
		// @44: iconst_0
		// @45: iastore
		// @46: dup
		// @47: iconst_1
		// @48: bipush 55 (0x37)
		// @4A: iastore
		// @4B: dup
		// @4C: iconst_2
		// @4D: bipush 57 (0x39)
		// @4F: iastore
		// @50: dup
		// @51: iconst_3
		// @52: bipush 62 (0x3E)
		// @54: iastore
		// @55: dup
		// @56: iconst_4
		// @57: bipush 65 (0x41)
		// @59: iastore
		// @5A: dup
		// @5B: iconst_5
		// @5C: bipush 69 (0x45)
		// @5E: iastore
		// @5F: dup
		// @60: bipush 6 (0x06)
		// @62: bipush 72 (0x48)
		// @64: iastore
		// @65: dup
		// @66: bipush 7 (0x07)
		// @68: bipush 75 (0x4B)
		// @6A: iastore
		// @6B: dup
		// @6C: bipush 8 (0x08)
		// @6E: bipush 79 (0x4F)
		// @70: iastore
		// @71: dup
		// @72: bipush 9 (0x09)
		// @74: bipush 84 (0x54)
		// @76: iastore
		// @77: dup
		// @78: bipush 10 (0x0A)
		// @7A: bipush 88 (0x58)
		// @7C: iastore
		// @7D: dup
		// @7E: bipush 11 (0x0B)
		// @80: bipush 92 (0x5C)
		// @82: iastore
		// @83: putstatic int[] game.C_100017_wj.field_103821_j
		// @86: iconst_m1
		// @87: putstatic int game.C_100017_wj.field_103815_g
		// @8A: aconst_null
		// @8B: putstatic game.C_100115_ej game.C_100017_wj.field_103823_k
		// @8E: ldc "3\r6uy\u0007\u00044gy\u0003\r8vy\u0006\u00176oy\r\u001cyd+\t\u00007f*"
		// @90: invokestatic game.C_100017_wj.func_103812_z(java.lang.String)char[]
		// @93: invokestatic game.C_100017_wj.func_103810_z(char[])java.lang.String
		// @96: putstatic java.lang.String game.C_100017_wj.field_103825_i
		// @99: sipush 8192 (0x2000)
		// @9C: newarray int[]
		// @9E: putstatic int[] game.C_100017_wj.field_103824_h
		// @A1: ldc "2\u0000*r8\u0017\u000b*\"t@"
		// @A3: invokestatic game.C_100017_wj.func_103812_z(java.lang.String)char[]
		// @A6: invokestatic game.C_100017_wj.func_103810_z(char[])java.lang.String
		// @A9: putstatic java.lang.String game.C_100017_wj.field_103817_e
		// @AC: ldc "-\u0000*q8\u0007\u0000yn6\u0002\u0007 "
		// @AE: invokestatic game.C_100017_wj.func_103812_z(java.lang.String)char[]
		// @B1: invokestatic game.C_100017_wj.func_103810_z(char[])java.lang.String
		// @B4: putstatic java.lang.String game.C_100017_wj.field_103819_c
		// @B7: return
	}
	
	private static char[] func_103812_z(String arg0)
	{
		// @00: aload_0
		// @01: invokevirtual java.lang.String.toCharArray()char[]
		// @04: dup
		// @05: arraylength
		// @06: iconst_2
		// @07: if_icmpge @13
		// @0A: dup
		// @0B: iconst_0
		// @0C: dup2
		// @0D: caload
		// @0E: bipush 89 (0x59)
		// @10: ixor
		// @11: i2c
		// @12: castore
		// @13: areturn
	}
	
	private static String func_103810_z(char[] arg0)
	{
		// @00: aload_0
		// @01: dup
		// @02: arraylength
		// @03: swap
		// @04: iconst_0
		// @05: istore_1
		// @06: goto @4B
		// @09: dup
		// @0A: iload_1
		// @0B: dup2
		// @0C: caload
		// @0D: iload_1
		// @0E: iconst_5
		// @0F: irem
		// @10: tableswitch def: @43, for 0: @30, for 1: @35, for 2: @3A, for 3: @3F
		// @30: bipush 96 (0x60)
		// @32: goto @45
		// @35: bipush 101 (0x65)
		// @37: goto @45
		// @3A: bipush 89 (0x59)
		// @3C: goto @45
		// @3F: iconst_2
		// @40: goto @45
		// @43: bipush 89 (0x59)
		// @45: ixor
		// @46: i2c
		// @47: castore
		// @48: iinc #1 +1
		// @4B: swap
		// @4C: dup_x1
		// @4D: iload_1
		// @4E: if_icmpgt @09
		// @51: new java.lang.String
		// @54: dup_x1
		// @55: swap
		// @56: invokespecial java.lang.String.<init>(char[])void
		// @59: invokevirtual java.lang.String.intern()java.lang.String
		// @5C: areturn
	}
}
