package game;

import java.net.URL;
import java.applet.Applet;

final class C_100244_pe
{
	static C_100037_wb field_106376_e;
	static int field_106379_a;
	static boolean field_106377_b;
	static int field_106374_f;
	static String field_106378_c;
	static int field_106375_d;
	private static final String[] field_106380_z;
	
	static final void func_106372_a(C_100098_h arg0, int arg1, C_100098_h arg2, C_100098_h arg3)
	{
		// @000: getstatic int game.SteelSentinels.field_105275_O
		// @003: istore #13
		// @005: aload_0
		// @006: getstatic java.lang.String[] game.C_100244_pe.field_106380_z
		// @009: bipush 14 (0x0E)
		// @00B: aaload
		// @00C: getstatic java.lang.String[] game.C_100244_pe.field_106380_z
		// @00F: iconst_4
		// @010: aaload
		// @011: bipush -124 (0x84)
		// @013: invokestatic game.C_100163_sf.func_105433_a(game.C_100098_h, java.lang.String, java.lang.String, byte)game.C_100037_wb[]
		// @016: putstatic game.C_100037_wb[] game.C_100218_am.field_103110_E
		// @019: aload_0
		// @01A: getstatic java.lang.String[] game.C_100244_pe.field_106380_z
		// @01D: iconst_2
		// @01E: aaload
		// @01F: getstatic java.lang.String[] game.C_100244_pe.field_106380_z
		// @022: iconst_4
		// @023: aaload
		// @024: bipush -125 (0x83)
		// @026: invokestatic game.C_100163_sf.func_105433_a(game.C_100098_h, java.lang.String, java.lang.String, byte)game.C_100037_wb[]
		// @029: putstatic game.C_100037_wb[] game.C_100157_db.field_103558_e
		// @02C: bipush 123 (0x7B)
		// @02E: getstatic java.lang.String[] game.C_100244_pe.field_106380_z
		// @031: iconst_4
		// @032: aaload
		// @033: aload_0
		// @034: getstatic java.lang.String[] game.C_100244_pe.field_106380_z
		// @037: bipush 9 (0x09)
		// @039: aaload
		// @03A: invokestatic game.C_100021_wn.func_103861_a(byte, java.lang.String, game.C_100098_h, java.lang.String)game.C_100037_wb
		// @03D: putstatic game.C_100037_wb game.C_100148_bh.field_101794_F
		// @040: aload_0
		// @041: getstatic java.lang.String[] game.C_100244_pe.field_106380_z
		// @044: iconst_3
		// @045: aaload
		// @046: getstatic java.lang.String[] game.C_100244_pe.field_106380_z
		// @049: iconst_4
		// @04A: aaload
		// @04B: bipush -88 (0xA8)
		// @04D: invokestatic game.C_100163_sf.func_105433_a(game.C_100098_h, java.lang.String, java.lang.String, byte)game.C_100037_wb[]
		// @050: putstatic game.C_100037_wb[] game.C_100103_eh.field_104664_d
		// @053: getstatic java.lang.String[] game.C_100244_pe.field_106380_z
		// @056: iconst_4
		// @057: aaload
		// @058: aload_0
		// @059: bipush 91 (0x5B)
		// @05B: getstatic java.lang.String[] game.C_100244_pe.field_106380_z
		// @05E: bipush 10 (0x0A)
		// @060: aaload
		// @061: invokestatic game.C_100188_rj.func_105731_a(java.lang.String, game.C_100098_h, int, java.lang.String)game.C_100037_wb[]
		// @064: putstatic game.C_100037_wb[] game.C_100163_sf.field_105435_g
		// @067: bipush -70 (0xBA)
		// @069: getstatic java.lang.String[] game.C_100244_pe.field_106380_z
		// @06C: iconst_4
		// @06D: aaload
		// @06E: getstatic java.lang.String[] game.C_100244_pe.field_106380_z
		// @071: bipush 12 (0x0C)
		// @073: aaload
		// @074: aload_0
		// @075: aload_3
		// @076: invokestatic game.C_100160_sm.func_105412_a(byte, java.lang.String, java.lang.String, game.C_100098_h, game.C_100098_h)game.C_100193_re
		// @079: putstatic game.C_100112_r game.C_100318_hj.field_107198_b
		// @07C: bipush -70 (0xBA)
		// @07E: getstatic java.lang.String[] game.C_100244_pe.field_106380_z
		// @081: iconst_4
		// @082: aaload
		// @083: getstatic java.lang.String[] game.C_100244_pe.field_106380_z
		// @086: bipush 11 (0x0B)
		// @088: aaload
		// @089: aload_0
		// @08A: aload_3
		// @08B: invokestatic game.C_100160_sm.func_105412_a(byte, java.lang.String, java.lang.String, game.C_100098_h, game.C_100098_h)game.C_100193_re
		// @08E: putstatic game.C_100112_r game.C_100230_of.field_106205_g
		// @091: bipush -70 (0xBA)
		// @093: getstatic java.lang.String[] game.C_100244_pe.field_106380_z
		// @096: iconst_4
		// @097: aaload
		// @098: getstatic java.lang.String[] game.C_100244_pe.field_106380_z
		// @09B: bipush 6 (0x06)
		// @09D: aaload
		// @09E: aload_0
		// @09F: aload_3
		// @0A0: invokestatic game.C_100160_sm.func_105412_a(byte, java.lang.String, java.lang.String, game.C_100098_h, game.C_100098_h)game.C_100193_re
		// @0A3: putstatic game.C_100112_r game.C_100185_rm.field_105484_d
		// @0A6: new game.C_100037_wb
		// @0A9: dup
		// @0AA: aload_2
		// @0AB: ldc ""
		// @0AD: getstatic java.lang.String[] game.C_100244_pe.field_106380_z
		// @0B0: bipush 16 (0x10)
		// @0B2: aaload
		// @0B3: bipush -96 (0xA0)
		// @0B5: invokevirtual game.C_100098_h.func_104608_a(java.lang.String, java.lang.String, int)byte[]
		// @0B8: getstatic java.awt.Canvas game.C_100034_gi.field_104033_a
		// @0BB: invokespecial game.C_100037_wb.<init>(byte[], java.awt.Component)void
		// @0BE: astore #4
		// @0C0: getstatic java.lang.String[] game.C_100244_pe.field_106380_z
		// @0C3: iconst_4
		// @0C4: aaload
		// @0C5: bipush -62 (0xC2)
		// @0C7: getstatic java.lang.String[] game.C_100244_pe.field_106380_z
		// @0CA: bipush 15 (0x0F)
		// @0CC: aaload
		// @0CD: aload_0
		// @0CE: invokestatic game.C_100004_gb.func_103569_a(java.lang.String, byte, java.lang.String, game.C_100098_h)game.C_100153_be
		// @0D1: pop
		// @0D2: getstatic java.lang.String[] game.C_100244_pe.field_106380_z
		// @0D5: iconst_5
		// @0D6: aaload
		// @0D7: aload_0
		// @0D8: getstatic java.lang.String[] game.C_100244_pe.field_106380_z
		// @0DB: iconst_4
		// @0DC: aaload
		// @0DD: bipush 88 (0x58)
		// @0DF: invokestatic game.C_100341_jd.func_102631_a(java.lang.String, game.C_100098_h, java.lang.String, int)game.C_100153_be[]
		// @0E2: astore #5
		// @0E4: iconst_4
		// @0E5: anewarray game.C_100153_be
		// @0E8: putstatic game.C_100153_be[] game.C_100114_q.field_100489_v
		// @0EB: iconst_4
		// @0EC: anewarray game.C_100153_be
		// @0EF: putstatic game.C_100153_be[] game.C_100290_jm.field_106865_k
		// @0F2: iconst_4
		// @0F3: anewarray game.C_100153_be
		// @0F6: putstatic game.C_100153_be[] game.C_100192_rf.field_101682_J
		// @0F9: iconst_3
		// @0FA: anewarray game.C_100153_be[]
		// @0FD: dup
		// @0FE: iconst_0
		// @0FF: getstatic game.C_100153_be[] game.C_100192_rf.field_101682_J
		// @102: aastore
		// @103: dup
		// @104: iconst_1
		// @105: getstatic game.C_100153_be[] game.C_100290_jm.field_106865_k
		// @108: aastore
		// @109: dup
		// @10A: iconst_2
		// @10B: getstatic game.C_100153_be[] game.C_100114_q.field_100489_v
		// @10E: aastore
		// @10F: astore #6
		// @111: iconst_4
		// @112: anewarray int[]
		// @115: astore #7
		// @117: aload #7
		// @119: iconst_0
		// @11A: aload #5
		// @11C: iconst_0
		// @11D: aaload
		// @11E: getfield int[] game.C_100153_be.field_105320_t
		// @121: aastore
		// @122: iconst_1
		// @123: istore #8
		// @125: aload #7
		// @127: arraylength
		// @128: iconst_m1
		// @129: ixor
		// @12A: iload #8
		// @12C: iconst_m1
		// @12D: ixor
		// @12E: if_icmpge @154
		// @131: aload #7
		// @133: iload #8
		// @135: aload #7
		// @137: iconst_0
		// @138: aaload
		// @139: invokevirtual int[].clone()java.lang.Object
		// @13C: checkcast int[]
		// @13F: checkcast int[]
		// @142: aastore
		// @143: iinc #8 +1
		// @146: iload #13
		// @148: ifne @17A
		// @14B: iload #13
		// @14D: ifeq @125
		// @150: goto @154
		// @153: athrow
		// @154: aload #5
		// @156: iconst_0
		// @157: aaload
		// @158: getfield byte[] game.C_100153_be.field_105319_u
		// @15B: iload_1
		// @15C: baload
		// @15D: istore #8
		// @15F: aload #7
		// @161: iconst_2
		// @162: aaload
		// @163: iload #8
		// @165: ldc 16777215 (0xffffff)
		// @167: iastore
		// @168: aload #7
		// @16A: iconst_1
		// @16B: aaload
		// @16C: iload #8
		// @16E: ldc 2394342 (0x2488e6)
		// @170: iastore
		// @171: aload #7
		// @173: iconst_3
		// @174: aaload
		// @175: iload #8
		// @177: ldc 4767999 (0x48c0ff)
		// @179: iastore
		// @17A: iconst_0
		// @17B: istore #9
		// @17D: iload #9
		// @17F: iconst_m1
		// @180: ixor
		// @181: bipush -4 (0xFC)
		// @183: if_icmple @1CF
		// @186: aload #6
		// @188: iload #9
		// @18A: aaload
		// @18B: astore #10
		// @18D: iconst_0
		// @18E: iload #13
		// @190: ifne @1E1
		// @193: istore #11
		// @195: aload #10
		// @197: arraylength
		// @198: iconst_m1
		// @199: ixor
		// @19A: iload #11
		// @19C: iconst_m1
		// @19D: ixor
		// @19E: if_icmpge @1C7
		// @1A1: aload #10
		// @1A3: iload #11
		// @1A5: aload #5
		// @1A7: iload #9
		// @1A9: aaload
		// @1AA: iload_1
		// @1AB: iconst_3
		// @1AC: iadd
		// @1AD: aload #7
		// @1AF: iload #11
		// @1B1: aaload
		// @1B2: invokestatic game.C_100044_vm.func_100934_a(game.C_100153_be, int, int[])game.C_100153_be
		// @1B5: aastore
		// @1B6: iinc #11 +1
		// @1B9: iload #13
		// @1BB: ifne @1CA
		// @1BE: iload #13
		// @1C0: ifeq @195
		// @1C3: goto @1C7
		// @1C6: athrow
		// @1C7: iinc #9 +1
		// @1CA: iload #13
		// @1CC: ifeq @17D
		// @1CF: aload #4
		// @1D1: getfield int game.C_100037_wb.field_102337_u
		// @1D4: istore #9
		// @1D6: bipush -46 (0xD2)
		// @1D8: invokestatic game.C_100328_ia.func_107254_b(byte)void
		// @1DB: aload #4
		// @1DD: invokevirtual game.C_100037_wb.func_102379_d()void
		// @1E0: iconst_0
		// @1E1: iconst_0
		// @1E2: getstatic int game.C_100196_rb.field_105819_e
		// @1E5: getstatic int game.C_100196_rb.field_105821_c
		// @1E8: invokestatic game.C_100196_rb.func_105799_c(int, int, int, int)void
		// @1EB: new game.C_100037_wb
		// @1EE: dup
		// @1EF: iload #9
		// @1F1: iload #9
		// @1F3: invokespecial game.C_100037_wb.<init>(int, int)void
		// @1F6: astore #10
		// @1F8: aload #10
		// @1FA: invokevirtual game.C_100037_wb.func_102379_d()void
		// @1FD: aload #4
		// @1FF: iconst_0
		// @200: iconst_0
		// @201: invokevirtual game.C_100037_wb.func_102386_f(int, int)void
		// @204: new game.C_100037_wb
		// @207: dup
		// @208: iload #9
		// @20A: iload #9
		// @20C: invokespecial game.C_100037_wb.<init>(int, int)void
		// @20F: astore #11
		// @211: aload #11
		// @213: invokevirtual game.C_100037_wb.func_102379_d()void
		// @216: aload #4
		// @218: iload #9
		// @21A: aload #4
		// @21C: getfield int game.C_100037_wb.field_102339_s
		// @21F: isub
		// @220: iconst_0
		// @221: invokevirtual game.C_100037_wb.func_102386_f(int, int)void
		// @224: new game.C_100037_wb
		// @227: dup
		// @228: iconst_2
		// @229: iload #9
		// @22B: imul
		// @22C: ineg
		// @22D: aload #4
		// @22F: getfield int game.C_100037_wb.field_102339_s
		// @232: iadd
		// @233: iload #9
		// @235: invokespecial game.C_100037_wb.<init>(int, int)void
		// @238: astore #12
		// @23A: aload #12
		// @23C: invokevirtual game.C_100037_wb.func_102379_d()void
		// @23F: aload #4
		// @241: iload #9
		// @243: ineg
		// @244: iconst_0
		// @245: invokevirtual game.C_100037_wb.func_102386_f(int, int)void
		// @248: bipush -77 (0xB3)
		// @24A: invokestatic game.C_100200_ba.func_105842_a(byte)void
		// @24D: iconst_3
		// @24E: anewarray game.C_100037_wb
		// @251: dup
		// @252: iconst_0
		// @253: aload #10
		// @255: aastore
		// @256: dup
		// @257: iconst_1
		// @258: aload #12
		// @25A: aastore
		// @25B: dup
		// @25C: iconst_2
		// @25D: aload #11
		// @25F: aastore
		// @260: putstatic game.C_100037_wb[] game.C_100103_eh.field_104664_d
		// @263: goto @2DE
		// @266: astore #4
		// @268: aload #4
		// @26A: new java.lang.StringBuilder
		// @26D: dup
		// @26E: invokespecial java.lang.StringBuilder.<init>()void
		// @271: getstatic java.lang.String[] game.C_100244_pe.field_106380_z
		// @274: bipush 8 (0x08)
		// @276: aaload
		// @277: invokevirtual java.lang.StringBuilder.append(java.lang.String)java.lang.StringBuilder
		// @27A: aload_0
		// @27B: ifnull @288
		// @27E: getstatic java.lang.String[] game.C_100244_pe.field_106380_z
		// @281: bipush 7 (0x07)
		// @283: aaload
		// @284: goto @28E
		// @287: athrow
		// @288: getstatic java.lang.String[] game.C_100244_pe.field_106380_z
		// @28B: bipush 13 (0x0D)
		// @28D: aaload
		// @28E: invokevirtual java.lang.StringBuilder.append(java.lang.String)java.lang.StringBuilder
		// @291: bipush 44 (0x2C)
		// @293: invokevirtual java.lang.StringBuilder.append(char)java.lang.StringBuilder
		// @296: iload_1
		// @297: invokevirtual java.lang.StringBuilder.append(int)java.lang.StringBuilder
		// @29A: bipush 44 (0x2C)
		// @29C: invokevirtual java.lang.StringBuilder.append(char)java.lang.StringBuilder
		// @29F: aload_2
		// @2A0: ifnull @2AD
		// @2A3: getstatic java.lang.String[] game.C_100244_pe.field_106380_z
		// @2A6: bipush 7 (0x07)
		// @2A8: aaload
		// @2A9: goto @2B3
		// @2AC: athrow
		// @2AD: getstatic java.lang.String[] game.C_100244_pe.field_106380_z
		// @2B0: bipush 13 (0x0D)
		// @2B2: aaload
		// @2B3: invokevirtual java.lang.StringBuilder.append(java.lang.String)java.lang.StringBuilder
		// @2B6: bipush 44 (0x2C)
		// @2B8: invokevirtual java.lang.StringBuilder.append(char)java.lang.StringBuilder
		// @2BB: aload_3
		// @2BC: ifnull @2C9
		// @2BF: getstatic java.lang.String[] game.C_100244_pe.field_106380_z
		// @2C2: bipush 7 (0x07)
		// @2C4: aaload
		// @2C5: goto @2CF
		// @2C8: athrow
		// @2C9: getstatic java.lang.String[] game.C_100244_pe.field_106380_z
		// @2CC: bipush 13 (0x0D)
		// @2CE: aaload
		// @2CF: invokevirtual java.lang.StringBuilder.append(java.lang.String)java.lang.StringBuilder
		// @2D2: bipush 41 (0x29)
		// @2D4: invokevirtual java.lang.StringBuilder.append(char)java.lang.StringBuilder
		// @2D7: invokevirtual java.lang.StringBuilder.toString()java.lang.String
		// @2DA: invokestatic game.C_100181_cf.func_105695_a(java.lang.Throwable, java.lang.String)game.C_100170_cm
		// @2DD: athrow
		// @2DE: return
	}
	
	static final URL func_106368_a(int arg0, URL arg1, Applet arg2)
	{
		// @00: aconst_null
		// @01: astore_3
		// @02: iload_0
		// @03: iconst_m1
		// @04: if_icmpeq @19
		// @07: aconst_null
		// @08: checkcast game.C_100280_nf
		// @0B: iconst_0
		// @0C: bipush 89 (0x59)
		// @0E: bipush 30 (0x1E)
		// @10: bipush 50 (0x32)
		// @12: invokestatic game.C_100244_pe.func_106365_a(game.C_100280_nf, boolean, int, int, int)void
		// @15: goto @19
		// @18: athrow
		// @19: aconst_null
		// @1A: getstatic java.lang.String game.C_100186_rl.field_105723_e
		// @1D: if_acmpeq @3B
		// @20: getstatic java.lang.String game.C_100186_rl.field_105723_e
		// @23: aload_2
		// @24: getstatic java.lang.String[] game.C_100244_pe.field_106380_z
		// @27: bipush 18 (0x12)
		// @29: aaload
		// @2A: invokevirtual java.applet.Applet.getParameter(java.lang.String)java.lang.String
		// @2D: invokevirtual java.lang.String.equals(java.lang.Object)boolean
		// @30: ifne @3B
		// @33: goto @37
		// @36: athrow
		// @37: getstatic java.lang.String game.C_100186_rl.field_105723_e
		// @3A: astore_3
		// @3B: aconst_null
		// @3C: astore #4
		// @3E: aconst_null
		// @3F: getstatic java.lang.String game.C_100314_lf.field_101303_Eb
		// @42: if_acmpeq @61
		// @45: getstatic java.lang.String game.C_100314_lf.field_101303_Eb
		// @48: aload_2
		// @49: getstatic java.lang.String[] game.C_100244_pe.field_106380_z
		// @4C: bipush 19 (0x13)
		// @4E: aaload
		// @4F: invokevirtual java.applet.Applet.getParameter(java.lang.String)java.lang.String
		// @52: invokevirtual java.lang.String.equals(java.lang.Object)boolean
		// @55: ifne @61
		// @58: goto @5C
		// @5B: athrow
		// @5C: getstatic java.lang.String game.C_100314_lf.field_101303_Eb
		// @5F: astore #4
		// @61: aload_3
		// @62: bipush -14 (0xF2)
		// @64: aload #4
		// @66: iconst_m1
		// @67: aload_1
		// @68: invokestatic game.C_100278_nd.func_101193_a(java.lang.String, byte, java.lang.String, int, java.net.URL)java.net.URL
		// @6B: areturn
		// @6C: astore_3
		// @6D: aload_3
		// @6E: new java.lang.StringBuilder
		// @71: dup
		// @72: invokespecial java.lang.StringBuilder.<init>()void
		// @75: getstatic java.lang.String[] game.C_100244_pe.field_106380_z
		// @78: bipush 17 (0x11)
		// @7A: aaload
		// @7B: invokevirtual java.lang.StringBuilder.append(java.lang.String)java.lang.StringBuilder
		// @7E: iload_0
		// @7F: invokevirtual java.lang.StringBuilder.append(int)java.lang.StringBuilder
		// @82: bipush 44 (0x2C)
		// @84: invokevirtual java.lang.StringBuilder.append(char)java.lang.StringBuilder
		// @87: aload_1
		// @88: ifnull @95
		// @8B: getstatic java.lang.String[] game.C_100244_pe.field_106380_z
		// @8E: bipush 7 (0x07)
		// @90: aaload
		// @91: goto @9B
		// @94: athrow
		// @95: getstatic java.lang.String[] game.C_100244_pe.field_106380_z
		// @98: bipush 13 (0x0D)
		// @9A: aaload
		// @9B: invokevirtual java.lang.StringBuilder.append(java.lang.String)java.lang.StringBuilder
		// @9E: bipush 44 (0x2C)
		// @A0: invokevirtual java.lang.StringBuilder.append(char)java.lang.StringBuilder
		// @A3: aload_2
		// @A4: ifnull @B1
		// @A7: getstatic java.lang.String[] game.C_100244_pe.field_106380_z
		// @AA: bipush 7 (0x07)
		// @AC: aaload
		// @AD: goto @B7
		// @B0: athrow
		// @B1: getstatic java.lang.String[] game.C_100244_pe.field_106380_z
		// @B4: bipush 13 (0x0D)
		// @B6: aaload
		// @B7: invokevirtual java.lang.StringBuilder.append(java.lang.String)java.lang.StringBuilder
		// @BA: bipush 41 (0x29)
		// @BC: invokevirtual java.lang.StringBuilder.append(char)java.lang.StringBuilder
		// @BF: invokevirtual java.lang.StringBuilder.toString()java.lang.String
		// @C2: invokestatic game.C_100181_cf.func_105695_a(java.lang.Throwable, java.lang.String)game.C_100170_cm
		// @C5: athrow
	}
	
	static final void func_106363_a(int arg0, boolean arg1, int arg2, C_100211_qd arg3)
	{
		// @000: getstatic int game.SteelSentinels.field_105275_O
		// @003: istore #26
		// @005: iload_1
		// @006: ifeq @020
		// @009: getstatic boolean game.C_100226_ae.field_106149_e
		// @00C: ifne @018
		// @00F: goto @013
		// @012: athrow
		// @013: iconst_1
		// @014: goto @019
		// @017: athrow
		// @018: iconst_0
		// @019: istore #4
		// @01B: iload #26
		// @01D: ifeq @03F
		// @020: bipush 92 (0x5C)
		// @022: invokestatic game.C_100227_af.func_106156_a(byte)boolean
		// @025: ifeq @03C
		// @028: goto @02C
		// @02B: athrow
		// @02C: aload_3
		// @02D: getfield boolean game.C_100211_qd.field_102173_Ic
		// @030: ifne @03C
		// @033: goto @037
		// @036: athrow
		// @037: iconst_1
		// @038: goto @03D
		// @03B: athrow
		// @03C: iconst_0
		// @03D: istore #4
		// @03F: iconst_0
		// @040: istore #5
		// @042: iload_1
		// @043: ifne @12D
		// @046: iconst_0
		// @047: istore #6
		// @049: iload #6
		// @04B: iconst_m1
		// @04C: ixor
		// @04D: bipush -6 (0xFA)
		// @04F: if_icmple @0E9
		// @052: iload #4
		// @054: iload #26
		// @056: ifne @0F3
		// @059: ifeq @08D
		// @05C: goto @060
		// @05F: athrow
		// @060: iconst_m1
		// @061: getstatic game.C_100144_bm[][] game.C_100272_mn.field_102434_J
		// @064: iconst_0
		// @065: aaload
		// @066: iload #6
		// @068: iconst_m1
		// @069: isub
		// @06A: aaload
		// @06B: getfield int game.C_100144_bm.field_101854_N
		// @06E: iconst_m1
		// @06F: ixor
		// @070: if_icmpeq @08D
		// @073: goto @077
		// @076: athrow
		// @077: iload #6
		// @079: aload_3
		// @07A: getfield int game.C_100211_qd.field_102159_sc
		// @07D: if_icmpeq @08D
		// @080: goto @084
		// @083: athrow
		// @084: iconst_1
		// @085: istore #5
		// @087: aload_3
		// @088: iload #6
		// @08A: putfield int game.C_100211_qd.field_102159_sc
		// @08D: getstatic game.C_100144_bm[][] game.C_100272_mn.field_102434_J
		// @090: iconst_0
		// @091: aaload
		// @092: iload #6
		// @094: iconst_1
		// @095: iadd
		// @096: aaload
		// @097: iload #4
		// @099: putfield boolean game.C_100144_bm.field_101864_W
		// @09C: getstatic boolean game.C_100273_mm.field_106682_e
		// @09F: ifne @0C1
		// @0A2: iload #6
		// @0A4: iconst_m1
		// @0A5: ixor
		// @0A6: bipush -4 (0xFC)
		// @0A8: if_icmpne @0C1
		// @0AB: goto @0AF
		// @0AE: athrow
		// @0AF: getstatic game.C_100144_bm[][] game.C_100272_mn.field_102434_J
		// @0B2: iconst_0
		// @0B3: aaload
		// @0B4: iload #6
		// @0B6: iconst_m1
		// @0B7: isub
		// @0B8: aaload
		// @0B9: iconst_0
		// @0BA: putfield boolean game.C_100144_bm.field_101864_W
		// @0BD: goto @0C1
		// @0C0: athrow
		// @0C1: getstatic game.C_100144_bm[][] game.C_100272_mn.field_102434_J
		// @0C4: iconst_0
		// @0C5: aaload
		// @0C6: iload #6
		// @0C8: iconst_1
		// @0C9: iadd
		// @0CA: aaload
		// @0CB: iload #6
		// @0CD: iconst_m1
		// @0CE: ixor
		// @0CF: aload_3
		// @0D0: getfield int game.C_100211_qd.field_102159_sc
		// @0D3: iconst_m1
		// @0D4: ixor
		// @0D5: if_icmpne @0DD
		// @0D8: iconst_1
		// @0D9: goto @0DE
		// @0DC: athrow
		// @0DD: iconst_0
		// @0DE: putfield boolean game.C_100144_bm.field_101861_U
		// @0E1: iinc #6 +1
		// @0E4: iload #26
		// @0E6: ifeq @049
		// @0E9: getstatic game.C_100144_bm[][] game.C_100272_mn.field_102434_J
		// @0EC: iconst_0
		// @0ED: aaload
		// @0EE: iconst_2
		// @0EF: aaload
		// @0F0: getfield boolean game.C_100144_bm.field_101836_Hb
		// @0F3: ifne @0F9
		// @0F6: goto @12D
		// @0F9: bipush 89 (0x59)
		// @0FB: invokestatic game.C_100227_af.func_106156_a(byte)boolean
		// @0FE: ifne @123
		// @101: sipush -30945 (0x871F)
		// @104: iconst_1
		// @105: anewarray java.lang.String
		// @108: dup
		// @109: iconst_0
		// @10A: getstatic game.C_100211_qd game.C_100068_vc.field_104342_d
		// @10D: getfield java.lang.String game.C_100211_qd.field_102155_dc
		// @110: aastore
		// @111: getstatic java.lang.String game.C_100100_i.field_102022_ac
		// @114: invokestatic game.C_100132_td.func_104965_a(int, java.lang.String[], java.lang.String)java.lang.String
		// @117: putstatic java.lang.String game.C_100321_hi.field_107220_c
		// @11A: iload #26
		// @11C: ifeq @12D
		// @11F: goto @123
		// @122: athrow
		// @123: getstatic java.lang.String game.C_100053_vn.field_102840_R
		// @126: putstatic java.lang.String game.C_100321_hi.field_107220_c
		// @129: goto @12D
		// @12C: athrow
		// @12D: getstatic int[] game.C_100126_cb.field_103060_v
		// @130: arraylength
		// @131: iconst_m1
		// @132: ixor
		// @133: bipush -3 (0xFD)
		// @135: if_icmple @13C
		// @138: goto @369
		// @13B: athrow
		// @13C: iload_1
		// @13D: ifeq @150
		// @140: iconst_m1
		// @141: getstatic int game.C_100113_ek.field_104876_f
		// @144: if_icmpeq @150
		// @147: goto @14B
		// @14A: athrow
		// @14B: iconst_1
		// @14C: goto @151
		// @14F: athrow
		// @150: iconst_0
		// @151: istore #6
		// @153: iload #6
		// @155: ifne @15C
		// @158: goto @1A2
		// @15B: athrow
		// @15C: getstatic int game.C_100113_ek.field_104876_f
		// @15F: istore #7
		// @161: iconst_0
		// @162: istore #8
		// @164: getstatic byte[] game.C_100217_ao.field_106037_b
		// @167: arraylength
		// @168: iload #8
		// @16A: if_icmple @185
		// @16D: getstatic byte[] game.C_100217_ao.field_106037_b
		// @170: iload #8
		// @172: iconst_0
		// @173: bastore
		// @174: iinc #8 +1
		// @177: iload #26
		// @179: ifne @1A2
		// @17C: iload #26
		// @17E: ifeq @164
		// @181: goto @185
		// @184: athrow
		// @185: getstatic byte[] game.C_100217_ao.field_106037_b
		// @188: iload #7
		// @18A: bipush 8 (0x08)
		// @18C: idiv
		// @18D: getstatic byte[] game.C_100217_ao.field_106037_b
		// @190: iload #7
		// @192: bipush 8 (0x08)
		// @194: idiv
		// @195: baload
		// @196: iconst_1
		// @197: iload #7
		// @199: bipush 8 (0x08)
		// @19B: irem
		// @19C: ishl
		// @19D: invokestatic game.C_100116_ei.func_104117_a(int, int)int
		// @1A0: i2b
		// @1A1: bastore
		// @1A2: iload_1
		// @1A3: ifne @1AB
		// @1A6: iconst_0
		// @1A7: goto @1AC
		// @1AA: athrow
		// @1AB: iconst_m1
		// @1AC: istore #7
		// @1AE: iload #7
		// @1B0: iconst_m1
		// @1B1: ixor
		// @1B2: getstatic int[] game.C_100126_cb.field_103060_v
		// @1B5: arraylength
		// @1B6: iconst_m1
		// @1B7: ixor
		// @1B8: if_icmple @369
		// @1BB: iload #6
		// @1BD: iload #26
		// @1BF: ifne @36A
		// @1C2: ifeq @1DA
		// @1C5: goto @1C9
		// @1C8: athrow
		// @1C9: iload #7
		// @1CB: getstatic int game.C_100113_ek.field_104876_f
		// @1CE: if_icmpeq @1DA
		// @1D1: goto @1D5
		// @1D4: athrow
		// @1D5: iconst_1
		// @1D6: goto @1DB
		// @1D9: athrow
		// @1DA: iconst_0
		// @1DB: istore #8
		// @1DD: iload #4
		// @1DF: ifeq @281
		// @1E2: getstatic game.C_100144_bm[][] game.C_100272_mn.field_102434_J
		// @1E5: iconst_1
		// @1E6: aaload
		// @1E7: iconst_1
		// @1E8: iload #7
		// @1EA: iadd
		// @1EB: aaload
		// @1EC: getfield int game.C_100144_bm.field_101854_N
		// @1EF: ifne @1FA
		// @1F2: goto @1F6
		// @1F5: athrow
		// @1F6: goto @281
		// @1F9: athrow
		// @1FA: iload_1
		// @1FB: ifeq @263
		// @1FE: iload #6
		// @200: ifeq @20B
		// @203: goto @207
		// @206: athrow
		// @207: goto @281
		// @20A: athrow
		// @20B: iload #7
		// @20D: iconst_m1
		// @20E: ixor
		// @20F: ifeq @23A
		// @212: getstatic byte[] game.C_100217_ao.field_106037_b
		// @215: iload #7
		// @217: bipush 8 (0x08)
		// @219: idiv
		// @21A: getstatic byte[] game.C_100217_ao.field_106037_b
		// @21D: iload #7
		// @21F: bipush 8 (0x08)
		// @221: idiv
		// @222: baload
		// @223: iconst_1
		// @224: bipush 7 (0x07)
		// @226: iload #7
		// @228: invokestatic game.C_100256_pk.func_100449_a(int, int)int
		// @22B: ishl
		// @22C: invokestatic game.C_100089_fa.func_103722_a(int, int)int
		// @22F: i2b
		// @230: bastore
		// @231: iload #26
		// @233: ifeq @281
		// @236: goto @23A
		// @239: athrow
		// @23A: iconst_0
		// @23B: istore #9
		// @23D: iload #9
		// @23F: getstatic byte[] game.C_100217_ao.field_106037_b
		// @242: arraylength
		// @243: if_icmpge @25E
		// @246: getstatic byte[] game.C_100217_ao.field_106037_b
		// @249: iload #9
		// @24B: iconst_0
		// @24C: bastore
		// @24D: iinc #9 +1
		// @250: iload #26
		// @252: ifne @281
		// @255: iload #26
		// @257: ifeq @23D
		// @25A: goto @25E
		// @25D: athrow
		// @25E: iload #26
		// @260: ifeq @281
		// @263: getstatic int[] game.C_100126_cb.field_103060_v
		// @266: iload #7
		// @268: iaload
		// @269: istore #9
		// @26B: aload_3
		// @26C: getfield int game.C_100211_qd.field_102160_Zb
		// @26F: iconst_m1
		// @270: ixor
		// @271: iload #9
		// @273: iconst_m1
		// @274: ixor
		// @275: if_icmpeq @281
		// @278: aload_3
		// @279: iload #9
		// @27B: putfield int game.C_100211_qd.field_102160_Zb
		// @27E: iconst_1
		// @27F: istore #5
		// @281: iload_1
		// @282: ifeq @31C
		// @285: iconst_0
		// @286: iload #7
		// @288: iconst_m1
		// @289: ixor
		// @28A: if_icmpeq @2C1
		// @28D: goto @291
		// @290: athrow
		// @291: getstatic game.C_100144_bm[][] game.C_100272_mn.field_102434_J
		// @294: iconst_1
		// @295: aaload
		// @296: iload #7
		// @298: iconst_m1
		// @299: isub
		// @29A: aaload
		// @29B: getstatic byte[] game.C_100217_ao.field_106037_b
		// @29E: iload #7
		// @2A0: bipush 8 (0x08)
		// @2A2: idiv
		// @2A3: baload
		// @2A4: iconst_1
		// @2A5: bipush 7 (0x07)
		// @2A7: iload #7
		// @2A9: iand
		// @2AA: goto @2AE
		// @2AD: athrow
		// @2AE: ishl
		// @2AF: iand
		// @2B0: ifeq @2B8
		// @2B3: iconst_1
		// @2B4: goto @2B9
		// @2B7: athrow
		// @2B8: iconst_0
		// @2B9: putfield boolean game.C_100144_bm.field_101861_U
		// @2BC: iload #26
		// @2BE: ifeq @340
		// @2C1: getstatic game.C_100144_bm[][] game.C_100272_mn.field_102434_J
		// @2C4: iconst_1
		// @2C5: aaload
		// @2C6: iload #7
		// @2C8: iconst_m1
		// @2C9: isub
		// @2CA: aaload
		// @2CB: iconst_1
		// @2CC: putfield boolean game.C_100144_bm.field_101861_U
		// @2CF: iconst_0
		// @2D0: istore #9
		// @2D2: getstatic int[] game.C_100126_cb.field_103060_v
		// @2D5: arraylength
		// @2D6: iload #9
		// @2D8: if_icmple @317
		// @2DB: getstatic game.C_100144_bm[][] game.C_100272_mn.field_102434_J
		// @2DE: iconst_1
		// @2DF: aaload
		// @2E0: iconst_1
		// @2E1: iload #7
		// @2E3: iadd
		// @2E4: aaload
		// @2E5: dup
		// @2E6: getfield boolean game.C_100144_bm.field_101861_U
		// @2E9: getstatic byte[] game.C_100217_ao.field_106037_b
		// @2EC: iload #9
		// @2EE: bipush 8 (0x08)
		// @2F0: idiv
		// @2F1: baload
		// @2F2: iconst_1
		// @2F3: iload #9
		// @2F5: bipush 7 (0x07)
		// @2F7: iand
		// @2F8: ishl
		// @2F9: iand
		// @2FA: iconst_m1
		// @2FB: ixor
		// @2FC: iconst_m1
		// @2FD: iload #26
		// @2FF: ifne @2AE
		// @302: if_icmpne @30A
		// @305: iconst_1
		// @306: goto @30B
		// @309: athrow
		// @30A: iconst_0
		// @30B: iand
		// @30C: putfield boolean game.C_100144_bm.field_101861_U
		// @30F: iinc #9 +1
		// @312: iload #26
		// @314: ifeq @2D2
		// @317: iload #26
		// @319: ifeq @340
		// @31C: getstatic int[] game.C_100126_cb.field_103060_v
		// @31F: iload #7
		// @321: iaload
		// @322: istore #9
		// @324: getstatic game.C_100144_bm[][] game.C_100272_mn.field_102434_J
		// @327: iconst_1
		// @328: aaload
		// @329: iload #7
		// @32B: iconst_m1
		// @32C: isub
		// @32D: aaload
		// @32E: aload_3
		// @32F: getfield int game.C_100211_qd.field_102160_Zb
		// @332: iload #9
		// @334: if_icmpne @33C
		// @337: iconst_1
		// @338: goto @33D
		// @33B: athrow
		// @33C: iconst_0
		// @33D: putfield boolean game.C_100144_bm.field_101861_U
		// @340: getstatic game.C_100144_bm[][] game.C_100272_mn.field_102434_J
		// @343: iconst_1
		// @344: aaload
		// @345: iload #7
		// @347: iconst_1
		// @348: iadd
		// @349: aaload
		// @34A: iload #4
		// @34C: ifeq @35D
		// @34F: iload #8
		// @351: ifne @35D
		// @354: goto @358
		// @357: athrow
		// @358: iconst_1
		// @359: goto @35E
		// @35C: athrow
		// @35D: iconst_0
		// @35E: putfield boolean game.C_100144_bm.field_101864_W
		// @361: iinc #7 +1
		// @364: iload #26
		// @366: ifeq @1AE
		// @369: iload_1
		// @36A: ifeq @372
		// @36D: iconst_0
		// @36E: goto @373
		// @371: athrow
		// @372: iconst_1
		// @373: istore #6
		// @375: bipush -4 (0xFC)
		// @377: iload #6
		// @379: iconst_m1
		// @37A: ixor
		// @37B: if_icmpge @45E
		// @37E: getstatic game.C_100144_bm[][] game.C_100272_mn.field_102434_J
		// @381: iconst_2
		// @382: aaload
		// @383: iload #6
		// @385: aaload
		// @386: astore #7
		// @388: iload #4
		// @38A: iload #26
		// @38C: ifne @45F
		// @38F: ifeq @3EB
		// @392: goto @396
		// @395: athrow
		// @396: aload #7
		// @398: getfield int game.C_100144_bm.field_101854_N
		// @39B: ifeq @3EB
		// @39E: goto @3A2
		// @3A1: athrow
		// @3A2: iload_1
		// @3A3: ifne @3C5
		// @3A6: goto @3AA
		// @3A9: athrow
		// @3AA: aload_3
		// @3AB: getfield int game.C_100211_qd.field_102133_Fc
		// @3AE: iload #6
		// @3B0: if_icmpeq @3EB
		// @3B3: goto @3B7
		// @3B6: athrow
		// @3B7: iconst_1
		// @3B8: istore #5
		// @3BA: aload_3
		// @3BB: iload #6
		// @3BD: putfield int game.C_100211_qd.field_102133_Fc
		// @3C0: iload #26
		// @3C2: ifeq @3EB
		// @3C5: iload #6
		// @3C7: iconst_m1
		// @3C8: ixor
		// @3C9: iconst_m1
		// @3CA: if_icmpeq @3E3
		// @3CD: goto @3D1
		// @3D0: athrow
		// @3D1: getstatic int game.C_100029_gn.field_103366_Q
		// @3D4: iload #6
		// @3D6: ixor
		// @3D7: putstatic int game.C_100029_gn.field_103366_Q
		// @3DA: iload #26
		// @3DC: ifeq @3EB
		// @3DF: goto @3E3
		// @3E2: athrow
		// @3E3: iconst_0
		// @3E4: putstatic int game.C_100029_gn.field_103366_Q
		// @3E7: goto @3EB
		// @3EA: athrow
		// @3EB: aload #7
		// @3ED: iload #4
		// @3EF: putfield boolean game.C_100144_bm.field_101864_W
		// @3F2: iload_1
		// @3F3: ifne @415
		// @3F6: aload #7
		// @3F8: iconst_0
		// @3F9: iload #6
		// @3FB: aload_3
		// @3FC: getfield int game.C_100211_qd.field_102133_Fc
		// @3FF: iand
		// @400: if_icmpeq @40C
		// @403: goto @407
		// @406: athrow
		// @407: iconst_1
		// @408: goto @40D
		// @40B: athrow
		// @40C: iconst_0
		// @40D: putfield boolean game.C_100144_bm.field_101861_U
		// @410: iload #26
		// @412: ifeq @456
		// @415: iconst_m1
		// @416: iload #6
		// @418: iconst_m1
		// @419: ixor
		// @41A: if_icmpne @43E
		// @41D: goto @421
		// @420: athrow
		// @421: aload #7
		// @423: getstatic int game.C_100029_gn.field_103366_Q
		// @426: iconst_m1
		// @427: ixor
		// @428: iconst_m1
		// @429: if_icmpne @435
		// @42C: goto @430
		// @42F: athrow
		// @430: iconst_1
		// @431: goto @436
		// @434: athrow
		// @435: iconst_0
		// @436: putfield boolean game.C_100144_bm.field_101861_U
		// @439: iload #26
		// @43B: ifeq @456
		// @43E: aload #7
		// @440: getstatic int game.C_100029_gn.field_103366_Q
		// @443: iload #6
		// @445: iand
		// @446: ifeq @452
		// @449: goto @44D
		// @44C: athrow
		// @44D: iconst_1
		// @44E: goto @453
		// @451: athrow
		// @452: iconst_0
		// @453: putfield boolean game.C_100144_bm.field_101861_U
		// @456: iinc #6 +1
		// @459: iload #26
		// @45B: ifeq @375
		// @45E: iload_1
		// @45F: ifeq @50E
		// @462: getstatic int game.C_100140_bj.field_102966_e
		// @465: iconst_m1
		// @466: ixor
		// @467: bipush -2 (0xFE)
		// @469: if_icmplt @474
		// @46C: goto @470
		// @46F: athrow
		// @470: goto @50E
		// @473: athrow
		// @474: iconst_0
		// @475: istore #6
		// @477: getstatic int game.C_100140_bj.field_102966_e
		// @47A: iconst_1
		// @47B: iadd
		// @47C: iload #6
		// @47E: if_icmple @50E
		// @481: getstatic game.C_100144_bm[][] game.C_100272_mn.field_102434_J
		// @484: iconst_3
		// @485: aaload
		// @486: iload #6
		// @488: aaload
		// @489: astore #7
		// @48B: iload #4
		// @48D: iload #26
		// @48F: ifne @512
		// @492: ifeq @4AE
		// @495: goto @499
		// @498: athrow
		// @499: aload #7
		// @49B: getfield int game.C_100144_bm.field_101854_N
		// @49E: ifne @4A9
		// @4A1: goto @4A5
		// @4A4: athrow
		// @4A5: goto @4AE
		// @4A8: athrow
		// @4A9: iload #6
		// @4AB: putstatic int game.C_100271_mj.field_103437_P
		// @4AE: aload #7
		// @4B0: getfield boolean game.C_100144_bm.field_101836_Hb
		// @4B3: ifeq @4E8
		// @4B6: iload #6
		// @4B8: ifgt @4C3
		// @4BB: goto @4BF
		// @4BE: athrow
		// @4BF: goto @4E8
		// @4C2: athrow
		// @4C3: aconst_null
		// @4C4: getstatic java.lang.String[] game.C_100302_ka.field_101873_vb
		// @4C7: if_acmpne @4CF
		// @4CA: aconst_null
		// @4CB: goto @4D7
		// @4CE: athrow
		// @4CF: getstatic java.lang.String[] game.C_100302_ka.field_101873_vb
		// @4D2: iconst_m1
		// @4D3: iload #6
		// @4D5: iadd
		// @4D6: aaload
		// @4D7: astore #8
		// @4D9: aconst_null
		// @4DA: aload #8
		// @4DC: if_acmpeq @4E8
		// @4DF: aload #8
		// @4E1: putstatic java.lang.String game.C_100321_hi.field_107220_c
		// @4E4: goto @4E8
		// @4E7: athrow
		// @4E8: aload #7
		// @4EA: iload #4
		// @4EC: putfield boolean game.C_100144_bm.field_101864_W
		// @4EF: aload #7
		// @4F1: getstatic int game.C_100271_mj.field_103437_P
		// @4F4: iconst_m1
		// @4F5: ixor
		// @4F6: iload #6
		// @4F8: iconst_m1
		// @4F9: ixor
		// @4FA: if_icmpne @502
		// @4FD: iconst_1
		// @4FE: goto @503
		// @501: athrow
		// @502: iconst_0
		// @503: putfield boolean game.C_100144_bm.field_101861_U
		// @506: iinc #6 +1
		// @509: iload #26
		// @50B: ifeq @477
		// @50E: iconst_0
		// @50F: istore #6
		// @511: iload_2
		// @512: sipush -15837 (0xC223)
		// @515: if_icmpeq @522
		// @518: bipush 51 (0x33)
		// @51A: iconst_0
		// @51B: invokestatic game.C_100244_pe.func_106373_a(int, boolean)void
		// @51E: goto @522
		// @521: athrow
		// @522: iconst_0
		// @523: istore #7
		// @525: getstatic int game.C_100137_bn.field_105038_l
		// @528: iload #7
		// @52A: if_icmple @D0B
		// @52D: getstatic game.C_100144_bm[][] game.C_100272_mn.field_102434_J
		// @530: iload #7
		// @532: iconst_4
		// @533: iadd
		// @534: aaload
		// @535: astore #8
		// @537: iload_1
		// @538: iload #26
		// @53A: ifne @D0D
		// @53D: ifeq @549
		// @540: goto @544
		// @543: athrow
		// @544: iconst_m1
		// @545: goto @54A
		// @548: athrow
		// @549: iconst_0
		// @54A: istore #9
		// @54C: iload #9
		// @54E: iconst_m1
		// @54F: ixor
		// @550: iconst_m1
		// @551: aload #8
		// @553: arraylength
		// @554: iadd
		// @555: iconst_m1
		// @556: ixor
		// @557: if_icmple @CF4
		// @55A: iconst_0
		// @55B: istore #10
		// @55D: iconst_0
		// @55E: istore #11
		// @560: iconst_0
		// @561: istore #12
		// @563: iconst_0
		// @564: istore #13
		// @566: iconst_0
		// @567: istore #14
		// @569: iconst_0
		// @56A: istore #15
		// @56C: iload #4
		// @56E: iload #26
		// @570: ifne @D01
		// @573: ifeq @6EC
		// @576: goto @57A
		// @579: athrow
		// @57A: iconst_m1
		// @57B: iload #9
		// @57D: iconst_m1
		// @57E: ixor
		// @57F: if_icmpge @58A
		// @582: goto @586
		// @585: athrow
		// @586: goto @6EC
		// @589: athrow
		// @58A: getstatic int[][] game.C_100231_oc.field_102194_Zb
		// @58D: ifnull @5CF
		// @590: aconst_null
		// @591: getstatic int[][] game.C_100231_oc.field_102194_Zb
		// @594: iload #7
		// @596: aaload
		// @597: if_acmpeq @5CF
		// @59A: goto @59E
		// @59D: athrow
		// @59E: iconst_m1
		// @59F: getstatic int game.C_100306_kn.field_107140_k
		// @5A2: iconst_m1
		// @5A3: ixor
		// @5A4: getstatic int[][] game.C_100231_oc.field_102194_Zb
		// @5A7: iload #7
		// @5A9: aaload
		// @5AA: iload #9
		// @5AC: iaload
		// @5AD: iand
		// @5AE: iconst_m1
		// @5AF: ixor
		// @5B0: if_icmple @5CF
		// @5B3: goto @5B7
		// @5B6: athrow
		// @5B7: iconst_1
		// @5B8: istore #14
		// @5BA: iconst_0
		// @5BB: getstatic int game.C_100306_kn.field_107140_k
		// @5BE: iconst_m1
		// @5BF: ixor
		// @5C0: getstatic int[][] game.C_100231_oc.field_102194_Zb
		// @5C3: iload #7
		// @5C5: aaload
		// @5C6: iload #9
		// @5C8: iaload
		// @5C9: iand
		// @5CA: invokestatic game.C_100195_rc.func_105769_a(boolean, int)int
		// @5CD: istore #15
		// @5CF: getstatic boolean[][] game.C_100245_pf.field_106386_d
		// @5D2: ifnull @600
		// @5D5: aconst_null
		// @5D6: getstatic boolean[][] game.C_100245_pf.field_106386_d
		// @5D9: iload #7
		// @5DB: aaload
		// @5DC: if_acmpne @5E7
		// @5DF: goto @5E3
		// @5E2: athrow
		// @5E3: goto @600
		// @5E6: athrow
		// @5E7: getstatic int game.C_100212_qc.field_105976_b
		// @5EA: ifgt @600
		// @5ED: getstatic boolean[][] game.C_100245_pf.field_106386_d
		// @5F0: iload #7
		// @5F2: aaload
		// @5F3: iload #9
		// @5F5: baload
		// @5F6: ifeq @600
		// @5F9: goto @5FD
		// @5FC: athrow
		// @5FD: iconst_1
		// @5FE: istore #10
		// @600: getstatic int[][] game.C_100332_ii.field_107319_k
		// @603: ifnull @657
		// @606: getstatic int[][] game.C_100332_ii.field_107319_k
		// @609: iload #7
		// @60B: aaload
		// @60C: ifnull @657
		// @60F: goto @613
		// @612: athrow
		// @613: getstatic int[][] game.C_100332_ii.field_107319_k
		// @616: iload #7
		// @618: aaload
		// @619: iload #9
		// @61B: iaload
		// @61C: istore #16
		// @61E: iconst_0
		// @61F: iload #16
		// @621: if_icmpge @637
		// @624: iload #16
		// @626: iconst_m1
		// @627: ixor
		// @628: getstatic int game.C_100255_pj.field_105255_s
		// @62B: iconst_m1
		// @62C: ixor
		// @62D: if_icmpge @637
		// @630: goto @634
		// @633: athrow
		// @634: iconst_1
		// @635: istore #12
		// @637: iconst_0
		// @638: iload #16
		// @63A: if_icmpeq @657
		// @63D: getstatic boolean game.C_100154_sl.field_105330_g
		// @640: ifne @657
		// @643: goto @647
		// @646: athrow
		// @647: getstatic int game.C_100212_qc.field_105976_b
		// @64A: iconst_m1
		// @64B: ixor
		// @64C: iconst_m1
		// @64D: if_icmplt @657
		// @650: goto @654
		// @653: athrow
		// @654: iconst_1
		// @655: istore #10
		// @657: getstatic int[][] game.C_100151_bc.field_102939_V
		// @65A: ifnull @6B7
		// @65D: getstatic int[][] game.C_100151_bc.field_102939_V
		// @660: iload #7
		// @662: aaload
		// @663: ifnonnull @66E
		// @666: goto @66A
		// @669: athrow
		// @66A: goto @6B7
		// @66D: athrow
		// @66E: getstatic int[][] game.C_100151_bc.field_102939_V
		// @671: iload #7
		// @673: aaload
		// @674: iload #9
		// @676: iaload
		// @677: istore #16
		// @679: iconst_m1
		// @67A: iload #16
		// @67C: iconst_m1
		// @67D: ixor
		// @67E: if_icmple @694
		// @681: iload #16
		// @683: getstatic int game.C_100022_hf.field_103893_f
		// @686: if_icmpgt @691
		// @689: goto @68D
		// @68C: athrow
		// @68D: goto @694
		// @690: athrow
		// @691: iconst_1
		// @692: istore #11
		// @694: iconst_m1
		// @695: iload #16
		// @697: iconst_m1
		// @698: ixor
		// @699: if_icmpeq @6B7
		// @69C: getstatic boolean game.C_100154_sl.field_105330_g
		// @69F: ifne @6B7
		// @6A2: goto @6A6
		// @6A5: athrow
		// @6A6: getstatic int game.C_100212_qc.field_105976_b
		// @6A9: ifle @6B4
		// @6AC: goto @6B0
		// @6AF: athrow
		// @6B0: goto @6B7
		// @6B3: athrow
		// @6B4: iconst_1
		// @6B5: istore #10
		// @6B7: iload_1
		// @6B8: ifeq @6E9
		// @6BB: aconst_null
		// @6BC: getstatic boolean[][] game.C_100320_hh.field_102912_T
		// @6BF: if_acmpeq @6E9
		// @6C2: goto @6C6
		// @6C5: athrow
		// @6C6: aconst_null
		// @6C7: getstatic boolean[][] game.C_100320_hh.field_102912_T
		// @6CA: iload #7
		// @6CC: aaload
		// @6CD: if_acmpeq @6E9
		// @6D0: goto @6D4
		// @6D3: athrow
		// @6D4: getstatic boolean[][] game.C_100320_hh.field_102912_T
		// @6D7: iload #7
		// @6D9: aaload
		// @6DA: iload #9
		// @6DC: baload
		// @6DD: ifeq @6E9
		// @6E0: goto @6E4
		// @6E3: athrow
		// @6E4: iconst_1
		// @6E5: goto @6EA
		// @6E8: athrow
		// @6E9: iconst_0
		// @6EA: istore #13
		// @6EC: getstatic int game.C_100107_u.field_104770_g
		// @6EF: iconst_2
		// @6F0: if_icmplt @70F
		// @6F3: getstatic boolean[] game.C_100309_lk.field_103258_hb
		// @6F6: bipush 12 (0x0C)
		// @6F8: baload
		// @6F9: ifeq @70F
		// @6FC: goto @700
		// @6FF: athrow
		// @700: iconst_0
		// @701: istore #10
		// @703: iconst_0
		// @704: istore #11
		// @706: iconst_0
		// @707: istore #13
		// @709: iconst_0
		// @70A: istore #12
		// @70C: iconst_0
		// @70D: istore #14
		// @70F: iconst_1
		// @710: putstatic boolean game.C_100049_vf.field_104210_h
		// @713: iload #10
		// @715: ifne @73C
		// @718: iload #11
		// @71A: ifne @73C
		// @71D: goto @721
		// @720: athrow
		// @721: iload #12
		// @723: ifne @73C
		// @726: goto @72A
		// @729: athrow
		// @72A: iload #13
		// @72C: ifne @73C
		// @72F: goto @733
		// @732: athrow
		// @733: iload #14
		// @735: ifeq @741
		// @738: goto @73C
		// @73B: athrow
		// @73C: iconst_1
		// @73D: goto @742
		// @740: athrow
		// @741: iconst_0
		// @742: istore #16
		// @744: iload #16
		// @746: ifne @7EF
		// @749: iconst_m1
		// @74A: iload #9
		// @74C: iconst_m1
		// @74D: ixor
		// @74E: if_icmplt @7EF
		// @751: goto @755
		// @754: athrow
		// @755: getstatic int[][] game.C_100092_um.field_104539_i
		// @758: ifnull @7EF
		// @75B: goto @75F
		// @75E: athrow
		// @75F: iload_1
		// @760: ifeq @771
		// @763: goto @767
		// @766: athrow
		// @767: getstatic boolean game.C_100226_ae.field_106149_e
		// @76A: ifne @7EF
		// @76D: goto @771
		// @770: athrow
		// @771: iconst_0
		// @772: putstatic boolean game.C_100327_ib.field_102503_y
		// @775: iconst_0
		// @776: putstatic boolean game.C_100049_vf.field_104210_h
		// @779: getstatic byte[] game.C_100341_jd.field_102646_ib
		// @77C: ifnonnull @797
		// @77F: goto @783
		// @782: athrow
		// @783: getstatic int game.C_100137_bn.field_105038_l
		// @786: newarray byte[]
		// @788: putstatic byte[] game.C_100341_jd.field_102646_ib
		// @78B: getstatic int game.C_100137_bn.field_105038_l
		// @78E: newarray boolean[]
		// @790: putstatic boolean[] game.C_100207_qh.field_102873_U
		// @793: goto @797
		// @796: athrow
		// @797: iconst_0
		// @798: istore #17
		// @79A: iload #17
		// @79C: iload #7
		// @79E: if_icmpge @7B9
		// @7A1: getstatic boolean[] game.C_100207_qh.field_102873_U
		// @7A4: iload #17
		// @7A6: iconst_0
		// @7A7: bastore
		// @7A8: iinc #17 +1
		// @7AB: iload #26
		// @7AD: ifne @7C6
		// @7B0: iload #26
		// @7B2: ifeq @79A
		// @7B5: goto @7B9
		// @7B8: athrow
		// @7B9: iload #9
		// @7BB: iconst_0
		// @7BC: iload_1
		// @7BD: iconst_1
		// @7BE: iconst_m1
		// @7BF: aload_3
		// @7C0: iload #7
		// @7C2: iconst_m1
		// @7C3: invokestatic game.C_100209_qb.func_102684_a(int, int, boolean, int, int, game.C_100211_qd, int, int)void
		// @7C6: iconst_2
		// @7C7: getstatic int game.C_100107_u.field_104770_g
		// @7CA: if_icmpgt @7E2
		// @7CD: getstatic boolean[] game.C_100309_lk.field_103258_hb
		// @7D0: bipush 12 (0x0C)
		// @7D2: baload
		// @7D3: ifne @7DE
		// @7D6: goto @7DA
		// @7D9: athrow
		// @7DA: goto @7E2
		// @7DD: athrow
		// @7DE: iconst_1
		// @7DF: putstatic boolean game.C_100049_vf.field_104210_h
		// @7E2: getstatic boolean game.C_100049_vf.field_104210_h
		// @7E5: ifeq @7EC
		// @7E8: goto @7EF
		// @7EB: athrow
		// @7EC: iconst_1
		// @7ED: istore #16
		// @7EF: aload #8
		// @7F1: iload #9
		// @7F3: iconst_m1
		// @7F4: isub
		// @7F5: aaload
		// @7F6: astore #17
		// @7F8: iload #4
		// @7FA: ifeq @8C3
		// @7FD: aload #17
		// @7FF: getfield int game.C_100144_bm.field_101854_N
		// @802: iconst_m1
		// @803: ixor
		// @804: iconst_m1
		// @805: if_icmpne @810
		// @808: goto @80C
		// @80B: athrow
		// @80C: goto @8C3
		// @80F: athrow
		// @810: iload_1
		// @811: ifeq @898
		// @814: iconst_m1
		// @815: iload #9
		// @817: if_icmpne @866
		// @81A: goto @81E
		// @81D: athrow
		// @81E: iload #6
		// @820: istore #18
		// @822: iconst_m1
		// @823: aload #8
		// @825: arraylength
		// @826: iadd
		// @827: iload #6
		// @829: iadd
		// @82A: iload #18
		// @82C: if_icmple @861
		// @82F: getstatic byte[] game.C_100132_td.field_104970_f
		// @832: iload #18
		// @834: bipush 8 (0x08)
		// @836: idiv
		// @837: getstatic byte[] game.C_100132_td.field_104970_f
		// @83A: iload #18
		// @83C: bipush 8 (0x08)
		// @83E: idiv
		// @83F: baload
		// @840: iconst_1
		// @841: bipush 7 (0x07)
		// @843: iload #18
		// @845: invokestatic game.C_100256_pk.func_100449_a(int, int)int
		// @848: ishl
		// @849: iconst_m1
		// @84A: ixor
		// @84B: invokestatic game.C_100256_pk.func_100449_a(int, int)int
		// @84E: i2b
		// @84F: bastore
		// @850: iinc #18 +1
		// @853: iload #26
		// @855: ifne @8C3
		// @858: iload #26
		// @85A: ifeq @822
		// @85D: goto @861
		// @860: athrow
		// @861: iload #26
		// @863: ifeq @8C3
		// @866: getstatic byte[] game.C_100132_td.field_104970_f
		// @869: iload #9
		// @86B: iload #6
		// @86D: ineg
		// @86E: isub
		// @86F: bipush 8 (0x08)
		// @871: idiv
		// @872: getstatic byte[] game.C_100132_td.field_104970_f
		// @875: iload #9
		// @877: iload #6
		// @879: iadd
		// @87A: bipush 8 (0x08)
		// @87C: idiv
		// @87D: baload
		// @87E: iconst_1
		// @87F: iload #6
		// @881: iload #9
		// @883: iadd
		// @884: bipush 7 (0x07)
		// @886: invokestatic game.C_100256_pk.func_100449_a(int, int)int
		// @889: ishl
		// @88A: invokestatic game.C_100089_fa.func_103722_a(int, int)int
		// @88D: i2b
		// @88E: bastore
		// @88F: iload #26
		// @891: ifeq @8C3
		// @894: goto @898
		// @897: athrow
		// @898: iload #16
		// @89A: ifne @8C3
		// @89D: goto @8A1
		// @8A0: athrow
		// @8A1: iload #9
		// @8A3: i2b
		// @8A4: aload_3
		// @8A5: getfield byte[] game.C_100211_qd.field_102165_jc
		// @8A8: iload #7
		// @8AA: baload
		// @8AB: if_icmpne @8B6
		// @8AE: goto @8B2
		// @8B1: athrow
		// @8B2: goto @8C3
		// @8B5: athrow
		// @8B6: iconst_1
		// @8B7: istore #5
		// @8B9: aload_3
		// @8BA: getfield byte[] game.C_100211_qd.field_102165_jc
		// @8BD: iload #7
		// @8BF: iload #9
		// @8C1: i2b
		// @8C2: bastore
		// @8C3: iload_1
		// @8C4: ifeq @8FF
		// @8C7: iload #16
		// @8C9: ifne @8D4
		// @8CC: goto @8D0
		// @8CF: athrow
		// @8D0: goto @8FF
		// @8D3: athrow
		// @8D4: getstatic byte[] game.C_100132_td.field_104970_f
		// @8D7: iload #9
		// @8D9: iload #6
		// @8DB: ineg
		// @8DC: isub
		// @8DD: bipush 8 (0x08)
		// @8DF: idiv
		// @8E0: getstatic byte[] game.C_100132_td.field_104970_f
		// @8E3: iload #9
		// @8E5: iload #6
		// @8E7: iadd
		// @8E8: bipush 8 (0x08)
		// @8EA: idiv
		// @8EB: baload
		// @8EC: iconst_1
		// @8ED: iload #9
		// @8EF: iload #6
		// @8F1: iadd
		// @8F2: bipush 7 (0x07)
		// @8F4: invokestatic game.C_100256_pk.func_100449_a(int, int)int
		// @8F7: ishl
		// @8F8: iconst_m1
		// @8F9: ixor
		// @8FA: invokestatic game.C_100256_pk.func_100449_a(int, int)int
		// @8FD: i2b
		// @8FE: bastore
		// @8FF: iload #9
		// @901: iflt @C17
		// @904: aload #17
		// @906: getfield boolean game.C_100144_bm.field_101836_Hb
		// @909: ifne @914
		// @90C: goto @910
		// @90F: athrow
		// @910: goto @C17
		// @913: athrow
		// @914: aconst_null
		// @915: getstatic java.lang.String[][] game.C_100086_uh.field_103031_r
		// @918: if_acmpne @920
		// @91B: aconst_null
		// @91C: goto @938
		// @91F: athrow
		// @920: aconst_null
		// @921: getstatic java.lang.String[][] game.C_100086_uh.field_103031_r
		// @924: iload #7
		// @926: aaload
		// @927: if_acmpeq @937
		// @92A: getstatic java.lang.String[][] game.C_100086_uh.field_103031_r
		// @92D: iload #7
		// @92F: aaload
		// @930: iload #9
		// @932: aaload
		// @933: goto @938
		// @936: athrow
		// @937: aconst_null
		// @938: astore #18
		// @93A: aconst_null
		// @93B: getstatic java.lang.String[][] game.C_100047_vh.field_104153_c
		// @93E: if_acmpeq @960
		// @941: aconst_null
		// @942: getstatic java.lang.String[][] game.C_100047_vh.field_104153_c
		// @945: iload #7
		// @947: aaload
		// @948: if_acmpeq @95C
		// @94B: goto @94F
		// @94E: athrow
		// @94F: getstatic java.lang.String[][] game.C_100047_vh.field_104153_c
		// @952: iload #7
		// @954: aaload
		// @955: iload #9
		// @957: aaload
		// @958: goto @961
		// @95B: athrow
		// @95C: aconst_null
		// @95D: goto @961
		// @960: aconst_null
		// @961: astore #19
		// @963: aconst_null
		// @964: astore #20
		// @966: aload #19
		// @968: ifnull @97D
		// @96B: aload #19
		// @96D: aload #18
		// @96F: invokevirtual java.lang.String.equals(java.lang.Object)boolean
		// @972: ifne @97D
		// @975: goto @979
		// @978: athrow
		// @979: aload #19
		// @97B: astore #20
		// @97D: aconst_null
		// @97E: astore #21
		// @980: iload #13
		// @982: ifne @AA7
		// @985: iload #10
		// @987: ifne @A9F
		// @98A: goto @98E
		// @98D: athrow
		// @98E: iload #11
		// @990: ifne @99B
		// @993: goto @997
		// @996: athrow
		// @997: goto @9D0
		// @99A: athrow
		// @99B: getstatic int game.C_100022_hf.field_103893_f
		// @99E: ineg
		// @99F: getstatic int[][] game.C_100151_bc.field_102939_V
		// @9A2: iload #7
		// @9A4: aaload
		// @9A5: iload #9
		// @9A7: iaload
		// @9A8: iadd
		// @9A9: istore #22
		// @9AB: iconst_1
		// @9AC: iload #22
		// @9AE: if_icmpne @9B9
		// @9B1: getstatic java.lang.String game.C_100033_gj.field_101919_ic
		// @9B4: astore #21
		// @9B6: goto @9D0
		// @9B9: sipush -30945 (0x871F)
		// @9BC: iconst_1
		// @9BD: anewarray java.lang.String
		// @9C0: dup
		// @9C1: iconst_0
		// @9C2: iload #22
		// @9C4: invokestatic java.lang.Integer.toString(int)java.lang.String
		// @9C7: aastore
		// @9C8: getstatic java.lang.String game.C_100328_ia.field_107261_a
		// @9CB: invokestatic game.C_100132_td.func_104965_a(int, java.lang.String[], java.lang.String)java.lang.String
		// @9CE: astore #21
		// @9D0: iload #12
		// @9D2: ifeq @A2C
		// @9D5: iload_2
		// @9D6: sipush -15108 (0xC4FC)
		// @9D9: iadd
		// @9DA: iconst_2
		// @9DB: anewarray java.lang.String
		// @9DE: dup
		// @9DF: iconst_0
		// @9E0: getstatic int game.C_100255_pj.field_105255_s
		// @9E3: invokestatic java.lang.Integer.toString(int)java.lang.String
		// @9E6: aastore
		// @9E7: dup
		// @9E8: iconst_1
		// @9E9: getstatic int[][] game.C_100332_ii.field_107319_k
		// @9EC: iload #7
		// @9EE: aaload
		// @9EF: iload #9
		// @9F1: iaload
		// @9F2: invokestatic java.lang.Integer.toString(int)java.lang.String
		// @9F5: aastore
		// @9F6: getstatic java.lang.String game.C_100228_nn.field_106195_i
		// @9F9: invokestatic game.C_100132_td.func_104965_a(int, java.lang.String[], java.lang.String)java.lang.String
		// @9FC: astore #22
		// @9FE: aconst_null
		// @9FF: aload #21
		// @A01: if_acmpeq @A28
		// @A04: new java.lang.StringBuilder
		// @A07: dup
		// @A08: invokespecial java.lang.StringBuilder.<init>()void
		// @A0B: aload #21
		// @A0D: invokevirtual java.lang.StringBuilder.append(java.lang.String)java.lang.StringBuilder
		// @A10: getstatic java.lang.String[] game.C_100244_pe.field_106380_z
		// @A13: bipush 25 (0x19)
		// @A15: aaload
		// @A16: invokevirtual java.lang.StringBuilder.append(java.lang.String)java.lang.StringBuilder
		// @A19: aload #22
		// @A1B: invokevirtual java.lang.StringBuilder.append(java.lang.String)java.lang.StringBuilder
		// @A1E: invokevirtual java.lang.StringBuilder.toString()java.lang.String
		// @A21: astore #21
		// @A23: iload #26
		// @A25: ifeq @A2C
		// @A28: aload #22
		// @A2A: astore #21
		// @A2C: iload #14
		// @A2E: ifeq @AAC
		// @A31: getstatic java.lang.String game.C_100031_gl.field_103971_h
		// @A34: astore #22
		// @A36: iload #15
		// @A38: ifle @A6E
		// @A3B: aconst_null
		// @A3C: getstatic java.lang.String[][] game.C_100339_jb.field_107384_c
		// @A3F: if_acmpeq @A6E
		// @A42: goto @A46
		// @A45: athrow
		// @A46: iload #15
		// @A48: getstatic java.lang.String[][] game.C_100339_jb.field_107384_c
		// @A4B: arraylength
		// @A4C: if_icmpgt @A6E
		// @A4F: goto @A53
		// @A52: athrow
		// @A53: getstatic java.lang.String[][] game.C_100339_jb.field_107384_c
		// @A56: iload #15
		// @A58: iconst_m1
		// @A59: iadd
		// @A5A: aaload
		// @A5B: ifnull @A6E
		// @A5E: goto @A62
		// @A61: athrow
		// @A62: getstatic java.lang.String[][] game.C_100339_jb.field_107384_c
		// @A65: iconst_m1
		// @A66: iload #15
		// @A68: iadd
		// @A69: aaload
		// @A6A: iconst_0
		// @A6B: aaload
		// @A6C: astore #22
		// @A6E: aconst_null
		// @A6F: aload #21
		// @A71: if_acmpeq @A98
		// @A74: new java.lang.StringBuilder
		// @A77: dup
		// @A78: invokespecial java.lang.StringBuilder.<init>()void
		// @A7B: aload #21
		// @A7D: invokevirtual java.lang.StringBuilder.append(java.lang.String)java.lang.StringBuilder
		// @A80: getstatic java.lang.String[] game.C_100244_pe.field_106380_z
		// @A83: bipush 25 (0x19)
		// @A85: aaload
		// @A86: invokevirtual java.lang.StringBuilder.append(java.lang.String)java.lang.StringBuilder
		// @A89: aload #22
		// @A8B: invokevirtual java.lang.StringBuilder.append(java.lang.String)java.lang.StringBuilder
		// @A8E: invokevirtual java.lang.StringBuilder.toString()java.lang.String
		// @A91: astore #21
		// @A93: iload #26
		// @A95: ifeq @A9C
		// @A98: aload #22
		// @A9A: astore #21
		// @A9C: goto @AAC
		// @A9F: getstatic java.lang.String game.C_100041_wf.field_104106_b
		// @AA2: astore #21
		// @AA4: goto @AAC
		// @AA7: getstatic java.lang.String game.C_100010_ff.field_103703_w
		// @AAA: astore #21
		// @AAC: iload #4
		// @AAE: ifeq @BA5
		// @AB1: getstatic boolean game.C_100049_vf.field_104210_h
		// @AB4: ifne @BA5
		// @AB7: goto @ABB
		// @ABA: athrow
		// @ABB: aconst_null
		// @ABC: astore #22
		// @ABE: getstatic boolean game.C_100327_ib.field_102503_y
		// @AC1: ifeq @AE8
		// @AC4: new java.lang.StringBuilder
		// @AC7: dup
		// @AC8: invokespecial java.lang.StringBuilder.<init>()void
		// @ACB: getstatic java.lang.String[] game.C_100244_pe.field_106380_z
		// @ACE: bipush 26 (0x1A)
		// @AD0: aaload
		// @AD1: invokevirtual java.lang.StringBuilder.append(java.lang.String)java.lang.StringBuilder
		// @AD4: getstatic java.lang.String game.C_100332_ii.field_107312_c
		// @AD7: invokevirtual java.lang.StringBuilder.append(java.lang.String)java.lang.StringBuilder
		// @ADA: getstatic java.lang.String[] game.C_100244_pe.field_106380_z
		// @ADD: bipush 24 (0x18)
		// @ADF: aaload
		// @AE0: invokevirtual java.lang.StringBuilder.append(java.lang.String)java.lang.StringBuilder
		// @AE3: invokevirtual java.lang.StringBuilder.toString()java.lang.String
		// @AE6: astore #22
		// @AE8: iconst_0
		// @AE9: istore #23
		// @AEB: iconst_0
		// @AEC: istore #24
		// @AEE: iload #7
		// @AF0: iconst_m1
		// @AF1: ixor
		// @AF2: iload #24
		// @AF4: iconst_m1
		// @AF5: ixor
		// @AF6: if_icmpge @B6E
		// @AF9: getstatic boolean[] game.C_100207_qh.field_102873_U
		// @AFC: iload #24
		// @AFE: baload
		// @AFF: iload #26
		// @B01: ifne @B70
		// @B04: ifne @B0E
		// @B07: goto @B0B
		// @B0A: athrow
		// @B0B: goto @B66
		// @B0E: new java.lang.StringBuilder
		// @B11: dup
		// @B12: invokespecial java.lang.StringBuilder.<init>()void
		// @B15: getstatic java.lang.String[] game.C_100244_pe.field_106380_z
		// @B18: bipush 26 (0x1A)
		// @B1A: aaload
		// @B1B: invokevirtual java.lang.StringBuilder.append(java.lang.String)java.lang.StringBuilder
		// @B1E: getstatic java.lang.String[] game.C_100036_gg.field_103155_R
		// @B21: iload #24
		// @B23: aaload
		// @B24: invokevirtual java.lang.StringBuilder.append(java.lang.String)java.lang.StringBuilder
		// @B27: getstatic java.lang.String[] game.C_100244_pe.field_106380_z
		// @B2A: bipush 24 (0x18)
		// @B2C: aaload
		// @B2D: invokevirtual java.lang.StringBuilder.append(java.lang.String)java.lang.StringBuilder
		// @B30: invokevirtual java.lang.StringBuilder.toString()java.lang.String
		// @B33: astore #25
		// @B35: aconst_null
		// @B36: aload #22
		// @B38: if_acmpne @B44
		// @B3B: aload #25
		// @B3D: astore #22
		// @B3F: iload #26
		// @B41: ifeq @B66
		// @B44: iconst_1
		// @B45: istore #23
		// @B47: new java.lang.StringBuilder
		// @B4A: dup
		// @B4B: invokespecial java.lang.StringBuilder.<init>()void
		// @B4E: aload #22
		// @B50: invokevirtual java.lang.StringBuilder.append(java.lang.String)java.lang.StringBuilder
		// @B53: getstatic java.lang.String[] game.C_100244_pe.field_106380_z
		// @B56: bipush 23 (0x17)
		// @B58: aaload
		// @B59: invokevirtual java.lang.StringBuilder.append(java.lang.String)java.lang.StringBuilder
		// @B5C: aload #25
		// @B5E: invokevirtual java.lang.StringBuilder.append(java.lang.String)java.lang.StringBuilder
		// @B61: invokevirtual java.lang.StringBuilder.toString()java.lang.String
		// @B64: astore #22
		// @B66: iinc #24 +1
		// @B69: iload #26
		// @B6B: ifeq @AEE
		// @B6E: iload #23
		// @B70: ifne @B8E
		// @B73: iload_2
		// @B74: sipush 17724 (0x453C)
		// @B77: ixor
		// @B78: iconst_1
		// @B79: anewarray java.lang.String
		// @B7C: dup
		// @B7D: iconst_0
		// @B7E: aload #22
		// @B80: aastore
		// @B81: getstatic java.lang.String game.C_100140_bj.field_102969_a
		// @B84: invokestatic game.C_100132_td.func_104965_a(int, java.lang.String[], java.lang.String)java.lang.String
		// @B87: astore #21
		// @B89: iload #26
		// @B8B: ifeq @BA5
		// @B8E: new java.lang.StringBuilder
		// @B91: dup
		// @B92: invokespecial java.lang.StringBuilder.<init>()void
		// @B95: getstatic java.lang.String game.C_100298_ke.field_103212_W
		// @B98: invokevirtual java.lang.StringBuilder.append(java.lang.String)java.lang.StringBuilder
		// @B9B: aload #22
		// @B9D: invokevirtual java.lang.StringBuilder.append(java.lang.String)java.lang.StringBuilder
		// @BA0: invokevirtual java.lang.StringBuilder.toString()java.lang.String
		// @BA3: astore #21
		// @BA5: aconst_null
		// @BA6: aload #21
		// @BA8: if_acmpeq @C09
		// @BAB: new java.lang.StringBuilder
		// @BAE: dup
		// @BAF: invokespecial java.lang.StringBuilder.<init>()void
		// @BB2: getstatic java.lang.String[] game.C_100244_pe.field_106380_z
		// @BB5: bipush 24 (0x18)
		// @BB7: aaload
		// @BB8: invokevirtual java.lang.StringBuilder.append(java.lang.String)java.lang.StringBuilder
		// @BBB: aload #21
		// @BBD: invokevirtual java.lang.StringBuilder.append(java.lang.String)java.lang.StringBuilder
		// @BC0: invokevirtual java.lang.StringBuilder.toString()java.lang.String
		// @BC3: astore #21
		// @BC5: getstatic java.lang.String[] game.C_100244_pe.field_106380_z
		// @BC8: bipush 27 (0x1B)
		// @BCA: aaload
		// @BCB: aload #21
		// @BCD: sipush 25557 (0x63D5)
		// @BD0: getstatic java.lang.String[] game.C_100244_pe.field_106380_z
		// @BD3: bipush 25 (0x19)
		// @BD5: aaload
		// @BD6: invokestatic game.C_100018_wk.func_101497_a(java.lang.String, java.lang.String, int, java.lang.String)java.lang.String
		// @BD9: astore #21
		// @BDB: aconst_null
		// @BDC: aload #20
		// @BDE: if_acmpeq @C05
		// @BE1: new java.lang.StringBuilder
		// @BE4: dup
		// @BE5: invokespecial java.lang.StringBuilder.<init>()void
		// @BE8: aload #20
		// @BEA: invokevirtual java.lang.StringBuilder.append(java.lang.String)java.lang.StringBuilder
		// @BED: getstatic java.lang.String[] game.C_100244_pe.field_106380_z
		// @BF0: bipush 25 (0x19)
		// @BF2: aaload
		// @BF3: invokevirtual java.lang.StringBuilder.append(java.lang.String)java.lang.StringBuilder
		// @BF6: aload #21
		// @BF8: invokevirtual java.lang.StringBuilder.append(java.lang.String)java.lang.StringBuilder
		// @BFB: invokevirtual java.lang.StringBuilder.toString()java.lang.String
		// @BFE: astore #20
		// @C00: iload #26
		// @C02: ifeq @C09
		// @C05: aload #21
		// @C07: astore #20
		// @C09: aload #20
		// @C0B: ifnull @C17
		// @C0E: aload #20
		// @C10: putstatic java.lang.String game.C_100321_hi.field_107220_c
		// @C13: goto @C17
		// @C16: athrow
		// @C17: iload_1
		// @C18: ifeq @CA9
		// @C1B: iload #9
		// @C1D: iconst_m1
		// @C1E: if_icmpeq @C57
		// @C21: goto @C25
		// @C24: athrow
		// @C25: aload #17
		// @C27: iconst_m1
		// @C28: getstatic byte[] game.C_100132_td.field_104970_f
		// @C2B: iload #6
		// @C2D: iload #9
		// @C2F: ineg
		// @C30: isub
		// @C31: bipush 8 (0x08)
		// @C33: idiv
		// @C34: baload
		// @C35: iconst_1
		// @C36: bipush 7 (0x07)
		// @C38: iload #9
		// @C3A: iload #6
		// @C3C: iadd
		// @C3D: iand
		// @C3E: ishl
		// @C3F: iand
		// @C40: iconst_m1
		// @C41: ixor
		// @C42: if_icmpeq @C4E
		// @C45: goto @C49
		// @C48: athrow
		// @C49: iconst_1
		// @C4A: goto @C4F
		// @C4D: athrow
		// @C4E: iconst_0
		// @C4F: putfield boolean game.C_100144_bm.field_101861_U
		// @C52: iload #26
		// @C54: ifeq @CD3
		// @C57: aload #17
		// @C59: iconst_1
		// @C5A: putfield boolean game.C_100144_bm.field_101861_U
		// @C5D: iload #6
		// @C5F: istore #18
		// @C61: iload #18
		// @C63: iconst_m1
		// @C64: aload #8
		// @C66: arraylength
		// @C67: iadd
		// @C68: iload #6
		// @C6A: iadd
		// @C6B: if_icmpge @CA4
		// @C6E: aload #17
		// @C70: dup
		// @C71: getfield boolean game.C_100144_bm.field_101861_U
		// @C74: iconst_0
		// @C75: getstatic byte[] game.C_100132_td.field_104970_f
		// @C78: iload #18
		// @C7A: bipush 8 (0x08)
		// @C7C: idiv
		// @C7D: baload
		// @C7E: iconst_1
		// @C7F: bipush 7 (0x07)
		// @C81: iload #18
		// @C83: iand
		// @C84: ishl
		// @C85: iand
		// @C86: iload #26
		// @C88: ifne @CC6
		// @C8B: if_icmpne @C97
		// @C8E: goto @C92
		// @C91: athrow
		// @C92: iconst_1
		// @C93: goto @C98
		// @C96: athrow
		// @C97: iconst_0
		// @C98: iand
		// @C99: putfield boolean game.C_100144_bm.field_101861_U
		// @C9C: iinc #18 +1
		// @C9F: iload #26
		// @CA1: ifeq @C61
		// @CA4: iload #26
		// @CA6: ifeq @CD3
		// @CA9: aload #17
		// @CAB: getstatic boolean game.C_100049_vf.field_104210_h
		// @CAE: ifeq @CCF
		// @CB1: goto @CB5
		// @CB4: athrow
		// @CB5: aload_3
		// @CB6: getfield byte[] game.C_100211_qd.field_102165_jc
		// @CB9: iload #7
		// @CBB: baload
		// @CBC: iconst_m1
		// @CBD: ixor
		// @CBE: iload #9
		// @CC0: i2b
		// @CC1: iconst_m1
		// @CC2: goto @CC6
		// @CC5: athrow
		// @CC6: ixor
		// @CC7: if_icmpne @CCF
		// @CCA: iconst_1
		// @CCB: goto @CD0
		// @CCE: athrow
		// @CCF: iconst_0
		// @CD0: putfield boolean game.C_100144_bm.field_101861_U
		// @CD3: aload #17
		// @CD5: iload #4
		// @CD7: ifeq @CE8
		// @CDA: iload #16
		// @CDC: ifne @CE8
		// @CDF: goto @CE3
		// @CE2: athrow
		// @CE3: iconst_1
		// @CE4: goto @CE9
		// @CE7: athrow
		// @CE8: iconst_0
		// @CE9: putfield boolean game.C_100144_bm.field_101864_W
		// @CEC: iinc #9 +1
		// @CEF: iload #26
		// @CF1: ifeq @54C
		// @CF4: iload #6
		// @CF6: getstatic byte[] game.C_100019_wl.field_103840_f
		// @CF9: iload #7
		// @CFB: baload
		// @CFC: sipush 255 (0x00FF)
		// @CFF: iand
		// @D00: iadd
		// @D01: istore #6
		// @D03: iinc #7 +1
		// @D06: iload #26
		// @D08: ifeq @525
		// @D0B: iload #5
		// @D0D: ifeq @D22
		// @D10: iload_1
		// @D11: ifeq @D1C
		// @D14: goto @D18
		// @D17: athrow
		// @D18: goto @D22
		// @D1B: athrow
		// @D1C: iload_0
		// @D1D: bipush -98 (0x9E)
		// @D1F: invokestatic game.C_100200_ba.func_105838_b(int, int)void
		// @D22: goto @D77
		// @D25: astore #4
		// @D27: aload #4
		// @D29: new java.lang.StringBuilder
		// @D2C: dup
		// @D2D: invokespecial java.lang.StringBuilder.<init>()void
		// @D30: getstatic java.lang.String[] game.C_100244_pe.field_106380_z
		// @D33: bipush 22 (0x16)
		// @D35: aaload
		// @D36: invokevirtual java.lang.StringBuilder.append(java.lang.String)java.lang.StringBuilder
		// @D39: iload_0
		// @D3A: invokevirtual java.lang.StringBuilder.append(int)java.lang.StringBuilder
		// @D3D: bipush 44 (0x2C)
		// @D3F: invokevirtual java.lang.StringBuilder.append(char)java.lang.StringBuilder
		// @D42: iload_1
		// @D43: invokevirtual java.lang.StringBuilder.append(boolean)java.lang.StringBuilder
		// @D46: bipush 44 (0x2C)
		// @D48: invokevirtual java.lang.StringBuilder.append(char)java.lang.StringBuilder
		// @D4B: iload_2
		// @D4C: invokevirtual java.lang.StringBuilder.append(int)java.lang.StringBuilder
		// @D4F: bipush 44 (0x2C)
		// @D51: invokevirtual java.lang.StringBuilder.append(char)java.lang.StringBuilder
		// @D54: aload_3
		// @D55: ifnull @D62
		// @D58: getstatic java.lang.String[] game.C_100244_pe.field_106380_z
		// @D5B: bipush 7 (0x07)
		// @D5D: aaload
		// @D5E: goto @D68
		// @D61: athrow
		// @D62: getstatic java.lang.String[] game.C_100244_pe.field_106380_z
		// @D65: bipush 13 (0x0D)
		// @D67: aaload
		// @D68: invokevirtual java.lang.StringBuilder.append(java.lang.String)java.lang.StringBuilder
		// @D6B: bipush 41 (0x29)
		// @D6D: invokevirtual java.lang.StringBuilder.append(char)java.lang.StringBuilder
		// @D70: invokevirtual java.lang.StringBuilder.toString()java.lang.String
		// @D73: invokestatic game.C_100181_cf.func_105695_a(java.lang.Throwable, java.lang.String)game.C_100170_cm
		// @D76: athrow
		// @D77: return
	}
	
	static final void func_106365_a(C_100280_nf arg0, boolean arg1, int arg2, int arg3, int arg4)
	{
		// @00: aload_0
		// @01: sipush 7838 (0x1E9E)
		// @04: bipush 12 (0x0C)
		// @06: invokevirtual game.C_100280_nf.func_101169_f(int, int)void
		// @09: aload_0
		// @0A: bipush 17 (0x11)
		// @0C: bipush 109 (0x6D)
		// @0E: invokevirtual game.C_100280_nf.func_101141_d(int, byte)void
		// @11: iload_1
		// @12: iconst_1
		// @13: if_icmpeq @1E
		// @16: iconst_0
		// @17: putstatic boolean game.C_100244_pe.field_106377_b
		// @1A: goto @1E
		// @1D: athrow
		// @1E: aload_0
		// @1F: iload_2
		// @20: bipush -59 (0xC5)
		// @22: invokevirtual game.C_100280_nf.func_101141_d(int, byte)void
		// @25: aload_0
		// @26: iload_3
		// @27: bipush 93 (0x5D)
		// @29: invokevirtual game.C_100280_nf.func_101141_d(int, byte)void
		// @2C: aload_0
		// @2D: sipush 7838 (0x1E9E)
		// @30: iload #4
		// @32: invokevirtual game.C_100280_nf.func_101169_f(int, int)void
		// @35: goto @94
		// @38: astore #5
		// @3A: aload #5
		// @3C: new java.lang.StringBuilder
		// @3F: dup
		// @40: invokespecial java.lang.StringBuilder.<init>()void
		// @43: getstatic java.lang.String[] game.C_100244_pe.field_106380_z
		// @46: bipush 29 (0x1D)
		// @48: aaload
		// @49: invokevirtual java.lang.StringBuilder.append(java.lang.String)java.lang.StringBuilder
		// @4C: aload_0
		// @4D: ifnull @5A
		// @50: getstatic java.lang.String[] game.C_100244_pe.field_106380_z
		// @53: bipush 7 (0x07)
		// @55: aaload
		// @56: goto @60
		// @59: athrow
		// @5A: getstatic java.lang.String[] game.C_100244_pe.field_106380_z
		// @5D: bipush 13 (0x0D)
		// @5F: aaload
		// @60: invokevirtual java.lang.StringBuilder.append(java.lang.String)java.lang.StringBuilder
		// @63: bipush 44 (0x2C)
		// @65: invokevirtual java.lang.StringBuilder.append(char)java.lang.StringBuilder
		// @68: iload_1
		// @69: invokevirtual java.lang.StringBuilder.append(boolean)java.lang.StringBuilder
		// @6C: bipush 44 (0x2C)
		// @6E: invokevirtual java.lang.StringBuilder.append(char)java.lang.StringBuilder
		// @71: iload_2
		// @72: invokevirtual java.lang.StringBuilder.append(int)java.lang.StringBuilder
		// @75: bipush 44 (0x2C)
		// @77: invokevirtual java.lang.StringBuilder.append(char)java.lang.StringBuilder
		// @7A: iload_3
		// @7B: invokevirtual java.lang.StringBuilder.append(int)java.lang.StringBuilder
		// @7E: bipush 44 (0x2C)
		// @80: invokevirtual java.lang.StringBuilder.append(char)java.lang.StringBuilder
		// @83: iload #4
		// @85: invokevirtual java.lang.StringBuilder.append(int)java.lang.StringBuilder
		// @88: bipush 41 (0x29)
		// @8A: invokevirtual java.lang.StringBuilder.append(char)java.lang.StringBuilder
		// @8D: invokevirtual java.lang.StringBuilder.toString()java.lang.String
		// @90: invokestatic game.C_100181_cf.func_105695_a(java.lang.Throwable, java.lang.String)game.C_100170_cm
		// @93: athrow
		// @94: return
	}
	
	static final void func_106367_a(int arg0, boolean arg1, int arg2, boolean arg3)
	{
		// @00: getstatic int game.SteelSentinels.field_105275_O
		// @03: istore #5
		// @05: iload_2
		// @06: bipush -120 (0x88)
		// @08: if_icmplt @0C
		// @0B: return
		// @0C: iconst_0
		// @0D: iload_0
		// @0E: iconst_m1
		// @0F: ixor
		// @10: if_icmpne @22
		// @13: iload_3
		// @14: bipush -101 (0x9B)
		// @16: invokestatic game.C_100260_mc.func_102222_a(boolean, int)void
		// @19: iload #5
		// @1B: ifeq @55
		// @1E: goto @22
		// @21: athrow
		// @22: iconst_1
		// @23: iload_0
		// @24: iconst_m1
		// @25: ixor
		// @26: if_icmpne @39
		// @29: goto @2D
		// @2C: athrow
		// @2D: invokestatic game.C_100196_rb.func_105792_b()void
		// @30: iload #5
		// @32: ifeq @55
		// @35: goto @39
		// @38: athrow
		// @39: iload_1
		// @3A: ifne @45
		// @3D: goto @41
		// @40: athrow
		// @41: goto @4B
		// @44: athrow
		// @45: iconst_0
		// @46: bipush -67 (0xBD)
		// @48: invokestatic game.C_100260_mc.func_102222_a(boolean, int)void
		// @4B: getstatic game.C_100034_gi[] game.C_100295_kh.field_105293_c
		// @4E: iload_0
		// @4F: aaload
		// @50: bipush 82 (0x52)
		// @52: invokevirtual game.C_100034_gi.func_104013_a(byte)void
		// @55: goto @96
		// @58: astore #4
		// @5A: aload #4
		// @5C: new java.lang.StringBuilder
		// @5F: dup
		// @60: invokespecial java.lang.StringBuilder.<init>()void
		// @63: getstatic java.lang.String[] game.C_100244_pe.field_106380_z
		// @66: iconst_0
		// @67: aaload
		// @68: invokevirtual java.lang.StringBuilder.append(java.lang.String)java.lang.StringBuilder
		// @6B: iload_0
		// @6C: invokevirtual java.lang.StringBuilder.append(int)java.lang.StringBuilder
		// @6F: bipush 44 (0x2C)
		// @71: invokevirtual java.lang.StringBuilder.append(char)java.lang.StringBuilder
		// @74: iload_1
		// @75: invokevirtual java.lang.StringBuilder.append(boolean)java.lang.StringBuilder
		// @78: bipush 44 (0x2C)
		// @7A: invokevirtual java.lang.StringBuilder.append(char)java.lang.StringBuilder
		// @7D: iload_2
		// @7E: invokevirtual java.lang.StringBuilder.append(int)java.lang.StringBuilder
		// @81: bipush 44 (0x2C)
		// @83: invokevirtual java.lang.StringBuilder.append(char)java.lang.StringBuilder
		// @86: iload_3
		// @87: invokevirtual java.lang.StringBuilder.append(boolean)java.lang.StringBuilder
		// @8A: bipush 41 (0x29)
		// @8C: invokevirtual java.lang.StringBuilder.append(char)java.lang.StringBuilder
		// @8F: invokevirtual java.lang.StringBuilder.toString()java.lang.String
		// @92: invokestatic game.C_100181_cf.func_105695_a(java.lang.Throwable, java.lang.String)game.C_100170_cm
		// @95: athrow
		// @96: return
	}
	
	static final void func_106373_a(int arg0, boolean arg1)
	{
		// @00: aconst_null
		// @01: getstatic game.C_100118_ub game.C_100038_wa.field_104073_n
		// @04: if_acmpeq @14
		// @07: getstatic game.C_100118_ub game.C_100038_wa.field_104073_n
		// @0A: bipush -128 (0x80)
		// @0C: iload_1
		// @0D: invokevirtual game.C_100118_ub.func_101809_a(byte, boolean)void
		// @10: goto @14
		// @13: athrow
		// @14: bipush 50 (0x32)
		// @16: iload_0
		// @17: bipush -18 (0xEE)
		// @19: isub
		// @1A: bipush 48 (0x30)
		// @1C: idiv
		// @1D: idiv
		// @1E: istore_2
		// @1F: goto @4C
		// @22: astore_2
		// @23: aload_2
		// @24: new java.lang.StringBuilder
		// @27: dup
		// @28: invokespecial java.lang.StringBuilder.<init>()void
		// @2B: getstatic java.lang.String[] game.C_100244_pe.field_106380_z
		// @2E: iconst_1
		// @2F: aaload
		// @30: invokevirtual java.lang.StringBuilder.append(java.lang.String)java.lang.StringBuilder
		// @33: iload_0
		// @34: invokevirtual java.lang.StringBuilder.append(int)java.lang.StringBuilder
		// @37: bipush 44 (0x2C)
		// @39: invokevirtual java.lang.StringBuilder.append(char)java.lang.StringBuilder
		// @3C: iload_1
		// @3D: invokevirtual java.lang.StringBuilder.append(boolean)java.lang.StringBuilder
		// @40: bipush 41 (0x29)
		// @42: invokevirtual java.lang.StringBuilder.append(char)java.lang.StringBuilder
		// @45: invokevirtual java.lang.StringBuilder.toString()java.lang.String
		// @48: invokestatic game.C_100181_cf.func_105695_a(java.lang.Throwable, java.lang.String)game.C_100170_cm
		// @4B: athrow
		// @4C: return
	}
	
	public static void func_106364_a(int arg0)
	{
		// @00: aconst_null
		// @01: putstatic game.C_100037_wb game.C_100244_pe.field_106376_e
		// @04: bipush 66 (0x42)
		// @06: iload_0
		// @07: bipush -55 (0xC9)
		// @09: isub
		// @0A: bipush 62 (0x3E)
		// @0C: idiv
		// @0D: idiv
		// @0E: istore_1
		// @0F: aconst_null
		// @10: putstatic java.lang.String game.C_100244_pe.field_106378_c
		// @13: goto @38
		// @16: astore_1
		// @17: aload_1
		// @18: new java.lang.StringBuilder
		// @1B: dup
		// @1C: invokespecial java.lang.StringBuilder.<init>()void
		// @1F: getstatic java.lang.String[] game.C_100244_pe.field_106380_z
		// @22: bipush 28 (0x1C)
		// @24: aaload
		// @25: invokevirtual java.lang.StringBuilder.append(java.lang.String)java.lang.StringBuilder
		// @28: iload_0
		// @29: invokevirtual java.lang.StringBuilder.append(int)java.lang.StringBuilder
		// @2C: bipush 41 (0x29)
		// @2E: invokevirtual java.lang.StringBuilder.append(char)java.lang.StringBuilder
		// @31: invokevirtual java.lang.StringBuilder.toString()java.lang.String
		// @34: invokestatic game.C_100181_cf.func_105695_a(java.lang.Throwable, java.lang.String)game.C_100170_cm
		// @37: athrow
		// @38: return
	}
	
	static final int func_106370_a(boolean arg0)
	{
		// @00: iload_0
		// @01: iconst_1
		// @02: if_icmpeq @08
		// @05: bipush 112 (0x70)
		// @07: ireturn
		// @08: getstatic int game.C_100093_fd.field_102785_S
		// @0B: ireturn
		// @0C: astore_1
		// @0D: aload_1
		// @0E: new java.lang.StringBuilder
		// @11: dup
		// @12: invokespecial java.lang.StringBuilder.<init>()void
		// @15: getstatic java.lang.String[] game.C_100244_pe.field_106380_z
		// @18: bipush 20 (0x14)
		// @1A: aaload
		// @1B: invokevirtual java.lang.StringBuilder.append(java.lang.String)java.lang.StringBuilder
		// @1E: iload_0
		// @1F: invokevirtual java.lang.StringBuilder.append(boolean)java.lang.StringBuilder
		// @22: bipush 41 (0x29)
		// @24: invokevirtual java.lang.StringBuilder.append(char)java.lang.StringBuilder
		// @27: invokevirtual java.lang.StringBuilder.toString()java.lang.String
		// @2A: invokestatic game.C_100181_cf.func_105695_a(java.lang.Throwable, java.lang.String)game.C_100170_cm
		// @2D: athrow
	}
	
	static final void func_106371_a(int arg0, int arg1, int arg2, int arg3, int arg4, int arg5)
	{
		// @00: getstatic int game.SteelSentinels.field_105275_O
		// @03: istore #11
		// @05: iload #4
		// @07: iload_0
		// @08: getstatic int game.C_100196_rb.field_105819_e
		// @0B: imul
		// @0C: iadd
		// @0D: istore #6
		// @0F: iload_0
		// @10: istore #7
		// @12: iload_3
		// @13: iload #7
		// @15: if_icmple @6D
		// @18: sipush 255 (0x00FF)
		// @1B: iload_3
		// @1C: iload #7
		// @1E: ineg
		// @1F: iadd
		// @20: imul
		// @21: iload_0
		// @22: ineg
		// @23: iload_3
		// @24: iadd
		// @25: idiv
		// @26: istore #8
		// @28: sipush 255 (0x00FF)
		// @2B: iload #7
		// @2D: iload_0
		// @2E: ineg
		// @2F: iadd
		// @30: imul
		// @31: iload_0
		// @32: ineg
		// @33: iload_3
		// @34: iadd
		// @35: idiv
		// @36: istore #9
		// @38: iload #8
		// @3A: iload #5
		// @3C: imul
		// @3D: iload #9
		// @3F: iload_2
		// @40: imul
		// @41: ineg
		// @42: isub
		// @43: sipush 256 (0x0100)
		// @46: idiv
		// @47: istore #10
		// @49: getstatic int[] game.C_100196_rb.field_105818_d
		// @4C: iload #6
		// @4E: iload #10
		// @50: ldc 65793 (0x10101)
		// @52: imul
		// @53: iastore
		// @54: iload #6
		// @56: getstatic int game.C_100196_rb.field_105819_e
		// @59: iadd
		// @5A: istore #6
		// @5C: iinc #7 +1
		// @5F: iload #11
		// @61: ifne @7D
		// @64: iload #11
		// @66: ifeq @12
		// @69: goto @6D
		// @6C: athrow
		// @6D: iload_1
		// @6E: bipush 44 (0x2C)
		// @70: if_icmpge @7D
		// @73: bipush 15 (0x0F)
		// @75: iconst_0
		// @76: invokestatic game.C_100244_pe.func_106373_a(int, boolean)void
		// @79: goto @7D
		// @7C: athrow
		// @7D: goto @D3
		// @80: astore #6
		// @82: aload #6
		// @84: new java.lang.StringBuilder
		// @87: dup
		// @88: invokespecial java.lang.StringBuilder.<init>()void
		// @8B: getstatic java.lang.String[] game.C_100244_pe.field_106380_z
		// @8E: bipush 21 (0x15)
		// @90: aaload
		// @91: invokevirtual java.lang.StringBuilder.append(java.lang.String)java.lang.StringBuilder
		// @94: iload_0
		// @95: invokevirtual java.lang.StringBuilder.append(int)java.lang.StringBuilder
		// @98: bipush 44 (0x2C)
		// @9A: invokevirtual java.lang.StringBuilder.append(char)java.lang.StringBuilder
		// @9D: iload_1
		// @9E: invokevirtual java.lang.StringBuilder.append(int)java.lang.StringBuilder
		// @A1: bipush 44 (0x2C)
		// @A3: invokevirtual java.lang.StringBuilder.append(char)java.lang.StringBuilder
		// @A6: iload_2
		// @A7: invokevirtual java.lang.StringBuilder.append(int)java.lang.StringBuilder
		// @AA: bipush 44 (0x2C)
		// @AC: invokevirtual java.lang.StringBuilder.append(char)java.lang.StringBuilder
		// @AF: iload_3
		// @B0: invokevirtual java.lang.StringBuilder.append(int)java.lang.StringBuilder
		// @B3: bipush 44 (0x2C)
		// @B5: invokevirtual java.lang.StringBuilder.append(char)java.lang.StringBuilder
		// @B8: iload #4
		// @BA: invokevirtual java.lang.StringBuilder.append(int)java.lang.StringBuilder
		// @BD: bipush 44 (0x2C)
		// @BF: invokevirtual java.lang.StringBuilder.append(char)java.lang.StringBuilder
		// @C2: iload #5
		// @C4: invokevirtual java.lang.StringBuilder.append(int)java.lang.StringBuilder
		// @C7: bipush 41 (0x29)
		// @C9: invokevirtual java.lang.StringBuilder.append(char)java.lang.StringBuilder
		// @CC: invokevirtual java.lang.StringBuilder.toString()java.lang.String
		// @CF: invokestatic game.C_100181_cf.func_105695_a(java.lang.Throwable, java.lang.String)game.C_100170_cm
		// @D2: athrow
		// @D3: return
	}
	
	static
	{
		// @000: bipush 30 (0x1E)
		// @002: anewarray java.lang.String
		// @005: dup
		// @006: iconst_0
		// @007: ldc "\u0001FP\nx"
		// @009: invokestatic game.C_100244_pe.func_106369_z(java.lang.String)char[]
		// @00C: invokestatic game.C_100244_pe.func_106366_z(char[])java.lang.String
		// @00F: aastore
		// @010: dup
		// @011: iconst_1
		// @012: ldc "\u0001FP\rx"
		// @014: invokestatic game.C_100244_pe.func_106369_z(java.lang.String)char[]
		// @017: invokestatic game.C_100244_pe.func_106366_z(char[])java.lang.String
		// @01A: aastore
		// @01B: dup
		// @01C: iconst_2
		// @01D: ldc "\u0017Q\u001f!5.A\u00118$\u001eN"
		// @01F: invokestatic game.C_100244_pe.func_106369_z(java.lang.String)char[]
		// @022: invokestatic game.C_100244_pe.func_106366_z(char[])java.lang.String
		// @025: aastore
		// @026: dup
		// @027: iconst_3
		// @028: ldc "\u0013V\n8?\u001f"
		// @02A: invokestatic game.C_100244_pe.func_106369_z(java.lang.String)char[]
		// @02D: invokestatic game.C_100244_pe.func_106366_z(char[])java.lang.String
		// @030: aastore
		// @031: dup
		// @032: iconst_4
		// @033: ldc "\u0012L\u0013!?\u001fV\u0017"
		// @035: invokestatic game.C_100244_pe.func_106369_z(java.lang.String)char[]
		// @038: invokestatic game.C_100244_pe.func_106366_z(char[])java.lang.String
		// @03B: aastore
		// @03C: dup
		// @03D: iconst_5
		// @03E: ldc "\u0002@\u000c)5\u001f|\u0011<$\u0018L\u0010?"
		// @040: invokestatic game.C_100244_pe.func_106369_z(java.lang.String)char[]
		// @043: invokestatic game.C_100244_pe.func_106366_z(char[])java.lang.String
		// @046: aastore
		// @047: dup
		// @048: bipush 6 (0x06)
		// @04A: ldc "\u0010Q\u001b6*\u001e\u0012J.?\u001dG"
		// @04C: invokestatic game.C_100244_pe.func_106369_z(java.lang.String)char[]
		// @04F: invokestatic game.C_100244_pe.func_106366_z(char[])java.lang.String
		// @052: aastore
		// @053: dup
		// @054: bipush 7 (0x07)
		// @056: ldc "\n\rPb-"
		// @058: invokestatic game.C_100244_pe.func_106369_z(java.lang.String)char[]
		// @05B: invokestatic game.C_100244_pe.func_106366_z(char[])java.lang.String
		// @05E: aastore
		// @05F: dup
		// @060: bipush 8 (0x08)
		// @062: ldc "\u0001FP\tx"
		// @064: invokestatic game.C_100244_pe.func_106369_z(java.lang.String)char[]
		// @067: invokestatic game.C_100244_pe.func_106366_z(char[])java.lang.String
		// @06A: aastore
		// @06B: dup
		// @06C: bipush 9 (0x09)
		// @06E: ldc "\u001bB\u0019)(.O\u0011+?.D\u000c))"
		// @070: invokestatic game.C_100244_pe.func_106369_z(java.lang.String)char[]
		// @073: invokestatic game.C_100244_pe.func_106366_z(char[])java.lang.String
		// @076: aastore
		// @077: dup
		// @078: bipush 10 (0x0A)
		// @07A: ldc "\u0007B\u0012%4\u0010W\u0017#>"
		// @07C: invokestatic game.C_100244_pe.func_106369_z(java.lang.String)char[]
		// @07F: invokestatic game.C_100244_pe.func_106366_z(char[])java.lang.String
		// @082: aastore
		// @083: dup
		// @084: bipush 11 (0x0B)
		// @086: ldc "\u0010Q\u001b6*\u001e\u0012J"
		// @088: invokestatic game.C_100244_pe.func_106369_z(java.lang.String)char[]
		// @08B: invokestatic game.C_100244_pe.func_106366_z(char[])java.lang.String
		// @08E: aastore
		// @08F: dup
		// @090: bipush 12 (0x0C)
		// @092: ldc "\u0010Q\u001b6*\u001e\u0012L"
		// @094: invokestatic game.C_100244_pe.func_106369_z(java.lang.String)char[]
		// @097: invokestatic game.C_100244_pe.func_106366_z(char[])java.lang.String
		// @09A: aastore
		// @09B: dup
		// @09C: bipush 13 (0x0D)
		// @09E: ldc "\u001fV\u0012 "
		// @0A0: invokestatic game.C_100244_pe.func_106369_z(java.lang.String)char[]
		// @0A3: invokestatic game.C_100244_pe.func_106366_z(char[])java.lang.String
		// @0A6: aastore
		// @0A7: dup
		// @0A8: bipush 14 (0x0E)
		// @0AA: ldc "\u0017Q\u001f!5.W\u0011<"
		// @0AC: invokestatic game.C_100244_pe.func_106369_z(java.lang.String)char[]
		// @0AF: invokestatic game.C_100244_pe.func_106366_z(char[])java.lang.String
		// @0B2: aastore
		// @0B3: dup
		// @0B4: bipush 15 (0x0F)
		// @0B6: ldc "\u0015Q\u0011<4\u001eT\u0010"
		// @0B8: invokestatic game.C_100244_pe.func_106369_z(java.lang.String)char[]
		// @0BB: invokestatic game.C_100244_pe.func_106366_z(char[])java.lang.String
		// @0BE: aastore
		// @0BF: dup
		// @0C0: bipush 16 (0x10)
		// @0C2: ldc "\u0013V\n8?\u001f\r\u0019%6"
		// @0C4: invokestatic game.C_100244_pe.func_106369_z(java.lang.String)char[]
		// @0C7: invokestatic game.C_100244_pe.func_106366_z(char[])java.lang.String
		// @0CA: aastore
		// @0CB: dup
		// @0CC: bipush 17 (0x11)
		// @0CE: ldc "\u0001FP\u0004x"
		// @0D0: invokestatic game.C_100244_pe.func_106369_z(java.lang.String)char[]
		// @0D3: invokestatic game.C_100244_pe.func_106366_z(char[])java.lang.String
		// @0D6: aastore
		// @0D7: dup
		// @0D8: bipush 18 (0x12)
		// @0DA: ldc "\u0002F\n89\u001fD\r"
		// @0DC: invokestatic game.C_100244_pe.func_106369_z(java.lang.String)char[]
		// @0DF: invokestatic game.C_100244_pe.func_106366_z(char[])java.lang.String
		// @0E2: aastore
		// @0E3: dup
		// @0E4: bipush 19 (0x13)
		// @0E6: ldc "\u0002F\r?9\u001eM"
		// @0E8: invokestatic game.C_100244_pe.func_106369_z(java.lang.String)char[]
		// @0EB: invokestatic game.C_100244_pe.func_106366_z(char[])java.lang.String
		// @0EE: aastore
		// @0EF: dup
		// @0F0: bipush 20 (0x14)
		// @0F2: ldc "\u0001FP\u0008x"
		// @0F4: invokestatic game.C_100244_pe.func_106369_z(java.lang.String)char[]
		// @0F7: invokestatic game.C_100244_pe.func_106366_z(char[])java.lang.String
		// @0FA: aastore
		// @0FB: dup
		// @0FC: bipush 21 (0x15)
		// @0FE: ldc "\u0001FP\u000fx"
		// @100: invokestatic game.C_100244_pe.func_106369_z(java.lang.String)char[]
		// @103: invokestatic game.C_100244_pe.func_106366_z(char[])java.lang.String
		// @106: aastore
		// @107: dup
		// @108: bipush 22 (0x16)
		// @10A: ldc "\u0001FP\u000bx"
		// @10C: invokestatic game.C_100244_pe.func_106369_z(java.lang.String)char[]
		// @10F: invokestatic game.C_100244_pe.func_106366_z(char[])java.lang.String
		// @112: aastore
		// @113: dup
		// @114: bipush 23 (0x17)
		// @116: ldc "]\u0003"
		// @118: invokestatic game.C_100244_pe.func_106369_z(java.lang.String)char[]
		// @11B: invokestatic game.C_100244_pe.func_106366_z(char[])java.lang.String
		// @11E: aastore
		// @11F: dup
		// @120: bipush 24 (0x18)
		// @122: ldc "M@\u0011 m0\u0013N|`A\u001d"
		// @124: invokestatic game.C_100244_pe.func_106369_z(java.lang.String)char[]
		// @127: invokestatic game.C_100244_pe.func_106366_z(char[])java.lang.String
		// @12A: aastore
		// @12B: dup
		// @12C: bipush 25 (0x19)
		// @12E: ldc "MA\u000cr"
		// @130: invokestatic game.C_100244_pe.func_106369_z(java.lang.String)char[]
		// @133: invokestatic game.C_100244_pe.func_106366_z(char[])java.lang.String
		// @136: aastore
		// @137: dup
		// @138: bipush 26 (0x1A)
		// @13A: ldc "M\u000c\u001d#<O"
		// @13C: invokestatic game.C_100244_pe.func_106369_z(java.lang.String)char[]
		// @13F: invokestatic game.C_100244_pe.func_106366_z(char[])java.lang.String
		// @142: aastore
		// @143: dup
		// @144: bipush 27 (0x1B)
		// @146: ldc "MA\u000crl\u0012L\u0012q\u0011A\u0013N|`O"
		// @148: invokestatic game.C_100244_pe.func_106369_z(java.lang.String)char[]
		// @14B: invokestatic game.C_100244_pe.func_106366_z(char[])java.lang.String
		// @14E: aastore
		// @14F: dup
		// @150: bipush 28 (0x1C)
		// @152: ldc "\u0001FP\u000ex"
		// @154: invokestatic game.C_100244_pe.func_106369_z(java.lang.String)char[]
		// @157: invokestatic game.C_100244_pe.func_106366_z(char[])java.lang.String
		// @15A: aastore
		// @15B: dup
		// @15C: bipush 29 (0x1D)
		// @15E: ldc "\u0001FP\u0005x"
		// @160: invokestatic game.C_100244_pe.func_106369_z(java.lang.String)char[]
		// @163: invokestatic game.C_100244_pe.func_106366_z(char[])java.lang.String
		// @166: aastore
		// @167: putstatic java.lang.String[] game.C_100244_pe.field_106380_z
		// @16A: iconst_0
		// @16B: putstatic int game.C_100244_pe.field_106374_f
		// @16E: ldc "?B\u0013)#Q@\u001f\">\u001eW^?$\u0010Q\nl?\u0003\u0003\u001b\"4QT\u001788QP\u000e-3\u0014\u0003\u0011>p\u0004M\u001a)\"\u0002@\u0011>5"
		// @170: invokestatic game.C_100244_pe.func_106369_z(java.lang.String)char[]
		// @173: invokestatic game.C_100244_pe.func_106366_z(char[])java.lang.String
		// @176: putstatic java.lang.String game.C_100244_pe.field_106378_c
		// @179: return
	}
	
	private static char[] func_106369_z(String arg0)
	{
		// @00: aload_0
		// @01: invokevirtual java.lang.String.toCharArray()char[]
		// @04: dup
		// @05: arraylength
		// @06: iconst_2
		// @07: if_icmpge @13
		// @0A: dup
		// @0B: iconst_0
		// @0C: dup2
		// @0D: caload
		// @0E: bipush 80 (0x50)
		// @10: ixor
		// @11: i2c
		// @12: castore
		// @13: areturn
	}
	
	private static String func_106366_z(char[] arg0)
	{
		// @00: aload_0
		// @01: dup
		// @02: arraylength
		// @03: swap
		// @04: iconst_0
		// @05: istore_1
		// @06: goto @4C
		// @09: dup
		// @0A: iload_1
		// @0B: dup2
		// @0C: caload
		// @0D: iload_1
		// @0E: iconst_5
		// @0F: irem
		// @10: tableswitch def: @44, for 0: @30, for 1: @35, for 2: @3A, for 3: @3F
		// @30: bipush 113 (0x71)
		// @32: goto @46
		// @35: bipush 35 (0x23)
		// @37: goto @46
		// @3A: bipush 126 (0x7E)
		// @3C: goto @46
		// @3F: bipush 76 (0x4C)
		// @41: goto @46
		// @44: bipush 80 (0x50)
		// @46: ixor
		// @47: i2c
		// @48: castore
		// @49: iinc #1 +1
		// @4C: swap
		// @4D: dup_x1
		// @4E: iload_1
		// @4F: if_icmpgt @09
		// @52: new java.lang.String
		// @55: dup_x1
		// @56: swap
		// @57: invokespecial java.lang.String.<init>(char[])void
		// @5A: invokevirtual java.lang.String.intern()java.lang.String
		// @5D: areturn
	}
}
