package game;

import java.awt.Component;

final class C_100293_kj
{
	static C_100268_mk field_106891_a;
	static long field_106887_d;
	static int field_106890_c;
	static boolean field_106888_e;
	static C_100302_ka field_106889_b;
	private static final String[] field_106892_z;
	
	static final boolean func_106886_a(int arg0, C_100280_nf arg1)
	{
		// @00: iload_0
		// @01: sipush -22292 (0xA8EC)
		// @04: if_icmpeq @09
		// @07: iconst_1
		// @08: ireturn
		// @09: aload_1
		// @0A: iconst_0
		// @0B: invokevirtual game.C_100280_nf.func_101156_c(boolean)int
		// @0E: istore_2
		// @0F: iconst_1
		// @10: iload_2
		// @11: if_icmpne @19
		// @14: iconst_1
		// @15: goto @1A
		// @18: athrow
		// @19: iconst_0
		// @1A: istore_3
		// @1B: iload_3
		// @1C: ireturn
		// @1D: astore_2
		// @1E: aload_2
		// @1F: new java.lang.StringBuilder
		// @22: dup
		// @23: invokespecial java.lang.StringBuilder.<init>()void
		// @26: getstatic java.lang.String[] game.C_100293_kj.field_106892_z
		// @29: bipush 11 (0x0B)
		// @2B: aaload
		// @2C: invokevirtual java.lang.StringBuilder.append(java.lang.String)java.lang.StringBuilder
		// @2F: iload_0
		// @30: invokevirtual java.lang.StringBuilder.append(int)java.lang.StringBuilder
		// @33: bipush 44 (0x2C)
		// @35: invokevirtual java.lang.StringBuilder.append(char)java.lang.StringBuilder
		// @38: aload_1
		// @39: ifnull @46
		// @3C: getstatic java.lang.String[] game.C_100293_kj.field_106892_z
		// @3F: bipush 13 (0x0D)
		// @41: aaload
		// @42: goto @4C
		// @45: athrow
		// @46: getstatic java.lang.String[] game.C_100293_kj.field_106892_z
		// @49: bipush 12 (0x0C)
		// @4B: aaload
		// @4C: invokevirtual java.lang.StringBuilder.append(java.lang.String)java.lang.StringBuilder
		// @4F: bipush 41 (0x29)
		// @51: invokevirtual java.lang.StringBuilder.append(char)java.lang.StringBuilder
		// @54: invokevirtual java.lang.StringBuilder.toString()java.lang.String
		// @57: invokestatic game.C_100181_cf.func_105695_a(java.lang.Throwable, java.lang.String)game.C_100170_cm
		// @5A: athrow
	}
	
	static final C_100302_ka func_106885_a(byte arg0)
	{
		// @00: iload_0
		// @01: bipush -103 (0x99)
		// @03: if_icmpeq @11
		// @06: aconst_null
		// @07: checkcast game.C_100302_ka
		// @0A: putstatic game.C_100302_ka game.C_100293_kj.field_106889_b
		// @0D: goto @11
		// @10: athrow
		// @11: getstatic game.C_100100_i game.C_100202_qi.field_105913_f
		// @14: getfield game.C_100302_ka game.C_100100_i.field_102015_Yb
		// @17: areturn
		// @18: astore_1
		// @19: aload_1
		// @1A: new java.lang.StringBuilder
		// @1D: dup
		// @1E: invokespecial java.lang.StringBuilder.<init>()void
		// @21: getstatic java.lang.String[] game.C_100293_kj.field_106892_z
		// @24: bipush 16 (0x10)
		// @26: aaload
		// @27: invokevirtual java.lang.StringBuilder.append(java.lang.String)java.lang.StringBuilder
		// @2A: iload_0
		// @2B: invokevirtual java.lang.StringBuilder.append(int)java.lang.StringBuilder
		// @2E: bipush 41 (0x29)
		// @30: invokevirtual java.lang.StringBuilder.append(char)java.lang.StringBuilder
		// @33: invokevirtual java.lang.StringBuilder.toString()java.lang.String
		// @36: invokestatic game.C_100181_cf.func_105695_a(java.lang.Throwable, java.lang.String)game.C_100170_cm
		// @39: athrow
	}
	
	static final void func_106881_b(int arg0)
	{
		// @000: getstatic int game.SteelSentinels.field_105275_O
		// @003: istore #10
		// @005: aconst_null
		// @006: getstatic game.C_100098_h game.C_100336_im.field_102545_s
		// @009: if_acmpeq @38F
		// @00C: getstatic game.C_100098_h game.C_100336_im.field_102545_s
		// @00F: iconst_0
		// @010: invokevirtual game.C_100098_h.func_104597_a(boolean)boolean
		// @013: ifeq @38F
		// @016: goto @01A
		// @019: athrow
		// @01A: getstatic game.C_100098_h game.C_100336_im.field_102545_s
		// @01D: getstatic java.lang.String[] game.C_100293_kj.field_106892_z
		// @020: bipush 8 (0x08)
		// @022: aaload
		// @023: iconst_0
		// @024: invokevirtual game.C_100098_h.func_104593_a(java.lang.String, boolean)boolean
		// @027: ifeq @38F
		// @02A: goto @02E
		// @02D: athrow
		// @02E: getstatic game.C_100098_h game.C_100013_fn.field_103744_j
		// @031: ifnull @38F
		// @034: goto @038
		// @037: athrow
		// @038: getstatic game.C_100098_h game.C_100013_fn.field_103744_j
		// @03B: iconst_0
		// @03C: invokevirtual game.C_100098_h.func_104597_a(boolean)boolean
		// @03F: ifeq @38F
		// @042: goto @046
		// @045: athrow
		// @046: getstatic game.C_100098_h game.C_100013_fn.field_103744_j
		// @049: getstatic java.lang.String[] game.C_100293_kj.field_106892_z
		// @04C: bipush 8 (0x08)
		// @04E: aaload
		// @04F: iconst_0
		// @050: invokevirtual game.C_100098_h.func_104593_a(java.lang.String, boolean)boolean
		// @053: ifeq @38F
		// @056: goto @05A
		// @059: athrow
		// @05A: bipush 107 (0x6B)
		// @05C: getstatic java.lang.String[] game.C_100293_kj.field_106892_z
		// @05F: bipush 8 (0x08)
		// @061: aaload
		// @062: getstatic game.C_100098_h game.C_100336_im.field_102545_s
		// @065: getstatic java.lang.String[] game.C_100293_kj.field_106892_z
		// @068: iconst_3
		// @069: aaload
		// @06A: invokestatic game.C_100021_wn.func_103861_a(byte, java.lang.String, game.C_100098_h, java.lang.String)game.C_100037_wb
		// @06D: putstatic game.C_100037_wb game.C_100306_kn.field_107132_e
		// @070: bipush 122 (0x7A)
		// @072: getstatic java.lang.String[] game.C_100293_kj.field_106892_z
		// @075: bipush 8 (0x08)
		// @077: aaload
		// @078: getstatic game.C_100098_h game.C_100336_im.field_102545_s
		// @07B: getstatic java.lang.String[] game.C_100293_kj.field_106892_z
		// @07E: bipush 9 (0x09)
		// @080: aaload
		// @081: invokestatic game.C_100021_wn.func_103861_a(byte, java.lang.String, game.C_100098_h, java.lang.String)game.C_100037_wb
		// @084: putstatic game.C_100037_wb game.C_100233_oa.field_106253_v
		// @087: bipush 94 (0x5E)
		// @089: getstatic java.lang.String[] game.C_100293_kj.field_106892_z
		// @08C: bipush 8 (0x08)
		// @08E: aaload
		// @08F: getstatic game.C_100098_h game.C_100336_im.field_102545_s
		// @092: getstatic java.lang.String[] game.C_100293_kj.field_106892_z
		// @095: bipush 6 (0x06)
		// @097: aaload
		// @098: invokestatic game.C_100021_wn.func_103861_a(byte, java.lang.String, game.C_100098_h, java.lang.String)game.C_100037_wb
		// @09B: putstatic game.C_100037_wb game.C_100252_pn.field_105513_r
		// @09E: bipush 92 (0x5C)
		// @0A0: getstatic java.lang.String[] game.C_100293_kj.field_106892_z
		// @0A3: bipush 8 (0x08)
		// @0A5: aaload
		// @0A6: getstatic game.C_100098_h game.C_100336_im.field_102545_s
		// @0A9: getstatic java.lang.String[] game.C_100293_kj.field_106892_z
		// @0AC: bipush 7 (0x07)
		// @0AE: aaload
		// @0AF: invokestatic game.C_100021_wn.func_103861_a(byte, java.lang.String, game.C_100098_h, java.lang.String)game.C_100037_wb
		// @0B2: putstatic game.C_100037_wb game.C_100180_ce.field_104804_B
		// @0B5: bipush 91 (0x5B)
		// @0B7: getstatic java.lang.String[] game.C_100293_kj.field_106892_z
		// @0BA: bipush 8 (0x08)
		// @0BC: aaload
		// @0BD: getstatic game.C_100098_h game.C_100336_im.field_102545_s
		// @0C0: getstatic java.lang.String[] game.C_100293_kj.field_106892_z
		// @0C3: bipush 10 (0x0A)
		// @0C5: aaload
		// @0C6: invokestatic game.C_100021_wn.func_103861_a(byte, java.lang.String, game.C_100098_h, java.lang.String)game.C_100037_wb
		// @0C9: putstatic game.C_100037_wb game.C_100270_mi.field_102271_Wb
		// @0CC: bipush 124 (0x7C)
		// @0CE: getstatic java.lang.String[] game.C_100293_kj.field_106892_z
		// @0D1: bipush 8 (0x08)
		// @0D3: aaload
		// @0D4: getstatic game.C_100098_h game.C_100336_im.field_102545_s
		// @0D7: getstatic java.lang.String[] game.C_100293_kj.field_106892_z
		// @0DA: iconst_1
		// @0DB: aaload
		// @0DC: invokestatic game.C_100021_wn.func_103861_a(byte, java.lang.String, game.C_100098_h, java.lang.String)game.C_100037_wb
		// @0DF: putstatic game.C_100037_wb game.C_100061_dh.field_101981_Zb
		// @0E2: bipush 95 (0x5F)
		// @0E4: getstatic java.lang.String[] game.C_100293_kj.field_106892_z
		// @0E7: bipush 8 (0x08)
		// @0E9: aaload
		// @0EA: getstatic game.C_100098_h game.C_100336_im.field_102545_s
		// @0ED: getstatic java.lang.String[] game.C_100293_kj.field_106892_z
		// @0F0: iconst_4
		// @0F1: aaload
		// @0F2: invokestatic game.C_100021_wn.func_103861_a(byte, java.lang.String, game.C_100098_h, java.lang.String)game.C_100037_wb
		// @0F5: putstatic game.C_100037_wb game.C_100309_lk.field_103275_Z
		// @0F8: bipush 125 (0x7D)
		// @0FA: getstatic game.C_100098_h game.C_100013_fn.field_103744_j
		// @0FD: getstatic game.C_100098_h game.C_100336_im.field_102545_s
		// @100: getstatic java.lang.String[] game.C_100293_kj.field_106892_z
		// @103: bipush 8 (0x08)
		// @105: aaload
		// @106: getstatic java.lang.String[] game.C_100293_kj.field_106892_z
		// @109: iconst_2
		// @10A: aaload
		// @10B: invokestatic game.C_100004_gb.func_103564_a(int, game.C_100098_h, game.C_100098_h, java.lang.String, java.lang.String)game.C_100317_lb
		// @10E: putstatic game.C_100112_r game.C_100218_am.field_103109_D
		// @111: bipush 76 (0x4C)
		// @113: getstatic game.C_100098_h game.C_100013_fn.field_103744_j
		// @116: getstatic game.C_100098_h game.C_100336_im.field_102545_s
		// @119: getstatic java.lang.String[] game.C_100293_kj.field_106892_z
		// @11C: bipush 8 (0x08)
		// @11E: aaload
		// @11F: getstatic java.lang.String[] game.C_100293_kj.field_106892_z
		// @122: iconst_5
		// @123: aaload
		// @124: invokestatic game.C_100004_gb.func_103564_a(int, game.C_100098_h, game.C_100098_h, java.lang.String, java.lang.String)game.C_100317_lb
		// @127: putstatic game.C_100112_r game.C_100003_ga.field_103541_q
		// @12A: getstatic int[] game.C_100196_rb.field_105818_d
		// @12D: astore_1
		// @12E: getstatic int game.C_100196_rb.field_105819_e
		// @131: istore_2
		// @132: getstatic int game.C_100196_rb.field_105821_c
		// @135: istore_3
		// @136: getstatic int[] game.C_100032_gk.field_103129_U
		// @139: invokestatic game.C_100196_rb.func_105801_a(int[])void
		// @13C: new game.C_100037_wb
		// @13F: dup
		// @140: getstatic game.C_100037_wb game.C_100309_lk.field_103275_Z
		// @143: getfield int game.C_100037_wb.field_102339_s
		// @146: bipush -4 (0xFC)
		// @148: isub
		// @149: getstatic game.C_100037_wb game.C_100309_lk.field_103275_Z
		// @14C: getfield int game.C_100037_wb.field_102337_u
		// @14F: iconst_4
		// @150: iadd
		// @151: invokespecial game.C_100037_wb.<init>(int, int)void
		// @154: astore #4
		// @156: aload #4
		// @158: invokevirtual game.C_100037_wb.func_102379_d()void
		// @15B: getstatic game.C_100037_wb game.C_100309_lk.field_103275_Z
		// @15E: iconst_2
		// @15F: iconst_2
		// @160: getstatic int game.C_100140_bj.field_102967_b
		// @163: invokevirtual game.C_100037_wb.func_102383_f(int, int, int)void
		// @166: iconst_0
		// @167: iconst_2
		// @168: iconst_0
		// @169: aload #4
		// @16B: getfield int game.C_100037_wb.field_102337_u
		// @16E: iconst_1
		// @16F: aload #4
		// @171: getfield int game.C_100037_wb.field_102339_s
		// @174: ldc 38642 (0x96f2)
		// @176: aload #4
		// @178: invokestatic game.C_100202_qi.func_105911_a(int, int, int, int, int, int, int, game.C_100037_wb)void
		// @17B: aload #4
		// @17D: putstatic game.C_100037_wb game.C_100309_lk.field_103275_Z
		// @180: getstatic game.C_100037_wb game.C_100309_lk.field_103275_Z
		// @183: invokevirtual game.C_100037_wb.func_102371_f()game.C_100037_wb
		// @186: putstatic game.C_100037_wb game.C_100140_bj.field_102964_g
		// @189: new game.C_100037_wb
		// @18C: dup
		// @18D: sipush 195 (0x00C3)
		// @190: sipush 221 (0x00DD)
		// @193: invokespecial game.C_100037_wb.<init>(int, int)void
		// @196: astore #5
		// @198: aload #5
		// @19A: getfield int game.C_100037_wb.field_102339_s
		// @19D: iconst_2
		// @19E: idiv
		// @19F: istore #6
		// @1A1: aload #5
		// @1A3: invokevirtual game.C_100037_wb.func_102379_d()void
		// @1A6: getstatic game.C_100112_r game.C_100218_am.field_103109_D
		// @1A9: sipush -30945 (0x871F)
		// @1AC: iconst_1
		// @1AD: anewarray java.lang.String
		// @1B0: dup
		// @1B1: iconst_0
		// @1B2: getstatic java.lang.String game.C_100092_um.field_104535_l
		// @1B5: aastore
		// @1B6: getstatic java.lang.String game.C_100295_kh.field_105289_g
		// @1B9: invokestatic game.C_100132_td.func_104965_a(int, java.lang.String[], java.lang.String)java.lang.String
		// @1BC: iload #6
		// @1BE: bipush 40 (0x28)
		// @1C0: ldc 16777215 (0xffffff)
		// @1C2: iconst_m1
		// @1C3: invokevirtual game.C_100112_r.func_101744_b(java.lang.String, int, int, int, int)void
		// @1C6: getstatic game.C_100112_r game.C_100003_ga.field_103541_q
		// @1C9: sipush -30945 (0x871F)
		// @1CC: iconst_1
		// @1CD: anewarray java.lang.String
		// @1D0: dup
		// @1D1: iconst_0
		// @1D2: getstatic java.lang.String game.C_100092_um.field_104535_l
		// @1D5: aastore
		// @1D6: getstatic java.lang.String game.C_100295_kh.field_105296_o
		// @1D9: invokestatic game.C_100132_td.func_104965_a(int, java.lang.String[], java.lang.String)java.lang.String
		// @1DC: iload #6
		// @1DE: bipush 60 (0x3C)
		// @1E0: ldc 16777215 (0xffffff)
		// @1E2: iconst_m1
		// @1E3: invokevirtual game.C_100112_r.func_101744_b(java.lang.String, int, int, int, int)void
		// @1E6: getstatic game.C_100112_r game.C_100218_am.field_103109_D
		// @1E9: sipush -30945 (0x871F)
		// @1EC: iconst_1
		// @1ED: anewarray java.lang.String
		// @1F0: dup
		// @1F1: iconst_0
		// @1F2: getstatic java.lang.String game.C_100306_kn.field_107141_h
		// @1F5: aastore
		// @1F6: getstatic java.lang.String game.C_100339_jb.field_107389_j
		// @1F9: invokestatic game.C_100132_td.func_104965_a(int, java.lang.String[], java.lang.String)java.lang.String
		// @1FC: iload #6
		// @1FE: bipush 110 (0x6E)
		// @200: ldc 16777215 (0xffffff)
		// @202: iconst_m1
		// @203: invokevirtual game.C_100112_r.func_101744_b(java.lang.String, int, int, int, int)void
		// @206: getstatic game.C_100112_r game.C_100003_ga.field_103541_q
		// @209: sipush -30945 (0x871F)
		// @20C: iconst_1
		// @20D: anewarray java.lang.String
		// @210: dup
		// @211: iconst_0
		// @212: getstatic java.lang.String game.C_100306_kn.field_107141_h
		// @215: aastore
		// @216: getstatic java.lang.String game.C_100243_pd.field_106356_g
		// @219: invokestatic game.C_100132_td.func_104965_a(int, java.lang.String[], java.lang.String)java.lang.String
		// @21C: iload #6
		// @21E: sipush 130 (0x0082)
		// @221: ldc 16777215 (0xffffff)
		// @223: iconst_m1
		// @224: invokevirtual game.C_100112_r.func_101744_b(java.lang.String, int, int, int, int)void
		// @227: getstatic game.C_100112_r game.C_100218_am.field_103109_D
		// @22A: getstatic java.lang.String game.C_100207_qh.field_102880_R
		// @22D: iload #6
		// @22F: sipush 180 (0x00B4)
		// @232: ldc 16777215 (0xffffff)
		// @234: iconst_m1
		// @235: invokevirtual game.C_100112_r.func_101744_b(java.lang.String, int, int, int, int)void
		// @238: getstatic game.C_100112_r game.C_100003_ga.field_103541_q
		// @23B: getstatic java.lang.String game.C_100256_pk.field_100479_q
		// @23E: iload #6
		// @240: sipush 200 (0x00C8)
		// @243: ldc 16777215 (0xffffff)
		// @245: iconst_m1
		// @246: invokevirtual game.C_100112_r.func_101744_b(java.lang.String, int, int, int, int)void
		// @249: iconst_0
		// @24A: iconst_3
		// @24B: iconst_0
		// @24C: aload #5
		// @24E: getfield int game.C_100037_wb.field_102337_u
		// @251: iconst_1
		// @252: aload #5
		// @254: getfield int game.C_100037_wb.field_102339_s
		// @257: ldc 38642 (0x96f2)
		// @259: aload #5
		// @25B: invokestatic game.C_100202_qi.func_105911_a(int, int, int, int, int, int, int, game.C_100037_wb)void
		// @25E: getstatic game.C_100037_wb game.C_100233_oa.field_106253_v
		// @261: invokevirtual game.C_100037_wb.func_102379_d()void
		// @264: aload #5
		// @266: bipush 18 (0x12)
		// @268: getstatic game.C_100037_wb game.C_100233_oa.field_106253_v
		// @26B: getfield int game.C_100037_wb.field_102335_w
		// @26E: ineg
		// @26F: iadd
		// @270: sipush 241 (0x00F1)
		// @273: getstatic game.C_100037_wb game.C_100233_oa.field_106253_v
		// @276: getfield int game.C_100037_wb.field_102332_H
		// @279: isub
		// @27A: invokevirtual game.C_100037_wb.func_102353_h(int, int)void
		// @27D: iconst_0
		// @27E: istore #7
		// @280: iload #7
		// @282: getstatic java.lang.String[] game.C_100041_wf.field_104102_f
		// @285: arraylength
		// @286: if_icmpge @2FE
		// @289: getstatic game.C_100037_wb[] game.C_100053_vn.field_102845_Z
		// @28C: iload #7
		// @28E: aaload
		// @28F: invokevirtual game.C_100037_wb.func_102379_d()void
		// @292: getstatic game.C_100112_r game.C_100003_ga.field_103541_q
		// @295: getstatic java.lang.String[] game.C_100041_wf.field_104102_f
		// @298: iload #7
		// @29A: aaload
		// @29B: iconst_3
		// @29C: iconst_3
		// @29D: bipush -6 (0xFA)
		// @29F: getstatic game.C_100037_wb[] game.C_100053_vn.field_102845_Z
		// @2A2: iload #7
		// @2A4: aaload
		// @2A5: getfield int game.C_100037_wb.field_102339_s
		// @2A8: iadd
		// @2A9: getstatic game.C_100037_wb[] game.C_100053_vn.field_102845_Z
		// @2AC: iload #7
		// @2AE: aaload
		// @2AF: getfield int game.C_100037_wb.field_102337_u
		// @2B2: bipush -6 (0xFA)
		// @2B4: iadd
		// @2B5: getstatic int game.C_100140_bj.field_102967_b
		// @2B8: iconst_m1
		// @2B9: iconst_1
		// @2BA: iconst_1
		// @2BB: getstatic game.C_100112_r game.C_100003_ga.field_103541_q
		// @2BE: getfield int game.C_100112_r.field_101763_H
		// @2C1: getstatic game.C_100112_r game.C_100003_ga.field_103541_q
		// @2C4: getfield int game.C_100112_r.field_101772_Q
		// @2C7: iadd
		// @2C8: invokevirtual game.C_100112_r.func_101729_a(java.lang.String, int, int, int, int, int, int, int, int, int)int
		// @2CB: pop
		// @2CC: iconst_0
		// @2CD: iconst_3
		// @2CE: iconst_0
		// @2CF: getstatic game.C_100037_wb[] game.C_100053_vn.field_102845_Z
		// @2D2: iload #7
		// @2D4: aaload
		// @2D5: getfield int game.C_100037_wb.field_102337_u
		// @2D8: iconst_1
		// @2D9: getstatic game.C_100037_wb[] game.C_100053_vn.field_102845_Z
		// @2DC: iload #7
		// @2DE: aaload
		// @2DF: getfield int game.C_100037_wb.field_102339_s
		// @2E2: ldc 38642 (0x96f2)
		// @2E4: getstatic game.C_100037_wb[] game.C_100053_vn.field_102845_Z
		// @2E7: iload #7
		// @2E9: aaload
		// @2EA: invokestatic game.C_100202_qi.func_105911_a(int, int, int, int, int, int, int, game.C_100037_wb)void
		// @2ED: iinc #7 +1
		// @2F0: iload #10
		// @2F2: ifne @38B
		// @2F5: iload #10
		// @2F7: ifeq @280
		// @2FA: goto @2FE
		// @2FD: athrow
		// @2FE: aconst_null
		// @2FF: putstatic java.lang.String[] game.C_100041_wf.field_104102_f
		// @302: getstatic game.C_100037_wb game.C_100180_ce.field_104804_B
		// @305: invokevirtual game.C_100037_wb.func_102381_e()game.C_100037_wb
		// @308: putstatic game.C_100037_wb game.C_100312_ld.field_107151_f
		// @30B: getstatic game.C_100037_wb game.C_100312_ld.field_107151_f
		// @30E: invokevirtual game.C_100037_wb.func_102379_d()void
		// @311: iconst_0
		// @312: getstatic int game.C_100196_rb.field_105819_e
		// @315: iconst_m1
		// @316: bipush 64 (0x40)
		// @318: iconst_2
		// @319: getstatic int game.C_100196_rb.field_105821_c
		// @31C: imul
		// @31D: iconst_3
		// @31E: idiv
		// @31F: iconst_0
		// @320: invokestatic game.C_100068_vc.func_104338_a(int, int, int, int, int, int)void
		// @323: aload_1
		// @324: iload_2
		// @325: iload_3
		// @326: invokestatic game.C_100196_rb.func_105808_a(int[], int, int)void
		// @329: getstatic int[] game.C_100032_gk.field_103129_U
		// @32C: invokestatic game.C_100196_rb.func_105777_b(int[])void
		// @32F: sipush 390 (0x0186)
		// @332: getstatic game.C_100037_wb game.C_100252_pn.field_105513_r
		// @335: getfield int game.C_100037_wb.field_102337_u
		// @338: getstatic game.C_100037_wb game.C_100061_dh.field_101981_Zb
		// @33B: getfield int game.C_100037_wb.field_102337_u
		// @33E: ineg
		// @33F: iadd
		// @340: iconst_2
		// @341: idiv
		// @342: iadd
		// @343: putstatic int game.C_100006_fj.field_103616_f
		// @346: sipush 231 (0x00E7)
		// @349: getstatic game.C_100037_wb game.C_100252_pn.field_105513_r
		// @34C: getfield int game.C_100037_wb.field_102339_s
		// @34F: getstatic game.C_100037_wb game.C_100061_dh.field_101981_Zb
		// @352: getfield int game.C_100037_wb.field_102339_s
		// @355: ineg
		// @356: iadd
		// @357: iconst_2
		// @358: idiv
		// @359: iadd
		// @35A: putstatic int game.C_100200_ba.field_105849_d
		// @35D: sipush 390 (0x0186)
		// @360: getstatic game.C_100037_wb game.C_100061_dh.field_101981_Zb
		// @363: getfield int game.C_100037_wb.field_102337_u
		// @366: ineg
		// @367: getstatic game.C_100037_wb game.C_100252_pn.field_105513_r
		// @36A: getfield int game.C_100037_wb.field_102337_u
		// @36D: iadd
		// @36E: iconst_2
		// @36F: idiv
		// @370: iadd
		// @371: putstatic int game.C_100310_lj.field_100548_z
		// @374: getstatic game.C_100037_wb game.C_100061_dh.field_101981_Zb
		// @377: getfield int game.C_100037_wb.field_102339_s
		// @37A: ineg
		// @37B: getstatic game.C_100037_wb game.C_100252_pn.field_105513_r
		// @37E: getfield int game.C_100037_wb.field_102339_s
		// @381: iadd
		// @382: iconst_2
		// @383: idiv
		// @384: sipush 434 (0x01B2)
		// @387: iadd
		// @388: putstatic int game.C_100114_q.field_100488_w
		// @38B: aconst_null
		// @38C: putstatic game.C_100098_h game.C_100336_im.field_102545_s
		// @38F: aconst_null
		// @390: getstatic game.C_100037_wb game.C_100131_te.field_100759_n
		// @393: if_acmpeq @39A
		// @396: goto @39B
		// @399: athrow
		// @39A: return
		// @39B: getstatic game.C_100037_wb game.C_100269_ml.field_101129_k
		// @39E: ifnull @639
		// @3A1: getstatic game.C_100112_r game.C_100218_am.field_103109_D
		// @3A4: ifnull @639
		// @3A7: goto @3AB
		// @3AA: athrow
		// @3AB: getstatic int[] game.C_100196_rb.field_105818_d
		// @3AE: astore_1
		// @3AF: getstatic int game.C_100196_rb.field_105819_e
		// @3B2: istore_2
		// @3B3: getstatic int game.C_100196_rb.field_105821_c
		// @3B6: istore_3
		// @3B7: getstatic int[] game.C_100032_gk.field_103129_U
		// @3BA: invokestatic game.C_100196_rb.func_105801_a(int[])void
		// @3BD: sipush -30945 (0x871F)
		// @3C0: iconst_1
		// @3C1: anewarray java.lang.String
		// @3C4: dup
		// @3C5: iconst_0
		// @3C6: getstatic java.lang.String[] game.C_100057_dd.field_104255_d
		// @3C9: getstatic int game.C_100180_ce.field_104813_z
		// @3CC: aaload
		// @3CD: aastore
		// @3CE: getstatic java.lang.String game.C_100083_c.field_103174_X
		// @3D1: invokestatic game.C_100132_td.func_104965_a(int, java.lang.String[], java.lang.String)java.lang.String
		// @3D4: astore #4
		// @3D6: getstatic game.C_100112_r game.C_100218_am.field_103109_D
		// @3D9: aload #4
		// @3DB: getstatic int game.C_100066_dl.field_101646_x
		// @3DE: invokevirtual game.C_100112_r.func_101738_b(java.lang.String, int)int
		// @3E1: istore #5
		// @3E3: getstatic game.C_100112_r game.C_100218_am.field_103109_D
		// @3E6: aload #4
		// @3E8: getstatic int game.C_100066_dl.field_101646_x
		// @3EB: getstatic game.C_100112_r game.C_100218_am.field_103109_D
		// @3EE: getfield int game.C_100112_r.field_101763_H
		// @3F1: getstatic game.C_100112_r game.C_100218_am.field_103109_D
		// @3F4: getfield int game.C_100112_r.field_101772_Q
		// @3F7: iadd
		// @3F8: invokevirtual game.C_100112_r.func_101734_a(java.lang.String, int, int)int
		// @3FB: istore #6
		// @3FD: getstatic int game.C_100066_dl.field_101646_x
		// @400: iload #5
		// @402: isub
		// @403: iconst_2
		// @404: idiv
		// @405: getstatic int game.C_100211_qd.field_102139_rc
		// @408: iadd
		// @409: istore #7
		// @40B: iinc #7 +253
		// @40E: iinc #5 +6
		// @411: getstatic int game.C_100056_de.field_103186_jb
		// @414: iload #6
		// @416: ineg
		// @417: getstatic int game.C_100277_nc.field_106742_p
		// @41A: iadd
		// @41B: iconst_2
		// @41C: idiv
		// @41D: iadd
		// @41E: istore #8
		// @420: iload #7
		// @422: iconst_m1
		// @423: ixor
		// @424: iconst_m1
		// @425: if_icmple @46B
		// @428: iload #7
		// @42A: ineg
		// @42B: istore #9
		// @42D: getstatic int game.C_100170_cm.field_105541_c
		// @430: iload #9
		// @432: isub
		// @433: putstatic int game.C_100170_cm.field_105541_c
		// @436: iload #5
		// @438: iconst_2
		// @439: iload #9
		// @43B: imul
		// @43C: iadd
		// @43D: istore #5
		// @43F: getstatic game.C_100037_wb game.C_100269_ml.field_101129_k
		// @442: dup
		// @443: getfield int game.C_100037_wb.field_102341_y
		// @446: iconst_2
		// @447: iload #9
		// @449: imul
		// @44A: iadd
		// @44B: putfield int game.C_100037_wb.field_102341_y
		// @44E: getstatic game.C_100037_wb game.C_100269_ml.field_101129_k
		// @451: dup
		// @452: getfield int game.C_100037_wb.field_102335_w
		// @455: iload #9
		// @457: iadd
		// @458: putfield int game.C_100037_wb.field_102335_w
		// @45B: iload #7
		// @45D: iload #9
		// @45F: iadd
		// @460: istore #7
		// @462: getstatic int game.C_100211_qd.field_102139_rc
		// @465: iload #9
		// @467: iadd
		// @468: putstatic int game.C_100211_qd.field_102139_rc
		// @46B: iinc #6 +6
		// @46E: iinc #8 +253
		// @471: iload #7
		// @473: iload #5
		// @475: ineg
		// @476: isub
		// @477: getstatic game.C_100037_wb game.C_100269_ml.field_101129_k
		// @47A: getfield int game.C_100037_wb.field_102341_y
		// @47D: if_icmpgt @484
		// @480: goto @4D2
		// @483: athrow
		// @484: iload #7
		// @486: iload #5
		// @488: ineg
		// @489: isub
		// @48A: getstatic game.C_100037_wb game.C_100269_ml.field_101129_k
		// @48D: getfield int game.C_100037_wb.field_102341_y
		// @490: ineg
		// @491: iadd
		// @492: istore #9
		// @494: iload #7
		// @496: iload #9
		// @498: iadd
		// @499: istore #7
		// @49B: getstatic game.C_100037_wb game.C_100269_ml.field_101129_k
		// @49E: dup
		// @49F: getfield int game.C_100037_wb.field_102335_w
		// @4A2: iload #9
		// @4A4: iadd
		// @4A5: putfield int game.C_100037_wb.field_102335_w
		// @4A8: iload #5
		// @4AA: iload #9
		// @4AC: iconst_2
		// @4AD: imul
		// @4AE: iadd
		// @4AF: istore #5
		// @4B1: getstatic int game.C_100170_cm.field_105541_c
		// @4B4: iload #9
		// @4B6: isub
		// @4B7: putstatic int game.C_100170_cm.field_105541_c
		// @4BA: getstatic game.C_100037_wb game.C_100269_ml.field_101129_k
		// @4BD: dup
		// @4BE: getfield int game.C_100037_wb.field_102341_y
		// @4C1: iconst_2
		// @4C2: iload #9
		// @4C4: imul
		// @4C5: iadd
		// @4C6: putfield int game.C_100037_wb.field_102341_y
		// @4C9: getstatic int game.C_100211_qd.field_102139_rc
		// @4CC: iload #9
		// @4CE: iadd
		// @4CF: putstatic int game.C_100211_qd.field_102139_rc
		// @4D2: iconst_m1
		// @4D3: iload #8
		// @4D5: iconst_m1
		// @4D6: ixor
		// @4D7: if_icmplt @4DE
		// @4DA: goto @521
		// @4DD: athrow
		// @4DE: iload #8
		// @4E0: ineg
		// @4E1: istore #9
		// @4E3: getstatic int game.C_100316_lc.field_102416_y
		// @4E6: iload #9
		// @4E8: isub
		// @4E9: putstatic int game.C_100316_lc.field_102416_y
		// @4EC: getstatic int game.C_100056_de.field_103186_jb
		// @4EF: iload #9
		// @4F1: iadd
		// @4F2: putstatic int game.C_100056_de.field_103186_jb
		// @4F5: iload #6
		// @4F7: iconst_2
		// @4F8: iload #9
		// @4FA: imul
		// @4FB: iadd
		// @4FC: istore #6
		// @4FE: iload #8
		// @500: iload #9
		// @502: iadd
		// @503: istore #8
		// @505: getstatic game.C_100037_wb game.C_100269_ml.field_101129_k
		// @508: dup
		// @509: getfield int game.C_100037_wb.field_102332_H
		// @50C: iload #9
		// @50E: iadd
		// @50F: putfield int game.C_100037_wb.field_102332_H
		// @512: getstatic game.C_100037_wb game.C_100269_ml.field_101129_k
		// @515: dup
		// @516: getfield int game.C_100037_wb.field_102340_z
		// @519: iload #9
		// @51B: iconst_2
		// @51C: imul
		// @51D: iadd
		// @51E: putfield int game.C_100037_wb.field_102340_z
		// @521: getstatic game.C_100037_wb game.C_100269_ml.field_101129_k
		// @524: getfield int game.C_100037_wb.field_102340_z
		// @527: iload #6
		// @529: iload #8
		// @52B: iadd
		// @52C: if_icmpge @57C
		// @52F: getstatic game.C_100037_wb game.C_100269_ml.field_101129_k
		// @532: getfield int game.C_100037_wb.field_102340_z
		// @535: ineg
		// @536: iload #6
		// @538: iadd
		// @539: iload #8
		// @53B: iadd
		// @53C: istore #9
		// @53E: getstatic game.C_100037_wb game.C_100269_ml.field_101129_k
		// @541: dup
		// @542: getfield int game.C_100037_wb.field_102332_H
		// @545: iload #9
		// @547: iadd
		// @548: putfield int game.C_100037_wb.field_102332_H
		// @54B: getstatic int game.C_100316_lc.field_102416_y
		// @54E: iload #9
		// @550: isub
		// @551: putstatic int game.C_100316_lc.field_102416_y
		// @554: iload #8
		// @556: iload #9
		// @558: iadd
		// @559: istore #8
		// @55B: getstatic int game.C_100056_de.field_103186_jb
		// @55E: iload #9
		// @560: iadd
		// @561: putstatic int game.C_100056_de.field_103186_jb
		// @564: getstatic game.C_100037_wb game.C_100269_ml.field_101129_k
		// @567: dup
		// @568: getfield int game.C_100037_wb.field_102340_z
		// @56B: iconst_2
		// @56C: iload #9
		// @56E: imul
		// @56F: iadd
		// @570: putfield int game.C_100037_wb.field_102340_z
		// @573: iload #6
		// @575: iconst_2
		// @576: iload #9
		// @578: imul
		// @579: iadd
		// @57A: istore #6
		// @57C: getstatic game.C_100037_wb game.C_100269_ml.field_101129_k
		// @57F: invokevirtual game.C_100037_wb.func_102349_a()void
		// @582: new game.C_100037_wb
		// @585: dup
		// @586: getstatic game.C_100037_wb game.C_100269_ml.field_101129_k
		// @589: getfield int game.C_100037_wb.field_102341_y
		// @58C: getstatic game.C_100037_wb game.C_100269_ml.field_101129_k
		// @58F: getfield int game.C_100037_wb.field_102340_z
		// @592: invokespecial game.C_100037_wb.<init>(int, int)void
		// @595: astore #9
		// @597: aload #9
		// @599: invokevirtual game.C_100037_wb.func_102379_d()void
		// @59C: getstatic game.C_100112_r game.C_100218_am.field_103109_D
		// @59F: aload #4
		// @5A1: getstatic int game.C_100211_qd.field_102139_rc
		// @5A4: getstatic int game.C_100056_de.field_103186_jb
		// @5A7: getstatic int game.C_100066_dl.field_101646_x
		// @5AA: getstatic int game.C_100277_nc.field_106742_p
		// @5AD: ldc 16777215 (0xffffff)
		// @5AF: iconst_m1
		// @5B0: iconst_1
		// @5B1: iconst_1
		// @5B2: getstatic game.C_100112_r game.C_100218_am.field_103109_D
		// @5B5: getfield int game.C_100112_r.field_101772_Q
		// @5B8: getstatic game.C_100112_r game.C_100218_am.field_103109_D
		// @5BB: getfield int game.C_100112_r.field_101763_H
		// @5BE: ineg
		// @5BF: isub
		// @5C0: invokevirtual game.C_100112_r.func_101729_a(java.lang.String, int, int, int, int, int, int, int, int, int)int
		// @5C3: pop
		// @5C4: iconst_0
		// @5C5: iconst_3
		// @5C6: iconst_0
		// @5C7: aload #9
		// @5C9: getfield int game.C_100037_wb.field_102340_z
		// @5CC: iconst_1
		// @5CD: aload #9
		// @5CF: getfield int game.C_100037_wb.field_102341_y
		// @5D2: ldc 38642 (0x96f2)
		// @5D4: aload #9
		// @5D6: invokestatic game.C_100202_qi.func_105911_a(int, int, int, int, int, int, int, game.C_100037_wb)void
		// @5D9: getstatic game.C_100037_wb game.C_100269_ml.field_101129_k
		// @5DC: invokevirtual game.C_100037_wb.func_102379_d()void
		// @5DF: aload #9
		// @5E1: iconst_0
		// @5E2: iconst_0
		// @5E3: invokevirtual game.C_100037_wb.func_102353_h(int, int)void
		// @5E6: new game.C_100037_wb
		// @5E9: dup
		// @5EA: sipush 640 (0x0280)
		// @5ED: sipush 480 (0x01E0)
		// @5F0: invokespecial game.C_100037_wb.<init>(int, int)void
		// @5F3: putstatic game.C_100037_wb game.C_100260_mc.field_102236_ic
		// @5F6: getstatic game.C_100037_wb game.C_100260_mc.field_102236_ic
		// @5F9: invokevirtual game.C_100037_wb.func_102379_d()void
		// @5FC: getstatic game.C_100037_wb game.C_100269_ml.field_101129_k
		// @5FF: getstatic int game.C_100170_cm.field_105541_c
		// @602: getstatic game.C_100037_wb game.C_100269_ml.field_101129_k
		// @605: getfield int game.C_100037_wb.field_102341_y
		// @608: ldc 116900673 (0x6f7c341)
		// @60A: ishr
		// @60B: iadd
		// @60C: getstatic game.C_100037_wb game.C_100269_ml.field_101129_k
		// @60F: getfield int game.C_100037_wb.field_102340_z
		// @612: ldc 452225473 (0x1af469c1)
		// @614: ishr
		// @615: getstatic int game.C_100316_lc.field_102416_y
		// @618: ineg
		// @619: isub
		// @61A: getstatic int game.C_100044_vm.field_100945_s
		// @61D: sipush 4096 (0x1000)
		// @620: invokevirtual game.C_100037_wb.func_102373_c(int, int, int, int)void
		// @623: aconst_null
		// @624: putstatic game.C_100037_wb game.C_100269_ml.field_101129_k
		// @627: getstatic game.C_100037_wb game.C_100260_mc.field_102236_ic
		// @62A: invokevirtual game.C_100037_wb.func_102385_c()void
		// @62D: aload_1
		// @62E: iload_2
		// @62F: iload_3
		// @630: invokestatic game.C_100196_rb.func_105808_a(int[], int, int)void
		// @633: getstatic int[] game.C_100032_gk.field_103129_U
		// @636: invokestatic game.C_100196_rb.func_105777_b(int[])void
		// @639: aconst_null
		// @63A: getstatic java.lang.String game.C_100245_pf.field_106387_e
		// @63D: if_acmpeq @6F5
		// @640: aconst_null
		// @641: getstatic game.C_100112_r game.C_100003_ga.field_103541_q
		// @644: if_acmpeq @6F5
		// @647: goto @64B
		// @64A: athrow
		// @64B: getstatic int[] game.C_100196_rb.field_105818_d
		// @64E: astore_1
		// @64F: getstatic int game.C_100196_rb.field_105819_e
		// @652: istore_2
		// @653: getstatic int game.C_100196_rb.field_105821_c
		// @656: istore_3
		// @657: getstatic int[] game.C_100032_gk.field_103129_U
		// @65A: invokestatic game.C_100196_rb.func_105801_a(int[])void
		// @65D: new game.C_100037_wb
		// @660: dup
		// @661: sipush 412 (0x019C)
		// @664: bipush 43 (0x2B)
		// @666: invokespecial game.C_100037_wb.<init>(int, int)void
		// @669: astore #4
		// @66B: sipush -30945 (0x871F)
		// @66E: iconst_1
		// @66F: anewarray java.lang.String
		// @672: dup
		// @673: iconst_0
		// @674: getstatic java.lang.String game.C_100245_pf.field_106387_e
		// @677: aastore
		// @678: getstatic java.lang.String game.C_100056_de.field_103183_eb
		// @67B: invokestatic game.C_100132_td.func_104965_a(int, java.lang.String[], java.lang.String)java.lang.String
		// @67E: astore #5
		// @680: aconst_null
		// @681: putstatic java.lang.String game.C_100245_pf.field_106387_e
		// @684: aload #4
		// @686: invokevirtual game.C_100037_wb.func_102379_d()void
		// @689: getstatic game.C_100112_r game.C_100003_ga.field_103541_q
		// @68C: aload #5
		// @68E: iconst_3
		// @68F: iconst_3
		// @690: aload #4
		// @692: getfield int game.C_100037_wb.field_102339_s
		// @695: bipush 6 (0x06)
		// @697: isub
		// @698: bipush -6 (0xFA)
		// @69A: aload #4
		// @69C: getfield int game.C_100037_wb.field_102337_u
		// @69F: iadd
		// @6A0: ldc 16777215 (0xffffff)
		// @6A2: iconst_m1
		// @6A3: iconst_0
		// @6A4: iconst_1
		// @6A5: getstatic game.C_100112_r game.C_100003_ga.field_103541_q
		// @6A8: getfield int game.C_100112_r.field_101763_H
		// @6AB: getstatic game.C_100112_r game.C_100003_ga.field_103541_q
		// @6AE: getfield int game.C_100112_r.field_101772_Q
		// @6B1: iadd
		// @6B2: invokevirtual game.C_100112_r.func_101729_a(java.lang.String, int, int, int, int, int, int, int, int, int)int
		// @6B5: pop
		// @6B6: iconst_0
		// @6B7: iconst_3
		// @6B8: iconst_0
		// @6B9: aload #4
		// @6BB: getfield int game.C_100037_wb.field_102337_u
		// @6BE: iconst_1
		// @6BF: aload #4
		// @6C1: getfield int game.C_100037_wb.field_102339_s
		// @6C4: ldc 38642 (0x96f2)
		// @6C6: aload #4
		// @6C8: invokestatic game.C_100202_qi.func_105911_a(int, int, int, int, int, int, int, game.C_100037_wb)void
		// @6CB: getstatic game.C_100037_wb game.C_100131_te.field_100759_n
		// @6CE: invokevirtual game.C_100037_wb.func_102379_d()void
		// @6D1: aload #4
		// @6D3: sipush 199 (0x00C7)
		// @6D6: getstatic game.C_100037_wb game.C_100131_te.field_100759_n
		// @6D9: getfield int game.C_100037_wb.field_102335_w
		// @6DC: isub
		// @6DD: bipush 83 (0x53)
		// @6DF: getstatic game.C_100037_wb game.C_100131_te.field_100759_n
		// @6E2: getfield int game.C_100037_wb.field_102332_H
		// @6E5: isub
		// @6E6: invokevirtual game.C_100037_wb.func_102353_h(int, int)void
		// @6E9: aload_1
		// @6EA: iload_2
		// @6EB: iload_3
		// @6EC: invokestatic game.C_100196_rb.func_105808_a(int[], int, int)void
		// @6EF: getstatic int[] game.C_100032_gk.field_103129_U
		// @6F2: invokestatic game.C_100196_rb.func_105777_b(int[])void
		// @6F5: getstatic game.C_100037_wb game.C_100104_v.field_104696_l
		// @6F8: ifnull @7F8
		// @6FB: getstatic game.C_100112_r game.C_100003_ga.field_103541_q
		// @6FE: ifnonnull @709
		// @701: goto @705
		// @704: athrow
		// @705: goto @7F8
		// @708: athrow
		// @709: getstatic int[] game.C_100196_rb.field_105818_d
		// @70C: astore_1
		// @70D: getstatic int game.C_100196_rb.field_105819_e
		// @710: istore_2
		// @711: getstatic int game.C_100196_rb.field_105821_c
		// @714: istore_3
		// @715: getstatic int[] game.C_100032_gk.field_103129_U
		// @718: invokestatic game.C_100196_rb.func_105801_a(int[])void
		// @71B: bipush 6 (0x06)
		// @71D: getstatic game.C_100112_r game.C_100003_ga.field_103541_q
		// @720: getstatic java.lang.String game.C_100278_nd.field_101206_x
		// @723: sipush 640 (0x0280)
		// @726: invokevirtual game.C_100112_r.func_101738_b(java.lang.String, int)int
		// @729: iadd
		// @72A: istore #4
		// @72C: iload #4
		// @72E: getstatic game.C_100037_wb game.C_100104_v.field_104696_l
		// @731: getfield int game.C_100037_wb.field_102341_y
		// @734: iadd
		// @735: bipush 20 (0x14)
		// @737: iadd
		// @738: istore #5
		// @73A: iload #5
		// @73C: iconst_2
		// @73D: idiv
		// @73E: ineg
		// @73F: sipush 427 (0x01AB)
		// @742: iadd
		// @743: istore #6
		// @745: bipush 20 (0x14)
		// @747: iload #6
		// @749: iadd
		// @74A: getstatic game.C_100037_wb game.C_100104_v.field_104696_l
		// @74D: getfield int game.C_100037_wb.field_102341_y
		// @750: ineg
		// @751: isub
		// @752: istore #7
		// @754: getstatic game.C_100037_wb game.C_100131_te.field_100759_n
		// @757: invokevirtual game.C_100037_wb.func_102379_d()void
		// @75A: getstatic game.C_100112_r game.C_100003_ga.field_103541_q
		// @75D: getstatic java.lang.String game.C_100278_nd.field_101206_x
		// @760: iload #7
		// @762: getstatic game.C_100037_wb game.C_100131_te.field_100759_n
		// @765: getfield int game.C_100037_wb.field_102335_w
		// @768: ineg
		// @769: iadd
		// @76A: getstatic game.C_100112_r game.C_100003_ga.field_103541_q
		// @76D: getfield int game.C_100112_r.field_101763_H
		// @770: getstatic game.C_100112_r game.C_100003_ga.field_103541_q
		// @773: getfield int game.C_100112_r.field_101772_Q
		// @776: sipush 155 (0x009B)
		// @779: iadd
		// @77A: getstatic game.C_100037_wb game.C_100131_te.field_100759_n
		// @77D: getfield int game.C_100037_wb.field_102332_H
		// @780: isub
		// @781: iadd
		// @782: ldc 16777215 (0xffffff)
		// @784: iconst_m1
		// @785: invokevirtual game.C_100112_r.func_101749_c(java.lang.String, int, int, int, int)void
		// @788: getstatic game.C_100037_wb game.C_100131_te.field_100759_n
		// @78B: getfield int game.C_100037_wb.field_102332_H
		// @78E: ineg
		// @78F: sipush 155 (0x009B)
		// @792: iadd
		// @793: iconst_3
		// @794: getstatic game.C_100037_wb game.C_100131_te.field_100759_n
		// @797: getfield int game.C_100037_wb.field_102335_w
		// @79A: ineg
		// @79B: iload #7
		// @79D: bipush -4 (0xFC)
		// @79F: iadd
		// @7A0: iadd
		// @7A1: bipush 50 (0x32)
		// @7A3: iconst_1
		// @7A4: iload #4
		// @7A6: ldc 38642 (0x96f2)
		// @7A8: getstatic game.C_100037_wb game.C_100131_te.field_100759_n
		// @7AB: invokestatic game.C_100202_qi.func_105911_a(int, int, int, int, int, int, int, game.C_100037_wb)void
		// @7AE: getstatic game.C_100037_wb game.C_100131_te.field_100759_n
		// @7B1: getfield int game.C_100037_wb.field_102332_H
		// @7B4: ineg
		// @7B5: sipush 155 (0x009B)
		// @7B8: iadd
		// @7B9: getstatic game.C_100112_r game.C_100003_ga.field_103541_q
		// @7BC: getfield int game.C_100112_r.field_101772_Q
		// @7BF: ineg
		// @7C0: getstatic game.C_100037_wb game.C_100104_v.field_104696_l
		// @7C3: getfield int game.C_100037_wb.field_102340_z
		// @7C6: iadd
		// @7C7: bipush -3 (0xFD)
		// @7C9: getstatic game.C_100112_r game.C_100003_ga.field_103541_q
		// @7CC: getfield int game.C_100112_r.field_101763_H
		// @7CF: isub
		// @7D0: iadd
		// @7D1: iconst_2
		// @7D2: idiv
		// @7D3: isub
		// @7D4: istore #8
		// @7D6: getstatic game.C_100037_wb game.C_100104_v.field_104696_l
		// @7D9: iload #6
		// @7DB: getstatic game.C_100037_wb game.C_100131_te.field_100759_n
		// @7DE: getfield int game.C_100037_wb.field_102335_w
		// @7E1: ineg
		// @7E2: iadd
		// @7E3: iload #8
		// @7E5: invokevirtual game.C_100037_wb.func_102353_h(int, int)void
		// @7E8: aload_1
		// @7E9: iload_2
		// @7EA: iload_3
		// @7EB: invokestatic game.C_100196_rb.func_105808_a(int[], int, int)void
		// @7EE: getstatic int[] game.C_100032_gk.field_103129_U
		// @7F1: invokestatic game.C_100196_rb.func_105777_b(int[])void
		// @7F4: aconst_null
		// @7F5: putstatic game.C_100037_wb game.C_100104_v.field_104696_l
		// @7F8: getstatic int[] game.C_100032_gk.field_103129_U
		// @7FB: invokestatic game.C_100196_rb.func_105801_a(int[])void
		// @7FE: bipush 16 (0x10)
		// @800: bipush 16 (0x10)
		// @802: sipush 608 (0x0260)
		// @805: bipush 112 (0x70)
		// @807: bipush 15 (0x0F)
		// @809: getstatic int game.C_100220_ac.field_106054_g
		// @80C: getstatic int game.C_100102_w.field_104648_u
		// @80F: invokestatic game.C_100196_rb.func_105811_a(int, int, int, int, int, int, int)void
		// @812: sipush 231 (0x00E7)
		// @815: sipush 144 (0x0090)
		// @818: sipush 393 (0x0189)
		// @81B: sipush 232 (0x00E8)
		// @81E: bipush 15 (0x0F)
		// @820: getstatic int game.C_100220_ac.field_106054_g
		// @823: getstatic int game.C_100102_w.field_104648_u
		// @826: invokestatic game.C_100196_rb.func_105811_a(int, int, int, int, int, int, int)void
		// @829: getstatic game.C_100037_wb game.C_100306_kn.field_107132_e
		// @82C: ifnull @83B
		// @82F: getstatic game.C_100037_wb game.C_100306_kn.field_107132_e
		// @832: iconst_0
		// @833: iconst_0
		// @834: invokevirtual game.C_100037_wb.func_102353_h(int, int)void
		// @837: goto @83B
		// @83A: athrow
		// @83B: getstatic game.C_100037_wb game.C_100233_oa.field_106253_v
		// @83E: ifnull @84D
		// @841: getstatic game.C_100037_wb game.C_100233_oa.field_106253_v
		// @844: iconst_0
		// @845: iconst_0
		// @846: invokevirtual game.C_100037_wb.func_102353_h(int, int)void
		// @849: goto @84D
		// @84C: athrow
		// @84D: getstatic game.C_100037_wb game.C_100131_te.field_100759_n
		// @850: iconst_0
		// @851: iconst_0
		// @852: invokevirtual game.C_100037_wb.func_102353_h(int, int)void
		// @855: iload_0
		// @856: bipush -37 (0xDB)
		// @858: if_icmplt @85C
		// @85B: return
		// @85C: getstatic game.C_100037_wb game.C_100260_mc.field_102236_ic
		// @85F: ifnull @86E
		// @862: getstatic game.C_100037_wb game.C_100260_mc.field_102236_ic
		// @865: iconst_0
		// @866: iconst_0
		// @867: invokevirtual game.C_100037_wb.func_102353_h(int, int)void
		// @86A: goto @86E
		// @86D: athrow
		// @86E: aconst_null
		// @86F: getstatic game.C_100037_wb game.C_100252_pn.field_105513_r
		// @872: if_acmpeq @940
		// @875: aconst_null
		// @876: getstatic game.C_100037_wb game.C_100061_dh.field_101981_Zb
		// @879: if_acmpeq @940
		// @87C: goto @880
		// @87F: athrow
		// @880: getstatic game.C_100037_wb game.C_100252_pn.field_105513_r
		// @883: sipush 231 (0x00E7)
		// @886: sipush 390 (0x0186)
		// @889: invokevirtual game.C_100037_wb.func_102353_h(int, int)void
		// @88C: getstatic game.C_100037_wb game.C_100180_ce.field_104804_B
		// @88F: astore_1
		// @890: getstatic game.C_100333_ij game.C_100220_ac.field_106064_h
		// @893: getfield int game.C_100333_ij.field_107347_b
		// @896: ifeq @89D
		// @899: goto @8A1
		// @89C: athrow
		// @89D: getstatic game.C_100037_wb game.C_100312_ld.field_107151_f
		// @8A0: astore_1
		// @8A1: aload_1
		// @8A2: iconst_0
		// @8A3: iconst_0
		// @8A4: invokevirtual game.C_100037_wb.func_102353_h(int, int)void
		// @8A7: bipush 40 (0x28)
		// @8A9: bipush 40 (0x28)
		// @8AB: iconst_0
		// @8AC: getstatic int game.C_100287_nm.field_106826_b
		// @8AF: iconst_0
		// @8B0: getstatic game.C_100333_ij game.C_100220_ac.field_106064_h
		// @8B3: getfield int game.C_100333_ij.field_107347_b
		// @8B6: if_icmpeq @8BE
		// @8B9: iconst_3
		// @8BA: goto @8BF
		// @8BD: athrow
		// @8BE: iconst_4
		// @8BF: ishl
		// @8C0: invokestatic game.C_100166_sg.func_105460_a(boolean, int)int
		// @8C3: imul
		// @8C4: ldc 607056528 (0x242ef290)
		// @8C6: ishr
		// @8C7: ineg
		// @8C8: isub
		// @8C9: istore_2
		// @8CA: iload_2
		// @8CB: ifle @922
		// @8CE: getstatic game.C_100037_wb game.C_100252_pn.field_105513_r
		// @8D1: sipush 230 (0x00E6)
		// @8D4: sipush 389 (0x0185)
		// @8D7: iload_2
		// @8D8: invokevirtual game.C_100037_wb.func_102367_c(int, int, int)void
		// @8DB: getstatic game.C_100037_wb game.C_100252_pn.field_105513_r
		// @8DE: sipush 232 (0x00E8)
		// @8E1: sipush 389 (0x0185)
		// @8E4: iload_2
		// @8E5: invokevirtual game.C_100037_wb.func_102367_c(int, int, int)void
		// @8E8: getstatic game.C_100037_wb game.C_100252_pn.field_105513_r
		// @8EB: sipush 232 (0x00E8)
		// @8EE: sipush 391 (0x0187)
		// @8F1: iload_2
		// @8F2: invokevirtual game.C_100037_wb.func_102367_c(int, int, int)void
		// @8F5: getstatic game.C_100037_wb game.C_100252_pn.field_105513_r
		// @8F8: sipush 230 (0x00E6)
		// @8FB: sipush 391 (0x0187)
		// @8FE: iload_2
		// @8FF: invokevirtual game.C_100037_wb.func_102367_c(int, int, int)void
		// @902: aload_1
		// @903: iconst_1
		// @904: iconst_1
		// @905: iload_2
		// @906: invokevirtual game.C_100037_wb.func_102367_c(int, int, int)void
		// @909: aload_1
		// @90A: iconst_m1
		// @90B: iconst_1
		// @90C: iload_2
		// @90D: invokevirtual game.C_100037_wb.func_102367_c(int, int, int)void
		// @910: aload_1
		// @911: iconst_1
		// @912: iconst_m1
		// @913: iload_2
		// @914: invokevirtual game.C_100037_wb.func_102367_c(int, int, int)void
		// @917: aload_1
		// @918: iconst_m1
		// @919: iconst_m1
		// @91A: iload_2
		// @91B: invokevirtual game.C_100037_wb.func_102367_c(int, int, int)void
		// @91E: goto @922
		// @921: athrow
		// @922: iconst_m1
		// @923: getstatic game.C_100333_ij game.C_100220_ac.field_106064_h
		// @926: getfield int game.C_100333_ij.field_107347_b
		// @929: iconst_m1
		// @92A: ixor
		// @92B: if_icmpne @933
		// @92E: iconst_1
		// @92F: goto @934
		// @932: athrow
		// @933: iconst_0
		// @934: sipush 16412 (0x401C)
		// @937: getstatic int game.C_100006_fj.field_103616_f
		// @93A: getstatic int game.C_100200_ba.field_105849_d
		// @93D: invokestatic game.C_100297_kf.func_101233_a(boolean, int, int, int)void
		// @940: getstatic game.C_100037_wb game.C_100252_pn.field_105513_r
		// @943: ifnull @9B9
		// @946: getstatic game.C_100037_wb game.C_100061_dh.field_101981_Zb
		// @949: ifnonnull @954
		// @94C: goto @950
		// @94F: athrow
		// @950: goto @9B9
		// @953: athrow
		// @954: getstatic game.C_100037_wb game.C_100252_pn.field_105513_r
		// @957: sipush 434 (0x01B2)
		// @95A: sipush 390 (0x0186)
		// @95D: invokevirtual game.C_100037_wb.func_102353_h(int, int)void
		// @960: getstatic game.C_100037_wb game.C_100270_mi.field_102271_Wb
		// @963: iconst_0
		// @964: iconst_0
		// @965: invokevirtual game.C_100037_wb.func_102353_h(int, int)void
		// @968: bipush -2 (0xFE)
		// @96A: getstatic game.C_100333_ij game.C_100220_ac.field_106064_h
		// @96D: getfield int game.C_100333_ij.field_107347_b
		// @970: iconst_m1
		// @971: ixor
		// @972: if_icmpeq @979
		// @975: goto @99A
		// @978: athrow
		// @979: sipush 392 (0x0188)
		// @97C: bipush -4 (0xFC)
		// @97E: getstatic game.C_100037_wb game.C_100252_pn.field_105513_r
		// @981: getfield int game.C_100037_wb.field_102339_s
		// @984: iadd
		// @985: iconst_m1
		// @986: bipush 64 (0x40)
		// @988: getstatic game.C_100037_wb game.C_100252_pn.field_105513_r
		// @98B: getfield int game.C_100037_wb.field_102337_u
		// @98E: bipush 7 (0x07)
		// @990: imul
		// @991: bipush 12 (0x0C)
		// @993: idiv
		// @994: sipush 436 (0x01B4)
		// @997: invokestatic game.C_100068_vc.func_104338_a(int, int, int, int, int, int)void
		// @99A: bipush -2 (0xFE)
		// @99C: getstatic game.C_100333_ij game.C_100220_ac.field_106064_h
		// @99F: getfield int game.C_100333_ij.field_107347_b
		// @9A2: iconst_m1
		// @9A3: ixor
		// @9A4: if_icmpne @9AC
		// @9A7: iconst_1
		// @9A8: goto @9AD
		// @9AB: athrow
		// @9AC: iconst_0
		// @9AD: sipush 16412 (0x401C)
		// @9B0: getstatic int game.C_100310_lj.field_100548_z
		// @9B3: getstatic int game.C_100114_q.field_100488_w
		// @9B6: invokestatic game.C_100297_kf.func_101233_a(boolean, int, int, int)void
		// @9B9: getstatic game.C_100037_wb game.C_100309_lk.field_103275_Z
		// @9BC: ifnull @B04
		// @9BF: sipush 357 (0x0165)
		// @9C2: getstatic game.C_100037_wb game.C_100309_lk.field_103275_Z
		// @9C5: getfield int game.C_100037_wb.field_102340_z
		// @9C8: iconst_2
		// @9C9: idiv
		// @9CA: isub
		// @9CB: istore_1
		// @9CC: getstatic game.C_100037_wb game.C_100309_lk.field_103275_Z
		// @9CF: getstatic game.C_100037_wb game.C_100309_lk.field_103275_Z
		// @9D2: getfield int game.C_100037_wb.field_102341_y
		// @9D5: ineg
		// @9D6: sipush 269 (0x010D)
		// @9D9: iadd
		// @9DA: iload_1
		// @9DB: invokevirtual game.C_100037_wb.func_102353_h(int, int)void
		// @9DE: getstatic game.C_100037_wb game.C_100140_bj.field_102964_g
		// @9E1: sipush 586 (0x024A)
		// @9E4: iload_1
		// @9E5: invokevirtual game.C_100037_wb.func_102353_h(int, int)void
		// @9E8: iload_1
		// @9E9: iconst_m1
		// @9EA: ixor
		// @9EB: getstatic int game.C_100338_jc.field_105370_l
		// @9EE: iconst_m1
		// @9EF: ixor
		// @9F0: if_icmple @B04
		// @9F3: getstatic game.C_100037_wb game.C_100309_lk.field_103275_Z
		// @9F6: getfield int game.C_100037_wb.field_102337_u
		// @9F9: iload_1
		// @9FA: iadd
		// @9FB: iconst_m1
		// @9FC: ixor
		// @9FD: getstatic int game.C_100338_jc.field_105370_l
		// @A00: iconst_m1
		// @A01: ixor
		// @A02: if_icmplt @A0D
		// @A05: goto @A09
		// @A08: athrow
		// @A09: goto @B04
		// @A0C: athrow
		// @A0D: bipush 40 (0x28)
		// @A0F: iconst_0
		// @A10: getstatic int game.C_100287_nm.field_106826_b
		// @A13: ldc -2083326876 (0x83d2f464)
		// @A15: ishl
		// @A16: invokestatic game.C_100166_sg.func_105460_a(boolean, int)int
		// @A19: bipush 40 (0x28)
		// @A1B: imul
		// @A1C: ldc 176562896 (0xa8622d0)
		// @A1E: ishr
		// @A1F: iadd
		// @A20: istore_2
		// @A21: iload_2
		// @A22: iconst_m1
		// @A23: ixor
		// @A24: iconst_m1
		// @A25: if_icmpge @B04
		// @A28: sipush 269 (0x010D)
		// @A2B: getstatic game.C_100037_wb game.C_100309_lk.field_103275_Z
		// @A2E: getfield int game.C_100037_wb.field_102339_s
		// @A31: ineg
		// @A32: iadd
		// @A33: getstatic int game.C_100015_wh.field_103781_g
		// @A36: if_icmpge @AA9
		// @A39: goto @A3D
		// @A3C: athrow
		// @A3D: sipush 269 (0x010D)
		// @A40: getstatic int game.C_100015_wh.field_103781_g
		// @A43: if_icmple @AA9
		// @A46: goto @A4A
		// @A49: athrow
		// @A4A: getstatic game.C_100037_wb game.C_100309_lk.field_103275_Z
		// @A4D: iconst_m1
		// @A4E: sipush 269 (0x010D)
		// @A51: getstatic game.C_100037_wb game.C_100309_lk.field_103275_Z
		// @A54: getfield int game.C_100037_wb.field_102341_y
		// @A57: ineg
		// @A58: iadd
		// @A59: iadd
		// @A5A: iconst_m1
		// @A5B: iload_1
		// @A5C: iadd
		// @A5D: iload_2
		// @A5E: invokevirtual game.C_100037_wb.func_102367_c(int, int, int)void
		// @A61: getstatic game.C_100037_wb game.C_100309_lk.field_103275_Z
		// @A64: sipush 269 (0x010D)
		// @A67: getstatic game.C_100037_wb game.C_100309_lk.field_103275_Z
		// @A6A: getfield int game.C_100037_wb.field_102341_y
		// @A6D: isub
		// @A6E: iconst_m1
		// @A6F: isub
		// @A70: iload_1
		// @A71: iconst_m1
		// @A72: iadd
		// @A73: iload_2
		// @A74: invokevirtual game.C_100037_wb.func_102367_c(int, int, int)void
		// @A77: getstatic game.C_100037_wb game.C_100309_lk.field_103275_Z
		// @A7A: getstatic game.C_100037_wb game.C_100309_lk.field_103275_Z
		// @A7D: getfield int game.C_100037_wb.field_102341_y
		// @A80: ineg
		// @A81: sipush 268 (0x010C)
		// @A84: iadd
		// @A85: iconst_1
		// @A86: iload_1
		// @A87: iadd
		// @A88: iload_2
		// @A89: invokevirtual game.C_100037_wb.func_102367_c(int, int, int)void
		// @A8C: getstatic game.C_100037_wb game.C_100309_lk.field_103275_Z
		// @A8F: sipush 270 (0x010E)
		// @A92: getstatic game.C_100037_wb game.C_100309_lk.field_103275_Z
		// @A95: getfield int game.C_100037_wb.field_102341_y
		// @A98: isub
		// @A99: iload_1
		// @A9A: iconst_m1
		// @A9B: isub
		// @A9C: iload_2
		// @A9D: invokevirtual game.C_100037_wb.func_102367_c(int, int, int)void
		// @AA0: iload #10
		// @AA2: ifeq @B04
		// @AA5: goto @AA9
		// @AA8: athrow
		// @AA9: sipush -587 (0xFDB5)
		// @AAC: getstatic int game.C_100015_wh.field_103781_g
		// @AAF: iconst_m1
		// @AB0: ixor
		// @AB1: if_icmple @B04
		// @AB4: goto @AB8
		// @AB7: athrow
		// @AB8: getstatic int game.C_100015_wh.field_103781_g
		// @ABB: getstatic game.C_100037_wb game.C_100309_lk.field_103275_Z
		// @ABE: getfield int game.C_100037_wb.field_102339_s
		// @AC1: sipush 586 (0x024A)
		// @AC4: iadd
		// @AC5: if_icmplt @AD0
		// @AC8: goto @ACC
		// @ACB: athrow
		// @ACC: goto @B04
		// @ACF: athrow
		// @AD0: getstatic game.C_100037_wb game.C_100140_bj.field_102964_g
		// @AD3: sipush 585 (0x0249)
		// @AD6: iconst_m1
		// @AD7: iload_1
		// @AD8: iadd
		// @AD9: iload_2
		// @ADA: invokevirtual game.C_100037_wb.func_102367_c(int, int, int)void
		// @ADD: getstatic game.C_100037_wb game.C_100140_bj.field_102964_g
		// @AE0: sipush 587 (0x024B)
		// @AE3: iload_1
		// @AE4: iconst_m1
		// @AE5: iadd
		// @AE6: iload_2
		// @AE7: invokevirtual game.C_100037_wb.func_102367_c(int, int, int)void
		// @AEA: getstatic game.C_100037_wb game.C_100140_bj.field_102964_g
		// @AED: sipush 585 (0x0249)
		// @AF0: iload_1
		// @AF1: iconst_m1
		// @AF2: isub
		// @AF3: iload_2
		// @AF4: invokevirtual game.C_100037_wb.func_102367_c(int, int, int)void
		// @AF7: getstatic game.C_100037_wb game.C_100140_bj.field_102964_g
		// @AFA: sipush 587 (0x024B)
		// @AFD: iconst_1
		// @AFE: iload_1
		// @AFF: iadd
		// @B00: iload_2
		// @B01: invokevirtual game.C_100037_wb.func_102367_c(int, int, int)void
		// @B04: sipush 139 (0x008B)
		// @B07: invokestatic game.C_100015_wh.func_103775_a(int)void
		// @B0A: getstatic game.C_100037_wb[] game.C_100053_vn.field_102845_Z
		// @B0D: getstatic int game.C_100292_jk.field_101215_r
		// @B10: aaload
		// @B11: sipush 269 (0x010D)
		// @B14: sipush 340 (0x0154)
		// @B17: invokevirtual game.C_100037_wb.func_102353_h(int, int)void
		// @B1A: goto @B3E
		// @B1D: astore_1
		// @B1E: aload_1
		// @B1F: new java.lang.StringBuilder
		// @B22: dup
		// @B23: invokespecial java.lang.StringBuilder.<init>()void
		// @B26: getstatic java.lang.String[] game.C_100293_kj.field_106892_z
		// @B29: iconst_0
		// @B2A: aaload
		// @B2B: invokevirtual java.lang.StringBuilder.append(java.lang.String)java.lang.StringBuilder
		// @B2E: iload_0
		// @B2F: invokevirtual java.lang.StringBuilder.append(int)java.lang.StringBuilder
		// @B32: bipush 41 (0x29)
		// @B34: invokevirtual java.lang.StringBuilder.append(char)java.lang.StringBuilder
		// @B37: invokevirtual java.lang.StringBuilder.toString()java.lang.String
		// @B3A: invokestatic game.C_100181_cf.func_105695_a(java.lang.Throwable, java.lang.String)game.C_100170_cm
		// @B3D: athrow
		// @B3E: return
	}
	
	static final void func_106880_a(int arg0, Component arg1)
	{
		// @00: aload_1
		// @01: iconst_0
		// @02: invokevirtual java.awt.Component.setFocusTraversalKeysEnabled(boolean)void
		// @05: iload_0
		// @06: sipush 22262 (0x56F6)
		// @09: if_icmpeq @15
		// @0C: bipush -92 (0xA4)
		// @0E: invokestatic game.C_100293_kj.func_106882_a(int)void
		// @11: goto @15
		// @14: athrow
		// @15: aload_1
		// @16: getstatic game.C_100323_hl game.C_100264_mg.field_106528_i
		// @19: invokevirtual java.awt.Component.addKeyListener(java.awt.event.KeyListener)void
		// @1C: aload_1
		// @1D: getstatic game.C_100323_hl game.C_100264_mg.field_106528_i
		// @20: invokevirtual java.awt.Component.addFocusListener(java.awt.event.FocusListener)void
		// @23: goto @64
		// @26: astore_2
		// @27: aload_2
		// @28: new java.lang.StringBuilder
		// @2B: dup
		// @2C: invokespecial java.lang.StringBuilder.<init>()void
		// @2F: getstatic java.lang.String[] game.C_100293_kj.field_106892_z
		// @32: bipush 14 (0x0E)
		// @34: aaload
		// @35: invokevirtual java.lang.StringBuilder.append(java.lang.String)java.lang.StringBuilder
		// @38: iload_0
		// @39: invokevirtual java.lang.StringBuilder.append(int)java.lang.StringBuilder
		// @3C: bipush 44 (0x2C)
		// @3E: invokevirtual java.lang.StringBuilder.append(char)java.lang.StringBuilder
		// @41: aload_1
		// @42: ifnull @4F
		// @45: getstatic java.lang.String[] game.C_100293_kj.field_106892_z
		// @48: bipush 13 (0x0D)
		// @4A: aaload
		// @4B: goto @55
		// @4E: athrow
		// @4F: getstatic java.lang.String[] game.C_100293_kj.field_106892_z
		// @52: bipush 12 (0x0C)
		// @54: aaload
		// @55: invokevirtual java.lang.StringBuilder.append(java.lang.String)java.lang.StringBuilder
		// @58: bipush 41 (0x29)
		// @5A: invokevirtual java.lang.StringBuilder.append(char)java.lang.StringBuilder
		// @5D: invokevirtual java.lang.StringBuilder.toString()java.lang.String
		// @60: invokestatic game.C_100181_cf.func_105695_a(java.lang.Throwable, java.lang.String)game.C_100170_cm
		// @63: athrow
		// @64: return
	}
	
	public static void func_106882_a(int arg0)
	{
		// @00: aconst_null
		// @01: putstatic game.C_100268_mk game.C_100293_kj.field_106891_a
		// @04: iload_0
		// @05: bipush -2 (0xFE)
		// @07: if_icmpeq @0B
		// @0A: return
		// @0B: aconst_null
		// @0C: putstatic game.C_100302_ka game.C_100293_kj.field_106889_b
		// @0F: goto @34
		// @12: astore_1
		// @13: aload_1
		// @14: new java.lang.StringBuilder
		// @17: dup
		// @18: invokespecial java.lang.StringBuilder.<init>()void
		// @1B: getstatic java.lang.String[] game.C_100293_kj.field_106892_z
		// @1E: bipush 15 (0x0F)
		// @20: aaload
		// @21: invokevirtual java.lang.StringBuilder.append(java.lang.String)java.lang.StringBuilder
		// @24: iload_0
		// @25: invokevirtual java.lang.StringBuilder.append(int)java.lang.StringBuilder
		// @28: bipush 41 (0x29)
		// @2A: invokevirtual java.lang.StringBuilder.append(char)java.lang.StringBuilder
		// @2D: invokevirtual java.lang.StringBuilder.toString()java.lang.String
		// @30: invokestatic game.C_100181_cf.func_105695_a(java.lang.Throwable, java.lang.String)game.C_100170_cm
		// @33: athrow
		// @34: return
	}
	
	static
	{
		// @00: bipush 17 (0x11)
		// @02: anewarray java.lang.String
		// @05: dup
		// @06: iconst_0
		// @07: ldc "7,b*r"
		// @09: invokestatic game.C_100293_kj.func_106884_z(java.lang.String)char[]
		// @0C: invokestatic game.C_100293_kj.func_106883_z(char[])java.lang.String
		// @0F: aastore
		// @10: dup
		// @11: iconst_1
		// @12: ldc ">38\u001c52\u0019*\u001a;1#"
		// @14: invokestatic game.C_100293_kj.func_106884_z(java.lang.String)char[]
		// @17: invokestatic game.C_100293_kj.func_106883_z(char[])java.lang.String
		// @1A: aastore
		// @1B: dup
		// @1C: iconst_2
		// @1D: ldc "0'>\u000f?\u0003 #\u0006."
		// @1F: invokestatic game.C_100293_kj.func_106884_z(java.lang.String)char[]
		// @22: invokestatic game.C_100293_kj.func_106883_z(char[])java.lang.String
		// @25: aastore
		// @26: dup
		// @27: iconst_3
		// @28: ldc "4#-\u000c65()"
		// @2A: invokestatic game.C_100293_kj.func_106884_z(java.lang.String)char[]
		// @2D: invokestatic game.C_100293_kj.func_106883_z(char[])java.lang.String
		// @30: aastore
		// @31: dup
		// @32: iconst_4
		// @33: ldc "=4>\u0007-"
		// @35: invokestatic game.C_100293_kj.func_106884_z(java.lang.String)char[]
		// @38: invokestatic game.C_100293_kj.func_106883_z(char[])java.lang.String
		// @3B: aastore
		// @3C: dup
		// @3D: iconst_5
		// @3E: ldc "/+-\u00046\u0003 #\u0006."
		// @40: invokestatic game.C_100293_kj.func_106884_z(java.lang.String)char[]
		// @43: invokestatic game.C_100293_kj.func_106883_z(char[])java.lang.String
		// @46: aastore
		// @47: dup
		// @48: bipush 6 (0x06)
		// @4A: ldc ">38\u001c52"
		// @4C: invokestatic game.C_100293_kj.func_106884_z(java.lang.String)char[]
		// @4F: invokestatic game.C_100293_kj.func_106883_z(char[])java.lang.String
		// @52: aastore
		// @53: dup
		// @54: bipush 7 (0x07)
		// @56: ldc "//+\u0006/,\u00198\r\"("
		// @58: invokestatic game.C_100293_kj.func_106884_z(java.lang.String)char[]
		// @5B: invokestatic game.C_100293_kj.func_106883_z(char[])java.lang.String
		// @5E: aastore
		// @5F: dup
		// @60: bipush 8 (0x08)
		// @62: ldc ">#\"\r<52?"
		// @64: invokestatic game.C_100293_kj.func_106884_z(java.lang.String)char[]
		// @67: invokestatic game.C_100293_kj.func_106883_z(char[])java.lang.String
		// @6A: aastore
		// @6B: dup
		// @6C: bipush 9 (0x09)
		// @6E: ldc ">*9\u001a8,'\"\r"
		// @70: invokestatic game.C_100293_kj.func_106884_z(java.lang.String)char[]
		// @73: invokestatic game.C_100293_kj.func_106883_z(char[])java.lang.String
		// @76: aastore
		// @77: dup
		// @78: bipush 10 (0x0A)
		// @7A: ldc "1#\"\u001d\u0005(#4\u001c"
		// @7C: invokestatic game.C_100293_kj.func_106884_z(java.lang.String)char[]
		// @7F: invokestatic game.C_100293_kj.func_106883_z(char[])java.lang.String
		// @82: aastore
		// @83: dup
		// @84: bipush 11 (0x0B)
		// @86: ldc "7,b-r"
		// @88: invokestatic game.C_100293_kj.func_106884_z(java.lang.String)char[]
		// @8B: invokestatic game.C_100293_kj.func_106883_z(char[])java.lang.String
		// @8E: aastore
		// @8F: dup
		// @90: bipush 12 (0x0C)
		// @92: ldc "23 \u0004"
		// @94: invokestatic game.C_100293_kj.func_106884_z(java.lang.String)char[]
		// @97: invokestatic game.C_100293_kj.func_106883_z(char[])java.lang.String
		// @9A: aastore
		// @9B: dup
		// @9C: bipush 13 (0x0D)
		// @9E: ldc "'hbF'"
		// @A0: invokestatic game.C_100293_kj.func_106884_z(java.lang.String)char[]
		// @A3: invokestatic game.C_100293_kj.func_106883_z(char[])java.lang.String
		// @A6: aastore
		// @A7: dup
		// @A8: bipush 14 (0x0E)
		// @AA: ldc "7,b)r"
		// @AC: invokestatic game.C_100293_kj.func_106884_z(java.lang.String)char[]
		// @AF: invokestatic game.C_100293_kj.func_106883_z(char[])java.lang.String
		// @B2: aastore
		// @B3: dup
		// @B4: bipush 15 (0x0F)
		// @B6: ldc "7,b+r"
		// @B8: invokestatic game.C_100293_kj.func_106884_z(java.lang.String)char[]
		// @BB: invokestatic game.C_100293_kj.func_106883_z(char[])java.lang.String
		// @BE: aastore
		// @BF: dup
		// @C0: bipush 16 (0x10)
		// @C2: ldc "7,b,r"
		// @C4: invokestatic game.C_100293_kj.func_106884_z(java.lang.String)char[]
		// @C7: invokestatic game.C_100293_kj.func_106883_z(char[])java.lang.String
		// @CA: aastore
		// @CB: putstatic java.lang.String[] game.C_100293_kj.field_106892_z
		// @CE: new game.C_100268_mk
		// @D1: dup
		// @D2: invokespecial game.C_100268_mk.<init>()void
		// @D5: putstatic game.C_100268_mk game.C_100293_kj.field_106891_a
		// @D8: iconst_0
		// @D9: putstatic boolean game.C_100293_kj.field_106888_e
		// @DC: return
	}
	
	private static char[] func_106884_z(String arg0)
	{
		// @00: aload_0
		// @01: invokevirtual java.lang.String.toCharArray()char[]
		// @04: dup
		// @05: arraylength
		// @06: iconst_2
		// @07: if_icmpge @13
		// @0A: dup
		// @0B: iconst_0
		// @0C: dup2
		// @0D: caload
		// @0E: bipush 90 (0x5A)
		// @10: ixor
		// @11: i2c
		// @12: castore
		// @13: areturn
	}
	
	private static String func_106883_z(char[] arg0)
	{
		// @00: aload_0
		// @01: dup
		// @02: arraylength
		// @03: swap
		// @04: iconst_0
		// @05: istore_1
		// @06: goto @4C
		// @09: dup
		// @0A: iload_1
		// @0B: dup2
		// @0C: caload
		// @0D: iload_1
		// @0E: iconst_5
		// @0F: irem
		// @10: tableswitch def: @44, for 0: @30, for 1: @35, for 2: @3A, for 3: @3F
		// @30: bipush 92 (0x5C)
		// @32: goto @46
		// @35: bipush 70 (0x46)
		// @37: goto @46
		// @3A: bipush 76 (0x4C)
		// @3C: goto @46
		// @3F: bipush 104 (0x68)
		// @41: goto @46
		// @44: bipush 90 (0x5A)
		// @46: ixor
		// @47: i2c
		// @48: castore
		// @49: iinc #1 +1
		// @4C: swap
		// @4D: dup_x1
		// @4E: iload_1
		// @4F: if_icmpgt @09
		// @52: new java.lang.String
		// @55: dup_x1
		// @56: swap
		// @57: invokespecial java.lang.String.<init>(char[])void
		// @5A: invokevirtual java.lang.String.intern()java.lang.String
		// @5D: areturn
	}
}
