package game;

final class C_100268_mk
{
	static int[] field_106670_c;
	static int field_106667_d;
	static String field_106668_e;
	static byte[][] field_106665_f;
	static int field_106671_a;
	static String[] field_106669_b;
	static int field_106666_g;
	private static final String[] field_106672_z;
	
	public static void func_106660_c(int arg0)
	{
		// @00: aconst_null
		// @01: putstatic int[] game.C_100268_mk.field_106670_c
		// @04: aconst_null
		// @05: putstatic java.lang.String[] game.C_100268_mk.field_106669_b
		// @08: iload_0
		// @09: bipush 96 (0x60)
		// @0B: if_icmpgt @0F
		// @0E: return
		// @0F: aconst_null
		// @10: putstatic java.lang.String game.C_100268_mk.field_106668_e
		// @13: aconst_null
		// @14: checkcast byte[][]
		// @17: putstatic byte[][] game.C_100268_mk.field_106665_f
		// @1A: goto @3E
		// @1D: astore_1
		// @1E: aload_1
		// @1F: new java.lang.StringBuilder
		// @22: dup
		// @23: invokespecial java.lang.StringBuilder.<init>()void
		// @26: getstatic java.lang.String[] game.C_100268_mk.field_106672_z
		// @29: iconst_0
		// @2A: aaload
		// @2B: invokevirtual java.lang.StringBuilder.append(java.lang.String)java.lang.StringBuilder
		// @2E: iload_0
		// @2F: invokevirtual java.lang.StringBuilder.append(int)java.lang.StringBuilder
		// @32: bipush 41 (0x29)
		// @34: invokevirtual java.lang.StringBuilder.append(char)java.lang.StringBuilder
		// @37: invokevirtual java.lang.StringBuilder.toString()java.lang.String
		// @3A: invokestatic game.C_100181_cf.func_105695_a(java.lang.Throwable, java.lang.String)game.C_100170_cm
		// @3D: athrow
		// @3E: return
	}
	
	static final void func_106659_b(int arg0)
	{
		// @00: getstatic int game.SteelSentinels.field_105275_O
		// @03: istore_2
		// @04: getstatic game.C_100338_jc game.C_100301_kb.field_107094_a
		// @07: sipush 9873 (0x2691)
		// @0A: invokevirtual game.C_100338_jc.func_105356_c(int)void
		// @0D: iconst_0
		// @0E: istore_1
		// @0F: bipush 32 (0x20)
		// @11: iload_1
		// @12: if_icmple @2A
		// @15: getstatic long[] game.C_100103_eh.field_104673_i
		// @18: iload_1
		// @19: lconst_0
		// @1A: lastore
		// @1B: iinc #1 +1
		// @1E: iload_2
		// @1F: ifne @2C
		// @22: iload_2
		// @23: ifeq @0F
		// @26: goto @2A
		// @29: athrow
		// @2A: iconst_0
		// @2B: istore_1
		// @2C: iload_1
		// @2D: bipush 32 (0x20)
		// @2F: if_icmpge @4B
		// @32: getstatic long[] game.C_100270_mi.field_102262_dc
		// @35: iload_1
		// @36: lconst_0
		// @37: lastore
		// @38: iinc #1 +1
		// @3B: iload_2
		// @3C: ifne @4F
		// @3F: goto @43
		// @42: athrow
		// @43: iload_2
		// @44: ifeq @2C
		// @47: goto @4B
		// @4A: athrow
		// @4B: iload_0
		// @4C: putstatic int game.C_100012_fh.field_100518_P
		// @4F: goto @73
		// @52: astore_1
		// @53: aload_1
		// @54: new java.lang.StringBuilder
		// @57: dup
		// @58: invokespecial java.lang.StringBuilder.<init>()void
		// @5B: getstatic java.lang.String[] game.C_100268_mk.field_106672_z
		// @5E: iconst_2
		// @5F: aaload
		// @60: invokevirtual java.lang.StringBuilder.append(java.lang.String)java.lang.StringBuilder
		// @63: iload_0
		// @64: invokevirtual java.lang.StringBuilder.append(int)java.lang.StringBuilder
		// @67: bipush 41 (0x29)
		// @69: invokevirtual java.lang.StringBuilder.append(char)java.lang.StringBuilder
		// @6C: invokevirtual java.lang.StringBuilder.toString()java.lang.String
		// @6F: invokestatic game.C_100181_cf.func_105695_a(java.lang.Throwable, java.lang.String)game.C_100170_cm
		// @72: athrow
		// @73: return
	}
	
	public final String toString()
	{
		// @00: new java.lang.IllegalStateException
		// @03: dup
		// @04: invokespecial java.lang.IllegalStateException.<init>()void
		// @07: athrow
		// @08: astore_1
		// @09: aload_1
		// @0A: getstatic java.lang.String[] game.C_100268_mk.field_106672_z
		// @0D: iconst_1
		// @0E: aaload
		// @0F: invokestatic game.C_100181_cf.func_105695_a(java.lang.Throwable, java.lang.String)game.C_100170_cm
		// @12: athrow
	}
	
	final boolean func_106663_a(int arg0)
	{
		// @00: iload_1
		// @01: bipush 100 (0x64)
		// @03: if_icmpge @14
		// @06: aconst_null
		// @07: checkcast byte[][]
		// @0A: checkcast byte[][]
		// @0D: putstatic byte[][] game.C_100268_mk.field_106665_f
		// @10: goto @14
		// @13: athrow
		// @14: aload_0
		// @15: getstatic game.C_100268_mk game.C_100205_qf.field_103679_e
		// @18: if_acmpeq @31
		// @1B: aload_0
		// @1C: getstatic game.C_100268_mk game.C_100315_la.field_107179_c
		// @1F: if_acmpeq @31
		// @22: goto @26
		// @25: athrow
		// @26: getstatic game.C_100268_mk game.C_100046_vk.field_102763_sb
		// @29: aload_0
		// @2A: if_acmpne @36
		// @2D: goto @31
		// @30: athrow
		// @31: iconst_1
		// @32: goto @37
		// @35: athrow
		// @36: iconst_0
		// @37: ireturn
		// @38: astore_2
		// @39: aload_2
		// @3A: new java.lang.StringBuilder
		// @3D: dup
		// @3E: invokespecial java.lang.StringBuilder.<init>()void
		// @41: getstatic java.lang.String[] game.C_100268_mk.field_106672_z
		// @44: iconst_3
		// @45: aaload
		// @46: invokevirtual java.lang.StringBuilder.append(java.lang.String)java.lang.StringBuilder
		// @49: iload_1
		// @4A: invokevirtual java.lang.StringBuilder.append(int)java.lang.StringBuilder
		// @4D: bipush 41 (0x29)
		// @4F: invokevirtual java.lang.StringBuilder.append(char)java.lang.StringBuilder
		// @52: invokevirtual java.lang.StringBuilder.toString()java.lang.String
		// @55: invokestatic game.C_100181_cf.func_105695_a(java.lang.Throwable, java.lang.String)game.C_100170_cm
		// @58: athrow
	}
	
	static final void func_106664_a(int arg0, int arg1, boolean arg2)
	{
		// @00: iload_0
		// @01: bipush 79 (0x4F)
		// @03: if_icmpgt @0F
		// @06: bipush -8 (0xF8)
		// @08: putstatic int game.C_100268_mk.field_106671_a
		// @0B: goto @0F
		// @0E: athrow
		// @0F: bipush 70 (0x46)
		// @11: iload_2
		// @12: iload_1
		// @13: invokestatic game.C_100021_wn.func_103860_a(byte, boolean, int)game.C_100061_dh
		// @16: astore_3
		// @17: aload_3
		// @18: ifnull @59
		// @1B: getstatic game.C_100022_hf game.C_100136_th.field_102623_R
		// @1E: iconst_0
		// @1F: iconst_0
		// @20: invokevirtual game.C_100022_hf.func_103884_a(boolean, boolean)void
		// @23: getstatic game.C_100022_hf game.C_100136_th.field_102623_R
		// @26: astore #4
		// @28: getstatic java.lang.String game.C_100096_un.field_104562_g
		// @2B: astore #5
		// @2D: aload #4
		// @2F: getfield game.C_100270_mi game.C_100022_hf.field_103903_m
		// @32: bipush 80 (0x50)
		// @34: iconst_5
		// @35: aload #5
		// @37: invokevirtual game.C_100270_mi.func_102250_a(int, int, java.lang.String)void
		// @3A: getstatic game.C_100022_hf game.C_100136_th.field_102623_R
		// @3D: astore #4
		// @3F: getstatic int game.C_100340_je.field_102981_m
		// @42: istore #5
		// @44: getstatic int game.C_100125_tm.field_100745_p
		// @47: istore #6
		// @49: aload #4
		// @4B: getfield game.C_100270_mi game.C_100022_hf.field_103903_m
		// @4E: iload #5
		// @50: iload #6
		// @52: iconst_0
		// @53: bipush 107 (0x6B)
		// @55: iconst_0
		// @56: invokevirtual game.C_100270_mi.func_102261_b(int, int, int, int, int)void
		// @59: iconst_0
		// @5A: iload_2
		// @5B: iload_1
		// @5C: invokestatic game.C_100113_ek.func_104875_a(int, boolean, int)void
		// @5F: goto @95
		// @62: astore_3
		// @63: aload_3
		// @64: new java.lang.StringBuilder
		// @67: dup
		// @68: invokespecial java.lang.StringBuilder.<init>()void
		// @6B: getstatic java.lang.String[] game.C_100268_mk.field_106672_z
		// @6E: iconst_4
		// @6F: aaload
		// @70: invokevirtual java.lang.StringBuilder.append(java.lang.String)java.lang.StringBuilder
		// @73: iload_0
		// @74: invokevirtual java.lang.StringBuilder.append(int)java.lang.StringBuilder
		// @77: bipush 44 (0x2C)
		// @79: invokevirtual java.lang.StringBuilder.append(char)java.lang.StringBuilder
		// @7C: iload_1
		// @7D: invokevirtual java.lang.StringBuilder.append(int)java.lang.StringBuilder
		// @80: bipush 44 (0x2C)
		// @82: invokevirtual java.lang.StringBuilder.append(char)java.lang.StringBuilder
		// @85: iload_2
		// @86: invokevirtual java.lang.StringBuilder.append(boolean)java.lang.StringBuilder
		// @89: bipush 41 (0x29)
		// @8B: invokevirtual java.lang.StringBuilder.append(char)java.lang.StringBuilder
		// @8E: invokevirtual java.lang.StringBuilder.toString()java.lang.String
		// @91: invokestatic game.C_100181_cf.func_105695_a(java.lang.Throwable, java.lang.String)game.C_100170_cm
		// @94: athrow
		// @95: return
	}
	
	static
	{
		// @000: iconst_5
		// @001: anewarray java.lang.String
		// @004: dup
		// @005: iconst_0
		// @006: ldc "h.gg\u0017"
		// @008: invokestatic game.C_100268_mk.func_106662_z(java.lang.String)char[]
		// @00B: invokestatic game.C_100268_mk.func_106661_z(char[])java.lang.String
		// @00E: aastore
		// @00F: dup
		// @010: iconst_1
		// @011: ldc "h.gPPV1;MQbm`"
		// @013: invokestatic game.C_100268_mk.func_106662_z(java.lang.String)char[]
		// @016: invokestatic game.C_100268_mk.func_106661_z(char[])java.lang.String
		// @019: aastore
		// @01A: dup
		// @01B: iconst_2
		// @01C: ldc "h.ge\u0017"
		// @01E: invokestatic game.C_100268_mk.func_106662_z(java.lang.String)char[]
		// @021: invokestatic game.C_100268_mk.func_106661_z(char[])java.lang.String
		// @024: aastore
		// @025: dup
		// @026: iconst_3
		// @027: ldc "h.gf\u0017"
		// @029: invokestatic game.C_100268_mk.func_106662_z(java.lang.String)char[]
		// @02C: invokestatic game.C_100268_mk.func_106661_z(char[])java.lang.String
		// @02F: aastore
		// @030: dup
		// @031: iconst_4
		// @032: ldc "h.g`\u0017"
		// @034: invokestatic game.C_100268_mk.func_106662_z(java.lang.String)char[]
		// @037: invokestatic game.C_100268_mk.func_106661_z(char[])java.lang.String
		// @03A: aastore
		// @03B: putstatic java.lang.String[] game.C_100268_mk.field_106672_z
		// @03E: bipush 36 (0x24)
		// @040: anewarray byte[]
		// @043: dup
		// @044: iconst_0
		// @045: bipush 8 (0x08)
		// @047: newarray byte[]
		// @049: dup
		// @04A: iconst_0
		// @04B: iconst_0
		// @04C: bastore
		// @04D: dup
		// @04E: iconst_1
		// @04F: iconst_1
		// @050: bastore
		// @051: dup
		// @052: iconst_2
		// @053: iconst_1
		// @054: bastore
		// @055: dup
		// @056: iconst_3
		// @057: iconst_4
		// @058: bastore
		// @059: dup
		// @05A: iconst_4
		// @05B: iconst_3
		// @05C: bastore
		// @05D: dup
		// @05E: iconst_5
		// @05F: iconst_2
		// @060: bastore
		// @061: dup
		// @062: bipush 6 (0x06)
		// @064: iconst_5
		// @065: bastore
		// @066: dup
		// @067: bipush 7 (0x07)
		// @069: iconst_1
		// @06A: bastore
		// @06B: aastore
		// @06C: dup
		// @06D: iconst_1
		// @06E: bipush 6 (0x06)
		// @070: newarray byte[]
		// @072: dup
		// @073: iconst_0
		// @074: iconst_0
		// @075: bastore
		// @076: dup
		// @077: iconst_1
		// @078: iconst_1
		// @079: bastore
		// @07A: dup
		// @07B: iconst_2
		// @07C: iconst_1
		// @07D: bastore
		// @07E: dup
		// @07F: iconst_3
		// @080: iconst_5
		// @081: bastore
		// @082: dup
		// @083: iconst_4
		// @084: iconst_5
		// @085: bastore
		// @086: dup
		// @087: iconst_5
		// @088: iconst_2
		// @089: bastore
		// @08A: aastore
		// @08B: dup
		// @08C: iconst_2
		// @08D: bipush 8 (0x08)
		// @08F: newarray byte[]
		// @091: dup
		// @092: iconst_0
		// @093: iconst_0
		// @094: bastore
		// @095: dup
		// @096: iconst_1
		// @097: iconst_2
		// @098: bastore
		// @099: dup
		// @09A: iconst_2
		// @09B: iconst_1
		// @09C: bastore
		// @09D: dup
		// @09E: iconst_3
		// @09F: iconst_2
		// @0A0: bastore
		// @0A1: dup
		// @0A2: iconst_4
		// @0A3: iconst_3
		// @0A4: bastore
		// @0A5: dup
		// @0A6: iconst_5
		// @0A7: iconst_3
		// @0A8: bastore
		// @0A9: dup
		// @0AA: bipush 6 (0x06)
		// @0AC: bipush 6 (0x06)
		// @0AE: bastore
		// @0AF: dup
		// @0B0: bipush 7 (0x07)
		// @0B2: iconst_1
		// @0B3: bastore
		// @0B4: aastore
		// @0B5: dup
		// @0B6: iconst_3
		// @0B7: bipush 8 (0x08)
		// @0B9: newarray byte[]
		// @0BB: dup
		// @0BC: iconst_0
		// @0BD: iconst_0
		// @0BE: bastore
		// @0BF: dup
		// @0C0: iconst_1
		// @0C1: iconst_5
		// @0C2: bastore
		// @0C3: dup
		// @0C4: iconst_2
		// @0C5: iconst_1
		// @0C6: bastore
		// @0C7: dup
		// @0C8: iconst_3
		// @0C9: iconst_3
		// @0CA: bastore
		// @0CB: dup
		// @0CC: iconst_4
		// @0CD: iconst_4
		// @0CE: bastore
		// @0CF: dup
		// @0D0: iconst_5
		// @0D1: iconst_5
		// @0D2: bastore
		// @0D3: dup
		// @0D4: bipush 6 (0x06)
		// @0D6: iconst_5
		// @0D7: bastore
		// @0D8: dup
		// @0D9: bipush 7 (0x07)
		// @0DB: iconst_2
		// @0DC: bastore
		// @0DD: aastore
		// @0DE: dup
		// @0DF: iconst_4
		// @0E0: bipush 8 (0x08)
		// @0E2: newarray byte[]
		// @0E4: dup
		// @0E5: iconst_0
		// @0E6: iconst_0
		// @0E7: bastore
		// @0E8: dup
		// @0E9: iconst_1
		// @0EA: iconst_5
		// @0EB: bastore
		// @0EC: dup
		// @0ED: iconst_2
		// @0EE: iconst_1
		// @0EF: bastore
		// @0F0: dup
		// @0F1: iconst_3
		// @0F2: iconst_2
		// @0F3: bastore
		// @0F4: dup
		// @0F5: iconst_4
		// @0F6: iconst_4
		// @0F7: bastore
		// @0F8: dup
		// @0F9: iconst_5
		// @0FA: iconst_4
		// @0FB: bastore
		// @0FC: dup
		// @0FD: bipush 6 (0x06)
		// @0FF: bipush 7 (0x07)
		// @101: bastore
		// @102: dup
		// @103: bipush 7 (0x07)
		// @105: iconst_2
		// @106: bastore
		// @107: aastore
		// @108: dup
		// @109: iconst_5
		// @10A: bipush 10 (0x0A)
		// @10C: newarray byte[]
		// @10E: dup
		// @10F: iconst_0
		// @110: iconst_0
		// @111: bastore
		// @112: dup
		// @113: iconst_1
		// @114: iconst_1
		// @115: bastore
		// @116: dup
		// @117: iconst_2
		// @118: iconst_1
		// @119: bastore
		// @11A: dup
		// @11B: iconst_3
		// @11C: iconst_2
		// @11D: bastore
		// @11E: dup
		// @11F: iconst_4
		// @120: iconst_3
		// @121: bastore
		// @122: dup
		// @123: iconst_5
		// @124: iconst_2
		// @125: bastore
		// @126: dup
		// @127: bipush 6 (0x06)
		// @129: iconst_4
		// @12A: bastore
		// @12B: dup
		// @12C: bipush 7 (0x07)
		// @12E: iconst_3
		// @12F: bastore
		// @130: dup
		// @131: bipush 8 (0x08)
		// @133: bipush 7 (0x07)
		// @135: bastore
		// @136: dup
		// @137: bipush 9 (0x09)
		// @139: iconst_2
		// @13A: bastore
		// @13B: aastore
		// @13C: dup
		// @13D: bipush 6 (0x06)
		// @13F: bipush 8 (0x08)
		// @141: newarray byte[]
		// @143: dup
		// @144: iconst_0
		// @145: iconst_0
		// @146: bastore
		// @147: dup
		// @148: iconst_1
		// @149: iconst_4
		// @14A: bastore
		// @14B: dup
		// @14C: iconst_2
		// @14D: iconst_2
		// @14E: bastore
		// @14F: dup
		// @150: iconst_3
		// @151: iconst_4
		// @152: bastore
		// @153: dup
		// @154: iconst_4
		// @155: iconst_3
		// @156: bastore
		// @157: dup
		// @158: iconst_5
		// @159: iconst_1
		// @15A: bastore
		// @15B: dup
		// @15C: bipush 6 (0x06)
		// @15E: bipush 6 (0x06)
		// @160: bastore
		// @161: dup
		// @162: bipush 7 (0x07)
		// @164: iconst_2
		// @165: bastore
		// @166: aastore
		// @167: dup
		// @168: bipush 7 (0x07)
		// @16A: bipush 8 (0x08)
		// @16C: newarray byte[]
		// @16E: dup
		// @16F: iconst_0
		// @170: iconst_0
		// @171: bastore
		// @172: dup
		// @173: iconst_1
		// @174: iconst_4
		// @175: bastore
		// @176: dup
		// @177: iconst_2
		// @178: iconst_2
		// @179: bastore
		// @17A: dup
		// @17B: iconst_3
		// @17C: iconst_4
		// @17D: bastore
		// @17E: dup
		// @17F: iconst_4
		// @180: iconst_3
		// @181: bastore
		// @182: dup
		// @183: iconst_5
		// @184: iconst_2
		// @185: bastore
		// @186: dup
		// @187: bipush 6 (0x06)
		// @189: bipush 6 (0x06)
		// @18B: bastore
		// @18C: dup
		// @18D: bipush 7 (0x07)
		// @18F: iconst_2
		// @190: bastore
		// @191: aastore
		// @192: dup
		// @193: bipush 8 (0x08)
		// @195: bipush 8 (0x08)
		// @197: newarray byte[]
		// @199: dup
		// @19A: iconst_0
		// @19B: iconst_0
		// @19C: bastore
		// @19D: dup
		// @19E: iconst_1
		// @19F: iconst_4
		// @1A0: bastore
		// @1A1: dup
		// @1A2: iconst_2
		// @1A3: iconst_2
		// @1A4: bastore
		// @1A5: dup
		// @1A6: iconst_3
		// @1A7: iconst_3
		// @1A8: bastore
		// @1A9: dup
		// @1AA: iconst_4
		// @1AB: iconst_3
		// @1AC: bastore
		// @1AD: dup
		// @1AE: iconst_5
		// @1AF: iconst_3
		// @1B0: bastore
		// @1B1: dup
		// @1B2: bipush 6 (0x06)
		// @1B4: bipush 8 (0x08)
		// @1B6: bastore
		// @1B7: dup
		// @1B8: bipush 7 (0x07)
		// @1BA: iconst_3
		// @1BB: bastore
		// @1BC: aastore
		// @1BD: dup
		// @1BE: bipush 9 (0x09)
		// @1C0: bipush 8 (0x08)
		// @1C2: newarray byte[]
		// @1C4: dup
		// @1C5: iconst_0
		// @1C6: iconst_0
		// @1C7: bastore
		// @1C8: dup
		// @1C9: iconst_1
		// @1CA: iconst_2
		// @1CB: bastore
		// @1CC: dup
		// @1CD: iconst_2
		// @1CE: iconst_2
		// @1CF: bastore
		// @1D0: dup
		// @1D1: iconst_3
		// @1D2: iconst_4
		// @1D3: bastore
		// @1D4: dup
		// @1D5: iconst_4
		// @1D6: iconst_3
		// @1D7: bastore
		// @1D8: dup
		// @1D9: iconst_5
		// @1DA: iconst_2
		// @1DB: bastore
		// @1DC: dup
		// @1DD: bipush 6 (0x06)
		// @1DF: iconst_5
		// @1E0: bastore
		// @1E1: dup
		// @1E2: bipush 7 (0x07)
		// @1E4: iconst_1
		// @1E5: bastore
		// @1E6: aastore
		// @1E7: dup
		// @1E8: bipush 10 (0x0A)
		// @1EA: bipush 8 (0x08)
		// @1EC: newarray byte[]
		// @1EE: dup
		// @1EF: iconst_0
		// @1F0: iconst_0
		// @1F1: bastore
		// @1F2: dup
		// @1F3: iconst_1
		// @1F4: iconst_2
		// @1F5: bastore
		// @1F6: dup
		// @1F7: iconst_2
		// @1F8: iconst_1
		// @1F9: bastore
		// @1FA: dup
		// @1FB: iconst_3
		// @1FC: iconst_3
		// @1FD: bastore
		// @1FE: dup
		// @1FF: iconst_4
		// @200: iconst_4
		// @201: bastore
		// @202: dup
		// @203: iconst_5
		// @204: iconst_5
		// @205: bastore
		// @206: dup
		// @207: bipush 6 (0x06)
		// @209: bipush 8 (0x08)
		// @20B: bastore
		// @20C: dup
		// @20D: bipush 7 (0x07)
		// @20F: iconst_1
		// @210: bastore
		// @211: aastore
		// @212: dup
		// @213: bipush 11 (0x0B)
		// @215: bipush 8 (0x08)
		// @217: newarray byte[]
		// @219: dup
		// @21A: iconst_0
		// @21B: iconst_0
		// @21C: bastore
		// @21D: dup
		// @21E: iconst_1
		// @21F: iconst_2
		// @220: bastore
		// @221: dup
		// @222: iconst_2
		// @223: iconst_1
		// @224: bastore
		// @225: dup
		// @226: iconst_3
		// @227: iconst_4
		// @228: bastore
		// @229: dup
		// @22A: iconst_4
		// @22B: iconst_3
		// @22C: bastore
		// @22D: dup
		// @22E: iconst_5
		// @22F: iconst_2
		// @230: bastore
		// @231: dup
		// @232: bipush 6 (0x06)
		// @234: iconst_5
		// @235: bastore
		// @236: dup
		// @237: bipush 7 (0x07)
		// @239: iconst_1
		// @23A: bastore
		// @23B: aastore
		// @23C: dup
		// @23D: bipush 12 (0x0C)
		// @23F: bipush 6 (0x06)
		// @241: newarray byte[]
		// @243: dup
		// @244: iconst_0
		// @245: iconst_0
		// @246: bastore
		// @247: dup
		// @248: iconst_1
		// @249: iconst_2
		// @24A: bastore
		// @24B: dup
		// @24C: iconst_2
		// @24D: iconst_1
		// @24E: bastore
		// @24F: dup
		// @250: iconst_3
		// @251: iconst_5
		// @252: bastore
		// @253: dup
		// @254: iconst_4
		// @255: iconst_5
		// @256: bastore
		// @257: dup
		// @258: iconst_5
		// @259: iconst_2
		// @25A: bastore
		// @25B: aastore
		// @25C: dup
		// @25D: bipush 13 (0x0D)
		// @25F: bipush 6 (0x06)
		// @261: newarray byte[]
		// @263: dup
		// @264: iconst_0
		// @265: iconst_0
		// @266: bastore
		// @267: dup
		// @268: iconst_1
		// @269: iconst_3
		// @26A: bastore
		// @26B: dup
		// @26C: iconst_2
		// @26D: iconst_1
		// @26E: bastore
		// @26F: dup
		// @270: iconst_3
		// @271: iconst_3
		// @272: bastore
		// @273: dup
		// @274: iconst_4
		// @275: bipush 6 (0x06)
		// @277: bastore
		// @278: dup
		// @279: iconst_5
		// @27A: iconst_1
		// @27B: bastore
		// @27C: aastore
		// @27D: dup
		// @27E: bipush 14 (0x0E)
		// @280: bipush 8 (0x08)
		// @282: newarray byte[]
		// @284: dup
		// @285: iconst_0
		// @286: iconst_0
		// @287: bastore
		// @288: dup
		// @289: iconst_1
		// @28A: iconst_4
		// @28B: bastore
		// @28C: dup
		// @28D: iconst_2
		// @28E: iconst_1
		// @28F: bastore
		// @290: dup
		// @291: iconst_3
		// @292: iconst_2
		// @293: bastore
		// @294: dup
		// @295: iconst_4
		// @296: iconst_3
		// @297: bastore
		// @298: dup
		// @299: iconst_5
		// @29A: iconst_1
		// @29B: bastore
		// @29C: dup
		// @29D: bipush 6 (0x06)
		// @29F: bipush 6 (0x06)
		// @2A1: bastore
		// @2A2: dup
		// @2A3: bipush 7 (0x07)
		// @2A5: iconst_2
		// @2A6: bastore
		// @2A7: aastore
		// @2A8: dup
		// @2A9: bipush 15 (0x0F)
		// @2AB: bipush 6 (0x06)
		// @2AD: newarray byte[]
		// @2AF: dup
		// @2B0: iconst_0
		// @2B1: iconst_0
		// @2B2: bastore
		// @2B3: dup
		// @2B4: iconst_1
		// @2B5: iconst_4
		// @2B6: bastore
		// @2B7: dup
		// @2B8: iconst_2
		// @2B9: iconst_1
		// @2BA: bastore
		// @2BB: dup
		// @2BC: iconst_3
		// @2BD: iconst_2
		// @2BE: bastore
		// @2BF: dup
		// @2C0: iconst_4
		// @2C1: bipush 6 (0x06)
		// @2C3: bastore
		// @2C4: dup
		// @2C5: iconst_5
		// @2C6: iconst_2
		// @2C7: bastore
		// @2C8: aastore
		// @2C9: dup
		// @2CA: bipush 16 (0x10)
		// @2CC: bipush 8 (0x08)
		// @2CE: newarray byte[]
		// @2D0: dup
		// @2D1: iconst_0
		// @2D2: iconst_0
		// @2D3: bastore
		// @2D4: dup
		// @2D5: iconst_1
		// @2D6: iconst_5
		// @2D7: bastore
		// @2D8: dup
		// @2D9: iconst_2
		// @2DA: iconst_1
		// @2DB: bastore
		// @2DC: dup
		// @2DD: iconst_3
		// @2DE: iconst_3
		// @2DF: bastore
		// @2E0: dup
		// @2E1: iconst_4
		// @2E2: iconst_4
		// @2E3: bastore
		// @2E4: dup
		// @2E5: iconst_5
		// @2E6: iconst_4
		// @2E7: bastore
		// @2E8: dup
		// @2E9: bipush 6 (0x06)
		// @2EB: iconst_5
		// @2EC: bastore
		// @2ED: dup
		// @2EE: bipush 7 (0x07)
		// @2F0: iconst_3
		// @2F1: bastore
		// @2F2: aastore
		// @2F3: dup
		// @2F4: bipush 17 (0x11)
		// @2F6: bipush 8 (0x08)
		// @2F8: newarray byte[]
		// @2FA: dup
		// @2FB: iconst_0
		// @2FC: iconst_0
		// @2FD: bastore
		// @2FE: dup
		// @2FF: iconst_1
		// @300: iconst_5
		// @301: bastore
		// @302: dup
		// @303: iconst_2
		// @304: iconst_1
		// @305: bastore
		// @306: dup
		// @307: iconst_3
		// @308: iconst_2
		// @309: bastore
		// @30A: dup
		// @30B: iconst_4
		// @30C: iconst_4
		// @30D: bastore
		// @30E: dup
		// @30F: iconst_5
		// @310: iconst_3
		// @311: bastore
		// @312: dup
		// @313: bipush 6 (0x06)
		// @315: bipush 7 (0x07)
		// @317: bastore
		// @318: dup
		// @319: bipush 7 (0x07)
		// @31B: iconst_2
		// @31C: bastore
		// @31D: aastore
		// @31E: dup
		// @31F: bipush 18 (0x12)
		// @321: bipush 10 (0x0A)
		// @323: newarray byte[]
		// @325: dup
		// @326: iconst_0
		// @327: iconst_0
		// @328: bastore
		// @329: dup
		// @32A: iconst_1
		// @32B: iconst_2
		// @32C: bastore
		// @32D: dup
		// @32E: iconst_2
		// @32F: iconst_1
		// @330: bastore
		// @331: dup
		// @332: iconst_3
		// @333: iconst_2
		// @334: bastore
		// @335: dup
		// @336: iconst_4
		// @337: iconst_3
		// @338: bastore
		// @339: dup
		// @33A: iconst_5
		// @33B: iconst_3
		// @33C: bastore
		// @33D: dup
		// @33E: bipush 6 (0x06)
		// @340: iconst_4
		// @341: bastore
		// @342: dup
		// @343: bipush 7 (0x07)
		// @345: iconst_2
		// @346: bastore
		// @347: dup
		// @348: bipush 8 (0x08)
		// @34A: bipush 7 (0x07)
		// @34C: bastore
		// @34D: dup
		// @34E: bipush 9 (0x09)
		// @350: iconst_3
		// @351: bastore
		// @352: aastore
		// @353: dup
		// @354: bipush 19 (0x13)
		// @356: bipush 8 (0x08)
		// @358: newarray byte[]
		// @35A: dup
		// @35B: iconst_0
		// @35C: iconst_0
		// @35D: bastore
		// @35E: dup
		// @35F: iconst_1
		// @360: iconst_4
		// @361: bastore
		// @362: dup
		// @363: iconst_2
		// @364: iconst_2
		// @365: bastore
		// @366: dup
		// @367: iconst_3
		// @368: iconst_2
		// @369: bastore
		// @36A: dup
		// @36B: iconst_4
		// @36C: iconst_3
		// @36D: bastore
		// @36E: dup
		// @36F: iconst_5
		// @370: iconst_4
		// @371: bastore
		// @372: dup
		// @373: bipush 6 (0x06)
		// @375: bipush 6 (0x06)
		// @377: bastore
		// @378: dup
		// @379: bipush 7 (0x07)
		// @37B: iconst_3
		// @37C: bastore
		// @37D: aastore
		// @37E: dup
		// @37F: bipush 20 (0x14)
		// @381: bipush 8 (0x08)
		// @383: newarray byte[]
		// @385: dup
		// @386: iconst_0
		// @387: iconst_0
		// @388: bastore
		// @389: dup
		// @38A: iconst_1
		// @38B: iconst_4
		// @38C: bastore
		// @38D: dup
		// @38E: iconst_2
		// @38F: iconst_2
		// @390: bastore
		// @391: dup
		// @392: iconst_3
		// @393: iconst_2
		// @394: bastore
		// @395: dup
		// @396: iconst_4
		// @397: iconst_3
		// @398: bastore
		// @399: dup
		// @39A: iconst_5
		// @39B: iconst_3
		// @39C: bastore
		// @39D: dup
		// @39E: bipush 6 (0x06)
		// @3A0: bipush 6 (0x06)
		// @3A2: bastore
		// @3A3: dup
		// @3A4: bipush 7 (0x07)
		// @3A6: iconst_4
		// @3A7: bastore
		// @3A8: aastore
		// @3A9: dup
		// @3AA: bipush 21 (0x15)
		// @3AC: bipush 8 (0x08)
		// @3AE: newarray byte[]
		// @3B0: dup
		// @3B1: iconst_0
		// @3B2: iconst_0
		// @3B3: bastore
		// @3B4: dup
		// @3B5: iconst_1
		// @3B6: iconst_3
		// @3B7: bastore
		// @3B8: dup
		// @3B9: iconst_2
		// @3BA: iconst_1
		// @3BB: bastore
		// @3BC: dup
		// @3BD: iconst_3
		// @3BE: iconst_4
		// @3BF: bastore
		// @3C0: dup
		// @3C1: iconst_4
		// @3C2: iconst_4
		// @3C3: bastore
		// @3C4: dup
		// @3C5: iconst_5
		// @3C6: iconst_3
		// @3C7: bastore
		// @3C8: dup
		// @3C9: bipush 6 (0x06)
		// @3CB: bipush 8 (0x08)
		// @3CD: bastore
		// @3CE: dup
		// @3CF: bipush 7 (0x07)
		// @3D1: iconst_2
		// @3D2: bastore
		// @3D3: aastore
		// @3D4: dup
		// @3D5: bipush 22 (0x16)
		// @3D7: iconst_0
		// @3D8: newarray byte[]
		// @3DA: aastore
		// @3DB: dup
		// @3DC: bipush 23 (0x17)
		// @3DE: iconst_0
		// @3DF: newarray byte[]
		// @3E1: aastore
		// @3E2: dup
		// @3E3: bipush 24 (0x18)
		// @3E5: iconst_0
		// @3E6: newarray byte[]
		// @3E8: aastore
		// @3E9: dup
		// @3EA: bipush 25 (0x19)
		// @3EC: iconst_0
		// @3ED: newarray byte[]
		// @3EF: aastore
		// @3F0: dup
		// @3F1: bipush 26 (0x1A)
		// @3F3: bipush 6 (0x06)
		// @3F5: newarray byte[]
		// @3F7: dup
		// @3F8: iconst_0
		// @3F9: iconst_0
		// @3FA: bastore
		// @3FB: dup
		// @3FC: iconst_1
		// @3FD: iconst_3
		// @3FE: bastore
		// @3FF: dup
		// @400: iconst_2
		// @401: iconst_1
		// @402: bastore
		// @403: dup
		// @404: iconst_3
		// @405: iconst_5
		// @406: bastore
		// @407: dup
		// @408: iconst_4
		// @409: iconst_5
		// @40A: bastore
		// @40B: dup
		// @40C: iconst_5
		// @40D: iconst_3
		// @40E: bastore
		// @40F: aastore
		// @410: dup
		// @411: bipush 27 (0x1B)
		// @413: bipush 8 (0x08)
		// @415: newarray byte[]
		// @417: dup
		// @418: iconst_0
		// @419: iconst_0
		// @41A: bastore
		// @41B: dup
		// @41C: iconst_1
		// @41D: iconst_4
		// @41E: bastore
		// @41F: dup
		// @420: iconst_2
		// @421: iconst_1
		// @422: bastore
		// @423: dup
		// @424: iconst_3
		// @425: iconst_3
		// @426: bastore
		// @427: dup
		// @428: iconst_4
		// @429: iconst_3
		// @42A: bastore
		// @42B: dup
		// @42C: iconst_5
		// @42D: iconst_2
		// @42E: bastore
		// @42F: dup
		// @430: bipush 6 (0x06)
		// @432: bipush 6 (0x06)
		// @434: bastore
		// @435: dup
		// @436: bipush 7 (0x07)
		// @438: iconst_3
		// @439: bastore
		// @43A: aastore
		// @43B: dup
		// @43C: bipush 28 (0x1C)
		// @43E: bipush 8 (0x08)
		// @440: newarray byte[]
		// @442: dup
		// @443: iconst_0
		// @444: iconst_0
		// @445: bastore
		// @446: dup
		// @447: iconst_1
		// @448: iconst_4
		// @449: bastore
		// @44A: dup
		// @44B: iconst_2
		// @44C: iconst_1
		// @44D: bastore
		// @44E: dup
		// @44F: iconst_3
		// @450: iconst_2
		// @451: bastore
		// @452: dup
		// @453: iconst_4
		// @454: iconst_3
		// @455: bastore
		// @456: dup
		// @457: iconst_5
		// @458: iconst_2
		// @459: bastore
		// @45A: dup
		// @45B: bipush 6 (0x06)
		// @45D: bipush 6 (0x06)
		// @45F: bastore
		// @460: dup
		// @461: bipush 7 (0x07)
		// @463: iconst_3
		// @464: bastore
		// @465: aastore
		// @466: dup
		// @467: bipush 29 (0x1D)
		// @469: bipush 8 (0x08)
		// @46B: newarray byte[]
		// @46D: dup
		// @46E: iconst_0
		// @46F: iconst_0
		// @470: bastore
		// @471: dup
		// @472: iconst_1
		// @473: iconst_5
		// @474: bastore
		// @475: dup
		// @476: iconst_2
		// @477: iconst_1
		// @478: bastore
		// @479: dup
		// @47A: iconst_3
		// @47B: iconst_3
		// @47C: bastore
		// @47D: dup
		// @47E: iconst_4
		// @47F: iconst_4
		// @480: bastore
		// @481: dup
		// @482: iconst_5
		// @483: iconst_3
		// @484: bastore
		// @485: dup
		// @486: bipush 6 (0x06)
		// @488: iconst_5
		// @489: bastore
		// @48A: dup
		// @48B: bipush 7 (0x07)
		// @48D: iconst_4
		// @48E: bastore
		// @48F: aastore
		// @490: dup
		// @491: bipush 30 (0x1E)
		// @493: bipush 8 (0x08)
		// @495: newarray byte[]
		// @497: dup
		// @498: iconst_0
		// @499: iconst_0
		// @49A: bastore
		// @49B: dup
		// @49C: iconst_1
		// @49D: iconst_5
		// @49E: bastore
		// @49F: dup
		// @4A0: iconst_2
		// @4A1: iconst_1
		// @4A2: bastore
		// @4A3: dup
		// @4A4: iconst_3
		// @4A5: iconst_1
		// @4A6: bastore
		// @4A7: dup
		// @4A8: iconst_4
		// @4A9: iconst_4
		// @4AA: bastore
		// @4AB: dup
		// @4AC: iconst_5
		// @4AD: iconst_1
		// @4AE: bastore
		// @4AF: dup
		// @4B0: bipush 6 (0x06)
		// @4B2: bipush 7 (0x07)
		// @4B4: bastore
		// @4B5: dup
		// @4B6: bipush 7 (0x07)
		// @4B8: iconst_3
		// @4B9: bastore
		// @4BA: aastore
		// @4BB: dup
		// @4BC: bipush 31 (0x1F)
		// @4BE: bipush 10 (0x0A)
		// @4C0: newarray byte[]
		// @4C2: dup
		// @4C3: iconst_0
		// @4C4: iconst_0
		// @4C5: bastore
		// @4C6: dup
		// @4C7: iconst_1
		// @4C8: iconst_3
		// @4C9: bastore
		// @4CA: dup
		// @4CB: iconst_2
		// @4CC: iconst_1
		// @4CD: bastore
		// @4CE: dup
		// @4CF: iconst_3
		// @4D0: iconst_2
		// @4D1: bastore
		// @4D2: dup
		// @4D3: iconst_4
		// @4D4: iconst_3
		// @4D5: bastore
		// @4D6: dup
		// @4D7: iconst_5
		// @4D8: iconst_3
		// @4D9: bastore
		// @4DA: dup
		// @4DB: bipush 6 (0x06)
		// @4DD: iconst_4
		// @4DE: bastore
		// @4DF: dup
		// @4E0: bipush 7 (0x07)
		// @4E2: iconst_0
		// @4E3: bastore
		// @4E4: dup
		// @4E5: bipush 8 (0x08)
		// @4E7: bipush 7 (0x07)
		// @4E9: bastore
		// @4EA: dup
		// @4EB: bipush 9 (0x09)
		// @4ED: iconst_5
		// @4EE: bastore
		// @4EF: aastore
		// @4F0: dup
		// @4F1: bipush 32 (0x20)
		// @4F3: bipush 10 (0x0A)
		// @4F5: newarray byte[]
		// @4F7: dup
		// @4F8: iconst_0
		// @4F9: iconst_0
		// @4FA: bastore
		// @4FB: dup
		// @4FC: iconst_1
		// @4FD: iconst_4
		// @4FE: bastore
		// @4FF: dup
		// @500: iconst_2
		// @501: iconst_2
		// @502: bastore
		// @503: dup
		// @504: iconst_3
		// @505: iconst_0
		// @506: bastore
		// @507: dup
		// @508: iconst_4
		// @509: iconst_3
		// @50A: bastore
		// @50B: dup
		// @50C: iconst_5
		// @50D: iconst_5
		// @50E: bastore
		// @50F: dup
		// @510: bipush 6 (0x06)
		// @512: bipush 6 (0x06)
		// @514: bastore
		// @515: dup
		// @516: bipush 7 (0x07)
		// @518: iconst_5
		// @519: bastore
		// @51A: dup
		// @51B: bipush 8 (0x08)
		// @51D: bipush 8 (0x08)
		// @51F: bastore
		// @520: dup
		// @521: bipush 9 (0x09)
		// @523: iconst_4
		// @524: bastore
		// @525: aastore
		// @526: dup
		// @527: bipush 33 (0x21)
		// @529: bipush 8 (0x08)
		// @52B: newarray byte[]
		// @52D: dup
		// @52E: iconst_0
		// @52F: iconst_0
		// @530: bastore
		// @531: dup
		// @532: iconst_1
		// @533: iconst_4
		// @534: bastore
		// @535: dup
		// @536: iconst_2
		// @537: iconst_2
		// @538: bastore
		// @539: dup
		// @53A: iconst_3
		// @53B: iconst_1
		// @53C: bastore
		// @53D: dup
		// @53E: iconst_4
		// @53F: iconst_3
		// @540: bastore
		// @541: dup
		// @542: iconst_5
		// @543: iconst_4
		// @544: bastore
		// @545: dup
		// @546: bipush 6 (0x06)
		// @548: bipush 6 (0x06)
		// @54A: bastore
		// @54B: dup
		// @54C: bipush 7 (0x07)
		// @54E: iconst_5
		// @54F: bastore
		// @550: aastore
		// @551: dup
		// @552: bipush 34 (0x22)
		// @554: bipush 8 (0x08)
		// @556: newarray byte[]
		// @558: dup
		// @559: iconst_0
		// @55A: iconst_0
		// @55B: bastore
		// @55C: dup
		// @55D: iconst_1
		// @55E: iconst_3
		// @55F: bastore
		// @560: dup
		// @561: iconst_2
		// @562: iconst_2
		// @563: bastore
		// @564: dup
		// @565: iconst_3
		// @566: iconst_1
		// @567: bastore
		// @568: dup
		// @569: iconst_4
		// @56A: iconst_3
		// @56B: bastore
		// @56C: dup
		// @56D: iconst_5
		// @56E: iconst_3
		// @56F: bastore
		// @570: dup
		// @571: bipush 6 (0x06)
		// @573: bipush 6 (0x06)
		// @575: bastore
		// @576: dup
		// @577: bipush 7 (0x07)
		// @579: iconst_4
		// @57A: bastore
		// @57B: aastore
		// @57C: dup
		// @57D: bipush 35 (0x23)
		// @57F: bipush 8 (0x08)
		// @581: newarray byte[]
		// @583: dup
		// @584: iconst_0
		// @585: iconst_0
		// @586: bastore
		// @587: dup
		// @588: iconst_1
		// @589: iconst_3
		// @58A: bastore
		// @58B: dup
		// @58C: iconst_2
		// @58D: iconst_1
		// @58E: bastore
		// @58F: dup
		// @590: iconst_3
		// @591: iconst_1
		// @592: bastore
		// @593: dup
		// @594: iconst_4
		// @595: iconst_4
		// @596: bastore
		// @597: dup
		// @598: iconst_5
		// @599: iconst_2
		// @59A: bastore
		// @59B: dup
		// @59C: bipush 6 (0x06)
		// @59E: bipush 8 (0x08)
		// @5A0: bastore
		// @5A1: dup
		// @5A2: bipush 7 (0x07)
		// @5A4: iconst_5
		// @5A5: bastore
		// @5A6: aastore
		// @5A7: putstatic byte[][] game.C_100268_mk.field_106665_f
		// @5AA: ldc "M,-A\u001fu7 R^q iGWd1iEQae(TO`$;\u0004Pc#%MQ`e=K\u001fc7 AQa6"
		// @5AC: invokestatic game.C_100268_mk.func_106662_z(java.lang.String)char[]
		// @5AF: invokestatic game.C_100268_mk.func_106661_z(char[])java.lang.String
		// @5B2: putstatic java.lang.String game.C_100268_mk.field_106668_e
		// @5B5: iconst_0
		// @5B6: putstatic int game.C_100268_mk.field_106671_a
		// @5B9: return
	}
	
	private static char[] func_106662_z(String arg0)
	{
		// @00: aload_0
		// @01: invokevirtual java.lang.String.toCharArray()char[]
		// @04: dup
		// @05: arraylength
		// @06: iconst_2
		// @07: if_icmpge @13
		// @0A: dup
		// @0B: iconst_0
		// @0C: dup2
		// @0D: caload
		// @0E: bipush 63 (0x3F)
		// @10: ixor
		// @11: i2c
		// @12: castore
		// @13: areturn
	}
	
	private static String func_106661_z(char[] arg0)
	{
		// @00: aload_0
		// @01: dup
		// @02: arraylength
		// @03: swap
		// @04: iconst_0
		// @05: istore_1
		// @06: goto @4B
		// @09: dup
		// @0A: iload_1
		// @0B: dup2
		// @0C: caload
		// @0D: iload_1
		// @0E: iconst_5
		// @0F: irem
		// @10: tableswitch def: @43, for 0: @30, for 1: @34, for 2: @39, for 3: @3E
		// @30: iconst_5
		// @31: goto @45
		// @34: bipush 69 (0x45)
		// @36: goto @45
		// @39: bipush 73 (0x49)
		// @3B: goto @45
		// @3E: bipush 36 (0x24)
		// @40: goto @45
		// @43: bipush 63 (0x3F)
		// @45: ixor
		// @46: i2c
		// @47: castore
		// @48: iinc #1 +1
		// @4B: swap
		// @4C: dup_x1
		// @4D: iload_1
		// @4E: if_icmpgt @09
		// @51: new java.lang.String
		// @54: dup_x1
		// @55: swap
		// @56: invokespecial java.lang.String.<init>(char[])void
		// @59: invokevirtual java.lang.String.intern()java.lang.String
		// @5C: areturn
	}
}
