package game;

import java.awt.Canvas;

final class C_100000_gd
{
	static String field_100356_d;
	static String[] field_100360_a;
	static String field_100359_c;
	static String field_100354_f;
	static String field_100358_b;
	static int field_100355_g;
	static double field_100357_e;
	private static final String[] field_100361_z;
	
	static final boolean func_100353_b(int arg0)
	{
		// @00: aconst_null
		// @01: getstatic game.C_100037_wb game.C_100228_nn.field_106186_d
		// @04: if_acmpne @0B
		// @07: goto @0D
		// @0A: athrow
		// @0B: iconst_1
		// @0C: ireturn
		// @0D: getstatic game.C_100098_h game.C_100148_bh.field_101804_t
		// @10: getstatic java.lang.String[] game.C_100000_gd.field_100361_z
		// @13: bipush 12 (0x0C)
		// @15: aaload
		// @16: iconst_0
		// @17: invokevirtual game.C_100098_h.func_104593_a(java.lang.String, boolean)boolean
		// @1A: ifeq @21
		// @1D: goto @23
		// @20: athrow
		// @21: iconst_0
		// @22: ireturn
		// @23: bipush 123 (0x7B)
		// @25: getstatic java.lang.String[] game.C_100000_gd.field_100361_z
		// @28: bipush 12 (0x0C)
		// @2A: aaload
		// @2B: getstatic game.C_100098_h game.C_100148_bh.field_101804_t
		// @2E: getstatic java.lang.String[] game.C_100000_gd.field_100361_z
		// @31: bipush 10 (0x0A)
		// @33: aaload
		// @34: invokestatic game.C_100021_wn.func_103861_a(byte, java.lang.String, game.C_100098_h, java.lang.String)game.C_100037_wb
		// @37: putstatic game.C_100037_wb game.C_100228_nn.field_106186_d
		// @3A: bipush 90 (0x5A)
		// @3C: getstatic java.lang.String[] game.C_100000_gd.field_100361_z
		// @3F: bipush 12 (0x0C)
		// @41: aaload
		// @42: getstatic game.C_100098_h game.C_100148_bh.field_101804_t
		// @45: getstatic java.lang.String[] game.C_100000_gd.field_100361_z
		// @48: bipush 14 (0x0E)
		// @4A: aaload
		// @4B: invokestatic game.C_100021_wn.func_103861_a(byte, java.lang.String, game.C_100098_h, java.lang.String)game.C_100037_wb
		// @4E: putstatic game.C_100037_wb game.C_100030_gm.field_103342_E
		// @51: iload_0
		// @52: sipush 30452 (0x76F4)
		// @55: if_icmpeq @63
		// @58: aconst_null
		// @59: checkcast java.lang.String
		// @5C: putstatic java.lang.String game.C_100000_gd.field_100358_b
		// @5F: goto @63
		// @62: athrow
		// @63: bipush 98 (0x62)
		// @65: getstatic java.lang.String[] game.C_100000_gd.field_100361_z
		// @68: bipush 12 (0x0C)
		// @6A: aaload
		// @6B: getstatic game.C_100098_h game.C_100148_bh.field_101804_t
		// @6E: getstatic java.lang.String[] game.C_100000_gd.field_100361_z
		// @71: bipush 9 (0x09)
		// @73: aaload
		// @74: invokestatic game.C_100021_wn.func_103861_a(byte, java.lang.String, game.C_100098_h, java.lang.String)game.C_100037_wb
		// @77: putstatic game.C_100037_wb game.C_100327_ib.field_102499_u
		// @7A: getstatic game.C_100098_h game.C_100148_bh.field_101804_t
		// @7D: getstatic java.lang.String[] game.C_100000_gd.field_100361_z
		// @80: bipush 11 (0x0B)
		// @82: aaload
		// @83: getstatic java.lang.String[] game.C_100000_gd.field_100361_z
		// @86: bipush 12 (0x0C)
		// @88: aaload
		// @89: bipush -91 (0xA5)
		// @8B: invokestatic game.C_100163_sf.func_105433_a(game.C_100098_h, java.lang.String, java.lang.String, byte)game.C_100037_wb[]
		// @8E: putstatic game.C_100037_wb[] game.C_100191_rg.field_100850_k
		// @91: getstatic java.lang.String game.C_100335_il.field_107367_d
		// @94: bipush -40 (0xD8)
		// @96: getstatic game.C_100037_wb game.C_100228_nn.field_106186_d
		// @99: invokestatic game.C_100297_kf.func_101231_a(java.lang.String, byte, game.C_100037_wb)void
		// @9C: bipush 40 (0x28)
		// @9E: bipush 40 (0x28)
		// @A0: bipush 80 (0x50)
		// @A2: bipush 80 (0x50)
		// @A4: iconst_2
		// @A5: getstatic game.C_100317_lb game.C_100265_mh.field_106605_Q
		// @A8: bipush 15 (0x0F)
		// @AA: getstatic game.C_100037_wb game.C_100030_gm.field_103342_E
		// @AD: bipush -45 (0xD3)
		// @AF: ldc 16744576 (0xff8080)
		// @B1: sipush -2400 (0xF6A0)
		// @B4: invokestatic game.C_100219_an.func_100875_a(int, int, int, int, int, game.C_100112_r, int, game.C_100037_wb, byte, int, int)void
		// @B7: bipush 124 (0x7C)
		// @B9: getstatic game.C_100037_wb[] game.C_100191_rg.field_100850_k
		// @BC: invokestatic game.C_100085_a.func_102554_a(byte, game.C_100037_wb[])void
		// @BF: getstatic game.C_100037_wb game.C_100327_ib.field_102499_u
		// @C2: bipush 72 (0x48)
		// @C4: invokestatic game.C_100097_k.func_104574_a(game.C_100037_wb, byte)void
		// @C7: iconst_1
		// @C8: ireturn
		// @C9: astore_1
		// @CA: aload_1
		// @CB: new java.lang.StringBuilder
		// @CE: dup
		// @CF: invokespecial java.lang.StringBuilder.<init>()void
		// @D2: getstatic java.lang.String[] game.C_100000_gd.field_100361_z
		// @D5: bipush 13 (0x0D)
		// @D7: aaload
		// @D8: invokevirtual java.lang.StringBuilder.append(java.lang.String)java.lang.StringBuilder
		// @DB: iload_0
		// @DC: invokevirtual java.lang.StringBuilder.append(int)java.lang.StringBuilder
		// @DF: bipush 41 (0x29)
		// @E1: invokevirtual java.lang.StringBuilder.append(char)java.lang.StringBuilder
		// @E4: invokevirtual java.lang.StringBuilder.toString()java.lang.String
		// @E7: invokestatic game.C_100181_cf.func_105695_a(java.lang.Throwable, java.lang.String)game.C_100170_cm
		// @EA: athrow
	}
	
	static final C_100302_ka func_100348_a(int arg0, int arg1, int arg2, int arg3, boolean arg4, int arg5)
	{
		// @000: getstatic int game.SteelSentinels.field_105275_O
		// @003: istore #23
		// @005: getstatic int game.C_100233_oa.field_106250_h
		// @008: istore #6
		// @00A: bipush -25 (0xE7)
		// @00C: invokestatic game.C_100234_ob.func_106268_c(byte)boolean
		// @00F: ifne @01C
		// @012: getstatic int game.C_100212_qc.field_105976_b
		// @015: ifgt @030
		// @018: goto @01C
		// @01B: athrow
		// @01C: iconst_1
		// @01D: sipush -11145 (0xD477)
		// @020: iload_0
		// @021: invokestatic game.C_100080_b.func_104421_a(boolean, int, int)boolean
		// @024: ifeq @030
		// @027: goto @02B
		// @02A: athrow
		// @02B: iconst_1
		// @02C: goto @031
		// @02F: athrow
		// @030: iconst_0
		// @031: istore #7
		// @033: aconst_null
		// @034: astore #8
		// @036: aconst_null
		// @037: astore #9
		// @039: iload_0
		// @03A: bipush 34 (0x22)
		// @03C: if_icmpeq @049
		// @03F: getstatic java.lang.String[] game.C_100167_sj.field_100794_t
		// @042: iload_0
		// @043: aaload
		// @044: astore #9
		// @046: goto @051
		// @049: getstatic java.lang.String[] game.C_100000_gd.field_100361_z
		// @04C: bipush 7 (0x07)
		// @04E: aaload
		// @04F: astore #9
		// @051: aconst_null
		// @052: astore #10
		// @054: iconst_0
		// @055: istore #11
		// @057: iconst_5
		// @058: istore #12
		// @05A: iload_0
		// @05B: istore #13
		// @05D: iload #13
		// @05F: iconst_m1
		// @060: ixor
		// @061: iconst_m1
		// @062: if_icmpeq @153
		// @065: iload #13
		// @067: iconst_m1
		// @068: ixor
		// @069: bipush -2 (0xFE)
		// @06B: if_icmpne @07B
		// @06E: goto @072
		// @071: athrow
		// @072: iload #23
		// @074: ifeq @160
		// @077: goto @07B
		// @07A: athrow
		// @07B: iload #13
		// @07D: iconst_2
		// @07E: if_icmpeq @16D
		// @081: goto @085
		// @084: athrow
		// @085: iload #13
		// @087: iconst_3
		// @088: if_icmpeq @17A
		// @08B: goto @08F
		// @08E: athrow
		// @08F: iconst_4
		// @090: iload #13
		// @092: if_icmpeq @187
		// @095: goto @099
		// @098: athrow
		// @099: bipush 20 (0x14)
		// @09B: iload #13
		// @09D: if_icmpeq @194
		// @0A0: goto @0A4
		// @0A3: athrow
		// @0A4: iconst_5
		// @0A5: iload #13
		// @0A7: if_icmpeq @1A2
		// @0AA: goto @0AE
		// @0AD: athrow
		// @0AE: iload #13
		// @0B0: iconst_m1
		// @0B1: ixor
		// @0B2: bipush -7 (0xF9)
		// @0B4: if_icmpne @0C4
		// @0B7: goto @0BB
		// @0BA: athrow
		// @0BB: iload #23
		// @0BD: ifeq @1AF
		// @0C0: goto @0C4
		// @0C3: athrow
		// @0C4: iload #13
		// @0C6: iconst_m1
		// @0C7: ixor
		// @0C8: bipush -8 (0xF8)
		// @0CA: if_icmpeq @1BC
		// @0CD: goto @0D1
		// @0D0: athrow
		// @0D1: iload #13
		// @0D3: iconst_m1
		// @0D4: ixor
		// @0D5: bipush -9 (0xF7)
		// @0D7: if_icmpeq @1C9
		// @0DA: goto @0DE
		// @0DD: athrow
		// @0DE: iload #13
		// @0E0: iconst_m1
		// @0E1: ixor
		// @0E2: bipush -10 (0xF6)
		// @0E4: if_icmpne @0F4
		// @0E7: goto @0EB
		// @0EA: athrow
		// @0EB: iload #23
		// @0ED: ifeq @1D6
		// @0F0: goto @0F4
		// @0F3: athrow
		// @0F4: iload #13
		// @0F6: iconst_m1
		// @0F7: ixor
		// @0F8: bipush -11 (0xF5)
		// @0FA: if_icmpne @10A
		// @0FD: goto @101
		// @100: athrow
		// @101: iload #23
		// @103: ifeq @1E3
		// @106: goto @10A
		// @109: athrow
		// @10A: bipush -12 (0xF4)
		// @10C: iload #13
		// @10E: iconst_m1
		// @10F: ixor
		// @110: if_icmpne @120
		// @113: goto @117
		// @116: athrow
		// @117: iload #23
		// @119: ifeq @1F5
		// @11C: goto @120
		// @11F: athrow
		// @120: iload #13
		// @122: bipush 12 (0x0C)
		// @124: if_icmpne @134
		// @127: goto @12B
		// @12A: athrow
		// @12B: iload #23
		// @12D: ifeq @207
		// @130: goto @134
		// @133: athrow
		// @134: bipush 13 (0x0D)
		// @136: iload #13
		// @138: if_icmpeq @219
		// @13B: goto @13F
		// @13E: athrow
		// @13F: iload #13
		// @141: bipush 14 (0x0E)
		// @143: if_icmpne @23C
		// @146: goto @14A
		// @149: athrow
		// @14A: iload #23
		// @14C: ifeq @22C
		// @14F: goto @153
		// @152: athrow
		// @153: getstatic java.lang.String[] game.C_100000_gd.field_100361_z
		// @156: iconst_5
		// @157: aaload
		// @158: astore #10
		// @15A: iconst_1
		// @15B: istore #11
		// @15D: goto @23C
		// @160: getstatic java.lang.String[] game.C_100000_gd.field_100361_z
		// @163: iconst_5
		// @164: aaload
		// @165: astore #10
		// @167: iconst_2
		// @168: istore #11
		// @16A: goto @23C
		// @16D: iconst_3
		// @16E: istore #11
		// @170: getstatic java.lang.String[] game.C_100000_gd.field_100361_z
		// @173: iconst_5
		// @174: aaload
		// @175: astore #10
		// @177: goto @23C
		// @17A: iconst_4
		// @17B: istore #11
		// @17D: getstatic java.lang.String[] game.C_100000_gd.field_100361_z
		// @180: iconst_5
		// @181: aaload
		// @182: astore #10
		// @184: goto @23C
		// @187: getstatic java.lang.String[] game.C_100000_gd.field_100361_z
		// @18A: iconst_5
		// @18B: aaload
		// @18C: astore #10
		// @18E: iconst_5
		// @18F: istore #11
		// @191: goto @23C
		// @194: bipush 10 (0x0A)
		// @196: istore #11
		// @198: getstatic java.lang.String[] game.C_100000_gd.field_100361_z
		// @19B: iconst_5
		// @19C: aaload
		// @19D: astore #10
		// @19F: goto @23C
		// @1A2: iconst_1
		// @1A3: istore #11
		// @1A5: getstatic java.lang.String[] game.C_100000_gd.field_100361_z
		// @1A8: iconst_1
		// @1A9: aaload
		// @1AA: astore #10
		// @1AC: goto @23C
		// @1AF: getstatic java.lang.String[] game.C_100000_gd.field_100361_z
		// @1B2: iconst_1
		// @1B3: aaload
		// @1B4: astore #10
		// @1B6: iconst_2
		// @1B7: istore #11
		// @1B9: goto @23C
		// @1BC: iconst_3
		// @1BD: istore #11
		// @1BF: getstatic java.lang.String[] game.C_100000_gd.field_100361_z
		// @1C2: iconst_1
		// @1C3: aaload
		// @1C4: astore #10
		// @1C6: goto @23C
		// @1C9: iconst_4
		// @1CA: istore #11
		// @1CC: getstatic java.lang.String[] game.C_100000_gd.field_100361_z
		// @1CF: iconst_1
		// @1D0: aaload
		// @1D1: astore #10
		// @1D3: goto @23C
		// @1D6: getstatic java.lang.String[] game.C_100000_gd.field_100361_z
		// @1D9: iconst_1
		// @1DA: aaload
		// @1DB: astore #10
		// @1DD: iconst_5
		// @1DE: istore #11
		// @1E0: goto @23C
		// @1E3: bipush 10 (0x0A)
		// @1E5: istore #12
		// @1E7: getstatic java.lang.String[] game.C_100000_gd.field_100361_z
		// @1EA: bipush 6 (0x06)
		// @1EC: aaload
		// @1ED: astore #10
		// @1EF: iconst_1
		// @1F0: istore #11
		// @1F2: goto @23C
		// @1F5: iconst_2
		// @1F6: istore #11
		// @1F8: bipush 10 (0x0A)
		// @1FA: istore #12
		// @1FC: getstatic java.lang.String[] game.C_100000_gd.field_100361_z
		// @1FF: bipush 6 (0x06)
		// @201: aaload
		// @202: astore #10
		// @204: goto @23C
		// @207: bipush 10 (0x0A)
		// @209: istore #12
		// @20B: iconst_5
		// @20C: istore #11
		// @20E: getstatic java.lang.String[] game.C_100000_gd.field_100361_z
		// @211: bipush 6 (0x06)
		// @213: aaload
		// @214: astore #10
		// @216: goto @23C
		// @219: getstatic java.lang.String[] game.C_100000_gd.field_100361_z
		// @21C: bipush 6 (0x06)
		// @21E: aaload
		// @21F: astore #10
		// @221: bipush 10 (0x0A)
		// @223: istore #11
		// @225: bipush 10 (0x0A)
		// @227: istore #12
		// @229: goto @23C
		// @22C: bipush 20 (0x14)
		// @22E: istore #11
		// @230: getstatic java.lang.String[] game.C_100000_gd.field_100361_z
		// @233: bipush 6 (0x06)
		// @235: aaload
		// @236: astore #10
		// @238: bipush 10 (0x0A)
		// @23A: istore #12
		// @23C: aconst_null
		// @23D: aload #10
		// @23F: if_acmpne @247
		// @242: iconst_2
		// @243: goto @248
		// @246: athrow
		// @247: iconst_1
		// @248: istore #13
		// @24A: new game.C_100302_ka
		// @24D: dup
		// @24E: iload_0
		// @24F: i2l
		// @250: getstatic game.C_100302_ka game.C_100042_we.field_104131_r
		// @253: invokespecial game.C_100302_ka.<init>(long, game.C_100302_ka)void
		// @256: astore #8
		// @258: getstatic game.C_100302_ka[] game.C_100063_dj.field_104290_f
		// @25B: iload_0
		// @25C: aload #8
		// @25E: aastore
		// @25F: aload #8
		// @261: iconst_m1
		// @262: iload_1
		// @263: iconst_m1
		// @264: ixor
		// @265: if_icmpne @26F
		// @268: getstatic game.C_100037_wb[] game.C_100316_lc.field_102411_v
		// @26B: goto @272
		// @26E: athrow
		// @26F: getstatic game.C_100037_wb[] game.C_100200_ba.field_105851_b
		// @272: putfield game.C_100037_wb[] game.C_100302_ka.field_101883_qb
		// @275: aload #8
		// @277: iconst_0
		// @278: iload_1
		// @279: if_icmpne @283
		// @27C: getstatic game.C_100037_wb[] game.C_100200_ba.field_105851_b
		// @27F: goto @286
		// @282: athrow
		// @283: getstatic game.C_100037_wb[] game.C_100287_nm.field_106829_l
		// @286: putfield game.C_100037_wb[] game.C_100302_ka.field_101862_T
		// @289: bipush 46 (0x2E)
		// @28B: istore #14
		// @28D: new game.C_100302_ka
		// @290: dup
		// @291: ldc2_w -1
		// @294: getstatic game.C_100302_ka game.C_100286_nl.field_106813_m
		// @297: aload #9
		// @299: invokespecial game.C_100302_ka.<init>(long, game.C_100302_ka, java.lang.String)void
		// @29C: astore #15
		// @29E: iload #5
		// @2A0: bipush 77 (0x4D)
		// @2A2: if_icmpge @2B2
		// @2A5: aconst_null
		// @2A6: checkcast java.awt.Canvas
		// @2A9: bipush 21 (0x15)
		// @2AB: invokestatic game.C_100000_gd.func_100347_a(java.awt.Canvas, int)void
		// @2AE: goto @2B2
		// @2B1: athrow
		// @2B2: aload #15
		// @2B4: bipush 10 (0x0A)
		// @2B6: putfield int game.C_100302_ka.field_101833_ob
		// @2B9: aload #15
		// @2BB: iload #14
		// @2BD: iload_2
		// @2BE: bipush 15 (0x0F)
		// @2C0: isub
		// @2C1: iconst_4
		// @2C2: isub
		// @2C3: iconst_m1
		// @2C4: iconst_2
		// @2C5: iload #14
		// @2C7: ineg
		// @2C8: iload_3
		// @2C9: bipush -10 (0xF6)
		// @2CB: iadd
		// @2CC: iadd
		// @2CD: invokevirtual game.C_100302_ka.func_101825_a(int, int, int, int, int)void
		// @2D0: iload #13
		// @2D2: iconst_m1
		// @2D3: ixor
		// @2D4: bipush -2 (0xFE)
		// @2D6: if_icmpeq @2DD
		// @2D9: goto @2FA
		// @2DC: athrow
		// @2DD: aload #9
		// @2DF: iconst_2
		// @2E0: aload #15
		// @2E2: getfield int game.C_100302_ka.field_101829_Db
		// @2E5: imul
		// @2E6: ineg
		// @2E7: aload #15
		// @2E9: getfield int game.C_100302_ka.field_101886_Kb
		// @2EC: iadd
		// @2ED: sipush -3598 (0xF1F2)
		// @2F0: aload #15
		// @2F2: getfield game.C_100112_r game.C_100302_ka.field_101845_sb
		// @2F5: invokestatic game.C_100192_rf.func_101672_a(java.lang.String, int, int, game.C_100112_r)java.lang.String
		// @2F8: astore #9
		// @2FA: sipush -30945 (0x871F)
		// @2FD: iconst_1
		// @2FE: anewarray java.lang.String
		// @301: dup
		// @302: iconst_0
		// @303: aload #9
		// @305: aastore
		// @306: getstatic java.lang.String[] game.C_100000_gd.field_100361_z
		// @309: iconst_3
		// @30A: aaload
		// @30B: invokestatic game.C_100132_td.func_104965_a(int, java.lang.String[], java.lang.String)java.lang.String
		// @30E: astore #9
		// @310: aload #15
		// @312: aload #9
		// @314: putfield java.lang.String game.C_100302_ka.field_101890_ab
		// @317: aload #8
		// @319: bipush -91 (0xA5)
		// @31B: aload #15
		// @31D: invokevirtual game.C_100302_ka.func_101824_b(int, game.C_100302_ka)void
		// @320: bipush 6 (0x06)
		// @322: aload #15
		// @324: getfield game.C_100112_r game.C_100302_ka.field_101845_sb
		// @327: aload #15
		// @329: getfield java.lang.String game.C_100302_ka.field_101890_ab
		// @32C: aload #15
		// @32E: getfield int game.C_100302_ka.field_101829_Db
		// @331: iconst_2
		// @332: imul
		// @333: ineg
		// @334: aload #15
		// @336: getfield int game.C_100302_ka.field_101886_Kb
		// @339: iadd
		// @33A: aload #15
		// @33C: getfield int game.C_100302_ka.field_101833_ob
		// @33F: invokevirtual game.C_100112_r.func_101734_a(java.lang.String, int, int)int
		// @342: iadd
		// @343: istore #16
		// @345: sipush 2000 (0x07D0)
		// @348: iload #14
		// @34A: getstatic java.lang.String[] game.C_100000_gd.field_100361_z
		// @34D: iconst_0
		// @34E: aaload
		// @34F: getstatic int[] game.C_100021_wn.field_103870_e
		// @352: iload_0
		// @353: iaload
		// @354: iload #6
		// @356: aload #8
		// @358: iload_0
		// @359: iload #16
		// @35B: sipush 1000 (0x03E8)
		// @35E: invokestatic game.C_100305_km.func_103225_a(int, int, java.lang.String, int, int, game.C_100302_ka, int, int, int)void
		// @361: iinc #16 +14
		// @364: aconst_null
		// @365: aload #10
		// @367: if_acmpne @36E
		// @36A: goto @383
		// @36D: athrow
		// @36E: sipush 2000 (0x07D0)
		// @371: iload #14
		// @373: aload #10
		// @375: iload #11
		// @377: iload #6
		// @379: aload #8
		// @37B: iload_0
		// @37C: iload #16
		// @37E: iload #12
		// @380: invokestatic game.C_100305_km.func_103225_a(int, int, java.lang.String, int, int, game.C_100302_ka, int, int, int)void
		// @383: new game.C_100302_ka
		// @386: dup
		// @387: iload_0
		// @388: i2l
		// @389: aconst_null
		// @38A: invokespecial game.C_100302_ka.<init>(long, game.C_100302_ka)void
		// @38D: astore #17
		// @38F: aload #17
		// @391: iconst_2
		// @392: bipush -4 (0xFC)
		// @394: iload_2
		// @395: iadd
		// @396: iconst_m1
		// @397: iconst_2
		// @398: bipush -4 (0xFC)
		// @39A: iload #14
		// @39C: iadd
		// @39D: invokevirtual game.C_100302_ka.func_101825_a(int, int, int, int, int)void
		// @3A0: aload #17
		// @3A2: getstatic game.C_100037_wb[] game.C_100287_nm.field_106829_l
		// @3A5: putfield game.C_100037_wb[] game.C_100302_ka.field_101862_T
		// @3A8: getstatic game.C_100153_be[] game.C_100242_oh.field_106347_a
		// @3AB: iload_0
		// @3AC: aaload
		// @3AD: astore #18
		// @3AF: aload #17
		// @3B1: aload #18
		// @3B3: invokevirtual game.C_100153_be.func_105309_b()game.C_100037_wb
		// @3B6: putfield game.C_100037_wb game.C_100302_ka.field_101887_nb
		// @3B9: iload #4
		// @3BB: ifeq @3C7
		// @3BE: iload #7
		// @3C0: ifeq @400
		// @3C3: goto @3C7
		// @3C6: athrow
		// @3C7: aload #17
		// @3C9: getfield game.C_100037_wb game.C_100302_ka.field_101887_nb
		// @3CC: getfield int[] game.C_100037_wb.field_102388_J
		// @3CF: astore #19
		// @3D1: iconst_0
		// @3D2: istore #20
		// @3D4: iload #20
		// @3D6: aload #19
		// @3D8: arraylength
		// @3D9: if_icmpge @400
		// @3DC: iconst_0
		// @3DD: aload #19
		// @3DF: iload #20
		// @3E1: iaload
		// @3E2: iload #23
		// @3E4: ifne @40E
		// @3E7: if_icmpne @3F1
		// @3EA: goto @3EE
		// @3ED: athrow
		// @3EE: goto @3F8
		// @3F1: aload #19
		// @3F3: iload #20
		// @3F5: ldc 4210752 (0x404040)
		// @3F7: iastore
		// @3F8: iinc #20 +1
		// @3FB: iload #23
		// @3FD: ifeq @3D4
		// @400: aload #8
		// @402: bipush -106 (0x96)
		// @404: aload #17
		// @406: invokevirtual game.C_100302_ka.func_101824_b(int, game.C_100302_ka)void
		// @409: iload_0
		// @40A: iconst_m1
		// @40B: ixor
		// @40C: bipush -11 (0xF5)
		// @40E: if_icmpne @411
		// @411: iload #7
		// @413: ifne @4CE
		// @416: iconst_0
		// @417: iload_1
		// @418: if_icmpeq @529
		// @41B: goto @41F
		// @41E: athrow
		// @41F: bipush 28 (0x1C)
		// @421: istore #19
		// @423: iload #19
		// @425: istore #20
		// @427: new game.C_100302_ka
		// @42A: dup
		// @42B: getstatic java.lang.String[] game.C_100000_gd.field_100361_z
		// @42E: iconst_2
		// @42F: aaload
		// @430: aconst_null
		// @431: invokespecial game.C_100302_ka.<init>(java.lang.String, game.C_100302_ka)void
		// @434: astore #21
		// @436: aload #21
		// @438: aload #17
		// @43A: getfield int game.C_100302_ka.field_101841_Pb
		// @43D: iload #19
		// @43F: ineg
		// @440: aload #17
		// @442: getfield int game.C_100302_ka.field_101886_Kb
		// @445: iadd
		// @446: iconst_2
		// @447: idiv
		// @448: iadd
		// @449: iload #20
		// @44B: iconst_m1
		// @44C: aload #17
		// @44E: getfield int game.C_100302_ka.field_101880_Gb
		// @451: iload #20
		// @453: ineg
		// @454: aload #17
		// @456: getfield int game.C_100302_ka.field_101848_lb
		// @459: iadd
		// @45A: iconst_2
		// @45B: idiv
		// @45C: iadd
		// @45D: iload #19
		// @45F: invokevirtual game.C_100302_ka.func_101825_a(int, int, int, int, int)void
		// @462: aload #21
		// @464: iconst_2
		// @465: putfield int game.C_100302_ka.field_101875_X
		// @468: aload #21
		// @46A: iconst_2
		// @46B: putfield int game.C_100302_ka.field_101846_Ib
		// @46E: aload #21
		// @470: getstatic game.C_100037_wb[] game.C_100321_hi.field_107228_h
		// @473: putfield game.C_100037_wb[] game.C_100302_ka.field_101862_T
		// @476: aload #21
		// @478: getstatic game.C_100037_wb[] game.C_100154_sl.field_105329_f
		// @47B: putfield game.C_100037_wb[] game.C_100302_ka.field_101883_qb
		// @47E: aload #21
		// @480: getstatic game.C_100037_wb[] game.C_100111_el.field_104867_h
		// @483: iload_1
		// @484: aaload
		// @485: putfield game.C_100037_wb game.C_100302_ka.field_101887_nb
		// @488: new game.C_100302_ka
		// @48B: dup
		// @48C: ldc2_w -1
		// @48F: aconst_null
		// @490: invokespecial game.C_100302_ka.<init>(long, game.C_100302_ka)void
		// @493: astore #22
		// @495: aload #22
		// @497: iconst_0
		// @498: bipush 28 (0x1C)
		// @49A: iconst_m1
		// @49B: iconst_0
		// @49C: bipush 28 (0x1C)
		// @49E: invokevirtual game.C_100302_ka.func_101825_a(int, int, int, int, int)void
		// @4A1: aload #22
		// @4A3: getstatic game.C_100037_wb[] game.C_100058_dg.field_101562_E
		// @4A6: iload_1
		// @4A7: aaload
		// @4A8: putfield game.C_100037_wb game.C_100302_ka.field_101887_nb
		// @4AB: aload #22
		// @4AD: iconst_2
		// @4AE: putfield int game.C_100302_ka.field_101875_X
		// @4B1: aload #22
		// @4B3: iconst_2
		// @4B4: putfield int game.C_100302_ka.field_101846_Ib
		// @4B7: aload #21
		// @4B9: bipush -100 (0x9C)
		// @4BB: aload #22
		// @4BD: invokevirtual game.C_100302_ka.func_101824_b(int, game.C_100302_ka)void
		// @4C0: aload #8
		// @4C2: bipush -89 (0xA7)
		// @4C4: aload #21
		// @4C6: invokevirtual game.C_100302_ka.func_101824_b(int, game.C_100302_ka)void
		// @4C9: iload #23
		// @4CB: ifeq @529
		// @4CE: getstatic game.C_100037_wb game.C_100244_pe.field_106376_e
		// @4D1: getfield int game.C_100037_wb.field_102339_s
		// @4D4: istore #19
		// @4D6: getstatic game.C_100037_wb game.C_100244_pe.field_106376_e
		// @4D9: getfield int game.C_100037_wb.field_102337_u
		// @4DC: istore #20
		// @4DE: new game.C_100302_ka
		// @4E1: dup
		// @4E2: ldc2_w -1
		// @4E5: aconst_null
		// @4E6: invokespecial game.C_100302_ka.<init>(long, game.C_100302_ka)void
		// @4E9: astore #21
		// @4EB: aload #21
		// @4ED: aload #17
		// @4EF: getfield int game.C_100302_ka.field_101841_Pb
		// @4F2: iload #19
		// @4F4: ineg
		// @4F5: aload #17
		// @4F7: getfield int game.C_100302_ka.field_101886_Kb
		// @4FA: iadd
		// @4FB: iconst_2
		// @4FC: idiv
		// @4FD: ineg
		// @4FE: isub
		// @4FF: iload #20
		// @501: iconst_m1
		// @502: iload #19
		// @504: ineg
		// @505: aload #17
		// @507: getfield int game.C_100302_ka.field_101848_lb
		// @50A: iadd
		// @50B: iconst_2
		// @50C: idiv
		// @50D: aload #17
		// @50F: getfield int game.C_100302_ka.field_101880_Gb
		// @512: iadd
		// @513: iload #19
		// @515: invokevirtual game.C_100302_ka.func_101825_a(int, int, int, int, int)void
		// @518: aload #21
		// @51A: getstatic game.C_100037_wb game.C_100244_pe.field_106376_e
		// @51D: putfield game.C_100037_wb game.C_100302_ka.field_101887_nb
		// @520: aload #8
		// @522: bipush -86 (0xAA)
		// @524: aload #21
		// @526: invokevirtual game.C_100302_ka.func_101824_b(int, game.C_100302_ka)void
		// @529: aload #8
		// @52B: areturn
		// @52C: astore #6
		// @52E: aload #6
		// @530: new java.lang.StringBuilder
		// @533: dup
		// @534: invokespecial java.lang.StringBuilder.<init>()void
		// @537: getstatic java.lang.String[] game.C_100000_gd.field_100361_z
		// @53A: iconst_4
		// @53B: aaload
		// @53C: invokevirtual java.lang.StringBuilder.append(java.lang.String)java.lang.StringBuilder
		// @53F: iload_0
		// @540: invokevirtual java.lang.StringBuilder.append(int)java.lang.StringBuilder
		// @543: bipush 44 (0x2C)
		// @545: invokevirtual java.lang.StringBuilder.append(char)java.lang.StringBuilder
		// @548: iload_1
		// @549: invokevirtual java.lang.StringBuilder.append(int)java.lang.StringBuilder
		// @54C: bipush 44 (0x2C)
		// @54E: invokevirtual java.lang.StringBuilder.append(char)java.lang.StringBuilder
		// @551: iload_2
		// @552: invokevirtual java.lang.StringBuilder.append(int)java.lang.StringBuilder
		// @555: bipush 44 (0x2C)
		// @557: invokevirtual java.lang.StringBuilder.append(char)java.lang.StringBuilder
		// @55A: iload_3
		// @55B: invokevirtual java.lang.StringBuilder.append(int)java.lang.StringBuilder
		// @55E: bipush 44 (0x2C)
		// @560: invokevirtual java.lang.StringBuilder.append(char)java.lang.StringBuilder
		// @563: iload #4
		// @565: invokevirtual java.lang.StringBuilder.append(boolean)java.lang.StringBuilder
		// @568: bipush 44 (0x2C)
		// @56A: invokevirtual java.lang.StringBuilder.append(char)java.lang.StringBuilder
		// @56D: iload #5
		// @56F: invokevirtual java.lang.StringBuilder.append(int)java.lang.StringBuilder
		// @572: bipush 41 (0x29)
		// @574: invokevirtual java.lang.StringBuilder.append(char)java.lang.StringBuilder
		// @577: invokevirtual java.lang.StringBuilder.toString()java.lang.String
		// @57A: invokestatic game.C_100181_cf.func_105695_a(java.lang.Throwable, java.lang.String)game.C_100170_cm
		// @57D: athrow
	}
	
	public static void func_100350_a(int arg0)
	{
		// @00: aconst_null
		// @01: putstatic java.lang.String game.C_100000_gd.field_100358_b
		// @04: aconst_null
		// @05: putstatic java.lang.String game.C_100000_gd.field_100354_f
		// @08: aconst_null
		// @09: putstatic java.lang.String game.C_100000_gd.field_100356_d
		// @0C: aconst_null
		// @0D: putstatic java.lang.String[] game.C_100000_gd.field_100360_a
		// @10: aconst_null
		// @11: putstatic java.lang.String game.C_100000_gd.field_100359_c
		// @14: iload_0
		// @15: sipush 24871 (0x6127)
		// @18: if_icmpeq @2A
		// @1B: bipush -24 (0xE8)
		// @1D: bipush -93 (0xA3)
		// @1F: bipush -122 (0x86)
		// @21: bipush 63 (0x3F)
		// @23: iconst_0
		// @24: bipush -89 (0xA7)
		// @26: invokestatic game.C_100000_gd.func_100348_a(int, int, int, int, boolean, int)game.C_100302_ka
		// @29: pop
		// @2A: goto @4F
		// @2D: astore_1
		// @2E: aload_1
		// @2F: new java.lang.StringBuilder
		// @32: dup
		// @33: invokespecial java.lang.StringBuilder.<init>()void
		// @36: getstatic java.lang.String[] game.C_100000_gd.field_100361_z
		// @39: bipush 8 (0x08)
		// @3B: aaload
		// @3C: invokevirtual java.lang.StringBuilder.append(java.lang.String)java.lang.StringBuilder
		// @3F: iload_0
		// @40: invokevirtual java.lang.StringBuilder.append(int)java.lang.StringBuilder
		// @43: bipush 41 (0x29)
		// @45: invokevirtual java.lang.StringBuilder.append(char)java.lang.StringBuilder
		// @48: invokevirtual java.lang.StringBuilder.toString()java.lang.String
		// @4B: invokestatic game.C_100181_cf.func_105695_a(java.lang.Throwable, java.lang.String)game.C_100170_cm
		// @4E: athrow
		// @4F: return
	}
	
	static final void func_100349_a(int arg0, int arg1, int arg2, String arg3, int arg4, int arg5, boolean arg6, int arg7)
	{
		// @000: iconst_m1
		// @001: getstatic game.C_100302_ka game.C_100019_wl.field_103844_b
		// @004: getfield int game.C_100302_ka.field_101854_N
		// @007: iconst_m1
		// @008: ixor
		// @009: if_icmpeq @036
		// @00C: getstatic boolean game.C_100272_mn.field_102435_K
		// @00F: ifne @036
		// @012: goto @016
		// @015: athrow
		// @016: getstatic boolean game.C_100164_se.field_105449_g
		// @019: ifne @02E
		// @01C: goto @020
		// @01F: athrow
		// @020: iconst_1
		// @021: putstatic boolean game.C_100230_of.field_106216_k
		// @024: getstatic int game.SteelSentinels.field_105275_O
		// @027: ifeq @036
		// @02A: goto @02E
		// @02D: athrow
		// @02E: iconst_0
		// @02F: invokestatic game.C_100078_ul.func_103276_f(boolean)void
		// @032: goto @036
		// @035: athrow
		// @036: getstatic boolean game.C_100230_of.field_106216_k
		// @039: ifne @040
		// @03C: goto @092
		// @03F: athrow
		// @040: iload #5
		// @042: aload_3
		// @043: bipush -112 (0x90)
		// @045: bipush 20 (0x14)
		// @047: iload_1
		// @048: iload_0
		// @049: iload #7
		// @04B: iload #5
		// @04D: iload #4
		// @04F: invokestatic game.C_100044_vm.func_100937_a(int, java.lang.String, byte, int, int, int, int, int, int)void
		// @052: getstatic game.C_100302_ka game.C_100154_sl.field_105332_e
		// @055: iload #6
		// @057: bipush -111 (0x91)
		// @059: invokevirtual game.C_100302_ka.func_101819_a(boolean, byte)void
		// @05C: iload #6
		// @05E: ifne @065
		// @061: goto @092
		// @064: athrow
		// @065: iconst_m1
		// @066: getstatic game.C_100302_ka game.C_100291_jj.field_106874_d
		// @069: getfield int game.C_100302_ka.field_101854_N
		// @06C: iconst_m1
		// @06D: ixor
		// @06E: if_icmpeq @079
		// @071: iconst_0
		// @072: putstatic boolean game.C_100230_of.field_106216_k
		// @075: goto @079
		// @078: athrow
		// @079: iconst_m1
		// @07A: getstatic game.C_100302_ka game.C_100032_gk.field_103140_X
		// @07D: getfield int game.C_100302_ka.field_101854_N
		// @080: iconst_m1
		// @081: ixor
		// @082: if_icmpeq @092
		// @085: bipush 111 (0x6F)
		// @087: invokestatic game.C_100233_oa.func_106223_b(int)void
		// @08A: iconst_0
		// @08B: putstatic boolean game.C_100230_of.field_106216_k
		// @08E: goto @092
		// @091: athrow
		// @092: iload_2
		// @093: sipush -1692 (0xF964)
		// @096: if_icmpeq @0B1
		// @099: bipush -124 (0x84)
		// @09B: bipush -80 (0xB0)
		// @09D: bipush 11 (0x0B)
		// @09F: aconst_null
		// @0A0: checkcast java.lang.String
		// @0A3: bipush -58 (0xC6)
		// @0A5: bipush 23 (0x17)
		// @0A7: iconst_0
		// @0A8: bipush 64 (0x40)
		// @0AA: invokestatic game.C_100000_gd.func_100349_a(int, int, int, java.lang.String, int, int, boolean, int)void
		// @0AD: goto @0B1
		// @0B0: athrow
		// @0B1: goto @12E
		// @0B4: astore #8
		// @0B6: aload #8
		// @0B8: new java.lang.StringBuilder
		// @0BB: dup
		// @0BC: invokespecial java.lang.StringBuilder.<init>()void
		// @0BF: getstatic java.lang.String[] game.C_100000_gd.field_100361_z
		// @0C2: bipush 18 (0x12)
		// @0C4: aaload
		// @0C5: invokevirtual java.lang.StringBuilder.append(java.lang.String)java.lang.StringBuilder
		// @0C8: iload_0
		// @0C9: invokevirtual java.lang.StringBuilder.append(int)java.lang.StringBuilder
		// @0CC: bipush 44 (0x2C)
		// @0CE: invokevirtual java.lang.StringBuilder.append(char)java.lang.StringBuilder
		// @0D1: iload_1
		// @0D2: invokevirtual java.lang.StringBuilder.append(int)java.lang.StringBuilder
		// @0D5: bipush 44 (0x2C)
		// @0D7: invokevirtual java.lang.StringBuilder.append(char)java.lang.StringBuilder
		// @0DA: iload_2
		// @0DB: invokevirtual java.lang.StringBuilder.append(int)java.lang.StringBuilder
		// @0DE: bipush 44 (0x2C)
		// @0E0: invokevirtual java.lang.StringBuilder.append(char)java.lang.StringBuilder
		// @0E3: aload_3
		// @0E4: ifnull @0F1
		// @0E7: getstatic java.lang.String[] game.C_100000_gd.field_100361_z
		// @0EA: bipush 16 (0x10)
		// @0EC: aaload
		// @0ED: goto @0F7
		// @0F0: athrow
		// @0F1: getstatic java.lang.String[] game.C_100000_gd.field_100361_z
		// @0F4: bipush 15 (0x0F)
		// @0F6: aaload
		// @0F7: invokevirtual java.lang.StringBuilder.append(java.lang.String)java.lang.StringBuilder
		// @0FA: bipush 44 (0x2C)
		// @0FC: invokevirtual java.lang.StringBuilder.append(char)java.lang.StringBuilder
		// @0FF: iload #4
		// @101: invokevirtual java.lang.StringBuilder.append(int)java.lang.StringBuilder
		// @104: bipush 44 (0x2C)
		// @106: invokevirtual java.lang.StringBuilder.append(char)java.lang.StringBuilder
		// @109: iload #5
		// @10B: invokevirtual java.lang.StringBuilder.append(int)java.lang.StringBuilder
		// @10E: bipush 44 (0x2C)
		// @110: invokevirtual java.lang.StringBuilder.append(char)java.lang.StringBuilder
		// @113: iload #6
		// @115: invokevirtual java.lang.StringBuilder.append(boolean)java.lang.StringBuilder
		// @118: bipush 44 (0x2C)
		// @11A: invokevirtual java.lang.StringBuilder.append(char)java.lang.StringBuilder
		// @11D: iload #7
		// @11F: invokevirtual java.lang.StringBuilder.append(int)java.lang.StringBuilder
		// @122: bipush 41 (0x29)
		// @124: invokevirtual java.lang.StringBuilder.append(char)java.lang.StringBuilder
		// @127: invokevirtual java.lang.StringBuilder.toString()java.lang.String
		// @12A: invokestatic game.C_100181_cf.func_105695_a(java.lang.Throwable, java.lang.String)game.C_100170_cm
		// @12D: athrow
		// @12E: return
	}
	
	static final void func_100347_a(Canvas arg0, int arg1)
	{
		// @00: getstatic int game.C_100087_n.field_100697_v
		// @03: iconst_m1
		// @04: ixor
		// @05: bipush -12 (0xF4)
		// @07: if_icmpeq @0E
		// @0A: goto @13
		// @0D: athrow
		// @0E: bipush -2 (0xFE)
		// @10: invokestatic game.C_100225_ah.func_106106_a(int)void
		// @13: getstatic boolean game.C_100077_d.field_103326_eb
		// @16: getstatic java.lang.String game.C_100122_em.field_102079_Vb
		// @19: getstatic float game.C_100100_i.field_102011_gc
		// @1C: bipush -125 (0x83)
		// @1E: invokestatic game.C_100093_fd.func_102775_a(boolean, java.lang.String, float, int)void
		// @21: iload_1
		// @22: sipush -25993 (0x9A77)
		// @25: iconst_0
		// @26: aload_0
		// @27: invokestatic game.C_100238_ol.func_101689_a(int, int, int, java.awt.Canvas)void
		// @2A: goto @6B
		// @2D: astore_2
		// @2E: aload_2
		// @2F: new java.lang.StringBuilder
		// @32: dup
		// @33: invokespecial java.lang.StringBuilder.<init>()void
		// @36: getstatic java.lang.String[] game.C_100000_gd.field_100361_z
		// @39: bipush 17 (0x11)
		// @3B: aaload
		// @3C: invokevirtual java.lang.StringBuilder.append(java.lang.String)java.lang.StringBuilder
		// @3F: aload_0
		// @40: ifnull @4D
		// @43: getstatic java.lang.String[] game.C_100000_gd.field_100361_z
		// @46: bipush 16 (0x10)
		// @48: aaload
		// @49: goto @53
		// @4C: athrow
		// @4D: getstatic java.lang.String[] game.C_100000_gd.field_100361_z
		// @50: bipush 15 (0x0F)
		// @52: aaload
		// @53: invokevirtual java.lang.StringBuilder.append(java.lang.String)java.lang.StringBuilder
		// @56: bipush 44 (0x2C)
		// @58: invokevirtual java.lang.StringBuilder.append(char)java.lang.StringBuilder
		// @5B: iload_1
		// @5C: invokevirtual java.lang.StringBuilder.append(int)java.lang.StringBuilder
		// @5F: bipush 41 (0x29)
		// @61: invokevirtual java.lang.StringBuilder.append(char)java.lang.StringBuilder
		// @64: invokevirtual java.lang.StringBuilder.toString()java.lang.String
		// @67: invokestatic game.C_100181_cf.func_105695_a(java.lang.Throwable, java.lang.String)game.C_100170_cm
		// @6A: athrow
		// @6B: return
	}
	
	static
	{
		// @000: bipush 19 (0x13)
		// @002: anewarray java.lang.String
		// @005: dup
		// @006: iconst_0
		// @007: ldc "H\u000f\u007f\r%EX"
		// @009: invokestatic game.C_100000_gd.func_100352_z(java.lang.String)char[]
		// @00C: invokestatic game.C_100000_gd.func_100351_z(char[])java.lang.String
		// @00F: aastore
		// @010: dup
		// @011: iconst_1
		// @012: ldc "H\u000f\u007f\r%@X"
		// @014: invokestatic game.C_100000_gd.func_100352_z(java.lang.String)char[]
		// @017: invokestatic game.C_100000_gd.func_100351_z(char[])java.lang.String
		// @01A: aastore
		// @01B: dup
		// @01C: iconst_2
		// @01D: ldc "\u0011\u0008u\u0003v\u0011\u0003`"
		// @01F: invokestatic game.C_100000_gd.func_100352_z(java.lang.String)char[]
		// @022: invokestatic game.C_100000_gd.func_100351_z(char[])java.lang.String
		// @025: aastore
		// @026: dup
		// @027: iconst_3
		// @028: ldc "H\u0005}\u0006%E\u0003%YyEX.O(JZ=\tw\u0018X"
		// @02A: invokestatic game.C_100000_gd.func_100352_z(java.lang.String)char[]
		// @02D: invokestatic game.C_100000_gd.func_100351_z(char[])java.lang.String
		// @030: aastore
		// @031: dup
		// @032: iconst_4
		// @033: ldc "\u0013\u0002<(0"
		// @035: invokestatic game.C_100000_gd.func_100352_z(java.lang.String)char[]
		// @038: invokestatic game.C_100000_gd.func_100351_z(char[])java.lang.String
		// @03B: aastore
		// @03C: dup
		// @03D: iconst_5
		// @03E: ldc "H\u000f\u007f\r%CX"
		// @040: invokestatic game.C_100000_gd.func_100352_z(java.lang.String)char[]
		// @043: invokestatic game.C_100000_gd.func_100351_z(char[])java.lang.String
		// @046: aastore
		// @047: dup
		// @048: bipush 6 (0x06)
		// @04A: ldc "H\u000f\u007f\r%AX"
		// @04C: invokestatic game.C_100000_gd.func_100352_z(java.lang.String)char[]
		// @04F: invokestatic game.C_100000_gd.func_100351_z(char[])java.lang.String
		// @052: aastore
		// @053: dup
		// @054: bipush 7 (0x07)
		// @056: ldc "3)V?T1"
		// @058: invokestatic game.C_100000_gd.func_100352_z(java.lang.String)char[]
		// @05B: invokestatic game.C_100000_gd.func_100351_z(char[])java.lang.String
		// @05E: aastore
		// @05F: dup
		// @060: bipush 8 (0x08)
		// @062: ldc "\u0013\u0002<+0"
		// @064: invokestatic game.C_100000_gd.func_100352_z(java.lang.String)char[]
		// @067: invokestatic game.C_100000_gd.func_100351_z(char[])java.lang.String
		// @06A: aastore
		// @06B: dup
		// @06C: bipush 9 (0x09)
		// @06E: ldc "\u0019\u0003\u007f\u0008}\u0006\u0015M\u0008}\u001a\u0003t\u0003l\u00079~\u0005\u007f\u001b"
		// @070: invokestatic game.C_100000_gd.func_100352_z(java.lang.String)char[]
		// @073: invokestatic game.C_100000_gd.func_100351_z(char[])java.lang.String
		// @076: aastore
		// @077: dup
		// @078: bipush 10 (0x0A)
		// @07A: ldc "\u0019\u0003\u007f\u0008}\u0006\u0015M\u0008}\u001a\u0003t\u0003l\u00079p\u0005j\u0010\u0003`\u0019"
		// @07C: invokestatic game.C_100000_gd.func_100352_z(java.lang.String)char[]
		// @07F: invokestatic game.C_100000_gd.func_100351_z(char[])java.lang.String
		// @082: aastore
		// @083: dup
		// @084: bipush 11 (0x0B)
		// @086: ldc "\u0019\u0003\u007f\u0008}\u0006\u0015M\u0008}\u001a\u0003t\u0003l\u00079a\tj\u0011\u0003|\u0019p\u001b\u0012a"
		// @088: invokestatic game.C_100000_gd.func_100352_z(java.lang.String)char[]
		// @08B: invokestatic game.C_100000_gd.func_100351_z(char[])java.lang.String
		// @08E: aastore
		// @08F: dup
		// @090: bipush 12 (0x0C)
		// @092: ldc "\u0016\u0003|\u000f~\u001d\u0012a"
		// @094: invokestatic game.C_100000_gd.func_100352_z(java.lang.String)char[]
		// @097: invokestatic game.C_100000_gd.func_100351_z(char[])java.lang.String
		// @09A: aastore
		// @09B: dup
		// @09C: bipush 13 (0x0D)
		// @09E: ldc "\u0013\u0002</0"
		// @0A0: invokestatic game.C_100000_gd.func_100352_z(java.lang.String)char[]
		// @0A3: invokestatic game.C_100000_gd.func_100351_z(char[])java.lang.String
		// @0A6: aastore
		// @0A7: dup
		// @0A8: bipush 14 (0x0E)
		// @0AA: ldc "\u0019\u0003\u007f\u0008}\u0006\u0015M\u0008}\u001a\u0003t\u0003l\u00079b\u0018q\u0017\u0003"
		// @0AC: invokestatic game.C_100000_gd.func_100352_z(java.lang.String)char[]
		// @0AF: invokestatic game.C_100000_gd.func_100351_z(char[])java.lang.String
		// @0B2: aastore
		// @0B3: dup
		// @0B4: bipush 15 (0x0F)
		// @0B6: ldc "\u001a\u0013~\u0006"
		// @0B8: invokestatic game.C_100000_gd.func_100352_z(java.lang.String)char[]
		// @0BB: invokestatic game.C_100000_gd.func_100351_z(char[])java.lang.String
		// @0BE: aastore
		// @0BF: dup
		// @0C0: bipush 16 (0x10)
		// @0C2: ldc "\u000fH<De"
		// @0C4: invokestatic game.C_100000_gd.func_100352_z(java.lang.String)char[]
		// @0C7: invokestatic game.C_100000_gd.func_100351_z(char[])java.lang.String
		// @0CA: aastore
		// @0CB: dup
		// @0CC: bipush 17 (0x11)
		// @0CE: ldc "\u0013\u0002<.0"
		// @0D0: invokestatic game.C_100000_gd.func_100352_z(java.lang.String)char[]
		// @0D3: invokestatic game.C_100000_gd.func_100351_z(char[])java.lang.String
		// @0D6: aastore
		// @0D7: dup
		// @0D8: bipush 18 (0x12)
		// @0DA: ldc "\u0013\u0002<)0"
		// @0DC: invokestatic game.C_100000_gd.func_100352_z(java.lang.String)char[]
		// @0DF: invokestatic game.C_100000_gd.func_100351_z(char[])java.lang.String
		// @0E2: aastore
		// @0E3: putstatic java.lang.String[] game.C_100000_gd.field_100361_z
		// @0E6: ldc "3\u0003fJy\u0017\u0005w\u0019kT\u0012}Jv\u0011\u00112\u0007w\u0010\u0013~\u000fkT\u0004kJ}\u000c\u0016w\u0004|\u001d\u0008uJk\u001b\ns\u0018q\u0000\u00032\tm\u0016\u0003aJw\u001aFw\u0004\u007f\u001d\u0008w\u000fj\u001d\u0008uD8!\u0008f\u0003tT\u001f}\u001f8\u0011\u0008u\u0003v\u0011\u0003`JyT\u000b}\u000em\u0018\u0003>Jq\u0000Fq\u000bv\u001a\tfJz\u0011Fw\u001bm\u001d\u0016b\u000f|T\t|JyT\u0015w\u0004l\u001d\u0008w\u00066"
		// @0E8: invokestatic game.C_100000_gd.func_100352_z(java.lang.String)char[]
		// @0EB: invokestatic game.C_100000_gd.func_100351_z(char[])java.lang.String
		// @0EE: putstatic java.lang.String game.C_100000_gd.field_100356_d
		// @0F1: ldc ";\u0016f\u0003w\u001a\u0015"
		// @0F3: invokestatic game.C_100000_gd.func_100352_z(java.lang.String)char[]
		// @0F6: invokestatic game.C_100000_gd.func_100351_z(char[])java.lang.String
		// @0F9: putstatic java.lang.String game.C_100000_gd.field_100359_c
		// @0FC: iconst_3
		// @0FD: anewarray java.lang.String
		// @100: putstatic java.lang.String[] game.C_100000_gd.field_100360_a
		// @103: ldc "$\nw\u000bk\u0011Fa\u000ft\u0011\u0005fJw\u0004\u0012{\u0005v\u0007F{\u00048\u0000\u000ewJ~\u001b\n~\u0005o\u001d\u0008uJj\u001b\u0011aP8T"
		// @105: invokestatic game.C_100000_gd.func_100352_z(java.lang.String)char[]
		// @108: invokestatic game.C_100000_gd.func_100351_z(char[])java.lang.String
		// @10B: putstatic java.lang.String game.C_100000_gd.field_100354_f
		// @10E: ldc " \u000e{\u00198\u0004\u0007a\u0019o\u001b\u0014vJ{\u001b\u0008f\u000bq\u001a\u00152\u0013w\u0001\u00142\u000fu\u0015\u000f~Jy\u0010\u0002`\u000fk\u0007J2\u000bv\u0010Fe\u0005m\u0018\u00022\u0008}T\u0003s\u0019aT\u0012}J\u007f\u0001\u0003a\u0019"
		// @110: invokestatic game.C_100000_gd.func_100352_z(java.lang.String)char[]
		// @113: invokestatic game.C_100000_gd.func_100351_z(char[])java.lang.String
		// @116: putstatic java.lang.String game.C_100000_gd.field_100358_b
		// @119: iconst_1
		// @11A: putstatic int game.C_100000_gd.field_100355_g
		// @11D: dconst_0
		// @11E: putstatic double game.C_100000_gd.field_100357_e
		// @121: return
	}
	
	private static char[] func_100352_z(String arg0)
	{
		// @00: aload_0
		// @01: invokevirtual java.lang.String.toCharArray()char[]
		// @04: dup
		// @05: arraylength
		// @06: iconst_2
		// @07: if_icmpge @13
		// @0A: dup
		// @0B: iconst_0
		// @0C: dup2
		// @0D: caload
		// @0E: bipush 24 (0x18)
		// @10: ixor
		// @11: i2c
		// @12: castore
		// @13: areturn
	}
	
	private static String func_100351_z(char[] arg0)
	{
		// @00: aload_0
		// @01: dup
		// @02: arraylength
		// @03: swap
		// @04: iconst_0
		// @05: istore_1
		// @06: goto @4C
		// @09: dup
		// @0A: iload_1
		// @0B: dup2
		// @0C: caload
		// @0D: iload_1
		// @0E: iconst_5
		// @0F: irem
		// @10: tableswitch def: @44, for 0: @30, for 1: @35, for 2: @3A, for 3: @3F
		// @30: bipush 116 (0x74)
		// @32: goto @46
		// @35: bipush 102 (0x66)
		// @37: goto @46
		// @3A: bipush 18 (0x12)
		// @3C: goto @46
		// @3F: bipush 106 (0x6A)
		// @41: goto @46
		// @44: bipush 24 (0x18)
		// @46: ixor
		// @47: i2c
		// @48: castore
		// @49: iinc #1 +1
		// @4C: swap
		// @4D: dup_x1
		// @4E: iload_1
		// @4F: if_icmpgt @09
		// @52: new java.lang.String
		// @55: dup_x1
		// @56: swap
		// @57: invokespecial java.lang.String.<init>(char[])void
		// @5A: invokevirtual java.lang.String.intern()java.lang.String
		// @5D: areturn
	}
}
