package game;

final class C_100093_fd extends C_100085_a implements C_100237_ok, C_100334_ik
{
	static int[] field_102781_W;
	static int field_102785_S;
	private C_100342_jg field_102788_X;
	static int[] field_102784_P;
	static String field_102786_R;
	static C_100197_ra field_102782_V;
	static String field_102779_U;
	private C_100083_c field_102783_Q;
	private C_100218_am field_102780_T;
	private static final String[] field_102787_Y;
	
	static final void func_102778_a(int arg0, int arg1)
	{
		// @00: getstatic int game.SteelSentinels.field_105275_O
		// @03: istore_3
		// @04: getstatic game.C_100202_qi game.C_100178_cg.field_105689_e
		// @07: bipush 75 (0x4B)
		// @09: invokevirtual game.C_100202_qi.func_105899_c(int)game.C_100158_da
		// @0C: checkcast game.C_100292_jk
		// @0F: astore_2
		// @10: aload_2
		// @11: ifnull @31
		// @14: iload_1
		// @15: ldc 16777144 (0xffffb8)
		// @17: ixor
		// @18: aload_2
		// @19: iload_0
		// @1A: invokestatic game.C_100016_wi.func_103801_a(int, game.C_100292_jk, int)void
		// @1D: getstatic game.C_100202_qi game.C_100178_cg.field_105689_e
		// @20: bipush 118 (0x76)
		// @22: invokevirtual game.C_100202_qi.func_105907_c(byte)game.C_100158_da
		// @25: checkcast game.C_100292_jk
		// @28: iload_3
		// @29: ifne @39
		// @2C: astore_2
		// @2D: iload_3
		// @2E: ifeq @10
		// @31: getstatic game.C_100202_qi game.C_100143_bl.field_105100_g
		// @34: bipush 47 (0x2F)
		// @36: invokevirtual game.C_100202_qi.func_105899_c(int)game.C_100158_da
		// @39: checkcast game.C_100187_rk
		// @3C: astore_2
		// @3D: aconst_null
		// @3E: aload_2
		// @3F: if_acmpeq @60
		// @42: iload_0
		// @43: iconst_5
		// @44: aload_2
		// @45: invokestatic game.C_100283_ni.func_106751_a(int, int, game.C_100187_rk)void
		// @48: getstatic game.C_100202_qi game.C_100143_bl.field_105100_g
		// @4B: bipush 69 (0x45)
		// @4D: invokevirtual game.C_100202_qi.func_105907_c(byte)game.C_100158_da
		// @50: checkcast game.C_100187_rk
		// @53: astore_2
		// @54: iload_3
		// @55: ifne @70
		// @58: iload_3
		// @59: ifeq @3D
		// @5C: goto @60
		// @5F: athrow
		// @60: iload_1
		// @61: ldc 16777215 (0xffffff)
		// @63: if_icmpeq @70
		// @66: bipush 77 (0x4D)
		// @68: invokestatic game.C_100093_fd.func_102776_k(int)boolean
		// @6B: pop
		// @6C: goto @70
		// @6F: athrow
		// @70: goto @9E
		// @73: astore_2
		// @74: aload_2
		// @75: new java.lang.StringBuilder
		// @78: dup
		// @79: invokespecial java.lang.StringBuilder.<init>()void
		// @7C: getstatic java.lang.String[] game.C_100093_fd.field_102787_Y
		// @7F: bipush 13 (0x0D)
		// @81: aaload
		// @82: invokevirtual java.lang.StringBuilder.append(java.lang.String)java.lang.StringBuilder
		// @85: iload_0
		// @86: invokevirtual java.lang.StringBuilder.append(int)java.lang.StringBuilder
		// @89: bipush 44 (0x2C)
		// @8B: invokevirtual java.lang.StringBuilder.append(char)java.lang.StringBuilder
		// @8E: iload_1
		// @8F: invokevirtual java.lang.StringBuilder.append(int)java.lang.StringBuilder
		// @92: bipush 41 (0x29)
		// @94: invokevirtual java.lang.StringBuilder.append(char)java.lang.StringBuilder
		// @97: invokevirtual java.lang.StringBuilder.toString()java.lang.String
		// @9A: invokestatic game.C_100181_cf.func_105695_a(java.lang.Throwable, java.lang.String)game.C_100170_cm
		// @9D: athrow
		// @9E: return
	}
	
	public final void func_102769_a(int arg0, int arg1, int arg2, C_100083_c arg3)
	{
		// @00: getstatic int game.SteelSentinels.field_105275_O
		// @03: istore #6
		// @05: iload_3
		// @06: iconst_m1
		// @07: if_icmpeq @0B
		// @0A: return
		// @0B: iload_1
		// @0C: ifne @23
		// @0F: getstatic java.lang.String[] game.C_100093_fd.field_102787_Y
		// @12: bipush 8 (0x08)
		// @14: aaload
		// @15: bipush -81 (0xAF)
		// @17: invokestatic game.C_100101_fc.func_103392_a(java.lang.String, int)void
		// @1A: iload #6
		// @1C: ifeq @5B
		// @1F: goto @23
		// @22: athrow
		// @23: iload_1
		// @24: iconst_1
		// @25: if_icmpeq @4C
		// @28: goto @2C
		// @2B: athrow
		// @2C: bipush -3 (0xFD)
		// @2E: iload_1
		// @2F: iconst_m1
		// @30: ixor
		// @31: if_icmpeq @3C
		// @34: goto @38
		// @37: athrow
		// @38: goto @5B
		// @3B: athrow
		// @3C: getstatic java.lang.String[] game.C_100093_fd.field_102787_Y
		// @3F: bipush 10 (0x0A)
		// @41: aaload
		// @42: bipush -73 (0xB7)
		// @44: invokestatic game.C_100101_fc.func_103392_a(java.lang.String, int)void
		// @47: iload #6
		// @49: ifeq @5B
		// @4C: getstatic java.lang.String[] game.C_100093_fd.field_102787_Y
		// @4F: bipush 7 (0x07)
		// @51: aaload
		// @52: bipush -70 (0xBA)
		// @54: invokestatic game.C_100101_fc.func_103392_a(java.lang.String, int)void
		// @57: goto @5B
		// @5A: athrow
		// @5B: goto @AF
		// @5E: astore #5
		// @60: aload #5
		// @62: new java.lang.StringBuilder
		// @65: dup
		// @66: invokespecial java.lang.StringBuilder.<init>()void
		// @69: getstatic java.lang.String[] game.C_100093_fd.field_102787_Y
		// @6C: bipush 9 (0x09)
		// @6E: aaload
		// @6F: invokevirtual java.lang.StringBuilder.append(java.lang.String)java.lang.StringBuilder
		// @72: iload_1
		// @73: invokevirtual java.lang.StringBuilder.append(int)java.lang.StringBuilder
		// @76: bipush 44 (0x2C)
		// @78: invokevirtual java.lang.StringBuilder.append(char)java.lang.StringBuilder
		// @7B: iload_2
		// @7C: invokevirtual java.lang.StringBuilder.append(int)java.lang.StringBuilder
		// @7F: bipush 44 (0x2C)
		// @81: invokevirtual java.lang.StringBuilder.append(char)java.lang.StringBuilder
		// @84: iload_3
		// @85: invokevirtual java.lang.StringBuilder.append(int)java.lang.StringBuilder
		// @88: bipush 44 (0x2C)
		// @8A: invokevirtual java.lang.StringBuilder.append(char)java.lang.StringBuilder
		// @8D: aload #4
		// @8F: ifnull @9B
		// @92: getstatic java.lang.String[] game.C_100093_fd.field_102787_Y
		// @95: iconst_1
		// @96: aaload
		// @97: goto @A0
		// @9A: athrow
		// @9B: getstatic java.lang.String[] game.C_100093_fd.field_102787_Y
		// @9E: iconst_3
		// @9F: aaload
		// @A0: invokevirtual java.lang.StringBuilder.append(java.lang.String)java.lang.StringBuilder
		// @A3: bipush 41 (0x29)
		// @A5: invokevirtual java.lang.StringBuilder.append(char)java.lang.StringBuilder
		// @A8: invokevirtual java.lang.StringBuilder.toString()java.lang.String
		// @AB: invokestatic game.C_100181_cf.func_105695_a(java.lang.Throwable, java.lang.String)game.C_100170_cm
		// @AE: athrow
		// @AF: return
	}
	
	final boolean func_102506_a(char arg0, int arg1, int arg2, C_100336_im arg3)
	{
		// @00: aload_0
		// @01: iload_1
		// @02: iload_2
		// @03: iload_3
		// @04: aload #4
		// @06: invokespecial game.C_100085_a.func_102506_a(char, int, int, game.C_100336_im)boolean
		// @09: ifeq @0E
		// @0C: iconst_1
		// @0D: ireturn
		// @0E: iload_2
		// @0F: bipush 98 (0x62)
		// @11: if_icmpne @1D
		// @14: aload_0
		// @15: aload #4
		// @17: bipush 122 (0x7A)
		// @19: invokevirtual game.C_100093_fd.func_102555_a(game.C_100336_im, int)boolean
		// @1C: ireturn
		// @1D: bipush 99 (0x63)
		// @1F: iload_2
		// @20: if_icmpeq @27
		// @23: goto @32
		// @26: athrow
		// @27: aload_0
		// @28: iload_3
		// @29: ldc -40088 (0xffff6368)
		// @2B: iadd
		// @2C: aload #4
		// @2E: invokevirtual game.C_100093_fd.func_102558_b(int, game.C_100336_im)boolean
		// @31: ireturn
		// @32: iconst_0
		// @33: ireturn
		// @34: astore #5
		// @36: aload #5
		// @38: new java.lang.StringBuilder
		// @3B: dup
		// @3C: invokespecial java.lang.StringBuilder.<init>()void
		// @3F: getstatic java.lang.String[] game.C_100093_fd.field_102787_Y
		// @42: bipush 17 (0x11)
		// @44: aaload
		// @45: invokevirtual java.lang.StringBuilder.append(java.lang.String)java.lang.StringBuilder
		// @48: iload_1
		// @49: invokevirtual java.lang.StringBuilder.append(char)java.lang.StringBuilder
		// @4C: bipush 44 (0x2C)
		// @4E: invokevirtual java.lang.StringBuilder.append(char)java.lang.StringBuilder
		// @51: iload_2
		// @52: invokevirtual java.lang.StringBuilder.append(int)java.lang.StringBuilder
		// @55: bipush 44 (0x2C)
		// @57: invokevirtual java.lang.StringBuilder.append(char)java.lang.StringBuilder
		// @5A: iload_3
		// @5B: invokevirtual java.lang.StringBuilder.append(int)java.lang.StringBuilder
		// @5E: bipush 44 (0x2C)
		// @60: invokevirtual java.lang.StringBuilder.append(char)java.lang.StringBuilder
		// @63: aload #4
		// @65: ifnull @71
		// @68: getstatic java.lang.String[] game.C_100093_fd.field_102787_Y
		// @6B: iconst_1
		// @6C: aaload
		// @6D: goto @76
		// @70: athrow
		// @71: getstatic java.lang.String[] game.C_100093_fd.field_102787_Y
		// @74: iconst_3
		// @75: aaload
		// @76: invokevirtual java.lang.StringBuilder.append(java.lang.String)java.lang.StringBuilder
		// @79: bipush 41 (0x29)
		// @7B: invokevirtual java.lang.StringBuilder.append(char)java.lang.StringBuilder
		// @7E: invokevirtual java.lang.StringBuilder.toString()java.lang.String
		// @81: invokestatic game.C_100181_cf.func_105695_a(java.lang.Throwable, java.lang.String)game.C_100170_cm
		// @84: athrow
	}
	
	C_100093_fd(C_100342_jg arg0)
	{
		// @000: aload_0
		// @001: iconst_0
		// @002: iconst_0
		// @003: sipush 288 (0x0120)
		// @006: iconst_0
		// @007: aconst_null
		// @008: invokespecial game.C_100085_a.<init>(int, int, int, int, game.C_100326_ic)void
		// @00B: aload_0
		// @00C: aload_1
		// @00D: putfield game.C_100342_jg game.C_100093_fd.field_102788_X
		// @010: aload_0
		// @011: new game.C_100218_am
		// @014: dup
		// @015: getstatic java.lang.String game.C_100272_mn.field_102429_M
		// @018: aconst_null
		// @019: invokespecial game.C_100218_am.<init>(java.lang.String, game.C_100337_in)void
		// @01C: putfield game.C_100218_am game.C_100093_fd.field_102780_T
		// @01F: aload_0
		// @020: getfield game.C_100218_am game.C_100093_fd.field_102780_T
		// @023: new game.C_100310_lj
		// @026: dup
		// @027: invokespecial game.C_100310_lj.<init>()void
		// @02A: putfield game.C_100326_ic game.C_100218_am.field_102533_B
		// @02D: sipush -30945 (0x871F)
		// @030: iconst_2
		// @031: anewarray java.lang.String
		// @034: dup
		// @035: iconst_0
		// @036: aload_0
		// @037: bipush -102 (0x9A)
		// @039: invokespecial game.C_100093_fd.func_102777_g(byte)java.lang.String
		// @03C: aastore
		// @03D: dup
		// @03E: iconst_1
		// @03F: aload_0
		// @040: bipush -85 (0xAB)
		// @042: invokespecial game.C_100093_fd.func_102771_f(byte)java.lang.String
		// @045: aastore
		// @046: getstatic java.lang.String game.C_100054_ec.field_101956_Yb
		// @049: invokestatic game.C_100132_td.func_104965_a(int, java.lang.String[], java.lang.String)java.lang.String
		// @04C: astore_2
		// @04D: bipush 20 (0x14)
		// @04F: istore_3
		// @050: new game.C_100256_pk
		// @053: dup
		// @054: getstatic game.C_100112_r game.C_100230_of.field_106205_g
		// @057: iconst_0
		// @058: iconst_0
		// @059: iconst_0
		// @05A: iconst_0
		// @05B: ldc 16777215 (0xffffff)
		// @05D: iconst_m1
		// @05E: iconst_3
		// @05F: iconst_0
		// @060: getstatic game.C_100112_r game.C_100230_of.field_106205_g
		// @063: getfield int game.C_100112_r.field_101772_Q
		// @066: iconst_m1
		// @067: ldc 2147483647 (0x7fffffff)
		// @069: iconst_1
		// @06A: invokespecial game.C_100256_pk.<init>(game.C_100112_r, int, int, int, int, int, int, int, int, int, int, int, boolean)void
		// @06D: astore #4
		// @06F: aload_0
		// @070: new game.C_100083_c
		// @073: dup
		// @074: aload_2
		// @075: aload #4
		// @077: invokespecial game.C_100083_c.<init>(java.lang.String, game.C_100326_ic)void
		// @07A: putfield game.C_100083_c game.C_100093_fd.field_102783_Q
		// @07D: aload_0
		// @07E: getfield game.C_100083_c game.C_100093_fd.field_102783_Q
		// @081: ldc ""
		// @083: putfield java.lang.String game.C_100083_c.field_102536_o
		// @086: aload_0
		// @087: getfield game.C_100083_c game.C_100093_fd.field_102783_Q
		// @08A: getstatic java.lang.String game.C_100245_pf.field_106394_h
		// @08D: bipush 37 (0x25)
		// @08F: iconst_0
		// @090: invokevirtual game.C_100083_c.func_103158_a(java.lang.String, int, int)void
		// @093: aload_0
		// @094: getfield game.C_100083_c game.C_100093_fd.field_102783_Q
		// @097: getstatic java.lang.String game.C_100245_pf.field_106394_h
		// @09A: bipush 89 (0x59)
		// @09C: iconst_1
		// @09D: invokevirtual game.C_100083_c.func_103158_a(java.lang.String, int, int)void
		// @0A0: aload_0
		// @0A1: getfield game.C_100083_c game.C_100093_fd.field_102783_Q
		// @0A4: aload_0
		// @0A5: getfield int game.C_100093_fd.field_102537_l
		// @0A8: bipush 40 (0x28)
		// @0AA: isub
		// @0AB: putfield int game.C_100083_c.field_102537_l
		// @0AE: aload_0
		// @0AF: getfield game.C_100083_c game.C_100093_fd.field_102783_Q
		// @0B2: aload_0
		// @0B3: putfield game.C_100337_in game.C_100083_c.field_102543_u
		// @0B6: aload_0
		// @0B7: getfield game.C_100083_c game.C_100093_fd.field_102783_Q
		// @0BA: aload_0
		// @0BB: getfield int game.C_100093_fd.field_102537_l
		// @0BE: bipush -40 (0xD8)
		// @0C0: iadd
		// @0C1: bipush 26 (0x1A)
		// @0C3: iload_3
		// @0C4: iconst_m1
		// @0C5: invokevirtual game.C_100083_c.func_103157_b(int, int, int, int)void
		// @0C8: iload_3
		// @0C9: bipush 15 (0x0F)
		// @0CB: aload_0
		// @0CC: getfield game.C_100083_c game.C_100093_fd.field_102783_Q
		// @0CF: getfield int game.C_100083_c.field_102544_t
		// @0D2: iadd
		// @0D3: iadd
		// @0D4: istore_3
		// @0D5: aload_0
		// @0D6: aload_0
		// @0D7: getfield game.C_100083_c game.C_100093_fd.field_102783_Q
		// @0DA: iconst_1
		// @0DB: invokevirtual game.C_100093_fd.func_102561_b(game.C_100336_im, int)void
		// @0DE: iconst_4
		// @0DF: istore #5
		// @0E1: sipush 200 (0x00C8)
		// @0E4: istore #6
		// @0E6: aload_0
		// @0E7: getfield game.C_100218_am game.C_100093_fd.field_102780_T
		// @0EA: bipush 40 (0x28)
		// @0EC: iload_3
		// @0ED: iload #6
		// @0EF: ineg
		// @0F0: sipush 300 (0x012C)
		// @0F3: iadd
		// @0F4: ldc -391467167 (0xe8aaaf61)
		// @0F6: ishr
		// @0F7: iload #6
		// @0F9: bipush -125 (0x83)
		// @0FB: invokevirtual game.C_100218_am.func_102524_a(int, int, int, int, byte)void
		// @0FE: aload_0
		// @0FF: getfield game.C_100218_am game.C_100093_fd.field_102780_T
		// @102: aload_0
		// @103: putfield game.C_100337_in game.C_100218_am.field_102543_u
		// @106: aload_0
		// @107: aload_0
		// @108: getfield game.C_100218_am game.C_100093_fd.field_102780_T
		// @10B: iconst_1
		// @10C: invokevirtual game.C_100093_fd.func_102561_b(game.C_100336_im, int)void
		// @10F: aload_0
		// @110: iload_3
		// @111: bipush -55 (0xC9)
		// @113: isub
		// @114: iload #5
		// @116: iadd
		// @117: iconst_0
		// @118: iconst_0
		// @119: sipush 300 (0x012C)
		// @11C: bipush -80 (0xB0)
		// @11E: invokevirtual game.C_100093_fd.func_102524_a(int, int, int, int, byte)void
		// @121: goto @156
		// @124: astore_2
		// @125: aload_2
		// @126: new java.lang.StringBuilder
		// @129: dup
		// @12A: invokespecial java.lang.StringBuilder.<init>()void
		// @12D: getstatic java.lang.String[] game.C_100093_fd.field_102787_Y
		// @130: iconst_4
		// @131: aaload
		// @132: invokevirtual java.lang.StringBuilder.append(java.lang.String)java.lang.StringBuilder
		// @135: aload_1
		// @136: ifnull @142
		// @139: getstatic java.lang.String[] game.C_100093_fd.field_102787_Y
		// @13C: iconst_1
		// @13D: aaload
		// @13E: goto @147
		// @141: athrow
		// @142: getstatic java.lang.String[] game.C_100093_fd.field_102787_Y
		// @145: iconst_3
		// @146: aaload
		// @147: invokevirtual java.lang.StringBuilder.append(java.lang.String)java.lang.StringBuilder
		// @14A: bipush 41 (0x29)
		// @14C: invokevirtual java.lang.StringBuilder.append(char)java.lang.StringBuilder
		// @14F: invokevirtual java.lang.StringBuilder.toString()java.lang.String
		// @152: invokestatic game.C_100181_cf.func_105695_a(java.lang.Throwable, java.lang.String)game.C_100170_cm
		// @155: athrow
		// @156: return
	}
	
	static final void func_102775_a(boolean arg0, String arg1, float arg2, int arg3)
	{
		// @00: getstatic game.C_100129_tg game.C_100061_dh.field_101992_mc
		// @03: ifnonnull @26
		// @06: new game.C_100129_tg
		// @09: dup
		// @0A: getstatic game.C_100029_gn game.C_100085_a.field_102576_K
		// @0D: getstatic java.lang.String game.C_100069_vb.field_104358_b
		// @10: invokespecial game.C_100129_tg.<init>(game.C_100029_gn, java.lang.String)void
		// @13: putstatic game.C_100129_tg game.C_100061_dh.field_101992_mc
		// @16: getstatic game.C_100029_gn game.C_100085_a.field_102576_K
		// @19: getstatic game.C_100129_tg game.C_100061_dh.field_101992_mc
		// @1C: sipush 2839 (0x0B17)
		// @1F: invokevirtual game.C_100029_gn.func_103359_a(game.C_100336_im, int)void
		// @22: goto @26
		// @25: athrow
		// @26: getstatic game.C_100129_tg game.C_100061_dh.field_101992_mc
		// @29: aload_1
		// @2A: sipush 150 (0x0096)
		// @2D: fload_2
		// @2E: iload_0
		// @2F: invokevirtual game.C_100129_tg.func_102735_a(java.lang.String, int, float, boolean)void
		// @32: invokestatic game.C_100196_rb.func_105792_b()void
		// @35: iload_3
		// @36: bipush -62 (0xC2)
		// @38: if_icmple @3C
		// @3B: return
		// @3C: iconst_0
		// @3D: iconst_1
		// @3E: invokestatic game.C_100226_ae.func_106145_a(int, boolean)void
		// @41: goto @94
		// @44: astore #4
		// @46: aload #4
		// @48: new java.lang.StringBuilder
		// @4B: dup
		// @4C: invokespecial java.lang.StringBuilder.<init>()void
		// @4F: getstatic java.lang.String[] game.C_100093_fd.field_102787_Y
		// @52: bipush 11 (0x0B)
		// @54: aaload
		// @55: invokevirtual java.lang.StringBuilder.append(java.lang.String)java.lang.StringBuilder
		// @58: iload_0
		// @59: invokevirtual java.lang.StringBuilder.append(boolean)java.lang.StringBuilder
		// @5C: bipush 44 (0x2C)
		// @5E: invokevirtual java.lang.StringBuilder.append(char)java.lang.StringBuilder
		// @61: aload_1
		// @62: ifnull @6E
		// @65: getstatic java.lang.String[] game.C_100093_fd.field_102787_Y
		// @68: iconst_1
		// @69: aaload
		// @6A: goto @73
		// @6D: athrow
		// @6E: getstatic java.lang.String[] game.C_100093_fd.field_102787_Y
		// @71: iconst_3
		// @72: aaload
		// @73: invokevirtual java.lang.StringBuilder.append(java.lang.String)java.lang.StringBuilder
		// @76: bipush 44 (0x2C)
		// @78: invokevirtual java.lang.StringBuilder.append(char)java.lang.StringBuilder
		// @7B: fload_2
		// @7C: invokevirtual java.lang.StringBuilder.append(float)java.lang.StringBuilder
		// @7F: bipush 44 (0x2C)
		// @81: invokevirtual java.lang.StringBuilder.append(char)java.lang.StringBuilder
		// @84: iload_3
		// @85: invokevirtual java.lang.StringBuilder.append(int)java.lang.StringBuilder
		// @88: bipush 41 (0x29)
		// @8A: invokevirtual java.lang.StringBuilder.append(char)java.lang.StringBuilder
		// @8D: invokevirtual java.lang.StringBuilder.toString()java.lang.String
		// @90: invokestatic game.C_100181_cf.func_105695_a(java.lang.Throwable, java.lang.String)game.C_100170_cm
		// @93: athrow
		// @94: return
	}
	
	public static void func_102773_a(byte arg0)
	{
		// @00: aconst_null
		// @01: putstatic game.C_100197_ra game.C_100093_fd.field_102782_V
		// @04: aconst_null
		// @05: putstatic java.lang.String game.C_100093_fd.field_102786_R
		// @08: aconst_null
		// @09: putstatic int[] game.C_100093_fd.field_102784_P
		// @0C: bipush -89 (0xA7)
		// @0E: iload_0
		// @0F: bipush 20 (0x14)
		// @11: isub
		// @12: bipush 32 (0x20)
		// @14: idiv
		// @15: irem
		// @16: istore_1
		// @17: aconst_null
		// @18: putstatic int[] game.C_100093_fd.field_102781_W
		// @1B: aconst_null
		// @1C: putstatic java.lang.String game.C_100093_fd.field_102779_U
		// @1F: goto @43
		// @22: astore_1
		// @23: aload_1
		// @24: new java.lang.StringBuilder
		// @27: dup
		// @28: invokespecial java.lang.StringBuilder.<init>()void
		// @2B: getstatic java.lang.String[] game.C_100093_fd.field_102787_Y
		// @2E: iconst_0
		// @2F: aaload
		// @30: invokevirtual java.lang.StringBuilder.append(java.lang.String)java.lang.StringBuilder
		// @33: iload_0
		// @34: invokevirtual java.lang.StringBuilder.append(int)java.lang.StringBuilder
		// @37: bipush 41 (0x29)
		// @39: invokevirtual java.lang.StringBuilder.append(char)java.lang.StringBuilder
		// @3C: invokevirtual java.lang.StringBuilder.toString()java.lang.String
		// @3F: invokestatic game.C_100181_cf.func_105695_a(java.lang.Throwable, java.lang.String)game.C_100170_cm
		// @42: athrow
		// @43: return
	}
	
	private final String func_102777_g(byte arg0)
	{
		// @00: iload_1
		// @01: bipush -98 (0x9E)
		// @03: if_icmplt @0B
		// @06: aconst_null
		// @07: checkcast java.lang.String
		// @0A: areturn
		// @0B: getstatic java.lang.String[] game.C_100093_fd.field_102787_Y
		// @0E: bipush 6 (0x06)
		// @10: aaload
		// @11: areturn
		// @12: astore_2
		// @13: aload_2
		// @14: new java.lang.StringBuilder
		// @17: dup
		// @18: invokespecial java.lang.StringBuilder.<init>()void
		// @1B: getstatic java.lang.String[] game.C_100093_fd.field_102787_Y
		// @1E: iconst_5
		// @1F: aaload
		// @20: invokevirtual java.lang.StringBuilder.append(java.lang.String)java.lang.StringBuilder
		// @23: iload_1
		// @24: invokevirtual java.lang.StringBuilder.append(int)java.lang.StringBuilder
		// @27: bipush 41 (0x29)
		// @29: invokevirtual java.lang.StringBuilder.append(char)java.lang.StringBuilder
		// @2C: invokevirtual java.lang.StringBuilder.toString()java.lang.String
		// @2F: invokestatic game.C_100181_cf.func_105695_a(java.lang.Throwable, java.lang.String)game.C_100170_cm
		// @32: athrow
	}
	
	static final boolean func_102776_k(int arg0)
	{
		// @000: getstatic int game.SteelSentinels.field_105275_O
		// @003: istore #15
		// @005: iconst_0
		// @006: istore_1
		// @007: iconst_0
		// @008: istore_2
		// @009: iload_0
		// @00A: sipush -17910 (0xBA0A)
		// @00D: if_icmpeq @012
		// @010: iconst_0
		// @011: ireturn
		// @012: sipush 640 (0x0280)
		// @015: iload_2
		// @016: if_icmple @25A
		// @019: iload_2
		// @01A: sipush -320 (0xFEC0)
		// @01D: iadd
		// @01E: i2d
		// @01F: sipush -320 (0xFEC0)
		// @022: iload_2
		// @023: iadd
		// @024: i2d
		// @025: ldc2_w 2.34375E-4
		// @028: dmul
		// @029: dmul
		// @02A: ldc2_w 374.0
		// @02D: dadd
		// @02E: dstore_3
		// @02F: dload_3
		// @030: invokestatic java.lang.Math.ceil(double)double
		// @033: d2i
		// @034: istore #5
		// @036: getstatic int game.C_100015_wh.field_103781_g
		// @039: iconst_m1
		// @03A: ixor
		// @03B: iload #15
		// @03D: ifne @25B
		// @040: iload_2
		// @041: iconst_m1
		// @042: ixor
		// @043: if_icmpne @05C
		// @046: goto @04A
		// @049: athrow
		// @04A: getstatic int game.C_100338_jc.field_105370_l
		// @04D: iconst_m1
		// @04E: ixor
		// @04F: iload #5
		// @051: iconst_m1
		// @052: ixor
		// @053: if_icmpgt @05C
		// @056: goto @05A
		// @059: athrow
		// @05A: iconst_1
		// @05B: istore_1
		// @05C: iload #5
		// @05E: bipush 113 (0x71)
		// @060: bipush 48 (0x30)
		// @062: sipush 480 (0x01E0)
		// @065: iload_2
		// @066: iconst_0
		// @067: invokestatic game.C_100244_pe.func_106371_a(int, int, int, int, int, int)void
		// @06A: iload #5
		// @06C: iconst_1
		// @06D: isub
		// @06E: istore #6
		// @070: iconst_1
		// @071: iload #5
		// @073: iadd
		// @074: istore #7
		// @076: iload #5
		// @078: i2d
		// @079: dload_3
		// @07A: dsub
		// @07B: ldc2_w 256.0
		// @07E: dmul
		// @07F: d2i
		// @080: istore #8
		// @082: sipush 200 (0x00C8)
		// @085: istore #9
		// @087: iconst_m1
		// @088: iload #6
		// @08A: iadd
		// @08B: istore #5
		// @08D: iload #6
		// @08F: bipush -20 (0xEC)
		// @091: iadd
		// @092: iload #5
		// @094: if_icmpge @12D
		// @097: iload_2
		// @098: getstatic int game.C_100196_rb.field_105819_e
		// @09B: iload #5
		// @09D: imul
		// @09E: iadd
		// @09F: istore #10
		// @0A1: getstatic int[] game.C_100196_rb.field_105818_d
		// @0A4: iload #10
		// @0A6: iaload
		// @0A7: ldc 259829872 (0xf7cb070)
		// @0A9: ishr
		// @0AA: sipush 255 (0x00FF)
		// @0AD: iand
		// @0AE: istore #11
		// @0B0: ldc 65280 (0xff00)
		// @0B2: getstatic int[] game.C_100196_rb.field_105818_d
		// @0B5: iload #10
		// @0B7: iaload
		// @0B8: iand
		// @0B9: ldc 986034376 (0x3ac5b0c8)
		// @0BB: ishr
		// @0BC: istore #12
		// @0BE: iload #12
		// @0C0: iload #9
		// @0C2: ineg
		// @0C3: sipush 256 (0x0100)
		// @0C6: iadd
		// @0C7: imul
		// @0C8: sipush 256 (0x0100)
		// @0CB: idiv
		// @0CC: istore #12
		// @0CE: iload #9
		// @0D0: ineg
		// @0D1: sipush 256 (0x0100)
		// @0D4: iadd
		// @0D5: iload #11
		// @0D7: imul
		// @0D8: sipush 256 (0x0100)
		// @0DB: idiv
		// @0DC: istore #11
		// @0DE: sipush 255 (0x00FF)
		// @0E1: getstatic int[] game.C_100196_rb.field_105818_d
		// @0E4: iload #10
		// @0E6: iaload
		// @0E7: iand
		// @0E8: istore #13
		// @0EA: iload #13
		// @0EC: iload #9
		// @0EE: ineg
		// @0EF: sipush 256 (0x0100)
		// @0F2: iadd
		// @0F3: imul
		// @0F4: sipush 256 (0x0100)
		// @0F7: idiv
		// @0F8: istore #13
		// @0FA: bipush 6 (0x06)
		// @0FC: iload #9
		// @0FE: imul
		// @0FF: bipush 7 (0x07)
		// @101: idiv
		// @102: istore #9
		// @104: getstatic int[] game.C_100196_rb.field_105818_d
		// @107: iload #10
		// @109: iload #13
		// @10B: iload #11
		// @10D: ldc -922117744 (0xc9099990)
		// @10F: ishl
		// @110: iload #12
		// @112: ldc 145126984 (0x8a67648)
		// @114: ishl
		// @115: invokestatic game.C_100116_ei.func_104117_a(int, int)int
		// @118: invokestatic game.C_100116_ei.func_104117_a(int, int)int
		// @11B: iastore
		// @11C: iinc #5 +255
		// @11F: iload #15
		// @121: ifne @13B
		// @124: iload #15
		// @126: ifeq @08D
		// @129: goto @12D
		// @12C: athrow
		// @12D: iload_2
		// @12E: iload #6
		// @130: iload #7
		// @132: iload #6
		// @134: ineg
		// @135: iadd
		// @136: ldc 4210752 (0x404040)
		// @138: invokestatic game.C_100196_rb.func_105778_a(int, int, int, int)void
		// @13B: iconst_0
		// @13C: iload #8
		// @13E: if_icmpgt @252
		// @141: iload_2
		// @142: getstatic int game.C_100196_rb.field_105819_e
		// @145: iconst_m1
		// @146: iload #6
		// @148: iadd
		// @149: imul
		// @14A: iadd
		// @14B: istore #10
		// @14D: getstatic int[] game.C_100196_rb.field_105818_d
		// @150: iload #10
		// @152: iaload
		// @153: ldc 16711680 (0xff0000)
		// @155: iand
		// @156: ldc 846092976 (0x326e5ab0)
		// @158: ishr
		// @159: istore #11
		// @15B: getstatic int[] game.C_100196_rb.field_105818_d
		// @15E: iload #10
		// @160: iaload
		// @161: ldc -1287557624 (0xb3416e08)
		// @163: ishr
		// @164: sipush 255 (0x00FF)
		// @167: iand
		// @168: istore #12
		// @16A: getstatic int[] game.C_100196_rb.field_105818_d
		// @16D: iload #10
		// @16F: iaload
		// @170: sipush 255 (0x00FF)
		// @173: iand
		// @174: istore #13
		// @176: bipush 64 (0x40)
		// @178: iload #8
		// @17A: imul
		// @17B: istore #14
		// @17D: iload #11
		// @17F: sipush 256 (0x0100)
		// @182: iload #8
		// @184: isub
		// @185: imul
		// @186: iload #14
		// @188: ineg
		// @189: isub
		// @18A: sipush 256 (0x0100)
		// @18D: idiv
		// @18E: istore #11
		// @190: iload #13
		// @192: sipush 256 (0x0100)
		// @195: iload #8
		// @197: ineg
		// @198: iadd
		// @199: imul
		// @19A: iload #14
		// @19C: iadd
		// @19D: sipush 256 (0x0100)
		// @1A0: idiv
		// @1A1: istore #13
		// @1A3: iload #12
		// @1A5: iload #8
		// @1A7: ineg
		// @1A8: sipush 256 (0x0100)
		// @1AB: iadd
		// @1AC: imul
		// @1AD: iload #14
		// @1AF: ineg
		// @1B0: isub
		// @1B1: sipush 256 (0x0100)
		// @1B4: idiv
		// @1B5: istore #12
		// @1B7: getstatic int[] game.C_100196_rb.field_105818_d
		// @1BA: iload #10
		// @1BC: iload #13
		// @1BE: iload #11
		// @1C0: ldc 2027703376 (0x78dc4c50)
		// @1C2: ishl
		// @1C3: iload #12
		// @1C5: ldc 1494006216 (0x590cb9c8)
		// @1C7: ishl
		// @1C8: invokestatic game.C_100116_ei.func_104117_a(int, int)int
		// @1CB: invokestatic game.C_100116_ei.func_104117_a(int, int)int
		// @1CE: iastore
		// @1CF: iload_2
		// @1D0: getstatic int game.C_100196_rb.field_105819_e
		// @1D3: iload #7
		// @1D5: imul
		// @1D6: iadd
		// @1D7: istore #10
		// @1D9: sipush 255 (0x00FF)
		// @1DC: getstatic int[] game.C_100196_rb.field_105818_d
		// @1DF: iload #10
		// @1E1: iaload
		// @1E2: iand
		// @1E3: istore #13
		// @1E5: sipush 255 (0x00FF)
		// @1E8: getstatic int[] game.C_100196_rb.field_105818_d
		// @1EB: iload #10
		// @1ED: iaload
		// @1EE: ldc -1316976568 (0xb1808848)
		// @1F0: ishr
		// @1F1: iand
		// @1F2: istore #12
		// @1F4: bipush 64 (0x40)
		// @1F6: iload #8
		// @1F8: imul
		// @1F9: ineg
		// @1FA: sipush 16384 (0x4000)
		// @1FD: iadd
		// @1FE: istore #14
		// @200: sipush 255 (0x00FF)
		// @203: getstatic int[] game.C_100196_rb.field_105818_d
		// @206: iload #10
		// @208: iaload
		// @209: ldc 396015024 (0x179ab5b0)
		// @20B: ishr
		// @20C: iand
		// @20D: istore #11
		// @20F: iload #14
		// @211: iload #8
		// @213: iload #11
		// @215: imul
		// @216: iadd
		// @217: sipush 256 (0x0100)
		// @21A: idiv
		// @21B: istore #11
		// @21D: iload #14
		// @21F: iload #8
		// @221: iload #13
		// @223: imul
		// @224: iadd
		// @225: sipush 256 (0x0100)
		// @228: idiv
		// @229: istore #13
		// @22B: iload #12
		// @22D: iload #8
		// @22F: imul
		// @230: iload #14
		// @232: ineg
		// @233: isub
		// @234: sipush 256 (0x0100)
		// @237: idiv
		// @238: istore #12
		// @23A: getstatic int[] game.C_100196_rb.field_105818_d
		// @23D: iload #10
		// @23F: iload #13
		// @241: iload #12
		// @243: ldc -1146514104 (0xbba99548)
		// @245: ishl
		// @246: iload #11
		// @248: ldc -521702160 (0xe0e774f0)
		// @24A: ishl
		// @24B: invokestatic game.C_100116_ei.func_104117_a(int, int)int
		// @24E: invokestatic game.C_100116_ei.func_104117_a(int, int)int
		// @251: iastore
		// @252: iinc #2 +1
		// @255: iload #15
		// @257: ifeq @012
		// @25A: iload_1
		// @25B: ireturn
		// @25C: astore_1
		// @25D: aload_1
		// @25E: new java.lang.StringBuilder
		// @261: dup
		// @262: invokespecial java.lang.StringBuilder.<init>()void
		// @265: getstatic java.lang.String[] game.C_100093_fd.field_102787_Y
		// @268: bipush 12 (0x0C)
		// @26A: aaload
		// @26B: invokevirtual java.lang.StringBuilder.append(java.lang.String)java.lang.StringBuilder
		// @26E: iload_0
		// @26F: invokevirtual java.lang.StringBuilder.append(int)java.lang.StringBuilder
		// @272: bipush 41 (0x29)
		// @274: invokevirtual java.lang.StringBuilder.append(char)java.lang.StringBuilder
		// @277: invokevirtual java.lang.StringBuilder.toString()java.lang.String
		// @27A: invokestatic game.C_100181_cf.func_105695_a(java.lang.Throwable, java.lang.String)game.C_100170_cm
		// @27D: athrow
	}
	
	public final void func_102581_a(int arg0, int arg1, byte arg2, C_100218_am arg3, int arg4)
	{
		// @00: bipush -21 (0xEB)
		// @02: iload_3
		// @03: bipush -2 (0xFE)
		// @05: isub
		// @06: bipush 52 (0x34)
		// @08: idiv
		// @09: idiv
		// @0A: istore #6
		// @0C: aload_0
		// @0D: getfield game.C_100218_am game.C_100093_fd.field_102780_T
		// @10: aload #4
		// @12: if_acmpeq @19
		// @15: goto @27
		// @18: athrow
		// @19: bipush -36 (0xDC)
		// @1B: invokestatic game.C_100119_ua.func_104890_c(byte)void
		// @1E: aload_0
		// @1F: getfield game.C_100342_jg game.C_100093_fd.field_102788_X
		// @22: bipush -86 (0xAA)
		// @24: invokevirtual game.C_100342_jg.func_102701_r(int)void
		// @27: goto @84
		// @2A: astore #6
		// @2C: aload #6
		// @2E: new java.lang.StringBuilder
		// @31: dup
		// @32: invokespecial java.lang.StringBuilder.<init>()void
		// @35: getstatic java.lang.String[] game.C_100093_fd.field_102787_Y
		// @38: iconst_2
		// @39: aaload
		// @3A: invokevirtual java.lang.StringBuilder.append(java.lang.String)java.lang.StringBuilder
		// @3D: iload_1
		// @3E: invokevirtual java.lang.StringBuilder.append(int)java.lang.StringBuilder
		// @41: bipush 44 (0x2C)
		// @43: invokevirtual java.lang.StringBuilder.append(char)java.lang.StringBuilder
		// @46: iload_2
		// @47: invokevirtual java.lang.StringBuilder.append(int)java.lang.StringBuilder
		// @4A: bipush 44 (0x2C)
		// @4C: invokevirtual java.lang.StringBuilder.append(char)java.lang.StringBuilder
		// @4F: iload_3
		// @50: invokevirtual java.lang.StringBuilder.append(int)java.lang.StringBuilder
		// @53: bipush 44 (0x2C)
		// @55: invokevirtual java.lang.StringBuilder.append(char)java.lang.StringBuilder
		// @58: aload #4
		// @5A: ifnull @66
		// @5D: getstatic java.lang.String[] game.C_100093_fd.field_102787_Y
		// @60: iconst_1
		// @61: aaload
		// @62: goto @6B
		// @65: athrow
		// @66: getstatic java.lang.String[] game.C_100093_fd.field_102787_Y
		// @69: iconst_3
		// @6A: aaload
		// @6B: invokevirtual java.lang.StringBuilder.append(java.lang.String)java.lang.StringBuilder
		// @6E: bipush 44 (0x2C)
		// @70: invokevirtual java.lang.StringBuilder.append(char)java.lang.StringBuilder
		// @73: iload #5
		// @75: invokevirtual java.lang.StringBuilder.append(int)java.lang.StringBuilder
		// @78: bipush 41 (0x29)
		// @7A: invokevirtual java.lang.StringBuilder.append(char)java.lang.StringBuilder
		// @7D: invokevirtual java.lang.StringBuilder.toString()java.lang.String
		// @80: invokestatic game.C_100181_cf.func_105695_a(java.lang.Throwable, java.lang.String)game.C_100170_cm
		// @83: athrow
		// @84: return
	}
	
	static final void func_102770_a(boolean arg0, byte arg1, int arg2, int arg3)
	{
		// @00: iload_3
		// @01: getstatic int game.C_100245_pf.field_106389_c
		// @04: getstatic int game.C_100244_pe.field_106375_d
		// @07: iload_0
		// @08: bipush -94 (0xA2)
		// @0A: iload_2
		// @0B: getstatic int game.C_100033_gj.field_101917_jc
		// @0E: invokestatic game.C_100234_ob.func_106265_a(int, int, int, boolean, byte, int, int)void
		// @11: iload_1
		// @12: bipush 78 (0x4E)
		// @14: if_icmpge @23
		// @17: iconst_0
		// @18: aconst_null
		// @19: checkcast java.lang.String
		// @1C: ldc -1.5238264
		// @1E: bipush 9 (0x09)
		// @20: invokestatic game.C_100093_fd.func_102775_a(boolean, java.lang.String, float, int)void
		// @23: goto @65
		// @26: astore #4
		// @28: aload #4
		// @2A: new java.lang.StringBuilder
		// @2D: dup
		// @2E: invokespecial java.lang.StringBuilder.<init>()void
		// @31: getstatic java.lang.String[] game.C_100093_fd.field_102787_Y
		// @34: bipush 14 (0x0E)
		// @36: aaload
		// @37: invokevirtual java.lang.StringBuilder.append(java.lang.String)java.lang.StringBuilder
		// @3A: iload_0
		// @3B: invokevirtual java.lang.StringBuilder.append(boolean)java.lang.StringBuilder
		// @3E: bipush 44 (0x2C)
		// @40: invokevirtual java.lang.StringBuilder.append(char)java.lang.StringBuilder
		// @43: iload_1
		// @44: invokevirtual java.lang.StringBuilder.append(int)java.lang.StringBuilder
		// @47: bipush 44 (0x2C)
		// @49: invokevirtual java.lang.StringBuilder.append(char)java.lang.StringBuilder
		// @4C: iload_2
		// @4D: invokevirtual java.lang.StringBuilder.append(int)java.lang.StringBuilder
		// @50: bipush 44 (0x2C)
		// @52: invokevirtual java.lang.StringBuilder.append(char)java.lang.StringBuilder
		// @55: iload_3
		// @56: invokevirtual java.lang.StringBuilder.append(int)java.lang.StringBuilder
		// @59: bipush 41 (0x29)
		// @5B: invokevirtual java.lang.StringBuilder.append(char)java.lang.StringBuilder
		// @5E: invokevirtual java.lang.StringBuilder.toString()java.lang.String
		// @61: invokestatic game.C_100181_cf.func_105695_a(java.lang.Throwable, java.lang.String)game.C_100170_cm
		// @64: athrow
		// @65: return
	}
	
	private final String func_102771_f(byte arg0)
	{
		// @00: iload_1
		// @01: bipush -27 (0xE5)
		// @03: if_icmplt @12
		// @06: aload_0
		// @07: aconst_null
		// @08: checkcast game.C_100342_jg
		// @0B: putfield game.C_100342_jg game.C_100093_fd.field_102788_X
		// @0E: goto @12
		// @11: athrow
		// @12: getstatic java.lang.String[] game.C_100093_fd.field_102787_Y
		// @15: bipush 15 (0x0F)
		// @17: aaload
		// @18: areturn
		// @19: astore_2
		// @1A: aload_2
		// @1B: new java.lang.StringBuilder
		// @1E: dup
		// @1F: invokespecial java.lang.StringBuilder.<init>()void
		// @22: getstatic java.lang.String[] game.C_100093_fd.field_102787_Y
		// @25: bipush 16 (0x10)
		// @27: aaload
		// @28: invokevirtual java.lang.StringBuilder.append(java.lang.String)java.lang.StringBuilder
		// @2B: iload_1
		// @2C: invokevirtual java.lang.StringBuilder.append(int)java.lang.StringBuilder
		// @2F: bipush 41 (0x29)
		// @31: invokevirtual java.lang.StringBuilder.append(char)java.lang.StringBuilder
		// @34: invokevirtual java.lang.StringBuilder.toString()java.lang.String
		// @37: invokestatic game.C_100181_cf.func_105695_a(java.lang.Throwable, java.lang.String)game.C_100170_cm
		// @3A: athrow
	}
	
	static
	{
		// @000: bipush 18 (0x12)
		// @002: anewarray java.lang.String
		// @005: dup
		// @006: iconst_0
		// @007: ldc "(r/*Jf"
		// @009: invokestatic game.C_100093_fd.func_102774_z(java.lang.String)char[]
		// @00C: invokestatic game.C_100093_fd.func_102772_z(char[])java.lang.String
		// @00F: aastore
		// @010: dup
		// @011: iconst_1
		// @012: ldc "58/Iv"
		// @014: invokestatic game.C_100093_fd.func_102774_z(java.lang.String)char[]
		// @017: invokestatic game.C_100093_fd.func_102772_z(char[])java.lang.String
		// @01A: aastore
		// @01B: dup
		// @01C: iconst_2
		// @01D: ldc "(r/-Jf"
		// @01F: invokestatic game.C_100093_fd.func_102774_z(java.lang.String)char[]
		// @022: invokestatic game.C_100093_fd.func_102772_z(char[])java.lang.String
		// @025: aastore
		// @026: dup
		// @027: iconst_3
		// @028: ldc " cm\u000b"
		// @02A: invokestatic game.C_100093_fd.func_102774_z(java.lang.String)char[]
		// @02D: invokestatic game.C_100093_fd.func_102772_z(char[])java.lang.String
		// @030: aastore
		// @031: dup
		// @032: iconst_4
		// @033: ldc "(r/[b \u007fuY#"
		// @035: invokestatic game.C_100093_fd.func_102774_z(java.lang.String)char[]
		// @038: invokestatic game.C_100093_fd.func_102772_z(char[])java.lang.String
		// @03B: aastore
		// @03C: dup
		// @03D: iconst_5
		// @03E: ldc "(r/7Jf"
		// @040: invokestatic game.C_100093_fd.func_102774_z(java.lang.String)char[]
		// @043: invokestatic game.C_100093_fd.func_102772_z(char[])java.lang.String
		// @046: aastore
		// @047: dup
		// @048: bipush 6 (0x06)
		// @04A: ldc "rc<U:x\"@U5run\u000b6|'7SJ|("
		// @04C: invokestatic game.C_100093_fd.func_102774_z(java.lang.String)char[]
		// @04F: invokestatic game.C_100093_fd.func_102772_z(char[])java.lang.String
		// @052: aastore
		// @053: dup
		// @054: bipush 7 (0x07)
		// @056: ldc ">dh\u0011j-o/\u0010x"
		// @058: invokestatic game.C_100093_fd.func_102774_z(java.lang.String)char[]
		// @05B: invokestatic game.C_100093_fd.func_102772_z(char[])java.lang.String
		// @05E: aastore
		// @05F: dup
		// @060: bipush 8 (0x08)
		// @062: ldc ":ss\nx`ar"
		// @064: invokestatic game.C_100093_fd.func_102774_z(java.lang.String)char[]
		// @067: invokestatic game.C_100093_fd.func_102772_z(char[])java.lang.String
		// @06A: aastore
		// @06B: dup
		// @06C: bipush 9 (0x09)
		// @06E: ldc "(r/)Jf"
		// @070: invokestatic game.C_100093_fd.func_102774_z(java.lang.String)char[]
		// @073: invokestatic game.C_100093_fd.func_102772_z(char[])java.lang.String
		// @076: aastore
		// @077: dup
		// @078: bipush 10 (0x0A)
		// @07A: ldc "-yo\u0003~-b/\u0010x"
		// @07C: invokestatic game.C_100093_fd.func_102774_z(java.lang.String)char[]
		// @07F: invokestatic game.C_100093_fd.func_102772_z(char[])java.lang.String
		// @082: aastore
		// @083: dup
		// @084: bipush 11 (0x0B)
		// @086: ldc "(r/ Jf"
		// @088: invokestatic game.C_100093_fd.func_102774_z(java.lang.String)char[]
		// @08B: invokestatic game.C_100093_fd.func_102772_z(char[])java.lang.String
		// @08E: aastore
		// @08F: dup
		// @090: bipush 12 (0x0C)
		// @092: ldc "(r/(Jf"
		// @094: invokestatic game.C_100093_fd.func_102774_z(java.lang.String)char[]
		// @097: invokestatic game.C_100093_fd.func_102772_z(char[])java.lang.String
		// @09A: aastore
		// @09B: dup
		// @09C: bipush 13 (0x0D)
		// @09E: ldc "(r/,Jf"
		// @0A0: invokestatic game.C_100093_fd.func_102774_z(java.lang.String)char[]
		// @0A3: invokestatic game.C_100093_fd.func_102772_z(char[])java.lang.String
		// @0A6: aastore
		// @0A7: dup
		// @0A8: bipush 14 (0x0E)
		// @0AA: ldc "(r/.Jf"
		// @0AC: invokestatic game.C_100093_fd.func_102774_z(java.lang.String)char[]
		// @0AF: invokestatic game.C_100093_fd.func_102772_z(char[])java.lang.String
		// @0B2: aastore
		// @0B3: dup
		// @0B4: bipush 15 (0x0F)
		// @0B6: ldc "r9b\u0008gp*.\u00125"
		// @0B8: invokestatic game.C_100093_fd.func_102774_z(java.lang.String)char[]
		// @0BB: invokestatic game.C_100093_fd.func_102772_z(char[])java.lang.String
		// @0BE: aastore
		// @0BF: dup
		// @0C0: bipush 16 (0x10)
		// @0C2: ldc "(r//Jf"
		// @0C4: invokestatic game.C_100093_fd.func_102774_z(java.lang.String)char[]
		// @0C7: invokestatic game.C_100093_fd.func_102772_z(char[])java.lang.String
		// @0CA: aastore
		// @0CB: dup
		// @0CC: bipush 17 (0x11)
		// @0CE: ldc "(r/!Jf"
		// @0D0: invokestatic game.C_100093_fd.func_102774_z(java.lang.String)char[]
		// @0D3: invokestatic game.C_100093_fd.func_102772_z(char[])java.lang.String
		// @0D6: aastore
		// @0D7: putstatic java.lang.String[] game.C_100093_fd.field_102787_Y
		// @0DA: bipush 7 (0x07)
		// @0DC: newarray int[]
		// @0DE: dup
		// @0DF: iconst_0
		// @0E0: bipush 48 (0x30)
		// @0E2: iastore
		// @0E3: dup
		// @0E4: iconst_1
		// @0E5: sipush 272 (0x0110)
		// @0E8: iastore
		// @0E9: dup
		// @0EA: iconst_2
		// @0EB: sipush 340 (0x0154)
		// @0EE: iastore
		// @0EF: dup
		// @0F0: iconst_3
		// @0F1: sipush 400 (0x0190)
		// @0F4: iastore
		// @0F5: dup
		// @0F6: iconst_4
		// @0F7: sipush 456 (0x01C8)
		// @0FA: iastore
		// @0FB: dup
		// @0FC: iconst_5
		// @0FD: iconst_0
		// @0FE: iastore
		// @0FF: dup
		// @100: bipush 6 (0x06)
		// @102: sipush 591 (0x024F)
		// @105: iastore
		// @106: putstatic int[] game.C_100093_fd.field_102784_P
		// @109: sipush 16384 (0x4000)
		// @10C: newarray int[]
		// @10E: putstatic int[] game.C_100093_fd.field_102781_W
		// @111: ldc "A"
		// @113: putstatic java.lang.String game.C_100093_fd.field_102786_R
		// @116: return
	}
	
	private static char[] func_102774_z(String arg0)
	{
		// @00: aload_0
		// @01: invokevirtual java.lang.String.toCharArray()char[]
		// @04: dup
		// @05: arraylength
		// @06: iconst_2
		// @07: if_icmpge @13
		// @0A: dup
		// @0B: iconst_0
		// @0C: dup2
		// @0D: caload
		// @0E: bipush 11 (0x0B)
		// @10: ixor
		// @11: i2c
		// @12: castore
		// @13: areturn
	}
	
	private static String func_102772_z(char[] arg0)
	{
		// @00: aload_0
		// @01: dup
		// @02: arraylength
		// @03: swap
		// @04: iconst_0
		// @05: istore_1
		// @06: goto @4B
		// @09: dup
		// @0A: iload_1
		// @0B: dup2
		// @0C: caload
		// @0D: iload_1
		// @0E: iconst_5
		// @0F: irem
		// @10: tableswitch def: @43, for 0: @30, for 1: @35, for 2: @3A, for 3: @3E
		// @30: bipush 78 (0x4E)
		// @32: goto @45
		// @35: bipush 22 (0x16)
		// @37: goto @45
		// @3A: iconst_1
		// @3B: goto @45
		// @3E: bipush 103 (0x67)
		// @40: goto @45
		// @43: bipush 11 (0x0B)
		// @45: ixor
		// @46: i2c
		// @47: castore
		// @48: iinc #1 +1
		// @4B: swap
		// @4C: dup_x1
		// @4D: iload_1
		// @4E: if_icmpgt @09
		// @51: new java.lang.String
		// @54: dup_x1
		// @55: swap
		// @56: invokespecial java.lang.String.<init>(char[])void
		// @59: invokevirtual java.lang.String.intern()java.lang.String
		// @5C: areturn
	}
}
