package game;

import java.applet.Applet;

final class C_100253_ph extends C_100261_md
{
	private int field_101095_E;
	private C_100002_gf field_101111_p;
	private int field_101098_A;
	static String field_101109_r;
	private C_100210_qa field_101107_t;
	private boolean field_101102_o;
	static String field_101100_C;
	private int[] field_101094_D;
	static String field_101110_q;
	static String field_101097_G;
	static String field_101099_B;
	private int[] field_101101_n;
	private C_100210_qa field_101105_v;
	private C_100002_gf field_101112_z;
	static String field_101106_u;
	private C_100210_qa field_101113_y;
	private int field_101114_x;
	private int field_101103_H;
	private C_100002_gf field_101108_s;
	private boolean field_101104_w;
	private static final String[] field_101096_F;
	
	public static void func_101091_f(int arg0)
	{
		// @00: aconst_null
		// @01: putstatic java.lang.String game.C_100253_ph.field_101110_q
		// @04: aconst_null
		// @05: putstatic java.lang.String game.C_100253_ph.field_101106_u
		// @08: aconst_null
		// @09: putstatic java.lang.String game.C_100253_ph.field_101109_r
		// @0C: aconst_null
		// @0D: putstatic java.lang.String game.C_100253_ph.field_101097_G
		// @10: aconst_null
		// @11: putstatic java.lang.String game.C_100253_ph.field_101100_C
		// @14: aconst_null
		// @15: putstatic java.lang.String game.C_100253_ph.field_101099_B
		// @18: iload_0
		// @19: bipush -103 (0x99)
		// @1B: if_icmpeq @25
		// @1E: bipush 13 (0x0D)
		// @20: bipush 109 (0x6D)
		// @22: invokestatic game.C_100253_ph.func_101093_a(int, int)void
		// @25: goto @4A
		// @28: astore_1
		// @29: aload_1
		// @2A: new java.lang.StringBuilder
		// @2D: dup
		// @2E: invokespecial java.lang.StringBuilder.<init>()void
		// @31: getstatic java.lang.String[] game.C_100253_ph.field_101096_F
		// @34: bipush 17 (0x11)
		// @36: aaload
		// @37: invokevirtual java.lang.StringBuilder.append(java.lang.String)java.lang.StringBuilder
		// @3A: iload_0
		// @3B: invokevirtual java.lang.StringBuilder.append(int)java.lang.StringBuilder
		// @3E: bipush 41 (0x29)
		// @40: invokevirtual java.lang.StringBuilder.append(char)java.lang.StringBuilder
		// @43: invokevirtual java.lang.StringBuilder.toString()java.lang.String
		// @46: invokestatic game.C_100181_cf.func_105695_a(java.lang.Throwable, java.lang.String)game.C_100170_cm
		// @49: athrow
		// @4A: return
	}
	
	final synchronized int func_100913_a()
	{
		// @0: iconst_2
		// @1: ireturn
		// @2: astore_1
		// @3: aload_1
		// @4: getstatic java.lang.String[] game.C_100253_ph.field_101096_F
		// @7: bipush 12 (0x0C)
		// @9: aaload
		// @A: invokestatic game.C_100181_cf.func_105695_a(java.lang.Throwable, java.lang.String)game.C_100170_cm
		// @D: athrow
	}
	
	final synchronized void func_101089_b(int arg0, int arg1)
	{
		// @00: aload_0
		// @01: iload_1
		// @02: putfield int game.C_100253_ph.field_101095_E
		// @05: iload_2
		// @06: bipush -81 (0xAF)
		// @08: if_icmple @13
		// @0B: aload_0
		// @0C: aconst_null
		// @0D: checkcast int[]
		// @10: putfield int[] game.C_100253_ph.field_101101_n
		// @13: goto @40
		// @16: astore_3
		// @17: aload_3
		// @18: new java.lang.StringBuilder
		// @1B: dup
		// @1C: invokespecial java.lang.StringBuilder.<init>()void
		// @1F: getstatic java.lang.String[] game.C_100253_ph.field_101096_F
		// @22: iconst_3
		// @23: aaload
		// @24: invokevirtual java.lang.StringBuilder.append(java.lang.String)java.lang.StringBuilder
		// @27: iload_1
		// @28: invokevirtual java.lang.StringBuilder.append(int)java.lang.StringBuilder
		// @2B: bipush 44 (0x2C)
		// @2D: invokevirtual java.lang.StringBuilder.append(char)java.lang.StringBuilder
		// @30: iload_2
		// @31: invokevirtual java.lang.StringBuilder.append(int)java.lang.StringBuilder
		// @34: bipush 41 (0x29)
		// @36: invokevirtual java.lang.StringBuilder.append(char)java.lang.StringBuilder
		// @39: invokevirtual java.lang.StringBuilder.toString()java.lang.String
		// @3C: invokestatic game.C_100181_cf.func_105695_a(java.lang.Throwable, java.lang.String)game.C_100170_cm
		// @3F: athrow
		// @40: return
	}
	
	static final void func_101093_a(int arg0, int arg1)
	{
		// @00: getstatic int game.SteelSentinels.field_105275_O
		// @03: istore_3
		// @04: iload_1
		// @05: iconst_m1
		// @06: if_icmpeq @17
		// @09: aconst_null
		// @0A: checkcast java.applet.Applet
		// @0D: bipush 117 (0x75)
		// @0F: invokestatic game.C_100253_ph.func_101084_a(java.applet.Applet, int)java.lang.String
		// @12: pop
		// @13: goto @17
		// @16: athrow
		// @17: getstatic game.C_100202_qi game.C_100312_ld.field_107159_h
		// @1A: bipush 21 (0x15)
		// @1C: invokevirtual game.C_100202_qi.func_105899_c(int)game.C_100158_da
		// @1F: checkcast game.C_100125_tm
		// @22: astore_2
		// @23: aconst_null
		// @24: aload_2
		// @25: if_acmpeq @46
		// @28: iload_0
		// @29: iconst_0
		// @2A: aload_2
		// @2B: invokestatic game.C_100015_wh.func_103778_a(int, boolean, game.C_100125_tm)void
		// @2E: getstatic game.C_100202_qi game.C_100312_ld.field_107159_h
		// @31: bipush 83 (0x53)
		// @33: invokevirtual game.C_100202_qi.func_105907_c(byte)game.C_100158_da
		// @36: checkcast game.C_100125_tm
		// @39: astore_2
		// @3A: iload_3
		// @3B: ifne @74
		// @3E: iload_3
		// @3F: ifeq @23
		// @42: goto @46
		// @45: athrow
		// @46: goto @74
		// @49: astore_2
		// @4A: aload_2
		// @4B: new java.lang.StringBuilder
		// @4E: dup
		// @4F: invokespecial java.lang.StringBuilder.<init>()void
		// @52: getstatic java.lang.String[] game.C_100253_ph.field_101096_F
		// @55: bipush 11 (0x0B)
		// @57: aaload
		// @58: invokevirtual java.lang.StringBuilder.append(java.lang.String)java.lang.StringBuilder
		// @5B: iload_0
		// @5C: invokevirtual java.lang.StringBuilder.append(int)java.lang.StringBuilder
		// @5F: bipush 44 (0x2C)
		// @61: invokevirtual java.lang.StringBuilder.append(char)java.lang.StringBuilder
		// @64: iload_1
		// @65: invokevirtual java.lang.StringBuilder.append(int)java.lang.StringBuilder
		// @68: bipush 41 (0x29)
		// @6A: invokevirtual java.lang.StringBuilder.append(char)java.lang.StringBuilder
		// @6D: invokevirtual java.lang.StringBuilder.toString()java.lang.String
		// @70: invokestatic game.C_100181_cf.func_105695_a(java.lang.Throwable, java.lang.String)game.C_100170_cm
		// @73: athrow
		// @74: return
	}
	
	final synchronized void func_101090_a(int arg0, boolean arg1, int arg2, C_100002_gf arg3, int arg4, boolean arg5)
	{
		// @000: getstatic int game.SteelSentinels.field_105275_O
		// @003: istore #8
		// @005: aload_0
		// @006: getfield boolean game.C_100253_ph.field_101102_o
		// @009: ifeq @0BD
		// @00C: iload #6
		// @00E: ifne @019
		// @011: goto @015
		// @014: athrow
		// @015: goto @0BD
		// @018: athrow
		// @019: iconst_m1
		// @01A: aload_0
		// @01B: getfield int game.C_100253_ph.field_101114_x
		// @01E: iconst_m1
		// @01F: ixor
		// @020: if_icmpgt @072
		// @023: aload_0
		// @024: getfield game.C_100002_gf game.C_100253_ph.field_101112_z
		// @027: ifnull @03B
		// @02A: goto @02E
		// @02D: athrow
		// @02E: aload_0
		// @02F: getfield game.C_100210_qa game.C_100253_ph.field_101105_v
		// @032: bipush 109 (0x6D)
		// @034: invokevirtual game.C_100210_qa.func_101028_a(byte)void
		// @037: goto @03B
		// @03A: athrow
		// @03B: aload_0
		// @03C: aload #4
		// @03E: putfield game.C_100002_gf game.C_100253_ph.field_101112_z
		// @041: aconst_null
		// @042: aload #4
		// @044: if_acmpeq @0BC
		// @047: aload_0
		// @048: getfield game.C_100210_qa game.C_100253_ph.field_101105_v
		// @04B: iconst_0
		// @04C: iload_2
		// @04D: ifne @059
		// @050: goto @054
		// @053: athrow
		// @054: iconst_1
		// @055: goto @05A
		// @058: athrow
		// @059: iconst_0
		// @05A: aload #4
		// @05C: invokevirtual game.C_100210_qa.func_101035_a(boolean, boolean, game.C_100002_gf)void
		// @05F: aload_0
		// @060: aload_0
		// @061: getfield game.C_100210_qa game.C_100253_ph.field_101105_v
		// @064: sipush -4136 (0xEFD8)
		// @067: iload #5
		// @069: iload_1
		// @06A: invokespecial game.C_100253_ph.func_101088_a(game.C_100210_qa, int, int, int)void
		// @06D: iload #8
		// @06F: ifeq @0BC
		// @072: aconst_null
		// @073: aload_0
		// @074: getfield game.C_100002_gf game.C_100253_ph.field_101108_s
		// @077: if_acmpne @082
		// @07A: goto @07E
		// @07D: athrow
		// @07E: goto @08B
		// @081: athrow
		// @082: aload_0
		// @083: getfield game.C_100210_qa game.C_100253_ph.field_101107_t
		// @086: bipush 115 (0x73)
		// @088: invokevirtual game.C_100210_qa.func_101028_a(byte)void
		// @08B: aload_0
		// @08C: aload #4
		// @08E: putfield game.C_100002_gf game.C_100253_ph.field_101108_s
		// @091: aload #4
		// @093: ifnull @0BC
		// @096: aload_0
		// @097: getfield game.C_100210_qa game.C_100253_ph.field_101107_t
		// @09A: iconst_0
		// @09B: iload_2
		// @09C: ifne @0A8
		// @09F: goto @0A3
		// @0A2: athrow
		// @0A3: iconst_1
		// @0A4: goto @0A9
		// @0A7: athrow
		// @0A8: iconst_0
		// @0A9: aload #4
		// @0AB: invokevirtual game.C_100210_qa.func_101035_a(boolean, boolean, game.C_100002_gf)void
		// @0AE: aload_0
		// @0AF: aload_0
		// @0B0: getfield game.C_100210_qa game.C_100253_ph.field_101107_t
		// @0B3: sipush -4136 (0xEFD8)
		// @0B6: iload #5
		// @0B8: iload_1
		// @0B9: invokespecial game.C_100253_ph.func_101088_a(game.C_100210_qa, int, int, int)void
		// @0BC: return
		// @0BD: aload_0
		// @0BE: iload #6
		// @0C0: putfield boolean game.C_100253_ph.field_101102_o
		// @0C3: aload #4
		// @0C5: aload_0
		// @0C6: getfield game.C_100002_gf game.C_100253_ph.field_101108_s
		// @0C9: if_acmpeq @0F2
		// @0CC: aload #4
		// @0CE: aload_0
		// @0CF: getfield game.C_100002_gf game.C_100253_ph.field_101112_z
		// @0D2: if_acmpeq @0DD
		// @0D5: goto @0D9
		// @0D8: athrow
		// @0D9: goto @106
		// @0DC: athrow
		// @0DD: aload_0
		// @0DE: iload_3
		// @0DF: ineg
		// @0E0: putfield int game.C_100253_ph.field_101114_x
		// @0E3: aload_0
		// @0E4: aload_0
		// @0E5: getfield game.C_100210_qa game.C_100253_ph.field_101105_v
		// @0E8: sipush -4136 (0xEFD8)
		// @0EB: iload #5
		// @0ED: iload_1
		// @0EE: invokespecial game.C_100253_ph.func_101088_a(game.C_100210_qa, int, int, int)void
		// @0F1: return
		// @0F2: aload_0
		// @0F3: iload_3
		// @0F4: putfield int game.C_100253_ph.field_101114_x
		// @0F7: aload_0
		// @0F8: aload_0
		// @0F9: getfield game.C_100210_qa game.C_100253_ph.field_101107_t
		// @0FC: sipush -4136 (0xEFD8)
		// @0FF: iload #5
		// @101: iload_1
		// @102: invokespecial game.C_100253_ph.func_101088_a(game.C_100210_qa, int, int, int)void
		// @105: return
		// @106: iload_2
		// @107: iconst_1
		// @108: if_icmpeq @117
		// @10B: bipush -106 (0x96)
		// @10D: bipush 84 (0x54)
		// @10F: invokestatic game.C_100253_ph.func_101092_c(int, int)boolean
		// @112: pop
		// @113: goto @117
		// @116: athrow
		// @117: aload_0
		// @118: getfield game.C_100002_gf game.C_100253_ph.field_101108_s
		// @11B: ifnull @14E
		// @11E: aconst_null
		// @11F: aload_0
		// @120: getfield game.C_100002_gf game.C_100253_ph.field_101112_z
		// @123: if_acmpeq @146
		// @126: goto @12A
		// @129: athrow
		// @12A: aload_0
		// @12B: getfield int game.C_100253_ph.field_101098_A
		// @12E: iconst_m1
		// @12F: ixor
		// @130: ldc -524289 (0xfff7ffff)
		// @132: if_icmple @13E
		// @135: goto @139
		// @138: athrow
		// @139: iconst_1
		// @13A: goto @13F
		// @13D: athrow
		// @13E: iconst_0
		// @13F: istore #7
		// @141: iload #8
		// @143: ifeq @151
		// @146: iconst_0
		// @147: istore #7
		// @149: iload #8
		// @14B: ifeq @151
		// @14E: iconst_1
		// @14F: istore #7
		// @151: iload #7
		// @153: ifeq @1B4
		// @156: aload_0
		// @157: getfield game.C_100002_gf game.C_100253_ph.field_101108_s
		// @15A: ifnonnull @165
		// @15D: goto @161
		// @160: athrow
		// @161: goto @16E
		// @164: athrow
		// @165: aload_0
		// @166: getfield game.C_100210_qa game.C_100253_ph.field_101107_t
		// @169: bipush 56 (0x38)
		// @16B: invokevirtual game.C_100210_qa.func_101028_a(byte)void
		// @16E: aload_0
		// @16F: aload #4
		// @171: putfield game.C_100002_gf game.C_100253_ph.field_101108_s
		// @174: aconst_null
		// @175: aload #4
		// @177: if_acmpne @17E
		// @17A: goto @1AA
		// @17D: athrow
		// @17E: aload_0
		// @17F: getfield game.C_100210_qa game.C_100253_ph.field_101107_t
		// @182: iload #6
		// @184: ifne @18C
		// @187: iconst_1
		// @188: goto @18D
		// @18B: athrow
		// @18C: iconst_0
		// @18D: iload_2
		// @18E: ifne @196
		// @191: iconst_1
		// @192: goto @197
		// @195: athrow
		// @196: iconst_0
		// @197: aload #4
		// @199: invokevirtual game.C_100210_qa.func_101035_a(boolean, boolean, game.C_100002_gf)void
		// @19C: aload_0
		// @19D: aload_0
		// @19E: getfield game.C_100210_qa game.C_100253_ph.field_101107_t
		// @1A1: sipush -4136 (0xEFD8)
		// @1A4: iload #5
		// @1A6: iload_1
		// @1A7: invokespecial game.C_100253_ph.func_101088_a(game.C_100210_qa, int, int, int)void
		// @1AA: aload_0
		// @1AB: iload_3
		// @1AC: putfield int game.C_100253_ph.field_101114_x
		// @1AF: iload #8
		// @1B1: ifeq @205
		// @1B4: aload_0
		// @1B5: getfield game.C_100002_gf game.C_100253_ph.field_101112_z
		// @1B8: ifnull @1CC
		// @1BB: goto @1BF
		// @1BE: athrow
		// @1BF: aload_0
		// @1C0: getfield game.C_100210_qa game.C_100253_ph.field_101105_v
		// @1C3: bipush 91 (0x5B)
		// @1C5: invokevirtual game.C_100210_qa.func_101028_a(byte)void
		// @1C8: goto @1CC
		// @1CB: athrow
		// @1CC: aload_0
		// @1CD: aload #4
		// @1CF: putfield game.C_100002_gf game.C_100253_ph.field_101112_z
		// @1D2: aconst_null
		// @1D3: aload #4
		// @1D5: if_acmpeq @1FF
		// @1D8: aload_0
		// @1D9: getfield game.C_100210_qa game.C_100253_ph.field_101105_v
		// @1DC: iload #6
		// @1DE: ifne @1EA
		// @1E1: goto @1E5
		// @1E4: athrow
		// @1E5: iconst_1
		// @1E6: goto @1EB
		// @1E9: athrow
		// @1EA: iconst_0
		// @1EB: iconst_0
		// @1EC: aload #4
		// @1EE: invokevirtual game.C_100210_qa.func_101035_a(boolean, boolean, game.C_100002_gf)void
		// @1F1: aload_0
		// @1F2: aload_0
		// @1F3: getfield game.C_100210_qa game.C_100253_ph.field_101105_v
		// @1F6: sipush -4136 (0xEFD8)
		// @1F9: iload #5
		// @1FB: iload_1
		// @1FC: invokespecial game.C_100253_ph.func_101088_a(game.C_100210_qa, int, int, int)void
		// @1FF: aload_0
		// @200: iload_3
		// @201: ineg
		// @202: putfield int game.C_100253_ph.field_101114_x
		// @205: goto @26D
		// @208: astore #7
		// @20A: aload #7
		// @20C: new java.lang.StringBuilder
		// @20F: dup
		// @210: invokespecial java.lang.StringBuilder.<init>()void
		// @213: getstatic java.lang.String[] game.C_100253_ph.field_101096_F
		// @216: bipush 14 (0x0E)
		// @218: aaload
		// @219: invokevirtual java.lang.StringBuilder.append(java.lang.String)java.lang.StringBuilder
		// @21C: iload_1
		// @21D: invokevirtual java.lang.StringBuilder.append(int)java.lang.StringBuilder
		// @220: bipush 44 (0x2C)
		// @222: invokevirtual java.lang.StringBuilder.append(char)java.lang.StringBuilder
		// @225: iload_2
		// @226: invokevirtual java.lang.StringBuilder.append(boolean)java.lang.StringBuilder
		// @229: bipush 44 (0x2C)
		// @22B: invokevirtual java.lang.StringBuilder.append(char)java.lang.StringBuilder
		// @22E: iload_3
		// @22F: invokevirtual java.lang.StringBuilder.append(int)java.lang.StringBuilder
		// @232: bipush 44 (0x2C)
		// @234: invokevirtual java.lang.StringBuilder.append(char)java.lang.StringBuilder
		// @237: aload #4
		// @239: ifnull @245
		// @23C: getstatic java.lang.String[] game.C_100253_ph.field_101096_F
		// @23F: iconst_1
		// @240: aaload
		// @241: goto @24A
		// @244: athrow
		// @245: getstatic java.lang.String[] game.C_100253_ph.field_101096_F
		// @248: iconst_0
		// @249: aaload
		// @24A: invokevirtual java.lang.StringBuilder.append(java.lang.String)java.lang.StringBuilder
		// @24D: bipush 44 (0x2C)
		// @24F: invokevirtual java.lang.StringBuilder.append(char)java.lang.StringBuilder
		// @252: iload #5
		// @254: invokevirtual java.lang.StringBuilder.append(int)java.lang.StringBuilder
		// @257: bipush 44 (0x2C)
		// @259: invokevirtual java.lang.StringBuilder.append(char)java.lang.StringBuilder
		// @25C: iload #6
		// @25E: invokevirtual java.lang.StringBuilder.append(boolean)java.lang.StringBuilder
		// @261: bipush 41 (0x29)
		// @263: invokevirtual java.lang.StringBuilder.append(char)java.lang.StringBuilder
		// @266: invokevirtual java.lang.StringBuilder.toString()java.lang.String
		// @269: invokestatic game.C_100181_cf.func_105695_a(java.lang.Throwable, java.lang.String)game.C_100170_cm
		// @26C: athrow
		// @26D: return
	}
	
	final C_100261_md func_100912_c()
	{
		// @0: aconst_null
		// @1: areturn
		// @2: astore_1
		// @3: aload_1
		// @4: getstatic java.lang.String[] game.C_100253_ph.field_101096_F
		// @7: bipush 13 (0x0D)
		// @9: aaload
		// @A: invokestatic game.C_100181_cf.func_105695_a(java.lang.Throwable, java.lang.String)game.C_100170_cm
		// @D: athrow
	}
	
	static final String func_101084_a(Applet arg0, int arg1)
	{
		// @000: getstatic int game.SteelSentinels.field_105275_O
		// @003: istore #8
		// @005: aload_0
		// @006: getstatic java.lang.String[] game.C_100253_ph.field_101096_F
		// @009: bipush 6 (0x06)
		// @00B: aaload
		// @00C: invokevirtual java.applet.Applet.getParameter(java.lang.String)java.lang.String
		// @00F: astore_2
		// @010: new java.lang.StringBuilder
		// @013: dup
		// @014: invokespecial java.lang.StringBuilder.<init>()void
		// @017: aload_2
		// @018: invokevirtual java.lang.StringBuilder.append(java.lang.String)java.lang.StringBuilder
		// @01B: getstatic java.lang.String[] game.C_100253_ph.field_101096_F
		// @01E: bipush 9 (0x09)
		// @020: aaload
		// @021: invokevirtual java.lang.StringBuilder.append(java.lang.String)java.lang.StringBuilder
		// @024: invokevirtual java.lang.StringBuilder.toString()java.lang.String
		// @027: astore_3
		// @028: iload_1
		// @029: bipush 61 (0x3D)
		// @02B: if_icmpeq @03A
		// @02E: bipush 15 (0x0F)
		// @030: bipush 49 (0x31)
		// @032: invokestatic game.C_100253_ph.func_101092_c(int, int)boolean
		// @035: pop
		// @036: goto @03A
		// @039: athrow
		// @03A: sipush 17228 (0x434C)
		// @03D: getstatic java.lang.String[] game.C_100253_ph.field_101096_F
		// @040: bipush 8 (0x08)
		// @042: aaload
		// @043: aload_0
		// @044: invokestatic game.C_100175_cl.func_105614_a(int, java.lang.String, java.applet.Applet)java.lang.Object
		// @047: checkcast java.lang.String
		// @04A: astore #4
		// @04C: bipush -9 (0xF7)
		// @04E: aload #4
		// @050: bipush 59 (0x3B)
		// @052: invokestatic game.C_100087_n.func_100679_a(int, java.lang.String, char)java.lang.String[]
		// @055: astore #5
		// @057: iconst_0
		// @058: istore #6
		// @05A: aload #5
		// @05C: arraylength
		// @05D: iconst_m1
		// @05E: ixor
		// @05F: iload #6
		// @061: iconst_m1
		// @062: ixor
		// @063: if_icmpge @0B8
		// @066: aload #5
		// @068: iload #6
		// @06A: aaload
		// @06B: bipush 61 (0x3D)
		// @06D: invokevirtual java.lang.String.indexOf(int)int
		// @070: istore #7
		// @072: iload #8
		// @074: ifne @0BC
		// @077: iload #7
		// @079: iconst_m1
		// @07A: ixor
		// @07B: iconst_m1
		// @07C: if_icmpgt @0B0
		// @07F: goto @083
		// @082: athrow
		// @083: aload #5
		// @085: iload #6
		// @087: aaload
		// @088: iconst_0
		// @089: iload #7
		// @08B: invokevirtual java.lang.String.substring(int, int)java.lang.String
		// @08E: invokevirtual java.lang.String.trim()java.lang.String
		// @091: aload_3
		// @092: invokevirtual java.lang.String.equals(java.lang.Object)boolean
		// @095: ifne @0A0
		// @098: goto @09C
		// @09B: athrow
		// @09C: goto @0B0
		// @09F: athrow
		// @0A0: aload #5
		// @0A2: iload #6
		// @0A4: aaload
		// @0A5: iload #7
		// @0A7: iconst_m1
		// @0A8: isub
		// @0A9: invokevirtual java.lang.String.substring(int)java.lang.String
		// @0AC: invokevirtual java.lang.String.trim()java.lang.String
		// @0AF: areturn
		// @0B0: iinc #6 +1
		// @0B3: iload #8
		// @0B5: ifeq @05A
		// @0B8: goto @0BC
		// @0BB: astore_2
		// @0BC: getstatic java.lang.String game.C_100186_rl.field_105723_e
		// @0BF: ifnull @0C6
		// @0C2: getstatic java.lang.String game.C_100186_rl.field_105723_e
		// @0C5: areturn
		// @0C6: aload_0
		// @0C7: getstatic java.lang.String[] game.C_100253_ph.field_101096_F
		// @0CA: bipush 9 (0x09)
		// @0CC: aaload
		// @0CD: invokevirtual java.applet.Applet.getParameter(java.lang.String)java.lang.String
		// @0D0: areturn
		// @0D1: astore_2
		// @0D2: aload_2
		// @0D3: new java.lang.StringBuilder
		// @0D6: dup
		// @0D7: invokespecial java.lang.StringBuilder.<init>()void
		// @0DA: getstatic java.lang.String[] game.C_100253_ph.field_101096_F
		// @0DD: bipush 7 (0x07)
		// @0DF: aaload
		// @0E0: invokevirtual java.lang.StringBuilder.append(java.lang.String)java.lang.StringBuilder
		// @0E3: aload_0
		// @0E4: ifnull @0F0
		// @0E7: getstatic java.lang.String[] game.C_100253_ph.field_101096_F
		// @0EA: iconst_1
		// @0EB: aaload
		// @0EC: goto @0F5
		// @0EF: athrow
		// @0F0: getstatic java.lang.String[] game.C_100253_ph.field_101096_F
		// @0F3: iconst_0
		// @0F4: aaload
		// @0F5: invokevirtual java.lang.StringBuilder.append(java.lang.String)java.lang.StringBuilder
		// @0F8: bipush 44 (0x2C)
		// @0FA: invokevirtual java.lang.StringBuilder.append(char)java.lang.StringBuilder
		// @0FD: iload_1
		// @0FE: invokevirtual java.lang.StringBuilder.append(int)java.lang.StringBuilder
		// @101: bipush 41 (0x29)
		// @103: invokevirtual java.lang.StringBuilder.append(char)java.lang.StringBuilder
		// @106: invokevirtual java.lang.StringBuilder.toString()java.lang.String
		// @109: invokestatic game.C_100181_cf.func_105695_a(java.lang.Throwable, java.lang.String)game.C_100170_cm
		// @10C: athrow
	}
	
	final C_100261_md func_100916_d()
	{
		// @0: aconst_null
		// @1: areturn
		// @2: astore_1
		// @3: aload_1
		// @4: getstatic java.lang.String[] game.C_100253_ph.field_101096_F
		// @7: bipush 15 (0x0F)
		// @9: aaload
		// @A: invokestatic game.C_100181_cf.func_105695_a(java.lang.Throwable, java.lang.String)game.C_100170_cm
		// @D: athrow
	}
	
	final void func_100910_a(int[] arg0, int arg1, int arg2)
	{
		// @000: getstatic int game.SteelSentinels.field_105275_O
		// @003: istore #11
		// @005: iconst_m1
		// @006: aload_0
		// @007: getfield int game.C_100253_ph.field_101095_E
		// @00A: iconst_m1
		// @00B: ixor
		// @00C: if_icmpgt @015
		// @00F: aload_0
		// @010: iload_3
		// @011: invokevirtual game.C_100253_ph.func_100914_e(int)void
		// @014: return
		// @015: aload_0
		// @016: getfield boolean game.C_100253_ph.field_101102_o
		// @019: ifeq @08B
		// @01C: iconst_m1
		// @01D: aload_0
		// @01E: getfield int game.C_100253_ph.field_101114_x
		// @021: iconst_m1
		// @022: ixor
		// @023: if_icmple @056
		// @026: goto @02A
		// @029: athrow
		// @02A: aload_0
		// @02B: getfield game.C_100210_qa game.C_100253_ph.field_101107_t
		// @02E: bipush -128 (0x80)
		// @030: invokevirtual game.C_100210_qa.func_101043_f(int)boolean
		// @033: ifne @056
		// @036: goto @03A
		// @039: athrow
		// @03A: aload_0
		// @03B: aload_0
		// @03C: getfield int game.C_100253_ph.field_101114_x
		// @03F: ineg
		// @040: putfield int game.C_100253_ph.field_101114_x
		// @043: aload_0
		// @044: aconst_null
		// @045: putfield game.C_100002_gf game.C_100253_ph.field_101108_s
		// @048: aload_0
		// @049: iconst_0
		// @04A: putfield boolean game.C_100253_ph.field_101102_o
		// @04D: iload #11
		// @04F: ifeq @08B
		// @052: goto @056
		// @055: athrow
		// @056: aload_0
		// @057: getfield int game.C_100253_ph.field_101114_x
		// @05A: iconst_m1
		// @05B: ixor
		// @05C: iconst_m1
		// @05D: if_icmple @08B
		// @060: goto @064
		// @063: athrow
		// @064: aload_0
		// @065: getfield game.C_100210_qa game.C_100253_ph.field_101105_v
		// @068: bipush -55 (0xC9)
		// @06A: invokevirtual game.C_100210_qa.func_101043_f(int)boolean
		// @06D: ifne @08B
		// @070: goto @074
		// @073: athrow
		// @074: aload_0
		// @075: aconst_null
		// @076: putfield game.C_100002_gf game.C_100253_ph.field_101112_z
		// @079: aload_0
		// @07A: aload_0
		// @07B: getfield int game.C_100253_ph.field_101114_x
		// @07E: ineg
		// @07F: putfield int game.C_100253_ph.field_101114_x
		// @082: aload_0
		// @083: iconst_0
		// @084: putfield boolean game.C_100253_ph.field_101102_o
		// @087: goto @08B
		// @08A: athrow
		// @08B: aload_0
		// @08C: getfield int game.C_100253_ph.field_101095_E
		// @08F: aload_0
		// @090: getfield int game.C_100253_ph.field_101098_A
		// @093: ldc 718873676 (0x2ad9244c)
		// @095: ishr
		// @096: imul
		// @097: sipush 256 (0x0100)
		// @09A: idiv
		// @09B: istore #4
		// @09D: aload_0
		// @09E: getfield int game.C_100253_ph.field_101095_E
		// @0A1: iload #4
		// @0A3: ineg
		// @0A4: iadd
		// @0A5: istore #5
		// @0A7: iconst_m1
		// @0A8: aload_0
		// @0A9: getfield int game.C_100253_ph.field_101114_x
		// @0AC: iconst_m1
		// @0AD: ixor
		// @0AE: if_icmpeq @15C
		// @0B1: aload_0
		// @0B2: dup
		// @0B3: getfield int game.C_100253_ph.field_101098_A
		// @0B6: iload_3
		// @0B7: aload_0
		// @0B8: getfield int game.C_100253_ph.field_101114_x
		// @0BB: imul
		// @0BC: iadd
		// @0BD: putfield int game.C_100253_ph.field_101098_A
		// @0C0: aload_0
		// @0C1: getfield int game.C_100253_ph.field_101098_A
		// @0C4: ldc 1048576 (0x100000)
		// @0C6: if_icmplt @110
		// @0C9: goto @0CD
		// @0CC: athrow
		// @0CD: aload_0
		// @0CE: ldc 1048576 (0x100000)
		// @0D0: putfield int game.C_100253_ph.field_101098_A
		// @0D3: aload_0
		// @0D4: getfield boolean game.C_100253_ph.field_101102_o
		// @0D7: ifne @15C
		// @0DA: goto @0DE
		// @0DD: athrow
		// @0DE: aload_0
		// @0DF: iconst_0
		// @0E0: putfield int game.C_100253_ph.field_101114_x
		// @0E3: aload_0
		// @0E4: getfield boolean game.C_100253_ph.field_101104_w
		// @0E7: ifeq @0F2
		// @0EA: goto @0EE
		// @0ED: athrow
		// @0EE: goto @15C
		// @0F1: athrow
		// @0F2: aload_0
		// @0F3: getfield game.C_100002_gf game.C_100253_ph.field_101112_z
		// @0F6: ifnonnull @0FD
		// @0F9: goto @106
		// @0FC: athrow
		// @0FD: aload_0
		// @0FE: getfield game.C_100210_qa game.C_100253_ph.field_101105_v
		// @101: bipush 101 (0x65)
		// @103: invokevirtual game.C_100210_qa.func_101028_a(byte)void
		// @106: aload_0
		// @107: aconst_null
		// @108: putfield game.C_100002_gf game.C_100253_ph.field_101112_z
		// @10B: iload #11
		// @10D: ifeq @15C
		// @110: iconst_m1
		// @111: aload_0
		// @112: getfield int game.C_100253_ph.field_101098_A
		// @115: iconst_m1
		// @116: ixor
		// @117: if_icmple @122
		// @11A: goto @11E
		// @11D: athrow
		// @11E: goto @15C
		// @121: athrow
		// @122: aload_0
		// @123: iconst_0
		// @124: putfield int game.C_100253_ph.field_101098_A
		// @127: aload_0
		// @128: getfield boolean game.C_100253_ph.field_101102_o
		// @12B: ifeq @132
		// @12E: goto @15C
		// @131: athrow
		// @132: aload_0
		// @133: iconst_0
		// @134: putfield int game.C_100253_ph.field_101114_x
		// @137: aload_0
		// @138: getfield boolean game.C_100253_ph.field_101104_w
		// @13B: ifne @15C
		// @13E: aconst_null
		// @13F: aload_0
		// @140: getfield game.C_100002_gf game.C_100253_ph.field_101108_s
		// @143: if_acmpeq @157
		// @146: goto @14A
		// @149: athrow
		// @14A: aload_0
		// @14B: getfield game.C_100210_qa game.C_100253_ph.field_101107_t
		// @14E: bipush 74 (0x4A)
		// @150: invokevirtual game.C_100210_qa.func_101028_a(byte)void
		// @153: goto @157
		// @156: athrow
		// @157: aload_0
		// @158: aconst_null
		// @159: putfield game.C_100002_gf game.C_100253_ph.field_101108_s
		// @15C: getstatic boolean game.C_100177_cj.field_105646_g
		// @15F: ifne @167
		// @162: iload_3
		// @163: goto @16B
		// @166: athrow
		// @167: iload_3
		// @168: ldc 1750821281 (0x685b69a1)
		// @16A: ishl
		// @16B: istore #6
		// @16D: aload_0
		// @16E: getfield int game.C_100253_ph.field_101103_H
		// @171: sipush 256 (0x0100)
		// @174: if_icmplt @17B
		// @177: goto @282
		// @17A: athrow
		// @17B: aload_0
		// @17C: getfield game.C_100002_gf game.C_100253_ph.field_101108_s
		// @17F: ifnonnull @18D
		// @182: aload_0
		// @183: getfield game.C_100002_gf game.C_100253_ph.field_101112_z
		// @186: ifnull @282
		// @189: goto @18D
		// @18C: athrow
		// @18D: iload #4
		// @18F: sipush 256 (0x0100)
		// @192: if_icmpne @1AC
		// @195: goto @199
		// @198: athrow
		// @199: aload_0
		// @19A: getfield game.C_100210_qa game.C_100253_ph.field_101107_t
		// @19D: aload_1
		// @19E: iload_2
		// @19F: iload_3
		// @1A0: invokevirtual game.C_100210_qa.func_100910_a(int[], int, int)void
		// @1A3: iload #11
		// @1A5: ifeq @282
		// @1A8: goto @1AC
		// @1AB: athrow
		// @1AC: iload #5
		// @1AE: sipush 256 (0x0100)
		// @1B1: if_icmpne @1CB
		// @1B4: goto @1B8
		// @1B7: athrow
		// @1B8: aload_0
		// @1B9: getfield game.C_100210_qa game.C_100253_ph.field_101105_v
		// @1BC: aload_1
		// @1BD: iload_2
		// @1BE: iload_3
		// @1BF: invokevirtual game.C_100210_qa.func_100910_a(int[], int, int)void
		// @1C2: iload #11
		// @1C4: ifeq @282
		// @1C7: goto @1CB
		// @1CA: athrow
		// @1CB: aload_0
		// @1CC: getfield int[] game.C_100253_ph.field_101101_n
		// @1CF: ifnull @1E4
		// @1D2: goto @1D6
		// @1D5: athrow
		// @1D6: iload #6
		// @1D8: aload_0
		// @1D9: getfield int[] game.C_100253_ph.field_101101_n
		// @1DC: arraylength
		// @1DD: if_icmple @1FD
		// @1E0: goto @1E4
		// @1E3: athrow
		// @1E4: aload_0
		// @1E5: iload #6
		// @1E7: newarray int[]
		// @1E9: putfield int[] game.C_100253_ph.field_101101_n
		// @1EC: aload_0
		// @1ED: iload #6
		// @1EF: newarray int[]
		// @1F1: putfield int[] game.C_100253_ph.field_101094_D
		// @1F4: iload #11
		// @1F6: ifeq @215
		// @1F9: goto @1FD
		// @1FC: athrow
		// @1FD: aload_0
		// @1FE: getfield int[] game.C_100253_ph.field_101101_n
		// @201: iconst_0
		// @202: iload #6
		// @204: invokestatic game.C_100120_en.func_104910_a(int[], int, int)void
		// @207: aload_0
		// @208: getfield int[] game.C_100253_ph.field_101094_D
		// @20B: iconst_0
		// @20C: iload #6
		// @20E: invokestatic game.C_100120_en.func_104910_a(int[], int, int)void
		// @211: goto @215
		// @214: athrow
		// @215: aload_0
		// @216: getfield game.C_100210_qa game.C_100253_ph.field_101107_t
		// @219: aload_0
		// @21A: getfield int[] game.C_100253_ph.field_101101_n
		// @21D: iconst_0
		// @21E: iload_3
		// @21F: invokevirtual game.C_100210_qa.func_100910_a(int[], int, int)void
		// @222: aload_0
		// @223: getfield game.C_100210_qa game.C_100253_ph.field_101105_v
		// @226: aload_0
		// @227: getfield int[] game.C_100253_ph.field_101094_D
		// @22A: iconst_0
		// @22B: iload_3
		// @22C: invokevirtual game.C_100210_qa.func_100910_a(int[], int, int)void
		// @22F: getstatic boolean game.C_100177_cj.field_105646_g
		// @232: ifeq @23D
		// @235: iload_2
		// @236: iconst_1
		// @237: ishl
		// @238: dup
		// @239: istore_2
		// @23A: goto @23E
		// @23D: iload_2
		// @23E: istore #7
		// @240: iconst_0
		// @241: istore #8
		// @243: iload #8
		// @245: iconst_m1
		// @246: ixor
		// @247: iload #6
		// @249: iconst_m1
		// @24A: ixor
		// @24B: if_icmple @282
		// @24E: aload_1
		// @24F: iload #8
		// @251: iload #7
		// @253: iadd
		// @254: dup2
		// @255: iaload
		// @256: iload #4
		// @258: aload_0
		// @259: getfield int[] game.C_100253_ph.field_101101_n
		// @25C: iload #8
		// @25E: iaload
		// @25F: imul
		// @260: iload #5
		// @262: aload_0
		// @263: getfield int[] game.C_100253_ph.field_101094_D
		// @266: iload #8
		// @268: iaload
		// @269: imul
		// @26A: ineg
		// @26B: isub
		// @26C: ldc 723030632 (0x2b189268)
		// @26E: ishr
		// @26F: iadd
		// @270: iastore
		// @271: iinc #8 +1
		// @274: iload #11
		// @276: ifne @34C
		// @279: iload #11
		// @27B: ifeq @243
		// @27E: goto @282
		// @281: athrow
		// @282: aload_0
		// @283: getfield game.C_100002_gf game.C_100253_ph.field_101111_p
		// @286: ifnull @34C
		// @289: iconst_m1
		// @28A: aload_0
		// @28B: getfield int game.C_100253_ph.field_101103_H
		// @28E: iconst_m1
		// @28F: ixor
		// @290: if_icmpeq @34C
		// @293: goto @297
		// @296: athrow
		// @297: aload_0
		// @298: getfield int[] game.C_100253_ph.field_101101_n
		// @29B: ifnull @2C7
		// @29E: goto @2A2
		// @2A1: athrow
		// @2A2: aload_0
		// @2A3: getfield int[] game.C_100253_ph.field_101101_n
		// @2A6: arraylength
		// @2A7: iconst_m1
		// @2A8: ixor
		// @2A9: iload #6
		// @2AB: iconst_m1
		// @2AC: ixor
		// @2AD: if_icmpgt @2C7
		// @2B0: goto @2B4
		// @2B3: athrow
		// @2B4: aload_0
		// @2B5: getfield int[] game.C_100253_ph.field_101101_n
		// @2B8: iconst_0
		// @2B9: iload #6
		// @2BB: invokestatic game.C_100120_en.func_104910_a(int[], int, int)void
		// @2BE: iload #11
		// @2C0: ifeq @2DB
		// @2C3: goto @2C7
		// @2C6: athrow
		// @2C7: aload_0
		// @2C8: iload #6
		// @2CA: newarray int[]
		// @2CC: putfield int[] game.C_100253_ph.field_101094_D
		// @2CF: aload_0
		// @2D0: iload #6
		// @2D2: newarray int[]
		// @2D4: putfield int[] game.C_100253_ph.field_101101_n
		// @2D7: goto @2DB
		// @2DA: athrow
		// @2DB: aload_0
		// @2DC: getfield game.C_100210_qa game.C_100253_ph.field_101113_y
		// @2DF: aload_0
		// @2E0: getfield int[] game.C_100253_ph.field_101101_n
		// @2E3: iconst_0
		// @2E4: iload_3
		// @2E5: invokevirtual game.C_100210_qa.func_100910_a(int[], int, int)void
		// @2E8: getstatic boolean game.C_100177_cj.field_105646_g
		// @2EB: ifeq @2F6
		// @2EE: iload_2
		// @2EF: iconst_1
		// @2F0: ishl
		// @2F1: dup
		// @2F2: istore_2
		// @2F3: goto @2F7
		// @2F6: iload_2
		// @2F7: istore #7
		// @2F9: aload_0
		// @2FA: getfield int game.C_100253_ph.field_101103_H
		// @2FD: aload_0
		// @2FE: getfield int game.C_100253_ph.field_101095_E
		// @301: imul
		// @302: sipush 256 (0x0100)
		// @305: idiv
		// @306: istore #8
		// @308: iload #8
		// @30A: ineg
		// @30B: aload_0
		// @30C: getfield int game.C_100253_ph.field_101095_E
		// @30F: iadd
		// @310: istore #9
		// @312: iconst_0
		// @313: istore #10
		// @315: iload #10
		// @317: iload #6
		// @319: if_icmpge @34C
		// @31C: aload_1
		// @31D: iload #10
		// @31F: iload #7
		// @321: iadd
		// @322: iload #8
		// @324: aload_0
		// @325: getfield int[] game.C_100253_ph.field_101101_n
		// @328: iload #10
		// @32A: iaload
		// @32B: imul
		// @32C: iload #9
		// @32E: aload_1
		// @32F: iload #10
		// @331: iload #7
		// @333: iadd
		// @334: iaload
		// @335: imul
		// @336: iadd
		// @337: ldc -1995206904 (0x89138f08)
		// @339: ishr
		// @33A: iastore
		// @33B: iinc #10 +1
		// @33E: iload #11
		// @340: ifne @395
		// @343: iload #11
		// @345: ifeq @315
		// @348: goto @34C
		// @34B: athrow
		// @34C: goto @395
		// @34F: astore #4
		// @351: aload #4
		// @353: new java.lang.StringBuilder
		// @356: dup
		// @357: invokespecial java.lang.StringBuilder.<init>()void
		// @35A: getstatic java.lang.String[] game.C_100253_ph.field_101096_F
		// @35D: iconst_2
		// @35E: aaload
		// @35F: invokevirtual java.lang.StringBuilder.append(java.lang.String)java.lang.StringBuilder
		// @362: aload_1
		// @363: ifnull @36F
		// @366: getstatic java.lang.String[] game.C_100253_ph.field_101096_F
		// @369: iconst_1
		// @36A: aaload
		// @36B: goto @374
		// @36E: athrow
		// @36F: getstatic java.lang.String[] game.C_100253_ph.field_101096_F
		// @372: iconst_0
		// @373: aaload
		// @374: invokevirtual java.lang.StringBuilder.append(java.lang.String)java.lang.StringBuilder
		// @377: bipush 44 (0x2C)
		// @379: invokevirtual java.lang.StringBuilder.append(char)java.lang.StringBuilder
		// @37C: iload_2
		// @37D: invokevirtual java.lang.StringBuilder.append(int)java.lang.StringBuilder
		// @380: bipush 44 (0x2C)
		// @382: invokevirtual java.lang.StringBuilder.append(char)java.lang.StringBuilder
		// @385: iload_3
		// @386: invokevirtual java.lang.StringBuilder.append(int)java.lang.StringBuilder
		// @389: bipush 41 (0x29)
		// @38B: invokevirtual java.lang.StringBuilder.append(char)java.lang.StringBuilder
		// @38E: invokevirtual java.lang.StringBuilder.toString()java.lang.String
		// @391: invokestatic game.C_100181_cf.func_105695_a(java.lang.Throwable, java.lang.String)game.C_100170_cm
		// @394: athrow
		// @395: return
	}
	
	static final boolean func_101092_c(int arg0, int arg1)
	{
		// @00: bipush -99 (0x9D)
		// @02: bipush -11 (0xF5)
		// @04: iload_1
		// @05: isub
		// @06: bipush 45 (0x2D)
		// @08: idiv
		// @09: idiv
		// @0A: istore_2
		// @0B: iconst_m1
		// @0C: iload_0
		// @0D: if_icmpne @12
		// @10: iconst_1
		// @11: ireturn
		// @12: getstatic int game.C_100084_ug.field_104484_a
		// @15: iconst_1
		// @16: iload_0
		// @17: ishl
		// @18: iand
		// @19: iconst_m1
		// @1A: ixor
		// @1B: iconst_m1
		// @1C: if_icmpeq @24
		// @1F: iconst_1
		// @20: goto @25
		// @23: athrow
		// @24: iconst_0
		// @25: ireturn
		// @26: astore_2
		// @27: aload_2
		// @28: new java.lang.StringBuilder
		// @2B: dup
		// @2C: invokespecial java.lang.StringBuilder.<init>()void
		// @2F: getstatic java.lang.String[] game.C_100253_ph.field_101096_F
		// @32: bipush 16 (0x10)
		// @34: aaload
		// @35: invokevirtual java.lang.StringBuilder.append(java.lang.String)java.lang.StringBuilder
		// @38: iload_0
		// @39: invokevirtual java.lang.StringBuilder.append(int)java.lang.StringBuilder
		// @3C: bipush 44 (0x2C)
		// @3E: invokevirtual java.lang.StringBuilder.append(char)java.lang.StringBuilder
		// @41: iload_1
		// @42: invokevirtual java.lang.StringBuilder.append(int)java.lang.StringBuilder
		// @45: bipush 41 (0x29)
		// @47: invokevirtual java.lang.StringBuilder.append(char)java.lang.StringBuilder
		// @4A: invokevirtual java.lang.StringBuilder.toString()java.lang.String
		// @4D: invokestatic game.C_100181_cf.func_105695_a(java.lang.Throwable, java.lang.String)game.C_100170_cm
		// @50: athrow
	}
	
	static final void func_101085_a(byte arg0)
	{
		// @00: iconst_0
		// @01: putstatic boolean game.C_100198_qn.field_105834_b
		// @04: iconst_0
		// @05: putstatic boolean game.C_100186_rl.field_105720_f
		// @08: iconst_1
		// @09: iconst_m1
		// @0A: invokestatic game.C_100152_bd.func_105184_a(boolean, int)void
		// @0D: iload_0
		// @0E: bipush 85 (0x55)
		// @10: if_icmpgt @14
		// @13: return
		// @14: getstatic game.C_100068_vc game.C_100220_ac.field_106056_e
		// @17: putstatic game.C_100068_vc game.C_100191_rg.field_100845_o
		// @1A: getstatic game.C_100068_vc game.C_100220_ac.field_106056_e
		// @1D: putstatic game.C_100068_vc game.C_100222_aa.field_106086_a
		// @20: goto @45
		// @23: astore_1
		// @24: aload_1
		// @25: new java.lang.StringBuilder
		// @28: dup
		// @29: invokespecial java.lang.StringBuilder.<init>()void
		// @2C: getstatic java.lang.String[] game.C_100253_ph.field_101096_F
		// @2F: bipush 19 (0x13)
		// @31: aaload
		// @32: invokevirtual java.lang.StringBuilder.append(java.lang.String)java.lang.StringBuilder
		// @35: iload_0
		// @36: invokevirtual java.lang.StringBuilder.append(int)java.lang.StringBuilder
		// @39: bipush 41 (0x29)
		// @3B: invokevirtual java.lang.StringBuilder.append(char)java.lang.StringBuilder
		// @3E: invokevirtual java.lang.StringBuilder.toString()java.lang.String
		// @41: invokestatic game.C_100181_cf.func_105695_a(java.lang.Throwable, java.lang.String)game.C_100170_cm
		// @44: athrow
		// @45: return
	}
	
	static final void func_101087_a(byte arg0, String arg1)
	{
		// @00: getstatic game.C_100302_ka game.C_100293_kj.field_106889_b
		// @03: aload_1
		// @04: putfield java.lang.String game.C_100302_ka.field_101890_ab
		// @07: iconst_1
		// @08: putstatic boolean game.C_100188_rj.field_105735_f
		// @0B: getstatic game.C_100185_rm game.C_100049_vf.field_104206_l
		// @0E: getfield int game.C_100185_rm.field_105483_g
		// @11: istore_2
		// @12: getstatic game.C_100185_rm game.C_100049_vf.field_104206_l
		// @15: getfield int game.C_100185_rm.field_105491_i
		// @18: istore_3
		// @19: getstatic game.C_100302_ka game.C_100293_kj.field_106889_b
		// @1C: getfield game.C_100112_r game.C_100302_ka.field_101845_sb
		// @1F: aload_1
		// @20: sipush 272 (0x0110)
		// @23: getstatic game.C_100302_ka game.C_100293_kj.field_106889_b
		// @26: getfield int game.C_100302_ka.field_101833_ob
		// @29: invokevirtual game.C_100112_r.func_101734_a(java.lang.String, int, int)int
		// @2C: istore #4
		// @2E: bipush -103 (0x99)
		// @30: iload_3
		// @31: iconst_2
		// @32: idiv
		// @33: iadd
		// @34: iload #4
		// @36: iconst_2
		// @37: idiv
		// @38: isub
		// @39: istore #5
		// @3B: getstatic game.C_100302_ka game.C_100053_vn.field_102842_Y
		// @3E: sipush -320 (0xFEC0)
		// @41: iload_2
		// @42: iadd
		// @43: iconst_2
		// @44: idiv
		// @45: iconst_2
		// @46: iload #5
		// @48: imul
		// @49: ineg
		// @4A: bipush -120 (0x88)
		// @4C: iload_3
		// @4D: iadd
		// @4E: iadd
		// @4F: iconst_m1
		// @50: iload #5
		// @52: sipush 320 (0x0140)
		// @55: invokevirtual game.C_100302_ka.func_101825_a(int, int, int, int, int)void
		// @58: getstatic game.C_100302_ka game.C_100053_vn.field_102842_Y
		// @5B: ldc 11579568 (0xb0b0b0)
		// @5D: iconst_1
		// @5E: ldc 8421504 (0x808080)
		// @60: iconst_3
		// @61: ldc 2105376 (0x202020)
		// @63: getstatic game.C_100302_ka game.C_100053_vn.field_102842_Y
		// @66: getfield int game.C_100302_ka.field_101848_lb
		// @69: invokestatic game.C_100265_mh.func_106563_a(int, boolean, int, int, int, int)game.C_100037_wb[]
		// @6C: putfield game.C_100037_wb[] game.C_100302_ka.field_101862_T
		// @6F: getstatic game.C_100302_ka game.C_100293_kj.field_106889_b
		// @72: bipush 24 (0x18)
		// @74: bipush -20 (0xEC)
		// @76: getstatic game.C_100302_ka game.C_100053_vn.field_102842_Y
		// @79: getfield int game.C_100302_ka.field_101848_lb
		// @7C: iadd
		// @7D: bipush -24 (0xE8)
		// @7F: iadd
		// @80: iconst_m1
		// @81: bipush 16 (0x10)
		// @83: bipush -24 (0xE8)
		// @85: bipush -24 (0xE8)
		// @87: getstatic game.C_100302_ka game.C_100053_vn.field_102842_Y
		// @8A: getfield int game.C_100302_ka.field_101886_Kb
		// @8D: iadd
		// @8E: iadd
		// @8F: invokevirtual game.C_100302_ka.func_101825_a(int, int, int, int, int)void
		// @92: getstatic game.C_100302_ka game.C_100066_dl.field_101639_w
		// @95: bipush 120 (0x78)
		// @97: bipush 24 (0x18)
		// @99: iconst_m1
		// @9A: bipush -24 (0xE8)
		// @9C: bipush -20 (0xEC)
		// @9E: getstatic game.C_100302_ka game.C_100053_vn.field_102842_Y
		// @A1: getfield int game.C_100302_ka.field_101848_lb
		// @A4: iadd
		// @A5: iadd
		// @A6: bipush 80 (0x50)
		// @A8: invokevirtual game.C_100302_ka.func_101825_a(int, int, int, int, int)void
		// @AB: iload_0
		// @AC: bipush -61 (0xC3)
		// @AE: if_icmpeq @BC
		// @B1: aconst_null
		// @B2: checkcast java.lang.String
		// @B5: putstatic java.lang.String game.C_100253_ph.field_101110_q
		// @B8: goto @BC
		// @BB: athrow
		// @BC: goto @FB
		// @BF: astore_2
		// @C0: aload_2
		// @C1: new java.lang.StringBuilder
		// @C4: dup
		// @C5: invokespecial java.lang.StringBuilder.<init>()void
		// @C8: getstatic java.lang.String[] game.C_100253_ph.field_101096_F
		// @CB: bipush 18 (0x12)
		// @CD: aaload
		// @CE: invokevirtual java.lang.StringBuilder.append(java.lang.String)java.lang.StringBuilder
		// @D1: iload_0
		// @D2: invokevirtual java.lang.StringBuilder.append(int)java.lang.StringBuilder
		// @D5: bipush 44 (0x2C)
		// @D7: invokevirtual java.lang.StringBuilder.append(char)java.lang.StringBuilder
		// @DA: aload_1
		// @DB: ifnull @E7
		// @DE: getstatic java.lang.String[] game.C_100253_ph.field_101096_F
		// @E1: iconst_1
		// @E2: aaload
		// @E3: goto @EC
		// @E6: athrow
		// @E7: getstatic java.lang.String[] game.C_100253_ph.field_101096_F
		// @EA: iconst_0
		// @EB: aaload
		// @EC: invokevirtual java.lang.StringBuilder.append(java.lang.String)java.lang.StringBuilder
		// @EF: bipush 41 (0x29)
		// @F1: invokevirtual java.lang.StringBuilder.append(char)java.lang.StringBuilder
		// @F4: invokevirtual java.lang.StringBuilder.toString()java.lang.String
		// @F7: invokestatic game.C_100181_cf.func_105695_a(java.lang.Throwable, java.lang.String)game.C_100170_cm
		// @FA: athrow
		// @FB: return
	}
	
	final synchronized void func_100914_e(int arg0)
	{
		// @000: getstatic int game.SteelSentinels.field_105275_O
		// @003: istore_3
		// @004: aload_0
		// @005: getfield int game.C_100253_ph.field_101098_A
		// @008: ifle @022
		// @00B: aload_0
		// @00C: getfield game.C_100002_gf game.C_100253_ph.field_101108_s
		// @00F: ifnull @022
		// @012: goto @016
		// @015: athrow
		// @016: aload_0
		// @017: getfield game.C_100210_qa game.C_100253_ph.field_101107_t
		// @01A: iload_1
		// @01B: invokevirtual game.C_100210_qa.func_100914_e(int)void
		// @01E: goto @022
		// @021: athrow
		// @022: ldc -1048577 (0xffefffff)
		// @024: aload_0
		// @025: getfield int game.C_100253_ph.field_101098_A
		// @028: iconst_m1
		// @029: ixor
		// @02A: if_icmpge @045
		// @02D: aconst_null
		// @02E: aload_0
		// @02F: getfield game.C_100002_gf game.C_100253_ph.field_101112_z
		// @032: if_acmpeq @045
		// @035: goto @039
		// @038: athrow
		// @039: aload_0
		// @03A: getfield game.C_100210_qa game.C_100253_ph.field_101105_v
		// @03D: iload_1
		// @03E: invokevirtual game.C_100210_qa.func_100914_e(int)void
		// @041: goto @045
		// @044: athrow
		// @045: aload_0
		// @046: getfield int game.C_100253_ph.field_101103_H
		// @049: iconst_m1
		// @04A: ixor
		// @04B: iconst_m1
		// @04C: if_icmpge @066
		// @04F: aload_0
		// @050: getfield game.C_100002_gf game.C_100253_ph.field_101111_p
		// @053: ifnonnull @05E
		// @056: goto @05A
		// @059: athrow
		// @05A: goto @066
		// @05D: athrow
		// @05E: aload_0
		// @05F: getfield game.C_100210_qa game.C_100253_ph.field_101113_y
		// @062: iload_1
		// @063: invokevirtual game.C_100210_qa.func_100914_e(int)void
		// @066: aload_0
		// @067: getfield boolean game.C_100253_ph.field_101102_o
		// @06A: ifeq @0D5
		// @06D: aload_0
		// @06E: getfield int game.C_100253_ph.field_101114_x
		// @071: ifle @0A3
		// @074: goto @078
		// @077: athrow
		// @078: aload_0
		// @079: getfield game.C_100210_qa game.C_100253_ph.field_101107_t
		// @07C: bipush -94 (0xA2)
		// @07E: invokevirtual game.C_100210_qa.func_101043_f(int)boolean
		// @081: ifne @0A3
		// @084: goto @088
		// @087: athrow
		// @088: aload_0
		// @089: iconst_0
		// @08A: putfield boolean game.C_100253_ph.field_101102_o
		// @08D: aload_0
		// @08E: aload_0
		// @08F: getfield int game.C_100253_ph.field_101114_x
		// @092: ineg
		// @093: putfield int game.C_100253_ph.field_101114_x
		// @096: aload_0
		// @097: aconst_null
		// @098: putfield game.C_100002_gf game.C_100253_ph.field_101108_s
		// @09B: iload_3
		// @09C: ifeq @0D5
		// @09F: goto @0A3
		// @0A2: athrow
		// @0A3: aload_0
		// @0A4: getfield int game.C_100253_ph.field_101114_x
		// @0A7: ifge @0D5
		// @0AA: goto @0AE
		// @0AD: athrow
		// @0AE: aload_0
		// @0AF: getfield game.C_100210_qa game.C_100253_ph.field_101105_v
		// @0B2: bipush -74 (0xB6)
		// @0B4: invokevirtual game.C_100210_qa.func_101043_f(int)boolean
		// @0B7: ifne @0D5
		// @0BA: goto @0BE
		// @0BD: athrow
		// @0BE: aload_0
		// @0BF: aconst_null
		// @0C0: putfield game.C_100002_gf game.C_100253_ph.field_101112_z
		// @0C3: aload_0
		// @0C4: iconst_0
		// @0C5: putfield boolean game.C_100253_ph.field_101102_o
		// @0C8: aload_0
		// @0C9: aload_0
		// @0CA: getfield int game.C_100253_ph.field_101114_x
		// @0CD: ineg
		// @0CE: putfield int game.C_100253_ph.field_101114_x
		// @0D1: goto @0D5
		// @0D4: athrow
		// @0D5: iconst_0
		// @0D6: aload_0
		// @0D7: getfield int game.C_100253_ph.field_101114_x
		// @0DA: if_icmpne @0E1
		// @0DD: goto @187
		// @0E0: athrow
		// @0E1: aload_0
		// @0E2: dup
		// @0E3: getfield int game.C_100253_ph.field_101098_A
		// @0E6: aload_0
		// @0E7: getfield int game.C_100253_ph.field_101114_x
		// @0EA: iload_1
		// @0EB: imul
		// @0EC: iadd
		// @0ED: putfield int game.C_100253_ph.field_101098_A
		// @0F0: ldc 1048576 (0x100000)
		// @0F2: aload_0
		// @0F3: getfield int game.C_100253_ph.field_101098_A
		// @0F6: if_icmple @148
		// @0F9: aload_0
		// @0FA: getfield int game.C_100253_ph.field_101098_A
		// @0FD: iconst_m1
		// @0FE: ixor
		// @0FF: iconst_m1
		// @100: if_icmpge @10B
		// @103: goto @107
		// @106: athrow
		// @107: goto @187
		// @10A: athrow
		// @10B: aload_0
		// @10C: iconst_0
		// @10D: putfield int game.C_100253_ph.field_101098_A
		// @110: aload_0
		// @111: getfield boolean game.C_100253_ph.field_101102_o
		// @114: ifne @187
		// @117: aload_0
		// @118: iconst_0
		// @119: putfield int game.C_100253_ph.field_101114_x
		// @11C: aload_0
		// @11D: getfield boolean game.C_100253_ph.field_101104_w
		// @120: ifne @187
		// @123: goto @127
		// @126: athrow
		// @127: aload_0
		// @128: getfield game.C_100002_gf game.C_100253_ph.field_101108_s
		// @12B: ifnull @13F
		// @12E: goto @132
		// @131: athrow
		// @132: aload_0
		// @133: getfield game.C_100210_qa game.C_100253_ph.field_101107_t
		// @136: bipush 84 (0x54)
		// @138: invokevirtual game.C_100210_qa.func_101028_a(byte)void
		// @13B: goto @13F
		// @13E: athrow
		// @13F: aload_0
		// @140: aconst_null
		// @141: putfield game.C_100002_gf game.C_100253_ph.field_101108_s
		// @144: iload_3
		// @145: ifeq @187
		// @148: aload_0
		// @149: ldc 1048576 (0x100000)
		// @14B: putfield int game.C_100253_ph.field_101098_A
		// @14E: aload_0
		// @14F: getfield boolean game.C_100253_ph.field_101102_o
		// @152: ifne @187
		// @155: goto @159
		// @158: athrow
		// @159: aload_0
		// @15A: iconst_0
		// @15B: putfield int game.C_100253_ph.field_101114_x
		// @15E: aload_0
		// @15F: getfield boolean game.C_100253_ph.field_101104_w
		// @162: ifne @187
		// @165: goto @169
		// @168: athrow
		// @169: aconst_null
		// @16A: aload_0
		// @16B: getfield game.C_100002_gf game.C_100253_ph.field_101112_z
		// @16E: if_acmpne @179
		// @171: goto @175
		// @174: athrow
		// @175: goto @182
		// @178: athrow
		// @179: aload_0
		// @17A: getfield game.C_100210_qa game.C_100253_ph.field_101105_v
		// @17D: bipush 105 (0x69)
		// @17F: invokevirtual game.C_100210_qa.func_101028_a(byte)void
		// @182: aload_0
		// @183: aconst_null
		// @184: putfield game.C_100002_gf game.C_100253_ph.field_101112_z
		// @187: goto @1AB
		// @18A: astore_2
		// @18B: aload_2
		// @18C: new java.lang.StringBuilder
		// @18F: dup
		// @190: invokespecial java.lang.StringBuilder.<init>()void
		// @193: getstatic java.lang.String[] game.C_100253_ph.field_101096_F
		// @196: iconst_4
		// @197: aaload
		// @198: invokevirtual java.lang.StringBuilder.append(java.lang.String)java.lang.StringBuilder
		// @19B: iload_1
		// @19C: invokevirtual java.lang.StringBuilder.append(int)java.lang.StringBuilder
		// @19F: bipush 41 (0x29)
		// @1A1: invokevirtual java.lang.StringBuilder.append(char)java.lang.StringBuilder
		// @1A4: invokevirtual java.lang.StringBuilder.toString()java.lang.String
		// @1A7: invokestatic game.C_100181_cf.func_105695_a(java.lang.Throwable, java.lang.String)game.C_100170_cm
		// @1AA: athrow
		// @1AB: return
	}
	
	private final void func_101088_a(C_100210_qa arg0, int arg1, int arg2, int arg3)
	{
		// @00: iload_2
		// @01: sipush -4136 (0xEFD8)
		// @04: if_icmpeq @08
		// @07: return
		// @08: aload_1
		// @09: iload #4
		// @0B: iconst_m1
		// @0C: sipush 8192 (0x2000)
		// @0F: invokevirtual game.C_100210_qa.func_101025_c(int, int, int)void
		// @12: aload_1
		// @13: iload_3
		// @14: bipush -57 (0xC7)
		// @16: invokevirtual game.C_100210_qa.func_101017_c(int, byte)void
		// @19: goto @6C
		// @1C: astore #5
		// @1E: aload #5
		// @20: new java.lang.StringBuilder
		// @23: dup
		// @24: invokespecial java.lang.StringBuilder.<init>()void
		// @27: getstatic java.lang.String[] game.C_100253_ph.field_101096_F
		// @2A: iconst_5
		// @2B: aaload
		// @2C: invokevirtual java.lang.StringBuilder.append(java.lang.String)java.lang.StringBuilder
		// @2F: aload_1
		// @30: ifnull @3C
		// @33: getstatic java.lang.String[] game.C_100253_ph.field_101096_F
		// @36: iconst_1
		// @37: aaload
		// @38: goto @41
		// @3B: athrow
		// @3C: getstatic java.lang.String[] game.C_100253_ph.field_101096_F
		// @3F: iconst_0
		// @40: aaload
		// @41: invokevirtual java.lang.StringBuilder.append(java.lang.String)java.lang.StringBuilder
		// @44: bipush 44 (0x2C)
		// @46: invokevirtual java.lang.StringBuilder.append(char)java.lang.StringBuilder
		// @49: iload_2
		// @4A: invokevirtual java.lang.StringBuilder.append(int)java.lang.StringBuilder
		// @4D: bipush 44 (0x2C)
		// @4F: invokevirtual java.lang.StringBuilder.append(char)java.lang.StringBuilder
		// @52: iload_3
		// @53: invokevirtual java.lang.StringBuilder.append(int)java.lang.StringBuilder
		// @56: bipush 44 (0x2C)
		// @58: invokevirtual java.lang.StringBuilder.append(char)java.lang.StringBuilder
		// @5B: iload #4
		// @5D: invokevirtual java.lang.StringBuilder.append(int)java.lang.StringBuilder
		// @60: bipush 41 (0x29)
		// @62: invokevirtual java.lang.StringBuilder.append(char)java.lang.StringBuilder
		// @65: invokevirtual java.lang.StringBuilder.toString()java.lang.String
		// @68: invokestatic game.C_100181_cf.func_105695_a(java.lang.Throwable, java.lang.String)game.C_100170_cm
		// @6B: athrow
		// @6C: return
	}
	
	private C_100253_ph() throws Throwable
	{
		// @00: aload_0
		// @01: invokespecial game.C_100261_md.<init>()void
		// @04: new java.lang.Error
		// @07: dup
		// @08: invokespecial java.lang.Error.<init>()void
		// @0B: athrow
		// @0C: astore_1
		// @0D: aload_1
		// @0E: getstatic java.lang.String[] game.C_100253_ph.field_101096_F
		// @11: bipush 10 (0x0A)
		// @13: aaload
		// @14: invokestatic game.C_100181_cf.func_105695_a(java.lang.Throwable, java.lang.String)game.C_100170_cm
		// @17: athrow
	}
	
	static
	{
		// @000: bipush 20 (0x14)
		// @002: anewarray java.lang.String
		// @005: dup
		// @006: iconst_0
		// @007: ldc "h=^/"
		// @009: invokestatic game.C_100253_ph.func_101086_z(java.lang.String)char[]
		// @00C: invokestatic game.C_100253_ph.func_101083_z(char[])java.lang.String
		// @00F: aastore
		// @010: dup
		// @011: iconst_1
		// @012: ldc "}f\u001cm9"
		// @014: invokestatic game.C_100253_ph.func_101086_z(java.lang.String)char[]
		// @017: invokestatic game.C_100253_ph.func_101083_z(char[])java.lang.String
		// @01A: aastore
		// @01B: dup
		// @01C: iconst_2
		// @01D: ldc "v \u001c\u0002l"
		// @01F: invokestatic game.C_100253_ph.func_101086_z(java.lang.String)char[]
		// @022: invokestatic game.C_100253_ph.func_101083_z(char[])java.lang.String
		// @025: aastore
		// @026: dup
		// @027: iconst_3
		// @028: ldc "v \u001c\u0016l"
		// @02A: invokestatic game.C_100253_ph.func_101086_z(java.lang.String)char[]
		// @02D: invokestatic game.C_100253_ph.func_101083_z(char[])java.lang.String
		// @030: aastore
		// @031: dup
		// @032: iconst_4
		// @033: ldc "v \u001c\u0001l"
		// @035: invokestatic game.C_100253_ph.func_101086_z(java.lang.String)char[]
		// @038: invokestatic game.C_100253_ph.func_101083_z(char[])java.lang.String
		// @03B: aastore
		// @03C: dup
		// @03D: iconst_5
		// @03E: ldc "v \u001c\u0014l"
		// @040: invokestatic game.C_100253_ph.func_101086_z(java.lang.String)char[]
		// @043: invokestatic game.C_100253_ph.func_101083_z(char[])java.lang.String
		// @046: aastore
		// @047: dup
		// @048: bipush 6 (0x06)
		// @04A: ldc "e'](-c8@&\"o0"
		// @04C: invokestatic game.C_100253_ph.func_101086_z(java.lang.String)char[]
		// @04F: invokestatic game.C_100253_ph.func_101083_z(char[])java.lang.String
		// @052: aastore
		// @053: dup
		// @054: bipush 7 (0x07)
		// @056: ldc "v \u001c\u0010l"
		// @058: invokestatic game.C_100253_ph.func_101086_z(java.lang.String)char[]
		// @05B: invokestatic game.C_100253_ph.func_101083_z(char[])java.lang.String
		// @05E: aastore
		// @05F: dup
		// @060: bipush 8 (0x08)
		// @062: ldc "a-F +i#[&7"
		// @064: invokestatic game.C_100253_ph.func_101086_z(java.lang.String)char[]
		// @067: invokestatic game.C_100253_ph.func_101083_z(char[])java.lang.String
		// @06A: aastore
		// @06B: dup
		// @06C: bipush 9 (0x09)
		// @06E: ldc "u-F7-h/A"
		// @070: invokestatic game.C_100253_ph.func_101086_z(java.lang.String)char[]
		// @073: invokestatic game.C_100253_ph.func_101083_z(char[])java.lang.String
		// @076: aastore
		// @077: dup
		// @078: bipush 10 (0x0A)
		// @07A: ldc "v \u001c\u007f-h!F}l/"
		// @07C: invokestatic game.C_100253_ph.func_101086_z(java.lang.String)char[]
		// @07F: invokestatic game.C_100253_ph.func_101083_z(char[])java.lang.String
		// @082: aastore
		// @083: dup
		// @084: bipush 11 (0x0B)
		// @086: ldc "v \u001c\u0012l"
		// @088: invokestatic game.C_100253_ph.func_101086_z(java.lang.String)char[]
		// @08B: invokestatic game.C_100253_ph.func_101083_z(char[])java.lang.String
		// @08E: aastore
		// @08F: dup
		// @090: bipush 12 (0x0C)
		// @092: ldc "v \u001c\u0007l/"
		// @094: invokestatic game.C_100253_ph.func_101086_z(java.lang.String)char[]
		// @097: invokestatic game.C_100253_ph.func_101083_z(char[])java.lang.String
		// @09A: aastore
		// @09B: dup
		// @09C: bipush 13 (0x0D)
		// @09E: ldc "v \u001c\u0006l/"
		// @0A0: invokestatic game.C_100253_ph.func_101086_z(java.lang.String)char[]
		// @0A3: invokestatic game.C_100253_ph.func_101083_z(char[])java.lang.String
		// @0A6: aastore
		// @0A7: dup
		// @0A8: bipush 14 (0x0E)
		// @0AA: ldc "v \u001c\u000bl"
		// @0AC: invokestatic game.C_100253_ph.func_101086_z(java.lang.String)char[]
		// @0AF: invokestatic game.C_100253_ph.func_101083_z(char[])java.lang.String
		// @0B2: aastore
		// @0B3: dup
		// @0B4: bipush 15 (0x0F)
		// @0B6: ldc "v \u001c\u0005l/"
		// @0B8: invokestatic game.C_100253_ph.func_101086_z(java.lang.String)char[]
		// @0BB: invokestatic game.C_100253_ph.func_101083_z(char[])java.lang.String
		// @0BE: aastore
		// @0BF: dup
		// @0C0: bipush 16 (0x10)
		// @0C2: ldc "v \u001c\u0015l"
		// @0C4: invokestatic game.C_100253_ph.func_101086_z(java.lang.String)char[]
		// @0C7: invokestatic game.C_100253_ph.func_101083_z(char[])java.lang.String
		// @0CA: aastore
		// @0CB: dup
		// @0CC: bipush 17 (0x11)
		// @0CE: ldc "v \u001c\nl"
		// @0D0: invokestatic game.C_100253_ph.func_101086_z(java.lang.String)char[]
		// @0D3: invokestatic game.C_100253_ph.func_101083_z(char[])java.lang.String
		// @0D6: aastore
		// @0D7: dup
		// @0D8: bipush 18 (0x12)
		// @0DA: ldc "v \u001c\u0017l"
		// @0DC: invokestatic game.C_100253_ph.func_101086_z(java.lang.String)char[]
		// @0DF: invokestatic game.C_100253_ph.func_101083_z(char[])java.lang.String
		// @0E2: aastore
		// @0E3: dup
		// @0E4: bipush 19 (0x13)
		// @0E6: ldc "v \u001c\u0011l"
		// @0E8: invokestatic game.C_100253_ph.func_101086_z(java.lang.String)char[]
		// @0EB: invokestatic game.C_100253_ph.func_101083_z(char[])java.lang.String
		// @0EE: aastore
		// @0EF: putstatic java.lang.String[] game.C_100253_ph.field_101096_F
		// @0F2: ldc "T-A&%t+Zc-h<]cxe'^~t6.T%\"88^\"7k)\u00124!g8]-7:gQ,(8h[0dh-W'!bhP&\"i:Wc0n-\u0012\u007fa6v\u0012 %hhP&dc&U**c-@& ("
		// @0F4: invokestatic game.C_100253_ph.func_101086_z(java.lang.String)char[]
		// @0F7: invokestatic game.C_100253_ph.func_101083_z(char[])java.lang.String
		// @0FA: putstatic java.lang.String game.C_100253_ph.field_101110_q
		// @0FD: ldc "S&B\"'m!\\$da:S3,o+A"
		// @0FF: invokestatic game.C_100253_ph.func_101086_z(java.lang.String)char[]
		// @102: invokestatic game.C_100253_ph.func_101083_z(char[])java.lang.String
		// @105: putstatic java.lang.String game.C_100253_ph.field_101109_r
		// @108: ldc ":*@}xd:\u000c\u007f'i$\u000f%\"`.T%zR [0du-\\7-h-^c1u-Ac0n-\u0012%+j$]4-h/\u0012"
		// @10A: invokestatic game.C_100253_ph.func_101086_z(java.lang.String)char[]
		// @10D: invokestatic game.C_100253_ph.func_101083_z(char[])java.lang.String
		// @110: putstatic java.lang.String game.C_100253_ph.field_101106_u
		// @113: ldc "Q)@c\ti,W"
		// @115: invokestatic game.C_100253_ph.func_101086_z(java.lang.String)char[]
		// @118: invokestatic game.C_100253_ph.func_101083_z(char[])java.lang.String
		// @11B: putstatic java.lang.String game.C_100253_ph.field_101099_B
		// @11E: return
	}
	
	private static char[] func_101086_z(String arg0)
	{
		// @00: aload_0
		// @01: invokevirtual java.lang.String.toCharArray()char[]
		// @04: dup
		// @05: arraylength
		// @06: iconst_2
		// @07: if_icmpge @13
		// @0A: dup
		// @0B: iconst_0
		// @0C: dup2
		// @0D: caload
		// @0E: bipush 68 (0x44)
		// @10: ixor
		// @11: i2c
		// @12: castore
		// @13: areturn
	}
	
	private static String func_101083_z(char[] arg0)
	{
		// @00: aload_0
		// @01: dup
		// @02: arraylength
		// @03: swap
		// @04: iconst_0
		// @05: istore_1
		// @06: goto @4C
		// @09: dup
		// @0A: iload_1
		// @0B: dup2
		// @0C: caload
		// @0D: iload_1
		// @0E: iconst_5
		// @0F: irem
		// @10: tableswitch def: @44, for 0: @30, for 1: @35, for 2: @3A, for 3: @3F
		// @30: bipush 6 (0x06)
		// @32: goto @46
		// @35: bipush 72 (0x48)
		// @37: goto @46
		// @3A: bipush 50 (0x32)
		// @3C: goto @46
		// @3F: bipush 67 (0x43)
		// @41: goto @46
		// @44: bipush 68 (0x44)
		// @46: ixor
		// @47: i2c
		// @48: castore
		// @49: iinc #1 +1
		// @4C: swap
		// @4D: dup_x1
		// @4E: iload_1
		// @4F: if_icmpgt @09
		// @52: new java.lang.String
		// @55: dup_x1
		// @56: swap
		// @57: invokespecial java.lang.String.<init>(char[])void
		// @5A: invokevirtual java.lang.String.intern()java.lang.String
		// @5D: areturn
	}
}
