package game;

import java.applet.Applet;

final class C_100146_bf
{
	private C_100037_wb field_105126_c;
	private C_100037_wb field_105129_o;
	static C_100217_ao field_105125_b;
	private int field_105138_u;
	private String[] field_105136_w;
	private int field_105141_r;
	private boolean field_105135_i;
	private C_100037_wb field_105130_l;
	private int field_105134_h;
	private C_100153_be[] field_105143_p;
	private int field_105137_v;
	static int field_105132_j;
	private C_100333_ij field_105133_k;
	static String field_105121_f;
	private String field_105142_q;
	static int field_105131_m;
	static int[] field_105122_g;
	private int field_105145_x;
	static C_100009_fg field_105128_n;
	static int field_105139_t;
	static C_100117_p field_105124_e;
	private int field_105140_s;
	static C_100302_ka field_105127_a;
	static String[] field_105123_d;
	private static final String[] field_105144_z;
	
	private final void func_105119_a(byte arg0, int arg1, int arg2, String arg3, C_100112_r arg4, int[] arg5, int arg6, int arg7)
	{
		// @000: getstatic int game.SteelSentinels.field_105275_O
		// @003: istore #12
		// @005: bipush -46 (0xD2)
		// @007: invokestatic game.C_100328_ia.func_107254_b(byte)void
		// @00A: iload_1
		// @00B: bipush -14 (0xF2)
		// @00D: if_icmple @01A
		// @010: aload_0
		// @011: bipush 123 (0x7B)
		// @013: putfield int game.C_100146_bf.field_105137_v
		// @016: goto @01A
		// @019: athrow
		// @01A: iload #8
		// @01C: istore #9
		// @01E: iload #9
		// @020: iload #7
		// @022: if_icmpge @06E
		// @025: iload_2
		// @026: iload #9
		// @028: iload_3
		// @029: iconst_1
		// @02A: iload #9
		// @02C: iadd
		// @02D: invokestatic game.C_100196_rb.func_105815_h(int, int, int, int)void
		// @030: aload #6
		// @032: arraylength
		// @033: iload #9
		// @035: imul
		// @036: iload #7
		// @038: idiv
		// @039: istore #10
		// @03B: aload #6
		// @03D: iconst_m1
		// @03E: iload #10
		// @040: ineg
		// @041: iadd
		// @042: aload #6
		// @044: arraylength
		// @045: iadd
		// @046: iaload
		// @047: istore #11
		// @049: aload #5
		// @04B: aload #4
		// @04D: iload_2
		// @04E: iload #8
		// @050: iload_3
		// @051: iload #7
		// @053: iload #11
		// @055: iconst_m1
		// @056: iconst_1
		// @057: iconst_1
		// @058: iconst_0
		// @059: invokevirtual game.C_100112_r.func_101729_a(java.lang.String, int, int, int, int, int, int, int, int, int)int
		// @05C: pop
		// @05D: iinc #9 +1
		// @060: iload #12
		// @062: ifne @073
		// @065: iload #12
		// @067: ifeq @01E
		// @06A: goto @06E
		// @06D: athrow
		// @06E: bipush -77 (0xB3)
		// @070: invokestatic game.C_100200_ba.func_105842_a(byte)void
		// @073: goto @111
		// @076: astore #9
		// @078: aload #9
		// @07A: new java.lang.StringBuilder
		// @07D: dup
		// @07E: invokespecial java.lang.StringBuilder.<init>()void
		// @081: getstatic java.lang.String[] game.C_100146_bf.field_105144_z
		// @084: bipush 20 (0x14)
		// @086: aaload
		// @087: invokevirtual java.lang.StringBuilder.append(java.lang.String)java.lang.StringBuilder
		// @08A: iload_1
		// @08B: invokevirtual java.lang.StringBuilder.append(int)java.lang.StringBuilder
		// @08E: bipush 44 (0x2C)
		// @090: invokevirtual java.lang.StringBuilder.append(char)java.lang.StringBuilder
		// @093: iload_2
		// @094: invokevirtual java.lang.StringBuilder.append(int)java.lang.StringBuilder
		// @097: bipush 44 (0x2C)
		// @099: invokevirtual java.lang.StringBuilder.append(char)java.lang.StringBuilder
		// @09C: iload_3
		// @09D: invokevirtual java.lang.StringBuilder.append(int)java.lang.StringBuilder
		// @0A0: bipush 44 (0x2C)
		// @0A2: invokevirtual java.lang.StringBuilder.append(char)java.lang.StringBuilder
		// @0A5: aload #4
		// @0A7: ifnull @0B3
		// @0AA: getstatic java.lang.String[] game.C_100146_bf.field_105144_z
		// @0AD: iconst_3
		// @0AE: aaload
		// @0AF: goto @0B8
		// @0B2: athrow
		// @0B3: getstatic java.lang.String[] game.C_100146_bf.field_105144_z
		// @0B6: iconst_1
		// @0B7: aaload
		// @0B8: invokevirtual java.lang.StringBuilder.append(java.lang.String)java.lang.StringBuilder
		// @0BB: bipush 44 (0x2C)
		// @0BD: invokevirtual java.lang.StringBuilder.append(char)java.lang.StringBuilder
		// @0C0: aload #5
		// @0C2: ifnull @0CE
		// @0C5: getstatic java.lang.String[] game.C_100146_bf.field_105144_z
		// @0C8: iconst_3
		// @0C9: aaload
		// @0CA: goto @0D3
		// @0CD: athrow
		// @0CE: getstatic java.lang.String[] game.C_100146_bf.field_105144_z
		// @0D1: iconst_1
		// @0D2: aaload
		// @0D3: invokevirtual java.lang.StringBuilder.append(java.lang.String)java.lang.StringBuilder
		// @0D6: bipush 44 (0x2C)
		// @0D8: invokevirtual java.lang.StringBuilder.append(char)java.lang.StringBuilder
		// @0DB: aload #6
		// @0DD: ifnull @0E9
		// @0E0: getstatic java.lang.String[] game.C_100146_bf.field_105144_z
		// @0E3: iconst_3
		// @0E4: aaload
		// @0E5: goto @0EE
		// @0E8: athrow
		// @0E9: getstatic java.lang.String[] game.C_100146_bf.field_105144_z
		// @0EC: iconst_1
		// @0ED: aaload
		// @0EE: invokevirtual java.lang.StringBuilder.append(java.lang.String)java.lang.StringBuilder
		// @0F1: bipush 44 (0x2C)
		// @0F3: invokevirtual java.lang.StringBuilder.append(char)java.lang.StringBuilder
		// @0F6: iload #7
		// @0F8: invokevirtual java.lang.StringBuilder.append(int)java.lang.StringBuilder
		// @0FB: bipush 44 (0x2C)
		// @0FD: invokevirtual java.lang.StringBuilder.append(char)java.lang.StringBuilder
		// @100: iload #8
		// @102: invokevirtual java.lang.StringBuilder.append(int)java.lang.StringBuilder
		// @105: bipush 41 (0x29)
		// @107: invokevirtual java.lang.StringBuilder.append(char)java.lang.StringBuilder
		// @10A: invokevirtual java.lang.StringBuilder.toString()java.lang.String
		// @10D: invokestatic game.C_100181_cf.func_105695_a(java.lang.Throwable, java.lang.String)game.C_100170_cm
		// @110: athrow
		// @111: return
	}
	
	private final void func_105115_a(String arg0, String[] arg1, C_100153_be[] arg2, Applet arg3, boolean arg4, int arg5)
	{
		// @000: iload #6
		// @002: sipush 26917 (0x6925)
		// @005: if_icmpeq @009
		// @008: return
		// @009: aload #4
		// @00B: getstatic java.lang.String[] game.C_100146_bf.field_105144_z
		// @00E: bipush 17 (0x11)
		// @010: aaload
		// @011: invokevirtual java.applet.Applet.getParameter(java.lang.String)java.lang.String
		// @014: astore #7
		// @016: aload #7
		// @018: ifnull @028
		// @01B: iconst_1
		// @01C: aload #7
		// @01E: invokestatic game.C_100298_ke.func_103205_a(boolean, java.lang.CharSequence)boolean
		// @021: ifne @037
		// @024: goto @028
		// @027: athrow
		// @028: aload_0
		// @029: iconst_2
		// @02A: putfield int game.C_100146_bf.field_105138_u
		// @02D: getstatic int game.SteelSentinels.field_105275_O
		// @030: ifeq @046
		// @033: goto @037
		// @036: athrow
		// @037: aload_0
		// @038: aload #7
		// @03A: bipush -118 (0x8A)
		// @03C: invokestatic game.C_100001_ge.func_100552_a(java.lang.CharSequence, int)int
		// @03F: putfield int game.C_100146_bf.field_105138_u
		// @042: goto @046
		// @045: athrow
		// @046: aload_0
		// @047: aload_1
		// @048: putfield java.lang.String game.C_100146_bf.field_105142_q
		// @04B: aload_0
		// @04C: new game.C_100333_ij
		// @04F: dup
		// @050: iconst_2
		// @051: invokespecial game.C_100333_ij.<init>(int)void
		// @054: putfield game.C_100333_ij game.C_100146_bf.field_105133_k
		// @057: aload_0
		// @058: aload_3
		// @059: putfield game.C_100153_be[] game.C_100146_bf.field_105143_p
		// @05C: aload_0
		// @05D: aload_2
		// @05E: putfield java.lang.String[] game.C_100146_bf.field_105136_w
		// @061: aconst_null
		// @062: aload_0
		// @063: getfield game.C_100153_be[] game.C_100146_bf.field_105143_p
		// @066: if_acmpeq @07D
		// @069: aload_0
		// @06A: getfield game.C_100153_be[] game.C_100146_bf.field_105143_p
		// @06D: arraylength
		// @06E: iconst_m1
		// @06F: ixor
		// @070: bipush -4 (0xFC)
		// @072: if_icmpgt @07D
		// @075: goto @079
		// @078: athrow
		// @079: goto @087
		// @07C: athrow
		// @07D: new java.lang.IllegalArgumentException
		// @080: dup
		// @081: ldc ""
		// @083: invokespecial java.lang.IllegalArgumentException.<init>(java.lang.String)void
		// @086: athrow
		// @087: iload #5
		// @089: putstatic boolean game.C_100121_ud.field_100716_G
		// @08C: goto @127
		// @08F: astore #7
		// @091: aload #7
		// @093: new java.lang.StringBuilder
		// @096: dup
		// @097: invokespecial java.lang.StringBuilder.<init>()void
		// @09A: getstatic java.lang.String[] game.C_100146_bf.field_105144_z
		// @09D: bipush 18 (0x12)
		// @09F: aaload
		// @0A0: invokevirtual java.lang.StringBuilder.append(java.lang.String)java.lang.StringBuilder
		// @0A3: aload_1
		// @0A4: ifnull @0B0
		// @0A7: getstatic java.lang.String[] game.C_100146_bf.field_105144_z
		// @0AA: iconst_3
		// @0AB: aaload
		// @0AC: goto @0B5
		// @0AF: athrow
		// @0B0: getstatic java.lang.String[] game.C_100146_bf.field_105144_z
		// @0B3: iconst_1
		// @0B4: aaload
		// @0B5: invokevirtual java.lang.StringBuilder.append(java.lang.String)java.lang.StringBuilder
		// @0B8: bipush 44 (0x2C)
		// @0BA: invokevirtual java.lang.StringBuilder.append(char)java.lang.StringBuilder
		// @0BD: aload_2
		// @0BE: ifnull @0CA
		// @0C1: getstatic java.lang.String[] game.C_100146_bf.field_105144_z
		// @0C4: iconst_3
		// @0C5: aaload
		// @0C6: goto @0CF
		// @0C9: athrow
		// @0CA: getstatic java.lang.String[] game.C_100146_bf.field_105144_z
		// @0CD: iconst_1
		// @0CE: aaload
		// @0CF: invokevirtual java.lang.StringBuilder.append(java.lang.String)java.lang.StringBuilder
		// @0D2: bipush 44 (0x2C)
		// @0D4: invokevirtual java.lang.StringBuilder.append(char)java.lang.StringBuilder
		// @0D7: aload_3
		// @0D8: ifnull @0E4
		// @0DB: getstatic java.lang.String[] game.C_100146_bf.field_105144_z
		// @0DE: iconst_3
		// @0DF: aaload
		// @0E0: goto @0E9
		// @0E3: athrow
		// @0E4: getstatic java.lang.String[] game.C_100146_bf.field_105144_z
		// @0E7: iconst_1
		// @0E8: aaload
		// @0E9: invokevirtual java.lang.StringBuilder.append(java.lang.String)java.lang.StringBuilder
		// @0EC: bipush 44 (0x2C)
		// @0EE: invokevirtual java.lang.StringBuilder.append(char)java.lang.StringBuilder
		// @0F1: aload #4
		// @0F3: ifnull @0FF
		// @0F6: getstatic java.lang.String[] game.C_100146_bf.field_105144_z
		// @0F9: iconst_3
		// @0FA: aaload
		// @0FB: goto @104
		// @0FE: athrow
		// @0FF: getstatic java.lang.String[] game.C_100146_bf.field_105144_z
		// @102: iconst_1
		// @103: aaload
		// @104: invokevirtual java.lang.StringBuilder.append(java.lang.String)java.lang.StringBuilder
		// @107: bipush 44 (0x2C)
		// @109: invokevirtual java.lang.StringBuilder.append(char)java.lang.StringBuilder
		// @10C: iload #5
		// @10E: invokevirtual java.lang.StringBuilder.append(boolean)java.lang.StringBuilder
		// @111: bipush 44 (0x2C)
		// @113: invokevirtual java.lang.StringBuilder.append(char)java.lang.StringBuilder
		// @116: iload #6
		// @118: invokevirtual java.lang.StringBuilder.append(int)java.lang.StringBuilder
		// @11B: bipush 41 (0x29)
		// @11D: invokevirtual java.lang.StringBuilder.append(char)java.lang.StringBuilder
		// @120: invokevirtual java.lang.StringBuilder.toString()java.lang.String
		// @123: invokestatic game.C_100181_cf.func_105695_a(java.lang.Throwable, java.lang.String)game.C_100170_cm
		// @126: athrow
		// @127: return
	}
	
	private final int func_105107_c(int arg0)
	{
		// @00: aload_0
		// @01: getfield game.C_100333_ij game.C_100146_bf.field_105133_k
		// @04: bipush -70 (0xBA)
		// @06: invokevirtual game.C_100333_ij.func_107328_a(int)void
		// @09: aload_0
		// @0A: getfield game.C_100333_ij game.C_100146_bf.field_105133_k
		// @0D: iconst_1
		// @0E: invokevirtual game.C_100333_ij.func_107339_b(boolean)boolean
		// @11: ifeq @42
		// @14: iconst_m1
		// @15: aload_0
		// @16: getfield game.C_100333_ij game.C_100146_bf.field_105133_k
		// @19: getfield int game.C_100333_ij.field_107347_b
		// @1C: iconst_m1
		// @1D: ixor
		// @1E: if_icmpeq @29
		// @21: goto @25
		// @24: athrow
		// @25: goto @32
		// @28: athrow
		// @29: aload_0
		// @2A: sipush 12410 (0x307A)
		// @2D: invokespecial game.C_100146_bf.func_105110_a(int)void
		// @30: iconst_3
		// @31: ireturn
		// @32: bipush -2 (0xFE)
		// @34: aload_0
		// @35: getfield game.C_100333_ij game.C_100146_bf.field_105133_k
		// @38: getfield int game.C_100333_ij.field_107347_b
		// @3B: iconst_m1
		// @3C: ixor
		// @3D: if_icmpne @42
		// @40: iconst_1
		// @41: ireturn
		// @42: getstatic int game.C_100293_kj.field_106890_c
		// @45: iconst_m1
		// @46: ixor
		// @47: bipush -14 (0xF2)
		// @49: if_icmpne @4E
		// @4C: iconst_1
		// @4D: ireturn
		// @4E: iload_1
		// @4F: sipush 14109 (0x371D)
		// @52: if_icmpeq @58
		// @55: bipush -99 (0x9D)
		// @57: ireturn
		// @58: iconst_0
		// @59: ireturn
		// @5A: astore_2
		// @5B: aload_2
		// @5C: new java.lang.StringBuilder
		// @5F: dup
		// @60: invokespecial java.lang.StringBuilder.<init>()void
		// @63: getstatic java.lang.String[] game.C_100146_bf.field_105144_z
		// @66: bipush 19 (0x13)
		// @68: aaload
		// @69: invokevirtual java.lang.StringBuilder.append(java.lang.String)java.lang.StringBuilder
		// @6C: iload_1
		// @6D: invokevirtual java.lang.StringBuilder.append(int)java.lang.StringBuilder
		// @70: bipush 41 (0x29)
		// @72: invokevirtual java.lang.StringBuilder.append(char)java.lang.StringBuilder
		// @75: invokevirtual java.lang.StringBuilder.toString()java.lang.String
		// @78: invokestatic game.C_100181_cf.func_105695_a(java.lang.Throwable, java.lang.String)game.C_100170_cm
		// @7B: athrow
	}
	
	private final void func_105120_a(int[] arg0, int arg1, int arg2, int arg3, int arg4, int arg5, float arg6, C_100112_r arg7, String arg8, C_100037_wb arg9)
	{
		// @000: iload_3
		// @001: bipush -14 (0xF2)
		// @003: if_icmple @010
		// @006: aload_0
		// @007: bipush -39 (0xD9)
		// @009: putfield int game.C_100146_bf.field_105134_h
		// @00C: goto @010
		// @00F: athrow
		// @010: iload #5
		// @012: i2f
		// @013: fload #7
		// @015: fdiv
		// @016: f2i
		// @017: istore #11
		// @019: iload #6
		// @01B: i2f
		// @01C: fload #7
		// @01E: fdiv
		// @01F: f2i
		// @020: istore #12
		// @022: new game.C_100037_wb
		// @025: dup
		// @026: iload #11
		// @028: iload #12
		// @02A: invokespecial game.C_100037_wb.<init>(int, int)void
		// @02D: astore #13
		// @02F: aload #13
		// @031: bipush -4 (0xFC)
		// @033: invokestatic game.C_100138_bo.func_100398_a(game.C_100037_wb, int)void
		// @036: aload #10
		// @038: iload_2
		// @039: ineg
		// @03A: i2f
		// @03B: fload #7
		// @03D: fdiv
		// @03E: f2i
		// @03F: iload #4
		// @041: ineg
		// @042: i2f
		// @043: fload #7
		// @045: fdiv
		// @046: f2i
		// @047: aload #10
		// @049: getfield int game.C_100037_wb.field_102339_s
		// @04C: i2f
		// @04D: fload #7
		// @04F: fdiv
		// @050: f2i
		// @051: aload #10
		// @053: getfield int game.C_100037_wb.field_102337_u
		// @056: i2f
		// @057: fload #7
		// @059: fdiv
		// @05A: f2i
		// @05B: invokevirtual game.C_100037_wb.func_102364_d(int, int, int, int)void
		// @05E: aload_0
		// @05F: bipush -48 (0xD0)
		// @061: iconst_0
		// @062: iload #11
		// @064: aload #9
		// @066: aload #8
		// @068: aload_1
		// @069: iload #12
		// @06B: iconst_0
		// @06C: invokespecial game.C_100146_bf.func_105119_a(byte, int, int, java.lang.String, game.C_100112_r, int[], int, int)void
		// @06F: bipush -77 (0xB3)
		// @071: invokestatic game.C_100200_ba.func_105842_a(byte)void
		// @074: aload #10
		// @076: bipush -4 (0xFC)
		// @078: invokestatic game.C_100138_bo.func_100398_a(game.C_100037_wb, int)void
		// @07B: aload #13
		// @07D: iload_2
		// @07E: iload #4
		// @080: iload #5
		// @082: iload #6
		// @084: invokevirtual game.C_100037_wb.func_102345_a(int, int, int, int)void
		// @087: bipush -77 (0xB3)
		// @089: invokestatic game.C_100200_ba.func_105842_a(byte)void
		// @08C: goto @14F
		// @08F: astore #11
		// @091: aload #11
		// @093: new java.lang.StringBuilder
		// @096: dup
		// @097: invokespecial java.lang.StringBuilder.<init>()void
		// @09A: getstatic java.lang.String[] game.C_100146_bf.field_105144_z
		// @09D: bipush 16 (0x10)
		// @09F: aaload
		// @0A0: invokevirtual java.lang.StringBuilder.append(java.lang.String)java.lang.StringBuilder
		// @0A3: aload_1
		// @0A4: ifnull @0B0
		// @0A7: getstatic java.lang.String[] game.C_100146_bf.field_105144_z
		// @0AA: iconst_3
		// @0AB: aaload
		// @0AC: goto @0B5
		// @0AF: athrow
		// @0B0: getstatic java.lang.String[] game.C_100146_bf.field_105144_z
		// @0B3: iconst_1
		// @0B4: aaload
		// @0B5: invokevirtual java.lang.StringBuilder.append(java.lang.String)java.lang.StringBuilder
		// @0B8: bipush 44 (0x2C)
		// @0BA: invokevirtual java.lang.StringBuilder.append(char)java.lang.StringBuilder
		// @0BD: iload_2
		// @0BE: invokevirtual java.lang.StringBuilder.append(int)java.lang.StringBuilder
		// @0C1: bipush 44 (0x2C)
		// @0C3: invokevirtual java.lang.StringBuilder.append(char)java.lang.StringBuilder
		// @0C6: iload_3
		// @0C7: invokevirtual java.lang.StringBuilder.append(int)java.lang.StringBuilder
		// @0CA: bipush 44 (0x2C)
		// @0CC: invokevirtual java.lang.StringBuilder.append(char)java.lang.StringBuilder
		// @0CF: iload #4
		// @0D1: invokevirtual java.lang.StringBuilder.append(int)java.lang.StringBuilder
		// @0D4: bipush 44 (0x2C)
		// @0D6: invokevirtual java.lang.StringBuilder.append(char)java.lang.StringBuilder
		// @0D9: iload #5
		// @0DB: invokevirtual java.lang.StringBuilder.append(int)java.lang.StringBuilder
		// @0DE: bipush 44 (0x2C)
		// @0E0: invokevirtual java.lang.StringBuilder.append(char)java.lang.StringBuilder
		// @0E3: iload #6
		// @0E5: invokevirtual java.lang.StringBuilder.append(int)java.lang.StringBuilder
		// @0E8: bipush 44 (0x2C)
		// @0EA: invokevirtual java.lang.StringBuilder.append(char)java.lang.StringBuilder
		// @0ED: fload #7
		// @0EF: invokevirtual java.lang.StringBuilder.append(float)java.lang.StringBuilder
		// @0F2: bipush 44 (0x2C)
		// @0F4: invokevirtual java.lang.StringBuilder.append(char)java.lang.StringBuilder
		// @0F7: aload #8
		// @0F9: ifnull @105
		// @0FC: getstatic java.lang.String[] game.C_100146_bf.field_105144_z
		// @0FF: iconst_3
		// @100: aaload
		// @101: goto @10A
		// @104: athrow
		// @105: getstatic java.lang.String[] game.C_100146_bf.field_105144_z
		// @108: iconst_1
		// @109: aaload
		// @10A: invokevirtual java.lang.StringBuilder.append(java.lang.String)java.lang.StringBuilder
		// @10D: bipush 44 (0x2C)
		// @10F: invokevirtual java.lang.StringBuilder.append(char)java.lang.StringBuilder
		// @112: aload #9
		// @114: ifnull @120
		// @117: getstatic java.lang.String[] game.C_100146_bf.field_105144_z
		// @11A: iconst_3
		// @11B: aaload
		// @11C: goto @125
		// @11F: athrow
		// @120: getstatic java.lang.String[] game.C_100146_bf.field_105144_z
		// @123: iconst_1
		// @124: aaload
		// @125: invokevirtual java.lang.StringBuilder.append(java.lang.String)java.lang.StringBuilder
		// @128: bipush 44 (0x2C)
		// @12A: invokevirtual java.lang.StringBuilder.append(char)java.lang.StringBuilder
		// @12D: aload #10
		// @12F: ifnull @13B
		// @132: getstatic java.lang.String[] game.C_100146_bf.field_105144_z
		// @135: iconst_3
		// @136: aaload
		// @137: goto @140
		// @13A: athrow
		// @13B: getstatic java.lang.String[] game.C_100146_bf.field_105144_z
		// @13E: iconst_1
		// @13F: aaload
		// @140: invokevirtual java.lang.StringBuilder.append(java.lang.String)java.lang.StringBuilder
		// @143: bipush 41 (0x29)
		// @145: invokevirtual java.lang.StringBuilder.append(char)java.lang.StringBuilder
		// @148: invokevirtual java.lang.StringBuilder.toString()java.lang.String
		// @14B: invokestatic game.C_100181_cf.func_105695_a(java.lang.Throwable, java.lang.String)game.C_100170_cm
		// @14E: athrow
		// @14F: return
	}
	
	final int func_105112_a(boolean arg0, byte arg1)
	{
		// @000: getstatic int game.SteelSentinels.field_105275_O
		// @003: istore #7
		// @005: aload_0
		// @006: dup
		// @007: getfield int game.C_100146_bf.field_105140_s
		// @00A: ldc 65536 (0x10000)
		// @00C: iadd
		// @00D: putfield int game.C_100146_bf.field_105140_s
		// @010: ldc -65537 (0xfffeffff)
		// @012: getstatic int game.C_100031_gl.field_103966_b
		// @015: aload_0
		// @016: getfield int game.C_100146_bf.field_105140_s
		// @019: bipush -65 (0xBF)
		// @01B: invokestatic game.C_100087_n.func_100684_a(int, int, byte)int
		// @01E: iconst_m1
		// @01F: ixor
		// @020: if_icmplt @03E
		// @023: aload_0
		// @024: dup
		// @025: getfield int game.C_100146_bf.field_105140_s
		// @028: getstatic int game.C_100031_gl.field_103966_b
		// @02B: isub
		// @02C: putfield int game.C_100146_bf.field_105140_s
		// @02F: aload_0
		// @030: dup
		// @031: getfield int game.C_100146_bf.field_105134_h
		// @034: iconst_1
		// @035: iadd
		// @036: putfield int game.C_100146_bf.field_105134_h
		// @039: iload #7
		// @03B: ifeq @010
		// @03E: iconst_m1
		// @03F: istore_3
		// @040: aload_0
		// @041: getfield game.C_100153_be[] game.C_100146_bf.field_105143_p
		// @044: ifnonnull @04B
		// @047: goto @051
		// @04A: athrow
		// @04B: aload_0
		// @04C: getfield game.C_100153_be[] game.C_100146_bf.field_105143_p
		// @04F: arraylength
		// @050: istore_3
		// @051: iload_3
		// @052: iconst_m1
		// @053: ixor
		// @054: ifne @05B
		// @057: goto @16C
		// @05A: athrow
		// @05B: aload_0
		// @05C: getfield int game.C_100146_bf.field_105137_v
		// @05F: getstatic int game.C_100031_gl.field_103969_j
		// @062: if_icmpge @0DD
		// @065: aload_0
		// @066: dup
		// @067: getfield int game.C_100146_bf.field_105137_v
		// @06A: iconst_1
		// @06B: iadd
		// @06C: putfield int game.C_100146_bf.field_105137_v
		// @06F: getstatic int game.C_100031_gl.field_103962_f
		// @072: aload_0
		// @073: getfield int game.C_100146_bf.field_105137_v
		// @076: if_icmpge @0AC
		// @079: goto @07D
		// @07C: athrow
		// @07D: aconst_null
		// @07E: aload_0
		// @07F: getfield game.C_100153_be[] game.C_100146_bf.field_105143_p
		// @082: if_acmpeq @099
		// @085: goto @089
		// @088: athrow
		// @089: aload_0
		// @08A: getfield game.C_100153_be[] game.C_100146_bf.field_105143_p
		// @08D: aload_0
		// @08E: getfield int game.C_100146_bf.field_105141_r
		// @091: aaload
		// @092: ifnonnull @0AC
		// @095: goto @099
		// @098: athrow
		// @099: aload_0
		// @09A: dup
		// @09B: getfield int game.C_100146_bf.field_105137_v
		// @09E: iconst_1
		// @09F: isub
		// @0A0: putfield int game.C_100146_bf.field_105137_v
		// @0A3: iload #7
		// @0A5: ifeq @0DD
		// @0A8: goto @0AC
		// @0AB: athrow
		// @0AC: getstatic int game.C_100031_gl.field_103969_j
		// @0AF: aload_0
		// @0B0: getfield int game.C_100146_bf.field_105137_v
		// @0B3: if_icmpgt @0DD
		// @0B6: goto @0BA
		// @0B9: athrow
		// @0BA: aconst_null
		// @0BB: aload_0
		// @0BC: getfield game.C_100153_be[] game.C_100146_bf.field_105143_p
		// @0BF: iconst_1
		// @0C0: aload_0
		// @0C1: getfield int game.C_100146_bf.field_105141_r
		// @0C4: iadd
		// @0C5: iload_3
		// @0C6: irem
		// @0C7: aaload
		// @0C8: if_acmpne @0DD
		// @0CB: goto @0CF
		// @0CE: athrow
		// @0CF: aload_0
		// @0D0: dup
		// @0D1: getfield int game.C_100146_bf.field_105137_v
		// @0D4: iconst_1
		// @0D5: isub
		// @0D6: putfield int game.C_100146_bf.field_105137_v
		// @0D9: goto @0DD
		// @0DC: athrow
		// @0DD: aload_0
		// @0DE: getfield int game.C_100146_bf.field_105137_v
		// @0E1: getstatic int game.C_100031_gl.field_103969_j
		// @0E4: if_icmplt @159
		// @0E7: aload_0
		// @0E8: aload_0
		// @0E9: getfield int game.C_100146_bf.field_105141_r
		// @0EC: putfield int game.C_100146_bf.field_105145_x
		// @0EF: aload_0
		// @0F0: dup
		// @0F1: getfield int game.C_100146_bf.field_105137_v
		// @0F4: getstatic int game.C_100031_gl.field_103969_j
		// @0F7: isub
		// @0F8: putfield int game.C_100146_bf.field_105137_v
		// @0FB: aload_0
		// @0FC: getfield boolean game.C_100146_bf.field_105135_i
		// @0FF: ifne @131
		// @102: goto @106
		// @105: athrow
		// @106: aload_0
		// @107: dup
		// @108: getfield int game.C_100146_bf.field_105141_r
		// @10B: iconst_1
		// @10C: isub
		// @10D: putfield int game.C_100146_bf.field_105141_r
		// @110: aload_0
		// @111: getfield int game.C_100146_bf.field_105141_r
		// @114: iconst_m1
		// @115: ixor
		// @116: iconst_m1
		// @117: if_icmpgt @122
		// @11A: goto @11E
		// @11D: athrow
		// @11E: goto @159
		// @121: athrow
		// @122: aload_0
		// @123: dup
		// @124: getfield int game.C_100146_bf.field_105141_r
		// @127: iload_3
		// @128: iadd
		// @129: putfield int game.C_100146_bf.field_105141_r
		// @12C: iload #7
		// @12E: ifeq @159
		// @131: aload_0
		// @132: dup
		// @133: getfield int game.C_100146_bf.field_105141_r
		// @136: iconst_1
		// @137: iadd
		// @138: putfield int game.C_100146_bf.field_105141_r
		// @13B: aload_0
		// @13C: getfield int game.C_100146_bf.field_105141_r
		// @13F: iconst_m1
		// @140: ixor
		// @141: iload_3
		// @142: iconst_m1
		// @143: ixor
		// @144: if_icmple @14F
		// @147: goto @14B
		// @14A: athrow
		// @14B: goto @159
		// @14E: athrow
		// @14F: aload_0
		// @150: dup
		// @151: getfield int game.C_100146_bf.field_105141_r
		// @154: iload_3
		// @155: isub
		// @156: putfield int game.C_100146_bf.field_105141_r
		// @159: aload_0
		// @15A: getfield int game.C_100146_bf.field_105137_v
		// @15D: getstatic int game.C_100031_gl.field_103962_f
		// @160: if_icmple @16C
		// @163: aload_0
		// @164: iconst_1
		// @165: putfield boolean game.C_100146_bf.field_105135_i
		// @168: goto @16C
		// @16B: athrow
		// @16C: bipush 7 (0x07)
		// @16E: bipush 81 (0x51)
		// @170: iload_2
		// @171: isub
		// @172: bipush 34 (0x22)
		// @174: idiv
		// @175: idiv
		// @176: istore #4
		// @178: aconst_null
		// @179: getstatic game.C_100037_wb game.C_100195_rc.field_105772_b
		// @17C: if_acmpeq @27B
		// @17F: iconst_0
		// @180: istore #5
		// @182: getstatic int game.C_100102_w.field_104636_c
		// @185: ifeq @200
		// @188: sipush -258 (0xFEFE)
		// @18B: getstatic int game.C_100125_tm.field_100745_p
		// @18E: iconst_m1
		// @18F: ixor
		// @190: if_icmple @200
		// @193: goto @197
		// @196: athrow
		// @197: getstatic int game.C_100125_tm.field_100745_p
		// @19A: iconst_m1
		// @19B: ixor
		// @19C: sipush -291 (0xFEDD)
		// @19F: if_icmple @200
		// @1A2: goto @1A6
		// @1A5: athrow
		// @1A6: bipush 9 (0x09)
		// @1A8: getstatic int game.C_100340_je.field_102981_m
		// @1AB: if_icmpge @1D3
		// @1AE: goto @1B2
		// @1B1: athrow
		// @1B2: getstatic int game.C_100340_je.field_102981_m
		// @1B5: iconst_m1
		// @1B6: ixor
		// @1B7: bipush -83 (0xAD)
		// @1B9: if_icmpgt @1C4
		// @1BC: goto @1C0
		// @1BF: athrow
		// @1C0: goto @1D3
		// @1C3: athrow
		// @1C4: iconst_1
		// @1C5: istore #5
		// @1C7: aload_0
		// @1C8: iconst_0
		// @1C9: putfield boolean game.C_100146_bf.field_105135_i
		// @1CC: aload_0
		// @1CD: getstatic int game.C_100031_gl.field_103969_j
		// @1D0: putfield int game.C_100146_bf.field_105137_v
		// @1D3: getstatic int game.C_100340_je.field_102981_m
		// @1D6: iconst_m1
		// @1D7: ixor
		// @1D8: sipush -559 (0xFDD1)
		// @1DB: if_icmpge @200
		// @1DE: sipush -632 (0xFD88)
		// @1E1: getstatic int game.C_100340_je.field_102981_m
		// @1E4: iconst_m1
		// @1E5: ixor
		// @1E6: if_icmplt @1F1
		// @1E9: goto @1ED
		// @1EC: athrow
		// @1ED: goto @200
		// @1F0: athrow
		// @1F1: aload_0
		// @1F2: getstatic int game.C_100031_gl.field_103969_j
		// @1F5: putfield int game.C_100146_bf.field_105137_v
		// @1F8: aload_0
		// @1F9: iconst_1
		// @1FA: putfield boolean game.C_100146_bf.field_105135_i
		// @1FD: iconst_1
		// @1FE: istore #5
		// @200: iload #5
		// @202: ifne @27B
		// @205: aload_0
		// @206: getfield int game.C_100146_bf.field_105137_v
		// @209: iconst_m1
		// @20A: ixor
		// @20B: getstatic int game.C_100031_gl.field_103962_f
		// @20E: iconst_m1
		// @20F: ixor
		// @210: if_icmpge @27B
		// @213: goto @217
		// @216: athrow
		// @217: sipush -258 (0xFEFE)
		// @21A: getstatic int game.C_100125_tm.field_100745_p
		// @21D: iconst_m1
		// @21E: ixor
		// @21F: if_icmple @27B
		// @222: goto @226
		// @225: athrow
		// @226: getstatic int game.C_100125_tm.field_100745_p
		// @229: sipush 290 (0x0122)
		// @22C: if_icmpge @27B
		// @22F: goto @233
		// @232: athrow
		// @233: getstatic int game.C_100015_wh.field_103781_g
		// @236: bipush 9 (0x09)
		// @238: if_icmple @256
		// @23B: goto @23F
		// @23E: athrow
		// @23F: getstatic int game.C_100015_wh.field_103781_g
		// @242: bipush 82 (0x52)
		// @244: if_icmpge @256
		// @247: goto @24B
		// @24A: athrow
		// @24B: aload_0
		// @24C: getstatic int game.C_100031_gl.field_103962_f
		// @24F: putfield int game.C_100146_bf.field_105137_v
		// @252: goto @256
		// @255: athrow
		// @256: getstatic int game.C_100015_wh.field_103781_g
		// @259: iconst_m1
		// @25A: ixor
		// @25B: sipush -559 (0xFDD1)
		// @25E: if_icmpge @27B
		// @261: sipush -632 (0xFD88)
		// @264: getstatic int game.C_100015_wh.field_103781_g
		// @267: iconst_m1
		// @268: ixor
		// @269: if_icmplt @274
		// @26C: goto @270
		// @26F: athrow
		// @270: goto @27B
		// @273: athrow
		// @274: aload_0
		// @275: getstatic int game.C_100031_gl.field_103962_f
		// @278: putfield int game.C_100146_bf.field_105137_v
		// @27B: iload_1
		// @27C: ifeq @312
		// @27F: aload_0
		// @280: getfield game.C_100333_ij game.C_100146_bf.field_105133_k
		// @283: bipush 120 (0x78)
		// @285: aload_0
		// @286: getstatic int game.C_100125_tm.field_100745_p
		// @289: bipush 121 (0x79)
		// @28B: getstatic int game.C_100340_je.field_102981_m
		// @28E: invokespecial game.C_100146_bf.func_105109_a(int, int, int)int
		// @291: aload_0
		// @292: getstatic int game.C_100338_jc.field_105370_l
		// @295: bipush 127 (0x7F)
		// @297: getstatic int game.C_100015_wh.field_103781_g
		// @29A: invokespecial game.C_100146_bf.func_105109_a(int, int, int)int
		// @29D: invokevirtual game.C_100333_ij.func_107335_a(int, int, int)void
		// @2A0: iconst_0
		// @2A1: istore #5
		// @2A3: aload_0
		// @2A4: getfield game.C_100333_ij game.C_100146_bf.field_105133_k
		// @2A7: iconst_1
		// @2A8: invokevirtual game.C_100333_ij.func_107339_b(boolean)boolean
		// @2AB: ifne @2B2
		// @2AE: goto @2D0
		// @2B1: athrow
		// @2B2: iconst_0
		// @2B3: aload_0
		// @2B4: getfield game.C_100333_ij game.C_100146_bf.field_105133_k
		// @2B7: getfield int game.C_100333_ij.field_107347_b
		// @2BA: if_icmpne @2C0
		// @2BD: iconst_1
		// @2BE: istore #5
		// @2C0: aload_0
		// @2C1: getfield game.C_100333_ij game.C_100146_bf.field_105133_k
		// @2C4: getfield int game.C_100333_ij.field_107347_b
		// @2C7: iconst_m1
		// @2C8: ixor
		// @2C9: bipush -2 (0xFE)
		// @2CB: if_icmpne @2D0
		// @2CE: iconst_2
		// @2CF: ireturn
		// @2D0: getstatic boolean game.C_100121_ud.field_100716_G
		// @2D3: ifeq @304
		// @2D6: bipush 64 (0x40)
		// @2D8: invokestatic game.C_100189_ri.func_105748_a(int)boolean
		// @2DB: ifeq @304
		// @2DE: goto @2E2
		// @2E1: athrow
		// @2E2: aload_0
		// @2E3: sipush 14109 (0x371D)
		// @2E6: invokespecial game.C_100146_bf.func_105107_c(int)int
		// @2E9: istore #6
		// @2EB: iload #6
		// @2ED: iload #7
		// @2EF: ifne @306
		// @2F2: ifne @2FC
		// @2F5: goto @2F9
		// @2F8: athrow
		// @2F9: goto @2FF
		// @2FC: iload #6
		// @2FE: ireturn
		// @2FF: iload #7
		// @301: ifeq @2D6
		// @304: iload #5
		// @306: ifeq @312
		// @309: aload_0
		// @30A: sipush 12410 (0x307A)
		// @30D: invokespecial game.C_100146_bf.func_105110_a(int)void
		// @310: iconst_3
		// @311: ireturn
		// @312: iconst_0
		// @313: ireturn
		// @314: astore_3
		// @315: aload_3
		// @316: new java.lang.StringBuilder
		// @319: dup
		// @31A: invokespecial java.lang.StringBuilder.<init>()void
		// @31D: getstatic java.lang.String[] game.C_100146_bf.field_105144_z
		// @320: bipush 23 (0x17)
		// @322: aaload
		// @323: invokevirtual java.lang.StringBuilder.append(java.lang.String)java.lang.StringBuilder
		// @326: iload_1
		// @327: invokevirtual java.lang.StringBuilder.append(boolean)java.lang.StringBuilder
		// @32A: bipush 44 (0x2C)
		// @32C: invokevirtual java.lang.StringBuilder.append(char)java.lang.StringBuilder
		// @32F: iload_2
		// @330: invokevirtual java.lang.StringBuilder.append(int)java.lang.StringBuilder
		// @333: bipush 41 (0x29)
		// @335: invokevirtual java.lang.StringBuilder.append(char)java.lang.StringBuilder
		// @338: invokevirtual java.lang.StringBuilder.toString()java.lang.String
		// @33B: invokestatic game.C_100181_cf.func_105695_a(java.lang.Throwable, java.lang.String)game.C_100170_cm
		// @33E: athrow
	}
	
	final void func_105117_a(boolean arg0)
	{
		// @000: getstatic int game.SteelSentinels.field_105275_O
		// @003: istore #4
		// @005: bipush 9 (0x09)
		// @007: bipush 9 (0x09)
		// @009: sipush 622 (0x026E)
		// @00C: bipush 47 (0x2F)
		// @00E: ldc 4540749 (0x45494d)
		// @010: ldc 65793 (0x10101)
		// @012: invokestatic game.C_100196_rb.func_105798_b(int, int, int, int, int, int)void
		// @015: bipush 9 (0x09)
		// @017: sipush 257 (0x0101)
		// @01A: sipush 622 (0x026E)
		// @01D: bipush 33 (0x21)
		// @01F: sipush 2585 (0x0A19)
		// @022: invokestatic game.C_100196_rb.func_105782_i(int, int, int, int, int)void
		// @025: bipush 9 (0x09)
		// @027: sipush 265 (0x0109)
		// @02A: sipush 622 (0x026E)
		// @02D: bipush 11 (0x0B)
		// @02F: sipush 2585 (0x0A19)
		// @032: ldc 1515566 (0x17202e)
		// @034: invokestatic game.C_100196_rb.func_105798_b(int, int, int, int, int, int)void
		// @037: iconst_0
		// @038: istore_2
		// @039: bipush 14 (0x0E)
		// @03B: istore_3
		// @03C: iconst_4
		// @03D: iload_2
		// @03E: if_icmple @064
		// @041: iload_3
		// @042: sipush 331 (0x014B)
		// @045: bipush 117 (0x75)
		// @047: bipush 90 (0x5A)
		// @049: ldc 460551 (0x70707)
		// @04B: ldc 3881787 (0x3b3b3b)
		// @04D: invokestatic game.C_100196_rb.func_105798_b(int, int, int, int, int, int)void
		// @050: iinc #3 +121
		// @053: iinc #2 +1
		// @056: iload #4
		// @058: ifne @066
		// @05B: iload #4
		// @05D: ifeq @03C
		// @060: goto @064
		// @063: athrow
		// @064: iconst_0
		// @065: istore_2
		// @066: sipush 299 (0x012B)
		// @069: istore_3
		// @06A: iload_2
		// @06B: iconst_m1
		// @06C: ixor
		// @06D: bipush -3 (0xFD)
		// @06F: if_icmple @0A6
		// @072: sipush 508 (0x01FC)
		// @075: iload_3
		// @076: bipush 127 (0x7F)
		// @078: bipush 42 (0x2A)
		// @07A: ldc 1130115 (0x113e83)
		// @07C: ldc 3365268 (0x335994)
		// @07E: invokestatic game.C_100196_rb.func_105798_b(int, int, int, int, int, int)void
		// @081: sipush 508 (0x01FC)
		// @084: bipush 42 (0x2A)
		// @086: iload_3
		// @087: iadd
		// @088: bipush 127 (0x7F)
		// @08A: bipush 42 (0x2A)
		// @08C: sipush 12410 (0x307A)
		// @08F: invokestatic game.C_100196_rb.func_105782_i(int, int, int, int, int)void
		// @092: iinc #2 +1
		// @095: iinc #3 +91
		// @098: iload #4
		// @09A: ifne @0AC
		// @09D: iload #4
		// @09F: ifeq @06A
		// @0A2: goto @0A6
		// @0A5: athrow
		// @0A6: aload_0
		// @0A7: bipush 127 (0x7F)
		// @0A9: invokespecial game.C_100146_bf.func_105113_a(byte)void
		// @0AC: getstatic game.C_100098_h game.C_100154_sl.field_105338_k
		// @0AF: ifnull @1F3
		// @0B2: getstatic game.C_100098_h game.C_100154_sl.field_105338_k
		// @0B5: iconst_0
		// @0B6: invokevirtual game.C_100098_h.func_104597_a(boolean)boolean
		// @0B9: ifeq @1F3
		// @0BC: goto @0C0
		// @0BF: athrow
		// @0C0: getstatic game.C_100098_h game.C_100154_sl.field_105338_k
		// @0C3: getstatic java.lang.String[] game.C_100146_bf.field_105144_z
		// @0C6: bipush 12 (0x0C)
		// @0C8: aaload
		// @0C9: iconst_0
		// @0CA: invokevirtual game.C_100098_h.func_104593_a(java.lang.String, boolean)boolean
		// @0CD: ifeq @1F3
		// @0D0: goto @0D4
		// @0D3: athrow
		// @0D4: getstatic game.C_100098_h game.C_100154_sl.field_105338_k
		// @0D7: getstatic java.lang.String[] game.C_100146_bf.field_105144_z
		// @0DA: bipush 14 (0x0E)
		// @0DC: aaload
		// @0DD: iconst_0
		// @0DE: invokevirtual game.C_100098_h.func_104593_a(java.lang.String, boolean)boolean
		// @0E1: ifeq @1F3
		// @0E4: goto @0E8
		// @0E7: athrow
		// @0E8: getstatic game.C_100098_h game.C_100154_sl.field_105338_k
		// @0EB: getstatic java.lang.String[] game.C_100146_bf.field_105144_z
		// @0EE: bipush 13 (0x0D)
		// @0F0: aaload
		// @0F1: iconst_0
		// @0F2: invokevirtual game.C_100098_h.func_104593_a(java.lang.String, boolean)boolean
		// @0F5: ifeq @1F3
		// @0F8: goto @0FC
		// @0FB: athrow
		// @0FC: aconst_null
		// @0FD: getstatic game.C_100098_h game.C_100171_cn.field_105566_d
		// @100: if_acmpeq @1F3
		// @103: goto @107
		// @106: athrow
		// @107: getstatic game.C_100098_h game.C_100171_cn.field_105566_d
		// @10A: iload_1
		// @10B: ifne @117
		// @10E: goto @112
		// @111: athrow
		// @112: iconst_1
		// @113: goto @118
		// @116: athrow
		// @117: iconst_0
		// @118: invokevirtual game.C_100098_h.func_104597_a(boolean)boolean
		// @11B: ifeq @1F3
		// @11E: getstatic game.C_100098_h game.C_100171_cn.field_105566_d
		// @121: getstatic java.lang.String[] game.C_100146_bf.field_105144_z
		// @124: bipush 14 (0x0E)
		// @126: aaload
		// @127: iconst_0
		// @128: invokevirtual game.C_100098_h.func_104593_a(java.lang.String, boolean)boolean
		// @12B: ifeq @1F3
		// @12E: goto @132
		// @131: athrow
		// @132: getstatic game.C_100098_h game.C_100171_cn.field_105566_d
		// @135: getstatic java.lang.String[] game.C_100146_bf.field_105144_z
		// @138: bipush 13 (0x0D)
		// @13A: aaload
		// @13B: iconst_0
		// @13C: invokevirtual game.C_100098_h.func_104593_a(java.lang.String, boolean)boolean
		// @13F: ifne @14A
		// @142: goto @146
		// @145: athrow
		// @146: goto @1F3
		// @149: athrow
		// @14A: getstatic java.lang.String[] game.C_100146_bf.field_105144_z
		// @14D: bipush 12 (0x0C)
		// @14F: aaload
		// @150: bipush -62 (0xC2)
		// @152: getstatic java.lang.String[] game.C_100146_bf.field_105144_z
		// @155: bipush 11 (0x0B)
		// @157: aaload
		// @158: getstatic game.C_100098_h game.C_100154_sl.field_105338_k
		// @15B: invokestatic game.C_100004_gb.func_103569_a(java.lang.String, byte, java.lang.String, game.C_100098_h)game.C_100153_be
		// @15E: putstatic game.C_100153_be game.C_100005_fk.field_103591_d
		// @161: bipush 98 (0x62)
		// @163: getstatic java.lang.String[] game.C_100146_bf.field_105144_z
		// @166: bipush 12 (0x0C)
		// @168: aaload
		// @169: getstatic game.C_100098_h game.C_100154_sl.field_105338_k
		// @16C: getstatic java.lang.String[] game.C_100146_bf.field_105144_z
		// @16F: bipush 8 (0x08)
		// @171: aaload
		// @172: invokestatic game.C_100021_wn.func_103861_a(byte, java.lang.String, game.C_100098_h, java.lang.String)game.C_100037_wb
		// @175: putstatic game.C_100037_wb game.C_100195_rc.field_105772_b
		// @178: bipush 101 (0x65)
		// @17A: getstatic game.C_100098_h game.C_100171_cn.field_105566_d
		// @17D: getstatic game.C_100098_h game.C_100154_sl.field_105338_k
		// @180: getstatic java.lang.String[] game.C_100146_bf.field_105144_z
		// @183: bipush 14 (0x0E)
		// @185: aaload
		// @186: ldc ""
		// @188: invokestatic game.C_100004_gb.func_103564_a(int, game.C_100098_h, game.C_100098_h, java.lang.String, java.lang.String)game.C_100317_lb
		// @18B: putstatic game.C_100317_lb game.C_100030_gm.field_103349_H
		// @18E: bipush -70 (0xBA)
		// @190: getstatic java.lang.String[] game.C_100146_bf.field_105144_z
		// @193: bipush 13 (0x0D)
		// @195: aaload
		// @196: ldc ""
		// @198: getstatic game.C_100098_h game.C_100154_sl.field_105338_k
		// @19B: getstatic game.C_100098_h game.C_100171_cn.field_105566_d
		// @19E: invokestatic game.C_100160_sm.func_105412_a(byte, java.lang.String, java.lang.String, game.C_100098_h, game.C_100098_h)game.C_100193_re
		// @1A1: putstatic game.C_100193_re game.C_100030_gm.field_103343_F
		// @1A4: getstatic game.C_100098_h game.C_100154_sl.field_105338_k
		// @1A7: getstatic java.lang.String[] game.C_100146_bf.field_105144_z
		// @1AA: bipush 7 (0x07)
		// @1AC: aaload
		// @1AD: getstatic java.lang.String[] game.C_100146_bf.field_105144_z
		// @1B0: bipush 12 (0x0C)
		// @1B2: aaload
		// @1B3: sipush 1237 (0x04D5)
		// @1B6: invokestatic game.C_100143_bl.func_105092_a(game.C_100098_h, java.lang.String, java.lang.String, int)game.C_100037_wb
		// @1B9: putstatic game.C_100037_wb game.C_100297_kf.field_101244_k
		// @1BC: getstatic game.C_100098_h game.C_100154_sl.field_105338_k
		// @1BF: getstatic java.lang.String[] game.C_100146_bf.field_105144_z
		// @1C2: bipush 9 (0x09)
		// @1C4: aaload
		// @1C5: getstatic java.lang.String[] game.C_100146_bf.field_105144_z
		// @1C8: bipush 12 (0x0C)
		// @1CA: aaload
		// @1CB: sipush 1237 (0x04D5)
		// @1CE: invokestatic game.C_100143_bl.func_105092_a(game.C_100098_h, java.lang.String, java.lang.String, int)game.C_100037_wb
		// @1D1: putstatic game.C_100037_wb game.C_100102_w.field_104639_o
		// @1D4: getstatic java.lang.String[] game.C_100146_bf.field_105144_z
		// @1D7: bipush 12 (0x0C)
		// @1D9: aaload
		// @1DA: getstatic game.C_100098_h game.C_100154_sl.field_105338_k
		// @1DD: bipush 115 (0x73)
		// @1DF: getstatic java.lang.String[] game.C_100146_bf.field_105144_z
		// @1E2: bipush 6 (0x06)
		// @1E4: aaload
		// @1E5: invokestatic game.C_100188_rj.func_105731_a(java.lang.String, game.C_100098_h, int, java.lang.String)game.C_100037_wb[]
		// @1E8: putstatic game.C_100037_wb[] game.C_100281_ng.field_103467_T
		// @1EB: aconst_null
		// @1EC: putstatic game.C_100098_h game.C_100171_cn.field_105566_d
		// @1EF: aconst_null
		// @1F0: putstatic game.C_100098_h game.C_100154_sl.field_105338_k
		// @1F3: aload_0
		// @1F4: bipush -117 (0x8B)
		// @1F6: invokespecial game.C_100146_bf.func_105108_b(int)void
		// @1F9: getstatic game.C_100153_be game.C_100005_fk.field_103591_d
		// @1FC: ifnonnull @200
		// @1FF: return
		// @200: aload_0
		// @201: getfield game.C_100037_wb game.C_100146_bf.field_105130_l
		// @204: sipush 376 (0x0178)
		// @207: sipush 339 (0x0153)
		// @20A: invokevirtual game.C_100037_wb.func_102353_h(int, int)void
		// @20D: iload_1
		// @20E: iconst_1
		// @20F: if_icmpeq @21D
		// @212: aload_0
		// @213: bipush -7 (0xF9)
		// @215: invokespecial game.C_100146_bf.func_105107_c(int)int
		// @218: pop
		// @219: goto @21D
		// @21C: athrow
		// @21D: aload_0
		// @21E: getfield game.C_100037_wb game.C_100146_bf.field_105129_o
		// @221: bipush 9 (0x09)
		// @223: bipush 9 (0x09)
		// @225: invokevirtual game.C_100037_wb.func_102353_h(int, int)void
		// @228: getstatic game.C_100153_be game.C_100005_fk.field_103591_d
		// @22B: iconst_0
		// @22C: iconst_0
		// @22D: invokevirtual game.C_100153_be.func_105286_a(int, int)void
		// @230: getstatic game.C_100037_wb game.C_100195_rc.field_105772_b
		// @233: ifnonnull @23A
		// @236: goto @338
		// @239: athrow
		// @23A: getstatic game.C_100037_wb game.C_100195_rc.field_105772_b
		// @23D: bipush 9 (0x09)
		// @23F: sipush 257 (0x0101)
		// @242: invokevirtual game.C_100037_wb.func_102353_h(int, int)void
		// @245: getstatic game.C_100037_wb game.C_100195_rc.field_105772_b
		// @248: sipush 558 (0x022E)
		// @24B: sipush 257 (0x0101)
		// @24E: invokevirtual game.C_100037_wb.func_102351_e(int, int)void
		// @251: sipush -258 (0xFEFE)
		// @254: getstatic int game.C_100338_jc.field_105370_l
		// @257: iconst_m1
		// @258: ixor
		// @259: if_icmple @338
		// @25C: sipush 290 (0x0122)
		// @25F: getstatic int game.C_100338_jc.field_105370_l
		// @262: if_icmpgt @26D
		// @265: goto @269
		// @268: athrow
		// @269: goto @338
		// @26C: athrow
		// @26D: bipush 40 (0x28)
		// @26F: iconst_0
		// @270: aload_0
		// @271: getfield int game.C_100146_bf.field_105134_h
		// @274: ldc -557882716 (0xdebf62a4)
		// @276: ishl
		// @277: invokestatic game.C_100166_sg.func_105460_a(boolean, int)int
		// @27A: bipush 40 (0x28)
		// @27C: imul
		// @27D: ldc 1535791600 (0x5b8a51f0)
		// @27F: ishr
		// @280: ineg
		// @281: isub
		// @282: istore_2
		// @283: iload_2
		// @284: ifle @338
		// @287: bipush -10 (0xF6)
		// @289: getstatic int game.C_100015_wh.field_103781_g
		// @28C: iconst_m1
		// @28D: ixor
		// @28E: if_icmple @2A1
		// @291: goto @295
		// @294: athrow
		// @295: bipush 82 (0x52)
		// @297: getstatic int game.C_100015_wh.field_103781_g
		// @29A: if_icmpgt @304
		// @29D: goto @2A1
		// @2A0: athrow
		// @2A1: sipush 558 (0x022E)
		// @2A4: getstatic int game.C_100015_wh.field_103781_g
		// @2A7: if_icmpge @338
		// @2AA: goto @2AE
		// @2AD: athrow
		// @2AE: getstatic int game.C_100015_wh.field_103781_g
		// @2B1: sipush 631 (0x0277)
		// @2B4: if_icmpge @338
		// @2B7: goto @2BB
		// @2BA: athrow
		// @2BB: getstatic game.C_100037_wb game.C_100195_rc.field_105772_b
		// @2BE: invokevirtual game.C_100037_wb.func_102380_g()void
		// @2C1: getstatic game.C_100037_wb game.C_100195_rc.field_105772_b
		// @2C4: sipush 557 (0x022D)
		// @2C7: sipush 256 (0x0100)
		// @2CA: iload_2
		// @2CB: invokevirtual game.C_100037_wb.func_102367_c(int, int, int)void
		// @2CE: getstatic game.C_100037_wb game.C_100195_rc.field_105772_b
		// @2D1: sipush 559 (0x022F)
		// @2D4: sipush 256 (0x0100)
		// @2D7: iload_2
		// @2D8: invokevirtual game.C_100037_wb.func_102367_c(int, int, int)void
		// @2DB: getstatic game.C_100037_wb game.C_100195_rc.field_105772_b
		// @2DE: sipush 557 (0x022D)
		// @2E1: sipush 258 (0x0102)
		// @2E4: iload_2
		// @2E5: invokevirtual game.C_100037_wb.func_102367_c(int, int, int)void
		// @2E8: getstatic game.C_100037_wb game.C_100195_rc.field_105772_b
		// @2EB: sipush 559 (0x022F)
		// @2EE: sipush 258 (0x0102)
		// @2F1: iload_2
		// @2F2: invokevirtual game.C_100037_wb.func_102367_c(int, int, int)void
		// @2F5: getstatic game.C_100037_wb game.C_100195_rc.field_105772_b
		// @2F8: invokevirtual game.C_100037_wb.func_102380_g()void
		// @2FB: iload #4
		// @2FD: ifeq @338
		// @300: goto @304
		// @303: athrow
		// @304: getstatic game.C_100037_wb game.C_100195_rc.field_105772_b
		// @307: bipush 8 (0x08)
		// @309: sipush 256 (0x0100)
		// @30C: iload_2
		// @30D: invokevirtual game.C_100037_wb.func_102367_c(int, int, int)void
		// @310: getstatic game.C_100037_wb game.C_100195_rc.field_105772_b
		// @313: bipush 10 (0x0A)
		// @315: sipush 256 (0x0100)
		// @318: iload_2
		// @319: invokevirtual game.C_100037_wb.func_102367_c(int, int, int)void
		// @31C: getstatic game.C_100037_wb game.C_100195_rc.field_105772_b
		// @31F: bipush 8 (0x08)
		// @321: sipush 258 (0x0102)
		// @324: iload_2
		// @325: invokevirtual game.C_100037_wb.func_102367_c(int, int, int)void
		// @328: getstatic game.C_100037_wb game.C_100195_rc.field_105772_b
		// @32B: bipush 10 (0x0A)
		// @32D: sipush 258 (0x0102)
		// @330: iload_2
		// @331: invokevirtual game.C_100037_wb.func_102367_c(int, int, int)void
		// @334: goto @338
		// @337: athrow
		// @338: aload_0
		// @339: getfield game.C_100037_wb game.C_100146_bf.field_105126_c
		// @33C: bipush 16 (0x10)
		// @33E: sipush 302 (0x012E)
		// @341: invokevirtual game.C_100037_wb.func_102353_h(int, int)void
		// @344: getstatic game.C_100317_lb game.C_100030_gm.field_103349_H
		// @347: aload_0
		// @348: getfield java.lang.String[] game.C_100146_bf.field_105136_w
		// @34B: aload_0
		// @34C: getfield int game.C_100146_bf.field_105141_r
		// @34F: aaload
		// @350: bipush 9 (0x09)
		// @352: sipush 257 (0x0101)
		// @355: sipush 622 (0x026E)
		// @358: bipush 33 (0x21)
		// @35A: ldc 16754688 (0xffa800)
		// @35C: iconst_m1
		// @35D: iconst_1
		// @35E: iconst_1
		// @35F: iconst_0
		// @360: invokevirtual game.C_100317_lb.func_101729_a(java.lang.String, int, int, int, int, int, int, int, int, int)int
		// @363: pop
		// @364: getstatic game.C_100037_wb game.C_100297_kf.field_101244_k
		// @367: bipush 30 (0x1E)
		// @369: sipush 330 (0x014A)
		// @36C: invokevirtual game.C_100037_wb.func_102353_h(int, int)void
		// @36F: getstatic game.C_100317_lb game.C_100030_gm.field_103349_H
		// @372: getstatic java.lang.String[] game.C_100227_af.field_106164_f
		// @375: iconst_0
		// @376: aaload
		// @377: bipush 17 (0x11)
		// @379: sipush 428 (0x01AC)
		// @37C: bipush 111 (0x6F)
		// @37E: bipush 35 (0x23)
		// @380: ldc 16754688 (0xffa800)
		// @382: iconst_m1
		// @383: iconst_1
		// @384: iconst_1
		// @385: iconst_0
		// @386: invokevirtual game.C_100317_lb.func_101729_a(java.lang.String, int, int, int, int, int, int, int, int, int)int
		// @389: pop
		// @38A: getstatic game.C_100317_lb game.C_100030_gm.field_103349_H
		// @38D: getstatic java.lang.String[] game.C_100227_af.field_106164_f
		// @390: iconst_1
		// @391: aaload
		// @392: sipush 138 (0x008A)
		// @395: sipush 428 (0x01AC)
		// @398: bipush 111 (0x6F)
		// @39A: bipush 35 (0x23)
		// @39C: ldc 16754688 (0xffa800)
		// @39E: iconst_m1
		// @39F: iconst_1
		// @3A0: iconst_1
		// @3A1: iconst_0
		// @3A2: invokevirtual game.C_100317_lb.func_101729_a(java.lang.String, int, int, int, int, int, int, int, int, int)int
		// @3A5: pop
		// @3A6: getstatic game.C_100317_lb game.C_100030_gm.field_103349_H
		// @3A9: getstatic java.lang.String[] game.C_100227_af.field_106164_f
		// @3AC: iconst_2
		// @3AD: aaload
		// @3AE: sipush 259 (0x0103)
		// @3B1: sipush 428 (0x01AC)
		// @3B4: bipush 111 (0x6F)
		// @3B6: bipush 35 (0x23)
		// @3B8: ldc 16754688 (0xffa800)
		// @3BA: iconst_m1
		// @3BB: iconst_1
		// @3BC: iconst_1
		// @3BD: iconst_0
		// @3BE: invokevirtual game.C_100317_lb.func_101729_a(java.lang.String, int, int, int, int, int, int, int, int, int)int
		// @3C1: pop
		// @3C2: getstatic game.C_100037_wb game.C_100102_w.field_104639_o
		// @3C5: sipush 508 (0x01FC)
		// @3C8: getstatic game.C_100037_wb game.C_100102_w.field_104639_o
		// @3CB: getfield int game.C_100037_wb.field_102341_y
		// @3CE: ineg
		// @3CF: bipush 127 (0x7F)
		// @3D1: iadd
		// @3D2: iconst_2
		// @3D3: idiv
		// @3D4: ineg
		// @3D5: isub
		// @3D6: sipush 315 (0x013B)
		// @3D9: invokevirtual game.C_100037_wb.func_102353_h(int, int)void
		// @3DC: iconst_m1
		// @3DD: aload_0
		// @3DE: getfield game.C_100333_ij game.C_100146_bf.field_105133_k
		// @3E1: getfield int game.C_100333_ij.field_107347_b
		// @3E4: iconst_m1
		// @3E5: ixor
		// @3E6: if_icmpne @400
		// @3E9: getstatic game.C_100037_wb[] game.C_100281_ng.field_103467_T
		// @3EC: iconst_0
		// @3ED: aaload
		// @3EE: sipush 508 (0x01FC)
		// @3F1: sipush 299 (0x012B)
		// @3F4: invokevirtual game.C_100037_wb.func_102353_h(int, int)void
		// @3F7: iload #4
		// @3F9: ifeq @424
		// @3FC: goto @400
		// @3FF: athrow
		// @400: bipush -2 (0xFE)
		// @402: aload_0
		// @403: getfield game.C_100333_ij game.C_100146_bf.field_105133_k
		// @406: getfield int game.C_100333_ij.field_107347_b
		// @409: iconst_m1
		// @40A: ixor
		// @40B: if_icmpne @424
		// @40E: goto @412
		// @411: athrow
		// @412: getstatic game.C_100037_wb[] game.C_100281_ng.field_103467_T
		// @415: iconst_1
		// @416: aaload
		// @417: sipush 508 (0x01FC)
		// @41A: sipush 387 (0x0183)
		// @41D: invokevirtual game.C_100037_wb.func_102353_h(int, int)void
		// @420: goto @424
		// @423: athrow
		// @424: goto @449
		// @427: astore_2
		// @428: aload_2
		// @429: new java.lang.StringBuilder
		// @42C: dup
		// @42D: invokespecial java.lang.StringBuilder.<init>()void
		// @430: getstatic java.lang.String[] game.C_100146_bf.field_105144_z
		// @433: bipush 10 (0x0A)
		// @435: aaload
		// @436: invokevirtual java.lang.StringBuilder.append(java.lang.String)java.lang.StringBuilder
		// @439: iload_1
		// @43A: invokevirtual java.lang.StringBuilder.append(boolean)java.lang.StringBuilder
		// @43D: bipush 41 (0x29)
		// @43F: invokevirtual java.lang.StringBuilder.append(char)java.lang.StringBuilder
		// @442: invokevirtual java.lang.StringBuilder.toString()java.lang.String
		// @445: invokestatic game.C_100181_cf.func_105695_a(java.lang.Throwable, java.lang.String)game.C_100170_cm
		// @448: athrow
		// @449: return
	}
	
	private final void func_105110_a(int arg0)
	{
		// @00: sipush 360 (0x0168)
		// @03: iconst_0
		// @04: invokestatic game.C_100206_qe.func_105938_b(boolean)java.applet.Applet
		// @07: invokestatic game.C_100303_kk.func_104780_a(int, java.applet.Applet)void
		// @0A: iload_1
		// @0B: sipush 12410 (0x307A)
		// @0E: if_icmpeq @19
		// @11: aload_0
		// @12: aconst_null
		// @13: checkcast game.C_100037_wb
		// @16: putfield game.C_100037_wb game.C_100146_bf.field_105126_c
		// @19: goto @21
		// @1C: astore_2
		// @1D: aload_2
		// @1E: invokevirtual java.lang.Exception.printStackTrace()void
		// @21: goto @45
		// @24: astore_2
		// @25: aload_2
		// @26: new java.lang.StringBuilder
		// @29: dup
		// @2A: invokespecial java.lang.StringBuilder.<init>()void
		// @2D: getstatic java.lang.String[] game.C_100146_bf.field_105144_z
		// @30: iconst_0
		// @31: aaload
		// @32: invokevirtual java.lang.StringBuilder.append(java.lang.String)java.lang.StringBuilder
		// @35: iload_1
		// @36: invokevirtual java.lang.StringBuilder.append(int)java.lang.StringBuilder
		// @39: bipush 41 (0x29)
		// @3B: invokevirtual java.lang.StringBuilder.append(char)java.lang.StringBuilder
		// @3E: invokevirtual java.lang.StringBuilder.toString()java.lang.String
		// @41: invokestatic game.C_100181_cf.func_105695_a(java.lang.Throwable, java.lang.String)game.C_100170_cm
		// @44: athrow
		// @45: return
	}
	
	private final void func_105108_b(int arg0)
	{
		// @000: aconst_null
		// @001: aload_0
		// @002: getfield game.C_100037_wb game.C_100146_bf.field_105129_o
		// @005: if_acmpne @016
		// @008: getstatic game.C_100193_re game.C_100030_gm.field_103343_F
		// @00B: ifnull @016
		// @00E: goto @012
		// @011: athrow
		// @012: goto @017
		// @015: athrow
		// @016: return
		// @017: aload_0
		// @018: new game.C_100037_wb
		// @01B: dup
		// @01C: sipush 622 (0x026E)
		// @01F: bipush 47 (0x2F)
		// @021: invokespecial game.C_100037_wb.<init>(int, int)void
		// @024: putfield game.C_100037_wb game.C_100146_bf.field_105129_o
		// @027: aload_0
		// @028: getfield game.C_100037_wb game.C_100146_bf.field_105129_o
		// @02B: bipush -4 (0xFC)
		// @02D: invokestatic game.C_100138_bo.func_100398_a(game.C_100037_wb, int)void
		// @030: iconst_0
		// @031: iconst_0
		// @032: sipush 622 (0x026E)
		// @035: bipush 47 (0x2F)
		// @037: ldc 4540749 (0x45494d)
		// @039: ldc 65793 (0x10101)
		// @03B: invokestatic game.C_100196_rb.func_105798_b(int, int, int, int, int, int)void
		// @03E: ldc 16448250 (0xfafafa)
		// @040: istore_2
		// @041: ldc 10068666 (0x99a2ba)
		// @043: istore_3
		// @044: iload_3
		// @045: iload_2
		// @046: ldc 1199019304 (0x47779528)
		// @048: invokestatic game.C_100142_bk.func_105082_a(int, int, int)int[]
		// @04B: astore #4
		// @04D: aload_0
		// @04E: bipush -53 (0xCB)
		// @050: iconst_0
		// @051: sipush 622 (0x026E)
		// @054: aload_0
		// @055: getfield java.lang.String game.C_100146_bf.field_105142_q
		// @058: getstatic game.C_100193_re game.C_100030_gm.field_103343_F
		// @05B: aload #4
		// @05D: bipush 47 (0x2F)
		// @05F: iconst_0
		// @060: invokespecial game.C_100146_bf.func_105119_a(byte, int, int, java.lang.String, game.C_100112_r, int[], int, int)void
		// @063: bipush -77 (0xB3)
		// @065: invokestatic game.C_100200_ba.func_105842_a(byte)void
		// @068: aload_0
		// @069: new game.C_100037_wb
		// @06C: dup
		// @06D: sipush 475 (0x01DB)
		// @070: bipush 24 (0x18)
		// @072: invokespecial game.C_100037_wb.<init>(int, int)void
		// @075: putfield game.C_100037_wb game.C_100146_bf.field_105126_c
		// @078: aload_0
		// @079: aload #4
		// @07B: iconst_0
		// @07C: bipush -119 (0x89)
		// @07E: bipush -4 (0xFC)
		// @080: sipush 475 (0x01DB)
		// @083: bipush 24 (0x18)
		// @085: ldc 0.75
		// @087: getstatic game.C_100193_re game.C_100030_gm.field_103343_F
		// @08A: getstatic java.lang.String game.C_100275_na.field_103089_j
		// @08D: aload_0
		// @08E: getfield game.C_100037_wb game.C_100146_bf.field_105126_c
		// @091: invokespecial game.C_100146_bf.func_105120_a(int[], int, int, int, int, int, float, game.C_100112_r, java.lang.String, game.C_100037_wb)void
		// @094: ldc 526344 (0x80808)
		// @096: ldc 526344 (0x80808)
		// @098: ldc 1199019304 (0x47779528)
		// @09A: invokestatic game.C_100142_bk.func_105082_a(int, int, int)int[]
		// @09D: astore #4
		// @09F: new game.C_100037_wb
		// @0A2: dup
		// @0A3: bipush 121 (0x79)
		// @0A5: bipush 122 (0x7A)
		// @0A7: invokespecial game.C_100037_wb.<init>(int, int)void
		// @0AA: astore #5
		// @0AC: aload #5
		// @0AE: bipush -4 (0xFC)
		// @0B0: invokestatic game.C_100138_bo.func_100398_a(game.C_100037_wb, int)void
		// @0B3: iconst_0
		// @0B4: iconst_0
		// @0B5: aload #5
		// @0B7: getfield int game.C_100037_wb.field_102339_s
		// @0BA: aload #5
		// @0BC: getfield int game.C_100037_wb.field_102337_u
		// @0BF: iconst_2
		// @0C0: idiv
		// @0C1: ldc 16180917 (0xf6e6b5)
		// @0C3: ldc 16306250 (0xf8d04a)
		// @0C5: invokestatic game.C_100196_rb.func_105798_b(int, int, int, int, int, int)void
		// @0C8: iconst_0
		// @0C9: aload #5
		// @0CB: getfield int game.C_100037_wb.field_102337_u
		// @0CE: iconst_2
		// @0CF: idiv
		// @0D0: aload #5
		// @0D2: getfield int game.C_100037_wb.field_102339_s
		// @0D5: aload #5
		// @0D7: getfield int game.C_100037_wb.field_102337_u
		// @0DA: ldc 16306250 (0xf8d04a)
		// @0DC: ldc 15568919 (0xed9017)
		// @0DE: invokestatic game.C_100196_rb.func_105798_b(int, int, int, int, int, int)void
		// @0E1: getstatic java.lang.String game.C_100126_cb.field_103064_r
		// @0E4: astore #6
		// @0E6: getstatic java.lang.String game.C_100165_sh.field_100776_m
		// @0E9: astore #7
		// @0EB: aload_0
		// @0EC: aload #4
		// @0EE: iconst_0
		// @0EF: bipush -67 (0xBD)
		// @0F1: bipush -16 (0xF0)
		// @0F3: aload #5
		// @0F5: getfield int game.C_100037_wb.field_102339_s
		// @0F8: aload #5
		// @0FA: getfield int game.C_100037_wb.field_102337_u
		// @0FD: ldc 0.5
		// @0FF: getstatic game.C_100193_re game.C_100030_gm.field_103343_F
		// @102: aload #6
		// @104: aload #5
		// @106: invokespecial game.C_100146_bf.func_105120_a(int[], int, int, int, int, int, float, game.C_100112_r, java.lang.String, game.C_100037_wb)void
		// @109: aload_0
		// @10A: aload #4
		// @10C: iconst_0
		// @10D: bipush -90 (0xA6)
		// @10F: bipush 20 (0x14)
		// @111: aload #5
		// @113: getfield int game.C_100037_wb.field_102339_s
		// @116: aload #5
		// @118: getfield int game.C_100037_wb.field_102337_u
		// @11B: ldc 0.5
		// @11D: getstatic game.C_100193_re game.C_100030_gm.field_103343_F
		// @120: aload #7
		// @122: aload #5
		// @124: invokespecial game.C_100146_bf.func_105120_a(int[], int, int, int, int, int, float, game.C_100112_r, java.lang.String, game.C_100037_wb)void
		// @127: aload_0
		// @128: aload #4
		// @12A: iconst_0
		// @12B: bipush -89 (0xA7)
		// @12D: aload #5
		// @12F: getfield int game.C_100037_wb.field_102337_u
		// @132: iconst_2
		// @133: idiv
		// @134: getstatic game.C_100193_re game.C_100030_gm.field_103343_F
		// @137: getfield int game.C_100193_re.field_101772_Q
		// @13A: ineg
		// @13B: bipush -12 (0xF4)
		// @13D: isub
		// @13E: iadd
		// @13F: aload #5
		// @141: getfield int game.C_100037_wb.field_102339_s
		// @144: aload #5
		// @146: getfield int game.C_100037_wb.field_102337_u
		// @149: iconst_3
		// @14A: idiv
		// @14B: ldc 0.7
		// @14D: getstatic game.C_100193_re game.C_100030_gm.field_103343_F
		// @150: getstatic java.lang.String[] game.C_100057_dd.field_104255_d
		// @153: aload_0
		// @154: getfield int game.C_100146_bf.field_105138_u
		// @157: aaload
		// @158: aload #5
		// @15A: invokespecial game.C_100146_bf.func_105120_a(int[], int, int, int, int, int, float, game.C_100112_r, java.lang.String, game.C_100037_wb)void
		// @15D: bipush -77 (0xB3)
		// @15F: invokestatic game.C_100200_ba.func_105842_a(byte)void
		// @162: aload_0
		// @163: new game.C_100037_wb
		// @166: dup
		// @167: bipush 121 (0x79)
		// @169: bipush 122 (0x7A)
		// @16B: invokespecial game.C_100037_wb.<init>(int, int)void
		// @16E: putfield game.C_100037_wb game.C_100146_bf.field_105130_l
		// @171: aload_0
		// @172: getfield game.C_100037_wb game.C_100146_bf.field_105130_l
		// @175: bipush -4 (0xFC)
		// @177: invokestatic game.C_100138_bo.func_100398_a(game.C_100037_wb, int)void
		// @17A: aload #5
		// @17C: aload_0
		// @17D: getfield game.C_100037_wb game.C_100146_bf.field_105130_l
		// @180: getfield int game.C_100037_wb.field_102339_s
		// @183: iconst_2
		// @184: idiv
		// @185: aload_0
		// @186: getfield game.C_100037_wb game.C_100146_bf.field_105130_l
		// @189: getfield int game.C_100037_wb.field_102337_u
		// @18C: iconst_2
		// @18D: idiv
		// @18E: sipush -2048 (0xF800)
		// @191: sipush 4096 (0x1000)
		// @194: invokevirtual game.C_100037_wb.func_102373_c(int, int, int, int)void
		// @197: bipush -41 (0xD7)
		// @199: bipush 33 (0x21)
		// @19B: iload_1
		// @19C: isub
		// @19D: bipush 56 (0x38)
		// @19F: idiv
		// @1A0: idiv
		// @1A1: istore #8
		// @1A3: bipush -77 (0xB3)
		// @1A5: invokestatic game.C_100200_ba.func_105842_a(byte)void
		// @1A8: goto @1CD
		// @1AB: astore_2
		// @1AC: aload_2
		// @1AD: new java.lang.StringBuilder
		// @1B0: dup
		// @1B1: invokespecial java.lang.StringBuilder.<init>()void
		// @1B4: getstatic java.lang.String[] game.C_100146_bf.field_105144_z
		// @1B7: bipush 22 (0x16)
		// @1B9: aaload
		// @1BA: invokevirtual java.lang.StringBuilder.append(java.lang.String)java.lang.StringBuilder
		// @1BD: iload_1
		// @1BE: invokevirtual java.lang.StringBuilder.append(int)java.lang.StringBuilder
		// @1C1: bipush 41 (0x29)
		// @1C3: invokevirtual java.lang.StringBuilder.append(char)java.lang.StringBuilder
		// @1C6: invokevirtual java.lang.StringBuilder.toString()java.lang.String
		// @1C9: invokestatic game.C_100181_cf.func_105695_a(java.lang.Throwable, java.lang.String)game.C_100170_cm
		// @1CC: athrow
		// @1CD: return
	}
	
	private final int func_105109_a(int arg0, int arg1, int arg2)
	{
		// @00: aconst_null
		// @01: getstatic game.C_100153_be game.C_100005_fk.field_103591_d
		// @04: if_acmpeq @0B
		// @07: goto @0D
		// @0A: athrow
		// @0B: iconst_m1
		// @0C: ireturn
		// @0D: iload_2
		// @0E: bipush 111 (0x6F)
		// @10: if_icmpgt @1F
		// @13: aload_0
		// @14: aconst_null
		// @15: checkcast game.C_100037_wb
		// @18: putfield game.C_100037_wb game.C_100146_bf.field_105126_c
		// @1B: goto @1F
		// @1E: athrow
		// @1F: sipush 508 (0x01FC)
		// @22: iload_3
		// @23: if_icmpgt @4D
		// @26: iload_3
		// @27: iconst_m1
		// @28: ixor
		// @29: sipush -636 (0xFD84)
		// @2C: if_icmple @4D
		// @2F: goto @33
		// @32: athrow
		// @33: iload_1
		// @34: sipush 299 (0x012B)
		// @37: if_icmplt @4D
		// @3A: goto @3E
		// @3D: athrow
		// @3E: iload_1
		// @3F: iconst_m1
		// @40: ixor
		// @41: sipush -387 (0xFE7D)
		// @44: if_icmple @4D
		// @47: goto @4B
		// @4A: athrow
		// @4B: iconst_0
		// @4C: ireturn
		// @4D: sipush 508 (0x01FC)
		// @50: iload_3
		// @51: if_icmpgt @7B
		// @54: sipush -636 (0xFD84)
		// @57: iload_3
		// @58: iconst_m1
		// @59: ixor
		// @5A: if_icmpge @7B
		// @5D: goto @61
		// @60: athrow
		// @61: sipush 390 (0x0186)
		// @64: iload_1
		// @65: if_icmpgt @7B
		// @68: goto @6C
		// @6B: athrow
		// @6C: iload_1
		// @6D: iconst_m1
		// @6E: ixor
		// @6F: sipush -476 (0xFE24)
		// @72: if_icmple @7B
		// @75: goto @79
		// @78: athrow
		// @79: iconst_1
		// @7A: ireturn
		// @7B: iconst_m1
		// @7C: ireturn
		// @7D: astore #4
		// @7F: aload #4
		// @81: new java.lang.StringBuilder
		// @84: dup
		// @85: invokespecial java.lang.StringBuilder.<init>()void
		// @88: getstatic java.lang.String[] game.C_100146_bf.field_105144_z
		// @8B: iconst_5
		// @8C: aaload
		// @8D: invokevirtual java.lang.StringBuilder.append(java.lang.String)java.lang.StringBuilder
		// @90: iload_1
		// @91: invokevirtual java.lang.StringBuilder.append(int)java.lang.StringBuilder
		// @94: bipush 44 (0x2C)
		// @96: invokevirtual java.lang.StringBuilder.append(char)java.lang.StringBuilder
		// @99: iload_2
		// @9A: invokevirtual java.lang.StringBuilder.append(int)java.lang.StringBuilder
		// @9D: bipush 44 (0x2C)
		// @9F: invokevirtual java.lang.StringBuilder.append(char)java.lang.StringBuilder
		// @A2: iload_3
		// @A3: invokevirtual java.lang.StringBuilder.append(int)java.lang.StringBuilder
		// @A6: bipush 41 (0x29)
		// @A8: invokevirtual java.lang.StringBuilder.append(char)java.lang.StringBuilder
		// @AB: invokevirtual java.lang.StringBuilder.toString()java.lang.String
		// @AE: invokestatic game.C_100181_cf.func_105695_a(java.lang.Throwable, java.lang.String)game.C_100170_cm
		// @B1: athrow
	}
	
	private final void func_105113_a(byte arg0)
	{
		// @000: getstatic int game.SteelSentinels.field_105275_O
		// @003: istore #5
		// @005: aconst_null
		// @006: aload_0
		// @007: getfield game.C_100153_be[] game.C_100146_bf.field_105143_p
		// @00A: if_acmpeq @011
		// @00D: goto @036
		// @010: athrow
		// @011: getstatic game.C_100317_lb game.C_100030_gm.field_103349_H
		// @014: ifnull @035
		// @017: getstatic game.C_100317_lb game.C_100030_gm.field_103349_H
		// @01A: getstatic java.lang.String game.C_100185_rm.field_105485_e
		// @01D: bipush 9 (0x09)
		// @01F: bipush 58 (0x3A)
		// @021: sipush 622 (0x026E)
		// @024: sipush 196 (0x00C4)
		// @027: ldc 16754688 (0xffa800)
		// @029: iconst_m1
		// @02A: iconst_1
		// @02B: iconst_1
		// @02C: iconst_0
		// @02D: invokevirtual game.C_100317_lb.func_101729_a(java.lang.String, int, int, int, int, int, int, int, int, int)int
		// @030: pop
		// @031: goto @035
		// @034: athrow
		// @035: return
		// @036: aload_0
		// @037: getfield game.C_100153_be[] game.C_100146_bf.field_105143_p
		// @03A: aload_0
		// @03B: getfield int game.C_100146_bf.field_105141_r
		// @03E: aaload
		// @03F: astore_2
		// @040: aload_2
		// @041: ifnonnull @072
		// @044: aconst_null
		// @045: getstatic game.C_100317_lb game.C_100030_gm.field_103349_H
		// @048: if_acmpeq @07E
		// @04B: goto @04F
		// @04E: athrow
		// @04F: getstatic game.C_100317_lb game.C_100030_gm.field_103349_H
		// @052: getstatic java.lang.String game.C_100185_rm.field_105485_e
		// @055: bipush 9 (0x09)
		// @057: bipush 58 (0x3A)
		// @059: sipush 622 (0x026E)
		// @05C: sipush 196 (0x00C4)
		// @05F: ldc 16754688 (0xffa800)
		// @061: iconst_m1
		// @062: iconst_1
		// @063: iconst_1
		// @064: iconst_0
		// @065: invokevirtual game.C_100317_lb.func_101729_a(java.lang.String, int, int, int, int, int, int, int, int, int)int
		// @068: pop
		// @069: iload #5
		// @06B: ifeq @07E
		// @06E: goto @072
		// @071: athrow
		// @072: aload_2
		// @073: bipush 9 (0x09)
		// @075: bipush 58 (0x3A)
		// @077: invokevirtual game.C_100153_be.func_105286_a(int, int)void
		// @07A: goto @07E
		// @07D: athrow
		// @07E: getstatic int game.C_100031_gl.field_103962_f
		// @081: iconst_m1
		// @082: ixor
		// @083: aload_0
		// @084: getfield int game.C_100146_bf.field_105137_v
		// @087: iconst_m1
		// @088: ixor
		// @089: if_icmplt @090
		// @08C: goto @112
		// @08F: athrow
		// @090: aload_0
		// @091: getfield game.C_100153_be[] game.C_100146_bf.field_105143_p
		// @094: aload_0
		// @095: getfield int game.C_100146_bf.field_105145_x
		// @098: aaload
		// @099: astore_2
		// @09A: aconst_null
		// @09B: aload_2
		// @09C: if_acmpne @0A3
		// @09F: goto @112
		// @0A2: athrow
		// @0A3: aload_0
		// @0A4: getfield int game.C_100146_bf.field_105137_v
		// @0A7: bipush 60 (0x3C)
		// @0A9: aload_2
		// @0AA: getfield int game.C_100153_be.field_105301_h
		// @0AD: iadd
		// @0AE: imul
		// @0AF: getstatic int game.C_100031_gl.field_103962_f
		// @0B2: idiv
		// @0B3: istore_3
		// @0B4: iload_3
		// @0B5: bipush 30 (0x1E)
		// @0B7: isub
		// @0B8: istore #4
		// @0BA: aload_0
		// @0BB: getfield boolean game.C_100146_bf.field_105135_i
		// @0BE: ifne @0EC
		// @0C1: bipush -34 (0xDE)
		// @0C3: sipush -256 (0xFF00)
		// @0C6: iload #4
		// @0C8: imul
		// @0C9: bipush 30 (0x1E)
		// @0CB: idiv
		// @0CC: sipush 256 (0x0100)
		// @0CF: iload #4
		// @0D1: ineg
		// @0D2: aload_2
		// @0D3: getfield int game.C_100153_be.field_105301_h
		// @0D6: iadd
		// @0D7: imul
		// @0D8: bipush 30 (0x1E)
		// @0DA: idiv
		// @0DB: aload_2
		// @0DC: bipush 58 (0x3A)
		// @0DE: bipush 9 (0x09)
		// @0E0: invokestatic game.C_100271_mj.func_103430_a(byte, int, int, game.C_100153_be, int, int)void
		// @0E3: iload #5
		// @0E5: ifeq @112
		// @0E8: goto @0EC
		// @0EB: athrow
		// @0EC: bipush -34 (0xDE)
		// @0EE: sipush 256 (0x0100)
		// @0F1: aload_2
		// @0F2: getfield int game.C_100153_be.field_105301_h
		// @0F5: iload #4
		// @0F7: ineg
		// @0F8: iadd
		// @0F9: imul
		// @0FA: bipush 30 (0x1E)
		// @0FC: idiv
		// @0FD: iload #4
		// @0FF: sipush -256 (0xFF00)
		// @102: imul
		// @103: bipush 30 (0x1E)
		// @105: idiv
		// @106: aload_2
		// @107: bipush 58 (0x3A)
		// @109: bipush 9 (0x09)
		// @10B: invokestatic game.C_100271_mj.func_103430_a(byte, int, int, game.C_100153_be, int, int)void
		// @10E: goto @112
		// @111: athrow
		// @112: iload_1
		// @113: bipush 117 (0x75)
		// @115: if_icmpge @121
		// @118: aload_0
		// @119: iconst_1
		// @11A: putfield boolean game.C_100146_bf.field_105135_i
		// @11D: goto @121
		// @120: athrow
		// @121: goto @146
		// @124: astore_2
		// @125: aload_2
		// @126: new java.lang.StringBuilder
		// @129: dup
		// @12A: invokespecial java.lang.StringBuilder.<init>()void
		// @12D: getstatic java.lang.String[] game.C_100146_bf.field_105144_z
		// @130: bipush 15 (0x0F)
		// @132: aaload
		// @133: invokevirtual java.lang.StringBuilder.append(java.lang.String)java.lang.StringBuilder
		// @136: iload_1
		// @137: invokevirtual java.lang.StringBuilder.append(int)java.lang.StringBuilder
		// @13A: bipush 41 (0x29)
		// @13C: invokevirtual java.lang.StringBuilder.append(char)java.lang.StringBuilder
		// @13F: invokevirtual java.lang.StringBuilder.toString()java.lang.String
		// @142: invokestatic game.C_100181_cf.func_105695_a(java.lang.Throwable, java.lang.String)game.C_100170_cm
		// @145: athrow
		// @146: return
	}
	
	public static void func_105116_b(byte arg0)
	{
		// @00: aconst_null
		// @01: putstatic game.C_100117_p game.C_100146_bf.field_105124_e
		// @04: aconst_null
		// @05: putstatic java.lang.String game.C_100146_bf.field_105121_f
		// @08: aconst_null
		// @09: putstatic int[] game.C_100146_bf.field_105122_g
		// @0C: aconst_null
		// @0D: putstatic game.C_100217_ao game.C_100146_bf.field_105125_b
		// @10: iload_0
		// @11: bipush 118 (0x76)
		// @13: if_icmpge @17
		// @16: return
		// @17: aconst_null
		// @18: putstatic game.C_100302_ka game.C_100146_bf.field_105127_a
		// @1B: aconst_null
		// @1C: putstatic game.C_100009_fg game.C_100146_bf.field_105128_n
		// @1F: aconst_null
		// @20: putstatic java.lang.String[] game.C_100146_bf.field_105123_d
		// @23: goto @47
		// @26: astore_1
		// @27: aload_1
		// @28: new java.lang.StringBuilder
		// @2B: dup
		// @2C: invokespecial java.lang.StringBuilder.<init>()void
		// @2F: getstatic java.lang.String[] game.C_100146_bf.field_105144_z
		// @32: iconst_4
		// @33: aaload
		// @34: invokevirtual java.lang.StringBuilder.append(java.lang.String)java.lang.StringBuilder
		// @37: iload_0
		// @38: invokevirtual java.lang.StringBuilder.append(int)java.lang.StringBuilder
		// @3B: bipush 41 (0x29)
		// @3D: invokevirtual java.lang.StringBuilder.append(char)java.lang.StringBuilder
		// @40: invokevirtual java.lang.StringBuilder.toString()java.lang.String
		// @43: invokestatic game.C_100181_cf.func_105695_a(java.lang.Throwable, java.lang.String)game.C_100170_cm
		// @46: athrow
		// @47: return
	}
	
	static final C_100153_be func_105118_a(int arg0, int arg1, C_100098_h arg2, int arg3)
	{
		// @00: iload_3
		// @01: iconst_1
		// @02: aload_2
		// @03: iload_0
		// @04: invokestatic game.C_100333_ij.func_107341_a(int, boolean, game.C_100098_h, int)boolean
		// @07: ifne @0C
		// @0A: aconst_null
		// @0B: areturn
		// @0C: iload_1
		// @0D: bipush -127 (0x81)
		// @0F: if_icmple @1B
		// @12: bipush -20 (0xEC)
		// @14: invokestatic game.C_100146_bf.func_105116_b(byte)void
		// @17: goto @1B
		// @1A: athrow
		// @1B: iconst_1
		// @1C: invokestatic game.C_100051_ea.func_103298_o(int)game.C_100153_be
		// @1F: areturn
		// @20: astore #4
		// @22: aload #4
		// @24: new java.lang.StringBuilder
		// @27: dup
		// @28: invokespecial java.lang.StringBuilder.<init>()void
		// @2B: getstatic java.lang.String[] game.C_100146_bf.field_105144_z
		// @2E: bipush 21 (0x15)
		// @30: aaload
		// @31: invokevirtual java.lang.StringBuilder.append(java.lang.String)java.lang.StringBuilder
		// @34: iload_0
		// @35: invokevirtual java.lang.StringBuilder.append(int)java.lang.StringBuilder
		// @38: bipush 44 (0x2C)
		// @3A: invokevirtual java.lang.StringBuilder.append(char)java.lang.StringBuilder
		// @3D: iload_1
		// @3E: invokevirtual java.lang.StringBuilder.append(int)java.lang.StringBuilder
		// @41: bipush 44 (0x2C)
		// @43: invokevirtual java.lang.StringBuilder.append(char)java.lang.StringBuilder
		// @46: aload_2
		// @47: ifnull @53
		// @4A: getstatic java.lang.String[] game.C_100146_bf.field_105144_z
		// @4D: iconst_3
		// @4E: aaload
		// @4F: goto @58
		// @52: athrow
		// @53: getstatic java.lang.String[] game.C_100146_bf.field_105144_z
		// @56: iconst_1
		// @57: aaload
		// @58: invokevirtual java.lang.StringBuilder.append(java.lang.String)java.lang.StringBuilder
		// @5B: bipush 44 (0x2C)
		// @5D: invokevirtual java.lang.StringBuilder.append(char)java.lang.StringBuilder
		// @60: iload_3
		// @61: invokevirtual java.lang.StringBuilder.append(int)java.lang.StringBuilder
		// @64: bipush 41 (0x29)
		// @66: invokevirtual java.lang.StringBuilder.append(char)java.lang.StringBuilder
		// @69: invokevirtual java.lang.StringBuilder.toString()java.lang.String
		// @6C: invokestatic game.C_100181_cf.func_105695_a(java.lang.Throwable, java.lang.String)game.C_100170_cm
		// @6F: athrow
	}
	
	C_100146_bf(Applet arg0, String arg1, C_100153_be[] arg2, String[] arg3)
	{
		// @00: aload_0
		// @01: invokespecial java.lang.Object.<init>()void
		// @04: aload_0
		// @05: iconst_0
		// @06: putfield int game.C_100146_bf.field_105134_h
		// @09: aload_0
		// @0A: iconst_1
		// @0B: putfield boolean game.C_100146_bf.field_105135_i
		// @0E: aload_0
		// @0F: iconst_0
		// @10: putfield int game.C_100146_bf.field_105140_s
		// @13: aload_0
		// @14: aload_2
		// @15: aload #4
		// @17: aload_3
		// @18: aload_1
		// @19: iconst_1
		// @1A: sipush 26917 (0x6925)
		// @1D: invokespecial game.C_100146_bf.func_105115_a(java.lang.String, java.lang.String[], game.C_100153_be[], java.applet.Applet, boolean, int)void
		// @20: goto @A6
		// @23: astore #5
		// @25: aload #5
		// @27: new java.lang.StringBuilder
		// @2A: dup
		// @2B: invokespecial java.lang.StringBuilder.<init>()void
		// @2E: getstatic java.lang.String[] game.C_100146_bf.field_105144_z
		// @31: iconst_2
		// @32: aaload
		// @33: invokevirtual java.lang.StringBuilder.append(java.lang.String)java.lang.StringBuilder
		// @36: aload_1
		// @37: ifnull @43
		// @3A: getstatic java.lang.String[] game.C_100146_bf.field_105144_z
		// @3D: iconst_3
		// @3E: aaload
		// @3F: goto @48
		// @42: athrow
		// @43: getstatic java.lang.String[] game.C_100146_bf.field_105144_z
		// @46: iconst_1
		// @47: aaload
		// @48: invokevirtual java.lang.StringBuilder.append(java.lang.String)java.lang.StringBuilder
		// @4B: bipush 44 (0x2C)
		// @4D: invokevirtual java.lang.StringBuilder.append(char)java.lang.StringBuilder
		// @50: aload_2
		// @51: ifnull @5D
		// @54: getstatic java.lang.String[] game.C_100146_bf.field_105144_z
		// @57: iconst_3
		// @58: aaload
		// @59: goto @62
		// @5C: athrow
		// @5D: getstatic java.lang.String[] game.C_100146_bf.field_105144_z
		// @60: iconst_1
		// @61: aaload
		// @62: invokevirtual java.lang.StringBuilder.append(java.lang.String)java.lang.StringBuilder
		// @65: bipush 44 (0x2C)
		// @67: invokevirtual java.lang.StringBuilder.append(char)java.lang.StringBuilder
		// @6A: aload_3
		// @6B: ifnull @77
		// @6E: getstatic java.lang.String[] game.C_100146_bf.field_105144_z
		// @71: iconst_3
		// @72: aaload
		// @73: goto @7C
		// @76: athrow
		// @77: getstatic java.lang.String[] game.C_100146_bf.field_105144_z
		// @7A: iconst_1
		// @7B: aaload
		// @7C: invokevirtual java.lang.StringBuilder.append(java.lang.String)java.lang.StringBuilder
		// @7F: bipush 44 (0x2C)
		// @81: invokevirtual java.lang.StringBuilder.append(char)java.lang.StringBuilder
		// @84: aload #4
		// @86: ifnull @92
		// @89: getstatic java.lang.String[] game.C_100146_bf.field_105144_z
		// @8C: iconst_3
		// @8D: aaload
		// @8E: goto @97
		// @91: athrow
		// @92: getstatic java.lang.String[] game.C_100146_bf.field_105144_z
		// @95: iconst_1
		// @96: aaload
		// @97: invokevirtual java.lang.StringBuilder.append(java.lang.String)java.lang.StringBuilder
		// @9A: bipush 41 (0x29)
		// @9C: invokevirtual java.lang.StringBuilder.append(char)java.lang.StringBuilder
		// @9F: invokevirtual java.lang.StringBuilder.toString()java.lang.String
		// @A2: invokestatic game.C_100181_cf.func_105695_a(java.lang.Throwable, java.lang.String)game.C_100170_cm
		// @A5: athrow
		// @A6: return
	}
	
	static
	{
		// @000: bipush 24 (0x18)
		// @002: anewarray java.lang.String
		// @005: dup
		// @006: iconst_0
		// @007: ldc "y\u00011\rn"
		// @009: invokestatic game.C_100146_bf.func_105114_z(java.lang.String)char[]
		// @00C: invokestatic game.C_100146_bf.func_105111_z(char[])java.lang.String
		// @00F: aastore
		// @010: dup
		// @011: iconst_1
		// @012: ldc "u\u0012s)"
		// @014: invokestatic game.C_100146_bf.func_105114_z(java.lang.String)char[]
		// @017: invokestatic game.C_100146_bf.func_105111_z(char[])java.lang.String
		// @01A: aastore
		// @01B: dup
		// @01C: iconst_2
		// @01D: ldc "y\u00011y/u\u000ek{n"
		// @01F: invokestatic game.C_100146_bf.func_105114_z(java.lang.String)char[]
		// @022: invokestatic game.C_100146_bf.func_105111_z(char[])java.lang.String
		// @025: aastore
		// @026: dup
		// @027: iconst_3
		// @028: ldc "`I1k;"
		// @02A: invokestatic game.C_100146_bf.func_105114_z(java.lang.String)char[]
		// @02D: invokestatic game.C_100146_bf.func_105111_z(char[])java.lang.String
		// @030: aastore
		// @031: dup
		// @032: iconst_4
		// @033: ldc "y\u00011\tn"
		// @035: invokestatic game.C_100146_bf.func_105114_z(java.lang.String)char[]
		// @038: invokestatic game.C_100146_bf.func_105111_z(char[])java.lang.String
		// @03B: aastore
		// @03C: dup
		// @03D: iconst_5
		// @03E: ldc "y\u00011\u0002n"
		// @040: invokestatic game.C_100146_bf.func_105114_z(java.lang.String)char[]
		// @043: invokestatic game.C_100146_bf.func_105111_z(char[])java.lang.String
		// @046: aastore
		// @047: dup
		// @048: bipush 6 (0x06)
		// @04A: ldc "y\u0012k1)u8w,!s\u000bv\".o\u0014"
		// @04C: invokestatic game.C_100146_bf.func_105114_z(java.lang.String)char[]
		// @04F: invokestatic game.C_100146_bf.func_105111_z(char[])java.lang.String
		// @052: aastore
		// @053: dup
		// @054: bipush 7 (0x07)
		// @056: ldc "y\u0002q  r\u0013@*4y\u0014"
		// @058: invokestatic game.C_100146_bf.func_105114_z(java.lang.String)char[]
		// @05B: invokestatic game.C_100146_bf.func_105111_z(char[])java.lang.String
		// @05E: aastore
		// @05F: dup
		// @060: bipush 8 (0x08)
		// @062: ldc "z\u0015m*1"
		// @064: invokestatic game.C_100146_bf.func_105114_z(java.lang.String)char[]
		// @067: invokestatic game.C_100146_bf.func_105111_z(char[])java.lang.String
		// @06A: aastore
		// @06B: dup
		// @06C: bipush 9 (0x09)
		// @06E: ldc "y\u0012k1)u8k >o"
		// @070: invokestatic game.C_100146_bf.func_105114_z(java.lang.String)char[]
		// @073: invokestatic game.C_100146_bf.func_105111_z(char[])java.lang.String
		// @076: aastore
		// @077: dup
		// @078: bipush 10 (0x0A)
		// @07A: ldc "y\u00011\u000fn"
		// @07C: invokestatic game.C_100146_bf.func_105114_z(java.lang.String)char[]
		// @07F: invokestatic game.C_100146_bf.func_105111_z(char[])java.lang.String
		// @082: aastore
		// @083: dup
		// @084: bipush 11 (0x0B)
		// @086: ldc "}\u0015~(#"
		// @088: invokestatic game.C_100146_bf.func_105114_z(java.lang.String)char[]
		// @08B: invokestatic game.C_100146_bf.func_105111_z(char[])java.lang.String
		// @08E: aastore
		// @08F: dup
		// @090: bipush 12 (0x0C)
		// @092: ldc "v\u0002r'#i\u0014@ >k\u0006q6/t\t@6%i\u0002z+"
		// @094: invokestatic game.C_100146_bf.func_105114_z(java.lang.String)char[]
		// @097: invokestatic game.C_100146_bf.func_105111_z(char[])java.lang.String
		// @09A: aastore
		// @09B: dup
		// @09C: bipush 13 (0x0D)
		// @09E: ldc "k\u0012r5u)"
		// @0A0: invokestatic game.C_100146_bf.func_105114_z(java.lang.String)char[]
		// @0A3: invokestatic game.C_100146_bf.func_105111_z(char[])java.lang.String
		// @0A6: aastore
		// @0A7: dup
		// @0A8: bipush 14 (0x0E)
		// @0AA: ldc "z\u0015v$*r\u0014wtt"
		// @0AC: invokestatic game.C_100146_bf.func_105114_z(java.lang.String)char[]
		// @0AF: invokestatic game.C_100146_bf.func_105111_z(char[])java.lang.String
		// @0B2: aastore
		// @0B3: dup
		// @0B4: bipush 15 (0x0F)
		// @0B6: ldc "y\u00011\u0003n"
		// @0B8: invokestatic game.C_100146_bf.func_105114_z(java.lang.String)char[]
		// @0BB: invokestatic game.C_100146_bf.func_105111_z(char[])java.lang.String
		// @0BE: aastore
		// @0BF: dup
		// @0C0: bipush 16 (0x10)
		// @0C2: ldc "y\u00011\u0007n"
		// @0C4: invokestatic game.C_100146_bf.func_105114_z(java.lang.String)char[]
		// @0C7: invokestatic game.C_100146_bf.func_105111_z(char[])java.lang.String
		// @0CA: aastore
		// @0CB: dup
		// @0CC: bipush 17 (0x11)
		// @0CE: ldc "x\u0012m7#u\u0004f"
		// @0D0: invokestatic game.C_100146_bf.func_105114_z(java.lang.String)char[]
		// @0D3: invokestatic game.C_100146_bf.func_105111_z(char[])java.lang.String
		// @0D6: aastore
		// @0D7: dup
		// @0D8: bipush 18 (0x12)
		// @0DA: ldc "y\u00011\u000cn"
		// @0DC: invokestatic game.C_100146_bf.func_105114_z(java.lang.String)char[]
		// @0DF: invokestatic game.C_100146_bf.func_105111_z(char[])java.lang.String
		// @0E2: aastore
		// @0E3: dup
		// @0E4: bipush 19 (0x13)
		// @0E6: ldc "y\u00011\u000en"
		// @0E8: invokestatic game.C_100146_bf.func_105114_z(java.lang.String)char[]
		// @0EB: invokestatic game.C_100146_bf.func_105111_z(char[])java.lang.String
		// @0EE: aastore
		// @0EF: dup
		// @0F0: bipush 20 (0x14)
		// @0F2: ldc "y\u00011\u0004n"
		// @0F4: invokestatic game.C_100146_bf.func_105114_z(java.lang.String)char[]
		// @0F7: invokestatic game.C_100146_bf.func_105111_z(char[])java.lang.String
		// @0FA: aastore
		// @0FB: dup
		// @0FC: bipush 21 (0x15)
		// @0FE: ldc "y\u00011\u0001n"
		// @100: invokestatic game.C_100146_bf.func_105114_z(java.lang.String)char[]
		// @103: invokestatic game.C_100146_bf.func_105111_z(char[])java.lang.String
		// @106: aastore
		// @107: dup
		// @108: bipush 22 (0x16)
		// @10A: ldc "y\u00011\u0006n"
		// @10C: invokestatic game.C_100146_bf.func_105114_z(java.lang.String)char[]
		// @10F: invokestatic game.C_100146_bf.func_105111_z(char[])java.lang.String
		// @112: aastore
		// @113: dup
		// @114: bipush 23 (0x17)
		// @116: ldc "y\u00011\u0000n"
		// @118: invokestatic game.C_100146_bf.func_105114_z(java.lang.String)char[]
		// @11B: invokestatic game.C_100146_bf.func_105111_z(char[])java.lang.String
		// @11E: aastore
		// @11F: putstatic java.lang.String[] game.C_100146_bf.field_105144_z
		// @122: new game.C_100217_ao
		// @125: dup
		// @126: bipush 6 (0x06)
		// @128: iconst_0
		// @129: iconst_4
		// @12A: iconst_2
		// @12B: invokespecial game.C_100217_ao.<init>(int, int, int, int)void
		// @12E: putstatic game.C_100217_ao game.C_100146_bf.field_105125_b
		// @131: iconst_0
		// @132: putstatic int game.C_100146_bf.field_105132_j
		// @135: ldc "^4\\ek;\u0004~+%~\u000b?54r\u0011~1#;\nz65z\u0000z"
		// @137: invokestatic game.C_100146_bf.func_105114_z(java.lang.String)char[]
		// @13A: invokestatic game.C_100146_bf.func_105111_z(char[])java.lang.String
		// @13D: putstatic java.lang.String game.C_100146_bf.field_105121_f
		// @140: sipush 8192 (0x2000)
		// @143: newarray int[]
		// @145: putstatic int[] game.C_100146_bf.field_105122_g
		// @148: bipush 6 (0x06)
		// @14A: anewarray java.lang.String
		// @14D: dup
		// @14E: iconst_0
		// @14F: ldc "W\u0008~!/u\u0000?1#c\u0013"
		// @151: invokestatic game.C_100146_bf.func_105114_z(java.lang.String)char[]
		// @154: invokestatic game.C_100146_bf.func_105111_z(char[])java.lang.String
		// @157: aastore
		// @158: dup
		// @159: iconst_1
		// @15A: ldc "W\u0006{ fO\u0002g1"
		// @15C: invokestatic game.C_100146_bf.func_105114_z(java.lang.String)char[]
		// @15F: invokestatic game.C_100146_bf.func_105111_z(char[])java.lang.String
		// @162: aastore
		// @163: dup
		// @164: iconst_2
		// @165: ldc "X\u000f~7!~\nz+2;\u0003je2~\u001fk "
		// @167: invokestatic game.C_100146_bf.func_105114_z(java.lang.String)char[]
		// @16A: invokestatic game.C_100146_bf.func_105111_z(char[])java.lang.String
		// @16D: aastore
		// @16E: dup
		// @16F: iconst_3
		// @170: ldc "X\u0006m7#|\u0006q!);\u0013z=2t\u0014"
		// @172: invokestatic game.C_100146_bf.func_105114_z(java.lang.String)char[]
		// @175: invokestatic game.C_100146_bf.func_105111_z(char[])java.lang.String
		// @178: aastore
		// @179: dup
		// @17A: iconst_4
		// @17B: ldc "O\u0002t62;\u000b~!#u"
		// @17D: invokestatic game.C_100146_bf.func_105114_z(java.lang.String)char[]
		// @180: invokestatic game.C_100146_bf.func_105111_z(char[])java.lang.String
		// @183: aastore
		// @184: dup
		// @185: iconst_5
		// @186: ldc "X\u0006m\"'u\u0003pe2~\u001fk*"
		// @188: invokestatic game.C_100146_bf.func_105114_z(java.lang.String)char[]
		// @18B: invokestatic game.C_100146_bf.func_105111_z(char[])java.lang.String
		// @18E: aastore
		// @18F: putstatic java.lang.String[] game.C_100146_bf.field_105123_d
		// @192: return
	}
	
	private static char[] func_105114_z(String arg0)
	{
		// @00: aload_0
		// @01: invokevirtual java.lang.String.toCharArray()char[]
		// @04: dup
		// @05: arraylength
		// @06: iconst_2
		// @07: if_icmpge @13
		// @0A: dup
		// @0B: iconst_0
		// @0C: dup2
		// @0D: caload
		// @0E: bipush 70 (0x46)
		// @10: ixor
		// @11: i2c
		// @12: castore
		// @13: areturn
	}
	
	private static String func_105111_z(char[] arg0)
	{
		// @00: aload_0
		// @01: dup
		// @02: arraylength
		// @03: swap
		// @04: iconst_0
		// @05: istore_1
		// @06: goto @4C
		// @09: dup
		// @0A: iload_1
		// @0B: dup2
		// @0C: caload
		// @0D: iload_1
		// @0E: iconst_5
		// @0F: irem
		// @10: tableswitch def: @44, for 0: @30, for 1: @35, for 2: @3A, for 3: @3F
		// @30: bipush 27 (0x1B)
		// @32: goto @46
		// @35: bipush 103 (0x67)
		// @37: goto @46
		// @3A: bipush 31 (0x1F)
		// @3C: goto @46
		// @3F: bipush 69 (0x45)
		// @41: goto @46
		// @44: bipush 70 (0x46)
		// @46: ixor
		// @47: i2c
		// @48: castore
		// @49: iinc #1 +1
		// @4C: swap
		// @4D: dup_x1
		// @4E: iload_1
		// @4F: if_icmpgt @09
		// @52: new java.lang.String
		// @55: dup_x1
		// @56: swap
		// @57: invokespecial java.lang.String.<init>(char[])void
		// @5A: invokevirtual java.lang.String.intern()java.lang.String
		// @5D: areturn
	}
}
