package game;

final class C_100125_tm extends C_100158_da
{
	static int field_100745_p;
	int field_100750_j;
	static boolean field_100748_l;
	static String field_100746_n;
	static String field_100749_m;
	int field_100744_q;
	static String[] field_100752_k;
	static C_100101_fc field_100747_o;
	private static final String[] field_100751_z;
	
	public static void func_100742_e(int arg0)
	{
		// @00: bipush -7 (0xF9)
		// @02: bipush 9 (0x09)
		// @04: iload_0
		// @05: isub
		// @06: bipush 59 (0x3B)
		// @08: idiv
		// @09: idiv
		// @0A: istore_1
		// @0B: aconst_null
		// @0C: putstatic game.C_100101_fc game.C_100125_tm.field_100747_o
		// @0F: aconst_null
		// @10: putstatic java.lang.String game.C_100125_tm.field_100746_n
		// @13: aconst_null
		// @14: putstatic java.lang.String game.C_100125_tm.field_100749_m
		// @17: aconst_null
		// @18: putstatic java.lang.String[] game.C_100125_tm.field_100752_k
		// @1B: goto @3F
		// @1E: astore_1
		// @1F: aload_1
		// @20: new java.lang.StringBuilder
		// @23: dup
		// @24: invokespecial java.lang.StringBuilder.<init>()void
		// @27: getstatic java.lang.String[] game.C_100125_tm.field_100751_z
		// @2A: iconst_4
		// @2B: aaload
		// @2C: invokevirtual java.lang.StringBuilder.append(java.lang.String)java.lang.StringBuilder
		// @2F: iload_0
		// @30: invokevirtual java.lang.StringBuilder.append(int)java.lang.StringBuilder
		// @33: bipush 41 (0x29)
		// @35: invokevirtual java.lang.StringBuilder.append(char)java.lang.StringBuilder
		// @38: invokevirtual java.lang.StringBuilder.toString()java.lang.String
		// @3B: invokestatic game.C_100181_cf.func_105695_a(java.lang.Throwable, java.lang.String)game.C_100170_cm
		// @3E: athrow
		// @3F: return
	}
	
	static final void func_100743_a(C_100073_f arg0, int arg1)
	{
		// @00: aload_0
		// @01: iconst_1
		// @02: newarray char[]
		// @04: dup
		// @05: iconst_0
		// @06: bipush 63 (0x3F)
		// @08: castore
		// @09: putfield char[] game.C_100073_f.field_101712_w
		// @0C: aload_0
		// @0D: iconst_1
		// @0E: newarray int[]
		// @10: dup
		// @11: iconst_0
		// @12: iload_1
		// @13: iastore
		// @14: putfield int[] game.C_100073_f.field_101721_y
		// @17: goto @55
		// @1A: astore_2
		// @1B: aload_2
		// @1C: new java.lang.StringBuilder
		// @1F: dup
		// @20: invokespecial java.lang.StringBuilder.<init>()void
		// @23: getstatic java.lang.String[] game.C_100125_tm.field_100751_z
		// @26: iconst_5
		// @27: aaload
		// @28: invokevirtual java.lang.StringBuilder.append(java.lang.String)java.lang.StringBuilder
		// @2B: aload_0
		// @2C: ifnull @38
		// @2F: getstatic java.lang.String[] game.C_100125_tm.field_100751_z
		// @32: iconst_3
		// @33: aaload
		// @34: goto @3D
		// @37: athrow
		// @38: getstatic java.lang.String[] game.C_100125_tm.field_100751_z
		// @3B: iconst_1
		// @3C: aaload
		// @3D: invokevirtual java.lang.StringBuilder.append(java.lang.String)java.lang.StringBuilder
		// @40: bipush 44 (0x2C)
		// @42: invokevirtual java.lang.StringBuilder.append(char)java.lang.StringBuilder
		// @45: iload_1
		// @46: invokevirtual java.lang.StringBuilder.append(int)java.lang.StringBuilder
		// @49: bipush 41 (0x29)
		// @4B: invokevirtual java.lang.StringBuilder.append(char)java.lang.StringBuilder
		// @4E: invokevirtual java.lang.StringBuilder.toString()java.lang.String
		// @51: invokestatic game.C_100181_cf.func_105695_a(java.lang.Throwable, java.lang.String)game.C_100170_cm
		// @54: athrow
		// @55: return
	}
	
	static final C_100130_tf func_100741_a(String arg0, int arg1)
	{
		// @00: aload_0
		// @01: ifnull @12
		// @04: aload_0
		// @05: invokevirtual java.lang.String.length()int
		// @08: iconst_m1
		// @09: ixor
		// @0A: iconst_m1
		// @0B: if_icmpne @16
		// @0E: goto @12
		// @11: athrow
		// @12: getstatic game.C_100130_tf game.C_100033_gj.field_101930_cc
		// @15: areturn
		// @16: aload_0
		// @17: bipush 64 (0x40)
		// @19: invokevirtual java.lang.String.indexOf(int)int
		// @1C: istore_2
		// @1D: iload_1
		// @1E: sipush -30335 (0x8981)
		// @21: if_icmpeq @2F
		// @24: aconst_null
		// @25: checkcast game.C_100101_fc
		// @28: putstatic game.C_100101_fc game.C_100125_tm.field_100747_o
		// @2B: goto @2F
		// @2E: athrow
		// @2F: iconst_0
		// @30: iload_2
		// @31: iconst_m1
		// @32: ixor
		// @33: if_icmpne @3A
		// @36: getstatic game.C_100130_tf game.C_100082_uf.field_100374_a
		// @39: areturn
		// @3A: aload_0
		// @3B: iconst_0
		// @3C: iload_2
		// @3D: invokevirtual java.lang.String.substring(int, int)java.lang.String
		// @40: astore_3
		// @41: aload_0
		// @42: iload_2
		// @43: iconst_m1
		// @44: isub
		// @45: invokevirtual java.lang.String.substring(int)java.lang.String
		// @48: astore #4
		// @4A: sipush 5244 (0x147C)
		// @4D: aload_3
		// @4E: invokestatic game.C_100166_sg.func_105461_a(int, java.lang.String)game.C_100130_tf
		// @51: astore #5
		// @53: aconst_null
		// @54: aload #5
		// @56: if_acmpeq @5C
		// @59: aload #5
		// @5B: areturn
		// @5C: aload #4
		// @5E: iload_1
		// @5F: sipush 30334 (0x767E)
		// @62: iadd
		// @63: invokestatic game.C_100325_id.func_101476_a(java.lang.String, int)game.C_100130_tf
		// @66: areturn
		// @67: astore_2
		// @68: aload_2
		// @69: new java.lang.StringBuilder
		// @6C: dup
		// @6D: invokespecial java.lang.StringBuilder.<init>()void
		// @70: getstatic java.lang.String[] game.C_100125_tm.field_100751_z
		// @73: iconst_2
		// @74: aaload
		// @75: invokevirtual java.lang.StringBuilder.append(java.lang.String)java.lang.StringBuilder
		// @78: aload_0
		// @79: ifnull @85
		// @7C: getstatic java.lang.String[] game.C_100125_tm.field_100751_z
		// @7F: iconst_3
		// @80: aaload
		// @81: goto @8A
		// @84: athrow
		// @85: getstatic java.lang.String[] game.C_100125_tm.field_100751_z
		// @88: iconst_1
		// @89: aaload
		// @8A: invokevirtual java.lang.StringBuilder.append(java.lang.String)java.lang.StringBuilder
		// @8D: bipush 44 (0x2C)
		// @8F: invokevirtual java.lang.StringBuilder.append(char)java.lang.StringBuilder
		// @92: iload_1
		// @93: invokevirtual java.lang.StringBuilder.append(int)java.lang.StringBuilder
		// @96: bipush 41 (0x29)
		// @98: invokevirtual java.lang.StringBuilder.append(char)java.lang.StringBuilder
		// @9B: invokevirtual java.lang.StringBuilder.toString()java.lang.String
		// @9E: invokestatic game.C_100181_cf.func_105695_a(java.lang.Throwable, java.lang.String)game.C_100170_cm
		// @A1: athrow
	}
	
	private C_100125_tm() throws Throwable
	{
		// @00: aload_0
		// @01: invokespecial game.C_100158_da.<init>()void
		// @04: new java.lang.Error
		// @07: dup
		// @08: invokespecial java.lang.Error.<init>()void
		// @0B: athrow
		// @0C: astore_1
		// @0D: aload_1
		// @0E: getstatic java.lang.String[] game.C_100125_tm.field_100751_z
		// @11: iconst_0
		// @12: aaload
		// @13: invokestatic game.C_100181_cf.func_105695_a(java.lang.Throwable, java.lang.String)game.C_100170_cm
		// @16: athrow
	}
	
	static
	{
		// @000: bipush 6 (0x06)
		// @002: anewarray java.lang.String
		// @005: dup
		// @006: iconst_0
		// @007: ldc "YAd$\"CE>&c\u0004"
		// @009: invokestatic game.C_100125_tm.func_100740_z(java.lang.String)char[]
		// @00C: invokestatic game.C_100125_tm.func_100739_z(char[])java.lang.String
		// @00F: aastore
		// @010: dup
		// @011: iconst_1
		// @012: ldc "CY&t"
		// @014: invokestatic game.C_100125_tm.func_100740_z(java.lang.String)char[]
		// @017: invokestatic game.C_100125_tm.func_100739_z(char[])java.lang.String
		// @01A: aastore
		// @01B: dup
		// @01C: iconst_2
		// @01D: ldc "YAd[c"
		// @01F: invokestatic game.C_100125_tm.func_100740_z(java.lang.String)char[]
		// @022: invokestatic game.C_100125_tm.func_100739_z(char[])java.lang.String
		// @025: aastore
		// @026: dup
		// @027: iconst_3
		// @028: ldc "V\u0002d66"
		// @02A: invokestatic game.C_100125_tm.func_100740_z(java.lang.String)char[]
		// @02D: invokestatic game.C_100125_tm.func_100739_z(char[])java.lang.String
		// @030: aastore
		// @031: dup
		// @032: iconst_4
		// @033: ldc "YAdYc"
		// @035: invokestatic game.C_100125_tm.func_100740_z(java.lang.String)char[]
		// @038: invokestatic game.C_100125_tm.func_100739_z(char[])java.lang.String
		// @03B: aastore
		// @03C: dup
		// @03D: iconst_5
		// @03E: ldc "YAdZc"
		// @040: invokestatic game.C_100125_tm.func_100740_z(java.lang.String)char[]
		// @043: invokestatic game.C_100125_tm.func_100739_z(char[])java.lang.String
		// @046: aastore
		// @047: putstatic java.lang.String[] game.C_100125_tm.field_100751_z
		// @04A: iconst_0
		// @04B: putstatic int game.C_100125_tm.field_100745_p
		// @04E: ldc "}@/y8H\u000c=y\"Y\u000c?v?D@jt$LH#v,\rD+kkKE$q8EI.6"
		// @050: invokestatic game.C_100125_tm.func_100740_z(java.lang.String)char[]
		// @053: invokestatic game.C_100125_tm.func_100739_z(char[])java.lang.String
		// @056: putstatic java.lang.String game.C_100125_tm.field_100749_m
		// @059: bipush 30 (0x1E)
		// @05B: anewarray java.lang.String
		// @05E: dup
		// @05F: iconst_0
		// @060: ldc "zI&{$@If8w\u0008\u001ct4kYCjl#H\u000c,q9^Xjl9LE$q%J\u000c'q8^E%ve\u0011N8&wO^tQ%\rX\"q8\rA#k8DC$82BYjo\"A@jz.\rY9q%J\u000c+88Y^#h;HHg|$ZBjn.__#w%\rC,8$CIjw-\rC?jk^X+h'H\u000c9}%YE$}'^\u0000jl#H\u000c\u0019t*[Ig{'L_98(EM9k\"^\u0002jA$X\u000c=q'A\u000c(}kYM?\u007f#Y\u000c\"w<\rX%8$]I8y?H\u000c#l8\rA%n.@I$lk^U9l.@_jy%I\u000c>j2\rU%m9\r_!q'A_jq%\rMjk\"@\\&}kNC'z*Y\u000c/`._O#k.\u0003\u0010(juyD/j.\rE98&XO\"82BYjv.HHjl$\rG$w<\rN/~$_Ija$X\u000c)y%\rN/8?_Y9l.I\u000c%vkYD/8)LX>t.KE/t/\u0003\u000c\u0005v(H\u000c3w>\r\\8w=H\u000c3w>_\u000c9s\"A@98\"C\u000c>p\"^\u000c)y&]M#\u007f%\u0001\u000c3w>\r[#t'\rN/8*O@/8?B\u000c:q?\rU%m9\r_!q'A_jy,LE$k?\rC>p._\u000c9}%YE$}'\rO%u&LB.}9^\u000c,j$@\u000c+j$XB.8?EIjm%DZ/j8H\u0002vz9\u0013\u0010(jubBjl$\rZ#{?B^39"
		// @062: invokestatic game.C_100125_tm.func_100740_z(java.lang.String)char[]
		// @065: invokestatic game.C_100125_tm.func_100739_z(char[])java.lang.String
		// @068: aastore
		// @069: dup
		// @06A: iconst_1
		// @06B: ldc "zI&{$@Ijl$\rX\"}k^I)w%I\u000c>j*DB#v,\rA#k8DC$4k\u0011\tz&e\u0011N8&wO^tQ%\rX\"q8\rA#k8DC$82BYjo\"A@jz.\rY9q%J\u000c+8\u0018AM<}kZE>pkLBj}3YI$|.I\u000c+j9LUjw-\r\\#}9NI889BO!}?^\u0002jA$X\u000c=q'A\u000c&}*_Bjy)BY>8<HM:w%\rX8y!HO>w9DI98*CHjy>YC'y?DOjj$NG/lkII,}%NId$)_\u0012vz9\u0013c$8?B\u000c<q(YC8aj"
		// @06D: invokestatic game.C_100125_tm.func_100740_z(java.lang.String)char[]
		// @070: invokestatic game.C_100125_tm.func_100739_z(char[])java.lang.String
		// @073: aastore
		// @074: dup
		// @075: iconst_2
		// @076: ldc "tC?jkY^+q%DB-8\"^\u000c:j$NI/|\"CKjo.A@f8w\u0008\u001ct6wO^t$)_\u0012\u0013w>\rD+n.\rO%u;AI>}/\rE$q?DM&8?_M#v\"CKf8)XXjz.KC8}kTC?8*_Ij~>A@38(AI+j.I\u000c>wkX_/8?EIjK'LZ/5(AM9kk^I$l\"CI&4kTC?8&X_>8)H\u000c>}8YI.8\"C\u000c(y?Y@/6wO^t$)_\u0012\u001ey H\u000c>p.\r\u007f&y=H\u000c>wkYD/8<L^0w%H\u000c+v/\rH/k?_C38?EIj}%HA388HB>q%H@96wO^t$)_\u0012\u0005vkYCjn\"NX%j2\u000c"
		// @078: invokestatic game.C_100125_tm.func_100740_z(java.lang.String)char[]
		// @07B: invokestatic game.C_100125_tm.func_100739_z(char[])java.lang.String
		// @07E: aastore
		// @07F: dup
		// @080: iconst_3
		// @081: ldc "zI&{$@If8w\u0008\u001ct4kYCjl#H\u000c>j*DB#v,\rJ%jkYD/8\n\\Y#t*\u0000O&y8^\u000c9}%YE$}'\u0003\u0010(ju\u0011N8&\u001fEIjY:XE&ykD_jykKM9lg\r@#\u007f#Y[/q,EXjk.CX#v.A\u000c)y;LN&}kBJj~'DK\"le\ru%mkZE&tkAI+j%\rM(w>Y\u000c?k\"CKjl#_Y9lg\rI$}9JUju*CM-}&HB>4kLB.8'L_/j8\u0003\u0010(ju\u0011N8&\u0004C\u000c>wk[E)l$_Uk"
		// @083: invokestatic game.C_100125_tm.func_100740_z(java.lang.String)char[]
		// @086: invokestatic game.C_100125_tm.func_100739_z(char[])java.lang.String
		// @089: aastore
		// @08A: dup
		// @08B: iconst_4
		// @08C: ldc "yD/8%HT>8;EM9}kBJja$X^jY:XE&ykY^+q%DB-8\"^\u000c&q=H\u000c)w&OM>4k\u0011\tz&e\u0011N8&wO^tL*FIjl#H\u000c\u000bi>D@+8?B\u000c>p.\r[+j1BB/8*CHj|.^X8w2\rC?jkHB/u\"H_d$)_\u0012vz9\u0013~/u.@N/jkTC?jkY^+q%DB-8$C\u000c/v._K38&LB+\u007f.@I$le\re,82BYjj>C\u000c%m?\rC,8.CI8\u007f2\r[\"q'H\u000c#vkOM>l'H\u0000ja$X\u000c=q'A\u000c(}k[I8ak[Y&v._M(t.\rX%8*YX+{ \u0003\u0010(ju\u0011N8&\u0004C\u000c>wk[E)l$_Uk"
		// @08E: invokestatic game.C_100125_tm.func_100740_z(java.lang.String)char[]
		// @091: invokestatic game.C_100125_tm.func_100739_z(char[])java.lang.String
		// @094: aastore
		// @095: dup
		// @096: iconst_5
		// @097: ldc "zI&{$@Ijl$\rX+j,HX#v,\rM$|k@E9k\"AIjl9LE$q%J\u0000j$n\u001d\u0012d$)_\u0012vz9\u0013e$8?EE98&D_9q$C\u000c3w>\r[#t'\rN/8>^E$\u007fkL\u000c,m'A\u000c\u000bi>D@+4kLB.8'HM8v\"CKjl$\rY9}kDX98?L^-}?DB-88T_>}&^\u000c+v/\rA#k8D@/ke\u0011N8&wO^tW%\rX%8=DO>w9T\r"
		// @099: invokestatic game.C_100125_tm.func_100740_z(java.lang.String)char[]
		// @09C: invokestatic game.C_100125_tm.func_100739_z(char[])java.lang.String
		// @09F: aastore
		// @0A0: dup
		// @0A1: bipush 6 (0x06)
		// @0A3: ldc "tC?jk^G#t'^\u000c+j.\r\\8w,_I9k\"CKjo.A@f8w\u0008\u001ct6wO^t$)_\u0012\u001ep.\r@+k?\r\\+j?\rC,8\n\\Y#t*\rX8y\"CE$\u007fkD_jykKE/t/\rM9k.^_'}%Y\u0002jW%\rMjv.L^(akZC8t/\rE98*\r^?q%HHj{\"YUjq%\r[\"q(E\u000c/v.@Ujk.CX#v.A_jp*[Ijz.HBjj.]C8l.I\u0002jH9BO/}/\rH%o%\rX%8?EIj{\"YUjo\"YDjl#H\u000c\u000bi>D@+8*CHj|$\rN+l?AId$)_\u0012vz9\u0013c$8?B\u000c<q(YC8aj"
		// @0A5: invokestatic game.C_100125_tm.func_100740_z(java.lang.String)char[]
		// @0A8: invokestatic game.C_100125_tm.func_100739_z(char[])java.lang.String
		// @0AB: aastore
		// @0AC: dup
		// @0AD: bipush 7 (0x07)
		// @0AF: ldc "zI&{$@If8w\u0008\u001ct4kYCjl#H\u000c>j*DB#v,\rJ%jkYD/8\u000cB@/ufN@+k8\r_/v?DB/te\u0011N8&wO^tL#H\u000c\rw'HAjq8\rJ%j&DH+z'H\u000c#vkYD/8(BB>j$A\u000c%~kL\u000c9s\"A@/|k]E&w?\u0003\u000c\u0003l8\rO+v%BBjy%I\u000c\"}*[Ujj$NG/lkNM$8\"CJ&q(Y\u000c9}=H^/8.U\\&w8DZ/8/LA+\u007f.\u0001\u000c+v/\rE>kk^O+v%H^ju$IY&}kL@&w<^\u000c#lkYCjy\"@\u000c&w%J\u00018y%JIjo.L\\%v8\r[#l#\r@/l#L@jy(NY8y(T\u0002vz9\u0013\u0010(jubBjl$\rZ#{?B^39"
		// @0B1: invokestatic game.C_100125_tm.func_100740_z(java.lang.String)char[]
		// @0B4: invokestatic game.C_100125_tm.func_100739_z(char[])java.lang.String
		// @0B7: aastore
		// @0B8: dup
		// @0B9: bipush 8 (0x08)
		// @0BB: ldc "yD/8%HT>8&D_9q$C\u000c#kkL\u000c,q.AHjl.^Xf8w\u0008\u001ct6wO^t$)_\u0012\u0013w>\r[#t'\rN/8>^E$\u007fkL\u000c\rw'HAf8*_A/|kZE>pkL\u000c\"}*[Ujj$NG/lg\rO+v%BBf8*CHj\u007f>C\u0002jJ.YY8vkYCjl#H\u000c=y9WC$}kLB.8/H_>j$T\u000c>p.\rI$}&T\u000c,w9NI98?EI8}e\u0011N8&wO^tW%\rX%8=DO>w9T\r"
		// @0BD: invokestatic game.C_100125_tm.func_100740_z(java.lang.String)char[]
		// @0C0: invokestatic game.C_100125_tm.func_100739_z(char[])java.lang.String
		// @0C3: aastore
		// @0C4: dup
		// @0C5: bipush 9 (0x09)
		// @0C7: ldc "zI&{$@Ijl$\rX\"}kK@+skY^+q%DB-8&D_9q$C\u0000j$n\u001d\u0012d$)_\u0012vz9\u0013x\"}k^X+v/L^.8\u000cB@/ukD_jy9@I.8<DX\"8*\rJ&y \r^/h.LX/jkLB.8*D^(m9^Xjj$NG/l8\u0003\u000c\u001fk\"CKjl#HAj}-KI)l\"[I&akD_jykFI38;L^>8$K\u000c>p.\rk%t.@\u000b98/HJ/v(H_d$)_\u0012vz9\u0013c${.\rX\"q8\rA#k8DC$8\"^\u000c)w&]@/l.\u0001\u000c3w>\r[#t'\rN/8(AI+jkYCjl*FIjl#H\u000c\rw'HAjw>Y\u000c#v?B\u000c(y?Y@/6wO^t$)_\u0012\u0005vkYCjn\"NX%j2\u000c"
		// @0C9: invokestatic game.C_100125_tm.func_100740_z(java.lang.String)char[]
		// @0CC: invokestatic game.C_100125_tm.func_100739_z(char[])java.lang.String
		// @0CF: aastore
		// @0D0: dup
		// @0D1: bipush 10 (0x0A)
		// @0D3: ldc "yD/8\u0007B_>8\u001cB^&|kD_jyk]@+v.Y\u000c(}\"CKjz*YX&}/\rC<}9\rN38$_N#l\"CKjk?L^j{9XE9}9^\u0002jO#D@/8?EI38/H_>j$T\u000c/y(E\u000c%l#H^f88HB>q%H@98)LX>t.\rC$8?EIjk>_J+{.\u0003\u0010(ju\u0011N8&w\u0008\u001dt4kYM!}kYD/8\u0018AM<}fN@+k8\r_/v?DB/tg\rH8w;\rE>8/B[$8?B\u000c>p.\r_?j-LO/8*CHj|.^X8w2\rM&tkHB/u\"H_d$)_\u0012vz9\u0013c$8?B\u000c8q(EI98*CHjn\"NX%j2\u000c"
		// @0D5: invokestatic game.C_100125_tm.func_100740_z(java.lang.String)char[]
		// @0D8: invokestatic game.C_100125_tm.func_100739_z(char[])java.lang.String
		// @0DB: aastore
		// @0DC: dup
		// @0DD: bipush 11 (0x0B)
		// @0DF: ldc "\u0011\t{&g\rU%m9\rA#k8DC$8?B\u000c>p.\r`%k?\r{%j'I\u000c\"y8\r@/|kYCjq%YI&t\"JI${.\rX\"y?\rC?jkHB/u\"H_jy9H\u000c.};AC3q%J\u000c-j$XB.88HB>q%H@98<DX\"8;B[/j-X@jy9YE&t._Ujo.L\\%v8\u0003\u000c\u001ey H\u000c+vkl]?q'L\u000c(y(F\u000c>wkYD/8\u0007B_>8\u001cB^&|kLB.8/H_>j$T\u000c+v2\rB/ok^I$l\"CI&8&BH/t8\rU%mkHB)w>CX/je\u0011N8&wO^tW%\rX%89DO\"}8\rM$|k[E)l$_Uk"
		// @0E1: invokestatic game.C_100125_tm.func_100740_z(java.lang.String)char[]
		// @0E4: invokestatic game.C_100125_tm.func_100739_z(char[])java.lang.String
		// @0E7: aastore
		// @0E8: dup
		// @0E9: bipush 12 (0x0C)
		// @0EB: ldc "\u0011\t{&g\rC?jkZC8skBBjl#H\u000c\u001em9Y@/5(AM9kk^I$l\"CI&8\"^\u000c&}*IE$\u007fkYCjn*AY+z'H\u000c$}<\rH/n.AC:u.CX96kl@>p$XK\"8$X^jL>_X&}k]^%l$YU:}kD_jm%KE$q8EI.4kZIjv.HHja$X\u000c>wk_I>m9C\u000c>wkYD/8\u0007B_>8\u001cB^&|kLB.8?_Ujw>Y\u000c#l8\rM8u*@I$l8\rM-y\"C_>8.CI'ak^I$l\"CI&ke\u0011N8&wO^tW%\rX%89DO\"}8\rM$|k[E)l$_Uk"
		// @0ED: invokestatic game.C_100125_tm.func_100740_z(java.lang.String)char[]
		// @0F0: invokestatic game.C_100125_tm.func_100739_z(char[])java.lang.String
		// @0F3: aastore
		// @0F4: dup
		// @0F5: bipush 13 (0x0D)
		// @0F7: ldc "jC%|kCI=kg\r\u0010o(u\u0003\u000c\u001ep*CG98?B\u000c3w>_\u000c=w9F\u000c=q?E\u000c>p.\rB/ok^I$l\"CI&8&BH/tg\rC?jkHB-q%HI8q%J\u000c%vkYD/8\u001fX^>t.\rE98(BA:t.YId8\u001fLG/8\"Y\u000c.w<C\u000c>wkYD/8\u0007B_>8\u001cB^&|kLB.8?_Ujq?\rC?le\rc${.\rX\"}kyY8l'H\u000c\"y8\r\\+k8HHjl#D_j~\"CM&8-DI&|kYI9lg\r[/8<D@&8)HK#vk@M9kk]^%|>NX#w%\u0003\u0010(ju\u0011N8&\u0004C\u000c>wk_E)p.^\u000c+v/\rZ#{?B^39"
		// @0F9: invokestatic game.C_100125_tm.func_100740_z(java.lang.String)char[]
		// @0FC: invokestatic game.C_100125_tm.func_100739_z(char[])java.lang.String
		// @0FF: aastore
		// @100: dup
		// @101: bipush 14 (0x0E)
		// @103: ldc "yD#v,^\u000c%vkYD/8-_C$lkAE$}kEM<}kII<}'B\\/|kCC>8%HO/k8L^#t2\rX%8$X^jy/[M$l*JIf8w\u0008\u001ct6kbY88.CI'q.^\u000c\"y=H\u000c.}=H@%h.I\u000c+vkHB\"y%NI.8)D\\/|*A\u000c9}%YE$}'\r[#l#\r\\&y8@Mjy%I\u000c)t$^Ig{$@N+lkZI+h$C_d8\u001cH\u000c?j,HB>t2\rB/}/\rU%mkYCjj.YY8vkYCjl#H\u000c=y9\rV%v.\rM$|kYM!}kBY>8?EI9}kCI=8?E^/y?^\u0002vz9\u0013\u0010(juzIjp$]Ijl#LXjl#H\u000c\u0019t*[Ig{'L_988HB>q%H@jo\"A@j\u007f\"[Ija$X\u000c>p.\rJ#j.]C=}9\rM$|kLK#t\"YUjv.NI9k*_Ujl$\rO%u;HX/8<DX\"8?EI9}kCI=8*IZ/j8L^#}8\u0003\u0010(ju\u0011N8&\u0004C\u000c>wk_E)p.^\u000c+v/\rZ#{?B^39"
		// @105: invokestatic game.C_100125_tm.func_100740_z(java.lang.String)char[]
		// @108: invokestatic game.C_100125_tm.func_100739_z(char[])java.lang.String
		// @10B: aastore
		// @10C: dup
		// @10D: bipush 15 (0x0F)
		// @10F: ldc "zIjy9H\u000c>j2DB-8?B\u000c8};_C.m(H\u000c>p.\rX/{#CC&w,T\u000c%~kYD/8\u0008BA'y%ICg{'L_988HB>q%H@f8w\u0008\u001ct4kOY>8<H\u000c$}.I\u000c#lkKE/t/\rX/k?HHjz.KC8}kZIj{*C\u000c,q%D_\"6kyM!}kYD#kkZC8sfDBgh9BK8}8^\u000c9}%YE$}'\rH%o%\rX%8?EIjo*_\u000c0w%H\u000c+v/\rX/k?\rE>8$XXjq%\rN+l?AId$)_\u0012vz9\u0013c$8?B\u000c8q(EI98*CHjn\"NX%j2\u000c"
		// @111: invokestatic game.C_100125_tm.func_100740_z(java.lang.String)char[]
		// @114: invokestatic game.C_100125_tm.func_100739_z(char[])java.lang.String
		// @117: aastore
		// @118: dup
		// @119: bipush 16 (0x10)
		// @11B: ldc "hT)}'AI$lkCI=kg\r\u0010o(u\u0003\u000c\u0005o\"CKjl$\rU%m9\rJ#}'I\u000c>}8Y\u0000jo.\rD+n.\rH/n.AC:}/\rMj~>A@38-XB)l\"BB+tknC'u*CH%5(AM9kk^I$l\"CI&8$K\u000c%m9\rC=ve\rb%lkL\u000c'w&HB>8?BCjk$BBp8?EIjk\"YY+l\"BBjw%\rX\"}kaC9lkzC8t/\rD+kk_I+{#HHjykN^#l\"NM&8;BE$lg\rM$|kZIjv.HHja$X\u000c>wkYM!}kYD/8\u0008BA'y%ICj|$ZBjl#H^/8*CHj|.^X8w2\rX\"}kHB/u2\rJ%j(H_d$)_\u0012vz9\u0013c$8?B\u000c8q(EI98*CHjn\"NX%j2\u000c"
		// @11D: invokestatic game.C_100125_tm.func_100740_z(java.lang.String)char[]
		// @120: invokestatic game.C_100125_tm.func_100739_z(char[])java.lang.String
		// @123: aastore
		// @124: dup
		// @125: bipush 17 (0x11)
		// @127: ldc "zIjv.HHja$X^jp.A\\jy,LE$4k\u0011\tz&e\r~/h$_X98*_Ij{$@E$\u007fkDBjw-\rMjv.Z\u000c9}%YE$}'\rE$8>_N+vkL^/y8\u0001\u000c9o$B\\#v,\rH%o%\rM$|kII9l9BU#v,\rC?jkKC8{.^\u000c=q?E\u000c(y9_M-}8\rC,89BO!}?^\u000c+v/\rM){.AI8y?HHjs\"CI>q(\r[/y;BB96kzIjm9JI$l'T\u000c$}.I\u000c#v?H@&q,HB)}kK^%uk^C'}$CIjo#B\u000c)y%\rJ+{.\rX\"}8H\u000c$}<\rM.n.__+j\"H_jq%\rN+l?AId$)_\u0012vz9\u0013x+s.\rX\"}kyY8l'H\u0001)t*^_jk.CX#v.A\u000c>wkYD/8(DX38*CHj|.KI+lkYD/8.CI'akKC8{.^\u000c>p._Id$)_\u0012vz9\u0013c$8?B\u000c8q(EI98*CHjn\"NX%j2\u000c"
		// @129: invokestatic game.C_100125_tm.func_100740_z(java.lang.String)char[]
		// @12C: invokestatic game.C_100125_tm.func_100739_z(char[])java.lang.String
		// @12F: aastore
		// @130: dup
		// @131: bipush 18 (0x12)
		// @133: ldc "yD/8%H[j~'TE$\u007fk^I$l\"CI&kkL^/8/HZ+k?LX#v,\rC?jkZM88.KJ%j?\u0001\u000cv={\u0013\u0002jO.\rM8}kZC8s\"CKjw%\rI$\u007f\"CI/j\"CKjw>_\u000c%o%\rZ/j8DC$4kOY>4kDBjl#H\u000c'}*CX#u.\u0001\u000c=}kCI/|kTC?8?B\u000c-wkOM)skYCjl#H\u000c)q?T\u000c+v/\rJ/v/\rC,~kYD/q9\rM>l*NG96ktC?8(LBjl*FIjl#H\u000c\tw&@M$|$\u0000O&y8^\u000c9}%YE$}'\u0003\u0010(ju\u0011N8&\u0004C\u000c>wk_E)p.^\u000c+v/\rZ#{?B^39"
		// @135: invokestatic game.C_100125_tm.func_100740_z(java.lang.String)char[]
		// @138: invokestatic game.C_100125_tm.func_100739_z(char[])java.lang.String
		// @13B: aastore
		// @13C: dup
		// @13D: bipush 19 (0x13)
		// @13F: ldc "~Y:}9AM>q=H\u000c$}<^\u0000j$n\u001d\u0012d8\u001cH\u000c\"y=H\u000c)w&]@/l.I\u000c=w9F\u000c%vkYD/8\u0003X^8q(LB/5(AM9kk^I$l\"CI&6kzIjp*[I$??\rK%lkYE'}kYCjl.^Xjq?\u0017\u000c>p.\r_#l>LX#w%\rE$8?EIj{\"YUjp*^\u000c(}(BA/8>CX/v*O@/6k~]?y/_C$kkBJjP>_^#{*CI98*CHjo$__/8*_Ijl*FE$\u007fkBY>8*A@jw>_\u000c,w9NI96wO^t$)_\u0012\u0013w>\r[#t'\rN/8?LG#v,\rC?jk]^%l$YU:}keY8j\"NM$}fN@+k8\r_/v?DB/te\rx\"}k]^%z*OE&q?T\u000c%~k^Y8n\"[M&8\"^\u000c9t\"@\u0000jz>Y\u000c.wkYD/8)H_>82BYj{*C\u0002vz9\u0013\u0010(jubBjl$\r^#{#H_jy%I\u000c<q(YC8ag\r\u0010o(u\u000c"
		// @141: invokestatic game.C_100125_tm.func_100740_z(java.lang.String)char[]
		// @144: invokestatic game.C_100125_tm.func_100739_z(char[])java.lang.String
		// @147: aastore
		// @148: dup
		// @149: bipush 20 (0x14)
		// @14B: ldc "zI&{$@Ijz*NGf8w\u0008\u001ct6kzIjv.HHja$X^j}3]I8l\"^Ijq%\rX\"}kKE/t/\u0003\u000c\u001ey H\u000c>p\"^\u000c\tw&@M$|$\u0000O&y8^\u000c9}%YE$}'\rH%o%\rX%8?EIjj>DB/|kNE>akLB.8(AI+jkBY>8?EIj}%HA38-B^)}8\u0003\u0010(ju\u0011N8&\u0004C\u000c>wk_E)p.^\u000c+v/\rZ#{?B^39"
		// @14D: invokestatic game.C_100125_tm.func_100740_z(java.lang.String)char[]
		// @150: invokestatic game.C_100125_tm.func_100739_z(char[])java.lang.String
		// @153: aastore
		// @154: dup
		// @155: bipush 21 (0x15)
		// @157: ldc "\u0011\t{&g\rX\"}k_Y#v.I\u000c)q?T\u000c#kkOI#v,\rC<}9_Y$8)T\u000c\u000bi>D@+5(AM9kk^I$l\"CI&ke\rx+s.\rX\"}keY8j\"NM$}kLB.8/H_>j$T\u000c+t'\rX\"}kHB/u2\rm;m\"AM94kLB.8*CUjw?EI88.CI'q.^\u000c>p*Y\u000c3w>\rI${$XB>}9\u0003\u0010(ju\u0011N8&\u0004C\u000c>wk_E)p.^\u000c+v/\rZ#{?B^39"
		// @159: invokestatic game.C_100125_tm.func_100740_z(java.lang.String)char[]
		// @15C: invokestatic game.C_100125_tm.func_100739_z(char[])java.lang.String
		// @15F: aastore
		// @160: dup
		// @161: bipush 22 (0x16)
		// @163: ldc "\u0011\t{&g\rX\"}kHB/u2\rE98>^E$\u007fkL\u000c$}<\rM$l\"\u0000M#jk^I$l\"CI&4kII9q,CM>}/\r\u007f)w9]E%vfN@+k8\u0003\u000c\u001ep._Ijy9H\u000c'm'YE:t.\r\u007f)w9]E%v8\r^/h$_X/|kBBjl#H\u000c\u0006w8Y\u000c\u001dw9AHd$)_\u0012vz9\u0013{/8/BBmlkEM<}kL\u000c9l9LX/\u007f2\rX%8/HJ/y?\rX\"}&\rU/lg\rN?lkYM!}kYD/8\u0003X^8q(LB/8*CHj|$\rX\"}kOI9lkTC?8(LBd$)_\u0012vz9\u0013c$8?B\u000c8q(EI98*CHjn\"NX%j2\u000c"
		// @165: invokestatic game.C_100125_tm.func_100740_z(java.lang.String)char[]
		// @168: invokestatic game.C_100125_tm.func_100739_z(char[])java.lang.String
		// @16B: aastore
		// @16C: dup
		// @16D: bipush 23 (0x17)
		// @16F: ldc "\u0011\t{&g\rX\"}kIM>ykK^%ukTC?jkOM>l'H_jo\"YDjl#H\u000c\u0019{$_\\#w%^\u000c=y8\rE$n*AY+z'H\u0002jO.\rD+n.\rH/n.AC:}/\rMjo$_G#v,\r\u007f)w9]E%vkBJjw>_\u000c%o%\u0001\u000c(m?\rE>8%HI.kkYCjz.\rX8q.I\u000c%m?\rE$8(BA(y?\u0003\u0010(ju\u0011N8&\u001fLG/8?EIjK(B^:q$C\u000c>wkYD/8<L^jb$CIjy%I\u000c.}-HM>8?EIj}%HA38-B^)}8\rX\"}9H\u0002vz9\u0013\u0010(jubBjl$\r^#{#H_jy%I\u000c<q(YC8aj"
		// @171: invokestatic game.C_100125_tm.func_100740_z(java.lang.String)char[]
		// @174: invokestatic game.C_100125_tm.func_100739_z(char[])java.lang.String
		// @177: aastore
		// @178: dup
		// @179: bipush 24 (0x18)
		// @17B: ldc "cC=8<H\u000c\"y=H\u000c%m9\rC=vkZC8s\"CKjt\"CIjw-\r\u007f)w9]E%v8\u0001\u000c#ll^\u000c>q&H\u000c>wkYM!}kOM)skYD/8\u0007B_>8\u001cB^&|e\r\u0010o)u\u0001\u000c-wkIC=vkYD/j.\u0001\u000c>y H\u000c%m?\rX\"}kHB/u\"H_f8*CHjj.]C8lkOM)skBBjy%T\u000c$}<\r_/v?DB/t8\rU%mkKM)}e\u0011N8&wO^tW%\rX%89DO\"}8\rM$|k[E)l$_Uk"
		// @17D: invokestatic game.C_100125_tm.func_100740_z(java.lang.String)char[]
		// @180: invokestatic game.C_100125_tm.func_100739_z(char[])java.lang.String
		// @183: aastore
		// @184: dup
		// @185: bipush 25 (0x19)
		// @187: ldc "zC8j2DB-8%H[94k\u0011\tz&e\rx\"}kHB/u2\n_jv.Z\u000c\"}*[Ujz\"]I.y'\r_/v?DB/tg\rH/k\"JB+l.I\u000c\tj>^D/jfN@+k8\u0001\u000c>p9HM>}%^\u000c>wkYY8vkYD/8?DH/8$K\u000c>p.\r[+jkLK+q%^Xjm8\u0001\u000c+v/\rE>?8\rX+s\"CKjy'A\u000c%~kBY889H_%m9NI98?B\u000c)w&OM>8\"Y\u0002vz9\u0013\u0010(juzIjv.HHju$_Ijq%YI&8?B\u000c.}=H@%hkBY88$ZBf8)XXjy'A\u000c=}kNM$88]M8}kKC88?EE98&D_9q$C\u000c#kkLBjY:XE&yfN@+k8\u0003\u000c\u000cw9YY$y?H@34kYD/8(DX388EC?t/\r\\8w=DH/82BYjo\"YDjj.AM>q=H@388LJ/8=LB>y,H\u000c:w\"CX94k^Cja$X\u000c)y%\rM<w\"I\u000c,j$CX+tkLX>y(F_d8\u001cH\u000c/`;HO>8?B\u000c9}.\rX\"}kNC'z*Y\u000c9s\"A@98?EM>8#LZ/8&LH/82BYj~*@C?ke\u0011N8&wO^tW%\rX%89DO\"}8\rM$|k[E)l$_Uk"
		// @189: invokestatic game.C_100125_tm.func_100740_z(java.lang.String)char[]
		// @18C: invokestatic game.C_100125_tm.func_100739_z(char[])java.lang.String
		// @18F: aastore
		// @190: dup
		// @191: bipush 26 (0x1A)
		// @193: ldc "`M8n.A@%m8\rB/o8\u0001\u000cv={\u0013\u0002j^9BAja$X^jq%YI&t\"JI${.\r[/8#LZ/8/HZ/t$]I.8$X^jn.__#w%\rC,8?EIj[9X_\"}9\u0000O&y8^\u000c9}%YE$}'\u0003\u000c\u001d}kEM<}kEE-pkEC:}8\rJ%jkDXd$)_\u0012vz9\u0013mjk?L^j{9XE9}9\rD+kkN^+k#HHjw%\rX\"}k@C%vkLB.8$X^j}%HA#}8\rM8}k@M!q%J\u000c,w9LU98?B\u000c9y'[M-}kDXd8\u001fLG/8?EIj[9X_\"}9\rM$|kKI$|kYD/ukBJ,6koIjy<L^/8?EM>8?EIjt$Z\u000c-j*[E>akZE&tkLJ,}(Y\u000c>p.\rA+v$HY<j\"CKj{*]M(q'DX#}8\rC,8*A@jk.CX#v.A_d$)_\u0012vz9\u0013c$8?B\u000c8q(EI98*CHjn\"NX%j2\u000c"
		// @195: invokestatic game.C_100125_tm.func_100740_z(java.lang.String)char[]
		// @198: invokestatic game.C_100125_tm.func_100739_z(char[])java.lang.String
		// @19B: aastore
		// @19C: dup
		// @19D: bipush 27 (0x1B)
		// @19F: ldc "zIjp*[Ijw>_\u000c/v.@E/kkBBjl#H\u000c8m%\u0001\u000cv={\u0013\u0002jW>_\u000c9m;H^#w9\r_!q'A_jp*[Ij~$_O/|kYD/ukYCjj.^C8lkYCjl#HE88$AH/jk@C.}'^\u000c%~k^I$l\"CI&6kyD/k.\rM8}kCC>8*^\u000c9w;EE9l\"NM>}/\rM98&BH/j%\rO&y8^I94kOY>8<EI$8?EI38*_Ij~\"YX/|kZE>pkDB)j.L_#v,AUjh$ZI8~>A\u000c=}*]C$kg\rX\"}2\r\\%k.\rMj~$_A#|*O@/8?E^/y?\u0003\u0010(ju\u0011N8&\u001fLG/8?EIjK(B^:q$C\u000c(y(F\u000c>wkYD/8&BC$8*CHjl*FIjw>Y\u000c>p.\rI$}&DI96wO^t$)_\u0012\u0005vkYCjj\"ND/kkLB.8=DO>w9T\r"
		// @1A1: invokestatic game.C_100125_tm.func_100740_z(java.lang.String)char[]
		// @1A4: invokestatic game.C_100125_tm.func_100739_z(char[])java.lang.String
		// @1A7: aastore
		// @1A8: dup
		// @1A9: bipush 28 (0x1C)
		// @1AB: ldc "yD/8\tH^>p*\u0000O&y8^\u000c9}%YE$}'\rE98%BXjy8\rC(k$AI>}kL_jo.\rX\"w>JD>4k\u0011\tz&e\rx+s.\rE>8/B[$8?B\u000c>p.\r`%k?\r{%j'I\u000c+v/\rO&}*_\u000c%m?\rX\"}kHB/u2\rJ%j(H_d$)_\u0012vz9\u0013c$8?B\u000c8q(EI98*CHjn\"NX%j2\u000c"
		// @1AD: invokestatic game.C_100125_tm.func_100740_z(java.lang.String)char[]
		// @1B0: invokestatic game.C_100125_tm.func_100739_z(char[])java.lang.String
		// @1B3: aastore
		// @1B4: dup
		// @1B5: bipush 29 (0x1D)
		// @1B7: ldc "yD/8<L^jp*^\u000c8}*ND/|kL\u000c)j\"YE)y'\rF?v(YY8}e\rx\"}kHB/u2\rE98%HM8t2\rH/~.LX/|g\rN?lkYD/akL^/8>^E$\u007fkHT:}9DA/v?L@jl.ND$w'BK38?EM>8<H\u000c)y%CC>8/HJ/v/\rM-y\"C_>6wO^t$)_\u0012\u001ey H\u000c>p.\rd?j9DO+v.\rH%o%\rX%8?EIjT$^XjO$_@.8*CHj}%JM-}kDBj{$@N+le\r{\"}%\rU%mkEM<}kYM!}%\rC?lkYD/89H_>8$K\u000c>p.\rI$}&T\u000c,w9NI94kYD/akZE&tk^I$|kBY>8?EI#jkHT:}9DA/v?L@ju$II&ke\ru%mkZE&tkEM<}kYCjm8H\u000c+t'\rX\"}k^G#t'^\u000c>p*Y\u000c\"y=H\u000c'y/H\u000c3w>\rMjt.JI$|kYCj|.^X8w2\rX\"}&\u0003\u0010(ju\u0011N8&\u0004C\u000c>wkJ@%j2\u0001\u000cv={\u0013\r"
		// @1B9: invokestatic game.C_100125_tm.func_100740_z(java.lang.String)char[]
		// @1BC: invokestatic game.C_100125_tm.func_100739_z(char[])java.lang.String
		// @1BF: aastore
		// @1C0: putstatic java.lang.String[] game.C_100125_tm.field_100752_k
		// @1C3: ldc "tC?8#LZ/8z\rY$j.LHju.^_+\u007f.\u000c"
		// @1C5: invokestatic game.C_100125_tm.func_100740_z(java.lang.String)char[]
		// @1C8: invokestatic game.C_100125_tm.func_100739_z(char[])java.lang.String
		// @1CB: putstatic java.lang.String game.C_100125_tm.field_100746_n
		// @1CE: return
	}
	
	private static char[] func_100740_z(String arg0)
	{
		// @00: aload_0
		// @01: invokevirtual java.lang.String.toCharArray()char[]
		// @04: dup
		// @05: arraylength
		// @06: iconst_2
		// @07: if_icmpge @13
		// @0A: dup
		// @0B: iconst_0
		// @0C: dup2
		// @0D: caload
		// @0E: bipush 75 (0x4B)
		// @10: ixor
		// @11: i2c
		// @12: castore
		// @13: areturn
	}
	
	private static String func_100739_z(char[] arg0)
	{
		// @00: aload_0
		// @01: dup
		// @02: arraylength
		// @03: swap
		// @04: iconst_0
		// @05: istore_1
		// @06: goto @4C
		// @09: dup
		// @0A: iload_1
		// @0B: dup2
		// @0C: caload
		// @0D: iload_1
		// @0E: iconst_5
		// @0F: irem
		// @10: tableswitch def: @44, for 0: @30, for 1: @35, for 2: @3A, for 3: @3F
		// @30: bipush 45 (0x2D)
		// @32: goto @46
		// @35: bipush 44 (0x2C)
		// @37: goto @46
		// @3A: bipush 74 (0x4A)
		// @3C: goto @46
		// @3F: bipush 24 (0x18)
		// @41: goto @46
		// @44: bipush 75 (0x4B)
		// @46: ixor
		// @47: i2c
		// @48: castore
		// @49: iinc #1 +1
		// @4C: swap
		// @4D: dup_x1
		// @4E: iload_1
		// @4F: if_icmpgt @09
		// @52: new java.lang.String
		// @55: dup_x1
		// @56: swap
		// @57: invokespecial java.lang.String.<init>(char[])void
		// @5A: invokevirtual java.lang.String.intern()java.lang.String
		// @5D: areturn
	}
}
