package game;

final class C_100217_ao
{
	static C_100153_be[] field_106045_i;
	static String field_106033_f;
	int field_106043_k;
	static long field_106035_d;
	static C_100302_ka field_106040_l;
	static String field_106042_j;
	static C_100037_wb field_106036_e;
	static String[] field_106041_m;
	int field_106039_a;
	static byte[] field_106037_b;
	static String field_106034_g;
	static String field_106044_h;
	static C_100037_wb[] field_106038_c;
	private static final String[] field_106046_z;
	
	static final C_100113_ek[] func_106029_a(boolean arg0)
	{
		// @00: iload_0
		// @01: iconst_1
		// @02: if_icmpeq @10
		// @05: aconst_null
		// @06: checkcast java.lang.String
		// @09: putstatic java.lang.String game.C_100217_ao.field_106044_h
		// @0C: goto @10
		// @0F: athrow
		// @10: iconst_3
		// @11: anewarray game.C_100113_ek
		// @14: dup
		// @15: iconst_0
		// @16: getstatic game.C_100113_ek game.C_100121_ud.field_100715_F
		// @19: aastore
		// @1A: dup
		// @1B: iconst_1
		// @1C: getstatic game.C_100113_ek game.C_100280_nf.field_101181_j
		// @1F: aastore
		// @20: dup
		// @21: iconst_2
		// @22: getstatic game.C_100113_ek game.C_100144_bm.field_102096_Xb
		// @25: aastore
		// @26: areturn
		// @27: astore_1
		// @28: aload_1
		// @29: new java.lang.StringBuilder
		// @2C: dup
		// @2D: invokespecial java.lang.StringBuilder.<init>()void
		// @30: getstatic java.lang.String[] game.C_100217_ao.field_106046_z
		// @33: iconst_2
		// @34: aaload
		// @35: invokevirtual java.lang.StringBuilder.append(java.lang.String)java.lang.StringBuilder
		// @38: iload_0
		// @39: invokevirtual java.lang.StringBuilder.append(boolean)java.lang.StringBuilder
		// @3C: bipush 41 (0x29)
		// @3E: invokevirtual java.lang.StringBuilder.append(char)java.lang.StringBuilder
		// @41: invokevirtual java.lang.StringBuilder.toString()java.lang.String
		// @44: invokestatic game.C_100181_cf.func_105695_a(java.lang.Throwable, java.lang.String)game.C_100170_cm
		// @47: athrow
	}
	
	public final String toString()
	{
		// @00: new java.lang.IllegalStateException
		// @03: dup
		// @04: invokespecial java.lang.IllegalStateException.<init>()void
		// @07: athrow
		// @08: astore_1
		// @09: aload_1
		// @0A: getstatic java.lang.String[] game.C_100217_ao.field_106046_z
		// @0D: iconst_1
		// @0E: aaload
		// @0F: invokestatic game.C_100181_cf.func_105695_a(java.lang.Throwable, java.lang.String)game.C_100170_cm
		// @12: athrow
	}
	
	static final C_100096_un func_106032_a(byte arg0, boolean arg1)
	{
		// @00: iload_0
		// @01: bipush -67 (0xBD)
		// @03: if_icmplt @0B
		// @06: aconst_null
		// @07: checkcast game.C_100096_un
		// @0A: areturn
		// @0B: new game.C_100096_un
		// @0E: dup
		// @0F: iconst_1
		// @10: invokespecial game.C_100096_un.<init>(boolean)void
		// @13: astore_2
		// @14: aload_2
		// @15: iload_1
		// @16: putfield boolean game.C_100096_un.field_104568_j
		// @19: aload_2
		// @1A: areturn
		// @1B: astore_2
		// @1C: aload_2
		// @1D: new java.lang.StringBuilder
		// @20: dup
		// @21: invokespecial java.lang.StringBuilder.<init>()void
		// @24: getstatic java.lang.String[] game.C_100217_ao.field_106046_z
		// @27: bipush 7 (0x07)
		// @29: aaload
		// @2A: invokevirtual java.lang.StringBuilder.append(java.lang.String)java.lang.StringBuilder
		// @2D: iload_0
		// @2E: invokevirtual java.lang.StringBuilder.append(int)java.lang.StringBuilder
		// @31: bipush 44 (0x2C)
		// @33: invokevirtual java.lang.StringBuilder.append(char)java.lang.StringBuilder
		// @36: iload_1
		// @37: invokevirtual java.lang.StringBuilder.append(boolean)java.lang.StringBuilder
		// @3A: bipush 41 (0x29)
		// @3C: invokevirtual java.lang.StringBuilder.append(char)java.lang.StringBuilder
		// @3F: invokevirtual java.lang.StringBuilder.toString()java.lang.String
		// @42: invokestatic game.C_100181_cf.func_105695_a(java.lang.Throwable, java.lang.String)game.C_100170_cm
		// @45: athrow
	}
	
	static final void func_106031_a(int arg0, int arg1, int arg2, int arg3, int arg4)
	{
		// @00: iload_3
		// @01: putstatic int game.C_100097_k.field_104582_b
		// @04: iload_0
		// @05: putstatic int game.C_100239_oi.field_102307_w
		// @08: iload #4
		// @0A: putstatic int game.C_100110_s.field_104848_a
		// @0D: iload_1
		// @0E: ifeq @12
		// @11: return
		// @12: iload_2
		// @13: putstatic int game.C_100003_ga.field_103539_s
		// @16: goto @61
		// @19: astore #5
		// @1B: aload #5
		// @1D: new java.lang.StringBuilder
		// @20: dup
		// @21: invokespecial java.lang.StringBuilder.<init>()void
		// @24: getstatic java.lang.String[] game.C_100217_ao.field_106046_z
		// @27: iconst_0
		// @28: aaload
		// @29: invokevirtual java.lang.StringBuilder.append(java.lang.String)java.lang.StringBuilder
		// @2C: iload_0
		// @2D: invokevirtual java.lang.StringBuilder.append(int)java.lang.StringBuilder
		// @30: bipush 44 (0x2C)
		// @32: invokevirtual java.lang.StringBuilder.append(char)java.lang.StringBuilder
		// @35: iload_1
		// @36: invokevirtual java.lang.StringBuilder.append(int)java.lang.StringBuilder
		// @39: bipush 44 (0x2C)
		// @3B: invokevirtual java.lang.StringBuilder.append(char)java.lang.StringBuilder
		// @3E: iload_2
		// @3F: invokevirtual java.lang.StringBuilder.append(int)java.lang.StringBuilder
		// @42: bipush 44 (0x2C)
		// @44: invokevirtual java.lang.StringBuilder.append(char)java.lang.StringBuilder
		// @47: iload_3
		// @48: invokevirtual java.lang.StringBuilder.append(int)java.lang.StringBuilder
		// @4B: bipush 44 (0x2C)
		// @4D: invokevirtual java.lang.StringBuilder.append(char)java.lang.StringBuilder
		// @50: iload #4
		// @52: invokevirtual java.lang.StringBuilder.append(int)java.lang.StringBuilder
		// @55: bipush 41 (0x29)
		// @57: invokevirtual java.lang.StringBuilder.append(char)java.lang.StringBuilder
		// @5A: invokevirtual java.lang.StringBuilder.toString()java.lang.String
		// @5D: invokestatic game.C_100181_cf.func_105695_a(java.lang.Throwable, java.lang.String)game.C_100170_cm
		// @60: athrow
		// @61: return
	}
	
	public static void func_106027_a(byte arg0)
	{
		// @00: aconst_null
		// @01: putstatic java.lang.String[] game.C_100217_ao.field_106041_m
		// @04: aconst_null
		// @05: putstatic game.C_100302_ka game.C_100217_ao.field_106040_l
		// @08: aconst_null
		// @09: putstatic java.lang.String game.C_100217_ao.field_106044_h
		// @0C: aconst_null
		// @0D: putstatic byte[] game.C_100217_ao.field_106037_b
		// @10: aconst_null
		// @11: putstatic game.C_100037_wb game.C_100217_ao.field_106036_e
		// @14: aconst_null
		// @15: putstatic game.C_100153_be[] game.C_100217_ao.field_106045_i
		// @18: aconst_null
		// @19: putstatic java.lang.String game.C_100217_ao.field_106034_g
		// @1C: aconst_null
		// @1D: putstatic java.lang.String game.C_100217_ao.field_106033_f
		// @20: iload_0
		// @21: bipush 66 (0x42)
		// @23: if_icmpeq @27
		// @26: return
		// @27: aconst_null
		// @28: putstatic game.C_100037_wb[] game.C_100217_ao.field_106038_c
		// @2B: aconst_null
		// @2C: putstatic java.lang.String game.C_100217_ao.field_106042_j
		// @2F: goto @54
		// @32: astore_1
		// @33: aload_1
		// @34: new java.lang.StringBuilder
		// @37: dup
		// @38: invokespecial java.lang.StringBuilder.<init>()void
		// @3B: getstatic java.lang.String[] game.C_100217_ao.field_106046_z
		// @3E: bipush 6 (0x06)
		// @40: aaload
		// @41: invokevirtual java.lang.StringBuilder.append(java.lang.String)java.lang.StringBuilder
		// @44: iload_0
		// @45: invokevirtual java.lang.StringBuilder.append(int)java.lang.StringBuilder
		// @48: bipush 41 (0x29)
		// @4A: invokevirtual java.lang.StringBuilder.append(char)java.lang.StringBuilder
		// @4D: invokevirtual java.lang.StringBuilder.toString()java.lang.String
		// @50: invokestatic game.C_100181_cf.func_105695_a(java.lang.Throwable, java.lang.String)game.C_100170_cm
		// @53: athrow
		// @54: return
	}
	
	static final String func_106025_a(CharSequence arg0, boolean arg1, byte arg2)
	{
		// @00: getstatic int game.SteelSentinels.field_105275_O
		// @03: istore #5
		// @05: iload_2
		// @06: bipush -42 (0xD6)
		// @08: if_icmple @10
		// @0B: aconst_null
		// @0C: checkcast java.lang.String
		// @0F: areturn
		// @10: iload_1
		// @11: bipush 22 (0x16)
		// @13: aload_0
		// @14: invokestatic game.C_100005_fk.func_103584_a(boolean, byte, java.lang.CharSequence)java.lang.String
		// @17: astore_3
		// @18: aload_3
		// @19: ifnull @1E
		// @1C: aload_3
		// @1D: areturn
		// @1E: iconst_0
		// @1F: istore #4
		// @21: iload #4
		// @23: iconst_m1
		// @24: ixor
		// @25: aload_0
		// @26: invokeinterface java.lang.CharSequence.length()int
		// @2B: iconst_m1
		// @2C: ixor
		// @2D: if_icmple @4B
		// @30: aload_0
		// @31: iload #4
		// @33: invokeinterface java.lang.CharSequence.charAt(int)char
		// @38: iconst_1
		// @39: invokestatic game.C_100218_am.func_103102_a(char, boolean)boolean
		// @3C: ifne @43
		// @3F: getstatic java.lang.String game.C_100124_tn.field_104933_d
		// @42: areturn
		// @43: iinc #4 +1
		// @46: iload #5
		// @48: ifeq @21
		// @4B: aconst_null
		// @4C: areturn
		// @4D: astore_3
		// @4E: aload_3
		// @4F: new java.lang.StringBuilder
		// @52: dup
		// @53: invokespecial java.lang.StringBuilder.<init>()void
		// @56: getstatic java.lang.String[] game.C_100217_ao.field_106046_z
		// @59: iconst_3
		// @5A: aaload
		// @5B: invokevirtual java.lang.StringBuilder.append(java.lang.String)java.lang.StringBuilder
		// @5E: aload_0
		// @5F: ifnull @6B
		// @62: getstatic java.lang.String[] game.C_100217_ao.field_106046_z
		// @65: iconst_4
		// @66: aaload
		// @67: goto @70
		// @6A: athrow
		// @6B: getstatic java.lang.String[] game.C_100217_ao.field_106046_z
		// @6E: iconst_5
		// @6F: aaload
		// @70: invokevirtual java.lang.StringBuilder.append(java.lang.String)java.lang.StringBuilder
		// @73: bipush 44 (0x2C)
		// @75: invokevirtual java.lang.StringBuilder.append(char)java.lang.StringBuilder
		// @78: iload_1
		// @79: invokevirtual java.lang.StringBuilder.append(boolean)java.lang.StringBuilder
		// @7C: bipush 44 (0x2C)
		// @7E: invokevirtual java.lang.StringBuilder.append(char)java.lang.StringBuilder
		// @81: iload_2
		// @82: invokevirtual java.lang.StringBuilder.append(int)java.lang.StringBuilder
		// @85: bipush 41 (0x29)
		// @87: invokevirtual java.lang.StringBuilder.append(char)java.lang.StringBuilder
		// @8A: invokevirtual java.lang.StringBuilder.toString()java.lang.String
		// @8D: invokestatic game.C_100181_cf.func_105695_a(java.lang.Throwable, java.lang.String)game.C_100170_cm
		// @90: athrow
	}
	
	static final int func_106030_a(int arg0)
	{
		// @00: iload_0
		// @01: ifeq @0F
		// @04: aconst_null
		// @05: checkcast game.C_100153_be[]
		// @08: putstatic game.C_100153_be[] game.C_100217_ao.field_106045_i
		// @0B: goto @0F
		// @0E: athrow
		// @0F: getstatic int game.C_100176_ci.field_105626_a
		// @12: ireturn
		// @13: astore_1
		// @14: aload_1
		// @15: new java.lang.StringBuilder
		// @18: dup
		// @19: invokespecial java.lang.StringBuilder.<init>()void
		// @1C: getstatic java.lang.String[] game.C_100217_ao.field_106046_z
		// @1F: bipush 9 (0x09)
		// @21: aaload
		// @22: invokevirtual java.lang.StringBuilder.append(java.lang.String)java.lang.StringBuilder
		// @25: iload_0
		// @26: invokevirtual java.lang.StringBuilder.append(int)java.lang.StringBuilder
		// @29: bipush 41 (0x29)
		// @2B: invokevirtual java.lang.StringBuilder.append(char)java.lang.StringBuilder
		// @2E: invokevirtual java.lang.StringBuilder.toString()java.lang.String
		// @31: invokestatic game.C_100181_cf.func_105695_a(java.lang.Throwable, java.lang.String)game.C_100170_cm
		// @34: athrow
	}
	
	C_100217_ao(int arg0, int arg1, int arg2, int arg3)
	{
		// @00: aload_0
		// @01: invokespecial java.lang.Object.<init>()void
		// @04: aload_0
		// @05: iload #4
		// @07: putfield int game.C_100217_ao.field_106043_k
		// @0A: aload_0
		// @0B: iload_1
		// @0C: putfield int game.C_100217_ao.field_106039_a
		// @0F: goto @52
		// @12: astore #5
		// @14: aload #5
		// @16: new java.lang.StringBuilder
		// @19: dup
		// @1A: invokespecial java.lang.StringBuilder.<init>()void
		// @1D: getstatic java.lang.String[] game.C_100217_ao.field_106046_z
		// @20: bipush 8 (0x08)
		// @22: aaload
		// @23: invokevirtual java.lang.StringBuilder.append(java.lang.String)java.lang.StringBuilder
		// @26: iload_1
		// @27: invokevirtual java.lang.StringBuilder.append(int)java.lang.StringBuilder
		// @2A: bipush 44 (0x2C)
		// @2C: invokevirtual java.lang.StringBuilder.append(char)java.lang.StringBuilder
		// @2F: iload_2
		// @30: invokevirtual java.lang.StringBuilder.append(int)java.lang.StringBuilder
		// @33: bipush 44 (0x2C)
		// @35: invokevirtual java.lang.StringBuilder.append(char)java.lang.StringBuilder
		// @38: iload_3
		// @39: invokevirtual java.lang.StringBuilder.append(int)java.lang.StringBuilder
		// @3C: bipush 44 (0x2C)
		// @3E: invokevirtual java.lang.StringBuilder.append(char)java.lang.StringBuilder
		// @41: iload #4
		// @43: invokevirtual java.lang.StringBuilder.append(int)java.lang.StringBuilder
		// @46: bipush 41 (0x29)
		// @48: invokevirtual java.lang.StringBuilder.append(char)java.lang.StringBuilder
		// @4B: invokevirtual java.lang.StringBuilder.toString()java.lang.String
		// @4E: invokestatic game.C_100181_cf.func_105695_a(java.lang.Throwable, java.lang.String)game.C_100170_cm
		// @51: athrow
		// @52: return
	}
	
	static
	{
		// @00: bipush 10 (0x0A)
		// @02: anewarray java.lang.String
		// @05: dup
		// @06: iconst_0
		// @07: ldc "pu2ZN"
		// @09: invokestatic game.C_100217_ao.func_106028_z(java.lang.String)char[]
		// @0C: invokestatic game.C_100217_ao.func_106026_z(char[])java.lang.String
		// @0F: aastore
		// @10: dup
		// @11: iconst_1
		// @12: ldc "pu2o\tBnnr\u0008v25"
		// @14: invokestatic game.C_100217_ao.func_106028_z(java.lang.String)char[]
		// @17: invokestatic game.C_100217_ao.func_106026_z(char[])java.lang.String
		// @1A: aastore
		// @1B: dup
		// @1C: iconst_2
		// @1D: ldc "pu2_N"
		// @1F: invokestatic game.C_100217_ao.func_106028_z(java.lang.String)char[]
		// @22: invokestatic game.C_100217_ao.func_106026_z(char[])java.lang.String
		// @25: aastore
		// @26: dup
		// @27: iconst_3
		// @28: ldc "pu2^N"
		// @2A: invokestatic game.C_100217_ao.func_106028_z(java.lang.String)char[]
		// @2D: invokestatic game.C_100217_ao.func_106026_z(char[])java.lang.String
		// @30: aastore
		// @31: dup
		// @32: iconst_4
		// @33: ldc "j425\u001b"
		// @35: invokestatic game.C_100217_ao.func_106028_z(java.lang.String)char[]
		// @38: invokestatic game.C_100217_ao.func_106026_z(char[])java.lang.String
		// @3B: aastore
		// @3C: dup
		// @3D: iconst_5
		// @3E: ldc "\u007fopw"
		// @40: invokestatic game.C_100217_ao.func_106028_z(java.lang.String)char[]
		// @43: invokestatic game.C_100217_ao.func_106026_z(char[])java.lang.String
		// @46: aastore
		// @47: dup
		// @48: bipush 6 (0x06)
		// @4A: ldc "pu2XN"
		// @4C: invokestatic game.C_100217_ao.func_106028_z(java.lang.String)char[]
		// @4F: invokestatic game.C_100217_ao.func_106026_z(char[])java.lang.String
		// @52: aastore
		// @53: dup
		// @54: bipush 7 (0x07)
		// @56: ldc "pu2YN"
		// @58: invokestatic game.C_100217_ao.func_106028_z(java.lang.String)char[]
		// @5B: invokestatic game.C_100217_ao.func_106026_z(char[])java.lang.String
		// @5E: aastore
		// @5F: dup
		// @60: bipush 8 (0x08)
		// @62: ldc "pu2'\u000f\u007fsh%N"
		// @64: invokestatic game.C_100217_ao.func_106028_z(java.lang.String)char[]
		// @67: invokestatic game.C_100217_ao.func_106026_z(char[])java.lang.String
		// @6A: aastore
		// @6B: dup
		// @6C: bipush 9 (0x09)
		// @6E: ldc "pu2]N"
		// @70: invokestatic game.C_100217_ao.func_106028_z(java.lang.String)char[]
		// @73: invokestatic game.C_100217_ao.func_106026_z(char[])java.lang.String
		// @76: aastore
		// @77: putstatic java.lang.String[] game.C_100217_ao.field_106046_z
		// @7A: ldc "Ttx;!pwy"
		// @7C: invokestatic game.C_100217_ao.func_106028_z(java.lang.String)char[]
		// @7F: invokestatic game.C_100217_ao.func_106026_z(char[])java.lang.String
		// @82: putstatic java.lang.String game.C_100217_ao.field_106033_f
		// @85: ldc "Hui;\u0008t\u007fx;\u00071h}o\u000f\u007f}<t\u00001&9*X1ns;\u0016}{e;\u0011xnt;\u0012y\u007f<x\u0013chyu\u00121ulo\u000f~to5"
		// @87: invokestatic game.C_100217_ao.func_106028_z(java.lang.String)char[]
		// @8A: invokestatic game.C_100217_ao.func_106026_z(char[])java.lang.String
		// @8D: putstatic java.lang.String game.C_100217_ao.field_106042_j
		// @90: ldc "Pytr\u0003g\u007fx"
		// @92: invokestatic game.C_100217_ao.func_106028_z(java.lang.String)char[]
		// @95: invokestatic game.C_100217_ao.func_106026_z(char[])java.lang.String
		// @98: putstatic java.lang.String game.C_100217_ao.field_106034_g
		// @9B: ldc "Usox\u0007c~"
		// @9D: invokestatic game.C_100217_ao.func_106028_z(java.lang.String)char[]
		// @A0: invokestatic game.C_100217_ao.func_106026_z(char[])java.lang.String
		// @A3: putstatic java.lang.String game.C_100217_ao.field_106044_h
		// @A6: return
	}
	
	private static char[] func_106028_z(String arg0)
	{
		// @00: aload_0
		// @01: invokevirtual java.lang.String.toCharArray()char[]
		// @04: dup
		// @05: arraylength
		// @06: iconst_2
		// @07: if_icmpge @13
		// @0A: dup
		// @0B: iconst_0
		// @0C: dup2
		// @0D: caload
		// @0E: bipush 102 (0x66)
		// @10: ixor
		// @11: i2c
		// @12: castore
		// @13: areturn
	}
	
	private static String func_106026_z(char[] arg0)
	{
		// @00: aload_0
		// @01: dup
		// @02: arraylength
		// @03: swap
		// @04: iconst_0
		// @05: istore_1
		// @06: goto @4C
		// @09: dup
		// @0A: iload_1
		// @0B: dup2
		// @0C: caload
		// @0D: iload_1
		// @0E: iconst_5
		// @0F: irem
		// @10: tableswitch def: @44, for 0: @30, for 1: @35, for 2: @3A, for 3: @3F
		// @30: bipush 17 (0x11)
		// @32: goto @46
		// @35: bipush 26 (0x1A)
		// @37: goto @46
		// @3A: bipush 28 (0x1C)
		// @3C: goto @46
		// @3F: bipush 27 (0x1B)
		// @41: goto @46
		// @44: bipush 102 (0x66)
		// @46: ixor
		// @47: i2c
		// @48: castore
		// @49: iinc #1 +1
		// @4C: swap
		// @4D: dup_x1
		// @4E: iload_1
		// @4F: if_icmpgt @09
		// @52: new java.lang.String
		// @55: dup_x1
		// @56: swap
		// @57: invokespecial java.lang.String.<init>(char[])void
		// @5A: invokevirtual java.lang.String.intern()java.lang.String
		// @5D: areturn
	}
}
