package game;

final class C_100032_gk extends C_100218_am
{
	int field_103131_W;
	int field_103128_O;
	int field_103134_P;
	static String[] field_103133_Q;
	int field_103138_Y;
	static C_100302_ka field_103140_X;
	static C_100302_ka field_103137_ab;
	int field_103130_T;
	static int[] field_103129_U;
	static String field_103135_S;
	static int[] field_103139_bb;
	static int field_103132_V;
	static int field_103141_Z;
	int field_103136_R;
	private static final String[] field_103127_cb;
	
	static final void func_103124_a(boolean arg0)
	{
		// @000: getstatic int game.SteelSentinels.field_105275_O
		// @003: istore_2
		// @004: getstatic game.C_100202_qi game.C_100083_c.field_103168_Q
		// @007: bipush 121 (0x79)
		// @009: invokevirtual game.C_100202_qi.func_105899_c(int)game.C_100158_da
		// @00C: checkcast game.C_100054_ec
		// @00F: astore_1
		// @010: aload_1
		// @011: ifnull @066
		// @014: aload_1
		// @015: getfield int game.C_100054_ec.field_101962_ic
		// @018: iload_2
		// @019: ifne @129
		// @01C: ifgt @026
		// @01F: goto @023
		// @022: athrow
		// @023: goto @056
		// @026: aload_1
		// @027: dup
		// @028: getfield int game.C_100054_ec.field_101962_ic
		// @02B: iconst_1
		// @02C: isub
		// @02D: putfield int game.C_100054_ec.field_101962_ic
		// @030: iconst_m1
		// @031: aload_1
		// @032: getfield int game.C_100054_ec.field_101962_ic
		// @035: iconst_m1
		// @036: ixor
		// @037: if_icmpeq @03E
		// @03A: goto @056
		// @03D: athrow
		// @03E: aload_1
		// @03F: iconst_0
		// @040: putfield int game.C_100054_ec.field_101954_Zb
		// @043: aload_1
		// @044: bipush -113 (0x8F)
		// @046: invokevirtual game.C_100054_ec.func_101951_m(int)boolean
		// @049: ifeq @056
		// @04C: aload_1
		// @04D: bipush 45 (0x2D)
		// @04F: invokevirtual game.C_100054_ec.func_100583_c(int)void
		// @052: goto @056
		// @055: athrow
		// @056: getstatic game.C_100202_qi game.C_100083_c.field_103168_Q
		// @059: bipush 82 (0x52)
		// @05B: invokevirtual game.C_100202_qi.func_105907_c(byte)game.C_100158_da
		// @05E: checkcast game.C_100054_ec
		// @061: astore_1
		// @062: iload_2
		// @063: ifeq @010
		// @066: getstatic game.C_100202_qi game.C_100335_il.field_107368_e
		// @069: bipush 101 (0x65)
		// @06B: invokevirtual game.C_100202_qi.func_105899_c(int)game.C_100158_da
		// @06E: checkcast game.C_100211_qd
		// @071: astore_1
		// @072: aconst_null
		// @073: aload_1
		// @074: if_acmpeq @0C3
		// @077: iconst_0
		// @078: aload_1
		// @079: getfield int game.C_100211_qd.field_102142_Ub
		// @07C: if_icmplt @083
		// @07F: goto @0B3
		// @082: athrow
		// @083: aload_1
		// @084: dup
		// @085: getfield int game.C_100211_qd.field_102142_Ub
		// @088: iconst_1
		// @089: isub
		// @08A: putfield int game.C_100211_qd.field_102142_Ub
		// @08D: aload_1
		// @08E: getfield int game.C_100211_qd.field_102142_Ub
		// @091: iconst_m1
		// @092: ixor
		// @093: iconst_m1
		// @094: if_icmpeq @09B
		// @097: goto @0B3
		// @09A: athrow
		// @09B: aload_1
		// @09C: iconst_0
		// @09D: putfield int game.C_100211_qd.field_102170_ac
		// @0A0: aload_1
		// @0A1: bipush -108 (0x94)
		// @0A3: invokevirtual game.C_100211_qd.func_102125_g(byte)boolean
		// @0A6: ifeq @0B3
		// @0A9: aload_1
		// @0AA: bipush 45 (0x2D)
		// @0AC: invokevirtual game.C_100211_qd.func_100583_c(int)void
		// @0AF: goto @0B3
		// @0B2: athrow
		// @0B3: getstatic game.C_100202_qi game.C_100335_il.field_107368_e
		// @0B6: bipush 72 (0x48)
		// @0B8: invokevirtual game.C_100202_qi.func_105907_c(byte)game.C_100158_da
		// @0BB: checkcast game.C_100211_qd
		// @0BE: astore_1
		// @0BF: iload_2
		// @0C0: ifeq @072
		// @0C3: getstatic game.C_100202_qi game.C_100339_jb.field_107387_l
		// @0C6: bipush 93 (0x5D)
		// @0C8: invokevirtual game.C_100202_qi.func_105899_c(int)game.C_100158_da
		// @0CB: checkcast game.C_100054_ec
		// @0CE: astore_1
		// @0CF: aload_1
		// @0D0: ifnull @128
		// @0D3: aload_1
		// @0D4: getfield int game.C_100054_ec.field_101962_ic
		// @0D7: iconst_m1
		// @0D8: ixor
		// @0D9: iconst_m1
		// @0DA: iload_2
		// @0DB: ifne @12A
		// @0DE: if_icmplt @0E8
		// @0E1: goto @0E5
		// @0E4: athrow
		// @0E5: goto @118
		// @0E8: aload_1
		// @0E9: dup
		// @0EA: getfield int game.C_100054_ec.field_101962_ic
		// @0ED: iconst_1
		// @0EE: isub
		// @0EF: putfield int game.C_100054_ec.field_101962_ic
		// @0F2: aload_1
		// @0F3: getfield int game.C_100054_ec.field_101962_ic
		// @0F6: iconst_m1
		// @0F7: ixor
		// @0F8: iconst_m1
		// @0F9: if_icmpne @118
		// @0FC: aload_1
		// @0FD: iconst_0
		// @0FE: putfield int game.C_100054_ec.field_101954_Zb
		// @101: aload_1
		// @102: bipush 51 (0x33)
		// @104: invokevirtual game.C_100054_ec.func_101951_m(int)boolean
		// @107: ifne @112
		// @10A: goto @10E
		// @10D: athrow
		// @10E: goto @118
		// @111: athrow
		// @112: aload_1
		// @113: bipush 45 (0x2D)
		// @115: invokevirtual game.C_100054_ec.func_100583_c(int)void
		// @118: getstatic game.C_100202_qi game.C_100339_jb.field_107387_l
		// @11B: bipush 45 (0x2D)
		// @11D: invokevirtual game.C_100202_qi.func_105907_c(byte)game.C_100158_da
		// @120: checkcast game.C_100054_ec
		// @123: astore_1
		// @124: iload_2
		// @125: ifeq @0CF
		// @128: iload_0
		// @129: iconst_1
		// @12A: if_icmpeq @135
		// @12D: iconst_1
		// @12E: invokestatic game.C_100032_gk.func_103123_c(boolean)void
		// @131: goto @135
		// @134: athrow
		// @135: goto @159
		// @138: astore_1
		// @139: aload_1
		// @13A: new java.lang.StringBuilder
		// @13D: dup
		// @13E: invokespecial java.lang.StringBuilder.<init>()void
		// @141: getstatic java.lang.String[] game.C_100032_gk.field_103127_cb
		// @144: iconst_1
		// @145: aaload
		// @146: invokevirtual java.lang.StringBuilder.append(java.lang.String)java.lang.StringBuilder
		// @149: iload_0
		// @14A: invokevirtual java.lang.StringBuilder.append(boolean)java.lang.StringBuilder
		// @14D: bipush 41 (0x29)
		// @14F: invokevirtual java.lang.StringBuilder.append(char)java.lang.StringBuilder
		// @152: invokevirtual java.lang.StringBuilder.toString()java.lang.String
		// @155: invokestatic game.C_100181_cf.func_105695_a(java.lang.Throwable, java.lang.String)game.C_100170_cm
		// @158: athrow
		// @159: return
	}
	
	final boolean func_102520_a(int arg0, C_100336_im arg1, int arg2, int arg3, int arg4, int arg5, int arg6)
	{
		// @000: getstatic int game.SteelSentinels.field_105275_O
		// @003: istore #12
		// @005: aload_0
		// @006: iload_1
		// @007: aload_2
		// @008: bipush -22 (0xEA)
		// @00A: iload #4
		// @00C: iload #5
		// @00E: iload #6
		// @010: iload #7
		// @012: invokespecial game.C_100218_am.func_102520_a(int, game.C_100336_im, int, int, int, int, int)boolean
		// @015: ifne @01C
		// @018: goto @0FD
		// @01B: athrow
		// @01C: iload_1
		// @01D: aload_0
		// @01E: getfield int game.C_100032_gk.field_103130_T
		// @021: ineg
		// @022: iadd
		// @023: aload_0
		// @024: getfield int game.C_100032_gk.field_102538_m
		// @027: ineg
		// @028: iadd
		// @029: iload #6
		// @02B: ineg
		// @02C: iadd
		// @02D: istore #8
		// @02F: aload_0
		// @030: getfield int game.C_100032_gk.field_102541_w
		// @033: ineg
		// @034: iload #5
		// @036: ineg
		// @037: iadd
		// @038: aload_0
		// @039: getfield int game.C_100032_gk.field_103134_P
		// @03C: iload #4
		// @03E: isub
		// @03F: isub
		// @040: istore #9
		// @042: aload_0
		// @043: getfield int game.C_100032_gk.field_103138_Y
		// @046: aload_0
		// @047: getfield int game.C_100032_gk.field_103138_Y
		// @04A: imul
		// @04B: iconst_m1
		// @04C: ixor
		// @04D: iload #8
		// @04F: iload #8
		// @051: imul
		// @052: iload #9
		// @054: iload #9
		// @056: imul
		// @057: ineg
		// @058: isub
		// @059: iconst_m1
		// @05A: ixor
		// @05B: if_icmpge @0FB
		// @05E: iload #9
		// @060: i2d
		// @061: iload #8
		// @063: i2d
		// @064: invokestatic java.lang.Math.atan2(double, double)double
		// @067: getstatic double game.C_100314_lf.field_101363_Vb
		// @06A: dsub
		// @06B: dstore #10
		// @06D: dconst_0
		// @06E: dload #10
		// @070: dcmpl
		// @071: ifle @087
		// @074: dload #10
		// @076: ldc2_w 3.141592653589793
		// @079: aload_0
		// @07A: getfield int game.C_100032_gk.field_103136_R
		// @07D: i2d
		// @07E: ddiv
		// @07F: dsub
		// @080: dstore #10
		// @082: iload #12
		// @084: ifeq @0A4
		// @087: dconst_0
		// @088: dload #10
		// @08A: dcmpg
		// @08B: iflt @096
		// @08E: goto @092
		// @091: athrow
		// @092: goto @0A4
		// @095: athrow
		// @096: dload #10
		// @098: ldc2_w 3.141592653589793
		// @09B: aload_0
		// @09C: getfield int game.C_100032_gk.field_103136_R
		// @09F: i2d
		// @0A0: ddiv
		// @0A1: dadd
		// @0A2: dstore #10
		// @0A4: aload_0
		// @0A5: aload_0
		// @0A6: getfield int game.C_100032_gk.field_103136_R
		// @0A9: i2d
		// @0AA: dload #10
		// @0AC: dmul
		// @0AD: ldc2_w 6.283185307179586
		// @0B0: ddiv
		// @0B1: d2i
		// @0B2: putfield int game.C_100032_gk.field_103128_O
		// @0B5: aload_0
		// @0B6: getfield int game.C_100032_gk.field_103128_O
		// @0B9: iconst_m1
		// @0BA: ixor
		// @0BB: aload_0
		// @0BC: getfield int game.C_100032_gk.field_103136_R
		// @0BF: iconst_m1
		// @0C0: ixor
		// @0C1: if_icmpgt @0DF
		// @0C4: aload_0
		// @0C5: dup
		// @0C6: getfield int game.C_100032_gk.field_103128_O
		// @0C9: aload_0
		// @0CA: getfield int game.C_100032_gk.field_103136_R
		// @0CD: isub
		// @0CE: putfield int game.C_100032_gk.field_103128_O
		// @0D1: iload #12
		// @0D3: ifne @0FB
		// @0D6: iload #12
		// @0D8: ifeq @0B5
		// @0DB: goto @0DF
		// @0DE: athrow
		// @0DF: aload_0
		// @0E0: getfield int game.C_100032_gk.field_103128_O
		// @0E3: iconst_m1
		// @0E4: ixor
		// @0E5: iconst_m1
		// @0E6: if_icmple @0FB
		// @0E9: aload_0
		// @0EA: dup
		// @0EB: getfield int game.C_100032_gk.field_103128_O
		// @0EE: aload_0
		// @0EF: getfield int game.C_100032_gk.field_103136_R
		// @0F2: iadd
		// @0F3: putfield int game.C_100032_gk.field_103128_O
		// @0F6: iload #12
		// @0F8: ifeq @0DF
		// @0FB: iconst_1
		// @0FC: ireturn
		// @0FD: bipush 8 (0x08)
		// @0FF: bipush 32 (0x20)
		// @101: iload_3
		// @102: isub
		// @103: bipush 52 (0x34)
		// @105: idiv
		// @106: irem
		// @107: istore #8
		// @109: iconst_0
		// @10A: ireturn
		// @10B: astore #8
		// @10D: aload #8
		// @10F: new java.lang.StringBuilder
		// @112: dup
		// @113: invokespecial java.lang.StringBuilder.<init>()void
		// @116: getstatic java.lang.String[] game.C_100032_gk.field_103127_cb
		// @119: iconst_5
		// @11A: aaload
		// @11B: invokevirtual java.lang.StringBuilder.append(java.lang.String)java.lang.StringBuilder
		// @11E: iload_1
		// @11F: invokevirtual java.lang.StringBuilder.append(int)java.lang.StringBuilder
		// @122: bipush 44 (0x2C)
		// @124: invokevirtual java.lang.StringBuilder.append(char)java.lang.StringBuilder
		// @127: aload_2
		// @128: ifnull @134
		// @12B: getstatic java.lang.String[] game.C_100032_gk.field_103127_cb
		// @12E: iconst_3
		// @12F: aaload
		// @130: goto @139
		// @133: athrow
		// @134: getstatic java.lang.String[] game.C_100032_gk.field_103127_cb
		// @137: iconst_4
		// @138: aaload
		// @139: invokevirtual java.lang.StringBuilder.append(java.lang.String)java.lang.StringBuilder
		// @13C: bipush 44 (0x2C)
		// @13E: invokevirtual java.lang.StringBuilder.append(char)java.lang.StringBuilder
		// @141: iload_3
		// @142: invokevirtual java.lang.StringBuilder.append(int)java.lang.StringBuilder
		// @145: bipush 44 (0x2C)
		// @147: invokevirtual java.lang.StringBuilder.append(char)java.lang.StringBuilder
		// @14A: iload #4
		// @14C: invokevirtual java.lang.StringBuilder.append(int)java.lang.StringBuilder
		// @14F: bipush 44 (0x2C)
		// @151: invokevirtual java.lang.StringBuilder.append(char)java.lang.StringBuilder
		// @154: iload #5
		// @156: invokevirtual java.lang.StringBuilder.append(int)java.lang.StringBuilder
		// @159: bipush 44 (0x2C)
		// @15B: invokevirtual java.lang.StringBuilder.append(char)java.lang.StringBuilder
		// @15E: iload #6
		// @160: invokevirtual java.lang.StringBuilder.append(int)java.lang.StringBuilder
		// @163: bipush 44 (0x2C)
		// @165: invokevirtual java.lang.StringBuilder.append(char)java.lang.StringBuilder
		// @168: iload #7
		// @16A: invokevirtual java.lang.StringBuilder.append(int)java.lang.StringBuilder
		// @16D: bipush 41 (0x29)
		// @16F: invokevirtual java.lang.StringBuilder.append(char)java.lang.StringBuilder
		// @172: invokevirtual java.lang.StringBuilder.toString()java.lang.String
		// @175: invokestatic game.C_100181_cf.func_105695_a(java.lang.Throwable, java.lang.String)game.C_100170_cm
		// @178: athrow
	}
	
	static final int func_103126_a(boolean arg0, int arg1, int arg2, int arg3, int arg4)
	{
		// @00: getstatic int game.SteelSentinels.field_105275_O
		// @03: istore #8
		// @05: iinc #3 +239
		// @08: iload_2
		// @09: iload_3
		// @0A: if_icmpgt @1D
		// @0D: getstatic byte[][] game.C_100268_mk.field_106665_f
		// @10: arraylength
		// @11: iconst_m1
		// @12: ixor
		// @13: iload_3
		// @14: iconst_m1
		// @15: ixor
		// @16: if_icmplt @1F
		// @19: goto @1D
		// @1C: athrow
		// @1D: iconst_0
		// @1E: ireturn
		// @1F: iconst_0
		// @20: istore #5
		// @22: getstatic byte[][] game.C_100268_mk.field_106665_f
		// @25: iload_3
		// @26: aaload
		// @27: astore #6
		// @29: iconst_0
		// @2A: istore #7
		// @2C: aload #6
		// @2E: arraylength
		// @2F: iconst_m1
		// @30: ixor
		// @31: iload #7
		// @33: iconst_m1
		// @34: ixor
		// @35: if_icmpge @88
		// @38: iload_0
		// @39: iload #8
		// @3B: ifne @8A
		// @3E: ifeq @48
		// @41: goto @45
		// @44: athrow
		// @45: goto @7D
		// @48: getstatic game.C_100317_lb game.C_100311_le.field_104719_A
		// @4B: getstatic java.lang.String[] game.C_100079_e.field_102673_sb
		// @4E: aload #6
		// @50: iload #7
		// @52: baload
		// @53: aaload
		// @54: iload_1
		// @55: bipush -74 (0xB6)
		// @57: isub
		// @58: iload #4
		// @5A: iload #5
		// @5C: bipush 8 (0x08)
		// @5E: iadd
		// @5F: iadd
		// @60: ldc 16777215 (0xffffff)
		// @62: iconst_m1
		// @63: invokevirtual game.C_100317_lb.func_101746_a(java.lang.String, int, int, int, int)void
		// @66: getstatic game.C_100037_wb[] game.C_100346_ja.field_103497_z
		// @69: aload #6
		// @6B: iconst_1
		// @6C: iload #7
		// @6E: iadd
		// @6F: baload
		// @70: aaload
		// @71: iload_1
		// @72: bipush -76 (0xB4)
		// @74: isub
		// @75: iload #5
		// @77: iload #4
		// @79: iadd
		// @7A: invokevirtual game.C_100037_wb.func_102386_f(int, int)void
		// @7D: iinc #5 +12
		// @80: iinc #7 +2
		// @83: iload #8
		// @85: ifeq @2C
		// @88: iload #5
		// @8A: ireturn
		// @8B: astore #5
		// @8D: aload #5
		// @8F: new java.lang.StringBuilder
		// @92: dup
		// @93: invokespecial java.lang.StringBuilder.<init>()void
		// @96: getstatic java.lang.String[] game.C_100032_gk.field_103127_cb
		// @99: iconst_2
		// @9A: aaload
		// @9B: invokevirtual java.lang.StringBuilder.append(java.lang.String)java.lang.StringBuilder
		// @9E: iload_0
		// @9F: invokevirtual java.lang.StringBuilder.append(boolean)java.lang.StringBuilder
		// @A2: bipush 44 (0x2C)
		// @A4: invokevirtual java.lang.StringBuilder.append(char)java.lang.StringBuilder
		// @A7: iload_1
		// @A8: invokevirtual java.lang.StringBuilder.append(int)java.lang.StringBuilder
		// @AB: bipush 44 (0x2C)
		// @AD: invokevirtual java.lang.StringBuilder.append(char)java.lang.StringBuilder
		// @B0: iload_2
		// @B1: invokevirtual java.lang.StringBuilder.append(int)java.lang.StringBuilder
		// @B4: bipush 44 (0x2C)
		// @B6: invokevirtual java.lang.StringBuilder.append(char)java.lang.StringBuilder
		// @B9: iload_3
		// @BA: invokevirtual java.lang.StringBuilder.append(int)java.lang.StringBuilder
		// @BD: bipush 44 (0x2C)
		// @BF: invokevirtual java.lang.StringBuilder.append(char)java.lang.StringBuilder
		// @C2: iload #4
		// @C4: invokevirtual java.lang.StringBuilder.append(int)java.lang.StringBuilder
		// @C7: bipush 41 (0x29)
		// @C9: invokevirtual java.lang.StringBuilder.append(char)java.lang.StringBuilder
		// @CC: invokevirtual java.lang.StringBuilder.toString()java.lang.String
		// @CF: invokestatic game.C_100181_cf.func_105695_a(java.lang.Throwable, java.lang.String)game.C_100170_cm
		// @D2: athrow
	}
	
	static final boolean func_103125_a(String arg0, byte arg1)
	{
		// @00: iload_1
		// @01: bipush -45 (0xD3)
		// @03: if_icmpeq @0F
		// @06: bipush 33 (0x21)
		// @08: putstatic int game.C_100032_gk.field_103141_Z
		// @0B: goto @0F
		// @0E: athrow
		// @0F: aconst_null
		// @10: aload_0
		// @11: bipush -85 (0xAB)
		// @13: invokestatic game.C_100075_uj.func_100640_a(java.lang.String, int)game.C_100061_dh
		// @16: if_acmpeq @1E
		// @19: iconst_1
		// @1A: goto @1F
		// @1D: athrow
		// @1E: iconst_0
		// @1F: ireturn
		// @20: astore_2
		// @21: aload_2
		// @22: new java.lang.StringBuilder
		// @25: dup
		// @26: invokespecial java.lang.StringBuilder.<init>()void
		// @29: getstatic java.lang.String[] game.C_100032_gk.field_103127_cb
		// @2C: bipush 6 (0x06)
		// @2E: aaload
		// @2F: invokevirtual java.lang.StringBuilder.append(java.lang.String)java.lang.StringBuilder
		// @32: aload_0
		// @33: ifnull @3F
		// @36: getstatic java.lang.String[] game.C_100032_gk.field_103127_cb
		// @39: iconst_3
		// @3A: aaload
		// @3B: goto @44
		// @3E: athrow
		// @3F: getstatic java.lang.String[] game.C_100032_gk.field_103127_cb
		// @42: iconst_4
		// @43: aaload
		// @44: invokevirtual java.lang.StringBuilder.append(java.lang.String)java.lang.StringBuilder
		// @47: bipush 44 (0x2C)
		// @49: invokevirtual java.lang.StringBuilder.append(char)java.lang.StringBuilder
		// @4C: iload_1
		// @4D: invokevirtual java.lang.StringBuilder.append(int)java.lang.StringBuilder
		// @50: bipush 41 (0x29)
		// @52: invokevirtual java.lang.StringBuilder.append(char)java.lang.StringBuilder
		// @55: invokevirtual java.lang.StringBuilder.toString()java.lang.String
		// @58: invokestatic game.C_100181_cf.func_105695_a(java.lang.Throwable, java.lang.String)game.C_100170_cm
		// @5B: athrow
	}
	
	public static void func_103123_c(boolean arg0)
	{
		// @00: aconst_null
		// @01: putstatic int[] game.C_100032_gk.field_103129_U
		// @04: aconst_null
		// @05: putstatic java.lang.String game.C_100032_gk.field_103135_S
		// @08: aconst_null
		// @09: putstatic game.C_100302_ka game.C_100032_gk.field_103140_X
		// @0C: aconst_null
		// @0D: putstatic game.C_100302_ka game.C_100032_gk.field_103137_ab
		// @10: aconst_null
		// @11: putstatic java.lang.String[] game.C_100032_gk.field_103133_Q
		// @14: iload_0
		// @15: ifeq @19
		// @18: return
		// @19: aconst_null
		// @1A: putstatic int[] game.C_100032_gk.field_103139_bb
		// @1D: goto @41
		// @20: astore_1
		// @21: aload_1
		// @22: new java.lang.StringBuilder
		// @25: dup
		// @26: invokespecial java.lang.StringBuilder.<init>()void
		// @29: getstatic java.lang.String[] game.C_100032_gk.field_103127_cb
		// @2C: iconst_0
		// @2D: aaload
		// @2E: invokevirtual java.lang.StringBuilder.append(java.lang.String)java.lang.StringBuilder
		// @31: iload_0
		// @32: invokevirtual java.lang.StringBuilder.append(boolean)java.lang.StringBuilder
		// @35: bipush 41 (0x29)
		// @37: invokevirtual java.lang.StringBuilder.append(char)java.lang.StringBuilder
		// @3A: invokevirtual java.lang.StringBuilder.toString()java.lang.String
		// @3D: invokestatic game.C_100181_cf.func_105695_a(java.lang.Throwable, java.lang.String)game.C_100170_cm
		// @40: athrow
		// @41: return
	}
	
	private C_100032_gk() throws Throwable
	{
		// @00: aload_0
		// @01: invokespecial game.C_100218_am.<init>()void
		// @04: new java.lang.Error
		// @07: dup
		// @08: invokespecial java.lang.Error.<init>()void
		// @0B: athrow
		// @0C: astore_1
		// @0D: aload_1
		// @0E: getstatic java.lang.String[] game.C_100032_gk.field_103127_cb
		// @11: bipush 7 (0x07)
		// @13: aaload
		// @14: invokestatic game.C_100181_cf.func_105695_a(java.lang.Throwable, java.lang.String)game.C_100170_cm
		// @17: athrow
	}
	
	static
	{
		// @000: bipush 8 (0x08)
		// @002: anewarray java.lang.String
		// @005: dup
		// @006: iconst_0
		// @007: ldc "U\u000e`+J"
		// @009: invokestatic game.C_100032_gk.func_103122_z(java.lang.String)char[]
		// @00C: invokestatic game.C_100032_gk.func_103121_z(char[])java.lang.String
		// @00F: aastore
		// @010: dup
		// @011: iconst_1
		// @012: ldc "U\u000e`*J"
		// @014: invokestatic game.C_100032_gk.func_103122_z(java.lang.String)char[]
		// @017: invokestatic game.C_100032_gk.func_103121_z(char[])java.lang.String
		// @01A: aastore
		// @01B: dup
		// @01C: iconst_2
		// @01D: ldc "U\u000e`.J"
		// @01F: invokestatic game.C_100032_gk.func_103122_z(java.lang.String)char[]
		// @022: invokestatic game.C_100032_gk.func_103121_z(char[])java.lang.String
		// @025: aastore
		// @026: dup
		// @027: iconst_3
		// @028: ldc "IK`A\u001f"
		// @02A: invokestatic game.C_100032_gk.func_103122_z(java.lang.String)char[]
		// @02D: invokestatic game.C_100032_gk.func_103121_z(char[])java.lang.String
		// @030: aastore
		// @031: dup
		// @032: iconst_4
		// @033: ldc "\\\u0010\"\u0003"
		// @035: invokestatic game.C_100032_gk.func_103122_z(java.lang.String)char[]
		// @038: invokestatic game.C_100032_gk.func_103121_z(char[])java.lang.String
		// @03B: aastore
		// @03C: dup
		// @03D: iconst_5
		// @03E: ldc "U\u000e`:J"
		// @040: invokestatic game.C_100032_gk.func_103122_z(java.lang.String)char[]
		// @043: invokestatic game.C_100032_gk.func_103121_z(char[])java.lang.String
		// @046: aastore
		// @047: dup
		// @048: bipush 6 (0x06)
		// @04A: ldc "U\u000e`-J"
		// @04C: invokestatic game.C_100032_gk.func_103122_z(java.lang.String)char[]
		// @04F: invokestatic game.C_100032_gk.func_103121_z(char[])java.lang.String
		// @052: aastore
		// @053: dup
		// @054: bipush 7 (0x07)
		// @056: ldc "U\u000e`S\u000b\\\u000c:QJ\u001b"
		// @058: invokestatic game.C_100032_gk.func_103122_z(java.lang.String)char[]
		// @05B: invokestatic game.C_100032_gk.func_103121_z(char[])java.lang.String
		// @05E: aastore
		// @05F: putstatic java.lang.String[] game.C_100032_gk.field_103127_cb
		// @062: iconst_5
		// @063: anewarray java.lang.String
		// @066: dup
		// @067: iconst_0
		// @068: ldc ""
		// @06A: aastore
		// @06B: dup
		// @06C: iconst_1
		// @06D: ldc "\u000e\u0007<Q;]\u0010n\u0007\u0003D\u0000n\u001b\u0007\\E#\u0006\u000cG\u0011+\u001cBP\u0000(\u0000\u0010WE:\u0007\u0007\u0012\u0007/\u001b\u0016^\u0000n\u0006\u000c\u0012\n<\r\u000bFE<\n\u0003Q\r+\u001cBF\r+O\u0011G\u0017(\u000e\u0001WK"
		// @06F: invokestatic game.C_100032_gk.func_103122_z(java.lang.String)char[]
		// @072: invokestatic game.C_100032_gk.func_103121_z(char[])java.lang.String
		// @075: aastore
		// @076: dup
		// @077: iconst_2
		// @078: ldc "\u000e\u0007<Q!S\u0015:\u001a\u0010WE:\u0007\u0007\u0012(\t),\u0012\u0011+\u000c\n\\\n\"\u0000\u0005KE:\u0000BE\u000c O\u0016Z\u0000n\u001c\u0001]\u0017+B\u0005S\u000c \u0006\u000cUE>\u0000\u0015W\u0017`"
		// @07A: invokestatic game.C_100032_gk.func_103122_z(java.lang.String)char[]
		// @07D: invokestatic game.C_100032_gk.func_103121_z(char[])java.lang.String
		// @080: aastore
		// @081: dup
		// @082: iconst_3
		// @083: ldc "\u000e\u0007<Q1F\u00047O\u0015[\u0011&\u0006\u000c\u0012\u0011&\nBQ\u0017/\u001c\nW\u0001n\u001c\n[\u0015i\u001cBW\u000b+\u001d\u0005KE=\u0007\u000bW\t*O\u0016]E)\u000e\u000b\\E=\u000c\r@\u0000`"
		// @085: invokestatic game.C_100032_gk.func_103122_z(java.lang.String)char[]
		// @088: invokestatic game.C_100032_gk.func_103121_z(char[])java.lang.String
		// @08B: aastore
		// @08C: dup
		// @08D: iconst_4
		// @08E: ldc "\u000e\u0007<Q0W\u0004-\u0007BF\r+O\u0007\\\u0000#\u0016BA\r'\u001fBS\u000b*O\u0010W\u0011;\u001d\u000c\u0012\u0011!O\nW\t>O\u001b]\u0010<O\u0016W\u0004#O\u0015[\u000bn\u001b\nWE,\u000e\u0016F\t+A"
		// @090: invokestatic game.C_100032_gk.func_103122_z(java.lang.String)char[]
		// @093: invokestatic game.C_100032_gk.func_103121_z(char[])java.lang.String
		// @096: aastore
		// @097: putstatic java.lang.String[] game.C_100032_gk.field_103133_Q
		// @09A: iconst_m1
		// @09B: putstatic int game.C_100032_gk.field_103132_V
		// @09E: bipush 24 (0x18)
		// @0A0: newarray int[]
		// @0A2: dup
		// @0A3: iconst_0
		// @0A4: bipush 92 (0x5C)
		// @0A6: iastore
		// @0A7: dup
		// @0A8: iconst_1
		// @0A9: bipush 106 (0x6A)
		// @0AB: iastore
		// @0AC: dup
		// @0AD: iconst_2
		// @0AE: bipush 48 (0x30)
		// @0B0: iastore
		// @0B1: dup
		// @0B2: iconst_3
		// @0B3: bipush 24 (0x18)
		// @0B5: iastore
		// @0B6: dup
		// @0B7: iconst_4
		// @0B8: bipush 24 (0x18)
		// @0BA: iastore
		// @0BB: dup
		// @0BC: iconst_5
		// @0BD: bipush 24 (0x18)
		// @0BF: iastore
		// @0C0: dup
		// @0C1: bipush 6 (0x06)
		// @0C3: bipush 95 (0x5F)
		// @0C5: iastore
		// @0C6: dup
		// @0C7: bipush 7 (0x07)
		// @0C9: bipush 24 (0x18)
		// @0CB: iastore
		// @0CC: dup
		// @0CD: bipush 8 (0x08)
		// @0CF: bipush 24 (0x18)
		// @0D1: iastore
		// @0D2: dup
		// @0D3: bipush 9 (0x09)
		// @0D5: bipush 24 (0x18)
		// @0D7: iastore
		// @0D8: dup
		// @0D9: bipush 10 (0x0A)
		// @0DB: bipush 24 (0x18)
		// @0DD: iastore
		// @0DE: dup
		// @0DF: bipush 11 (0x0B)
		// @0E1: bipush 93 (0x5D)
		// @0E3: iastore
		// @0E4: dup
		// @0E5: bipush 12 (0x0C)
		// @0E7: bipush 37 (0x25)
		// @0E9: iastore
		// @0EA: dup
		// @0EB: bipush 13 (0x0D)
		// @0ED: bipush 37 (0x25)
		// @0EF: iastore
		// @0F0: dup
		// @0F1: bipush 14 (0x0E)
		// @0F3: bipush 37 (0x25)
		// @0F5: iastore
		// @0F6: dup
		// @0F7: bipush 15 (0x0F)
		// @0F9: bipush 52 (0x34)
		// @0FB: iastore
		// @0FC: dup
		// @0FD: bipush 16 (0x10)
		// @0FF: bipush 9 (0x09)
		// @101: iastore
		// @102: dup
		// @103: bipush 17 (0x11)
		// @105: bipush 14 (0x0E)
		// @107: iastore
		// @108: dup
		// @109: bipush 18 (0x12)
		// @10B: bipush 27 (0x1B)
		// @10D: iastore
		// @10E: dup
		// @10F: bipush 19 (0x13)
		// @111: bipush 20 (0x14)
		// @113: iastore
		// @114: dup
		// @115: bipush 20 (0x14)
		// @117: bipush 31 (0x1F)
		// @119: iastore
		// @11A: dup
		// @11B: bipush 21 (0x15)
		// @11D: iconst_4
		// @11E: iastore
		// @11F: dup
		// @120: bipush 22 (0x16)
		// @122: iconst_m1
		// @123: iastore
		// @124: dup
		// @125: bipush 23 (0x17)
		// @127: iconst_m1
		// @128: iastore
		// @129: putstatic int[] game.C_100032_gk.field_103139_bb
		// @12C: sipush 500 (0x01F4)
		// @12F: putstatic int game.C_100032_gk.field_103141_Z
		// @132: ldc "q\u0010=\u001b\r_H,\u001a\u000b^\u0001'\u0001\u0005\u0012\n(O\u0011W\u000b:\u0006\u000cW\t=O\u000bAE/\u0019\u0003[\t/\r\u000eWE'\u0001BS\u00018\u000e\u000cQ\u0000*O\u000f]\u0001+O\r\\\t7ABw\u0004<\u0001B\u0003I~_R\u0012\u0016!\u0003\u0003@\u000c:\nBQ\u0010,\n\u0011\u0012\u000c O\u000fG\t:\u0006\u0012^\u00047\n\u0010\u0012\u0002/\u0002\u0007AE!\u001dB[\u000bn\u0002\u000bA\u0016'\u0000\u000cAE:\u0000BG\u000b\"\u0000\u0001YE/\u000b\u0014S\u000b-\n\u0006\u0012\u0008!\u000b\u0007\u001c"
		// @134: invokestatic game.C_100032_gk.func_103122_z(java.lang.String)char[]
		// @137: invokestatic game.C_100032_gk.func_103121_z(char[])java.lang.String
		// @13A: putstatic java.lang.String game.C_100032_gk.field_103135_S
		// @13D: iconst_4
		// @13E: newarray int[]
		// @140: putstatic int[] game.C_100032_gk.field_103129_U
		// @143: return
	}
	
	private static char[] func_103122_z(String arg0)
	{
		// @00: aload_0
		// @01: invokevirtual java.lang.String.toCharArray()char[]
		// @04: dup
		// @05: arraylength
		// @06: iconst_2
		// @07: if_icmpge @13
		// @0A: dup
		// @0B: iconst_0
		// @0C: dup2
		// @0D: caload
		// @0E: bipush 98 (0x62)
		// @10: ixor
		// @11: i2c
		// @12: castore
		// @13: areturn
	}
	
	private static String func_103121_z(char[] arg0)
	{
		// @00: aload_0
		// @01: dup
		// @02: arraylength
		// @03: swap
		// @04: iconst_0
		// @05: istore_1
		// @06: goto @4C
		// @09: dup
		// @0A: iload_1
		// @0B: dup2
		// @0C: caload
		// @0D: iload_1
		// @0E: iconst_5
		// @0F: irem
		// @10: tableswitch def: @44, for 0: @30, for 1: @35, for 2: @3A, for 3: @3F
		// @30: bipush 50 (0x32)
		// @32: goto @46
		// @35: bipush 101 (0x65)
		// @37: goto @46
		// @3A: bipush 78 (0x4E)
		// @3C: goto @46
		// @3F: bipush 111 (0x6F)
		// @41: goto @46
		// @44: bipush 98 (0x62)
		// @46: ixor
		// @47: i2c
		// @48: castore
		// @49: iinc #1 +1
		// @4C: swap
		// @4D: dup_x1
		// @4E: iload_1
		// @4F: if_icmpgt @09
		// @52: new java.lang.String
		// @55: dup_x1
		// @56: swap
		// @57: invokespecial java.lang.String.<init>(char[])void
		// @5A: invokevirtual java.lang.String.intern()java.lang.String
		// @5D: areturn
	}
}
