package game;

final class C_100219_an extends C_100158_da
{
	static int[] field_100876_n;
	boolean field_100879_j;
	static C_100037_wb[] field_100878_m;
	static String field_100877_l;
	int[] field_100881_k;
	private static final String[] field_100880_z;
	
	static final void func_100875_a(int arg0, int arg1, int arg2, int arg3, int arg4, C_100112_r arg5, int arg6, C_100037_wb arg7, byte arg8, int arg9, int arg10)
	{
		// @00: iload #4
		// @02: putstatic int game.C_100316_lc.field_102416_y
		// @05: iload #8
		// @07: bipush -45 (0xD3)
		// @09: if_icmpeq @2D
		// @0C: bipush -76 (0xB4)
		// @0E: bipush -53 (0xCB)
		// @10: bipush -56 (0xC8)
		// @12: bipush 72 (0x48)
		// @14: bipush -128 (0x80)
		// @16: aconst_null
		// @17: checkcast game.C_100112_r
		// @1A: bipush 110 (0x6E)
		// @1C: aconst_null
		// @1D: checkcast game.C_100037_wb
		// @20: bipush 97 (0x61)
		// @22: bipush 75 (0x4B)
		// @24: bipush -90 (0xA6)
		// @26: invokestatic game.C_100219_an.func_100875_a(int, int, int, int, int, game.C_100112_r, int, game.C_100037_wb, byte, int, int)void
		// @29: goto @2D
		// @2C: athrow
		// @2D: iload_1
		// @2E: putstatic int game.C_100211_qd.field_102139_rc
		// @31: iload_2
		// @32: putstatic int game.C_100277_nc.field_106742_p
		// @35: aload #7
		// @37: putstatic game.C_100037_wb game.C_100269_ml.field_101129_k
		// @3A: iload_3
		// @3B: putstatic int game.C_100066_dl.field_101646_x
		// @3E: iload_0
		// @3F: putstatic int game.C_100056_de.field_103186_jb
		// @42: iload #10
		// @44: putstatic int game.C_100044_vm.field_100945_s
		// @47: iload #6
		// @49: putstatic int game.C_100170_cm.field_105541_c
		// @4C: goto @F5
		// @4F: astore #11
		// @51: aload #11
		// @53: new java.lang.StringBuilder
		// @56: dup
		// @57: invokespecial java.lang.StringBuilder.<init>()void
		// @5A: getstatic java.lang.String[] game.C_100219_an.field_100880_z
		// @5D: iconst_3
		// @5E: aaload
		// @5F: invokevirtual java.lang.StringBuilder.append(java.lang.String)java.lang.StringBuilder
		// @62: iload_0
		// @63: invokevirtual java.lang.StringBuilder.append(int)java.lang.StringBuilder
		// @66: bipush 44 (0x2C)
		// @68: invokevirtual java.lang.StringBuilder.append(char)java.lang.StringBuilder
		// @6B: iload_1
		// @6C: invokevirtual java.lang.StringBuilder.append(int)java.lang.StringBuilder
		// @6F: bipush 44 (0x2C)
		// @71: invokevirtual java.lang.StringBuilder.append(char)java.lang.StringBuilder
		// @74: iload_2
		// @75: invokevirtual java.lang.StringBuilder.append(int)java.lang.StringBuilder
		// @78: bipush 44 (0x2C)
		// @7A: invokevirtual java.lang.StringBuilder.append(char)java.lang.StringBuilder
		// @7D: iload_3
		// @7E: invokevirtual java.lang.StringBuilder.append(int)java.lang.StringBuilder
		// @81: bipush 44 (0x2C)
		// @83: invokevirtual java.lang.StringBuilder.append(char)java.lang.StringBuilder
		// @86: iload #4
		// @88: invokevirtual java.lang.StringBuilder.append(int)java.lang.StringBuilder
		// @8B: bipush 44 (0x2C)
		// @8D: invokevirtual java.lang.StringBuilder.append(char)java.lang.StringBuilder
		// @90: aload #5
		// @92: ifnull @9E
		// @95: getstatic java.lang.String[] game.C_100219_an.field_100880_z
		// @98: iconst_1
		// @99: aaload
		// @9A: goto @A3
		// @9D: athrow
		// @9E: getstatic java.lang.String[] game.C_100219_an.field_100880_z
		// @A1: iconst_2
		// @A2: aaload
		// @A3: invokevirtual java.lang.StringBuilder.append(java.lang.String)java.lang.StringBuilder
		// @A6: bipush 44 (0x2C)
		// @A8: invokevirtual java.lang.StringBuilder.append(char)java.lang.StringBuilder
		// @AB: iload #6
		// @AD: invokevirtual java.lang.StringBuilder.append(int)java.lang.StringBuilder
		// @B0: bipush 44 (0x2C)
		// @B2: invokevirtual java.lang.StringBuilder.append(char)java.lang.StringBuilder
		// @B5: aload #7
		// @B7: ifnull @C3
		// @BA: getstatic java.lang.String[] game.C_100219_an.field_100880_z
		// @BD: iconst_1
		// @BE: aaload
		// @BF: goto @C8
		// @C2: athrow
		// @C3: getstatic java.lang.String[] game.C_100219_an.field_100880_z
		// @C6: iconst_2
		// @C7: aaload
		// @C8: invokevirtual java.lang.StringBuilder.append(java.lang.String)java.lang.StringBuilder
		// @CB: bipush 44 (0x2C)
		// @CD: invokevirtual java.lang.StringBuilder.append(char)java.lang.StringBuilder
		// @D0: iload #8
		// @D2: invokevirtual java.lang.StringBuilder.append(int)java.lang.StringBuilder
		// @D5: bipush 44 (0x2C)
		// @D7: invokevirtual java.lang.StringBuilder.append(char)java.lang.StringBuilder
		// @DA: iload #9
		// @DC: invokevirtual java.lang.StringBuilder.append(int)java.lang.StringBuilder
		// @DF: bipush 44 (0x2C)
		// @E1: invokevirtual java.lang.StringBuilder.append(char)java.lang.StringBuilder
		// @E4: iload #10
		// @E6: invokevirtual java.lang.StringBuilder.append(int)java.lang.StringBuilder
		// @E9: bipush 41 (0x29)
		// @EB: invokevirtual java.lang.StringBuilder.append(char)java.lang.StringBuilder
		// @EE: invokevirtual java.lang.StringBuilder.toString()java.lang.String
		// @F1: invokestatic game.C_100181_cf.func_105695_a(java.lang.Throwable, java.lang.String)game.C_100170_cm
		// @F4: athrow
		// @F5: return
	}
	
	public static void func_100873_a(byte arg0)
	{
		// @00: aconst_null
		// @01: putstatic int[] game.C_100219_an.field_100876_n
		// @04: aconst_null
		// @05: putstatic java.lang.String game.C_100219_an.field_100877_l
		// @08: aconst_null
		// @09: putstatic game.C_100037_wb[] game.C_100219_an.field_100878_m
		// @0C: iload_0
		// @0D: bipush -126 (0x82)
		// @0F: if_icmple @19
		// @12: aconst_null
		// @13: checkcast java.lang.String
		// @16: putstatic java.lang.String game.C_100219_an.field_100877_l
		// @19: goto @3D
		// @1C: astore_1
		// @1D: aload_1
		// @1E: new java.lang.StringBuilder
		// @21: dup
		// @22: invokespecial java.lang.StringBuilder.<init>()void
		// @25: getstatic java.lang.String[] game.C_100219_an.field_100880_z
		// @28: iconst_0
		// @29: aaload
		// @2A: invokevirtual java.lang.StringBuilder.append(java.lang.String)java.lang.StringBuilder
		// @2D: iload_0
		// @2E: invokevirtual java.lang.StringBuilder.append(int)java.lang.StringBuilder
		// @31: bipush 41 (0x29)
		// @33: invokevirtual java.lang.StringBuilder.append(char)java.lang.StringBuilder
		// @36: invokevirtual java.lang.StringBuilder.toString()java.lang.String
		// @39: invokestatic game.C_100181_cf.func_105695_a(java.lang.Throwable, java.lang.String)game.C_100170_cm
		// @3C: athrow
		// @3D: return
	}
	
	C_100219_an()
	{
		// @0: aload_0
		// @1: invokespecial game.C_100158_da.<init>()void
		// @4: aload_0
		// @5: iconst_0
		// @6: putfield boolean game.C_100219_an.field_100879_j
		// @9: return
	}
	
	static
	{
		// @00: iconst_4
		// @01: anewarray java.lang.String
		// @04: dup
		// @05: iconst_0
		// @06: ldc "(\u001bu\u007f{"
		// @08: invokestatic game.C_100219_an.func_100874_z(java.lang.String)char[]
		// @0B: invokestatic game.C_100219_an.func_100872_z(char[])java.lang.String
		// @0E: aastore
		// @0F: dup
		// @10: iconst_1
		// @11: ldc "2[u\u0013."
		// @13: invokestatic game.C_100219_an.func_100874_z(java.lang.String)char[]
		// @16: invokestatic game.C_100219_an.func_100872_z(char[])java.lang.String
		// @19: aastore
		// @1A: dup
		// @1B: iconst_2
		// @1C: ldc "'\u00007Q"
		// @1E: invokestatic game.C_100219_an.func_100874_z(java.lang.String)char[]
		// @21: invokestatic game.C_100219_an.func_100872_z(char[])java.lang.String
		// @24: aastore
		// @25: dup
		// @26: iconst_3
		// @27: ldc "(\u001bu|{"
		// @29: invokestatic game.C_100219_an.func_100874_z(java.lang.String)char[]
		// @2C: invokestatic game.C_100219_an.func_100872_z(char[])java.lang.String
		// @2F: aastore
		// @30: putstatic java.lang.String[] game.C_100219_an.field_100880_z
		// @33: return
	}
	
	private static char[] func_100874_z(String arg0)
	{
		// @00: aload_0
		// @01: invokevirtual java.lang.String.toCharArray()char[]
		// @04: dup
		// @05: arraylength
		// @06: iconst_2
		// @07: if_icmpge @13
		// @0A: dup
		// @0B: iconst_0
		// @0C: dup2
		// @0D: caload
		// @0E: bipush 83 (0x53)
		// @10: ixor
		// @11: i2c
		// @12: castore
		// @13: areturn
	}
	
	private static String func_100872_z(char[] arg0)
	{
		// @00: aload_0
		// @01: dup
		// @02: arraylength
		// @03: swap
		// @04: iconst_0
		// @05: istore_1
		// @06: goto @4C
		// @09: dup
		// @0A: iload_1
		// @0B: dup2
		// @0C: caload
		// @0D: iload_1
		// @0E: iconst_5
		// @0F: irem
		// @10: tableswitch def: @44, for 0: @30, for 1: @35, for 2: @3A, for 3: @3F
		// @30: bipush 73 (0x49)
		// @32: goto @46
		// @35: bipush 117 (0x75)
		// @37: goto @46
		// @3A: bipush 91 (0x5B)
		// @3C: goto @46
		// @3F: bipush 61 (0x3D)
		// @41: goto @46
		// @44: bipush 83 (0x53)
		// @46: ixor
		// @47: i2c
		// @48: castore
		// @49: iinc #1 +1
		// @4C: swap
		// @4D: dup_x1
		// @4E: iload_1
		// @4F: if_icmpgt @09
		// @52: new java.lang.String
		// @55: dup_x1
		// @56: swap
		// @57: invokespecial java.lang.String.<init>(char[])void
		// @5A: invokevirtual java.lang.String.intern()java.lang.String
		// @5D: areturn
	}
}
