package game;

final class C_100195_rc
{
	static boolean field_105773_c;
	static C_100037_wb field_105772_b;
	static C_100302_ka field_105774_a;
	private static final String[] field_105775_z;
	
	static final void func_105764_b(int arg0)
	{
		// @00: sipush 224 (0x00E0)
		// @03: getstatic int game.C_100346_ja.field_103498_y
		// @06: if_icmpgt @1B
		// @09: bipush 110 (0x6E)
		// @0B: sipush 256 (0x0100)
		// @0E: invokestatic game.C_100266_me.func_106646_a(int, int)void
		// @11: getstatic int game.SteelSentinels.field_105275_O
		// @14: ifeq @30
		// @17: goto @1B
		// @1A: athrow
		// @1B: getstatic int game.C_100346_ja.field_103498_y
		// @1E: bipush 32 (0x20)
		// @20: irem
		// @21: istore_1
		// @22: bipush 111 (0x6F)
		// @24: iload_1
		// @25: ineg
		// @26: bipush 32 (0x20)
		// @28: iadd
		// @29: getstatic int game.C_100346_ja.field_103498_y
		// @2C: iadd
		// @2D: invokestatic game.C_100266_me.func_106646_a(int, int)void
		// @30: iload_0
		// @31: bipush -99 (0x9D)
		// @33: if_icmple @41
		// @36: aconst_null
		// @37: checkcast game.C_100037_wb
		// @3A: putstatic game.C_100037_wb game.C_100195_rc.field_105772_b
		// @3D: goto @41
		// @40: athrow
		// @41: goto @66
		// @44: astore_1
		// @45: aload_1
		// @46: new java.lang.StringBuilder
		// @49: dup
		// @4A: invokespecial java.lang.StringBuilder.<init>()void
		// @4D: getstatic java.lang.String[] game.C_100195_rc.field_105775_z
		// @50: bipush 6 (0x06)
		// @52: aaload
		// @53: invokevirtual java.lang.StringBuilder.append(java.lang.String)java.lang.StringBuilder
		// @56: iload_0
		// @57: invokevirtual java.lang.StringBuilder.append(int)java.lang.StringBuilder
		// @5A: bipush 41 (0x29)
		// @5C: invokevirtual java.lang.StringBuilder.append(char)java.lang.StringBuilder
		// @5F: invokevirtual java.lang.StringBuilder.toString()java.lang.String
		// @62: invokestatic game.C_100181_cf.func_105695_a(java.lang.Throwable, java.lang.String)game.C_100170_cm
		// @65: athrow
		// @66: return
	}
	
	static final C_100327_ib func_105771_a(boolean arg0, int[] arg1, int[] arg2, byte arg3)
	{
		// @000: getstatic int game.SteelSentinels.field_105275_O
		// @003: istore #10
		// @005: aload_2
		// @006: ifnull @019
		// @009: aload_2
		// @00A: arraylength
		// @00B: iconst_m1
		// @00C: ixor
		// @00D: iconst_m1
		// @00E: if_icmpeq @019
		// @011: goto @015
		// @014: athrow
		// @015: goto @01B
		// @018: athrow
		// @019: aconst_null
		// @01A: areturn
		// @01B: iconst_0
		// @01C: istore #4
		// @01E: aload_2
		// @01F: iload #4
		// @021: iinc #4 +1
		// @024: iaload
		// @025: istore #5
		// @027: iload #5
		// @029: bipush -60 (0xC4)
		// @02B: invokestatic game.C_100209_qb.func_102686_b(int, byte)game.C_100327_ib
		// @02E: astore #6
		// @030: iload_3
		// @031: bipush -46 (0xD2)
		// @033: if_icmpeq @041
		// @036: aconst_null
		// @037: checkcast game.C_100302_ka
		// @03A: putstatic game.C_100302_ka game.C_100195_rc.field_105774_a
		// @03D: goto @041
		// @040: athrow
		// @041: aload #6
		// @043: ifnull @056
		// @046: aload #6
		// @048: getfield int game.C_100327_ib.field_102497_w
		// @04B: iconst_m1
		// @04C: ixor
		// @04D: bipush -2 (0xFE)
		// @04F: if_icmpeq @074
		// @052: goto @056
		// @055: athrow
		// @056: sipush -30945 (0x871F)
		// @059: iconst_1
		// @05A: anewarray java.lang.String
		// @05D: dup
		// @05E: iconst_0
		// @05F: iload #5
		// @061: invokestatic java.lang.Integer.toString(int)java.lang.String
		// @064: aastore
		// @065: getstatic java.lang.String[] game.C_100195_rc.field_105775_z
		// @068: iconst_3
		// @069: aaload
		// @06A: invokestatic game.C_100132_td.func_104965_a(int, java.lang.String[], java.lang.String)java.lang.String
		// @06D: bipush 6 (0x06)
		// @06F: invokestatic game.C_100140_bj.func_102961_a(java.lang.String, int)void
		// @072: aconst_null
		// @073: areturn
		// @074: new game.C_100327_ib
		// @077: dup
		// @078: aload #6
		// @07A: iload_0
		// @07B: invokespecial game.C_100327_ib.<init>(game.C_100327_ib, boolean)void
		// @07E: astore #7
		// @080: aload #7
		// @082: aload_2
		// @083: bipush 16 (0x10)
		// @085: iload_0
		// @086: iload #4
		// @088: invokevirtual game.C_100327_ib.func_102442_a(int[], int, boolean, int)int
		// @08B: istore #4
		// @08D: iconst_0
		// @08E: istore #9
		// @090: bipush -9 (0xF7)
		// @092: iload #9
		// @094: iconst_m1
		// @095: ixor
		// @096: if_icmpge @0A6
		// @099: aload_1
		// @09A: iload #9
		// @09C: iconst_m1
		// @09D: iastore
		// @09E: iinc #9 +1
		// @0A1: iload #10
		// @0A3: ifeq @090
		// @0A6: iload #4
		// @0A8: istore #8
		// @0AA: iload #8
		// @0AC: istore #4
		// @0AE: iload #4
		// @0B0: iconst_m1
		// @0B1: ixor
		// @0B2: aload_2
		// @0B3: arraylength
		// @0B4: iconst_m1
		// @0B5: ixor
		// @0B6: if_icmple @0E8
		// @0B9: bipush 8 (0x08)
		// @0BB: iload #8
		// @0BD: ineg
		// @0BE: iload #4
		// @0C0: iadd
		// @0C1: if_icmple @0C8
		// @0C4: goto @0D4
		// @0C7: athrow
		// @0C8: getstatic java.lang.String[] game.C_100195_rc.field_105775_z
		// @0CB: iconst_5
		// @0CC: aaload
		// @0CD: bipush 6 (0x06)
		// @0CF: invokestatic game.C_100140_bj.func_102961_a(java.lang.String, int)void
		// @0D2: aconst_null
		// @0D3: areturn
		// @0D4: aload_1
		// @0D5: iload #4
		// @0D7: iload #8
		// @0D9: ineg
		// @0DA: iadd
		// @0DB: aload_2
		// @0DC: iload #4
		// @0DE: iaload
		// @0DF: iastore
		// @0E0: iinc #4 +1
		// @0E3: iload #10
		// @0E5: ifeq @0AE
		// @0E8: aload #7
		// @0EA: areturn
		// @0EB: astore #4
		// @0ED: aload #4
		// @0EF: new java.lang.StringBuilder
		// @0F2: dup
		// @0F3: invokespecial java.lang.StringBuilder.<init>()void
		// @0F6: getstatic java.lang.String[] game.C_100195_rc.field_105775_z
		// @0F9: iconst_4
		// @0FA: aaload
		// @0FB: invokevirtual java.lang.StringBuilder.append(java.lang.String)java.lang.StringBuilder
		// @0FE: iload_0
		// @0FF: invokevirtual java.lang.StringBuilder.append(boolean)java.lang.StringBuilder
		// @102: bipush 44 (0x2C)
		// @104: invokevirtual java.lang.StringBuilder.append(char)java.lang.StringBuilder
		// @107: aload_1
		// @108: ifnull @114
		// @10B: getstatic java.lang.String[] game.C_100195_rc.field_105775_z
		// @10E: iconst_2
		// @10F: aaload
		// @110: goto @119
		// @113: athrow
		// @114: getstatic java.lang.String[] game.C_100195_rc.field_105775_z
		// @117: iconst_1
		// @118: aaload
		// @119: invokevirtual java.lang.StringBuilder.append(java.lang.String)java.lang.StringBuilder
		// @11C: bipush 44 (0x2C)
		// @11E: invokevirtual java.lang.StringBuilder.append(char)java.lang.StringBuilder
		// @121: aload_2
		// @122: ifnull @12E
		// @125: getstatic java.lang.String[] game.C_100195_rc.field_105775_z
		// @128: iconst_2
		// @129: aaload
		// @12A: goto @133
		// @12D: athrow
		// @12E: getstatic java.lang.String[] game.C_100195_rc.field_105775_z
		// @131: iconst_1
		// @132: aaload
		// @133: invokevirtual java.lang.StringBuilder.append(java.lang.String)java.lang.StringBuilder
		// @136: bipush 44 (0x2C)
		// @138: invokevirtual java.lang.StringBuilder.append(char)java.lang.StringBuilder
		// @13B: iload_3
		// @13C: invokevirtual java.lang.StringBuilder.append(int)java.lang.StringBuilder
		// @13F: bipush 41 (0x29)
		// @141: invokevirtual java.lang.StringBuilder.append(char)java.lang.StringBuilder
		// @144: invokevirtual java.lang.StringBuilder.toString()java.lang.String
		// @147: invokestatic game.C_100181_cf.func_105695_a(java.lang.Throwable, java.lang.String)game.C_100170_cm
		// @14A: athrow
	}
	
	static final int func_105769_a(boolean arg0, int arg1)
	{
		// @00: iload_1
		// @01: ldc -2051940479 (0x85b1df81)
		// @03: iushr
		// @04: istore_2
		// @05: iload_2
		// @06: iload_2
		// @07: ldc -1152716991 (0xbb4aef41)
		// @09: iushr
		// @0A: ior
		// @0B: istore_2
		// @0C: iload_0
		// @0D: ifeq @19
		// @10: bipush -111 (0x91)
		// @12: invokestatic game.C_100195_rc.func_105765_c(int)void
		// @15: goto @19
		// @18: athrow
		// @19: iload_2
		// @1A: iload_2
		// @1B: ldc -441956414 (0xe5a847c2)
		// @1D: iushr
		// @1E: ior
		// @1F: istore_2
		// @20: iload_2
		// @21: iload_2
		// @22: ldc 558610884 (0x214bb9c4)
		// @24: iushr
		// @25: ior
		// @26: istore_2
		// @27: iload_2
		// @28: iload_2
		// @29: ldc 1666510888 (0x6354f028)
		// @2B: iushr
		// @2C: ior
		// @2D: istore_2
		// @2E: iload_2
		// @2F: iload_2
		// @30: ldc -688392752 (0xd6f7f5d0)
		// @32: iushr
		// @33: ior
		// @34: istore_2
		// @35: iload_2
		// @36: iconst_m1
		// @37: ixor
		// @38: iload_1
		// @39: iand
		// @3A: ireturn
		// @3B: astore_2
		// @3C: aload_2
		// @3D: new java.lang.StringBuilder
		// @40: dup
		// @41: invokespecial java.lang.StringBuilder.<init>()void
		// @44: getstatic java.lang.String[] game.C_100195_rc.field_105775_z
		// @47: bipush 7 (0x07)
		// @49: aaload
		// @4A: invokevirtual java.lang.StringBuilder.append(java.lang.String)java.lang.StringBuilder
		// @4D: iload_0
		// @4E: invokevirtual java.lang.StringBuilder.append(boolean)java.lang.StringBuilder
		// @51: bipush 44 (0x2C)
		// @53: invokevirtual java.lang.StringBuilder.append(char)java.lang.StringBuilder
		// @56: iload_1
		// @57: invokevirtual java.lang.StringBuilder.append(int)java.lang.StringBuilder
		// @5A: bipush 41 (0x29)
		// @5C: invokevirtual java.lang.StringBuilder.append(char)java.lang.StringBuilder
		// @5F: invokevirtual java.lang.StringBuilder.toString()java.lang.String
		// @62: invokestatic game.C_100181_cf.func_105695_a(java.lang.Throwable, java.lang.String)game.C_100170_cm
		// @65: athrow
	}
	
	static final void func_105770_a(int arg0, int arg1, int arg2, int arg3, int[] arg4, int arg5, int arg6)
	{
		// @00: getstatic int[][] game.C_100012_fh.field_100515_K
		// @03: iload_2
		// @04: aload #4
		// @06: aastore
		// @07: getstatic int[] game.C_100012_fh.field_100519_S
		// @0A: iload_2
		// @0B: iload_3
		// @0C: iastore
		// @0D: getstatic int[] game.C_100012_fh.field_100513_I
		// @10: iload_2
		// @11: iload_1
		// @12: iastore
		// @13: getstatic int[] game.C_100012_fh.field_100504_D
		// @16: iload_2
		// @17: iload #6
		// @19: iastore
		// @1A: iload_0
		// @1B: bipush -52 (0xCC)
		// @1D: if_icmplt @21
		// @20: return
		// @21: getstatic int[] game.C_100012_fh.field_100508_L
		// @24: iload_2
		// @25: iload #5
		// @27: iastore
		// @28: goto @99
		// @2B: astore #7
		// @2D: aload #7
		// @2F: new java.lang.StringBuilder
		// @32: dup
		// @33: invokespecial java.lang.StringBuilder.<init>()void
		// @36: getstatic java.lang.String[] game.C_100195_rc.field_105775_z
		// @39: bipush 9 (0x09)
		// @3B: aaload
		// @3C: invokevirtual java.lang.StringBuilder.append(java.lang.String)java.lang.StringBuilder
		// @3F: iload_0
		// @40: invokevirtual java.lang.StringBuilder.append(int)java.lang.StringBuilder
		// @43: bipush 44 (0x2C)
		// @45: invokevirtual java.lang.StringBuilder.append(char)java.lang.StringBuilder
		// @48: iload_1
		// @49: invokevirtual java.lang.StringBuilder.append(int)java.lang.StringBuilder
		// @4C: bipush 44 (0x2C)
		// @4E: invokevirtual java.lang.StringBuilder.append(char)java.lang.StringBuilder
		// @51: iload_2
		// @52: invokevirtual java.lang.StringBuilder.append(int)java.lang.StringBuilder
		// @55: bipush 44 (0x2C)
		// @57: invokevirtual java.lang.StringBuilder.append(char)java.lang.StringBuilder
		// @5A: iload_3
		// @5B: invokevirtual java.lang.StringBuilder.append(int)java.lang.StringBuilder
		// @5E: bipush 44 (0x2C)
		// @60: invokevirtual java.lang.StringBuilder.append(char)java.lang.StringBuilder
		// @63: aload #4
		// @65: ifnull @71
		// @68: getstatic java.lang.String[] game.C_100195_rc.field_105775_z
		// @6B: iconst_2
		// @6C: aaload
		// @6D: goto @76
		// @70: athrow
		// @71: getstatic java.lang.String[] game.C_100195_rc.field_105775_z
		// @74: iconst_1
		// @75: aaload
		// @76: invokevirtual java.lang.StringBuilder.append(java.lang.String)java.lang.StringBuilder
		// @79: bipush 44 (0x2C)
		// @7B: invokevirtual java.lang.StringBuilder.append(char)java.lang.StringBuilder
		// @7E: iload #5
		// @80: invokevirtual java.lang.StringBuilder.append(int)java.lang.StringBuilder
		// @83: bipush 44 (0x2C)
		// @85: invokevirtual java.lang.StringBuilder.append(char)java.lang.StringBuilder
		// @88: iload #6
		// @8A: invokevirtual java.lang.StringBuilder.append(int)java.lang.StringBuilder
		// @8D: bipush 41 (0x29)
		// @8F: invokevirtual java.lang.StringBuilder.append(char)java.lang.StringBuilder
		// @92: invokevirtual java.lang.StringBuilder.toString()java.lang.String
		// @95: invokestatic game.C_100181_cf.func_105695_a(java.lang.Throwable, java.lang.String)game.C_100170_cm
		// @98: athrow
		// @99: return
	}
	
	static final void func_105766_a(int arg0)
	{
		// @00: iload_0
		// @01: bipush -81 (0xAF)
		// @03: if_icmplt @11
		// @06: aconst_null
		// @07: checkcast game.C_100302_ka
		// @0A: putstatic game.C_100302_ka game.C_100195_rc.field_105774_a
		// @0D: goto @11
		// @10: athrow
		// @11: bipush 46 (0x2E)
		// @13: invokestatic game.C_100290_jm.func_106853_a(byte)void
		// @16: bipush 54 (0x36)
		// @18: invokestatic game.C_100265_mh.func_106533_m(int)void
		// @1B: aconst_null
		// @1C: putstatic game.C_100260_mc game.C_100228_nn.field_106189_c
		// @1F: bipush 39 (0x27)
		// @21: invokestatic game.C_100128_ca.func_102800_f(byte)void
		// @24: goto @48
		// @27: astore_1
		// @28: aload_1
		// @29: new java.lang.StringBuilder
		// @2C: dup
		// @2D: invokespecial java.lang.StringBuilder.<init>()void
		// @30: getstatic java.lang.String[] game.C_100195_rc.field_105775_z
		// @33: iconst_0
		// @34: aaload
		// @35: invokevirtual java.lang.StringBuilder.append(java.lang.String)java.lang.StringBuilder
		// @38: iload_0
		// @39: invokevirtual java.lang.StringBuilder.append(int)java.lang.StringBuilder
		// @3C: bipush 41 (0x29)
		// @3E: invokevirtual java.lang.StringBuilder.append(char)java.lang.StringBuilder
		// @41: invokevirtual java.lang.StringBuilder.toString()java.lang.String
		// @44: invokestatic game.C_100181_cf.func_105695_a(java.lang.Throwable, java.lang.String)game.C_100170_cm
		// @47: athrow
		// @48: return
	}
	
	public static void func_105765_c(int arg0)
	{
		// @00: aconst_null
		// @01: putstatic game.C_100037_wb game.C_100195_rc.field_105772_b
		// @04: iload_0
		// @05: bipush 23 (0x17)
		// @07: if_icmpge @0B
		// @0A: return
		// @0B: aconst_null
		// @0C: putstatic game.C_100302_ka game.C_100195_rc.field_105774_a
		// @0F: goto @34
		// @12: astore_1
		// @13: aload_1
		// @14: new java.lang.StringBuilder
		// @17: dup
		// @18: invokespecial java.lang.StringBuilder.<init>()void
		// @1B: getstatic java.lang.String[] game.C_100195_rc.field_105775_z
		// @1E: bipush 8 (0x08)
		// @20: aaload
		// @21: invokevirtual java.lang.StringBuilder.append(java.lang.String)java.lang.StringBuilder
		// @24: iload_0
		// @25: invokevirtual java.lang.StringBuilder.append(int)java.lang.StringBuilder
		// @28: bipush 41 (0x29)
		// @2A: invokevirtual java.lang.StringBuilder.append(char)java.lang.StringBuilder
		// @2D: invokevirtual java.lang.StringBuilder.toString()java.lang.String
		// @30: invokestatic game.C_100181_cf.func_105695_a(java.lang.Throwable, java.lang.String)game.C_100170_cm
		// @33: athrow
		// @34: return
	}
	
	static
	{
		// @00: bipush 10 (0x0A)
		// @02: anewarray java.lang.String
		// @05: dup
		// @06: iconst_0
		// @07: ldc "\u0018q|\u0001y"
		// @09: invokestatic game.C_100195_rc.func_105768_z(java.lang.String)char[]
		// @0C: invokestatic game.C_100195_rc.func_105767_z(char[])java.lang.String
		// @0F: aastore
		// @10: dup
		// @11: iconst_1
		// @12: ldc "\u0004g>+"
		// @14: invokestatic game.C_100195_rc.func_105768_z(java.lang.String)char[]
		// @17: invokestatic game.C_100195_rc.func_105767_z(char[])java.lang.String
		// @1A: aastore
		// @1B: dup
		// @1C: iconst_2
		// @1D: ldc "\u0011<|i,"
		// @1F: invokestatic game.C_100195_rc.func_105768_z(java.lang.String)char[]
		// @22: invokestatic game.C_100195_rc.func_105767_z(char[])java.lang.String
		// @25: aastore
		// @26: dup
		// @27: iconst_3
		// @28: ldc ")z34\"\u0003ar)>\u001e21(#\u0018w13q\u0003vhg\u0018./nbaT"
		// @2A: invokestatic game.C_100195_rc.func_105768_z(java.lang.String)char[]
		// @2D: invokestatic game.C_100195_rc.func_105767_z(char[])java.lang.String
		// @30: aastore
		// @31: dup
		// @32: iconst_4
		// @33: ldc "\u0018q|\u0005y"
		// @35: invokestatic game.C_100195_rc.func_105768_z(java.lang.String)char[]
		// @38: invokestatic game.C_100195_rc.func_105767_z(char[])java.lang.String
		// @3B: aastore
		// @3C: dup
		// @3D: iconst_5
		// @3E: ldc ">}=g<\u001fq:g5\u000bf3"
		// @40: invokestatic game.C_100195_rc.func_105768_z(java.lang.String)char[]
		// @43: invokestatic game.C_100195_rc.func_105767_z(char[])java.lang.String
		// @46: aastore
		// @47: dup
		// @48: bipush 6 (0x06)
		// @4A: ldc "\u0018q|\u0003y"
		// @4C: invokestatic game.C_100195_rc.func_105768_z(java.lang.String)char[]
		// @4F: invokestatic game.C_100195_rc.func_105767_z(char[])java.lang.String
		// @52: aastore
		// @53: dup
		// @54: bipush 7 (0x07)
		// @56: ldc "\u0018q|\u0006y"
		// @58: invokestatic game.C_100195_rc.func_105768_z(java.lang.String)char[]
		// @5B: invokestatic game.C_100195_rc.func_105767_z(char[])java.lang.String
		// @5E: aastore
		// @5F: dup
		// @60: bipush 8 (0x08)
		// @62: ldc "\u0018q|\u0002y"
		// @64: invokestatic game.C_100195_rc.func_105768_z(java.lang.String)char[]
		// @67: invokestatic game.C_100195_rc.func_105767_z(char[])java.lang.String
		// @6A: aastore
		// @6B: dup
		// @6C: bipush 9 (0x09)
		// @6E: ldc "\u0018q|\u0004y"
		// @70: invokestatic game.C_100195_rc.func_105768_z(java.lang.String)char[]
		// @73: invokestatic game.C_100195_rc.func_105767_z(char[])java.lang.String
		// @76: aastore
		// @77: putstatic java.lang.String[] game.C_100195_rc.field_105775_z
		// @7A: return
	}
	
	private static char[] func_105768_z(String arg0)
	{
		// @00: aload_0
		// @01: invokevirtual java.lang.String.toCharArray()char[]
		// @04: dup
		// @05: arraylength
		// @06: iconst_2
		// @07: if_icmpge @13
		// @0A: dup
		// @0B: iconst_0
		// @0C: dup2
		// @0D: caload
		// @0E: bipush 81 (0x51)
		// @10: ixor
		// @11: i2c
		// @12: castore
		// @13: areturn
	}
	
	private static String func_105767_z(char[] arg0)
	{
		// @00: aload_0
		// @01: dup
		// @02: arraylength
		// @03: swap
		// @04: iconst_0
		// @05: istore_1
		// @06: goto @4C
		// @09: dup
		// @0A: iload_1
		// @0B: dup2
		// @0C: caload
		// @0D: iload_1
		// @0E: iconst_5
		// @0F: irem
		// @10: tableswitch def: @44, for 0: @30, for 1: @35, for 2: @3A, for 3: @3F
		// @30: bipush 106 (0x6A)
		// @32: goto @46
		// @35: bipush 18 (0x12)
		// @37: goto @46
		// @3A: bipush 82 (0x52)
		// @3C: goto @46
		// @3F: bipush 71 (0x47)
		// @41: goto @46
		// @44: bipush 81 (0x51)
		// @46: ixor
		// @47: i2c
		// @48: castore
		// @49: iinc #1 +1
		// @4C: swap
		// @4D: dup_x1
		// @4E: iload_1
		// @4F: if_icmpgt @09
		// @52: new java.lang.String
		// @55: dup_x1
		// @56: swap
		// @57: invokespecial java.lang.String.<init>(char[])void
		// @5A: invokevirtual java.lang.String.intern()java.lang.String
		// @5D: areturn
	}
}
