package game;

import java.awt.Image;
import java.awt.Graphics;
import java.awt.Component;

abstract class C_100185_rm
{
	static String field_105488_a;
	int[] field_105486_b;
	static String field_105487_c;
	int field_105491_i;
	static int field_105490_h;
	static String field_105485_e;
	Image field_105482_f;
	static C_100112_r field_105484_d;
	int field_105483_g;
	private static final String[] field_105489_z;
	
	abstract void func_105474_a(int arg0, int arg1, Graphics arg2, int arg3);
	
	static final C_100302_ka func_105480_a(int arg0)
	{
		// @00: getstatic int game.C_100100_i.field_102014_hc
		// @03: iconst_m1
		// @04: ixor
		// @05: iconst_m1
		// @06: if_icmplt @1A
		// @09: iconst_m1
		// @0A: getstatic int game.C_100102_w.field_104635_b
		// @0D: iconst_m1
		// @0E: ixor
		// @0F: if_icmpgt @1A
		// @12: goto @16
		// @15: athrow
		// @16: goto @1E
		// @19: athrow
		// @1A: getstatic game.C_100302_ka game.C_100033_gj.field_101926_pc
		// @1D: areturn
		// @1E: iload_0
		// @1F: bipush 100 (0x64)
		// @21: if_icmpeq @2D
		// @24: bipush 24 (0x18)
		// @26: putstatic int game.C_100185_rm.field_105490_h
		// @29: goto @2D
		// @2C: athrow
		// @2D: aconst_null
		// @2E: areturn
		// @2F: astore_1
		// @30: aload_1
		// @31: new java.lang.StringBuilder
		// @34: dup
		// @35: invokespecial java.lang.StringBuilder.<init>()void
		// @38: getstatic java.lang.String[] game.C_100185_rm.field_105489_z
		// @3B: bipush 6 (0x06)
		// @3D: aaload
		// @3E: invokevirtual java.lang.StringBuilder.append(java.lang.String)java.lang.StringBuilder
		// @41: iload_0
		// @42: invokevirtual java.lang.StringBuilder.append(int)java.lang.StringBuilder
		// @45: bipush 41 (0x29)
		// @47: invokevirtual java.lang.StringBuilder.append(char)java.lang.StringBuilder
		// @4A: invokevirtual java.lang.StringBuilder.toString()java.lang.String
		// @4D: invokestatic game.C_100181_cf.func_105695_a(java.lang.Throwable, java.lang.String)game.C_100170_cm
		// @50: athrow
	}
	
	final void func_105476_a(byte arg0)
	{
		// @00: iload_1
		// @01: bipush 109 (0x6D)
		// @03: if_icmpgt @10
		// @06: aload_0
		// @07: bipush -50 (0xCE)
		// @09: putfield int game.C_100185_rm.field_105483_g
		// @0C: goto @10
		// @0F: athrow
		// @10: aload_0
		// @11: getfield int[] game.C_100185_rm.field_105486_b
		// @14: aload_0
		// @15: getfield int game.C_100185_rm.field_105483_g
		// @18: aload_0
		// @19: getfield int game.C_100185_rm.field_105491_i
		// @1C: invokestatic game.C_100196_rb.func_105808_a(int[], int, int)void
		// @1F: goto @43
		// @22: astore_2
		// @23: aload_2
		// @24: new java.lang.StringBuilder
		// @27: dup
		// @28: invokespecial java.lang.StringBuilder.<init>()void
		// @2B: getstatic java.lang.String[] game.C_100185_rm.field_105489_z
		// @2E: iconst_4
		// @2F: aaload
		// @30: invokevirtual java.lang.StringBuilder.append(java.lang.String)java.lang.StringBuilder
		// @33: iload_1
		// @34: invokevirtual java.lang.StringBuilder.append(int)java.lang.StringBuilder
		// @37: bipush 41 (0x29)
		// @39: invokevirtual java.lang.StringBuilder.append(char)java.lang.StringBuilder
		// @3C: invokevirtual java.lang.StringBuilder.toString()java.lang.String
		// @3F: invokestatic game.C_100181_cf.func_105695_a(java.lang.Throwable, java.lang.String)game.C_100170_cm
		// @42: athrow
		// @43: return
	}
	
	abstract void func_105478_a(int arg0, int arg1, Component arg2, byte arg3);
	
	static final C_100179_ch func_105479_a(byte arg0, C_100214_al arg1)
	{
		// @00: bipush 64 (0x40)
		// @02: iload_0
		// @03: bipush 86 (0x56)
		// @05: isub
		// @06: bipush 36 (0x24)
		// @08: idiv
		// @09: irem
		// @0A: istore_2
		// @0B: aload_1
		// @0C: bipush 100 (0x64)
		// @0E: bipush 96 (0x60)
		// @10: invokestatic game.C_100117_p.func_100959_a(game.C_100214_al, int, int)game.C_100117_p
		// @13: bipush 45 (0x2D)
		// @15: invokestatic game.C_100130_tf.func_104952_a(game.C_100117_p, byte)game.C_100179_ch
		// @18: areturn
		// @19: astore_2
		// @1A: aload_2
		// @1B: new java.lang.StringBuilder
		// @1E: dup
		// @1F: invokespecial java.lang.StringBuilder.<init>()void
		// @22: getstatic java.lang.String[] game.C_100185_rm.field_105489_z
		// @25: iconst_2
		// @26: aaload
		// @27: invokevirtual java.lang.StringBuilder.append(java.lang.String)java.lang.StringBuilder
		// @2A: iload_0
		// @2B: invokevirtual java.lang.StringBuilder.append(int)java.lang.StringBuilder
		// @2E: bipush 44 (0x2C)
		// @30: invokevirtual java.lang.StringBuilder.append(char)java.lang.StringBuilder
		// @33: aload_1
		// @34: ifnull @40
		// @37: getstatic java.lang.String[] game.C_100185_rm.field_105489_z
		// @3A: iconst_1
		// @3B: aaload
		// @3C: goto @45
		// @3F: athrow
		// @40: getstatic java.lang.String[] game.C_100185_rm.field_105489_z
		// @43: iconst_3
		// @44: aaload
		// @45: invokevirtual java.lang.StringBuilder.append(java.lang.String)java.lang.StringBuilder
		// @48: bipush 41 (0x29)
		// @4A: invokevirtual java.lang.StringBuilder.append(char)java.lang.StringBuilder
		// @4D: invokevirtual java.lang.StringBuilder.toString()java.lang.String
		// @50: invokestatic game.C_100181_cf.func_105695_a(java.lang.Throwable, java.lang.String)game.C_100170_cm
		// @53: athrow
	}
	
	static final void func_105473_b(int arg0)
	{
		// @00: getstatic boolean game.C_100034_gi.field_104036_j
		// @03: ifne @0B
		// @06: iconst_1
		// @07: goto @0C
		// @0A: athrow
		// @0B: iconst_0
		// @0C: putstatic boolean game.C_100034_gi.field_104036_j
		// @0F: getstatic boolean game.C_100034_gi.field_104036_j
		// @12: ifeq @6C
		// @15: getstatic game.C_100265_mh game.C_100127_tl.field_104948_b
		// @18: ifnull @6C
		// @1B: goto @1F
		// @1E: athrow
		// @1F: getstatic game.C_100265_mh game.C_100127_tl.field_104948_b
		// @22: getfield game.C_100314_lf game.C_100265_mh.field_106636_z
		// @25: ifnonnull @30
		// @28: goto @2C
		// @2B: athrow
		// @2C: goto @6C
		// @2F: athrow
		// @30: getstatic game.C_100265_mh game.C_100127_tl.field_104948_b
		// @33: getstatic game.C_100265_mh game.C_100127_tl.field_104948_b
		// @36: getfield game.C_100314_lf game.C_100265_mh.field_106636_z
		// @39: getfield int game.C_100314_lf.field_101377_tc
		// @3C: ldc 388398308 (0x17267ce4)
		// @3E: ishr
		// @3F: ineg
		// @40: getstatic game.C_100265_mh game.C_100127_tl.field_104948_b
		// @43: getfield int game.C_100265_mh.field_106632_r
		// @46: iadd
		// @47: sipush 5120 (0x1400)
		// @4A: iadd
		// @4B: putfield int game.C_100265_mh.field_106637_y
		// @4E: getstatic game.C_100265_mh game.C_100127_tl.field_104948_b
		// @51: getstatic game.C_100265_mh game.C_100127_tl.field_104948_b
		// @54: getfield game.C_100314_lf game.C_100265_mh.field_106636_z
		// @57: getfield int game.C_100314_lf.field_101395_rc
		// @5A: ldc 1719871172 (0x668326c4)
		// @5C: ishr
		// @5D: ineg
		// @5E: getstatic game.C_100265_mh game.C_100127_tl.field_104948_b
		// @61: getfield int game.C_100265_mh.field_106602_T
		// @64: iadd
		// @65: sipush -3200 (0xF380)
		// @68: iadd
		// @69: putfield int game.C_100265_mh.field_106635_ab
		// @6C: iload_0
		// @6D: sipush -22169 (0xA967)
		// @70: if_icmpeq @74
		// @73: return
		// @74: getstatic java.lang.String[] game.C_100268_mk.field_106669_b
		// @77: bipush 41 (0x29)
		// @79: getstatic boolean game.C_100034_gi.field_104036_j
		// @7C: ifne @86
		// @7F: getstatic java.lang.String game.C_100116_ei.field_104122_b
		// @82: goto @89
		// @85: athrow
		// @86: getstatic java.lang.String game.C_100027_hc.field_102597_P
		// @89: aastore
		// @8A: goto @AE
		// @8D: astore_1
		// @8E: aload_1
		// @8F: new java.lang.StringBuilder
		// @92: dup
		// @93: invokespecial java.lang.StringBuilder.<init>()void
		// @96: getstatic java.lang.String[] game.C_100185_rm.field_105489_z
		// @99: iconst_0
		// @9A: aaload
		// @9B: invokevirtual java.lang.StringBuilder.append(java.lang.String)java.lang.StringBuilder
		// @9E: iload_0
		// @9F: invokevirtual java.lang.StringBuilder.append(int)java.lang.StringBuilder
		// @A2: bipush 41 (0x29)
		// @A4: invokevirtual java.lang.StringBuilder.append(char)java.lang.StringBuilder
		// @A7: invokevirtual java.lang.StringBuilder.toString()java.lang.String
		// @AA: invokestatic game.C_100181_cf.func_105695_a(java.lang.Throwable, java.lang.String)game.C_100170_cm
		// @AD: athrow
		// @AE: return
	}
	
	public static void func_105481_d(int arg0)
	{
		// @00: aconst_null
		// @01: putstatic java.lang.String game.C_100185_rm.field_105488_a
		// @04: aconst_null
		// @05: putstatic game.C_100112_r game.C_100185_rm.field_105484_d
		// @08: aconst_null
		// @09: putstatic java.lang.String game.C_100185_rm.field_105487_c
		// @0C: iload_0
		// @0D: sipush -24307 (0xA10D)
		// @10: if_icmpeq @14
		// @13: return
		// @14: aconst_null
		// @15: putstatic java.lang.String game.C_100185_rm.field_105485_e
		// @18: goto @3D
		// @1B: astore_1
		// @1C: aload_1
		// @1D: new java.lang.StringBuilder
		// @20: dup
		// @21: invokespecial java.lang.StringBuilder.<init>()void
		// @24: getstatic java.lang.String[] game.C_100185_rm.field_105489_z
		// @27: bipush 7 (0x07)
		// @29: aaload
		// @2A: invokevirtual java.lang.StringBuilder.append(java.lang.String)java.lang.StringBuilder
		// @2D: iload_0
		// @2E: invokevirtual java.lang.StringBuilder.append(int)java.lang.StringBuilder
		// @31: bipush 41 (0x29)
		// @33: invokevirtual java.lang.StringBuilder.append(char)java.lang.StringBuilder
		// @36: invokevirtual java.lang.StringBuilder.toString()java.lang.String
		// @39: invokestatic game.C_100181_cf.func_105695_a(java.lang.Throwable, java.lang.String)game.C_100170_cm
		// @3C: athrow
		// @3D: return
	}
	
	static final int func_105472_c(int arg0)
	{
		// @00: getstatic int game.SteelSentinels.field_105275_O
		// @03: istore #4
		// @05: iconst_0
		// @06: istore_1
		// @07: bipush 64 (0x40)
		// @09: invokestatic game.C_100189_ri.func_105748_a(int)boolean
		// @0C: ifeq @31
		// @0F: getstatic game.C_100333_ij game.C_100143_bl.field_105101_d
		// @12: bipush -68 (0xBC)
		// @14: invokevirtual game.C_100333_ij.func_107328_a(int)void
		// @17: getstatic game.C_100333_ij game.C_100143_bl.field_105101_d
		// @1A: iconst_1
		// @1B: invokevirtual game.C_100333_ij.func_107339_b(boolean)boolean
		// @1E: ifeq @07
		// @21: iconst_1
		// @22: istore_1
		// @23: iload #4
		// @25: ifne @4D
		// @28: iload #4
		// @2A: ifeq @07
		// @2D: goto @31
		// @30: athrow
		// @31: getstatic game.C_100333_ij game.C_100143_bl.field_105101_d
		// @34: bipush 124 (0x7C)
		// @36: getstatic int game.C_100340_je.field_102981_m
		// @39: iconst_m1
		// @3A: getstatic int game.C_100125_tm.field_100745_p
		// @3D: invokestatic game.C_100075_uj.func_100641_a(int, int, int)int
		// @40: getstatic int game.C_100015_wh.field_103781_g
		// @43: iconst_m1
		// @44: getstatic int game.C_100338_jc.field_105370_l
		// @47: invokestatic game.C_100075_uj.func_100641_a(int, int, int)int
		// @4A: invokevirtual game.C_100333_ij.func_107335_a(int, int, int)void
		// @4D: getstatic game.C_100333_ij game.C_100143_bl.field_105101_d
		// @50: iconst_1
		// @51: invokevirtual game.C_100333_ij.func_107339_b(boolean)boolean
		// @54: ifne @5B
		// @57: goto @5D
		// @5A: athrow
		// @5B: iconst_1
		// @5C: istore_1
		// @5D: bipush 89 (0x59)
		// @5F: bipush 65 (0x41)
		// @61: iload_0
		// @62: isub
		// @63: bipush 35 (0x23)
		// @65: idiv
		// @66: irem
		// @67: istore_3
		// @68: iconst_0
		// @69: istore_2
		// @6A: iload_1
		// @6B: ifeq @94
		// @6E: getstatic game.C_100333_ij game.C_100143_bl.field_105101_d
		// @71: getfield int game.C_100333_ij.field_107347_b
		// @74: iflt @94
		// @77: goto @7B
		// @7A: athrow
		// @7B: getstatic int[] game.C_100056_de.field_103187_ib
		// @7E: getstatic game.C_100333_ij game.C_100143_bl.field_105101_d
		// @81: getfield int game.C_100333_ij.field_107347_b
		// @84: iaload
		// @85: istore_2
		// @86: iload_2
		// @87: iconst_2
		// @88: if_icmpne @94
		// @8B: bipush -32 (0xE0)
		// @8D: invokestatic game.C_100187_rk.func_100819_a(byte)void
		// @90: goto @94
		// @93: athrow
		// @94: iload_2
		// @95: ireturn
		// @96: astore_1
		// @97: aload_1
		// @98: new java.lang.StringBuilder
		// @9B: dup
		// @9C: invokespecial java.lang.StringBuilder.<init>()void
		// @9F: getstatic java.lang.String[] game.C_100185_rm.field_105489_z
		// @A2: iconst_5
		// @A3: aaload
		// @A4: invokevirtual java.lang.StringBuilder.append(java.lang.String)java.lang.StringBuilder
		// @A7: iload_0
		// @A8: invokevirtual java.lang.StringBuilder.append(int)java.lang.StringBuilder
		// @AB: bipush 41 (0x29)
		// @AD: invokevirtual java.lang.StringBuilder.append(char)java.lang.StringBuilder
		// @B0: invokevirtual java.lang.StringBuilder.toString()java.lang.String
		// @B3: invokestatic game.C_100181_cf.func_105695_a(java.lang.Throwable, java.lang.String)game.C_100170_cm
		// @B6: athrow
	}
	
	static
	{
		// @00: bipush 8 (0x08)
		// @02: anewarray java.lang.String
		// @05: dup
		// @06: iconst_0
		// @07: ldc "\u0017!@\u0017p"
		// @09: invokestatic game.C_100185_rm.func_105477_z(java.lang.String)char[]
		// @0C: invokestatic game.C_100185_rm.func_105475_z(char[])java.lang.String
		// @0F: aastore
		// @10: dup
		// @11: iconst_1
		// @12: ldc "\u001eb@t%"
		// @14: invokestatic game.C_100185_rm.func_105477_z(java.lang.String)char[]
		// @17: invokestatic game.C_100185_rm.func_105475_z(char[])java.lang.String
		// @1A: aastore
		// @1B: dup
		// @1C: iconst_2
		// @1D: ldc "\u0017!@\u0014p"
		// @1F: invokestatic game.C_100185_rm.func_105477_z(java.lang.String)char[]
		// @22: invokestatic game.C_100185_rm.func_105475_z(char[])java.lang.String
		// @25: aastore
		// @26: dup
		// @27: iconst_3
		// @28: ldc "\u000b9\u00026"
		// @2A: invokestatic game.C_100185_rm.func_105477_z(java.lang.String)char[]
		// @2D: invokestatic game.C_100185_rm.func_105475_z(char[])java.lang.String
		// @30: aastore
		// @31: dup
		// @32: iconst_4
		// @33: ldc "\u0017!@\u0015p"
		// @35: invokestatic game.C_100185_rm.func_105477_z(java.lang.String)char[]
		// @38: invokestatic game.C_100185_rm.func_105475_z(char[])java.lang.String
		// @3B: aastore
		// @3C: dup
		// @3D: iconst_5
		// @3E: ldc "\u0017!@\np"
		// @40: invokestatic game.C_100185_rm.func_105477_z(java.lang.String)char[]
		// @43: invokestatic game.C_100185_rm.func_105475_z(char[])java.lang.String
		// @46: aastore
		// @47: dup
		// @48: bipush 6 (0x06)
		// @4A: ldc "\u0017!@\u0011p"
		// @4C: invokestatic game.C_100185_rm.func_105477_z(java.lang.String)char[]
		// @4F: invokestatic game.C_100185_rm.func_105475_z(char[])java.lang.String
		// @52: aastore
		// @53: dup
		// @54: bipush 7 (0x07)
		// @56: ldc "\u0017!@\u0016p"
		// @58: invokestatic game.C_100185_rm.func_105477_z(java.lang.String)char[]
		// @5B: invokestatic game.C_100185_rm.func_105475_z(char[])java.lang.String
		// @5E: aastore
		// @5F: putstatic java.lang.String[] game.C_100185_rm.field_105489_z
		// @62: ldc ",\"\u00183,\u0000l\u00035*\u0000l\u001e69\u001c)\u001c)tE#\u001cz9\t8\u000b(6\u00048\u0007,=\t5N.*\u001cl\r29\u000b+\u00074?E8\u0006?x\u0003#\u000267\u0012%\u0000=x\u0016)\u001a.1\u000b+\u001d`xE"
		// @64: invokestatic game.C_100185_rm.func_105477_z(java.lang.String)char[]
		// @67: invokestatic game.C_100185_rm.func_105475_z(char[])java.lang.String
		// @6A: putstatic java.lang.String game.C_100185_rm.field_105487_c
		// @6D: ldc ")#\u000f>1\u000b+@tv"
		// @6F: invokestatic game.C_100185_rm.func_105477_z(java.lang.String)char[]
		// @72: invokestatic game.C_100185_rm.func_105475_z(char[])java.lang.String
		// @75: putstatic java.lang.String game.C_100185_rm.field_105485_e
		// @78: ldc "7)\u001d3?\u000b"
		// @7A: invokestatic game.C_100185_rm.func_105477_z(java.lang.String)char[]
		// @7D: invokestatic game.C_100185_rm.func_105475_z(char[])java.lang.String
		// @80: putstatic java.lang.String game.C_100185_rm.field_105488_a
		// @83: return
	}
	
	private static char[] func_105477_z(String arg0)
	{
		// @00: aload_0
		// @01: invokevirtual java.lang.String.toCharArray()char[]
		// @04: dup
		// @05: arraylength
		// @06: iconst_2
		// @07: if_icmpge @13
		// @0A: dup
		// @0B: iconst_0
		// @0C: dup2
		// @0D: caload
		// @0E: bipush 88 (0x58)
		// @10: ixor
		// @11: i2c
		// @12: castore
		// @13: areturn
	}
	
	private static String func_105475_z(char[] arg0)
	{
		// @00: aload_0
		// @01: dup
		// @02: arraylength
		// @03: swap
		// @04: iconst_0
		// @05: istore_1
		// @06: goto @4C
		// @09: dup
		// @0A: iload_1
		// @0B: dup2
		// @0C: caload
		// @0D: iload_1
		// @0E: iconst_5
		// @0F: irem
		// @10: tableswitch def: @44, for 0: @30, for 1: @35, for 2: @3A, for 3: @3F
		// @30: bipush 101 (0x65)
		// @32: goto @46
		// @35: bipush 76 (0x4C)
		// @37: goto @46
		// @3A: bipush 110 (0x6E)
		// @3C: goto @46
		// @3F: bipush 90 (0x5A)
		// @41: goto @46
		// @44: bipush 88 (0x58)
		// @46: ixor
		// @47: i2c
		// @48: castore
		// @49: iinc #1 +1
		// @4C: swap
		// @4D: dup_x1
		// @4E: iload_1
		// @4F: if_icmpgt @09
		// @52: new java.lang.String
		// @55: dup_x1
		// @56: swap
		// @57: invokespecial java.lang.String.<init>(char[])void
		// @5A: invokevirtual java.lang.String.intern()java.lang.String
		// @5D: areturn
	}
}
