package game;

import java.awt.Component;

abstract class C_100089_fa
{
	static String field_103723_f;
	private static int[] field_103729_a;
	static String field_103725_d;
	static boolean field_103726_e;
	static String field_103727_b;
	static int field_103728_c;
	static String field_103724_g;
	private static final String[] field_103730_z;
	
	public static void func_103715_b(int arg0)
	{
		// @00: aconst_null
		// @01: putstatic java.lang.String game.C_100089_fa.field_103723_f
		// @04: aconst_null
		// @05: putstatic java.lang.String game.C_100089_fa.field_103725_d
		// @08: aconst_null
		// @09: putstatic java.lang.String game.C_100089_fa.field_103727_b
		// @0C: aconst_null
		// @0D: putstatic int[] game.C_100089_fa.field_103729_a
		// @10: aconst_null
		// @11: putstatic java.lang.String game.C_100089_fa.field_103724_g
		// @14: iload_0
		// @15: sipush 12651 (0x316B)
		// @18: if_icmpeq @20
		// @1B: bipush -107 (0x95)
		// @1D: invokestatic game.C_100089_fa.func_103716_a(int)void
		// @20: goto @44
		// @23: astore_1
		// @24: aload_1
		// @25: new java.lang.StringBuilder
		// @28: dup
		// @29: invokespecial java.lang.StringBuilder.<init>()void
		// @2C: getstatic java.lang.String[] game.C_100089_fa.field_103730_z
		// @2F: iconst_0
		// @30: aaload
		// @31: invokevirtual java.lang.StringBuilder.append(java.lang.String)java.lang.StringBuilder
		// @34: iload_0
		// @35: invokevirtual java.lang.StringBuilder.append(int)java.lang.StringBuilder
		// @38: bipush 41 (0x29)
		// @3A: invokevirtual java.lang.StringBuilder.append(char)java.lang.StringBuilder
		// @3D: invokevirtual java.lang.StringBuilder.toString()java.lang.String
		// @40: invokestatic game.C_100181_cf.func_105695_a(java.lang.Throwable, java.lang.String)game.C_100170_cm
		// @43: athrow
		// @44: return
	}
	
	abstract void func_103720_a(byte arg0, Component arg1);
	
	static int func_103722_a(int arg0, int arg1)
	{
		// @00: iload_0
		// @01: iload_1
		// @02: ixor
		// @03: ireturn
		// @04: astore_2
		// @05: aload_2
		// @06: new java.lang.StringBuilder
		// @09: dup
		// @0A: invokespecial java.lang.StringBuilder.<init>()void
		// @0D: getstatic java.lang.String[] game.C_100089_fa.field_103730_z
		// @10: iconst_5
		// @11: aaload
		// @12: invokevirtual java.lang.StringBuilder.append(java.lang.String)java.lang.StringBuilder
		// @15: iload_0
		// @16: invokevirtual java.lang.StringBuilder.append(int)java.lang.StringBuilder
		// @19: bipush 44 (0x2C)
		// @1B: invokevirtual java.lang.StringBuilder.append(char)java.lang.StringBuilder
		// @1E: iload_1
		// @1F: invokevirtual java.lang.StringBuilder.append(int)java.lang.StringBuilder
		// @22: bipush 41 (0x29)
		// @24: invokevirtual java.lang.StringBuilder.append(char)java.lang.StringBuilder
		// @27: invokevirtual java.lang.StringBuilder.toString()java.lang.String
		// @2A: invokestatic game.C_100181_cf.func_105695_a(java.lang.Throwable, java.lang.String)game.C_100170_cm
		// @2D: athrow
	}
	
	abstract int func_103714_a(byte arg0);
	
	static final boolean func_103713_a(int arg0, String arg1, String arg2)
	{
		// @00: aload_2
		// @01: bipush 95 (0x5F)
		// @03: ldc ""
		// @05: iconst_0
		// @06: invokestatic game.C_100118_ub.func_102051_a(java.lang.String, char, java.lang.String, int)java.lang.String
		// @09: astore_2
		// @0A: iload_0
		// @0B: sipush -4787 (0xED4D)
		// @0E: if_icmpeq @1A
		// @11: bipush 122 (0x7A)
		// @13: putstatic int game.C_100089_fa.field_103728_c
		// @16: goto @1A
		// @19: athrow
		// @1A: iconst_0
		// @1B: aload_1
		// @1C: invokestatic game.C_100155_dc.func_105342_a(int, java.lang.String)java.lang.String
		// @1F: astore_3
		// @20: aload_2
		// @21: aload_1
		// @22: invokevirtual java.lang.String.indexOf(java.lang.String)int
		// @25: iconst_m1
		// @26: if_icmpne @38
		// @29: iconst_0
		// @2A: aload_2
		// @2B: aload_3
		// @2C: invokevirtual java.lang.String.indexOf(java.lang.String)int
		// @2F: iconst_m1
		// @30: ixor
		// @31: if_icmpeq @3D
		// @34: goto @38
		// @37: athrow
		// @38: iconst_1
		// @39: goto @3E
		// @3C: athrow
		// @3D: iconst_0
		// @3E: ireturn
		// @3F: astore_3
		// @40: aload_3
		// @41: new java.lang.StringBuilder
		// @44: dup
		// @45: invokespecial java.lang.StringBuilder.<init>()void
		// @48: getstatic java.lang.String[] game.C_100089_fa.field_103730_z
		// @4B: bipush 8 (0x08)
		// @4D: aaload
		// @4E: invokevirtual java.lang.StringBuilder.append(java.lang.String)java.lang.StringBuilder
		// @51: iload_0
		// @52: invokevirtual java.lang.StringBuilder.append(int)java.lang.StringBuilder
		// @55: bipush 44 (0x2C)
		// @57: invokevirtual java.lang.StringBuilder.append(char)java.lang.StringBuilder
		// @5A: aload_1
		// @5B: ifnull @67
		// @5E: getstatic java.lang.String[] game.C_100089_fa.field_103730_z
		// @61: iconst_4
		// @62: aaload
		// @63: goto @6C
		// @66: athrow
		// @67: getstatic java.lang.String[] game.C_100089_fa.field_103730_z
		// @6A: iconst_3
		// @6B: aaload
		// @6C: invokevirtual java.lang.StringBuilder.append(java.lang.String)java.lang.StringBuilder
		// @6F: bipush 44 (0x2C)
		// @71: invokevirtual java.lang.StringBuilder.append(char)java.lang.StringBuilder
		// @74: aload_2
		// @75: ifnull @81
		// @78: getstatic java.lang.String[] game.C_100089_fa.field_103730_z
		// @7B: iconst_4
		// @7C: aaload
		// @7D: goto @86
		// @80: athrow
		// @81: getstatic java.lang.String[] game.C_100089_fa.field_103730_z
		// @84: iconst_3
		// @85: aaload
		// @86: invokevirtual java.lang.StringBuilder.append(java.lang.String)java.lang.StringBuilder
		// @89: bipush 41 (0x29)
		// @8B: invokevirtual java.lang.StringBuilder.append(char)java.lang.StringBuilder
		// @8E: invokevirtual java.lang.StringBuilder.toString()java.lang.String
		// @91: invokestatic game.C_100181_cf.func_105695_a(java.lang.Throwable, java.lang.String)game.C_100170_cm
		// @94: athrow
	}
	
	abstract void func_103712_a(int arg0, Component arg1);
	
	static final String func_103719_a(int arg0, C_100280_nf arg1, int arg2)
	{
		// @00: aload_1
		// @01: iconst_0
		// @02: invokevirtual game.C_100280_nf.func_101135_b(boolean)int
		// @05: istore_3
		// @06: iload_0
		// @07: iconst_m1
		// @08: ixor
		// @09: iload_3
		// @0A: iconst_m1
		// @0B: ixor
		// @0C: if_icmple @11
		// @0F: iload_0
		// @10: istore_3
		// @11: iload_2
		// @12: sipush -25438 (0x9CA2)
		// @15: if_icmpeq @21
		// @18: bipush -124 (0x84)
		// @1A: putstatic int game.C_100089_fa.field_103728_c
		// @1D: goto @21
		// @20: athrow
		// @21: iload_3
		// @22: newarray byte[]
		// @24: astore #4
		// @26: aload_1
		// @27: dup
		// @28: getfield int game.C_100280_nf.field_101177_n
		// @2B: getstatic game.C_100290_jm game.C_100038_wa.field_104069_e
		// @2E: aload #4
		// @30: iconst_0
		// @31: bipush -40 (0xD8)
		// @33: iload_3
		// @34: aload_1
		// @35: getfield byte[] game.C_100280_nf.field_101179_l
		// @38: aload_1
		// @39: getfield int game.C_100280_nf.field_101177_n
		// @3C: invokevirtual game.C_100290_jm.func_106847_a(byte[], int, byte, int, byte[], int)int
		// @3F: iadd
		// @40: putfield int game.C_100280_nf.field_101177_n
		// @43: aload #4
		// @45: sipush 5278 (0x149E)
		// @48: iconst_0
		// @49: iload_3
		// @4A: invokestatic game.C_100280_nf.func_101130_c(byte[], int, int, int)java.lang.String
		// @4D: astore #5
		// @4F: aload #5
		// @51: areturn
		// @52: astore_3
		// @53: getstatic java.lang.String[] game.C_100089_fa.field_103730_z
		// @56: iconst_2
		// @57: aaload
		// @58: areturn
		// @59: astore_3
		// @5A: aload_3
		// @5B: new java.lang.StringBuilder
		// @5E: dup
		// @5F: invokespecial java.lang.StringBuilder.<init>()void
		// @62: getstatic java.lang.String[] game.C_100089_fa.field_103730_z
		// @65: iconst_1
		// @66: aaload
		// @67: invokevirtual java.lang.StringBuilder.append(java.lang.String)java.lang.StringBuilder
		// @6A: iload_0
		// @6B: invokevirtual java.lang.StringBuilder.append(int)java.lang.StringBuilder
		// @6E: bipush 44 (0x2C)
		// @70: invokevirtual java.lang.StringBuilder.append(char)java.lang.StringBuilder
		// @73: aload_1
		// @74: ifnull @80
		// @77: getstatic java.lang.String[] game.C_100089_fa.field_103730_z
		// @7A: iconst_4
		// @7B: aaload
		// @7C: goto @85
		// @7F: athrow
		// @80: getstatic java.lang.String[] game.C_100089_fa.field_103730_z
		// @83: iconst_3
		// @84: aaload
		// @85: invokevirtual java.lang.StringBuilder.append(java.lang.String)java.lang.StringBuilder
		// @88: bipush 44 (0x2C)
		// @8A: invokevirtual java.lang.StringBuilder.append(char)java.lang.StringBuilder
		// @8D: iload_2
		// @8E: invokevirtual java.lang.StringBuilder.append(int)java.lang.StringBuilder
		// @91: bipush 41 (0x29)
		// @93: invokevirtual java.lang.StringBuilder.append(char)java.lang.StringBuilder
		// @96: invokevirtual java.lang.StringBuilder.toString()java.lang.String
		// @99: invokestatic game.C_100181_cf.func_105695_a(java.lang.Throwable, java.lang.String)game.C_100170_cm
		// @9C: athrow
	}
	
	static final void func_103721_a(int arg0, byte arg1)
	{
		// @00: iload_1
		// @01: bipush 82 (0x52)
		// @03: if_icmpeq @11
		// @06: aconst_null
		// @07: checkcast java.lang.String
		// @0A: putstatic java.lang.String game.C_100089_fa.field_103724_g
		// @0D: goto @11
		// @10: athrow
		// @11: getstatic game.C_100278_nd game.C_100115_ej.field_102043_Yb
		// @14: astore_2
		// @15: aload_2
		// @16: iload_0
		// @17: bipush 103 (0x67)
		// @19: invokevirtual game.C_100278_nd.func_101189_h(int, int)void
		// @1C: aload_2
		// @1D: iload_1
		// @1E: sipush 7884 (0x1ECC)
		// @21: ixor
		// @22: iconst_1
		// @23: invokevirtual game.C_100278_nd.func_101169_f(int, int)void
		// @26: aload_2
		// @27: sipush 7838 (0x1E9E)
		// @2A: iconst_1
		// @2B: invokevirtual game.C_100278_nd.func_101169_f(int, int)void
		// @2E: goto @5C
		// @31: astore_2
		// @32: aload_2
		// @33: new java.lang.StringBuilder
		// @36: dup
		// @37: invokespecial java.lang.StringBuilder.<init>()void
		// @3A: getstatic java.lang.String[] game.C_100089_fa.field_103730_z
		// @3D: bipush 7 (0x07)
		// @3F: aaload
		// @40: invokevirtual java.lang.StringBuilder.append(java.lang.String)java.lang.StringBuilder
		// @43: iload_0
		// @44: invokevirtual java.lang.StringBuilder.append(int)java.lang.StringBuilder
		// @47: bipush 44 (0x2C)
		// @49: invokevirtual java.lang.StringBuilder.append(char)java.lang.StringBuilder
		// @4C: iload_1
		// @4D: invokevirtual java.lang.StringBuilder.append(int)java.lang.StringBuilder
		// @50: bipush 41 (0x29)
		// @52: invokevirtual java.lang.StringBuilder.append(char)java.lang.StringBuilder
		// @55: invokevirtual java.lang.StringBuilder.toString()java.lang.String
		// @58: invokestatic game.C_100181_cf.func_105695_a(java.lang.Throwable, java.lang.String)game.C_100170_cm
		// @5B: athrow
		// @5C: return
	}
	
	static final void func_103716_a(int arg0)
	{
		// @00: getstatic int game.C_100087_n.field_100697_v
		// @03: bipush 10 (0x0A)
		// @05: if_icmpeq @18
		// @08: bipush 104 (0x68)
		// @0A: invokestatic game.C_100069_vb.func_104350_a(byte)boolean
		// @0D: ifeq @18
		// @10: goto @14
		// @13: athrow
		// @14: goto @22
		// @17: athrow
		// @18: bipush 96 (0x60)
		// @1A: invokestatic game.C_100119_ua.func_104887_a(byte)void
		// @1D: bipush 11 (0x0B)
		// @1F: putstatic int game.C_100087_n.field_100697_v
		// @22: iload_0
		// @23: bipush 71 (0x47)
		// @25: if_icmpgt @33
		// @28: bipush 101 (0x65)
		// @2A: bipush -85 (0xAB)
		// @2C: invokestatic game.C_100089_fa.func_103721_a(int, byte)void
		// @2F: goto @33
		// @32: athrow
		// @33: iconst_1
		// @34: putstatic boolean game.C_100077_d.field_103326_eb
		// @37: goto @5C
		// @3A: astore_1
		// @3B: aload_1
		// @3C: new java.lang.StringBuilder
		// @3F: dup
		// @40: invokespecial java.lang.StringBuilder.<init>()void
		// @43: getstatic java.lang.String[] game.C_100089_fa.field_103730_z
		// @46: bipush 6 (0x06)
		// @48: aaload
		// @49: invokevirtual java.lang.StringBuilder.append(java.lang.String)java.lang.StringBuilder
		// @4C: iload_0
		// @4D: invokevirtual java.lang.StringBuilder.append(int)java.lang.StringBuilder
		// @50: bipush 41 (0x29)
		// @52: invokevirtual java.lang.StringBuilder.append(char)java.lang.StringBuilder
		// @55: invokevirtual java.lang.StringBuilder.toString()java.lang.String
		// @58: invokestatic game.C_100181_cf.func_105695_a(java.lang.Throwable, java.lang.String)game.C_100170_cm
		// @5B: athrow
		// @5C: return
	}
	
	static
	{
		// @000: bipush 9 (0x09)
		// @002: anewarray java.lang.String
		// @005: dup
		// @006: iconst_0
		// @007: ldc "E'Ft5"
		// @009: invokestatic game.C_100089_fa.func_103718_z(java.lang.String)char[]
		// @00C: invokestatic game.C_100089_fa.func_103717_z(char[])java.lang.String
		// @00F: aastore
		// @010: dup
		// @011: iconst_1
		// @012: ldc "E'Fx5"
		// @014: invokestatic game.C_100089_fa.func_103718_z(java.lang.String)char[]
		// @017: invokestatic game.C_100089_fa.func_103717_z(char[])java.lang.String
		// @01A: aastore
		// @01B: dup
		// @01C: iconst_2
		// @01D: ldc "`'\nS|D#"
		// @01F: invokestatic game.C_100089_fa.func_103718_z(java.lang.String)char[]
		// @022: invokestatic game.C_100089_fa.func_103717_z(char[])java.lang.String
		// @025: aastore
		// @026: dup
		// @027: iconst_3
		// @028: ldc "M3\u0004]"
		// @02A: invokestatic game.C_100089_fa.func_103718_z(java.lang.String)char[]
		// @02D: invokestatic game.C_100089_fa.func_103717_z(char[])java.lang.String
		// @030: aastore
		// @031: dup
		// @032: iconst_4
		// @033: ldc "XhF\u001f`"
		// @035: invokestatic game.C_100089_fa.func_103718_z(java.lang.String)char[]
		// @038: invokestatic game.C_100089_fa.func_103717_z(char[])java.lang.String
		// @03B: aastore
		// @03C: dup
		// @03D: iconst_5
		// @03E: ldc "E'Fp5"
		// @040: invokestatic game.C_100089_fa.func_103718_z(java.lang.String)char[]
		// @043: invokestatic game.C_100089_fa.func_103717_z(char[])java.lang.String
		// @046: aastore
		// @047: dup
		// @048: bipush 6 (0x06)
		// @04A: ldc "E'Fy5"
		// @04C: invokestatic game.C_100089_fa.func_103718_z(java.lang.String)char[]
		// @04F: invokestatic game.C_100089_fa.func_103717_z(char[])java.lang.String
		// @052: aastore
		// @053: dup
		// @054: bipush 7 (0x07)
		// @056: ldc "E'Fr5"
		// @058: invokestatic game.C_100089_fa.func_103718_z(java.lang.String)char[]
		// @05B: invokestatic game.C_100089_fa.func_103717_z(char[])java.lang.String
		// @05E: aastore
		// @05F: dup
		// @060: bipush 8 (0x08)
		// @062: ldc "E'Fs5"
		// @064: invokestatic game.C_100089_fa.func_103718_z(java.lang.String)char[]
		// @067: invokestatic game.C_100089_fa.func_103717_z(char[])java.lang.String
		// @06A: aastore
		// @06B: putstatic java.lang.String[] game.C_100089_fa.field_103730_z
		// @06E: ldc "b%\u000bTmWf\u000cC|T"
		// @070: invokestatic game.C_100089_fa.func_103718_z(java.lang.String)char[]
		// @073: invokestatic game.C_100089_fa.func_103717_z(char[])java.lang.String
		// @076: putstatic java.lang.String game.C_100089_fa.field_103723_f
		// @079: ldc "l \u000eTo\u00033\u0006C|W#\u000c\u0011oF+\tE~K"
		// @07B: invokestatic game.C_100089_fa.func_103718_z(java.lang.String)char[]
		// @07E: invokestatic game.C_100089_fa.func_103717_z(char[])java.lang.String
		// @081: putstatic java.lang.String game.C_100089_fa.field_103725_d
		// @084: ldc 98304 (0x18000)
		// @086: newarray int[]
		// @088: putstatic int[] game.C_100089_fa.field_103729_a
		// @08B: ldc 92682 (0x16a0a)
		// @08D: istore_0
		// @08E: ldc -46342 (0xffff4afa)
		// @090: iload_0
		// @091: iconst_m1
		// @092: ixor
		// @093: if_icmplt @0FB
		// @096: iload_0
		// @097: ldc -596658463 (0xdc6fb6e1)
		// @099: ishl
		// @09A: iconst_1
		// @09B: iadd
		// @09C: i2l
		// @09D: lstore #6
		// @09F: iload_0
		// @0A0: ldc -1867292415 (0x90b36101)
		// @0A2: ishl
		// @0A3: iconst_m1
		// @0A4: iadd
		// @0A5: i2l
		// @0A6: lstore #4
		// @0A8: ldc2_w -32768
		// @0AB: lload #4
		// @0AD: lload #4
		// @0AF: lmul
		// @0B0: ldc -444653742 (0xe57f1f52)
		// @0B2: lshr
		// @0B3: ladd
		// @0B4: l2i
		// @0B5: istore_2
		// @0B6: lload #6
		// @0B8: lload #6
		// @0BA: lmul
		// @0BB: ldc 1727568914 (0x66f89c12)
		// @0BD: lshr
		// @0BE: ldc2_w -32768
		// @0C1: ladd
		// @0C2: l2i
		// @0C3: istore_3
		// @0C4: iload_3
		// @0C5: getstatic int[] game.C_100089_fa.field_103729_a
		// @0C8: arraylength
		// @0C9: if_icmplt @0D3
		// @0CC: getstatic int[] game.C_100089_fa.field_103729_a
		// @0CF: arraylength
		// @0D0: iconst_m1
		// @0D1: iadd
		// @0D2: istore_3
		// @0D3: iconst_0
		// @0D4: iload_2
		// @0D5: if_icmpgt @0DD
		// @0D8: iload_2
		// @0D9: goto @0DE
		// @0DC: athrow
		// @0DD: iconst_0
		// @0DE: istore_1
		// @0DF: iload_3
		// @0E0: iconst_m1
		// @0E1: ixor
		// @0E2: iload_1
		// @0E3: iconst_m1
		// @0E4: ixor
		// @0E5: if_icmpgt @0F5
		// @0E8: getstatic int[] game.C_100089_fa.field_103729_a
		// @0EB: iload_1
		// @0EC: iload_0
		// @0ED: iastore
		// @0EE: iinc #1 +1
		// @0F1: goto @0DF
		// @0F4: athrow
		// @0F5: iinc #0 +255
		// @0F8: goto @08E
		// @0FB: iconst_1
		// @0FC: putstatic boolean game.C_100089_fa.field_103726_e
		// @0FF: ldc "g'\u0011"
		// @101: invokestatic game.C_100089_fa.func_103718_z(java.lang.String)char[]
		// @104: invokestatic game.C_100089_fa.func_103717_z(char[])java.lang.String
		// @107: putstatic java.lang.String game.C_100089_fa.field_103727_b
		// @10A: return
	}
	
	private static char[] func_103718_z(String arg0)
	{
		// @00: aload_0
		// @01: invokevirtual java.lang.String.toCharArray()char[]
		// @04: dup
		// @05: arraylength
		// @06: iconst_2
		// @07: if_icmpge @13
		// @0A: dup
		// @0B: iconst_0
		// @0C: dup2
		// @0D: caload
		// @0E: bipush 29 (0x1D)
		// @10: ixor
		// @11: i2c
		// @12: castore
		// @13: areturn
	}
	
	private static String func_103717_z(char[] arg0)
	{
		// @00: aload_0
		// @01: dup
		// @02: arraylength
		// @03: swap
		// @04: iconst_0
		// @05: istore_1
		// @06: goto @4C
		// @09: dup
		// @0A: iload_1
		// @0B: dup2
		// @0C: caload
		// @0D: iload_1
		// @0E: iconst_5
		// @0F: irem
		// @10: tableswitch def: @44, for 0: @30, for 1: @35, for 2: @3A, for 3: @3F
		// @30: bipush 35 (0x23)
		// @32: goto @46
		// @35: bipush 70 (0x46)
		// @37: goto @46
		// @3A: bipush 104 (0x68)
		// @3C: goto @46
		// @3F: bipush 49 (0x31)
		// @41: goto @46
		// @44: bipush 29 (0x1D)
		// @46: ixor
		// @47: i2c
		// @48: castore
		// @49: iinc #1 +1
		// @4C: swap
		// @4D: dup_x1
		// @4E: iload_1
		// @4F: if_icmpgt @09
		// @52: new java.lang.String
		// @55: dup_x1
		// @56: swap
		// @57: invokespecial java.lang.String.<init>(char[])void
		// @5A: invokevirtual java.lang.String.intern()java.lang.String
		// @5D: areturn
	}
}
